{
  "type": "Feature",
  "properties": {
    "addr:full":"2532 E University Dr Phoenix AZ 85034",
    "addr:housenumber":"2532",
    "addr:postcode":"85034",
    "addr:street":"E University Dr",
    "iso:country":"US",
    "sg:address":"2532 E University Dr",
    "sg:city":"Phoenix",
    "sg:classifiers":[
        {
            "category":"Building & Trades",
            "subcategory":"Construction",
            "type":"Services"
        }
    ],
    "sg:phone":"+1 602 340 0092",
    "sg:postcode":"85034",
    "sg:province":"AZ",
    "sg:tags":[
        "mason",
        "masonry",
        "industrial",
        "contractors-commercial",
        "contractor"
    ],
    "wof:name":"Masonry Connection",
    "wof:placetype":"venue"
},
  "geometry": {"coordinates":[-112.02478000000001,33.423913],"type":"Point"}
}