{
  "type": "Feature",
  "properties": {
    "iso:country":"US",
    "sg:address":"2319 E Behrend Dr",
    "sg:city":"Phoenix",
    "sg:classifiers":[
        {
            "category":"Professional",
            "subcategory":"Secretarial Services",
            "type":"Services"
        },
        {
            "category":"Professional",
            "subcategory":"Employment Agencies",
            "type":"Services"
        }
    ],
    "sg:phone":"+1 602 787 1300",
    "sg:postcode":"85024",
    "sg:province":"AZ",
    "sg:tags":[
        "typing"
    ],
    "wof:name":"Award Secretarial Service Inc",
    "wof:placetype":"venue"
},
  "geometry": {"coordinates":[-112.032082,33.664268],"type":"Point"}
}