{
  "type": "Feature",
  "properties": {
    "addr:full":"4301 E Grant Rd Tucson AZ 85712",
    "addr:housenumber":"4301",
    "addr:postcode":"85712",
    "addr:street":"E Grant Rd",
    "iso:country":"US",
    "sg:address":"4301 E Grant Rd",
    "sg:city":"Tucson",
    "sg:classifiers":[
        {
            "category":"Food & Beverages",
            "subcategory":"Groceries & Convenience Stores",
            "type":"Retail Goods"
        }
    ],
    "sg:phone":"+1 520 326 6174",
    "sg:postcode":"85712",
    "sg:province":"AZ",
    "sg:tags":[
        "station",
        "gasoline"
    ],
    "wof:name":"Circle K",
    "wof:placetype":"venue"
},
  "geometry": {"coordinates":[-110.90016900000001,32.250605],"type":"Point"}
}