{
  "type": "Feature",
  "properties": {
    "addr:full":"1152 E Indian School Rd Phoenix AZ 85014",
    "addr:housenumber":"1152",
    "addr:postcode":"85014",
    "addr:street":"E Indian School Rd",
    "iso:country":"US",
    "sg:address":"1152 E Indian School Rd",
    "sg:city":"Phoenix",
    "sg:classifiers":[
        {
            "category":"Shopping",
            "subcategory":"Hobbies, Toys, & Games",
            "type":"Retail Goods"
        },
        {
            "category":"Banks & Credit Unions",
            "subcategory":"Financial Services",
            "type":"Services"
        },
        {
            "category":"Shopping",
            "subcategory":"Computers & Home Electronics",
            "type":"Retail Goods"
        },
        {
            "category":"Manufacturing",
            "subcategory":"Jewelry",
            "type":"Manufacturing & Wholesale Goods"
        },
        {
            "category":"Shopping",
            "subcategory":"Pawn Shop",
            "type":"Retail Goods"
        },
        {
            "category":"Shopping",
            "subcategory":"Jewelry",
            "type":"Retail Goods"
        }
    ],
    "sg:phone":"+1 602 635 1403",
    "sg:postcode":"85014",
    "sg:province":"AZ",
    "sg:tags":[
        "platinum",
        "television",
        "gold",
        "loan",
        "gun",
        "jeweler",
        "pawnbroker",
        "radio",
        "buyer",
        "gunsmith",
        "consumer",
        "silver",
        "store"
    ],
    "sg:website":"http://www.momoneypawn.com/",
    "wof:name":"Mo Money Pawn",
    "wof:placetype":"venue"
},
  "geometry": {"coordinates":[-112.057142,33.494701],"type":"Point"}
}