{
  "type": "Feature",
  "properties": {
    "iso:country":"US",
    "sg:address":"2300 N Kramer St",
    "sg:city":"Flagstaff",
    "sg:classifiers":[
        {
            "category":"Wholesale",
            "subcategory":"Machinery & Supplies",
            "type":"Manufacturing & Wholesale Goods"
        },
        {
            "category":"Wholesale",
            "subcategory":"Electrical",
            "type":"Manufacturing & Wholesale Goods"
        }
    ],
    "sg:phone":"+1 928 779 5131",
    "sg:postcode":"86001",
    "sg:province":"AZ",
    "sg:tags":[
        "battery",
        "forklift"
    ],
    "wof:name":"Naumann-Hobbs Material Hndlng",
    "wof:placetype":"venue"
},
  "geometry": {"coordinates":[-111.675068,35.229661],"type":"Point"}
}