{
  "type": "Feature",
  "properties": {
    "addr:full":"431 S Brighton Ln Tucson AZ 85711",
    "addr:housenumber":"431",
    "addr:postcode":"85711",
    "addr:street":"S Brighton Ln",
    "iso:country":"US",
    "sg:address":"431 S Brighton Ln",
    "sg:city":"Tucson",
    "sg:classifiers":[
        {
            "category":"Health Services",
            "subcategory":"Doctor",
            "type":"Services"
        },
        {
            "category":"Health Services",
            "subcategory":"Hospital",
            "type":"Services"
        }
    ],
    "sg:phone":"+1 520 748 2122",
    "sg:postcode":"85711",
    "sg:province":"AZ",
    "sg:tags":[
        "psychologist",
        "sleep",
        "treatment",
        "disorders-information"
    ],
    "wof:name":"Dr Robert Schwebel",
    "wof:placetype":"venue"
},
  "geometry": {"coordinates":[-110.87000999999999,32.21498],"type":"Point"}
}