{
  "type": "Feature",
  "properties": {
    "iso:country":"US",
    "sg:address":"2525 E Arizona Biltmore Cir",
    "sg:city":"Phoenix",
    "sg:classifiers":[
        {
            "category":"Education",
            "subcategory":"College",
            "type":"Public Place"
        }
    ],
    "sg:phone":"+1 602 906 6000",
    "sg:postcode":"85016",
    "sg:province":"AZ",
    "sg:tags":[
        "academic",
        "school"
    ],
    "sg:website":"www.mastersonline.com",
    "wof:name":"Masters Online",
    "wof:placetype":"venue"
},
  "geometry": {"coordinates":[-112.027912,33.525721],"type":"Point"}
}