{
  "type": "Feature",
  "properties": {
    "addr:full":"15640 S 17th St Phoenix AZ 85048",
    "addr:housenumber":"15640",
    "addr:postcode":"85048",
    "addr:street":"S 17Th St",
    "iso:country":"US",
    "sg:address":"15640 S 17th St",
    "sg:city":"Phoenix",
    "sg:classifiers":[
        {
            "category":"Professional",
            "type":"Services"
        }
    ],
    "sg:phone":"+1 480 283 9181",
    "sg:postcode":"85048",
    "sg:province":"AZ",
    "wof:name":"Breadwinners Inc",
    "wof:placetype":"venue"
},
  "geometry": {"coordinates":[-112.047434,33.303694],"type":"Point"}
}