{
  "type": "Feature",
  "properties": {
    "addr:full":"3175 N Price Rd Ofc Chandler AZ 85224",
    "addr:housenumber":"3175",
    "addr:postcode":"85224",
    "addr:street":"N Price Rd",
    "iso:country":"US",
    "sg:address":"3175 N Price Rd Ofc",
    "sg:city":"Chandler",
    "sg:classifiers":[
        {
            "category":"Real Estate",
            "subcategory":"Real Estate Operator",
            "type":"Services"
        }
    ],
    "sg:phone":"+1 480 820 9620",
    "sg:postcode":"85224",
    "sg:province":"AZ",
    "sg:tags":[
        "apartment"
    ],
    "wof:name":"Chandler Pointe",
    "wof:placetype":"venue"
},
  "geometry": {"coordinates":[-111.89299800000001,33.351601],"type":"Point"}
}