{
  "type": "Feature",
  "properties": {
    "addr:full":"333 E Van Buren St Avondale AZ 85323",
    "addr:housenumber":"333",
    "addr:postcode":"85323",
    "addr:street":"E Van Buren St",
    "iso:country":"US",
    "sg:address":"333 E Van Buren St",
    "sg:city":"Avondale",
    "sg:classifiers":[
        {
            "category":"Real Estate",
            "subcategory":"Real Estate Operator",
            "type":"Services"
        }
    ],
    "sg:phone":"+1 623 932 4378",
    "sg:postcode":"85323",
    "sg:province":"AZ",
    "sg:tags":[
        "apartment"
    ],
    "wof:name":"Mountain View Apartments",
    "wof:placetype":"venue"
},
  "geometry": {"coordinates":[-112.352997,33.449799],"type":"Point"}
}