{
  "type": "Feature",
  "properties": {
    "addr:full":"4658 S Higley Rd Gilbert AZ 85297",
    "addr:housenumber":"4658",
    "addr:postcode":"85297",
    "addr:street":"S Higley Rd",
    "iso:country":"US",
    "sg:address":"4658 S Higley Rd",
    "sg:city":"Gilbert",
    "sg:classifiers":[
        {
            "category":"Shopping",
            "subcategory":"Department Store",
            "type":"Retail Goods"
        },
        {
            "category":"Shopping",
            "subcategory":"Discount & Variety Stores",
            "type":"Retail Goods"
        },
        {
            "category":"Shopping",
            "type":"Retail Goods"
        }
    ],
    "sg:phone":"+1 480 840 6366",
    "sg:postcode":"85297",
    "sg:province":"AZ",
    "sg:tags":[
        "merchandise"
    ],
    "sg:website":"http://www.dollartree.com/",
    "wof:name":"Dollar Tree",
    "wof:placetype":"venue"
},
  "geometry": {"coordinates":[-111.72055400000001,33.27496],"type":"Point"}
}