{
  "type": "Feature",
  "properties": {
    "iso:country":"US",
    "sg:address":"2851 N Arizona Trl",
    "sg:city":"Chino Valley",
    "sg:classifiers":[
        {
            "category":"Autos & Motor Vehicles",
            "subcategory":"Automobile Sales",
            "type":"Retail Goods"
        }
    ],
    "sg:phone":"+1 928 636 0600",
    "sg:postcode":"86323",
    "sg:province":"AZ",
    "sg:tags":[
        "wrecker"
    ],
    "wof:name":"Chino Salvage",
    "wof:placetype":"venue"
},
  "geometry": {"coordinates":[-112.437527,34.786677],"type":"Point"}
}