{
  "type": "Feature",
  "properties": {
    "iso:country":"US",
    "sg:address":"1831 Kiowa Blvd N",
    "sg:city":"Lake Havasu City",
    "sg:classifiers":[
        {
            "category":"Food & Beverages",
            "subcategory":"Groceries & Convenience Stores",
            "type":"Retail Goods"
        }
    ],
    "sg:phone":"+1 928 855 3800",
    "sg:postcode":"86403",
    "sg:province":"AZ",
    "sg:tags":[
        "grocer"
    ],
    "wof:name":"Food City",
    "wof:placetype":"venue"
},
  "geometry": {"coordinates":[-114.348783,34.503089],"type":"Point"}
}