{
  "type": "Feature",
  "properties": {
    "addr:full":"5038 N 55th Ave Apt 2105 Glendale AZ 85301",
    "addr:housenumber":"5038;2105",
    "addr:postcode":"85301",
    "addr:street":"N 55Th Ave Apt",
    "iso:country":"US",
    "sg:address":"5038 N 55th Ave Apt 2105",
    "sg:city":"Glendale",
    "sg:classifiers":[
        {
            "category":"Real Estate",
            "subcategory":"Real Estate Services",
            "type":"Services"
        },
        {
            "category":"Real Estate",
            "subcategory":"Real Estate Operator",
            "type":"Services"
        }
    ],
    "sg:phone":"+1 623 931 0308",
    "sg:postcode":"85301",
    "sg:province":"AZ",
    "sg:tags":[
        "vacancy",
        "apartment",
        "rental",
        "finder",
        "listing"
    ],
    "wof:name":"Advantage Point",
    "wof:placetype":"venue"
},
  "geometry": {"coordinates":[-112.17755099999999,33.510659],"type":"Point"}
}