{
  "type": "Feature",
  "properties": {
    "iso:country":"US",
    "sg:address":"11115 W Grand Ave",
    "sg:city":"Youngtown",
    "sg:classifiers":[
        {
            "category":"Professional",
            "subcategory":"Advertising",
            "type":"Services"
        }
    ],
    "sg:phone":"+1 623 972 0700",
    "sg:postcode":"85363",
    "sg:province":"AZ",
    "sg:tags":[
        "mailing",
        "shipping"
    ],
    "wof:name":"Fed Ex",
    "wof:placetype":"venue"
},
  "geometry": {"coordinates":[-112.299505,33.605385],"type":"Point"}
}