{
  "type": "Feature",
  "properties": {
    "addr:full":"7871 W Pima Farms Rd Tucson AZ 85743",
    "addr:housenumber":"7871",
    "addr:postcode":"85743",
    "addr:street":"W Pima Farms Rd",
    "iso:country":"US",
    "sg:address":"7871 W Pima Farms Rd",
    "sg:city":"Tucson",
    "sg:classifiers":[
        {
            "category":"Banks & Credit Unions",
            "subcategory":"Investment Brokerage",
            "type":"Services"
        }
    ],
    "sg:phone":"+1 520 744 5000",
    "sg:postcode":"85743",
    "sg:province":"AZ",
    "sg:tags":[
        "advisory"
    ],
    "wof:name":"Interface Financial",
    "wof:placetype":"venue"
},
  "geometry": {"coordinates":[-111.131838,32.359158],"type":"Point"}
}