{
  "type": "Feature",
  "properties": {
    "addr:full":"2311 N Cheri Lynn Dr Chandler AZ 85225",
    "addr:housenumber":"2311",
    "addr:postcode":"85225",
    "addr:street":"N Cheri Lynn Dr",
    "iso:country":"US",
    "sg:address":"2311 N Cheri Lynn Dr",
    "sg:city":"Chandler",
    "sg:classifiers":[
        {
            "category":"Building & Trades",
            "subcategory":"Construction",
            "type":"Services"
        }
    ],
    "sg:phone":"+1 480 628 5966",
    "sg:postcode":"85225",
    "sg:province":"AZ",
    "sg:tags":[
        "house"
    ],
    "wof:name":"CJ Remodeling",
    "wof:placetype":"venue"
},
  "geometry": {"coordinates":[-111.851468,33.339456],"type":"Point"}
}