{
  "type": "Feature",
  "properties": {
    "iso:country":"US",
    "sg:address":"24039 S Val Vista Dr",
    "sg:city":"Chandler",
    "sg:classifiers":[
        {
            "category":"Building & Trades",
            "subcategory":"Plumbing",
            "type":"Services"
        }
    ],
    "sg:phone":"+1 480 895 0522",
    "sg:postcode":"85249",
    "sg:province":"AZ",
    "sg:tags":[
        "plumbing",
        "contractor"
    ],
    "wof:name":"Joe Sangemimo",
    "wof:placetype":"venue"
},
  "geometry": {"coordinates":[-111.755489,33.226615],"type":"Point"}
}