{
  "type": "Feature",
  "properties": {
    "iso:country":"US",
    "sg:address":"6247 N 7th St",
    "sg:city":"Phoenix",
    "sg:classifiers":[
        {
            "category":"Restaurant",
            "type":"Food & Drink"
        }
    ],
    "sg:phone":"+1 602 274 6836",
    "sg:postcode":"85014",
    "sg:province":"AZ",
    "wof:name":"Jordan's Mexican",
    "wof:placetype":"venue"
},
  "geometry": {"coordinates":[-112.06501299999999,33.528572],"type":"Point"}
}