{
  "type": "Feature",
  "properties": {
    "iso:country":"US",
    "sg:address":"741 E Armor Springs Pl",
    "sg:city":"Green Valley",
    "sg:classifiers":[
        {
            "category":"Wholesale",
            "subcategory":"Durable Goods & Equipment",
            "type":"Manufacturing & Wholesale Goods"
        }
    ],
    "sg:phone":"+1 520 393 1989",
    "sg:postcode":"85614",
    "sg:province":"AZ",
    "wof:name":"Advanti Auto Wholesale",
    "wof:placetype":"venue"
},
  "geometry": {"coordinates":[-110.970007,31.851247],"type":"Point"}
}