{
  "type": "Feature",
  "properties": {
    "iso:country":"US",
    "sg:address":"11209 E Karen Dr",
    "sg:city":"Scottsdale",
    "sg:classifiers":[
        {
            "category":"Home & Garden",
            "subcategory":"Home Furnishings",
            "type":"Retail Goods"
        }
    ],
    "sg:phone":"+1 480 990 9123",
    "sg:postcode":"85255",
    "sg:province":"AZ",
    "sg:tags":[
        "kitchen",
        "accessory"
    ],
    "wof:name":"Scottsdale Kitchen Co",
    "wof:placetype":"venue"
},
  "geometry": {"coordinates":[-111.844084,33.625476],"type":"Point"}
}