{
  "type": "Feature",
  "properties": {
    "iso:country":"US",
    "sg:address":"7700 W Bell Rd",
    "sg:city":"Glendale",
    "sg:classifiers":[
        {
            "category":"Cinema",
            "subcategory":"Movie Theater",
            "type":"Entertainment"
        }
    ],
    "sg:phone":"+1 602 956 4262",
    "sg:postcode":"85308",
    "sg:province":"AZ",
    "wof:name":"Amc Arrowhead 14",
    "wof:placetype":"venue"
},
  "geometry": {"coordinates":[-112.224615,33.638204],"type":"Point"}
}