{
  "type": "Feature",
  "properties": {
    "addr:full":"9448 W McRae Way Peoria AZ 85382",
    "addr:housenumber":"9448",
    "addr:postcode":"85382",
    "addr:street":"W Mcrae Way",
    "iso:country":"US",
    "sg:address":"9448 W McRae Way",
    "sg:city":"Peoria",
    "sg:classifiers":[
        {
            "category":"Real Estate",
            "subcategory":"Real Estate Agent",
            "type":"Services"
        }
    ],
    "sg:phone":"+1 623 566 2126",
    "sg:postcode":"85382",
    "sg:province":"AZ",
    "wof:name":"Egm Realty International",
    "wof:placetype":"venue"
},
  "geometry": {"coordinates":[-112.26196299999999,33.653254],"type":"Point"}
}