{
  "type": "Feature",
  "properties": {
    "iso:country":"US",
    "sg:address":"12644 N 28th Dr",
    "sg:city":"Phoenix",
    "sg:classifiers":[
        {
            "category":"Shopping",
            "type":"Retail Goods"
        }
    ],
    "sg:phone":"+1 602 938 7887",
    "sg:postcode":"85029",
    "sg:province":"AZ",
    "sg:tags":[
        "pet",
        "shop"
    ],
    "wof:name":"Pups & Stuff",
    "wof:placetype":"venue"
},
  "geometry": {"coordinates":[-112.119812,33.601413],"type":"Point"}
}