{
  "type": "Feature",
  "properties": {
    "iso:country":"US",
    "sg:address":"2550 S 15th Ave",
    "sg:city":"Phoenix",
    "sg:classifiers":[
        {
            "category":"Building & Trades",
            "subcategory":"Cleaning & Sanitation",
            "type":"Services"
        }
    ],
    "sg:phone":"+1 602 253 8040",
    "sg:postcode":"85007",
    "sg:province":"AZ",
    "sg:tags":[
        "control",
        "hazardous",
        "material",
        "removal"
    ],
    "wof:name":"Industrial Waste Utilization",
    "wof:placetype":"venue"
},
  "geometry": {"coordinates":[-112.091095,33.423778],"type":"Point"}
}