{
  "type": "Feature",
  "properties": {
    "addr:full":"860 N David Ct Chandler AZ 85226",
    "addr:housenumber":"860",
    "addr:postcode":"85226",
    "addr:street":"N David Ct",
    "iso:country":"US",
    "sg:address":"860 N David Ct",
    "sg:city":"Chandler",
    "sg:classifiers":[
        {
            "category":"Manufacturing",
            "subcategory":"Tools & Machinery",
            "type":"Manufacturing & Wholesale Goods"
        }
    ],
    "sg:phone":"+1 480 753 0492",
    "sg:postcode":"85226",
    "sg:province":"AZ",
    "sg:tags":[
        "equipment",
        "mfg"
    ],
    "wof:name":"Jsg Assoc Inc",
    "wof:placetype":"venue"
},
  "geometry": {"coordinates":[-111.95773,33.317927],"type":"Point"}
}