{
  "type": "Feature",
  "properties": {
    "addr:full":"1301 S 27th St Phoenix AZ 85034",
    "addr:housenumber":"1301",
    "addr:postcode":"85034",
    "addr:street":"S 27Th St",
    "iso:country":"US",
    "sg:address":"1301 S 27th St",
    "sg:city":"Phoenix",
    "sg:classifiers":[
        {
            "category":"Airline",
            "type":"Transportation"
        }
    ],
    "sg:phone":"+1 602 275 2132",
    "sg:postcode":"85034",
    "sg:province":"AZ",
    "sg:tags":[
        "scheduled",
        "air"
    ],
    "wof:name":"Deutsche Lfthnsa Aktngsllschaf",
    "wof:placetype":"venue"
},
  "geometry": {"coordinates":[-112.023734,33.435424],"type":"Point"}
}