{
  "type": "Feature",
  "properties": {
    "iso:country":"US",
    "sg:address":"4232 E Chandler Blvd",
    "sg:city":"Phoenix",
    "sg:classifiers":[
        {
            "category":"Professional",
            "subcategory":"Research",
            "type":"Services"
        }
    ],
    "sg:phone":"+1 480 706 0027",
    "sg:postcode":"85048",
    "sg:province":"AZ",
    "sg:tags":[
        "environmental",
        "ecological"
    ],
    "wof:name":"Environmental Remedies",
    "wof:placetype":"venue"
},
  "geometry": {"coordinates":[-111.992638,33.30529],"type":"Point"}
}