{
  "type": "Feature",
  "properties": {
    "iso:country":"US",
    "sg:address":"3332 W Flower St",
    "sg:city":"Phoenix",
    "sg:classifiers":[
        {
            "category":"Manufacturing",
            "subcategory":"Metals",
            "type":"Manufacturing & Wholesale Goods"
        }
    ],
    "sg:phone":"+1 602 943 9735",
    "sg:postcode":"85017",
    "sg:province":"AZ",
    "sg:tags":[
        "fabricator",
        "sheet",
        "fabrication"
    ],
    "wof:name":"Best Metal Fabricators Inc",
    "wof:placetype":"venue"
},
  "geometry": {"coordinates":[-112.131933,33.485695],"type":"Point"}
}