{
  "type": "Feature",
  "properties": {
    "addr:full":"215 S Power Rd Mesa AZ 85206",
    "addr:housenumber":"215",
    "addr:postcode":"85206",
    "addr:street":"S Power Rd",
    "iso:country":"US",
    "sg:address":"215 S Power Rd",
    "sg:city":"Mesa",
    "sg:classifiers":[
        {
            "category":"Health Services",
            "subcategory":"Nursing And Care Facility",
            "type":"Services"
        }
    ],
    "sg:phone":"+1 480 985 6992",
    "sg:postcode":"85206",
    "sg:province":"AZ",
    "sg:tags":[
        "home",
        "convalescent"
    ],
    "wof:name":"Hearthstone Of Mesa",
    "wof:placetype":"venue"
},
  "geometry": {"coordinates":[-111.684471,33.410636],"type":"Point"}
}