{
  "type": "Feature",
  "properties": {
    "iso:country":"US",
    "sg:address":"835 E Camelback Rd",
    "sg:city":"Phoenix",
    "sg:classifiers":[
        {
            "category":"Shopping",
            "subcategory":"Gifts & Souvenirs",
            "type":"Retail Goods"
        }
    ],
    "sg:phone":"+1 602 200 0190",
    "sg:postcode":"85014",
    "sg:province":"AZ",
    "sg:tags":[
        "shop"
    ],
    "wof:name":"Do Me A Favor",
    "wof:placetype":"venue"
},
  "geometry": {"coordinates":[-112.060694,33.509148],"type":"Point"}
}