{
  "type": "Feature",
  "properties": {
    "iso:country":"US",
    "sg:address":"15449 N 25th St",
    "sg:city":"Phoenix",
    "sg:classifiers":[
        {
            "category":"Manufacturing",
            "subcategory":"Buildings",
            "type":"Manufacturing & Wholesale Goods"
        },
        {
            "category":"Building & Trades",
            "subcategory":"Construction",
            "type":"Services"
        },
        {
            "category":"Manufacturing",
            "subcategory":"Building Materials",
            "type":"Manufacturing & Wholesale Goods"
        }
    ],
    "sg:phone":"+1 602 788 3970",
    "sg:postcode":"85032",
    "sg:province":"AZ",
    "sg:tags":[
        "industrial",
        "cabinetmakers-commercial",
        "builder",
        "contractor",
        "contractors-commercial",
        "home",
        "cabinet",
        "maker"
    ],
    "wof:name":"Pfeiffer Customs",
    "wof:placetype":"venue"
},
  "geometry": {"coordinates":[-112.028492,33.627373],"type":"Point"}
}