{
  "type": "Feature",
  "properties": {
    "addr:full":"8962 E Indian Bend Rd Scottsdale AZ 85250",
    "addr:housenumber":"8962",
    "addr:postcode":"85250",
    "addr:street":"E Indian Bend Rd",
    "iso:country":"US",
    "sg:address":"8962 E Indian Bend Rd",
    "sg:city":"Scottsdale",
    "sg:classifiers":[
        {
            "category":"Personal",
            "subcategory":"Beauty Salon",
            "type":"Services"
        }
    ],
    "sg:phone":"+1 480 731 9776",
    "sg:postcode":"85250",
    "sg:province":"AZ",
    "wof:name":"Supercuts",
    "wof:placetype":"venue"
},
  "geometry": {"coordinates":[-111.889444,33.538346],"type":"Point"}
}