{
  "type": "Feature",
  "properties": {
    "iso:country":"US",
    "sg:address":"2126 McCulloch Blvd N",
    "sg:city":"Lake Havasu City",
    "sg:classifiers":[
        {
            "category":"Organizations",
            "subcategory":"Professional Association",
            "type":"Services"
        }
    ],
    "sg:phone":"+1 928 453 8190",
    "sg:postcode":"86403",
    "sg:province":"AZ",
    "wof:name":"Havasu Community Health Trust",
    "wof:placetype":"venue"
},
  "geometry": {"coordinates":[-114.32765499999999,34.475227],"type":"Point"}
}