{
  "type": "Feature",
  "properties": {
    "iso:country":"US",
    "sg:address":"6601 E Grant Rd",
    "sg:city":"Tucson",
    "sg:classifiers":[
        {
            "category":"Health Services",
            "subcategory":"Clinic",
            "type":"Services"
        }
    ],
    "sg:phone":"+1 520 886 6620",
    "sg:postcode":"85715",
    "sg:province":"AZ",
    "sg:tags":[
        "home"
    ],
    "wof:name":"Health Core Nursing",
    "wof:placetype":"venue"
},
  "geometry": {"coordinates":[-110.851542,32.249891],"type":"Point"}
}