{
  "type": "Feature",
  "properties": {
    "iso:country":"US",
    "sg:address":"7406 W McDowell Rd",
    "sg:city":"Phoenix",
    "sg:classifiers":[
        {
            "category":"Restaurant",
            "type":"Food & Drink"
        }
    ],
    "sg:phone":"+1 623 846 2631",
    "sg:postcode":"85035",
    "sg:province":"AZ",
    "sg:tags":[
        "buffet"
    ],
    "wof:name":"Lin's Grand Buffet",
    "wof:placetype":"venue"
},
  "geometry": {"coordinates":[-112.217417,33.465693],"type":"Point"}
}