{
  "type": "Feature",
  "properties": {
    "addr:full":"24908 S 194th St Queen Creek AZ 85242",
    "addr:housenumber":"24908",
    "addr:postcode":"85242",
    "addr:street":"S 194Th St",
    "iso:country":"US",
    "sg:address":"24908 S 194th St",
    "sg:city":"Queen Creek",
    "sg:classifiers":[
        {
            "category":"Building & Trades",
            "subcategory":"Construction",
            "type":"Services"
        }
    ],
    "sg:phone":"+1 480 539 4515",
    "sg:postcode":"85242",
    "sg:province":"AZ",
    "sg:tags":[
        "designer",
        "dealer",
        "pool",
        "swimming"
    ],
    "wof:name":"New Image Pool Design",
    "wof:placetype":"venue"
},
  "geometry": {"coordinates":[-111.66472400000001,33.219517],"type":"Point"}
}