{
  "type": "Feature",
  "properties": {
    "iso:country":"US",
    "sg:address":"7945 Sumac Dr",
    "sg:city":"Pine",
    "sg:classifiers":[
        {
            "category":"Freight",
            "type":"Transportation"
        }
    ],
    "sg:phone":"+1 928 476 2040",
    "sg:postcode":"85544",
    "sg:province":"AZ",
    "sg:tags":[
        "storage",
        "commercial",
        "special"
    ],
    "wof:name":"Bissell Mini Storage",
    "wof:placetype":"venue"
},
  "geometry": {"coordinates":[-111.491258,34.407461],"type":"Point"}
}