{
  "type": "Feature",
  "properties": {
    "addr:full":"32817 Luray Rd Wickenburg AZ 85390",
    "addr:housenumber":"32817",
    "addr:postcode":"85390",
    "addr:street":"Luray Rd",
    "iso:country":"US",
    "sg:address":"32817 Luray Rd",
    "sg:city":"Wickenburg",
    "sg:classifiers":[
        {
            "category":"Building & Trades",
            "subcategory":"Construction",
            "type":"Services"
        }
    ],
    "sg:phone":"+1 928 684 5269",
    "sg:postcode":"85390",
    "sg:province":"AZ",
    "sg:tags":[
        "house",
        "general",
        "contractor"
    ],
    "wof:name":"A H Construction",
    "wof:placetype":"venue"
},
  "geometry": {"coordinates":[-112.767723,33.949975],"type":"Point"}
}