{
  "type": "Feature",
  "properties": {
    "addr:full":"5000 E McDowell Rd Mesa AZ 85215",
    "addr:housenumber":"5000",
    "addr:postcode":"85215",
    "addr:street":"E Mcdowell Rd",
    "iso:country":"US",
    "sg:address":"5000 E McDowell Rd",
    "sg:city":"Mesa",
    "sg:classifiers":[
        {
            "category":"Professional",
            "subcategory":"Management & Consulting",
            "type":"Services"
        }
    ],
    "sg:phone":"+1 480 654 1678",
    "sg:postcode":"85215",
    "sg:province":"AZ",
    "sg:tags":[
        "fuel"
    ],
    "wof:name":"Processing Management Corp",
    "wof:placetype":"venue"
},
  "geometry": {"coordinates":[-111.723116,33.466427],"type":"Point"}
}