{
  "type": "Feature",
  "properties": {
    "iso:country":"US",
    "sg:address":"120 W Coronado Rd",
    "sg:city":"Phoenix",
    "sg:classifiers":[
        {
            "category":"Building & Trades",
            "subcategory":"Construction",
            "type":"Services"
        }
    ],
    "sg:phone":"+1 602 340 0301",
    "sg:postcode":"85003",
    "sg:province":"AZ",
    "wof:name":"Cheuvront Construction",
    "wof:placetype":"venue"
},
  "geometry": {"coordinates":[-112.07783000000001,33.467702],"type":"Point"}
}