{
  "type": "Feature",
  "properties": {
    "iso:country":"US",
    "sg:address":"250 W Continental Rd",
    "sg:city":"Green Valley",
    "sg:classifiers":[
        {
            "category":"Food & Beverages",
            "subcategory":"Specialty",
            "type":"Retail Goods"
        }
    ],
    "sg:phone":"+1 520 625 1499",
    "sg:postcode":"85614",
    "sg:province":"AZ",
    "sg:tags":[
        "health",
        "diet"
    ],
    "wof:name":"Warehouse Vitamins",
    "wof:placetype":"venue"
},
  "geometry": {"coordinates":[-110.99571400000001,31.851604],"type":"Point"}
}