{
  "type": "Feature",
  "properties": {
    "addr:full":"711 E McKinley St Phoenix AZ 85006",
    "addr:housenumber":"711",
    "addr:postcode":"85006",
    "addr:street":"E Mckinley St",
    "iso:country":"US",
    "sg:address":"711 E McKinley St",
    "sg:city":"Phoenix",
    "sg:classifiers":[
        {
            "category":"Shopping",
            "type":"Retail Goods"
        }
    ],
    "sg:phone":"+1 602 340 1023",
    "sg:postcode":"85006",
    "sg:province":"AZ",
    "sg:tags":[
        "merchandise"
    ],
    "wof:name":"Hook Up",
    "wof:placetype":"venue"
},
  "geometry": {"coordinates":[-112.062331,33.456649],"type":"Point"}
}