{
  "type": "Feature",
  "properties": {
    "iso:country":"US",
    "sg:address":"2235 W 1st St",
    "sg:city":"Tempe",
    "sg:classifiers":[
        {
            "category":"Building & Trades",
            "subcategory":"Construction",
            "type":"Services"
        }
    ],
    "sg:phone":"+1 480 894 1306",
    "sg:postcode":"85281",
    "sg:province":"AZ",
    "sg:tags":[
        "concrete",
        "contractor"
    ],
    "wof:name":"All American Concrete LLC",
    "wof:placetype":"venue"
},
  "geometry": {"coordinates":[-111.974897,33.428413],"type":"Point"}
}