{
  "type": "Feature",
  "properties": {
    "addr:full":"675 S 27th Ave Phoenix AZ 85009",
    "addr:housenumber":"675",
    "addr:postcode":"85009",
    "addr:street":"S 27Th Ave",
    "iso:country":"US",
    "sg:address":"675 S 27th Ave",
    "sg:city":"Phoenix",
    "sg:classifiers":[
        {
            "category":"Structure",
            "subcategory":"Warehouse",
            "type":"Public Place"
        },
        {
            "category":"Retail",
            "subcategory":"Storage",
            "type":"Services"
        }
    ],
    "sg:phone":"+1 602 269 0868",
    "sg:postcode":"85009",
    "sg:province":"AZ",
    "sg:tags":[
        "self",
        "warehouses-merchandise"
    ],
    "wof:name":"Phoenix Ranch Market Warehouse",
    "wof:placetype":"venue"
},
  "geometry": {"coordinates":[-112.11744,33.441335],"type":"Point"}
}