{
  "type": "Feature",
  "properties": {
    "iso:country":"US",
    "sg:address":"2831 E Southern Ave",
    "sg:city":"Mesa",
    "sg:classifiers":[
        {
            "category":"Professional",
            "type":"Services"
        }
    ],
    "sg:phone":"+1 480 558 4888",
    "sg:postcode":"85204",
    "sg:province":"AZ",
    "sg:tags":[
        "establishment"
    ],
    "wof:name":"Oh My Ach'n Back",
    "wof:placetype":"venue"
},
  "geometry": {"coordinates":[-111.771205,33.393634],"type":"Point"}
}