{
  "type": "Feature",
  "properties": {
    "addr:full":"4240 E Winslow Ave Phoenix AZ 85040",
    "addr:housenumber":"4240",
    "addr:postcode":"85040",
    "addr:street":"E Winslow Ave",
    "iso:country":"US",
    "sg:address":"4240 E Winslow Ave",
    "sg:city":"Phoenix",
    "sg:classifiers":[
        {
            "category":"Manufacturing",
            "subcategory":"Glass & Minerals",
            "type":"Manufacturing & Wholesale Goods"
        }
    ],
    "sg:phone":"+1 602 437 5641",
    "sg:postcode":"85040",
    "sg:province":"AZ",
    "sg:tags":[
        "product",
        "nonmetallic",
        "mfg"
    ],
    "wof:name":"Featherweight Founder",
    "wof:placetype":"venue"
},
  "geometry": {"coordinates":[-111.987708,33.421106],"type":"Point"}
}