{
  "type": "Feature",
  "properties": {
    "addr:full":"314 N Morley Ave Nogales AZ 85621",
    "addr:housenumber":"314",
    "addr:postcode":"85621",
    "addr:street":"N Morley Ave",
    "iso:country":"US",
    "sg:address":"314 N Morley Ave",
    "sg:city":"Nogales",
    "sg:classifiers":[
        {
            "category":"Building & Trades",
            "subcategory":"Equipment Rental",
            "type":"Services"
        }
    ],
    "sg:phone":"+1 520 287 9333",
    "sg:postcode":"85621",
    "sg:province":"AZ",
    "sg:tags":[
        "yard"
    ],
    "wof:name":"Diamond House",
    "wof:placetype":"venue"
},
  "geometry": {"coordinates":[-110.937067,31.337952],"type":"Point"}
}