{
  "type": "Feature",
  "properties": {
    "iso:country":"US",
    "sg:address":"4109 N 34th St",
    "sg:city":"Phoenix",
    "sg:classifiers":[
        {
            "category":"Social Services",
            "subcategory":"Child Care",
            "type":"Services"
        }
    ],
    "sg:phone":"+1 602 957 1460",
    "sg:postcode":"85018",
    "sg:province":"AZ",
    "wof:name":"Better Beginnings",
    "wof:placetype":"venue"
},
  "geometry": {"coordinates":[-112.008506,33.495566],"type":"Point"}
}