{
  "type": "Feature",
  "properties": {
    "iso:country":"US",
    "sg:address":"340 N Grand Court Plz",
    "sg:city":"Nogales",
    "sg:classifiers":[
        {
            "category":"Shopping",
            "subcategory":"Clothing, Apparel, & Fashions",
            "type":"Retail Goods"
        }
    ],
    "sg:phone":"+1 520 397 9301",
    "sg:postcode":"85621",
    "sg:province":"AZ",
    "wof:name":"Fashion Paradise",
    "wof:placetype":"venue"
},
  "geometry": {"coordinates":[-110.938242,31.338855],"type":"Point"}
}