{
  "type": "Feature",
  "properties": {
    "addr:full":"1304 E Commodore Pl Tempe AZ 85283",
    "addr:housenumber":"1304",
    "addr:postcode":"85283",
    "addr:street":"E Commodore Pl",
    "iso:country":"US",
    "sg:address":"1304 E Commodore Pl",
    "sg:city":"Tempe",
    "sg:classifiers":[
        {
            "category":"Manufacturing",
            "subcategory":"Buildings",
            "type":"Manufacturing & Wholesale Goods"
        },
        {
            "category":"Building & Trades",
            "subcategory":"Construction",
            "type":"Services"
        }
    ],
    "sg:phone":"+1 480 831 9658",
    "sg:postcode":"85283",
    "sg:province":"AZ",
    "sg:tags":[
        "home",
        "builder",
        "contractor"
    ],
    "wof:name":"Raindance Mobile Home Park",
    "wof:placetype":"venue"
},
  "geometry": {"coordinates":[-111.917282,33.37495],"type":"Point"}
}