{
  "type": "Feature",
  "properties": {
    "addr:full":"307 Meander Dr Bullhead City AZ 86442",
    "addr:housenumber":"307",
    "addr:postcode":"86442",
    "addr:street":"Meander Dr",
    "iso:country":"US",
    "sg:address":"307 Meander Dr",
    "sg:city":"Bullhead City",
    "sg:classifiers":[
        {
            "category":"Shopping",
            "subcategory":"Clothing, Apparel, & Fashions",
            "type":"Retail Goods"
        }
    ],
    "sg:phone":"+1 928 763 6731",
    "sg:postcode":"86442",
    "sg:province":"AZ",
    "wof:name":"D Whims",
    "wof:placetype":"venue"
},
  "geometry": {"coordinates":[-114.64009900000001,35.102793],"type":"Point"}
}