{
  "type": "Feature",
  "properties": {
    "iso:country":"US",
    "sg:address":"2000 S Park Ave",
    "sg:city":"Tucson",
    "sg:classifiers":[
        {
            "category":"Place Of Worship",
            "subcategory":"Church",
            "type":"Public Place"
        },
        {
            "category":"Place Of Worship",
            "type":"Public Place"
        }
    ],
    "sg:phone":"+1 520 624 4510",
    "sg:postcode":"85713",
    "sg:province":"AZ",
    "sg:tags":[
        "churches-baptist-general",
        "churches-baptist"
    ],
    "wof:name":"Shield Of Faith Christian Center",
    "wof:placetype":"venue"
},
  "geometry": {"coordinates":[-110.95613899999999,32.198589],"type":"Point"}
}