{
  "type": "Feature",
  "properties": {
    "iso:country":"US",
    "sg:address":"1605 N Industrial Park Dr",
    "sg:city":"Nogales",
    "sg:classifiers":[
        {
            "category":"Freight",
            "type":"Transportation"
        }
    ],
    "sg:phone":"+1 520 761 4552",
    "sg:postcode":"85621",
    "sg:province":"AZ",
    "sg:tags":[
        "broker",
        "trucking"
    ],
    "wof:name":"International Destiny Lgstcs",
    "wof:placetype":"venue"
},
  "geometry": {"coordinates":[-110.947664,31.362238],"type":"Point"}
}