{
  "type": "Feature",
  "properties": {
    "iso:country":"US",
    "sg:address":"5301 E Thomas Rd",
    "sg:city":"Phoenix",
    "sg:classifiers":[
        {
            "category":"Health Services",
            "subcategory":"Nursing And Care Facility",
            "type":"Services"
        }
    ],
    "sg:phone":"+1 602 840 7600",
    "sg:postcode":"85018",
    "sg:province":"AZ",
    "sg:tags":[
        "home",
        "convalescent"
    ],
    "wof:name":"Arbors Of Phoenix",
    "wof:placetype":"venue"
},
  "geometry": {"coordinates":[-111.967071,33.479972],"type":"Point"}
}