{
  "type": "Feature",
  "properties": {
    "iso:country":"US",
    "sg:address":"2580 W Highland Ct",
    "sg:city":"Chandler",
    "sg:classifiers":[
        {
            "category":"Wholesale",
            "subcategory":"Machinery & Supplies",
            "type":"Manufacturing & Wholesale Goods"
        }
    ],
    "sg:phone":"+1 480 782 7412",
    "sg:postcode":"85224",
    "sg:province":"AZ",
    "sg:tags":[
        "equipment",
        "industrial"
    ],
    "wof:name":"Gilson Enterprises Inc",
    "wof:placetype":"venue"
},
  "geometry": {"coordinates":[-111.886277,33.333047],"type":"Point"}
}