{
  "type": "Feature",
  "properties": {
    "iso:country":"US",
    "sg:address":"7611 W Thomas",
    "sg:city":"Litchfield Park",
    "sg:classifiers":[
        {
            "category":"Health Services",
            "subcategory":"Dentist",
            "type":"Services"
        }
    ],
    "sg:phone":"+1 623 873 0880",
    "sg:postcode":"85340",
    "sg:province":"AZ",
    "wof:name":"Gentle Dental",
    "wof:placetype":"venue"
},
  "geometry": {"coordinates":[-112.350222,33.518456],"type":"Point"}
}