{
  "type": "Feature",
  "properties": {
    "iso:country":"US",
    "sg:address":"1285 Hancock Rd",
    "sg:city":"Bullhead City",
    "sg:classifiers":[
        {
            "category":"Insurance",
            "subcategory":"Insurance Agent",
            "type":"Services"
        }
    ],
    "sg:phone":"+1 928 758 7961",
    "sg:postcode":"86442",
    "sg:province":"AZ",
    "wof:name":"Farmers Insurance",
    "wof:placetype":"venue"
},
  "geometry": {"coordinates":[-114.602897,35.107959],"type":"Point"}
}