{
  "type": "Feature",
  "properties": {
    "iso:country":"US",
    "sg:address":"4526 E Camp Lowell Dr",
    "sg:city":"Tucson",
    "sg:classifiers":[
        {
            "category":"Banks & Credit Unions",
            "subcategory":"Bank",
            "type":"Services"
        }
    ],
    "sg:phone":"+1 520 531 8081",
    "sg:postcode":"85712",
    "sg:province":"AZ",
    "sg:tags":[
        "loan",
        "real estate"
    ],
    "wof:name":"Miracle Mortgage",
    "wof:placetype":"venue"
},
  "geometry": {"coordinates":[-110.89538,32.264993],"type":"Point"}
}