{
  "type": "Feature",
  "properties": {
    "addr:full":"246 N Hudson Pl Chandler AZ 85225",
    "addr:housenumber":"246",
    "addr:postcode":"85225",
    "addr:street":"N Hudson Pl",
    "iso:country":"US",
    "sg:address":"246 N Hudson Pl",
    "sg:city":"Chandler",
    "sg:classifiers":[
        {
            "category":"Building & Trades",
            "subcategory":"Construction",
            "type":"Services"
        }
    ],
    "sg:phone":"+1 480 917 2901",
    "sg:postcode":"85225",
    "sg:province":"AZ",
    "sg:tags":[
        "nonresidential"
    ],
    "wof:name":"M & M Services",
    "wof:placetype":"venue"
},
  "geometry": {"coordinates":[-111.819345,33.307598],"type":"Point"}
}