{
  "type": "Feature",
  "properties": {
    "iso:country":"US",
    "sg:address":"6823 E Cam Principal",
    "sg:city":"Tucson",
    "sg:classifiers":[
        {
            "category":"Personal",
            "subcategory":"Beauty Salon",
            "type":"Services"
        }
    ],
    "sg:phone":"+1 520 298 9197",
    "sg:postcode":"85715",
    "sg:province":"AZ",
    "sg:website":"www.dollyquinn.com",
    "wof:name":"Dolly Quinn Salon",
    "wof:placetype":"venue"
},
  "geometry": {"coordinates":[-110.848029,32.250324],"type":"Point"}
}