{
  "type": "Feature",
  "properties": {
    "addr:full":"1548 S Engler Ave Yuma AZ 85365",
    "addr:housenumber":"1548",
    "addr:postcode":"85365",
    "addr:street":"S Engler Ave",
    "iso:country":"US",
    "sg:address":"1548 S Engler Ave",
    "sg:city":"Yuma",
    "sg:classifiers":[
        {
            "category":"Manufacturing",
            "subcategory":"Tools & Machinery",
            "type":"Manufacturing & Wholesale Goods"
        }
    ],
    "sg:phone":"+1 928 783 8167",
    "sg:postcode":"85365",
    "sg:province":"AZ",
    "sg:tags":[
        "mfg",
        "harvesting",
        "cotton",
        "belt"
    ],
    "wof:name":"Goodin Belt Manufacturing Co",
    "wof:placetype":"venue"
},
  "geometry": {"coordinates":[-114.59459,32.700109],"type":"Point"}
}