{
  "type": "Feature",
  "properties": {
    "iso:country":"US",
    "sg:address":"4804 W Gardenia Ave",
    "sg:city":"Glendale",
    "sg:classifiers":[
        {
            "category":"Building & Trades",
            "subcategory":"Construction",
            "type":"Services"
        }
    ],
    "sg:phone":"+1 623 939 0725",
    "sg:postcode":"85301",
    "sg:province":"AZ",
    "sg:tags":[
        "dry wall",
        "contractor"
    ],
    "wof:name":"J W Snipes & Assoc Drywall Inc",
    "wof:placetype":"venue"
},
  "geometry": {"coordinates":[-112.16269,33.545028],"type":"Point"}
}