{
  "type": "Feature",
  "properties": {
    "addr:full":"6819 W Peoria Ave Peoria AZ 85345",
    "addr:housenumber":"6819",
    "addr:postcode":"85345",
    "addr:street":"W Peoria Ave",
    "iso:country":"US",
    "sg:address":"6819 W Peoria Ave",
    "sg:city":"Peoria",
    "sg:classifiers":[
        {
            "category":"Recreation",
            "type":"Entertainment"
        }
    ],
    "sg:phone":"+1 623 486 4779",
    "sg:postcode":"85345",
    "sg:province":"AZ",
    "sg:tags":[
        "martial",
        "arts",
        "instruction"
    ],
    "wof:name":"ATA Black Belt Academy",
    "wof:placetype":"venue"
},
  "geometry": {"coordinates":[-112.20482800000001,33.581585],"type":"Point"}
}