{
  "type": "Feature",
  "properties": {
    "iso:country":"US",
    "sg:address":"6929 E Jenan Dr",
    "sg:city":"Scottsdale",
    "sg:classifiers":[
        {
            "category":"Home & Garden",
            "subcategory":"Carpets & Floor Coverings",
            "type":"Retail Goods"
        }
    ],
    "sg:phone":"+1 480 922 9232",
    "sg:postcode":"85254",
    "sg:province":"AZ",
    "wof:name":"Navajo Arts",
    "wof:placetype":"venue"
},
  "geometry": {"coordinates":[-111.932586,33.592313],"type":"Point"}
}