{
  "type": "Feature",
  "properties": {
    "iso:country":"US",
    "sg:address":"2020 W Indian School Rd",
    "sg:city":"Phoenix",
    "sg:classifiers":[
        {
            "category":"Shopping",
            "subcategory":"Department Store",
            "type":"Retail Goods"
        },
        {
            "category":"Shopping",
            "subcategory":"Discount & Variety Stores",
            "type":"Retail Goods"
        }
    ],
    "sg:phone":"+1 602 266 0662",
    "sg:postcode":"85015",
    "sg:province":"AZ",
    "wof:name":"Noor Family Dollar Discount Store",
    "wof:placetype":"venue"
},
  "geometry": {"coordinates":[-112.102547,33.495024],"type":"Point"}
}