{
  "type": "Feature",
  "properties": {
    "iso:country":"US",
    "sg:address":"962 W Medina Ave",
    "sg:city":"Mesa",
    "sg:classifiers":[
        {
            "category":"Building & Trades",
            "subcategory":"Locksmith",
            "type":"Services"
        }
    ],
    "sg:phone":"+1 480 459 4496",
    "sg:postcode":"85201",
    "sg:province":"AZ",
    "sg:tags":[
        "key"
    ],
    "wof:name":"0 A A A 24 Hr Locksmith",
    "wof:placetype":"venue"
},
  "geometry": {"coordinates":[-111.854287,33.371637],"type":"Point"}
}