{
  "type": "Feature",
  "properties": {
    "iso:country":"US",
    "sg:address":"5365 N 51st Ave",
    "sg:city":"Glendale",
    "sg:classifiers":[
        {
            "category":"Manufacturing",
            "subcategory":"Furniture",
            "type":"Manufacturing & Wholesale Goods"
        }
    ],
    "sg:phone":"+1 623 934 5857",
    "sg:postcode":"85301",
    "sg:province":"AZ",
    "wof:name":"Legends Furniture Warehouse",
    "wof:placetype":"venue"
},
  "geometry": {"coordinates":[-112.16864,33.515446],"type":"Point"}
}