{
  "type": "Feature",
  "properties": {
    "addr:full":"6922 E 5th Ave Scottsdale AZ 85251",
    "addr:housenumber":"6922",
    "addr:postcode":"85251",
    "addr:street":"E 5Th Ave",
    "iso:country":"US",
    "sg:address":"6922 E 5th Ave",
    "sg:city":"Scottsdale",
    "sg:classifiers":[
        {
            "category":"Personal",
            "subcategory":"Beauty Salon",
            "type":"Services"
        }
    ],
    "sg:phone":"+1 480 970 4660",
    "sg:postcode":"85251",
    "sg:province":"AZ",
    "wof:name":"D'Aubyn Color",
    "wof:placetype":"venue"
},
  "geometry": {"coordinates":[-111.933393,33.494835],"type":"Point"}
}