{
  "type": "Feature",
  "properties": {
    "iso:country":"US",
    "sg:address":"8620 S 14th Pl",
    "sg:city":"Phoenix",
    "sg:classifiers":[
        {
            "category":"Social Services",
            "subcategory":"Adult Care",
            "type":"Services"
        }
    ],
    "sg:phone":"+1 602 243 6885",
    "sg:postcode":"85042",
    "sg:province":"AZ",
    "sg:tags":[
        "nurses-home"
    ],
    "wof:name":"Tender Care Group Home",
    "wof:placetype":"venue"
},
  "geometry": {"coordinates":[-112.052117,33.368417],"type":"Point"}
}