{
  "type": "Feature",
  "properties": {
    "addr:full":"7404 S 30th Ln Phoenix AZ 85041",
    "addr:housenumber":"7404",
    "addr:postcode":"85041",
    "addr:street":"S 30Th Ln",
    "iso:country":"US",
    "sg:address":"7404 S 30th Ln",
    "sg:city":"Phoenix",
    "sg:classifiers":[
        {
            "category":"Local Transit",
            "type":"Transportation"
        }
    ],
    "sg:phone":"+1 602 276 0186",
    "sg:postcode":"85041",
    "sg:province":"AZ",
    "wof:name":"JFG Transport Inc",
    "wof:placetype":"venue"
},
  "geometry": {"coordinates":[-112.12441699999999,33.379118],"type":"Point"}
}