{
  "type": "Feature",
  "properties": {
    "iso:country":"US",
    "sg:address":"20220 N 59th Ave",
    "sg:city":"Glendale",
    "sg:classifiers":[
        {
            "category":"Food & Beverages",
            "subcategory":"Groceries & Convenience Stores",
            "type":"Retail Goods"
        }
    ],
    "sg:phone":"+1 623 825 3111",
    "sg:postcode":"85308",
    "sg:province":"AZ",
    "wof:name":"Dillons",
    "wof:placetype":"venue"
},
  "geometry": {"coordinates":[-112.186796,33.668448],"type":"Point"}
}