{
  "type": "Feature",
  "properties": {
    "iso:country":"US",
    "sg:address":"12814 N 28th Dr",
    "sg:city":"Phoenix",
    "sg:classifiers":[
        {
            "category":"Professional",
            "type":"Services"
        }
    ],
    "sg:phone":"+1 602 863 0195",
    "sg:postcode":"85029",
    "sg:province":"AZ",
    "wof:name":"R & G",
    "wof:placetype":"venue"
},
  "geometry": {"coordinates":[-112.119771,33.603516],"type":"Point"}
}