{
  "type": "Feature",
  "properties": {
    "addr:full":"2899 Hidden Meadow Ln Bisbee AZ 85603",
    "addr:housenumber":"2899",
    "addr:postcode":"85603",
    "addr:street":"Hidden Meadow Ln",
    "iso:country":"US",
    "sg:address":"2899 Hidden Meadow Ln",
    "sg:city":"Bisbee",
    "sg:classifiers":[
        {
            "category":"Organizations",
            "subcategory":"Community Association",
            "type":"Services"
        }
    ],
    "sg:phone":"+1 520 432 1388",
    "sg:postcode":"85603",
    "sg:province":"AZ",
    "sg:tags":[
        "environmental",
        "org"
    ],
    "wof:name":"Southeastern Bird Observatory",
    "wof:placetype":"venue"
},
  "geometry": {"coordinates":[-109.974226,31.47277],"type":"Point"}
}