{
  "type": "Feature",
  "properties": {
    "iso:country":"US",
    "sg:address":"16652 E Glenbrook Blvd",
    "sg:city":"Fountain Hills",
    "sg:classifiers":[
        {
            "category":"Organizations",
            "subcategory":"Religious Organization",
            "type":"Services"
        }
    ],
    "sg:phone":"+1 480 837 7627",
    "sg:postcode":"85268",
    "sg:province":"AZ",
    "sg:tags":[
        "church"
    ],
    "sg:website":"www.thefountainsumc.org",
    "wof:name":"Fountains United Methodist Chr",
    "wof:placetype":"venue"
},
  "geometry": {"coordinates":[-111.721694,33.624653],"type":"Point"}
}