{
  "type": "Feature",
  "properties": {
    "addr:full":"2101 W Dove Way Amado AZ 85645",
    "addr:housenumber":"2101",
    "addr:postcode":"85645",
    "addr:street":"W Dove Way",
    "iso:country":"US",
    "sg:address":"2101 W Dove Way",
    "sg:city":"Amado",
    "sg:classifiers":[
        {
            "category":"Building & Trades",
            "subcategory":"Construction",
            "type":"Services"
        }
    ],
    "sg:phone":"+1 520 398 9067",
    "sg:postcode":"85645",
    "sg:province":"AZ",
    "sg:tags":[
        "concrete",
        "contractor"
    ],
    "wof:name":"J & L Concrete",
    "wof:placetype":"venue"
},
  "geometry": {"coordinates":[-111.007886,31.748357],"type":"Point"}
}