{
  "type": "Feature",
  "properties": {
    "iso:country":"US",
    "sg:address":"5915 E Cielo Run N",
    "sg:city":"Cave Creek",
    "sg:classifiers":[
        {
            "category":"Autos & Motor Vehicles",
            "subcategory":"Motorcycle Sales",
            "type":"Retail Goods"
        }
    ],
    "sg:phone":"+1 480 488 5814",
    "sg:postcode":"85331",
    "sg:province":"AZ",
    "wof:name":"Cas Communications Inc",
    "wof:placetype":"venue"
},
  "geometry": {"coordinates":[-111.946733,33.862742],"type":"Point"}
}