{
  "type": "Feature",
  "properties": {
    "addr:full":"8501 E Princess Dr Scottsdale AZ 85255",
    "addr:housenumber":"8501",
    "addr:postcode":"85255",
    "addr:street":"E Princess Dr",
    "iso:country":"US",
    "sg:address":"8501 E Princess Dr",
    "sg:city":"Scottsdale",
    "sg:classifiers":[
        {
            "category":"Manufacturing",
            "subcategory":"Printing",
            "type":"Manufacturing & Wholesale Goods"
        }
    ],
    "sg:phone":"+1 480 664 3960",
    "sg:postcode":"85255",
    "sg:province":"AZ",
    "sg:tags":[
        "publisher"
    ],
    "sg:website":"www.phoenixmag.com",
    "wof:name":"Cities West Publishing Inc",
    "wof:placetype":"venue"
},
  "geometry": {"coordinates":[-111.89385299999999,33.646446],"type":"Point"}
}