{
  "type": "Feature",
  "properties": {
    "iso:country":"US",
    "sg:address":"417 E Broadway Rd",
    "sg:city":"Phoenix",
    "sg:classifiers":[
        {
            "category":"Real Estate",
            "subcategory":"Real Estate Services",
            "type":"Services"
        }
    ],
    "sg:phone":"+1 602 264 3216",
    "sg:postcode":"85040",
    "sg:province":"AZ",
    "sg:tags":[
        "company",
        "title"
    ],
    "wof:name":"B Everitt Title Svc",
    "wof:placetype":"venue"
},
  "geometry": {"coordinates":[-112.067604,33.406637],"type":"Point"}
}