{
  "type": "Feature",
  "properties": {
    "iso:country":"US",
    "sg:address":"1108 E Carlise Rd",
    "sg:city":"Phoenix",
    "sg:classifiers":[
        {
            "category":"Travel",
            "subcategory":"Bed & Breakfast",
            "type":"Entertainment"
        }
    ],
    "sg:phone":"+1 623 465 0062",
    "sg:postcode":"85086",
    "sg:province":"AZ",
    "sg:tags":[
        "inn"
    ],
    "wof:name":"Lee S Wok Inn Inc",
    "wof:placetype":"venue"
},
  "geometry": {"coordinates":[-112.061072,33.824473],"type":"Point"}
}