{
  "type": "Feature",
  "properties": {
    "iso:country":"US",
    "sg:address":"4720 W Banff Ln",
    "sg:city":"Glendale",
    "sg:classifiers":[
        {
            "category":"Manufacturing",
            "subcategory":"Building Materials",
            "type":"Manufacturing & Wholesale Goods"
        }
    ],
    "sg:phone":"+1 602 938 1301",
    "sg:postcode":"85306",
    "sg:province":"AZ",
    "sg:tags":[
        "mfg"
    ],
    "wof:name":"R B Creations",
    "wof:placetype":"venue"
},
  "geometry": {"coordinates":[-112.168044,33.619827],"type":"Point"}
}