{
  "type": "Feature",
  "properties": {
    "iso:country":"US",
    "sg:address":"7930 E Arlington Rd",
    "sg:city":"Scottsdale",
    "sg:classifiers":[
        {
            "category":"Banks & Credit Unions",
            "subcategory":"Bank",
            "type":"Services"
        }
    ],
    "sg:phone":"+1 888 882 8430",
    "sg:postcode":"85250",
    "sg:province":"AZ",
    "sg:tags":[
        "broker",
        "mortgage"
    ],
    "wof:name":"Peak Mortgage Co",
    "wof:placetype":"venue"
},
  "geometry": {"coordinates":[-111.909604,33.517822],"type":"Point"}
}