{
  "type": "Feature",
  "properties": {
    "addr:full":"9000 US Hwy 89 Flagstaff AZ 86004",
    "addr:housenumber":"9000",
    "addr:postcode":"86004",
    "addr:street":"Us Hwy 89",
    "iso:country":"US",
    "sg:address":"9000 US Hwy 89",
    "sg:city":"Flagstaff",
    "sg:classifiers":[
        {
            "category":"Real Estate",
            "subcategory":"Developer",
            "type":"Services"
        }
    ],
    "sg:phone":"+1 928 526 0899",
    "sg:postcode":"86004",
    "sg:province":"AZ",
    "sg:tags":[
        "mobile",
        "home"
    ],
    "wof:name":"Silver Saddle Mobile Home Park",
    "wof:placetype":"venue"
},
  "geometry": {"coordinates":[-111.54489599999999,35.270842],"type":"Point"}
}