{
  "type": "Feature",
  "properties": {
    "iso:country":"US",
    "sg:address":"24827 S Dobson Rd",
    "sg:city":"Sun Lakes",
    "sg:classifiers":[
        {
            "category":"Organizations",
            "subcategory":"Religious Organization",
            "type":"Services"
        }
    ],
    "sg:phone":"+1 480 895 9266",
    "sg:postcode":"85248",
    "sg:province":"AZ",
    "wof:name":"St Stevens Church",
    "wof:placetype":"venue"
},
  "geometry": {"coordinates":[-111.87599899999999,33.222801],"type":"Point"}
}