{
  "type": "Feature",
  "properties": {
    "iso:country":"US",
    "sg:address":"1201 W 13th St",
    "sg:city":"Yuma",
    "sg:classifiers":[
        {
            "category":"Taxi",
            "type":"Transportation"
        }
    ],
    "sg:phone":"+1 928 329 1182",
    "sg:postcode":"85364",
    "sg:province":"AZ",
    "sg:tags":[
        "taxicab"
    ],
    "wof:name":"Nomar Zeds Taxi Service",
    "wof:placetype":"venue"
},
  "geometry": {"coordinates":[-114.635381,32.704039],"type":"Point"}
}