{
  "type": "Feature",
  "properties": {
    "iso:country":"US",
    "sg:address":"150 N McCormick St",
    "sg:city":"Prescott",
    "sg:classifiers":[
        {
            "category":"Shopping",
            "subcategory":"Used Merchandise",
            "type":"Retail Goods"
        }
    ],
    "sg:phone":"+1 928 445 2451",
    "sg:postcode":"86301",
    "sg:province":"AZ",
    "wof:name":"Parada Art Gallery",
    "wof:placetype":"venue"
},
  "geometry": {"coordinates":[-112.472931,34.542889],"type":"Point"}
}