{
  "type": "Feature",
  "properties": {
    "iso:country":"US",
    "sg:address":"801 W Elliot Rd",
    "sg:city":"Chandler",
    "sg:classifiers":[
        {
            "category":"Health Services",
            "subcategory":"Dentist",
            "type":"Services"
        }
    ],
    "sg:phone":"+1 480 899 6229",
    "sg:postcode":"85225",
    "sg:province":"AZ",
    "wof:name":"Otteson Kevin H",
    "wof:placetype":"venue"
},
  "geometry": {"coordinates":[-111.856003,33.349602],"type":"Point"}
}