{
  "type": "Feature",
  "properties": {
    "iso:country":"US",
    "sg:address":"254 W Baseline Rd",
    "sg:city":"Tempe",
    "sg:classifiers":[
        {
            "category":"Professional",
            "subcategory":"Testing Lab",
            "type":"Services"
        }
    ],
    "sg:phone":"+1 480 820 9444",
    "sg:postcode":"85283",
    "sg:province":"AZ",
    "sg:tags":[
        "laboratory"
    ],
    "wof:name":"Techsystems",
    "wof:placetype":"venue"
},
  "geometry": {"coordinates":[-111.941768,33.378304],"type":"Point"}
}