{
  "type": "Feature",
  "properties": {
    "addr:full":"10404 E Apache Trl Apache Junction AZ 85220",
    "addr:housenumber":"10404",
    "addr:postcode":"85220",
    "addr:street":"E Apache Trl",
    "iso:country":"US",
    "sg:address":"10404 E Apache Trl",
    "sg:city":"Apache Junction",
    "sg:classifiers":[
        {
            "category":"Manufacturing",
            "subcategory":"Motor Vehicles & Parts",
            "type":"Manufacturing & Wholesale Goods"
        }
    ],
    "sg:phone":"+1 480 358 0515",
    "sg:postcode":"85220",
    "sg:province":"AZ",
    "sg:tags":[
        "mfg"
    ],
    "wof:name":"Z Moto",
    "wof:placetype":"venue"
},
  "geometry": {"coordinates":[-111.606461,33.415096],"type":"Point"}
}