{
  "type": "Feature",
  "properties": {
    "iso:country":"US",
    "sg:address":"101 W Beck Ln",
    "sg:city":"Phoenix",
    "sg:classifiers":[
        {
            "category":"Real Estate",
            "subcategory":"Developer",
            "type":"Services"
        }
    ],
    "sg:phone":"+1 602 863 3050",
    "sg:postcode":"85023",
    "sg:province":"AZ",
    "sg:tags":[
        "general",
        "contractor"
    ],
    "wof:name":"Luxury Plus Development Ltd",
    "wof:placetype":"venue"
},
  "geometry": {"coordinates":[-112.07602799999999,33.626506],"type":"Point"}
}