{
  "type": "Feature",
  "properties": {
    "iso:country":"US",
    "sg:address":"5937 W Golden Ln",
    "sg:city":"Glendale",
    "sg:classifiers":[
        {
            "category":"Retail",
            "subcategory":"Auto Repair",
            "type":"Services"
        }
    ],
    "sg:phone":"+1 623 435 1766",
    "sg:postcode":"85302",
    "sg:province":"AZ",
    "sg:tags":[
        "automobile",
        "co",
        "drive",
        "transporter"
    ],
    "wof:name":"Smoov Transport",
    "wof:placetype":"venue"
},
  "geometry": {"coordinates":[-112.188128,33.5645],"type":"Point"}
}