{
  "type": "Feature",
  "properties": {
    "iso:country":"US",
    "sg:address":"21 W Jefferson St",
    "sg:city":"Phoenix",
    "sg:classifiers":[
        {
            "category":"Autos & Motor Vehicles",
            "subcategory":"Automobile Sales",
            "type":"Retail Goods"
        },
        {
            "category":"Personal",
            "type":"Services"
        },
        {
            "category":"Wholesale",
            "subcategory":"Scrap",
            "type":"Manufacturing & Wholesale Goods"
        }
    ],
    "sg:phone":"+1 877 586 5692",
    "sg:postcode":"85003",
    "sg:province":"AZ",
    "sg:tags":[
        "truck",
        "salvage",
        "wrecking",
        "towing"
    ],
    "wof:name":"Junkmycar.com",
    "wof:placetype":"venue"
},
  "geometry": {"coordinates":[-112.07408,33.447128],"type":"Point"}
}