{
  "type": "Feature",
  "properties": {
    "addr:full":"4137 W Thunderbird Rd Phoenix AZ 85053",
    "addr:housenumber":"4137",
    "addr:postcode":"85053",
    "addr:street":"W Thunderbird Rd",
    "iso:country":"US",
    "sg:address":"4137 W Thunderbird Rd",
    "sg:city":"Phoenix",
    "sg:classifiers":[
        {
            "category":"Wholesale",
            "subcategory":"Machinery & Supplies",
            "type":"Manufacturing & Wholesale Goods"
        }
    ],
    "sg:phone":"+1 602 938 3387",
    "sg:postcode":"85053",
    "sg:province":"AZ",
    "sg:tags":[
        "shop",
        "equipment",
        "salon",
        "barber",
        "beauty"
    ],
    "wof:name":"Sally Beauty Supply 577",
    "wof:placetype":"venue"
},
  "geometry": {"coordinates":[-112.14956100000001,33.610653],"type":"Point"}
}