{
  "type": "Feature",
  "properties": {
    "iso:country":"US",
    "sg:address":"6241 N Panorama Dr",
    "sg:city":"Tucson",
    "sg:classifiers":[
        {
            "category":"Real Estate",
            "subcategory":"Real Estate Agent",
            "type":"Services"
        }
    ],
    "sg:phone":"+1 520 744 7219",
    "sg:postcode":"85743",
    "sg:province":"AZ",
    "wof:name":"Schoen Est Inc",
    "wof:placetype":"venue"
},
  "geometry": {"coordinates":[-111.06925099999999,32.323012],"type":"Point"}
}