{
  "type": "Feature",
  "properties": {
    "addr:full":"6905 E Broadway Blvd Tucson AZ 85710",
    "addr:housenumber":"6905",
    "addr:postcode":"85710",
    "addr:street":"E Broadway Blvd",
    "iso:country":"US",
    "sg:address":"6905 E Broadway Blvd",
    "sg:city":"Tucson",
    "sg:classifiers":[
        {
            "category":"Autos & Motor Vehicles",
            "subcategory":"Auto Supplies",
            "type":"Retail Goods"
        },
        {
            "category":"Retail",
            "subcategory":"Auto Repair",
            "type":"Services"
        }
    ],
    "sg:phone":"+1 520 298 5500",
    "sg:postcode":"85710",
    "sg:province":"AZ",
    "sg:tags":[
        "repairing",
        "automobile",
        "r",
        "automotive",
        "exhaust"
    ],
    "sg:website":"www.meineke.com",
    "wof:name":"Meineke Car Care Center",
    "wof:placetype":"venue"
},
  "geometry": {"coordinates":[-110.841055,32.221113],"type":"Point"}
}