{
  "type": "Feature",
  "properties": {
    "iso:country":"US",
    "sg:address":"8560 E 22nd St",
    "sg:city":"Tucson",
    "sg:classifiers":[
        {
            "category":"Health Services",
            "subcategory":"Health Practitioner",
            "type":"Services"
        }
    ],
    "sg:phone":"+1 520 733 2244",
    "sg:postcode":"85710",
    "sg:province":"AZ",
    "sg:tags":[
        "acupuncture"
    ],
    "wof:name":"Diane Notarianni Phd Lac Dipl",
    "wof:placetype":"venue"
},
  "geometry": {"coordinates":[-110.810001,32.206318],"type":"Point"}
}