{
  "type": "Feature",
  "properties": {
    "iso:country":"US",
    "sg:address":"8221 N 73rd Pl",
    "sg:city":"Scottsdale",
    "sg:classifiers":[
        {
            "category":"Shopping",
            "subcategory":"Pets & Pet Supplies",
            "type":"Retail Goods"
        }
    ],
    "sg:phone":"+1 480 443 8729",
    "sg:postcode":"85258",
    "sg:province":"AZ",
    "sg:tags":[
        "taxidermists-equipment"
    ],
    "wof:name":"Bear Bones",
    "wof:placetype":"venue"
},
  "geometry": {"coordinates":[-111.922656,33.555593],"type":"Point"}
}