{
  "type": "Feature",
  "properties": {
    "iso:country":"US",
    "sg:address":"4505 E 22nd St",
    "sg:city":"Tucson",
    "sg:classifiers":[
        {
            "category":"Retail",
            "subcategory":"Auto Repair",
            "type":"Services"
        }
    ],
    "sg:phone":"+1 520 750 8523",
    "sg:postcode":"85711",
    "sg:province":"AZ",
    "sg:tags":[
        "glass",
        "replacement"
    ],
    "wof:name":"National Auto Glass Co Tucson",
    "wof:placetype":"venue"
},
  "geometry": {"coordinates":[-110.895358,32.207036],"type":"Point"}
}