{
  "type": "Feature",
  "properties": {
    "iso:country":"US",
    "sg:address":"656 Jordan Rd",
    "sg:city":"Sedona",
    "sg:classifiers":[
        {
            "category":"Travel",
            "subcategory":"Hotels & Motels",
            "type":"Entertainment"
        },
        {
            "category":"Travel",
            "subcategory":"Bed & Breakfast",
            "type":"Entertainment"
        }
    ],
    "sg:phone":"+1 928 282 5328",
    "sg:postcode":"86336",
    "sg:province":"AZ",
    "sg:tags":[
        "inn",
        "lodging"
    ],
    "wof:name":"Apple Orchard Inn",
    "wof:placetype":"venue"
},
  "geometry": {"coordinates":[-111.761008,34.877272],"type":"Point"}
}