{
  "type": "Feature",
  "properties": {
    "addr:full":"22149 E Ocotillo Rd Queen Creek AZ 85242",
    "addr:housenumber":"22149",
    "addr:postcode":"85242",
    "addr:street":"E Ocotillo Rd",
    "iso:country":"US",
    "sg:address":"22149 E Ocotillo Rd",
    "sg:city":"Queen Creek",
    "sg:classifiers":[
        {
            "category":"Education",
            "subcategory":"School",
            "type":"Public Place"
        }
    ],
    "sg:phone":"+1 480 987 5960",
    "sg:postcode":"85242",
    "sg:province":"AZ",
    "wof:name":"Queen Creek High School",
    "wof:placetype":"venue"
},
  "geometry": {"coordinates":[-111.60611900000001,33.248534],"type":"Point"}
}