{
  "type": "Feature",
  "properties": {
    "iso:country":"US",
    "sg:address":"13200 N 113th Ave",
    "sg:city":"Youngtown",
    "sg:classifiers":[
        {
            "category":"Building & Trades",
            "subcategory":"Pest Control",
            "type":"Services"
        }
    ],
    "sg:phone":"+1 623 979 6467",
    "sg:postcode":"85363",
    "sg:province":"AZ",
    "wof:name":"Amera Sun City Pest Control",
    "wof:placetype":"venue"
},
  "geometry": {"coordinates":[-112.301834,33.603409],"type":"Point"}
}