{
  "type": "Feature",
  "properties": {
    "iso:country":"US",
    "sg:address":"1715 Becker Ln",
    "sg:city":"Springerville",
    "sg:classifiers":[
        {
            "category":"Building & Trades",
            "subcategory":"Electrical",
            "type":"Services"
        }
    ],
    "sg:phone":"+1 928 333 5192",
    "sg:postcode":"85938",
    "sg:province":"AZ",
    "sg:tags":[
        "electrical",
        "contractor"
    ],
    "wof:name":"Arc & Spark Electric",
    "wof:placetype":"venue"
},
  "geometry": {"coordinates":[-109.250162,34.122222],"type":"Point"}
}