{
  "type": "Feature",
  "properties": {
    "iso:country":"US",
    "sg:address":"7400 E Monte Cristo Ave",
    "sg:city":"Scottsdale",
    "sg:classifiers":[
        {
            "category":"Wholesale",
            "subcategory":"Computers",
            "type":"Manufacturing & Wholesale Goods"
        },
        {
            "category":"Shopping",
            "subcategory":"Computers & Home Electronics",
            "type":"Retail Goods"
        }
    ],
    "sg:phone":"+1 480 947 9912",
    "sg:postcode":"85260",
    "sg:province":"AZ",
    "sg:tags":[
        "equipment",
        "dealer"
    ],
    "sg:website":"www.featuremarketing.com",
    "wof:name":"Feature Marketing Inc",
    "wof:placetype":"venue"
},
  "geometry": {"coordinates":[-111.921997,33.631198],"type":"Point"}
}