{
  "type": "Feature",
  "properties": {
    "addr:full":"12152 N Rancho Vistoso Blvd Tucson AZ 85737",
    "addr:housenumber":"12152",
    "addr:postcode":"85737",
    "addr:street":"N Rancho Vistoso Blvd",
    "iso:country":"US",
    "sg:address":"12152 N Rancho Vistoso Blvd",
    "sg:city":"Tucson",
    "sg:classifiers":[
        {
            "category":"Health Services",
            "subcategory":"Doctor",
            "type":"Services"
        }
    ],
    "sg:phone":"+1 520 531 8207",
    "sg:postcode":"85737",
    "sg:province":"AZ",
    "sg:tags":[
        "dentist"
    ],
    "wof:name":"Northstar Dental PC",
    "wof:placetype":"venue"
},
  "geometry": {"coordinates":[-110.960999,32.4244],"type":"Point"}
}