{
  "type": "Feature",
  "properties": {
    "addr:full":"2405 E Long Shadow Pl Tucson AZ 85718",
    "addr:housenumber":"2405",
    "addr:postcode":"85718",
    "addr:street":"E Long Shadow Pl",
    "iso:country":"US",
    "sg:address":"2405 E Long Shadow Pl",
    "sg:city":"Tucson",
    "sg:classifiers":[
        {
            "category":"Professional",
            "subcategory":"Management & Consulting",
            "type":"Services"
        }
    ],
    "sg:phone":"+1 520 229 9105",
    "sg:postcode":"85718",
    "sg:province":"AZ",
    "sg:tags":[
        "consultant",
        "business"
    ],
    "wof:name":"Lee Browne Inc",
    "wof:placetype":"venue"
},
  "geometry": {"coordinates":[-110.937763,32.340194],"type":"Point"}
}