{
  "type": "Feature",
  "properties": {
    "iso:country":"US",
    "sg:address":"7580 E Gray Rd",
    "sg:city":"Scottsdale",
    "sg:classifiers":[
        {
            "category":"Real Estate",
            "subcategory":"Real Estate Operator",
            "type":"Services"
        }
    ],
    "sg:phone":"+1 480 948 3255",
    "sg:postcode":"85260",
    "sg:province":"AZ",
    "sg:tags":[
        "apartment"
    ],
    "wof:name":"All Florida Apartments LLC",
    "wof:placetype":"venue"
},
  "geometry": {"coordinates":[-111.91719000000001,33.612716],"type":"Point"}
}