{
  "type": "Feature",
  "properties": {
    "iso:country":"US",
    "sg:address":"3822 E 5th St",
    "sg:city":"Tucson",
    "sg:classifiers":[
        {
            "category":"Health Services",
            "subcategory":"Doctor",
            "type":"Services"
        }
    ],
    "sg:phone":"+1 520 326 1031",
    "sg:postcode":"85716",
    "sg:province":"AZ",
    "sg:tags":[
        "dentist"
    ],
    "wof:name":"Fred J White DDS",
    "wof:placetype":"venue"
},
  "geometry": {"coordinates":[-110.910055,32.228814],"type":"Point"}
}