{
  "type": "Feature",
  "properties": {
    "iso:country":"US",
    "sg:address":"211 W Corral Dr",
    "sg:city":"Payson",
    "sg:classifiers":[
        {
            "category":"Building & Trades",
            "subcategory":"Construction",
            "type":"Services"
        }
    ],
    "sg:phone":"+1 928 472 8024",
    "sg:postcode":"85541",
    "sg:province":"AZ",
    "sg:tags":[
        "roofing",
        "contractor"
    ],
    "wof:name":"Whaley's Roofing",
    "wof:placetype":"venue"
},
  "geometry": {"coordinates":[-111.326138,34.265123],"type":"Point"}
}