{
  "type": "Feature",
  "properties": {
    "iso:country":"US",
    "sg:address":"40 S 11th St",
    "sg:city":"Show Low",
    "sg:classifiers":[
        {
            "category":"Government",
            "subcategory":"Office",
            "type":"Public Place"
        }
    ],
    "sg:phone":"+1 928 537 4261",
    "sg:postcode":"85901",
    "sg:province":"AZ",
    "sg:tags":[
        "assistance",
        "family"
    ],
    "wof:name":"Family Assistance ADM",
    "wof:placetype":"venue"
},
  "geometry": {"coordinates":[-110.030314,34.24865],"type":"Point"}
}