{
  "type": "Feature",
  "properties": {
    "iso:country":"US",
    "sg:address":"2112 N Dragoon St",
    "sg:city":"Tucson",
    "sg:classifiers":[
        {
            "category":"Home & Garden",
            "subcategory":"Carpets & Floor Coverings",
            "type":"Retail Goods"
        }
    ],
    "sg:phone":"+1 520 884 1131",
    "sg:postcode":"85745",
    "sg:province":"AZ",
    "wof:name":"Lindbergh Carpet Co",
    "wof:placetype":"venue"
},
  "geometry": {"coordinates":[-111.00052599999999,32.249004],"type":"Point"}
}