{
  "type": "Feature",
  "properties": {
    "iso:country":"US",
    "sg:address":"2708 E Grant Rd",
    "sg:city":"Tucson",
    "sg:classifiers":[
        {
            "category":"Shopping",
            "subcategory":"Gifts & Souvenirs",
            "type":"Retail Goods"
        }
    ],
    "sg:phone":"+1 520 795 7832",
    "sg:postcode":"85716",
    "sg:province":"AZ",
    "sg:tags":[
        "basket",
        "parcel"
    ],
    "wof:name":"Centerfold Studio",
    "wof:placetype":"venue"
},
  "geometry": {"coordinates":[-110.93217,32.250275],"type":"Point"}
}