{
  "type": "Feature",
  "properties": {
    "addr:full":"PO Box 45124 Phoenix AZ 85064",
    "addr:housenumber":"po box 45124",
    "addr:postcode":"85064",
    "iso:country":"US",
    "sg:address":"PO Box 45124",
    "sg:city":"Phoenix",
    "sg:classifiers":[
        {
            "category":"Building & Trades",
            "subcategory":"Construction",
            "type":"Services"
        }
    ],
    "sg:phone":"+1 602 955 4097",
    "sg:postcode":"85064",
    "sg:province":"AZ",
    "sg:tags":[
        "contractor"
    ],
    "wof:name":"Tallman Construction",
    "wof:placetype":"venue"
},
  "geometry": {"coordinates":[-112.22199999999999,33.480099],"type":"Point"}
}