{
  "type": "Feature",
  "properties": {
    "iso:country":"US",
    "sg:address":"2825 N Glassford Hill Rd",
    "sg:city":"Prescott Valley",
    "sg:classifiers":[
        {
            "category":"Insurance",
            "subcategory":"Insurance Agent",
            "type":"Services"
        }
    ],
    "sg:phone":"+1 928 775 6666",
    "sg:postcode":"86314",
    "sg:province":"AZ",
    "wof:name":"Allstate Insurance Co",
    "wof:placetype":"venue"
},
  "geometry": {"coordinates":[-112.342501,34.584482],"type":"Point"}
}