{
  "type": "Feature",
  "properties": {
    "iso:country":"US",
    "sg:address":"1644 McCulloch Blvd N",
    "sg:city":"Lake Havasu City",
    "sg:classifiers":[
        {
            "category":"Shopping",
            "subcategory":"Gifts & Souvenirs",
            "type":"Retail Goods"
        }
    ],
    "sg:phone":"+1 928 855 9184",
    "sg:postcode":"86403",
    "sg:province":"AZ",
    "sg:tags":[
        "shop"
    ],
    "wof:name":"Lake Havasu Gift Gallery",
    "wof:placetype":"venue"
},
  "geometry": {"coordinates":[-114.342081,34.475629],"type":"Point"}
}