{
  "type": "Feature",
  "properties": {
    "addr:full":"434 S Main St Camp Verde AZ 86322",
    "addr:housenumber":"434",
    "addr:postcode":"az 86322",
    "addr:street":"S Main St",
    "iso:country":"US",
    "sg:address":"434 S Main St",
    "sg:city":"Camp Verde",
    "sg:classifiers":[
        {
            "category":"Personal",
            "subcategory":"Beauty Salon",
            "type":"Services"
        }
    ],
    "sg:phone":"+1 928 567 6860",
    "sg:postcode":"86322",
    "sg:province":"AZ",
    "wof:name":"Old Town Hair Salon",
    "wof:placetype":"venue"
},
  "geometry": {"coordinates":[-111.85412599999999,34.563143],"type":"Point"}
}