{
  "type": "Feature",
  "properties": {
    "addr:full":"625 S 5th St Phoenix AZ 85004",
    "addr:housenumber":"625",
    "addr:postcode":"85004",
    "addr:street":"S 5Th St",
    "iso:country":"US",
    "sg:address":"625 S 5th St",
    "sg:city":"Phoenix",
    "sg:classifiers":[
        {
            "category":"Real Estate",
            "subcategory":"Real Estate Operator",
            "type":"Services"
        }
    ],
    "sg:phone":"+1 602 324 7743",
    "sg:postcode":"85004",
    "sg:province":"AZ",
    "sg:tags":[
        "property",
        "management",
        "commercial"
    ],
    "wof:name":"Stack Industrial LLC",
    "wof:placetype":"venue"
},
  "geometry": {"coordinates":[-112.067359,33.44123],"type":"Point"}
}