{
  "type": "Feature",
  "properties": {
    "iso:country":"US",
    "sg:address":"1672 Shamrock Rd",
    "sg:city":"Bullhead City",
    "sg:classifiers":[
        {
            "category":"Building & Trades",
            "subcategory":"Cleaning & Sanitation",
            "type":"Services"
        }
    ],
    "sg:phone":"+1 928 704 0186",
    "sg:postcode":"86442",
    "sg:province":"AZ",
    "sg:tags":[
        "property",
        "maintenance"
    ],
    "wof:name":"Show Shape",
    "wof:placetype":"venue"
},
  "geometry": {"coordinates":[-114.599476,35.110414],"type":"Point"}
}