{
  "type": "Feature",
  "properties": {
    "iso:country":"US",
    "sg:address":"809 E Carter Rd",
    "sg:city":"Phoenix",
    "sg:classifiers":[
        {
            "category":"Social Services",
            "subcategory":"Child Care",
            "type":"Services"
        }
    ],
    "sg:phone":"+1 602 268 3605",
    "sg:postcode":"85042",
    "sg:province":"AZ",
    "sg:tags":[
        "nursery",
        "day"
    ],
    "wof:name":"Josie's Tots & Nots",
    "wof:placetype":"venue"
},
  "geometry": {"coordinates":[-112.061783,33.382099],"type":"Point"}
}