{
  "type": "Feature",
  "properties": {
    "iso:country":"US",
    "sg:address":"812 N 3rd St",
    "sg:city":"Phoenix",
    "sg:classifiers":[
        {
            "category":"Real Estate",
            "subcategory":"Real Estate Operator",
            "type":"Services"
        }
    ],
    "sg:phone":"+1 602 716 5588",
    "sg:postcode":"85004",
    "sg:province":"AZ",
    "sg:tags":[
        "building",
        "nonresidential"
    ],
    "wof:name":"Callaway Properties LLC",
    "wof:placetype":"venue"
},
  "geometry": {"coordinates":[-112.070049,33.457509],"type":"Point"}
}