{
  "type": "Feature",
  "properties": {
    "iso:country":"US",
    "sg:address":"2127 E Catamaran Dr",
    "sg:city":"Gilbert",
    "sg:classifiers":[
        {
            "category":"Travel",
            "subcategory":"Travel Agent",
            "type":"Entertainment"
        }
    ],
    "sg:phone":"+1 480 807 1330",
    "sg:postcode":"85234",
    "sg:province":"AZ",
    "sg:tags":[
        "information",
        "tourist"
    ],
    "wof:name":"Bcs Hospitality Consultants",
    "wof:placetype":"venue"
},
  "geometry": {"coordinates":[-111.746009,33.376001],"type":"Point"}
}