{
  "type": "Feature",
  "properties": {
    "iso:country":"US",
    "sg:address":"5050 W McDowell Rd",
    "sg:city":"Phoenix",
    "sg:classifiers":[
        {
            "category":"Food & Beverages",
            "subcategory":"Groceries & Convenience Stores",
            "type":"Retail Goods"
        }
    ],
    "sg:phone":"+1 602 278 2296",
    "sg:postcode":"85035",
    "sg:province":"AZ",
    "sg:website":"www.7-eleven.com",
    "wof:name":"7-Eleven",
    "wof:placetype":"venue"
},
  "geometry": {"coordinates":[-112.168238,33.466044],"type":"Point"}
}