{
  "type": "Feature",
  "properties": {
    "addr:full":"8550 N Burke Dr Tucson AZ 85742",
    "addr:housenumber":"8550",
    "addr:postcode":"85742",
    "addr:street":"N Burke Dr",
    "iso:country":"US",
    "sg:address":"8550 N Burke Dr",
    "sg:city":"Tucson",
    "sg:classifiers":[
        {
            "category":"Building & Trades",
            "subcategory":"Electrical",
            "type":"Services"
        }
    ],
    "sg:phone":"+1 520 579 7299",
    "sg:postcode":"85742",
    "sg:province":"AZ",
    "sg:tags":[
        "electrical",
        "contractor"
    ],
    "wof:name":"Green & Lee Electric Inc",
    "wof:placetype":"venue"
},
  "geometry": {"coordinates":[-111.057345,32.362944],"type":"Point"}
}