{
  "type": "Feature",
  "properties": {
    "iso:country":"US",
    "sg:address":"3539 E Stanford Dr",
    "sg:city":"Paradise Valley",
    "sg:classifiers":[
        {
            "category":"Organizations",
            "subcategory":"Religious Organization",
            "type":"Services"
        }
    ],
    "sg:phone":"+1 602 955 7330",
    "sg:postcode":"85253",
    "sg:province":"AZ",
    "sg:tags":[
        "church"
    ],
    "sg:website":"www.gloriadeipv.org",
    "wof:name":"Gloria Dei Lutheran Church",
    "wof:placetype":"venue"
},
  "geometry": {"coordinates":[-112.00482,33.517196],"type":"Point"}
}