{
  "type": "Feature",
  "properties": {
    "iso:country":"US",
    "sg:address":"1375 N Hayden Rd",
    "sg:city":"Scottsdale",
    "sg:classifiers":[
        {
            "category":"Airline",
            "type":"Transportation"
        }
    ],
    "sg:phone":"+1 480 941 4601",
    "sg:postcode":"85257",
    "sg:province":"AZ",
    "sg:tags":[
        "courier",
        "air"
    ],
    "wof:name":"Fedex",
    "wof:placetype":"venue"
},
  "geometry": {"coordinates":[-111.90882499999999,33.463138],"type":"Point"}
}