{
  "type": "Feature",
  "properties": {
    "addr:full":"129 E Pso de Golf Green Valley AZ 85614",
    "addr:housenumber":"129",
    "addr:postcode":"85614",
    "addr:street":"E Pso De Golf",
    "iso:country":"US",
    "sg:address":"129 E Pso de Golf",
    "sg:city":"Green Valley",
    "sg:classifiers":[
        {
            "category":"Professional",
            "type":"Services"
        },
        {
            "category":"Home & Garden",
            "subcategory":"Home Furnishings",
            "type":"Retail Goods"
        }
    ],
    "sg:phone":"+1 520 399 0849",
    "sg:postcode":"85614",
    "sg:province":"AZ",
    "sg:tags":[
        "venetian",
        "blind"
    ],
    "wof:name":"Arizona Blind Company",
    "wof:placetype":"venue"
},
  "geometry": {"coordinates":[-110.985354,31.882916],"type":"Point"}
}