{
  "type": "Feature",
  "properties": {
    "iso:country":"US",
    "sg:address":"7760 S Priest Dr",
    "sg:city":"Tempe",
    "sg:classifiers":[
        {
            "category":"Shopping",
            "subcategory":"Bicycles & Sporting Goods",
            "type":"Retail Goods"
        }
    ],
    "sg:phone":"+1 480 496 8622",
    "sg:postcode":"85284",
    "sg:province":"AZ",
    "wof:name":"Sports Authority",
    "wof:placetype":"venue"
},
  "geometry": {"coordinates":[-111.96319200000001,33.34841],"type":"Point"}
}