{
  "type": "Feature",
  "properties": {
    "addr:full":"1976 W Thatcher Blvd Safford AZ 85546",
    "addr:housenumber":"1976",
    "addr:postcode":"85546",
    "addr:street":"W Thatcher Blvd",
    "iso:country":"US",
    "sg:address":"1976 W Thatcher Blvd",
    "sg:city":"Safford",
    "sg:classifiers":[
        {
            "category":"Education",
            "subcategory":"School",
            "type":"Public Place"
        }
    ],
    "sg:phone":"+1 928 348 8688",
    "sg:postcode":"85546",
    "sg:province":"AZ",
    "wof:name":"Gila Preparatory Academy",
    "wof:placetype":"venue"
},
  "geometry": {"coordinates":[-109.732697,32.836101],"type":"Point"}
}