{
  "type": "Feature",
  "properties": {
    "iso:country":"US",
    "sg:address":"9501 W Pima Rd",
    "sg:city":"Tolleson",
    "sg:classifiers":[
        {
            "category":"Government",
            "subcategory":"Office",
            "type":"Public Place"
        }
    ],
    "sg:phone":"+1 623 936 7141",
    "sg:postcode":"85353",
    "sg:province":"AZ",
    "wof:name":"Dead Animal Pickup",
    "wof:placetype":"venue"
},
  "geometry": {"coordinates":[-112.26587499999999,33.45753],"type":"Point"}
}