{
  "type": "Feature",
  "properties": {
    "iso:country":"US",
    "sg:address":"1355 N Beaver St Ste 190",
    "sg:city":"Flagstaff",
    "sg:classifiers":[
        {
            "category":"Health Services",
            "subcategory":"Doctor",
            "type":"Services"
        }
    ],
    "sg:phone":"+1 928 226 1454",
    "sg:postcode":"86001",
    "sg:province":"AZ",
    "sg:tags":[
        "medicine",
        "physician",
        "practice",
        "surgeons",
        "family"
    ],
    "wof:name":"Christine Ameduri Md",
    "wof:placetype":"venue"
},
  "geometry": {"coordinates":[-111.64466,35.210096],"type":"Point"}
}