{
  "type": "Feature",
  "properties": {
    "iso:country":"US",
    "sg:address":"4653 W Myrtle Ave",
    "sg:city":"Glendale",
    "sg:classifiers":[
        {
            "category":"Building & Trades",
            "subcategory":"Cleaning & Sanitation",
            "type":"Services"
        }
    ],
    "sg:phone":"+1 623 939 5759",
    "sg:postcode":"85301",
    "sg:province":"AZ",
    "sg:tags":[
        "for",
        "work",
        "general",
        "contractor",
        "remodeling",
        "janitorial"
    ],
    "wof:name":"Ayala Maintenance Inc",
    "wof:placetype":"venue"
},
  "geometry": {"coordinates":[-112.158123,33.542393],"type":"Point"}
}