{
  "type": "Feature",
  "properties": {
    "iso:country":"US",
    "sg:address":"9082 W Glendale Ave",
    "sg:city":"Glendale",
    "sg:classifiers":[
        {
            "category":"Banks & Credit Unions",
            "subcategory":"Bank",
            "type":"Services"
        }
    ],
    "sg:phone":"+1 623 772 7420",
    "sg:postcode":"85305",
    "sg:province":"AZ",
    "sg:website":"http://www.wellsfargo.com",
    "wof:name":"Wells Fargo Bank, National Association",
    "wof:placetype":"venue"
},
  "geometry": {"coordinates":[-112.254384,33.53764],"type":"Point"}
}