{
  "type": "Feature",
  "properties": {
    "addr:full":"7920 E Speedway Blvd Tucson AZ 85710",
    "addr:housenumber":"7920",
    "addr:postcode":"85710",
    "addr:street":"E Speedway Blvd",
    "iso:country":"US",
    "sg:address":"7920 E Speedway Blvd",
    "sg:city":"Tucson",
    "sg:phone":"+1 520 296 5171",
    "sg:postcode":"85710",
    "sg:province":"AZ",
    "sg:website":"http://www.arbys.com",
    "wof:name":"Arby's",
    "wof:placetype":"venue"
},
  "geometry": {"coordinates":[-110.823432,32.235481],"type":"Point"}
}