{
  "type": "Feature",
  "properties": {
    "iso:country":"US",
    "sg:address":"6725 W Peoria Ave",
    "sg:city":"Peoria",
    "sg:classifiers":[
        {
            "category":"Restaurant",
            "type":"Food & Drink"
        }
    ],
    "sg:phone":"+1 623 878 1846",
    "sg:postcode":"85345",
    "sg:province":"AZ",
    "sg:tags":[
        "eating"
    ],
    "wof:name":"China Place",
    "wof:placetype":"venue"
},
  "geometry": {"coordinates":[-112.206889,33.581561],"type":"Point"}
}