{
  "type": "Feature",
  "properties": {
    "iso:country":"US",
    "sg:address":"315 N 31st Ave",
    "sg:city":"Phoenix",
    "sg:classifiers":[
        {
            "category":"Banks & Credit Unions",
            "subcategory":"Bank",
            "type":"Services"
        }
    ],
    "sg:phone":"+1 602 233 2403",
    "sg:postcode":"85009",
    "sg:province":"AZ",
    "sg:tags":[
        "loan",
        "real estate"
    ],
    "wof:name":"Epic Lending Svc LLC",
    "wof:placetype":"venue"
},
  "geometry": {"coordinates":[-112.125943,33.451456],"type":"Point"}
}