{
  "type": "Feature",
  "properties": {
    "addr:full":"1171 W Target Range Rd Nogales AZ 85621",
    "addr:housenumber":"1171",
    "addr:postcode":"85621",
    "addr:street":"W Target Range Rd",
    "iso:country":"US",
    "sg:address":"1171 W Target Range Rd",
    "sg:city":"Nogales",
    "sg:classifiers":[
        {
            "category":"Health Services",
            "subcategory":"Nursing And Care Facility",
            "type":"Services"
        }
    ],
    "sg:phone":"+1 520 285 5930",
    "sg:postcode":"85621",
    "sg:province":"AZ",
    "sg:tags":[
        "hospice"
    ],
    "wof:name":"Carondelet Hospice",
    "wof:placetype":"venue"
},
  "geometry": {"coordinates":[-110.958123,31.341205],"type":"Point"}
}