{
  "type": "Feature",
  "properties": {
    "iso:country":"US",
    "sg:address":"8841 N 19th Ave",
    "sg:city":"Phoenix",
    "sg:classifiers":[
        {
            "category":"Personal",
            "subcategory":"Beauty Salon",
            "type":"Services"
        }
    ],
    "sg:phone":"+1 602 943 0720",
    "sg:postcode":"85021",
    "sg:province":"AZ",
    "wof:name":"Marys Beauty Salon",
    "wof:placetype":"venue"
},
  "geometry": {"coordinates":[-112.099544,33.567322],"type":"Point"}
}