{
  "type": "Feature",
  "properties": {
    "addr:full":"3970 W Ray Road Chandler AZ 85226",
    "addr:housenumber":"3970",
    "addr:postcode":"85226",
    "addr:street":"W Ray Road",
    "iso:country":"US",
    "sg:address":"3970 W Ray Road",
    "sg:city":"Chandler",
    "sg:classifiers":[
        {
            "category":"Banks & Credit Unions",
            "subcategory":"Bank",
            "type":"Services"
        }
    ],
    "sg:phone":"+1 480 963 2767",
    "sg:postcode":"85226",
    "sg:province":"AZ",
    "wof:name":"Chase",
    "wof:placetype":"venue"
},
  "geometry": {"coordinates":[-111.910246,33.320096],"type":"Point"}
}