{
  "type": "Feature",
  "properties": {
    "iso:country":"US",
    "sg:address":"1655 S Stapley Drive",
    "sg:city":"Mesa",
    "sg:classifiers":[
        {
            "category":"Shopping",
            "subcategory":"Computers & Home Electronics",
            "type":"Retail Goods"
        }
    ],
    "sg:phone":"+1 480 507 2880",
    "sg:postcode":"85204",
    "sg:province":"AZ",
    "sg:website":"www.ultimateelectronics.com",
    "wof:name":"Ultimate Electronics",
    "wof:placetype":"venue"
},
  "geometry": {"coordinates":[-111.80558,33.382671],"type":"Point"}
}