{
  "type": "Feature",
  "properties": {
    "addr:full":"3951 E Sequoia Trl Phoenix AZ 85044",
    "addr:housenumber":"3951",
    "addr:postcode":"85044",
    "addr:street":"E Sequoia Trl",
    "iso:country":"US",
    "sg:address":"3951 E Sequoia Trl",
    "sg:city":"Phoenix",
    "sg:classifiers":[
        {
            "category":"Arts & Performance",
            "subcategory":"Theater",
            "type":"Entertainment"
        }
    ],
    "sg:phone":"+1 480 966 9900",
    "sg:postcode":"85044",
    "sg:province":"AZ",
    "sg:tags":[
        "live",
        "music"
    ],
    "sg:website":"www.windycitydiscjockeys.com",
    "wof:name":"Disc Jockey-Windy City D J's",
    "wof:placetype":"venue"
},
  "geometry": {"coordinates":[-111.998722,33.334747],"type":"Point"}
}