{
  "type": "Feature",
  "properties": {
    "iso:country":"US",
    "sg:address":"3118 N 7th Ave",
    "sg:city":"Phoenix",
    "sg:classifiers":[
        {
            "category":"Social Services",
            "type":"Services"
        }
    ],
    "sg:phone":"+1 602 230 9946",
    "sg:postcode":"85013",
    "sg:province":"AZ",
    "sg:tags":[
        "care",
        "center",
        "day"
    ],
    "wof:name":"Central Adult Health Care",
    "wof:placetype":"venue"
},
  "geometry": {"coordinates":[-112.083128,33.481967],"type":"Point"}
}