{
  "type": "Feature",
  "properties": {
    "iso:country":"US",
    "sg:address":"16445 N 168th Ave",
    "sg:city":"Surprise",
    "sg:classifiers":[
        {
            "category":"Professional",
            "subcategory":"Engineering",
            "type":"Services"
        }
    ],
    "sg:phone":"+1 623 388 6294",
    "sg:postcode":"85388",
    "sg:province":"AZ",
    "sg:tags":[
        "refrigeration",
        "engineer"
    ],
    "wof:name":"J Rowen Refrigeration",
    "wof:placetype":"venue"
},
  "geometry": {"coordinates":[-112.419613,33.633849],"type":"Point"}
}