{
  "type": "Feature",
  "properties": {
    "addr:full":"9207 W Elkhorn Dr Sun City AZ 85351",
    "addr:housenumber":"9207",
    "addr:postcode":"85351",
    "addr:street":"W Elkhorn Dr",
    "iso:country":"US",
    "sg:address":"9207 W Elkhorn Dr",
    "sg:city":"Sun City",
    "sg:classifiers":[
        {
            "category":"Professional",
            "type":"Services"
        }
    ],
    "sg:phone":"+1 623 875 4464",
    "sg:postcode":"85351",
    "sg:province":"AZ",
    "sg:tags":[
        "establishment"
    ],
    "wof:name":"Addicott & Addicott",
    "wof:placetype":"venue"
},
  "geometry": {"coordinates":[-112.25947499999999,33.612113],"type":"Point"}
}