{
  "type": "Feature",
  "properties": {
    "iso:country":"US",
    "sg:address":"7 W Knox Rd",
    "sg:city":"Chandler",
    "sg:classifiers":[
        {
            "category":"Retail",
            "subcategory":"Veterinary Services",
            "type":"Services"
        }
    ],
    "sg:phone":"+1 480 963 2340",
    "sg:postcode":"85225",
    "sg:province":"AZ",
    "sg:tags":[
        "veterinarian"
    ],
    "wof:name":"Gardetto Mike L DVM",
    "wof:placetype":"venue"
},
  "geometry": {"coordinates":[-111.841752,33.327722],"type":"Point"}
}