{
  "type": "Feature",
  "properties": {
    "iso:country":"US",
    "sg:address":"1225 W Clarendon Ave",
    "sg:city":"Phoenix",
    "sg:classifiers":[
        {
            "category":"Education",
            "subcategory":"School",
            "type":"Public Place"
        }
    ],
    "sg:phone":"+1 602 707 2200",
    "sg:postcode":"85013",
    "sg:province":"AZ",
    "sg:website":"http://www.osbornnet.org",
    "wof:name":"Clarendon School",
    "wof:placetype":"venue"
},
  "geometry": {"coordinates":[-112.087593,33.491251],"type":"Point"}
}