{
  "type": "Feature",
  "properties": {
    "iso:country":"US",
    "sg:address":"1230 W 23rd St",
    "sg:city":"Tempe",
    "sg:classifiers":[
        {
            "category":"Wholesale",
            "subcategory":"Construction Materials",
            "type":"Manufacturing & Wholesale Goods"
        },
        {
            "category":"Home & Garden",
            "subcategory":"Building Materials",
            "type":"Retail Goods"
        }
    ],
    "sg:phone":"+1 480 317 9494",
    "sg:postcode":"85282",
    "sg:province":"AZ",
    "sg:tags":[
        "shower",
        "product",
        "door",
        "enclosure",
        "mfg"
    ],
    "wof:name":"Marin Shower and Mirror Co",
    "wof:placetype":"venue"
},
  "geometry": {"coordinates":[-111.958749,33.403794],"type":"Point"}
}