{
  "type": "Feature",
  "properties": {
    "iso:country":"US",
    "sg:address":"1556 E Fountain St",
    "sg:city":"Mesa",
    "sg:classifiers":[
        {
            "category":"Manufacturing",
            "subcategory":"Tools & Machinery",
            "type":"Manufacturing & Wholesale Goods"
        },
        {
            "category":"Manufacturing",
            "subcategory":"Motor Vehicles & Parts",
            "type":"Manufacturing & Wholesale Goods"
        }
    ],
    "sg:phone":"+1 480 321 6211",
    "sg:postcode":"85203",
    "sg:province":"AZ",
    "sg:tags":[
        "trailers-equipment",
        "trailers-automobile",
        "parts-wholesale",
        "utility-manufacturers",
        "manufacturer"
    ],
    "wof:name":"Zen Class",
    "wof:placetype":"venue"
},
  "geometry": {"coordinates":[-111.797825,33.435381],"type":"Point"}
}