{
  "type": "Feature",
  "properties": {
    "iso:country":"US",
    "sg:address":"3875 N 44th St",
    "sg:city":"Phoenix",
    "sg:classifiers":[
        {
            "category":"Manufacturing",
            "subcategory":"Building Materials",
            "type":"Manufacturing & Wholesale Goods"
        }
    ],
    "sg:phone":"+1 602 212 2442",
    "sg:postcode":"85018",
    "sg:province":"AZ",
    "sg:tags":[
        "mfg"
    ],
    "wof:name":"Young Woodworking",
    "wof:placetype":"venue"
},
  "geometry": {"coordinates":[-111.98683800000001,33.492334],"type":"Point"}
}