{
  "type": "Feature",
  "properties": {
    "iso:country":"US",
    "sg:address":"658 W Silver Creek Rd",
    "sg:city":"Gilbert",
    "sg:classifiers":[
        {
            "category":"Professional",
            "subcategory":"Engineering",
            "type":"Services"
        }
    ],
    "sg:phone":"+1 480 507 5038",
    "sg:postcode":"85233",
    "sg:province":"AZ",
    "sg:tags":[
        "engineer"
    ],
    "wof:name":"Tastefully Simple Consultant",
    "wof:placetype":"venue"
},
  "geometry": {"coordinates":[-111.803669,33.347223],"type":"Point"}
}