{
  "type": "Feature",
  "properties": {
    "iso:country":"US",
    "sg:address":"2645 E Osborn Rd",
    "sg:city":"Phoenix",
    "sg:classifiers":[
        {
            "category":"Education",
            "subcategory":"Special Training",
            "type":"Public Place"
        }
    ],
    "sg:phone":"+1 602 388 0532",
    "sg:postcode":"85016",
    "sg:province":"AZ",
    "sg:tags":[
        "educational"
    ],
    "wof:name":"Sonoran Science Academy-Phoenix Metro",
    "wof:placetype":"venue"
},
  "geometry": {"coordinates":[-112.024494,33.487657],"type":"Point"}
}