{
  "type": "Feature",
  "properties": {
    "iso:country":"US",
    "sg:address":"2202 W Beaubien Dr",
    "sg:city":"Phoenix",
    "sg:classifiers":[
        {
            "category":"Wholesale",
            "subcategory":"Jewelry",
            "type":"Manufacturing & Wholesale Goods"
        },
        {
            "category":"Shopping",
            "subcategory":"Crafts & Fabrics",
            "type":"Retail Goods"
        }
    ],
    "sg:phone":"+1 623 322 0186",
    "sg:postcode":"85027",
    "sg:province":"AZ",
    "sg:tags":[
        "bead",
        "beads-wholesale",
        "manufacturer"
    ],
    "wof:name":"Treasure Trove Beads And Tassels",
    "wof:placetype":"venue"
},
  "geometry": {"coordinates":[-112.105934,33.675751],"type":"Point"}
}