{
  "type": "Feature",
  "properties": {
    "iso:country":"US",
    "sg:address":"6248 E Speedway Blvd",
    "sg:city":"Tucson",
    "sg:classifiers":[
        {
            "category":"Shopping",
            "subcategory":"Computers & Home Electronics",
            "type":"Retail Goods"
        }
    ],
    "sg:phone":"+1 520 745 6440",
    "sg:postcode":"85712",
    "sg:province":"AZ",
    "wof:name":"Radio Shack",
    "wof:placetype":"venue"
},
  "geometry": {"coordinates":[-110.859008,32.235988],"type":"Point"}
}