{
  "type": "Feature",
  "properties": {
    "iso:country":"US",
    "sg:address":"3903 E Douglas Loop",
    "sg:city":"Gilbert",
    "sg:classifiers":[
        {
            "category":"Social Services",
            "subcategory":"Adult Care",
            "type":"Services"
        }
    ],
    "sg:phone":"+1 480 235 7145",
    "sg:postcode":"85234",
    "sg:province":"AZ",
    "sg:tags":[
        "foster"
    ],
    "wof:name":"Maria's Assisted Living Home",
    "wof:placetype":"venue"
},
  "geometry": {"coordinates":[-111.706197,33.365466],"type":"Point"}
}