{
  "type": "Feature",
  "properties": {
    "iso:country":"US",
    "sg:address":"1489 N Dysart Rd",
    "sg:city":"Avondale",
    "sg:classifiers":[
        {
            "category":"Home & Garden",
            "subcategory":"Building Materials",
            "type":"Retail Goods"
        }
    ],
    "sg:phone":"+1 623 925 2896",
    "sg:postcode":"85323",
    "sg:province":"AZ",
    "sg:tags":[
        "center"
    ],
    "sg:website":"www.homedepot.com",
    "wof:name":"Home Depot",
    "wof:placetype":"venue"
},
  "geometry": {"coordinates":[-112.341025,33.446123],"type":"Point"}
}