{
  "type": "Feature",
  "properties": {
    "addr:full":"1848 N 52nd St Phoenix AZ 85008",
    "addr:housenumber":"1848",
    "addr:postcode":"85008",
    "addr:street":"N 52Nd St",
    "iso:country":"US",
    "sg:address":"1848 N 52nd St",
    "sg:city":"Phoenix",
    "sg:classifiers":[
        {
            "category":"Social Services",
            "subcategory":"Child Care",
            "type":"Services"
        }
    ],
    "sg:phone":"+1 602 275 4440",
    "sg:postcode":"85008",
    "sg:province":"AZ",
    "wof:name":"Montessori Marina School",
    "wof:placetype":"venue"
},
  "geometry": {"coordinates":[-111.96981100000001,33.466187],"type":"Point"}
}