{
  "type": "Feature",
  "properties": {
    "addr:full":"819 W 32nd St Yuma AZ 85364",
    "addr:housenumber":"819",
    "addr:postcode":"85364",
    "addr:street":"W 32Nd St",
    "iso:country":"US",
    "sg:address":"819 W 32nd St",
    "sg:city":"Yuma",
    "sg:classifiers":[
        {
            "category":"Banks & Credit Unions",
            "subcategory":"Investment Brokerage",
            "type":"Services"
        },
        {
            "category":"Shopping",
            "subcategory":"Music",
            "type":"Retail Goods"
        },
        {
            "category":"Shopping",
            "subcategory":"Computers & Home Electronics",
            "type":"Retail Goods"
        },
        {
            "category":"Shopping",
            "subcategory":"Gifts & Souvenirs",
            "type":"Retail Goods"
        },
        {
            "category":"Utilities",
            "subcategory":"Mobile Phone",
            "type":"Services"
        },
        {
            "category":"Communications",
            "subcategory":"Film & Video Production",
            "type":"Services"
        },
        {
            "category":"Shopping",
            "subcategory":"Books",
            "type":"Retail Goods"
        },
        {
            "category":"Wholesale",
            "subcategory":"Books, Periodicals, & Newspapers",
            "type":"Manufacturing & Wholesale Goods"
        }
    ],
    "sg:phone":"+1 928 317 1466",
    "sg:postcode":"85364",
    "sg:province":"AZ",
    "sg:tags":[
        "shop",
        "educational",
        "dvd",
        "material",
        "sale",
        "hotspot",
        "dvds-rental",
        "record",
        "magazine",
        "tapes-wholesale",
        "tape",
        "cd's",
        "wi-fi",
        "store",
        "manufacturer"
    ],
    "sg:website":"http://store-locator.barnesandnoble.com/store/2756",
    "wof:name":"Barnes & Noble Booksellers",
    "wof:placetype":"venue"
},
  "geometry": {"coordinates":[-114.62914000000001,32.669381],"type":"Point"}
}