{
  "type": "Feature",
  "properties": {
    "addr:full":"29 E Kelly Ln Tempe AZ 85284",
    "addr:housenumber":"29",
    "addr:postcode":"85284",
    "addr:street":"E Kelly Ln",
    "iso:country":"US",
    "sg:address":"29 E Kelly Ln",
    "sg:city":"Tempe",
    "sg:classifiers":[
        {
            "category":"Real Estate",
            "subcategory":"Real Estate Agent",
            "type":"Services"
        }
    ],
    "sg:phone":"+1 480 893 7754",
    "sg:postcode":"85284",
    "sg:province":"AZ",
    "wof:name":"AM Home Appraisal",
    "wof:placetype":"venue"
},
  "geometry": {"coordinates":[-111.935992,33.32119],"type":"Point"}
}