{
  "type": "Feature",
  "properties": {
    "iso:country":"US",
    "sg:address":"8455 W Grand Ave",
    "sg:city":"Peoria",
    "sg:classifiers":[
        {
            "category":"Home & Garden",
            "subcategory":"Furniture",
            "type":"Retail Goods"
        }
    ],
    "sg:phone":"+1 623 979 3347",
    "sg:postcode":"85345",
    "sg:province":"AZ",
    "sg:tags":[
        "store"
    ],
    "wof:name":"Tricolor Furniture",
    "wof:placetype":"venue"
},
  "geometry": {"coordinates":[-112.240646,33.583885],"type":"Point"}
}