{
  "type": "Feature",
  "properties": {
    "iso:country":"US",
    "sg:address":"6030 S Kings Ranch Rd",
    "sg:city":"Apache Junction",
    "sg:classifiers":[
        {
            "category":"Restaurant",
            "type":"Food & Drink"
        }
    ],
    "sg:phone":"+1 480 983 3020",
    "sg:postcode":"85218",
    "sg:province":"AZ",
    "sg:tags":[
        "eating",
        "merchandise",
        "general"
    ],
    "wof:name":"Open Range Steak House",
    "wof:placetype":"venue"
},
  "geometry": {"coordinates":[-111.4419,33.36038],"type":"Point"}
}