{
  "type": "Feature",
  "properties": {
    "iso:country":"US",
    "sg:address":"4959 W Ray Rd",
    "sg:city":"Chandler",
    "sg:classifiers":[
        {
            "category":"Restaurant",
            "type":"Food & Drink"
        }
    ],
    "sg:phone":"+1 480 961 2913",
    "sg:postcode":"85226",
    "sg:province":"AZ",
    "wof:name":"Sandstone Cafe",
    "wof:placetype":"venue"
},
  "geometry": {"coordinates":[-111.927681,33.318372],"type":"Point"}
}