{
  "type": "Feature",
  "properties": {
    "iso:country":"US",
    "sg:address":"3001 E Park Ave",
    "sg:city":"Gilbert",
    "sg:classifiers":[
        {
            "category":"Professional",
            "type":"Services"
        }
    ],
    "sg:phone":"+1 480 558 3040",
    "sg:postcode":"85234",
    "sg:province":"AZ",
    "wof:name":"Stumbleherecom Inc",
    "wof:placetype":"venue"
},
  "geometry": {"coordinates":[-111.728072,33.353085],"type":"Point"}
}