{
  "type": "Feature",
  "properties": {
    "iso:country":"US",
    "sg:address":"66 Rainbow Dr",
    "sg:city":"Payson",
    "sg:classifiers":[
        {
            "category":"Personal",
            "type":"Services"
        }
    ],
    "sg:phone":"+1 928 468 9009",
    "sg:postcode":"85541",
    "sg:province":"AZ",
    "sg:tags":[
        "therapist",
        "massage"
    ],
    "wof:name":"Massage For A Reason",
    "wof:placetype":"venue"
},
  "geometry": {"coordinates":[-111.251777,34.249998],"type":"Point"}
}