{
  "type": "Feature",
  "properties": {
    "iso:country":"US",
    "sg:address":"10989 E Dynamite Boulevard",
    "sg:city":"Scottsdale",
    "sg:classifiers":[
        {
            "category":"Restaurant",
            "type":"Food & Drink"
        }
    ],
    "sg:phone":"+1 480 585 8499",
    "sg:postcode":"85262",
    "sg:province":"AZ",
    "sg:website":"paintedhorserestaurant.com",
    "wof:name":"Painted Horse Cafe",
    "wof:placetype":"venue"
},
  "geometry": {"coordinates":[-111.842828,33.742342],"type":"Point"}
}