{
  "type": "Feature",
  "properties": {
    "iso:country":"US",
    "sg:address":"8541 E Florentine Rd",
    "sg:city":"Prescott Valley",
    "sg:classifiers":[
        {
            "category":"Food & Beverages",
            "subcategory":"Groceries & Convenience Stores",
            "type":"Retail Goods"
        }
    ],
    "sg:phone":"+1 928 772 3350",
    "sg:postcode":"86314",
    "sg:province":"AZ",
    "wof:name":"Bargain Mart",
    "wof:placetype":"venue"
},
  "geometry": {"coordinates":[-112.315799,34.586944],"type":"Point"}
}