{
  "type": "Feature",
  "properties": {
    "addr:full":"1518 E Broadway Blvd Tucson AZ 85719",
    "addr:housenumber":"1518",
    "addr:postcode":"85719",
    "addr:street":"E Broadway Blvd",
    "iso:country":"US",
    "sg:address":"1518 E Broadway Blvd",
    "sg:city":"Tucson",
    "sg:classifiers":[
        {
            "category":"Shopping",
            "subcategory":"Catalog Store",
            "type":"Retail Goods"
        }
    ],
    "sg:phone":"+1 520 882 3853",
    "sg:postcode":"85719",
    "sg:province":"AZ",
    "sg:tags":[
        "recording",
        "mail",
        "order",
        "supply"
    ],
    "wof:name":"I C S",
    "wof:placetype":"venue"
},
  "geometry": {"coordinates":[-110.948286,32.221317],"type":"Point"}
}