{
  "type": "Feature",
  "properties": {
    "addr:full":"1315 E Gibson Ln Ste B1 Phoenix AZ 85034",
    "addr:housenumber":"1315",
    "addr:postcode":"85034",
    "addr:street":"E Gibson Ln Ste B1",
    "iso:country":"US",
    "sg:address":"1315 E Gibson Ln Ste B1",
    "sg:city":"Phoenix",
    "sg:classifiers":[
        {
            "category":"Manufacturing",
            "subcategory":"Chemicals & Compounds",
            "type":"Manufacturing & Wholesale Goods"
        }
    ],
    "sg:phone":"+1 602 712 9754",
    "sg:postcode":"85034",
    "sg:province":"AZ",
    "sg:tags":[
        "chemicals-wholesale",
        "manufacturer"
    ],
    "wof:name":"Arizona Packaging Inc",
    "wof:placetype":"venue"
},
  "geometry": {"coordinates":[-112.053563,33.42689],"type":"Point"}
}