{
  "type": "Feature",
  "properties": {
    "iso:country":"US",
    "sg:address":"144 Old Tucson Rd",
    "sg:city":"Nogales",
    "sg:classifiers":[
        {
            "category":"Food & Beverages",
            "subcategory":"Fruits & Vegetables",
            "type":"Retail Goods"
        }
    ],
    "sg:phone":"+1 520 761 3806",
    "sg:postcode":"85621",
    "sg:province":"AZ",
    "sg:tags":[
        "produce"
    ],
    "wof:name":"Stevco Inc",
    "wof:placetype":"venue"
},
  "geometry": {"coordinates":[-110.95368000000001,31.405845],"type":"Point"}
}