{
  "type": "Feature",
  "properties": {
    "addr:full":"1050 E Southern Ave Ste F7 Tempe AZ 85282",
    "addr:housenumber":"1050",
    "addr:postcode":"85282",
    "addr:street":"E Southern Ave Ste F7",
    "iso:country":"US",
    "sg:address":"1050 E Southern Ave Ste F7",
    "sg:city":"Tempe",
    "sg:classifiers":[
        {
            "category":"Wholesale",
            "subcategory":"Office Equipment",
            "type":"Manufacturing & Wholesale Goods"
        },
        {
            "category":"Professional",
            "subcategory":"Accounting & Tax Preparation",
            "type":"Services"
        }
    ],
    "sg:phone":"+1 480 966 6770",
    "sg:postcode":"85282",
    "sg:province":"AZ",
    "sg:tags":[
        "return",
        "preparation-business",
        "supply",
        "machine",
        "bookkeeping"
    ],
    "wof:name":"Lewis & Schiefer",
    "wof:placetype":"venue"
},
  "geometry": {"coordinates":[-111.923816,33.39296],"type":"Point"}
}