{
  "type": "Feature",
  "properties": {
    "addr:full":"6145 N 35th Ave Phoenix AZ 85017",
    "addr:housenumber":"6145",
    "addr:postcode":"85017",
    "addr:street":"N 35Th Ave",
    "iso:country":"US",
    "sg:address":"6145 N 35th Ave",
    "sg:city":"Phoenix",
    "sg:classifiers":[
        {
            "category":"Personal",
            "subcategory":"Beauty Salon",
            "type":"Services"
        }
    ],
    "sg:phone":"+1 602 973 8150",
    "sg:postcode":"85017",
    "sg:province":"AZ",
    "sg:tags":[
        "hair",
        "stylist"
    ],
    "sg:website":"http://www.smartstyle.com/",
    "wof:name":"Smartstyle Family Hair Salon",
    "wof:placetype":"venue"
},
  "geometry": {"coordinates":[-112.13427,33.526928],"type":"Point"}
}