{
  "type": "Feature",
  "properties": {
    "iso:country":"US",
    "sg:address":"10053 S Twin Oaks Rd",
    "sg:city":"Hereford",
    "sg:classifiers":[
        {
            "category":"Building & Trades",
            "subcategory":"Construction",
            "type":"Services"
        }
    ],
    "sg:phone":"+1 520 803 9764",
    "sg:postcode":"85615",
    "sg:province":"AZ",
    "sg:tags":[
        "contractor"
    ],
    "wof:name":"Toms Ceramic Tile",
    "wof:placetype":"venue"
},
  "geometry": {"coordinates":[-110.234543,31.385382],"type":"Point"}
}