{
  "type": "Feature",
  "properties": {
    "iso:country":"US",
    "sg:address":"1761 E McNair Dr",
    "sg:city":"Tempe",
    "sg:classifiers":[
        {
            "category":"Professional",
            "subcategory":"Lawyer & Legal Services",
            "type":"Services"
        }
    ],
    "sg:phone":"+1 480 413 1300",
    "sg:postcode":"85283",
    "sg:province":"AZ",
    "sg:tags":[
        "attorney"
    ],
    "wof:name":"Slade Lawson",
    "wof:placetype":"venue"
},
  "geometry": {"coordinates":[-111.9123,33.351321],"type":"Point"}
}