{
  "type": "Feature",
  "properties": {
    "iso:country":"US",
    "sg:address":"1022 S Euclid Ave",
    "sg:city":"Tucson",
    "sg:classifiers":[
        {
            "category":"Wholesale",
            "subcategory":"Construction Materials",
            "type":"Manufacturing & Wholesale Goods"
        }
    ],
    "sg:phone":"+1 520 696 0470",
    "sg:postcode":"85719",
    "sg:province":"AZ",
    "sg:tags":[
        "fence"
    ],
    "wof:name":"Quality Design Iron Work",
    "wof:placetype":"venue"
},
  "geometry": {"coordinates":[-110.959345,32.208435],"type":"Point"}
}