{
  "type": "Feature",
  "properties": {
    "addr:full":"60 Chavez Ranch Rd Sedona AZ 86336",
    "addr:housenumber":"60",
    "addr:postcode":"86336",
    "addr:street":"Chavez Ranch Rd",
    "iso:country":"US",
    "sg:address":"60 Chavez Ranch Rd",
    "sg:city":"Sedona",
    "sg:classifiers":[
        {
            "category":"Professional",
            "subcategory":"Computer Services",
            "type":"Services"
        }
    ],
    "sg:phone":"+1 928 282 6831",
    "sg:postcode":"86336",
    "sg:province":"AZ",
    "sg:tags":[
        "consultant",
        "designer",
        "datum",
        "system"
    ],
    "sg:website":"www.serendipsys.com",
    "wof:name":"Serendipity Systems",
    "wof:placetype":"venue"
},
  "geometry": {"coordinates":[-111.81283500000001,34.83314],"type":"Point"}
}