{
  "type": "Feature",
  "properties": {
    "iso:country":"US",
    "sg:address":"8001 N 19th Ave",
    "sg:city":"Phoenix",
    "sg:classifiers":[
        {
            "category":"Restaurant",
            "type":"Food & Drink"
        }
    ],
    "sg:menulink":"http://www.allmenus.com/az/phoenix/152536-boston-market/menu/",
    "sg:phone":"+1 602 944 7000",
    "sg:postcode":"85021",
    "sg:province":"AZ",
    "sg:tags":[
        "barbecue",
        "american",
        "soup"
    ],
    "wof:name":"Boston Market",
    "wof:placetype":"venue"
},
  "geometry": {"coordinates":[-112.099259,33.553477],"type":"Point"}
}