{
  "type": "Feature",
  "properties": {
    "iso:country":"US",
    "sg:address":"1881 N Mastick Way",
    "sg:city":"Nogales",
    "sg:classifiers":[
        {
            "category":"Real Estate",
            "subcategory":"Developer",
            "type":"Services"
        }
    ],
    "sg:phone":"+1 520 281 0944",
    "sg:postcode":"85621",
    "sg:province":"AZ",
    "wof:name":"Mastick Trust",
    "wof:placetype":"venue"
},
  "geometry": {"coordinates":[-110.93403000000001,31.366451],"type":"Point"}
}