{
  "type": "Feature",
  "properties": {
    "addr:full":"6812 W Taylor St Phoenix AZ 85043",
    "addr:housenumber":"6812",
    "addr:postcode":"85043",
    "addr:street":"W Taylor St",
    "iso:country":"US",
    "sg:address":"6812 W Taylor St",
    "sg:city":"Phoenix",
    "sg:classifiers":[
        {
            "category":"Professional",
            "type":"Services"
        }
    ],
    "sg:phone":"+1 623 936 5051",
    "sg:postcode":"85043",
    "sg:province":"AZ",
    "sg:tags":[
        "establishment"
    ],
    "wof:name":"Summer Wade Salsbury",
    "wof:placetype":"venue"
},
  "geometry": {"coordinates":[-112.206373,33.454266],"type":"Point"}
}