{
  "type": "Feature",
  "properties": {
    "addr:full":"3 S 2nd St Phoenix AZ 85004",
    "addr:housenumber":"3",
    "addr:postcode":"85004",
    "addr:street":"S 2Nd St",
    "iso:country":"US",
    "sg:address":"3 S 2nd St",
    "sg:city":"Phoenix",
    "sg:classifiers":[
        {
            "category":"Restaurant",
            "type":"Food & Drink"
        }
    ],
    "sg:phone":"+1 602 255 0810",
    "sg:postcode":"85004",
    "sg:province":"AZ",
    "wof:name":"China Inn",
    "wof:placetype":"venue"
},
  "geometry": {"coordinates":[-112.07118199999999,33.446824],"type":"Point"}
}