{
  "type": "Feature",
  "properties": {
    "iso:country":"US",
    "sg:address":"11462 E Rutledge Ave",
    "sg:city":"Mesa",
    "sg:classifiers":[
        {
            "category":"Professional",
            "type":"Services"
        }
    ],
    "sg:phone":"+1 480 495 1003",
    "sg:postcode":"85212",
    "sg:province":"AZ",
    "wof:name":"Cabinetmasters & More",
    "wof:placetype":"venue"
},
  "geometry": {"coordinates":[-111.585118,33.335998],"type":"Point"}
}