{
  "type": "Feature",
  "properties": {
    "addr:full":"3030 E Cactus Rd Phoenix AZ 85032",
    "addr:housenumber":"3030",
    "addr:postcode":"85032",
    "addr:street":"E Cactus Rd",
    "iso:country":"US",
    "sg:address":"3030 E Cactus Rd",
    "sg:city":"Phoenix",
    "sg:classifiers":[
        {
            "category":"Professional",
            "subcategory":"Accounting & Tax Preparation",
            "type":"Services"
        }
    ],
    "sg:phone":"+1 602 482 9101",
    "sg:postcode":"85032",
    "sg:province":"AZ",
    "sg:tags":[
        "accountant"
    ],
    "wof:name":"Alan Hoffmann CPA",
    "wof:placetype":"venue"
},
  "geometry": {"coordinates":[-112.016959,33.597021],"type":"Point"}
}