{
  "type": "Feature",
  "properties": {
    "addr:full":"13771 N Fountain Hills Blvd Fountain Hills AZ 85268",
    "addr:housenumber":"13771",
    "addr:postcode":"85268",
    "addr:street":"N Fountain Hills Blvd",
    "iso:country":"US",
    "sg:address":"13771 N Fountain Hills Blvd",
    "sg:city":"Fountain Hills",
    "sg:classifiers":[
        {
            "category":"Wholesale",
            "subcategory":"Furniture",
            "type":"Manufacturing & Wholesale Goods"
        }
    ],
    "sg:phone":"+1 480 836 8222",
    "sg:postcode":"85268",
    "sg:province":"AZ",
    "wof:name":"Baker Manufacturing Inc",
    "wof:placetype":"venue"
},
  "geometry": {"coordinates":[-111.72927900000001,33.61037],"type":"Point"}
}