{
  "type": "Feature",
  "properties": {
    "addr:full":"19888 N 73rd Ave Glendale AZ 85308",
    "addr:housenumber":"19888",
    "addr:postcode":"85308",
    "addr:street":"N 73Rd Ave",
    "iso:country":"US",
    "sg:address":"19888 N 73rd Ave",
    "sg:city":"Glendale",
    "sg:classifiers":[
        {
            "category":"Health Services",
            "subcategory":"Clinic",
            "type":"Services"
        },
        {
            "category":"Health Services",
            "subcategory":"Health Practitioner",
            "type":"Services"
        }
    ],
    "sg:phone":"+1 602 547 1961",
    "sg:postcode":"85308",
    "sg:province":"AZ",
    "sg:tags":[
        "therapist",
        "therapy",
        "physical"
    ],
    "wof:name":"Donahue Karen Pt",
    "wof:placetype":"venue"
},
  "geometry": {"coordinates":[-112.21472199999999,33.66367],"type":"Point"}
}