{
  "type": "Feature",
  "properties": {
    "iso:country":"US",
    "sg:address":"1701 Short St",
    "sg:city":"Kingman",
    "sg:classifiers":[
        {
            "category":"Manufacturing",
            "subcategory":"Food",
            "type":"Manufacturing & Wholesale Goods"
        },
        {
            "category":"Wholesale",
            "subcategory":"Beer",
            "type":"Manufacturing & Wholesale Goods"
        }
    ],
    "sg:phone":"+1 928 753 5537",
    "sg:postcode":"86401",
    "sg:province":"AZ",
    "sg:tags":[
        "mfg",
        "ale",
        "alcoholic",
        "beverage"
    ],
    "wof:name":"Nachard Beverage Co",
    "wof:placetype":"venue"
},
  "geometry": {"coordinates":[-114.023317,35.205729],"type":"Point"}
}