{
  "type": "Feature",
  "properties": {
    "iso:country":"US",
    "sg:address":"4144 E Thomas Rd",
    "sg:city":"Phoenix",
    "sg:classifiers":[
        {
            "category":"Retail",
            "subcategory":"Auto Repair",
            "type":"Services"
        }
    ],
    "sg:phone":"+1 602 903 6674",
    "sg:postcode":"85018",
    "sg:province":"AZ",
    "sg:tags":[
        "brake"
    ],
    "sg:website":"http://phoenixautorepair.iarbiz.com/rY94PybKZ04=",
    "wof:name":"Discount Brake Tune 'n Lube",
    "wof:placetype":"venue"
},
  "geometry": {"coordinates":[-111.992161,33.480408],"type":"Point"}
}