{
  "type": "Feature",
  "properties": {
    "addr:full":"1501 N Dysart Rd Avondale AZ 85323",
    "addr:housenumber":"1501",
    "addr:postcode":"85323",
    "addr:street":"N Dysart Rd",
    "iso:country":"US",
    "sg:address":"1501 N Dysart Rd",
    "sg:city":"Avondale",
    "sg:classifiers":[
        {
            "category":"Health Services",
            "subcategory":"Doctor",
            "type":"Services"
        }
    ],
    "sg:phone":"+1 602 344 6809",
    "sg:postcode":"85323",
    "sg:province":"AZ",
    "sg:tags":[
        "clinic"
    ],
    "wof:name":"Maricopa Integrated Health",
    "wof:placetype":"venue"
},
  "geometry": {"coordinates":[-112.341024,33.446102],"type":"Point"}
}