{
  "type": "Feature",
  "properties": {
    "iso:country":"US",
    "sg:address":"2960 S Alma School Road Suite 3",
    "sg:city":"Chandler",
    "sg:classifiers":[
        {
            "category":"Ice Cream",
            "type":"Food & Drink"
        }
    ],
    "sg:phone":"+1 480 786 8506",
    "sg:postcode":"85248",
    "sg:province":"AZ",
    "sg:tags":[
        "frozen",
        "yogurt"
    ],
    "sg:website":"www.coldstonecreamery.com",
    "wof:name":"Cold Stone Creamery",
    "wof:placetype":"venue"
},
  "geometry": {"coordinates":[-111.85871,33.262848],"type":"Point"}
}