{
  "type": "Feature",
  "properties": {
    "iso:country":"US",
    "sg:address":"1930 W Van Buren St",
    "sg:city":"Phoenix",
    "sg:classifiers":[
        {
            "category":"Banks & Credit Unions",
            "subcategory":"Financial Services",
            "type":"Services"
        }
    ],
    "sg:phone":"+1 602 258 9696",
    "sg:postcode":"85009",
    "sg:province":"AZ",
    "sg:tags":[
        "company",
        "holding"
    ],
    "wof:name":"Equitable Holdings",
    "wof:placetype":"venue"
},
  "geometry": {"coordinates":[-112.100123,33.451329],"type":"Point"}
}