{
  "type": "Feature",
  "properties": {
    "iso:country":"US",
    "sg:address":"301 S 4th St",
    "sg:city":"Kingman",
    "sg:classifiers":[
        {
            "category":"Freight",
            "type":"Transportation"
        }
    ],
    "sg:phone":"+1 928 753 2957",
    "sg:postcode":"86401",
    "sg:province":"AZ",
    "sg:tags":[
        "mobile",
        "home"
    ],
    "wof:name":"Old Trails Mobile Home Park",
    "wof:placetype":"venue"
},
  "geometry": {"coordinates":[-114.053265,35.186772],"type":"Point"}
}