{
  "type": "Feature",
  "properties": {
    "iso:country":"US",
    "sg:address":"1550 E Thunderbird Rd",
    "sg:city":"Phoenix",
    "sg:classifiers":[
        {
            "category":"Real Estate",
            "subcategory":"Real Estate Operator",
            "type":"Services"
        }
    ],
    "sg:phone":"+1 602 787 4700",
    "sg:postcode":"85022",
    "sg:province":"AZ",
    "sg:tags":[
        "apartment",
        "complex"
    ],
    "wof:name":"Mirador Apartments",
    "wof:placetype":"venue"
},
  "geometry": {"coordinates":[-112.04741,33.600314],"type":"Point"}
}