{
  "type": "Feature",
  "properties": {
    "addr:full":"1941 W Guadalupe Rd Mesa AZ 85202",
    "addr:housenumber":"1941",
    "addr:postcode":"85202",
    "addr:street":"W Guadalupe Rd",
    "iso:country":"US",
    "sg:address":"1941 W Guadalupe Rd",
    "sg:city":"Mesa",
    "sg:classifiers":[
        {
            "category":"Health Services",
            "subcategory":"Dentist",
            "type":"Services"
        }
    ],
    "sg:phone":"+1 480 967 9457",
    "sg:postcode":"85202",
    "sg:province":"AZ",
    "sg:tags":[
        "orthodontist"
    ],
    "wof:name":"Jones John D Orthodontist",
    "wof:placetype":"venue"
},
  "geometry": {"coordinates":[-111.875,33.364101],"type":"Point"}
}