{
  "type": "Feature",
  "properties": {
    "iso:country":"US",
    "sg:address":"2221 E Fry Blvd",
    "sg:city":"Sierra Vista",
    "sg:classifiers":[
        {
            "category":"Retail",
            "subcategory":"Laundry & Dry Cleaning",
            "type":"Services"
        }
    ],
    "sg:phone":"+1 520 458 7729",
    "sg:postcode":"85635",
    "sg:province":"AZ",
    "sg:tags":[
        "cleaners"
    ],
    "wof:name":"Bonanza Cleaners & Laundry",
    "wof:placetype":"venue"
},
  "geometry": {"coordinates":[-110.27555,31.55471],"type":"Point"}
}