{
  "type": "Feature",
  "properties": {
    "iso:country":"US",
    "sg:address":"11025 N Black Canyon Hwy",
    "sg:city":"Phoenix",
    "sg:classifiers":[
        {
            "category":"Restaurant",
            "type":"Food & Drink"
        }
    ],
    "sg:menulink":"http://www.allmenus.com/az/phoenix/75222-tgi-fridays/menu/",
    "sg:phone":"+1 602 861 1577",
    "sg:postcode":"85029",
    "sg:province":"AZ",
    "sg:tags":[
        "american"
    ],
    "wof:name":"T.G.I. Friday's",
    "wof:placetype":"venue"
},
  "geometry": {"coordinates":[-112.116336,33.586877],"type":"Point"}
}