{
  "type": "Feature",
  "properties": {
    "addr:full":"4322 E County 13th St Yuma AZ 85365",
    "addr:housenumber":"4322",
    "addr:postcode":"85365",
    "addr:street":"E County 13Th St",
    "iso:country":"US",
    "sg:address":"4322 E County 13th St",
    "sg:city":"Yuma",
    "sg:classifiers":[
        {
            "category":"Food & Beverages",
            "subcategory":"Candy",
            "type":"Retail Goods"
        }
    ],
    "sg:phone":"+1 928 726 6292",
    "sg:postcode":"85365",
    "sg:province":"AZ",
    "wof:name":"Peanut Patch Inc",
    "wof:placetype":"venue"
},
  "geometry": {"coordinates":[-114.558356,32.640803],"type":"Point"}
}