{
  "type": "Feature",
  "properties": {
    "iso:country":"US",
    "sg:address":"1566 Palace Way",
    "sg:city":"Lake Havasu City",
    "sg:classifiers":[
        {
            "category":"Shopping",
            "subcategory":"Clothing, Apparel, & Fashions",
            "type":"Retail Goods"
        }
    ],
    "sg:phone":"+1 928 855 2920",
    "sg:postcode":"86403",
    "sg:province":"AZ",
    "sg:tags":[
        "woman"
    ],
    "wof:name":"Isthmus",
    "wof:placetype":"venue"
},
  "geometry": {"coordinates":[-114.341523,34.467727],"type":"Point"}
}