{
  "type": "Feature",
  "properties": {
    "iso:country":"US",
    "sg:address":"2602 S 35th Ave",
    "sg:city":"Phoenix",
    "sg:classifiers":[
        {
            "category":"Manufacturing",
            "subcategory":"Buildings",
            "type":"Manufacturing & Wholesale Goods"
        }
    ],
    "sg:phone":"+1 602 484 0171",
    "sg:postcode":"85009",
    "sg:province":"AZ",
    "sg:tags":[
        "mobile",
        "home",
        "mfg"
    ],
    "wof:name":"Cavco Industries Inc",
    "wof:placetype":"venue"
},
  "geometry": {"coordinates":[-112.134613,33.425047],"type":"Point"}
}