{
  "type": "Feature",
  "properties": {
    "iso:country":"US",
    "sg:address":"4775 W Hidden Canyon Rd",
    "sg:city":"Chino Valley",
    "sg:classifiers":[
        {
            "category":"Real Estate",
            "subcategory":"Real Estate Agent",
            "type":"Services"
        }
    ],
    "sg:phone":"+1 928 636 9450",
    "sg:postcode":"86323",
    "sg:province":"AZ",
    "sg:website":"www.azcountryhome.com",
    "wof:name":"Countryside Properties",
    "wof:placetype":"venue"
},
  "geometry": {"coordinates":[-112.534504,34.790081],"type":"Point"}
}