{
  "type": "Feature",
  "properties": {
    "addr:full":"1222 E Missouri Ave Phoenix AZ 85014",
    "addr:housenumber":"1222",
    "addr:postcode":"85014",
    "addr:street":"E Missouri Ave",
    "iso:country":"US",
    "sg:address":"1222 E Missouri Ave",
    "sg:city":"Phoenix",
    "sg:classifiers":[
        {
            "category":"Banks & Credit Unions",
            "subcategory":"Bank",
            "type":"Services"
        }
    ],
    "sg:phone":"+1 602 266 3865",
    "sg:postcode":"85014",
    "sg:province":"AZ",
    "sg:tags":[
        "company",
        "mortgage"
    ],
    "wof:name":"Paragon Mortgage Corp",
    "wof:placetype":"venue"
},
  "geometry": {"coordinates":[-112.05459500000001,33.516558],"type":"Point"}
}