{
  "type": "Feature",
  "properties": {
    "iso:country":"US",
    "sg:address":"1620 US Hwy 89",
    "sg:city":"Chino Valley",
    "sg:classifiers":[
        {
            "category":"Wholesale",
            "subcategory":"Machinery & Supplies",
            "type":"Manufacturing & Wholesale Goods"
        }
    ],
    "sg:phone":"+1 928 636 0046",
    "sg:postcode":"86323",
    "sg:province":"AZ",
    "sg:tags":[
        "tank"
    ],
    "wof:name":"Loomis Tank Ctr",
    "wof:placetype":"venue"
},
  "geometry": {"coordinates":[-112.453259,34.768904],"type":"Point"}
}