{
  "type": "Feature",
  "properties": {
    "iso:country":"US",
    "sg:address":"3018 W Gran Paradiso Dr",
    "sg:city":"Phoenix",
    "sg:classifiers":[
        {
            "category":"Government",
            "subcategory":"Fire Station",
            "type":"Public Place"
        }
    ],
    "sg:phone":"+1 623 587 9349",
    "sg:postcode":"85086",
    "sg:province":"AZ",
    "sg:tags":[
        "protection",
        "engineer"
    ],
    "wof:name":"Pyro Tech Design",
    "wof:placetype":"venue"
},
  "geometry": {"coordinates":[-112.124654,33.804988],"type":"Point"}
}