{
  "type": "Feature",
  "properties": {
    "iso:country":"US",
    "sg:address":"1331 N Swan Rd",
    "sg:city":"Tucson",
    "sg:classifiers":[
        {
            "category":"Professional",
            "subcategory":"Lawyer & Legal Services",
            "type":"Services"
        }
    ],
    "sg:phone":"+1 520 319 0370",
    "sg:postcode":"85712",
    "sg:province":"AZ",
    "sg:tags":[
        "attorney"
    ],
    "wof:name":"Peter Beren",
    "wof:placetype":"venue"
},
  "geometry": {"coordinates":[-110.892684,32.238646],"type":"Point"}
}