{
  "type": "Feature",
  "properties": {
    "iso:country":"US",
    "sg:address":"1201 W Galveston St",
    "sg:city":"Chandler",
    "sg:classifiers":[
        {
            "category":"Social Services",
            "type":"Services"
        }
    ],
    "sg:phone":"+1 480 821 6895",
    "sg:postcode":"85224",
    "sg:province":"AZ",
    "wof:name":"Covenant Counseling Center",
    "wof:placetype":"venue"
},
  "geometry": {"coordinates":[-111.86341899999999,33.313301],"type":"Point"}
}