{
  "type": "Feature",
  "properties": {
    "iso:country":"US",
    "sg:address":"1721 E 7th Ave",
    "sg:city":"Mesa",
    "sg:classifiers":[
        {
            "category":"Building & Trades",
            "subcategory":"Plumbing",
            "type":"Services"
        }
    ],
    "sg:phone":"+1 480 964 1513",
    "sg:postcode":"85204",
    "sg:province":"AZ",
    "sg:tags":[
        "plumbing",
        "contractor"
    ],
    "wof:name":"Wakefield Plumbing",
    "wof:placetype":"venue"
},
  "geometry": {"coordinates":[-111.793317,33.402936],"type":"Point"}
}