{
  "type": "Feature",
  "properties": {
    "iso:country":"US",
    "sg:address":"4521 W Lord Redman Loop",
    "sg:city":"Tucson",
    "sg:classifiers":[
        {
            "category":"Retail",
            "subcategory":"Auto Repair",
            "type":"Services"
        }
    ],
    "sg:phone":"+1 520 572 2483",
    "sg:postcode":"85741",
    "sg:province":"AZ",
    "sg:tags":[
        "recreational",
        "vehicle"
    ],
    "wof:name":"Southwestern Rv Mobile Repair",
    "wof:placetype":"venue"
},
  "geometry": {"coordinates":[-111.0611,32.354593],"type":"Point"}
}