{
  "type": "Feature",
  "properties": {
    "addr:full":"3333 W Indian School Rd Phoenix AZ 85017",
    "addr:housenumber":"3333",
    "addr:postcode":"85017",
    "addr:street":"W Indian School Rd",
    "iso:country":"US",
    "sg:address":"3333 W Indian School Rd",
    "sg:city":"Phoenix",
    "sg:classifiers":[
        {
            "category":"Manufacturing",
            "subcategory":"Buildings",
            "type":"Manufacturing & Wholesale Goods"
        },
        {
            "category":"Home & Garden",
            "subcategory":"Building Materials",
            "type":"Retail Goods"
        }
    ],
    "sg:phone":"+1 602 248 0101",
    "sg:postcode":"85017",
    "sg:province":"AZ",
    "sg:tags":[
        "manufactured",
        "builder"
    ],
    "sg:website":"http://www.homesamericaphoenix.com",
    "wof:name":"A-1 Homes",
    "wof:placetype":"venue"
},
  "geometry": {"coordinates":[-112.131011,33.49492],"type":"Point"}
}