{
  "type": "Feature",
  "properties": {
    "iso:country":"US",
    "sg:address":"55 E Yvonne Ln",
    "sg:city":"Tempe",
    "sg:classifiers":[
        {
            "category":"Professional",
            "type":"Services"
        }
    ],
    "sg:phone":"+1 480 940 8819",
    "sg:postcode":"85284",
    "sg:province":"AZ",
    "wof:name":"AZ Green LLC",
    "wof:placetype":"venue"
},
  "geometry": {"coordinates":[-111.935451,33.321901],"type":"Point"}
}