{
  "type": "Feature",
  "properties": {
    "iso:country":"US",
    "sg:address":"5480 W Campbell Ave",
    "sg:city":"Phoenix",
    "sg:classifiers":[
        {
            "category":"Education",
            "subcategory":"School",
            "type":"Public Place"
        }
    ],
    "sg:phone":"+1 623 846 6482",
    "sg:postcode":"85031",
    "sg:province":"AZ",
    "wof:name":"Cartwright Center Head Start",
    "wof:placetype":"venue"
},
  "geometry": {"coordinates":[-112.175549,33.502251],"type":"Point"}
}