{
  "type": "Feature",
  "properties": {
    "iso:country":"US",
    "sg:address":"2049 Acoma Blvd W",
    "sg:city":"Lake Havasu City",
    "sg:classifiers":[
        {
            "category":"Building & Trades",
            "subcategory":"Electrical",
            "type":"Services"
        }
    ],
    "sg:phone":"+1 928 855 4539",
    "sg:postcode":"86403",
    "sg:province":"AZ",
    "sg:tags":[
        "electric",
        "contractor"
    ],
    "wof:name":"Blitz Electric",
    "wof:placetype":"venue"
},
  "geometry": {"coordinates":[-114.34109599999999,34.496236],"type":"Point"}
}