{
  "type": "Feature",
  "properties": {
    "addr:full":"201 E Broadway Blvd Tucson AZ 85701",
    "addr:housenumber":"201",
    "addr:postcode":"85701",
    "addr:street":"E Broadway Blvd",
    "iso:country":"US",
    "sg:address":"201 E Broadway Blvd",
    "sg:city":"Tucson",
    "sg:classifiers":[
        {
            "category":"Social Services",
            "type":"Services"
        }
    ],
    "sg:phone":"+1 520 622 3028",
    "sg:postcode":"85701",
    "sg:province":"AZ",
    "sg:tags":[
        "youth",
        "organization",
        "center"
    ],
    "wof:name":"Our Town Family Ctr",
    "wof:placetype":"venue"
},
  "geometry": {"coordinates":[-110.966256,32.22119],"type":"Point"}
}