{
  "type": "Feature",
  "properties": {
    "iso:country":"US",
    "sg:address":"5197 E Seminole Dr",
    "sg:city":"Flagstaff",
    "sg:classifiers":[
        {
            "category":"Freight",
            "type":"Transportation"
        }
    ],
    "sg:phone":"+1 928 714 9811",
    "sg:postcode":"86004",
    "sg:province":"AZ",
    "sg:tags":[
        "arrangement"
    ],
    "wof:name":"Heater Enterprises",
    "wof:placetype":"venue"
},
  "geometry": {"coordinates":[-111.586758,35.195282],"type":"Point"}
}