{
  "type": "Feature",
  "properties": {
    "iso:country":"US",
    "sg:address":"4890 Flightline Dr",
    "sg:city":"Kingman",
    "sg:classifiers":[
        {
            "category":"Professional",
            "subcategory":"Engineering",
            "type":"Services"
        },
        {
            "category":"Retail",
            "subcategory":"Repair Shop",
            "type":"Services"
        },
        {
            "category":"Building & Trades",
            "subcategory":"Construction",
            "type":"Services"
        }
    ],
    "sg:phone":"+1 928 757 2727",
    "sg:postcode":"86401",
    "sg:province":"AZ",
    "sg:tags":[
        "rebuilding",
        "industrial",
        "aircraft",
        "contractors-commercial",
        "maintenance",
        "painting"
    ],
    "wof:name":"Straube's Aircraft Services, Inc.",
    "wof:placetype":"venue"
},
  "geometry": {"coordinates":[-113.94949200000001,35.255837],"type":"Point"}
}