{
  "type": "Feature",
  "properties": {
    "addr:full":"2223 E Florence Blvd Casa Grande AZ 85222",
    "addr:housenumber":"2223",
    "addr:postcode":"85222",
    "addr:street":"E Florence Blvd",
    "iso:country":"US",
    "sg:address":"2223 E Florence Blvd",
    "sg:city":"Casa Grande",
    "sg:classifiers":[
        {
            "category":"Restaurant",
            "type":"Food & Drink"
        }
    ],
    "sg:menulink":"http://www.allmenus.com/az/casa-grande/165383-del-taco/menu/",
    "sg:phone":"+1 520 876 0837",
    "sg:postcode":"85222",
    "sg:province":"AZ",
    "sg:tags":[
        "american",
        "mexican",
        "tex-mex"
    ],
    "wof:name":"Del Taco",
    "wof:placetype":"venue"
},
  "geometry": {"coordinates":[-111.691558,32.879306],"type":"Point"}
}