{
  "type": "Feature",
  "properties": {
    "addr:full":"2526 W McDowell Rd Phoenix AZ 85009",
    "addr:housenumber":"2526",
    "addr:postcode":"85009",
    "addr:street":"W Mcdowell Rd",
    "iso:country":"US",
    "sg:address":"2526 W McDowell Rd",
    "sg:city":"Phoenix",
    "sg:classifiers":[
        {
            "category":"Autos & Motor Vehicles",
            "subcategory":"Auto Supplies",
            "type":"Retail Goods"
        }
    ],
    "sg:phone":"+1 602 233 0447",
    "sg:postcode":"85009",
    "sg:province":"AZ",
    "sg:tags":[
        "tire"
    ],
    "wof:name":"SMS Tire Shop",
    "wof:placetype":"venue"
},
  "geometry": {"coordinates":[-112.113184,33.465995],"type":"Point"}
}