{
  "type": "Feature",
  "properties": {
    "addr:full":"240 W Osborn Rd Ste 101 Phoenix AZ 85013",
    "addr:housenumber":"240",
    "addr:postcode":"85013",
    "addr:street":"W Osborn Rd Ste 101",
    "iso:country":"US",
    "sg:address":"240 W Osborn Rd Ste 101",
    "sg:city":"Phoenix",
    "sg:classifiers":[
        {
            "category":"Wholesale",
            "subcategory":"Medical Equipment & Supplies",
            "type":"Manufacturing & Wholesale Goods"
        }
    ],
    "sg:phone":"+1 602 279 0003",
    "sg:postcode":"85013",
    "sg:province":"AZ",
    "sg:tags":[
        "device",
        "assistive",
        "aid",
        "hearing"
    ],
    "sg:website":"http://www.abbotthearing.com",
    "wof:name":"Sonus-Usa, Inc.",
    "wof:placetype":"venue"
},
  "geometry": {"coordinates":[-112.07719400000001,33.487523],"type":"Point"}
}