{
  "type": "Feature",
  "properties": {
    "iso:country":"US",
    "sg:address":"2433 E Ocotillo Rd",
    "sg:city":"Queen Creek",
    "sg:classifiers":[
        {
            "category":"Professional",
            "type":"Services"
        }
    ],
    "sg:phone":"+1 480 458 5636",
    "sg:postcode":"85242",
    "sg:province":"AZ",
    "sg:tags":[
        "establishment"
    ],
    "wof:name":"Meadow Vista Homeowners Assc",
    "wof:placetype":"venue"
},
  "geometry": {"coordinates":[-111.539293,33.248987],"type":"Point"}
}