{
  "type": "Feature",
  "properties": {
    "addr:full":"17250 N 43rd Ave Ste 3 Glendale AZ 85308",
    "addr:housenumber":"17250",
    "addr:postcode":"85308",
    "addr:street":"N 43Rd Ave Ste 3",
    "iso:country":"US",
    "sg:address":"17250 N 43rd Ave Ste 3",
    "sg:city":"Glendale",
    "sg:classifiers":[
        {
            "category":"Health Services",
            "subcategory":"Dentist",
            "type":"Services"
        }
    ],
    "sg:phone":"+1 602 978 0901",
    "sg:postcode":"85308",
    "sg:province":"AZ",
    "wof:name":"John C Oatis DDS",
    "wof:placetype":"venue"
},
  "geometry": {"coordinates":[-112.151856,33.642415],"type":"Point"}
}