{
  "type": "Feature",
  "properties": {
    "iso:country":"US",
    "sg:address":"2575 E Camelback Rd",
    "sg:city":"Phoenix",
    "sg:classifiers":[
        {
            "category":"Restaurant",
            "type":"Food & Drink"
        }
    ],
    "sg:menulink":"http://www.allmenus.com/az/phoenix/101161-mccormick--schmicks/menu/",
    "sg:phone":"+1 602 468 1200",
    "sg:postcode":"85016",
    "sg:province":"AZ",
    "sg:tags":[
        "seafood",
        "american"
    ],
    "wof:name":"McCormick & Schmick's",
    "wof:placetype":"venue"
},
  "geometry": {"coordinates":[-112.02624400000001,33.50821],"type":"Point"}
}