{
  "type": "Feature",
  "properties": {
    "iso:country":"US",
    "sg:address":"9022 E Chino Dr",
    "sg:city":"Scottsdale",
    "sg:classifiers":[
        {
            "category":"Building & Trades",
            "subcategory":"Construction",
            "type":"Services"
        }
    ],
    "sg:phone":"+1 480 254 1050",
    "sg:postcode":"85255",
    "sg:province":"AZ",
    "sg:tags":[
        "altering",
        "remodeling",
        "contractor"
    ],
    "wof:name":"Ross Development And Remodeling",
    "wof:placetype":"venue"
},
  "geometry": {"coordinates":[-111.885811,33.66761],"type":"Point"}
}