{
  "type": "Feature",
  "properties": {
    "iso:country":"US",
    "sg:address":"1840 E Berridge Ln",
    "sg:city":"Phoenix",
    "sg:classifiers":[
        {
            "category":"Retail",
            "subcategory":"Auto Repair",
            "type":"Services"
        }
    ],
    "sg:phone":"+1 602 279 7847",
    "sg:postcode":"85016",
    "sg:province":"AZ",
    "sg:tags":[
        "truck"
    ],
    "wof:name":"Action Refrigeration",
    "wof:placetype":"venue"
},
  "geometry": {"coordinates":[-112.041873,33.525665],"type":"Point"}
}