{
  "type": "Feature",
  "properties": {
    "iso:country":"US",
    "sg:address":"2338 E Broadway Rd",
    "sg:city":"Tempe",
    "sg:classifiers":[
        {
            "category":"Retail",
            "subcategory":"Auto Repair",
            "type":"Services"
        }
    ],
    "sg:phone":"+1 480 966 7180",
    "sg:postcode":"85282",
    "sg:province":"AZ",
    "sg:tags":[
        "body",
        "automobile",
        "painting"
    ],
    "wof:name":"Harvil's Auto Body",
    "wof:placetype":"venue"
},
  "geometry": {"coordinates":[-111.888786,33.407595],"type":"Point"}
}