{
  "type": "Feature",
  "properties": {
    "addr:full":"37005 N 7th St Phoenix AZ 85086",
    "addr:housenumber":"37005",
    "addr:postcode":"85086",
    "addr:street":"N 7Th St",
    "iso:country":"US",
    "sg:address":"37005 N 7th St",
    "sg:city":"Phoenix",
    "sg:classifiers":[
        {
            "category":"Real Estate",
            "subcategory":"Developer",
            "type":"Services"
        }
    ],
    "sg:phone":"+1 480 473 4782",
    "sg:postcode":"85086",
    "sg:province":"AZ",
    "wof:name":"Excelsior Development",
    "wof:placetype":"venue"
},
  "geometry": {"coordinates":[-112.065386,33.824487],"type":"Point"}
}