{
  "type": "Feature",
  "properties": {
    "iso:country":"US",
    "sg:address":"3865 N Business Center Dr",
    "sg:city":"Tucson",
    "sg:classifiers":[
        {
            "category":"Manufacturing",
            "subcategory":"Printing",
            "type":"Manufacturing & Wholesale Goods"
        }
    ],
    "sg:phone":"+1 520 326 2886",
    "sg:postcode":"85705",
    "sg:province":"AZ",
    "sg:tags":[
        "publisher"
    ],
    "sg:website":"www.tucson.traderpub.com",
    "wof:name":"Auto Trader",
    "wof:placetype":"venue"
},
  "geometry": {"coordinates":[-111.015243,32.276522],"type":"Point"}
}