{
  "type": "Feature",
  "properties": {
    "addr:full":"24881 S Rittenhouse Rd Queen Creek AZ 85242",
    "addr:housenumber":"24881",
    "addr:postcode":"85242",
    "addr:street":"S Rittenhouse Rd",
    "iso:country":"US",
    "sg:address":"24881 S Rittenhouse Rd",
    "sg:city":"Queen Creek",
    "sg:classifiers":[
        {
            "category":"Manufacturing",
            "subcategory":"Chemicals & Compounds",
            "type":"Manufacturing & Wholesale Goods"
        }
    ],
    "sg:phone":"+1 480 987 9320",
    "sg:postcode":"85242",
    "sg:province":"AZ",
    "sg:tags":[
        "cleaning"
    ],
    "wof:name":"Industrial Blending & Pkg Co",
    "wof:placetype":"venue"
},
  "geometry": {"coordinates":[-111.589879,33.225351],"type":"Point"}
}