{
  "type": "Feature",
  "properties": {
    "addr:full":"3151 W Buckeye Rd Phoenix AZ 85009",
    "addr:housenumber":"3151",
    "addr:postcode":"85009",
    "addr:street":"W Buckeye Rd",
    "iso:country":"US",
    "sg:address":"3151 W Buckeye Rd",
    "sg:city":"Phoenix",
    "sg:classifiers":[
        {
            "category":"Wholesale",
            "subcategory":"Machinery & Supplies",
            "type":"Manufacturing & Wholesale Goods"
        }
    ],
    "sg:phone":"+1 602 484 0199",
    "sg:postcode":"85009",
    "sg:province":"AZ",
    "sg:tags":[
        "crane",
        "derrick"
    ],
    "wof:name":"Craneworks LLC",
    "wof:placetype":"venue"
},
  "geometry": {"coordinates":[-112.12696800000001,33.436839],"type":"Point"}
}