{
  "type": "Feature",
  "properties": {
    "iso:country":"US",
    "sg:address":"5653 Hwy 95",
    "sg:city":"Fort Mohave",
    "sg:classifiers":[
        {
            "category":"Home & Garden",
            "subcategory":"Home Furnishings",
            "type":"Retail Goods"
        }
    ],
    "sg:phone":"+1 928 768 1818",
    "sg:postcode":"86426",
    "sg:province":"AZ",
    "sg:tags":[
        "venetian",
        "blind",
        "window",
        "shades",
        "vertical"
    ],
    "wof:name":"Mohave Interiors",
    "wof:placetype":"venue"
},
  "geometry": {"coordinates":[-114.598124,34.992444],"type":"Point"}
}