{
  "type": "Feature",
  "properties": {
    "iso:country":"US",
    "sg:address":"1865 E Van Buren St",
    "sg:city":"Phoenix",
    "sg:classifiers":[
        {
            "category":"Travel",
            "subcategory":"Hotels & Motels",
            "type":"Entertainment"
        },
        {
            "category":"Travel",
            "subcategory":"Bed & Breakfast",
            "type":"Entertainment"
        }
    ],
    "sg:phone":"+1 602 254 4407",
    "sg:postcode":"85006",
    "sg:province":"AZ",
    "sg:tags":[
        "inn",
        "lodging"
    ],
    "wof:name":"Classic Inn",
    "wof:placetype":"venue"
},
  "geometry": {"coordinates":[-112.04195300000001,33.45142],"type":"Point"}
}