{
  "type": "Feature",
  "properties": {
    "iso:country":"US",
    "sg:address":"17007 E Colony Dr",
    "sg:city":"Fountain Hills",
    "sg:classifiers":[
        {
            "category":"Insurance",
            "subcategory":"Insurance Agent",
            "type":"Services"
        }
    ],
    "sg:phone":"+1 480 816 5665",
    "sg:postcode":"85268",
    "sg:province":"AZ",
    "wof:name":"Global Insurance Alliance",
    "wof:placetype":"venue"
},
  "geometry": {"coordinates":[-111.71474000000001,33.596789],"type":"Point"}
}