{
  "type": "Feature",
  "properties": {
    "iso:country":"US",
    "sg:address":"2942 N 24th St",
    "sg:city":"Phoenix",
    "sg:classifiers":[
        {
            "category":"Wholesale",
            "subcategory":"Apparel",
            "type":"Manufacturing & Wholesale Goods"
        }
    ],
    "sg:phone":"+1 520 979 3355",
    "sg:postcode":"85016",
    "sg:province":"AZ",
    "sg:tags":[
        "shoes-wholesale",
        "manufacturer"
    ],
    "wof:name":"The Pro Sports Network",
    "wof:placetype":"venue"
},
  "geometry": {"coordinates":[-112.03019,33.481089],"type":"Point"}
}