{
  "type": "Feature",
  "properties": {
    "addr:full":"6102 E Calle del Sud Scottsdale AZ 85251",
    "addr:housenumber":"6102",
    "addr:postcode":"85251",
    "addr:street":"Calle Del Sud",
    "iso:country":"US",
    "sg:address":"6102 E Calle del Sud",
    "sg:city":"Scottsdale",
    "sg:classifiers":[
        {
            "category":"Manufacturing",
            "subcategory":"Buildings",
            "type":"Manufacturing & Wholesale Goods"
        }
    ],
    "sg:phone":"+1 480 994 9447",
    "sg:postcode":"85251",
    "sg:province":"AZ",
    "sg:tags":[
        "prefabricated",
        "modular",
        "buildings-pre-cut"
    ],
    "wof:name":"R G Poriss Enterprises Inc",
    "wof:placetype":"venue"
},
  "geometry": {"coordinates":[-111.94980700000001,33.495689],"type":"Point"}
}