{
  "type": "Feature",
  "properties": {
    "addr:full":"18502 E Cloud Rd Queen Creek AZ 85242",
    "addr:housenumber":"18502",
    "addr:postcode":"85242",
    "addr:street":"E Cloud Rd",
    "iso:country":"US",
    "sg:address":"18502 E Cloud Rd",
    "sg:city":"Queen Creek",
    "sg:classifiers":[
        {
            "category":"Building & Trades",
            "subcategory":"Construction",
            "type":"Services"
        }
    ],
    "sg:phone":"+1 480 987 0601",
    "sg:postcode":"85242",
    "sg:province":"AZ",
    "sg:tags":[
        "house"
    ],
    "wof:name":"Rex Construction",
    "wof:placetype":"venue"
},
  "geometry": {"coordinates":[-111.67855400000001,33.227002],"type":"Point"}
}