{
  "type": "Feature",
  "properties": {
    "iso:country":"US",
    "sg:address":"12151 E State Rte 69",
    "sg:city":"Dewey",
    "sg:classifiers":[
        {
            "category":"Manufacturing",
            "subcategory":"Glass & Minerals",
            "type":"Manufacturing & Wholesale Goods"
        }
    ],
    "sg:phone":"+1 928 772 7300",
    "sg:postcode":"86327",
    "sg:province":"AZ",
    "sg:tags":[
        "nonmetallic",
        "mfg"
    ],
    "wof:name":"Century Corporation",
    "wof:placetype":"venue"
},
  "geometry": {"coordinates":[-112.253077,34.55357],"type":"Point"}
}