{
  "type": "Feature",
  "properties": {
    "addr:full":"816 S 19th Ave Phoenix AZ 85009",
    "addr:housenumber":"816",
    "addr:postcode":"85009",
    "addr:street":"S 19Th Ave",
    "iso:country":"US",
    "sg:address":"816 S 19th Ave",
    "sg:city":"Phoenix",
    "sg:classifiers":[
        {
            "category":"Shopping",
            "subcategory":"Gifts & Souvenirs",
            "type":"Retail Goods"
        }
    ],
    "sg:phone":"+1 602 499 4928",
    "sg:postcode":"85009",
    "sg:province":"AZ",
    "sg:tags":[
        "shop"
    ],
    "wof:name":"Robert's Tattoos",
    "wof:placetype":"venue"
},
  "geometry": {"coordinates":[-112.10002799999999,33.440112],"type":"Point"}
}