{
  "type": "Feature",
  "properties": {
    "iso:country":"US",
    "sg:address":"816 S 19th Ave",
    "sg:city":"Phoenix",
    "sg:classifiers":[
        {
            "category":"Shopping",
            "subcategory":"Gifts & Souvenirs",
            "type":"Retail Goods"
        }
    ],
    "sg:phone":"+1 602 499 4928",
    "sg:postcode":"85009",
    "sg:province":"AZ",
    "sg:tags":[
        "shop"
    ],
    "wof:name":"Robert's Tattoos",
    "wof:placetype":"venue"
},
  "geometry": {"coordinates":[-112.100028,33.440112],"type":"Point"}
}