{
  "type": "Feature",
  "properties": {
    "iso:country":"US",
    "sg:address":"3549 W Thomas Rd Ste 103",
    "sg:city":"Phoenix",
    "sg:classifiers":[
        {
            "category":"Health Services",
            "subcategory":"Chiropractor",
            "type":"Services"
        }
    ],
    "sg:phone":"+1 602 353 8888",
    "sg:postcode":"85019",
    "sg:province":"AZ",
    "sg:tags":[
        "chiropractic"
    ],
    "wof:name":"Got Chiropratic, Pc",
    "wof:placetype":"venue"
},
  "geometry": {"coordinates":[-112.135872,33.480461],"type":"Point"}
}