{
  "type": "Feature",
  "properties": {
    "addr:full":"1500 E Bethany Home Rd H Phoenix AZ 85014",
    "addr:housenumber":"1500",
    "addr:postcode":"85014",
    "addr:street":"E Bethany Home Rd H",
    "iso:country":"US",
    "sg:address":"1500 E Bethany Home Rd H",
    "sg:city":"Phoenix",
    "sg:classifiers":[
        {
            "category":"Professional",
            "subcategory":"Business Services",
            "type":"Services"
        }
    ],
    "sg:phone":"+1 602 788 1717",
    "sg:postcode":"85014",
    "sg:province":"AZ",
    "sg:tags":[
        "consultant",
        "coach"
    ],
    "sg:website":"http://www.sandersandwade.com",
    "wof:name":"Sanders Wade Rodarte Consulting Inc.",
    "wof:placetype":"venue"
},
  "geometry": {"coordinates":[-112.049713,33.523739],"type":"Point"}
}