{
  "type": "Feature",
  "properties": {
    "addr:full":"875 W Pecos Rd Chandler AZ 85225",
    "addr:housenumber":"875",
    "addr:postcode":"85225",
    "addr:street":"W Pecos Rd",
    "iso:country":"US",
    "sg:address":"875 W Pecos Rd",
    "sg:city":"Chandler",
    "sg:classifiers":[
        {
            "category":"Professional",
            "subcategory":"Computer Services",
            "type":"Services"
        }
    ],
    "sg:phone":"+1 480 812 9332",
    "sg:postcode":"85225",
    "sg:province":"AZ",
    "sg:tags":[
        "consultant",
        "designer"
    ],
    "wof:name":"Shakti Solutions Inc",
    "wof:placetype":"venue"
},
  "geometry": {"coordinates":[-111.855154,33.291395],"type":"Point"}
}