{
  "type": "Feature",
  "properties": {
    "iso:country":"US",
    "sg:address":"2828 N Dobson Rd",
    "sg:city":"Chandler",
    "sg:classifiers":[
        {
            "category":"Education",
            "subcategory":"Special Training",
            "type":"Public Place"
        }
    ],
    "sg:phone":"+1 480 786 4850",
    "sg:postcode":"85224",
    "sg:province":"AZ",
    "sg:tags":[
        "educational"
    ],
    "wof:name":"Advanced Educational",
    "wof:placetype":"venue"
},
  "geometry": {"coordinates":[-111.876542,33.349184],"type":"Point"}
}