{
  "type": "Feature",
  "properties": {
    "addr:full":"3350 Ridge Dr Sierra Vista AZ 85650",
    "addr:housenumber":"3350",
    "addr:postcode":"85650",
    "addr:street":"Ridge Dr",
    "iso:country":"US",
    "sg:address":"3350 Ridge Dr",
    "sg:city":"Sierra Vista",
    "sg:classifiers":[
        {
            "category":"Manufacturing",
            "subcategory":"Soap",
            "type":"Manufacturing & Wholesale Goods"
        }
    ],
    "sg:phone":"+1 520 378 4708",
    "sg:postcode":"85650",
    "sg:province":"AZ",
    "sg:tags":[
        "detergent",
        "mfg"
    ],
    "wof:name":"Scents Si Bon Savon",
    "wof:placetype":"venue"
},
  "geometry": {"coordinates":[-110.262398,31.508116],"type":"Point"}
}