{
  "type": "Feature",
  "properties": {
    "iso:country":"US",
    "sg:address":"4802 E Berneil Dr",
    "sg:city":"Paradise Valley",
    "sg:classifiers":[
        {
            "category":"Professional",
            "subcategory":"Management & Consulting",
            "type":"Services"
        }
    ],
    "sg:phone":"+1 480 607 9021",
    "sg:postcode":"85253",
    "sg:province":"AZ",
    "sg:tags":[
        "fuel"
    ],
    "wof:name":"Millennium Asset Management",
    "wof:placetype":"venue"
},
  "geometry": {"coordinates":[-111.976348,33.571989],"type":"Point"}
}