{
  "type": "Feature",
  "properties": {
    "iso:country":"US",
    "sg:address":"4050 W Ray Rd",
    "sg:city":"Chandler",
    "sg:classifiers":[
        {
            "category":"Personal",
            "subcategory":"Beauty Salon",
            "type":"Services"
        }
    ],
    "sg:phone":"+1 480 831 7072",
    "sg:postcode":"85226",
    "sg:province":"AZ",
    "wof:name":"Supercuts",
    "wof:placetype":"venue"
},
  "geometry": {"coordinates":[-111.914462,33.320106],"type":"Point"}
}