{
  "type": "Feature",
  "properties": {
    "addr:full":"2025 W Ruthrauff Rd Tucson AZ 85705",
    "addr:housenumber":"2025",
    "addr:postcode":"85705",
    "addr:street":"W Ruthrauff Rd",
    "iso:country":"US",
    "sg:address":"2025 W Ruthrauff Rd",
    "sg:city":"Tucson",
    "sg:classifiers":[
        {
            "category":"Wholesale",
            "subcategory":"Electrical",
            "type":"Manufacturing & Wholesale Goods"
        }
    ],
    "sg:phone":"+1 520 887 2263",
    "sg:postcode":"85705",
    "sg:province":"AZ",
    "sg:tags":[
        "control",
        "security",
        "system"
    ],
    "wof:name":"Alarm Guys",
    "wof:placetype":"venue"
},
  "geometry": {"coordinates":[-111.01158100000001,32.294267],"type":"Point"}
}