{
  "type": "Feature",
  "properties": {
    "iso:country":"US",
    "sg:address":"1743 E Camelback Rd",
    "sg:city":"Phoenix",
    "sg:classifiers":[
        {
            "category":"Home & Garden",
            "subcategory":"Carpets & Floor Coverings",
            "type":"Retail Goods"
        }
    ],
    "sg:phone":"+1 602 263 7521",
    "sg:postcode":"85016",
    "sg:province":"AZ",
    "wof:name":"World of Rugs Inc",
    "wof:placetype":"venue"
},
  "geometry": {"coordinates":[-112.044713,33.509274],"type":"Point"}
}