{
  "type": "Feature",
  "properties": {
    "iso:country":"US",
    "sg:address":"5676 W Evergreen Rd",
    "sg:city":"Glendale",
    "sg:classifiers":[
        {
            "category":"Retail",
            "subcategory":"Repair Shop",
            "type":"Services"
        }
    ],
    "sg:phone":"+1 623 594 6570",
    "sg:postcode":"85302",
    "sg:province":"AZ",
    "sg:tags":[
        "equipment",
        "printing"
    ],
    "wof:name":"Plotter Doctor's",
    "wof:placetype":"venue"
},
  "geometry": {"coordinates":[-112.182124,33.560008],"type":"Point"}
}