{
  "type": "Feature",
  "properties": {
    "addr:full":"1522 E Southern Ave Ste 1 Phoenix AZ 85040",
    "addr:housenumber":"1522",
    "addr:postcode":"85040",
    "addr:street":"E Southern Ave Ste 1",
    "iso:country":"US",
    "sg:address":"1522 E Southern Ave Ste 1",
    "sg:city":"Phoenix",
    "sg:classifiers":[
        {
            "category":"Social Services",
            "type":"Services"
        }
    ],
    "sg:phone":"+1 602 243 1773",
    "sg:postcode":"85040",
    "sg:province":"AZ",
    "sg:website":"http://www.bfcsfamily.org",
    "wof:name":"Black Family And Child Services Inc",
    "wof:placetype":"venue"
},
  "geometry": {"coordinates":[-112.048777,33.392719],"type":"Point"}
}