{
  "type": "Feature",
  "properties": {
    "addr:full":"7018 E Golf Links Rd Tucson AZ 85730",
    "addr:housenumber":"7018",
    "addr:postcode":"85730",
    "addr:street":"E Golf Links Rd",
    "iso:country":"US",
    "sg:address":"7018 E Golf Links Rd",
    "sg:city":"Tucson",
    "sg:classifiers":[
        {
            "category":"Restaurant",
            "type":"Food & Drink"
        }
    ],
    "sg:phone":"+1 520 790 4988",
    "sg:postcode":"85730",
    "sg:province":"AZ",
    "sg:tags":[
        "eating"
    ],
    "wof:name":"Golden China Restaurant",
    "wof:placetype":"venue"
},
  "geometry": {"coordinates":[-110.84169900000001,32.191872],"type":"Point"}
}