{
  "type": "Feature",
  "properties": {
    "iso:country":"US",
    "sg:address":"393 W Warner Rd",
    "sg:city":"Chandler",
    "sg:classifiers":[
        {
            "category":"Restaurant",
            "type":"Food & Drink"
        }
    ],
    "sg:phone":"+1 480 963 7934",
    "sg:postcode":"85225",
    "sg:province":"AZ",
    "sg:tags":[
        "mediterranean"
    ],
    "wof:name":"Flaming Kabob 2",
    "wof:placetype":"venue"
},
  "geometry": {"coordinates":[-111.84710099999999,33.335121],"type":"Point"}
}