{
  "type": "Feature",
  "properties": {
    "iso:country":"US",
    "sg:address":"2916 N 35th Ave",
    "sg:city":"Phoenix",
    "sg:classifiers":[
        {
            "category":"Wholesale",
            "subcategory":"Machinery & Supplies",
            "type":"Manufacturing & Wholesale Goods"
        }
    ],
    "sg:phone":"+1 602 352 7575",
    "sg:postcode":"85017",
    "sg:province":"AZ",
    "sg:tags":[
        "equipment",
        "establishment"
    ],
    "wof:name":"Vending Connection",
    "wof:placetype":"venue"
},
  "geometry": {"coordinates":[-112.134426,33.482138],"type":"Point"}
}