{
  "type": "Feature",
  "properties": {
    "iso:country":"US",
    "sg:address":"30 E Terminal Produce Dr",
    "sg:city":"Nogales",
    "sg:classifiers":[
        {
            "category":"Real Estate",
            "subcategory":"Real Estate Operator",
            "type":"Services"
        }
    ],
    "sg:phone":"+1 520 281 1619",
    "sg:postcode":"85621",
    "sg:province":"AZ",
    "sg:tags":[
        "building",
        "nonresidential"
    ],
    "wof:name":"Border Terminal Inc",
    "wof:placetype":"venue"
},
  "geometry": {"coordinates":[-110.930141,31.370935],"type":"Point"}
}