{
  "type": "Feature",
  "properties": {
    "iso:country":"US",
    "sg:address":"800 E 22nd St",
    "sg:city":"Douglas",
    "sg:classifiers":[
        {
            "category":"Freight",
            "type":"Transportation"
        }
    ],
    "sg:phone":"+1 520 805 9255",
    "sg:postcode":"85607",
    "sg:province":"AZ",
    "sg:tags":[
        "general"
    ],
    "wof:name":"22nd Street Storage",
    "wof:placetype":"venue"
},
  "geometry": {"coordinates":[-109.54922999999999,31.356699],"type":"Point"}
}