{
  "type": "Feature",
  "properties": {
    "iso:country":"US",
    "sg:address":"6738 E Cave Creek Rd",
    "sg:city":"Cave Creek",
    "sg:classifiers":[
        {
            "category":"Restaurant",
            "type":"Food & Drink"
        }
    ],
    "sg:phone":"+1 480 488 9542",
    "sg:postcode":"85331",
    "sg:province":"AZ",
    "sg:tags":[
        "traditional",
        "american"
    ],
    "sg:website":"www.thehornytoad.com",
    "wof:name":"The Horny Toad",
    "wof:placetype":"venue"
},
  "geometry": {"coordinates":[-111.93,33.8293],"type":"Point"}
}