{
  "type": "Feature",
  "properties": {
    "iso:country":"US",
    "sg:address":"5807 W Myrtle Ave",
    "sg:city":"Glendale",
    "sg:classifiers":[
        {
            "category":"Organizations",
            "subcategory":"Religious Organization",
            "type":"Services"
        }
    ],
    "sg:phone":"+1 623 934 1324",
    "sg:postcode":"85301",
    "sg:province":"AZ",
    "sg:tags":[
        "church"
    ],
    "wof:name":"Sanctuary Of Sacred Space",
    "wof:placetype":"venue"
},
  "geometry": {"coordinates":[-112.184547,33.542138],"type":"Point"}
}