{
  "type": "Feature",
  "properties": {
    "iso:country":"US",
    "sg:address":"13771 N Fountain Hills Blvd",
    "sg:city":"Fountain Hills",
    "sg:classifiers":[
        {
            "category":"Retail",
            "subcategory":"Laundry & Dry Cleaning",
            "type":"Services"
        }
    ],
    "sg:phone":"+1 602 246 4469",
    "sg:postcode":"85268",
    "sg:province":"AZ",
    "sg:tags":[
        "cleaners",
        "rug",
        "carpet"
    ],
    "wof:name":"CFS Installations",
    "wof:placetype":"venue"
},
  "geometry": {"coordinates":[-111.729279,33.61037],"type":"Point"}
}