{
  "type": "Feature",
  "properties": {
    "addr:full":"740 W 2nd Pl Mesa AZ 85201",
    "addr:housenumber":"740",
    "addr:postcode":"85201",
    "addr:street":"W 2Nd Pl",
    "iso:country":"US",
    "sg:address":"740 W 2nd Pl",
    "sg:city":"Mesa",
    "sg:classifiers":[
        {
            "category":"Farming",
            "subcategory":"Dairy Farm",
            "type":"Manufacturing & Wholesale Goods"
        },
        {
            "category":"Farming",
            "subcategory":"Farm",
            "type":"Manufacturing & Wholesale Goods"
        }
    ],
    "sg:phone":"+1 480 890 2249",
    "sg:postcode":"85201",
    "sg:province":"AZ",
    "wof:name":"Boyster Dairy",
    "wof:placetype":"venue"
},
  "geometry": {"coordinates":[-111.84640400000001,33.419992],"type":"Point"}
}