{
  "type": "Feature",
  "properties": {
    "addr:full":"6554 E Cll Cavalier Tucson AZ 85715",
    "addr:housenumber":"6554",
    "addr:postcode":"85715",
    "addr:street":"E Cll Cavalier",
    "iso:country":"US",
    "sg:address":"6554 E Cll Cavalier",
    "sg:city":"Tucson",
    "sg:classifiers":[
        {
            "category":"Recreation",
            "type":"Entertainment"
        }
    ],
    "sg:phone":"+1 520 795 9882",
    "sg:postcode":"85715",
    "sg:province":"AZ",
    "sg:tags":[
        "instruction",
        "swimming"
    ],
    "wof:name":"Elaine's Private Swim",
    "wof:placetype":"venue"
},
  "geometry": {"coordinates":[-110.850988,32.24074],"type":"Point"}
}