{
  "type": "Feature",
  "properties": {
    "iso:country":"US",
    "sg:address":"3702 E Orange Dr",
    "sg:city":"Phoenix",
    "sg:classifiers":[
        {
            "category":"Professional",
            "subcategory":"Accounting & Tax Preparation",
            "type":"Services"
        }
    ],
    "sg:phone":"+1 602 956 5070",
    "sg:postcode":"85018",
    "sg:province":"AZ",
    "sg:tags":[
        "accountant"
    ],
    "wof:name":"Robert Jones CPA",
    "wof:placetype":"venue"
},
  "geometry": {"coordinates":[-112.001115,33.513153],"type":"Point"}
}