{
  "type": "Feature",
  "properties": {
    "iso:country":"US",
    "sg:address":"15332 W Bell Rd",
    "sg:city":"Surprise",
    "sg:classifiers":[
        {
            "category":"Restaurant",
            "type":"Food & Drink"
        }
    ],
    "sg:menulink":"http://www.allmenus.com/az/wickenburg/69373-dominos-pizza/menu/",
    "sg:phone":"+1 623 546 4998",
    "sg:postcode":"85374",
    "sg:province":"AZ",
    "sg:tags":[
        "american",
        "wing",
        "pizza"
    ],
    "wof:name":"Domino's Pizza",
    "wof:placetype":"venue"
},
  "geometry": {"coordinates":[-112.39044,33.638778],"type":"Point"}
}