{
  "type": "Feature",
  "properties": {
    "iso:country":"US",
    "sg:address":"120 E 5th St",
    "sg:city":"Tempe",
    "sg:classifiers":[
        {
            "category":"Government",
            "subcategory":"Police Station",
            "type":"Public Place"
        }
    ],
    "sg:phone":"+1 480 350 8346",
    "sg:postcode":"85281",
    "sg:province":"AZ",
    "sg:tags":[
        "department"
    ],
    "wof:name":"Police Dept-Traffic Bureau",
    "wof:placetype":"venue"
},
  "geometry": {"coordinates":[-111.936912,33.4256],"type":"Point"}
}