{
  "type": "Feature",
  "properties": {
    "iso:country":"US",
    "sg:address":"708 S Coeur D Alene Ln A",
    "sg:city":"Payson",
    "sg:classifiers":[
        {
            "category":"Health Services",
            "subcategory":"Doctor",
            "type":"Services"
        },
        {
            "category":"Health Services",
            "subcategory":"Clinic",
            "type":"Services"
        }
    ],
    "sg:phone":"+1 928 472 7440",
    "sg:postcode":"85541",
    "sg:province":"AZ",
    "sg:tags":[
        "physician",
        "cardiology",
        "thoracic",
        "surgeons",
        "osteopathic",
        "surgery",
        "surgeon",
        "cardiovascular"
    ],
    "wof:name":"Biltmore Cardiology",
    "wof:placetype":"venue"
},
  "geometry": {"coordinates":[-111.321229,34.231907],"type":"Point"}
}