{
  "type": "Feature",
  "properties": {
    "iso:country":"US",
    "sg:address":"3440 N 16th St",
    "sg:city":"Phoenix",
    "sg:classifiers":[
        {
            "category":"Real Estate",
            "subcategory":"Real Estate Agent",
            "type":"Services"
        },
        {
            "category":"Real Estate",
            "subcategory":"Real Estate Operator",
            "type":"Services"
        }
    ],
    "sg:phone":"+1 602 264 5607",
    "sg:postcode":"85016",
    "sg:province":"AZ",
    "sg:tags":[
        "building",
        "investment",
        "nonresidential"
    ],
    "wof:name":"Capital Land & Investments Co",
    "wof:placetype":"venue"
},
  "geometry": {"coordinates":[-112.047731,33.487165],"type":"Point"}
}