{
  "type": "Feature",
  "properties": {
    "iso:country":"US",
    "sg:address":"7313 N del Norte Dr",
    "sg:city":"Scottsdale",
    "sg:classifiers":[
        {
            "category":"Insurance",
            "subcategory":"Insurance Agent",
            "type":"Services"
        }
    ],
    "sg:phone":"+1 480 951 3308",
    "sg:postcode":"85258",
    "sg:province":"AZ",
    "wof:name":"NASE",
    "wof:placetype":"venue"
},
  "geometry": {"coordinates":[-111.899702,33.543725],"type":"Point"}
}