{
  "type": "Feature",
  "properties": {
    "iso:country":"US",
    "sg:address":"602 Hall St",
    "sg:city":"Kingman",
    "sg:classifiers":[
        {
            "category":"Professional",
            "subcategory":"Employment Agencies",
            "type":"Services"
        }
    ],
    "sg:phone":"+1 928 753 4774",
    "sg:postcode":"86401",
    "sg:province":"AZ",
    "sg:tags":[
        "help",
        "contractor"
    ],
    "wof:name":"Labor Express",
    "wof:placetype":"venue"
},
  "geometry": {"coordinates":[-114.03354,35.195827],"type":"Point"}
}