{
  "type": "Feature",
  "properties": {
    "addr:full":"103 N Cortez St Prescott AZ 86301",
    "addr:housenumber":"103",
    "addr:postcode":"86301",
    "addr:street":"N Cortez St",
    "iso:country":"US",
    "sg:address":"103 N Cortez St",
    "sg:city":"Prescott",
    "sg:classifiers":[
        {
            "category":"Real Estate",
            "subcategory":"Real Estate Agent",
            "type":"Services"
        }
    ],
    "sg:phone":"+1 928 777 9500",
    "sg:postcode":"86301",
    "sg:province":"AZ",
    "wof:name":"American Ranch",
    "wof:placetype":"venue"
},
  "geometry": {"coordinates":[-112.468602,34.543774],"type":"Point"}
}