{
  "type": "Feature",
  "properties": {
    "addr:full":"3439 E Larkspur Dr Phoenix AZ 85032",
    "addr:housenumber":"3439",
    "addr:postcode":"85032",
    "addr:street":"E Larkspur Dr",
    "iso:country":"US",
    "sg:address":"3439 E Larkspur Dr",
    "sg:city":"Phoenix",
    "sg:classifiers":[
        {
            "category":"Retail",
            "subcategory":"Repair Shop",
            "type":"Services"
        },
        {
            "category":"Building & Trades",
            "subcategory":"Construction",
            "type":"Services"
        }
    ],
    "sg:phone":"+1 602 992 1583",
    "sg:postcode":"85032",
    "sg:province":"AZ",
    "sg:tags":[
        "system",
        "specialty",
        "heating",
        "air conditioning",
        "contractor",
        "freezers-repair",
        "refrigerator"
    ],
    "wof:name":"Arizona Temperature Control",
    "wof:placetype":"venue"
},
  "geometry": {"coordinates":[-112.007941,33.6017],"type":"Point"}
}