{
  "type": "Feature",
  "properties": {
    "iso:country":"US",
    "sg:address":"8330 W Seldon Ln",
    "sg:city":"Peoria",
    "sg:classifiers":[
        {
            "category":"Retail",
            "subcategory":"Car Wash",
            "type":"Services"
        }
    ],
    "sg:phone":"+1 623 776 2070",
    "sg:postcode":"85345",
    "sg:province":"AZ",
    "sg:tags":[
        "automobile",
        "detail",
        "clean"
    ],
    "wof:name":"Advanced Auto Detail",
    "wof:placetype":"venue"
},
  "geometry": {"coordinates":[-112.239412,33.560255],"type":"Point"}
}