{
  "type": "Feature",
  "properties": {
    "addr:full":"615 E University Dr Mesa AZ 85203",
    "addr:housenumber":"615",
    "addr:postcode":"85203",
    "addr:street":"E University Dr",
    "iso:country":"US",
    "sg:address":"615 E University Dr",
    "sg:city":"Mesa",
    "sg:classifiers":[
        {
            "category":"Communications",
            "subcategory":"Film & Video Production",
            "type":"Services"
        }
    ],
    "sg:phone":"+1 480 835 1557",
    "sg:postcode":"85203",
    "sg:province":"AZ",
    "sg:tags":[
        "picture",
        "services-commercial",
        "motion"
    ],
    "wof:name":"Urban Truth",
    "wof:placetype":"venue"
},
  "geometry": {"coordinates":[-111.817909,33.422379],"type":"Point"}
}