{
  "type": "Feature",
  "properties": {
    "iso:country":"US",
    "sg:address":"7133 N 51st Ave",
    "sg:city":"Glendale",
    "sg:classifiers":[
        {
            "category":"Shopping",
            "type":"Retail Goods"
        }
    ],
    "sg:phone":"+1 623 934 1998",
    "sg:postcode":"85301",
    "sg:province":"AZ",
    "sg:tags":[
        "trophy",
        "plaque",
        "bowling"
    ],
    "wof:name":"Coast To Coast Trophies",
    "wof:placetype":"venue"
},
  "geometry": {"coordinates":[-112.168533,33.541022],"type":"Point"}
}