{
  "type": "Feature",
  "properties": {
    "iso:country":"US",
    "sg:address":"16929 E Enterprise Dr",
    "sg:city":"Fountain Hills",
    "sg:classifiers":[
        {
            "category":"Wholesale",
            "subcategory":"Apparel",
            "type":"Manufacturing & Wholesale Goods"
        }
    ],
    "sg:phone":"+1 480 837 8373",
    "sg:postcode":"85268",
    "sg:province":"AZ",
    "wof:name":"K D Spring",
    "wof:placetype":"venue"
},
  "geometry": {"coordinates":[-111.712512,33.595466],"type":"Point"}
}