{
  "type": "Feature",
  "properties": {
    "iso:country":"US",
    "sg:address":"4806 S Lincoln Ridge Dr",
    "sg:city":"Tucson",
    "sg:classifiers":[
        {
            "category":"Personal",
            "type":"Services"
        }
    ],
    "sg:phone":"+1 520 275 3128",
    "sg:postcode":"85730",
    "sg:province":"AZ",
    "sg:tags":[
        "wedding",
        "chapel"
    ],
    "wof:name":"Your Wedding Your Way",
    "wof:placetype":"venue"
},
  "geometry": {"coordinates":[-110.806066,32.16474],"type":"Point"}
}