{
  "type": "Feature",
  "properties": {
    "iso:country":"US",
    "sg:address":"5816 N 16th St",
    "sg:city":"Phoenix",
    "sg:phone":"+1 602 266 3001",
    "sg:postcode":"85016",
    "sg:province":"AZ",
    "sg:website":"http://www.phoenixcitygrille.com",
    "wof:name":"Phoenix City Grille",
    "wof:placetype":"venue"
},
  "geometry": {"coordinates":[-112.047493,33.522652],"type":"Point"}
}