{
  "type": "Feature",
  "properties": {
    "addr:full":"303 W Esperanza Blvd Green Valley AZ 85614",
    "addr:housenumber":"303",
    "addr:postcode":"85614",
    "addr:street":"W Esperanza Blvd",
    "iso:country":"US",
    "sg:address":"303 W Esperanza Blvd",
    "sg:city":"Green Valley",
    "sg:classifiers":[
        {
            "category":"Banks & Credit Unions",
            "subcategory":"Bank",
            "type":"Services"
        }
    ],
    "sg:phone":"+1 520 648 0109",
    "sg:postcode":"85614",
    "sg:province":"AZ",
    "sg:tags":[
        "federal",
        "savings",
        "assoc",
        "loan"
    ],
    "sg:website":"www.washingtonfederal.com",
    "wof:name":"Washington Federal Savings",
    "wof:placetype":"venue"
},
  "geometry": {"coordinates":[-110.995542,31.870397],"type":"Point"}
}