{
  "type": "Feature",
  "properties": {
    "addr:full":"6921 W Paradise Dr Peoria AZ 85345",
    "addr:housenumber":"6921",
    "addr:postcode":"85345",
    "addr:street":"W Paradise Dr",
    "iso:country":"US",
    "sg:address":"6921 W Paradise Dr",
    "sg:city":"Peoria",
    "sg:classifiers":[
        {
            "category":"Health Services",
            "subcategory":"Doctor",
            "type":"Services"
        }
    ],
    "sg:phone":"+1 623 979 2454",
    "sg:postcode":"85345",
    "sg:province":"AZ",
    "sg:tags":[
        "physician",
        "surgeon"
    ],
    "wof:name":"Mashallah Moshrefzadeh",
    "wof:placetype":"venue"
},
  "geometry": {"coordinates":[-112.209474,33.594686],"type":"Point"}
}