{
  "type": "Feature",
  "properties": {
    "iso:country":"US",
    "sg:address":"6508 N 181st Ave",
    "sg:city":"Waddell",
    "sg:classifiers":[
        {
            "category":"Building & Trades",
            "subcategory":"Construction",
            "type":"Services"
        }
    ],
    "sg:phone":"+1 623 853 0177",
    "sg:postcode":"85355",
    "sg:province":"AZ",
    "sg:tags":[
        "house"
    ],
    "wof:name":"Horizon Homes & Construction",
    "wof:placetype":"venue"
},
  "geometry": {"coordinates":[-112.448571,33.530287],"type":"Point"}
}