{
  "type": "Feature",
  "properties": {
    "iso:country":"US",
    "sg:address":"400 N 30th St",
    "sg:city":"Phoenix",
    "sg:classifiers":[
        {
            "category":"Professional",
            "type":"Services"
        }
    ],
    "sg:phone":"+1 602 267 1531",
    "sg:postcode":"85008",
    "sg:province":"AZ",
    "sg:tags":[
        "establishment"
    ],
    "wof:name":"Diocesan Center Prison",
    "wof:placetype":"venue"
},
  "geometry": {"coordinates":[-112.017291,33.453111],"type":"Point"}
}