{
  "type": "Feature",
  "properties": {
    "iso:country":"US",
    "sg:address":"2828 Karen Ave",
    "sg:city":"Kingman",
    "sg:classifiers":[
        {
            "category":"Personal",
            "subcategory":"Beauty Salon",
            "type":"Services"
        }
    ],
    "sg:phone":"+1 928 718 2547",
    "sg:postcode":"86401",
    "sg:province":"AZ",
    "wof:name":"Shear Timing",
    "wof:placetype":"venue"
},
  "geometry": {"coordinates":[-114.012034,35.192109],"type":"Point"}
}