{
  "type": "Feature",
  "properties": {
    "iso:country":"US",
    "sg:address":"11795 E Old Spanish Trl",
    "sg:city":"Tucson",
    "sg:classifiers":[
        {
            "category":"Organizations",
            "subcategory":"Religious Organization",
            "type":"Services"
        }
    ],
    "sg:phone":"+1 520 546 1377",
    "sg:postcode":"85730",
    "sg:province":"AZ",
    "sg:tags":[
        "church"
    ],
    "wof:name":"Old Spanish Trail Church",
    "wof:placetype":"venue"
},
  "geometry": {"coordinates":[-110.740538,32.184435],"type":"Point"}
}