{
  "type": "Feature",
  "properties": {
    "addr:full":"2045 E Camelback Rd Phoenix AZ 85016",
    "addr:housenumber":"2045",
    "addr:postcode":"85016",
    "addr:street":"E Camelback Rd",
    "iso:country":"US",
    "sg:address":"2045 E Camelback Rd",
    "sg:city":"Phoenix",
    "sg:classifiers":[
        {
            "category":"Food & Beverages",
            "subcategory":"Dairy",
            "type":"Retail Goods"
        },
        {
            "category":"Restaurant",
            "type":"Food & Drink"
        }
    ],
    "sg:phone":"+1 602 957 8576",
    "sg:postcode":"85016",
    "sg:province":"AZ",
    "sg:tags":[
        "parlor",
        "ice",
        "cream"
    ],
    "wof:name":"J T Marble Slab Creamery",
    "wof:placetype":"venue"
},
  "geometry": {"coordinates":[-112.03753500000001,33.509192],"type":"Point"}
}