{
  "type": "Feature",
  "properties": {
    "iso:country":"US",
    "sg:address":"8834 N 2nd St",
    "sg:city":"Phoenix",
    "sg:classifiers":[
        {
            "category":"Professional",
            "type":"Services"
        }
    ],
    "sg:phone":"+1 602 395 5808",
    "sg:postcode":"85020",
    "sg:province":"AZ",
    "wof:name":"Nunez Alfredo Vasquez",
    "wof:placetype":"venue"
},
  "geometry": {"coordinates":[-112.071769,33.565291],"type":"Point"}
}