{
  "type": "Feature",
  "properties": {
    "iso:country":"US",
    "sg:address":"1239 W Guadalupe Rd",
    "sg:city":"Mesa",
    "sg:classifiers":[
        {
            "category":"Autos & Motor Vehicles",
            "subcategory":"Auto Supplies",
            "type":"Retail Goods"
        }
    ],
    "sg:phone":"+1 480 831 7857",
    "sg:postcode":"85202",
    "sg:province":"AZ",
    "sg:tags":[
        "tire"
    ],
    "wof:name":"Firestone Tire & Service Centers",
    "wof:placetype":"venue"
},
  "geometry": {"coordinates":[-111.860001,33.364101],"type":"Point"}
}