{
  "type": "Feature",
  "properties": {
    "addr:full":"6804 N 51st Ave Glendale AZ 85301",
    "addr:housenumber":"6804",
    "addr:postcode":"85301",
    "addr:street":"N 51St Ave",
    "iso:country":"US",
    "sg:address":"6804 N 51st Ave",
    "sg:city":"Glendale",
    "sg:classifiers":[
        {
            "category":"Professional",
            "subcategory":"Employment Agencies",
            "type":"Services"
        }
    ],
    "sg:phone":"+1 623 435 8665",
    "sg:postcode":"85301",
    "sg:province":"AZ",
    "sg:tags":[
        "opportunity"
    ],
    "wof:name":"Allied Forces",
    "wof:placetype":"venue"
},
  "geometry": {"coordinates":[-112.168701,33.535545],"type":"Point"}
}