{
  "type": "Feature",
  "properties": {
    "iso:country":"US",
    "sg:address":"2931 W Whitman Ct",
    "sg:city":"Phoenix",
    "sg:classifiers":[
        {
            "category":"Freight",
            "type":"Transportation"
        }
    ],
    "sg:phone":"+1 602 570 7421",
    "sg:postcode":"85086",
    "sg:province":"AZ",
    "sg:tags":[
        "local",
        "hauling"
    ],
    "wof:name":"United Haulers of High Point",
    "wof:placetype":"venue"
},
  "geometry": {"coordinates":[-112.123104,33.856786],"type":"Point"}
}