{
  "type": "Feature",
  "properties": {
    "iso:country":"US",
    "sg:address":"1102 E 22nd St",
    "sg:city":"Tucson",
    "sg:classifiers":[
        {
            "category":"Shopping",
            "subcategory":"Hobbies, Toys, & Games",
            "type":"Retail Goods"
        },
        {
            "category":"Shopping",
            "subcategory":"Jewelry",
            "type":"Retail Goods"
        },
        {
            "category":"Manufacturing",
            "subcategory":"Jewelry",
            "type":"Manufacturing & Wholesale Goods"
        },
        {
            "category":"Shopping",
            "subcategory":"Pawn Shop",
            "type":"Retail Goods"
        },
        {
            "category":"Recreation",
            "subcategory":"Gun Range",
            "type":"Entertainment"
        }
    ],
    "sg:phone":"+1 520 740 0406",
    "sg:postcode":"85713",
    "sg:province":"AZ",
    "sg:tags":[
        "designer",
        "instruction",
        "marksmanship",
        "jeweler",
        "pawnbroker",
        "safety",
        "hobby",
        "model",
        "gunsmith"
    ],
    "wof:name":"All-Stars Jewelry & Pawn",
    "wof:placetype":"venue"
},
  "geometry": {"coordinates":[-110.953048,32.20689],"type":"Point"}
}