{
  "type": "Feature",
  "properties": {
    "addr:full":"7904 E Chaparral Rd Scottsdale AZ 85250",
    "addr:housenumber":"7904",
    "addr:postcode":"85250",
    "addr:street":"E Chaparral Rd",
    "iso:country":"US",
    "sg:address":"7904 E Chaparral Rd",
    "sg:city":"Scottsdale",
    "sg:classifiers":[
        {
            "category":"Professional",
            "type":"Services"
        }
    ],
    "sg:phone":"+1 480 922 4529",
    "sg:postcode":"85250",
    "sg:province":"AZ",
    "sg:tags":[
        "establishment"
    ],
    "wof:name":"Foot Express",
    "wof:placetype":"venue"
},
  "geometry": {"coordinates":[-111.911198,33.509489],"type":"Point"}
}