{
  "type": "Feature",
  "properties": {
    "iso:country":"US",
    "sg:address":"2251 E Santa Rosa Dr",
    "sg:city":"Gilbert",
    "sg:classifiers":[
        {
            "category":"Building & Trades",
            "subcategory":"Plumbing",
            "type":"Services"
        }
    ],
    "sg:phone":"+1 480 892 7860",
    "sg:postcode":"85234",
    "sg:province":"AZ",
    "sg:tags":[
        "contractor"
    ],
    "wof:name":"Val Vista Air Conditioning Hea",
    "wof:placetype":"venue"
},
  "geometry": {"coordinates":[-111.741973,33.375777],"type":"Point"}
}