{
  "type": "Feature",
  "properties": {
    "addr:full":"7212 N 41st Ave Phoenix AZ 85051",
    "addr:housenumber":"7212",
    "addr:postcode":"85051",
    "addr:street":"N 41St Ave",
    "iso:country":"US",
    "sg:address":"7212 N 41st Ave",
    "sg:city":"Phoenix",
    "sg:classifiers":[
        {
            "category":"Shopping",
            "subcategory":"Used Merchandise",
            "type":"Retail Goods"
        }
    ],
    "sg:phone":"+1 602 740 7601",
    "sg:postcode":"85051",
    "sg:province":"AZ",
    "sg:tags":[
        "flea",
        "market"
    ],
    "wof:name":"Bays Liquidation",
    "wof:placetype":"venue"
},
  "geometry": {"coordinates":[-112.147155,33.543341],"type":"Point"}
}