{
  "type": "Feature",
  "properties": {
    "iso:country":"US",
    "sg:address":"15001 N Hayden Rd",
    "sg:city":"Scottsdale",
    "sg:classifiers":[
        {
            "category":"Shopping",
            "type":"Retail Goods"
        }
    ],
    "sg:phone":"+1 480 991 7446",
    "sg:postcode":"85260",
    "sg:province":"AZ",
    "sg:tags":[
        "banner"
    ],
    "sg:website":"www.airparksign.com",
    "wof:name":"AIRPARK Banner & Signs",
    "wof:placetype":"venue"
},
  "geometry": {"coordinates":[-111.905518,33.622261],"type":"Point"}
}