{
  "type": "Feature",
  "properties": {
    "addr:full":"123 N Centennial Way Ste 135 Mesa AZ 85201",
    "addr:housenumber":"123",
    "addr:postcode":"85201",
    "addr:street":"N Centennial Way Ste 135",
    "iso:country":"US",
    "sg:address":"123 N Centennial Way Ste 135",
    "sg:city":"Mesa",
    "sg:classifiers":[
        {
            "category":"Professional",
            "subcategory":"Lawyer & Legal Services",
            "type":"Services"
        }
    ],
    "sg:phone":"+1 866 770 2667",
    "sg:postcode":"85201",
    "sg:province":"AZ",
    "sg:tags":[
        "plan"
    ],
    "sg:website":"http://www.kathleenbergman4.com",
    "wof:name":"Kathleen M. Bergman P.C.",
    "wof:placetype":"venue"
},
  "geometry": {"coordinates":[-111.828699,33.418245],"type":"Point"}
}