{
  "type": "Feature",
  "properties": {
    "iso:country":"US",
    "sg:address":"9902 E Ramparts Pl",
    "sg:city":"Tucson",
    "sg:classifiers":[
        {
            "category":"Professional",
            "type":"Services"
        }
    ],
    "sg:phone":"+1 520 885 1426",
    "sg:postcode":"85748",
    "sg:province":"AZ",
    "sg:tags":[
        "establishment"
    ],
    "wof:name":"Veloweb",
    "wof:placetype":"venue"
},
  "geometry": {"coordinates":[-110.781096,32.22484],"type":"Point"}
}