{
  "type": "Feature",
  "properties": {
    "addr:full":"5415 E Ellis St Mesa AZ 85205",
    "addr:housenumber":"5415",
    "addr:postcode":"85205",
    "addr:street":"E Ellis St",
    "iso:country":"US",
    "sg:address":"5415 E Ellis St",
    "sg:city":"Mesa",
    "sg:classifiers":[
        {
            "category":"Local Transit",
            "type":"Transportation"
        }
    ],
    "sg:phone":"+1 480 529 6666",
    "sg:postcode":"85205",
    "sg:province":"AZ",
    "sg:tags":[
        "shuttle"
    ],
    "wof:name":"Silver Shadow Services",
    "wof:placetype":"venue"
},
  "geometry": {"coordinates":[-111.714428,33.430592],"type":"Point"}
}