{
  "type": "Feature",
  "properties": {
    "iso:country":"US",
    "sg:address":"4048 W Sweetwater Ave",
    "sg:city":"Phoenix",
    "sg:classifiers":[
        {
            "category":"Building & Trades",
            "subcategory":"Electrical",
            "type":"Services"
        }
    ],
    "sg:phone":"+1 602 938 8991",
    "sg:postcode":"85029",
    "sg:province":"AZ",
    "sg:tags":[
        "fire",
        "alarm",
        "burglar",
        "system",
        "contractor"
    ],
    "wof:name":"Big Frank Alarms",
    "wof:placetype":"venue"
},
  "geometry": {"coordinates":[-112.147322,33.603635],"type":"Point"}
}