{
  "type": "Feature",
  "properties": {
    "iso:country":"US",
    "sg:address":"6760 E Sandra Ter",
    "sg:city":"Scottsdale",
    "sg:classifiers":[
        {
            "category":"Professional",
            "subcategory":"Management & Consulting",
            "type":"Services"
        }
    ],
    "sg:phone":"+1 480 607 6916",
    "sg:postcode":"85254",
    "sg:province":"AZ",
    "sg:tags":[
        "consultant",
        "business"
    ],
    "wof:name":"E Two Consultants Inc",
    "wof:placetype":"venue"
},
  "geometry": {"coordinates":[-111.934539,33.634763],"type":"Point"}
}