{
  "type": "Feature",
  "properties": {
    "addr:full":"5329 E Yale St Phoenix AZ 85008",
    "addr:housenumber":"5329",
    "addr:postcode":"85008",
    "addr:street":"E Yale St",
    "iso:country":"US",
    "sg:address":"5329 E Yale St",
    "sg:city":"Phoenix",
    "sg:classifiers":[
        {
            "category":"Professional",
            "subcategory":"Advertising",
            "type":"Services"
        }
    ],
    "sg:phone":"+1 480 947 7856",
    "sg:postcode":"85008",
    "sg:province":"AZ",
    "sg:tags":[
        "guide"
    ],
    "wof:name":"Hotel Concierge Guest Info Svc",
    "wof:placetype":"venue"
},
  "geometry": {"coordinates":[-111.965813,33.475571],"type":"Point"}
}