{
  "type": "Feature",
  "properties": {
    "iso:country":"US",
    "sg:address":"1411 W Dolores Rd",
    "sg:city":"Phoenix",
    "sg:classifiers":[
        {
            "category":"Travel",
            "subcategory":"Hotels & Motels",
            "type":"Entertainment"
        },
        {
            "category":"Personal",
            "type":"Services"
        }
    ],
    "sg:phone":"+1 602 281 5109",
    "sg:postcode":"85086",
    "sg:province":"AZ",
    "sg:tags":[
        "concierge",
        "assistant"
    ],
    "wof:name":"Dvs Photo",
    "wof:placetype":"venue"
},
  "geometry": {"coordinates":[-112.09088300000001,33.818986],"type":"Point"}
}