{
  "type": "Feature",
  "properties": {
    "iso:country":"US",
    "sg:address":"2824 E Washington St",
    "sg:city":"Phoenix",
    "sg:classifiers":[
        {
            "category":"Autos & Motor Vehicles",
            "subcategory":"Auto Supplies",
            "type":"Retail Goods"
        }
    ],
    "sg:phone":"+1 602 267 1160",
    "sg:postcode":"85034",
    "sg:province":"AZ",
    "sg:tags":[
        "automobile",
        "part"
    ],
    "wof:name":"Pro Dyno High Performance",
    "wof:placetype":"venue"
},
  "geometry": {"coordinates":[-112.021036,33.44829],"type":"Point"}
}