{
  "type": "Feature",
  "properties": {
    "iso:country":"US",
    "sg:address":"4285 Tamara Ter",
    "sg:city":"Fort Mohave",
    "sg:classifiers":[
        {
            "category":"Building & Trades",
            "subcategory":"Landscaping Services",
            "type":"Services"
        }
    ],
    "sg:phone":"+1 928 201 6005",
    "sg:postcode":"86426",
    "sg:province":"AZ",
    "sg:tags":[
        "landscape"
    ],
    "wof:name":"Flores Landscaping",
    "wof:placetype":"venue"
},
  "geometry": {"coordinates":[-114.561333,35.032874],"type":"Point"}
}