{
  "type": "Feature",
  "properties": {
    "iso:country":"US",
    "sg:address":"1185 S Ave B",
    "sg:city":"Yuma",
    "sg:phone":"+1 928 782 4482",
    "sg:postcode":"85364",
    "sg:province":"AZ",
    "sg:tags":[
        "melon",
        "farm"
    ],
    "wof:name":"Colin Lee Mellon Farms",
    "wof:placetype":"venue"
},
  "geometry": {"coordinates":[-114.650379,32.706271],"type":"Point"}
}