{
  "type": "Feature",
  "properties": {
    "iso:country":"US",
    "sg:address":"113 Hanna St",
    "sg:city":"Fort Huachuca",
    "sg:classifiers":[
        {
            "category":"Communications",
            "subcategory":"Radio Station",
            "type":"Services"
        }
    ],
    "sg:phone":"+1 520 452 0021",
    "sg:postcode":"85613",
    "sg:province":"AZ",
    "sg:tags":[
        "education",
        "health"
    ],
    "wof:name":"Colin Mitsue",
    "wof:placetype":"venue"
},
  "geometry": {"coordinates":[-110.336279,31.557162],"type":"Point"}
}