{
  "type": "Feature",
  "properties": {
    "addr:full":"1199 S Gardner Dr Chandler AZ 85281",
    "addr:housenumber":"1199",
    "addr:postcode":"85281",
    "addr:street":"S Gardner Dr",
    "iso:country":"US",
    "sg:address":"1199 S Gardner Dr",
    "sg:city":"Chandler",
    "sg:classifiers":[
        {
            "category":"Building & Trades",
            "subcategory":"Locksmith",
            "type":"Services"
        }
    ],
    "sg:phone":"+1 480 459 4467",
    "sg:postcode":"85281",
    "sg:province":"AZ",
    "sg:tags":[
        "key"
    ],
    "wof:name":"24 Hr Emerg A Locksmith",
    "wof:placetype":"venue"
},
  "geometry": {"coordinates":[-111.865477,33.289097],"type":"Point"}
}