{
  "type": "Feature",
  "properties": {
    "addr:full":"455 N 3rd St Phoenix AZ 85004",
    "addr:housenumber":"455",
    "addr:postcode":"85004",
    "addr:street":"N 3Rd St",
    "iso:country":"US",
    "sg:address":"455 N 3rd St",
    "sg:city":"Phoenix",
    "sg:classifiers":[
        {
            "category":"Restaurant",
            "type":"Food & Drink"
        }
    ],
    "sg:phone":"+1 602 252 6222",
    "sg:postcode":"85004",
    "sg:province":"AZ",
    "wof:name":"Copper Square Bakery Bar & Grl",
    "wof:placetype":"venue"
},
  "geometry": {"coordinates":[-112.069895,33.452967],"type":"Point"}
}