{
  "type": "Feature",
  "properties": {
    "addr:full":"6512 W Van Buren St Phoenix AZ 85043",
    "addr:housenumber":"6512",
    "addr:postcode":"85043",
    "addr:street":"W Van Buren St",
    "iso:country":"US",
    "sg:address":"6512 W Van Buren St",
    "sg:city":"Phoenix",
    "sg:classifiers":[
        {
            "category":"Building & Trades",
            "subcategory":"Plumbing",
            "type":"Services"
        }
    ],
    "sg:phone":"+1 623 936 5381",
    "sg:postcode":"85043",
    "sg:province":"AZ",
    "sg:tags":[
        "contractor"
    ],
    "wof:name":"Bens Rooter Service",
    "wof:placetype":"venue"
},
  "geometry": {"coordinates":[-112.199539,33.451633],"type":"Point"}
}