{
  "type": "Feature",
  "properties": {
    "iso:country":"US",
    "sg:address":"1415 E Osborn Rd",
    "sg:city":"Phoenix",
    "sg:classifiers":[
        {
            "category":"Building & Trades",
            "subcategory":"Construction",
            "type":"Services"
        }
    ],
    "sg:phone":"+1 602 222 5475",
    "sg:postcode":"85014",
    "sg:province":"AZ",
    "sg:tags":[
        "residential"
    ],
    "wof:name":"Vickrey Construction",
    "wof:placetype":"venue"
},
  "geometry": {"coordinates":[-112.051291,33.487338],"type":"Point"}
}