{
  "type": "Feature",
  "properties": {
    "addr:full":"8738 E Bonnie Rose Ave Scottsdale AZ 85250",
    "addr:housenumber":"8738",
    "addr:postcode":"85250",
    "addr:street":"E Bonnie Rose Ave",
    "iso:country":"US",
    "sg:address":"8738 E Bonnie Rose Ave",
    "sg:city":"Scottsdale",
    "sg:classifiers":[
        {
            "category":"Shopping",
            "subcategory":"Hobbies, Toys, & Games",
            "type":"Retail Goods"
        }
    ],
    "sg:phone":"+1 480 368 5159",
    "sg:postcode":"85250",
    "sg:province":"AZ",
    "sg:tags":[
        "coin",
        "supply"
    ],
    "wof:name":"Occasional Coins",
    "wof:placetype":"venue"
},
  "geometry": {"coordinates":[-111.89358199999999,33.514978],"type":"Point"}
}