{
  "type": "Feature",
  "properties": {
    "addr:full":"1415 E Warner Road Gilbert AZ 85296",
    "addr:housenumber":"1415",
    "addr:postcode":"85296",
    "addr:street":"E Warner Road",
    "iso:country":"US",
    "sg:address":"1415 E Warner Road",
    "sg:city":"Gilbert",
    "sg:classifiers":[
        {
            "category":"Shopping",
            "subcategory":"Pets & Pet Supplies",
            "type":"Retail Goods"
        }
    ],
    "sg:phone":"+1 480 558 4588",
    "sg:postcode":"85296",
    "sg:province":"AZ",
    "sg:tags":[
        "store"
    ],
    "sg:website":"www.petco.com",
    "wof:name":"Petco",
    "wof:placetype":"venue"
},
  "geometry": {"coordinates":[-111.759182,33.335698],"type":"Point"}
}