{
  "type": "Feature",
  "properties": {
    "iso:country":"US",
    "sg:address":"660 Hwy 95",
    "sg:city":"Bullhead City",
    "sg:classifiers":[
        {
            "category":"Home & Garden",
            "subcategory":"Building Materials",
            "type":"Retail Goods"
        }
    ],
    "sg:phone":"+1 928 754 5600",
    "sg:postcode":"86429",
    "sg:province":"AZ",
    "wof:name":"Home Depot",
    "wof:placetype":"venue"
},
  "geometry": {"coordinates":[-114.566295,35.165711],"type":"Point"}
}