{
  "type": "Feature",
  "properties": {
    "addr:full":"3702 E Paradise Dr Phoenix AZ 85028",
    "addr:housenumber":"3702",
    "addr:postcode":"85028",
    "addr:street":"E Paradise Dr",
    "iso:country":"US",
    "sg:address":"3702 E Paradise Dr",
    "sg:city":"Phoenix",
    "sg:classifiers":[
        {
            "category":"Building & Trades",
            "subcategory":"Pest Control",
            "type":"Services"
        }
    ],
    "sg:phone":"+1 602 923 1457",
    "sg:postcode":"85028",
    "sg:province":"AZ",
    "sg:website":"www.arizonaorganic.com",
    "wof:name":"Arizona Organic Pest Control",
    "wof:placetype":"venue"
},
  "geometry": {"coordinates":[-112.000951,33.595975],"type":"Point"}
}