{
  "type": "Feature",
  "properties": {
    "iso:country":"US",
    "sg:address":"7150 E Camelback Rd",
    "sg:city":"Scottsdale",
    "sg:classifiers":[
        {
            "category":"Real Estate",
            "subcategory":"Real Estate Agent",
            "type":"Services"
        }
    ],
    "sg:phone":"+1 480 429 3844",
    "sg:postcode":"85251",
    "sg:province":"AZ",
    "sg:tags":[
        "home",
        "management",
        "rental",
        "sale",
        "vacation"
    ],
    "sg:website":"http://www.specialtylodging.com",
    "wof:name":"Specialty Lodging",
    "wof:placetype":"venue"
},
  "geometry": {"coordinates":[-111.92765799999999,33.50227],"type":"Point"}
}