{
  "type": "Feature",
  "properties": {
    "iso:country":"US",
    "sg:address":"19 E Main St",
    "sg:city":"Avondale",
    "sg:classifiers":[
        {
            "category":"Personal",
            "subcategory":"Barber",
            "type":"Services"
        }
    ],
    "sg:phone":"+1 623 925 9015",
    "sg:postcode":"85323",
    "sg:province":"AZ",
    "wof:name":"Main Street Barber & Salon",
    "wof:placetype":"venue"
},
  "geometry": {"coordinates":[-112.347863,33.429988],"type":"Point"}
}