{
  "type": "Feature",
  "properties": {
    "iso:country":"US",
    "sg:address":"2064 Hwy 95",
    "sg:city":"Bullhead City",
    "sg:classifiers":[
        {
            "category":"Wholesale",
            "subcategory":"Auto Parts",
            "type":"Manufacturing & Wholesale Goods"
        }
    ],
    "sg:phone":"+1 928 758 7278",
    "sg:postcode":"86442",
    "sg:province":"AZ",
    "sg:tags":[
        "automotive"
    ],
    "wof:name":"NAPA Auto Parts",
    "wof:placetype":"venue"
},
  "geometry": {"coordinates":[-114.59804699999999,35.112648],"type":"Point"}
}