{
  "type": "Feature",
  "properties": {
    "addr:full":"3035 N 2nd Ave Tucson AZ 85705",
    "addr:housenumber":"3035",
    "addr:postcode":"85705",
    "addr:street":"N 2Nd Ave",
    "iso:country":"US",
    "sg:address":"3035 N 2nd Ave",
    "sg:city":"Tucson",
    "sg:classifiers":[
        {
            "category":"Shopping",
            "subcategory":"Gifts & Souvenirs",
            "type":"Retail Goods"
        }
    ],
    "sg:phone":"+1 520 624 8577",
    "sg:postcode":"85705",
    "sg:province":"AZ",
    "wof:name":"Wood N Things",
    "wof:placetype":"venue"
},
  "geometry": {"coordinates":[-110.962611,32.262471],"type":"Point"}
}