{
  "type": "Feature",
  "properties": {
    "addr:full":"3517 E Indian School Rd Phoenix AZ 85018",
    "addr:housenumber":"3517",
    "addr:postcode":"85018",
    "addr:street":"E Indian School Rd",
    "iso:country":"US",
    "sg:address":"3517 E Indian School Rd",
    "sg:city":"Phoenix",
    "sg:classifiers":[
        {
            "category":"Wholesale",
            "subcategory":"Electrical",
            "type":"Manufacturing & Wholesale Goods"
        }
    ],
    "sg:phone":"+1 602 522 2010",
    "sg:postcode":"85018",
    "sg:province":"AZ",
    "sg:tags":[
        "equipment",
        "electric",
        "supply"
    ],
    "sg:website":"http://www.swabs-az.com",
    "wof:name":"Swabs-AZ",
    "wof:placetype":"venue"
},
  "geometry": {"coordinates":[-112.006479,33.495159],"type":"Point"}
}