{
  "type": "Feature",
  "properties": {
    "addr:full":"13837 W McDowell Road Goodyear AZ 85338",
    "addr:housenumber":"13837",
    "addr:postcode":"85338",
    "addr:street":"W Mcdowell Road",
    "iso:country":"US",
    "sg:address":"13837 W McDowell Road",
    "sg:city":"Goodyear",
    "sg:classifiers":[
        {
            "category":"Restaurant",
            "type":"Food & Drink"
        }
    ],
    "sg:phone":"+1 623 536 6397",
    "sg:postcode":"85338",
    "sg:province":"AZ",
    "sg:website":"www.carlsjr.com",
    "wof:name":"Carl's Jr",
    "wof:placetype":"venue"
},
  "geometry": {"coordinates":[-112.356343,33.464392],"type":"Point"}
}