{
  "type": "Feature",
  "properties": {
    "iso:country":"US",
    "sg:address":"432 N 44th St",
    "sg:city":"Phoenix",
    "sg:classifiers":[
        {
            "category":"Organizations",
            "subcategory":"Professional Association",
            "type":"Services"
        }
    ],
    "sg:phone":"+1 602 306 4100",
    "sg:postcode":"85008",
    "sg:province":"AZ",
    "wof:name":"Air Line Pilots ASSOC-Awa",
    "wof:placetype":"venue"
},
  "geometry": {"coordinates":[-111.98721999999999,33.454394],"type":"Point"}
}