{
  "type": "Feature",
  "properties": {
    "addr:full":"2450 S 4th Ave Ste 119 Yuma AZ 85364",
    "addr:housenumber":"2450",
    "addr:postcode":"85364",
    "addr:street":"S 4Th Ave Ste 119",
    "iso:country":"US",
    "sg:address":"2450 S 4th Ave Ste 119",
    "sg:city":"Yuma",
    "sg:classifiers":[
        {
            "category":"Real Estate",
            "subcategory":"Real Estate Services",
            "type":"Services"
        },
        {
            "category":"Real Estate",
            "subcategory":"Real Estate Agent",
            "type":"Services"
        }
    ],
    "sg:phone":"+1 928 314 3030",
    "sg:postcode":"85364",
    "sg:province":"AZ",
    "sg:tags":[
        "buyer",
        "broker"
    ],
    "wof:name":"Shrader Realty & Associates",
    "wof:placetype":"venue"
},
  "geometry": {"coordinates":[-114.624611,32.68303],"type":"Point"}
}