{
  "type": "Feature",
  "properties": {
    "addr:full":"530 S Montezuma St Prescott AZ 86303",
    "addr:housenumber":"530",
    "addr:postcode":"86303",
    "addr:street":"S Montezuma St",
    "iso:country":"US",
    "sg:address":"530 S Montezuma St",
    "sg:city":"Prescott",
    "sg:classifiers":[
        {
            "category":"Personal",
            "subcategory":"Barber",
            "type":"Services"
        }
    ],
    "sg:phone":"+1 928 541 1566",
    "sg:postcode":"86303",
    "sg:province":"AZ",
    "wof:name":"Heads Up Barber Styling",
    "wof:placetype":"venue"
},
  "geometry": {"coordinates":[-112.470381,34.53361],"type":"Point"}
}