{
  "type": "Feature",
  "properties": {
    "addr:full":"455 Moser Ave Bullhead City AZ 86429",
    "addr:housenumber":"455",
    "addr:postcode":"86429",
    "addr:street":"Moser Ave",
    "iso:country":"US",
    "sg:address":"455 Moser Ave",
    "sg:city":"Bullhead City",
    "sg:classifiers":[
        {
            "category":"Professional",
            "type":"Services"
        }
    ],
    "sg:phone":"+1 928 754 2250",
    "sg:postcode":"86429",
    "sg:province":"AZ",
    "wof:name":"Millenium 7 LLC",
    "wof:placetype":"venue"
},
  "geometry": {"coordinates":[-114.571139,35.14319],"type":"Point"}
}