{
  "type": "Feature",
  "properties": {
    "iso:country":"US",
    "sg:address":"2352 E Christy Dr",
    "sg:city":"Phoenix",
    "sg:classifiers":[
        {
            "category":"Recreation",
            "type":"Entertainment"
        }
    ],
    "sg:phone":"+1 602 262 6696",
    "sg:postcode":"85028",
    "sg:province":"AZ",
    "sg:tags":[
        "parks"
    ],
    "wof:name":"Christy Cove Park",
    "wof:placetype":"venue"
},
  "geometry": {"coordinates":[-112.03141100000001,33.584712],"type":"Point"}
}