{
  "type": "Feature",
  "properties": {
    "iso:country":"US",
    "sg:address":"3848 W Purdue Ave",
    "sg:city":"Phoenix",
    "sg:classifiers":[
        {
            "category":"Building & Trades",
            "subcategory":"Construction",
            "type":"Services"
        }
    ],
    "sg:phone":"+1 602 973 6799",
    "sg:postcode":"85051",
    "sg:province":"AZ",
    "sg:tags":[
        "sales",
        "radiators-heating",
        "supply"
    ],
    "wof:name":"Tolifson Plumbing",
    "wof:placetype":"venue"
},
  "geometry": {"coordinates":[-112.140597,33.574267],"type":"Point"}
}