{
  "type": "Feature",
  "properties": {
    "iso:country":"US",
    "sg:address":"6657 State Rte 179",
    "sg:city":"Sedona",
    "sg:classifiers":[
        {
            "category":"Shopping",
            "subcategory":"Clothing, Apparel, & Fashions",
            "type":"Retail Goods"
        }
    ],
    "sg:phone":"+1 928 284 9844",
    "sg:postcode":"86351",
    "sg:province":"AZ",
    "sg:tags":[
        "family"
    ],
    "wof:name":"Izod",
    "wof:placetype":"venue"
},
  "geometry": {"coordinates":[-111.765787,34.765673],"type":"Point"}
}