{
  "type": "Feature",
  "properties": {
    "addr:full":"739 E Apache Blvd Tempe AZ 85281",
    "addr:housenumber":"739",
    "addr:postcode":"85281",
    "addr:street":"E Apache Blvd",
    "iso:country":"US",
    "sg:address":"739 E Apache Blvd",
    "sg:city":"Tempe",
    "sg:classifiers":[
        {
            "category":"Real Estate",
            "subcategory":"Real Estate Operator",
            "type":"Services"
        }
    ],
    "sg:phone":"+1 480 965 2192",
    "sg:postcode":"85281",
    "sg:province":"AZ",
    "sg:tags":[
        "dwelling"
    ],
    "wof:name":"Adelphi Commons",
    "wof:placetype":"venue"
},
  "geometry": {"coordinates":[-111.928701,33.414674],"type":"Point"}
}