{
  "type": "Feature",
  "properties": {
    "iso:country":"US",
    "sg:address":"250 State Hwy 260",
    "sg:city":"Payson",
    "sg:classifiers":[
        {
            "category":"Building & Trades",
            "subcategory":"Equipment Rental",
            "type":"Services"
        }
    ],
    "sg:phone":"+1 928 474 5787",
    "sg:postcode":"85541",
    "sg:province":"AZ",
    "sg:tags":[
        "crane"
    ],
    "wof:name":"Milam Crane Inc",
    "wof:placetype":"venue"
},
  "geometry": {"coordinates":[-111.323009,34.242532],"type":"Point"}
}