{
  "type": "Feature",
  "properties": {
    "iso:country":"US",
    "sg:address":"7650 S McClintock Drive",
    "sg:city":"Tempe",
    "sg:classifiers":[
        {
            "category":"Banks & Credit Unions",
            "subcategory":"Financial Services",
            "type":"Services"
        }
    ],
    "sg:phone":"+1 480 456 4700",
    "sg:postcode":"85284",
    "sg:province":"AZ",
    "sg:tags":[
        "broker",
        "mortgage"
    ],
    "wof:name":"U .S. Bushido Academy",
    "wof:placetype":"venue"
},
  "geometry": {"coordinates":[-111.911181,33.348453],"type":"Point"}
}