{
  "type": "Feature",
  "properties": {
    "addr:full":"1501 E 17th St Tucson AZ 85719",
    "addr:housenumber":"1501",
    "addr:postcode":"85719",
    "addr:street":"E 17Th St",
    "iso:country":"US",
    "sg:address":"1501 E 17th St",
    "sg:city":"Tucson",
    "sg:classifiers":[
        {
            "category":"Home & Garden",
            "subcategory":"Building Materials",
            "type":"Retail Goods"
        },
        {
            "category":"Building & Trades",
            "subcategory":"Construction",
            "type":"Services"
        },
        {
            "category":"Home & Garden",
            "subcategory":"Furniture",
            "type":"Retail Goods"
        }
    ],
    "sg:phone":"+1 520 792 3184",
    "sg:postcode":"85719",
    "sg:province":"AZ",
    "sg:tags":[
        "bathroom",
        "top",
        "counter",
        "cabinet",
        "planning",
        "equipment-household",
        "remodeling",
        "kitchen"
    ],
    "sg:website":"http://www.underbudgetcabinets.com",
    "wof:name":"Under Budget Cabinets",
    "wof:placetype":"venue"
},
  "geometry": {"coordinates":[-110.949158,32.213428],"type":"Point"}
}