{
  "type": "Feature",
  "properties": {
    "iso:country":"US",
    "sg:address":"1241 W Park Ave",
    "sg:city":"Gilbert",
    "sg:classifiers":[
        {
            "category":"Building & Trades",
            "subcategory":"Landscaping Services",
            "type":"Services"
        }
    ],
    "sg:phone":"+1 480 539 0761",
    "sg:postcode":"85233",
    "sg:province":"AZ",
    "sg:tags":[
        "landscape",
        "contractor"
    ],
    "wof:name":"Arizona Unique Landscaping",
    "wof:placetype":"venue"
},
  "geometry": {"coordinates":[-111.816655,33.351905],"type":"Point"}
}