{
  "type": "Feature",
  "properties": {
    "iso:country":"US",
    "sg:address":"2450 E Guadalupe Rd",
    "sg:city":"Gilbert",
    "sg:classifiers":[
        {
            "category":"Health Services",
            "subcategory":"Doctor",
            "type":"Services"
        }
    ],
    "sg:phone":"+1 480 892 5460",
    "sg:postcode":"85234",
    "sg:province":"AZ",
    "wof:name":"Desert Valley Infectious Dsease",
    "wof:placetype":"venue"
},
  "geometry": {"coordinates":[-111.741997,33.364799],"type":"Point"}
}