{
  "type": "Feature",
  "properties": {
    "iso:country":"US",
    "sg:address":"2820 W Augusta Ave",
    "sg:city":"Phoenix",
    "sg:classifiers":[
        {
            "category":"Real Estate",
            "subcategory":"Real Estate Operator",
            "type":"Services"
        }
    ],
    "sg:phone":"+1 602 864 6341",
    "sg:postcode":"85051",
    "sg:province":"AZ",
    "sg:tags":[
        "apartment"
    ],
    "wof:name":"Augusta Cove Apartments",
    "wof:placetype":"venue"
},
  "geometry": {"coordinates":[-112.119089,33.551309],"type":"Point"}
}