{
  "type": "Feature",
  "properties": {
    "iso:country":"US",
    "sg:address":"481 E Z St",
    "sg:city":"Prescott",
    "sg:classifiers":[
        {
            "category":"Wholesale",
            "subcategory":"Construction Materials",
            "type":"Manufacturing & Wholesale Goods"
        }
    ],
    "sg:phone":"+1 928 771 1190",
    "sg:postcode":"86301",
    "sg:province":"AZ",
    "sg:website":"www.alliedbuilding.com",
    "wof:name":"Allied Building Products Corp",
    "wof:placetype":"venue"
},
  "geometry": {"coordinates":[-112.463918,34.549028],"type":"Point"}
}