{
  "type": "Feature",
  "properties": {
    "addr:full":"21630 N 9th Ave Ste 101 Phoenix AZ 85027",
    "addr:housenumber":"21630",
    "addr:postcode":"85027",
    "addr:street":"N 9Th Ave Ste 101",
    "iso:country":"US",
    "sg:address":"21630 N 9th Ave Ste 101",
    "sg:city":"Phoenix",
    "sg:classifiers":[
        {
            "category":"Manufacturing",
            "subcategory":"Metals",
            "type":"Manufacturing & Wholesale Goods"
        },
        {
            "category":"Manufacturing",
            "subcategory":"Building Materials",
            "type":"Manufacturing & Wholesale Goods"
        }
    ],
    "sg:phone":"+1 602 254 2000",
    "sg:postcode":"85027",
    "sg:province":"AZ",
    "sg:tags":[
        "work-manufacturers",
        "work",
        "sheet",
        "fabricator"
    ],
    "wof:name":"Wood Art Products, Inc",
    "wof:placetype":"venue"
},
  "geometry": {"coordinates":[-112.08513000000001,33.682265],"type":"Point"}
}