{
  "type": "Feature",
  "properties": {
    "iso:country":"US",
    "sg:address":"3333 E Camelback Rd",
    "sg:city":"Phoenix",
    "sg:classifiers":[
        {
            "category":"Education",
            "subcategory":"Special Training",
            "type":"Public Place"
        }
    ],
    "sg:phone":"+1 602 468 9494",
    "sg:postcode":"85018",
    "sg:province":"AZ",
    "sg:tags":[
        "school",
        "language"
    ],
    "sg:website":"www.berlitz.com",
    "wof:name":"Berlitz Language Ctr",
    "wof:placetype":"venue"
},
  "geometry": {"coordinates":[-112.010963,33.50989],"type":"Point"}
}