{
  "type": "Feature",
  "properties": {
    "iso:country":"US",
    "sg:address":"7330 N 16th St",
    "sg:city":"Phoenix",
    "sg:classifiers":[
        {
            "category":"Building & Trades",
            "subcategory":"Construction",
            "type":"Services"
        }
    ],
    "sg:phone":"+1 602 943 8300",
    "sg:postcode":"85020",
    "sg:province":"AZ",
    "sg:tags":[
        "contractor"
    ],
    "wof:name":"Stormkeeper LLC",
    "wof:placetype":"venue"
},
  "geometry": {"coordinates":[-112.047581,33.543438],"type":"Point"}
}