{
  "type": "Feature",
  "properties": {
    "iso:country":"US",
    "sg:address":"2121 N Center St",
    "sg:city":"Mesa",
    "sg:classifiers":[
        {
            "category":"Building & Trades",
            "subcategory":"Pest Control",
            "type":"Services"
        }
    ],
    "sg:phone":"+1 480 833 7665",
    "sg:postcode":"85201",
    "sg:province":"AZ",
    "wof:name":"Delta Exterminating",
    "wof:placetype":"venue"
},
  "geometry": {"coordinates":[-111.831001,33.453211],"type":"Point"}
}