{
  "type": "Feature",
  "properties": {
    "iso:country":"US",
    "sg:address":"2814 E Cortez St",
    "sg:city":"Phoenix",
    "sg:phone":"+1 602 493 9685",
    "sg:postcode":"85028",
    "sg:province":"AZ",
    "wof:name":"Marys Pampered Pooches",
    "wof:placetype":"venue"
},
  "geometry": {"coordinates":[-112.021036,33.591191],"type":"Point"}
}