{
  "type": "Feature",
  "properties": {
    "addr:full":"900 N Fiesta Blvd Gilbert AZ 85233",
    "addr:housenumber":"900",
    "addr:postcode":"85233",
    "addr:street":"N Fiesta Blvd",
    "iso:country":"US",
    "sg:address":"900 N Fiesta Blvd",
    "sg:city":"Gilbert",
    "sg:classifiers":[
        {
            "category":"Organizations",
            "subcategory":"Labor Organization",
            "type":"Services"
        }
    ],
    "sg:phone":"+1 480 633 0149",
    "sg:postcode":"85233",
    "sg:province":"AZ",
    "wof:name":"Apwu",
    "wof:placetype":"venue"
},
  "geometry": {"coordinates":[-111.834259,33.364239],"type":"Point"}
}