{
  "type": "Feature",
  "properties": {
    "iso:country":"US",
    "sg:address":"232 E Balboa Dr",
    "sg:city":"Tempe",
    "sg:classifiers":[
        {
            "category":"Manufacturing",
            "subcategory":"Printing",
            "type":"Manufacturing & Wholesale Goods"
        }
    ],
    "sg:phone":"+1 480 968 0572",
    "sg:postcode":"85282",
    "sg:province":"AZ",
    "sg:tags":[
        "periodical"
    ],
    "wof:name":"Ajck Publishers",
    "wof:placetype":"venue"
},
  "geometry": {"coordinates":[-111.936475,33.399062],"type":"Point"}
}