{
  "type": "Feature",
  "properties": {
    "iso:country":"US",
    "sg:address":"702 W Hillside Ave",
    "sg:city":"Prescott",
    "sg:classifiers":[
        {
            "category":"Wholesale",
            "subcategory":"Medical Equipment & Supplies",
            "type":"Manufacturing & Wholesale Goods"
        },
        {
            "category":"Shopping",
            "subcategory":"Pharmacy",
            "type":"Retail Goods"
        }
    ],
    "sg:phone":"+1 928 717 1560",
    "sg:postcode":"86301",
    "sg:province":"AZ",
    "sg:tags":[
        "home",
        "health",
        "oxygen",
        "care"
    ],
    "sg:website":"http://www.alliancehomecare.org",
    "wof:name":"Alliance Home Care",
    "wof:placetype":"venue"
},
  "geometry": {"coordinates":[-112.477381,34.553162],"type":"Point"}
}