{
  "type": "Feature",
  "properties": {
    "iso:country":"US",
    "sg:address":"1633 E Brown Rd",
    "sg:city":"Mesa",
    "sg:classifiers":[
        {
            "category":"Real Estate",
            "subcategory":"Real Estate Services",
            "type":"Services"
        }
    ],
    "sg:phone":"+1 480 510 3056",
    "sg:postcode":"85203",
    "sg:province":"AZ",
    "sg:tags":[
        "vacancy",
        "apartment",
        "rental",
        "finder",
        "listing"
    ],
    "wof:name":"Silver Studio Arts",
    "wof:placetype":"venue"
},
  "geometry": {"coordinates":[-111.79595399999999,33.436956],"type":"Point"}
}