{
  "type": "Feature",
  "properties": {
    "iso:country":"US",
    "sg:address":"4221 E Chandler Blvd",
    "sg:city":"Phoenix",
    "sg:classifiers":[
        {
            "category":"Recreation",
            "subcategory":"Amusement Park",
            "type":"Entertainment"
        }
    ],
    "sg:phone":"+1 480 704 8200",
    "sg:postcode":"85048",
    "sg:province":"AZ",
    "wof:name":"Front Two",
    "wof:placetype":"venue"
},
  "geometry": {"coordinates":[-111.992442,33.305141],"type":"Point"}
}