{
  "type": "Feature",
  "properties": {
    "iso:country":"US",
    "sg:address":"3530 S Dodge Blvd",
    "sg:city":"Tucson",
    "sg:classifiers":[
        {
            "category":"Retail",
            "subcategory":"Auto Repair",
            "type":"Services"
        }
    ],
    "sg:phone":"+1 888 739 3951",
    "sg:postcode":"85713",
    "sg:province":"AZ",
    "sg:tags":[
        "body",
        "automobile",
        "painting",
        "repairing"
    ],
    "sg:website":"http://www.johnnymacsauto.com",
    "wof:name":"Johnny Macs Automotive",
    "wof:placetype":"venue"
},
  "geometry": {"coordinates":[-110.913586,32.182965],"type":"Point"}
}