{
  "type": "Feature",
  "properties": {
    "addr:full":"10442 S 159th St Gilbert AZ 85234",
    "addr:housenumber":"10442",
    "addr:postcode":"85234",
    "addr:street":"S 159Th St",
    "iso:country":"US",
    "sg:address":"10442 S 159th St",
    "sg:city":"Gilbert",
    "sg:classifiers":[
        {
            "category":"Professional",
            "type":"Services"
        }
    ],
    "sg:phone":"+1 480 558 8765",
    "sg:postcode":"85234",
    "sg:province":"AZ",
    "wof:name":"Ocean Choppers",
    "wof:placetype":"venue"
},
  "geometry": {"coordinates":[-111.740567,33.352786],"type":"Point"}
}