{
  "type": "Feature",
  "properties": {
    "iso:country":"US",
    "sg:address":"3819 E Surrey Ave",
    "sg:city":"Phoenix",
    "sg:classifiers":[
        {
            "category":"Building & Trades",
            "subcategory":"Plumbing",
            "type":"Services"
        }
    ],
    "sg:phone":"+1 602 971 2728",
    "sg:postcode":"85032",
    "sg:province":"AZ",
    "sg:tags":[
        "contractor"
    ],
    "wof:name":"Tom Ball Air Conditioning",
    "wof:placetype":"venue"
},
  "geometry": {"coordinates":[-111.99590499999999,33.605715],"type":"Point"}
}