{
  "type": "Feature",
  "properties": {
    "addr:full":"6629 N 58th Dr Glendale AZ 85301",
    "addr:housenumber":"6629",
    "addr:postcode":"85301",
    "addr:street":"N 58Th Dr",
    "iso:country":"US",
    "sg:address":"6629 N 58th Dr",
    "sg:city":"Glendale",
    "sg:classifiers":[
        {
            "category":"Building & Trades",
            "subcategory":"Construction",
            "type":"Services"
        }
    ],
    "sg:phone":"+1 602 298 2414",
    "sg:postcode":"85301",
    "sg:province":"AZ",
    "sg:tags":[
        "contractor"
    ],
    "wof:name":"Trinity Masonry Inc",
    "wof:placetype":"venue"
},
  "geometry": {"coordinates":[-112.18490300000001,33.5345],"type":"Point"}
}