{
  "type": "Feature",
  "properties": {
    "iso:country":"US",
    "sg:address":"6629 N 58th Dr",
    "sg:city":"Glendale",
    "sg:classifiers":[
        {
            "category":"Building & Trades",
            "subcategory":"Construction",
            "type":"Services"
        }
    ],
    "sg:phone":"+1 602 298 2414",
    "sg:postcode":"85301",
    "sg:province":"AZ",
    "sg:tags":[
        "contractor"
    ],
    "wof:name":"Trinity Masonry Inc",
    "wof:placetype":"venue"
},
  "geometry": {"coordinates":[-112.184903,33.5345],"type":"Point"}
}