{
  "type": "Feature",
  "properties": {
    "iso:country":"US",
    "sg:address":"8065 N 85th Way",
    "sg:city":"Scottsdale",
    "sg:classifiers":[
        {
            "category":"Insurance",
            "subcategory":"Insurance Agent",
            "type":"Services"
        }
    ],
    "sg:phone":"+1 480 951 2214",
    "sg:postcode":"85258",
    "sg:province":"AZ",
    "wof:name":"Native American Insurance Co",
    "wof:placetype":"venue"
},
  "geometry": {"coordinates":[-111.896071,33.554625],"type":"Point"}
}