{
  "type": "Feature",
  "properties": {
    "iso:country":"US",
    "sg:address":"5415 W Glendale Ave",
    "sg:city":"Glendale",
    "sg:classifiers":[
        {
            "category":"Personal",
            "subcategory":"Shoe Repair & Shine",
            "type":"Services"
        }
    ],
    "sg:phone":"+1 623 915 1700",
    "sg:postcode":"85301",
    "sg:province":"AZ",
    "wof:name":"We Buy Gold And Shoe Repair",
    "wof:placetype":"venue"
},
  "geometry": {"coordinates":[-112.175653,33.538497],"type":"Point"}
}