{
  "type": "Feature",
  "properties": {
    "iso:country":"US",
    "sg:address":"7726 S Apricot Dr",
    "sg:city":"Tempe",
    "sg:classifiers":[
        {
            "category":"Banks & Credit Unions",
            "subcategory":"Investment Brokerage",
            "type":"Services"
        },
        {
            "category":"Professional",
            "subcategory":"Lawyer & Legal Services",
            "type":"Services"
        }
    ],
    "sg:phone":"+1 480 730 0244",
    "sg:postcode":"85284",
    "sg:province":"AZ",
    "sg:tags":[
        "advisory",
        "planning",
        "estate"
    ],
    "wof:name":"American Living Trust Svcs LLC",
    "wof:placetype":"venue"
},
  "geometry": {"coordinates":[-111.907859,33.346205],"type":"Point"}
}