{
  "type": "Feature",
  "properties": {
    "iso:country":"US",
    "sg:address":"712 E Ivanhoe St",
    "sg:city":"Chandler",
    "sg:classifiers":[
        {
            "category":"Building & Trades",
            "subcategory":"Construction",
            "type":"Services"
        }
    ],
    "sg:phone":"+1 480 219 1003",
    "sg:postcode":"85225",
    "sg:province":"AZ",
    "sg:tags":[
        "home",
        "builder"
    ],
    "wof:name":"Elite Luxury Homes",
    "wof:placetype":"venue"
},
  "geometry": {"coordinates":[-111.830848,33.317532],"type":"Point"}
}