{
  "type": "Feature",
  "properties": {
    "iso:country":"US",
    "sg:address":"5413 W Cambridge Ave",
    "sg:city":"Phoenix",
    "sg:classifiers":[
        {
            "category":"Shopping",
            "subcategory":"Catalog Store",
            "type":"Retail Goods"
        }
    ],
    "sg:phone":"+1 602 272 5185",
    "sg:postcode":"85035",
    "sg:province":"AZ",
    "sg:tags":[
        "mail",
        "order",
        "online"
    ],
    "wof:name":"Tor-Eggs-Tor",
    "wof:placetype":"venue"
},
  "geometry": {"coordinates":[-112.176281,33.477302],"type":"Point"}
}