{
  "type": "Feature",
  "properties": {
    "iso:country":"US",
    "sg:address":"2135 E Jones Ave",
    "sg:city":"Phoenix",
    "sg:classifiers":[
        {
            "category":"Manufacturing",
            "subcategory":"Chemicals & Compounds",
            "type":"Manufacturing & Wholesale Goods"
        },
        {
            "category":"Manufacturing",
            "subcategory":"Tools & Machinery",
            "type":"Manufacturing & Wholesale Goods"
        },
        {
            "category":"Building & Trades",
            "subcategory":"Construction",
            "type":"Services"
        },
        {
            "category":"Professional",
            "subcategory":"Art Services",
            "type":"Services"
        },
        {
            "category":"Home & Garden",
            "subcategory":"Building Materials",
            "type":"Retail Goods"
        },
        {
            "category":"Wholesale",
            "subcategory":"Painting Supplies",
            "type":"Manufacturing & Wholesale Goods"
        },
        {
            "category":"Autos & Motor Vehicles",
            "subcategory":"Auto Supplies",
            "type":"Retail Goods"
        },
        {
            "category":"Building & Trades",
            "subcategory":"Equipment Rental",
            "type":"Services"
        },
        {
            "category":"Manufacturing",
            "subcategory":"Building Materials",
            "type":"Manufacturing & Wholesale Goods"
        }
    ],
    "sg:phone":"+1 602 252 7574",
    "sg:postcode":"85040",
    "sg:province":"AZ",
    "sg:tags":[
        "shop",
        "designer",
        "spraying",
        "wall",
        "automobile",
        "wallpaper",
        "coating",
        "contractor",
        "paint-wholesale",
        "paint",
        "body",
        "plastering",
        "decorator",
        "wallcoverings-installation",
        "wallcoverings",
        "interior",
        "equipment-renting",
        "painter",
        "manufacturer"
    ],
    "sg:website":"http://sherwin-williams.com",
    "wof:name":"Sherwin-Williams",
    "wof:placetype":"venue"
},
  "geometry": {"coordinates":[-112.036434,33.409778],"type":"Point"}
}