{
  "type": "Feature",
  "properties": {
    "iso:country":"US",
    "sg:address":"1750 S Los Feliz Dr # 101",
    "sg:city":"Tempe",
    "sg:classifiers":[
        {
            "category":"Professional",
            "subcategory":"Business Services",
            "type":"Services"
        }
    ],
    "sg:phone":"+1 480 922 3545",
    "sg:postcode":"85281",
    "sg:province":"AZ",
    "sg:tags":[
        "management"
    ],
    "wof:name":"Continental Carriage",
    "wof:placetype":"venue"
},
  "geometry": {"coordinates":[-111.90417100000001,33.409415],"type":"Point"}
}