{
  "type": "Feature",
  "properties": {
    "iso:country":"US",
    "sg:address":"221 E Dunlap Ave",
    "sg:city":"Phoenix",
    "sg:classifiers":[
        {
            "category":"Restaurant",
            "type":"Food & Drink"
        }
    ],
    "sg:phone":"+1 602 678 0262",
    "sg:postcode":"85020",
    "sg:province":"AZ",
    "sg:website":"www.deltaco.net",
    "wof:name":"Del Taco",
    "wof:placetype":"venue"
},
  "geometry": {"coordinates":[-112.07142899999999,33.567676],"type":"Point"}
}