{
  "type": "Feature",
  "properties": {
    "iso:country":"US",
    "sg:address":"2315 E South Mountain Ave",
    "sg:city":"Phoenix",
    "sg:classifiers":[
        {
            "category":"Home & Garden",
            "subcategory":"Furniture",
            "type":"Retail Goods"
        }
    ],
    "sg:phone":"+1 602 680 3024",
    "sg:postcode":"85042",
    "sg:province":"AZ",
    "sg:tags":[
        "store"
    ],
    "wof:name":"S. Thomas Jackson Fine Furniture/Woodwise",
    "wof:placetype":"venue"
},
  "geometry": {"coordinates":[-112.032965,33.37052],"type":"Point"}
}