{
  "type": "Feature",
  "properties": {
    "iso:country":"US",
    "sg:address":"7090 S Craycroft Rd",
    "sg:city":"Tucson",
    "sg:classifiers":[
        {
            "category":"Retail",
            "subcategory":"Car Wash",
            "type":"Services"
        }
    ],
    "sg:phone":"+1 520 574 0809",
    "sg:postcode":"85706",
    "sg:province":"AZ",
    "sg:tags":[
        "automobile",
        "detail",
        "clean"
    ],
    "wof:name":"Advanced Recon",
    "wof:placetype":"venue"
},
  "geometry": {"coordinates":[-110.87524000000001,32.12532],"type":"Point"}
}