{
  "type": "Feature",
  "properties": {
    "addr:full":"6220 N Cam Escalante Tucson AZ 85718",
    "addr:housenumber":"6220",
    "addr:postcode":"85718",
    "addr:street":"N Cam Escalante",
    "iso:country":"US",
    "sg:address":"6220 N Cam Escalante",
    "sg:city":"Tucson",
    "sg:classifiers":[
        {
            "category":"Manufacturing",
            "subcategory":"Printing",
            "type":"Manufacturing & Wholesale Goods"
        }
    ],
    "sg:phone":"+1 520 577 2494",
    "sg:postcode":"85718",
    "sg:province":"AZ",
    "sg:tags":[
        "painting",
        "contractor"
    ],
    "wof:name":"Martin M McGarry Inc",
    "wof:placetype":"venue"
},
  "geometry": {"coordinates":[-110.936339,32.31935],"type":"Point"}
}