{
  "type": "Feature",
  "properties": {
    "addr:full":"5335 E Shea Blvd Scottsdale AZ 85254",
    "addr:housenumber":"5335",
    "addr:postcode":"85254",
    "addr:street":"E Shea Blvd",
    "iso:country":"US",
    "sg:address":"5335 E Shea Blvd",
    "sg:city":"Scottsdale",
    "sg:classifiers":[
        {
            "category":"Real Estate",
            "subcategory":"Real Estate Operator",
            "type":"Services"
        }
    ],
    "sg:phone":"+1 480 948 7070",
    "sg:postcode":"85254",
    "sg:province":"AZ",
    "sg:tags":[
        "management",
        "condominium"
    ],
    "wof:name":"Bella Terra Condominiums",
    "wof:placetype":"venue"
},
  "geometry": {"coordinates":[-111.966202,33.582691],"type":"Point"}
}