{
  "type": "Feature",
  "properties": {
    "iso:country":"US",
    "sg:address":"6540 E Carondelet Dr",
    "sg:city":"Tucson",
    "sg:classifiers":[
        {
            "category":"Health Services",
            "subcategory":"Doctor",
            "type":"Services"
        }
    ],
    "sg:phone":"+1 520 751 8114",
    "sg:postcode":"85710",
    "sg:province":"AZ",
    "sg:tags":[
        "physician",
        "surgeon"
    ],
    "wof:name":"Arizona Community Physicians",
    "wof:placetype":"venue"
},
  "geometry": {"coordinates":[-110.84972,32.225548],"type":"Point"}
}