{
  "type": "Feature",
  "properties": {
    "iso:country":"US",
    "sg:address":"7600 E Doubletree Ranch Rd",
    "sg:city":"Scottsdale",
    "sg:classifiers":[
        {
            "category":"Real Estate",
            "subcategory":"Real Estate Agent",
            "type":"Services"
        }
    ],
    "sg:phone":"+1 480 367 1777",
    "sg:postcode":"85258",
    "sg:province":"AZ",
    "sg:tags":[
        "investment"
    ],
    "wof:name":"KBK Real Estate Advisors",
    "wof:placetype":"venue"
},
  "geometry": {"coordinates":[-111.918075,33.564883],"type":"Point"}
}