{
  "type": "Feature",
  "properties": {
    "addr:full":"2790 W Darleen Dr Flagstaff AZ 86001",
    "addr:housenumber":"2790",
    "addr:postcode":"86001",
    "addr:street":"W Darleen Dr",
    "iso:country":"US",
    "sg:address":"2790 W Darleen Dr",
    "sg:city":"Flagstaff",
    "sg:classifiers":[
        {
            "category":"Building & Trades",
            "subcategory":"Construction",
            "type":"Services"
        }
    ],
    "sg:phone":"+1 928 525 9651",
    "sg:postcode":"86001",
    "sg:province":"AZ",
    "sg:tags":[
        "house"
    ],
    "wof:name":"Blue Sky Builders",
    "wof:placetype":"venue"
},
  "geometry": {"coordinates":[-111.667439,35.231098],"type":"Point"}
}