{
  "type": "Feature",
  "properties": {
    "iso:country":"US",
    "sg:address":"4200 N Marshall Way",
    "sg:city":"Scottsdale",
    "sg:classifiers":[
        {
            "category":"Professional",
            "subcategory":"Business Services",
            "type":"Services"
        }
    ],
    "sg:phone":"+1 480 947 0011",
    "sg:postcode":"85251",
    "sg:province":"AZ",
    "sg:tags":[
        "interior",
        "consultant",
        "design",
        "decorator"
    ],
    "wof:name":"Inside Views",
    "wof:placetype":"venue"
},
  "geometry": {"coordinates":[-111.928991,33.497557],"type":"Point"}
}