{
  "type": "Feature",
  "properties": {
    "addr:full":"4800 W Ocotillo Rd Lot 30 Glendale AZ 85301",
    "addr:housenumber":"4800;30",
    "addr:postcode":"85301",
    "addr:street":"W Ocotillo Rd Lot",
    "iso:country":"US",
    "sg:address":"4800 W Ocotillo Rd Lot 30",
    "sg:city":"Glendale",
    "sg:classifiers":[
        {
            "category":"Professional",
            "type":"Services"
        }
    ],
    "sg:phone":"+1 623 435 8440",
    "sg:postcode":"85301",
    "sg:province":"AZ",
    "sg:tags":[
        "caterer"
    ],
    "wof:name":"Double H Catering",
    "wof:placetype":"venue"
},
  "geometry": {"coordinates":[-112.16189799999999,33.534804],"type":"Point"}
}