{
  "type": "Feature",
  "properties": {
    "addr:full":"6838 E Main St Mesa AZ 85207",
    "addr:housenumber":"6838",
    "addr:postcode":"85207",
    "addr:street":"E Main St",
    "iso:country":"US",
    "sg:address":"6838 E Main St",
    "sg:city":"Mesa",
    "sg:classifiers":[
        {
            "category":"Home & Garden",
            "subcategory":"Furniture",
            "type":"Retail Goods"
        }
    ],
    "sg:phone":"+1 480 218 0049",
    "sg:postcode":"85207",
    "sg:province":"AZ",
    "wof:name":"Action Jacks Of East Mesa LLC",
    "wof:placetype":"venue"
},
  "geometry": {"coordinates":[-111.684417,33.415751],"type":"Point"}
}