{
  "type": "Feature",
  "properties": {
    "iso:country":"US",
    "sg:address":"4627 W Laurie Ln",
    "sg:city":"Glendale",
    "sg:classifiers":[
        {
            "category":"Professional",
            "type":"Services"
        }
    ],
    "sg:phone":"+1 623 931 0647",
    "sg:postcode":"85302",
    "sg:province":"AZ",
    "wof:name":"Jim Gorman",
    "wof:placetype":"venue"
},
  "geometry": {"coordinates":[-112.15966,33.558618],"type":"Point"}
}