{
  "type": "Feature",
  "properties": {
    "iso:country":"US",
    "sg:address":"75 Edson Ave",
    "sg:city":"Colorado City",
    "sg:classifiers":[
        {
            "category":"Building & Trades",
            "subcategory":"Construction",
            "type":"Services"
        }
    ],
    "sg:phone":"+1 928 875 2522",
    "sg:postcode":"86021",
    "sg:province":"AZ",
    "sg:tags":[
        "general",
        "contractor"
    ],
    "wof:name":"Plane Construction",
    "wof:placetype":"venue"
},
  "geometry": {"coordinates":[-112.974806,36.988737],"type":"Point"}
}