{
  "type": "Feature",
  "properties": {
    "iso:country":"US",
    "sg:address":"9201 N 25th Ave Ste 280",
    "sg:city":"Phoenix",
    "sg:classifiers":[
        {
            "category":"Professional",
            "subcategory":"Management & Consulting",
            "type":"Services"
        },
        {
            "category":"Banks & Credit Unions",
            "subcategory":"Investment Brokerage",
            "type":"Services"
        },
        {
            "category":"Banks & Credit Unions",
            "subcategory":"Financial Services",
            "type":"Services"
        }
    ],
    "sg:phone":"+1 602 943 8623",
    "sg:postcode":"85021",
    "sg:province":"AZ",
    "sg:tags":[
        "financing",
        "retirement",
        "annuity",
        "planning",
        "plan",
        "consultant",
        "security",
        "insurance"
    ],
    "sg:website":"http://www.waddell.com",
    "wof:name":"Waddell & Reed Investment Management Company",
    "wof:placetype":"venue"
},
  "geometry": {"coordinates":[-112.112282,33.56918],"type":"Point"}
}