{
  "type": "Feature",
  "properties": {
    "iso:country":"US",
    "sg:address":"910 W Congress St",
    "sg:city":"Tucson",
    "sg:classifiers":[
        {
            "category":"Home & Garden",
            "subcategory":"Hardware",
            "type":"Retail Goods"
        }
    ],
    "sg:phone":"+1 520 623 3921",
    "sg:postcode":"85745",
    "sg:province":"AZ",
    "sg:tags":[
        "liquor",
        "store"
    ],
    "wof:name":"Manny's West Congress Hardware",
    "wof:placetype":"venue"
},
  "geometry": {"coordinates":[-110.988313,32.219992],"type":"Point"}
}