{
  "type": "Feature",
  "properties": {
    "addr:full":"2260 E University Dr Mesa AZ 85213",
    "addr:housenumber":"2260",
    "addr:postcode":"85213",
    "addr:street":"E University Dr",
    "iso:country":"US",
    "sg:address":"2260 E University Dr",
    "sg:city":"Mesa",
    "sg:classifiers":[
        {
            "category":"Professional",
            "subcategory":"Accounting & Tax Preparation",
            "type":"Services"
        }
    ],
    "sg:phone":"+1 480 844 8588",
    "sg:postcode":"85213",
    "sg:province":"AZ",
    "sg:tags":[
        "billing"
    ],
    "wof:name":"Medical Billing Management",
    "wof:placetype":"venue"
},
  "geometry": {"coordinates":[-111.781892,33.422733],"type":"Point"}
}