{
  "type": "Feature",
  "properties": {
    "addr:full":"7512 E Clinton St Scottsdale AZ 85260",
    "addr:housenumber":"7512",
    "addr:postcode":"85260",
    "addr:street":"E Clinton St",
    "iso:country":"US",
    "sg:address":"7512 E Clinton St",
    "sg:city":"Scottsdale",
    "sg:classifiers":[
        {
            "category":"Shopping",
            "subcategory":"Gifts & Souvenirs",
            "type":"Retail Goods"
        }
    ],
    "sg:phone":"+1 480 998 2304",
    "sg:postcode":"85260",
    "sg:province":"AZ",
    "sg:tags":[
        "announcement",
        "wedding",
        "invitation"
    ],
    "wof:name":"It's Perfect",
    "wof:placetype":"venue"
},
  "geometry": {"coordinates":[-111.919937,33.583737],"type":"Point"}
}