{
  "type": "Feature",
  "properties": {
    "addr:full":"5235 N Sabino Canyon Rd Tucson AZ 85750",
    "addr:housenumber":"5235",
    "addr:postcode":"85750",
    "addr:street":"N Sabino Canyon Rd",
    "iso:country":"US",
    "sg:address":"5235 N Sabino Canyon Rd",
    "sg:city":"Tucson",
    "sg:classifiers":[
        {
            "category":"Building & Trades",
            "subcategory":"Construction",
            "type":"Services"
        }
    ],
    "sg:phone":"+1 520 529 6300",
    "sg:postcode":"85750",
    "sg:province":"AZ",
    "sg:tags":[
        "housing",
        "family"
    ],
    "wof:name":"Miramonte Homes",
    "wof:placetype":"venue"
},
  "geometry": {"coordinates":[-110.824061,32.304868],"type":"Point"}
}