{
  "type": "Feature",
  "properties": {
    "iso:country":"US",
    "sg:address":"4007 E Greenway Rd",
    "sg:city":"Phoenix",
    "sg:classifiers":[
        {
            "category":"Restaurant",
            "type":"Food & Drink"
        }
    ],
    "sg:phone":"+1 602 765 8690",
    "sg:postcode":"85032",
    "sg:province":"AZ",
    "sg:tags":[
        "eating"
    ],
    "wof:name":"Sonic Drive-In",
    "wof:placetype":"venue"
},
  "geometry": {"coordinates":[-111.993199,33.62629],"type":"Point"}
}