{
  "type": "Feature",
  "properties": {
    "iso:country":"US",
    "sg:address":"835 W 22nd St",
    "sg:city":"Tempe",
    "sg:classifiers":[
        {
            "category":"Airline",
            "type":"Transportation"
        }
    ],
    "sg:phone":"+1 480 350 9927",
    "sg:postcode":"85282",
    "sg:province":"AZ",
    "sg:tags":[
        "cargo",
        "air"
    ],
    "wof:name":"Phoenix Freight Forwarding",
    "wof:placetype":"venue"
},
  "geometry": {"coordinates":[-111.94932,33.404549],"type":"Point"}
}