{
  "type": "Feature",
  "properties": {
    "iso:country":"US",
    "sg:address":"2306 Harrod Ave",
    "sg:city":"Kingman",
    "sg:classifiers":[
        {
            "category":"Manufacturing",
            "subcategory":"Motor Vehicles & Parts",
            "type":"Manufacturing & Wholesale Goods"
        }
    ],
    "sg:phone":"+1 928 753 4075",
    "sg:postcode":"86401",
    "sg:province":"AZ",
    "sg:tags":[
        "mfg",
        "trimming"
    ],
    "wof:name":"Fourte Imprints",
    "wof:placetype":"venue"
},
  "geometry": {"coordinates":[-114.024335,35.197887],"type":"Point"}
}