{
  "type": "Feature",
  "properties": {
    "iso:country":"US",
    "sg:address":"3190 S Debbie St",
    "sg:city":"Flagstaff",
    "sg:classifiers":[
        {
            "category":"Banks & Credit Unions",
            "subcategory":"Bank",
            "type":"Services"
        }
    ],
    "sg:phone":"+1 928 213 0569",
    "sg:postcode":"86001",
    "sg:province":"AZ",
    "sg:tags":[
        "loan",
        "real estate"
    ],
    "wof:name":"Pacific Coast Mortgages",
    "wof:placetype":"venue"
},
  "geometry": {"coordinates":[-111.682323,35.173591],"type":"Point"}
}