{
  "type": "Feature",
  "properties": {
    "iso:country":"US",
    "sg:address":"1350 W 5th St Ofc",
    "sg:city":"Yuma",
    "sg:classifiers":[
        {
            "category":"Real Estate",
            "subcategory":"Real Estate Operator",
            "type":"Services"
        }
    ],
    "sg:phone":"+1 928 726 8002",
    "sg:postcode":"85364",
    "sg:province":"AZ",
    "sg:tags":[
        "apartment"
    ],
    "wof:name":"Mary Manor Apartments",
    "wof:placetype":"venue"
},
  "geometry": {"coordinates":[-114.63641699999999,32.717905],"type":"Point"}
}