{
  "type": "Feature",
  "properties": {
    "addr:full":"5127 W Polk St Phoenix AZ 85043",
    "addr:housenumber":"5127",
    "addr:postcode":"85043",
    "addr:street":"W Polk St",
    "iso:country":"US",
    "sg:address":"5127 W Polk St",
    "sg:city":"Phoenix",
    "sg:classifiers":[
        {
            "category":"Manufacturing",
            "subcategory":"Chemicals & Compounds",
            "type":"Manufacturing & Wholesale Goods"
        }
    ],
    "sg:phone":"+1 602 233 0431",
    "sg:postcode":"85043",
    "sg:province":"AZ",
    "sg:tags":[
        "mfg",
        "printing",
        "ink"
    ],
    "sg:website":"www.inxinternational.com",
    "wof:name":"INX International Ink Co",
    "wof:placetype":"venue"
},
  "geometry": {"coordinates":[-112.17173200000001,33.45306],"type":"Point"}
}