{
  "type": "Feature",
  "properties": {
    "addr:full":"4450 N 12th St Ste 200 Phoenix AZ 85014",
    "addr:housenumber":"4450",
    "addr:postcode":"85014",
    "addr:street":"N 12Th St Ste 200",
    "iso:country":"US",
    "sg:address":"4450 N 12th St Ste 200",
    "sg:city":"Phoenix",
    "sg:classifiers":[
        {
            "category":"Professional",
            "subcategory":"Art Services",
            "type":"Services"
        },
        {
            "category":"Professional",
            "subcategory":"Business Services",
            "type":"Services"
        }
    ],
    "sg:phone":"+1 602 240 6750",
    "sg:postcode":"85014",
    "sg:province":"AZ",
    "sg:tags":[
        "development",
        "product",
        "graphic",
        "designers-industrial",
        "marketing",
        "commercial",
        "designer",
        "design"
    ],
    "wof:name":"Gray Matter",
    "wof:placetype":"venue"
},
  "geometry": {"coordinates":[-112.056313,33.500208],"type":"Point"}
}