{
  "type": "Feature",
  "properties": {
    "addr:full":"4010 E Greenway Rd Phoenix AZ 85032",
    "addr:housenumber":"4010",
    "addr:postcode":"85032",
    "addr:street":"E Greenway Rd",
    "iso:country":"US",
    "sg:address":"4010 E Greenway Rd",
    "sg:city":"Phoenix",
    "sg:classifiers":[
        {
            "category":"Coffee & Tea",
            "type":"Food & Drink"
        }
    ],
    "sg:menulink":"http://www.allmenus.com/az/phoenix/108322-starbucks-coffee/menu/",
    "sg:phone":"+1 602 494 3121",
    "sg:postcode":"85032",
    "sg:province":"AZ",
    "sg:tags":[
        "american"
    ],
    "wof:name":"Starbucks Coffee",
    "wof:placetype":"venue"
},
  "geometry": {"coordinates":[-111.995721,33.626472],"type":"Point"}
}