{
  "type": "Feature",
  "properties": {
    "iso:country":"US",
    "sg:address":"31313 N Scottsdale Rd Ste A155",
    "sg:city":"Scottsdale",
    "sg:classifiers":[
        {
            "category":"Personal",
            "subcategory":"Massage",
            "type":"Services"
        },
        {
            "category":"Personal",
            "subcategory":"Hair Removal",
            "type":"Services"
        },
        {
            "category":"Personal",
            "subcategory":"Nail Salon",
            "type":"Services"
        }
    ],
    "sg:phone":"+1 480 794 1455",
    "sg:postcode":"85266",
    "sg:province":"AZ",
    "wof:name":"Ivy Nails & Spa",
    "wof:placetype":"venue"
},
  "geometry": {"coordinates":[-111.925865,33.769274],"type":"Point"}
}