{
  "type": "Feature",
  "properties": {
    "iso:country":"US",
    "sg:address":"2741 W Southern Ave",
    "sg:city":"Tempe",
    "sg:classifiers":[
        {
            "category":"Building & Trades",
            "subcategory":"Construction",
            "type":"Services"
        }
    ],
    "sg:phone":"+1 602 305 8076",
    "sg:postcode":"85282",
    "sg:province":"AZ",
    "sg:tags":[
        "designer",
        "dealer",
        "pool",
        "swimming"
    ],
    "wof:name":"Fresca Pools",
    "wof:placetype":"venue"
},
  "geometry": {"coordinates":[-111.9769,33.392738],"type":"Point"}
}