{
  "type": "Feature",
  "properties": {
    "addr:full":"7808 N Roundstone Dr Tucson AZ 85741",
    "addr:housenumber":"7808",
    "addr:postcode":"85741",
    "addr:street":"N Roundstone Dr",
    "iso:country":"US",
    "sg:address":"7808 N Roundstone Dr",
    "sg:city":"Tucson",
    "sg:classifiers":[
        {
            "category":"Retail",
            "subcategory":"Repair Shop",
            "type":"Services"
        }
    ],
    "sg:phone":"+1 520 744 6825",
    "sg:postcode":"85741",
    "sg:province":"AZ",
    "sg:tags":[
        "vinyl"
    ],
    "wof:name":"Scott's Vinyl Repair",
    "wof:placetype":"venue"
},
  "geometry": {"coordinates":[-111.056032,32.34832],"type":"Point"}
}