{
  "type": "Feature",
  "properties": {
    "iso:country":"US",
    "sg:address":"5787 W Erie St",
    "sg:city":"Chandler",
    "sg:classifiers":[
        {
            "category":"Airport",
            "type":"Transportation"
        }
    ],
    "sg:phone":"+1 480 941 4946",
    "sg:postcode":"85226",
    "sg:province":"AZ",
    "wof:name":"Phoenix Regional Airport",
    "wof:placetype":"venue"
},
  "geometry": {"coordinates":[-111.940228,33.309118],"type":"Point"}
}