{
  "type": "Feature",
  "properties": {
    "iso:country":"US",
    "sg:address":"17900 S Copper Cut Trl",
    "sg:city":"Vail",
    "sg:classifiers":[
        {
            "category":"Home & Garden",
            "subcategory":"Carpets & Floor Coverings",
            "type":"Retail Goods"
        }
    ],
    "sg:phone":"+1 520 762 8699",
    "sg:postcode":"85641",
    "sg:province":"AZ",
    "sg:tags":[
        "material",
        "flooring",
        "contractor"
    ],
    "wof:name":"Sullivan Family Floors",
    "wof:placetype":"venue"
},
  "geometry": {"coordinates":[-110.71241999999999,31.930766],"type":"Point"}
}