{
  "type": "Feature",
  "properties": {
    "iso:country":"US",
    "sg:address":"1536 E Cheyenne St",
    "sg:city":"Gilbert",
    "sg:classifiers":[
        {
            "category":"Taxi",
            "type":"Transportation"
        }
    ],
    "sg:phone":"+1 480 329 9936",
    "sg:postcode":"85296",
    "sg:province":"AZ",
    "wof:name":"Valley Taxi",
    "wof:placetype":"venue"
},
  "geometry": {"coordinates":[-111.756823,33.346944],"type":"Point"}
}