{
  "type": "Feature",
  "properties": {
    "addr:full":"1249 E Canyon St Apache Junction AZ 85219",
    "addr:housenumber":"1249",
    "addr:postcode":"85219",
    "addr:street":"E Canyon St",
    "iso:country":"US",
    "sg:address":"1249 E Canyon St",
    "sg:city":"Apache Junction",
    "sg:classifiers":[
        {
            "category":"Building & Trades",
            "subcategory":"Construction",
            "type":"Services"
        }
    ],
    "sg:phone":"+1 480 671 0828",
    "sg:postcode":"85219",
    "sg:province":"AZ",
    "sg:tags":[
        "house"
    ],
    "wof:name":"Cr Desert Construction Co",
    "wof:placetype":"venue"
},
  "geometry": {"coordinates":[-111.53242,33.458552],"type":"Point"}
}