{
  "type": "Feature",
  "properties": {
    "iso:country":"US",
    "sg:address":"7339 E Evans Rd",
    "sg:city":"Scottsdale",
    "sg:classifiers":[
        {
            "category":"Retail",
            "subcategory":"Portrait Studio",
            "type":"Services"
        }
    ],
    "sg:phone":"+1 480 607 6445",
    "sg:postcode":"85260",
    "sg:province":"AZ",
    "sg:tags":[
        "photographer"
    ],
    "wof:name":"Growing Family Portraits",
    "wof:placetype":"venue"
},
  "geometry": {"coordinates":[-111.923875,33.615958],"type":"Point"}
}