{
  "type": "Feature",
  "properties": {
    "iso:country":"US",
    "sg:address":"5520 E Baseline Rd",
    "sg:city":"Mesa",
    "sg:classifiers":[
        {
            "category":"Building & Trades",
            "subcategory":"Construction",
            "type":"Services"
        }
    ],
    "sg:phone":"+1 480 830 4081",
    "sg:postcode":"85206",
    "sg:province":"AZ",
    "sg:tags":[
        "contractor"
    ],
    "wof:name":"R & L Builders",
    "wof:placetype":"venue"
},
  "geometry": {"coordinates":[-111.71503,33.379231],"type":"Point"}
}