{
  "type": "Feature",
  "properties": {
    "iso:country":"US",
    "sg:address":"10824 N 96th Ave",
    "sg:city":"Peoria",
    "sg:classifiers":[
        {
            "category":"Autos & Motor Vehicles",
            "subcategory":"Auto Supplies",
            "type":"Retail Goods"
        }
    ],
    "sg:phone":"+1 602 843 7275",
    "sg:postcode":"85345",
    "sg:province":"AZ",
    "sg:tags":[
        "equipment",
        "racing",
        "car",
        "automobile"
    ],
    "wof:name":"Corvette Performance",
    "wof:placetype":"venue"
},
  "geometry": {"coordinates":[-112.26428,33.583753],"type":"Point"}
}