{
  "type": "Feature",
  "properties": {
    "addr:full":"921 W University Dr # 1012 Mesa AZ 85201",
    "addr:housenumber":"921;1012",
    "addr:postcode":"85201",
    "addr:street":"W University Dr #",
    "iso:country":"US",
    "sg:address":"921 W University Dr # 1012",
    "sg:city":"Mesa",
    "sg:classifiers":[
        {
            "category":"Personal",
            "type":"Services"
        },
        {
            "category":"Professional",
            "subcategory":"Art Services",
            "type":"Services"
        },
        {
            "category":"Communications",
            "subcategory":"Film & Video Production",
            "type":"Services"
        }
    ],
    "sg:phone":"+1 480 834 5261",
    "sg:postcode":"85201",
    "sg:province":"AZ",
    "sg:tags":[
        "videography",
        "aerial",
        "photographer",
        "photography",
        "wedding"
    ],
    "sg:website":"http://www.trphotoonline.com",
    "wof:name":"Tim Roberts Photography",
    "wof:placetype":"venue"
},
  "geometry": {"coordinates":[-111.851404,33.422245],"type":"Point"}
}