{
  "type": "Feature",
  "properties": {
    "iso:country":"US",
    "sg:address":"2200 N Scottsdale Rd Suite C",
    "sg:city":"Scottsdale",
    "sg:classifiers":[
        {
            "category":"Personal",
            "type":"Services"
        },
        {
            "category":"Shopping",
            "subcategory":"Antiques",
            "type":"Retail Goods"
        },
        {
            "category":"Professional",
            "subcategory":"Business Services",
            "type":"Services"
        }
    ],
    "sg:phone":"+1 602 910 6184",
    "sg:postcode":"85257",
    "sg:province":"AZ",
    "sg:tags":[
        "liquidation",
        "auction",
        "estates-sales",
        "auctioneer",
        "appraisal",
        "appraiser"
    ],
    "sg:website":"http://www.jlevines.com/",
    "wof:name":"J Levine Auction & Appraisal LLC",
    "wof:placetype":"venue"
},
  "geometry": {"coordinates":[-111.926193,33.472122],"type":"Point"}
}