{
  "type": "Feature",
  "properties": {
    "addr:full":"4550 E Bell Rd Ste 150 Phoenix AZ 85032",
    "addr:housenumber":"4550",
    "addr:postcode":"85032",
    "addr:street":"E Bell Rd Ste 150",
    "iso:country":"US",
    "sg:address":"4550 E Bell Rd Ste 150",
    "sg:city":"Phoenix",
    "sg:classifiers":[
        {
            "category":"Autos & Motor Vehicles",
            "subcategory":"Boat Sales",
            "type":"Retail Goods"
        },
        {
            "category":"Manufacturing",
            "subcategory":"Watercraft",
            "type":"Manufacturing & Wholesale Goods"
        }
    ],
    "sg:phone":"+1 602 619 9200",
    "sg:postcode":"85032",
    "sg:province":"AZ",
    "sg:tags":[
        "distributor",
        "builder",
        "manufacturer"
    ],
    "wof:name":"Evo Custom Boats",
    "wof:placetype":"venue"
},
  "geometry": {"coordinates":[-111.98303799999999,33.640686],"type":"Point"}
}