{
  "type": "Feature",
  "properties": {
    "iso:country":"US",
    "sg:address":"15436 W Alexandria Way",
    "sg:city":"Surprise",
    "sg:classifiers":[
        {
            "category":"Structure",
            "subcategory":"Office Building",
            "type":"Public Place"
        }
    ],
    "sg:phone":"+1 623 594 8524",
    "sg:postcode":"85379",
    "sg:province":"AZ",
    "sg:tags":[
        "park"
    ],
    "wof:name":"Zimmerman Az Properties P",
    "wof:placetype":"venue"
},
  "geometry": {"coordinates":[-112.392455,33.606313],"type":"Point"}
}