{
  "type": "Feature",
  "properties": {
    "iso:country":"US",
    "sg:address":"2000 Zarragoza Dr",
    "sg:city":"Tucson",
    "sg:classifiers":[
        {
            "category":"Manufacturing",
            "subcategory":"Electronics",
            "type":"Manufacturing & Wholesale Goods"
        }
    ],
    "sg:phone":"+1 520 294 1221",
    "sg:postcode":"85704",
    "sg:province":"AZ",
    "sg:tags":[
        "printed",
        "circuit",
        "etched"
    ],
    "wof:name":"Circuit Engineering-CED",
    "wof:placetype":"venue"
},
  "geometry": {"coordinates":[-111.008971,32.346168],"type":"Point"}
}