{
  "type": "Feature",
  "properties": {
    "addr:full":"8801 W Bell Rd Peoria AZ 85382",
    "addr:housenumber":"8801",
    "addr:postcode":"85382",
    "addr:street":"W Bell Rd",
    "iso:country":"US",
    "sg:address":"8801 W Bell Rd",
    "sg:city":"Peoria",
    "sg:classifiers":[
        {
            "category":"Autos & Motor Vehicles",
            "subcategory":"Automobile Sales",
            "type":"Retail Goods"
        }
    ],
    "sg:phone":"+1 623 875 4000",
    "sg:postcode":"85382",
    "sg:province":"AZ",
    "sg:tags":[
        "car",
        "dealer"
    ],
    "wof:name":"Saturn Of Arrowhead",
    "wof:placetype":"venue"
},
  "geometry": {"coordinates":[-112.248919,33.638131],"type":"Point"}
}