{
  "type": "Feature",
  "properties": {
    "iso:country":"US",
    "sg:address":"309 W Live Oak St",
    "sg:city":"Miami",
    "sg:classifiers":[
        {
            "category":"Retail",
            "subcategory":"Funeral Services",
            "type":"Services"
        }
    ],
    "sg:phone":"+1 928 473 4496",
    "sg:postcode":"85539",
    "sg:province":"AZ",
    "sg:tags":[
        "director",
        "embalmer"
    ],
    "wof:name":"Arizona Funeral Services",
    "wof:placetype":"venue"
},
  "geometry": {"coordinates":[-110.87770500000001,33.394018],"type":"Point"}
}