{
  "type": "Feature",
  "properties": {
    "iso:country":"US",
    "sg:address":"2720 E Thomas Rd",
    "sg:city":"Phoenix",
    "sg:classifiers":[
        {
            "category":"Home & Garden",
            "subcategory":"Building Materials",
            "type":"Retail Goods"
        }
    ],
    "sg:phone":"+1 602 667 5540",
    "sg:postcode":"85016",
    "sg:province":"AZ",
    "sg:tags":[
        "glass",
        "window",
        "plate"
    ],
    "wof:name":"Action Glass",
    "wof:placetype":"venue"
},
  "geometry": {"coordinates":[-112.021914,33.480468],"type":"Point"}
}