{
  "type": "Feature",
  "properties": {
    "iso:country":"US",
    "sg:address":"7373 E Doubletree Ranch Rd",
    "sg:city":"Scottsdale",
    "sg:classifiers":[
        {
            "category":"Real Estate",
            "subcategory":"Real Estate Agent",
            "type":"Services"
        }
    ],
    "sg:phone":"+1 480 331 7974",
    "sg:postcode":"85258",
    "sg:province":"AZ",
    "sg:website":"http://www.americaonerealtyusa.com",
    "wof:name":"America -One Realty Services",
    "wof:placetype":"venue"
},
  "geometry": {"coordinates":[-111.921688,33.566619],"type":"Point"}
}