{
  "type": "Feature",
  "properties": {
    "addr:full":"5757 E Lost Dutchman Blvd Apache Junction AZ 85219",
    "addr:housenumber":"5757",
    "addr:postcode":"85219",
    "addr:street":"E Lost Dutchman Blvd",
    "iso:country":"US",
    "sg:address":"5757 E Lost Dutchman Blvd",
    "sg:city":"Apache Junction",
    "sg:classifiers":[
        {
            "category":"Shopping",
            "subcategory":"Florist",
            "type":"Retail Goods"
        }
    ],
    "sg:phone":"+1 480 288 7877",
    "sg:postcode":"85219",
    "sg:province":"AZ",
    "wof:name":"Diannes of Scottsdale",
    "wof:placetype":"venue"
},
  "geometry": {"coordinates":[-111.48278500000001,33.436904],"type":"Point"}
}