{
  "type": "Feature",
  "properties": {
    "iso:country":"US",
    "sg:address":"5041 W Northern Ave",
    "sg:city":"Glendale",
    "sg:classifiers":[
        {
            "category":"Health Services",
            "subcategory":"Chiropractor",
            "type":"Services"
        }
    ],
    "sg:phone":"+1 623 939 8325",
    "sg:postcode":"85301",
    "sg:province":"AZ",
    "wof:name":"Lord Chiropractic Ctr",
    "wof:placetype":"venue"
},
  "geometry": {"coordinates":[-112.16632,33.553021],"type":"Point"}
}