{
  "type": "Feature",
  "properties": {
    "addr:full":"2850 E Riviera Pl Chandler AZ 85249",
    "addr:housenumber":"2850",
    "addr:postcode":"85249",
    "addr:street":"E Riviera Pl",
    "iso:country":"US",
    "sg:address":"2850 E Riviera Pl",
    "sg:city":"Chandler",
    "sg:classifiers":[
        {
            "category":"Building & Trades",
            "subcategory":"Construction",
            "type":"Services"
        }
    ],
    "sg:phone":"+1 480 946 3888",
    "sg:postcode":"85249",
    "sg:province":"AZ",
    "sg:tags":[
        "house"
    ],
    "wof:name":"Gdm Handyman Services",
    "wof:placetype":"venue"
},
  "geometry": {"coordinates":[-111.791697,33.212624],"type":"Point"}
}