{
  "type": "Feature",
  "properties": {
    "addr:full":"3500 Old State Hwy 95 Lake Havasu City AZ 86404",
    "addr:housenumber":"3500",
    "addr:postcode":"86404",
    "addr:street":"Old State Hwy 95",
    "iso:country":"US",
    "sg:address":"3500 Old State Hwy 95",
    "sg:city":"Lake Havasu City",
    "sg:classifiers":[
        {
            "category":"Government",
            "subcategory":"Police Station",
            "type":"Public Place"
        }
    ],
    "sg:phone":"+1 928 764 3535",
    "sg:postcode":"86404",
    "sg:province":"AZ",
    "sg:tags":[
        "protection"
    ],
    "wof:name":"Mohave County Sheriffs Office",
    "wof:placetype":"venue"
},
  "geometry": {"coordinates":[-114.366733,34.538884],"type":"Point"}
}