{
  "type": "Feature",
  "properties": {
    "iso:country":"US",
    "sg:address":"1530 E Winged Foot Rd",
    "sg:city":"Phoenix",
    "sg:classifiers":[
        {
            "category":"Wholesale",
            "subcategory":"Durable Goods & Equipment",
            "type":"Manufacturing & Wholesale Goods"
        }
    ],
    "sg:phone":"+1 480 507 8887",
    "sg:postcode":"85022",
    "sg:province":"AZ",
    "sg:tags":[
        "representative",
        "manufacturer"
    ],
    "wof:name":"Levin International Inc",
    "wof:placetype":"venue"
},
  "geometry": {"coordinates":[-112.048629,33.617046],"type":"Point"}
}