{
  "type": "Feature",
  "properties": {
    "iso:country":"US",
    "sg:address":"19044 N 98th Ln",
    "sg:city":"Peoria",
    "sg:classifiers":[
        {
            "category":"Shopping",
            "subcategory":"Catalog Store",
            "type":"Retail Goods"
        }
    ],
    "sg:phone":"+1 623 566 0551",
    "sg:postcode":"85382",
    "sg:province":"AZ",
    "sg:tags":[
        "mail",
        "house"
    ],
    "wof:name":"World of Lugers",
    "wof:placetype":"venue"
},
  "geometry": {"coordinates":[-112.271956,33.656778],"type":"Point"}
}