{
  "type": "Feature",
  "properties": {
    "iso:country":"US",
    "sg:address":"200 N Adot Ln",
    "sg:city":"Winslow",
    "sg:classifiers":[
        {
            "category":"Government",
            "subcategory":"Office",
            "type":"Public Place"
        }
    ],
    "sg:phone":"+1 928 289 4718",
    "sg:postcode":"86047",
    "sg:province":"AZ",
    "sg:tags":[
        "transportation"
    ],
    "wof:name":"Transportation Arizona Dept",
    "wof:placetype":"venue"
},
  "geometry": {"coordinates":[-110.732579,35.036068],"type":"Point"}
}