{
  "type": "Feature",
  "properties": {
    "iso:country":"US",
    "sg:address":"380 N Estrella Pkwy",
    "sg:city":"Goodyear",
    "sg:classifiers":[
        {
            "category":"Building & Trades",
            "subcategory":"Locksmith",
            "type":"Services"
        }
    ],
    "sg:phone":"+1 866 243 2480",
    "sg:postcode":"85338",
    "sg:province":"AZ",
    "sg:tags":[
        "key"
    ],
    "wof:name":"A 1 Emergency Locksmith",
    "wof:placetype":"venue"
},
  "geometry": {"coordinates":[-112.392714,33.457562],"type":"Point"}
}