{
  "type": "Feature",
  "properties": {
    "iso:country":"US",
    "sg:address":"5333 N 7th St Ste B219",
    "sg:city":"Phoenix",
    "sg:classifiers":[
        {
            "category":"Health Services",
            "subcategory":"Doctor",
            "type":"Services"
        }
    ],
    "sg:phone":"+1 602 266 5100",
    "sg:postcode":"85014",
    "sg:province":"AZ",
    "sg:tags":[
        "physician",
        "surgeon",
        "surgeons",
        "surgery-general"
    ],
    "wof:name":"Cardiac &Thoracic Surgery Associates, P.C.",
    "wof:placetype":"venue"
},
  "geometry": {"coordinates":[-112.06500200000001,33.515375],"type":"Point"}
}