{
  "type": "Feature",
  "properties": {
    "iso:country":"US",
    "sg:address":"2835 E Brown Rd Ste 102",
    "sg:city":"Mesa",
    "sg:classifiers":[
        {
            "category":"Health Services",
            "subcategory":"Dentist",
            "type":"Services"
        }
    ],
    "sg:phone":"+1 480 832 3830",
    "sg:postcode":"85213",
    "sg:province":"AZ",
    "sg:tags":[
        "dentists-orthodontists"
    ],
    "wof:name":"Agm Orthodontics",
    "wof:placetype":"venue"
},
  "geometry": {"coordinates":[-111.77018,33.43726],"type":"Point"}
}