{
  "type": "Feature",
  "properties": {
    "iso:country":"US",
    "sg:address":"14019 E Sahuaro Dr",
    "sg:city":"Scottsdale",
    "sg:classifiers":[
        {
            "category":"Professional",
            "subcategory":"Computer Services",
            "type":"Services"
        }
    ],
    "sg:phone":"+1 480 991 9170",
    "sg:postcode":"85259",
    "sg:province":"AZ",
    "sg:tags":[
        "consultant",
        "designer"
    ],
    "wof:name":"Future Trends Technology Mgmt",
    "wof:placetype":"venue"
},
  "geometry": {"coordinates":[-111.777785,33.584949],"type":"Point"}
}