{
  "type": "Feature",
  "properties": {
    "addr:full":"1511 S Country Club Dr Mesa AZ 85210",
    "addr:housenumber":"1511",
    "addr:postcode":"85210",
    "addr:street":"S Country Club Dr",
    "iso:country":"US",
    "sg:address":"1511 S Country Club Dr",
    "sg:city":"Mesa",
    "sg:classifiers":[
        {
            "category":"Travel",
            "subcategory":"Hotels & Motels",
            "type":"Entertainment"
        }
    ],
    "sg:phone":"+1 480 834 0066",
    "sg:postcode":"85210",
    "sg:province":"AZ",
    "sg:website":"www.motel6.com",
    "wof:name":"Motel 6",
    "wof:placetype":"venue"
},
  "geometry": {"coordinates":[-111.839996,33.387501],"type":"Point"}
}