{
  "type": "Feature",
  "properties": {
    "iso:country":"US",
    "sg:address":"4609 N 89th Ln",
    "sg:city":"Phoenix",
    "sg:classifiers":[
        {
            "category":"Home & Garden",
            "subcategory":"Building Materials",
            "type":"Retail Goods"
        }
    ],
    "sg:phone":"+1 623 772 5394",
    "sg:postcode":"85037",
    "sg:province":"AZ",
    "sg:tags":[
        "bathroom",
        "cabinet",
        "fixtures",
        "accessory"
    ],
    "wof:name":"Hi Tech Scale Company",
    "wof:placetype":"venue"
},
  "geometry": {"coordinates":[-112.252473,33.503652],"type":"Point"}
}