{
  "type": "Feature",
  "properties": {
    "iso:country":"US",
    "sg:address":"5250 S Campbell Ave",
    "sg:city":"Tucson",
    "sg:classifiers":[
        {
            "category":"Wholesale",
            "subcategory":"Machinery & Supplies",
            "type":"Manufacturing & Wholesale Goods"
        }
    ],
    "sg:phone":"+1 520 573 9608",
    "sg:postcode":"85706",
    "sg:province":"AZ",
    "sg:tags":[
        "industrial",
        "export"
    ],
    "wof:name":"Abiso Export & Deliveries",
    "wof:placetype":"venue"
},
  "geometry": {"coordinates":[-110.94346400000001,32.157526],"type":"Point"}
}