{
  "type": "Feature",
  "properties": {
    "addr:full":"458 S Lebaron Mesa AZ 85210",
    "addr:housenumber":"458",
    "addr:postcode":"85210",
    "addr:street":"S Lebaron",
    "iso:country":"US",
    "sg:address":"458 S Lebaron",
    "sg:city":"Mesa",
    "sg:classifiers":[
        {
            "category":"Building & Trades",
            "subcategory":"Plumbing",
            "type":"Services"
        }
    ],
    "sg:phone":"+1 480 967 6111",
    "sg:postcode":"85210",
    "sg:province":"AZ",
    "sg:tags":[
        "plumbing",
        "contractor"
    ],
    "sg:website":"www.newcoplumbing.com",
    "wof:name":"Newco Plumbing",
    "wof:placetype":"venue"
},
  "geometry": {"coordinates":[-111.83798299999999,33.405924],"type":"Point"}
}