{
  "type": "Feature",
  "properties": {
    "iso:country":"US",
    "sg:address":"4314 N 7th Ave",
    "sg:city":"Phoenix",
    "sg:classifiers":[
        {
            "category":"Personal",
            "type":"Services"
        }
    ],
    "sg:phone":"+1 623 937 7199",
    "sg:postcode":"85013",
    "sg:province":"AZ",
    "sg:tags":[
        "wear",
        "formal"
    ],
    "wof:name":"Gary's Tux Shop",
    "wof:placetype":"venue"
},
  "geometry": {"coordinates":[-112.083068,33.49888],"type":"Point"}
}