{
  "type": "Feature",
  "properties": {
    "addr:full":"9401 N 17th Way Phoenix AZ 85020",
    "addr:housenumber":"9401",
    "addr:postcode":"85020",
    "addr:street":"N 17Th Way",
    "iso:country":"US",
    "sg:address":"9401 N 17th Way",
    "sg:city":"Phoenix",
    "sg:classifiers":[
        {
            "category":"Shopping",
            "subcategory":"Florist",
            "type":"Retail Goods"
        }
    ],
    "sg:phone":"+1 602 942 2892",
    "sg:postcode":"85020",
    "sg:province":"AZ",
    "wof:name":"Flowers by Marcelle",
    "wof:placetype":"venue"
},
  "geometry": {"coordinates":[-112.04450199999999,33.571201],"type":"Point"}
}