{
  "type": "Feature",
  "properties": {
    "addr:full":"135 S Morris Mesa AZ 85210",
    "addr:housenumber":"135",
    "addr:postcode":"85210",
    "addr:street":"S Morris",
    "iso:country":"US",
    "sg:address":"135 S Morris",
    "sg:city":"Mesa",
    "sg:classifiers":[
        {
            "category":"Building & Trades",
            "subcategory":"Construction",
            "type":"Services"
        }
    ],
    "sg:phone":"+1 480 797 4971",
    "sg:postcode":"85210",
    "sg:province":"AZ",
    "sg:tags":[
        "management"
    ],
    "wof:name":"Ten Investments",
    "wof:placetype":"venue"
},
  "geometry": {"coordinates":[-111.839254,33.412184],"type":"Point"}
}