{
  "type": "Feature",
  "properties": {
    "addr:full":"13821 N 35th Dr Phoenix AZ 85053",
    "addr:housenumber":"13821",
    "addr:postcode":"85053",
    "addr:street":"N 35Th Dr",
    "iso:country":"US",
    "sg:address":"13821 N 35th Dr",
    "sg:city":"Phoenix",
    "sg:classifiers":[
        {
            "category":"Health Services",
            "subcategory":"Doctor",
            "type":"Services"
        }
    ],
    "sg:phone":"+1 602 942 7800",
    "sg:postcode":"85053",
    "sg:province":"AZ",
    "sg:tags":[
        "dentist"
    ],
    "wof:name":"Phoenix Orthodontic Ctr LLC",
    "wof:placetype":"venue"
},
  "geometry": {"coordinates":[-112.13525799999999,33.611072],"type":"Point"}
}