{
  "type": "Feature",
  "properties": {
    "iso:country":"US",
    "sg:address":"751 E Belmont Ave",
    "sg:city":"Phoenix",
    "sg:classifiers":[
        {
            "category":"Professional",
            "subcategory":"Art Services",
            "type":"Services"
        }
    ],
    "sg:phone":"+1 602 944 3286",
    "sg:postcode":"85020",
    "sg:province":"AZ",
    "sg:tags":[
        "photographer"
    ],
    "sg:website":"www.jamescowlin.com",
    "wof:name":"Image Enterprises",
    "wof:placetype":"venue"
},
  "geometry": {"coordinates":[-112.064652,33.54863],"type":"Point"}
}