{
  "type": "Feature",
  "properties": {
    "iso:country":"US",
    "sg:address":"317 S 48th St",
    "sg:city":"Phoenix",
    "sg:classifiers":[
        {
            "category":"Recreation",
            "subcategory":"Picnic Area",
            "type":"Entertainment"
        },
        {
            "category":"Recreation",
            "subcategory":"Go Karts",
            "type":"Entertainment"
        },
        {
            "category":"Sports & Exercise",
            "subcategory":"Race Track",
            "type":"Entertainment"
        }
    ],
    "sg:phone":"+1 866 968 9458",
    "sg:postcode":"85034",
    "sg:province":"AZ",
    "sg:tags":[
        "place",
        "amusement",
        "arcade"
    ],
    "sg:website":"http://www.f1racefactory.com",
    "wof:name":"F1 Race Factory",
    "wof:placetype":"venue"
},
  "geometry": {"coordinates":[-111.978412,33.444397],"type":"Point"}
}