{
  "type": "Feature",
  "properties": {
    "iso:country":"US",
    "sg:address":"1545 E University Dr",
    "sg:city":"Mesa",
    "sg:classifiers":[
        {
            "category":"Health Services",
            "subcategory":"Doctor",
            "type":"Services"
        }
    ],
    "sg:phone":"+1 480 834 9001",
    "sg:postcode":"85203",
    "sg:province":"AZ",
    "sg:tags":[
        "physician",
        "surgery",
        "oral",
        "dentist",
        "surgeons"
    ],
    "sg:website":"http://www.mesaazdentist.com",
    "wof:name":"The Dental Center",
    "wof:placetype":"venue"
},
  "geometry": {"coordinates":[-111.797443,33.422528],"type":"Point"}
}