{
  "type": "Feature",
  "properties": {
    "iso:country":"US",
    "sg:address":"1025 N Arizona Ave",
    "sg:city":"Chandler",
    "sg:classifiers":[
        {
            "category":"Autos & Motor Vehicles",
            "subcategory":"Auto Supplies",
            "type":"Retail Goods"
        }
    ],
    "sg:phone":"+1 480 821 0064",
    "sg:postcode":"85225",
    "sg:province":"AZ",
    "sg:tags":[
        "automotive",
        "parts"
    ],
    "sg:website":"www.autozone.com",
    "wof:name":"Autozone",
    "wof:placetype":"venue"
},
  "geometry": {"coordinates":[-111.84153999999999,33.322394],"type":"Point"}
}