{
  "type": "Feature",
  "properties": {
    "iso:country":"US",
    "sg:address":"680 Main St",
    "sg:city":"Snowflake",
    "sg:classifiers":[
        {
            "category":"Restaurant",
            "type":"Food & Drink"
        }
    ],
    "sg:phone":"+1 928 536 4139",
    "sg:postcode":"85937",
    "sg:province":"AZ",
    "sg:tags":[
        "eating",
        "trailer"
    ],
    "wof:name":"El Rancho Restaurant & Trlr Pk",
    "wof:placetype":"venue"
},
  "geometry": {"coordinates":[-110.091264,34.456828],"type":"Point"}
}