{
  "type": "Feature",
  "properties": {
    "iso:country":"US",
    "sg:address":"8555 S River Pkwy",
    "sg:city":"Tempe",
    "sg:classifiers":[
        {
            "category":"Wholesale",
            "subcategory":"Electrical",
            "type":"Manufacturing & Wholesale Goods"
        }
    ],
    "sg:phone":"+1 480 383 4422",
    "sg:postcode":"85284",
    "sg:province":"AZ",
    "sg:tags":[
        "semiconductor",
        "sales",
        "devices"
    ],
    "wof:name":"Asml US Inc",
    "wof:placetype":"venue"
},
  "geometry": {"coordinates":[-111.899611,33.3382],"type":"Point"}
}