{
  "type": "Feature",
  "properties": {
    "iso:country":"US",
    "sg:address":"501 W Van Buren St Ste O",
    "sg:city":"Avondale",
    "sg:classifiers":[
        {
            "category":"Building & Trades",
            "subcategory":"Construction",
            "type":"Services"
        }
    ],
    "sg:phone":"+1 623 535 4201",
    "sg:postcode":"85323",
    "sg:province":"AZ",
    "sg:tags":[
        "altering",
        "consultant",
        "remodeling",
        "contractor"
    ],
    "wof:name":"Arizona Pipemasters Inc",
    "wof:placetype":"venue"
},
  "geometry": {"coordinates":[-112.353293,33.449823],"type":"Point"}
}