{
  "type": "Feature",
  "properties": {
    "addr:full":"10439 W Royal Palm Rd Peoria AZ 85345",
    "addr:housenumber":"10439",
    "addr:postcode":"85345",
    "addr:street":"W Royal Palm Rd",
    "iso:country":"US",
    "sg:address":"10439 W Royal Palm Rd",
    "sg:city":"Peoria",
    "sg:classifiers":[
        {
            "category":"Professional",
            "type":"Services"
        }
    ],
    "sg:phone":"+1 623 876 8168",
    "sg:postcode":"85345",
    "sg:province":"AZ",
    "sg:tags":[
        "editorial"
    ],
    "sg:website":"www.ossweb.com",
    "wof:name":"Office Support Svc",
    "wof:placetype":"venue"
},
  "geometry": {"coordinates":[-112.286061,33.553228],"type":"Point"}
}