{
  "type": "Feature",
  "properties": {
    "iso:country":"US",
    "sg:address":"14988 N 78th Way",
    "sg:city":"Scottsdale",
    "sg:classifiers":[
        {
            "category":"Professional",
            "subcategory":"Computer Services",
            "type":"Services"
        }
    ],
    "sg:phone":"+1 623 707 1600",
    "sg:postcode":"85260",
    "sg:province":"AZ",
    "sg:tags":[
        "website",
        "design"
    ],
    "sg:website":"www.interactivesites.com",
    "wof:name":"Interactive Sites",
    "wof:placetype":"venue"
},
  "geometry": {"coordinates":[-111.906871,33.622632],"type":"Point"}
}