{
  "type": "Feature",
  "properties": {
    "iso:country":"US",
    "sg:address":"5343 W Desert Hills Dr",
    "sg:city":"Glendale",
    "sg:classifiers":[
        {
            "category":"Retail",
            "subcategory":"Repair Shop",
            "type":"Services"
        }
    ],
    "sg:phone":"+1 623 878 7788",
    "sg:postcode":"85304",
    "sg:province":"AZ",
    "sg:tags":[
        "tile",
        "grout",
        "restoration",
        "cleaning"
    ],
    "wof:name":"All Stone Tile & Wood Rstrtn",
    "wof:placetype":"venue"
},
  "geometry": {"coordinates":[-112.17389799999999,33.594735],"type":"Point"}
}