{
  "type": "Feature",
  "properties": {
    "iso:country":"US",
    "sg:address":"16879 N 75th Ave",
    "sg:city":"Peoria",
    "sg:classifiers":[
        {
            "category":"Utilities",
            "subcategory":"Mobile Phone",
            "type":"Services"
        }
    ],
    "sg:phone":"+1 623 412 5500",
    "sg:postcode":"85382",
    "sg:province":"AZ",
    "sg:tags":[
        "communication",
        "radiotelephone"
    ],
    "wof:name":"2 B Wireless",
    "wof:placetype":"venue"
},
  "geometry": {"coordinates":[-112.220245,33.637978],"type":"Point"}
}