{
  "type": "Feature",
  "properties": {
    "iso:country":"US",
    "sg:address":"780 E Ponderosa Pkwy",
    "sg:city":"Flagstaff",
    "sg:classifiers":[
        {
            "category":"Landmark",
            "subcategory":"Tourist Information",
            "type":"Public Place"
        },
        {
            "category":"Landmark",
            "subcategory":"Tourist Attraction",
            "type":"Public Place"
        }
    ],
    "sg:phone":"+1 928 779 1614",
    "sg:postcode":"86001",
    "sg:province":"AZ",
    "sg:tags":[
        "tour",
        "promoter",
        "tours-operators",
        "sightseeing"
    ],
    "wof:name":"Grand Canyon Hikes",
    "wof:placetype":"venue"
},
  "geometry": {"coordinates":[-111.636049,35.203593],"type":"Point"}
}