{
  "type": "Feature",
  "properties": {
    "iso:country":"US",
    "sg:address":"9746 N 90th St",
    "sg:city":"Scottsdale",
    "sg:classifiers":[
        {
            "category":"Health Services",
            "subcategory":"Doctor",
            "type":"Services"
        }
    ],
    "sg:phone":"+1 480 614 8000",
    "sg:postcode":"85258",
    "sg:province":"AZ",
    "sg:tags":[
        "dentist"
    ],
    "wof:name":"Desert Dental Solutions",
    "wof:placetype":"venue"
},
  "geometry": {"coordinates":[-111.8862,33.574673],"type":"Point"}
}