{
  "type": "Feature",
  "properties": {
    "iso:country":"US",
    "sg:address":"8607 N 59th Ave",
    "sg:city":"Glendale",
    "sg:classifiers":[
        {
            "category":"Professional",
            "subcategory":"Detective & Security Services",
            "type":"Services"
        },
        {
            "category":"Shopping",
            "subcategory":"Computers & Home Electronics",
            "type":"Retail Goods"
        }
    ],
    "sg:phone":"+1 602 714 2429",
    "sg:postcode":"85302",
    "sg:province":"AZ",
    "sg:tags":[
        "control",
        "monitoring",
        "consultant",
        "system",
        "surveillance",
        "equipment"
    ],
    "sg:website":"http://www.protectyourhome.com/Arizona/Glendale.aspx?subid=GlendaleAZ&cpao=150&cpca=yellowpages&kw=GlendaleAZ",
    "wof:name":"Glendale ADT Authorized Security Dealer - Protect Your Home",
    "wof:placetype":"venue"
},
  "geometry": {"coordinates":[-112.186258,33.561705],"type":"Point"}
}