{
  "type": "Feature",
  "properties": {
    "addr:full":"61 N 8th St Show Low AZ 85901",
    "addr:housenumber":"61",
    "addr:postcode":"85901",
    "addr:street":"N 8Th St",
    "iso:country":"US",
    "sg:address":"61 N 8th St",
    "sg:city":"Show Low",
    "sg:classifiers":[
        {
            "category":"Building & Trades",
            "subcategory":"Cleaning & Sanitation",
            "type":"Services"
        }
    ],
    "sg:phone":"+1 928 537 4682",
    "sg:postcode":"85901",
    "sg:province":"AZ",
    "sg:tags":[
        "janitor"
    ],
    "wof:name":"Baird Janitor Svc",
    "wof:placetype":"venue"
},
  "geometry": {"coordinates":[-110.033644,34.249809],"type":"Point"}
}