{
  "type": "Feature",
  "properties": {
    "addr:full":"723 W Commerce Ave Ste 3C Gilbert AZ 85233",
    "addr:housenumber":"723",
    "addr:postcode":"85233",
    "addr:street":"W Commerce Ave Ste 3C",
    "iso:country":"US",
    "sg:address":"723 W Commerce Ave Ste 3C",
    "sg:city":"Gilbert",
    "sg:classifiers":[
        {
            "category":"Utilities",
            "subcategory":"Natural Gas",
            "type":"Services"
        }
    ],
    "sg:phone":"+1 480 892 6605",
    "sg:postcode":"85233",
    "sg:province":"AZ",
    "sg:tags":[
        "carburetor"
    ],
    "wof:name":"Fuel Systems Specialists",
    "wof:placetype":"venue"
},
  "geometry": {"coordinates":[-111.80572100000001,33.358186],"type":"Point"}
}