{
  "type": "Feature",
  "properties": {
    "iso:country":"US",
    "sg:address":"16090 N Vernon Dr",
    "sg:city":"Tucson",
    "sg:classifiers":[
        {
            "category":"Social Services",
            "subcategory":"Child Care",
            "type":"Services"
        }
    ],
    "sg:phone":"+1 520 818 2305",
    "sg:postcode":"85739",
    "sg:province":"AZ",
    "sg:tags":[
        "day"
    ],
    "wof:name":"Los Ninos Day Care of Catalina Llc",
    "wof:placetype":"venue"
},
  "geometry": {"coordinates":[-110.920517,32.498613],"type":"Point"}
}