{
  "type": "Feature",
  "properties": {
    "iso:country":"US",
    "sg:address":"955 W Chandler Boulevard",
    "sg:city":"Chandler",
    "sg:classifiers":[
        {
            "category":"Building & Trades",
            "subcategory":"Pest Control",
            "type":"Services"
        }
    ],
    "sg:phone":"+1 480 963 4769",
    "sg:postcode":"85225",
    "sg:province":"AZ",
    "wof:name":"Valley East Pest Control",
    "wof:placetype":"venue"
},
  "geometry": {"coordinates":[-111.857902,33.305938],"type":"Point"}
}