{
  "type": "Feature",
  "properties": {
    "iso:country":"US",
    "sg:address":"5775 W Bell Rd",
    "sg:city":"Glendale",
    "sg:classifiers":[
        {
            "category":"Restaurant",
            "type":"Food & Drink"
        }
    ],
    "sg:menulink":"http://www.allmenus.com/az/phoenix/26392-indian-maharaja-palace/menu/",
    "sg:phone":"+1 602 547 1000",
    "sg:postcode":"85308",
    "sg:province":"AZ",
    "sg:tags":[
        "indian",
        "asian"
    ],
    "wof:name":"Indian Maharaja Palace",
    "wof:placetype":"venue"
},
  "geometry": {"coordinates":[-112.183646,33.638679],"type":"Point"}
}