{
  "type": "Feature",
  "properties": {
    "iso:country":"US",
    "sg:address":"10418 E Dolphin Ave",
    "sg:city":"Mesa",
    "sg:classifiers":[
        {
            "category":"Building & Trades",
            "subcategory":"Construction",
            "type":"Services"
        }
    ],
    "sg:phone":"+1 480 250 8633",
    "sg:postcode":"85208",
    "sg:province":"AZ",
    "sg:tags":[
        "hanging",
        "contractor"
    ],
    "wof:name":"Valleys Premier Painting LLC",
    "wof:placetype":"venue"
},
  "geometry": {"coordinates":[-111.604491,33.40106],"type":"Point"}
}