{
  "type": "Feature",
  "properties": {
    "iso:country":"US",
    "sg:address":"1327 W Mulberry Dr",
    "sg:city":"Phoenix",
    "sg:classifiers":[
        {
            "category":"Professional",
            "type":"Services"
        }
    ],
    "sg:phone":"+1 602 277 5505",
    "sg:postcode":"85013",
    "sg:province":"AZ",
    "wof:name":"Sheldon Pensinger",
    "wof:placetype":"venue"
},
  "geometry": {"coordinates":[-112.09082600000001,33.486757],"type":"Point"}
}