{
  "type": "Feature",
  "properties": {
    "addr:full":"3170 Hwy 95 Bullhead City AZ 86442",
    "addr:housenumber":"3170",
    "addr:postcode":"86442",
    "addr:street":"Hwy 95",
    "iso:country":"US",
    "sg:address":"3170 Hwy 95",
    "sg:city":"Bullhead City",
    "sg:classifiers":[
        {
            "category":"Building & Trades",
            "subcategory":"Construction",
            "type":"Services"
        },
        {
            "category":"Home & Garden",
            "subcategory":"Furniture",
            "type":"Retail Goods"
        }
    ],
    "sg:phone":"+1 928 763 9307",
    "sg:postcode":"86442",
    "sg:province":"AZ",
    "sg:tags":[
        "cabinet",
        "carpentry",
        "contractor"
    ],
    "wof:name":"Design Centre",
    "wof:placetype":"venue"
},
  "geometry": {"coordinates":[-114.58988600000001,35.070753],"type":"Point"}
}