{
  "type": "Feature",
  "properties": {
    "iso:country":"US",
    "sg:address":"1245 E Curry Rd",
    "sg:city":"Tempe",
    "sg:classifiers":[
        {
            "category":"Retail",
            "subcategory":"Auto Repair",
            "type":"Services"
        }
    ],
    "sg:phone":"+1 480 966 6061",
    "sg:postcode":"85281",
    "sg:province":"AZ",
    "sg:tags":[
        "general",
        "supply"
    ],
    "wof:name":"Elite Auto Parts & Machine",
    "wof:placetype":"venue"
},
  "geometry": {"coordinates":[-111.918192,33.440311],"type":"Point"}
}