{
  "type": "Feature",
  "properties": {
    "iso:country":"US",
    "sg:address":"5358 S Nogales Hwy",
    "sg:city":"Tucson",
    "sg:classifiers":[
        {
            "category":"Restaurant",
            "type":"Food & Drink"
        }
    ],
    "sg:phone":"+1 520 807 5600",
    "sg:postcode":"85706",
    "sg:province":"AZ",
    "wof:name":"Parrilla Del Rey",
    "wof:placetype":"venue"
},
  "geometry": {"coordinates":[-110.962683,32.151127],"type":"Point"}
}