{
  "type": "Feature",
  "properties": {
    "iso:country":"US",
    "sg:address":"756 S Gilbert Rd Ste 102",
    "sg:city":"Gilbert",
    "sg:classifiers":[
        {
            "category":"Fast Food",
            "type":"Food & Drink"
        },
        {
            "category":"Restaurant",
            "type":"Food & Drink"
        },
        {
            "category":"Food & Beverages",
            "subcategory":"Groceries & Convenience Stores",
            "type":"Retail Goods"
        }
    ],
    "sg:phone":"+1 480 892 4910",
    "sg:postcode":"85296",
    "sg:province":"AZ",
    "sg:tags":[
        "shop",
        "american",
        "sandwich",
        "take"
    ],
    "sg:website":"http://www.subway.com",
    "wof:name":"Subway",
    "wof:placetype":"venue"
},
  "geometry": {"coordinates":[-111.790037,33.335821],"type":"Point"}
}