{
  "type": "Feature",
  "properties": {
    "iso:country":"US",
    "sg:address":"13974 W Van Buren St",
    "sg:city":"Goodyear",
    "sg:classifiers":[
        {
            "category":"Autos & Motor Vehicles",
            "subcategory":"Motorcycle Sales",
            "type":"Retail Goods"
        }
    ],
    "sg:phone":"+1 623 486 7082",
    "sg:postcode":"85338",
    "sg:province":"AZ",
    "wof:name":"Ricochet Motor Sports",
    "wof:placetype":"venue"
},
  "geometry": {"coordinates":[-112.360902,33.449914],"type":"Point"}
}