{
  "type": "Feature",
  "properties": {
    "addr:full":"415 E Andy Devine Ave Kingman AZ 86401",
    "addr:housenumber":"415",
    "addr:postcode":"86401",
    "addr:street":"E Andy Devine Ave",
    "iso:country":"US",
    "sg:address":"415 E Andy Devine Ave",
    "sg:city":"Kingman",
    "sg:classifiers":[
        {
            "category":"Utilities",
            "subcategory":"Telephone",
            "type":"Services"
        }
    ],
    "sg:phone":"+1 928 753 1122",
    "sg:postcode":"86401",
    "sg:province":"AZ",
    "sg:tags":[
        "company"
    ],
    "wof:name":"Citizens Utilities Co",
    "wof:placetype":"venue"
},
  "geometry": {"coordinates":[-114.05282699999999,35.188658],"type":"Point"}
}