{
  "type": "Feature",
  "properties": {
    "iso:country":"US",
    "sg:address":"11356 E San Juanito Pl",
    "sg:city":"Tucson",
    "sg:classifiers":[
        {
            "category":"Organizations",
            "subcategory":"Religious Organization",
            "type":"Services"
        }
    ],
    "sg:phone":"+1 520 749 5314",
    "sg:postcode":"85749",
    "sg:province":"AZ",
    "sg:tags":[
        "church"
    ],
    "wof:name":"Church Of Jesus Christ Of Lds",
    "wof:placetype":"venue"
},
  "geometry": {"coordinates":[-110.749979,32.270837],"type":"Point"}
}