{
  "type": "Feature",
  "properties": {
    "iso:country":"US",
    "sg:address":"4008 E Lariat Ln",
    "sg:city":"Phoenix",
    "sg:classifiers":[
        {
            "category":"Professional",
            "type":"Services"
        },
        {
            "category":"Professional",
            "subcategory":"Advertising",
            "type":"Services"
        }
    ],
    "sg:phone":"+1 480 585 7735",
    "sg:postcode":"85050",
    "sg:province":"AZ",
    "sg:tags":[
        "product",
        "fair",
        "trade",
        "exposition",
        "advertising-promotional",
        "shows"
    ],
    "sg:website":"http://www.eweniquepromotions.com",
    "wof:name":"Tyton Enterprises",
    "wof:placetype":"venue"
},
  "geometry": {"coordinates":[-111.99593900000001,33.722244],"type":"Point"}
}