{
  "type": "Feature",
  "properties": {
    "iso:country":"US",
    "sg:address":"2022 W Mulberry Dr",
    "sg:city":"Phoenix",
    "sg:classifiers":[
        {
            "category":"Building & Trades",
            "subcategory":"Landscaping Services",
            "type":"Services"
        }
    ],
    "sg:phone":"+1 602 486 0221",
    "sg:postcode":"85015",
    "sg:province":"AZ",
    "sg:tags":[
        "lawn"
    ],
    "wof:name":"American Landscape",
    "wof:placetype":"venue"
},
  "geometry": {"coordinates":[-112.102125,33.486747],"type":"Point"}
}