{
  "type": "Feature",
  "properties": {
    "iso:country":"US",
    "sg:address":"2231 Golden Gate Ave",
    "sg:city":"Kingman",
    "sg:classifiers":[
        {
            "category":"Freight",
            "type":"Transportation"
        }
    ],
    "sg:phone":"+1 928 718 1526",
    "sg:postcode":"86401",
    "sg:province":"AZ",
    "sg:tags":[
        "operator",
        "local",
        "trucking"
    ],
    "wof:name":"Arizona Regional Area Trucking",
    "wof:placetype":"venue"
},
  "geometry": {"coordinates":[-114.025363,35.206818],"type":"Point"}
}