{
  "type": "Feature",
  "properties": {
    "addr:full":"1616 S Stapley Dr Mesa AZ 85204",
    "addr:housenumber":"1616",
    "addr:postcode":"85204",
    "addr:street":"S Stapley Dr",
    "iso:country":"US",
    "sg:address":"1616 S Stapley Dr",
    "sg:city":"Mesa",
    "sg:classifiers":[
        {
            "category":"Personal",
            "subcategory":"Barber",
            "type":"Services"
        }
    ],
    "sg:phone":"+1 480 632 1729",
    "sg:postcode":"85204",
    "sg:province":"AZ",
    "wof:name":"B's Barbershop",
    "wof:placetype":"venue"
},
  "geometry": {"coordinates":[-111.805809,33.385212],"type":"Point"}
}