{
  "type": "Feature",
  "properties": {
    "addr:full":"5445 E 22nd St Tucson AZ 85711",
    "addr:housenumber":"5445",
    "addr:postcode":"85711",
    "addr:street":"E 22Nd St",
    "iso:country":"US",
    "sg:address":"5445 E 22nd St",
    "sg:city":"Tucson",
    "sg:classifiers":[
        {
            "category":"Insurance",
            "subcategory":"Insurance Agent",
            "type":"Services"
        }
    ],
    "sg:phone":"+1 520 747 4223",
    "sg:postcode":"85711",
    "sg:province":"AZ",
    "sg:tags":[
        "agency"
    ],
    "wof:name":"Geico",
    "wof:placetype":"venue"
},
  "geometry": {"coordinates":[-110.875812,32.206972],"type":"Point"}
}