{
  "type": "Feature",
  "properties": {
    "addr:full":"10613 N Hayden Rd Suite J-103 Scottsdale AZ 85260",
    "addr:housenumber":"10613",
    "addr:postcode":"85260",
    "addr:street":"N Hayden Rd Suite J-103",
    "iso:country":"US",
    "sg:address":"10613 N Hayden Rd Suite J-103",
    "sg:city":"Scottsdale",
    "sg:classifiers":[
        {
            "category":"Health Services",
            "subcategory":"Health Practitioner",
            "type":"Services"
        }
    ],
    "sg:phone":"+1 480 991 9400",
    "sg:postcode":"85260",
    "sg:province":"AZ",
    "sg:tags":[
        "addiction",
        "abuse",
        "drug"
    ],
    "sg:website":"http://www.thegetwellcenter.com",
    "wof:name":"Get Well Center",
    "wof:placetype":"venue"
},
  "geometry": {"coordinates":[-111.908737,33.583851],"type":"Point"}
}