{
  "type": "Feature",
  "properties": {
    "addr:full":"503 E Allen St Tombstone AZ 85638",
    "addr:housenumber":"503",
    "addr:postcode":"85638",
    "addr:street":"E Allen St",
    "iso:country":"US",
    "sg:address":"503 E Allen St",
    "sg:city":"Tombstone",
    "sg:classifiers":[
        {
            "category":"Shopping",
            "subcategory":"Clothing, Apparel, & Fashions",
            "type":"Retail Goods"
        }
    ],
    "sg:phone":"+1 520 457 3465",
    "sg:postcode":"85638",
    "sg:province":"AZ",
    "sg:tags":[
        "western"
    ],
    "wof:name":"Branding Iron",
    "wof:placetype":"venue"
},
  "geometry": {"coordinates":[-110.066063,31.712265],"type":"Point"}
}