{
  "type": "Feature",
  "properties": {
    "iso:country":"US",
    "sg:address":"503 E Allen St",
    "sg:city":"Tombstone",
    "sg:classifiers":[
        {
            "category":"Shopping",
            "subcategory":"Clothing, Apparel, & Fashions",
            "type":"Retail Goods"
        }
    ],
    "sg:phone":"+1 520 457 3465",
    "sg:postcode":"85638",
    "sg:province":"AZ",
    "sg:tags":[
        "western"
    ],
    "wof:name":"Branding Iron",
    "wof:placetype":"venue"
},
  "geometry": {"coordinates":[-110.066063,31.712265],"type":"Point"}
}