{
  "type": "Feature",
  "properties": {
    "iso:country":"US",
    "sg:address":"9124 E Apache Trl",
    "sg:city":"Mesa",
    "sg:classifiers":[
        {
            "category":"Personal",
            "subcategory":"Beauty Salon",
            "type":"Services"
        }
    ],
    "sg:phone":"+1 480 358 1877",
    "sg:postcode":"85207",
    "sg:province":"AZ",
    "sg:tags":[
        "manicuring"
    ],
    "wof:name":"Bamboo Nails",
    "wof:placetype":"venue"
},
  "geometry": {"coordinates":[-111.635692,33.415203],"type":"Point"}
}