{
  "type": "Feature",
  "properties": {
    "addr:full":"902 N 17th Ave Phoenix AZ 85007",
    "addr:housenumber":"902",
    "addr:postcode":"85007",
    "addr:street":"N 17Th Ave",
    "iso:country":"US",
    "sg:address":"902 N 17th Ave",
    "sg:city":"Phoenix",
    "sg:classifiers":[
        {
            "category":"Manufacturing",
            "subcategory":"Signs",
            "type":"Manufacturing & Wholesale Goods"
        }
    ],
    "sg:phone":"+1 602 254 0203",
    "sg:postcode":"85007",
    "sg:province":"AZ",
    "sg:tags":[
        "specialty",
        "mfg"
    ],
    "wof:name":"Exhibitec",
    "wof:placetype":"venue"
},
  "geometry": {"coordinates":[-112.09570600000001,33.458608],"type":"Point"}
}