{
  "type": "Feature",
  "properties": {
    "addr:full":"1305 S Gilbert Road Gilbert AZ 85296",
    "addr:housenumber":"1305",
    "addr:postcode":"85296",
    "addr:street":"S Gilbert Road",
    "iso:country":"US",
    "sg:address":"1305 S Gilbert Road",
    "sg:city":"Gilbert",
    "sg:classifiers":[
        {
            "category":"Social Services",
            "subcategory":"Child Care",
            "type":"Services"
        },
        {
            "category":"Education",
            "subcategory":"Special Training",
            "type":"Public Place"
        },
        {
            "category":"Education",
            "subcategory":"Preschool",
            "type":"Public Place"
        },
        {
            "category":"Education",
            "subcategory":"School",
            "type":"Public Place"
        }
    ],
    "sg:phone":"+1 480 899 6877",
    "sg:postcode":"85296",
    "sg:province":"AZ",
    "sg:tags":[
        "high",
        "middle",
        "specialty",
        "elementary",
        "day"
    ],
    "wof:name":"Rancho Solano Private Schools",
    "wof:placetype":"venue"
},
  "geometry": {"coordinates":[-111.789615,33.326181],"type":"Point"}
}