{
  "type": "Feature",
  "properties": {
    "iso:country":"US",
    "sg:address":"3909 N Pomona Rd",
    "sg:city":"Tucson",
    "sg:classifiers":[
        {
            "category":"Shopping",
            "subcategory":"Computers & Home Electronics",
            "type":"Retail Goods"
        }
    ],
    "sg:phone":"+1 520 515 6119",
    "sg:postcode":"85705",
    "sg:province":"AZ",
    "wof:name":"Arm Computers",
    "wof:placetype":"venue"
},
  "geometry": {"coordinates":[-110.999283,32.278684],"type":"Point"}
}