{
  "type": "Feature",
  "properties": {
    "iso:country":"US",
    "sg:address":"5214 E Alberta Dr",
    "sg:city":"Tucson",
    "sg:classifiers":[
        {
            "category":"Building & Trades",
            "subcategory":"Electrical",
            "type":"Services"
        }
    ],
    "sg:phone":"+1 520 403 3533",
    "sg:postcode":"85711",
    "sg:province":"AZ",
    "sg:tags":[
        "electric",
        "contractor"
    ],
    "wof:name":"David Lawrence Electrical Entr",
    "wof:placetype":"venue"
},
  "geometry": {"coordinates":[-110.881168,32.224876],"type":"Point"}
}