{
  "type": "Feature",
  "properties": {
    "iso:country":"US",
    "sg:address":"4013 N 75th Ave",
    "sg:city":"Phoenix",
    "sg:classifiers":[
        {
            "category":"Banks & Credit Unions",
            "subcategory":"Bank",
            "type":"Services"
        }
    ],
    "sg:phone":"+1 623 247 1363",
    "sg:postcode":"85033",
    "sg:province":"AZ",
    "sg:tags":[
        "cashing",
        "check"
    ],
    "wof:name":"A A Check Cashing",
    "wof:placetype":"venue"
},
  "geometry": {"coordinates":[-112.220478,33.493601],"type":"Point"}
}