{
  "type": "Feature",
  "properties": {
    "iso:country":"US",
    "sg:address":"1903 E Kentucky Ln",
    "sg:city":"Tempe",
    "sg:classifiers":[
        {
            "category":"Building & Trades",
            "subcategory":"Construction",
            "type":"Services"
        }
    ],
    "sg:phone":"+1 480 777 9797",
    "sg:postcode":"85284",
    "sg:province":"AZ",
    "sg:tags":[
        "roofing",
        "contractor"
    ],
    "wof:name":"Roofing Experts Inc",
    "wof:placetype":"venue"
},
  "geometry": {"coordinates":[-111.905318,33.342269],"type":"Point"}
}