{
  "type": "Feature",
  "properties": {
    "iso:country":"US",
    "sg:address":"111 N 32nd St",
    "sg:city":"Phoenix",
    "sg:classifiers":[
        {
            "category":"Building & Trades",
            "subcategory":"Construction",
            "type":"Services"
        }
    ],
    "sg:phone":"+1 602 267 7385",
    "sg:postcode":"85034",
    "sg:province":"AZ",
    "sg:tags":[
        "fencing",
        "contractor"
    ],
    "wof:name":"United Fence Company Inc",
    "wof:placetype":"venue"
},
  "geometry": {"coordinates":[-112.01282500000001,33.450154],"type":"Point"}
}