{
  "type": "Feature",
  "properties": {
    "iso:country":"US",
    "sg:address":"1819 E Morten Ave",
    "sg:city":"Phoenix",
    "sg:classifiers":[
        {
            "category":"Real Estate",
            "subcategory":"Real Estate Agent",
            "type":"Services"
        }
    ],
    "sg:phone":"+1 602 997 7324",
    "sg:postcode":"85020",
    "sg:province":"AZ",
    "sg:website":"www.realtyexecutives.com",
    "wof:name":"Realty Executives",
    "wof:placetype":"venue"
},
  "geometry": {"coordinates":[-112.042231,33.545549],"type":"Point"}
}