{
  "type": "Feature",
  "properties": {
    "iso:country":"US",
    "sg:address":"367 S Arizona Ave",
    "sg:city":"Chandler",
    "sg:classifiers":[
        {
            "category":"Home & Garden",
            "subcategory":"Building Materials",
            "type":"Retail Goods"
        }
    ],
    "sg:phone":"+1 480 732 9360",
    "sg:postcode":"85225",
    "sg:province":"AZ",
    "sg:tags":[
        "screen",
        "window",
        "door",
        "security"
    ],
    "wof:name":"Screen Co By Penny",
    "wof:placetype":"venue"
},
  "geometry": {"coordinates":[-111.84146,33.298293],"type":"Point"}
}