{
  "type": "Feature",
  "properties": {
    "addr:full":"1402 S 27th Ave Phoenix AZ 85009",
    "addr:housenumber":"1402",
    "addr:postcode":"85009",
    "addr:street":"S 27Th Ave",
    "iso:country":"US",
    "sg:address":"1402 S 27th Ave",
    "sg:city":"Phoenix",
    "sg:classifiers":[
        {
            "category":"Building & Trades",
            "subcategory":"Construction",
            "type":"Services"
        }
    ],
    "sg:phone":"+1 602 415 1750",
    "sg:postcode":"85009",
    "sg:province":"AZ",
    "sg:tags":[
        "residential",
        "commercial",
        "contractor"
    ],
    "wof:name":"Femcon Inc",
    "wof:placetype":"venue"
},
  "geometry": {"coordinates":[-112.117255,33.434285],"type":"Point"}
}