{
  "type": "Feature",
  "properties": {
    "iso:country":"US",
    "sg:address":"345 W State Ave",
    "sg:city":"Phoenix",
    "sg:classifiers":[
        {
            "category":"Professional",
            "subcategory":"Management & Consulting",
            "type":"Services"
        }
    ],
    "sg:phone":"+1 602 997 8297",
    "sg:postcode":"85021",
    "sg:province":"AZ",
    "sg:tags":[
        "shopping",
        "sale",
        "direct",
        "online",
        "mail",
        "retail",
        "order"
    ],
    "wof:name":"Schwarz Enterprises Inc",
    "wof:placetype":"venue"
},
  "geometry": {"coordinates":[-112.079213,33.544211],"type":"Point"}
}