{
  "type": "Feature",
  "properties": {
    "iso:country":"US",
    "sg:address":"2039 W Windsor Ave",
    "sg:city":"Phoenix",
    "sg:classifiers":[
        {
            "category":"Social Services",
            "type":"Services"
        }
    ],
    "sg:phone":"+1 602 252 6342",
    "sg:postcode":"85009",
    "sg:province":"AZ",
    "sg:tags":[
        "worker"
    ],
    "wof:name":"Linda Pace Cisw",
    "wof:placetype":"venue"
},
  "geometry": {"coordinates":[-112.103089,33.4789],"type":"Point"}
}