{
  "type": "Feature",
  "properties": {
    "addr:full":"115 S Candy Ln Cottonwood AZ 86326",
    "addr:housenumber":"115",
    "addr:postcode":"86326",
    "addr:street":"S Candy Ln",
    "iso:country":"US",
    "sg:address":"115 S Candy Ln",
    "sg:city":"Cottonwood",
    "sg:classifiers":[
        {
            "category":"Shopping",
            "type":"Retail Goods"
        }
    ],
    "sg:phone":"+1 928 634 0566",
    "sg:postcode":"86326",
    "sg:province":"AZ",
    "sg:tags":[
        "hearing",
        "equipment",
        "supply",
        "impaired"
    ],
    "wof:name":"Beltone Hearing Aid Ctr",
    "wof:placetype":"venue"
},
  "geometry": {"coordinates":[-112.03099899999999,34.73776],"type":"Point"}
}