{
  "type": "Feature",
  "properties": {
    "iso:country":"US",
    "sg:address":"6539 E Mission St",
    "sg:city":"Yuma",
    "sg:classifiers":[
        {
            "category":"Professional",
            "subcategory":"Management & Consulting",
            "type":"Services"
        },
        {
            "category":"Professional",
            "subcategory":"Advertising",
            "type":"Services"
        }
    ],
    "sg:phone":"+1 602 549 2004",
    "sg:postcode":"85365",
    "sg:province":"AZ",
    "sg:tags":[
        "marketing",
        "program",
        "consultant"
    ],
    "wof:name":"Web Riders, Inc",
    "wof:placetype":"venue"
},
  "geometry": {"coordinates":[-114.520614,32.689739],"type":"Point"}
}