{
  "type": "Feature",
  "properties": {
    "iso:country":"US",
    "sg:address":"899 E Silverlake Rd",
    "sg:city":"Tucson",
    "sg:classifiers":[
        {
            "category":"Airline",
            "type":"Transportation"
        }
    ],
    "sg:phone":"+1 520 205 4810",
    "sg:postcode":"85713",
    "sg:province":"AZ",
    "sg:tags":[
        "courier",
        "air"
    ],
    "wof:name":"UPS",
    "wof:placetype":"venue"
},
  "geometry": {"coordinates":[-110.95921,32.199599],"type":"Point"}
}