{
  "type": "Feature",
  "properties": {
    "iso:country":"US",
    "sg:address":"1201 E Hall St",
    "sg:city":"Show Low",
    "sg:classifiers":[
        {
            "category":"Food & Beverages",
            "subcategory":"Groceries & Convenience Stores",
            "type":"Retail Goods"
        }
    ],
    "sg:phone":"+1 928 537 1453",
    "sg:postcode":"85901",
    "sg:province":"AZ",
    "sg:tags":[
        "house",
        "coffee"
    ],
    "wof:name":"High In Pines Deli & Cof",
    "wof:placetype":"venue"
},
  "geometry": {"coordinates":[-110.029372,34.25163],"type":"Point"}
}