{
  "type": "Feature",
  "properties": {
    "addr:full":"141 E Fort Lowell Rd Tucson AZ 85705",
    "addr:housenumber":"141",
    "addr:postcode":"85705",
    "addr:street":"E Fort Lowell Rd",
    "iso:country":"US",
    "sg:address":"141 E Fort Lowell Rd",
    "sg:city":"Tucson",
    "sg:classifiers":[
        {
            "category":"Retail",
            "subcategory":"Veterinary Services",
            "type":"Services"
        }
    ],
    "sg:phone":"+1 520 888 3177",
    "sg:postcode":"85705",
    "sg:province":"AZ",
    "sg:tags":[
        "veterinarian"
    ],
    "sg:website":"www.southernazvets.com",
    "wof:name":"Southern Arizona Veterinary",
    "wof:placetype":"venue"
},
  "geometry": {"coordinates":[-110.97124100000001,32.26482],"type":"Point"}
}