{
  "type": "Feature",
  "properties": {
    "iso:country":"US",
    "sg:address":"8853 N 78th Ave",
    "sg:city":"Peoria",
    "sg:phone":"+1 623 935 4878",
    "sg:postcode":"85345",
    "sg:province":"AZ",
    "sg:website":"http://www.teacherlynda.com",
    "wof:name":"Teacher Lynda's Swim School",
    "wof:placetype":"venue"
},
  "geometry": {"coordinates":[-112.227249,33.564276],"type":"Point"}
}