{
  "type": "Feature",
  "properties": {
    "iso:country":"US",
    "sg:address":"12801 E Gold Dust Ave",
    "sg:city":"Scottsdale",
    "sg:classifiers":[
        {
            "category":"Building & Trades",
            "subcategory":"Plumbing",
            "type":"Services"
        }
    ],
    "sg:phone":"+1 480 451 8282",
    "sg:postcode":"85259",
    "sg:province":"AZ",
    "sg:tags":[
        "contractor"
    ],
    "wof:name":"CMC Plumbing Master",
    "wof:placetype":"venue"
},
  "geometry": {"coordinates":[-111.804706,33.578756],"type":"Point"}
}