{
  "type": "Feature",
  "properties": {
    "iso:country":"US",
    "sg:address":"4014 E Pima St",
    "sg:city":"Tucson",
    "sg:classifiers":[
        {
            "category":"Social Services",
            "subcategory":"Adult Care",
            "type":"Services"
        }
    ],
    "sg:phone":"+1 520 325 7327",
    "sg:postcode":"85712",
    "sg:province":"AZ",
    "sg:tags":[
        "home",
        "residential"
    ],
    "wof:name":"Plum Tree Home",
    "wof:placetype":"venue"
},
  "geometry": {"coordinates":[-110.90686700000001,32.243379],"type":"Point"}
}