{
  "type": "Feature",
  "properties": {
    "iso:country":"US",
    "sg:address":"5512 W St Anne Ave",
    "sg:city":"Laveen",
    "sg:classifiers":[
        {
            "category":"Shopping",
            "subcategory":"Stationery & Office Supplies",
            "type":"Retail Goods"
        }
    ],
    "sg:phone":"+1 602 956 5155",
    "sg:postcode":"85339",
    "sg:province":"AZ",
    "sg:tags":[
        "stationer"
    ],
    "wof:name":"Designs By Hyera",
    "wof:placetype":"venue"
},
  "geometry": {"coordinates":[-112.178675,33.386995],"type":"Point"}
}