{
  "type": "Feature",
  "properties": {
    "iso:country":"US",
    "sg:address":"2625 N Craycroft Rd",
    "sg:city":"Tucson",
    "sg:classifiers":[
        {
            "category":"Health Services",
            "subcategory":"Doctor",
            "type":"Services"
        }
    ],
    "sg:phone":"+1 520 324 2409",
    "sg:postcode":"85712",
    "sg:province":"AZ",
    "sg:tags":[
        "physician",
        "surgeon"
    ],
    "wof:name":"Arizona Oncology Assoc",
    "wof:placetype":"venue"
},
  "geometry": {"coordinates":[-110.87535699999999,32.254734],"type":"Point"}
}