{
  "type": "Feature",
  "properties": {
    "iso:country":"US",
    "sg:address":"9433 W Mariposa Dr",
    "sg:city":"Phoenix",
    "sg:classifiers":[
        {
            "category":"Freight",
            "type":"Transportation"
        }
    ],
    "sg:phone":"+1 623 877 4644",
    "sg:postcode":"85037",
    "sg:province":"AZ",
    "sg:tags":[
        "operator",
        "local",
        "trucking"
    ],
    "wof:name":"Rico Transport",
    "wof:placetype":"venue"
},
  "geometry": {"coordinates":[-112.263007,33.507576],"type":"Point"}
}