{
  "type": "Feature",
  "properties": {
    "addr:full":"330 W Coral Gables Dr Phoenix AZ 85023",
    "addr:housenumber":"330",
    "addr:postcode":"85023",
    "addr:street":"W Coral;Dr",
    "iso:country":"US",
    "sg:address":"330 W Coral Gables Dr",
    "sg:city":"Phoenix",
    "sg:classifiers":[
        {
            "category":"Organizations",
            "subcategory":"Religious Organization",
            "type":"Services"
        }
    ],
    "sg:phone":"+1 602 942 2608",
    "sg:postcode":"85023",
    "sg:province":"AZ",
    "sg:tags":[
        "church"
    ],
    "sg:website":"www.diocesephoenix.org",
    "wof:name":"St Paul's Catholic Church",
    "wof:placetype":"venue"
},
  "geometry": {"coordinates":[-112.08277200000001,33.625692],"type":"Point"}
}