{
  "type": "Feature",
  "properties": {
    "addr:full":"11489 E Mark Ln Scottsdale AZ 85262",
    "addr:housenumber":"11489",
    "addr:postcode":"85262",
    "addr:street":"E Mark Ln",
    "iso:country":"US",
    "sg:address":"11489 E Mark Ln",
    "sg:city":"Scottsdale",
    "sg:classifiers":[
        {
            "category":"Professional",
            "type":"Services"
        }
    ],
    "sg:phone":"+1 480 502 7774",
    "sg:postcode":"85262",
    "sg:province":"AZ",
    "wof:name":"Best To You",
    "wof:placetype":"venue"
},
  "geometry": {"coordinates":[-111.832556,33.742023],"type":"Point"}
}