{
  "type": "Feature",
  "properties": {
    "addr:full":"16711 E Rancho del Oro Dr Scottsdale AZ 85262",
    "addr:housenumber":"16711",
    "addr:postcode":"85262",
    "addr:street":"E Rancho Del Oro Dr",
    "iso:country":"US",
    "sg:address":"16711 E Rancho del Oro Dr",
    "sg:city":"Scottsdale",
    "sg:classifiers":[
        {
            "category":"Building & Trades",
            "subcategory":"Construction",
            "type":"Services"
        }
    ],
    "sg:phone":"+1 480 471 2772",
    "sg:postcode":"85262",
    "sg:province":"AZ",
    "sg:tags":[
        "mason",
        "masonry",
        "industrial",
        "contractors-commercial",
        "contractor"
    ],
    "wof:name":"R D Pursell Masonry Inc",
    "wof:placetype":"venue"
},
  "geometry": {"coordinates":[-111.7191,33.767781],"type":"Point"}
}