{
  "type": "Feature",
  "properties": {
    "iso:country":"US",
    "sg:address":"2323 W Dunlap Ave",
    "sg:city":"Phoenix",
    "sg:classifiers":[
        {
            "category":"Shopping",
            "subcategory":"Clothing, Apparel, & Fashions",
            "type":"Retail Goods"
        }
    ],
    "sg:phone":"+1 602 674 5362",
    "sg:postcode":"85021",
    "sg:province":"AZ",
    "wof:name":"Jimenes Fashion",
    "wof:placetype":"venue"
},
  "geometry": {"coordinates":[-112.109885,33.567471],"type":"Point"}
}