{
  "type": "Feature",
  "properties": {
    "iso:country":"US",
    "sg:address":"16042 N 32nd St Ste D12",
    "sg:city":"Phoenix",
    "sg:classifiers":[
        {
            "category":"Manufacturing",
            "subcategory":"Buildings",
            "type":"Manufacturing & Wholesale Goods"
        },
        {
            "category":"Building & Trades",
            "subcategory":"Construction",
            "type":"Services"
        }
    ],
    "sg:phone":"+1 602 971 0337",
    "sg:postcode":"85032",
    "sg:province":"AZ",
    "sg:tags":[
        "industrial",
        "builder",
        "specialty",
        "heating",
        "contractors-commercial",
        "home",
        "contractor"
    ],
    "wof:name":"Finocchiaro Construction",
    "wof:placetype":"venue"
},
  "geometry": {"coordinates":[-112.013464,33.633044],"type":"Point"}
}