{
  "type": "Feature",
  "properties": {
    "iso:country":"US",
    "sg:address":"2850 W Camelback Rd",
    "sg:city":"Phoenix",
    "sg:classifiers":[
        {
            "category":"Banks & Credit Unions",
            "subcategory":"Bank",
            "type":"Services"
        }
    ],
    "sg:phone":"+1 602 589 6782",
    "sg:postcode":"85017",
    "sg:province":"AZ",
    "sg:tags":[
        "loan",
        "real estate"
    ],
    "sg:website":"www.azloans4you.com",
    "wof:name":"Freestand Financial Holding",
    "wof:placetype":"venue"
},
  "geometry": {"coordinates":[-112.120553,33.509523],"type":"Point"}
}