{
  "type": "Feature",
  "properties": {
    "iso:country":"US",
    "sg:address":"13757 N Fountain Hills Blvd",
    "sg:city":"Fountain Hills",
    "sg:classifiers":[
        {
            "category":"Shopping",
            "subcategory":"Department Store",
            "type":"Retail Goods"
        }
    ],
    "sg:phone":"+1 480 836 8058",
    "sg:postcode":"85268",
    "sg:province":"AZ",
    "wof:name":"Beall's Outlet",
    "wof:placetype":"venue"
},
  "geometry": {"coordinates":[-111.729178,33.610629],"type":"Point"}
}