{
  "type": "Feature",
  "properties": {
    "addr:full":"6040 W Belleview St Phoenix AZ 85043",
    "addr:housenumber":"6040",
    "addr:postcode":"85043",
    "addr:street":"W Belleview St",
    "iso:country":"US",
    "sg:address":"6040 W Belleview St",
    "sg:city":"Phoenix",
    "sg:classifiers":[
        {
            "category":"Shopping",
            "subcategory":"Florist",
            "type":"Retail Goods"
        }
    ],
    "sg:phone":"+1 602 279 5696",
    "sg:postcode":"85043",
    "sg:province":"AZ",
    "wof:name":"Galindos Florist",
    "wof:placetype":"venue"
},
  "geometry": {"coordinates":[-112.19017100000001,33.461912],"type":"Point"}
}