{
  "type": "Feature",
  "properties": {
    "iso:country":"US",
    "sg:address":"8301 N 19th Ave",
    "sg:city":"Phoenix",
    "sg:classifiers":[
        {
            "category":"Organizations",
            "subcategory":"Religious Organization",
            "type":"Services"
        }
    ],
    "sg:phone":"+1 602 242 4414",
    "sg:postcode":"85021",
    "sg:province":"AZ",
    "sg:tags":[
        "church"
    ],
    "sg:website":"www.odfchurch.org",
    "wof:name":"Open Door Fellowship Church",
    "wof:placetype":"venue"
},
  "geometry": {"coordinates":[-112.099587,33.557523],"type":"Point"}
}