{
  "type": "Feature",
  "properties": {
    "iso:country":"US",
    "sg:address":"2657 Village Dr",
    "sg:city":"Cottonwood",
    "sg:classifiers":[
        {
            "category":"Government",
            "subcategory":"Office",
            "type":"Public Place"
        }
    ],
    "sg:phone":"+1 928 639 8176",
    "sg:postcode":"86326",
    "sg:province":"AZ",
    "wof:name":"U Of A Co-Op Extension Svc",
    "wof:placetype":"venue"
},
  "geometry": {"coordinates":[-111.981111,34.692659],"type":"Point"}
}