{
  "type": "Feature",
  "properties": {
    "addr:full":"630 N Dysart Road Goodyear AZ 85338",
    "addr:housenumber":"630",
    "addr:postcode":"85338",
    "addr:street":"N Dysart Road",
    "iso:country":"US",
    "sg:address":"630 N Dysart Road",
    "sg:city":"Goodyear",
    "sg:classifiers":[
        {
            "category":"Retail",
            "subcategory":"Auto Repair",
            "type":"Services"
        }
    ],
    "sg:phone":"+1 623 882 0221",
    "sg:postcode":"85338",
    "sg:province":"AZ",
    "wof:name":"Lee Myles Transmissions",
    "wof:placetype":"venue"
},
  "geometry": {"coordinates":[-112.341043,33.452155],"type":"Point"}
}