{
  "type": "Feature",
  "properties": {
    "iso:country":"US",
    "sg:address":"2010 W Lower Buckeye Rd",
    "sg:city":"Phoenix",
    "sg:classifiers":[
        {
            "category":"Building & Trades",
            "subcategory":"Construction",
            "type":"Services"
        }
    ],
    "sg:phone":"+1 602 716 5566",
    "sg:postcode":"85009",
    "sg:province":"AZ",
    "sg:tags":[
        "sandblasting",
        "contractor"
    ],
    "wof:name":"A To Z Sandblasting LLC",
    "wof:placetype":"venue"
},
  "geometry": {"coordinates":[-112.10618100000001,33.422355],"type":"Point"}
}