{
  "type": "Feature",
  "properties": {
    "addr:full":"2025 E Rio Salado Pkwy # 104 Tempe AZ 85281",
    "addr:housenumber":"2025",
    "addr:postcode":"85281",
    "addr:street":"E Rio Salado Pkwy # 104",
    "iso:country":"US",
    "sg:address":"2025 E Rio Salado Pkwy # 104",
    "sg:city":"Tempe",
    "sg:classifiers":[
        {
            "category":"Wholesale",
            "subcategory":"Office Equipment",
            "type":"Manufacturing & Wholesale Goods"
        },
        {
            "category":"Shopping",
            "subcategory":"Stationery & Office Supplies",
            "type":"Retail Goods"
        },
        {
            "category":"Professional",
            "subcategory":"Computer Services",
            "type":"Services"
        }
    ],
    "sg:phone":"+1 480 921 0054",
    "sg:postcode":"85281",
    "sg:province":"AZ",
    "sg:tags":[
        "repair",
        "register",
        "cash",
        "equipment-service",
        "furniture"
    ],
    "sg:website":"http://www.valebusiness.com",
    "wof:name":"Vale Paper & Supply",
    "wof:placetype":"venue"
},
  "geometry": {"coordinates":[-111.899338,33.429249],"type":"Point"}
}