{
  "type": "Feature",
  "properties": {
    "iso:country":"US",
    "sg:address":"73 E Thunderbird Trl",
    "sg:city":"Phoenix",
    "sg:classifiers":[
        {
            "category":"Banks & Credit Unions",
            "subcategory":"Bank",
            "type":"Services"
        }
    ],
    "sg:phone":"+1 602 589 3480",
    "sg:postcode":"85042",
    "sg:province":"AZ",
    "sg:tags":[
        "national"
    ],
    "wof:name":"Bank One",
    "wof:placetype":"venue"
},
  "geometry": {"coordinates":[-112.07238099999999,33.358709],"type":"Point"}
}