{
  "type": "Feature",
  "properties": {
    "iso:country":"US",
    "sg:address":"5005 E Rancho del Oro Dr",
    "sg:city":"Cave Creek",
    "sg:classifiers":[
        {
            "category":"Building & Trades",
            "subcategory":"Construction",
            "type":"Services"
        }
    ],
    "sg:phone":"+1 480 595 9745",
    "sg:postcode":"85331",
    "sg:province":"AZ",
    "sg:tags":[
        "nonresidential"
    ],
    "wof:name":"Chairman of Board",
    "wof:placetype":"venue"
},
  "geometry": {"coordinates":[-111.97418,33.768925],"type":"Point"}
}