{
  "type": "Feature",
  "properties": {
    "iso:country":"US",
    "sg:address":"700 E Germann Rd",
    "sg:city":"Chandler",
    "sg:classifiers":[
        {
            "category":"Retail",
            "subcategory":"Storage",
            "type":"Services"
        }
    ],
    "sg:phone":"+1 480 447 8058",
    "sg:postcode":"85286",
    "sg:province":"AZ",
    "sg:tags":[
        "household",
        "commercial"
    ],
    "sg:website":"http://www.storage-solutions.org/self_storage_chandler_arizona/germann_self_storage_chandler_az.asp",
    "wof:name":"Germann Storage Solutions",
    "wof:placetype":"venue"
},
  "geometry": {"coordinates":[-111.828755,33.276885],"type":"Point"}
}