{
  "type": "Feature",
  "properties": {
    "addr:full":"322 E Glenn Dr Phoenix AZ 85020",
    "addr:housenumber":"322",
    "addr:postcode":"85020",
    "addr:street":"E Glenn Dr",
    "iso:country":"US",
    "sg:address":"322 E Glenn Dr",
    "sg:city":"Phoenix",
    "sg:classifiers":[
        {
            "category":"Banks & Credit Unions",
            "subcategory":"Financial Services",
            "type":"Services"
        }
    ],
    "sg:phone":"+1 602 395 9269",
    "sg:postcode":"85020",
    "sg:province":"AZ",
    "sg:tags":[
        "escrow"
    ],
    "wof:name":"Title Escrow Consulting Services Inc",
    "wof:placetype":"venue"
},
  "geometry": {"coordinates":[-112.069062,33.540136],"type":"Point"}
}