{
  "type": "Feature",
  "properties": {
    "addr:full":"10135 E Via Linda Scottsdale AZ 85258",
    "addr:housenumber":"10135",
    "addr:postcode":"85258",
    "addr:street":"E Via Linda",
    "iso:country":"US",
    "sg:address":"10135 E Via Linda",
    "sg:city":"Scottsdale",
    "sg:classifiers":[
        {
            "category":"Social Services",
            "subcategory":"Child Care",
            "type":"Services"
        }
    ],
    "sg:phone":"+1 480 314 9669",
    "sg:postcode":"85258",
    "sg:province":"AZ",
    "sg:website":"www.bestpalsaz.com",
    "wof:name":"Best Pals",
    "wof:placetype":"venue"
},
  "geometry": {"coordinates":[-111.862009,33.574716],"type":"Point"}
}