{
  "type": "Feature",
  "properties": {
    "addr:full":"18424 N 44th Pl Phoenix AZ 85032",
    "addr:housenumber":"18424",
    "addr:postcode":"85032",
    "addr:street":"N 44Th Pl",
    "iso:country":"US",
    "sg:address":"18424 N 44th Pl",
    "sg:city":"Phoenix",
    "sg:classifiers":[
        {
            "category":"Restaurant",
            "type":"Food & Drink"
        }
    ],
    "sg:phone":"+1 602 923 6106",
    "sg:postcode":"85032",
    "sg:province":"AZ",
    "wof:name":"Dinner By Design",
    "wof:placetype":"venue"
},
  "geometry": {"coordinates":[-111.98565499999999,33.653873],"type":"Point"}
}