{
  "type": "Feature",
  "properties": {
    "iso:country":"US",
    "sg:address":"48761 W Dune Shadow Rd",
    "sg:city":"Maricopa",
    "sg:classifiers":[
        {
            "category":"Wholesale",
            "subcategory":"Non-durable Goods",
            "type":"Manufacturing & Wholesale Goods"
        }
    ],
    "sg:phone":"+1 520 424 9888",
    "sg:postcode":"85239",
    "sg:province":"AZ",
    "wof:name":"Rebecca Lake Sale Rep",
    "wof:placetype":"venue"
},
  "geometry": {"coordinates":[-112.091006,32.883858],"type":"Point"}
}