{
  "type": "Feature",
  "properties": {
    "iso:country":"US",
    "sg:address":"1111 W Birchwood Ave",
    "sg:city":"Mesa",
    "sg:classifiers":[
        {
            "category":"Professional",
            "subcategory":"Engineering",
            "type":"Services"
        },
        {
            "category":"Retail",
            "subcategory":"Repair Shop",
            "type":"Services"
        }
    ],
    "sg:phone":"+1 480 969 9988",
    "sg:postcode":"85210",
    "sg:province":"AZ",
    "sg:tags":[
        "refrigeration",
        "major",
        "appliance",
        "refinishing",
        "engineer"
    ],
    "wof:name":"Refrigeration Supplies Distr",
    "wof:placetype":"venue"
},
  "geometry": {"coordinates":[-111.855614,33.409672],"type":"Point"}
}