{
  "type": "Feature",
  "properties": {
    "iso:country":"US",
    "sg:address":"601 S. Alma School Rd #280",
    "sg:city":"Mesa",
    "sg:classifiers":[
        {
            "category":"Shopping",
            "subcategory":"Hobbies, Toys, & Games",
            "type":"Retail Goods"
        },
        {
            "category":"Personal",
            "type":"Services"
        }
    ],
    "sg:phone":"+1 602 810 5003",
    "sg:postcode":"85210",
    "sg:province":"AZ",
    "sg:tags":[
        "consultant",
        "planning",
        "wedding"
    ],
    "sg:website":"http://elegant-designs.bravehost.com",
    "wof:name":"Elegant Designs Wedding Planning",
    "wof:placetype":"venue"
},
  "geometry": {"coordinates":[-111.837631,33.400885],"type":"Point"}
}