{
  "type": "Feature",
  "properties": {
    "iso:country":"US",
    "sg:address":"15038 N 59th Pl",
    "sg:city":"Scottsdale",
    "sg:classifiers":[
        {
            "category":"Wholesale",
            "subcategory":"Vending Machines",
            "type":"Manufacturing & Wholesale Goods"
        }
    ],
    "sg:phone":"+1 602 992 6058",
    "sg:postcode":"85254",
    "sg:province":"AZ",
    "sg:tags":[
        "operator"
    ],
    "wof:name":"Caliber Vending LLC",
    "wof:placetype":"venue"
},
  "geometry": {"coordinates":[-111.953125,33.623868],"type":"Point"}
}