{
  "type": "Feature",
  "properties": {
    "iso:country":"US",
    "sg:address":"201 E Southern Ave Ste 204",
    "sg:city":"Tempe",
    "sg:classifiers":[
        {
            "category":"Education",
            "subcategory":"Special Training",
            "type":"Public Place"
        }
    ],
    "sg:phone":"+1 602 427 7959",
    "sg:postcode":"85282",
    "sg:province":"AZ",
    "sg:tags":[
        "educational"
    ],
    "wof:name":"Arizona Safety Education Center, Inc.",
    "wof:placetype":"venue"
},
  "geometry": {"coordinates":[-111.93647300000001,33.392885],"type":"Point"}
}