{
  "type": "Feature",
  "properties": {
    "iso:country":"US",
    "sg:address":"18901 N Alameda Dr",
    "sg:city":"Surprise",
    "sg:classifiers":[
        {
            "category":"Wholesale",
            "subcategory":"Chemicals & Plastics",
            "type":"Manufacturing & Wholesale Goods"
        }
    ],
    "sg:phone":"+1 623 544 3296",
    "sg:postcode":"85387",
    "sg:province":"AZ",
    "sg:tags":[
        "lubricant",
        "dealer"
    ],
    "wof:name":"Opportunity Unlimited",
    "wof:placetype":"venue"
},
  "geometry": {"coordinates":[-112.43690599999999,33.65676],"type":"Point"}
}