{
  "type": "Feature",
  "properties": {
    "addr:full":"6291 N Via Acacia Tucson AZ 85718",
    "addr:housenumber":"6291",
    "addr:postcode":"85718",
    "addr:street":"N Via Acacia",
    "iso:country":"US",
    "sg:address":"6291 N Via Acacia",
    "sg:city":"Tucson",
    "sg:classifiers":[
        {
            "category":"Professional",
            "type":"Services"
        }
    ],
    "sg:phone":"+1 520 544 4293",
    "sg:postcode":"85718",
    "sg:province":"AZ",
    "wof:name":"Settlers Ridge of Cloquet LP",
    "wof:placetype":"venue"
},
  "geometry": {"coordinates":[-110.90456500000001,32.31956],"type":"Point"}
}