{
  "type": "Feature",
  "properties": {
    "iso:country":"US",
    "sg:address":"1842 W Broadway Rd",
    "sg:city":"Mesa",
    "sg:classifiers":[
        {
            "category":"Banks & Credit Unions",
            "subcategory":"Bank",
            "type":"Services"
        }
    ],
    "sg:phone":"+1 480 655 0396",
    "sg:postcode":"85202",
    "sg:province":"AZ",
    "sg:tags":[
        "personal",
        "institution"
    ],
    "wof:name":"Advance America",
    "wof:placetype":"venue"
},
  "geometry": {"coordinates":[-111.874166,33.407663],"type":"Point"}
}