{
  "type": "Feature",
  "properties": {
    "iso:country":"US",
    "sg:address":"320 W Lone Cactus Dr",
    "sg:city":"Phoenix",
    "sg:classifiers":[
        {
            "category":"Retail",
            "subcategory":"Repair Shop",
            "type":"Services"
        }
    ],
    "sg:phone":"+1 623 580 1459",
    "sg:postcode":"85027",
    "sg:province":"AZ",
    "sg:tags":[
        "upholsterer"
    ],
    "wof:name":"Enrique Cordova",
    "wof:placetype":"venue"
},
  "geometry": {"coordinates":[-112.07799300000001,33.680924],"type":"Point"}
}