{
  "type": "Feature",
  "properties": {
    "addr:full":"1303 W Devonshire St Mesa AZ 85201",
    "addr:housenumber":"1303",
    "addr:postcode":"85201",
    "addr:street":"W Devonshire St",
    "iso:country":"US",
    "sg:address":"1303 W Devonshire St",
    "sg:city":"Mesa",
    "sg:classifiers":[
        {
            "category":"Shopping",
            "subcategory":"Hobbies, Toys, & Games",
            "type":"Retail Goods"
        }
    ],
    "sg:phone":"+1 480 835 0353",
    "sg:postcode":"85201",
    "sg:province":"AZ",
    "sg:tags":[
        "doll"
    ],
    "wof:name":"ABC Doll Shop & Repair",
    "wof:placetype":"venue"
},
  "geometry": {"coordinates":[-111.86029499999999,33.428002],"type":"Point"}
}