{
  "type": "Feature",
  "properties": {
    "iso:country":"US",
    "sg:address":"1350 E Broadway Blvd",
    "sg:city":"Tucson",
    "sg:classifiers":[
        {
            "category":"Restaurant",
            "type":"Food & Drink"
        }
    ],
    "sg:menulink":"http://www.allmenus.com/az/tucson/18648-soul-feathers/menu/",
    "sg:phone":"+1 520 882 5030",
    "sg:postcode":"85719",
    "sg:province":"AZ",
    "sg:tags":[
        "barbecue",
        "american",
        "sandwich",
        "asian",
        "chinese"
    ],
    "wof:name":"Soul Feathers",
    "wof:placetype":"venue"
},
  "geometry": {"coordinates":[-110.95155200000001,32.221382],"type":"Point"}
}