{
  "type": "Feature",
  "properties": {
    "iso:country":"US",
    "sg:address":"15224 S 18th Ave",
    "sg:city":"Phoenix",
    "sg:classifiers":[
        {
            "category":"Home & Garden",
            "subcategory":"Building Materials",
            "type":"Retail Goods"
        }
    ],
    "sg:phone":"+1 480 706 4838",
    "sg:postcode":"85045",
    "sg:province":"AZ",
    "sg:tags":[
        "door"
    ],
    "wof:name":"Garage Door Svc Co",
    "wof:placetype":"venue"
},
  "geometry": {"coordinates":[-112.098949,33.304554],"type":"Point"}
}