{
  "type": "Feature",
  "properties": {
    "addr:full":"9015 E Via Linda Scottsdale AZ 85258",
    "addr:housenumber":"9015",
    "addr:postcode":"85258",
    "addr:street":"E Via Linda",
    "iso:country":"US",
    "sg:address":"9015 E Via Linda",
    "sg:city":"Scottsdale",
    "sg:classifiers":[
        {
            "category":"Home & Garden",
            "subcategory":"Hardware",
            "type":"Retail Goods"
        }
    ],
    "sg:phone":"+1 480 860 8800",
    "sg:postcode":"85258",
    "sg:province":"AZ",
    "sg:tags":[
        "store"
    ],
    "wof:name":"Ace Hardware",
    "wof:placetype":"venue"
},
  "geometry": {"coordinates":[-111.886702,33.569117],"type":"Point"}
}