{
  "type": "Feature",
  "properties": {
    "iso:country":"US",
    "sg:address":"7229 W Dreyfus Dr",
    "sg:city":"Peoria",
    "sg:classifiers":[
        {
            "category":"Building & Trades",
            "subcategory":"Landscaping Services",
            "type":"Services"
        }
    ],
    "sg:phone":"+1 623 878 7092",
    "sg:postcode":"85381",
    "sg:province":"AZ",
    "wof:name":"Carefree Landscaping",
    "wof:placetype":"venue"
},
  "geometry": {"coordinates":[-112.212571,33.603721],"type":"Point"}
}