{
  "type": "Feature",
  "properties": {
    "iso:country":"US",
    "sg:address":"4829 S 38th St Ste 1",
    "sg:city":"Phoenix",
    "sg:classifiers":[
        {
            "category":"Utilities",
            "subcategory":"Electric",
            "type":"Services"
        },
        {
            "category":"Building & Trades",
            "subcategory":"Electrical",
            "type":"Services"
        }
    ],
    "sg:phone":"+1 602 275 8500",
    "sg:postcode":"85040",
    "sg:province":"AZ",
    "sg:tags":[
        "equipment-repair",
        "industrial",
        "electrician",
        "contractors-commercial"
    ],
    "sg:website":"http://www.corbinselectric.com",
    "wof:name":"Corbins Service Electric",
    "wof:placetype":"venue"
},
  "geometry": {"coordinates":[-111.999847,33.402618],"type":"Point"}
}