{
  "type": "Feature",
  "properties": {
    "iso:country":"US",
    "sg:address":"2110 W Brichta Dr",
    "sg:city":"Tucson",
    "sg:classifiers":[
        {
            "category":"Education",
            "subcategory":"School",
            "type":"Public Place"
        }
    ],
    "sg:phone":"+1 520 225 1100",
    "sg:postcode":"85745",
    "sg:province":"AZ",
    "sg:tags":[
        "elementary"
    ],
    "wof:name":"Brichta Elementary School",
    "wof:placetype":"venue"
},
  "geometry": {"coordinates":[-111.011905,32.241661],"type":"Point"}
}