{
  "type": "Feature",
  "properties": {
    "addr:full":"1550 W Deer Valley Rd Phoenix AZ 85027",
    "addr:housenumber":"1550",
    "addr:postcode":"85027",
    "addr:street":"W Deer Valley Rd",
    "iso:country":"US",
    "sg:address":"1550 W Deer Valley Rd",
    "sg:city":"Phoenix",
    "sg:classifiers":[
        {
            "category":"Communications",
            "subcategory":"Television Station",
            "type":"Services"
        },
        {
            "category":"Utilities",
            "subcategory":"Telephone",
            "type":"Services"
        },
        {
            "category":"Internet Cafe",
            "subcategory":"None",
            "type":"Food & Drink"
        }
    ],
    "sg:phone":"+1 623 594 1000",
    "sg:postcode":"85027",
    "sg:province":"AZ",
    "sg:tags":[
        "companies-long",
        "distance",
        "product",
        "satellite",
        "cable"
    ],
    "wof:name":"Cox Communications",
    "wof:placetype":"venue"
},
  "geometry": {"coordinates":[-112.094032,33.68383],"type":"Point"}
}