{
  "type": "Feature",
  "properties": {
    "iso:country":"US",
    "sg:address":"85 Sycamore St",
    "sg:city":"Sedona",
    "sg:classifiers":[
        {
            "category":"Building & Trades",
            "subcategory":"Plumbing",
            "type":"Services"
        }
    ],
    "sg:phone":"+1 928 284 3484",
    "sg:postcode":"86351",
    "sg:province":"AZ",
    "sg:tags":[
        "contractor"
    ],
    "wof:name":"Russ Thompson Solar & Water",
    "wof:placetype":"venue"
},
  "geometry": {"coordinates":[-111.77487499999999,34.78699],"type":"Point"}
}