{
  "type": "Feature",
  "properties": {
    "iso:country":"US",
    "sg:address":"985 E Riggs Rd",
    "sg:city":"Chandler",
    "sg:classifiers":[
        {
            "category":"Shopping",
            "subcategory":"Pharmacy",
            "type":"Retail Goods"
        }
    ],
    "sg:phone":"+1 480 883 6533",
    "sg:postcode":"85249",
    "sg:province":"AZ",
    "wof:name":"Fry's Food Store Pharmacy",
    "wof:placetype":"venue"
},
  "geometry": {"coordinates":[-111.824494,33.218726],"type":"Point"}
}