{
  "type": "Feature",
  "properties": {
    "iso:country":"US",
    "sg:address":"700 N Superstition Blvd",
    "sg:city":"Chandler",
    "sg:classifiers":[
        {
            "category":"Education",
            "subcategory":"School",
            "type":"Public Place"
        }
    ],
    "sg:phone":"+1 480 812 7304",
    "sg:postcode":"85225",
    "sg:province":"AZ",
    "wof:name":"Chandler Unified School Dist",
    "wof:placetype":"venue"
},
  "geometry": {"coordinates":[-111.81410200000001,33.318823],"type":"Point"}
}