{
  "type": "Feature",
  "properties": {
    "iso:country":"US",
    "sg:address":"8240 W Lower Buckeye Rd",
    "sg:city":"Phoenix",
    "sg:classifiers":[
        {
            "category":"Professional",
            "type":"Services"
        },
        {
            "category":"Shopping",
            "subcategory":"Bicycles & Sporting Goods",
            "type":"Retail Goods"
        },
        {
            "category":"Personal",
            "subcategory":"Day Spa",
            "type":"Services"
        },
        {
            "category":"Personal",
            "subcategory":"Sauna",
            "type":"Services"
        },
        {
            "category":"Sports & Exercise",
            "subcategory":"Swimming Pool",
            "type":"Entertainment"
        }
    ],
    "sg:phone":"+1 623 936 8660",
    "sg:postcode":"85043",
    "sg:province":"AZ",
    "sg:tags":[
        "repair",
        "supply",
        "tubs-repair",
        "equipment",
        "hot",
        "tub"
    ],
    "sg:website":"http://www.lesliespool.com",
    "wof:name":"Leslie's Poolmart, Inc.",
    "wof:placetype":"venue"
},
  "geometry": {"coordinates":[-112.237146,33.423],"type":"Point"}
}