{
  "type": "Feature",
  "properties": {
    "iso:country":"US",
    "sg:address":"4718 S Clark Dr",
    "sg:city":"Tempe",
    "sg:classifiers":[
        {
            "category":"Communications",
            "subcategory":"Film & Video Production",
            "type":"Services"
        },
        {
            "category":"Professional",
            "subcategory":"Art Services",
            "type":"Services"
        }
    ],
    "sg:phone":"+1 480 330 4462",
    "sg:postcode":"85282",
    "sg:province":"AZ",
    "sg:tags":[
        "creative",
        "audio-visual"
    ],
    "sg:website":"http://www.desertmike.com",
    "wof:name":"Desert Mike Productions",
    "wof:placetype":"venue"
},
  "geometry": {"coordinates":[-111.899551,33.383131],"type":"Point"}
}