{
  "type": "Feature",
  "properties": {
    "iso:country":"US",
    "sg:address":"844 E Scott Ave",
    "sg:city":"Gilbert",
    "sg:classifiers":[
        {
            "category":"Farming",
            "subcategory":"Farm",
            "type":"Manufacturing & Wholesale Goods"
        }
    ],
    "sg:phone":"+1 480 545 6703",
    "sg:postcode":"85234",
    "sg:province":"AZ",
    "sg:tags":[
        "real",
        "property",
        "crop",
        "lessor",
        "general"
    ],
    "wof:name":"Herman Farms Inc",
    "wof:placetype":"venue"
},
  "geometry": {"coordinates":[-111.772702,33.365978],"type":"Point"}
}