{
  "type": "Feature",
  "properties": {
    "addr:full":"13714 W Bell Rd Surprise AZ 85374",
    "addr:housenumber":"13714",
    "addr:postcode":"85374",
    "addr:street":"W Bell Rd",
    "iso:country":"US",
    "sg:address":"13714 W Bell Rd",
    "sg:city":"Surprise",
    "sg:classifiers":[
        {
            "category":"Shopping",
            "subcategory":"Hobbies, Toys, & Games",
            "type":"Retail Goods"
        },
        {
            "category":"Banks & Credit Unions",
            "subcategory":"Investment Brokerage",
            "type":"Services"
        }
    ],
    "sg:phone":"+1 623 546 4334",
    "sg:postcode":"85374",
    "sg:province":"AZ",
    "sg:tags":[
        "video",
        "dvds-rental",
        "tape",
        "sale",
        "supply"
    ],
    "wof:name":"Game Tag",
    "wof:placetype":"venue"
},
  "geometry": {"coordinates":[-112.354613,33.638712],"type":"Point"}
}