{
  "type": "Feature",
  "properties": {
    "iso:country":"US",
    "sg:address":"38810 N 31st Ave",
    "sg:city":"Phoenix",
    "sg:classifiers":[
        {
            "category":"Home & Garden",
            "subcategory":"Home Furnishings",
            "type":"Retail Goods"
        },
        {
            "category":"Building & Trades",
            "subcategory":"Construction",
            "type":"Services"
        },
        {
            "category":"Manufacturing",
            "subcategory":"Building Materials",
            "type":"Manufacturing & Wholesale Goods"
        }
    ],
    "sg:phone":"+1 623 465 7449",
    "sg:postcode":"85086",
    "sg:province":"AZ",
    "sg:tags":[
        "industrial",
        "cabinetmakers-commercial",
        "cabinet",
        "refacing",
        "resurfacing",
        "maker",
        "cabinets-refinishing",
        "kitchen"
    ],
    "wof:name":"European Custom Cabinets & Store Fixture, Inc.",
    "wof:placetype":"venue"
},
  "geometry": {"coordinates":[-112.126188,33.836875],"type":"Point"}
}