{
  "type": "Feature",
  "properties": {
    "iso:country":"US",
    "sg:address":"10754 N Martineau Rd",
    "sg:city":"Elfrida",
    "sg:classifiers":[
        {
            "category":"Manufacturing",
            "subcategory":"Apparel",
            "type":"Manufacturing & Wholesale Goods"
        }
    ],
    "sg:phone":"+1 520 642 3891",
    "sg:postcode":"85610",
    "sg:province":"AZ",
    "sg:tags":[
        "suspender",
        "belt"
    ],
    "wof:name":"Belt Factory",
    "wof:placetype":"venue"
},
  "geometry": {"coordinates":[-109.704402,31.707537],"type":"Point"}
}