{
  "type": "Feature",
  "properties": {
    "addr:full":"244 S 3rd Ave Yuma AZ 85364",
    "addr:housenumber":"244",
    "addr:postcode":"85364",
    "addr:street":"S 3Rd Ave",
    "iso:country":"US",
    "sg:address":"244 S 3rd Ave",
    "sg:city":"Yuma",
    "sg:classifiers":[
        {
            "category":"Organizations",
            "subcategory":"Religious Organization",
            "type":"Services"
        }
    ],
    "sg:phone":"+1 928 783 5642",
    "sg:postcode":"85364",
    "sg:province":"AZ",
    "sg:tags":[
        "mission"
    ],
    "wof:name":"Crossroads Mission",
    "wof:placetype":"venue"
},
  "geometry": {"coordinates":[-114.62333700000001,32.723029],"type":"Point"}
}