{
  "type": "Feature",
  "properties": {
    "iso:country":"US",
    "sg:address":"16052 W Buchanan St",
    "sg:city":"Goodyear",
    "sg:classifiers":[
        {
            "category":"Building & Trades",
            "subcategory":"Construction",
            "type":"Services"
        }
    ],
    "sg:phone":"+1 602 826 8155",
    "sg:postcode":"85338",
    "sg:province":"AZ",
    "sg:tags":[
        "contractor"
    ],
    "wof:name":"Estrella Water Systems Inc",
    "wof:placetype":"venue"
},
  "geometry": {"coordinates":[-112.403806,33.441573],"type":"Point"}
}