{
  "type": "Feature",
  "properties": {
    "iso:country":"US",
    "sg:address":"5008 E Baseline Rd",
    "sg:city":"Mesa",
    "sg:classifiers":[
        {
            "category":"Food & Beverages",
            "subcategory":"Fruits & Vegetables",
            "type":"Retail Goods"
        }
    ],
    "sg:phone":"+1 480 832 8175",
    "sg:postcode":"85206",
    "sg:province":"AZ",
    "sg:tags":[
        "store",
        "market"
    ],
    "wof:name":"Lewis Linda A",
    "wof:placetype":"venue"
},
  "geometry": {"coordinates":[-111.72273,33.379329],"type":"Point"}
}