{
  "type": "Feature",
  "properties": {
    "iso:country":"US",
    "sg:address":"15025 N 74th St",
    "sg:city":"Scottsdale",
    "sg:classifiers":[
        {
            "category":"Restaurant",
            "type":"Food & Drink"
        }
    ],
    "sg:phone":"+1 480 948 9969",
    "sg:postcode":"85260",
    "sg:province":"AZ",
    "sg:tags":[
        "barbecue",
        "american",
        "italian"
    ],
    "sg:website":"http://www.tonyromas.com",
    "wof:name":"Tony Roma's",
    "wof:placetype":"venue"
},
  "geometry": {"coordinates":[-111.920042,33.622999],"type":"Point"}
}