{
  "type": "Feature",
  "properties": {
    "iso:country":"US",
    "sg:address":"9627 N Cave Creek Rd",
    "sg:city":"Phoenix",
    "sg:classifiers":[
        {
            "category":"Farming",
            "subcategory":"Farm & Veterinary Services",
            "type":"Manufacturing & Wholesale Goods"
        }
    ],
    "sg:phone":"+1 602 944 5263",
    "sg:postcode":"85020",
    "sg:province":"AZ",
    "sg:tags":[
        "breeder",
        "livestock"
    ],
    "wof:name":"Prescott Land & Cattle Co",
    "wof:placetype":"venue"
},
  "geometry": {"coordinates":[-112.057997,33.574429],"type":"Point"}
}