{
  "type": "Feature",
  "properties": {
    "iso:country":"US",
    "sg:address":"20235 N Cave Creek Rd",
    "sg:city":"Phoenix",
    "sg:classifiers":[
        {
            "category":"Retail",
            "subcategory":"Animal Services",
            "type":"Services"
        }
    ],
    "sg:phone":"+1 602 788 1566",
    "sg:postcode":"85024",
    "sg:province":"AZ",
    "sg:tags":[
        "pet"
    ],
    "wof:name":"Diva Dogs Boutique",
    "wof:placetype":"venue"
},
  "geometry": {"coordinates":[-112.03089300000001,33.671614],"type":"Point"}
}