{
  "type": "Feature",
  "properties": {
    "iso:country":"US",
    "sg:address":"940 S Warren Ave",
    "sg:city":"Tucson",
    "sg:classifiers":[
        {
            "category":"Manufacturing",
            "subcategory":"Jewelry",
            "type":"Manufacturing & Wholesale Goods"
        }
    ],
    "sg:phone":"+1 520 882 0233",
    "sg:postcode":"85719",
    "sg:province":"AZ",
    "sg:tags":[
        "equipment",
        "ware",
        "commercial",
        "mfg"
    ],
    "wof:name":"American Instllation Stainless",
    "wof:placetype":"venue"
},
  "geometry": {"coordinates":[-110.946417,32.210737],"type":"Point"}
}