{
  "type": "Feature",
  "properties": {
    "iso:country":"US",
    "sg:address":"2521 E Bluefield Ave",
    "sg:city":"Phoenix",
    "sg:classifiers":[
        {
            "category":"Building & Trades",
            "subcategory":"Construction",
            "type":"Services"
        }
    ],
    "sg:phone":"+1 602 485 0019",
    "sg:postcode":"85032",
    "sg:province":"AZ",
    "sg:tags":[
        "coping",
        "plastering",
        "tiling",
        "pool",
        "swimming"
    ],
    "wof:name":"Arcadia Pool Svc",
    "wof:placetype":"venue"
},
  "geometry": {"coordinates":[-112.027849,33.653165],"type":"Point"}
}