{
  "type": "Feature",
  "properties": {
    "iso:country":"US",
    "sg:address":"2222 S Price Rd",
    "sg:city":"Tempe",
    "sg:classifiers":[
        {
            "category":"Place Of Worship",
            "subcategory":"Church",
            "type":"Public Place"
        },
        {
            "category":"Shopping",
            "subcategory":"Party Supplies",
            "type":"Retail Goods"
        },
        {
            "category":"Social Services",
            "subcategory":"Child Care",
            "type":"Services"
        },
        {
            "category":"Place Of Worship",
            "type":"Public Place"
        },
        {
            "category":"Organizations",
            "subcategory":"Religious Organization",
            "type":"Services"
        }
    ],
    "sg:phone":"+1 480 968 4111",
    "sg:postcode":"85282",
    "sg:province":"AZ",
    "sg:tags":[
        "churches-episcopal",
        "wedding"
    ],
    "sg:website":"http://www.epiphanytempe.org",
    "wof:name":"The Church Of The Epiphany",
    "wof:placetype":"venue"
},
  "geometry": {"coordinates":[-111.892015,33.403574],"type":"Point"}
}