{
  "type": "Feature",
  "properties": {
    "addr:full":"1425 W 12th Pl Ste 101 Tempe AZ 85281",
    "addr:housenumber":"1425",
    "addr:postcode":"85281",
    "addr:street":"W 12Th Pl Ste 101",
    "iso:country":"US",
    "sg:address":"1425 W 12th Pl Ste 101",
    "sg:city":"Tempe",
    "sg:classifiers":[
        {
            "category":"Manufacturing",
            "subcategory":"Building Materials",
            "type":"Manufacturing & Wholesale Goods"
        },
        {
            "category":"Home & Garden",
            "subcategory":"Home Furnishings",
            "type":"Retail Goods"
        },
        {
            "category":"Home & Garden",
            "subcategory":"Building Materials",
            "type":"Retail Goods"
        },
        {
            "category":"Manufacturing",
            "subcategory":"Glass & Minerals",
            "type":"Manufacturing & Wholesale Goods"
        },
        {
            "category":"Retail",
            "subcategory":"Auto Repair",
            "type":"Services"
        }
    ],
    "sg:phone":"+1 480 967 5020",
    "sg:postcode":"85281",
    "sg:province":"AZ",
    "sg:tags":[
        "plate",
        "glazier",
        "window",
        "replacement",
        "glass-wholesale",
        "shape",
        "mirror",
        "circle",
        "windshield",
        "special",
        "manufacturer"
    ],
    "wof:name":"Mns",
    "wof:placetype":"venue"
},
  "geometry": {"coordinates":[-111.963993,33.415548],"type":"Point"}
}