{
  "type": "Feature",
  "properties": {
    "iso:country":"US",
    "sg:address":"600 E Bromley St",
    "sg:city":"Tucson",
    "sg:classifiers":[
        {
            "category":"Real Estate",
            "subcategory":"Real Estate Operator",
            "type":"Services"
        }
    ],
    "sg:phone":"+1 520 888 2417",
    "sg:postcode":"85704",
    "sg:province":"AZ",
    "sg:tags":[
        "apartment",
        "complex"
    ],
    "wof:name":"River Garden Apartments",
    "wof:placetype":"venue"
},
  "geometry": {"coordinates":[-110.961322,32.292271],"type":"Point"}
}