{
  "type": "Feature",
  "properties": {
    "iso:country":"US",
    "sg:address":"7707 E Acoma Dr",
    "sg:city":"Scottsdale",
    "sg:classifiers":[
        {
            "category":"Building & Trades",
            "subcategory":"Construction",
            "type":"Services"
        }
    ],
    "sg:phone":"+1 480 344 3366",
    "sg:postcode":"85260",
    "sg:province":"AZ",
    "sg:tags":[
        "demolition",
        "contractor"
    ],
    "wof:name":"Stealth Demolition LLC",
    "wof:placetype":"venue"
},
  "geometry": {"coordinates":[-111.913018,33.617684],"type":"Point"}
}