{
  "type": "Feature",
  "properties": {
    "addr:full":"1815 E Indian School Rd Phoenix AZ 85016",
    "addr:housenumber":"1815",
    "addr:postcode":"85016",
    "addr:street":"E Indian School Rd",
    "iso:country":"US",
    "sg:address":"1815 E Indian School Rd",
    "sg:city":"Phoenix",
    "sg:classifiers":[
        {
            "category":"Professional",
            "subcategory":"Management & Consulting",
            "type":"Services"
        }
    ],
    "sg:phone":"+1 602 266 7333",
    "sg:postcode":"85016",
    "sg:province":"AZ",
    "sg:tags":[
        "food",
        "facility"
    ],
    "sg:website":"www.frankredmond.com",
    "wof:name":"Frank Redmond Assoc Inc",
    "wof:placetype":"venue"
},
  "geometry": {"coordinates":[-112.041173,33.494693],"type":"Point"}
}