{
  "type": "Feature",
  "properties": {
    "addr:full":"6949 E Shea Blvd Scottsdale AZ 85254",
    "addr:housenumber":"6949",
    "addr:postcode":"85254",
    "addr:street":"E Shea Blvd",
    "iso:country":"US",
    "sg:address":"6949 E Shea Blvd",
    "sg:city":"Scottsdale",
    "sg:classifiers":[
        {
            "category":"Professional",
            "subcategory":"Management & Consulting",
            "type":"Services"
        }
    ],
    "sg:phone":"+1 480 367 1186",
    "sg:postcode":"85254",
    "sg:province":"AZ",
    "sg:tags":[
        "party",
        "planning"
    ],
    "wof:name":"Bake-A-Party",
    "wof:placetype":"venue"
},
  "geometry": {"coordinates":[-111.9311,33.582079],"type":"Point"}
}