{
  "type": "Feature",
  "properties": {
    "addr:full":"7 Bisbee Rd Bisbee AZ 85603",
    "addr:housenumber":"7",
    "addr:postcode":"85603",
    "addr:street":"Bisbee Rd",
    "iso:country":"US",
    "sg:address":"7 Bisbee Rd",
    "sg:city":"Bisbee",
    "sg:classifiers":[
        {
            "category":"Professional",
            "subcategory":"Business Services",
            "type":"Services"
        }
    ],
    "sg:phone":"+1 520 579 5548",
    "sg:postcode":"85603",
    "sg:province":"AZ",
    "sg:tags":[
        "consultant",
        "coach"
    ],
    "wof:name":"Associated Fire Consultants, Inc.",
    "wof:placetype":"venue"
},
  "geometry": {"coordinates":[-109.890649,31.426162],"type":"Point"}
}