{
  "type": "Feature",
  "properties": {
    "addr:full":"5817 N Canyon Dr Phoenix AZ 85016",
    "addr:housenumber":"5817",
    "addr:postcode":"85016",
    "addr:street":"N Canyon Dr",
    "iso:country":"US",
    "sg:address":"5817 N Canyon Dr",
    "sg:city":"Phoenix",
    "sg:classifiers":[
        {
            "category":"Banks & Credit Unions",
            "subcategory":"Financial Services",
            "type":"Services"
        }
    ],
    "sg:phone":"+1 602 524 1202",
    "sg:postcode":"85016",
    "sg:province":"AZ",
    "sg:tags":[
        "investment"
    ],
    "wof:name":"Bradford Marketing",
    "wof:placetype":"venue"
},
  "geometry": {"coordinates":[-112.014608,33.520409],"type":"Point"}
}