{
  "type": "Feature",
  "properties": {
    "iso:country":"US",
    "sg:address":"747 E White Mountain Blvd # 4",
    "sg:city":"Pinetop",
    "sg:phone":"+1 928 367 5050",
    "sg:postcode":"85935",
    "sg:province":"AZ",
    "wof:name":"Pinetop Sporting Goods",
    "wof:placetype":"venue"
},
  "geometry": {"coordinates":[-109.945809,34.129203],"type":"Point"}
}