{
  "type": "Feature",
  "properties": {
    "iso:country":"US",
    "sg:address":"2385 W Hwy 89A",
    "sg:city":"Sedona",
    "sg:classifiers":[
        {
            "category":"Home & Garden",
            "subcategory":"Building Materials",
            "type":"Retail Goods"
        }
    ],
    "sg:phone":"+1 928 282 7174",
    "sg:postcode":"86336",
    "sg:province":"AZ",
    "sg:tags":[
        "lumber"
    ],
    "wof:name":"Lumbermen's Building Ctr",
    "wof:placetype":"venue"
},
  "geometry": {"coordinates":[-111.802057,34.863068],"type":"Point"}
}