{
  "type": "Feature",
  "properties": {
    "iso:country":"US",
    "sg:address":"930 E Warner Rd Ste 19",
    "sg:city":"Chandler",
    "sg:classifiers":[
        {
            "category":"Shopping",
            "subcategory":"Clothing, Apparel, & Fashions",
            "type":"Retail Goods"
        }
    ],
    "sg:phone":"+1 480 688 7680",
    "sg:postcode":"85225",
    "sg:province":"AZ",
    "sg:tags":[
        "clothing",
        "women's"
    ],
    "sg:website":"www.ultimateblingboutique.com",
    "wof:name":"Ultimate Bling Boutique",
    "wof:placetype":"venue"
},
  "geometry": {"coordinates":[-111.826706,33.335732],"type":"Point"}
}