{
  "type": "Feature",
  "properties": {
    "iso:country":"US",
    "sg:address":"4802 E Ray Rd",
    "sg:city":"Phoenix",
    "sg:classifiers":[
        {
            "category":"Shopping",
            "subcategory":"Computers & Home Electronics",
            "type":"Retail Goods"
        }
    ],
    "sg:phone":"+1 480 893 1996",
    "sg:postcode":"85044",
    "sg:province":"AZ",
    "wof:name":"Electronics Boutique",
    "wof:placetype":"venue"
},
  "geometry": {"coordinates":[-111.976197,33.319949],"type":"Point"}
}