{
  "type": "Feature",
  "properties": {
    "iso:country":"US",
    "sg:address":"1901 N Cheri Lynn Dr",
    "sg:city":"Chandler",
    "sg:classifiers":[
        {
            "category":"Personal",
            "type":"Services"
        }
    ],
    "sg:phone":"+1 602 692 0694",
    "sg:postcode":"85225",
    "sg:province":"AZ",
    "sg:tags":[
        "mover"
    ],
    "sg:website":"JOESSMOOTHMOVE.COM",
    "wof:name":"Joes Smooth Move",
    "wof:placetype":"venue"
},
  "geometry": {"coordinates":[-111.852801,33.334698],"type":"Point"}
}