{
  "type": "Feature",
  "properties": {
    "iso:country":"US",
    "sg:address":"5157 E Bannock St",
    "sg:city":"Phoenix",
    "sg:classifiers":[
        {
            "category":"Professional",
            "subcategory":"Advertising",
            "type":"Services"
        }
    ],
    "sg:phone":"+1 480 598 1914",
    "sg:postcode":"85044",
    "sg:province":"AZ",
    "wof:name":"Mettie Advertising & Promotion",
    "wof:placetype":"venue"
},
  "geometry": {"coordinates":[-111.974245,33.3328],"type":"Point"}
}