{
  "type": "Feature",
  "properties": {
    "iso:country":"US",
    "sg:address":"8800 E Yavapai Rd",
    "sg:city":"Prescott Valley",
    "sg:classifiers":[
        {
            "category":"Real Estate",
            "subcategory":"Real Estate Operator",
            "type":"Services"
        }
    ],
    "sg:phone":"+1 928 772 8213",
    "sg:postcode":"86314",
    "sg:province":"AZ",
    "sg:tags":[
        "apartment"
    ],
    "wof:name":"Navapai Apartments",
    "wof:placetype":"venue"
},
  "geometry": {"coordinates":[-112.311768,34.591015],"type":"Point"}
}