{
  "type": "Feature",
  "properties": {
    "addr:full":"15444 N Frank Lloyd Wright Blvd Scottsdale AZ 85260",
    "addr:housenumber":"15444",
    "addr:postcode":"85260",
    "addr:street":"N Frank Lloyd Wright Blvd",
    "iso:country":"US",
    "sg:address":"15444 N Frank Lloyd Wright Blvd",
    "sg:city":"Scottsdale",
    "sg:classifiers":[
        {
            "category":"Coffee & Tea",
            "type":"Food & Drink"
        }
    ],
    "sg:menulink":"http://www.allmenus.com/az/phoenix/108396-starbucks-coffee/menu/",
    "sg:phone":"+1 480 860 2800",
    "sg:postcode":"85260",
    "sg:province":"AZ",
    "sg:tags":[
        "american"
    ],
    "wof:name":"Starbucks Coffee",
    "wof:placetype":"venue"
},
  "geometry": {"coordinates":[-111.88121099999999,33.628139],"type":"Point"}
}