{
  "type": "Feature",
  "properties": {
    "iso:country":"US",
    "sg:address":"2820 S Alma School Rd",
    "sg:city":"Chandler",
    "sg:classifiers":[
        {
            "category":"Building & Trades",
            "subcategory":"Locksmith",
            "type":"Services"
        }
    ],
    "sg:phone":"+1 602 732 7502",
    "sg:postcode":"85286",
    "sg:province":"AZ",
    "sg:tags":[
        "key"
    ],
    "wof:name":"24 7 Locksmith",
    "wof:placetype":"venue"
},
  "geometry": {"coordinates":[-111.858834,33.26458],"type":"Point"}
}