{
  "type": "Feature",
  "properties": {
    "iso:country":"US",
    "sg:address":"3221 W Genoa Way",
    "sg:city":"Chandler",
    "sg:classifiers":[
        {
            "category":"Shopping",
            "subcategory":"Jewelry",
            "type":"Retail Goods"
        }
    ],
    "sg:phone":"+1 480 821 1209",
    "sg:postcode":"85226",
    "sg:province":"AZ",
    "sg:tags":[
        "jeweler"
    ],
    "wof:name":"Earth Song Creations",
    "wof:placetype":"venue"
},
  "geometry": {"coordinates":[-111.898313,33.315181],"type":"Point"}
}