{
  "type": "Feature",
  "properties": {
    "iso:country":"US",
    "sg:address":"720 US Hwy 66",
    "sg:city":"Williams",
    "sg:classifiers":[
        {
            "category":"Travel",
            "subcategory":"Hotels & Motels",
            "type":"Entertainment"
        }
    ],
    "sg:phone":"+1 928 635 4464",
    "sg:postcode":"86046",
    "sg:province":"AZ",
    "wof:name":"Motel 6",
    "wof:placetype":"venue"
},
  "geometry": {"coordinates":[-112.179531,35.253343],"type":"Point"}
}