{
  "type": "Feature",
  "properties": {
    "iso:country":"US",
    "sg:address":"3444 E Camelback Rd",
    "sg:city":"Phoenix",
    "sg:classifiers":[
        {
            "category":"Professional",
            "subcategory":"Art Services",
            "type":"Services"
        }
    ],
    "sg:phone":"+1 602 224 1177",
    "sg:postcode":"85018",
    "sg:province":"AZ",
    "sg:tags":[
        "designer",
        "display",
        "producer"
    ],
    "wof:name":"Byo Design",
    "wof:placetype":"venue"
},
  "geometry": {"coordinates":[-112.00755,33.510115],"type":"Point"}
}