{
  "type": "Feature",
  "properties": {
    "addr:full":"3608 W Campbell Ave Phoenix AZ 85019",
    "addr:housenumber":"3608",
    "addr:postcode":"85019",
    "addr:street":"W Campbell Ave",
    "iso:country":"US",
    "sg:address":"3608 W Campbell Ave",
    "sg:city":"Phoenix",
    "sg:classifiers":[
        {
            "category":"Real Estate",
            "subcategory":"Real Estate Services",
            "type":"Services"
        }
    ],
    "sg:phone":"+1 602 973 1055",
    "sg:postcode":"85019",
    "sg:province":"AZ",
    "sg:tags":[
        "gage",
        "gauge"
    ],
    "wof:name":"Precision Speed Instruments",
    "wof:placetype":"venue"
},
  "geometry": {"coordinates":[-112.13558500000001,33.502163],"type":"Point"}
}