{
  "type": "Feature",
  "properties": {
    "iso:country":"US",
    "sg:address":"901 Main St",
    "sg:city":"Superior",
    "sg:classifiers":[
        {
            "category":"Freight",
            "type":"Transportation"
        }
    ],
    "sg:phone":"+1 520 689 2941",
    "sg:postcode":"85273",
    "sg:province":"AZ",
    "sg:tags":[
        "general"
    ],
    "wof:name":"District Warehouse",
    "wof:placetype":"venue"
},
  "geometry": {"coordinates":[-111.113838,33.286465],"type":"Point"}
}