{
  "type": "Feature",
  "properties": {
    "iso:country":"US",
    "sg:address":"707 S 3rd St",
    "sg:city":"Phoenix",
    "sg:classifiers":[
        {
            "category":"Professional",
            "subcategory":"Business Services",
            "type":"Services"
        }
    ],
    "sg:phone":"+1 602 255 0916",
    "sg:postcode":"85004",
    "sg:province":"AZ",
    "sg:tags":[
        "equipment",
        "microfilming"
    ],
    "wof:name":"Phoenix Micrographics Inc",
    "wof:placetype":"venue"
},
  "geometry": {"coordinates":[-112.069836,33.43919],"type":"Point"}
}