{
  "type": "Feature",
  "properties": {
    "iso:country":"US",
    "sg:address":"873 E Galveston St",
    "sg:city":"Chandler",
    "sg:classifiers":[
        {
            "category":"Home & Garden",
            "subcategory":"Carpets & Floor Coverings",
            "type":"Retail Goods"
        }
    ],
    "sg:phone":"+1 480 963 3877",
    "sg:postcode":"85225",
    "sg:province":"AZ",
    "wof:name":"E & J Custom Floors LLC",
    "wof:placetype":"venue"
},
  "geometry": {"coordinates":[-111.82764299999999,33.313392],"type":"Point"}
}