{
  "type": "Feature",
  "properties": {
    "iso:country":"US",
    "sg:address":"22020 N 21st Ave",
    "sg:city":"Phoenix",
    "sg:classifiers":[
        {
            "category":"Retail",
            "subcategory":"Repair Shop",
            "type":"Services"
        }
    ],
    "sg:phone":"+1 623 582 4171",
    "sg:postcode":"85027",
    "sg:province":"AZ",
    "sg:tags":[
        "m",
        "electrical"
    ],
    "wof:name":"Wessons Garage Doors",
    "wof:placetype":"venue"
},
  "geometry": {"coordinates":[-112.104357,33.685782],"type":"Point"}
}