{
  "type": "Feature",
  "properties": {
    "addr:full":"700 W 16th St Yuma AZ 85364",
    "addr:housenumber":"700",
    "addr:postcode":"85364",
    "addr:street":"W 16Th St",
    "iso:country":"US",
    "sg:address":"700 W 16th St",
    "sg:city":"Yuma",
    "sg:classifiers":[
        {
            "category":"Banks & Credit Unions",
            "subcategory":"Bank",
            "type":"Services"
        }
    ],
    "sg:phone":"+1 928 627 1504",
    "sg:postcode":"85364",
    "sg:province":"AZ",
    "sg:tags":[
        "mortgage"
    ],
    "wof:name":"Tucson Mortgage Company LLC",
    "wof:placetype":"venue"
},
  "geometry": {"coordinates":[-114.628242,32.698501],"type":"Point"}
}