{
  "type": "Feature",
  "properties": {
    "iso:country":"US",
    "sg:address":"7949 E Acoma Dr Ste 208",
    "sg:city":"Scottsdale",
    "sg:classifiers":[
        {
            "category":"Shopping",
            "subcategory":"Clothing, Apparel, & Fashions",
            "type":"Retail Goods"
        },
        {
            "category":"Manufacturing",
            "subcategory":"Apparel",
            "type":"Manufacturing & Wholesale Goods"
        }
    ],
    "sg:phone":"+1 480 951 2471",
    "sg:postcode":"85260",
    "sg:province":"AZ",
    "sg:tags":[
        "apparel-wholesale",
        "manufacturer",
        "women's"
    ],
    "wof:name":"Lone Mountain Designs",
    "wof:placetype":"venue"
},
  "geometry": {"coordinates":[-111.909184,33.617725],"type":"Point"}
}