{
  "type": "Feature",
  "properties": {
    "iso:country":"US",
    "sg:address":"600 W Hatcher Rd",
    "sg:city":"Phoenix",
    "sg:classifiers":[
        {
            "category":"Wholesale",
            "subcategory":"Electrical",
            "type":"Manufacturing & Wholesale Goods"
        },
        {
            "category":"Wholesale",
            "subcategory":"Durable Goods & Equipment",
            "type":"Manufacturing & Wholesale Goods"
        }
    ],
    "sg:phone":"+1 602 944 7474",
    "sg:postcode":"85021",
    "sg:province":"AZ",
    "sg:tags":[
        "product",
        "consumer",
        "representative",
        "manufacturer"
    ],
    "wof:name":"Pearson Southwest Marketing Co",
    "wof:placetype":"venue"
},
  "geometry": {"coordinates":[-112.08251,33.571247],"type":"Point"}
}