{
  "type": "Feature",
  "properties": {
    "iso:country":"US",
    "sg:address":"2992 N Alma School Rd Ste 2",
    "sg:city":"Chandler",
    "sg:classifiers":[
        {
            "category":"Personal",
            "subcategory":"Massage",
            "type":"Services"
        },
        {
            "category":"Health Services",
            "subcategory":"Health Practitioner",
            "type":"Services"
        }
    ],
    "sg:phone":"+1 480 917 6712",
    "sg:postcode":"85224",
    "sg:province":"AZ",
    "sg:tags":[
        "naturopathic/holistic"
    ],
    "sg:website":"www.moonstonemetaphysical.com/",
    "wof:name":"MoonStone Wellness",
    "wof:placetype":"venue"
},
  "geometry": {"coordinates":[-111.859077,33.349494],"type":"Point"}
}