{
  "type": "Feature",
  "properties": {
    "addr:full":"23910 N 19th Ave Ste 48 Phoenix AZ 85085",
    "addr:housenumber":"23910",
    "addr:postcode":"85085",
    "addr:street":"N 19Th Ave Ste 48",
    "iso:country":"US",
    "sg:address":"23910 N 19th Ave Ste 48",
    "sg:city":"Phoenix",
    "sg:classifiers":[
        {
            "category":"Health Services",
            "subcategory":"Hospital",
            "type":"Services"
        }
    ],
    "sg:phone":"+1 623 580 0556",
    "sg:postcode":"85085",
    "sg:province":"AZ",
    "sg:tags":[
        "equipment",
        "supply"
    ],
    "sg:website":"http://www.radscanmedical.com",
    "wof:name":"Radscan Medical Equipment Inc",
    "wof:placetype":"venue"
},
  "geometry": {"coordinates":[-112.099968,33.704423],"type":"Point"}
}