{
  "type": "Feature",
  "properties": {
    "addr:full":"5945 W Ray Rd Ste 13 Chandler AZ 85225",
    "addr:housenumber":"5945;13",
    "addr:postcode":"85225",
    "addr:street":"W Ray Rd Ste",
    "iso:country":"US",
    "sg:address":"5945 W Ray Rd Ste 13",
    "sg:city":"Chandler",
    "sg:classifiers":[
        {
            "category":"Restaurant",
            "type":"Food & Drink"
        },
        {
            "category":"Brewery",
            "type":"Food & Drink"
        }
    ],
    "sg:phone":"+1 480 705 9700",
    "sg:postcode":"85225",
    "sg:province":"AZ",
    "sg:tags":[
        "traditional",
        "american"
    ],
    "sg:website":"www.coppercanyonbrewery.com",
    "wof:name":"Copper Canyon Brewing & Alehouse",
    "wof:placetype":"venue"
},
  "geometry": {"coordinates":[-111.841792,33.306106],"type":"Point"}
}