{
  "type": "Feature",
  "properties": {
    "iso:country":"US",
    "sg:address":"2200 N Scottsdale Rd Ste H",
    "sg:city":"Scottsdale",
    "sg:classifiers":[
        {
            "category":"Personal",
            "subcategory":"Skin Care",
            "type":"Services"
        }
    ],
    "sg:phone":"+1 480 941 9436",
    "sg:postcode":"85257",
    "sg:province":"AZ",
    "sg:tags":[
        "linen",
        "supply"
    ],
    "wof:name":"Oak Street Linen Supply",
    "wof:placetype":"venue"
},
  "geometry": {"coordinates":[-111.926193,33.472122],"type":"Point"}
}