{
  "type": "Feature",
  "properties": {
    "iso:country":"US",
    "sg:address":"4368 W Olive Ave",
    "sg:city":"Glendale",
    "sg:classifiers":[
        {
            "category":"Retail",
            "subcategory":"Laundry & Dry Cleaning",
            "type":"Services"
        }
    ],
    "sg:phone":"+1 623 847 1678",
    "sg:postcode":"85302",
    "sg:province":"AZ",
    "sg:tags":[
        "cleaner",
        "commercial"
    ],
    "wof:name":"King's Dry Cleaners",
    "wof:placetype":"venue"
},
  "geometry": {"coordinates":[-112.153502,33.567532],"type":"Point"}
}