{
  "type": "Feature",
  "properties": {
    "iso:country":"US",
    "sg:address":"9744 W Northern Ave",
    "sg:city":"Peoria",
    "sg:classifiers":[
        {
            "category":"Shopping Center",
            "type":"Public Place"
        }
    ],
    "sg:phone":"+1 623 877 9975",
    "sg:postcode":"85345",
    "sg:province":"AZ",
    "sg:tags":[
        "mall"
    ],
    "wof:name":"Milard Mall Services Inc.",
    "wof:placetype":"venue"
},
  "geometry": {"coordinates":[-112.271304,33.551365],"type":"Point"}
}