{
  "type": "Feature",
  "properties": {
    "addr:full":"7729 E Clarence Pl Tucson AZ 85715",
    "addr:housenumber":"7729",
    "addr:postcode":"85715",
    "addr:street":"E Clarence Pl",
    "iso:country":"US",
    "sg:address":"7729 E Clarence Pl",
    "sg:city":"Tucson",
    "sg:classifiers":[
        {
            "category":"Building & Trades",
            "subcategory":"Construction",
            "type":"Services"
        }
    ],
    "sg:phone":"+1 520 721 7178",
    "sg:postcode":"85715",
    "sg:province":"AZ",
    "sg:tags":[
        "plumbing",
        "carpentry",
        "paper",
        "painting",
        "hanging"
    ],
    "wof:name":"Wests Home Maintenance & Repr",
    "wof:placetype":"venue"
},
  "geometry": {"coordinates":[-110.826443,32.243785],"type":"Point"}
}