{
  "type": "Feature",
  "properties": {
    "iso:country":"US",
    "sg:address":"2700 N Panorama Dr",
    "sg:city":"Prescott Valley",
    "sg:classifiers":[
        {
            "category":"Building & Trades",
            "subcategory":"Construction",
            "type":"Services"
        }
    ],
    "sg:phone":"+1 928 759 2397",
    "sg:postcode":"86314",
    "sg:province":"AZ",
    "sg:tags":[
        "contractor"
    ],
    "wof:name":"Abaugh Roofing Inc",
    "wof:placetype":"venue"
},
  "geometry": {"coordinates":[-112.324699,34.584928],"type":"Point"}
}