{
  "type": "Feature",
  "properties": {
    "iso:country":"US",
    "sg:address":"4515 S McClintock Dr Ste 221",
    "sg:city":"Tempe",
    "sg:classifiers":[
        {
            "category":"Shopping",
            "subcategory":"Jewelry",
            "type":"Retail Goods"
        }
    ],
    "sg:phone":"+1 480 990 0141",
    "sg:postcode":"85282",
    "sg:province":"AZ",
    "wof:name":"Balfour Traditions",
    "wof:placetype":"venue"
},
  "geometry": {"coordinates":[-111.90826300000001,33.384655],"type":"Point"}
}