{
  "type": "Feature",
  "properties": {
    "addr:full":"6070 W Behrend Dr Glendale AZ 85308",
    "addr:housenumber":"6070",
    "addr:postcode":"85308",
    "addr:street":"W Behrend Dr",
    "iso:country":"US",
    "sg:address":"6070 W Behrend Dr",
    "sg:city":"Glendale",
    "sg:classifiers":[
        {
            "category":"Banks & Credit Unions",
            "subcategory":"Bank",
            "type":"Services"
        }
    ],
    "sg:phone":"+1 623 561 6090",
    "sg:postcode":"85308",
    "sg:province":"AZ",
    "sg:tags":[
        "financing"
    ],
    "sg:website":"www.beneficial.com",
    "wof:name":"Beneficial Arizona Inc",
    "wof:placetype":"venue"
},
  "geometry": {"coordinates":[-112.187462,33.665317],"type":"Point"}
}