{
  "type": "Feature",
  "properties": {
    "iso:country":"US",
    "sg:address":"1825 W Marlette Ave",
    "sg:city":"Phoenix",
    "sg:classifiers":[
        {
            "category":"Real Estate",
            "subcategory":"Real Estate Services",
            "type":"Services"
        },
        {
            "category":"Professional",
            "subcategory":"Business Services",
            "type":"Services"
        }
    ],
    "sg:phone":"+1 602 595 1519",
    "sg:postcode":"85015",
    "sg:province":"AZ",
    "sg:tags":[
        "management",
        "organizing",
        "services-household"
    ],
    "wof:name":"Cid Management",
    "wof:placetype":"venue"
},
  "geometry": {"coordinates":[-112.09774,33.52932],"type":"Point"}
}