{
  "type": "Feature",
  "properties": {
    "iso:country":"US",
    "sg:address":"3780 Buoy Ln",
    "sg:city":"Lake Havasu City",
    "sg:classifiers":[
        {
            "category":"Building & Trades",
            "subcategory":"Construction",
            "type":"Services"
        }
    ],
    "sg:phone":"+1 928 680 1645",
    "sg:postcode":"86406",
    "sg:province":"AZ",
    "sg:tags":[
        "restoration",
        "cleaning",
        "patio",
        "deck"
    ],
    "wof:name":"First Class Power Washing",
    "wof:placetype":"venue"
},
  "geometry": {"coordinates":[-114.273871,34.486878],"type":"Point"}
}