{
  "type": "Feature",
  "properties": {
    "iso:country":"US",
    "sg:address":"15220 N 37th St",
    "sg:city":"Phoenix",
    "sg:classifiers":[
        {
            "category":"Manufacturing",
            "subcategory":"Retail Goods",
            "type":"Manufacturing & Wholesale Goods"
        }
    ],
    "sg:phone":"+1 602 403 1487",
    "sg:postcode":"85032",
    "sg:province":"AZ",
    "sg:tags":[
        "product",
        "mfg"
    ],
    "wof:name":"Luv Beads",
    "wof:placetype":"venue"
},
  "geometry": {"coordinates":[-112.00286,33.624636],"type":"Point"}
}