{
  "type": "Feature",
  "properties": {
    "iso:country":"US",
    "sg:address":"1044 Willow Creek Rd",
    "sg:city":"Prescott",
    "sg:classifiers":[
        {
            "category":"Restaurant",
            "type":"Food & Drink"
        }
    ],
    "sg:phone":"+1 928 445 4550",
    "sg:postcode":"86301",
    "sg:province":"AZ",
    "sg:tags":[
        "eating"
    ],
    "wof:name":"Starbucks",
    "wof:placetype":"venue"
},
  "geometry": {"coordinates":[-112.482302,34.562462],"type":"Point"}
}