{
  "type": "Feature",
  "properties": {
    "iso:country":"US",
    "sg:address":"2228 N Scottsdale Rd",
    "sg:city":"Scottsdale",
    "sg:classifiers":[
        {
            "category":"Personal",
            "type":"Services"
        },
        {
            "category":"Restaurant",
            "type":"Food & Drink"
        }
    ],
    "sg:phone":"+1 480 947 5479",
    "sg:postcode":"85257",
    "sg:province":"AZ",
    "sg:tags":[
        "eating"
    ],
    "wof:name":"Kam's Garden Restaurant",
    "wof:placetype":"venue"
},
  "geometry": {"coordinates":[-111.926121,33.470078],"type":"Point"}
}