{
  "type": "Feature",
  "properties": {
    "addr:full":"2036 E Baseline Rd Phoenix AZ 85042",
    "addr:housenumber":"2036",
    "addr:postcode":"85042",
    "addr:street":"E Baseline Rd",
    "iso:country":"US",
    "sg:address":"2036 E Baseline Rd",
    "sg:city":"Phoenix",
    "sg:classifiers":[
        {
            "category":"Home & Garden",
            "subcategory":"Home Furnishings",
            "type":"Retail Goods"
        }
    ],
    "sg:phone":"+1 602 243 6337",
    "sg:postcode":"85042",
    "sg:province":"AZ",
    "sg:tags":[
        "linen"
    ],
    "wof:name":"Anna's Linens",
    "wof:placetype":"venue"
},
  "geometry": {"coordinates":[-112.036513,33.377729],"type":"Point"}
}