{
  "type": "Feature",
  "properties": {
    "addr:full":"3614 N 24th St Phoenix AZ 85016",
    "addr:housenumber":"3614",
    "addr:postcode":"85016",
    "addr:street":"N 24Th St",
    "iso:country":"US",
    "sg:address":"3614 N 24th St",
    "sg:city":"Phoenix",
    "sg:classifiers":[
        {
            "category":"Manufacturing",
            "subcategory":"Printing",
            "type":"Manufacturing & Wholesale Goods"
        }
    ],
    "sg:phone":"+1 602 957 1270",
    "sg:postcode":"85016",
    "sg:province":"AZ",
    "sg:tags":[
        "publisher",
        "book"
    ],
    "wof:name":"Tucker Zeig & Company Inc",
    "wof:placetype":"venue"
},
  "geometry": {"coordinates":[-112.03019,33.489928],"type":"Point"}
}