{
  "type": "Feature",
  "properties": {
    "iso:country":"US",
    "sg:address":"3020 E Camelback Rd Ste 215",
    "sg:city":"Phoenix",
    "sg:classifiers":[
        {
            "category":"Real Estate",
            "subcategory":"Real Estate Services",
            "type":"Services"
        },
        {
            "category":"Real Estate",
            "subcategory":"Developer",
            "type":"Services"
        },
        {
            "category":"Real Estate",
            "subcategory":"Real Estate Agent",
            "type":"Services"
        },
        {
            "category":"Industrial Area",
            "type":"Public Place"
        }
    ],
    "sg:phone":"+1 602 957 9800",
    "sg:postcode":"85016",
    "sg:province":"AZ",
    "sg:tags":[
        "development",
        "investing",
        "commercial",
        "broker",
        "buyer"
    ],
    "sg:website":"http://www.phoenixcommercialadvisors.com",
    "wof:name":"Phoenix Commercial Advisors",
    "wof:placetype":"venue"
},
  "geometry": {"coordinates":[-112.01730000000001,33.509943],"type":"Point"}
}