{
  "type": "Feature",
  "properties": {
    "iso:country":"US",
    "sg:address":"8714 W Becker Ln",
    "sg:city":"Peoria",
    "sg:classifiers":[
        {
            "category":"Building & Trades",
            "subcategory":"Construction",
            "type":"Services"
        }
    ],
    "sg:phone":"+1 623 329 1833",
    "sg:postcode":"85345",
    "sg:province":"AZ",
    "sg:tags":[
        "mason",
        "masonry",
        "industrial",
        "contractors-commercial",
        "contractor"
    ],
    "wof:name":"Salas Masonary",
    "wof:placetype":"venue"
},
  "geometry": {"coordinates":[-112.24650699999999,33.582189],"type":"Point"}
}