{
  "type": "Feature",
  "properties": {
    "iso:country":"US",
    "sg:address":"901 S Dobson Rd",
    "sg:city":"Mesa",
    "sg:classifiers":[
        {
            "category":"Real Estate",
            "subcategory":"Real Estate Operator",
            "type":"Services"
        }
    ],
    "sg:phone":"+1 480 890 8033",
    "sg:postcode":"85202",
    "sg:province":"AZ",
    "sg:tags":[
        "apartment",
        "complex"
    ],
    "wof:name":"Dobson Village Apartments One",
    "wof:placetype":"venue"
},
  "geometry": {"coordinates":[-111.87459,33.397815],"type":"Point"}
}