{
  "type": "Feature",
  "properties": {
    "iso:country":"US",
    "sg:address":"2283 River Valley Pl",
    "sg:city":"Fort Mohave",
    "sg:classifiers":[
        {
            "category":"Shopping",
            "type":"Retail Goods"
        }
    ],
    "sg:phone":"+1 928 763 9078",
    "sg:postcode":"86426",
    "sg:province":"AZ",
    "sg:tags":[
        "merchandise"
    ],
    "wof:name":"Windsox Co",
    "wof:placetype":"venue"
},
  "geometry": {"coordinates":[-114.570215,35.032351],"type":"Point"}
}