{
  "type": "Feature",
  "properties": {
    "iso:country":"US",
    "sg:address":"4104 N Campbell Ave",
    "sg:city":"Tucson",
    "sg:classifiers":[
        {
            "category":"Education",
            "subcategory":"College",
            "type":"Public Place"
        }
    ],
    "sg:phone":"+1 520 323 7931",
    "sg:postcode":"85719",
    "sg:province":"AZ",
    "sg:tags":[
        "academic",
        "school"
    ],
    "wof:name":"University Of Arizona",
    "wof:placetype":"venue"
},
  "geometry": {"coordinates":[-110.94379,32.279505],"type":"Point"}
}