{
  "type": "Feature",
  "properties": {
    "addr:full":"4945 W Didion Dr Tucson AZ 85742",
    "addr:housenumber":"4945",
    "addr:postcode":"85742",
    "addr:street":"W Didion Dr",
    "iso:country":"US",
    "sg:address":"4945 W Didion Dr",
    "sg:city":"Tucson",
    "sg:classifiers":[
        {
            "category":"Personal",
            "subcategory":"Beauty Salon",
            "type":"Services"
        }
    ],
    "sg:phone":"+1 520 744 8936",
    "sg:postcode":"85742",
    "sg:province":"AZ",
    "wof:name":"Your Hair",
    "wof:placetype":"venue"
},
  "geometry": {"coordinates":[-111.071708,32.369613],"type":"Point"}
}