{
  "type": "Feature",
  "properties": {
    "iso:country":"US",
    "sg:address":"652 W Woodman Dr",
    "sg:city":"Tempe",
    "sg:classifiers":[
        {
            "category":"Building & Trades",
            "subcategory":"Construction",
            "type":"Services"
        }
    ],
    "sg:phone":"+1 480 839 8381",
    "sg:postcode":"85283",
    "sg:province":"AZ",
    "sg:tags":[
        "handyman"
    ],
    "wof:name":"Johnston Handyman Svc",
    "wof:placetype":"venue"
},
  "geometry": {"coordinates":[-111.95017799999999,33.362527],"type":"Point"}
}