{
  "type": "Feature",
  "properties": {
    "iso:country":"US",
    "sg:address":"3549 E Cambridge Ave",
    "sg:city":"Phoenix",
    "sg:classifiers":[
        {
            "category":"Health Services",
            "subcategory":"Clinic",
            "type":"Services"
        }
    ],
    "sg:phone":"+1 602 264 0010",
    "sg:postcode":"85008",
    "sg:province":"AZ",
    "sg:tags":[
        "information",
        "abortion"
    ],
    "wof:name":"Abortion Services Of Phoenix",
    "wof:placetype":"venue"
},
  "geometry": {"coordinates":[-112.007284,33.477632],"type":"Point"}
}