{
  "type": "Feature",
  "properties": {
    "iso:country":"US",
    "sg:address":"1863 W Rillito St",
    "sg:city":"Tucson",
    "sg:classifiers":[
        {
            "category":"Building & Trades",
            "subcategory":"Construction",
            "type":"Services"
        }
    ],
    "sg:phone":"+1 520 887 3490",
    "sg:postcode":"85705",
    "sg:province":"AZ",
    "sg:tags":[
        "excavating",
        "contractor"
    ],
    "wof:name":"Young & Sons Contracting Inc",
    "wof:placetype":"venue"
},
  "geometry": {"coordinates":[-111.005197,32.290477],"type":"Point"}
}