{
  "type": "Feature",
  "properties": {
    "addr:full":"756 N Standage Mesa AZ 85201",
    "addr:housenumber":"756",
    "addr:postcode":"85201",
    "addr:street":"N Standage",
    "iso:country":"US",
    "sg:address":"756 N Standage",
    "sg:city":"Mesa",
    "sg:classifiers":[
        {
            "category":"Professional",
            "type":"Services"
        }
    ],
    "sg:phone":"+1 480 964 4159",
    "sg:postcode":"85201",
    "sg:province":"AZ",
    "wof:name":"Geraldine Hawkins",
    "wof:placetype":"venue"
},
  "geometry": {"coordinates":[-111.86129800000001,33.42883],"type":"Point"}
}