{
  "type": "Feature",
  "properties": {
    "iso:country":"US",
    "sg:address":"3001 W Van Buren St",
    "sg:city":"Phoenix",
    "sg:classifiers":[
        {
            "category":"Autos & Motor Vehicles",
            "subcategory":"Automobile Sales",
            "type":"Retail Goods"
        }
    ],
    "sg:phone":"+1 602 455 4877",
    "sg:postcode":"85009",
    "sg:province":"AZ",
    "sg:tags":[
        "car",
        "used",
        "dealer"
    ],
    "wof:name":"Cachanilla Auto Sales",
    "wof:placetype":"venue"
},
  "geometry": {"coordinates":[-112.124921,33.451312],"type":"Point"}
}