{
  "type": "Feature",
  "properties": {
    "iso:country":"US",
    "sg:address":"3770 W Ina Rd",
    "sg:city":"Tucson",
    "sg:classifiers":[
        {
            "category":"Food & Beverages",
            "subcategory":"Groceries & Convenience Stores",
            "type":"Retail Goods"
        }
    ],
    "sg:phone":"+1 520 744 2472",
    "sg:postcode":"85741",
    "sg:province":"AZ",
    "wof:name":"Frys Food & Drug Store 36",
    "wof:placetype":"venue"
},
  "geometry": {"coordinates":[-111.045773,32.337584],"type":"Point"}
}