{
  "type": "Feature",
  "properties": {
    "addr:full":"6143 E Hannibal St Mesa AZ 85205",
    "addr:housenumber":"6143",
    "addr:postcode":"85205",
    "addr:street":"E Hannibal St",
    "iso:country":"US",
    "sg:address":"6143 E Hannibal St",
    "sg:city":"Mesa",
    "sg:classifiers":[
        {
            "category":"Building & Trades",
            "subcategory":"Construction",
            "type":"Services"
        }
    ],
    "sg:phone":"+1 480 654 0920",
    "sg:postcode":"85205",
    "sg:province":"AZ",
    "sg:tags":[
        "hanging",
        "contractor"
    ],
    "wof:name":"Southern Arizona Finishes Inc",
    "wof:placetype":"venue"
},
  "geometry": {"coordinates":[-111.696896,33.443803],"type":"Point"}
}