{
  "type": "Feature",
  "properties": {
    "addr:full":"6160 E Broadway Blvd Tucson AZ 85711",
    "addr:housenumber":"6160",
    "addr:postcode":"85711",
    "addr:street":"E Broadway Blvd",
    "iso:country":"US",
    "sg:address":"6160 E Broadway Blvd",
    "sg:city":"Tucson",
    "sg:classifiers":[
        {
            "category":"Autos & Motor Vehicles",
            "subcategory":"Automobile Sales",
            "type":"Retail Goods"
        }
    ],
    "sg:phone":"+1 520 881 6487",
    "sg:postcode":"85711",
    "sg:province":"AZ",
    "sg:tags":[
        "car",
        "dealer"
    ],
    "wof:name":"O'Rielly Mitsubishi",
    "wof:placetype":"venue"
},
  "geometry": {"coordinates":[-110.860202,32.221446],"type":"Point"}
}