{
  "type": "Feature",
  "properties": {
    "iso:country":"US",
    "sg:address":"2900 N Navajo Dr",
    "sg:city":"Prescott Valley",
    "sg:classifiers":[
        {
            "category":"Banks & Credit Unions",
            "subcategory":"Bank",
            "type":"Services"
        }
    ],
    "sg:phone":"+1 928 759 8004",
    "sg:postcode":"86314",
    "sg:province":"AZ",
    "wof:name":"Wells Fargo Bank",
    "wof:placetype":"venue"
},
  "geometry": {"coordinates":[-112.317854,34.586028],"type":"Point"}
}