{
  "type": "Feature",
  "properties": {
    "iso:country":"US",
    "sg:address":"1960 S Hopi Trl",
    "sg:city":"Dewey",
    "sg:classifiers":[
        {
            "category":"Manufacturing",
            "subcategory":"Printing",
            "type":"Manufacturing & Wholesale Goods"
        }
    ],
    "sg:phone":"+1 928 632 4525",
    "sg:postcode":"86327",
    "sg:province":"AZ",
    "sg:tags":[
        "screen"
    ],
    "wof:name":"Windyview Designs Dewey",
    "wof:placetype":"venue"
},
  "geometry": {"coordinates":[-112.298272,34.516768],"type":"Point"}
}