{
  "type": "Feature",
  "properties": {
    "iso:country":"US",
    "sg:address":"2050 W Dunlap Ave",
    "sg:city":"Phoenix",
    "sg:classifiers":[
        {
            "category":"Shopping",
            "type":"Retail Goods"
        }
    ],
    "sg:phone":"+1 602 943 7165",
    "sg:postcode":"85021",
    "sg:province":"AZ",
    "sg:tags":[
        "flag"
    ],
    "wof:name":"A A Flag Company",
    "wof:placetype":"venue"
},
  "geometry": {"coordinates":[-112.10454900000001,33.567646],"type":"Point"}
}