{
  "type": "Feature",
  "properties": {
    "iso:country":"US",
    "sg:address":"3981 N Business Center Dr",
    "sg:city":"Tucson",
    "sg:phone":"+1 520 748 2277",
    "sg:postcode":"85705",
    "sg:province":"AZ",
    "sg:website":"http://www.aufmuthmotors.com",
    "wof:name":"Aufmuth Motors",
    "wof:placetype":"venue"
},
  "geometry": {"coordinates":[-111.017789,32.279605],"type":"Point"}
}