{
  "type": "Feature",
  "properties": {
    "addr:full":"20827 N Cave Creek Rd Phoenix AZ 85024",
    "addr:housenumber":"20827",
    "addr:postcode":"85024",
    "addr:street":"N Cave Creek Rd",
    "iso:country":"US",
    "sg:address":"20827 N Cave Creek Rd",
    "sg:city":"Phoenix",
    "sg:classifiers":[
        {
            "category":"Wholesale",
            "subcategory":"Computers",
            "type":"Manufacturing & Wholesale Goods"
        },
        {
            "category":"Professional",
            "subcategory":"Computer Services",
            "type":"Services"
        }
    ],
    "sg:phone":"+1 602 445 7600",
    "sg:postcode":"85024",
    "sg:province":"AZ",
    "sg:tags":[
        "publisher",
        "software",
        "developer",
        "equipment"
    ],
    "wof:name":"Bitwits",
    "wof:placetype":"venue"
},
  "geometry": {"coordinates":[-112.031012,33.674937],"type":"Point"}
}