{
  "type": "Feature",
  "properties": {
    "addr:full":"2740 S Nolina Pl Chandler AZ 85286",
    "addr:housenumber":"2740",
    "addr:postcode":"85286",
    "addr:street":"S Nolina Pl",
    "iso:country":"US",
    "sg:address":"2740 S Nolina Pl",
    "sg:city":"Chandler",
    "sg:classifiers":[
        {
            "category":"Shopping",
            "subcategory":"Hobbies, Toys, & Games",
            "type":"Retail Goods"
        }
    ],
    "sg:phone":"+1 602 469 2686",
    "sg:postcode":"85286",
    "sg:province":"AZ",
    "sg:tags":[
        "craft"
    ],
    "wof:name":"Starlit Studio",
    "wof:placetype":"venue"
},
  "geometry": {"coordinates":[-111.871594,33.265243],"type":"Point"}
}