{
  "type": "Feature",
  "properties": {
    "addr:full":"8238 E Rancho Vista Dr Scottsdale AZ 85251",
    "addr:housenumber":"8238",
    "addr:postcode":"85251",
    "addr:street":"E Rancho Vista Dr",
    "iso:country":"US",
    "sg:address":"8238 E Rancho Vista Dr",
    "sg:city":"Scottsdale",
    "sg:classifiers":[
        {
            "category":"Retail",
            "subcategory":"Laundry & Dry Cleaning",
            "type":"Services"
        }
    ],
    "sg:phone":"+1 480 949 1517",
    "sg:postcode":"85251",
    "sg:province":"AZ",
    "sg:tags":[
        "compound"
    ],
    "wof:name":"Amway Distribution Bud & Yvonne Morrison",
    "wof:placetype":"venue"
},
  "geometry": {"coordinates":[-111.903278,33.506882],"type":"Point"}
}