{
  "type": "Feature",
  "properties": {
    "iso:country":"US",
    "sg:address":"17191 N 51st Dr",
    "sg:city":"Glendale",
    "sg:classifiers":[
        {
            "category":"Freight",
            "type":"Transportation"
        }
    ],
    "sg:phone":"+1 602 978 3741",
    "sg:postcode":"85308",
    "sg:province":"AZ",
    "wof:name":"Bestway Transportation Inc",
    "wof:placetype":"venue"
},
  "geometry": {"coordinates":[-112.169792,33.641057],"type":"Point"}
}