{
  "type": "Feature",
  "properties": {
    "addr:full":"5016 N Oracle Rd Tucson AZ 85704",
    "addr:housenumber":"5016",
    "addr:postcode":"85704",
    "addr:street":"N Oracle Rd",
    "iso:country":"US",
    "sg:address":"5016 N Oracle Rd",
    "sg:city":"Tucson",
    "sg:classifiers":[
        {
            "category":"Retail",
            "subcategory":"Veterinary Services",
            "type":"Services"
        }
    ],
    "sg:phone":"+1 520 293 8788",
    "sg:postcode":"85704",
    "sg:province":"AZ",
    "wof:name":"Desert Hills Pet Clinic",
    "wof:placetype":"venue"
},
  "geometry": {"coordinates":[-110.97844000000001,32.297919],"type":"Point"}
}