{
  "type": "Feature",
  "properties": {
    "addr:full":"5220 W Indian School Rd Phoenix AZ 85031",
    "addr:housenumber":"5220",
    "addr:postcode":"85031",
    "addr:street":"W Indian School Rd",
    "iso:country":"US",
    "sg:address":"5220 W Indian School Rd",
    "sg:city":"Phoenix",
    "sg:classifiers":[
        {
            "category":"Home & Garden",
            "subcategory":"Furniture",
            "type":"Retail Goods"
        }
    ],
    "sg:phone":"+1 623 245 2615",
    "sg:postcode":"85031",
    "sg:province":"AZ",
    "sg:tags":[
        "appliance"
    ],
    "wof:name":"Sears Outlet 4188",
    "wof:placetype":"venue"
},
  "geometry": {"coordinates":[-112.172888,33.495093],"type":"Point"}
}