{
  "type": "Feature",
  "properties": {
    "iso:country":"US",
    "sg:address":"2301 N. 27th Ave.",
    "sg:city":"Phoenix",
    "sg:classifiers":[
        {
            "category":"Autos & Motor Vehicles",
            "subcategory":"Auto Supplies",
            "type":"Retail Goods"
        }
    ],
    "sg:phone":"+1 602 348 3355",
    "sg:postcode":"85008",
    "sg:province":"AZ",
    "sg:tags":[
        "automobile",
        "stereo",
        "radio",
        "system"
    ],
    "wof:name":"Gamboas audio & tint",
    "wof:placetype":"venue"
},
  "geometry": {"coordinates":[-112.117119,33.47332],"type":"Point"}
}