{
  "type": "Feature",
  "properties": {
    "iso:country":"US",
    "sg:address":"1509 S Winchester Rd",
    "sg:city":"Apache Junction",
    "sg:classifiers":[
        {
            "category":"Wholesale",
            "subcategory":"Jewelry",
            "type":"Manufacturing & Wholesale Goods"
        }
    ],
    "sg:phone":"+1 480 677 6310",
    "sg:postcode":"85219",
    "sg:province":"AZ",
    "sg:tags":[
        "stone"
    ],
    "wof:name":"Aline Sterling LLC",
    "wof:placetype":"venue"
},
  "geometry": {"coordinates":[-111.54168199999999,33.401227],"type":"Point"}
}