{
  "type": "Feature",
  "properties": {
    "iso:country":"US",
    "sg:address":"4443 N Flowing Wells Rd",
    "sg:city":"Tucson",
    "sg:classifiers":[
        {
            "category":"Wholesale",
            "subcategory":"Electrical",
            "type":"Manufacturing & Wholesale Goods"
        }
    ],
    "sg:phone":"+1 520 888 3900",
    "sg:postcode":"85705",
    "sg:province":"AZ",
    "sg:tags":[
        "telecommunication"
    ],
    "sg:website":"www.ntds.org",
    "wof:name":"Convergence Group",
    "wof:placetype":"venue"
},
  "geometry": {"coordinates":[-110.995134,32.286971],"type":"Point"}
}