{
  "type": "Feature",
  "properties": {
    "iso:country":"US",
    "sg:address":"1839 W 1st Ave",
    "sg:city":"Mesa",
    "sg:classifiers":[
        {
            "category":"Manufacturing",
            "subcategory":"Metals",
            "type":"Manufacturing & Wholesale Goods"
        }
    ],
    "sg:phone":"+1 480 968 3287",
    "sg:postcode":"85202",
    "sg:province":"AZ",
    "sg:tags":[
        "blast",
        "works",
        "mfg",
        "trade",
        "fab",
        "contractor",
        "furnace"
    ],
    "wof:name":"Western Wire Forming Inc",
    "wof:placetype":"venue"
},
  "geometry": {"coordinates":[-111.870834,33.412162],"type":"Point"}
}