{
  "type": "Feature",
  "properties": {
    "iso:country":"US",
    "sg:address":"600 N Stone Ave",
    "sg:city":"Tucson",
    "sg:classifiers":[
        {
            "category":"Retail",
            "subcategory":"Auto Repair",
            "type":"Services"
        }
    ],
    "sg:phone":"+1 520 884 7758",
    "sg:postcode":"85705",
    "sg:province":"AZ",
    "sg:tags":[
        "repairing",
        "automobile"
    ],
    "sg:website":"www.milexauto.com",
    "wof:name":"Milex Auto Svc Ctr",
    "wof:placetype":"venue"
},
  "geometry": {"coordinates":[-110.971758,32.230313],"type":"Point"}
}