{
  "type": "Feature",
  "properties": {
    "iso:country":"US",
    "sg:address":"7745 W. Thomas Rd.",
    "sg:city":"Phoenix",
    "sg:classifiers":[
        {
            "category":"Fast Food",
            "type":"Food & Drink"
        }
    ],
    "sg:phone":"+1 623 247 1646",
    "sg:postcode":"85033",
    "sg:province":"AZ",
    "sg:website":"www.campero.com",
    "wof:name":"Pollo Campero",
    "wof:placetype":"venue"
},
  "geometry": {"coordinates":[-112.224375,33.480023],"type":"Point"}
}