{
  "type": "Feature",
  "properties": {
    "iso:country":"US",
    "sg:address":"120 E Van Buren St",
    "sg:city":"Phoenix",
    "sg:classifiers":[
        {
            "category":"Insurance",
            "subcategory":"Hazard Insurance",
            "type":"Services"
        },
        {
            "category":"Insurance",
            "subcategory":"Health Insurance",
            "type":"Services"
        }
    ],
    "sg:phone":"+1 602 252 4138",
    "sg:postcode":"85004",
    "sg:province":"AZ",
    "sg:tags":[
        "dental"
    ],
    "wof:name":"Delta Dental Of California",
    "wof:placetype":"venue"
},
  "geometry": {"coordinates":[-112.072289,33.451389],"type":"Point"}
}