{
  "type": "Feature",
  "properties": {
    "addr:full":"445 N Temple St Mesa AZ 85203",
    "addr:housenumber":"445",
    "addr:postcode":"85203",
    "addr:street":"N Temple St",
    "iso:country":"US",
    "sg:address":"445 N Temple St",
    "sg:city":"Mesa",
    "sg:classifiers":[
        {
            "category":"Manufacturing",
            "subcategory":"Buildings",
            "type":"Manufacturing & Wholesale Goods"
        }
    ],
    "sg:phone":"+1 480 570 2322",
    "sg:postcode":"85203",
    "sg:province":"AZ",
    "sg:tags":[
        "home",
        "builder"
    ],
    "wof:name":"Barry Custom",
    "wof:placetype":"venue"
},
  "geometry": {"coordinates":[-111.810219,33.42302],"type":"Point"}
}