{
  "type": "Feature",
  "properties": {
    "addr:full":"1171 E Rancho Vistoso Blvd Oro Valley AZ 85755",
    "addr:housenumber":"1171",
    "addr:postcode":"85755",
    "addr:street":"E Rancho Vistoso Blvd",
    "iso:country":"US",
    "sg:address":"1171 E Rancho Vistoso Blvd",
    "sg:city":"Oro Valley",
    "sg:classifiers":[
        {
            "category":"Health Services",
            "subcategory":"Chiropractor",
            "type":"Services"
        }
    ],
    "sg:phone":"+1 520 818 7788",
    "sg:postcode":"85755",
    "sg:province":"AZ",
    "wof:name":"Chiropractic USA",
    "wof:placetype":"venue"
},
  "geometry": {"coordinates":[-110.954206,32.465614],"type":"Point"}
}