{
  "type": "Feature",
  "properties": {
    "iso:country":"US",
    "sg:address":"1550 E Riviera Dr",
    "sg:city":"Chandler",
    "sg:classifiers":[
        {
            "category":"Insurance",
            "subcategory":"Insurance Agent",
            "type":"Services"
        }
    ],
    "sg:phone":"+1 480 802 2830",
    "sg:postcode":"85249",
    "sg:province":"AZ",
    "wof:name":"White Protection & Fincl Serv",
    "wof:placetype":"venue"
},
  "geometry": {"coordinates":[-111.81407299999999,33.21244],"type":"Point"}
}