{
  "type": "Feature",
  "properties": {
    "iso:country":"US",
    "sg:address":"3960 E Illinois St",
    "sg:city":"Tucson",
    "sg:classifiers":[
        {
            "category":"Home & Garden",
            "subcategory":"Mobile Homes",
            "type":"Retail Goods"
        },
        {
            "category":"Building & Trades",
            "subcategory":"Construction",
            "type":"Services"
        }
    ],
    "sg:phone":"+1 520 747 7870",
    "sg:postcode":"85714",
    "sg:province":"AZ",
    "sg:tags":[
        "rental",
        "trailer",
        "utility"
    ],
    "wof:name":"Desert Modulars Inc",
    "wof:placetype":"venue"
},
  "geometry": {"coordinates":[-110.899809,32.169027],"type":"Point"}
}