{
  "type": "Feature",
  "properties": {
    "iso:country":"US",
    "sg:address":"3431 E Elwood St",
    "sg:city":"Phoenix",
    "sg:classifiers":[
        {
            "category":"Shopping",
            "subcategory":"Stationery & Office Supplies",
            "type":"Retail Goods"
        },
        {
            "category":"Professional",
            "subcategory":"Business Services",
            "type":"Services"
        }
    ],
    "sg:phone":"+1 602 651 1600",
    "sg:postcode":"85040",
    "sg:province":"AZ",
    "sg:tags":[
        "envelope",
        "labeling",
        "store"
    ],
    "wof:name":"American Barcode and Rfid Inc",
    "wof:placetype":"venue"
},
  "geometry": {"coordinates":[-112.008242,33.414551],"type":"Point"}
}