{
  "type": "Feature",
  "properties": {
    "iso:country":"US",
    "sg:address":"222 E Baseline Rd",
    "sg:city":"Tempe",
    "sg:classifiers":[
        {
            "category":"Food & Beverages",
            "subcategory":"Groceries & Convenience Stores",
            "type":"Retail Goods"
        }
    ],
    "sg:phone":"+1 480 820 6205",
    "sg:postcode":"85283",
    "sg:province":"AZ",
    "wof:name":"Circle K",
    "wof:placetype":"venue"
},
  "geometry": {"coordinates":[-111.936976,33.378314],"type":"Point"}
}