{
  "type": "Feature",
  "properties": {
    "addr:full":"255 E Gurley St Prescott AZ 86301",
    "addr:housenumber":"255",
    "addr:postcode":"86301",
    "addr:street":"E Gurley St",
    "iso:country":"US",
    "sg:address":"255 E Gurley St",
    "sg:city":"Prescott",
    "sg:classifiers":[
        {
            "category":"Social Services",
            "type":"Services"
        }
    ],
    "sg:phone":"+1 928 771 3332",
    "sg:postcode":"86301",
    "sg:province":"AZ",
    "sg:tags":[
        "probation"
    ],
    "sg:website":"www.co.yavapai.az.us",
    "wof:name":"Yavapai County Adult Probation",
    "wof:placetype":"venue"
},
  "geometry": {"coordinates":[-112.466607,34.541779],"type":"Point"}
}