{
  "type": "Feature",
  "properties": {
    "addr:full":"2600 W Apache Trl Apache Junction AZ 85220",
    "addr:housenumber":"2600",
    "addr:postcode":"85220",
    "addr:street":"W Apache Trl",
    "iso:country":"US",
    "sg:address":"2600 W Apache Trl",
    "sg:city":"Apache Junction",
    "sg:classifiers":[
        {
            "category":"Restaurant",
            "type":"Food & Drink"
        }
    ],
    "sg:menulink":"http://www.allmenus.com/az/north-pinal/180162-jack-in-the-box/menu/",
    "sg:phone":"+1 480 671 1061",
    "sg:postcode":"85220",
    "sg:province":"AZ",
    "sg:tags":[
        "burger",
        "american"
    ],
    "wof:name":"Jack in the Box",
    "wof:placetype":"venue"
},
  "geometry": {"coordinates":[-111.574468,33.415837],"type":"Point"}
}