{
  "type": "Feature",
  "properties": {
    "iso:country":"US",
    "sg:address":"1351 US Hwy 70",
    "sg:city":"Safford",
    "sg:classifiers":[
        {
            "category":"Building & Trades",
            "subcategory":"Plumbing",
            "type":"Services"
        }
    ],
    "sg:phone":"+1 928 428 2919",
    "sg:postcode":"85546",
    "sg:province":"AZ",
    "sg:tags":[
        "plumbing",
        "contractor"
    ],
    "wof:name":"Joe's Plumbing",
    "wof:placetype":"venue"
},
  "geometry": {"coordinates":[-109.691495,32.825334],"type":"Point"}
}