{
  "type": "Feature",
  "properties": {
    "iso:country":"US",
    "sg:address":"2400 W Dragoon Rd",
    "sg:city":"Dragoon",
    "sg:classifiers":[
        {
            "category":"Travel",
            "subcategory":"Hotels & Motels",
            "type":"Entertainment"
        }
    ],
    "sg:phone":"+1 520 826 5410",
    "sg:postcode":"85609",
    "sg:province":"AZ",
    "sg:tags":[
        "breakfast",
        "accommodation",
        "bed"
    ],
    "wof:name":"And The Horse You Rode In On",
    "wof:placetype":"venue"
},
  "geometry": {"coordinates":[-109.964467,32.035918],"type":"Point"}
}