{
  "type": "Feature",
  "properties": {
    "addr:full":"9985 E Fanfol Dr Scottsdale AZ 85258",
    "addr:housenumber":"9985",
    "addr:postcode":"85258",
    "addr:street":"E Fanfol Dr",
    "iso:country":"US",
    "sg:address":"9985 E Fanfol Dr",
    "sg:city":"Scottsdale",
    "sg:classifiers":[
        {
            "category":"Shopping",
            "subcategory":"Musical Instruments",
            "type":"Retail Goods"
        }
    ],
    "sg:phone":"+1 480 391 9460",
    "sg:postcode":"85258",
    "sg:province":"AZ",
    "wof:name":"Musical Images",
    "wof:placetype":"venue"
},
  "geometry": {"coordinates":[-111.869299,33.573456],"type":"Point"}
}