{
  "type": "Feature",
  "properties": {
    "iso:country":"US",
    "sg:address":"1550 N Dysart Rd",
    "sg:city":"Goodyear",
    "sg:classifiers":[
        {
            "category":"Shopping",
            "subcategory":"Mobile Phones",
            "type":"Retail Goods"
        }
    ],
    "sg:phone":"+1 623 935 2323",
    "sg:postcode":"85395",
    "sg:province":"AZ",
    "sg:website":"www.bellsouth.com",
    "wof:name":"AT&T",
    "wof:placetype":"venue"
},
  "geometry": {"coordinates":[-112.341184,33.464528],"type":"Point"}
}