{
  "type": "Feature",
  "properties": {
    "addr:full":"230 W Elm St Nogales AZ 85621",
    "addr:housenumber":"230",
    "addr:postcode":"85621",
    "addr:street":"W Elm St",
    "iso:country":"US",
    "sg:address":"230 W Elm St",
    "sg:city":"Nogales",
    "sg:classifiers":[
        {
            "category":"Utilities",
            "subcategory":"Telephone",
            "type":"Services"
        }
    ],
    "sg:phone":"+1 520 287 9231",
    "sg:postcode":"85621",
    "sg:province":"AZ",
    "sg:tags":[
        "communications"
    ],
    "wof:name":"Qwest",
    "wof:placetype":"venue"
},
  "geometry": {"coordinates":[-110.94152,31.336614],"type":"Point"}
}