{
  "type": "Feature",
  "properties": {
    "iso:country":"US",
    "sg:address":"150 S Cam Seco",
    "sg:city":"Tucson",
    "sg:classifiers":[
        {
            "category":"Health Services",
            "subcategory":"Chiropractor",
            "type":"Services"
        }
    ],
    "sg:phone":"+1 520 296 8266",
    "sg:postcode":"85710",
    "sg:province":"AZ",
    "wof:name":"New Vision Chiropractic",
    "wof:placetype":"venue"
},
  "geometry": {"coordinates":[-110.806885,32.2204],"type":"Point"}
}