{
  "type": "Feature",
  "properties": {
    "iso:country":"US",
    "sg:address":"3218 N Oracle Rd",
    "sg:city":"Tucson",
    "sg:classifiers":[
        {
            "category":"Bars & Pubs",
            "type":"Food & Drink"
        }
    ],
    "sg:phone":"+1 520 293 9883",
    "sg:postcode":"85705",
    "sg:province":"AZ",
    "wof:name":"Mc Hugh's Good Times Lounge",
    "wof:placetype":"venue"
},
  "geometry": {"coordinates":[-110.977997,32.266019],"type":"Point"}
}