{
  "type": "Feature",
  "properties": {
    "iso:country":"US",
    "sg:address":"2039 W Union Hills Dr",
    "sg:city":"Phoenix",
    "sg:classifiers":[
        {
            "category":"Real Estate",
            "subcategory":"Real Estate Operator",
            "type":"Services"
        }
    ],
    "sg:phone":"+1 602 866 1030",
    "sg:postcode":"85027",
    "sg:province":"AZ",
    "sg:tags":[
        "building",
        "apartment"
    ],
    "wof:name":"Camino Village",
    "wof:placetype":"venue"
},
  "geometry": {"coordinates":[-112.1022,33.654651],"type":"Point"}
}