{
  "type": "Feature",
  "properties": {
    "addr:full":"37840 N 20th St Phoenix AZ 85086",
    "addr:housenumber":"37840",
    "addr:postcode":"85086",
    "addr:street":"N 20Th St",
    "iso:country":"US",
    "sg:address":"37840 N 20th St",
    "sg:city":"Phoenix",
    "sg:classifiers":[
        {
            "category":"Shopping",
            "type":"Retail Goods"
        }
    ],
    "sg:phone":"+1 623 465 7285",
    "sg:postcode":"85086",
    "sg:province":"AZ",
    "sg:tags":[
        "outdoor",
        "lighting",
        "specialty"
    ],
    "wof:name":"Anthem Ornamental Iron",
    "wof:placetype":"venue"
},
  "geometry": {"coordinates":[-112.03931,33.830449],"type":"Point"}
}