{
  "type": "Feature",
  "properties": {
    "iso:country":"US",
    "sg:address":"2327 N Richland St",
    "sg:city":"Phoenix",
    "sg:classifiers":[
        {
            "category":"Personal",
            "subcategory":"Beauty Salon",
            "type":"Services"
        }
    ],
    "sg:phone":"+1 602 435 7257",
    "sg:postcode":"85006",
    "sg:province":"AZ",
    "wof:name":"Lisa Marie Flesher",
    "wof:placetype":"venue"
},
  "geometry": {"coordinates":[-112.062839,33.473024],"type":"Point"}
}