{
  "type": "Feature",
  "properties": {
    "iso:country":"US",
    "sg:address":"2303 N 44th St",
    "sg:city":"Phoenix",
    "sg:classifiers":[
        {
            "category":"Building & Trades",
            "subcategory":"Landscaping Services",
            "type":"Services"
        }
    ],
    "sg:phone":"+1 602 768 5296",
    "sg:postcode":"85008",
    "sg:province":"AZ",
    "sg:tags":[
        "commercial",
        "landscape",
        "maintenance"
    ],
    "wof:name":"U S Lawns of Central Phoenix",
    "wof:placetype":"venue"
},
  "geometry": {"coordinates":[-111.986966,33.473969],"type":"Point"}
}