{
  "type": "Feature",
  "properties": {
    "iso:country":"US",
    "sg:address":"1645 Gardner Rd",
    "sg:city":"Fort Mohave",
    "sg:classifiers":[
        {
            "category":"Organizations",
            "subcategory":"Religious Organization",
            "type":"Services"
        }
    ],
    "sg:phone":"+1 928 763 8030",
    "sg:postcode":"86426",
    "sg:province":"AZ",
    "sg:tags":[
        "church"
    ],
    "wof:name":"Jehovah's Witnesses",
    "wof:placetype":"venue"
},
  "geometry": {"coordinates":[-114.592375,35.037053],"type":"Point"}
}