{
  "type": "Feature",
  "properties": {
    "iso:country":"US",
    "sg:address":"8370 E AZ-69",
    "sg:city":"Prescott Valley",
    "sg:classifiers":[
        {
            "category":"Restaurant",
            "type":"Food & Drink"
        }
    ],
    "sg:menulink":"http://www.allmenus.com/az/prescott/253430-olivas/menu/",
    "sg:phone":"+1 928 772 6070",
    "sg:postcode":"86314",
    "sg:province":"AZ",
    "sg:tags":[
        "mexican"
    ],
    "wof:name":"Olivas",
    "wof:placetype":"venue"
},
  "geometry": {"coordinates":[-112.317016,34.585459],"type":"Point"}
}