{
  "type": "Feature",
  "properties": {
    "addr:full":"2120 W Ina Rd Tucson AZ 85741",
    "addr:housenumber":"2120",
    "addr:postcode":"85741",
    "addr:street":"W Ina Rd",
    "iso:country":"US",
    "sg:address":"2120 W Ina Rd",
    "sg:city":"Tucson",
    "sg:classifiers":[
        {
            "category":"Insurance",
            "subcategory":"Insurance Agent",
            "type":"Services"
        }
    ],
    "sg:phone":"+1 520 877 7800",
    "sg:postcode":"85741",
    "sg:province":"AZ",
    "wof:name":"Verschave John",
    "wof:placetype":"venue"
},
  "geometry": {"coordinates":[-111.016425,32.337364],"type":"Point"}
}