{
  "type": "Feature",
  "properties": {
    "iso:country":"US",
    "sg:address":"2913 W Rose Ln",
    "sg:city":"Phoenix",
    "sg:classifiers":[
        {
            "category":"Shopping",
            "subcategory":"Bicycles & Sporting Goods",
            "type":"Retail Goods"
        }
    ],
    "sg:phone":"+1 602 589 0409",
    "sg:postcode":"85017",
    "sg:province":"AZ",
    "wof:name":"Acostas Bike Shop & Repair",
    "wof:placetype":"venue"
},
  "geometry": {"coordinates":[-112.12318500000001,33.527557],"type":"Point"}
}