{
  "type": "Feature",
  "properties": {
    "addr:full":"4151 W Thunderbird Rd Phoenix AZ 85053",
    "addr:housenumber":"4151",
    "addr:postcode":"85053",
    "addr:street":"W Thunderbird Rd",
    "iso:country":"US",
    "sg:address":"4151 W Thunderbird Rd",
    "sg:city":"Phoenix",
    "sg:classifiers":[
        {
            "category":"Insurance",
            "subcategory":"Insurance Agent",
            "type":"Services"
        },
        {
            "category":"Insurance",
            "subcategory":"Hazard Insurance",
            "type":"Services"
        },
        {
            "category":"Insurance",
            "subcategory":"Title Insurance",
            "type":"Services"
        }
    ],
    "sg:phone":"+1 602 548 8604",
    "sg:postcode":"85053",
    "sg:province":"AZ",
    "sg:tags":[
        "auto",
        "homeowner"
    ],
    "sg:website":"http://apps.amfam.com/agentlocator/DVOYCE?sourceid=yp3",
    "wof:name":"American Family Insurance- Rs Voyce Agency Inc",
    "wof:placetype":"venue"
},
  "geometry": {"coordinates":[-112.147774,33.610691],"type":"Point"}
}