{
  "type": "Feature",
  "properties": {
    "addr:full":"20022 N 67th Ave Glendale AZ 85308",
    "addr:housenumber":"20022",
    "addr:postcode":"85308",
    "addr:street":"N 67Th Ave",
    "iso:country":"US",
    "sg:address":"20022 N 67th Ave",
    "sg:city":"Glendale",
    "sg:classifiers":[
        {
            "category":"Shopping",
            "subcategory":"Discount & Variety Stores",
            "type":"Retail Goods"
        }
    ],
    "sg:phone":"+1 623 566 0385",
    "sg:postcode":"85308",
    "sg:province":"AZ",
    "wof:name":"Ten Thousand Villages",
    "wof:placetype":"venue"
},
  "geometry": {"coordinates":[-112.203076,33.665943],"type":"Point"}
}