{
  "type": "Feature",
  "properties": {
    "addr:full":"429 N 4th Ave Tucson AZ 85705",
    "addr:housenumber":"429",
    "addr:postcode":"85705",
    "addr:street":"N 4Th Ave",
    "iso:country":"US",
    "sg:address":"429 N 4th Ave",
    "sg:city":"Tucson",
    "sg:classifiers":[
        {
            "category":"Restaurant",
            "type":"Food & Drink"
        }
    ],
    "sg:phone":"+1 520 622 8207",
    "sg:postcode":"85705",
    "sg:province":"AZ",
    "wof:name":"Maya Quetzal",
    "wof:placetype":"venue"
},
  "geometry": {"coordinates":[-110.965654,32.227357],"type":"Point"}
}