{
  "type": "Feature",
  "properties": {
    "iso:country":"US",
    "sg:address":"2262 Grand Ave",
    "sg:city":"Phoenix",
    "sg:classifiers":[
        {
            "category":"Travel",
            "subcategory":"Hotels & Motels",
            "type":"Entertainment"
        }
    ],
    "sg:phone":"+1 602 258 3479",
    "sg:postcode":"85009",
    "sg:province":"AZ",
    "wof:name":"Rainbow Motel",
    "wof:placetype":"venue"
},
  "geometry": {"coordinates":[-112.10590500000001,33.470957],"type":"Point"}
}