{
  "type": "Feature",
  "properties": {
    "iso:country":"US",
    "sg:address":"12845 N Tatum Blvd",
    "sg:city":"Phoenix",
    "sg:classifiers":[
        {
            "category":"Shopping",
            "subcategory":"Clothing, Apparel, & Fashions",
            "type":"Retail Goods"
        }
    ],
    "sg:phone":"+1 602 923 8959",
    "sg:postcode":"85032",
    "sg:province":"AZ",
    "sg:tags":[
        "maternity",
        "wear"
    ],
    "wof:name":"Imaternity",
    "wof:placetype":"venue"
},
  "geometry": {"coordinates":[-111.977872,33.604244],"type":"Point"}
}