{
  "type": "Feature",
  "properties": {
    "addr:full":"910 W Willow Ave Phoenix AZ 85029",
    "addr:housenumber":"910",
    "addr:postcode":"85029",
    "addr:street":"W Willow Ave",
    "iso:country":"US",
    "sg:address":"910 W Willow Ave",
    "sg:city":"Phoenix",
    "sg:classifiers":[
        {
            "category":"Professional",
            "subcategory":"Engineering",
            "type":"Services"
        }
    ],
    "sg:phone":"+1 602 466 1988",
    "sg:postcode":"85029",
    "sg:province":"AZ",
    "sg:tags":[
        "civil",
        "contractor",
        "engineer"
    ],
    "wof:name":"K & T Engineering & Construction",
    "wof:placetype":"venue"
},
  "geometry": {"coordinates":[-112.08566,33.607084],"type":"Point"}
}