{
  "type": "Feature",
  "properties": {
    "addr:full":"2108 E Boston St Chandler AZ 85225",
    "addr:housenumber":"2108",
    "addr:postcode":"85225",
    "addr:street":"E Boston St",
    "iso:country":"US",
    "sg:address":"2108 E Boston St",
    "sg:city":"Chandler",
    "sg:classifiers":[
        {
            "category":"Freight",
            "type":"Transportation"
        }
    ],
    "sg:phone":"+1 480 621 7635",
    "sg:postcode":"85225",
    "sg:province":"AZ",
    "sg:tags":[
        "trucking"
    ],
    "wof:name":"Transfer Dude",
    "wof:placetype":"venue"
},
  "geometry": {"coordinates":[-111.803123,33.302103],"type":"Point"}
}