{
  "type": "Feature",
  "properties": {
    "addr:full":"1767 E Prince Rd Tucson AZ 85719",
    "addr:housenumber":"1767",
    "addr:postcode":"85719",
    "addr:street":"E Prince Rd",
    "iso:country":"US",
    "sg:address":"1767 E Prince Rd",
    "sg:city":"Tucson",
    "sg:classifiers":[
        {
            "category":"Banks & Credit Unions",
            "subcategory":"Bank",
            "type":"Services"
        },
        {
            "category":"Banks & Credit Unions",
            "subcategory":"Financial Services",
            "type":"Services"
        }
    ],
    "sg:phone":"+1 520 318 1224",
    "sg:postcode":"85719",
    "sg:province":"AZ",
    "sg:tags":[
        "saving",
        "loan",
        "commercial"
    ],
    "sg:website":"http://www.firstar.com",
    "wof:name":"Us Bank",
    "wof:placetype":"venue"
},
  "geometry": {"coordinates":[-110.945457,32.272202],"type":"Point"}
}