{
  "type": "Feature",
  "properties": {
    "addr:full":"602 E Roger Rd Tucson AZ 85705",
    "addr:housenumber":"602",
    "addr:postcode":"85705",
    "addr:street":"E Roger Rd",
    "iso:country":"US",
    "sg:address":"602 E Roger Rd",
    "sg:city":"Tucson",
    "sg:classifiers":[
        {
            "category":"Wholesale",
            "subcategory":"Books, Periodicals, & Newspapers",
            "type":"Manufacturing & Wholesale Goods"
        }
    ],
    "sg:phone":"+1 520 292 0011",
    "sg:postcode":"85705",
    "sg:province":"AZ",
    "sg:tags":[
        "correspondence",
        "course",
        "health",
        "for",
        "fitness"
    ],
    "wof:name":"Dswfitness",
    "wof:placetype":"venue"
},
  "geometry": {"coordinates":[-110.963426,32.279211],"type":"Point"}
}