{
  "type": "Feature",
  "properties": {
    "iso:country":"US",
    "sg:address":"7431 N Cobblestone Rd",
    "sg:city":"Tucson",
    "sg:classifiers":[
        {
            "category":"Building & Trades",
            "subcategory":"Construction",
            "type":"Services"
        }
    ],
    "sg:phone":"+1 520 577 3601",
    "sg:postcode":"85718",
    "sg:province":"AZ",
    "sg:tags":[
        "residential"
    ],
    "wof:name":"A H N Constr",
    "wof:placetype":"venue"
},
  "geometry": {"coordinates":[-110.9186,32.341177],"type":"Point"}
}