{
  "type": "Feature",
  "properties": {
    "iso:country":"US",
    "sg:address":"1940 E Thunderbird Rd",
    "sg:city":"Phoenix",
    "sg:classifiers":[
        {
            "category":"Real Estate",
            "subcategory":"Real Estate Agent",
            "type":"Services"
        }
    ],
    "sg:phone":"+1 602 957 7000",
    "sg:postcode":"85022",
    "sg:province":"AZ",
    "sg:tags":[
        "finding",
        "apartment",
        "rental"
    ],
    "sg:website":"www.aptfind.com",
    "wof:name":"Apartment Finders",
    "wof:placetype":"venue"
},
  "geometry": {"coordinates":[-112.042933,33.598061],"type":"Point"}
}