{
  "type": "Feature",
  "properties": {
    "addr:full":"2701 E Thomas Rd Ste E Phoenix AZ 85016",
    "addr:housenumber":"2701",
    "addr:postcode":"85016",
    "addr:street":"E Thomas Rd Ste E",
    "iso:country":"US",
    "sg:address":"2701 E Thomas Rd Ste E",
    "sg:city":"Phoenix",
    "sg:classifiers":[
        {
            "category":"Professional",
            "subcategory":"Accounting & Tax Preparation",
            "type":"Services"
        }
    ],
    "sg:phone":"+1 602 224 9038",
    "sg:postcode":"85016",
    "sg:province":"AZ",
    "sg:tags":[
        "bookkeeping"
    ],
    "wof:name":"Henry Wright Inc",
    "wof:placetype":"venue"
},
  "geometry": {"coordinates":[-112.023712,33.480389],"type":"Point"}
}