{
  "type": "Feature",
  "properties": {
    "addr:full":"15309 N 183rd Dr Surprise AZ 85388",
    "addr:housenumber":"15309",
    "addr:postcode":"85388",
    "addr:street":"N 183Rd Dr",
    "iso:country":"US",
    "sg:address":"15309 N 183rd Dr",
    "sg:city":"Surprise",
    "sg:classifiers":[
        {
            "category":"Building & Trades",
            "subcategory":"Pest Control",
            "type":"Services"
        }
    ],
    "sg:phone":"+1 623 399 9970",
    "sg:postcode":"85388",
    "sg:province":"AZ",
    "wof:name":"Greenleaf Pest Control",
    "wof:placetype":"venue"
},
  "geometry": {"coordinates":[-112.453653,33.623303],"type":"Point"}
}