{
  "type": "Feature",
  "properties": {
    "iso:country":"US",
    "sg:address":"10475 E Sahuaro Dr",
    "sg:city":"Scottsdale",
    "sg:classifiers":[
        {
            "category":"Banks & Credit Unions",
            "subcategory":"Bank",
            "type":"Services"
        }
    ],
    "sg:phone":"+1 480 391 2589",
    "sg:postcode":"85259",
    "sg:province":"AZ",
    "sg:tags":[
        "short",
        "institution",
        "business"
    ],
    "wof:name":"Funding Analysis Corp",
    "wof:placetype":"venue"
},
  "geometry": {"coordinates":[-111.855298,33.584224],"type":"Point"}
}