{
  "type": "Feature",
  "properties": {
    "addr:full":"150 Coronado Blvd Clifton AZ 85533",
    "addr:housenumber":"150",
    "addr:postcode":"85533",
    "addr:street":"Coronado Blvd",
    "iso:country":"US",
    "sg:address":"150 Coronado Blvd",
    "sg:city":"Clifton",
    "sg:classifiers":[
        {
            "category":"Autos & Motor Vehicles",
            "subcategory":"Automobile Sales",
            "type":"Retail Goods"
        }
    ],
    "sg:phone":"+1 928 865 5851",
    "sg:postcode":"85533",
    "sg:province":"AZ",
    "sg:tags":[
        "car",
        "dealer"
    ],
    "wof:name":"Kempton Chevrolet Buick Geo",
    "wof:placetype":"venue"
},
  "geometry": {"coordinates":[-109.294887,33.048972],"type":"Point"}
}