{
  "type": "Feature",
  "properties": {
    "iso:country":"US",
    "sg:address":"9028 E Laurel Ln",
    "sg:city":"Scottsdale",
    "sg:classifiers":[
        {
            "category":"Professional",
            "type":"Services"
        }
    ],
    "sg:phone":"+1 480 391 0103",
    "sg:postcode":"85260",
    "sg:province":"AZ",
    "wof:name":"Robert J Prokopuk",
    "wof:placetype":"venue"
},
  "geometry": {"coordinates":[-111.885735,33.595395],"type":"Point"}
}