{
  "type": "Feature",
  "properties": {
    "iso:country":"US",
    "sg:address":"11212 N Sundown Dr",
    "sg:city":"Scottsdale",
    "sg:phone":"+1 480 596 2690",
    "sg:postcode":"85260",
    "sg:province":"AZ",
    "sg:tags":[
        "equipment",
        "commercial"
    ],
    "wof:name":"Cactus Merchandising",
    "wof:placetype":"venue"
},
  "geometry": {"coordinates":[-111.91646,33.586016],"type":"Point"}
}