{
  "type": "Feature",
  "properties": {
    "addr:full":"3050 N Navajo Dr Prescott Valley AZ 86314",
    "addr:housenumber":"3050",
    "addr:postcode":"86314",
    "addr:street":"N Navajo Dr",
    "iso:country":"US",
    "sg:address":"3050 N Navajo Dr",
    "sg:city":"Prescott Valley",
    "sg:classifiers":[
        {
            "category":"Banks & Credit Unions",
            "subcategory":"Bank",
            "type":"Services"
        }
    ],
    "sg:phone":"+1 928 445 9795",
    "sg:postcode":"86314",
    "sg:province":"AZ",
    "sg:tags":[
        "loan",
        "broker",
        "real estate"
    ],
    "wof:name":"Sunrise Financial Inc",
    "wof:placetype":"venue"
},
  "geometry": {"coordinates":[-112.316349,34.589002],"type":"Point"}
}