{
  "type": "Feature",
  "properties": {
    "addr:full":"2502 W Huntington Dr Tempe AZ 85282",
    "addr:housenumber":"2502",
    "addr:postcode":"85282",
    "addr:street":"W Huntington Dr",
    "iso:country":"US",
    "sg:address":"2502 W Huntington Dr",
    "sg:city":"Tempe",
    "sg:classifiers":[
        {
            "category":"Home & Garden",
            "subcategory":"Building Materials",
            "type":"Retail Goods"
        }
    ],
    "sg:phone":"+1 602 454 7205",
    "sg:postcode":"85282",
    "sg:province":"AZ",
    "sg:tags":[
        "equipment",
        "electric",
        "supply"
    ],
    "wof:name":"Primarion Inc",
    "wof:placetype":"venue"
},
  "geometry": {"coordinates":[-111.97522499999999,33.394258],"type":"Point"}
}