{
  "type": "Feature",
  "properties": {
    "iso:country":"US",
    "sg:address":"3805 N 35th Ave",
    "sg:city":"Phoenix",
    "sg:classifiers":[
        {
            "category":"Home & Garden",
            "subcategory":"Carpets & Floor Coverings",
            "type":"Retail Goods"
        }
    ],
    "sg:phone":"+1 602 278 8779",
    "sg:postcode":"85017",
    "sg:province":"AZ",
    "wof:name":"The 1 Carpet Connection",
    "wof:placetype":"venue"
},
  "geometry": {"coordinates":[-112.134204,33.491142],"type":"Point"}
}