{
  "type": "Feature",
  "properties": {
    "iso:country":"US",
    "sg:address":"222 W Hopi Dr",
    "sg:city":"Holbrook",
    "sg:classifiers":[
        {
            "category":"Food & Beverages",
            "subcategory":"Groceries & Convenience Stores",
            "type":"Retail Goods"
        }
    ],
    "sg:phone":"+1 928 524 3027",
    "sg:postcode":"86025",
    "sg:province":"AZ",
    "wof:name":"Circle K",
    "wof:placetype":"venue"
},
  "geometry": {"coordinates":[-110.16166200000001,34.902067],"type":"Point"}
}