{
  "type": "Feature",
  "properties": {
    "iso:country":"US",
    "sg:address":"8024 N 51st Ave",
    "sg:city":"Glendale",
    "sg:classifiers":[
        {
            "category":"Health Services",
            "subcategory":"Chiropractor",
            "type":"Services"
        }
    ],
    "sg:phone":"+1 623 937 6151",
    "sg:postcode":"85301",
    "sg:province":"AZ",
    "wof:name":"Bickerton Family Chiropractor",
    "wof:placetype":"venue"
},
  "geometry": {"coordinates":[-112.168877,33.555349],"type":"Point"}
}