{
  "type": "Feature",
  "properties": {
    "iso:country":"US",
    "sg:address":"4950 E Elliot Rd Ste 101C",
    "sg:city":"Phoenix",
    "sg:classifiers":[
        {
            "category":"Health Services",
            "subcategory":"Dentist",
            "type":"Services"
        }
    ],
    "sg:phone":"+1 480 779 9918",
    "sg:postcode":"85044",
    "sg:province":"AZ",
    "sg:tags":[
        "dentists-cosmetic",
        "denture",
        "dentists-prosthodontists",
        "dentistry",
        "implant",
        "dentists-orthodontists",
        "dentists-implantology"
    ],
    "sg:website":"http://www.sharpsmile.com",
    "wof:name":"Ahwatukee Dental - General Dentists",
    "wof:placetype":"venue"
},
  "geometry": {"coordinates":[-111.976914,33.349041],"type":"Point"}
}