{
  "type": "Feature",
  "properties": {
    "iso:country":"US",
    "sg:address":"303 E Eva St",
    "sg:city":"Phoenix",
    "sg:classifiers":[
        {
            "category":"Community Center",
            "subcategory":"Senior",
            "type":"Public Place"
        },
        {
            "category":"Social Services",
            "subcategory":"Adult Care",
            "type":"Services"
        }
    ],
    "sg:phone":"+1 602 870 6374",
    "sg:postcode":"85020",
    "sg:province":"AZ",
    "sg:tags":[
        "counseling",
        "centers-adult",
        "day",
        "citizen"
    ],
    "wof:name":"John C Lincoln Adult Day Hlth",
    "wof:placetype":"venue"
},
  "geometry": {"coordinates":[-112.06952699999999,33.569111],"type":"Point"}
}