{
  "type": "Feature",
  "properties": {
    "addr:full":"1818 W Glendale Ave Phoenix AZ 85021",
    "addr:housenumber":"1818",
    "addr:postcode":"85021",
    "addr:street":"W Glendale Ave",
    "iso:country":"US",
    "sg:address":"1818 W Glendale Ave",
    "sg:city":"Phoenix",
    "sg:classifiers":[
        {
            "category":"Bars & Pubs",
            "type":"Food & Drink"
        }
    ],
    "sg:phone":"+1 602 995 5897",
    "sg:postcode":"85021",
    "sg:province":"AZ",
    "sg:tags":[
        "drinking",
        "restaurant"
    ],
    "wof:name":"Westwood Tap & Grill",
    "wof:placetype":"venue"
},
  "geometry": {"coordinates":[-112.098287,33.538608],"type":"Point"}
}