{
  "type": "Feature",
  "properties": {
    "addr:full":"2426 S Palm Springs Dr Tucson AZ 85710",
    "addr:housenumber":"2426",
    "addr:postcode":"85710",
    "addr:street":"S Palm Springs Dr",
    "iso:country":"US",
    "sg:address":"2426 S Palm Springs Dr",
    "sg:city":"Tucson",
    "sg:classifiers":[
        {
            "category":"Building & Trades",
            "subcategory":"Construction",
            "type":"Services"
        }
    ],
    "sg:phone":"+1 520 731 3377",
    "sg:postcode":"85710",
    "sg:province":"AZ",
    "sg:tags":[
        "contractor"
    ],
    "wof:name":"Generation III Builders Inc",
    "wof:placetype":"venue"
},
  "geometry": {"coordinates":[-110.798891,32.192091],"type":"Point"}
}