{
  "type": "Feature",
  "properties": {
    "iso:country":"US",
    "sg:address":"14015 N 51st Ave",
    "sg:city":"Glendale",
    "sg:classifiers":[
        {
            "category":"Wholesale",
            "subcategory":"Medical Equipment & Supplies",
            "type":"Manufacturing & Wholesale Goods"
        },
        {
            "category":"Shopping",
            "subcategory":"Pharmacy",
            "type":"Retail Goods"
        }
    ],
    "sg:phone":"+1 602 843 0688",
    "sg:postcode":"85306",
    "sg:province":"AZ",
    "sg:tags":[
        "appliance",
        "prosthetic",
        "surgical",
        "orthopedic",
        "health",
        "device",
        "home",
        "care"
    ],
    "wof:name":"Hanger Prosthetics & Orthotics",
    "wof:placetype":"venue"
},
  "geometry": {"coordinates":[-112.168457,33.613734],"type":"Point"}
}