{
  "type": "Feature",
  "properties": {
    "iso:country":"US",
    "sg:address":"12449 N 36th Dr",
    "sg:city":"Phoenix",
    "sg:classifiers":[
        {
            "category":"Professional",
            "subcategory":"Art Services",
            "type":"Services"
        }
    ],
    "sg:phone":"+1 602 978 5646",
    "sg:postcode":"85029",
    "sg:province":"AZ",
    "sg:tags":[
        "engraving",
        "separations-offset",
        "color",
        "photo"
    ],
    "wof:name":"Terry St Clair",
    "wof:placetype":"venue"
},
  "geometry": {"coordinates":[-112.135794,33.600118],"type":"Point"}
}