{
  "type": "Feature",
  "properties": {
    "addr:full":"2200 N Arizona Ave Ste 3 Chandler AZ 85225",
    "addr:housenumber":"2200",
    "addr:postcode":"85225",
    "addr:street":"N Arizona Ave Ste 3",
    "iso:country":"US",
    "sg:address":"2200 N Arizona Ave Ste 3",
    "sg:city":"Chandler",
    "sg:classifiers":[
        {
            "category":"Shopping",
            "subcategory":"Bicycles & Sporting Goods",
            "type":"Retail Goods"
        },
        {
            "category":"Sports & Exercise",
            "subcategory":"Bicycle Rental",
            "type":"Entertainment"
        }
    ],
    "sg:phone":"+1 480 963 2174",
    "sg:postcode":"85225",
    "sg:province":"AZ",
    "sg:tags":[
        "bike",
        "wear"
    ],
    "sg:website":"www.serenityrideshop.com",
    "wof:name":"Serenity Ride Shop",
    "wof:placetype":"venue"
},
  "geometry": {"coordinates":[-111.842883,33.34021],"type":"Point"}
}