{
  "type": "Feature",
  "properties": {
    "addr:full":"1468 N 26th Ave Phoenix AZ 85009",
    "addr:housenumber":"1468",
    "addr:postcode":"85009",
    "addr:street":"N 26Th Ave",
    "iso:country":"US",
    "sg:address":"1468 N 26th Ave",
    "sg:city":"Phoenix",
    "sg:classifiers":[
        {
            "category":"Building & Trades",
            "subcategory":"Construction",
            "type":"Services"
        }
    ],
    "sg:phone":"+1 602 437 4400",
    "sg:postcode":"85009",
    "sg:province":"AZ",
    "sg:tags":[
        "contractor"
    ],
    "wof:name":"Sierra Tile Supply Inc",
    "wof:placetype":"venue"
},
  "geometry": {"coordinates":[-112.115098,33.465105],"type":"Point"}
}