{
  "type": "Feature",
  "properties": {
    "addr:full":"7474 E Speedway Blvd Tucson AZ 85710",
    "addr:housenumber":"7474",
    "addr:postcode":"85710",
    "addr:street":"E Speedway Blvd",
    "iso:country":"US",
    "sg:address":"7474 E Speedway Blvd",
    "sg:city":"Tucson",
    "sg:classifiers":[
        {
            "category":"Building & Trades",
            "subcategory":"Construction",
            "type":"Services"
        }
    ],
    "sg:phone":"+1 520 290 9800",
    "sg:postcode":"85710",
    "sg:province":"AZ",
    "sg:tags":[
        "general",
        "contractor"
    ],
    "sg:website":"www.tmbuilding.com",
    "wof:name":"T M Building & Development Inc",
    "wof:placetype":"venue"
},
  "geometry": {"coordinates":[-110.83187700000001,32.235491],"type":"Point"}
}