{
  "type": "Feature",
  "properties": {
    "iso:country":"US",
    "sg:address":"1148 E Aero Park Blvd",
    "sg:city":"Tucson",
    "sg:classifiers":[
        {
            "category":"Banks & Credit Unions",
            "subcategory":"Bank",
            "type":"Services"
        }
    ],
    "sg:phone":"+1 520 794 7259",
    "sg:postcode":"85706",
    "sg:province":"AZ",
    "sg:tags":[
        "national",
        "commercial"
    ],
    "wof:name":"Banc Tec Inc",
    "wof:placetype":"venue"
},
  "geometry": {"coordinates":[-110.955341,32.110711],"type":"Point"}
}