{
  "type": "Feature",
  "properties": {
    "iso:country":"US",
    "sg:address":"3841 E Refinery Way",
    "sg:city":"Tucson",
    "sg:classifiers":[
        {
            "category":"Wholesale",
            "subcategory":"Petroleum",
            "type":"Manufacturing & Wholesale Goods"
        }
    ],
    "sg:phone":"+1 520 748 1087",
    "sg:postcode":"85713",
    "sg:province":"AZ",
    "sg:tags":[
        "pipe",
        "line",
        "company"
    ],
    "sg:website":"www.kindermorganenergy.com",
    "wof:name":"Santa Fe Pacific Pipeline",
    "wof:placetype":"venue"
},
  "geometry": {"coordinates":[-110.912185,32.178158],"type":"Point"}
}