{
  "type": "Feature",
  "properties": {
    "iso:country":"US",
    "sg:address":"810 N 6th Ave",
    "sg:city":"Phoenix",
    "sg:classifiers":[
        {
            "category":"Personal",
            "type":"Services"
        }
    ],
    "sg:phone":"+1 602 266 5399",
    "sg:postcode":"85003",
    "sg:province":"AZ",
    "sg:tags":[
        "counseling"
    ],
    "sg:website":"http://www.pppassociates.com",
    "wof:name":"Agape Chiropractic",
    "wof:placetype":"venue"
},
  "geometry": {"coordinates":[-112.081391,33.456901],"type":"Point"}
}