{
  "type": "Feature",
  "properties": {
    "iso:country":"US",
    "sg:address":"13220 W Twin Peaks Rd",
    "sg:city":"Marana",
    "sg:classifiers":[
        {
            "category":"Professional",
            "type":"Services"
        }
    ],
    "sg:phone":"+1 520 682 2400",
    "sg:postcode":"85653",
    "sg:province":"AZ",
    "sg:tags":[
        "establishment"
    ],
    "wof:name":"Dream With Colors",
    "wof:placetype":"venue"
},
  "geometry": {"coordinates":[-111.246218,32.380749],"type":"Point"}
}