{
  "type": "Feature",
  "properties": {
    "iso:country":"US",
    "sg:address":"1119 E Saddle Mountain Rd",
    "sg:city":"Phoenix",
    "sg:classifiers":[
        {
            "category":"Professional",
            "subcategory":"Detective & Security Services",
            "type":"Services"
        }
    ],
    "sg:phone":"+1 623 776 2192",
    "sg:postcode":"85086",
    "sg:province":"AZ",
    "sg:tags":[
        "investigator"
    ],
    "wof:name":"Mullen & Varela Inc",
    "wof:placetype":"venue"
},
  "geometry": {"coordinates":[-112.059225,33.849832],"type":"Point"}
}