{
  "type": "Feature",
  "properties": {
    "iso:country":"US",
    "sg:address":"14064 W Yuma Rd",
    "sg:city":"Goodyear",
    "sg:classifiers":[
        {
            "category":"Communications",
            "subcategory":"Television Station",
            "type":"Services"
        }
    ],
    "sg:phone":"+1 623 925 4730",
    "sg:postcode":"85338",
    "sg:province":"AZ",
    "sg:tags":[
        "satellite",
        "cable"
    ],
    "wof:name":"Cable Tv Alternatives",
    "wof:placetype":"venue"
},
  "geometry": {"coordinates":[-112.36446,33.435402],"type":"Point"}
}