{
  "type": "Feature",
  "properties": {
    "addr:full":"12506 W Campbell Ave Litchfield Park AZ 85340",
    "addr:housenumber":"12506",
    "addr:postcode":"85340",
    "addr:street":"W Campbell Ave",
    "iso:country":"US",
    "sg:address":"12506 W Campbell Ave",
    "sg:city":"Litchfield Park",
    "sg:classifiers":[
        {
            "category":"Retail",
            "subcategory":"Portrait Studio",
            "type":"Services"
        }
    ],
    "sg:phone":"+1 623 582 6200",
    "sg:postcode":"85340",
    "sg:province":"AZ",
    "sg:tags":[
        "photographer"
    ],
    "wof:name":"Nelson's Wedding & Portrait",
    "wof:placetype":"venue"
},
  "geometry": {"coordinates":[-112.329018,33.501504],"type":"Point"}
}