{
  "type": "Feature",
  "properties": {
    "iso:country":"US",
    "sg:address":"449 S Lebaron",
    "sg:city":"Mesa",
    "sg:classifiers":[
        {
            "category":"Building & Trades",
            "subcategory":"Construction",
            "type":"Services"
        }
    ],
    "sg:phone":"+1 480 834 6003",
    "sg:postcode":"85210",
    "sg:province":"AZ",
    "sg:tags":[
        "contractor"
    ],
    "wof:name":"Sun Dial Masonry Inc",
    "wof:placetype":"venue"
},
  "geometry": {"coordinates":[-111.837834,33.405783],"type":"Point"}
}