{
  "type": "Feature",
  "properties": {
    "iso:country":"US",
    "sg:address":"10328 W Indian School Rd",
    "sg:city":"Phoenix",
    "sg:classifiers":[
        {
            "category":"Food & Beverages",
            "subcategory":"Cheese",
            "type":"Retail Goods"
        },
        {
            "category":"Food & Beverages",
            "subcategory":"Meat & Fish",
            "type":"Retail Goods"
        }
    ],
    "sg:phone":"+1 623 877 8180",
    "sg:postcode":"85037",
    "sg:province":"AZ",
    "sg:tags":[
        "cheesesteaks",
        "hot",
        "dog"
    ],
    "wof:name":"Big Daddy's Hot Dogs and Cheesesteaks",
    "wof:placetype":"venue"
},
  "geometry": {"coordinates":[-112.279502,33.493761],"type":"Point"}
}