{
  "type": "Feature",
  "properties": {
    "addr:full":"741 E Kyle Dr Gilbert AZ 85296",
    "addr:housenumber":"741",
    "addr:postcode":"85296",
    "addr:street":"E Kyle Dr",
    "iso:country":"US",
    "sg:address":"741 E Kyle Dr",
    "sg:city":"Gilbert",
    "sg:classifiers":[
        {
            "category":"Professional",
            "subcategory":"Engineering",
            "type":"Services"
        }
    ],
    "sg:phone":"+1 480 813 1145",
    "sg:postcode":"85296",
    "sg:province":"AZ",
    "sg:tags":[
        "electronic",
        "electrical",
        "engineer"
    ],
    "wof:name":"Automation Solutions",
    "wof:placetype":"venue"
},
  "geometry": {"coordinates":[-111.774492,33.330629],"type":"Point"}
}