{
  "type": "Feature",
  "properties": {
    "iso:country":"US",
    "sg:address":"9040 S Central Ave",
    "sg:city":"Phoenix",
    "sg:classifiers":[
        {
            "category":"Food & Beverages",
            "subcategory":"Groceries & Convenience Stores",
            "type":"Retail Goods"
        }
    ],
    "sg:phone":"+1 602 243 7179",
    "sg:postcode":"85042",
    "sg:province":"AZ",
    "sg:tags":[
        "station",
        "gasoline"
    ],
    "wof:name":"Circle K",
    "wof:placetype":"venue"
},
  "geometry": {"coordinates":[-112.073198,33.365001],"type":"Point"}
}