{
  "type": "Feature",
  "properties": {
    "iso:country":"US",
    "sg:address":"1204 Hoffman Rd",
    "sg:city":"Prescott",
    "sg:classifiers":[
        {
            "category":"Shopping",
            "subcategory":"Department Store",
            "type":"Retail Goods"
        }
    ],
    "sg:phone":"+1 928 445 9798",
    "sg:postcode":"86303",
    "sg:province":"AZ",
    "wof:name":"Bashford Courts",
    "wof:placetype":"venue"
},
  "geometry": {"coordinates":[-112.490253,34.526954],"type":"Point"}
}