{
  "type": "Feature",
  "properties": {
    "addr:full":"8216 E Monterosa St Scottsdale AZ 85251",
    "addr:housenumber":"8216",
    "addr:postcode":"85251",
    "addr:street":"E Monterosa St",
    "iso:country":"US",
    "sg:address":"8216 E Monterosa St",
    "sg:city":"Scottsdale",
    "sg:classifiers":[
        {
            "category":"Building & Trades",
            "subcategory":"Cleaning & Sanitation",
            "type":"Services"
        }
    ],
    "sg:phone":"+1 602 920 9246",
    "sg:postcode":"85251",
    "sg:province":"AZ",
    "sg:tags":[
        "cleaning-industrial",
        "contractor"
    ],
    "wof:name":"Clean Living Impressions Inc",
    "wof:placetype":"venue"
},
  "geometry": {"coordinates":[-111.904233,33.4957],"type":"Point"}
}