{
  "type": "Feature",
  "properties": {
    "iso:country":"US",
    "sg:address":"19814 N 21st St",
    "sg:city":"Phoenix",
    "sg:classifiers":[
        {
            "category":"Wholesale",
            "subcategory":"Jewelry",
            "type":"Manufacturing & Wholesale Goods"
        },
        {
            "category":"Shopping",
            "subcategory":"Crafts & Fabrics",
            "type":"Retail Goods"
        }
    ],
    "sg:phone":"+1 602 493 5111",
    "sg:postcode":"85024",
    "sg:province":"AZ",
    "sg:tags":[
        "bead",
        "beads-wholesale",
        "manufacturer"
    ],
    "wof:name":"Bracelets Beads Bags And Beyon",
    "wof:placetype":"venue"
},
  "geometry": {"coordinates":[-112.037007,33.666293],"type":"Point"}
}