{
  "type": "Feature",
  "properties": {
    "addr:full":"333 W Fort Lowell Rd Tucson AZ 85705",
    "addr:housenumber":"333",
    "addr:postcode":"85705",
    "addr:street":"W Fort Lowell Rd",
    "iso:country":"US",
    "sg:address":"333 W Fort Lowell Rd",
    "sg:city":"Tucson",
    "sg:classifiers":[
        {
            "category":"Banks & Credit Unions",
            "subcategory":"Financial Services",
            "type":"Services"
        }
    ],
    "sg:phone":"+1 520 792 2099",
    "sg:postcode":"85705",
    "sg:province":"AZ",
    "sg:tags":[
        "program",
        "scholarship"
    ],
    "wof:name":"Tohono O'Odham Nation Schlrshp",
    "wof:placetype":"venue"
},
  "geometry": {"coordinates":[-110.977525,32.264626],"type":"Point"}
}