{
  "type": "Feature",
  "properties": {
    "addr:full":"1029 N Evergreen St Chandler AZ 85225",
    "addr:housenumber":"1029",
    "addr:postcode":"85225",
    "addr:street":"N Evergreen St",
    "iso:country":"US",
    "sg:address":"1029 N Evergreen St",
    "sg:city":"Chandler",
    "sg:classifiers":[
        {
            "category":"Sports & Exercise",
            "subcategory":"Gym",
            "type":"Entertainment"
        }
    ],
    "sg:phone":"+1 480 821 0414",
    "sg:postcode":"85225",
    "sg:province":"AZ",
    "sg:tags":[
        "spa",
        "health"
    ],
    "wof:name":"Larry The Spa Guy",
    "wof:placetype":"venue"
},
  "geometry": {"coordinates":[-111.854215,33.321305],"type":"Point"}
}