{
  "type": "Feature",
  "properties": {
    "iso:country":"US",
    "sg:address":"2002 W Cheryl Dr",
    "sg:city":"Phoenix",
    "sg:classifiers":[
        {
            "category":"Utilities",
            "type":"Services"
        },
        {
            "category":"Utilities",
            "subcategory":"Cable",
            "type":"Services"
        }
    ],
    "sg:phone":"+1 602 997 7234",
    "sg:postcode":"85021",
    "sg:province":"AZ",
    "sg:tags":[
        "pipe",
        "underground",
        "wire",
        "locating",
        "contractor"
    ],
    "wof:name":"C C Underground Utilities",
    "wof:placetype":"venue"
},
  "geometry": {"coordinates":[-112.101803,33.578445],"type":"Point"}
}