{
  "type": "Feature",
  "properties": {
    "iso:country":"US",
    "sg:address":"10202 N 109th Way",
    "sg:city":"Scottsdale",
    "sg:classifiers":[
        {
            "category":"Professional",
            "type":"Services"
        }
    ],
    "sg:phone":"+1 480 563 0773",
    "sg:postcode":"85259",
    "sg:province":"AZ",
    "sg:tags":[
        "establishment"
    ],
    "wof:name":"Global Credit Corp",
    "wof:placetype":"venue"
},
  "geometry": {"coordinates":[-111.843983,33.579689],"type":"Point"}
}