{
  "type": "Feature",
  "properties": {
    "addr:full":"1208 W Roger Rd Tucson AZ 85705",
    "addr:housenumber":"1208",
    "addr:postcode":"85705",
    "addr:street":"W Roger Rd",
    "iso:country":"US",
    "sg:address":"1208 W Roger Rd",
    "sg:city":"Tucson",
    "sg:classifiers":[
        {
            "category":"Real Estate",
            "subcategory":"Real Estate Agent",
            "type":"Services"
        }
    ],
    "sg:phone":"+1 520 888 2767",
    "sg:postcode":"85705",
    "sg:province":"AZ",
    "wof:name":"Adjacent Property Management",
    "wof:placetype":"venue"
},
  "geometry": {"coordinates":[-110.99232499999999,32.279549],"type":"Point"}
}