{
  "type": "Feature",
  "properties": {
    "addr:full":"4619 S Park Ave Tucson AZ 85714",
    "addr:housenumber":"4619",
    "addr:postcode":"85714",
    "addr:street":"S Park Ave",
    "iso:country":"US",
    "sg:address":"4619 S Park Ave",
    "sg:city":"Tucson",
    "sg:classifiers":[
        {
            "category":"Restaurant",
            "type":"Food & Drink"
        }
    ],
    "sg:phone":"+1 520 806 0049",
    "sg:postcode":"85714",
    "sg:province":"AZ",
    "sg:tags":[
        "eating"
    ],
    "wof:name":"El Dorado Tortilla Fctry Rest",
    "wof:placetype":"venue"
},
  "geometry": {"coordinates":[-110.956148,32.169254],"type":"Point"}
}