{
  "type": "Feature",
  "properties": {
    "addr:full":"15732 E Yucca Dr Fountain Hills AZ 85268",
    "addr:housenumber":"15732",
    "addr:postcode":"85268",
    "addr:street":"E Yucca Dr",
    "iso:country":"US",
    "sg:address":"15732 E Yucca Dr",
    "sg:city":"Fountain Hills",
    "sg:classifiers":[
        {
            "category":"Professional",
            "type":"Services"
        }
    ],
    "sg:phone":"+1 480 816 0444",
    "sg:postcode":"85268",
    "sg:province":"AZ",
    "wof:name":"Moments In Stone",
    "wof:placetype":"venue"
},
  "geometry": {"coordinates":[-111.74054700000001,33.618618],"type":"Point"}
}