{
  "type": "Feature",
  "properties": {
    "iso:country":"US",
    "sg:address":"15732 E Yucca Dr",
    "sg:city":"Fountain Hills",
    "sg:classifiers":[
        {
            "category":"Professional",
            "type":"Services"
        }
    ],
    "sg:phone":"+1 480 816 0444",
    "sg:postcode":"85268",
    "sg:province":"AZ",
    "wof:name":"Moments In Stone",
    "wof:placetype":"venue"
},
  "geometry": {"coordinates":[-111.740547,33.618618],"type":"Point"}
}