{
  "type": "Feature",
  "properties": {
    "iso:country":"US",
    "sg:address":"1481 W 3rd St",
    "sg:city":"Yuma",
    "sg:classifiers":[
        {
            "category":"Shopping",
            "subcategory":"Used Merchandise",
            "type":"Retail Goods"
        }
    ],
    "sg:phone":"+1 928 782 4224",
    "sg:postcode":"85364",
    "sg:province":"AZ",
    "wof:name":"Saint Vincent De Paul Thrift",
    "wof:placetype":"venue"
},
  "geometry": {"coordinates":[-114.637965,32.721446],"type":"Point"}
}