{
  "type": "Feature",
  "properties": {
    "addr:full":"10201 S 51st St Phoenix AZ 85044",
    "addr:housenumber":"10201",
    "addr:postcode":"85044",
    "addr:street":"S 51St St",
    "iso:country":"US",
    "sg:address":"10201 S 51st St",
    "sg:city":"Phoenix",
    "sg:classifiers":[
        {
            "category":"Professional",
            "type":"Services"
        }
    ],
    "sg:phone":"+1 480 705 4032",
    "sg:postcode":"85044",
    "sg:province":"AZ",
    "sg:tags":[
        "establishment"
    ],
    "wof:name":"CCI",
    "wof:placetype":"venue"
},
  "geometry": {"coordinates":[-111.97260199999999,33.354187],"type":"Point"}
}