{
  "type": "Feature",
  "properties": {
    "iso:country":"US",
    "sg:address":"4550 E Cactus Rd",
    "sg:city":"Phoenix",
    "sg:classifiers":[
        {
            "category":"Personal",
            "subcategory":"Beauty Salon",
            "type":"Services"
        }
    ],
    "sg:phone":"+1 602 494 2300",
    "sg:postcode":"85032",
    "sg:province":"AZ",
    "sg:tags":[
        "treatment",
        "skin"
    ],
    "sg:website":"www.usa.thebodyshop.com",
    "wof:name":"Body Shop",
    "wof:placetype":"venue"
},
  "geometry": {"coordinates":[-111.981346,33.599042],"type":"Point"}
}