{
  "type": "Feature",
  "properties": {
    "iso:country":"US",
    "sg:address":"4643 W Vista Ave",
    "sg:city":"Glendale",
    "sg:classifiers":[
        {
            "category":"Building & Trades",
            "subcategory":"Cleaning & Sanitation",
            "type":"Services"
        }
    ],
    "sg:phone":"+1 602 388 5385",
    "sg:postcode":"85301",
    "sg:province":"AZ",
    "sg:tags":[
        "janitor"
    ],
    "wof:name":"Arizona First Choice Cleaning",
    "wof:placetype":"venue"
},
  "geometry": {"coordinates":[-112.159994,33.546469],"type":"Point"}
}