{
  "type": "Feature",
  "properties": {
    "iso:country":"US",
    "sg:address":"1406 S 21st Dr",
    "sg:city":"Phoenix",
    "sg:classifiers":[
        {
            "category":"Retail",
            "subcategory":"Auto Repair",
            "type":"Services"
        }
    ],
    "sg:phone":"+1 602 254 7015",
    "sg:postcode":"85009",
    "sg:province":"AZ",
    "sg:tags":[
        "transmission",
        "tractor"
    ],
    "wof:name":"Arizona Gear Repair",
    "wof:placetype":"venue"
},
  "geometry": {"coordinates":[-112.10545500000001,33.434671],"type":"Point"}
}