{
  "type": "Feature",
  "properties": {
    "iso:country":"US",
    "sg:address":"1031 E Braeburn Dr",
    "sg:city":"Phoenix",
    "sg:classifiers":[
        {
            "category":"Professional",
            "type":"Services"
        }
    ],
    "sg:phone":"+1 602 375 8915",
    "sg:postcode":"85022",
    "sg:province":"AZ",
    "sg:tags":[
        "relocation"
    ],
    "wof:name":"Pro Insights",
    "wof:placetype":"venue"
},
  "geometry": {"coordinates":[-112.060542,33.620322],"type":"Point"}
}