{
  "type": "Feature",
  "properties": {
    "addr:full":"14009 West McDowell Road Goodyear AZ 85395",
    "addr:housenumber":"14009",
    "addr:postcode":"85395",
    "addr:street":"West Mcdowell Road",
    "iso:country":"US",
    "sg:address":"14009 West McDowell Road",
    "sg:city":"Goodyear",
    "sg:classifiers":[
        {
            "category":"Health Services",
            "subcategory":"Optometrist",
            "type":"Services"
        },
        {
            "category":"Shopping",
            "subcategory":"Optical Goods",
            "type":"Retail Goods"
        }
    ],
    "sg:phone":"+1 623 935 9784",
    "sg:postcode":"85395",
    "sg:province":"AZ",
    "sg:tags":[
        "eyeglass"
    ],
    "sg:website":"www.eyemasters.com",
    "wof:name":"Eye Masters",
    "wof:placetype":"venue"
},
  "geometry": {"coordinates":[-112.36041400000001,33.464297],"type":"Point"}
}