{
  "type": "Feature",
  "properties": {
    "iso:country":"US",
    "sg:address":"294 E Adams St",
    "sg:city":"Phoenix",
    "sg:classifiers":[
        {
            "category":"Retail",
            "subcategory":"Laundry & Dry Cleaning",
            "type":"Services"
        },
        {
            "category":"Retail",
            "subcategory":"Repair Shop",
            "type":"Services"
        },
        {
            "category":"Building & Trades",
            "subcategory":"Cleaning & Sanitation",
            "type":"Services"
        }
    ],
    "sg:phone":"+1 888 396 5195",
    "sg:postcode":"85004",
    "sg:province":"AZ",
    "sg:tags":[
        "cleaner",
        "upholstery",
        "upholsterer",
        "refinish",
        "rug",
        "furniture",
        "carpet"
    ],
    "wof:name":"Phoenix Carpet Cleaning",
    "wof:placetype":"venue"
},
  "geometry": {"coordinates":[-112.070891,33.44931],"type":"Point"}
}