{
  "type": "Feature",
  "properties": {
    "iso:country":"US",
    "sg:address":"1327 E Chandler Blvd",
    "sg:city":"Phoenix",
    "sg:classifiers":[
        {
            "category":"Restaurant",
            "type":"Food & Drink"
        }
    ],
    "sg:phone":"+1 480 460 5168",
    "sg:postcode":"85048",
    "sg:province":"AZ",
    "sg:tags":[
        "eating"
    ],
    "wof:name":"Beijing Beijing & Kirby",
    "wof:placetype":"venue"
},
  "geometry": {"coordinates":[-112.054501,33.305625],"type":"Point"}
}