{
  "type": "Feature",
  "properties": {
    "iso:country":"US",
    "sg:address":"5835 Desert Lakes Dr",
    "sg:city":"Fort Mohave",
    "sg:classifiers":[
        {
            "category":"Sports & Exercise",
            "subcategory":"Golf",
            "type":"Entertainment"
        }
    ],
    "sg:phone":"+1 928 768 1000",
    "sg:postcode":"86426",
    "sg:province":"AZ",
    "sg:tags":[
        "course"
    ],
    "sg:website":"www.desertlakes.com",
    "wof:name":"Desert Lakes Golf Course",
    "wof:placetype":"venue"
},
  "geometry": {"coordinates":[-114.586269,34.987213],"type":"Point"}
}