{
  "type": "Feature",
  "properties": {
    "iso:country":"US",
    "sg:address":"1231 W Target Range Rd",
    "sg:city":"Nogales",
    "sg:classifiers":[
        {
            "category":"Health Services",
            "subcategory":"Doctor",
            "type":"Services"
        }
    ],
    "sg:phone":"+1 520 287 6597",
    "sg:postcode":"85621",
    "sg:province":"AZ",
    "sg:tags":[
        "clinic"
    ],
    "sg:website":"www.gambro.com",
    "wof:name":"Davida Healthcare",
    "wof:placetype":"venue"
},
  "geometry": {"coordinates":[-110.959596,31.341068],"type":"Point"}
}