{
  "type": "Feature",
  "properties": {
    "addr:full":"7975 N Hayden Rd Ste C260 Scottsdale AZ 85258",
    "addr:housenumber":"7975",
    "addr:postcode":"85258",
    "addr:street":"N Hayden Rd Ste C260",
    "iso:country":"US",
    "sg:address":"7975 N Hayden Rd Ste C260",
    "sg:city":"Scottsdale",
    "sg:classifiers":[
        {
            "category":"Insurance",
            "subcategory":"Insurance Agent",
            "type":"Services"
        },
        {
            "category":"Insurance",
            "subcategory":"Hazard Insurance",
            "type":"Services"
        }
    ],
    "sg:phone":"+1 480 419 2456",
    "sg:postcode":"85258",
    "sg:province":"AZ",
    "sg:tags":[
        "surety",
        "fidelity",
        "commercial",
        "business",
        "bond"
    ],
    "sg:website":"http://www.adecco.com",
    "wof:name":"Surety Placement Services",
    "wof:placetype":"venue"
},
  "geometry": {"coordinates":[-111.899102,33.552002],"type":"Point"}
}