{
  "type": "Feature",
  "properties": {
    "addr:full":"16601 N 25th Ave Phoenix AZ 85023",
    "addr:housenumber":"16601",
    "addr:postcode":"85023",
    "addr:street":"N 25Th Ave",
    "iso:country":"US",
    "sg:address":"16601 N 25th Ave",
    "sg:city":"Phoenix",
    "sg:classifiers":[
        {
            "category":"Retail",
            "subcategory":"Repair Shop",
            "type":"Services"
        }
    ],
    "sg:phone":"+1 602 548 7117",
    "sg:postcode":"85023",
    "sg:province":"AZ",
    "sg:tags":[
        "door"
    ],
    "wof:name":"Arizona Sliding Door & Window",
    "wof:placetype":"venue"
},
  "geometry": {"coordinates":[-112.111475,33.636345],"type":"Point"}
}