{
  "type": "Feature",
  "properties": {
    "iso:country":"US",
    "sg:address":"2005 W Parkside Ln",
    "sg:city":"Phoenix",
    "sg:classifiers":[
        {
            "category":"Manufacturing",
            "subcategory":"Pet Food",
            "type":"Manufacturing & Wholesale Goods"
        },
        {
            "category":"Shopping",
            "subcategory":"Pets & Pet Supplies",
            "type":"Retail Goods"
        }
    ],
    "sg:phone":"+1 480 747 4828",
    "sg:postcode":"85027",
    "sg:province":"AZ",
    "sg:tags":[
        "manufacturer",
        "store",
        "foods-wholesale"
    ],
    "wof:name":"Green Duck Inc",
    "wof:placetype":"venue"
},
  "geometry": {"coordinates":[-112.102343,33.69577],"type":"Point"}
}