{
  "type": "Feature",
  "properties": {
    "iso:country":"US",
    "sg:address":"3220 S 48th St",
    "sg:city":"Phoenix",
    "sg:classifiers":[
        {
            "category":"Travel",
            "subcategory":"Hotels & Motels",
            "type":"Entertainment"
        },
        {
            "category":"Retail",
            "subcategory":"Event Space",
            "type":"Services"
        },
        {
            "category":"Travel",
            "subcategory":"Resort",
            "type":"Entertainment"
        }
    ],
    "sg:phone":"+1 800 345 8082",
    "sg:postcode":"85040",
    "sg:province":"AZ",
    "sg:tags":[
        "facility",
        "banquet",
        "reception",
        "lodging",
        "hall"
    ],
    "sg:website":"http://ad.doubleclick.net/clk;223371278;47096201;d?http://www.holidayinn.com/redirect?path=hd&brandCode=hi&hotelCode=phxaa&_PMID=99601036&cm_mmc=mdpr-_-yellowpages-_-hi-_-phxaa",
    "wof:name":"Holiday Inn Hotel & Suites Phoenix Airport",
    "wof:placetype":"venue"
},
  "geometry": {"coordinates":[-111.980128,33.419694],"type":"Point"}
}