{
  "type": "Feature",
  "properties": {
    "addr:full":"1048 N Arizona Avenue Chandler AZ 85225",
    "addr:housenumber":"1048",
    "addr:postcode":"85225",
    "addr:street":"N Arizona Avenue",
    "iso:country":"US",
    "sg:address":"1048 N Arizona Avenue",
    "sg:city":"Chandler",
    "sg:classifiers":[
        {
            "category":"Shopping",
            "subcategory":"Jewelry",
            "type":"Retail Goods"
        }
    ],
    "sg:phone":"+1 480 917 0290",
    "sg:postcode":"85225",
    "sg:province":"AZ",
    "wof:name":"Nancy's Jewelry",
    "wof:placetype":"venue"
},
  "geometry": {"coordinates":[-111.841463,33.321946],"type":"Point"}
}