{
  "type": "Feature",
  "properties": {
    "iso:country":"US",
    "sg:address":"12133 W Bell Rd",
    "sg:city":"Surprise",
    "sg:classifiers":[
        {
            "category":"Insurance",
            "subcategory":"Insurance Agent",
            "type":"Services"
        }
    ],
    "sg:phone":"+1 602 843 2400",
    "sg:postcode":"85374",
    "sg:province":"AZ",
    "wof:name":"Fontana Insurance",
    "wof:placetype":"venue"
},
  "geometry": {"coordinates":[-112.324214,33.638669],"type":"Point"}
}