{
  "type": "Feature",
  "properties": {
    "iso:country":"US",
    "sg:address":"4233 US Hwy 191",
    "sg:city":"Safford",
    "sg:classifiers":[
        {
            "category":"Retail",
            "subcategory":"Auto Repair",
            "type":"Services"
        },
        {
            "category":"Autos & Motor Vehicles",
            "subcategory":"Auto Supplies",
            "type":"Retail Goods"
        }
    ],
    "sg:phone":"+1 928 428 9611",
    "sg:postcode":"85546",
    "sg:province":"AZ",
    "sg:tags":[
        "brake"
    ],
    "wof:name":"Hernandez Tires & Service",
    "wof:placetype":"venue"
},
  "geometry": {"coordinates":[-109.644054,32.816508],"type":"Point"}
}