{
  "type": "Feature",
  "properties": {
    "iso:country":"US",
    "sg:address":"7343 E Camelback Rd Ste D",
    "sg:city":"Scottsdale",
    "sg:classifiers":[
        {
            "category":"Shopping",
            "subcategory":"Pets & Pet Supplies",
            "type":"Retail Goods"
        }
    ],
    "sg:phone":"+1 480 990 0709",
    "sg:postcode":"85251",
    "sg:province":"AZ",
    "sg:tags":[
        "soil",
        "testing"
    ],
    "wof:name":"Bio Genesis & Technologies",
    "wof:placetype":"venue"
},
  "geometry": {"coordinates":[-111.922157,33.502232],"type":"Point"}
}