{
  "type": "Feature",
  "properties": {
    "iso:country":"US",
    "sg:address":"4920 W Thunderbird Rd # 104",
    "sg:city":"Glendale",
    "sg:classifiers":[
        {
            "category":"Wholesale",
            "subcategory":"Non-durable Goods",
            "type":"Manufacturing & Wholesale Goods"
        },
        {
            "category":"Personal",
            "subcategory":"Barber",
            "type":"Services"
        }
    ],
    "sg:phone":"+1 602 687 9790",
    "sg:postcode":"85306",
    "sg:province":"AZ",
    "sg:tags":[
        "beauty",
        "supply",
        "equipment",
        "salons-equipment",
        "supplies-wholesale",
        "manufacturer"
    ],
    "wof:name":"Jom Global",
    "wof:placetype":"venue"
},
  "geometry": {"coordinates":[-112.165082,33.610797],"type":"Point"}
}