{
  "type": "Feature",
  "properties": {
    "addr:full":"11260 N Derringer Rd Marana AZ 85653",
    "addr:housenumber":"11260",
    "addr:postcode":"85653",
    "addr:street":"N Derringer Rd",
    "iso:country":"US",
    "sg:address":"11260 N Derringer Rd",
    "sg:city":"Marana",
    "sg:classifiers":[
        {
            "category":"Professional",
            "type":"Services"
        }
    ],
    "sg:phone":"+1 520 682 5575",
    "sg:postcode":"85653",
    "sg:province":"AZ",
    "sg:tags":[
        "establishment"
    ],
    "wof:name":"Mccammack M",
    "wof:placetype":"venue"
},
  "geometry": {"coordinates":[-111.32976600000001,32.409174],"type":"Point"}
}