{
  "type": "Feature",
  "properties": {
    "iso:country":"US",
    "sg:address":"1970 W Busoni Pl",
    "sg:city":"Phoenix",
    "sg:classifiers":[
        {
            "category":"Real Estate",
            "subcategory":"Real Estate Services",
            "type":"Services"
        },
        {
            "category":"Banks & Credit Unions",
            "subcategory":"Financial Services",
            "type":"Services"
        }
    ],
    "sg:phone":"+1 602 504 8550",
    "sg:postcode":"85023",
    "sg:province":"AZ",
    "sg:tags":[
        "loan",
        "processing"
    ],
    "wof:name":"Pulte Mortgage",
    "wof:placetype":"venue"
},
  "geometry": {"coordinates":[-112.101812,33.630589],"type":"Point"}
}