{
  "type": "Feature",
  "properties": {
    "iso:country":"US",
    "sg:address":"428 S Stone Ave",
    "sg:city":"Tucson",
    "sg:classifiers":[
        {
            "category":"Professional",
            "subcategory":"Engineering",
            "type":"Services"
        }
    ],
    "sg:phone":"+1 520 390 7920",
    "sg:postcode":"85701",
    "sg:province":"AZ",
    "sg:tags":[
        "general",
        "contractor"
    ],
    "wof:name":"Stanley Engineering",
    "wof:placetype":"venue"
},
  "geometry": {"coordinates":[-110.97027199999999,32.21597],"type":"Point"}
}