{
  "type": "Feature",
  "properties": {
    "addr:full":"1355 W University Dr Mesa AZ 85201",
    "addr:housenumber":"1355",
    "addr:postcode":"85201",
    "addr:street":"W University Dr",
    "iso:country":"US",
    "sg:address":"1355 W University Dr",
    "sg:city":"Mesa",
    "sg:classifiers":[
        {
            "category":"Manufacturing",
            "subcategory":"Printing",
            "type":"Manufacturing & Wholesale Goods"
        },
        {
            "category":"Professional",
            "subcategory":"Advertising",
            "type":"Services"
        },
        {
            "category":"Wholesale",
            "subcategory":"Books, Periodicals, & Newspapers",
            "type":"Manufacturing & Wholesale Goods"
        }
    ],
    "sg:phone":"+1 602 866 2333",
    "sg:postcode":"85201",
    "sg:province":"AZ",
    "sg:tags":[
        "publisher",
        "guide",
        "directory",
        "publishers-directory"
    ],
    "wof:name":"S B C Smart Yellow Pages",
    "wof:placetype":"venue"
},
  "geometry": {"coordinates":[-111.859939,33.422159],"type":"Point"}
}