{
  "type": "Feature",
  "properties": {
    "addr:full":"1221 S Westwood Mesa AZ 85210",
    "addr:housenumber":"1221",
    "addr:postcode":"85210",
    "addr:street":"S Westwood",
    "iso:country":"US",
    "sg:address":"1221 S Westwood",
    "sg:city":"Mesa",
    "sg:classifiers":[
        {
            "category":"Travel",
            "subcategory":"Hotels & Motels",
            "type":"Entertainment"
        }
    ],
    "sg:phone":"+1 480 461 3000",
    "sg:postcode":"85210",
    "sg:province":"AZ",
    "sg:tags":[
        "corporate",
        "lodging"
    ],
    "sg:website":"www.marriott.com",
    "wof:name":"Courtyard Phoenix Mesa",
    "wof:placetype":"venue"
},
  "geometry": {"coordinates":[-111.85212,33.391952],"type":"Point"}
}