{
  "type": "Feature",
  "properties": {
    "addr:full":"4924 W Glendale Ave Glendale AZ 85301",
    "addr:housenumber":"4924",
    "addr:postcode":"85301",
    "addr:street":"W Glendale Ave",
    "iso:country":"US",
    "sg:address":"4924 W Glendale Ave",
    "sg:city":"Glendale",
    "sg:classifiers":[
        {
            "category":"Manufacturing",
            "subcategory":"Glass & Minerals",
            "type":"Manufacturing & Wholesale Goods"
        },
        {
            "category":"Retail",
            "subcategory":"Auto Repair",
            "type":"Services"
        }
    ],
    "sg:phone":"+1 800 874 5277",
    "sg:postcode":"85301",
    "sg:province":"AZ",
    "sg:tags":[
        "plate",
        "doors-glass",
        "window",
        "shape",
        "glass-auto",
        "circle",
        "windshield",
        "special",
        "replacement"
    ],
    "sg:website":"http://www.speedyglass.com",
    "wof:name":"Speedy Glass",
    "wof:placetype":"venue"
},
  "geometry": {"coordinates":[-112.16521,33.538438],"type":"Point"}
}