{
  "type": "Feature",
  "properties": {
    "iso:country":"US",
    "sg:address":"5071 W Laredo St",
    "sg:city":"Chandler",
    "sg:classifiers":[
        {
            "category":"Manufacturing",
            "subcategory":"Retail Goods",
            "type":"Manufacturing & Wholesale Goods"
        }
    ],
    "sg:phone":"+1 480 456 8893",
    "sg:postcode":"85226",
    "sg:province":"AZ",
    "sg:tags":[
        "product",
        "manufacturer",
        "candles-wholesale",
        "mfg"
    ],
    "wof:name":"Gold Canyon Candles",
    "wof:placetype":"venue"
},
  "geometry": {"coordinates":[-111.929463,33.31319],"type":"Point"}
}