{
  "type": "Feature",
  "properties": {
    "iso:country":"US",
    "sg:address":"202 E Lehi Rd",
    "sg:city":"Mesa",
    "sg:classifiers":[
        {
            "category":"Retail",
            "subcategory":"Animal Services",
            "type":"Services"
        }
    ],
    "sg:phone":"+1 480 461 8962",
    "sg:postcode":"85201",
    "sg:province":"AZ",
    "wof:name":"West Wind Stables",
    "wof:placetype":"venue"
},
  "geometry": {"coordinates":[-111.82291600000001,33.458896],"type":"Point"}
}