{
  "type": "Feature",
  "properties": {
    "addr:full":"3427 W Chanute Pass Phoenix AZ 85041",
    "addr:housenumber":"3427",
    "addr:postcode":"85041",
    "addr:street":"W Chanute Pass",
    "iso:country":"US",
    "sg:address":"3427 W Chanute Pass",
    "sg:city":"Phoenix",
    "sg:classifiers":[
        {
            "category":"Utilities",
            "subcategory":"Electric",
            "type":"Services"
        }
    ],
    "sg:phone":"+1 602 617 0040",
    "sg:postcode":"85041",
    "sg:province":"AZ",
    "sg:tags":[
        "energy",
        "equipment",
        "systems-manufacturers",
        "solar",
        "distributor"
    ],
    "sg:website":"http://www.sopogy.com",
    "wof:name":"Sopogy, Inc.",
    "wof:placetype":"venue"
},
  "geometry": {"coordinates":[-112.13197599999999,33.398242],"type":"Point"}
}