{
  "type": "Feature",
  "properties": {
    "iso:country":"US",
    "sg:address":"5308 N 12th St",
    "sg:city":"Phoenix",
    "sg:classifiers":[
        {
            "category":"Real Estate",
            "subcategory":"Architect",
            "type":"Services"
        }
    ],
    "sg:phone":"+1 602 230 2080",
    "sg:postcode":"85014",
    "sg:province":"AZ",
    "wof:name":"Ccm3 Architects LTD",
    "wof:placetype":"venue"
},
  "geometry": {"coordinates":[-112.056245,33.512878],"type":"Point"}
}