{
  "type": "Feature",
  "properties": {
    "iso:country":"US",
    "sg:address":"3650 N 1st Ave",
    "sg:city":"Tucson",
    "sg:classifiers":[
        {
            "category":"Retail",
            "subcategory":"Auto Repair",
            "type":"Services"
        }
    ],
    "sg:phone":"+1 520 292 2869",
    "sg:postcode":"85719",
    "sg:province":"AZ",
    "sg:tags":[
        "wrecker"
    ],
    "wof:name":"Arizona's Best Towing",
    "wof:placetype":"venue"
},
  "geometry": {"coordinates":[-110.96095699999999,32.272749],"type":"Point"}
}