{
  "type": "Feature",
  "properties": {
    "addr:full":"101 S 24th St Phoenix AZ 85034",
    "addr:housenumber":"101",
    "addr:postcode":"85034",
    "addr:street":"S 24Th St",
    "iso:country":"US",
    "sg:address":"101 S 24th St",
    "sg:city":"Phoenix",
    "sg:classifiers":[
        {
            "category":"Restaurant",
            "type":"Food & Drink"
        }
    ],
    "sg:phone":"+1 602 267 0181",
    "sg:postcode":"85034",
    "sg:province":"AZ",
    "sg:tags":[
        "eating"
    ],
    "wof:name":"Haps Real Pit Barbecue",
    "wof:placetype":"venue"
},
  "geometry": {"coordinates":[-112.030153,33.44632],"type":"Point"}
}