{
  "type": "Feature",
  "properties": {
    "iso:country":"US",
    "sg:address":"5022 W Chicago Cir N",
    "sg:city":"Chandler",
    "sg:classifiers":[
        {
            "category":"Building & Trades",
            "subcategory":"Plumbing",
            "type":"Services"
        }
    ],
    "sg:phone":"+1 480 961 4582",
    "sg:postcode":"85226",
    "sg:province":"AZ",
    "sg:tags":[
        "contractor"
    ],
    "wof:name":"Deans Air Condtioning & Htg",
    "wof:placetype":"venue"
},
  "geometry": {"coordinates":[-111.92928000000001,33.299494],"type":"Point"}
}