{
  "type": "Feature",
  "properties": {
    "iso:country":"US",
    "sg:address":"612 D Autremont Ave",
    "sg:city":"Bisbee",
    "sg:classifiers":[
        {
            "category":"Retail",
            "subcategory":"Repair Shop",
            "type":"Services"
        }
    ],
    "sg:phone":"+1 520 432 2959",
    "sg:postcode":"85603",
    "sg:province":"AZ",
    "sg:tags":[
        "appliance",
        "household",
        "electrical"
    ],
    "wof:name":"American Appliance Svc & Parts",
    "wof:placetype":"venue"
},
  "geometry": {"coordinates":[-109.874707,31.41367],"type":"Point"}
}