{
  "type": "Feature",
  "properties": {
    "iso:country":"US",
    "sg:address":"1127 N ROOK AVE",
    "sg:city":"TUCSON",
    "sg:classifiers":[
        {
            "category":"Building & Trades",
            "subcategory":"Pest Control",
            "type":"Services"
        }
    ],
    "sg:phone":"+1 520 762 6174",
    "sg:postcode":"85712",
    "sg:province":"AZ",
    "sg:tags":[
        "industrial",
        "services-commercial",
        "termite",
        "bee",
        "removal"
    ],
    "sg:website":"http://www.azpest.com",
    "wof:name":"Arizona Pest Control Company",
    "wof:placetype":"venue"
},
  "geometry": {"coordinates":[-110.860197,32.23663],"type":"Point"}
}