{
  "type": "Feature",
  "properties": {
    "iso:country":"US",
    "sg:address":"8940 N 19th Ave",
    "sg:city":"Phoenix",
    "sg:classifiers":[
        {
            "category":"Social Services",
            "subcategory":"Job Training",
            "type":"Services"
        }
    ],
    "sg:phone":"+1 602 944 7778",
    "sg:postcode":"85021",
    "sg:province":"AZ",
    "sg:tags":[
        "rehabilitation"
    ],
    "wof:name":"Cascade Disability Mgmt Inc",
    "wof:placetype":"venue"
},
  "geometry": {"coordinates":[-112.099706,33.565891],"type":"Point"}
}