{
  "type": "Feature",
  "properties": {
    "addr:full":"2902 W Agua Fria Fwy # 1090 Phoenix AZ 85027",
    "addr:housenumber":"2902;#",
    "addr:postcode":"85027",
    "addr:street":"W Agua;Fwy",
    "iso:country":"US",
    "sg:address":"2902 W Agua Fria Fwy # 1090",
    "sg:city":"Phoenix",
    "sg:phone":"+1 623 869 8888",
    "sg:postcode":"85027",
    "sg:province":"AZ",
    "sg:website":"http://www.traderonline.com",
    "wof:name":"Employment Guide",
    "wof:placetype":"venue"
},
  "geometry": {"coordinates":[-112.122395,33.669343],"type":"Point"}
}