{
  "type": "Feature",
  "properties": {
    "addr:full":"7912 E Pepper Tree Ln Scottsdale AZ 85250",
    "addr:housenumber":"7912",
    "addr:postcode":"85250",
    "addr:street":"E Pepper Tree Ln",
    "iso:country":"US",
    "sg:address":"7912 E Pepper Tree Ln",
    "sg:city":"Scottsdale",
    "sg:classifiers":[
        {
            "category":"Banks & Credit Unions",
            "subcategory":"Investment Brokerage",
            "type":"Services"
        },
        {
            "category":"Banks & Credit Unions",
            "subcategory":"Financial Services",
            "type":"Services"
        }
    ],
    "sg:phone":"+1 480 991 2674",
    "sg:postcode":"85250",
    "sg:province":"AZ",
    "sg:tags":[
        "advisory",
        "planner"
    ],
    "wof:name":"Bluecap Financial",
    "wof:placetype":"venue"
},
  "geometry": {"coordinates":[-111.91030499999999,33.538057],"type":"Point"}
}