{
  "type": "Feature",
  "properties": {
    "iso:country":"US",
    "sg:address":"4440 N Saddlebag Trl",
    "sg:city":"Scottsdale",
    "sg:classifiers":[
        {
            "category":"Personal",
            "subcategory":"Beauty Salon",
            "type":"Services"
        }
    ],
    "sg:phone":"+1 480 970 8622",
    "sg:postcode":"85251",
    "sg:province":"AZ",
    "wof:name":"Salon Martinez",
    "wof:placetype":"venue"
},
  "geometry": {"coordinates":[-111.922234,33.502032],"type":"Point"}
}