{
  "type": "Feature",
  "properties": {
    "addr:full":"18205 N 51st Ave Ste 115 Glendale AZ 85308",
    "addr:housenumber":"18205",
    "addr:postcode":"85308",
    "addr:street":"N 51St Ave Ste 115",
    "iso:country":"US",
    "sg:address":"18205 N 51st Ave Ste 115",
    "sg:city":"Glendale",
    "sg:classifiers":[
        {
            "category":"Social Services",
            "type":"Services"
        },
        {
            "category":"Personal",
            "type":"Services"
        }
    ],
    "sg:phone":"+1 602 548 1444",
    "sg:postcode":"85308",
    "sg:province":"AZ",
    "sg:tags":[
        "family",
        "counselors-licensed",
        "individual",
        "marriage",
        "child",
        "professional",
        "counselor"
    ],
    "wof:name":"Growing Edges",
    "wof:placetype":"venue"
},
  "geometry": {"coordinates":[-112.16890600000001,33.650886],"type":"Point"}
}