{
  "type": "Feature",
  "properties": {
    "addr:full":"663 N Butte Ave Chandler AZ 85226",
    "addr:housenumber":"663",
    "addr:postcode":"85226",
    "addr:street":"N Butte Ave",
    "iso:country":"US",
    "sg:address":"663 N Butte Ave",
    "sg:city":"Chandler",
    "sg:classifiers":[
        {
            "category":"Manufacturing",
            "subcategory":"Motor Vehicles & Parts",
            "type":"Manufacturing & Wholesale Goods"
        }
    ],
    "sg:phone":"+1 480 753 3476",
    "sg:postcode":"85226",
    "sg:province":"AZ",
    "sg:tags":[
        "light",
        "industrial",
        "assembly",
        "certification"
    ],
    "wof:name":"Meridian Quality Services Inc",
    "wof:placetype":"venue"
},
  "geometry": {"coordinates":[-111.91256300000001,33.314395],"type":"Point"}
}