{
  "type": "Feature",
  "properties": {
    "iso:country":"US",
    "sg:address":"1430 E Missouri Ave B150",
    "sg:city":"Phoenix",
    "sg:classifiers":[
        {
            "category":"Professional",
            "subcategory":"Lawyer & Legal Services",
            "type":"Services"
        },
        {
            "category":"Banks & Credit Unions",
            "subcategory":"Financial Services",
            "type":"Services"
        }
    ],
    "sg:phone":"+1 602 515 0841",
    "sg:postcode":"85014",
    "sg:province":"AZ",
    "sg:tags":[
        "attorney",
        "business",
        "family",
        "law",
        "bankruptcy"
    ],
    "sg:website":"http://www.bkattorneys-arizona.com",
    "wof:name":"Chris Ariano & Reppucci PLLC",
    "wof:placetype":"venue"
},
  "geometry": {"coordinates":[-112.051107,33.516472],"type":"Point"}
}