{
  "type": "Feature",
  "properties": {
    "iso:country":"US",
    "sg:address":"352 S Laguna Dr",
    "sg:city":"Gilbert",
    "sg:classifiers":[
        {
            "category":"Wholesale",
            "subcategory":"Computers",
            "type":"Manufacturing & Wholesale Goods"
        }
    ],
    "sg:phone":"+1 480 545 1444",
    "sg:postcode":"85233",
    "sg:province":"AZ",
    "wof:name":"Larkin Consulting",
    "wof:placetype":"venue"
},
  "geometry": {"coordinates":[-111.810809,33.344381],"type":"Point"}
}