{
  "type": "Feature",
  "properties": {
    "iso:country":"US",
    "sg:address":"1048 N 44th St Ste 100",
    "sg:city":"Phoenix",
    "sg:classifiers":[
        {
            "category":"Banks & Credit Unions",
            "subcategory":"Investment Brokerage",
            "type":"Services"
        },
        {
            "category":"Banks & Credit Unions",
            "subcategory":"Financial Services",
            "type":"Services"
        }
    ],
    "sg:phone":"+1 602 956 9241",
    "sg:postcode":"85008",
    "sg:province":"AZ",
    "sg:tags":[
        "annuity",
        "retirement",
        "insurance",
        "plan"
    ],
    "sg:website":"https://www.aigsunamerica.com",
    "wof:name":"Sun America Securities",
    "wof:placetype":"venue"
},
  "geometry": {"coordinates":[-111.987213,33.460213],"type":"Point"}
}