{
  "type": "Feature",
  "properties": {
    "iso:country":"US",
    "sg:address":"9180 E Indian Bend Rd",
    "sg:city":"Scottsdale",
    "sg:classifiers":[
        {
            "category":"Home & Garden",
            "subcategory":"Furniture",
            "type":"Retail Goods"
        }
    ],
    "sg:phone":"+1 480 922 7176",
    "sg:postcode":"85253",
    "sg:province":"AZ",
    "wof:name":"Leather Home Furnishings",
    "wof:placetype":"venue"
},
  "geometry": {"coordinates":[-111.87989899999999,33.538516],"type":"Point"}
}