{
  "type": "Feature",
  "properties": {
    "iso:country":"US",
    "sg:address":"4291 W Ina Rd",
    "sg:city":"Tucson",
    "sg:classifiers":[
        {
            "category":"Autos & Motor Vehicles",
            "subcategory":"Auto Supplies",
            "type":"Retail Goods"
        }
    ],
    "sg:phone":"+1 520 744 1308",
    "sg:postcode":"85741",
    "sg:province":"AZ",
    "sg:tags":[
        "tire"
    ],
    "wof:name":"Jack Furriers Western Tire Ctr",
    "wof:placetype":"venue"
},
  "geometry": {"coordinates":[-111.055662,32.337501],"type":"Point"}
}