{
  "type": "Feature",
  "properties": {
    "iso:country":"US",
    "sg:address":"5860 Williamson Valley Rd",
    "sg:city":"Prescott",
    "sg:classifiers":[
        {
            "category":"Organizations",
            "subcategory":"Religious Organization",
            "type":"Services"
        }
    ],
    "sg:phone":"+1 928 776 0081",
    "sg:postcode":"86305",
    "sg:province":"AZ",
    "sg:tags":[
        "church"
    ],
    "wof:name":"Westside Christian Church",
    "wof:placetype":"venue"
},
  "geometry": {"coordinates":[-112.494737,34.625351],"type":"Point"}
}