{
  "type": "Feature",
  "properties": {
    "addr:full":"3683 E Tremaine Ct Gilbert AZ 85234",
    "addr:housenumber":"3683",
    "addr:postcode":"85234",
    "addr:street":"E Tremaine Ct",
    "iso:country":"US",
    "sg:address":"3683 E Tremaine Ct",
    "sg:city":"Gilbert",
    "sg:classifiers":[
        {
            "category":"Government",
            "subcategory":"Office",
            "type":"Public Place"
        }
    ],
    "sg:phone":"+1 480 807 3175",
    "sg:postcode":"85234",
    "sg:province":"AZ",
    "sg:tags":[
        "agricultural",
        "regulation",
        "marketing"
    ],
    "wof:name":"Dona L Inglish",
    "wof:placetype":"venue"
},
  "geometry": {"coordinates":[-111.71226,33.361109],"type":"Point"}
}