{
  "type": "Feature",
  "properties": {
    "iso:country":"US",
    "sg:address":"20 W 6th St",
    "sg:city":"Tempe",
    "sg:classifiers":[
        {
            "category":"Restaurant",
            "type":"Food & Drink"
        }
    ],
    "sg:phone":"+1 480 377 1170",
    "sg:postcode":"85281",
    "sg:province":"AZ",
    "sg:tags":[
        "grill",
        "style",
        "bar",
        "family",
        "lunch",
        "brunch",
        "breakfast"
    ],
    "wof:name":"Z Tejas",
    "wof:placetype":"venue"
},
  "geometry": {"coordinates":[-111.940268,33.424353],"type":"Point"}
}