{
  "type": "Feature",
  "properties": {
    "iso:country":"US",
    "sg:address":"11411 S Fortuna Rd",
    "sg:city":"Yuma",
    "sg:classifiers":[
        {
            "category":"Restaurant",
            "type":"Food & Drink"
        }
    ],
    "sg:phone":"+1 928 342 5270",
    "sg:postcode":"85367",
    "sg:province":"AZ",
    "sg:tags":[
        "drinking",
        "eating"
    ],
    "wof:name":"Bottoms Up Pub",
    "wof:placetype":"venue"
},
  "geometry": {"coordinates":[-114.44407,32.664918],"type":"Point"}
}