{
  "type": "Feature",
  "properties": {
    "addr:full":"3520 E Brown Rd Mesa AZ 85213",
    "addr:housenumber":"3520",
    "addr:postcode":"85213",
    "addr:street":"E Brown Rd",
    "iso:country":"US",
    "sg:address":"3520 E Brown Rd",
    "sg:city":"Mesa",
    "sg:classifiers":[
        {
            "category":"Organizations",
            "subcategory":"Religious Organization",
            "type":"Services"
        }
    ],
    "sg:phone":"+1 480 964 4463",
    "sg:postcode":"85213",
    "sg:province":"AZ",
    "sg:tags":[
        "church"
    ],
    "sg:website":"www.living-word.com",
    "wof:name":"Living Word Bible Church",
    "wof:placetype":"venue"
},
  "geometry": {"coordinates":[-111.754052,33.437405],"type":"Point"}
}