{
  "type": "Feature",
  "properties": {
    "addr:full":"3555 W Washington St Phoenix AZ 85009",
    "addr:housenumber":"3555",
    "addr:postcode":"85009",
    "addr:street":"W Washington St",
    "iso:country":"US",
    "sg:address":"3555 W Washington St",
    "sg:city":"Phoenix",
    "sg:classifiers":[
        {
            "category":"Home & Garden",
            "subcategory":"Furniture",
            "type":"Retail Goods"
        }
    ],
    "sg:phone":"+1 602 442 7800",
    "sg:postcode":"85009",
    "sg:province":"AZ",
    "wof:name":"Ashley Furniture Home Store",
    "wof:placetype":"venue"
},
  "geometry": {"coordinates":[-112.137787,33.447655],"type":"Point"}
}