{
  "type": "Feature",
  "properties": {
    "iso:country":"US",
    "sg:address":"5440 S Lakeshore Dr",
    "sg:city":"Tempe",
    "sg:classifiers":[
        {
            "category":"Insurance",
            "subcategory":"Insurance Agent",
            "type":"Services"
        },
        {
            "category":"Insurance",
            "subcategory":"Hazard Insurance",
            "type":"Services"
        },
        {
            "category":"Insurance",
            "subcategory":"Health Insurance",
            "type":"Services"
        }
    ],
    "sg:phone":"+1 480 839 6401",
    "sg:postcode":"85283",
    "sg:province":"AZ",
    "sg:tags":[
        "business",
        "auto",
        "commercial",
        "benefit",
        "employee"
    ],
    "sg:website":"http://www.farmersagent.com/dhorn",
    "wof:name":"Dyrk A Horn Inc",
    "wof:placetype":"venue"
},
  "geometry": {"coordinates":[-111.919182,33.375309],"type":"Point"}
}