{
  "type": "Feature",
  "properties": {
    "iso:country":"US",
    "sg:address":"2916 N 7th Ave Ste 100",
    "sg:city":"Phoenix",
    "sg:classifiers":[
        {
            "category":"Professional",
            "subcategory":"Lawyer & Legal Services",
            "type":"Services"
        },
        {
            "category":"Banks & Credit Unions",
            "subcategory":"Financial Services",
            "type":"Services"
        }
    ],
    "sg:phone":"+1 602 277 4441",
    "sg:postcode":"85013",
    "sg:province":"AZ",
    "sg:tags":[
        "attorney",
        "family",
        "divorce",
        "practice",
        "business",
        "planning",
        "real estate",
        "law",
        "bankruptcy"
    ],
    "sg:website":"http://www.plattwestby.com",
    "wof:name":"Platt & Westby Pc",
    "wof:placetype":"venue"
},
  "geometry": {"coordinates":[-112.083019,33.480721],"type":"Point"}
}