{
  "type": "Feature",
  "properties": {
    "iso:country":"US",
    "sg:address":"1730 E Mobile Ln",
    "sg:city":"Phoenix",
    "sg:classifiers":[
        {
            "category":"Professional",
            "subcategory":"Art Services",
            "type":"Services"
        }
    ],
    "sg:phone":"+1 602 276 3152",
    "sg:postcode":"85040",
    "sg:province":"AZ",
    "sg:tags":[
        "artist"
    ],
    "wof:name":"Studio 622",
    "wof:placetype":"venue"
},
  "geometry": {"coordinates":[-112.042899,33.401411],"type":"Point"}
}