{
  "type": "Feature",
  "properties": {
    "iso:country":"US",
    "sg:address":"3900 E Camelback Rd",
    "sg:city":"Phoenix",
    "sg:classifiers":[
        {
            "category":"Insurance",
            "subcategory":"Health Insurance",
            "type":"Services"
        }
    ],
    "sg:phone":"+1 602 764 3030",
    "sg:postcode":"85018",
    "sg:province":"AZ",
    "sg:tags":[
        "carrier"
    ],
    "wof:name":"Principal Life Insurance Co",
    "wof:placetype":"venue"
},
  "geometry": {"coordinates":[-111.995519,33.509936],"type":"Point"}
}