{
  "type": "Feature",
  "properties": {
    "addr:full":"7000 E Shea Blvd Scottsdale AZ 85254",
    "addr:housenumber":"7000",
    "addr:postcode":"85254",
    "addr:street":"E Shea Blvd",
    "iso:country":"US",
    "sg:address":"7000 E Shea Blvd",
    "sg:city":"Scottsdale",
    "sg:classifiers":[
        {
            "category":"Shopping",
            "subcategory":"Clothing, Apparel, & Fashions",
            "type":"Retail Goods"
        }
    ],
    "sg:phone":"+1 480 596 3844",
    "sg:postcode":"85254",
    "sg:province":"AZ",
    "wof:name":"Boutique Unique",
    "wof:placetype":"venue"
},
  "geometry": {"coordinates":[-111.92926,33.582163],"type":"Point"}
}