{
  "type": "Feature",
  "properties": {
    "iso:country":"US",
    "sg:address":"4700 S McClintock Dr",
    "sg:city":"Tempe",
    "sg:classifiers":[
        {
            "category":"Education",
            "subcategory":"School",
            "type":"Public Place"
        }
    ],
    "sg:phone":"+1 602 243 0184",
    "sg:postcode":"85281",
    "sg:province":"AZ",
    "wof:name":"Arizona Honor Schools Inc",
    "wof:placetype":"venue"
},
  "geometry": {"coordinates":[-111.90922,33.381836],"type":"Point"}
}