{
  "type": "Feature",
  "properties": {
    "iso:country":"US",
    "sg:address":"175 Toho Trl",
    "sg:city":"Flagstaff",
    "sg:classifiers":[
        {
            "category":"Professional",
            "type":"Services"
        }
    ],
    "sg:phone":"+1 928 525 9207",
    "sg:postcode":"86001",
    "sg:province":"AZ",
    "wof:name":"Tovon Co",
    "wof:placetype":"venue"
},
  "geometry": {"coordinates":[-111.70107,35.086995],"type":"Point"}
}