{
  "type": "Feature",
  "properties": {
    "iso:country":"US",
    "sg:address":"6722 W Pinnacle Peak Rd",
    "sg:city":"Peoria",
    "sg:classifiers":[
        {
            "category":"Manufacturing",
            "subcategory":"Metals",
            "type":"Manufacturing & Wholesale Goods"
        }
    ],
    "sg:phone":"+1 623 204 3636",
    "sg:postcode":"85383",
    "sg:province":"AZ",
    "wof:name":"James Miller & Son",
    "wof:placetype":"venue"
},
  "geometry": {"coordinates":[-112.204133,33.696353],"type":"Point"}
}