{
  "type": "Feature",
  "properties": {
    "addr:full":"2016 E Broadway Blvd Tucson AZ 85719",
    "addr:housenumber":"2016",
    "addr:postcode":"85719",
    "addr:street":"E Broadway Blvd",
    "iso:country":"US",
    "sg:address":"2016 E Broadway Blvd",
    "sg:city":"Tucson",
    "sg:classifiers":[
        {
            "category":"Social Services",
            "type":"Services"
        }
    ],
    "sg:phone":"+1 520 882 6120",
    "sg:postcode":"85719",
    "sg:province":"AZ",
    "sg:tags":[
        "organization",
        "welfare"
    ],
    "wof:name":"Native Images Inc",
    "wof:placetype":"venue"
},
  "geometry": {"coordinates":[-110.94112,32.221377],"type":"Point"}
}