{
  "type": "Feature",
  "properties": {
    "iso:country":"US",
    "sg:address":"1674 S Research Loop",
    "sg:city":"Tucson",
    "sg:classifiers":[
        {
            "category":"Professional",
            "subcategory":"Accounting & Tax Preparation",
            "type":"Services"
        }
    ],
    "sg:phone":"+1 520 748 1040",
    "sg:postcode":"85710",
    "sg:province":"AZ",
    "sg:tags":[
        "return",
        "filing"
    ],
    "wof:name":"April 15th Tax",
    "wof:placetype":"venue"
},
  "geometry": {"coordinates":[-110.821494,32.201384],"type":"Point"}
}