{
  "type": "Feature",
  "properties": {
    "iso:country":"US",
    "sg:address":"1630 S Stapley Dr",
    "sg:city":"Mesa",
    "sg:classifiers":[
        {
            "category":"Professional",
            "subcategory":"Lawyer & Legal Services",
            "type":"Services"
        }
    ],
    "sg:phone":"+1 602 271 7700",
    "sg:postcode":"85204",
    "sg:province":"AZ",
    "sg:tags":[
        "attorney"
    ],
    "wof:name":"Broening Oberg Woods Wilson",
    "wof:placetype":"venue"
},
  "geometry": {"coordinates":[-111.805617,33.385781],"type":"Point"}
}