{
  "type": "Feature",
  "properties": {
    "iso:country":"US",
    "sg:address":"5833 S Central Ave",
    "sg:city":"Phoenix",
    "sg:classifiers":[
        {
            "category":"Utilities",
            "subcategory":"Mobile Phone",
            "type":"Services"
        }
    ],
    "sg:phone":"+1 602 305 6790",
    "sg:postcode":"85040",
    "sg:province":"AZ",
    "sg:tags":[
        "telephone",
        "cellular"
    ],
    "wof:name":"MAS Cellulars",
    "wof:placetype":"venue"
},
  "geometry": {"coordinates":[-112.073233,33.392831],"type":"Point"}
}