{
  "type": "Feature",
  "properties": {
    "iso:country":"US",
    "sg:address":"3081 E Doral Dr",
    "sg:city":"Chandler",
    "sg:classifiers":[
        {
            "category":"Wholesale",
            "subcategory":"Drugs",
            "type":"Manufacturing & Wholesale Goods"
        }
    ],
    "sg:phone":"+1 480 629 8630",
    "sg:postcode":"85249",
    "sg:province":"AZ",
    "sg:tags":[
        "pharmaceutical",
        "product"
    ],
    "wof:name":"Eli Lilly & Co",
    "wof:placetype":"venue"
},
  "geometry": {"coordinates":[-111.78721,33.212427],"type":"Point"}
}