{
  "type": "Feature",
  "properties": {
    "addr:full":"1834 N 84th Pl Scottsdale AZ 85257",
    "addr:housenumber":"1834",
    "addr:postcode":"85257",
    "addr:street":"N 84Th Pl",
    "iso:country":"US",
    "sg:address":"1834 N 84th Pl",
    "sg:city":"Scottsdale",
    "sg:classifiers":[
        {
            "category":"Building & Trades",
            "subcategory":"Construction",
            "type":"Services"
        }
    ],
    "sg:phone":"+1 480 946 0304",
    "sg:postcode":"85257",
    "sg:province":"AZ",
    "sg:tags":[
        "painting",
        "contractor"
    ],
    "wof:name":"Tim Kubander Painting",
    "wof:placetype":"venue"
},
  "geometry": {"coordinates":[-111.899613,33.469208],"type":"Point"}
}