{
  "type": "Feature",
  "properties": {
    "iso:country":"US",
    "sg:address":"1420 US Hwy 66",
    "sg:city":"Flagstaff",
    "sg:classifiers":[
        {
            "category":"Personal",
            "subcategory":"Beauty Salon",
            "type":"Services"
        }
    ],
    "sg:phone":"+1 928 774 9920",
    "sg:postcode":"86001",
    "sg:province":"AZ",
    "wof:name":"Supercuts",
    "wof:placetype":"venue"
},
  "geometry": {"coordinates":[-111.631705,35.194264],"type":"Point"}
}