{
  "type": "Feature",
  "properties": {
    "iso:country":"US",
    "sg:address":"854 E Windsor Ave",
    "sg:city":"Phoenix",
    "sg:classifiers":[
        {
            "category":"Education",
            "subcategory":"Vocational School",
            "type":"Public Place"
        }
    ],
    "sg:phone":"+1 602 279 5506",
    "sg:postcode":"85006",
    "sg:province":"AZ",
    "sg:tags":[
        "training",
        "computer"
    ],
    "wof:name":"Mac To School",
    "wof:placetype":"venue"
},
  "geometry": {"coordinates":[-112.062984,33.478604],"type":"Point"}
}