{
  "type": "Feature",
  "properties": {
    "addr:full":"4250 W Thunderbird Rd Phoenix AZ 85053",
    "addr:housenumber":"4250",
    "addr:postcode":"85053",
    "addr:street":"W Thunderbird Rd",
    "iso:country":"US",
    "sg:address":"4250 W Thunderbird Rd",
    "sg:city":"Phoenix",
    "sg:classifiers":[
        {
            "category":"Banks & Credit Unions",
            "subcategory":"Bank",
            "type":"Services"
        }
    ],
    "sg:phone":"+1 602 589 3941",
    "sg:postcode":"85053",
    "sg:province":"AZ",
    "wof:name":"Chase Manhattan Bank",
    "wof:placetype":"venue"
},
  "geometry": {"coordinates":[-112.15074199999999,33.610802],"type":"Point"}
}