{
  "type": "Feature",
  "properties": {
    "addr:full":"1258 W Southern Ave Tempe AZ 85282",
    "addr:housenumber":"1258",
    "addr:postcode":"85282",
    "addr:street":"W Southern Ave",
    "iso:country":"US",
    "sg:address":"1258 W Southern Ave",
    "sg:city":"Tempe",
    "sg:classifiers":[
        {
            "category":"Professional",
            "subcategory":"Advertising",
            "type":"Services"
        },
        {
            "category":"Professional",
            "subcategory":"Business Services",
            "type":"Services"
        },
        {
            "category":"Professional",
            "subcategory":"Printing & Photocopies",
            "type":"Services"
        }
    ],
    "sg:phone":"+1 866 328 5989",
    "sg:postcode":"85282",
    "sg:province":"AZ",
    "sg:tags":[
        "mail",
        "direct",
        "shipping"
    ],
    "sg:website":"http://www.advantagemail.net",
    "wof:name":"AdvantageMail",
    "wof:placetype":"venue"
},
  "geometry": {"coordinates":[-111.957792,33.39286],"type":"Point"}
}