{
  "type": "Feature",
  "properties": {
    "addr:full":"25422 N 72nd Dr Peoria AZ 85383",
    "addr:housenumber":"25422",
    "addr:postcode":"85383",
    "addr:street":"N 72Nd Dr",
    "iso:country":"US",
    "sg:address":"25422 N 72nd Dr",
    "sg:city":"Peoria",
    "sg:classifiers":[
        {
            "category":"Home & Garden",
            "subcategory":"Carpets & Floor Coverings",
            "type":"Retail Goods"
        }
    ],
    "sg:phone":"+1 623 537 4300",
    "sg:postcode":"85383",
    "sg:province":"AZ",
    "sg:tags":[
        "material"
    ],
    "sg:website":"http://www.coolerdays.net",
    "wof:name":"Cooler Days Sunscreens And Home Covering",
    "wof:placetype":"venue"
},
  "geometry": {"coordinates":[-112.214939,33.714897],"type":"Point"}
}