{
  "type": "Feature",
  "properties": {
    "addr:full":"8530 N 59th Ave Glendale AZ 85302",
    "addr:housenumber":"8530",
    "addr:postcode":"85302",
    "addr:street":"N 59Th Ave",
    "iso:country":"US",
    "sg:address":"8530 N 59th Ave",
    "sg:city":"Glendale",
    "sg:classifiers":[
        {
            "category":"Real Estate",
            "subcategory":"Real Estate Operator",
            "type":"Services"
        }
    ],
    "sg:phone":"+1 623 435 1226",
    "sg:postcode":"85302",
    "sg:province":"AZ",
    "sg:tags":[
        "building",
        "apartment"
    ],
    "wof:name":"Evergreen Properties",
    "wof:placetype":"venue"
},
  "geometry": {"coordinates":[-112.18630400000001,33.561189],"type":"Point"}
}