{
  "type": "Feature",
  "properties": {
    "iso:country":"US",
    "sg:address":"5613 Ruby St N",
    "sg:city":"Fort Mohave",
    "sg:classifiers":[
        {
            "category":"Manufacturing",
            "subcategory":"Retail Goods",
            "type":"Manufacturing & Wholesale Goods"
        }
    ],
    "sg:phone":"+1 928 768 9295",
    "sg:postcode":"86426",
    "sg:province":"AZ",
    "sg:tags":[
        "product",
        "mfg"
    ],
    "wof:name":"Screen Factory",
    "wof:placetype":"venue"
},
  "geometry": {"coordinates":[-114.604378,34.995923],"type":"Point"}
}