{
  "type": "Feature",
  "properties": {
    "iso:country":"US",
    "sg:address":"8021 W Tonopah Dr",
    "sg:city":"Peoria",
    "sg:classifiers":[
        {
            "category":"Insurance",
            "subcategory":"Insurance Agent",
            "type":"Services"
        }
    ],
    "sg:phone":"+1 623 362 9087",
    "sg:postcode":"85382",
    "sg:province":"AZ",
    "wof:name":"Kole Insurance Service Co",
    "wof:placetype":"venue"
},
  "geometry": {"coordinates":[-112.232413,33.669026],"type":"Point"}
}