{
  "type": "Feature",
  "properties": {
    "iso:country":"US",
    "sg:address":"7201 N Ulene Pl",
    "sg:city":"Tucson",
    "sg:classifiers":[
        {
            "category":"Social Services",
            "subcategory":"Child Care",
            "type":"Services"
        }
    ],
    "sg:phone":"+1 520 579 8156",
    "sg:postcode":"85741",
    "sg:province":"AZ",
    "wof:name":"Smith's Little Britches Inc",
    "wof:placetype":"venue"
},
  "geometry": {"coordinates":[-111.05917700000001,32.338124],"type":"Point"}
}