{
  "type": "Feature",
  "properties": {
    "iso:country":"US",
    "sg:address":"1732 W Mohawk Ln",
    "sg:city":"Phoenix",
    "sg:classifiers":[
        {
            "category":"Building & Trades",
            "subcategory":"Plumbing",
            "type":"Services"
        }
    ],
    "sg:phone":"+1 623 695 3519",
    "sg:postcode":"85027",
    "sg:province":"AZ",
    "sg:tags":[
        "conditioning",
        "air",
        "system",
        "contractor"
    ],
    "wof:name":"Bry A/C",
    "wof:placetype":"venue"
},
  "geometry": {"coordinates":[-112.095675,33.672948],"type":"Point"}
}