{
  "type": "Feature",
  "properties": {
    "addr:full":"615 S Pantano Rd Tucson AZ 85710",
    "addr:housenumber":"615",
    "addr:postcode":"85710",
    "addr:street":"S Pantano Rd",
    "iso:country":"US",
    "sg:address":"615 S Pantano Rd",
    "sg:city":"Tucson",
    "sg:classifiers":[
        {
            "category":"Professional",
            "type":"Services"
        }
    ],
    "sg:phone":"+1 520 886 8129",
    "sg:postcode":"85710",
    "sg:province":"AZ",
    "sg:tags":[
        "establishment"
    ],
    "wof:name":"BPO",
    "wof:placetype":"venue"
},
  "geometry": {"coordinates":[-110.823697,32.212575],"type":"Point"}
}