{
  "type": "Feature",
  "properties": {
    "iso:country":"US",
    "sg:address":"401 E Rancho Rd",
    "sg:city":"Payson",
    "sg:classifiers":[
        {
            "category":"Building & Trades",
            "subcategory":"Construction",
            "type":"Services"
        }
    ],
    "sg:phone":"+1 928 478 0157",
    "sg:postcode":"85541",
    "sg:province":"AZ",
    "sg:tags":[
        "dry wall",
        "contractor"
    ],
    "wof:name":"Drywall Payson",
    "wof:placetype":"venue"
},
  "geometry": {"coordinates":[-111.317063,34.259346],"type":"Point"}
}