{
  "type": "Feature",
  "properties": {
    "iso:country":"US",
    "sg:address":"10020 E Palo Verde Dr",
    "sg:city":"Cornville",
    "sg:classifiers":[
        {
            "category":"Building & Trades",
            "subcategory":"Construction",
            "type":"Services"
        }
    ],
    "sg:phone":"+1 928 634 6118",
    "sg:postcode":"86325",
    "sg:province":"AZ",
    "sg:tags":[
        "contractor"
    ],
    "wof:name":"Sunrise Custom Drywall",
    "wof:placetype":"venue"
},
  "geometry": {"coordinates":[-111.916669,34.726449],"type":"Point"}
}