{
  "type": "Feature",
  "properties": {
    "addr:full":"1552 S Miller Rd Buckeye AZ 85326",
    "addr:housenumber":"1552",
    "addr:postcode":"85326",
    "addr:street":"S Miller Rd",
    "iso:country":"US",
    "sg:address":"1552 S Miller Rd",
    "sg:city":"Buckeye",
    "sg:classifiers":[
        {
            "category":"Restaurant",
            "type":"Food & Drink"
        }
    ],
    "sg:menulink":"http://www.allmenus.com/az/buckeye/166514-burger-king/menu/",
    "sg:phone":"+1 623 386 2796",
    "sg:postcode":"85326",
    "sg:province":"AZ",
    "sg:tags":[
        "burger",
        "american"
    ],
    "wof:name":"Burger King",
    "wof:placetype":"venue"
},
  "geometry": {"coordinates":[-112.590863,33.444971],"type":"Point"}
}