{
  "type": "Feature",
  "properties": {
    "iso:country":"US",
    "sg:address":"8011 N 7th St",
    "sg:city":"Phoenix",
    "sg:classifiers":[
        {
            "category":"Professional",
            "type":"Services"
        }
    ],
    "sg:phone":"+1 602 371 4947",
    "sg:postcode":"85020",
    "sg:province":"AZ",
    "wof:name":"Cassio",
    "wof:placetype":"venue"
},
  "geometry": {"coordinates":[-112.065149,33.553085],"type":"Point"}
}