{
  "type": "Feature",
  "properties": {
    "iso:country":"US",
    "sg:address":"6661 W Bell Rd",
    "sg:city":"Glendale",
    "sg:classifiers":[
        {
            "category":"Home & Garden",
            "subcategory":"Household Appliances",
            "type":"Retail Goods"
        }
    ],
    "sg:phone":"+1 623 487 0285",
    "sg:postcode":"85308",
    "sg:province":"AZ",
    "sg:tags":[
        "cleaners",
        "vacuum"
    ],
    "sg:website":"www.oreck.com",
    "wof:name":"Oreck",
    "wof:placetype":"venue"
},
  "geometry": {"coordinates":[-112.19620399999999,33.638472],"type":"Point"}
}