{
  "type": "Feature",
  "properties": {
    "addr:full":"1445 W Southern Ave Mesa AZ 85202",
    "addr:housenumber":"1445",
    "addr:postcode":"85202",
    "addr:street":"W Southern Ave",
    "iso:country":"US",
    "sg:address":"1445 W Southern Ave",
    "sg:city":"Mesa",
    "sg:classifiers":[
        {
            "category":"Shopping",
            "subcategory":"Hobbies, Toys, & Games",
            "type":"Retail Goods"
        }
    ],
    "sg:phone":"+1 480 844 8930",
    "sg:postcode":"85202",
    "sg:province":"AZ",
    "sg:tags":[
        "store"
    ],
    "wof:name":"KB Toys",
    "wof:placetype":"venue"
},
  "geometry": {"coordinates":[-111.861182,33.393026],"type":"Point"}
}