{
  "type": "Feature",
  "properties": {
    "addr:full":"4626 N 44th St Phoenix AZ 85018",
    "addr:housenumber":"4626",
    "addr:postcode":"85018",
    "addr:street":"N 44Th St",
    "iso:country":"US",
    "sg:address":"4626 N 44th St",
    "sg:city":"Phoenix",
    "sg:classifiers":[
        {
            "category":"Professional",
            "subcategory":"Management & Consulting",
            "type":"Services"
        },
        {
            "category":"Building & Trades",
            "subcategory":"Landscaping Services",
            "type":"Services"
        }
    ],
    "sg:phone":"+1 602 912 9691",
    "sg:postcode":"85018",
    "sg:province":"AZ",
    "sg:tags":[
        "designer",
        "business",
        "landscape"
    ],
    "wof:name":"G K Flanagan Associates Inc",
    "wof:placetype":"venue"
},
  "geometry": {"coordinates":[-111.986856,33.50535],"type":"Point"}
}