{
  "type": "Feature",
  "properties": {
    "iso:country":"US",
    "sg:address":"607 5th St",
    "sg:city":"Prescott",
    "sg:classifiers":[
        {
            "category":"Building & Trades",
            "subcategory":"Plumbing",
            "type":"Services"
        }
    ],
    "sg:phone":"+1 928 443 1253",
    "sg:postcode":"86301",
    "sg:province":"AZ",
    "sg:tags":[
        "contractor"
    ],
    "wof:name":"T Morris Plumbing",
    "wof:placetype":"venue"
},
  "geometry": {"coordinates":[-112.46731,34.550412],"type":"Point"}
}