{
  "type": "Feature",
  "properties": {
    "iso:country":"US",
    "sg:address":"9601 N 21st Dr",
    "sg:city":"Phoenix",
    "sg:classifiers":[
        {
            "category":"Government",
            "subcategory":"Office",
            "type":"Public Place"
        }
    ],
    "sg:phone":"+1 602 678 0176",
    "sg:postcode":"85021",
    "sg:province":"AZ",
    "sg:tags":[
        "county",
        "parish",
        "program",
        "government-county"
    ],
    "wof:name":"Maricopa County Flood Control",
    "wof:placetype":"venue"
},
  "geometry": {"coordinates":[-112.10453,33.57317],"type":"Point"}
}