{
  "type": "Feature",
  "properties": {
    "iso:country":"US",
    "sg:address":"7141 E 6th Ave",
    "sg:city":"Scottsdale",
    "sg:classifiers":[
        {
            "category":"Building & Trades",
            "subcategory":"Construction",
            "type":"Services"
        }
    ],
    "sg:phone":"+1 480 966 6744",
    "sg:postcode":"85251",
    "sg:province":"AZ",
    "sg:tags":[
        "general",
        "contractor"
    ],
    "wof:name":"HRW Builders",
    "wof:placetype":"venue"
},
  "geometry": {"coordinates":[-111.926839,33.498728],"type":"Point"}
}