{
  "type": "Feature",
  "properties": {
    "iso:country":"US",
    "sg:address":"550 W Baseline Road",
    "sg:city":"Mesa",
    "sg:classifiers":[
        {
            "category":"Retail",
            "subcategory":"Auto Rental",
            "type":"Services"
        }
    ],
    "sg:phone":"+1 480 969 7783",
    "sg:postcode":"85210",
    "sg:province":"AZ",
    "sg:tags":[
        "car"
    ],
    "wof:name":"Enterprise Rent-A-Car",
    "wof:placetype":"venue"
},
  "geometry": {"coordinates":[-111.844256,33.378837],"type":"Point"}
}