{
  "type": "Feature",
  "properties": {
    "addr:full":"1610 N 36th St Phoenix AZ 85008",
    "addr:housenumber":"1610",
    "addr:postcode":"85008",
    "addr:street":"N 36Th St",
    "iso:country":"US",
    "sg:address":"1610 N 36th St",
    "sg:city":"Phoenix",
    "sg:classifiers":[
        {
            "category":"Banks & Credit Unions",
            "subcategory":"Financial Services",
            "type":"Services"
        }
    ],
    "sg:phone":"+1 602 275 3525",
    "sg:postcode":"85008",
    "sg:province":"AZ",
    "sg:tags":[
        "cashing",
        "loan",
        "check"
    ],
    "wof:name":"1 Stop Check Cashing Payday & Title Loans",
    "wof:placetype":"venue"
},
  "geometry": {"coordinates":[-112.004227,33.465896],"type":"Point"}
}