{
  "type": "Feature",
  "properties": {
    "addr:full":"2 N Central Ave Phoenix AZ 85004",
    "addr:housenumber":"2",
    "addr:postcode":"85004",
    "addr:street":"N Central Ave",
    "iso:country":"US",
    "sg:address":"2 N Central Ave",
    "sg:city":"Phoenix",
    "sg:classifiers":[
        {
            "category":"Coffee & Tea",
            "type":"Food & Drink"
        },
        {
            "category":"Manufacturing",
            "subcategory":"Food",
            "type":"Manufacturing & Wholesale Goods"
        }
    ],
    "sg:phone":"+1 602 509 4700",
    "sg:postcode":"85004",
    "sg:province":"AZ",
    "sg:tags":[
        "tea-wholesale",
        "manufacturer"
    ],
    "wof:name":"Vida Java",
    "wof:placetype":"venue"
},
  "geometry": {"coordinates":[-112.073807,33.448341],"type":"Point"}
}