{
  "type": "Feature",
  "properties": {
    "iso:country":"US",
    "sg:address":"2048 S 6th Ave",
    "sg:city":"Tucson",
    "sg:classifiers":[
        {
            "category":"Food & Beverages",
            "subcategory":"Groceries & Convenience Stores",
            "type":"Retail Goods"
        }
    ],
    "sg:phone":"+1 520 623 0133",
    "sg:postcode":"85713",
    "sg:province":"AZ",
    "wof:name":"T & T Market",
    "wof:placetype":"venue"
},
  "geometry": {"coordinates":[-110.968491,32.198069],"type":"Point"}
}