{
  "type": "Feature",
  "properties": {
    "iso:country":"US",
    "sg:address":"38151 Center St",
    "sg:city":"Salome",
    "sg:classifiers":[
        {
            "category":"Home & Garden",
            "subcategory":"Hardware",
            "type":"Retail Goods"
        }
    ],
    "sg:phone":"+1 928 859 3448",
    "sg:postcode":"85345",
    "sg:province":"AZ",
    "wof:name":"Mo's Fix-It",
    "wof:placetype":"venue"
},
  "geometry": {"coordinates":[-113.617819,33.781614],"type":"Point"}
}