{
  "type": "Feature",
  "properties": {
    "addr:full":"7756 E Broadway Blvd Tucson AZ 85710",
    "addr:housenumber":"7756",
    "addr:postcode":"85710",
    "addr:street":"E Broadway Blvd",
    "iso:country":"US",
    "sg:address":"7756 E Broadway Blvd",
    "sg:city":"Tucson",
    "sg:classifiers":[
        {
            "category":"Professional",
            "subcategory":"Accounting & Tax Preparation",
            "type":"Services"
        }
    ],
    "sg:phone":"+1 520 296 1206",
    "sg:postcode":"85710",
    "sg:province":"AZ",
    "sg:tags":[
        "billing"
    ],
    "wof:name":"Professional Medical Svc",
    "wof:placetype":"venue"
},
  "geometry": {"coordinates":[-110.828615,32.220904],"type":"Point"}
}