{
  "type": "Feature",
  "properties": {
    "addr:full":"5605 E River Rd Tucson AZ 85750",
    "addr:housenumber":"5605",
    "addr:postcode":"85750",
    "addr:street":"E River Rd",
    "iso:country":"US",
    "sg:address":"5605 E River Rd",
    "sg:city":"Tucson",
    "sg:classifiers":[
        {
            "category":"Shopping",
            "subcategory":"Clothing, Apparel, & Fashions",
            "type":"Retail Goods"
        }
    ],
    "sg:phone":"+1 520 577 2053",
    "sg:postcode":"85750",
    "sg:province":"AZ",
    "wof:name":"Sabaku",
    "wof:placetype":"venue"
},
  "geometry": {"coordinates":[-110.873722,32.273464],"type":"Point"}
}