{
  "type": "Feature",
  "properties": {
    "iso:country":"US",
    "sg:address":"55 Chof Trl",
    "sg:city":"Flagstaff",
    "sg:classifiers":[
        {
            "category":"Building & Trades",
            "subcategory":"Construction",
            "type":"Services"
        }
    ],
    "sg:phone":"+1 928 525 1619",
    "sg:postcode":"86001",
    "sg:province":"AZ",
    "sg:tags":[
        "contractor"
    ],
    "wof:name":"John Smith Drywall",
    "wof:placetype":"venue"
},
  "geometry": {"coordinates":[-111.691654,35.090068],"type":"Point"}
}