{
  "type": "Feature",
  "properties": {
    "iso:country":"US",
    "sg:address":"16601 N 40th St Ste 110",
    "sg:city":"Phoenix",
    "sg:classifiers":[
        {
            "category":"Community Center",
            "subcategory":"Senior",
            "type":"Public Place"
        },
        {
            "category":"Social Services",
            "subcategory":"Adult Care",
            "type":"Services"
        }
    ],
    "sg:phone":"+1 602 237 6730",
    "sg:postcode":"85032",
    "sg:province":"AZ",
    "sg:tags":[
        "counseling",
        "citizen"
    ],
    "wof:name":"Senior Living Options",
    "wof:placetype":"venue"
},
  "geometry": {"coordinates":[-111.99614,33.637058],"type":"Point"}
}