{
  "type": "Feature",
  "properties": {
    "iso:country":"US",
    "sg:address":"1900 S Joshua Ave",
    "sg:city":"Parker",
    "sg:classifiers":[
        {
            "category":"Autos & Motor Vehicles",
            "subcategory":"Auto Supplies",
            "type":"Retail Goods"
        }
    ],
    "sg:phone":"+1 928 669 2828",
    "sg:postcode":"85344",
    "sg:province":"AZ",
    "sg:tags":[
        "tire"
    ],
    "wof:name":"For You Tire & Auto Service",
    "wof:placetype":"venue"
},
  "geometry": {"coordinates":[-114.284912,34.140961],"type":"Point"}
}