{
  "type": "Feature",
  "properties": {
    "iso:country":"US",
    "sg:address":"503 W Van Buren St",
    "sg:city":"Avondale",
    "sg:classifiers":[
        {
            "category":"Banks & Credit Unions",
            "subcategory":"Bank",
            "type":"Services"
        }
    ],
    "sg:phone":"+1 602 631 3200",
    "sg:postcode":"85323",
    "sg:province":"AZ",
    "wof:name":"Credit Union West",
    "wof:placetype":"venue"
},
  "geometry": {"coordinates":[-112.341003,33.449799],"type":"Point"}
}