{
  "type": "Feature",
  "properties": {
    "iso:country":"US",
    "sg:address":"8234 E Minnezona Ave",
    "sg:city":"Scottsdale",
    "sg:classifiers":[
        {
            "category":"Professional",
            "subcategory":"Business Services",
            "type":"Services"
        }
    ],
    "sg:phone":"+1 480 947 1166",
    "sg:postcode":"85251",
    "sg:province":"AZ",
    "sg:tags":[
        "passenger",
        "local",
        "transportation"
    ],
    "wof:name":"Camel Back Chauffers",
    "wof:placetype":"venue"
},
  "geometry": {"coordinates":[-111.900975,33.50299],"type":"Point"}
}