{
  "type": "Feature",
  "properties": {
    "iso:country":"US",
    "sg:address":"1501 W Forest Meadows St",
    "sg:city":"Flagstaff",
    "sg:classifiers":[
        {
            "category":"Professional",
            "subcategory":"Computer Services",
            "type":"Services"
        }
    ],
    "sg:phone":"+1 928 641 9760",
    "sg:postcode":"86001",
    "sg:province":"AZ",
    "sg:tags":[
        "internet"
    ],
    "wof:name":"A Z Access Internet",
    "wof:placetype":"venue"
},
  "geometry": {"coordinates":[-111.671748,35.185058],"type":"Point"}
}