{
  "type": "Feature",
  "properties": {
    "iso:country":"US",
    "sg:address":"4640 E Sunrise Dr",
    "sg:city":"Tucson",
    "sg:classifiers":[
        {
            "category":"Manufacturing",
            "subcategory":"Printing",
            "type":"Manufacturing & Wholesale Goods"
        }
    ],
    "sg:phone":"+1 520 577 4909",
    "sg:postcode":"85718",
    "sg:province":"AZ",
    "sg:tags":[
        "commercial"
    ],
    "wof:name":"REO Distribution Services",
    "wof:placetype":"venue"
},
  "geometry": {"coordinates":[-110.893322,32.308264],"type":"Point"}
}