{
  "type": "Feature",
  "properties": {
    "addr:full":"7123 N 138th Ave Glendale AZ 85307",
    "addr:housenumber":"7123",
    "addr:postcode":"85307",
    "addr:street":"N 138Th Ave",
    "iso:country":"US",
    "sg:address":"7123 N 138th Ave",
    "sg:city":"Glendale",
    "sg:classifiers":[
        {
            "category":"Shopping",
            "subcategory":"Gifts & Souvenirs",
            "type":"Retail Goods"
        }
    ],
    "sg:phone":"+1 623 536 5485",
    "sg:postcode":"85307",
    "sg:province":"AZ",
    "sg:tags":[
        "shop"
    ],
    "wof:name":"Black Feather Gift Gallery",
    "wof:placetype":"venue"
},
  "geometry": {"coordinates":[-112.356826,33.540242],"type":"Point"}
}