{
  "type": "Feature",
  "properties": {
    "iso:country":"US",
    "sg:address":"2107 W Sherman St",
    "sg:city":"Phoenix",
    "sg:classifiers":[
        {
            "category":"Place Of Worship",
            "type":"Public Place"
        }
    ],
    "sg:phone":"+1 602 488 6121",
    "sg:postcode":"85009",
    "sg:province":"AZ",
    "sg:tags":[
        "church"
    ],
    "wof:name":"Iglesia Pentecostales En El Desierto, Inc.",
    "wof:placetype":"venue"
},
  "geometry": {"coordinates":[-112.104495,33.440232],"type":"Point"}
}