{
  "type": "Feature",
  "properties": {
    "iso:country":"US",
    "sg:address":"4535 E Elwood St",
    "sg:city":"Phoenix",
    "sg:classifiers":[
        {
            "category":"Home & Garden",
            "subcategory":"Building Materials",
            "type":"Retail Goods"
        }
    ],
    "sg:phone":"+1 602 257 0800",
    "sg:postcode":"85040",
    "sg:province":"AZ",
    "sg:tags":[
        "glass",
        "window",
        "plate"
    ],
    "wof:name":"Glaspro",
    "wof:placetype":"venue"
},
  "geometry": {"coordinates":[-111.983086,33.413018],"type":"Point"}
}