{
  "type": "Feature",
  "properties": {
    "iso:country":"US",
    "sg:address":"603 W Baseline Rd",
    "sg:city":"Buckeye",
    "sg:classifiers":[
        {
            "category":"Insurance",
            "subcategory":"Insurance Agent",
            "type":"Services"
        }
    ],
    "sg:phone":"+1 623 935 6209",
    "sg:postcode":"85326",
    "sg:province":"AZ",
    "wof:name":"Farm Bureau Insurance Services",
    "wof:placetype":"venue"
},
  "geometry": {"coordinates":[-112.589656,33.378655],"type":"Point"}
}