{
  "type": "Feature",
  "properties": {
    "iso:country":"US",
    "sg:address":"2354 W University Dr",
    "sg:city":"Mesa",
    "sg:classifiers":[
        {
            "category":"Building & Trades",
            "subcategory":"Construction",
            "type":"Services"
        }
    ],
    "sg:phone":"+1 602 341 0696",
    "sg:postcode":"85201",
    "sg:province":"AZ",
    "sg:tags":[
        "floor",
        "laying",
        "contractor"
    ],
    "wof:name":"Obrien Enterprizes",
    "wof:placetype":"venue"
},
  "geometry": {"coordinates":[-111.874374,33.422134],"type":"Point"}
}