{
  "type": "Feature",
  "properties": {
    "addr:full":"5209 N Whitehurst Pl Tucson AZ 85750",
    "addr:housenumber":"5209",
    "addr:postcode":"85750",
    "addr:street":"N Whitehurst Pl",
    "iso:country":"US",
    "sg:address":"5209 N Whitehurst Pl",
    "sg:city":"Tucson",
    "sg:classifiers":[
        {
            "category":"Autos & Motor Vehicles",
            "subcategory":"Fuel & Gas Station",
            "type":"Retail Goods"
        }
    ],
    "sg:phone":"+1 520 577 1726",
    "sg:postcode":"85750",
    "sg:province":"AZ",
    "sg:tags":[
        "station",
        "gasoline"
    ],
    "wof:name":"Double D Texaco",
    "wof:placetype":"venue"
},
  "geometry": {"coordinates":[-110.82741799999999,32.301073],"type":"Point"}
}