{
  "type": "Feature",
  "properties": {
    "iso:country":"US",
    "sg:address":"215 E Lexington Ave",
    "sg:city":"Phoenix",
    "sg:classifiers":[
        {
            "category":"Professional",
            "subcategory":"Lawyer & Legal Services",
            "type":"Services"
        }
    ],
    "sg:phone":"+1 602 358 0007",
    "sg:postcode":"85012",
    "sg:province":"AZ",
    "sg:tags":[
        "attorney"
    ],
    "wof:name":"Ron Glazer",
    "wof:placetype":"venue"
},
  "geometry": {"coordinates":[-112.06961099999999,33.486005],"type":"Point"}
}