{
  "type": "Feature",
  "properties": {
    "iso:country":"US",
    "sg:address":"7501 E Redfield Rd",
    "sg:city":"Scottsdale",
    "sg:classifiers":[
        {
            "category":"Freight",
            "type":"Transportation"
        }
    ],
    "sg:phone":"+1 480 948 0600",
    "sg:postcode":"85260",
    "sg:province":"AZ",
    "sg:tags":[
        "operator",
        "trucking"
    ],
    "wof:name":"Quest Transportation Inc",
    "wof:placetype":"venue"
},
  "geometry": {"coordinates":[-111.916927,33.613963],"type":"Point"}
}