{
  "type": "Feature",
  "properties": {
    "addr:full":"943 Fair St Prescott AZ 86305",
    "addr:housenumber":"943",
    "addr:postcode":"86305",
    "addr:street":"Fair St",
    "iso:country":"US",
    "sg:address":"943 Fair St",
    "sg:city":"Prescott",
    "sg:classifiers":[
        {
            "category":"Personal",
            "subcategory":"Beauty Salon",
            "type":"Services"
        }
    ],
    "sg:phone":"+1 928 443 5242",
    "sg:postcode":"86305",
    "sg:province":"AZ",
    "wof:name":"A Juniper Moon Salon",
    "wof:placetype":"venue"
},
  "geometry": {"coordinates":[-112.482078,34.553216],"type":"Point"}
}