{
  "type": "Feature",
  "properties": {
    "iso:country":"US",
    "sg:address":"1915 N Lindsay Rd",
    "sg:city":"Mesa",
    "sg:classifiers":[
        {
            "category":"Building & Trades",
            "subcategory":"Plumbing",
            "type":"Services"
        }
    ],
    "sg:phone":"+1 480 654 2727",
    "sg:postcode":"85213",
    "sg:province":"AZ",
    "sg:tags":[
        "conditioning",
        "air",
        "system",
        "contractor"
    ],
    "wof:name":"ASAP Air Conditioning & Htg",
    "wof:placetype":"venue"
},
  "geometry": {"coordinates":[-111.770696,33.450627],"type":"Point"}
}