{
  "type": "Feature",
  "properties": {
    "iso:country":"US",
    "sg:address":"13063 W Bell Rd",
    "sg:city":"Surprise",
    "sg:classifiers":[
        {
            "category":"Government",
            "subcategory":"Police Station",
            "type":"Public Place"
        }
    ],
    "sg:phone":"+1 602 256 1602",
    "sg:postcode":"85374",
    "sg:province":"AZ",
    "sg:tags":[
        "protection"
    ],
    "wof:name":"Sheriffs Office - District 3",
    "wof:placetype":"venue"
},
  "geometry": {"coordinates":[-112.339516,33.638651],"type":"Point"}
}