{
  "type": "Feature",
  "properties": {
    "iso:country":"US",
    "sg:address":"2741 W Southern Ave Ste 2",
    "sg:city":"Tempe",
    "sg:classifiers":[
        {
            "category":"Professional",
            "subcategory":"Accounting & Tax Preparation",
            "type":"Services"
        },
        {
            "category":"Banks & Credit Unions",
            "subcategory":"Investment Brokerage",
            "type":"Services"
        },
        {
            "category":"Banks & Credit Unions",
            "subcategory":"Financial Services",
            "type":"Services"
        }
    ],
    "sg:phone":"+1 602 414 0017",
    "sg:postcode":"85282",
    "sg:province":"AZ",
    "sg:tags":[
        "trust",
        "representative",
        "foreclosure",
        "taxes-consultants"
    ],
    "sg:website":"http://www.tsofarizona.com",
    "wof:name":"Trustee Services Of Arizona",
    "wof:placetype":"venue"
},
  "geometry": {"coordinates":[-111.977627,33.392769],"type":"Point"}
}