{
  "type": "Feature",
  "properties": {
    "addr:full":"71 N Morley Ave Nogales AZ 85621",
    "addr:housenumber":"71",
    "addr:postcode":"85621",
    "addr:street":"N Morley Ave",
    "iso:country":"US",
    "sg:address":"71 N Morley Ave",
    "sg:city":"Nogales",
    "sg:classifiers":[
        {
            "category":"Shopping",
            "subcategory":"Clothing, Apparel, & Fashions",
            "type":"Retail Goods"
        }
    ],
    "sg:phone":"+1 520 287 7404",
    "sg:postcode":"85621",
    "sg:province":"AZ",
    "sg:tags":[
        "furnishing"
    ],
    "wof:name":"Charlie's",
    "wof:placetype":"venue"
},
  "geometry": {"coordinates":[-110.94104400000001,31.333495],"type":"Point"}
}