{
  "type": "Feature",
  "properties": {
    "iso:country":"US",
    "sg:address":"777 E. Baseline Rd",
    "sg:city":"Tempe",
    "sg:classifiers":[
        {
            "category":"Home & Garden",
            "subcategory":"Hardware",
            "type":"Retail Goods"
        },
        {
            "category":"Home & Garden",
            "subcategory":"Building Materials",
            "type":"Retail Goods"
        },
        {
            "category":"Home & Garden",
            "subcategory":"Household Appliances",
            "type":"Retail Goods"
        }
    ],
    "sg:phone":"+1 480 458 1870",
    "sg:postcode":"85283",
    "sg:province":"AZ",
    "sg:tags":[
        "store",
        "supply"
    ],
    "sg:website":"lowes.com",
    "wof:name":"Lowes",
    "wof:placetype":"venue"
},
  "geometry": {"coordinates":[-111.930401,33.377112],"type":"Point"}
}