{
  "type": "Feature",
  "properties": {
    "addr:full":"150 W Court St Ste B Yuma AZ 85364",
    "addr:housenumber":"150",
    "addr:postcode":"85364",
    "addr:street":"W Court St Ste B",
    "iso:country":"US",
    "sg:address":"150 W Court St Ste B",
    "sg:city":"Yuma",
    "sg:classifiers":[
        {
            "category":"Professional",
            "subcategory":"Lawyer & Legal Services",
            "type":"Services"
        }
    ],
    "sg:phone":"+1 928 329 6101",
    "sg:postcode":"85364",
    "sg:province":"AZ",
    "sg:tags":[
        "attorney",
        "criminal",
        "family",
        "personal",
        "damage",
        "accident",
        "injury",
        "property",
        "law"
    ],
    "wof:name":"Law Office of Vida Florez-Warner",
    "wof:placetype":"venue"
},
  "geometry": {"coordinates":[-114.62118100000001,32.723351],"type":"Point"}
}