{
  "type": "Feature",
  "properties": {
    "iso:country":"US",
    "sg:address":"1606 N Signal Butte Rd",
    "sg:city":"Mesa",
    "sg:classifiers":[
        {
            "category":"Restaurant",
            "type":"Food & Drink"
        }
    ],
    "sg:menulink":"http://www.allmenus.com/az/phoenix/190540-mcdonalds/menu/",
    "sg:postcode":"85207",
    "sg:province":"AZ",
    "sg:tags":[
        "burger",
        "american"
    ],
    "wof:name":"McDonald's",
    "wof:placetype":"venue"
},
  "geometry": {"coordinates":[-111.597932,33.441633],"type":"Point"}
}