{
  "type": "Feature",
  "properties": {
    "iso:country":"US",
    "sg:address":"3101 E Shea Blvd",
    "sg:city":"Phoenix",
    "sg:classifiers":[
        {
            "category":"Social Services",
            "type":"Services"
        }
    ],
    "sg:phone":"+1 602 992 8507",
    "sg:postcode":"85028",
    "sg:province":"AZ",
    "sg:tags":[
        "executive"
    ],
    "wof:name":"Probation- Adult",
    "wof:placetype":"venue"
},
  "geometry": {"coordinates":[-112.013104,33.582485],"type":"Point"}
}