{
  "type": "Feature",
  "properties": {
    "iso:country":"US",
    "sg:address":"9580 E Birch Tree Cir",
    "sg:city":"Tucson",
    "sg:classifiers":[
        {
            "category":"Professional",
            "type":"Services"
        }
    ],
    "sg:phone":"+1 520 794 1741",
    "sg:postcode":"85749",
    "sg:province":"AZ",
    "wof:name":"Michael W Sampsel",
    "wof:placetype":"venue"
},
  "geometry": {"coordinates":[-110.78888000000001,32.289267],"type":"Point"}
}