{
  "type": "Feature",
  "properties": {
    "addr:full":"1825 E 9th St Douglas AZ 85607",
    "addr:housenumber":"1825",
    "addr:postcode":"85607",
    "addr:street":"E 9Th St",
    "iso:country":"US",
    "sg:address":"1825 E 9th St",
    "sg:city":"Douglas",
    "sg:classifiers":[
        {
            "category":"Banks & Credit Unions",
            "subcategory":"Bank",
            "type":"Services"
        }
    ],
    "sg:phone":"+1 520 364 3405",
    "sg:postcode":"85607",
    "sg:province":"AZ",
    "sg:tags":[
        "commercial",
        "saving"
    ],
    "sg:website":"http://www.wellsfargo.com",
    "wof:name":"Wells Fargo Bank",
    "wof:placetype":"venue"
},
  "geometry": {"coordinates":[-109.533401,31.34339],"type":"Point"}
}