{
  "type": "Feature",
  "properties": {
    "iso:country":"US",
    "sg:address":"5440 E Calle Camelia",
    "sg:city":"Phoenix",
    "sg:classifiers":[
        {
            "category":"Manufacturing",
            "subcategory":"Petroleum Products",
            "type":"Manufacturing & Wholesale Goods"
        }
    ],
    "sg:phone":"+1 602 840 1225",
    "sg:postcode":"85018",
    "sg:province":"AZ",
    "sg:tags":[
        "contract"
    ],
    "wof:name":"New Chance Industries",
    "wof:placetype":"venue"
},
  "geometry": {"coordinates":[-111.963208,33.492368],"type":"Point"}
}