{
  "type": "Feature",
  "properties": {
    "iso:country":"US",
    "sg:address":"20118 N 67th Ave 300-470",
    "sg:city":"Glendale",
    "sg:classifiers":[
        {
            "category":"Education",
            "subcategory":"Special Training",
            "type":"Public Place"
        }
    ],
    "sg:phone":"+1 623 680 9955",
    "sg:postcode":"85308",
    "sg:province":"AZ",
    "sg:tags":[
        "educational"
    ],
    "wof:name":"Arizona Association For Healthcare Quality",
    "wof:placetype":"venue"
},
  "geometry": {"coordinates":[-112.203087,33.666758],"type":"Point"}
}