{
  "type": "Feature",
  "properties": {
    "iso:country":"US",
    "sg:address":"6671 E Baseline Rd",
    "sg:city":"Mesa",
    "sg:classifiers":[
        {
            "category":"Professional",
            "subcategory":"Business Services",
            "type":"Services"
        }
    ],
    "sg:phone":"+1 480 373 8532",
    "sg:postcode":"85206",
    "sg:province":"AZ",
    "sg:tags":[
        "process",
        "server"
    ],
    "wof:name":"A & A Document Svc",
    "wof:placetype":"venue"
},
  "geometry": {"coordinates":[-111.69044599999999,33.379279],"type":"Point"}
}