{
  "type": "Feature",
  "properties": {
    "iso:country":"US",
    "sg:address":"1950 Estrella Rd",
    "sg:city":"Prescott",
    "sg:classifiers":[
        {
            "category":"Freight",
            "type":"Transportation"
        }
    ],
    "sg:phone":"+1 928 775 8425",
    "sg:postcode":"86305",
    "sg:province":"AZ",
    "sg:tags":[
        "trucking"
    ],
    "wof:name":"Alanis Transport",
    "wof:placetype":"venue"
},
  "geometry": {"coordinates":[-112.490481,34.57751],"type":"Point"}
}