{
  "type": "Feature",
  "properties": {
    "iso:country":"US",
    "sg:address":"2007 W Peoria Ave",
    "sg:city":"Phoenix",
    "sg:classifiers":[
        {
            "category":"Personal",
            "subcategory":"Beauty Salon",
            "type":"Services"
        }
    ],
    "sg:phone":"+1 602 870 0222",
    "sg:postcode":"85029",
    "sg:province":"AZ",
    "wof:name":"Day Dreams Salon & Spa",
    "wof:placetype":"venue"
},
  "geometry": {"coordinates":[-112.101601,33.582004],"type":"Point"}
}