{
  "type": "Feature",
  "properties": {
    "addr:full":"1785 W Ajo Way Tucson AZ 85713",
    "addr:housenumber":"1785",
    "addr:postcode":"85713",
    "addr:street":"W Ajo Way",
    "iso:country":"US",
    "sg:address":"1785 W Ajo Way",
    "sg:city":"Tucson",
    "sg:classifiers":[
        {
            "category":"Shopping",
            "subcategory":"Discount & Variety Stores",
            "type":"Retail Goods"
        }
    ],
    "sg:phone":"+1 520 741 7575",
    "sg:postcode":"85713",
    "sg:province":"AZ",
    "wof:name":"Family Dollar Stores",
    "wof:placetype":"venue"
},
  "geometry": {"coordinates":[-111.00247299999999,32.177801],"type":"Point"}
}