{
  "type": "Feature",
  "properties": {
    "iso:country":"US",
    "sg:address":"11419 N Saguaro Blvd",
    "sg:city":"Fountain Hills",
    "sg:classifiers":[
        {
            "category":"Retail",
            "subcategory":"Car Wash",
            "type":"Services"
        }
    ],
    "sg:phone":"+1 480 816 4099",
    "sg:postcode":"85268",
    "sg:province":"AZ",
    "sg:tags":[
        "polishing",
        "washing"
    ],
    "wof:name":"Saguaro Carwash",
    "wof:placetype":"venue"
},
  "geometry": {"coordinates":[-111.706747,33.589989],"type":"Point"}
}