{
  "type": "Feature",
  "properties": {
    "iso:country":"US",
    "sg:address":"1234 W Bell Rd",
    "sg:city":"Phoenix",
    "sg:classifiers":[
        {
            "category":"Autos & Motor Vehicles",
            "subcategory":"Automobile Sales",
            "type":"Retail Goods"
        }
    ],
    "sg:phone":"+1 602 375 3750",
    "sg:postcode":"85023",
    "sg:province":"AZ",
    "sg:tags":[
        "dealership"
    ],
    "sg:website":"www.bellacura.com",
    "wof:name":"Bell Acura",
    "wof:placetype":"venue"
},
  "geometry": {"coordinates":[-112.090221,33.640256],"type":"Point"}
}