{
  "type": "Feature",
  "properties": {
    "addr:full":"2032 W Buckeye Rd Phoenix AZ 85009",
    "addr:housenumber":"2032",
    "addr:postcode":"85009",
    "addr:street":"W Buckeye Rd",
    "iso:country":"US",
    "sg:address":"2032 W Buckeye Rd",
    "sg:city":"Phoenix",
    "sg:classifiers":[
        {
            "category":"Building & Trades",
            "subcategory":"Construction",
            "type":"Services"
        },
        {
            "category":"Sports & Exercise",
            "subcategory":"Swimming Pool",
            "type":"Entertainment"
        }
    ],
    "sg:phone":"+1 602 272 0000",
    "sg:postcode":"85009",
    "sg:province":"AZ",
    "wof:name":"Mike's Construction",
    "wof:placetype":"venue"
},
  "geometry": {"coordinates":[-112.102868,33.436743],"type":"Point"}
}