{
  "type": "Feature",
  "properties": {
    "addr:full":"3002 E Washington St Phoenix AZ 85034",
    "addr:housenumber":"3002",
    "addr:postcode":"85034",
    "addr:street":"E Washington St",
    "iso:country":"US",
    "sg:address":"3002 E Washington St",
    "sg:city":"Phoenix",
    "sg:classifiers":[
        {
            "category":"Manufacturing",
            "subcategory":"Tools & Machinery",
            "type":"Manufacturing & Wholesale Goods"
        },
        {
            "category":"Wholesale",
            "subcategory":"Electrical",
            "type":"Manufacturing & Wholesale Goods"
        }
    ],
    "sg:phone":"+1 602 244 9009",
    "sg:postcode":"85034",
    "sg:province":"AZ",
    "sg:tags":[
        "electric",
        "supply",
        "equipment",
        "supplies-wholesale",
        "manufacturer"
    ],
    "wof:name":"Summers Group, Inc.",
    "wof:placetype":"venue"
},
  "geometry": {"coordinates":[-112.01682700000001,33.448269],"type":"Point"}
}