{
  "type": "Feature",
  "properties": {
    "addr:full":"6110 N 87th Ln Glendale AZ 85305",
    "addr:housenumber":"6110",
    "addr:postcode":"85305",
    "addr:street":"N 87Th Ln",
    "iso:country":"US",
    "sg:address":"6110 N 87th Ln",
    "sg:city":"Glendale",
    "sg:classifiers":[
        {
            "category":"Home & Garden",
            "subcategory":"Home Furnishings",
            "type":"Retail Goods"
        }
    ],
    "sg:phone":"+1 623 872 6414",
    "sg:postcode":"85305",
    "sg:province":"AZ",
    "sg:tags":[
        "glassware",
        "chinaware"
    ],
    "wof:name":"Princess House AAA Lifestyle",
    "wof:placetype":"venue"
},
  "geometry": {"coordinates":[-112.246842,33.524863],"type":"Point"}
}