{
  "type": "Feature",
  "properties": {
    "addr:full":"11296 E Sunnyside Dr Scottsdale AZ 85259",
    "addr:housenumber":"11296",
    "addr:postcode":"85259",
    "addr:street":"E Sunnyside Dr",
    "iso:country":"US",
    "sg:address":"11296 E Sunnyside Dr",
    "sg:city":"Scottsdale",
    "sg:classifiers":[
        {
            "category":"Building & Trades",
            "subcategory":"Construction",
            "type":"Services"
        }
    ],
    "sg:phone":"+1 480 657 6940",
    "sg:postcode":"85259",
    "sg:province":"AZ",
    "sg:tags":[
        "roofing",
        "contractor"
    ],
    "wof:name":"Seal Rite Roofing Inc",
    "wof:placetype":"venue"
},
  "geometry": {"coordinates":[-111.83716200000001,33.594029],"type":"Point"}
}