{
  "type": "Feature",
  "properties": {
    "iso:country":"US",
    "sg:address":"11296 E Sunnyside Dr",
    "sg:city":"Scottsdale",
    "sg:classifiers":[
        {
            "category":"Building & Trades",
            "subcategory":"Construction",
            "type":"Services"
        }
    ],
    "sg:phone":"+1 480 657 6940",
    "sg:postcode":"85259",
    "sg:province":"AZ",
    "sg:tags":[
        "roofing",
        "contractor"
    ],
    "wof:name":"Seal Rite Roofing Inc",
    "wof:placetype":"venue"
},
  "geometry": {"coordinates":[-111.837162,33.594029],"type":"Point"}
}