{
  "type": "Feature",
  "properties": {
    "iso:country":"US",
    "sg:address":"7154 E Stetson Dr Ste 310",
    "sg:city":"Scottsdale",
    "sg:classifiers":[
        {
            "category":"Professional",
            "subcategory":"Management & Consulting",
            "type":"Services"
        }
    ],
    "sg:phone":"+1 480 285 3535",
    "sg:postcode":"85251",
    "sg:province":"AZ",
    "sg:tags":[
        "consultant"
    ],
    "wof:name":"Brc Enterprises",
    "wof:placetype":"venue"
},
  "geometry": {"coordinates":[-111.92690899999999,33.49994],"type":"Point"}
}