{
  "type": "Feature",
  "properties": {
    "iso:country":"US",
    "sg:address":"4726 E Andrew St",
    "sg:city":"Tucson",
    "sg:classifiers":[
        {
            "category":"Recreation",
            "type":"Entertainment"
        }
    ],
    "sg:phone":"+1 520 591 2768",
    "sg:postcode":"85711",
    "sg:province":"AZ",
    "sg:tags":[
        "aquarium"
    ],
    "wof:name":"AAA Aquarium Cleaning",
    "wof:placetype":"venue"
},
  "geometry": {"coordinates":[-110.889251,32.203215],"type":"Point"}
}