{
  "type": "Feature",
  "properties": {
    "addr:full":"1904 N Black Canyon Hwy Phoenix AZ 85009",
    "addr:housenumber":"1904",
    "addr:postcode":"85009",
    "addr:street":"N Black Canyon Hwy",
    "iso:country":"US",
    "sg:address":"1904 N Black Canyon Hwy",
    "sg:city":"Phoenix",
    "sg:classifiers":[
        {
            "category":"Professional",
            "subcategory":"Advertising",
            "type":"Services"
        },
        {
            "category":"Retail",
            "subcategory":"Repair Shop",
            "type":"Services"
        },
        {
            "category":"Professional",
            "subcategory":"Printing & Photocopies",
            "type":"Services"
        },
        {
            "category":"Manufacturing",
            "subcategory":"Signs",
            "type":"Manufacturing & Wholesale Goods"
        }
    ],
    "sg:phone":"+1 602 272 9461",
    "sg:postcode":"85009",
    "sg:province":"AZ",
    "sg:tags":[
        "hanger",
        "specialty",
        "flag",
        "signs-maintenance",
        "pennant",
        "banners",
        "signs-erectors"
    ],
    "wof:name":"Pearson's Painting & Sign Co",
    "wof:placetype":"venue"
},
  "geometry": {"coordinates":[-112.111369,33.468239],"type":"Point"}
}