{
  "type": "Feature",
  "properties": {
    "iso:country":"US",
    "sg:address":"1335 W University Dr",
    "sg:city":"Tempe",
    "sg:classifiers":[
        {
            "category":"Health Services",
            "subcategory":"Clinic",
            "type":"Services"
        },
        {
            "category":"Food & Beverages",
            "subcategory":"Liquor & Beverages",
            "type":"Retail Goods"
        },
        {
            "category":"Wholesale",
            "subcategory":"Wine & Distilled Alcoholic Beverages",
            "type":"Manufacturing & Wholesale Goods"
        }
    ],
    "sg:phone":"+1 480 517 0404",
    "sg:postcode":"85281",
    "sg:province":"AZ",
    "sg:tags":[
        "information",
        "liquors-wholesale",
        "treatment",
        "alcoholism",
        "store"
    ],
    "wof:name":"Liquor Villa",
    "wof:placetype":"venue"
},
  "geometry": {"coordinates":[-111.959366,33.421928],"type":"Point"}
}