{
  "type": "Feature",
  "properties": {
    "addr:full":"4842 E Bell Rd Scottsdale AZ 85254",
    "addr:housenumber":"4842",
    "addr:postcode":"85254",
    "addr:street":"E Bell Rd",
    "iso:country":"US",
    "sg:address":"4842 E Bell Rd",
    "sg:city":"Scottsdale",
    "sg:classifiers":[
        {
            "category":"Food & Beverages",
            "subcategory":"Groceries & Convenience Stores",
            "type":"Retail Goods"
        }
    ],
    "sg:phone":"+1 602 867 0353",
    "sg:postcode":"85254",
    "sg:province":"AZ",
    "wof:name":"Smiths",
    "wof:placetype":"venue"
},
  "geometry": {"coordinates":[-111.97757300000001,33.640577],"type":"Point"}
}