{
  "type": "Feature",
  "properties": {
    "iso:country":"US",
    "sg:address":"4781 W New World Dr",
    "sg:city":"Glendale",
    "sg:classifiers":[
        {
            "category":"Professional",
            "subcategory":"Detective & Security Services",
            "type":"Services"
        }
    ],
    "sg:phone":"+1 623 937 7285",
    "sg:postcode":"85302",
    "sg:province":"AZ",
    "sg:tags":[
        "car",
        "bodyguard",
        "investment",
        "advisory"
    ],
    "wof:name":"Sentra Security Corporation",
    "wof:placetype":"venue"
},
  "geometry": {"coordinates":[-112.16275,33.56675],"type":"Point"}
}