{
  "type": "Feature",
  "properties": {
    "iso:country":"US",
    "sg:address":"1600 E Hanley Blvd",
    "sg:city":"Tucson",
    "sg:classifiers":[
        {
            "category":"Real Estate",
            "subcategory":"Real Estate Agent",
            "type":"Services"
        }
    ],
    "sg:phone":"+1 520 742 7001",
    "sg:postcode":"85737",
    "sg:province":"AZ",
    "wof:name":"Buzz Realty",
    "wof:placetype":"venue"
},
  "geometry": {"coordinates":[-110.947933,32.402647],"type":"Point"}
}