{
  "type": "Feature",
  "properties": {
    "iso:country":"US",
    "sg:address":"12801 W Bell Rd",
    "sg:city":"Surprise",
    "sg:classifiers":[
        {
            "category":"Shopping",
            "subcategory":"Bicycles & Sporting Goods",
            "type":"Retail Goods"
        }
    ],
    "sg:phone":"+1 623 974 3043",
    "sg:postcode":"85374",
    "sg:province":"AZ",
    "sg:website":"http://www.big5sportinggoods.com",
    "wof:name":"Big 5 Sporting Goods 380",
    "wof:placetype":"venue"
},
  "geometry": {"coordinates":[-112.335454,33.638452],"type":"Point"}
}