{
  "type": "Feature",
  "properties": {
    "iso:country":"US",
    "sg:address":"6245 E Cave Creek Rd",
    "sg:city":"Cave Creek",
    "sg:classifiers":[
        {
            "category":"Restaurant",
            "type":"Food & Drink"
        }
    ],
    "sg:phone":"+1 480 488 3317",
    "sg:postcode":"85331",
    "sg:province":"AZ",
    "sg:tags":[
        "traditional",
        "american"
    ],
    "sg:website":"silverspursaloon.com/",
    "wof:name":"Silver Spur Saloon",
    "wof:placetype":"venue"
},
  "geometry": {"coordinates":[-111.945634,33.831485],"type":"Point"}
}