{
  "type": "Feature",
  "properties": {
    "addr:full":"80 E Columbus Ave Phoenix AZ 85012",
    "addr:housenumber":"80",
    "addr:postcode":"85012",
    "addr:street":"E Columbus Ave",
    "iso:country":"US",
    "sg:address":"80 E Columbus Ave",
    "sg:city":"Phoenix",
    "sg:classifiers":[
        {
            "category":"Professional",
            "subcategory":"Lawyer & Legal Services",
            "type":"Services"
        },
        {
            "category":"Banks & Credit Unions",
            "subcategory":"Financial Services",
            "type":"Services"
        }
    ],
    "sg:phone":"+1 602 264 4550",
    "sg:postcode":"85012",
    "sg:province":"AZ",
    "sg:tags":[
        "attorney",
        "law",
        "bankruptcy"
    ],
    "wof:name":"New Delman, Allan D - Allan D Newdelman Pc",
    "wof:placetype":"venue"
},
  "geometry": {"coordinates":[-112.070204,33.489656],"type":"Point"}
}