{
  "type": "Feature",
  "properties": {
    "iso:country":"US",
    "sg:address":"3210 E Roeser Rd",
    "sg:city":"Phoenix",
    "sg:classifiers":[
        {
            "category":"Shopping",
            "subcategory":"Computers & Home Electronics",
            "type":"Retail Goods"
        }
    ],
    "sg:phone":"+1 602 243 5518",
    "sg:postcode":"85040",
    "sg:province":"AZ",
    "wof:name":"SCRAPCOMPUTER.COM",
    "wof:placetype":"venue"
},
  "geometry": {"coordinates":[-112.010968,33.3998],"type":"Point"}
}