{
  "type": "Feature",
  "properties": {
    "iso:country":"US",
    "sg:address":"15001 N Hayden Rd",
    "sg:city":"Scottsdale",
    "sg:classifiers":[
        {
            "category":"Building & Trades",
            "subcategory":"Construction",
            "type":"Services"
        }
    ],
    "sg:phone":"+1 480 596 8838",
    "sg:postcode":"85260",
    "sg:province":"AZ",
    "sg:tags":[
        "planning",
        "remodeling",
        "kitchen"
    ],
    "wof:name":"Design Instone Intl",
    "wof:placetype":"venue"
},
  "geometry": {"coordinates":[-111.905518,33.622261],"type":"Point"}
}