{
  "type": "Feature",
  "properties": {
    "iso:country":"US",
    "sg:address":"5933 S Red Tail Ln",
    "sg:city":"Hereford",
    "sg:classifiers":[
        {
            "category":"Building & Trades",
            "subcategory":"Construction",
            "type":"Services"
        }
    ],
    "sg:phone":"+1 520 378 6802",
    "sg:postcode":"85615",
    "sg:province":"AZ",
    "sg:tags":[
        "house"
    ],
    "wof:name":"Norsemen Construction LLC",
    "wof:placetype":"venue"
},
  "geometry": {"coordinates":[-110.209573,31.461846],"type":"Point"}
}