{
  "type": "Feature",
  "properties": {
    "iso:country":"US",
    "sg:address":"7014 E Camelback Rd",
    "sg:city":"Scottsdale",
    "sg:classifiers":[
        {
            "category":"Personal",
            "subcategory":"Beauty Salon",
            "type":"Services"
        }
    ],
    "sg:phone":"+1 480 945 1124",
    "sg:postcode":"85251",
    "sg:province":"AZ",
    "sg:tags":[
        "treatment",
        "skin"
    ],
    "sg:website":"www.usa.thebodyshop.com",
    "wof:name":"Body Shop",
    "wof:placetype":"venue"
},
  "geometry": {"coordinates":[-111.928875,33.502163],"type":"Point"}
}