{
  "type": "Feature",
  "properties": {
    "addr:full":"2450 N Huachuca Dr Tucson AZ 85745",
    "addr:housenumber":"2450",
    "addr:postcode":"85745",
    "addr:street":"N Huachuca Dr",
    "iso:country":"US",
    "sg:address":"2450 N Huachuca Dr",
    "sg:city":"Tucson",
    "sg:classifiers":[
        {
            "category":"Social Services",
            "subcategory":"Child Care",
            "type":"Services"
        }
    ],
    "sg:phone":"+1 520 882 4308",
    "sg:postcode":"85745",
    "sg:province":"AZ",
    "wof:name":"LA Casita",
    "wof:placetype":"venue"
},
  "geometry": {"coordinates":[-111.00218700000001,32.253298],"type":"Point"}
}