{
  "type": "Feature",
  "properties": {
    "iso:country":"US",
    "sg:address":"11010 S 51st St",
    "sg:city":"Phoenix",
    "sg:classifiers":[
        {
            "category":"Government",
            "subcategory":"Post Office",
            "type":"Public Place"
        }
    ],
    "sg:phone":"+1 480 893 1748",
    "sg:postcode":"85044",
    "sg:province":"AZ",
    "wof:name":"US Post Office",
    "wof:placetype":"venue"
},
  "geometry": {"coordinates":[-111.975003,33.346538],"type":"Point"}
}