{
  "type": "Feature",
  "properties": {
    "iso:country":"US",
    "sg:address":"119 6th St",
    "sg:city":"Sierra Vista",
    "sg:classifiers":[
        {
            "category":"Retail",
            "subcategory":"Auto Repair",
            "type":"Services"
        }
    ],
    "sg:phone":"+1 520 458 5399",
    "sg:postcode":"85635",
    "sg:province":"AZ",
    "sg:tags":[
        "body",
        "automobile",
        "painting"
    ],
    "wof:name":"Cruising Auto Body",
    "wof:placetype":"venue"
},
  "geometry": {"coordinates":[-110.292346,31.558149],"type":"Point"}
}