{
  "type": "Feature",
  "properties": {
    "addr:full":"4222 W Waltann Ln Phoenix AZ 85053",
    "addr:housenumber":"4222",
    "addr:postcode":"85053",
    "addr:street":"W Waltann Ln",
    "iso:country":"US",
    "sg:address":"4222 W Waltann Ln",
    "sg:city":"Phoenix",
    "sg:classifiers":[
        {
            "category":"Real Estate",
            "subcategory":"Real Estate Agent",
            "type":"Services"
        }
    ],
    "sg:phone":"+1 602 625 2170",
    "sg:postcode":"85053",
    "sg:province":"AZ",
    "wof:name":"Ione Heck Rl Est",
    "wof:placetype":"venue"
},
  "geometry": {"coordinates":[-112.148844,33.627032],"type":"Point"}
}