{
  "type": "Feature",
  "properties": {
    "iso:country":"US",
    "sg:address":"6616 E 2nd St",
    "sg:city":"Prescott Valley",
    "sg:classifiers":[
        {
            "category":"Home & Garden",
            "subcategory":"Furniture",
            "type":"Retail Goods"
        }
    ],
    "sg:phone":"+1 928 772 4510",
    "sg:postcode":"86314",
    "sg:province":"AZ",
    "sg:tags":[
        "mattress"
    ],
    "wof:name":"Mattress Americas",
    "wof:placetype":"venue"
},
  "geometry": {"coordinates":[-112.35193200000001,34.579932],"type":"Point"}
}