{
  "type": "Feature",
  "properties": {
    "iso:country":"US",
    "sg:address":"3811 E Bell Rd",
    "sg:city":"Phoenix",
    "sg:classifiers":[
        {
            "category":"Health Services",
            "subcategory":"Doctor",
            "type":"Services"
        }
    ],
    "sg:phone":"+1 602 493 6626",
    "sg:postcode":"85032",
    "sg:province":"AZ",
    "sg:tags":[
        "physician",
        "oncology",
        "surgeons",
        "surgeon",
        "gynecologic"
    ],
    "wof:name":"Bcg Oncology",
    "wof:placetype":"venue"
},
  "geometry": {"coordinates":[-112.000274,33.640596],"type":"Point"}
}