{
  "type": "Feature",
  "properties": {
    "iso:country":"US",
    "sg:address":"11024 N 28th Dr Ste 200",
    "sg:city":"Phoenix",
    "sg:classifiers":[
        {
            "category":"Structure",
            "subcategory":"Office Building",
            "type":"Public Place"
        }
    ],
    "sg:phone":"+1 602 866 6900",
    "sg:postcode":"85029",
    "sg:province":"AZ",
    "sg:tags":[
        "desk",
        "rental",
        "space"
    ],
    "sg:website":"http://www.interalfa.com",
    "wof:name":"Lake Biltmore Corporate Center",
    "wof:placetype":"venue"
},
  "geometry": {"coordinates":[-112.121871,33.587121],"type":"Point"}
}