{
  "type": "Feature",
  "properties": {
    "addr:full":"909 W 16th St Yuma AZ 85364",
    "addr:housenumber":"909",
    "addr:postcode":"85364",
    "addr:street":"W 16Th St",
    "iso:country":"US",
    "sg:address":"909 W 16th St",
    "sg:city":"Yuma",
    "sg:classifiers":[
        {
            "category":"Shopping",
            "subcategory":"Used Merchandise",
            "type":"Retail Goods"
        }
    ],
    "sg:phone":"+1 928 344 5557",
    "sg:postcode":"85364",
    "sg:province":"AZ",
    "wof:name":"Lil Stinkers",
    "wof:placetype":"venue"
},
  "geometry": {"coordinates":[-114.631096,32.698426],"type":"Point"}
}