{
  "type": "Feature",
  "properties": {
    "iso:country":"US",
    "sg:address":"5625 N Campbell Ave",
    "sg:city":"Tucson",
    "sg:classifiers":[
        {
            "category":"Professional",
            "subcategory":"Lawyer & Legal Services",
            "type":"Services"
        }
    ],
    "sg:phone":"+1 520 577 0815",
    "sg:postcode":"85718",
    "sg:province":"AZ",
    "sg:tags":[
        "attorney",
        "practice"
    ],
    "wof:name":"Traher, J Michael Attorney At Law",
    "wof:placetype":"venue"
},
  "geometry": {"coordinates":[-110.935021,32.308799],"type":"Point"}
}