{
  "type": "Feature",
  "properties": {
    "addr:full":"5106 N 51st Ave Glendale AZ 85301",
    "addr:housenumber":"5106",
    "addr:postcode":"85301",
    "addr:street":"N 51St Ave",
    "iso:country":"US",
    "sg:address":"5106 N 51st Ave",
    "sg:city":"Glendale",
    "sg:classifiers":[
        {
            "category":"Restaurant",
            "type":"Food & Drink"
        }
    ],
    "sg:phone":"+1 623 842 4946",
    "sg:postcode":"85301",
    "sg:province":"AZ",
    "sg:tags":[
        "eating"
    ],
    "wof:name":"Kahluas Bar & Grill",
    "wof:placetype":"venue"
},
  "geometry": {"coordinates":[-112.168819,33.511126],"type":"Point"}
}