{
  "type": "Feature",
  "properties": {
    "iso:country":"US",
    "sg:address":"7151 W Ray Rd",
    "sg:city":"Chandler",
    "sg:classifiers":[
        {
            "category":"Restaurant",
            "type":"Food & Drink"
        }
    ],
    "sg:phone":"+1 480 705 7697",
    "sg:postcode":"85226",
    "sg:province":"AZ",
    "sg:tags":[
        "american",
        "seafood"
    ],
    "sg:website":"http://www.roysrestaurant.com/",
    "wof:name":"Roy's",
    "wof:placetype":"venue"
},
  "geometry": {"coordinates":[-111.966642,33.319809],"type":"Point"}
}