{
  "type": "Feature",
  "properties": {
    "iso:country":"US",
    "sg:address":"6922 E Edgemont St",
    "sg:city":"Tucson",
    "sg:classifiers":[
        {
            "category":"Health Services",
            "subcategory":"Nursing And Care Facility",
            "type":"Services"
        }
    ],
    "sg:phone":"+1 520 885 6946",
    "sg:postcode":"85710",
    "sg:province":"AZ",
    "sg:tags":[
        "home",
        "retirement",
        "community"
    ],
    "wof:name":"Golden Days",
    "wof:placetype":"venue"
},
  "geometry": {"coordinates":[-110.84395600000001,32.23054],"type":"Point"}
}