{
  "type": "Feature",
  "properties": {
    "iso:country":"US",
    "sg:address":"9201 S Avenida del Yaqui",
    "sg:city":"Guadalupe",
    "sg:classifiers":[
        {
            "category":"Shopping",
            "subcategory":"Bicycles & Sporting Goods",
            "type":"Retail Goods"
        },
        {
            "category":"Professional",
            "subcategory":"Business Services",
            "type":"Services"
        },
        {
            "category":"Parking",
            "subcategory":"Bicycle",
            "type":"Transportation"
        }
    ],
    "sg:phone":"+1 480 839 1533",
    "sg:postcode":"85283",
    "sg:province":"AZ",
    "sg:tags":[
        "shop",
        "bicycles-wholesale",
        "system",
        "bicycles-repair",
        "security",
        "rack",
        "manufacturer"
    ],
    "sg:website":"http://www.garagebikeshop.com/",
    "wof:name":"The Garage Bike Shop",
    "wof:placetype":"venue"
},
  "geometry": {"coordinates":[-111.96312,33.363731],"type":"Point"}
}