{
  "type": "Feature",
  "properties": {
    "addr:full":"4222 E Thomas Rd Ste 400 Phoenix AZ 85018",
    "addr:housenumber":"4222",
    "addr:postcode":"85018",
    "addr:street":"E Thomas Rd Ste 400",
    "iso:country":"US",
    "sg:address":"4222 E Thomas Rd Ste 400",
    "sg:city":"Phoenix",
    "sg:classifiers":[
        {
            "category":"Education",
            "subcategory":"School",
            "type":"Public Place"
        }
    ],
    "sg:phone":"+1 602 850 8000",
    "sg:postcode":"85018",
    "sg:province":"AZ",
    "sg:tags":[
        "interest",
        "religious",
        "private",
        "k-"
    ],
    "wof:name":"Phoenix Seminary",
    "wof:placetype":"venue"
},
  "geometry": {"coordinates":[-111.990793,33.48037],"type":"Point"}
}