{
  "type": "Feature",
  "properties": {
    "iso:country":"US",
    "sg:address":"3010 S Potter Dr",
    "sg:city":"Tempe",
    "sg:classifiers":[
        {
            "category":"Communications",
            "type":"Services"
        }
    ],
    "sg:phone":"+1 602 438 4717",
    "sg:postcode":"85282",
    "sg:province":"AZ",
    "sg:tags":[
        "equipment",
        "data",
        "system"
    ],
    "wof:name":"Linksat Inc.",
    "wof:placetype":"venue"
},
  "geometry": {"coordinates":[-111.972328,33.396307],"type":"Point"}
}