{
  "type": "Feature",
  "properties": {
    "addr:full":"3465 Maricopa Ave Lake Havasu City AZ 86406",
    "addr:housenumber":"3465",
    "addr:postcode":"86406",
    "addr:street":"Maricopa Ave",
    "iso:country":"US",
    "sg:address":"3465 Maricopa Ave",
    "sg:city":"Lake Havasu City",
    "sg:classifiers":[
        {
            "category":"Food & Beverages",
            "subcategory":"Liquor & Beverages",
            "type":"Retail Goods"
        }
    ],
    "sg:phone":"+1 928 855 1078",
    "sg:postcode":"86406",
    "sg:province":"AZ",
    "sg:tags":[
        "drinking",
        "eating",
        "alcoholic"
    ],
    "wof:name":"Homestead Sloon Stkhuse Lq Str",
    "wof:placetype":"venue"
},
  "geometry": {"coordinates":[-114.271232,34.457015],"type":"Point"}
}