{
  "type": "Feature",
  "properties": {
    "iso:country":"US",
    "sg:address":"10842 S Via Salida",
    "sg:city":"Yuma",
    "sg:classifiers":[
        {
            "category":"Banks & Credit Unions",
            "subcategory":"Financial Services",
            "type":"Services"
        }
    ],
    "sg:phone":"+1 928 342 3376",
    "sg:postcode":"85367",
    "sg:province":"AZ",
    "sg:tags":[
        "trust",
        "management"
    ],
    "wof:name":"Vernon M Langager Trust",
    "wof:placetype":"venue"
},
  "geometry": {"coordinates":[-114.429263,32.671366],"type":"Point"}
}