{
  "type": "Feature",
  "properties": {
    "iso:country":"US",
    "sg:address":"3725 E Fort Lowell Rd",
    "sg:city":"Tucson",
    "sg:classifiers":[
        {
            "category":"Home & Garden",
            "subcategory":"Furniture",
            "type":"Retail Goods"
        },
        {
            "category":"Wholesale",
            "subcategory":"Furniture",
            "type":"Manufacturing & Wholesale Goods"
        }
    ],
    "sg:phone":"+1 520 881 4249",
    "sg:postcode":"85716",
    "sg:province":"AZ",
    "sg:tags":[
        "retailer",
        "for"
    ],
    "wof:name":"Knock On Wood Inc",
    "wof:placetype":"venue"
},
  "geometry": {"coordinates":[-110.913687,32.265192],"type":"Point"}
}