{
  "type": "Feature",
  "properties": {
    "addr:full":"3838 E Grove St Phoenix AZ 85040",
    "addr:housenumber":"3838",
    "addr:postcode":"85040",
    "addr:street":"E Grove St",
    "iso:country":"US",
    "sg:address":"3838 E Grove St",
    "sg:city":"Phoenix",
    "sg:classifiers":[
        {
            "category":"Home & Garden",
            "subcategory":"Home Furnishings",
            "type":"Retail Goods"
        },
        {
            "category":"Building & Trades",
            "subcategory":"Construction",
            "type":"Services"
        },
        {
            "category":"Manufacturing",
            "subcategory":"Building Materials",
            "type":"Manufacturing & Wholesale Goods"
        },
        {
            "category":"Home & Garden",
            "subcategory":"Furniture",
            "type":"Retail Goods"
        }
    ],
    "sg:phone":"+1 602 437 1133",
    "sg:postcode":"85040",
    "sg:province":"AZ",
    "sg:tags":[
        "industrial",
        "cabinetmakers-commercial",
        "carpenter",
        "cabinet",
        "refacing",
        "resurfacing",
        "contractor",
        "equipment-household",
        "maker",
        "cabinets-refinishing",
        "kitchen"
    ],
    "wof:name":"Woodworks Unlimited Inc",
    "wof:placetype":"venue"
},
  "geometry": {"coordinates":[-111.998391,33.398132],"type":"Point"}
}