{
  "type": "Feature",
  "properties": {
    "iso:country":"US",
    "sg:address":"1929 E Jefferson St",
    "sg:city":"Phoenix",
    "sg:classifiers":[
        {
            "category":"Retail",
            "subcategory":"Auto Repair",
            "type":"Services"
        }
    ],
    "sg:phone":"+1 602 253 0778",
    "sg:postcode":"85034",
    "sg:province":"AZ",
    "sg:tags":[
        "body",
        "automobile",
        "painting",
        "repairing"
    ],
    "sg:website":"http://www.randyfordplaywright.com",
    "wof:name":"Randy Specialties",
    "wof:placetype":"venue"
},
  "geometry": {"coordinates":[-112.040583,33.447182],"type":"Point"}
}