{
  "type": "Feature",
  "properties": {
    "iso:country":"US",
    "sg:address":"8840 E Chaparral Rd # 185",
    "sg:city":"Scottsdale",
    "sg:classifiers":[
        {
            "category":"Restaurant",
            "type":"Food & Drink"
        }
    ],
    "sg:phone":"+1 602 553 0202",
    "sg:postcode":"85250",
    "sg:province":"AZ",
    "sg:tags":[
        "asian",
        "chinese",
        "pan"
    ],
    "wof:name":"Y C's Mongolian Barbecue",
    "wof:placetype":"venue"
},
  "geometry": {"coordinates":[-111.89044199999999,33.509369],"type":"Point"}
}