{
  "type": "Feature",
  "properties": {
    "addr:full":"1312 S California Ave Parker AZ 85344",
    "addr:housenumber":"1312",
    "addr:postcode":"az 85344",
    "addr:street":"S California Ave",
    "iso:country":"US",
    "sg:address":"1312 S California Ave",
    "sg:city":"Parker",
    "sg:classifiers":[
        {
            "category":"Insurance",
            "subcategory":"Insurance Agent",
            "type":"Services"
        }
    ],
    "sg:phone":"+1 928 669 2698",
    "sg:postcode":"85344",
    "sg:province":"AZ",
    "wof:name":"Richard O Dell",
    "wof:placetype":"venue"
},
  "geometry": {"coordinates":[-114.287325,34.147227],"type":"Point"}
}