{
  "type": "Feature",
  "properties": {
    "iso:country":"US",
    "sg:address":"7885 W Arrowhead Towne Center",
    "sg:city":"Glendale",
    "sg:classifiers":[
        {
            "category":"Travel",
            "subcategory":"Hotels & Motels",
            "type":"Entertainment"
        }
    ],
    "sg:phone":"+1 623 412 2000",
    "sg:postcode":"85308",
    "sg:province":"AZ",
    "wof:name":"Ramada Inn-Arrowhead Mall",
    "wof:placetype":"venue"
},
  "geometry": {"coordinates":[-112.229645,33.641452],"type":"Point"}
}