{
  "type": "Feature",
  "properties": {
    "iso:country":"US",
    "sg:address":"8518 E Gary Rd",
    "sg:city":"Scottsdale",
    "sg:classifiers":[
        {
            "category":"Building & Trades",
            "subcategory":"Construction",
            "type":"Services"
        }
    ],
    "sg:phone":"+1 480 368 0366",
    "sg:postcode":"85260",
    "sg:province":"AZ",
    "sg:tags":[
        "contractor"
    ],
    "wof:name":"PC Pools Service & Repair LLC",
    "wof:placetype":"venue"
},
  "geometry": {"coordinates":[-111.894332,33.587914],"type":"Point"}
}