{
  "type": "Feature",
  "properties": {
    "iso:country":"US",
    "sg:address":"244 W Vera Ln",
    "sg:city":"Tempe",
    "sg:classifiers":[
        {
            "category":"Real Estate",
            "subcategory":"Real Estate Agent",
            "type":"Services"
        }
    ],
    "sg:phone":"+1 480 785 0934",
    "sg:postcode":"85284",
    "sg:province":"AZ",
    "wof:name":"Morton Appraisals",
    "wof:placetype":"venue"
},
  "geometry": {"coordinates":[-111.943409,33.326715],"type":"Point"}
}