{
  "type": "Feature",
  "properties": {
    "addr:full":"1405 S Honeysuckle Cir Gilbert AZ 85296",
    "addr:housenumber":"1405",
    "addr:postcode":"85296",
    "addr:street":"S Honeysuckle Cir",
    "iso:country":"US",
    "sg:address":"1405 S Honeysuckle Cir",
    "sg:city":"Gilbert",
    "sg:classifiers":[
        {
            "category":"Professional",
            "subcategory":"Business Services",
            "type":"Services"
        }
    ],
    "sg:phone":"+1 602 330 6109",
    "sg:postcode":"85296",
    "sg:province":"AZ",
    "sg:tags":[
        "pool",
        "swimming"
    ],
    "wof:name":"D & M Quality Pool Svc",
    "wof:placetype":"venue"
},
  "geometry": {"coordinates":[-111.773691,33.324436],"type":"Point"}
}