{
  "type": "Feature",
  "properties": {
    "addr:full":"4250 W Anthem Way Phoenix AZ 85086",
    "addr:housenumber":"4250",
    "addr:postcode":"85086",
    "addr:street":"W Anthem Way",
    "iso:country":"US",
    "sg:address":"4250 W Anthem Way",
    "sg:city":"Phoenix",
    "sg:classifiers":[
        {
            "category":"Bakery",
            "type":"Food & Drink"
        }
    ],
    "sg:menulink":"http://www.allmenus.com/az/deer-valley/219727-auntie-annes-pretzels/menu/",
    "sg:phone":"+1 623 742 6463",
    "sg:postcode":"85086",
    "sg:province":"AZ",
    "sg:tags":[
        "american",
        "pastry"
    ],
    "wof:name":"Auntie Anne's Pretzels",
    "wof:placetype":"venue"
},
  "geometry": {"coordinates":[-112.144688,33.870849],"type":"Point"}
}