{
  "type": "Feature",
  "properties": {
    "iso:country":"US",
    "sg:address":"15821 S 35th Way",
    "sg:city":"Phoenix",
    "sg:classifiers":[
        {
            "category":"Organizations",
            "subcategory":"Community Association",
            "type":"Services"
        },
        {
            "category":"Organizations",
            "subcategory":"Non-profit Organization",
            "type":"Services"
        }
    ],
    "sg:phone":"+1 480 759 6329",
    "sg:postcode":"85048",
    "sg:province":"AZ",
    "sg:tags":[
        "fund",
        "raising"
    ],
    "wof:name":"Asperger Parent Network",
    "wof:placetype":"venue"
},
  "geometry": {"coordinates":[-112.00627900000001,33.302841],"type":"Point"}
}