{
  "type": "Feature",
  "properties": {
    "iso:country":"US",
    "sg:address":"7428 E Stetson Dr",
    "sg:city":"Scottsdale",
    "sg:classifiers":[
        {
            "category":"Insurance",
            "subcategory":"Insurance Agent",
            "type":"Services"
        }
    ],
    "sg:phone":"+1 480 970 6443",
    "sg:postcode":"85251",
    "sg:province":"AZ",
    "sg:tags":[
        "wholesale",
        "broker"
    ],
    "wof:name":"BJ Insurance Services LLC",
    "wof:placetype":"venue"
},
  "geometry": {"coordinates":[-111.920388,33.499634],"type":"Point"}
}