{
  "type": "Feature",
  "properties": {
    "iso:country":"US",
    "sg:address":"7812 N 27th Ave",
    "sg:city":"Phoenix",
    "sg:classifiers":[
        {
            "category":"Organizations",
            "subcategory":"Non-profit Organization",
            "type":"Services"
        }
    ],
    "sg:phone":"+1 602 995 2838",
    "sg:postcode":"85051",
    "sg:province":"AZ",
    "sg:tags":[
        "disability"
    ],
    "wof:name":"Quest Alliance",
    "wof:placetype":"venue"
},
  "geometry": {"coordinates":[-112.117044,33.551982],"type":"Point"}
}