{
  "type": "Feature",
  "properties": {
    "iso:country":"US",
    "sg:address":"5255 E Williams Cir Ste 6800",
    "sg:city":"Tucson",
    "sg:classifiers":[
        {
            "category":"Professional",
            "subcategory":"Management & Consulting",
            "type":"Services"
        },
        {
            "category":"Professional",
            "subcategory":"Employment Agencies",
            "type":"Services"
        }
    ],
    "sg:phone":"+1 520 584 3490",
    "sg:postcode":"85711",
    "sg:province":"AZ",
    "sg:tags":[
        "consultant",
        "search",
        "executive",
        "temporary",
        "contractor"
    ],
    "sg:website":"http://www.officeteam.com",
    "wof:name":"Office Team",
    "wof:placetype":"venue"
},
  "geometry": {"coordinates":[-110.881152,32.220512],"type":"Point"}
}