{
  "type": "Feature",
  "properties": {
    "iso:country":"US",
    "sg:address":"2785 W Hwy 89A",
    "sg:city":"Sedona",
    "sg:classifiers":[
        {
            "category":"Home & Garden",
            "subcategory":"Furniture",
            "type":"Retail Goods"
        }
    ],
    "sg:phone":"+1 928 204 1195",
    "sg:postcode":"86336",
    "sg:province":"AZ",
    "wof:name":"Desert Moon Furniture",
    "wof:placetype":"venue"
},
  "geometry": {"coordinates":[-111.808276,34.862381],"type":"Point"}
}