{
  "type": "Feature",
  "properties": {
    "iso:country":"US",
    "sg:address":"614 E Glenn St",
    "sg:city":"Tucson",
    "sg:classifiers":[
        {
            "category":"Retail",
            "subcategory":"Auto Repair",
            "type":"Services"
        }
    ],
    "sg:phone":"+1 520 884 8800",
    "sg:postcode":"85705",
    "sg:province":"AZ",
    "sg:tags":[
        "repairing",
        "automobile"
    ],
    "sg:website":"www.stuttgartautohaus.com",
    "wof:name":"Stuttgart-Autohaus Inc",
    "wof:placetype":"venue"
},
  "geometry": {"coordinates":[-110.961129,32.257588],"type":"Point"}
}