{
  "type": "Feature",
  "properties": {
    "iso:country":"US",
    "sg:address":"20820 N 25th Pl",
    "sg:city":"Phoenix",
    "sg:classifiers":[
        {
            "category":"Shopping",
            "subcategory":"Optical Goods",
            "type":"Retail Goods"
        }
    ],
    "sg:phone":"+1 602 996 3088",
    "sg:postcode":"85050",
    "sg:province":"AZ",
    "wof:name":"Carlton Optical",
    "wof:placetype":"venue"
},
  "geometry": {"coordinates":[-112.028112,33.676644],"type":"Point"}
}