{
  "type": "Feature",
  "properties": {
    "iso:country":"US",
    "sg:address":"4828 E Earll Dr",
    "sg:city":"Phoenix",
    "sg:classifiers":[
        {
            "category":"Organizations",
            "subcategory":"Professional Association",
            "type":"Services"
        }
    ],
    "sg:phone":"+1 602 840 0457",
    "sg:postcode":"85018",
    "sg:province":"AZ",
    "wof:name":"Arcadia Greens",
    "wof:placetype":"venue"
},
  "geometry": {"coordinates":[-111.976849,33.48379],"type":"Point"}
}