{
  "type": "Feature",
  "properties": {
    "iso:country":"US",
    "sg:address":"3919 E Potter Dr",
    "sg:city":"Phoenix",
    "sg:classifiers":[
        {
            "category":"Shopping",
            "subcategory":"Books",
            "type":"Retail Goods"
        }
    ],
    "sg:phone":"+1 480 502 0266",
    "sg:postcode":"85050",
    "sg:province":"AZ",
    "sg:tags":[
        "store"
    ],
    "wof:name":"High Value Book Sales",
    "wof:placetype":"venue"
},
  "geometry": {"coordinates":[-111.997069,33.675496],"type":"Point"}
}