{
  "type": "Feature",
  "properties": {
    "iso:country":"US",
    "sg:address":"1007 W Taylor St",
    "sg:city":"Phoenix",
    "sg:classifiers":[
        {
            "category":"Place Of Worship",
            "type":"Public Place"
        }
    ],
    "sg:phone":"+1 602 262 2157",
    "sg:postcode":"85007",
    "sg:province":"AZ",
    "sg:tags":[
        "church"
    ],
    "wof:name":"Cristo Viene",
    "wof:placetype":"venue"
},
  "geometry": {"coordinates":[-112.086046,33.454242],"type":"Point"}
}