{
  "type": "Feature",
  "properties": {
    "iso:country":"US",
    "sg:address":"4811 E Cindrich St",
    "sg:city":"Tucson",
    "sg:classifiers":[
        {
            "category":"Wholesale",
            "subcategory":"Auto Parts",
            "type":"Manufacturing & Wholesale Goods"
        }
    ],
    "sg:phone":"+1 520 574 1808",
    "sg:postcode":"85706",
    "sg:province":"AZ",
    "sg:tags":[
        "used"
    ],
    "wof:name":"Catalina Auto Ranch",
    "wof:placetype":"venue"
},
  "geometry": {"coordinates":[-110.889976,32.154261],"type":"Point"}
}