{
  "type": "Feature",
  "properties": {
    "addr:full":"301 E Route 66 Williams AZ 86046",
    "addr:housenumber":"301",
    "addr:postcode":"86046",
    "addr:street":"E Route 66",
    "iso:country":"US",
    "sg:address":"301 E Route 66",
    "sg:city":"Williams",
    "sg:classifiers":[
        {
            "category":"Bars & Pubs",
            "type":"Food & Drink"
        },
        {
            "category":"Restaurant",
            "type":"Food & Drink"
        }
    ],
    "sg:phone":"+1 928 635 2671",
    "sg:postcode":"86046",
    "sg:province":"AZ",
    "sg:tags":[
        "brew",
        "house",
        "steak"
    ],
    "sg:website":"http://www.rods-steakhouse.com",
    "wof:name":"Rod's Steak House",
    "wof:placetype":"venue"
},
  "geometry": {"coordinates":[-112.18946099999999,35.25013],"type":"Point"}
}