{
  "type": "Feature",
  "properties": {
    "iso:country":"US",
    "sg:address":"3830 E Indian School Rd",
    "sg:city":"Phoenix",
    "sg:classifiers":[
        {
            "category":"Building & Trades",
            "subcategory":"Construction",
            "type":"Services"
        }
    ],
    "sg:phone":"+1 602 275 5906",
    "sg:postcode":"85018",
    "sg:province":"AZ",
    "sg:tags":[
        "repairing",
        "remodeling",
        "contractor"
    ],
    "wof:name":"Accurate Estimating Svc",
    "wof:placetype":"venue"
},
  "geometry": {"coordinates":[-111.998142,33.495218],"type":"Point"}
}