{
  "type": "Feature",
  "properties": {
    "addr:full":"4722 S Tennessee Pl Tucson AZ 85714",
    "addr:housenumber":"4722",
    "addr:postcode":"85714",
    "addr:street":"S Tennessee Pl",
    "iso:country":"US",
    "sg:address":"4722 S Tennessee Pl",
    "sg:city":"Tucson",
    "sg:classifiers":[
        {
            "category":"Wholesale",
            "subcategory":"Home Furnishings",
            "type":"Manufacturing & Wholesale Goods"
        }
    ],
    "sg:phone":"+1 520 747 7244",
    "sg:postcode":"85714",
    "sg:province":"AZ",
    "sg:tags":[
        "top",
        "marble",
        "cultured"
    ],
    "wof:name":"Accent Interiors",
    "wof:placetype":"venue"
},
  "geometry": {"coordinates":[-110.905856,32.165373],"type":"Point"}
}