{
  "type": "Feature",
  "properties": {
    "addr:full":"5112 N 40th St Phoenix AZ 85018",
    "addr:housenumber":"5112",
    "addr:postcode":"85018",
    "addr:street":"N 40Th St",
    "iso:country":"US",
    "sg:address":"5112 N 40th St",
    "sg:city":"Phoenix",
    "sg:phone":"+1 602 220 0197",
    "sg:postcode":"85018",
    "sg:province":"AZ",
    "sg:tags":[
        "equipment",
        "commercial"
    ],
    "wof:name":"Western Restaurant Equipment",
    "wof:placetype":"venue"
},
  "geometry": {"coordinates":[-111.995362,33.512189],"type":"Point"}
}