{
  "type": "Feature",
  "properties": {
    "addr:full":"14423 S 24th Pl Phoenix AZ 85048",
    "addr:housenumber":"14423",
    "addr:postcode":"85048",
    "addr:street":"S 24Th Pl",
    "iso:country":"US",
    "sg:address":"14423 S 24th Pl",
    "sg:city":"Phoenix",
    "sg:classifiers":[
        {
            "category":"Manufacturing",
            "subcategory":"Printing",
            "type":"Manufacturing & Wholesale Goods"
        }
    ],
    "sg:phone":"+1 602 460 0099",
    "sg:postcode":"85048",
    "sg:province":"AZ",
    "sg:tags":[
        "publishing"
    ],
    "wof:name":"Palmae Publishing",
    "wof:placetype":"venue"
},
  "geometry": {"coordinates":[-112.028008,33.315928],"type":"Point"}
}