{
  "type": "Feature",
  "properties": {
    "iso:country":"US",
    "sg:address":"2111 S Alma School Road",
    "sg:city":"Mesa",
    "sg:classifiers":[
        {
            "category":"Personal",
            "subcategory":"Massage",
            "type":"Services"
        }
    ],
    "sg:phone":"+1 480 755 8828",
    "sg:postcode":"85210",
    "sg:province":"AZ",
    "wof:name":"Ace Massage",
    "wof:placetype":"venue"
},
  "geometry": {"coordinates":[-111.859674,33.376645],"type":"Point"}
}