{
  "type": "Feature",
  "properties": {
    "iso:country":"US",
    "sg:address":"1718 N Mesa Dr",
    "sg:city":"Mesa",
    "sg:classifiers":[
        {
            "category":"Organizations",
            "subcategory":"Religious Organization",
            "type":"Services"
        }
    ],
    "sg:phone":"+1 480 964 1083",
    "sg:postcode":"85201",
    "sg:province":"AZ",
    "sg:tags":[
        "church"
    ],
    "wof:name":"Fountain Of Life",
    "wof:placetype":"venue"
},
  "geometry": {"coordinates":[-111.822498,33.445809],"type":"Point"}
}