{
  "type": "Feature",
  "properties": {
    "iso:country":"US",
    "sg:address":"890 W Grant Rd",
    "sg:city":"Tucson",
    "sg:classifiers":[
        {
            "category":"Insurance",
            "subcategory":"Insurance Agent",
            "type":"Services"
        },
        {
            "category":"Insurance",
            "subcategory":"Hazard Insurance",
            "type":"Services"
        },
        {
            "category":"Insurance",
            "subcategory":"Title Insurance",
            "type":"Services"
        }
    ],
    "sg:phone":"+1 520 620 0222",
    "sg:postcode":"85705",
    "sg:province":"AZ",
    "sg:tags":[
        "business",
        "auto",
        "commercial",
        "homeowner",
        "property",
        "casualty"
    ],
    "sg:website":"http://www.insurewithabc.com",
    "wof:name":"Mercury Insurance - Abc Insurance & Financial Serv",
    "wof:placetype":"venue"
},
  "geometry": {"coordinates":[-110.986164,32.250364],"type":"Point"}
}