{
  "type": "Feature",
  "properties": {
    "iso:country":"US",
    "sg:address":"29810 N 163rd St",
    "sg:city":"Scottsdale",
    "sg:phone":"+1 480 471 7920",
    "sg:postcode":"85262",
    "sg:province":"AZ",
    "wof:name":"Theresa Boks",
    "wof:placetype":"venue"
},
  "geometry": {"coordinates":[-111.72844,33.756104],"type":"Point"}
}