{
  "type": "Feature",
  "properties": {
    "addr:full":"8282 E Pima St Tucson AZ 85715",
    "addr:housenumber":"8282",
    "addr:postcode":"85715",
    "addr:street":"E Pima St",
    "iso:country":"US",
    "sg:address":"8282 E Pima St",
    "sg:city":"Tucson",
    "sg:classifiers":[
        {
            "category":"Organizations",
            "subcategory":"Religious Organization",
            "type":"Services"
        }
    ],
    "sg:phone":"+1 520 296 7755",
    "sg:postcode":"85715",
    "sg:province":"AZ",
    "sg:tags":[
        "church"
    ],
    "sg:website":"www.newapostolicchurch.org",
    "wof:name":"New Apostolic Church",
    "wof:placetype":"venue"
},
  "geometry": {"coordinates":[-110.819171,32.242764],"type":"Point"}
}