{
  "type": "Feature",
  "properties": {
    "iso:country":"US",
    "sg:address":"9 el Dorado Ct",
    "sg:city":"Page",
    "sg:classifiers":[
        {
            "category":"Building & Trades",
            "subcategory":"Construction",
            "type":"Services"
        }
    ],
    "sg:phone":"+1 928 645 4093",
    "sg:postcode":"86040",
    "sg:province":"AZ",
    "sg:tags":[
        "stucco",
        "contractor"
    ],
    "wof:name":"Gallagher Stucco",
    "wof:placetype":"venue"
},
  "geometry": {"coordinates":[-111.449646,36.916085],"type":"Point"}
}