{
  "type": "Feature",
  "properties": {
    "iso:country":"US",
    "sg:address":"1922 N Rustlers Trl",
    "sg:city":"Camp Verde",
    "sg:classifiers":[
        {
            "category":"Wholesale",
            "subcategory":"Construction Materials",
            "type":"Manufacturing & Wholesale Goods"
        }
    ],
    "sg:phone":"+1 928 567 4318",
    "sg:postcode":"86322",
    "sg:province":"AZ",
    "sg:tags":[
        "concrete",
        "shape",
        "block"
    ],
    "wof:name":"Curbco Custom Curbing LLC",
    "wof:placetype":"venue"
},
  "geometry": {"coordinates":[-111.878513,34.593808],"type":"Point"}
}