{
  "type": "Feature",
  "properties": {
    "iso:country":"US",
    "sg:address":"1747 N Alma School Rd",
    "sg:city":"Mesa",
    "sg:classifiers":[
        {
            "category":"Personal",
            "subcategory":"Massage",
            "type":"Services"
        }
    ],
    "sg:phone":"+1 480 835 5318",
    "sg:postcode":"85201",
    "sg:province":"AZ",
    "wof:name":"LA Palma Massage",
    "wof:placetype":"venue"
},
  "geometry": {"coordinates":[-111.85635000000001,33.445954],"type":"Point"}
}