{
  "type": "Feature",
  "properties": {
    "iso:country":"US",
    "sg:address":"302 E Flower St",
    "sg:city":"Phoenix",
    "sg:classifiers":[
        {
            "category":"Real Estate",
            "subcategory":"Real Estate Operator",
            "type":"Services"
        }
    ],
    "sg:phone":"+1 602 279 1747",
    "sg:postcode":"85012",
    "sg:province":"AZ",
    "sg:tags":[
        "building",
        "nonresidential"
    ],
    "wof:name":"California Daze",
    "wof:placetype":"venue"
},
  "geometry": {"coordinates":[-112.06720300000001,33.48567],"type":"Point"}
}