{
  "type": "Feature",
  "properties": {
    "iso:country":"US",
    "sg:address":"218 S McCormick St",
    "sg:city":"Prescott",
    "sg:classifiers":[
        {
            "category":"Real Estate",
            "subcategory":"Real Estate Operator",
            "type":"Services"
        }
    ],
    "sg:phone":"+1 928 778 4778",
    "sg:postcode":"86303",
    "sg:province":"AZ",
    "sg:tags":[
        "building",
        "apartment"
    ],
    "wof:name":"Yavapai Apartments",
    "wof:placetype":"venue"
},
  "geometry": {"coordinates":[-112.473024,34.539724],"type":"Point"}
}