{
  "type": "Feature",
  "properties": {
    "iso:country":"US",
    "sg:address":"1695 W Drake Dr",
    "sg:city":"Tempe",
    "sg:classifiers":[
        {
            "category":"Manufacturing",
            "subcategory":"Tools & Machinery",
            "type":"Manufacturing & Wholesale Goods"
        }
    ],
    "sg:phone":"+1 480 967 5354",
    "sg:postcode":"85283",
    "sg:province":"AZ",
    "sg:tags":[
        "industrial",
        "grinding"
    ],
    "sg:website":"http://www.pgm-tools.com",
    "wof:name":"Performance Grinding & Mfg Inc",
    "wof:placetype":"venue"
},
  "geometry": {"coordinates":[-111.96531299999999,33.355114],"type":"Point"}
}