{
  "type": "Feature",
  "properties": {
    "iso:country":"US",
    "sg:address":"23636 N 79th Ave",
    "sg:city":"Peoria",
    "sg:classifiers":[
        {
            "category":"Building & Trades",
            "subcategory":"Landscaping Services",
            "type":"Services"
        },
        {
            "category":"Social Services",
            "subcategory":"Retirement Home",
            "type":"Services"
        }
    ],
    "sg:phone":"+1 623 376 7198",
    "sg:postcode":"85383",
    "sg:province":"AZ",
    "sg:tags":[
        "convalescent",
        "aged",
        "nursing",
        "homes-institutional"
    ],
    "wof:name":"Legacy Manor Assisted Living",
    "wof:placetype":"venue"
},
  "geometry": {"coordinates":[-112.228989,33.697698],"type":"Point"}
}