{
  "type": "Feature",
  "properties": {
    "addr:full":"4842 S Oleander Dr Chandler AZ 85248",
    "addr:housenumber":"4842",
    "addr:postcode":"85248",
    "addr:street":"S Oleander Dr",
    "iso:country":"US",
    "sg:address":"4842 S Oleander Dr",
    "sg:city":"Chandler",
    "sg:classifiers":[
        {
            "category":"Professional",
            "type":"Services"
        }
    ],
    "sg:phone":"+1 480 802 8350",
    "sg:postcode":"85248",
    "sg:province":"AZ",
    "wof:name":"Skidmore Rance William Jo",
    "wof:placetype":"venue"
},
  "geometry": {"coordinates":[-111.869227,33.235677],"type":"Point"}
}