{
  "type": "Feature",
  "properties": {
    "addr:full":"1432 S Dobson Rd Ste 301 Mesa AZ 85202",
    "addr:housenumber":"1432",
    "addr:postcode":"85202",
    "addr:street":"S Dobson Rd Ste 301",
    "iso:country":"US",
    "sg:address":"1432 S Dobson Rd Ste 301",
    "sg:city":"Mesa",
    "sg:classifiers":[
        {
            "category":"Health Services",
            "subcategory":"Doctor",
            "type":"Services"
        }
    ],
    "sg:phone":"+1 480 412 9400",
    "sg:postcode":"85202",
    "sg:province":"AZ",
    "sg:tags":[
        "pediatrician"
    ],
    "sg:website":"www.bannerhealth.com/_Banner+Med...",
    "wof:name":"Banner Pediatric Specialists",
    "wof:placetype":"venue"
},
  "geometry": {"coordinates":[-111.87467599999999,33.389275],"type":"Point"}
}