{
  "type": "Feature",
  "properties": {
    "addr:full":"1101 E Thomas Rd Phoenix AZ 85014",
    "addr:housenumber":"1101",
    "addr:postcode":"85014",
    "addr:street":"E Thomas Rd",
    "iso:country":"US",
    "sg:address":"1101 E Thomas Rd",
    "sg:city":"Phoenix",
    "sg:classifiers":[
        {
            "category":"Education",
            "subcategory":"School",
            "type":"Public Place"
        }
    ],
    "sg:phone":"+1 602 764 6500",
    "sg:postcode":"85014",
    "sg:province":"AZ",
    "sg:tags":[
        "high"
    ],
    "sg:website":"http://www.north.ecasd.k12.wi.us",
    "wof:name":"North High School",
    "wof:placetype":"venue"
},
  "geometry": {"coordinates":[-112.059624,33.48024],"type":"Point"}
}