{
  "type": "Feature",
  "properties": {
    "iso:country":"US",
    "sg:address":"5335 E Shea Blvd",
    "sg:city":"Scottsdale",
    "sg:classifiers":[
        {
            "category":"Shopping",
            "type":"Retail Goods"
        }
    ],
    "sg:phone":"+1 480 778 1728",
    "sg:postcode":"85254",
    "sg:province":"AZ",
    "sg:tags":[
        "cosmetic",
        "perfume"
    ],
    "wof:name":"Avon",
    "wof:placetype":"venue"
},
  "geometry": {"coordinates":[-111.965871,33.582588],"type":"Point"}
}