{
  "type": "Feature",
  "properties": {
    "iso:country":"US",
    "sg:address":"2967 N Alvernon Way",
    "sg:city":"Tucson",
    "sg:classifiers":[
        {
            "category":"Manufacturing",
            "subcategory":"Tools & Machinery",
            "type":"Manufacturing & Wholesale Goods"
        }
    ],
    "sg:phone":"+1 520 325 7650",
    "sg:postcode":"85712",
    "sg:province":"AZ",
    "sg:tags":[
        "industrial",
        "mfg"
    ],
    "sg:website":"www.thevillageblacksmith.com",
    "wof:name":"Village Blacksmith",
    "wof:placetype":"venue"
},
  "geometry": {"coordinates":[-110.909874,32.26027],"type":"Point"}
}