{
  "type": "Feature",
  "properties": {
    "iso:country":"US",
    "sg:address":"4232 E Chandler Blvd",
    "sg:city":"Phoenix",
    "sg:classifiers":[
        {
            "category":"Restaurant",
            "type":"Food & Drink"
        }
    ],
    "sg:phone":"+1 480 704 2600",
    "sg:postcode":"85048",
    "sg:province":"AZ",
    "wof:name":"Havana Cafe",
    "wof:placetype":"venue"
},
  "geometry": {"coordinates":[-111.992638,33.30529],"type":"Point"}
}