{
  "type": "Feature",
  "properties": {
    "iso:country":"US",
    "sg:address":"711 N Gilbert Rd",
    "sg:city":"Mesa",
    "sg:classifiers":[
        {
            "category":"Home & Garden",
            "subcategory":"Furniture",
            "type":"Retail Goods"
        }
    ],
    "sg:phone":"+1 480 539 3300",
    "sg:postcode":"85203",
    "sg:province":"AZ",
    "sg:tags":[
        "mattress"
    ],
    "wof:name":"Bed Depot",
    "wof:placetype":"venue"
},
  "geometry": {"coordinates":[-111.787963,33.4289],"type":"Point"}
}