{
  "type": "Feature",
  "properties": {
    "iso:country":"US",
    "sg:address":"4531 N 16th St",
    "sg:city":"Phoenix",
    "sg:classifiers":[
        {
            "category":"Banks & Credit Unions",
            "subcategory":"Investment Brokerage",
            "type":"Services"
        }
    ],
    "sg:phone":"+1 602 287 8687",
    "sg:postcode":"85016",
    "sg:province":"AZ",
    "sg:tags":[
        "stock",
        "bond"
    ],
    "wof:name":"Plnkerton Security Regional",
    "wof:placetype":"venue"
},
  "geometry": {"coordinates":[-112.047479,33.503211],"type":"Point"}
}