{
  "type": "Feature",
  "properties": {
    "iso:country":"US",
    "sg:address":"16155 N 83rd Ave",
    "sg:city":"Peoria",
    "sg:classifiers":[
        {
            "category":"Banks & Credit Unions",
            "subcategory":"Bank",
            "type":"Services"
        }
    ],
    "sg:phone":"+1 623 412 1141",
    "sg:postcode":"85382",
    "sg:province":"AZ",
    "wof:name":"Johnson Bank",
    "wof:placetype":"venue"
},
  "geometry": {"coordinates":[-112.237167,33.631572],"type":"Point"}
}