{
  "type": "Feature",
  "properties": {
    "iso:country":"US",
    "sg:address":"5761 N Chieftain Trl",
    "sg:city":"Tucson",
    "sg:classifiers":[
        {
            "category":"Shopping",
            "subcategory":"Shoes",
            "type":"Retail Goods"
        }
    ],
    "sg:phone":"+1 520 577 1508",
    "sg:postcode":"85750",
    "sg:province":"AZ",
    "wof:name":"Friendly Feet",
    "wof:placetype":"venue"
},
  "geometry": {"coordinates":[-110.841593,32.309711],"type":"Point"}
}