{
  "type": "Feature",
  "properties": {
    "iso:country":"US",
    "sg:address":"5205 S 31st Pl",
    "sg:city":"Phoenix",
    "sg:classifiers":[
        {
            "category":"Manufacturing",
            "subcategory":"Furniture",
            "type":"Manufacturing & Wholesale Goods"
        },
        {
            "category":"Building & Trades",
            "subcategory":"Construction",
            "type":"Services"
        }
    ],
    "sg:phone":"+1 602 258 3858",
    "sg:postcode":"85040",
    "sg:province":"AZ",
    "sg:tags":[
        "front",
        "wood",
        "store",
        "mfg"
    ],
    "sg:website":"www.finewoodsmfg.com",
    "wof:name":"Fine Woods Mfg Inc",
    "wof:placetype":"venue"
},
  "geometry": {"coordinates":[-112.014968,33.399617],"type":"Point"}
}