{
  "type": "Feature",
  "properties": {
    "addr:full":"7075 W Bell Rd Glendale AZ 85308",
    "addr:housenumber":"7075",
    "addr:postcode":"85308",
    "addr:street":"W Bell Rd",
    "iso:country":"US",
    "sg:address":"7075 W Bell Rd",
    "sg:city":"Glendale",
    "sg:classifiers":[
        {
            "category":"Social Services",
            "type":"Services"
        }
    ],
    "sg:phone":"+1 602 896 1000",
    "sg:postcode":"85308",
    "sg:province":"AZ",
    "sg:tags":[
        "counselor",
        "marriage",
        "family"
    ],
    "wof:name":"Arrowhead Counseling Svc Inc",
    "wof:placetype":"venue"
},
  "geometry": {"coordinates":[-112.212602,33.638183],"type":"Point"}
}