{
  "type": "Feature",
  "properties": {
    "iso:country":"US",
    "sg:address":"2463 N Walgreens St",
    "sg:city":"Flagstaff",
    "sg:classifiers":[
        {
            "category":"Retail",
            "subcategory":"Repair Shop",
            "type":"Services"
        }
    ],
    "sg:phone":"+1 928 774 5141",
    "sg:postcode":"86004",
    "sg:province":"AZ",
    "sg:tags":[
        "machine",
        "supply"
    ],
    "wof:name":"IKON Office Solutions",
    "wof:placetype":"venue"
},
  "geometry": {"coordinates":[-111.60265200000001,35.208977],"type":"Point"}
}