{
  "type": "Feature",
  "properties": {
    "iso:country":"US",
    "sg:address":"1101 S 5th Ave",
    "sg:city":"Tucson",
    "sg:classifiers":[
        {
            "category":"Organizations",
            "subcategory":"Religious Organization",
            "type":"Services"
        }
    ],
    "sg:phone":"+1 520 622 1441",
    "sg:postcode":"85701",
    "sg:province":"AZ",
    "sg:tags":[
        "church"
    ],
    "wof:name":"Tucson Spanish 7-Day Adventist",
    "wof:placetype":"venue"
},
  "geometry": {"coordinates":[-110.96693,32.206815],"type":"Point"}
}