{
  "type": "Feature",
  "properties": {
    "addr:full":"2405 E Osborn Rd Phoenix AZ 85016",
    "addr:housenumber":"2405",
    "addr:postcode":"85016",
    "addr:street":"E Osborn Rd",
    "iso:country":"US",
    "sg:address":"2405 E Osborn Rd",
    "sg:city":"Phoenix",
    "sg:classifiers":[
        {
            "category":"Personal",
            "subcategory":"Beauty Salon",
            "type":"Services"
        }
    ],
    "sg:phone":"+1 602 957 2594",
    "sg:postcode":"85016",
    "sg:province":"AZ",
    "wof:name":"Beauty Workshops",
    "wof:placetype":"venue"
},
  "geometry": {"coordinates":[-112.028892,33.48752],"type":"Point"}
}