{
  "type": "Feature",
  "properties": {
    "iso:country":"US",
    "sg:address":"50 E Dunlap Ave",
    "sg:city":"Phoenix",
    "sg:classifiers":[
        {
            "category":"Professional",
            "type":"Services"
        }
    ],
    "sg:phone":"+1 602 331 1375",
    "sg:postcode":"85020",
    "sg:province":"AZ",
    "wof:name":"Spectra Scan Imaging Svc",
    "wof:placetype":"venue"
},
  "geometry": {"coordinates":[-112.073167,33.567819],"type":"Point"}
}