{
  "type": "Feature",
  "properties": {
    "iso:country":"US",
    "sg:address":"401 N 27th Ave",
    "sg:city":"Phoenix",
    "sg:classifiers":[
        {
            "category":"Professional",
            "type":"Services"
        }
    ],
    "sg:phone":"+1 623 328 7891",
    "sg:postcode":"85009",
    "sg:province":"AZ",
    "wof:name":"Arys Accessories",
    "wof:placetype":"venue"
},
  "geometry": {"coordinates":[-112.117469,33.453815],"type":"Point"}
}