{
  "type": "Feature",
  "properties": {
    "iso:country":"US",
    "sg:address":"9849 N 40th St",
    "sg:city":"Phoenix",
    "sg:classifiers":[
        {
            "category":"Place Of Worship",
            "subcategory":"Church",
            "type":"Public Place"
        },
        {
            "category":"Place Of Worship",
            "type":"Public Place"
        }
    ],
    "sg:phone":"+1 602 996 4040",
    "sg:postcode":"85028",
    "sg:province":"AZ",
    "sg:tags":[
        "churches-evangelical",
        "churches-covenant",
        "covenant"
    ],
    "wof:name":"Canaan In The Desert",
    "wof:placetype":"venue"
},
  "geometry": {"coordinates":[-111.995659,33.57638],"type":"Point"}
}