{
  "type": "Feature",
  "properties": {
    "addr:full":"9980 Hacienda Hermosa Dr Tucson AZ 85737",
    "addr:housenumber":"9980",
    "addr:postcode":"85737",
    "addr:street":"Hacienda Hermosa Dr",
    "iso:country":"US",
    "sg:address":"9980 Hacienda Hermosa Dr",
    "sg:city":"Tucson",
    "sg:classifiers":[
        {
            "category":"Professional",
            "subcategory":"Business Services",
            "type":"Services"
        }
    ],
    "sg:phone":"+1 520 818 0599",
    "sg:postcode":"85737",
    "sg:province":"AZ",
    "sg:tags":[
        "transcribing",
        "disc"
    ],
    "wof:name":"AAPT Transcription",
    "wof:placetype":"venue"
},
  "geometry": {"coordinates":[-110.998577,32.388075],"type":"Point"}
}