{
  "type": "Feature",
  "properties": {
    "addr:full":"41101 W Indian School Rd Tonopah AZ 85354",
    "addr:housenumber":"41101",
    "addr:postcode":"85354",
    "addr:street":"W Indian School Rd",
    "iso:country":"US",
    "sg:address":"41101 W Indian School Rd",
    "sg:city":"Tonopah",
    "sg:classifiers":[
        {
            "category":"Retail",
            "subcategory":"Auto Repair",
            "type":"Services"
        }
    ],
    "sg:phone":"+1 623 386 5141",
    "sg:postcode":"85354",
    "sg:province":"AZ",
    "sg:tags":[
        "wrecker"
    ],
    "wof:name":"A & M Towing",
    "wof:placetype":"venue"
},
  "geometry": {"coordinates":[-112.93731099999999,33.493691],"type":"Point"}
}