{
  "type": "Feature",
  "properties": {
    "addr:full":"6494 S Nucci Ln Hereford AZ 85615",
    "addr:housenumber":"6494",
    "addr:postcode":"85615",
    "addr:street":"S Nucci Ln",
    "iso:country":"US",
    "sg:address":"6494 S Nucci Ln",
    "sg:city":"Hereford",
    "sg:classifiers":[
        {
            "category":"Insurance",
            "subcategory":"Insurance Agent",
            "type":"Services"
        }
    ],
    "sg:phone":"+1 520 439 0856",
    "sg:postcode":"85615",
    "sg:province":"AZ",
    "wof:name":"Farm Bureau Insurance",
    "wof:placetype":"venue"
},
  "geometry": {"coordinates":[-110.164491,31.451386],"type":"Point"}
}