{
  "type": "Feature",
  "properties": {
    "iso:country":"US",
    "sg:address":"16150 W Hope Dr",
    "sg:city":"Surprise",
    "sg:classifiers":[
        {
            "category":"Transit Center",
            "subcategory":"Freight",
            "type":"Transportation"
        },
        {
            "category":"Freight",
            "type":"Transportation"
        }
    ],
    "sg:phone":"+1 623 444 4531",
    "sg:postcode":"85379",
    "sg:province":"AZ",
    "sg:tags":[
        "local",
        "trucking-motor",
        "trucking"
    ],
    "wof:name":"Cq Trucking",
    "wof:placetype":"venue"
},
  "geometry": {"coordinates":[-112.407016,33.585312],"type":"Point"}
}