{
  "type": "Feature",
  "properties": {
    "addr:full":"582 Jordan Rd Sedona AZ 86336",
    "addr:housenumber":"582",
    "addr:postcode":"86336",
    "addr:street":"Jordan Rd",
    "iso:country":"US",
    "sg:address":"582 Jordan Rd",
    "sg:city":"Sedona",
    "sg:classifiers":[
        {
            "category":"Building & Trades",
            "subcategory":"Plumbing",
            "type":"Services"
        }
    ],
    "sg:phone":"+1 928 203 4652",
    "sg:postcode":"86336",
    "sg:province":"AZ",
    "sg:tags":[
        "contractor"
    ],
    "wof:name":"Sedona Air LLC",
    "wof:placetype":"venue"
},
  "geometry": {"coordinates":[-111.760982,34.87574],"type":"Point"}
}