{
  "type": "Feature",
  "properties": {
    "addr:full":"3810 N Oracle Rd Tucson AZ 85705",
    "addr:housenumber":"3810",
    "addr:postcode":"85705",
    "addr:street":"N Oracle Rd",
    "iso:country":"US",
    "sg:address":"3810 N Oracle Rd",
    "sg:city":"Tucson",
    "sg:classifiers":[
        {
            "category":"Retail",
            "subcategory":"Auto Rental",
            "type":"Services"
        }
    ],
    "sg:phone":"+1 520 888 2688",
    "sg:postcode":"85705",
    "sg:province":"AZ",
    "sg:tags":[
        "renting",
        "automobile"
    ],
    "wof:name":"Hertz Rent A Car",
    "wof:placetype":"venue"
},
  "geometry": {"coordinates":[-110.978071,32.275623],"type":"Point"}
}