{
  "type": "Feature",
  "properties": {
    "iso:country":"US",
    "sg:address":"2735 W Mcdowell Rd",
    "sg:city":"Phoenix",
    "sg:classifiers":[
        {
            "category":"Wholesale",
            "subcategory":"Office Equipment",
            "type":"Manufacturing & Wholesale Goods"
        },
        {
            "category":"Professional",
            "subcategory":"Printing & Photocopies",
            "type":"Services"
        },
        {
            "category":"Shopping",
            "subcategory":"Computers & Home Electronics",
            "type":"Retail Goods"
        }
    ],
    "sg:phone":"+1 602 269 5739",
    "sg:postcode":"85009",
    "sg:province":"AZ",
    "sg:tags":[
        "scanning",
        "printer",
        "supply",
        "duplicating",
        "copying",
        "plotting"
    ],
    "wof:name":"Printworks Digital Graphics",
    "wof:placetype":"venue"
},
  "geometry": {"coordinates":[-112.118586,33.46595],"type":"Point"}
}