{
  "type": "Feature",
  "properties": {
    "iso:country":"US",
    "sg:address":"8019 E Main St",
    "sg:city":"Mesa",
    "sg:classifiers":[
        {
            "category":"Travel",
            "subcategory":"Hotels & Motels",
            "type":"Entertainment"
        },
        {
            "category":"Travel",
            "subcategory":"Bed & Breakfast",
            "type":"Entertainment"
        }
    ],
    "sg:phone":"+1 480 986 4531",
    "sg:postcode":"85207",
    "sg:province":"AZ",
    "sg:tags":[
        "inn"
    ],
    "wof:name":"East Mesa Inn",
    "wof:placetype":"venue"
},
  "geometry": {"coordinates":[-111.683865,33.415741],"type":"Point"}
}