{
  "type": "Feature",
  "properties": {
    "addr:full":"1237 W Galveston St Chandler AZ 85224",
    "addr:housenumber":"1237",
    "addr:postcode":"85224",
    "addr:street":"W Galveston St",
    "iso:country":"US",
    "sg:address":"1237 W Galveston St",
    "sg:city":"Chandler",
    "sg:classifiers":[
        {
            "category":"Building & Trades",
            "subcategory":"Construction",
            "type":"Services"
        }
    ],
    "sg:phone":"+1 480 963 4365",
    "sg:postcode":"85224",
    "sg:province":"AZ",
    "sg:tags":[
        "designer",
        "nonresidential",
        "residential",
        "dealer",
        "pool",
        "swimming"
    ],
    "wof:name":"Stephens Enterprises Inc",
    "wof:placetype":"venue"
},
  "geometry": {"coordinates":[-111.865489,33.313243],"type":"Point"}
}