{
  "type": "Feature",
  "properties": {
    "iso:country":"US",
    "sg:address":"13672 N 21st Ave",
    "sg:city":"Phoenix",
    "sg:classifiers":[
        {
            "category":"Building & Trades",
            "subcategory":"Construction",
            "type":"Services"
        }
    ],
    "sg:phone":"+1 602 469 7278",
    "sg:postcode":"85029",
    "sg:province":"AZ",
    "sg:tags":[
        "contractor"
    ],
    "wof:name":"Apartments Resurfacing",
    "wof:placetype":"venue"
},
  "geometry": {"coordinates":[-112.103969,33.609973],"type":"Point"}
}