{
  "type": "Feature",
  "properties": {
    "iso:country":"US",
    "sg:address":"115 S McCormick St",
    "sg:city":"Prescott",
    "sg:classifiers":[
        {
            "category":"Recreation",
            "type":"Entertainment"
        }
    ],
    "sg:phone":"+1 928 541 0004",
    "sg:postcode":"86303",
    "sg:province":"AZ",
    "sg:tags":[
        "instruction",
        "yoga"
    ],
    "wof:name":"Int'l Assoc Of Yoga Therapists",
    "wof:placetype":"venue"
},
  "geometry": {"coordinates":[-112.472831,34.541598],"type":"Point"}
}