{
  "type": "Feature",
  "properties": {
    "addr:full":"1955 N Center St Mesa AZ 85201",
    "addr:housenumber":"1955",
    "addr:postcode":"85201",
    "addr:street":"N Center St",
    "iso:country":"US",
    "sg:address":"1955 N Center St",
    "sg:city":"Mesa",
    "sg:classifiers":[
        {
            "category":"Retail",
            "subcategory":"Auto Repair",
            "type":"Services"
        }
    ],
    "sg:phone":"+1 480 833 7773",
    "sg:postcode":"85201",
    "sg:province":"AZ",
    "sg:tags":[
        "repairing",
        "automobile"
    ],
    "sg:website":"www.autoeng.org",
    "wof:name":"Automotive Engineering",
    "wof:placetype":"venue"
},
  "geometry": {"coordinates":[-111.831023,33.451197],"type":"Point"}
}