{
  "type": "Feature",
  "properties": {
    "iso:country":"US",
    "sg:address":"1422 N 27th Ln",
    "sg:city":"Phoenix",
    "sg:classifiers":[
        {
            "category":"Autos & Motor Vehicles",
            "subcategory":"Automobile Sales",
            "type":"Retail Goods"
        }
    ],
    "sg:phone":"+1 562 926 0283",
    "sg:postcode":"85009",
    "sg:province":"AZ",
    "sg:tags":[
        "new",
        "used",
        "car"
    ],
    "wof:name":"Iph Motor Sport",
    "wof:placetype":"venue"
},
  "geometry": {"coordinates":[-112.118579,33.464654],"type":"Point"}
}