{
  "type": "Feature",
  "properties": {
    "iso:country":"US",
    "sg:address":"8222 S 48th St",
    "sg:city":"Phoenix",
    "sg:classifiers":[
        {
            "category":"Professional",
            "subcategory":"Engineering",
            "type":"Services"
        }
    ],
    "sg:phone":"+1 602 454 9475",
    "sg:postcode":"85044",
    "sg:province":"AZ",
    "sg:tags":[
        "engineer"
    ],
    "wof:name":"Leighton & Assoc",
    "wof:placetype":"venue"
},
  "geometry": {"coordinates":[-111.974059,33.371639],"type":"Point"}
}