{
  "type": "Feature",
  "properties": {
    "iso:country":"US",
    "sg:address":"3548 N Ave Albor",
    "sg:city":"Tucson",
    "sg:classifiers":[
        {
            "category":"Wholesale",
            "subcategory":"Computers",
            "type":"Manufacturing & Wholesale Goods"
        }
    ],
    "sg:phone":"+1 520 742 7747",
    "sg:postcode":"85745",
    "sg:province":"AZ",
    "wof:name":"Quillis Inc",
    "wof:placetype":"venue"
},
  "geometry": {"coordinates":[-111.032678,32.276436],"type":"Point"}
}