{
  "type": "Feature",
  "properties": {
    "addr:full":"4814 N Shamrock Pl Tucson AZ 85705",
    "addr:housenumber":"4814",
    "addr:postcode":"85705",
    "addr:street":"N Shamrock Pl",
    "iso:country":"US",
    "sg:address":"4814 N Shamrock Pl",
    "sg:city":"Tucson",
    "sg:classifiers":[
        {
            "category":"Social Services",
            "type":"Services"
        }
    ],
    "sg:phone":"+1 520 323 3261",
    "sg:postcode":"85705",
    "sg:province":"AZ",
    "sg:tags":[
        "fire",
        "water",
        "restoration",
        "contractor"
    ],
    "sg:website":"www.abrarest.com",
    "wof:name":"Abracadabra Restoration",
    "wof:placetype":"venue"
},
  "geometry": {"coordinates":[-111.006469,32.295308],"type":"Point"}
}