{
  "type": "Feature",
  "properties": {
    "addr:full":"73 E 200th St Pima AZ 85543",
    "addr:housenumber":"73",
    "addr:postcode":"85543",
    "addr:street":"E 200Th St",
    "iso:country":"US",
    "sg:address":"73 E 200th St",
    "sg:city":"Pima",
    "sg:classifiers":[
        {
            "category":"Organizations",
            "subcategory":"Religious Organization",
            "type":"Services"
        }
    ],
    "sg:phone":"+1 928 485 2283",
    "sg:postcode":"85543",
    "sg:province":"AZ",
    "sg:tags":[
        "church"
    ],
    "sg:website":"www.lds.org",
    "wof:name":"Pima LDS Seminary",
    "wof:placetype":"venue"
},
  "geometry": {"coordinates":[-109.826369,32.892501],"type":"Point"}
}