{
  "type": "Feature",
  "properties": {
    "iso:country":"US",
    "sg:address":"245 London Bridge Rd",
    "sg:city":"Lake Havasu City",
    "sg:classifiers":[
        {
            "category":"Travel",
            "subcategory":"Hotels & Motels",
            "type":"Entertainment"
        }
    ],
    "sg:phone":"+1 928 855 4071",
    "sg:postcode":"86403",
    "sg:province":"AZ",
    "sg:website":"www.zmchotels.com",
    "wof:name":"Holiday Inn Lake Havasu",
    "wof:placetype":"venue"
},
  "geometry": {"coordinates":[-114.350953,34.481037],"type":"Point"}
}