{
  "type": "Feature",
  "properties": {
    "iso:country":"US",
    "sg:address":"4164 N Marshall Way",
    "sg:city":"Scottsdale",
    "sg:classifiers":[
        {
            "category":"Shopping",
            "subcategory":"Discount & Variety Stores",
            "type":"Retail Goods"
        }
    ],
    "sg:phone":"+1 480 481 0611",
    "sg:postcode":"85251",
    "sg:province":"AZ",
    "sg:tags":[
        "merchandise",
        "general"
    ],
    "wof:name":"Ferraras Retail Center",
    "wof:placetype":"venue"
},
  "geometry": {"coordinates":[-111.929059,33.497971],"type":"Point"}
}