{
  "type": "Feature",
  "properties": {
    "iso:country":"US",
    "sg:address":"1355 E Florence Blvd",
    "sg:city":"Casa Grande",
    "sg:classifiers":[
        {
            "category":"Restaurant",
            "type":"Food & Drink"
        }
    ],
    "sg:menulink":"http://www.allmenus.com/az/casa-grande/128944-subway/menu/",
    "sg:phone":"+1 520 421 1446",
    "sg:postcode":"85222",
    "sg:province":"AZ",
    "sg:tags":[
        "american",
        "sandwich"
    ],
    "wof:name":"Subway",
    "wof:placetype":"venue"
},
  "geometry": {"coordinates":[-111.72838299999999,32.877434],"type":"Point"}
}