{
  "type": "Feature",
  "properties": {
    "iso:country":"US",
    "sg:address":"7401 W Arrowhead Clubhouse Dr",
    "sg:city":"Glendale",
    "sg:classifiers":[
        {
            "category":"Banks & Credit Unions",
            "subcategory":"Investment Brokerage",
            "type":"Services"
        }
    ],
    "sg:phone":"+1 623 583 6361",
    "sg:postcode":"85308",
    "sg:province":"AZ",
    "sg:tags":[
        "security"
    ],
    "wof:name":"Bresnahan Investment Service",
    "wof:placetype":"venue"
},
  "geometry": {"coordinates":[-112.219007,33.664688],"type":"Point"}
}