{
  "type": "Feature",
  "properties": {
    "iso:country":"US",
    "sg:address":"31055 N 56th St",
    "sg:city":"Cave Creek",
    "sg:classifiers":[
        {
            "category":"Building & Trades",
            "subcategory":"Landscaping Services",
            "type":"Services"
        }
    ],
    "sg:phone":"+1 480 595 6400",
    "sg:postcode":"85331",
    "sg:province":"AZ",
    "sg:tags":[
        "landscape"
    ],
    "sg:website":"www.sonorandesertdesigns.com",
    "wof:name":"Sonoran Desert Designs Inc",
    "wof:placetype":"venue"
},
  "geometry": {"coordinates":[-111.960532,33.768129],"type":"Point"}
}