{
  "type": "Feature",
  "properties": {
    "iso:country":"US",
    "sg:address":"5330 N 16th St",
    "sg:city":"Phoenix",
    "sg:classifiers":[
        {
            "category":"Wholesale",
            "subcategory":"Hardware",
            "type":"Manufacturing & Wholesale Goods"
        },
        {
            "category":"Home & Garden",
            "subcategory":"Hardware",
            "type":"Retail Goods"
        },
        {
            "category":"Manufacturing",
            "subcategory":"Building Materials",
            "type":"Manufacturing & Wholesale Goods"
        }
    ],
    "sg:phone":"+1 602 264 1841",
    "sg:postcode":"85016",
    "sg:province":"AZ",
    "sg:tags":[
        "frames",
        "hardware-builders",
        "store",
        "doors",
        "accessory"
    ],
    "wof:name":"Nelson-Holland, Inc.",
    "wof:placetype":"venue"
},
  "geometry": {"coordinates":[-112.04753100000001,33.515223],"type":"Point"}
}