{
  "type": "Feature",
  "properties": {
    "iso:country":"US",
    "sg:address":"15915 W Glendale Ave",
    "sg:city":"Litchfield Park",
    "sg:classifiers":[
        {
            "category":"Building & Trades",
            "subcategory":"Landscaping Services",
            "type":"Services"
        }
    ],
    "sg:phone":"+1 623 848 8737",
    "sg:postcode":"85340",
    "sg:province":"AZ",
    "sg:tags":[
        "landscape",
        "contractor"
    ],
    "wof:name":"Mustang Landscaping",
    "wof:placetype":"venue"
},
  "geometry": {"coordinates":[-112.407348,33.537088],"type":"Point"}
}