{
  "type": "Feature",
  "properties": {
    "iso:country":"US",
    "sg:address":"8361 E Evans Rd Ste 110",
    "sg:city":"Scottsdale",
    "sg:classifiers":[
        {
            "category":"Manufacturing",
            "subcategory":"Aerospace",
            "type":"Manufacturing & Wholesale Goods"
        }
    ],
    "sg:phone":"+1 480 998 2420",
    "sg:postcode":"85260",
    "sg:province":"AZ",
    "sg:tags":[
        "avionics",
        "supply",
        "equipment",
        "aircraft",
        "part",
        "instrument",
        "supplies-wholesale",
        "manufacturer"
    ],
    "wof:name":"Mercury Trading Company",
    "wof:placetype":"venue"
},
  "geometry": {"coordinates":[-111.900529,33.616524],"type":"Point"}
}