{
  "type": "Feature",
  "properties": {
    "addr:full":"240 E Broadway Rd Mesa AZ 85210",
    "addr:housenumber":"240",
    "addr:postcode":"85210",
    "addr:street":"E Broadway Rd",
    "iso:country":"US",
    "sg:address":"240 E Broadway Rd",
    "sg:city":"Mesa",
    "sg:classifiers":[
        {
            "category":"Wholesale",
            "subcategory":"Farm Supplies",
            "type":"Manufacturing & Wholesale Goods"
        },
        {
            "category":"Shopping",
            "subcategory":"Pets & Pet Supplies",
            "type":"Retail Goods"
        }
    ],
    "sg:phone":"+1 480 969 9704",
    "sg:postcode":"85210",
    "sg:province":"AZ",
    "sg:tags":[
        "store"
    ],
    "wof:name":"Mesa Feed Barn",
    "wof:placetype":"venue"
},
  "geometry": {"coordinates":[-111.82505,33.407799],"type":"Point"}
}