{
  "type": "Feature",
  "properties": {
    "iso:country":"US",
    "sg:address":"2240 W Shangri la Rd",
    "sg:city":"Phoenix",
    "sg:classifiers":[
        {
            "category":"Utilities",
            "subcategory":"Water",
            "type":"Services"
        },
        {
            "category":"Building & Trades",
            "subcategory":"Plumbing",
            "type":"Services"
        }
    ],
    "sg:phone":"+1 602 861 3135",
    "sg:postcode":"85029",
    "sg:province":"AZ",
    "sg:tags":[
        "tank",
        "septic",
        "well",
        "system",
        "contractor",
        "pump",
        "drilling"
    ],
    "wof:name":"Waco Drilling & Septic",
    "wof:placetype":"venue"
},
  "geometry": {"coordinates":[-112.106188,33.587904],"type":"Point"}
}