{
  "type": "Feature",
  "properties": {
    "addr:full":"548 W Nopal Ave Mesa AZ 85210",
    "addr:housenumber":"548",
    "addr:postcode":"85210",
    "addr:street":"W Nopal Ave",
    "iso:country":"US",
    "sg:address":"548 W Nopal Ave",
    "sg:city":"Mesa",
    "sg:classifiers":[
        {
            "category":"Building & Trades",
            "subcategory":"Equipment Rental",
            "type":"Services"
        },
        {
            "category":"Wholesale",
            "subcategory":"Construction Materials",
            "type":"Manufacturing & Wholesale Goods"
        },
        {
            "category":"Home & Garden",
            "subcategory":"Building Materials",
            "type":"Retail Goods"
        }
    ],
    "sg:phone":"+1 480 545 1236",
    "sg:postcode":"85210",
    "sg:province":"AZ",
    "sg:tags":[
        "plant",
        "supply",
        "concrete",
        "mixing",
        "masonry"
    ],
    "wof:name":"Rockway Precast",
    "wof:placetype":"venue"
},
  "geometry": {"coordinates":[-111.84569500000001,33.365794],"type":"Point"}
}