{
  "type": "Feature",
  "properties": {
    "iso:country":"US",
    "sg:address":"2709 N 90th Dr",
    "sg:city":"Phoenix",
    "sg:classifiers":[
        {
            "category":"Professional",
            "subcategory":"Computer Services",
            "type":"Services"
        }
    ],
    "sg:phone":"+1 623 936 4800",
    "sg:postcode":"85037",
    "sg:province":"AZ",
    "sg:tags":[
        "internet"
    ],
    "sg:website":"www.adpak.com",
    "wof:name":"Adpak Communications",
    "wof:placetype":"venue"
},
  "geometry": {"coordinates":[-112.253455,33.477601],"type":"Point"}
}