{
  "type": "Feature",
  "properties": {
    "iso:country":"US",
    "sg:address":"6705 W Bethany Home Rd",
    "sg:city":"Glendale",
    "sg:classifiers":[
        {
            "category":"Food & Beverages",
            "subcategory":"Groceries & Convenience Stores",
            "type":"Retail Goods"
        }
    ],
    "sg:phone":"+1 623 846 7308",
    "sg:postcode":"85303",
    "sg:province":"AZ",
    "wof:name":"Carioca Co",
    "wof:placetype":"venue"
},
  "geometry": {"coordinates":[-112.203223,33.523761],"type":"Point"}
}