{
  "type": "Feature",
  "properties": {
    "iso:country":"US",
    "sg:address":"10200 E Vicksburg St",
    "sg:city":"Tucson",
    "sg:classifiers":[
        {
            "category":"Utilities",
            "subcategory":"Electric",
            "type":"Services"
        }
    ],
    "sg:phone":"+1 520 296 3873",
    "sg:postcode":"85748",
    "sg:province":"AZ",
    "wof:name":"Sparky Electric Co",
    "wof:placetype":"venue"
},
  "geometry": {"coordinates":[-110.774543,32.223207],"type":"Point"}
}