{
  "type": "Feature",
  "properties": {
    "iso:country":"US",
    "sg:address":"8601 N Black Canyon Hwy",
    "sg:city":"Phoenix",
    "sg:classifiers":[
        {
            "category":"Real Estate",
            "subcategory":"Real Estate Agent",
            "type":"Services"
        }
    ],
    "sg:phone":"+1 602 595 7460",
    "sg:postcode":"85021",
    "sg:province":"AZ",
    "wof:name":"Heritage Properties & Est LLC",
    "wof:placetype":"venue"
},
  "geometry": {"coordinates":[-112.116201,33.563933],"type":"Point"}
}