{
  "type": "Feature",
  "properties": {
    "iso:country":"US",
    "sg:address":"2524 W Perdido Way",
    "sg:city":"Phoenix",
    "sg:classifiers":[
        {
            "category":"Utilities",
            "subcategory":"Water",
            "type":"Services"
        }
    ],
    "sg:phone":"+1 623 466 9438",
    "sg:postcode":"85086",
    "sg:province":"AZ",
    "sg:tags":[
        "umbrella"
    ],
    "wof:name":"Umbrella Golf",
    "wof:placetype":"venue"
},
  "geometry": {"coordinates":[-112.11530399999999,33.80299],"type":"Point"}
}