{
  "type": "Feature",
  "properties": {
    "iso:country":"US",
    "sg:address":"446 S Mountain Ave",
    "sg:city":"Springerville",
    "sg:classifiers":[
        {
            "category":"Home & Garden",
            "subcategory":"Household Appliances",
            "type":"Retail Goods"
        }
    ],
    "sg:phone":"+1 928 333 2777",
    "sg:postcode":"85938",
    "sg:province":"AZ",
    "wof:name":"J & J Brannon's Refrigeration",
    "wof:placetype":"venue"
},
  "geometry": {"coordinates":[-109.289613,34.126747],"type":"Point"}
}