{
  "type": "Feature",
  "properties": {
    "iso:country":"US",
    "sg:address":"5127 W Thunderbird Rd",
    "sg:city":"Glendale",
    "sg:classifiers":[
        {
            "category":"Insurance",
            "subcategory":"Insurance Agent",
            "type":"Services"
        }
    ],
    "sg:phone":"+1 602 843 6666",
    "sg:postcode":"85306",
    "sg:province":"AZ",
    "wof:name":"Grieves Leland M",
    "wof:placetype":"venue"
},
  "geometry": {"coordinates":[-112.170571,33.610663],"type":"Point"}
}