{
  "type": "Feature",
  "properties": {
    "iso:country":"US",
    "sg:address":"3411 S 44th St",
    "sg:city":"Phoenix",
    "sg:classifiers":[
        {
            "category":"Manufacturing",
            "subcategory":"Motor Vehicles & Parts",
            "type":"Manufacturing & Wholesale Goods"
        }
    ],
    "sg:phone":"+1 602 437 0760",
    "sg:postcode":"85040",
    "sg:province":"AZ",
    "sg:tags":[
        "distributor",
        "motors-manufacturers",
        "electric"
    ],
    "sg:website":"http://www.rdc-electrical.com",
    "wof:name":"Wired Investment Group, Inc.",
    "wof:placetype":"venue"
},
  "geometry": {"coordinates":[-111.986794,33.415922],"type":"Point"}
}