{
  "type": "Feature",
  "properties": {
    "iso:country":"US",
    "sg:address":"1122 Hwy 95",
    "sg:city":"Bullhead City",
    "sg:classifiers":[
        {
            "category":"Professional",
            "type":"Services"
        }
    ],
    "sg:phone":"+1 928 754 5222",
    "sg:postcode":"86429",
    "sg:province":"AZ",
    "wof:name":"Mr & Mrs Computers",
    "wof:placetype":"venue"
},
  "geometry": {"coordinates":[-114.568467,35.146975],"type":"Point"}
}