{
  "type": "Feature",
  "properties": {
    "iso:country":"US",
    "sg:address":"9230 N 14th Ave",
    "sg:city":"Phoenix",
    "sg:classifiers":[
        {
            "category":"Retail",
            "subcategory":"Repair Shop",
            "type":"Services"
        }
    ],
    "sg:phone":"+1 602 997 9910",
    "sg:postcode":"85021",
    "sg:province":"AZ",
    "sg:tags":[
        "equipment",
        "hydraulic"
    ],
    "wof:name":"S & T Hydraulics Inc",
    "wof:placetype":"venue"
},
  "geometry": {"coordinates":[-112.090164,33.570809],"type":"Point"}
}