{
  "type": "Feature",
  "properties": {
    "iso:country":"US",
    "sg:address":"321 S Main St",
    "sg:city":"Cottonwood",
    "sg:classifiers":[
        {
            "category":"Restaurant",
            "type":"Food & Drink"
        }
    ],
    "sg:phone":"+1 877 314 1699",
    "sg:postcode":"86326",
    "sg:province":"AZ",
    "sg:tags":[
        "style",
        "italian",
        "family",
        "pizza"
    ],
    "sg:website":"http://www.strombollis.com",
    "wof:name":"Strombollis Restaurant and Pizzeria",
    "wof:placetype":"venue"
},
  "geometry": {"coordinates":[-112.009808,34.732615],"type":"Point"}
}