{
  "type": "Feature",
  "properties": {
    "addr:full":"12630 N 35th Pl Phoenix AZ 85032",
    "addr:housenumber":"12630",
    "addr:postcode":"85032",
    "addr:street":"N 35Th Pl",
    "iso:country":"US",
    "sg:address":"12630 N 35th Pl",
    "sg:city":"Phoenix",
    "sg:classifiers":[
        {
            "category":"Building & Trades",
            "subcategory":"Construction",
            "type":"Services"
        }
    ],
    "sg:phone":"+1 602 482 8292",
    "sg:postcode":"85032",
    "sg:province":"AZ",
    "sg:tags":[
        "contractor"
    ],
    "wof:name":"One Stop Tile Works Inc",
    "wof:placetype":"venue"
},
  "geometry": {"coordinates":[-112.005458,33.600753],"type":"Point"}
}