{
  "type": "Feature",
  "properties": {
    "iso:country":"US",
    "sg:address":"405 E Potters Wheel Ct",
    "sg:city":"Tucson",
    "sg:classifiers":[
        {
            "category":"Insurance",
            "subcategory":"Insurance Agent",
            "type":"Services"
        }
    ],
    "sg:phone":"+1 520 903 0227",
    "sg:postcode":"85704",
    "sg:province":"AZ",
    "wof:name":"Lon A Packer",
    "wof:placetype":"venue"
},
  "geometry": {"coordinates":[-110.965083,32.327259],"type":"Point"}
}