{
  "type": "Feature",
  "properties": {
    "addr:full":"7248 S Harl Ave Tempe AZ 85283",
    "addr:housenumber":"7248",
    "addr:postcode":"85283",
    "addr:street":"S Harl Ave",
    "iso:country":"US",
    "sg:address":"7248 S Harl Ave",
    "sg:city":"Tempe",
    "sg:classifiers":[
        {
            "category":"Building & Trades",
            "subcategory":"Construction",
            "type":"Services"
        }
    ],
    "sg:phone":"+1 480 756 8500",
    "sg:postcode":"85283",
    "sg:province":"AZ",
    "sg:tags":[
        "insulation",
        "heat",
        "contractor"
    ],
    "wof:name":"Insulpro Projects",
    "wof:placetype":"venue"
},
  "geometry": {"coordinates":[-111.96656299999999,33.353324],"type":"Point"}
}