{
  "type": "Feature",
  "properties": {
    "iso:country":"US",
    "sg:address":"1423 N Palo Verde Dr",
    "sg:city":"Goodyear",
    "sg:classifiers":[
        {
            "category":"Building & Trades",
            "subcategory":"Locksmith",
            "type":"Services"
        }
    ],
    "sg:phone":"+1 480 718 2741",
    "sg:postcode":"85338",
    "sg:province":"AZ",
    "sg:tags":[
        "key"
    ],
    "wof:name":"A Locksmith A Service",
    "wof:placetype":"venue"
},
  "geometry": {"coordinates":[-112.34521599999999,33.450254],"type":"Point"}
}