{
  "type": "Feature",
  "properties": {
    "iso:country":"US",
    "sg:address":"2501 W Ver Roja",
    "sg:city":"Tucson",
    "sg:classifiers":[
        {
            "category":"Shopping",
            "subcategory":"Clothing, Apparel, & Fashions",
            "type":"Retail Goods"
        }
    ],
    "sg:phone":"+1 520 578 7233",
    "sg:postcode":"85746",
    "sg:province":"AZ",
    "wof:name":"ABC Athletic Apparel",
    "wof:placetype":"venue"
},
  "geometry": {"coordinates":[-111.021419,32.125186],"type":"Point"}
}