{
  "type": "Feature",
  "properties": {
    "iso:country":"US",
    "sg:address":"353 S Washington St",
    "sg:city":"Chandler",
    "sg:classifiers":[
        {
            "category":"Wholesale",
            "subcategory":"Metals & Minerals",
            "type":"Manufacturing & Wholesale Goods"
        }
    ],
    "sg:phone":"+1 480 963 1424",
    "sg:postcode":"85225",
    "sg:province":"AZ",
    "sg:tags":[
        "mfg",
        "metalwork",
        "center",
        "structural"
    ],
    "wof:name":"Dunn Del RE Steel",
    "wof:placetype":"venue"
},
  "geometry": {"coordinates":[-111.84009,33.298737],"type":"Point"}
}