{
  "type": "Feature",
  "properties": {
    "iso:country":"US",
    "sg:address":"6155 E Cielo Run N",
    "sg:city":"Cave Creek",
    "sg:classifiers":[
        {
            "category":"Building & Trades",
            "subcategory":"Construction",
            "type":"Services"
        }
    ],
    "sg:phone":"+1 480 595 5591",
    "sg:postcode":"85331",
    "sg:province":"AZ",
    "sg:tags":[
        "contractor"
    ],
    "wof:name":"R C Lorenz Contracting Inc",
    "wof:placetype":"venue"
},
  "geometry": {"coordinates":[-111.945448,33.863133],"type":"Point"}
}