{
  "type": "Feature",
  "properties": {
    "addr:full":"4653 S Lakeshore Dr Tempe AZ 85282",
    "addr:housenumber":"4653",
    "addr:postcode":"85282",
    "addr:street":"S Lakeshore Dr",
    "iso:country":"US",
    "sg:address":"4653 S Lakeshore Dr",
    "sg:city":"Tempe",
    "sg:classifiers":[
        {
            "category":"Utilities",
            "subcategory":"Mobile Phone",
            "type":"Services"
        }
    ],
    "sg:phone":"+1 480 820 0071",
    "sg:postcode":"85282",
    "sg:province":"AZ",
    "sg:tags":[
        "telephone",
        "cellular"
    ],
    "wof:name":"E Square Wireless",
    "wof:placetype":"venue"
},
  "geometry": {"coordinates":[-111.921712,33.380647],"type":"Point"}
}