{
  "type": "Feature",
  "properties": {
    "addr:full":"298 W Mariposa Rd Nogales AZ 85621",
    "addr:housenumber":"298",
    "addr:postcode":"85621",
    "addr:street":"W Mariposa Rd",
    "iso:country":"US",
    "sg:address":"298 W Mariposa Rd",
    "sg:city":"Nogales",
    "sg:classifiers":[
        {
            "category":"Banks & Credit Unions",
            "subcategory":"Bank",
            "type":"Services"
        }
    ],
    "sg:phone":"+1 520 377 9319",
    "sg:postcode":"85621",
    "sg:province":"AZ",
    "wof:name":"Bank Of America",
    "wof:placetype":"venue"
},
  "geometry": {"coordinates":[-110.93574599999999,31.367028],"type":"Point"}
}