{
  "type": "Feature",
  "properties": {
    "iso:country":"US",
    "sg:address":"9338 E Sharon Dr",
    "sg:city":"Scottsdale",
    "sg:classifiers":[
        {
            "category":"Place Of Worship",
            "subcategory":"Church",
            "type":"Public Place"
        }
    ],
    "sg:phone":"+1 480 614 5596",
    "sg:postcode":"85260",
    "sg:province":"AZ",
    "sg:tags":[
        "churches-orthodox"
    ],
    "wof:name":"The Forerunner Business Group",
    "wof:placetype":"venue"
},
  "geometry": {"coordinates":[-111.880029,33.610997],"type":"Point"}
}