{
  "type": "Feature",
  "properties": {
    "addr:full":"2305 E Siesta Ln Phoenix AZ 85024",
    "addr:housenumber":"2305",
    "addr:postcode":"85024",
    "addr:street":"E Siesta Ln",
    "iso:country":"US",
    "sg:address":"2305 E Siesta Ln",
    "sg:city":"Phoenix",
    "sg:classifiers":[
        {
            "category":"Professional",
            "type":"Services"
        }
    ],
    "sg:phone":"+1 602 485 9988",
    "sg:postcode":"85024",
    "sg:province":"AZ",
    "wof:name":"3 5 Media Inc",
    "wof:placetype":"venue"
},
  "geometry": {"coordinates":[-112.032459,33.658378],"type":"Point"}
}