{
  "type": "Feature",
  "properties": {
    "iso:country":"US",
    "sg:address":"2127 E Catamaran Dr",
    "sg:city":"Gilbert",
    "sg:classifiers":[
        {
            "category":"Travel",
            "subcategory":"Hotels & Motels",
            "type":"Entertainment"
        }
    ],
    "sg:phone":"+1 480 497 2319",
    "sg:postcode":"85234",
    "sg:province":"AZ",
    "wof:name":"Campbell Motel Properties",
    "wof:placetype":"venue"
},
  "geometry": {"coordinates":[-111.745003,33.376099],"type":"Point"}
}