{
  "type": "Feature",
  "properties": {
    "iso:country":"US",
    "sg:address":"940 W Melinda Ln",
    "sg:city":"Phoenix",
    "sg:classifiers":[
        {
            "category":"Manufacturing",
            "subcategory":"Tools & Machinery",
            "type":"Manufacturing & Wholesale Goods"
        }
    ],
    "sg:phone":"+1 623 581 6340",
    "sg:postcode":"85027",
    "sg:province":"AZ",
    "sg:tags":[
        "die",
        "prototype",
        "mfg"
    ],
    "wof:name":"A-Rand Inc",
    "wof:placetype":"venue"
},
  "geometry": {"coordinates":[-112.085441,33.681737],"type":"Point"}
}