{
  "type": "Feature",
  "properties": {
    "iso:country":"US",
    "sg:address":"6957 W Briles Rd",
    "sg:city":"Peoria",
    "sg:classifiers":[
        {
            "category":"Shopping",
            "subcategory":"Pharmacy",
            "type":"Retail Goods"
        }
    ],
    "sg:phone":"+1 623 825 4910",
    "sg:postcode":"85383",
    "sg:province":"AZ",
    "wof:name":"FDM Sales/Marketing",
    "wof:placetype":"venue"
},
  "geometry": {"coordinates":[-112.207794,33.722169],"type":"Point"}
}