{
  "type": "Feature",
  "properties": {
    "addr:full":"6957 W Briles Rd Peoria AZ 85383",
    "addr:housenumber":"6957",
    "addr:postcode":"85383",
    "addr:street":"W Briles Rd",
    "iso:country":"US",
    "sg:address":"6957 W Briles Rd",
    "sg:city":"Peoria",
    "sg:classifiers":[
        {
            "category":"Shopping",
            "subcategory":"Pharmacy",
            "type":"Retail Goods"
        }
    ],
    "sg:phone":"+1 623 825 4910",
    "sg:postcode":"85383",
    "sg:province":"AZ",
    "wof:name":"FDM Sales/Marketing",
    "wof:placetype":"venue"
},
  "geometry": {"coordinates":[-112.20779400000001,33.722169],"type":"Point"}
}