{
  "type": "Feature",
  "properties": {
    "iso:country":"US",
    "sg:address":"2523 E Grovers Ave",
    "sg:city":"Phoenix",
    "sg:classifiers":[
        {
            "category":"Real Estate",
            "subcategory":"Real Estate Agent",
            "type":"Services"
        }
    ],
    "sg:phone":"+1 602 867 4406",
    "sg:postcode":"85032",
    "sg:province":"AZ",
    "sg:tags":[
        "authorities",
        "housing"
    ],
    "wof:name":"Ceda Housing",
    "wof:placetype":"venue"
},
  "geometry": {"coordinates":[-112.027718,33.647715],"type":"Point"}
}