{
  "type": "Feature",
  "properties": {
    "iso:country":"US",
    "sg:address":"2230 E Cedar Ave",
    "sg:city":"Flagstaff",
    "sg:classifiers":[
        {
            "category":"Insurance",
            "subcategory":"Insurance Agent",
            "type":"Services"
        }
    ],
    "sg:phone":"+1 928 774 3341",
    "sg:postcode":"86004",
    "sg:province":"AZ",
    "wof:name":"Douglas Hellyer",
    "wof:placetype":"venue"
},
  "geometry": {"coordinates":[-111.614475,35.218024],"type":"Point"}
}