{
  "type": "Feature",
  "properties": {
    "iso:country":"US",
    "sg:address":"5136 N 31st Pl",
    "sg:city":"Phoenix",
    "sg:classifiers":[
        {
            "category":"Banks & Credit Unions",
            "subcategory":"Bank",
            "type":"Services"
        }
    ],
    "sg:phone":"+1 602 957 6118",
    "sg:postcode":"85016",
    "sg:province":"AZ",
    "sg:tags":[
        "loan",
        "real estate"
    ],
    "wof:name":"Soo Nam & Assoc",
    "wof:placetype":"venue"
},
  "geometry": {"coordinates":[-112.015663,33.513391],"type":"Point"}
}