{
  "type": "Feature",
  "properties": {
    "iso:country":"US",
    "sg:address":"765 N Target Range Rd",
    "sg:city":"Nogales",
    "sg:classifiers":[
        {
            "category":"Manufacturing",
            "subcategory":"Electronics",
            "type":"Manufacturing & Wholesale Goods"
        }
    ],
    "sg:phone":"+1 520 287 9711",
    "sg:postcode":"85621",
    "sg:province":"AZ",
    "sg:tags":[
        "electronic",
        "component",
        "mfg"
    ],
    "wof:name":"EDS Manufacturing Inc",
    "wof:placetype":"venue"
},
  "geometry": {"coordinates":[-110.963101,31.346973],"type":"Point"}
}