{
  "type": "Feature",
  "properties": {
    "addr:full":"1129 Iron Springs Rd Prescott AZ 86305",
    "addr:housenumber":"1129",
    "addr:postcode":"86305",
    "addr:street":"Iron Springs Rd",
    "iso:country":"US",
    "sg:address":"1129 Iron Springs Rd",
    "sg:city":"Prescott",
    "sg:classifiers":[
        {
            "category":"Banks & Credit Unions",
            "subcategory":"Bank",
            "type":"Services"
        }
    ],
    "sg:phone":"+1 928 777 2369",
    "sg:postcode":"86305",
    "sg:province":"AZ",
    "sg:tags":[
        "loan"
    ],
    "wof:name":"Farm Credit Svc Southwest",
    "wof:placetype":"venue"
},
  "geometry": {"coordinates":[-112.483996,34.559129],"type":"Point"}
}