{
  "type": "Feature",
  "properties": {
    "iso:country":"US",
    "sg:address":"904 N Scottsdale Rd",
    "sg:city":"Tempe",
    "sg:classifiers":[
        {
            "category":"Manufacturing",
            "subcategory":"Glass & Minerals",
            "type":"Manufacturing & Wholesale Goods"
        }
    ],
    "sg:phone":"+1 480 966 6167",
    "sg:postcode":"85281",
    "sg:province":"AZ",
    "wof:name":"Artistry Glass Studios",
    "wof:placetype":"venue"
},
  "geometry": {"coordinates":[-111.926197,33.437848],"type":"Point"}
}