{
  "type": "Feature",
  "properties": {
    "iso:country":"US",
    "sg:address":"620 N Litchfield Road",
    "sg:city":"Goodyear",
    "sg:classifiers":[
        {
            "category":"Real Estate",
            "subcategory":"Real Estate Operator",
            "type":"Services"
        }
    ],
    "sg:phone":"+1 623 932 2960",
    "sg:postcode":"85338",
    "sg:province":"AZ",
    "sg:tags":[
        "apartment"
    ],
    "wof:name":"Park Shadows Apartments",
    "wof:placetype":"venue"
},
  "geometry": {"coordinates":[-112.358262,33.440039],"type":"Point"}
}