{
  "type": "Feature",
  "properties": {
    "addr:full":"3210 S Hardy Dr Tempe AZ 85282",
    "addr:housenumber":"3210",
    "addr:postcode":"85282",
    "addr:street":"S Hardy Dr",
    "iso:country":"US",
    "sg:address":"3210 S Hardy Dr",
    "sg:city":"Tempe",
    "sg:classifiers":[
        {
            "category":"Home & Garden",
            "subcategory":"Building Materials",
            "type":"Retail Goods"
        }
    ],
    "sg:phone":"+1 602 955 4144",
    "sg:postcode":"85282",
    "sg:province":"AZ",
    "sg:tags":[
        "repair",
        "door"
    ],
    "sg:website":"http://www.geniepro.com",
    "wof:name":"Lincoln Electric Garage",
    "wof:placetype":"venue"
},
  "geometry": {"coordinates":[-111.95196799999999,33.393483],"type":"Point"}
}