{
  "type": "Feature",
  "properties": {
    "iso:country":"US",
    "sg:address":"3134 N Freeway Industrial Loop",
    "sg:city":"Tucson",
    "sg:classifiers":[
        {
            "category":"Wholesale",
            "subcategory":"Groceries",
            "type":"Manufacturing & Wholesale Goods"
        }
    ],
    "sg:phone":"+1 520 889 5111",
    "sg:postcode":"85705",
    "sg:province":"AZ",
    "sg:tags":[
        "food",
        "product"
    ],
    "wof:name":"Frito-Lay Inc",
    "wof:placetype":"venue"
},
  "geometry": {"coordinates":[-111.004689,32.264567],"type":"Point"}
}