{
  "type": "Feature",
  "properties": {
    "iso:country":"US",
    "sg:address":"1323 E Christy Dr",
    "sg:city":"Phoenix",
    "sg:classifiers":[
        {
            "category":"Shopping",
            "subcategory":"Clothing, Apparel, & Fashions",
            "type":"Retail Goods"
        }
    ],
    "sg:phone":"+1 602 997 5132",
    "sg:postcode":"85020",
    "sg:province":"AZ",
    "sg:tags":[
        "dancing",
        "supply"
    ],
    "wof:name":"Eclypse",
    "wof:placetype":"venue"
},
  "geometry": {"coordinates":[-112.05578,33.584363],"type":"Point"}
}