{
  "type": "Feature",
  "properties": {
    "addr:full":"4225 E Mcdowell Rd Phoenix AZ 85008",
    "addr:housenumber":"4225",
    "addr:postcode":"85008",
    "addr:street":"E Mcdowell Rd",
    "iso:country":"US",
    "sg:address":"4225 E Mcdowell Rd",
    "sg:city":"Phoenix",
    "sg:classifiers":[
        {
            "category":"Social Services",
            "subcategory":"Job Training",
            "type":"Services"
        }
    ],
    "sg:phone":"+1 602 750 7463",
    "sg:postcode":"85008",
    "sg:province":"AZ",
    "sg:tags":[
        "employment"
    ],
    "wof:name":"Edutech Foundation",
    "wof:placetype":"venue"
},
  "geometry": {"coordinates":[-111.99082199999999,33.465684],"type":"Point"}
}