{
  "type": "Feature",
  "properties": {
    "iso:country":"US",
    "sg:address":"1850 S Stapley Dr",
    "sg:city":"Mesa",
    "sg:classifiers":[
        {
            "category":"Autos & Motor Vehicles",
            "subcategory":"Fuel & Gas Station",
            "type":"Retail Goods"
        }
    ],
    "sg:phone":"+1 480 558 7112",
    "sg:postcode":"85204",
    "sg:province":"AZ",
    "sg:tags":[
        "station",
        "gasoline"
    ],
    "wof:name":"Phillips 66 57563",
    "wof:placetype":"venue"
},
  "geometry": {"coordinates":[-111.806799,33.381292],"type":"Point"}
}