{
  "type": "Feature",
  "properties": {
    "addr:full":"3456 W 2nd St Thatcher AZ 85552",
    "addr:housenumber":"3456",
    "addr:postcode":"85552",
    "addr:street":"W 2Nd St",
    "iso:country":"US",
    "sg:address":"3456 W 2nd St",
    "sg:city":"Thatcher",
    "sg:classifiers":[
        {
            "category":"Building & Trades",
            "subcategory":"Plumbing",
            "type":"Services"
        }
    ],
    "sg:phone":"+1 928 428 0753",
    "sg:postcode":"85552",
    "sg:province":"AZ",
    "sg:tags":[
        "contractor",
        "system",
        "air conditioning"
    ],
    "wof:name":"Jon's Heating & Cooling",
    "wof:placetype":"venue"
},
  "geometry": {"coordinates":[-109.7581,32.850846],"type":"Point"}
}