{
  "type": "Feature",
  "properties": {
    "iso:country":"US",
    "sg:address":"823 Mission Ln",
    "sg:city":"Holbrook",
    "sg:classifiers":[
        {
            "category":"Organizations",
            "subcategory":"Religious Organization",
            "type":"Services"
        }
    ],
    "sg:phone":"+1 928 524 1787",
    "sg:postcode":"86025",
    "sg:province":"AZ",
    "sg:tags":[
        "church"
    ],
    "wof:name":"Holbrook Pentecostal Chr-God",
    "wof:placetype":"venue"
},
  "geometry": {"coordinates":[-110.145821,34.936277],"type":"Point"}
}