{
  "type": "Feature",
  "properties": {
    "addr:full":"1319 E Winter Dr Phoenix AZ 85020",
    "addr:housenumber":"1319",
    "addr:postcode":"85020",
    "addr:street":"E Winter Dr",
    "iso:country":"US",
    "sg:address":"1319 E Winter Dr",
    "sg:city":"Phoenix",
    "sg:classifiers":[
        {
            "category":"Building & Trades",
            "subcategory":"Construction",
            "type":"Services"
        }
    ],
    "sg:phone":"+1 602 997 4118",
    "sg:postcode":"85020",
    "sg:province":"AZ",
    "sg:tags":[
        "tile",
        "dealer"
    ],
    "sg:website":"www.chaparraltile.com",
    "wof:name":"Chaparral Tile Corp",
    "wof:placetype":"venue"
},
  "geometry": {"coordinates":[-112.052567,33.552153],"type":"Point"}
}