{
  "type": "Feature",
  "properties": {
    "addr:full":"5013 E Clarendon Ave Phoenix AZ 85018",
    "addr:housenumber":"5013",
    "addr:postcode":"85018",
    "addr:street":"E Clarendon Ave",
    "iso:country":"US",
    "sg:address":"5013 E Clarendon Ave",
    "sg:city":"Phoenix",
    "sg:classifiers":[
        {
            "category":"Professional",
            "subcategory":"Management & Consulting",
            "type":"Services"
        },
        {
            "category":"Professional",
            "subcategory":"Advertising",
            "type":"Services"
        }
    ],
    "sg:phone":"+1 480 329 9313",
    "sg:postcode":"85018",
    "sg:province":"AZ",
    "sg:tags":[
        "marketing",
        "program",
        "consultant"
    ],
    "wof:name":"Ideas Collide, Inc.",
    "wof:placetype":"venue"
},
  "geometry": {"coordinates":[-111.972824,33.490582],"type":"Point"}
}