{
  "type": "Feature",
  "properties": {
    "iso:country":"US",
    "sg:address":"9777 N 91st St",
    "sg:city":"Scottsdale",
    "sg:classifiers":[
        {
            "category":"Professional",
            "subcategory":"Engineering",
            "type":"Services"
        }
    ],
    "sg:phone":"+1 480 443 8773",
    "sg:postcode":"85258",
    "sg:province":"AZ",
    "sg:tags":[
        "engineer"
    ],
    "wof:name":"Johnston Engineering Co",
    "wof:placetype":"venue"
},
  "geometry": {"coordinates":[-111.882907,33.574724],"type":"Point"}
}