{
  "type": "Feature",
  "properties": {
    "addr:full":"1655 W el Paseo Real Yuma AZ 85364",
    "addr:housenumber":"1655",
    "addr:postcode":"85364",
    "addr:street":"W El Paseo Real",
    "iso:country":"US",
    "sg:address":"1655 W el Paseo Real",
    "sg:city":"Yuma",
    "sg:phone":"+1 928 782 4488",
    "sg:postcode":"85364",
    "sg:province":"AZ",
    "sg:tags":[
        "farm"
    ],
    "wof:name":"Ken Bingham",
    "wof:placetype":"venue"
},
  "geometry": {"coordinates":[-114.639854,32.698856],"type":"Point"}
}