{
  "type": "Feature",
  "properties": {
    "addr:full":"6544 W Thomas Rd Phoenix AZ 85033",
    "addr:housenumber":"6544",
    "addr:postcode":"85033",
    "addr:street":"W Thomas Rd",
    "iso:country":"US",
    "sg:address":"6544 W Thomas Rd",
    "sg:city":"Phoenix",
    "sg:classifiers":[
        {
            "category":"Professional",
            "subcategory":"Accounting & Tax Preparation",
            "type":"Services"
        },
        {
            "category":"Banks & Credit Unions",
            "subcategory":"Financial Services",
            "type":"Services"
        }
    ],
    "sg:phone":"+1 623 845 6746",
    "sg:postcode":"85033",
    "sg:province":"AZ",
    "sg:tags":[
        "return",
        "preparation-business",
        "taxes-consultants",
        "loan",
        "reporting",
        "representative",
        "alternative",
        "bookkeeping"
    ],
    "sg:website":"http://www.hrblock.com",
    "wof:name":"H&R Block",
    "wof:placetype":"venue"
},
  "geometry": {"coordinates":[-112.201279,33.480369],"type":"Point"}
}