{
  "type": "Feature",
  "properties": {
    "iso:country":"US",
    "sg:address":"2221 N 94th Ave",
    "sg:city":"Phoenix",
    "sg:classifiers":[
        {
            "category":"Building & Trades",
            "subcategory":"Construction",
            "type":"Services"
        }
    ],
    "sg:phone":"+1 623 936 5646",
    "sg:postcode":"85037",
    "sg:province":"AZ",
    "sg:tags":[
        "masonry",
        "contractor"
    ],
    "wof:name":"Alpha & Omega Masonry",
    "wof:placetype":"venue"
},
  "geometry": {"coordinates":[-112.262113,33.47197],"type":"Point"}
}