{
  "type": "Feature",
  "properties": {
    "iso:country":"US",
    "sg:address":"2058 E Southern Ave",
    "sg:city":"Tempe",
    "sg:classifiers":[
        {
            "category":"Personal",
            "subcategory":"Beauty Salon",
            "type":"Services"
        }
    ],
    "sg:phone":"+1 480 897 6358",
    "sg:postcode":"85282",
    "sg:province":"AZ",
    "wof:name":"Head Dressers",
    "wof:placetype":"venue"
},
  "geometry": {"coordinates":[-111.89713500000001,33.393072],"type":"Point"}
}