{
  "type": "Feature",
  "properties": {
    "iso:country":"US",
    "sg:address":"1507 N Litchfield Rd",
    "sg:city":"Goodyear",
    "sg:classifiers":[
        {
            "category":"Building & Trades",
            "subcategory":"Locksmith",
            "type":"Services"
        }
    ],
    "sg:phone":"+1 866 242 4779",
    "sg:postcode":"85395",
    "sg:province":"AZ",
    "sg:tags":[
        "key"
    ],
    "wof:name":"A 24 Emergency Locksmith",
    "wof:placetype":"venue"
},
  "geometry": {"coordinates":[-112.357826,33.46296],"type":"Point"}
}