{
  "type": "Feature",
  "properties": {
    "addr:full":"3333 N Campbell Ave # 11 Tucson AZ 85719",
    "addr:housenumber":"3333",
    "addr:postcode":"85719",
    "addr:street":"N Campbell Ave # 11",
    "iso:country":"US",
    "sg:address":"3333 N Campbell Ave # 11",
    "sg:city":"Tucson",
    "sg:classifiers":[
        {
            "category":"Communications",
            "subcategory":"Radio Station",
            "type":"Services"
        }
    ],
    "sg:phone":"+1 800 750 5239",
    "sg:postcode":"85719",
    "sg:province":"AZ",
    "sg:tags":[
        "broadcast"
    ],
    "wof:name":"Kzlz 105.3 Fm",
    "wof:placetype":"venue"
},
  "geometry": {"coordinates":[-110.94381,32.267344],"type":"Point"}
}