{
  "type": "Feature",
  "properties": {
    "addr:full":"14205 S 50th St Phoenix AZ 85044",
    "addr:housenumber":"14205",
    "addr:postcode":"85044",
    "addr:street":"S 50Th St",
    "iso:country":"US",
    "sg:address":"14205 S 50th St",
    "sg:city":"Phoenix",
    "sg:phone":"+1 480 598 1300",
    "sg:postcode":"85044",
    "sg:province":"AZ",
    "sg:website":"http://www.rockbottom.com",
    "wof:name":"Rock Bottom Rstrnt & Brewery",
    "wof:placetype":"venue"
},
  "geometry": {"coordinates":[-111.97613,33.318323],"type":"Point"}
}