{
  "type": "Feature",
  "properties": {
    "iso:country":"US",
    "sg:address":"160 S Macdonald",
    "sg:city":"Mesa",
    "sg:classifiers":[
        {
            "category":"Utilities",
            "subcategory":"Cable",
            "type":"Services"
        }
    ],
    "sg:phone":"+1 602 866 0072",
    "sg:postcode":"85210",
    "sg:province":"AZ",
    "sg:tags":[
        "television"
    ],
    "wof:name":"Dimension Cable Services",
    "wof:placetype":"venue"
},
  "geometry": {"coordinates":[-111.834173,33.412086],"type":"Point"}
}