{
  "type": "Feature",
  "properties": {
    "addr:full":"8151 E Main St Mesa AZ 85207",
    "addr:housenumber":"8151",
    "addr:postcode":"85207",
    "addr:street":"E Main St",
    "iso:country":"US",
    "sg:address":"8151 E Main St",
    "sg:city":"Mesa",
    "sg:classifiers":[
        {
            "category":"Manufacturing",
            "subcategory":"Wood Products",
            "type":"Manufacturing & Wholesale Goods"
        },
        {
            "category":"Building & Trades",
            "subcategory":"Construction",
            "type":"Services"
        }
    ],
    "sg:phone":"+1 480 986 3502",
    "sg:postcode":"85207",
    "sg:province":"AZ",
    "sg:tags":[
        "mfg",
        "woodworker"
    ],
    "wof:name":"Taylor Wood Designs",
    "wof:placetype":"venue"
},
  "geometry": {"coordinates":[-111.65541899999999,33.415094],"type":"Point"}
}