{
  "type": "Feature",
  "properties": {
    "addr:full":"2080 S Milton Rd Flagstaff AZ 86001",
    "addr:housenumber":"2080",
    "addr:postcode":"86001",
    "addr:street":"S Milton Rd",
    "iso:country":"US",
    "sg:address":"2080 S Milton Rd",
    "sg:city":"Flagstaff",
    "sg:classifiers":[
        {
            "category":"Restaurant",
            "type":"Food & Drink"
        }
    ],
    "sg:menulink":"http://www.allmenus.com/az/coconino/110784-quiznos-sub/menu/",
    "sg:phone":"+1 928 213 5553",
    "sg:postcode":"86001",
    "sg:province":"AZ",
    "sg:tags":[
        "wrap",
        "american",
        "sandwich"
    ],
    "wof:name":"Quiznos Sub",
    "wof:placetype":"venue"
},
  "geometry": {"coordinates":[-111.661254,35.179849],"type":"Point"}
}