{
  "type": "Feature",
  "properties": {
    "addr:full":"3101 N 47th Pl Phoenix AZ 85018",
    "addr:housenumber":"3101",
    "addr:postcode":"85018",
    "addr:street":"N 47Th Pl",
    "iso:country":"US",
    "sg:address":"3101 N 47th Pl",
    "sg:city":"Phoenix",
    "sg:classifiers":[
        {
            "category":"Wholesale",
            "subcategory":"Books, Periodicals, & Newspapers",
            "type":"Manufacturing & Wholesale Goods"
        }
    ],
    "sg:phone":"+1 602 808 0324",
    "sg:postcode":"85018",
    "sg:province":"AZ",
    "sg:tags":[
        "publisher",
        "book"
    ],
    "wof:name":"Divine Line Enterprises",
    "wof:placetype":"venue"
},
  "geometry": {"coordinates":[-111.97904200000001,33.48336],"type":"Point"}
}