{
  "type": "Feature",
  "properties": {
    "iso:country":"US",
    "sg:address":"6528 N 17th Ave",
    "sg:city":"Phoenix",
    "sg:classifiers":[
        {
            "category":"Real Estate",
            "subcategory":"Real Estate Operator",
            "type":"Services"
        }
    ],
    "sg:phone":"+1 602 347 1211",
    "sg:postcode":"85015",
    "sg:province":"AZ",
    "sg:tags":[
        "building",
        "apartment"
    ],
    "wof:name":"Galaxy Apartments",
    "wof:placetype":"venue"
},
  "geometry": {"coordinates":[-112.095451,33.533395],"type":"Point"}
}