{
  "type": "Feature",
  "properties": {
    "addr:full":"2332 W Northern Ave Phoenix AZ 85021",
    "addr:housenumber":"2332",
    "addr:postcode":"85021",
    "addr:street":"W Northern Ave",
    "iso:country":"US",
    "sg:address":"2332 W Northern Ave",
    "sg:city":"Phoenix",
    "sg:classifiers":[
        {
            "category":"Food & Beverages",
            "subcategory":"Groceries & Convenience Stores",
            "type":"Retail Goods"
        }
    ],
    "sg:phone":"+1 602 864 1624",
    "sg:postcode":"85021",
    "sg:province":"AZ",
    "wof:name":"Village Market",
    "wof:placetype":"venue"
},
  "geometry": {"coordinates":[-112.109551,33.553197],"type":"Point"}
}