{
  "type": "Feature",
  "properties": {
    "iso:country":"US",
    "sg:address":"2002 E 3rd Ave",
    "sg:city":"Flagstaff",
    "sg:classifiers":[
        {
            "category":"Professional",
            "type":"Services"
        }
    ],
    "sg:phone":"+1 928 226 0121",
    "sg:postcode":"86004",
    "sg:province":"AZ",
    "wof:name":"Nellys",
    "wof:placetype":"venue"
},
  "geometry": {"coordinates":[-111.61894700000001,35.207707],"type":"Point"}
}