{
  "type": "Feature",
  "properties": {
    "iso:country":"US",
    "sg:address":"4709 E Encanto St",
    "sg:city":"Mesa",
    "sg:classifiers":[
        {
            "category":"Banks & Credit Unions",
            "subcategory":"Financial Services",
            "type":"Services"
        }
    ],
    "sg:phone":"+1 480 832 5045",
    "sg:postcode":"85205",
    "sg:province":"AZ",
    "sg:tags":[
        "trust",
        "management"
    ],
    "wof:name":"Izard Family Trust",
    "wof:placetype":"venue"
},
  "geometry": {"coordinates":[-111.727864,33.433943],"type":"Point"}
}