{
  "type": "Feature",
  "properties": {
    "iso:country":"US",
    "sg:address":"10054 N 43rd Ave",
    "sg:city":"Glendale",
    "sg:phone":"+1 623 842 1181",
    "sg:postcode":"85302",
    "sg:province":"AZ",
    "sg:website":"http://www.greatskateglendale.com",
    "wof:name":"Great Skate",
    "wof:placetype":"venue"
},
  "geometry": {"coordinates":[-112.151579,33.578127],"type":"Point"}
}