{
  "type": "Feature",
  "properties": {
    "addr:full":"23043 N 16th Ln Phoenix AZ 85027",
    "addr:housenumber":"23043",
    "addr:postcode":"85027",
    "addr:street":"N 16Th Ln",
    "iso:country":"US",
    "sg:address":"23043 N 16th Ln",
    "sg:city":"Phoenix",
    "sg:classifiers":[
        {
            "category":"Manufacturing",
            "subcategory":"Printing",
            "type":"Manufacturing & Wholesale Goods"
        }
    ],
    "sg:phone":"+1 623 445 2800",
    "sg:postcode":"85027",
    "sg:province":"AZ",
    "sg:tags":[
        "newspaper"
    ],
    "wof:name":"Independent Newspapers Inc",
    "wof:placetype":"venue"
},
  "geometry": {"coordinates":[-112.094954,33.695456],"type":"Point"}
}