{
  "type": "Feature",
  "properties": {
    "addr:full":"3625 E Industrial Dr Flagstaff AZ 86004",
    "addr:housenumber":"3625",
    "addr:postcode":"86004",
    "addr:street":"E Industrial Dr",
    "iso:country":"US",
    "sg:address":"3625 E Industrial Dr",
    "sg:city":"Flagstaff",
    "sg:classifiers":[
        {
            "category":"Freight",
            "type":"Transportation"
        }
    ],
    "sg:phone":"+1 928 526 0509",
    "sg:postcode":"86004",
    "sg:province":"AZ",
    "sg:tags":[
        "operator",
        "trucking"
    ],
    "wof:name":"CTI Leasing",
    "wof:placetype":"venue"
},
  "geometry": {"coordinates":[-111.595072,35.215057],"type":"Point"}
}