{
  "type": "Feature",
  "properties": {
    "iso:country":"US",
    "sg:address":"9675 W Mountain View Rd",
    "sg:city":"Peoria",
    "sg:classifiers":[
        {
            "category":"Professional",
            "subcategory":"Accounting & Tax Preparation",
            "type":"Services"
        }
    ],
    "sg:phone":"+1 623 486 0052",
    "sg:postcode":"85345",
    "sg:province":"AZ",
    "sg:tags":[
        "return",
        "filing"
    ],
    "wof:name":"Compute Accounts",
    "wof:placetype":"venue"
},
  "geometry": {"coordinates":[-112.267459,33.572867],"type":"Point"}
}