{
  "type": "Feature",
  "properties": {
    "addr:full":"2010 S Dobson Rd Chandler AZ 85286",
    "addr:housenumber":"2010",
    "addr:postcode":"85286",
    "addr:street":"S Dobson Rd",
    "iso:country":"US",
    "sg:address":"2010 S Dobson Rd",
    "sg:city":"Chandler",
    "sg:classifiers":[
        {
            "category":"Shopping",
            "subcategory":"Pharmacy",
            "type":"Retail Goods"
        }
    ],
    "sg:phone":"+1 480 899 2183",
    "sg:postcode":"85286",
    "sg:province":"AZ",
    "wof:name":"CVS Pharmacy",
    "wof:placetype":"venue"
},
  "geometry": {"coordinates":[-111.87626899999999,33.276003],"type":"Point"}
}