{
  "type": "Feature",
  "properties": {
    "iso:country":"US",
    "sg:address":"801 S 75th Ave",
    "sg:city":"Phoenix",
    "sg:classifiers":[
        {
            "category":"Structure",
            "subcategory":"Warehouse",
            "type":"Public Place"
        },
        {
            "category":"Retail",
            "subcategory":"Storage",
            "type":"Services"
        }
    ],
    "sg:phone":"+1 623 936 1116",
    "sg:postcode":"85043",
    "sg:province":"AZ",
    "sg:tags":[
        "self",
        "warehouses-public-commercial"
    ],
    "sg:website":"http://www.apldirectlogistics.com",
    "wof:name":"Apl Logistics Warehouse Management Services, Inc.",
    "wof:placetype":"venue"
},
  "geometry": {"coordinates":[-112.221034,33.439581],"type":"Point"}
}