{
  "type": "Feature",
  "properties": {
    "addr:full":"8130 N 86th Pl Scottsdale AZ 85258",
    "addr:housenumber":"8130",
    "addr:postcode":"85258",
    "addr:street":"N 86Th Pl",
    "iso:country":"US",
    "sg:address":"8130 N 86th Pl",
    "sg:city":"Scottsdale",
    "sg:classifiers":[
        {
            "category":"Real Estate",
            "subcategory":"Architect",
            "type":"Services"
        }
    ],
    "sg:phone":"+1 480 941 0840",
    "sg:postcode":"85258",
    "sg:province":"AZ",
    "sg:website":"www.linderoth.com",
    "wof:name":"Linderoth Associate Inc",
    "wof:placetype":"venue"
},
  "geometry": {"coordinates":[-111.895056,33.554102],"type":"Point"}
}