{
  "type": "Feature",
  "properties": {
    "addr:full":"600 S Navajo Ave Parker AZ 85344",
    "addr:housenumber":"600",
    "addr:postcode":"az 85344",
    "addr:street":"S Navajo Ave",
    "iso:country":"US",
    "sg:address":"600 S Navajo Ave",
    "sg:city":"Parker",
    "sg:classifiers":[
        {
            "category":"Social Services",
            "subcategory":"Child Care",
            "type":"Services"
        }
    ],
    "sg:phone":"+1 928 669 9700",
    "sg:postcode":"85344",
    "sg:province":"AZ",
    "sg:tags":[
        "nursery",
        "day"
    ],
    "wof:name":"Weecare In Parker",
    "wof:placetype":"venue"
},
  "geometry": {"coordinates":[-114.297729,34.151619],"type":"Point"}
}