{
  "type": "Feature",
  "properties": {
    "iso:country":"US",
    "sg:address":"239 E Chilton Dr",
    "sg:city":"Tempe",
    "sg:classifiers":[
        {
            "category":"Wholesale",
            "subcategory":"Books, Periodicals, & Newspapers",
            "type":"Manufacturing & Wholesale Goods"
        }
    ],
    "sg:phone":"+1 480 968 8065",
    "sg:postcode":"85283",
    "sg:province":"AZ",
    "sg:tags":[
        "publisher",
        "book"
    ],
    "wof:name":"Kwik Trip Media",
    "wof:placetype":"venue"
},
  "geometry": {"coordinates":[-111.93624,33.351112],"type":"Point"}
}