{
  "type": "Feature",
  "properties": {
    "addr:full":"125 N 6th St Kingman AZ 86401",
    "addr:housenumber":"125",
    "addr:postcode":"86401",
    "addr:street":"N 6Th St",
    "iso:country":"US",
    "sg:address":"125 N 6th St",
    "sg:city":"Kingman",
    "sg:classifiers":[
        {
            "category":"Manufacturing",
            "subcategory":"Apparel",
            "type":"Manufacturing & Wholesale Goods"
        }
    ],
    "sg:phone":"+1 928 753 7780",
    "sg:postcode":"86401",
    "sg:province":"AZ",
    "sg:tags":[
        "clothes",
        "accessory"
    ],
    "wof:name":"Flashy Rag Boutique",
    "wof:placetype":"venue"
},
  "geometry": {"coordinates":[-114.049177,35.188858],"type":"Point"}
}