{
  "type": "Feature",
  "properties": {
    "addr:full":"4321 W Bell Rd Glendale AZ 85308",
    "addr:housenumber":"4321",
    "addr:postcode":"85308",
    "addr:street":"W Bell Rd",
    "iso:country":"US",
    "sg:address":"4321 W Bell Rd",
    "sg:city":"Glendale",
    "sg:classifiers":[
        {
            "category":"Home & Garden",
            "subcategory":"Carpets & Floor Coverings",
            "type":"Retail Goods"
        }
    ],
    "sg:phone":"+1 602 789 8800",
    "sg:postcode":"85308",
    "sg:province":"AZ",
    "sg:tags":[
        "dealer",
        "rug"
    ],
    "wof:name":"America's Flooring Wholesalers",
    "wof:placetype":"venue"
},
  "geometry": {"coordinates":[-112.155038,33.639185],"type":"Point"}
}