{
  "type": "Feature",
  "properties": {
    "iso:country":"US",
    "sg:address":"561 W Mesquite St",
    "sg:city":"Gilbert",
    "sg:classifiers":[
        {
            "category":"Real Estate",
            "subcategory":"Real Estate Agent",
            "type":"Services"
        }
    ],
    "sg:phone":"+1 480 892 5479",
    "sg:postcode":"85233",
    "sg:province":"AZ",
    "sg:tags":[
        "investment"
    ],
    "wof:name":"Decision Management Technology",
    "wof:placetype":"venue"
},
  "geometry": {"coordinates":[-111.802288,33.344393],"type":"Point"}
}