{
  "type": "Feature",
  "properties": {
    "iso:country":"US",
    "sg:address":"4151 N 32nd St",
    "sg:city":"Phoenix",
    "sg:classifiers":[
        {
            "category":"Personal",
            "type":"Services"
        },
        {
            "category":"Arena",
            "subcategory":"Sports Club",
            "type":"Entertainment"
        }
    ],
    "sg:phone":"+1 602 954 9262",
    "sg:postcode":"85018",
    "sg:province":"AZ",
    "sg:tags":[
        "trainer",
        "consultant",
        "physical",
        "health",
        "fitness"
    ],
    "wof:name":"Blossom Day Spa",
    "wof:placetype":"venue"
},
  "geometry": {"coordinates":[-112.01298,33.496939],"type":"Point"}
}