{
  "type": "Feature",
  "properties": {
    "addr:full":"150 E Wagon Wheel Dr Phoenix AZ 85020",
    "addr:housenumber":"150",
    "addr:postcode":"85020",
    "addr:street":"E Wagon Wheel Dr",
    "iso:country":"US",
    "sg:address":"150 E Wagon Wheel Dr",
    "sg:city":"Phoenix",
    "sg:classifiers":[
        {
            "category":"Restaurant",
            "type":"Food & Drink"
        }
    ],
    "sg:phone":"+1 602 870 9107",
    "sg:postcode":"85020",
    "sg:province":"AZ",
    "sg:tags":[
        "eating"
    ],
    "wof:name":"Everything Yogurt & Salad",
    "wof:placetype":"venue"
},
  "geometry": {"coordinates":[-112.070336,33.546959],"type":"Point"}
}