{
  "type": "Feature",
  "properties": {
    "addr:full":"1312 W 16th St Parker AZ 85344",
    "addr:housenumber":"1312",
    "addr:postcode":"az 85344",
    "addr:street":"W 16Th St",
    "iso:country":"US",
    "sg:address":"1312 W 16th St",
    "sg:city":"Parker",
    "sg:classifiers":[
        {
            "category":"Organizations",
            "subcategory":"Religious Organization",
            "type":"Services"
        }
    ],
    "sg:phone":"+1 928 669 8468",
    "sg:postcode":"85344",
    "sg:province":"AZ",
    "sg:tags":[
        "churches-baptist",
        "church"
    ],
    "sg:website":"http://www.abc-usa.org",
    "wof:name":"First Baptist Church",
    "wof:placetype":"venue"
},
  "geometry": {"coordinates":[-114.290705,34.142211],"type":"Point"}
}