{
  "type": "Feature",
  "properties": {
    "addr:full":"410 Hillcrest Dr Prescott AZ 86303",
    "addr:housenumber":"410",
    "addr:postcode":"86303",
    "addr:street":"Hillcrest Dr",
    "iso:country":"US",
    "sg:address":"410 Hillcrest Dr",
    "sg:city":"Prescott",
    "sg:classifiers":[
        {
            "category":"Professional",
            "subcategory":"Art Services",
            "type":"Services"
        }
    ],
    "sg:phone":"+1 928 445 7038",
    "sg:postcode":"86303",
    "sg:province":"AZ",
    "sg:tags":[
        "graphic",
        "designer"
    ],
    "wof:name":"Agrell Group",
    "wof:placetype":"venue"
},
  "geometry": {"coordinates":[-112.456776,34.536654],"type":"Point"}
}