{
  "type": "Feature",
  "properties": {
    "iso:country":"US",
    "sg:address":"2501 E Southern Ave Ste 12",
    "sg:city":"Tempe",
    "sg:classifiers":[
        {
            "category":"Health Services",
            "subcategory":"Doctor",
            "type":"Services"
        }
    ],
    "sg:phone":"+1 480 491 2082",
    "sg:postcode":"85282",
    "sg:province":"AZ",
    "sg:tags":[
        "physician",
        "family",
        "practice",
        "surgeons",
        "medicine",
        "surgeon"
    ],
    "wof:name":"Milam Robert C Md",
    "wof:placetype":"venue"
},
  "geometry": {"coordinates":[-111.88642900000001,33.393009],"type":"Point"}
}