{
  "type": "Feature",
  "properties": {
    "iso:country":"US",
    "sg:address":"2512 N 27th Ave",
    "sg:city":"Phoenix",
    "sg:classifiers":[
        {
            "category":"Wholesale",
            "subcategory":"Machinery & Supplies",
            "type":"Manufacturing & Wholesale Goods"
        }
    ],
    "sg:phone":"+1 602 272 2271",
    "sg:postcode":"85009",
    "sg:province":"AZ",
    "sg:tags":[
        "farm",
        "equipment",
        "industrial",
        "tractor"
    ],
    "wof:name":"Allison Equipment Company Inc",
    "wof:placetype":"venue"
},
  "geometry": {"coordinates":[-112.11716800000001,33.474329],"type":"Point"}
}