{
  "type": "Feature",
  "properties": {
    "addr:full":"1301 Grand Ave Phoenix AZ 85007",
    "addr:housenumber":"1301",
    "addr:postcode":"85007",
    "addr:street":"Grand Ave",
    "iso:country":"US",
    "sg:address":"1301 Grand Ave",
    "sg:city":"Phoenix",
    "sg:classifiers":[
        {
            "category":"Coffee & Tea",
            "type":"Food & Drink"
        },
        {
            "category":"Restaurant",
            "type":"Food & Drink"
        }
    ],
    "sg:phone":"+1 602 254 6726",
    "sg:postcode":"85007",
    "sg:province":"AZ",
    "sg:tags":[
        "espresso"
    ],
    "wof:name":"Sapna Cafe",
    "wof:placetype":"venue"
},
  "geometry": {"coordinates":[-112.089142,33.456902],"type":"Point"}
}