{
  "type": "Feature",
  "properties": {
    "addr:full":"6339 E Greenway Rd Scottsdale AZ 85254",
    "addr:housenumber":"6339",
    "addr:postcode":"85254",
    "addr:street":"E Greenway Rd",
    "iso:country":"US",
    "sg:address":"6339 E Greenway Rd",
    "sg:city":"Scottsdale",
    "sg:classifiers":[
        {
            "category":"Deli",
            "type":"Food & Drink"
        }
    ],
    "sg:menulink":"http://www.allmenus.com/az/phoenix/125890-blimpie-subs--sandwiches/menu/",
    "sg:phone":"+1 480 368 2916",
    "sg:postcode":"85254",
    "sg:province":"AZ",
    "sg:tags":[
        "wrap",
        "american",
        "sandwich"
    ],
    "wof:name":"Blimpie Subs & Sandwiches",
    "wof:placetype":"venue"
},
  "geometry": {"coordinates":[-111.943566,33.624638],"type":"Point"}
}