{
  "type": "Feature",
  "properties": {
    "addr:full":"3440 N 16th St Phoenix AZ 85016",
    "addr:housenumber":"3440",
    "addr:postcode":"85016",
    "addr:street":"N 16Th St",
    "iso:country":"US",
    "sg:address":"3440 N 16th St",
    "sg:city":"Phoenix",
    "sg:classifiers":[
        {
            "category":"Professional",
            "subcategory":"Lawyer & Legal Services",
            "type":"Services"
        }
    ],
    "sg:phone":"+1 602 264 6928",
    "sg:postcode":"85016",
    "sg:province":"AZ",
    "sg:tags":[
        "attorney"
    ],
    "wof:name":"John T Ryan",
    "wof:placetype":"venue"
},
  "geometry": {"coordinates":[-112.047731,33.487165],"type":"Point"}
}