{
  "type": "Feature",
  "properties": {
    "iso:country":"US",
    "sg:address":"4040 E Camelback Rd",
    "sg:city":"Phoenix",
    "sg:classifiers":[
        {
            "category":"Professional",
            "type":"Services"
        }
    ],
    "sg:phone":"+1 602 553 0033",
    "sg:postcode":"85018",
    "sg:province":"AZ",
    "wof:name":"Curastat Inc",
    "wof:placetype":"venue"
},
  "geometry": {"coordinates":[-111.99365299999999,33.509868],"type":"Point"}
}