{
  "type": "Feature",
  "properties": {
    "addr:full":"17642 N 23rd Ave Phoenix AZ 85023",
    "addr:housenumber":"17642",
    "addr:postcode":"85023",
    "addr:street":"N 23Rd Ave",
    "iso:country":"US",
    "sg:address":"17642 N 23rd Ave",
    "sg:city":"Phoenix",
    "sg:classifiers":[
        {
            "category":"Building & Trades",
            "subcategory":"Locksmith",
            "type":"Services"
        }
    ],
    "sg:phone":"+1 602 993 7498",
    "sg:postcode":"85023",
    "sg:province":"AZ",
    "sg:tags":[
        "equipment",
        "supply"
    ],
    "wof:name":"Errigo Mobile",
    "wof:placetype":"venue"
},
  "geometry": {"coordinates":[-112.10897,33.64668],"type":"Point"}
}