{
  "type": "Feature",
  "properties": {
    "iso:country":"US",
    "sg:address":"730 E Rowlands Ln",
    "sg:city":"Phoenix",
    "sg:classifiers":[
        {
            "category":"Professional",
            "type":"Services"
        },
        {
            "category":"Arts & Performance",
            "subcategory":"Music",
            "type":"Entertainment"
        }
    ],
    "sg:phone":"+1 602 298 6862",
    "sg:postcode":"85022",
    "sg:province":"AZ",
    "sg:tags":[
        "record",
        "producer",
        "label"
    ],
    "sg:website":"http://www.musicfortheheart.com",
    "wof:name":"Crucible",
    "wof:placetype":"venue"
},
  "geometry": {"coordinates":[-112.064709,33.616672],"type":"Point"}
}