{
  "type": "Feature",
  "properties": {
    "addr:full":"4940 S Wendler Dr Tempe AZ 85282",
    "addr:housenumber":"4940",
    "addr:postcode":"85282",
    "addr:street":"S Wendler Dr",
    "iso:country":"US",
    "sg:address":"4940 S Wendler Dr",
    "sg:city":"Tempe",
    "sg:classifiers":[
        {
            "category":"Banks & Credit Unions",
            "subcategory":"Bank",
            "type":"Services"
        }
    ],
    "sg:phone":"+1 602 431 9370",
    "sg:postcode":"85282",
    "sg:province":"AZ",
    "sg:tags":[
        "loan",
        "real estate"
    ],
    "wof:name":"Nationstar Mortgage",
    "wof:placetype":"venue"
},
  "geometry": {"coordinates":[-111.969796,33.381157],"type":"Point"}
}