{
  "type": "Feature",
  "properties": {
    "iso:country":"US",
    "sg:address":"16099 N 82nd St",
    "sg:city":"Scottsdale",
    "sg:classifiers":[
        {
            "category":"Recreation",
            "type":"Entertainment"
        }
    ],
    "sg:phone":"+1 480 425 7734",
    "sg:postcode":"85260",
    "sg:province":"AZ",
    "sg:tags":[
        "amusement"
    ],
    "sg:website":"www.motiondnacorp.com",
    "wof:name":"Motion DNA Corp",
    "wof:placetype":"venue"
},
  "geometry": {"coordinates":[-111.903716,33.63223],"type":"Point"}
}