{
  "type": "Feature",
  "properties": {
    "iso:country":"US",
    "sg:address":"3529 E Grant Rd",
    "sg:city":"Tucson",
    "sg:classifiers":[
        {
            "category":"Shopping",
            "subcategory":"Used Merchandise",
            "type":"Retail Goods"
        }
    ],
    "sg:phone":"+1 520 325 5100",
    "sg:postcode":"85716",
    "sg:province":"AZ",
    "wof:name":"Kollectors Kastle",
    "wof:placetype":"venue"
},
  "geometry": {"coordinates":[-110.916752,32.250593],"type":"Point"}
}