{
  "type": "Feature",
  "properties": {
    "iso:country":"US",
    "sg:address":"2455 E Broadway Rd",
    "sg:city":"Mesa",
    "sg:classifiers":[
        {
            "category":"Restaurant",
            "type":"Food & Drink"
        }
    ],
    "sg:phone":"+1 480 832 2452",
    "sg:postcode":"85204",
    "sg:province":"AZ",
    "wof:name":"Sunland Village Restaurant",
    "wof:placetype":"venue"
},
  "geometry": {"coordinates":[-111.776444,33.408069],"type":"Point"}
}