{
  "type": "Feature",
  "properties": {
    "iso:country":"US",
    "sg:address":"2848 E Bell Rd",
    "sg:city":"Phoenix",
    "sg:classifiers":[
        {
            "category":"Shopping",
            "subcategory":"Bicycles & Sporting Goods",
            "type":"Retail Goods"
        }
    ],
    "sg:phone":"+1 602 404 2142",
    "sg:postcode":"85032",
    "sg:province":"AZ",
    "sg:tags":[
        "equipment",
        "golf",
        "equipment-repairing",
        "supply"
    ],
    "sg:website":"http://jerrysgolfballs.com",
    "wof:name":"Jerry's Golf Balls",
    "wof:placetype":"venue"
},
  "geometry": {"coordinates":[-112.021102,33.640634],"type":"Point"}
}