{
  "type": "Feature",
  "properties": {
    "iso:country":"US",
    "sg:address":"15508 W Bell Rd",
    "sg:city":"Surprise",
    "sg:classifiers":[
        {
            "category":"Manufacturing",
            "subcategory":"Retail Goods",
            "type":"Manufacturing & Wholesale Goods"
        }
    ],
    "sg:phone":"+1 623 322 2567",
    "sg:postcode":"85374",
    "sg:province":"AZ",
    "sg:tags":[
        "distributor"
    ],
    "wof:name":"Military Force Products LLC",
    "wof:placetype":"venue"
},
  "geometry": {"coordinates":[-112.404485,33.638915],"type":"Point"}
}