{
  "type": "Feature",
  "properties": {
    "addr:full":"1680 Ca-Tim Dr Prescott AZ 86305",
    "addr:housenumber":"1680",
    "addr:postcode":"86305",
    "addr:street":"Ca-Tim Dr",
    "iso:country":"US",
    "sg:address":"1680 Ca-Tim Dr",
    "sg:city":"Prescott",
    "sg:classifiers":[
        {
            "category":"Building & Trades",
            "subcategory":"Construction",
            "type":"Services"
        }
    ],
    "sg:phone":"+1 928 445 3895",
    "sg:postcode":"86305",
    "sg:province":"AZ",
    "sg:tags":[
        "hanging",
        "contractor"
    ],
    "wof:name":"Listol Painting",
    "wof:placetype":"venue"
},
  "geometry": {"coordinates":[-112.49659800000001,34.592638],"type":"Point"}
}