{
  "type": "Feature",
  "properties": {
    "iso:country":"US",
    "sg:address":"5412 E Charter Oak Rd",
    "sg:city":"Scottsdale",
    "sg:classifiers":[
        {
            "category":"Building & Trades",
            "subcategory":"Construction",
            "type":"Services"
        }
    ],
    "sg:phone":"+1 602 788 7640",
    "sg:postcode":"85254",
    "sg:province":"AZ",
    "sg:tags":[
        "demolition",
        "contractor"
    ],
    "wof:name":"Desert West Demolition Inc",
    "wof:placetype":"venue"
},
  "geometry": {"coordinates":[-111.960812,33.599041],"type":"Point"}
}