{
  "type": "Feature",
  "properties": {
    "addr:full":"11225 N 41st Ave Phoenix AZ 85029",
    "addr:housenumber":"11225",
    "addr:postcode":"85029",
    "addr:street":"N 41St Ave",
    "iso:country":"US",
    "sg:address":"11225 N 41st Ave",
    "sg:city":"Phoenix",
    "sg:classifiers":[
        {
            "category":"Communications",
            "subcategory":"Film & Video Production",
            "type":"Services"
        }
    ],
    "sg:phone":"+1 602 246 0912",
    "sg:postcode":"85029",
    "sg:province":"AZ",
    "sg:tags":[
        "taping"
    ],
    "wof:name":"Myers Video Productions",
    "wof:placetype":"venue"
},
  "geometry": {"coordinates":[-112.14744,33.588796],"type":"Point"}
}