{
  "type": "Feature",
  "properties": {
    "iso:country":"US",
    "sg:address":"6420 E Exeter Blvd",
    "sg:city":"Scottsdale",
    "sg:classifiers":[
        {
            "category":"Professional",
            "type":"Services"
        }
    ],
    "sg:phone":"+1 480 946 6080",
    "sg:postcode":"85251",
    "sg:province":"AZ",
    "wof:name":"Walter W Rector",
    "wof:placetype":"venue"
},
  "geometry": {"coordinates":[-111.939078,33.4985],"type":"Point"}
}