{
  "type": "Feature",
  "properties": {
    "iso:country":"US",
    "sg:address":"600 S Rockford Dr",
    "sg:city":"Tempe",
    "sg:classifiers":[
        {
            "category":"Professional",
            "type":"Services"
        }
    ],
    "sg:phone":"+1 480 967 0090",
    "sg:postcode":"85281",
    "sg:province":"AZ",
    "sg:tags":[
        "establishment"
    ],
    "wof:name":"SVTR",
    "wof:placetype":"venue"
},
  "geometry": {"coordinates":[-111.898054,33.422108],"type":"Point"}
}