{
  "type": "Feature",
  "properties": {
    "addr:full":"3792 Grand Ave Phoenix AZ 85019",
    "addr:housenumber":"3792",
    "addr:postcode":"85019",
    "addr:street":"Grand Ave",
    "iso:country":"US",
    "sg:address":"3792 Grand Ave",
    "sg:city":"Phoenix",
    "sg:classifiers":[
        {
            "category":"Wholesale",
            "subcategory":"Construction Materials",
            "type":"Manufacturing & Wholesale Goods"
        }
    ],
    "sg:phone":"+1 602 242 1869",
    "sg:postcode":"85019",
    "sg:province":"AZ",
    "sg:tags":[
        "concrete",
        "product"
    ],
    "wof:name":"Neece Precast & Supply",
    "wof:placetype":"venue"
},
  "geometry": {"coordinates":[-112.14107300000001,33.50058],"type":"Point"}
}