{
  "type": "Feature",
  "properties": {
    "iso:country":"US",
    "sg:address":"3128 W Thomas Rd Ste 202",
    "sg:city":"Phoenix",
    "sg:classifiers":[
        {
            "category":"Professional",
            "subcategory":"Advertising",
            "type":"Services"
        },
        {
            "category":"Manufacturing",
            "subcategory":"Petroleum Products",
            "type":"Manufacturing & Wholesale Goods"
        },
        {
            "category":"Manufacturing",
            "subcategory":"Signs",
            "type":"Manufacturing & Wholesale Goods"
        }
    ],
    "sg:phone":"+1 602 889 7330",
    "sg:postcode":"85017",
    "sg:province":"AZ",
    "sg:tags":[
        "specialty",
        "contract"
    ],
    "wof:name":"Rss Industries",
    "wof:placetype":"venue"
},
  "geometry": {"coordinates":[-112.12678099999999,33.480431],"type":"Point"}
}