{
  "type": "Feature",
  "properties": {
    "iso:country":"US",
    "sg:address":"3224 S 40th St",
    "sg:city":"Phoenix",
    "sg:classifiers":[
        {
            "category":"Autos & Motor Vehicles",
            "subcategory":"Auto Supplies",
            "type":"Retail Goods"
        },
        {
            "category":"Wholesale",
            "subcategory":"Scrap",
            "type":"Manufacturing & Wholesale Goods"
        }
    ],
    "sg:phone":"+1 602 437 1222",
    "sg:postcode":"85040",
    "sg:province":"AZ",
    "sg:tags":[
        "wrecking",
        "automobile",
        "accessory",
        "part",
        "supplies-used",
        "truck",
        "rebuilt"
    ],
    "sg:website":"http://www.toyotasalvage.com",
    "wof:name":"Toyota Salvage",
    "wof:placetype":"venue"
},
  "geometry": {"coordinates":[-111.995435,33.417188],"type":"Point"}
}