{
  "type": "Feature",
  "properties": {
    "iso:country":"US",
    "sg:address":"1223 E Broadway Rd",
    "sg:city":"Tempe",
    "sg:classifiers":[
        {
            "category":"Banks & Credit Unions",
            "subcategory":"Bank",
            "type":"Services"
        }
    ],
    "sg:phone":"+1 480 222 9934",
    "sg:postcode":"85282",
    "sg:province":"AZ",
    "sg:tags":[
        "loan",
        "real estate"
    ],
    "wof:name":"Eagle First Mortgage",
    "wof:placetype":"venue"
},
  "geometry": {"coordinates":[-111.920214,33.407436],"type":"Point"}
}