{
  "type": "Feature",
  "properties": {
    "iso:country":"US",
    "sg:address":"10201 S 47th St",
    "sg:city":"Phoenix",
    "sg:classifiers":[
        {
            "category":"Social Services",
            "subcategory":"Adult Care",
            "type":"Services"
        }
    ],
    "sg:phone":"+1 480 753 5140",
    "sg:postcode":"85044",
    "sg:province":"AZ",
    "sg:tags":[
        "home",
        "group"
    ],
    "wof:name":"All About Kids Group Home LLC",
    "wof:placetype":"venue"
},
  "geometry": {"coordinates":[-111.98089,33.35346],"type":"Point"}
}