{
  "type": "Feature",
  "properties": {
    "iso:country":"US",
    "sg:address":"2644 Broken Arrow St",
    "sg:city":"Kingman",
    "sg:classifiers":[
        {
            "category":"Landmark",
            "subcategory":"Tourist Information",
            "type":"Public Place"
        },
        {
            "category":"Landmark",
            "subcategory":"Tourist Attraction",
            "type":"Public Place"
        }
    ],
    "sg:phone":"+1 928 681 4867",
    "sg:postcode":"86401",
    "sg:province":"AZ",
    "sg:tags":[
        "tour",
        "promoter",
        "tours-operators",
        "sightseeing"
    ],
    "wof:name":"Arizona Wildlife Outfitters",
    "wof:placetype":"venue"
},
  "geometry": {"coordinates":[-113.96627700000001,35.199713],"type":"Point"}
}