{
  "type": "Feature",
  "properties": {
    "addr:full":"73 N Sonoita Ave Nogales AZ 85621",
    "addr:housenumber":"73",
    "addr:postcode":"85621",
    "addr:street":"N Sonoita Ave",
    "iso:country":"US",
    "sg:address":"73 N Sonoita Ave",
    "sg:city":"Nogales",
    "sg:classifiers":[
        {
            "category":"Shopping",
            "subcategory":"Used Merchandise",
            "type":"Retail Goods"
        }
    ],
    "sg:phone":"+1 520 287 6666",
    "sg:postcode":"85621",
    "sg:province":"AZ",
    "sg:tags":[
        "pawnbroker"
    ],
    "wof:name":"Soto's Pawn Shop",
    "wof:placetype":"venue"
},
  "geometry": {"coordinates":[-110.942756,31.336188],"type":"Point"}
}