{
  "type": "Feature",
  "properties": {
    "iso:country":"US",
    "sg:address":"15455 N Greenway Hayden Loop",
    "sg:city":"Scottsdale",
    "sg:classifiers":[
        {
            "category":"Professional",
            "subcategory":"Printing & Photocopies",
            "type":"Services"
        }
    ],
    "sg:phone":"+1 480 948 1011",
    "sg:postcode":"85260",
    "sg:province":"AZ",
    "sg:tags":[
        "blueprinting"
    ],
    "wof:name":"Advanced Cadd Productions Inc",
    "wof:placetype":"venue"
},
  "geometry": {"coordinates":[-111.923803,33.625851],"type":"Point"}
}