{
  "type": "Feature",
  "properties": {
    "iso:country":"US",
    "sg:address":"330 Hound Dr",
    "sg:city":"Lake Havasu City",
    "sg:classifiers":[
        {
            "category":"Building & Trades",
            "subcategory":"Electrical",
            "type":"Services"
        }
    ],
    "sg:phone":"+1 928 453 9436",
    "sg:postcode":"86404",
    "sg:province":"AZ",
    "sg:tags":[
        "electrical",
        "contractor"
    ],
    "wof:name":"Mystic Electric Inc",
    "wof:placetype":"venue"
},
  "geometry": {"coordinates":[-114.296541,34.504829],"type":"Point"}
}