{
  "type": "Feature",
  "properties": {
    "iso:country":"US",
    "sg:address":"3225 W Ina Rd",
    "sg:city":"Tucson",
    "sg:classifiers":[
        {
            "category":"Shopping",
            "subcategory":"Computers & Home Electronics",
            "type":"Retail Goods"
        }
    ],
    "sg:phone":"+1 520 229 8730",
    "sg:postcode":"85741",
    "sg:province":"AZ",
    "sg:tags":[
        "software"
    ],
    "wof:name":"D'Mention Systems LLC",
    "wof:placetype":"venue"
},
  "geometry": {"coordinates":[-111.035159,32.33735],"type":"Point"}
}