{
  "type": "Feature",
  "properties": {
    "addr:full":"11805 S Fortuna Rd Yuma AZ 85367",
    "addr:housenumber":"11805",
    "addr:postcode":"85367",
    "addr:street":"S Fortuna Rd",
    "iso:country":"US",
    "sg:address":"11805 S Fortuna Rd",
    "sg:city":"Yuma",
    "sg:classifiers":[
        {
            "category":"Shopping",
            "subcategory":"Gifts & Souvenirs",
            "type":"Retail Goods"
        }
    ],
    "sg:phone":"+1 928 345 9511",
    "sg:postcode":"85367",
    "sg:province":"AZ",
    "wof:name":"Painted Pony",
    "wof:placetype":"venue"
},
  "geometry": {"coordinates":[-114.444047,32.65664],"type":"Point"}
}