{
  "type": "Feature",
  "properties": {
    "iso:country":"US",
    "sg:address":"1211 E Krista Way",
    "sg:city":"Tempe",
    "sg:classifiers":[
        {
            "category":"Education",
            "subcategory":"School",
            "type":"Public Place"
        }
    ],
    "sg:phone":"+1 480 820 1054",
    "sg:postcode":"85284",
    "sg:province":"AZ",
    "sg:tags":[
        "massage"
    ],
    "wof:name":"Healing Thru Balance & Ha",
    "wof:placetype":"venue"
},
  "geometry": {"coordinates":[-111.922346,33.3479],"type":"Point"}
}