{
  "type": "Feature",
  "properties": {
    "addr:full":"4355 W Indian School Rd Phoenix AZ 85031",
    "addr:housenumber":"4355",
    "addr:postcode":"85031",
    "addr:street":"W Indian School Rd",
    "iso:country":"US",
    "sg:address":"4355 W Indian School Rd",
    "sg:city":"Phoenix",
    "sg:classifiers":[
        {
            "category":"Real Estate",
            "subcategory":"Real Estate Agent",
            "type":"Services"
        }
    ],
    "sg:phone":"+1 602 272 2522",
    "sg:postcode":"85031",
    "sg:province":"AZ",
    "wof:name":"Maztec Realty",
    "wof:placetype":"venue"
},
  "geometry": {"coordinates":[-112.153336,33.494882],"type":"Point"}
}