{
  "type": "Feature",
  "properties": {
    "iso:country":"US",
    "sg:address":"10652 N 32nd St",
    "sg:city":"Phoenix",
    "sg:classifiers":[
        {
            "category":"Fast Food",
            "type":"Food & Drink"
        },
        {
            "category":"Restaurant",
            "type":"Food & Drink"
        }
    ],
    "sg:phone":"+1 602 867 8100",
    "sg:postcode":"85028",
    "sg:province":"AZ",
    "sg:tags":[
        "greek",
        "take"
    ],
    "wof:name":"Gyro House",
    "wof:placetype":"venue"
},
  "geometry": {"coordinates":[-112.01311800000001,33.583067],"type":"Point"}
}