{
  "type": "Feature",
  "properties": {
    "iso:country":"US",
    "sg:address":"3841 S Gilbert Rd Ste 108",
    "sg:city":"Gilbert",
    "sg:phone":"+1 480 821 1314",
    "sg:postcode":"85297",
    "sg:province":"AZ",
    "sg:website":"http://www.gamestop.com/",
    "wof:name":"Gamestop",
    "wof:placetype":"venue"
},
  "geometry": {"coordinates":[-111.78968,33.279829],"type":"Point"}
}