{
  "type": "Feature",
  "properties": {
    "addr:full":"20 S Dobson Rd Mesa AZ 85202",
    "addr:housenumber":"20",
    "addr:postcode":"85202",
    "addr:street":"S Dobson Rd",
    "iso:country":"US",
    "sg:address":"20 S Dobson Rd",
    "sg:city":"Mesa",
    "sg:classifiers":[
        {
            "category":"Banks & Credit Unions",
            "subcategory":"Bank",
            "type":"Services"
        }
    ],
    "sg:phone":"+1 480 898 7500",
    "sg:postcode":"85202",
    "sg:province":"AZ",
    "sg:tags":[
        "cashing",
        "check"
    ],
    "wof:name":"Buckeye Checksmart Collections",
    "wof:placetype":"venue"
},
  "geometry": {"coordinates":[-111.874578,33.41126],"type":"Point"}
}