{
  "type": "Feature",
  "properties": {
    "iso:country":"US",
    "sg:address":"13623 N Canterbury Dr",
    "sg:city":"Phoenix",
    "sg:classifiers":[
        {
            "category":"Real Estate",
            "subcategory":"Real Estate Operator",
            "type":"Services"
        }
    ],
    "sg:phone":"+1 602 942 9229",
    "sg:postcode":"85023",
    "sg:province":"AZ",
    "sg:tags":[
        "building",
        "nonresidential"
    ],
    "wof:name":"Railroad Properties LLC",
    "wof:placetype":"venue"
},
  "geometry": {"coordinates":[-112.074443,33.609671],"type":"Point"}
}