{
  "type": "Feature",
  "properties": {
    "iso:country":"US",
    "sg:address":"6833 W Willis Rd Ste 5050",
    "sg:city":"Chandler",
    "sg:classifiers":[
        {
            "category":"Manufacturing",
            "subcategory":"Metals",
            "type":"Manufacturing & Wholesale Goods"
        }
    ],
    "sg:phone":"+1 520 796 1098",
    "sg:postcode":"85226",
    "sg:province":"AZ",
    "sg:tags":[
        "rolling",
        "forming"
    ],
    "wof:name":"Pimalco, Inc.",
    "wof:placetype":"venue"
},
  "geometry": {"coordinates":[-111.956191,33.284542],"type":"Point"}
}