{
  "type": "Feature",
  "properties": {
    "iso:country":"US",
    "sg:address":"6217 E Carolina Dr",
    "sg:city":"Scottsdale",
    "sg:classifiers":[
        {
            "category":"Shopping",
            "subcategory":"Used Merchandise",
            "type":"Retail Goods"
        }
    ],
    "sg:phone":"+1 480 443 0508",
    "sg:postcode":"85254",
    "sg:province":"AZ",
    "wof:name":"Amber Waves Antiques",
    "wof:placetype":"venue"
},
  "geometry": {"coordinates":[-111.945566,33.629153],"type":"Point"}
}