{
  "type": "Feature",
  "properties": {
    "addr:full":"1951 E AZ-69 Prescott AZ 86301",
    "addr:housenumber":"1951",
    "addr:postcode":"86301",
    "addr:street":"E Az-69",
    "iso:country":"US",
    "sg:address":"1951 E AZ-69",
    "sg:city":"Prescott",
    "sg:classifiers":[
        {
            "category":"Restaurant",
            "type":"Food & Drink"
        }
    ],
    "sg:menulink":"http://www.allmenus.com/az/prescott/97882-outback-steakhouse/menu/",
    "sg:phone":"+1 928 541 0100",
    "sg:postcode":"86301",
    "sg:province":"AZ",
    "sg:tags":[
        "american",
        "steakhouse"
    ],
    "wof:name":"Outback Steakhouse",
    "wof:placetype":"venue"
},
  "geometry": {"coordinates":[-112.42482200000001,34.552909],"type":"Point"}
}