{
  "type": "Feature",
  "properties": {
    "addr:full":"2040 W Camelback Rd Phoenix AZ 85015",
    "addr:housenumber":"2040",
    "addr:postcode":"85015",
    "addr:street":"W Camelback Rd",
    "iso:country":"US",
    "sg:address":"2040 W Camelback Rd",
    "sg:city":"Phoenix",
    "sg:classifiers":[
        {
            "category":"Wholesale",
            "subcategory":"Stationery",
            "type":"Manufacturing & Wholesale Goods"
        }
    ],
    "sg:phone":"+1 602 336 0455",
    "sg:postcode":"85015",
    "sg:province":"AZ",
    "sg:tags":[
        "business",
        "form",
        "system"
    ],
    "wof:name":"Geis Business Printing",
    "wof:placetype":"venue"
},
  "geometry": {"coordinates":[-112.103588,33.509656],"type":"Point"}
}