{
  "type": "Feature",
  "properties": {
    "iso:country":"US",
    "sg:address":"7721 E Gray Rd",
    "sg:city":"Scottsdale",
    "sg:classifiers":[
        {
            "category":"Building & Trades",
            "subcategory":"Construction",
            "type":"Services"
        }
    ],
    "sg:phone":"+1 480 315 0678",
    "sg:postcode":"85260",
    "sg:province":"AZ",
    "sg:tags":[
        "masonry",
        "contractor"
    ],
    "wof:name":"Dale Gray & Assoc",
    "wof:placetype":"venue"
},
  "geometry": {"coordinates":[-111.91236600000001,33.612381],"type":"Point"}
}