{
  "type": "Feature",
  "properties": {
    "iso:country":"US",
    "sg:address":"4831 N 35th Ave",
    "sg:city":"Phoenix",
    "sg:classifiers":[
        {
            "category":"Building & Trades",
            "subcategory":"Construction",
            "type":"Services"
        }
    ],
    "sg:phone":"+1 602 973 8612",
    "sg:postcode":"85017",
    "sg:province":"AZ",
    "sg:tags":[
        "home",
        "builder",
        "residential"
    ],
    "wof:name":"J & J General Contractors",
    "wof:placetype":"venue"
},
  "geometry": {"coordinates":[-112.134119,33.508883],"type":"Point"}
}