{
  "type": "Feature",
  "properties": {
    "iso:country":"US",
    "sg:address":"12 S Tegner St",
    "sg:city":"Wickenburg",
    "sg:classifiers":[
        {
            "category":"Retail",
            "subcategory":"Auto Repair",
            "type":"Services"
        }
    ],
    "sg:phone":"+1 928 684 7862",
    "sg:postcode":"85390",
    "sg:province":"AZ",
    "sg:tags":[
        "repairing",
        "automobile"
    ],
    "wof:name":"Craig Motor Crafts",
    "wof:placetype":"venue"
},
  "geometry": {"coordinates":[-112.729999,33.968762],"type":"Point"}
}