{
  "type": "Feature",
  "properties": {
    "addr:full":"2921 S Eastview Ave Tucson AZ 85730",
    "addr:housenumber":"2921",
    "addr:postcode":"85730",
    "addr:street":"S Eastview Ave",
    "iso:country":"US",
    "sg:address":"2921 S Eastview Ave",
    "sg:city":"Tucson",
    "sg:classifiers":[
        {
            "category":"Shopping",
            "subcategory":"Clothing, Apparel, & Fashions",
            "type":"Retail Goods"
        }
    ],
    "sg:phone":"+1 520 298 5280",
    "sg:postcode":"85730",
    "sg:province":"AZ",
    "sg:tags":[
        "family"
    ],
    "wof:name":"Ro Ros",
    "wof:placetype":"venue"
},
  "geometry": {"coordinates":[-110.790719,32.18718],"type":"Point"}
}