{
  "type": "Feature",
  "properties": {
    "addr:full":"672 S 10th Ave Yuma AZ 85364",
    "addr:housenumber":"672",
    "addr:postcode":"85364",
    "addr:street":"S 10Th Ave",
    "iso:country":"US",
    "sg:address":"672 S 10th Ave",
    "sg:city":"Yuma",
    "sg:classifiers":[
        {
            "category":"Wholesale",
            "subcategory":"Durable Goods & Equipment",
            "type":"Manufacturing & Wholesale Goods"
        }
    ],
    "sg:phone":"+1 928 539 0219",
    "sg:postcode":"85364",
    "sg:province":"AZ",
    "sg:tags":[
        "sporting"
    ],
    "wof:name":"Gila River Gunworks",
    "wof:placetype":"venue"
},
  "geometry": {"coordinates":[-114.63206099999999,32.715597],"type":"Point"}
}