{
  "type": "Feature",
  "properties": {
    "iso:country":"US",
    "sg:address":"2095 N Alma School Rd",
    "sg:city":"Chandler",
    "sg:classifiers":[
        {
            "category":"Food & Beverages",
            "subcategory":"Bakery",
            "type":"Retail Goods"
        }
    ],
    "sg:phone":"+1 480 899 0909",
    "sg:postcode":"85224",
    "sg:province":"AZ",
    "sg:tags":[
        "sandwich"
    ],
    "wof:name":"Subway Sandwich",
    "wof:placetype":"venue"
},
  "geometry": {"coordinates":[-111.859032,33.336897],"type":"Point"}
}