{
  "type": "Feature",
  "properties": {
    "iso:country":"US",
    "sg:address":"18001 N 79th Ave",
    "sg:city":"Glendale",
    "sg:classifiers":[
        {
            "category":"Real Estate",
            "subcategory":"Real Estate Services",
            "type":"Services"
        }
    ],
    "sg:phone":"+1 623 486 5626",
    "sg:postcode":"85308",
    "sg:province":"AZ",
    "sg:tags":[
        "company",
        "title"
    ],
    "wof:name":"Land America Commonwealth",
    "wof:placetype":"venue"
},
  "geometry": {"coordinates":[-112.22986299999999,33.647133],"type":"Point"}
}