{
  "type": "Feature",
  "properties": {
    "iso:country":"US",
    "sg:address":"7074 E Golf Links Rd",
    "sg:city":"Tucson",
    "sg:classifiers":[
        {
            "category":"Restaurant",
            "type":"Food & Drink"
        }
    ],
    "sg:phone":"+1 520 747 9027",
    "sg:postcode":"85730",
    "sg:province":"AZ",
    "sg:tags":[
        "eating"
    ],
    "wof:name":"Los Jilbertos Restaurant",
    "wof:placetype":"venue"
},
  "geometry": {"coordinates":[-110.843029,32.191871],"type":"Point"}
}