{
  "type": "Feature",
  "properties": {
    "iso:country":"US",
    "sg:address":"2615 N Walnut Creek Dr",
    "sg:city":"Flagstaff",
    "sg:classifiers":[
        {
            "category":"Real Estate",
            "subcategory":"Real Estate Agent",
            "type":"Services"
        }
    ],
    "sg:phone":"+1 928 226 6968",
    "sg:postcode":"86004",
    "sg:province":"AZ",
    "wof:name":"Century 21 Metro Alliance",
    "wof:placetype":"venue"
},
  "geometry": {"coordinates":[-111.562693,35.197234],"type":"Point"}
}