{
  "type": "Feature",
  "properties": {
    "addr:full":"10455 N Cam de la Tierra Tucson AZ 85742",
    "addr:housenumber":"10455",
    "addr:postcode":"85742",
    "addr:street":"N Cam De La Tierra",
    "iso:country":"US",
    "sg:address":"10455 N Cam de la Tierra",
    "sg:city":"Tucson",
    "sg:classifiers":[
        {
            "category":"Home & Garden",
            "subcategory":"Hardware",
            "type":"Retail Goods"
        }
    ],
    "sg:phone":"+1 520 579 9100",
    "sg:postcode":"85742",
    "sg:province":"AZ",
    "sg:tags":[
        "tool",
        "used"
    ],
    "wof:name":"L R Tools Inc",
    "wof:placetype":"venue"
},
  "geometry": {"coordinates":[-111.038476,32.396151],"type":"Point"}
}