{
  "type": "Feature",
  "properties": {
    "iso:country":"US",
    "sg:address":"350 N Dawn Ave",
    "sg:city":"Tucson",
    "sg:classifiers":[
        {
            "category":"Building & Trades",
            "subcategory":"Construction",
            "type":"Services"
        }
    ],
    "sg:phone":"+1 520 751 4527",
    "sg:postcode":"85710",
    "sg:province":"AZ",
    "sg:tags":[
        "home",
        "improvement"
    ],
    "wof:name":"Complete Home Maintenance",
    "wof:placetype":"venue"
},
  "geometry": {"coordinates":[-110.80247799999999,32.225027],"type":"Point"}
}