{
  "type": "Feature",
  "properties": {
    "iso:country":"US",
    "sg:address":"16701 N Oracle Rd",
    "sg:city":"Tucson",
    "sg:classifiers":[
        {
            "category":"Social Services",
            "type":"Services"
        }
    ],
    "sg:phone":"+1 520 825 4120",
    "sg:postcode":"85739",
    "sg:province":"AZ",
    "sg:tags":[
        "senior",
        "citizen"
    ],
    "wof:name":"Senior Program Ctr",
    "wof:placetype":"venue"
},
  "geometry": {"coordinates":[-110.925865,32.509071],"type":"Point"}
}