{
  "type": "Feature",
  "properties": {
    "iso:country":"US",
    "sg:address":"802 S 51st Ave",
    "sg:city":"Phoenix",
    "sg:classifiers":[
        {
            "category":"Autos & Motor Vehicles",
            "subcategory":"Auto Supplies",
            "type":"Retail Goods"
        },
        {
            "category":"Wholesale",
            "subcategory":"Electrical",
            "type":"Manufacturing & Wholesale Goods"
        },
        {
            "category":"Wholesale",
            "subcategory":"Auto Parts",
            "type":"Manufacturing & Wholesale Goods"
        }
    ],
    "sg:phone":"+1 602 282 1298",
    "sg:postcode":"85043",
    "sg:province":"AZ",
    "sg:tags":[
        "battery",
        "automobile",
        "accessory",
        "equipment",
        "truck",
        "engines-supplies"
    ],
    "sg:website":"http://ad.doubleclick.net/clk;221862232;45455595;j?http://www.carquest.com/carquest/store_locator.html",
    "wof:name":"CARQUEST Auto Parts",
    "wof:placetype":"venue"
},
  "geometry": {"coordinates":[-112.16922,33.438908],"type":"Point"}
}