{
  "type": "Feature",
  "properties": {
    "addr:full":"5014 S Price Road Tempe AZ 85282",
    "addr:housenumber":"5014",
    "addr:postcode":"85282",
    "addr:street":"S Price Road",
    "iso:country":"US",
    "sg:address":"5014 S Price Road",
    "sg:city":"Tempe",
    "sg:classifiers":[
        {
            "category":"Bars & Pubs",
            "subcategory":"Nightclub",
            "type":"Food & Drink"
        }
    ],
    "sg:phone":"+1 480 897 1466",
    "sg:postcode":"85282",
    "sg:province":"AZ",
    "sg:tags":[
        "nightlife"
    ],
    "wof:name":"Real",
    "wof:placetype":"venue"
},
  "geometry": {"coordinates":[-111.893443,33.380004],"type":"Point"}
}