{
  "type": "Feature",
  "properties": {
    "iso:country":"US",
    "sg:address":"502 S Dobson Rd",
    "sg:city":"Mesa",
    "sg:classifiers":[
        {
            "category":"Restaurant",
            "type":"Food & Drink"
        }
    ],
    "sg:phone":"+1 480 898 7348",
    "sg:postcode":"85202",
    "sg:province":"AZ",
    "wof:name":"Hoang Huong Fast Food",
    "wof:placetype":"venue"
},
  "geometry": {"coordinates":[-111.874562,33.404617],"type":"Point"}
}