{
  "type": "Feature",
  "properties": {
    "addr:full":"1820 N Oracle Rd Tucson AZ 85705",
    "addr:housenumber":"1820",
    "addr:postcode":"85705",
    "addr:street":"N Oracle Rd",
    "iso:country":"US",
    "sg:address":"1820 N Oracle Rd",
    "sg:city":"Tucson",
    "sg:classifiers":[
        {
            "category":"Food & Beverages",
            "subcategory":"Liquor & Beverages",
            "type":"Retail Goods"
        }
    ],
    "sg:phone":"+1 520 620 6251",
    "sg:postcode":"85705",
    "sg:province":"AZ",
    "wof:name":"Lamp Post Liquors",
    "wof:placetype":"venue"
},
  "geometry": {"coordinates":[-110.97792699999999,32.244637],"type":"Point"}
}