{
  "type": "Feature",
  "properties": {
    "iso:country":"US",
    "sg:address":"8013 E Knoll St",
    "sg:city":"Mesa",
    "sg:classifiers":[
        {
            "category":"Manufacturing",
            "subcategory":"Apparel",
            "type":"Manufacturing & Wholesale Goods"
        }
    ],
    "sg:phone":"+1 480 844 1570",
    "sg:postcode":"85207",
    "sg:province":"AZ",
    "sg:tags":[
        "household",
        "furnishing",
        "mfg"
    ],
    "wof:name":"Drf Creations",
    "wof:placetype":"venue"
},
  "geometry": {"coordinates":[-111.65801999999999,33.452081],"type":"Point"}
}