{
  "type": "Feature",
  "properties": {
    "addr:full":"1314 W 11th St Parker AZ 85344",
    "addr:housenumber":"1314",
    "addr:postcode":"az 85344",
    "addr:street":"W 11Th St",
    "iso:country":"US",
    "sg:address":"1314 W 11th St",
    "sg:city":"Parker",
    "sg:classifiers":[
        {
            "category":"Wholesale",
            "subcategory":"Durable Goods & Equipment",
            "type":"Manufacturing & Wholesale Goods"
        }
    ],
    "sg:phone":"+1 928 669 8477",
    "sg:postcode":"85344",
    "sg:province":"AZ",
    "sg:tags":[
        "professional"
    ],
    "wof:name":"Crime Stoppers",
    "wof:placetype":"venue"
},
  "geometry": {"coordinates":[-114.29363600000001,34.147283],"type":"Point"}
}