{
  "type": "Feature",
  "properties": {
    "iso:country":"US",
    "sg:address":"4500 E Main St",
    "sg:city":"Mesa",
    "sg:classifiers":[
        {
            "category":"Restaurant",
            "type":"Food & Drink"
        }
    ],
    "sg:menulink":"http://www.allmenus.com/az/phoenix/2479-waldos-authentic-western-bbq/menu/",
    "sg:phone":"+1 480 807 6475",
    "sg:postcode":"85205",
    "sg:province":"AZ",
    "sg:tags":[
        "american"
    ],
    "wof:name":"Waldo's Authentic Western BBQ",
    "wof:placetype":"venue"
},
  "geometry": {"coordinates":[-111.735038,33.415515],"type":"Point"}
}