{
  "type": "Feature",
  "properties": {
    "iso:country":"US",
    "sg:address":"9180 E Walnut Tree Dr",
    "sg:city":"Tucson",
    "sg:classifiers":[
        {
            "category":"Building & Trades",
            "subcategory":"Plumbing",
            "type":"Services"
        }
    ],
    "sg:phone":"+1 520 760 8536",
    "sg:postcode":"85749",
    "sg:province":"AZ",
    "sg:tags":[
        "system",
        "contractor",
        "air conditioning"
    ],
    "wof:name":"Air Comercial & Residential",
    "wof:placetype":"venue"
},
  "geometry": {"coordinates":[-110.79589300000001,32.290874],"type":"Point"}
}