{
  "type": "Feature",
  "properties": {
    "iso:country":"US",
    "sg:address":"799 S Arizona Ave",
    "sg:city":"Chandler",
    "sg:classifiers":[
        {
            "category":"Retail",
            "subcategory":"Auto Repair",
            "type":"Services"
        }
    ],
    "sg:phone":"+1 480 963 6921",
    "sg:postcode":"85225",
    "sg:province":"AZ",
    "sg:tags":[
        "repairing",
        "automobile"
    ],
    "sg:website":"www.elcaminoinc.com",
    "wof:name":"El Camino Svc",
    "wof:placetype":"venue"
},
  "geometry": {"coordinates":[-111.841576,33.292556],"type":"Point"}
}