{
  "type": "Feature",
  "properties": {
    "iso:country":"US",
    "sg:address":"106 W Hatcher Rd",
    "sg:city":"Phoenix",
    "sg:classifiers":[
        {
            "category":"Building & Trades",
            "subcategory":"Construction",
            "type":"Services"
        }
    ],
    "sg:phone":"+1 602 357 8935",
    "sg:postcode":"85021",
    "sg:province":"AZ",
    "sg:tags":[
        "paint",
        "painting",
        "removing",
        "painter",
        "contractor"
    ],
    "sg:website":"http://www.ineedcolor.com",
    "wof:name":"CBP of Arizona Inc",
    "wof:placetype":"venue"
},
  "geometry": {"coordinates":[-112.07602,33.571321],"type":"Point"}
}