{
  "type": "Feature",
  "properties": {
    "iso:country":"US",
    "sg:address":"9018 E Caribbean Ln",
    "sg:city":"Scottsdale",
    "sg:classifiers":[
        {
            "category":"Professional",
            "type":"Services"
        }
    ],
    "sg:phone":"+1 480 451 6743",
    "sg:postcode":"85260",
    "sg:province":"AZ",
    "wof:name":"Mayhem Inc",
    "wof:placetype":"venue"
},
  "geometry": {"coordinates":[-111.885769,33.625788],"type":"Point"}
}