{
  "type": "Feature",
  "properties": {
    "iso:country":"US",
    "sg:address":"100 Birch Blvd",
    "sg:city":"Sedona",
    "sg:classifiers":[
        {
            "category":"Wholesale",
            "subcategory":"Construction Materials",
            "type":"Manufacturing & Wholesale Goods"
        }
    ],
    "sg:phone":"+1 928 282 1916",
    "sg:postcode":"86336",
    "sg:province":"AZ",
    "wof:name":"Sunbelt Mobile Homes",
    "wof:placetype":"venue"
},
  "geometry": {"coordinates":[-111.786682,34.861538],"type":"Point"}
}