{
  "type": "Feature",
  "properties": {
    "addr:full":"2300 W Willow Breeze Rd Chino Valley AZ 86323",
    "addr:housenumber":"2300",
    "addr:postcode":"86323",
    "addr:street":"W Willow Breeze Rd",
    "iso:country":"US",
    "sg:address":"2300 W Willow Breeze Rd",
    "sg:city":"Chino Valley",
    "sg:classifiers":[
        {
            "category":"Farming",
            "subcategory":"Poultry Farm",
            "type":"Manufacturing & Wholesale Goods"
        }
    ],
    "sg:phone":"+1 928 636 9366",
    "sg:postcode":"86323",
    "sg:province":"AZ",
    "sg:tags":[
        "egg"
    ],
    "wof:name":"Northland Game Bird Farm",
    "wof:placetype":"venue"
},
  "geometry": {"coordinates":[-112.491523,34.734558],"type":"Point"}
}