{
  "type": "Feature",
  "properties": {
    "iso:country":"US",
    "sg:address":"9181 E Bell Rd",
    "sg:city":"Scottsdale",
    "sg:classifiers":[
        {
            "category":"Professional",
            "type":"Services"
        },
        {
            "category":"Home & Garden",
            "subcategory":"Home Furnishings",
            "type":"Retail Goods"
        }
    ],
    "sg:phone":"+1 480 538 8353",
    "sg:postcode":"85260",
    "sg:province":"AZ",
    "sg:tags":[
        "pottery"
    ],
    "wof:name":"M Pots",
    "wof:placetype":"venue"
},
  "geometry": {"coordinates":[-111.883448,33.63996],"type":"Point"}
}