{
  "type": "Feature",
  "properties": {
    "iso:country":"US",
    "sg:address":"911 Lake Havasu Ave N",
    "sg:city":"Lake Havasu City",
    "sg:classifiers":[
        {
            "category":"Manufacturing",
            "subcategory":"Motor Vehicles & Parts",
            "type":"Manufacturing & Wholesale Goods"
        }
    ],
    "sg:phone":"+1 928 505 1160",
    "sg:postcode":"86403",
    "sg:province":"AZ",
    "sg:tags":[
        "mfg"
    ],
    "wof:name":"Force Motor Products",
    "wof:placetype":"venue"
},
  "geometry": {"coordinates":[-114.348026,34.501279],"type":"Point"}
}