{
  "type": "Feature",
  "properties": {
    "iso:country":"US",
    "sg:address":"7816 N 19th Ave",
    "sg:city":"Phoenix",
    "sg:classifiers":[
        {
            "category":"Banks & Credit Unions",
            "subcategory":"Bank",
            "type":"Services"
        }
    ],
    "sg:phone":"+1 602 249 0101",
    "sg:postcode":"85021",
    "sg:province":"AZ",
    "sg:tags":[
        "loan",
        "real estate"
    ],
    "wof:name":"Concord Mortgage",
    "wof:placetype":"venue"
},
  "geometry": {"coordinates":[-112.099729,33.549987],"type":"Point"}
}