{
  "type": "Feature",
  "properties": {
    "iso:country":"US",
    "sg:address":"14227 W Shawnee Trl",
    "sg:city":"Surprise",
    "sg:classifiers":[
        {
            "category":"Social Services",
            "subcategory":"Job Training",
            "type":"Services"
        }
    ],
    "sg:phone":"+1 623 584 6992",
    "sg:postcode":"85374",
    "sg:province":"AZ",
    "sg:tags":[
        "sale"
    ],
    "sg:website":"http://www.championseed.com",
    "wof:name":"Champion Seed Company",
    "wof:placetype":"venue"
},
  "geometry": {"coordinates":[-112.366446,33.645092],"type":"Point"}
}