{
  "type": "Feature",
  "properties": {
    "addr:full":"65 N Grand Ave Nogales AZ 85621",
    "addr:housenumber":"65",
    "addr:postcode":"85621",
    "addr:street":"N Grand Ave",
    "iso:country":"US",
    "sg:address":"65 N Grand Ave",
    "sg:city":"Nogales",
    "sg:classifiers":[
        {
            "category":"Shopping",
            "subcategory":"Shoes",
            "type":"Retail Goods"
        }
    ],
    "sg:phone":"+1 520 287 6010",
    "sg:postcode":"85621",
    "sg:province":"AZ",
    "wof:name":"Livius Footwear",
    "wof:placetype":"venue"
},
  "geometry": {"coordinates":[-110.94060899999999,31.335787],"type":"Point"}
}