{
  "type": "Feature",
  "properties": {
    "addr:full":"4435 N 78th St Scottsdale AZ 85251",
    "addr:housenumber":"4435",
    "addr:postcode":"85251",
    "addr:street":"N 78Th St",
    "iso:country":"US",
    "sg:address":"4435 N 78th St",
    "sg:city":"Scottsdale",
    "sg:classifiers":[
        {
            "category":"Building & Trades",
            "subcategory":"Construction",
            "type":"Services"
        }
    ],
    "sg:phone":"+1 480 671 9246",
    "sg:postcode":"85251",
    "sg:province":"AZ",
    "wof:name":"Cashel Properties LLC",
    "wof:placetype":"venue"
},
  "geometry": {"coordinates":[-111.913095,33.500633],"type":"Point"}
}