{
  "type": "Feature",
  "properties": {
    "iso:country":"US",
    "sg:address":"7850 N Oracle Rd",
    "sg:city":"Tucson",
    "sg:classifiers":[
        {
            "category":"Restaurant",
            "type":"Food & Drink"
        }
    ],
    "sg:phone":"+1 520 544 7970",
    "sg:postcode":"85704",
    "sg:province":"AZ",
    "sg:website":"http://www.picazzos.com",
    "wof:name":"Picazzos Gourmet Pizza, Salads & Pasta",
    "wof:placetype":"venue"
},
  "geometry": {"coordinates":[-110.975314,32.349326],"type":"Point"}
}