{
  "type": "Feature",
  "properties": {
    "iso:country":"US",
    "sg:address":"2760 E Inverness Ave",
    "sg:city":"Mesa",
    "sg:classifiers":[
        {
            "category":"Autos & Motor Vehicles",
            "subcategory":"Auto Supplies",
            "type":"Retail Goods"
        }
    ],
    "sg:phone":"+1 480 641 1387",
    "sg:postcode":"85204",
    "sg:province":"AZ",
    "sg:tags":[
        "automobile",
        "parts"
    ],
    "wof:name":"Rick's Pick-Up Parts",
    "wof:placetype":"venue"
},
  "geometry": {"coordinates":[-111.771596,33.382833],"type":"Point"}
}