{
  "type": "Feature",
  "properties": {
    "iso:country":"US",
    "sg:address":"4335 W Glendale Ave",
    "sg:city":"Glendale",
    "sg:classifiers":[
        {
            "category":"Shopping",
            "subcategory":"Jewelry",
            "type":"Retail Goods"
        }
    ],
    "sg:phone":"+1 623 435 1707",
    "sg:postcode":"85301",
    "sg:province":"AZ",
    "sg:tags":[
        "jeweler"
    ],
    "wof:name":"Corals Joyeria",
    "wof:placetype":"venue"
},
  "geometry": {"coordinates":[-112.155233,33.538371],"type":"Point"}
}