{
  "type": "Feature",
  "properties": {
    "iso:country":"US",
    "sg:address":"3752 W Shannon St",
    "sg:city":"Chandler",
    "sg:classifiers":[
        {
            "category":"Professional",
            "type":"Services"
        }
    ],
    "sg:phone":"+1 480 855 9222",
    "sg:postcode":"85226",
    "sg:province":"AZ",
    "wof:name":"Gag Inc",
    "wof:placetype":"venue"
},
  "geometry": {"coordinates":[-111.906232,33.318697],"type":"Point"}
}