{
  "type": "Feature",
  "properties": {
    "iso:country":"US",
    "sg:address":"7201 E Cave Creek Rd",
    "sg:city":"Cave Creek",
    "sg:classifiers":[
        {
            "category":"Autos & Motor Vehicles",
            "subcategory":"Fuel & Gas Station",
            "type":"Retail Goods"
        }
    ],
    "sg:phone":"+1 480 488 3451",
    "sg:postcode":"85331",
    "sg:province":"AZ",
    "sg:tags":[
        "oil"
    ],
    "wof:name":"Carefree Shell",
    "wof:placetype":"venue"
},
  "geometry": {"coordinates":[-111.918081,33.822305],"type":"Point"}
}