{
  "type": "Feature",
  "properties": {
    "addr:full":"1400 S Mcclintock Dr Suite # 11 Tempe AZ 85281",
    "addr:housenumber":"1400",
    "addr:postcode":"85281",
    "addr:street":"S Mcclintock Dr Suite # 11",
    "iso:country":"US",
    "sg:address":"1400 S Mcclintock Dr Suite # 11",
    "sg:city":"Tempe",
    "sg:classifiers":[
        {
            "category":"Shopping",
            "subcategory":"Beauty & Cosmetics",
            "type":"Retail Goods"
        },
        {
            "category":"Personal",
            "subcategory":"Beauty Salon",
            "type":"Services"
        }
    ],
    "sg:phone":"+1 480 829 7893",
    "sg:postcode":"85281",
    "sg:province":"AZ",
    "sg:tags":[
        "wig",
        "hair",
        "piece",
        "perfume"
    ],
    "wof:name":"Shades of Africa Salon & Boutique",
    "wof:placetype":"venue"
},
  "geometry": {"coordinates":[-111.90911800000001,33.4132],"type":"Point"}
}