{
  "type": "Feature",
  "properties": {
    "addr:full":"212 W Pima St Gila Bend AZ 85337",
    "addr:housenumber":"212",
    "addr:postcode":"85337",
    "addr:street":"W Pima St",
    "iso:country":"US",
    "sg:address":"212 W Pima St",
    "sg:city":"Gila Bend",
    "sg:classifiers":[
        {
            "category":"Travel",
            "subcategory":"Hotels & Motels",
            "type":"Entertainment"
        }
    ],
    "sg:phone":"+1 928 683 2281",
    "sg:postcode":"85337",
    "sg:province":"AZ",
    "wof:name":"El Coronado Motel",
    "wof:placetype":"venue"
},
  "geometry": {"coordinates":[-112.719205,32.946948],"type":"Point"}
}