{
  "type": "Feature",
  "properties": {
    "iso:country":"US",
    "sg:address":"777 E Macarthur Cir",
    "sg:city":"Tucson",
    "sg:classifiers":[
        {
            "category":"Manufacturing",
            "subcategory":"Retail Goods",
            "type":"Manufacturing & Wholesale Goods"
        }
    ],
    "sg:phone":"+1 520 618 4302",
    "sg:postcode":"85714",
    "sg:province":"AZ",
    "sg:tags":[
        "manufacturer"
    ],
    "wof:name":"Namco Manufacturing",
    "wof:placetype":"venue"
},
  "geometry": {"coordinates":[-110.958889,32.168592],"type":"Point"}
}