{
  "type": "Feature",
  "properties": {
    "iso:country":"US",
    "sg:address":"501 Wrangler Way",
    "sg:city":"Dewey",
    "sg:classifiers":[
        {
            "category":"Manufacturing",
            "subcategory":"Paper Products",
            "type":"Manufacturing & Wholesale Goods"
        }
    ],
    "sg:phone":"+1 928 775 2527",
    "sg:postcode":"86327",
    "sg:province":"AZ",
    "sg:tags":[
        "die",
        "mfg"
    ],
    "wof:name":"Images By Lloyd",
    "wof:placetype":"venue"
},
  "geometry": {"coordinates":[-112.257362,34.550364],"type":"Point"}
}