{
  "type": "Feature",
  "properties": {
    "addr:full":"4620 S Coach Dr Tucson AZ 85714",
    "addr:housenumber":"4620",
    "addr:postcode":"85714",
    "addr:street":"S Coach Dr",
    "iso:country":"US",
    "sg:address":"4620 S Coach Dr",
    "sg:city":"Tucson",
    "sg:classifiers":[
        {
            "category":"Building & Trades",
            "subcategory":"Construction",
            "type":"Services"
        }
    ],
    "sg:phone":"+1 520 790 2229",
    "sg:postcode":"85714",
    "sg:province":"AZ",
    "sg:tags":[
        "marine"
    ],
    "wof:name":"Ballast Technologies Inc",
    "wof:placetype":"venue"
},
  "geometry": {"coordinates":[-110.91375499999999,32.167247],"type":"Point"}
}