{
  "type": "Feature",
  "properties": {
    "iso:country":"US",
    "sg:address":"15814 N 83rd Ave",
    "sg:city":"Peoria",
    "sg:classifiers":[
        {
            "category":"Bars & Pubs",
            "type":"Food & Drink"
        },
        {
            "category":"Restaurant",
            "type":"Food & Drink"
        },
        {
            "category":"Bars & Pubs",
            "subcategory":"Sports Bar",
            "type":"Food & Drink"
        }
    ],
    "sg:phone":"+1 623 334 5000",
    "sg:postcode":"85382",
    "sg:province":"AZ",
    "sg:tags":[
        "brew"
    ],
    "wof:name":"McDuffys Peoria",
    "wof:placetype":"venue"
},
  "geometry": {"coordinates":[-112.237511,33.62867],"type":"Point"}
}