{
  "type": "Feature",
  "properties": {
    "iso:country":"US",
    "sg:address":"711 E Florence Blvd",
    "sg:city":"Casa Grande",
    "sg:classifiers":[
        {
            "category":"Manufacturing",
            "subcategory":"Building Materials",
            "type":"Manufacturing & Wholesale Goods"
        }
    ],
    "sg:phone":"+1 520 836 8590",
    "sg:postcode":"85222",
    "sg:province":"AZ",
    "sg:tags":[
        "mfg",
        "wood",
        "kitchen",
        "cabinet"
    ],
    "wof:name":"Chitwood Cabinet Tree",
    "wof:placetype":"venue"
},
  "geometry": {"coordinates":[-111.745323,32.879467],"type":"Point"}
}