{
  "type": "Feature",
  "properties": {
    "iso:country":"US",
    "sg:address":"1201 E Illinois St",
    "sg:city":"Tucson",
    "sg:classifiers":[
        {
            "category":"Building & Trades",
            "subcategory":"Plumbing",
            "type":"Services"
        }
    ],
    "sg:phone":"+1 520 807 7713",
    "sg:postcode":"85714",
    "sg:province":"AZ",
    "sg:tags":[
        "contractor"
    ],
    "wof:name":"Gallego Plumbing",
    "wof:placetype":"venue"
},
  "geometry": {"coordinates":[-110.953279,32.168451],"type":"Point"}
}