{
  "type": "Feature",
  "properties": {
    "addr:full":"820 Danita St Prescott AZ 86301",
    "addr:housenumber":"820",
    "addr:postcode":"86301",
    "addr:street":"Danita St",
    "iso:country":"US",
    "sg:address":"820 Danita St",
    "sg:city":"Prescott",
    "sg:classifiers":[
        {
            "category":"Manufacturing",
            "subcategory":"Tools & Machinery",
            "type":"Manufacturing & Wholesale Goods"
        }
    ],
    "sg:phone":"+1 928 776 7650",
    "sg:postcode":"86301",
    "sg:province":"AZ",
    "sg:tags":[
        "mfg"
    ],
    "wof:name":"Baldwin Supply",
    "wof:placetype":"venue"
},
  "geometry": {"coordinates":[-112.479595,34.564138],"type":"Point"}
}