{
  "type": "Feature",
  "properties": {
    "iso:country":"US",
    "sg:address":"3032 W Matthew Dr",
    "sg:city":"Phoenix",
    "sg:classifiers":[
        {
            "category":"Real Estate",
            "subcategory":"Real Estate Services",
            "type":"Services"
        },
        {
            "category":"Banks & Credit Unions",
            "subcategory":"Financial Services",
            "type":"Services"
        }
    ],
    "sg:phone":"+1 623 516 8915",
    "sg:postcode":"85027",
    "sg:province":"AZ",
    "sg:tags":[
        "loan",
        "processing"
    ],
    "wof:name":"Kitchen Table Loan Officer",
    "wof:placetype":"venue"
},
  "geometry": {"coordinates":[-112.124193,33.67725],"type":"Point"}
}