{
  "type": "Feature",
  "properties": {
    "addr:full":"3032 W Matthew Dr Phoenix AZ 85027",
    "addr:housenumber":"3032",
    "addr:postcode":"85027",
    "addr:street":"W Matthew Dr",
    "iso:country":"US",
    "sg:address":"3032 W Matthew Dr",
    "sg:city":"Phoenix",
    "sg:classifiers":[
        {
            "category":"Real Estate",
            "subcategory":"Real Estate Services",
            "type":"Services"
        },
        {
            "category":"Banks & Credit Unions",
            "subcategory":"Financial Services",
            "type":"Services"
        }
    ],
    "sg:phone":"+1 623 516 8915",
    "sg:postcode":"85027",
    "sg:province":"AZ",
    "sg:tags":[
        "loan",
        "processing"
    ],
    "wof:name":"Kitchen Table Loan Officer",
    "wof:placetype":"venue"
},
  "geometry": {"coordinates":[-112.12419300000001,33.67725],"type":"Point"}
}