{
  "type": "Feature",
  "properties": {
    "addr:full":"5522 W Roosevelt St Phoenix AZ 85043",
    "addr:housenumber":"5522",
    "addr:postcode":"85043",
    "addr:street":"W Roosevelt St",
    "iso:country":"US",
    "sg:address":"5522 W Roosevelt St",
    "sg:city":"Phoenix",
    "sg:classifiers":[
        {
            "category":"Freight",
            "type":"Transportation"
        }
    ],
    "sg:phone":"+1 602 278 4705",
    "sg:postcode":"85043",
    "sg:province":"AZ",
    "sg:tags":[
        "warehouse"
    ],
    "wof:name":"West Coast Distribution Center",
    "wof:placetype":"venue"
},
  "geometry": {"coordinates":[-112.17806899999999,33.458831],"type":"Point"}
}