{
  "type": "Feature",
  "properties": {
    "addr:full":"3940 N 33rd Ave Phoenix AZ 85017",
    "addr:housenumber":"3940",
    "addr:postcode":"85017",
    "addr:street":"N 33Rd Ave",
    "iso:country":"US",
    "sg:address":"3940 N 33rd Ave",
    "sg:city":"Phoenix",
    "sg:classifiers":[
        {
            "category":"Taxi",
            "type":"Transportation"
        },
        {
            "category":"Retail",
            "subcategory":"Auto Rental",
            "type":"Services"
        },
        {
            "category":"Airport",
            "type":"Transportation"
        }
    ],
    "sg:phone":"+1 602 299 3300",
    "sg:postcode":"85017",
    "sg:province":"AZ",
    "sg:tags":[
        "limousine"
    ],
    "sg:website":"http://www.royalqttaxi.com",
    "wof:name":"Royal Quick Trip Taxi",
    "wof:placetype":"venue"
},
  "geometry": {"coordinates":[-112.12997900000001,33.491594],"type":"Point"}
}