{
  "type": "Feature",
  "properties": {
    "iso:country":"US",
    "sg:address":"1241 E Broadway Rd",
    "sg:city":"Mesa",
    "sg:classifiers":[
        {
            "category":"Personal",
            "subcategory":"Beauty Salon",
            "type":"Services"
        }
    ],
    "sg:phone":"+1 480 844 1514",
    "sg:postcode":"85204",
    "sg:province":"AZ",
    "wof:name":"Knapps Hair Ctr",
    "wof:placetype":"venue"
},
  "geometry": {"coordinates":[-111.803634,33.407862],"type":"Point"}
}