{
  "type": "Feature",
  "properties": {
    "iso:country":"US",
    "sg:address":"9457 N 82nd St",
    "sg:city":"Scottsdale",
    "sg:classifiers":[
        {
            "category":"Travel",
            "subcategory":"Travel Agent",
            "type":"Entertainment"
        }
    ],
    "sg:phone":"+1 480 998 2532",
    "sg:postcode":"85258",
    "sg:province":"AZ",
    "sg:tags":[
        "agency"
    ],
    "wof:name":"Travel Connections",
    "wof:placetype":"venue"
},
  "geometry": {"coordinates":[-111.905835,33.572747],"type":"Point"}
}