{
  "type": "Feature",
  "properties": {
    "iso:country":"US",
    "sg:address":"10818 N Scottsdale Rd",
    "sg:city":"Scottsdale",
    "sg:classifiers":[
        {
            "category":"Shopping",
            "subcategory":"Hobbies, Toys, & Games",
            "type":"Retail Goods"
        },
        {
            "category":"Shopping",
            "subcategory":"Books",
            "type":"Retail Goods"
        },
        {
            "category":"Shopping",
            "subcategory":"Comic Books",
            "type":"Retail Goods"
        }
    ],
    "sg:phone":"+1 480 998 0606",
    "sg:postcode":"85254",
    "sg:province":"AZ",
    "sg:tags":[
        "dealers-used",
        "rare",
        "store",
        "supply"
    ],
    "sg:website":"http://www.bookmasteraz.com",
    "wof:name":"Bookmaster",
    "wof:placetype":"venue"
},
  "geometry": {"coordinates":[-111.926265,33.584445],"type":"Point"}
}