{
  "type": "Feature",
  "properties": {
    "iso:country":"US",
    "sg:address":"5012 E Van Buren St",
    "sg:city":"Phoenix",
    "sg:classifiers":[
        {
            "category":"Restaurant",
            "type":"Food & Drink"
        }
    ],
    "sg:menulink":"http://www.allmenus.com/az/phoenix/3941-honeybaked-ham/menu/",
    "sg:phone":"+1 602 273 9148",
    "sg:postcode":"85008",
    "sg:province":"AZ",
    "sg:tags":[
        "american"
    ],
    "wof:name":"The HoneyBaked Ham Company",
    "wof:placetype":"venue"
},
  "geometry": {"coordinates":[-111.973698,33.450902],"type":"Point"}
}