{
  "type": "Feature",
  "properties": {
    "addr:full":"4494 W Peoria Ave Ste 106 Glendale AZ 85302",
    "addr:housenumber":"4494",
    "addr:postcode":"85302",
    "addr:street":"W Peoria Ave Ste 106",
    "iso:country":"US",
    "sg:address":"4494 W Peoria Ave Ste 106",
    "sg:city":"Glendale",
    "sg:classifiers":[
        {
            "category":"Professional",
            "subcategory":"Advertising",
            "type":"Services"
        },
        {
            "category":"Professional",
            "subcategory":"Printing & Photocopies",
            "type":"Services"
        }
    ],
    "sg:phone":"+1 623 271 8311",
    "sg:postcode":"85302",
    "sg:province":"AZ",
    "sg:tags":[
        "engraving",
        "product",
        "agency",
        "trophies",
        "advertising-promotional",
        "medal",
        "plaque"
    ],
    "sg:website":"http://www.pimaawards.com",
    "wof:name":"Pima Awards & Promotional",
    "wof:placetype":"venue"
},
  "geometry": {"coordinates":[-112.155467,33.581921],"type":"Point"}
}