{
  "type": "Feature",
  "properties": {
    "iso:country":"US",
    "sg:address":"3361 E 36th St",
    "sg:city":"Tucson",
    "sg:classifiers":[
        {
            "category":"Home & Garden",
            "subcategory":"Building Materials",
            "type":"Retail Goods"
        }
    ],
    "sg:phone":"+1 520 622 4741",
    "sg:postcode":"85713",
    "sg:province":"AZ",
    "wof:name":"A & H Building Materials Inc",
    "wof:placetype":"venue"
},
  "geometry": {"coordinates":[-110.924044,32.191104],"type":"Point"}
}