{
  "type": "Feature",
  "properties": {
    "iso:country":"US",
    "sg:address":"1457 N Eliseo Felix Jr Way Ste 103",
    "sg:city":"Avondale",
    "sg:classifiers":[
        {
            "category":"Personal",
            "subcategory":"Beauty Salon",
            "type":"Services"
        },
        {
            "category":"Shopping",
            "subcategory":"Florist",
            "type":"Retail Goods"
        }
    ],
    "sg:phone":"+1 623 925 9662",
    "sg:postcode":"85323",
    "sg:province":"AZ",
    "sg:tags":[
        "hair"
    ],
    "sg:website":"www.quailruninc.com",
    "wof:name":"Quail Run Salon & Flowers",
    "wof:placetype":"venue"
},
  "geometry": {"coordinates":[-112.336793,33.450994],"type":"Point"}
}