{
  "type": "Feature",
  "properties": {
    "addr:full":"7615 N 75th Ave #103 Glendale AZ 85303",
    "addr:housenumber":"7615",
    "addr:postcode":"85303",
    "addr:street":"N 75Th Ave # 103",
    "iso:country":"US",
    "sg:address":"7615 N 75th Ave #103",
    "sg:city":"Glendale",
    "sg:classifiers":[
        {
            "category":"Building & Trades",
            "subcategory":"Pest Control",
            "type":"Services"
        }
    ],
    "sg:phone":"+1 623 516 2220",
    "sg:postcode":"85303",
    "sg:province":"AZ",
    "sg:tags":[
        "industrial",
        "services-commercial",
        "termite"
    ],
    "sg:website":"http://www.preventivepestcontrol.com",
    "wof:name":"Preventive Pest Control",
    "wof:placetype":"venue"
},
  "geometry": {"coordinates":[-112.220466,33.548647],"type":"Point"}
}