{
  "type": "Feature",
  "properties": {
    "addr:full":"231 E Main Street Avondale AZ 85323",
    "addr:housenumber":"231",
    "addr:postcode":"85323",
    "addr:street":"E Main Street",
    "iso:country":"US",
    "sg:address":"231 E Main Street",
    "sg:city":"Avondale",
    "sg:classifiers":[
        {
            "category":"Personal",
            "subcategory":"Beauty Salon",
            "type":"Services"
        }
    ],
    "sg:phone":"+1 623 932 5387",
    "sg:postcode":"85323",
    "sg:province":"AZ",
    "sg:tags":[
        "hair"
    ],
    "wof:name":"Eleganza Barber & Beauty Salon",
    "wof:placetype":"venue"
},
  "geometry": {"coordinates":[-112.34678,33.430835],"type":"Point"}
}