{
  "type": "Feature",
  "properties": {
    "iso:country":"US",
    "sg:address":"4802 E Ray Rd",
    "sg:city":"Phoenix",
    "sg:classifiers":[
        {
            "category":"Health Services",
            "subcategory":"Doctor",
            "type":"Services"
        }
    ],
    "sg:phone":"+1 480 893 7733",
    "sg:postcode":"85044",
    "sg:province":"AZ",
    "sg:tags":[
        "dentist"
    ],
    "wof:name":"Smilemakers Dental Care LTD",
    "wof:placetype":"venue"
},
  "geometry": {"coordinates":[-111.976197,33.319949],"type":"Point"}
}