{
  "type": "Feature",
  "properties": {
    "iso:country":"US",
    "sg:address":"210 S Bisbee Ave",
    "sg:city":"Willcox",
    "sg:classifiers":[
        {
            "category":"Real Estate",
            "subcategory":"Real Estate Services",
            "type":"Services"
        },
        {
            "category":"Real Estate",
            "subcategory":"Real Estate Operator",
            "type":"Services"
        }
    ],
    "sg:phone":"+1 520 384 4884",
    "sg:postcode":"85643",
    "sg:province":"AZ",
    "sg:tags":[
        "apartment",
        "vacancy",
        "listing",
        "rental",
        "finder"
    ],
    "wof:name":"Cochise Village Apartments",
    "wof:placetype":"venue"
},
  "geometry": {"coordinates":[-109.841309,32.252957],"type":"Point"}
}