{
  "type": "Feature",
  "properties": {
    "iso:country":"US",
    "sg:address":"3439 W Harrison St",
    "sg:city":"Phoenix",
    "sg:classifiers":[
        {
            "category":"Utilities",
            "subcategory":"Electric",
            "type":"Services"
        }
    ],
    "sg:phone":"+1 602 442 0915",
    "sg:postcode":"85009",
    "sg:province":"AZ",
    "sg:tags":[
        "electrical",
        "power",
        "systems-maintenance"
    ],
    "wof:name":"Digital Age Communications",
    "wof:placetype":"venue"
},
  "geometry": {"coordinates":[-112.133224,33.44399],"type":"Point"}
}