{
  "type": "Feature",
  "properties": {
    "addr:full":"2221 S Don Luis Mesa AZ 85202",
    "addr:housenumber":"2221",
    "addr:postcode":"85202",
    "addr:street":"S Don Luis",
    "iso:country":"US",
    "sg:address":"2221 S Don Luis",
    "sg:city":"Mesa",
    "sg:classifiers":[
        {
            "category":"Building & Trades",
            "subcategory":"Construction",
            "type":"Services"
        }
    ],
    "sg:phone":"+1 480 820 0193",
    "sg:postcode":"85202",
    "sg:province":"AZ",
    "sg:tags":[
        "house"
    ],
    "wof:name":"A-1 Home Repair",
    "wof:placetype":"venue"
},
  "geometry": {"coordinates":[-111.886414,33.373951],"type":"Point"}
}