{
  "type": "Feature",
  "properties": {
    "iso:country":"US",
    "sg:address":"745 N Alma School Rd",
    "sg:city":"Mesa",
    "sg:classifiers":[
        {
            "category":"Organizations",
            "subcategory":"Religious Organization",
            "type":"Services"
        }
    ],
    "sg:phone":"+1 480 969 0491",
    "sg:postcode":"85201",
    "sg:province":"AZ",
    "sg:tags":[
        "church"
    ],
    "wof:name":"Parkway Baptist Church",
    "wof:placetype":"venue"
},
  "geometry": {"coordinates":[-111.85623200000001,33.428403],"type":"Point"}
}