{
  "type": "Feature",
  "properties": {
    "iso:country":"US",
    "sg:address":"1870 E Apache Blvd",
    "sg:city":"Tempe",
    "sg:classifiers":[
        {
            "category":"Personal",
            "subcategory":"Beauty Salon",
            "type":"Services"
        }
    ],
    "sg:phone":"+1 480 894 9772",
    "sg:postcode":"85281",
    "sg:province":"AZ",
    "wof:name":"New Era Beauty Salon",
    "wof:placetype":"venue"
},
  "geometry": {"coordinates":[-111.90576799999999,33.414775],"type":"Point"}
}