{
  "type": "Feature",
  "properties": {
    "addr:full":"2114 W Monte Vista Rd Phoenix AZ 85009",
    "addr:housenumber":"2114",
    "addr:postcode":"85009",
    "addr:street":"W Monte Vista Rd",
    "iso:country":"US",
    "sg:address":"2114 W Monte Vista Rd",
    "sg:city":"Phoenix",
    "sg:classifiers":[
        {
            "category":"Manufacturing",
            "subcategory":"Metals",
            "type":"Manufacturing & Wholesale Goods"
        }
    ],
    "sg:phone":"+1 602 253 9744",
    "sg:postcode":"85009",
    "sg:province":"AZ",
    "sg:tags":[
        "ornamental",
        "product",
        "mfg",
        "equipment",
        "iron",
        "fireplace"
    ],
    "wof:name":"C F Sullivan Manufacturing Co",
    "wof:placetype":"venue"
},
  "geometry": {"coordinates":[-112.105695,33.47104],"type":"Point"}
}