{
  "type": "Feature",
  "properties": {
    "iso:country":"US",
    "sg:address":"5005 E Mcdowell Rd",
    "sg:city":"Phoenix",
    "sg:classifiers":[
        {
            "category":"Building & Trades",
            "subcategory":"Electrical",
            "type":"Services"
        }
    ],
    "sg:phone":"+1 602 275 1715",
    "sg:postcode":"85008",
    "sg:province":"AZ",
    "sg:tags":[
        "industrial",
        "electrician",
        "electric",
        "contractors-commercial"
    ],
    "wof:name":"Cannon & Wendt Electric Co",
    "wof:placetype":"venue"
},
  "geometry": {"coordinates":[-111.972061,33.4655],"type":"Point"}
}