{
  "type": "Feature",
  "properties": {
    "iso:country":"US",
    "sg:address":"10202 N 40th Ave",
    "sg:city":"Phoenix",
    "sg:classifiers":[
        {
            "category":"Building & Trades",
            "subcategory":"Construction",
            "type":"Services"
        }
    ],
    "sg:phone":"+1 602 843 7594",
    "sg:postcode":"85051",
    "sg:province":"AZ",
    "wof:name":"Advanced Modular Space Inc",
    "wof:placetype":"venue"
},
  "geometry": {"coordinates":[-112.14528,33.580251],"type":"Point"}
}