{
  "type": "Feature",
  "properties": {
    "iso:country":"US",
    "sg:address":"9 E Mission Ln",
    "sg:city":"Phoenix",
    "sg:classifiers":[
        {
            "category":"Social Services",
            "type":"Services"
        }
    ],
    "sg:phone":"+1 602 331 5817",
    "sg:postcode":"85020",
    "sg:province":"AZ",
    "sg:tags":[
        "organization",
        "welfare"
    ],
    "wof:name":"Marley House Family Resource",
    "wof:placetype":"venue"
},
  "geometry": {"coordinates":[-112.071832,33.569492],"type":"Point"}
}