{
  "type": "Feature",
  "properties": {
    "iso:country":"US",
    "sg:address":"5945 W Bethany Home Rd",
    "sg:city":"Glendale",
    "sg:classifiers":[
        {
            "category":"Health Services",
            "subcategory":"Doctor",
            "type":"Services"
        }
    ],
    "sg:phone":"+1 623 931 3794",
    "sg:postcode":"85301",
    "sg:province":"AZ",
    "sg:tags":[
        "dentist"
    ],
    "wof:name":"Graneto & Infeld LTD",
    "wof:placetype":"venue"
},
  "geometry": {"coordinates":[-112.186794,33.523985],"type":"Point"}
}