{
  "type": "Feature",
  "properties": {
    "addr:full":"1348 E Broadway Rd Phoenix AZ 85040",
    "addr:housenumber":"1348",
    "addr:postcode":"85040",
    "addr:street":"E Broadway Rd",
    "iso:country":"US",
    "sg:address":"1348 E Broadway Rd",
    "sg:city":"Phoenix",
    "sg:classifiers":[
        {
            "category":"Organizations",
            "subcategory":"Religious Organization",
            "type":"Services"
        }
    ],
    "sg:phone":"+1 602 276 8653",
    "sg:postcode":"85040",
    "sg:province":"AZ",
    "sg:tags":[
        "church"
    ],
    "wof:name":"Grace Temple",
    "wof:placetype":"venue"
},
  "geometry": {"coordinates":[-112.053117,33.40683],"type":"Point"}
}