{
  "type": "Feature",
  "properties": {
    "iso:country":"US",
    "sg:address":"1030 Sandretto Dr",
    "sg:city":"Prescott",
    "sg:classifiers":[
        {
            "category":"Building & Trades",
            "subcategory":"Construction",
            "type":"Services"
        }
    ],
    "sg:phone":"+1 928 445 1160",
    "sg:postcode":"86305",
    "sg:province":"AZ",
    "sg:tags":[
        "general",
        "industrial",
        "commercial",
        "contractor"
    ],
    "wof:name":"Bell Building Systems Arizona",
    "wof:placetype":"venue"
},
  "geometry": {"coordinates":[-112.45881199999999,34.602661],"type":"Point"}
}