{
  "type": "Feature",
  "properties": {
    "iso:country":"US",
    "sg:address":"2402 E Osborn Rd",
    "sg:city":"Phoenix",
    "sg:classifiers":[
        {
            "category":"Retail",
            "subcategory":"Auto Repair",
            "type":"Services"
        }
    ],
    "sg:phone":"+1 602 468 0010",
    "sg:postcode":"85016",
    "sg:province":"AZ",
    "sg:tags":[
        "automobile",
        "lubrication"
    ],
    "sg:website":"www.econolube.com",
    "wof:name":"Econo Lube N' Tune",
    "wof:placetype":"venue"
},
  "geometry": {"coordinates":[-112.028809,33.487672],"type":"Point"}
}