{
  "type": "Feature",
  "properties": {
    "addr:full":"3836 E Watkins St Phoenix AZ 85034",
    "addr:housenumber":"3836",
    "addr:postcode":"85034",
    "addr:street":"E Watkins St",
    "iso:country":"US",
    "sg:address":"3836 E Watkins St",
    "sg:city":"Phoenix",
    "sg:classifiers":[
        {
            "category":"Manufacturing",
            "subcategory":"Paper Products",
            "type":"Manufacturing & Wholesale Goods"
        }
    ],
    "sg:phone":"+1 602 296 0900",
    "sg:postcode":"85034",
    "sg:province":"AZ",
    "sg:tags":[
        "label"
    ],
    "wof:name":"Mesa Label Express",
    "wof:placetype":"venue"
},
  "geometry": {"coordinates":[-111.99908000000001,33.42429],"type":"Point"}
}