{
  "type": "Feature",
  "properties": {
    "addr:full":"358 Marina Blvd Bullhead City AZ 86442",
    "addr:housenumber":"358",
    "addr:postcode":"86442",
    "addr:street":"Marina Blvd",
    "iso:country":"US",
    "sg:address":"358 Marina Blvd",
    "sg:city":"Bullhead City",
    "sg:classifiers":[
        {
            "category":"Home & Garden",
            "subcategory":"Building Materials",
            "type":"Retail Goods"
        }
    ],
    "sg:phone":"+1 928 763 1711",
    "sg:postcode":"86442",
    "sg:province":"AZ",
    "wof:name":"Mason Glass",
    "wof:placetype":"venue"
},
  "geometry": {"coordinates":[-114.63546100000001,35.100347],"type":"Point"}
}