{
  "type": "Feature",
  "properties": {
    "addr:full":"3902 W Monte Cristo Ave Phoenix AZ 85053",
    "addr:housenumber":"3902",
    "addr:postcode":"85053",
    "addr:street":"W Monte Cristo Ave",
    "iso:country":"US",
    "sg:address":"3902 W Monte Cristo Ave",
    "sg:city":"Phoenix",
    "sg:classifiers":[
        {
            "category":"Building & Trades",
            "subcategory":"Construction",
            "type":"Services"
        }
    ],
    "sg:phone":"+1 602 866 0231",
    "sg:postcode":"85053",
    "sg:province":"AZ",
    "sg:tags":[
        "consultant",
        "restoration",
        "preservation",
        "contractor"
    ],
    "wof:name":"Building Specialist",
    "wof:placetype":"venue"
},
  "geometry": {"coordinates":[-112.14237,33.630581],"type":"Point"}
}