{
  "type": "Feature",
  "properties": {
    "iso:country":"US",
    "sg:address":"4509 E Cactus Rd",
    "sg:city":"Phoenix",
    "sg:classifiers":[
        {
            "category":"Autos & Motor Vehicles",
            "subcategory":"Automobile Sales",
            "type":"Retail Goods"
        },
        {
            "category":"Autos & Motor Vehicles",
            "subcategory":"Auto Supplies",
            "type":"Retail Goods"
        }
    ],
    "sg:phone":"+1 602 996 8383",
    "sg:postcode":"85032",
    "sg:province":"AZ",
    "sg:tags":[
        "stereo",
        "alarm",
        "system",
        "accessory",
        "equipment",
        "part",
        "electrical",
        "radio",
        "security"
    ],
    "sg:website":"http://www.audioexpress.com",
    "wof:name":"Audio Express Home of the One Dollar Install",
    "wof:placetype":"venue"
},
  "geometry": {"coordinates":[-111.986359,33.59972],"type":"Point"}
}