{
  "type": "Feature",
  "properties": {
    "iso:country":"US",
    "sg:address":"141 8th Ave",
    "sg:city":"San Manuel",
    "sg:classifiers":[
        {
            "category":"Banks & Credit Unions",
            "subcategory":"Bank",
            "type":"Services"
        }
    ],
    "sg:phone":"+1 520 385 4045",
    "sg:postcode":"85631",
    "sg:province":"AZ",
    "sg:tags":[
        "federal"
    ],
    "wof:name":"D M Federal Credit Union",
    "wof:placetype":"venue"
},
  "geometry": {"coordinates":[-110.630326,32.614205],"type":"Point"}
}