{
  "type": "Feature",
  "properties": {
    "iso:country":"US",
    "sg:address":"4980 W Ray Rd",
    "sg:city":"Chandler",
    "sg:classifiers":[
        {
            "category":"Utilities",
            "subcategory":"Mobile Phone",
            "type":"Services"
        }
    ],
    "sg:phone":"+1 480 222 0016",
    "sg:postcode":"85226",
    "sg:province":"AZ",
    "sg:tags":[
        "communications-common",
        "carrier",
        "radiotelephone",
        "cellular",
        "telephone"
    ],
    "wof:name":"Go Wireless",
    "wof:placetype":"venue"
},
  "geometry": {"coordinates":[-111.92757899999999,33.320046],"type":"Point"}
}