{
  "type": "Feature",
  "properties": {
    "iso:country":"US",
    "sg:address":"7331 E Osborn Dr Ste 220",
    "sg:city":"Scottsdale",
    "sg:classifiers":[
        {
            "category":"Health Services",
            "subcategory":"Clinic",
            "type":"Services"
        },
        {
            "category":"Health Services",
            "subcategory":"Medical Lab",
            "type":"Services"
        }
    ],
    "sg:phone":"+1 888 818 0355",
    "sg:postcode":"85251",
    "sg:province":"AZ",
    "sg:tags":[
        "information",
        "aid"
    ],
    "wof:name":"Scottsdale STD Testing Services",
    "wof:placetype":"venue"
},
  "geometry": {"coordinates":[-111.923952,33.486839],"type":"Point"}
}