{
  "type": "Feature",
  "properties": {
    "addr:full":"2820 W Cactus Rd Phoenix AZ 85029",
    "addr:housenumber":"2820",
    "addr:postcode":"85029",
    "addr:street":"W Cactus Rd",
    "iso:country":"US",
    "sg:address":"2820 W Cactus Rd",
    "sg:city":"Phoenix",
    "sg:classifiers":[
        {
            "category":"Retail",
            "subcategory":"Laundry & Dry Cleaning",
            "type":"Services"
        }
    ],
    "sg:phone":"+1 602 843 4046",
    "sg:postcode":"85029",
    "sg:province":"AZ",
    "sg:tags":[
        "cleaners"
    ],
    "wof:name":"Centurion Cleaners II",
    "wof:placetype":"venue"
},
  "geometry": {"coordinates":[-112.118303,33.596471],"type":"Point"}
}