{
  "type": "Feature",
  "properties": {
    "addr:full":"3040 N 36th St Phoenix AZ 85018",
    "addr:housenumber":"3040",
    "addr:postcode":"85018",
    "addr:street":"N 36Th St",
    "iso:country":"US",
    "sg:address":"3040 N 36th St",
    "sg:city":"Phoenix",
    "sg:classifiers":[
        {
            "category":"Banks & Credit Unions",
            "subcategory":"Bank",
            "type":"Services"
        }
    ],
    "sg:phone":"+1 602 261 2907",
    "sg:postcode":"85018",
    "sg:province":"AZ",
    "wof:name":"Chase Manhattan Bank",
    "wof:placetype":"venue"
},
  "geometry": {"coordinates":[-112.00427000000001,33.483769],"type":"Point"}
}