{
  "type": "Feature",
  "properties": {
    "iso:country":"US",
    "sg:address":"5740 W Peoria Ave",
    "sg:city":"Glendale",
    "sg:classifiers":[
        {
            "category":"Restaurant",
            "type":"Food & Drink"
        }
    ],
    "sg:phone":"+1 623 878 2180",
    "sg:postcode":"85302",
    "sg:province":"AZ",
    "wof:name":"J B's Restaurant",
    "wof:placetype":"venue"
},
  "geometry": {"coordinates":[-112.183357,33.581995],"type":"Point"}
}