{
  "type": "Feature",
  "properties": {
    "iso:country":"US",
    "sg:address":"2355 N Swan Rd",
    "sg:city":"Tucson",
    "sg:classifiers":[
        {
            "category":"Banks & Credit Unions",
            "subcategory":"Bank",
            "type":"Services"
        }
    ],
    "sg:phone":"+1 520 320 0888",
    "sg:postcode":"85712",
    "sg:province":"AZ",
    "sg:tags":[
        "institution",
        "business"
    ],
    "wof:name":"Cash Time Title Loans",
    "wof:placetype":"venue"
},
  "geometry": {"coordinates":[-110.892739,32.250383],"type":"Point"}
}