{
  "type": "Feature",
  "properties": {
    "addr:full":"721 N Monterey St Ste 101 Gilbert AZ 85233",
    "addr:housenumber":"721",
    "addr:postcode":"85233",
    "addr:street":"N Monterey St Ste 101",
    "iso:country":"US",
    "sg:address":"721 N Monterey St Ste 101",
    "sg:city":"Gilbert",
    "sg:classifiers":[
        {
            "category":"Retail",
            "subcategory":"Auto Repair",
            "type":"Services"
        }
    ],
    "sg:phone":"+1 480 507 5700",
    "sg:postcode":"85233",
    "sg:province":"AZ",
    "wof:name":"Gilbert Family Auto",
    "wof:placetype":"venue"
},
  "geometry": {"coordinates":[-111.79988400000001,33.362739],"type":"Point"}
}