{
  "type": "Feature",
  "properties": {
    "iso:country":"US",
    "sg:address":"3409 N 67th Dr",
    "sg:city":"Phoenix",
    "sg:classifiers":[
        {
            "category":"Health Services",
            "subcategory":"Nursing And Care Facility",
            "type":"Services"
        }
    ],
    "sg:phone":"+1 623 846 3524",
    "sg:postcode":"85033",
    "sg:province":"AZ",
    "sg:tags":[
        "home",
        "retirement",
        "community"
    ],
    "wof:name":"Humane Services For Humanity",
    "wof:placetype":"venue"
},
  "geometry": {"coordinates":[-112.203744,33.487859],"type":"Point"}
}