{
  "type": "Feature",
  "properties": {
    "iso:country":"US",
    "sg:address":"6860 S Nogales Hwy",
    "sg:city":"Tucson",
    "sg:classifiers":[
        {
            "category":"Freight",
            "type":"Transportation"
        }
    ],
    "sg:phone":"+1 520 573 9948",
    "sg:postcode":"85706",
    "sg:province":"AZ",
    "sg:tags":[
        "hauling",
        "trucking"
    ],
    "wof:name":"Lerod LLC",
    "wof:placetype":"venue"
},
  "geometry": {"coordinates":[-110.961259,32.127907],"type":"Point"}
}