{
  "type": "Feature",
  "properties": {
    "iso:country":"US",
    "sg:address":"20825 S Tiberius Dr",
    "sg:city":"Queen Creek",
    "sg:classifiers":[
        {
            "category":"Manufacturing",
            "subcategory":"Apparel",
            "type":"Manufacturing & Wholesale Goods"
        },
        {
            "category":"Shopping",
            "subcategory":"Bicycles & Sporting Goods",
            "type":"Retail Goods"
        }
    ],
    "sg:phone":"+1 480 503 2403",
    "sg:postcode":"85242",
    "sg:province":"AZ",
    "sg:tags":[
        "parachute",
        "textile",
        "product",
        "fabricated",
        "mfg"
    ],
    "wof:name":"Licence D Rigging",
    "wof:placetype":"venue"
},
  "geometry": {"coordinates":[-111.653822,33.25799],"type":"Point"}
}