{
  "type": "Feature",
  "properties": {
    "iso:country":"US",
    "sg:address":"10380 N 59th Ave",
    "sg:city":"Glendale",
    "sg:classifiers":[
        {
            "category":"Retail",
            "subcategory":"Car Wash",
            "type":"Services"
        }
    ],
    "sg:phone":"+1 623 878 4236",
    "sg:postcode":"85302",
    "sg:province":"AZ",
    "wof:name":"Weiss Guys Self Service Car",
    "wof:placetype":"venue"
},
  "geometry": {"coordinates":[-112.186248,33.580392],"type":"Point"}
}