{
  "type": "Feature",
  "properties": {
    "iso:country":"US",
    "sg:address":"11811 N Tatum Blvd # 3031",
    "sg:city":"Phoenix",
    "sg:classifiers":[
        {
            "category":"Professional",
            "subcategory":"Lawyer & Legal Services",
            "type":"Services"
        }
    ],
    "sg:phone":"+1 623 486 9797",
    "sg:postcode":"85028",
    "sg:province":"AZ",
    "sg:tags":[
        "attorney",
        "family",
        "divorce",
        "plan",
        "law"
    ],
    "wof:name":"Paula J Burnstein Pc",
    "wof:placetype":"venue"
},
  "geometry": {"coordinates":[-111.979644,33.593535],"type":"Point"}
}