{
  "type": "Feature",
  "properties": {
    "iso:country":"US",
    "sg:address":"8466 W Peoria Ave",
    "sg:city":"Peoria",
    "sg:classifiers":[
        {
            "category":"Banks & Credit Unions",
            "subcategory":"Bank",
            "type":"Services"
        },
        {
            "category":"Shopping",
            "subcategory":"Used Merchandise",
            "type":"Retail Goods"
        }
    ],
    "sg:phone":"+1 623 486 1999",
    "sg:postcode":"85345",
    "sg:province":"AZ",
    "sg:tags":[
        "shop",
        "second",
        "resale",
        "hand"
    ],
    "wof:name":"New Beginnings Thrift Shop",
    "wof:placetype":"venue"
},
  "geometry": {"coordinates":[-112.240935,33.581651],"type":"Point"}
}