{
  "type": "Feature",
  "properties": {
    "addr:full":"420 S 3rd Ave Phoenix AZ 85003",
    "addr:housenumber":"420",
    "addr:postcode":"85003",
    "addr:street":"S 3Rd Ave",
    "iso:country":"US",
    "sg:address":"420 S 3rd Ave",
    "sg:city":"Phoenix",
    "sg:classifiers":[
        {
            "category":"Freight",
            "type":"Transportation"
        }
    ],
    "sg:phone":"+1 602 254 5958",
    "sg:postcode":"85003",
    "sg:province":"AZ",
    "sg:tags":[
        "local",
        "storage",
        "trucking"
    ],
    "wof:name":"Mc Daniel Trucking Company",
    "wof:placetype":"venue"
},
  "geometry": {"coordinates":[-112.077715,33.443331],"type":"Point"}
}