{
  "type": "Feature",
  "properties": {
    "iso:country":"US",
    "sg:address":"3525 W Lenihan Ln",
    "sg:city":"Tucson",
    "sg:classifiers":[
        {
            "category":"Local Transit",
            "type":"Transportation"
        }
    ],
    "sg:phone":"+1 520 977 5555",
    "sg:postcode":"85742",
    "sg:province":"AZ",
    "sg:tags":[
        "airport"
    ],
    "wof:name":"Roadrunner Transportation",
    "wof:placetype":"venue"
},
  "geometry": {"coordinates":[-111.04166499999999,32.380231],"type":"Point"}
}