{
  "type": "Feature",
  "properties": {
    "addr:full":"6744 W Glendale Ave # 155 Glendale AZ 85303",
    "addr:housenumber":"6744",
    "addr:postcode":"85303",
    "addr:street":"W Glendale Ave # 155",
    "iso:country":"US",
    "sg:address":"6744 W Glendale Ave # 155",
    "sg:city":"Glendale",
    "sg:classifiers":[
        {
            "category":"Shopping",
            "subcategory":"Department Store",
            "type":"Retail Goods"
        }
    ],
    "sg:phone":"+1 623 435 9710",
    "sg:postcode":"85303",
    "sg:province":"AZ",
    "sg:tags":[
        "variety"
    ],
    "sg:website":"http://www.familydollar.com",
    "wof:name":"Family Dollar Stores",
    "wof:placetype":"venue"
},
  "geometry": {"coordinates":[-112.203525,33.538343],"type":"Point"}
}