{
  "type": "Feature",
  "properties": {
    "iso:country":"US",
    "sg:address":"3290 S Cam del Sol",
    "sg:city":"Green Valley",
    "sg:classifiers":[
        {
            "category":"Personal",
            "subcategory":"Beauty Salon",
            "type":"Services"
        }
    ],
    "sg:phone":"+1 520 625 7780",
    "sg:postcode":"85614",
    "sg:province":"AZ",
    "wof:name":"Christine's Hair Design",
    "wof:placetype":"venue"
},
  "geometry": {"coordinates":[-111.014576,31.819848],"type":"Point"}
}