{
  "type": "Feature",
  "properties": {
    "iso:country":"US",
    "sg:address":"680 Gail Gardner Way",
    "sg:city":"Prescott",
    "sg:classifiers":[
        {
            "category":"Health Services",
            "subcategory":"Doctor",
            "type":"Services"
        }
    ],
    "sg:phone":"+1 928 445 9233",
    "sg:postcode":"86305",
    "sg:province":"AZ",
    "sg:tags":[
        "dentist"
    ],
    "wof:name":"Gene Allen DDS",
    "wof:placetype":"venue"
},
  "geometry": {"coordinates":[-112.48674,34.551918],"type":"Point"}
}