{
  "type": "Feature",
  "properties": {
    "iso:country":"US",
    "sg:address":"106 E Pioneer St",
    "sg:city":"Phoenix",
    "sg:classifiers":[
        {
            "category":"Shopping",
            "type":"Retail Goods"
        }
    ],
    "sg:phone":"+1 602 269 6088",
    "sg:postcode":"85040",
    "sg:province":"AZ",
    "sg:tags":[
        "equipment",
        "merchandise",
        "furniture"
    ],
    "wof:name":"M&E Machinery Repair",
    "wof:placetype":"venue"
},
  "geometry": {"coordinates":[-112.07148100000001,33.41745],"type":"Point"}
}