{
  "type": "Feature",
  "properties": {
    "addr:full":"1306 E Van Buren St Phoenix AZ 85006",
    "addr:housenumber":"1306",
    "addr:postcode":"85006",
    "addr:street":"E Van Buren St",
    "iso:country":"US",
    "sg:address":"1306 E Van Buren St",
    "sg:city":"Phoenix",
    "sg:classifiers":[
        {
            "category":"Freight",
            "type":"Transportation"
        }
    ],
    "sg:phone":"+1 602 258 2355",
    "sg:postcode":"85006",
    "sg:province":"AZ",
    "wof:name":"TBC Transportation Inc",
    "wof:placetype":"venue"
},
  "geometry": {"coordinates":[-112.053696,33.451385],"type":"Point"}
}