{
  "type": "Feature",
  "properties": {
    "iso:country":"US",
    "sg:address":"35875 Joshua Pl",
    "sg:city":"Wickenburg",
    "sg:classifiers":[
        {
            "category":"Building & Trades",
            "subcategory":"Construction",
            "type":"Services"
        }
    ],
    "sg:phone":"+1 928 684 2199",
    "sg:postcode":"85390",
    "sg:province":"AZ",
    "sg:tags":[
        "house"
    ],
    "wof:name":"Hartman Homes",
    "wof:placetype":"venue"
},
  "geometry": {"coordinates":[-112.832037,34.031666],"type":"Point"}
}