{
  "type": "Feature",
  "properties": {
    "iso:country":"US",
    "sg:address":"3421 E McDowell Rd",
    "sg:city":"Mesa",
    "sg:classifiers":[
        {
            "category":"Building & Trades",
            "subcategory":"Construction",
            "type":"Services"
        }
    ],
    "sg:phone":"+1 480 924 2811",
    "sg:postcode":"85213",
    "sg:province":"AZ",
    "sg:tags":[
        "dwelling",
        "commercial",
        "for",
        "family",
        "contractor"
    ],
    "wof:name":"Puckett Development Inc",
    "wof:placetype":"venue"
},
  "geometry": {"coordinates":[-111.75693099999999,33.466293],"type":"Point"}
}