{
  "type": "Feature",
  "properties": {
    "iso:country":"US",
    "sg:address":"6502 W Glendale Ave",
    "sg:city":"Glendale",
    "sg:classifiers":[
        {
            "category":"Food & Beverages",
            "subcategory":"Candy",
            "type":"Retail Goods"
        }
    ],
    "sg:phone":"+1 623 847 3446",
    "sg:postcode":"85301",
    "sg:province":"AZ",
    "sg:tags":[
        "confectionery"
    ],
    "wof:name":"Dulceria Y Jugueteria Juarez",
    "wof:placetype":"venue"
},
  "geometry": {"coordinates":[-112.200281,33.538365],"type":"Point"}
}