{
  "type": "Feature",
  "properties": {
    "iso:country":"US",
    "sg:address":"112 N Central Ave",
    "sg:city":"Phoenix",
    "sg:classifiers":[
        {
            "category":"Arts & Performance",
            "subcategory":"Theater",
            "type":"Entertainment"
        }
    ],
    "sg:phone":"+1 602 254 9566",
    "sg:postcode":"85004",
    "sg:province":"AZ",
    "wof:name":"Actors Theatre Of Phoenix Adm",
    "wof:placetype":"venue"
},
  "geometry": {"coordinates":[-112.073888,33.450231],"type":"Point"}
}