{
  "type": "Feature",
  "properties": {
    "iso:country":"US",
    "sg:address":"6793 E Telegraph St",
    "sg:city":"Yuma",
    "sg:classifiers":[
        {
            "category":"Personal",
            "subcategory":"Beauty Salon",
            "type":"Services"
        }
    ],
    "sg:phone":"+1 928 344 4374",
    "sg:postcode":"85365",
    "sg:province":"AZ",
    "wof:name":"Lorraine Oldham Beauty",
    "wof:placetype":"venue"
},
  "geometry": {"coordinates":[-114.51437,32.688789],"type":"Point"}
}