{
  "type": "Feature",
  "properties": {
    "iso:country":"US",
    "sg:address":"906 W McDowell Rd",
    "sg:city":"Phoenix",
    "sg:classifiers":[
        {
            "category":"Real Estate",
            "subcategory":"Real Estate Agent",
            "type":"Services"
        }
    ],
    "sg:phone":"+1 602 252 4191",
    "sg:postcode":"85007",
    "sg:province":"AZ",
    "wof:name":"Mario Romero Team",
    "wof:placetype":"venue"
},
  "geometry": {"coordinates":[-112.08692499999999,33.465899],"type":"Point"}
}