{
  "type": "Feature",
  "properties": {
    "addr:full":"37417 N Tom Darlington Dr Carefree AZ 85377",
    "addr:housenumber":"37417",
    "addr:postcode":"az 85377",
    "addr:street":"N Tom Darlington Dr",
    "iso:country":"US",
    "sg:address":"37417 N Tom Darlington Dr",
    "sg:city":"Carefree",
    "sg:classifiers":[
        {
            "category":"Shopping",
            "type":"Retail Goods"
        }
    ],
    "sg:phone":"+1 480 488 3208",
    "sg:postcode":"85377",
    "sg:province":"AZ",
    "sg:tags":[
        "cosmetic",
        "perfume"
    ],
    "wof:name":"Merle Norman Cosmetics",
    "wof:placetype":"venue"
},
  "geometry": {"coordinates":[-111.924532,33.8259],"type":"Point"}
}