{
  "type": "Feature",
  "properties": {
    "iso:country":"US",
    "sg:address":"2721 N Travis",
    "sg:city":"Mesa",
    "sg:classifiers":[
        {
            "category":"Wholesale",
            "subcategory":"Photographic Equipment",
            "type":"Manufacturing & Wholesale Goods"
        }
    ],
    "sg:phone":"+1 480 969 5729",
    "sg:postcode":"85207",
    "sg:province":"AZ",
    "sg:tags":[
        "supply"
    ],
    "wof:name":"Leslie Sales",
    "wof:placetype":"venue"
},
  "geometry": {"coordinates":[-111.624473,33.464225],"type":"Point"}
}