{
  "type": "Feature",
  "properties": {
    "iso:country":"US",
    "sg:address":"8810 W Earll Dr",
    "sg:city":"Phoenix",
    "sg:classifiers":[
        {
            "category":"Wholesale",
            "subcategory":"Construction Materials",
            "type":"Manufacturing & Wholesale Goods"
        }
    ],
    "sg:phone":"+1 602 410 7223",
    "sg:postcode":"85037",
    "sg:province":"AZ",
    "sg:tags":[
        "mixed",
        "concrete-ready"
    ],
    "wof:name":"Tumbleweed Ready Mix Inc",
    "wof:placetype":"venue"
},
  "geometry": {"coordinates":[-112.24881,33.483554],"type":"Point"}
}