{
  "type": "Feature",
  "properties": {
    "iso:country":"US",
    "sg:address":"1650 E River Rd",
    "sg:city":"Tucson",
    "sg:classifiers":[
        {
            "category":"Insurance",
            "subcategory":"Insurance Agent",
            "type":"Services"
        }
    ],
    "sg:phone":"+1 520 529 7017",
    "sg:postcode":"85718",
    "sg:province":"AZ",
    "wof:name":"Gary Evans",
    "wof:placetype":"venue"
},
  "geometry": {"coordinates":[-110.946768,32.288564],"type":"Point"}
}