{
  "type": "Feature",
  "properties": {
    "iso:country":"US",
    "sg:address":"8111 E Indian Bend Rd",
    "sg:city":"Scottsdale",
    "sg:classifiers":[
        {
            "category":"Real Estate",
            "subcategory":"Real Estate Agent",
            "type":"Services"
        }
    ],
    "sg:phone":"+1 480 483 0373",
    "sg:postcode":"85250",
    "sg:province":"AZ",
    "sg:tags":[
        "management"
    ],
    "sg:website":"www.rbiaz.com",
    "wof:name":"RBI Management Svc Inc",
    "wof:placetype":"venue"
},
  "geometry": {"coordinates":[-111.903167,33.538386],"type":"Point"}
}