{
  "type": "Feature",
  "properties": {
    "iso:country":"US",
    "sg:address":"1526 W Glendale Ave",
    "sg:city":"Phoenix",
    "sg:classifiers":[
        {
            "category":"Health Services",
            "subcategory":"Doctor",
            "type":"Services"
        }
    ],
    "sg:phone":"+1 602 995 9722",
    "sg:postcode":"85021",
    "sg:province":"AZ",
    "sg:tags":[
        "dentist"
    ],
    "wof:name":"Associated Orthodontists LTD",
    "wof:placetype":"venue"
},
  "geometry": {"coordinates":[-112.093032,33.538605],"type":"Point"}
}