{
  "type": "Feature",
  "properties": {
    "addr:full":"7702 E. Doubletree Ranch Road Suite 300 Scottsdale AZ 85258",
    "addr:housenumber":"7702",
    "addr:postcode":"85258",
    "addr:street":"E. Doubletree Ranch Road Suite 300",
    "iso:country":"US",
    "sg:address":"7702 E. Doubletree Ranch Road Suite 300",
    "sg:city":"Scottsdale",
    "sg:classifiers":[
        {
            "category":"Professional",
            "subcategory":"Computer Services",
            "type":"Services"
        }
    ],
    "sg:phone":"+1 480 445 9883",
    "sg:postcode":"85258",
    "sg:province":"AZ",
    "sg:tags":[
        "sql-server",
        "data-warehousing",
        "database-integration",
        "business-intelligence",
        "integration",
        "olap",
        "rental-software",
        "database-design"
    ],
    "sg:website":"http://coredb.com",
    "wof:name":"Core Consulting Services, Inc.",
    "wof:placetype":"venue"
},
  "geometry": {"coordinates":[-111.913205,33.564017],"type":"Point"}
}