{
  "type": "Feature",
  "properties": {
    "iso:country":"US",
    "sg:address":"2640 W Adams St",
    "sg:city":"Phoenix",
    "sg:classifiers":[
        {
            "category":"Autos & Motor Vehicles",
            "subcategory":"Automobile Sales",
            "type":"Retail Goods"
        }
    ],
    "sg:phone":"+1 888 690 0647",
    "sg:postcode":"85009",
    "sg:province":"AZ",
    "sg:tags":[
        "new",
        "used",
        "car"
    ],
    "wof:name":"Discount Auto Sales",
    "wof:placetype":"venue"
},
  "geometry": {"coordinates":[-112.116061,33.449082],"type":"Point"}
}