{
  "type": "Feature",
  "properties": {
    "iso:country":"US",
    "sg:address":"1151 Sunrise Dr",
    "sg:city":"Clarkdale",
    "sg:classifiers":[
        {
            "category":"Building & Trades",
            "subcategory":"Landscaping Services",
            "type":"Services"
        }
    ],
    "sg:phone":"+1 928 634 6343",
    "sg:postcode":"86324",
    "sg:province":"AZ",
    "sg:tags":[
        "designer",
        "landscape"
    ],
    "wof:name":"Verde Valley Plant Tenders",
    "wof:placetype":"venue"
},
  "geometry": {"coordinates":[-112.053209,34.755725],"type":"Point"}
}