{
  "type": "Feature",
  "properties": {
    "iso:country":"US",
    "sg:address":"696 N Ocotillo Rd",
    "sg:city":"Benson",
    "sg:classifiers":[
        {
            "category":"Restaurant",
            "type":"Food & Drink"
        }
    ],
    "sg:phone":"+1 520 586 3118",
    "sg:postcode":"85602",
    "sg:province":"AZ",
    "wof:name":"Benson Plaza Restaurant",
    "wof:placetype":"venue"
},
  "geometry": {"coordinates":[-110.307013,31.971341],"type":"Point"}
}