{
  "type": "Feature",
  "properties": {
    "iso:country":"US",
    "sg:address":"2734 W Bell Rd",
    "sg:city":"Phoenix",
    "sg:classifiers":[
        {
            "category":"Shopping",
            "type":"Retail Goods"
        }
    ],
    "sg:phone":"+1 602 439 8744",
    "sg:postcode":"85053",
    "sg:province":"AZ",
    "sg:tags":[
        "picture",
        "frame"
    ],
    "wof:name":"Framin' Works",
    "wof:placetype":"venue"
},
  "geometry": {"coordinates":[-112.119801,33.639909],"type":"Point"}
}