{
  "type": "Feature",
  "properties": {
    "iso:country":"US",
    "sg:address":"6601 E Cheney Dr",
    "sg:city":"Paradise Valley",
    "sg:classifiers":[
        {
            "category":"Professional",
            "subcategory":"Art Services",
            "type":"Services"
        }
    ],
    "sg:phone":"+1 480 948 3341",
    "sg:postcode":"85253",
    "sg:province":"AZ",
    "sg:tags":[
        "commercial",
        "design"
    ],
    "wof:name":"Adams Graphics",
    "wof:placetype":"venue"
},
  "geometry": {"coordinates":[-111.937796,33.545859],"type":"Point"}
}