{
  "type": "Feature",
  "properties": {
    "addr:full":"1651 E Glenn St Tucson AZ 85719",
    "addr:housenumber":"1651",
    "addr:postcode":"85719",
    "addr:street":"E Glenn St",
    "iso:country":"US",
    "sg:address":"1651 E Glenn St",
    "sg:city":"Tucson",
    "sg:classifiers":[
        {
            "category":"Real Estate",
            "subcategory":"Real Estate Operator",
            "type":"Services"
        }
    ],
    "sg:phone":"+1 520 323 1130",
    "sg:postcode":"85719",
    "sg:province":"AZ",
    "sg:tags":[
        "building",
        "apartment"
    ],
    "wof:name":"Mesquite Grove",
    "wof:placetype":"venue"
},
  "geometry": {"coordinates":[-110.94746000000001,32.257631],"type":"Point"}
}