{
  "type": "Feature",
  "properties": {
    "addr:full":"4940 N Tamarind Pl Tucson AZ 85749",
    "addr:housenumber":"4940",
    "addr:postcode":"85749",
    "addr:street":"N Tamarind Pl",
    "iso:country":"US",
    "sg:address":"4940 N Tamarind Pl",
    "sg:city":"Tucson",
    "sg:classifiers":[
        {
            "category":"Wholesale",
            "subcategory":"Apparel",
            "type":"Manufacturing & Wholesale Goods"
        }
    ],
    "sg:phone":"+1 520 749 3443",
    "sg:postcode":"85749",
    "sg:province":"AZ",
    "sg:tags":[
        "clothing"
    ],
    "wof:name":"Tuoti Collection Inc",
    "wof:placetype":"venue"
},
  "geometry": {"coordinates":[-110.768884,32.299082],"type":"Point"}
}