{
  "type": "Feature",
  "properties": {
    "iso:country":"US",
    "sg:address":"6233 E Southern Ave",
    "sg:city":"Mesa",
    "sg:classifiers":[
        {
            "category":"Home & Garden",
            "subcategory":"Furniture",
            "type":"Retail Goods"
        }
    ],
    "sg:phone":"+1 480 507 9100",
    "sg:postcode":"85206",
    "sg:province":"AZ",
    "sg:website":"www.oasisbedrooms.com",
    "wof:name":"Oasis Bedrooms",
    "wof:placetype":"venue"
},
  "geometry": {"coordinates":[-111.700938,33.393811],"type":"Point"}
}