{
  "type": "Feature",
  "properties": {
    "iso:country":"US",
    "sg:address":"5261 W Kings Ave",
    "sg:city":"Glendale",
    "sg:classifiers":[
        {
            "category":"Professional",
            "subcategory":"Management & Consulting",
            "type":"Services"
        }
    ],
    "sg:phone":"+1 602 862 9112",
    "sg:postcode":"85306",
    "sg:province":"AZ",
    "sg:tags":[
        "consultant",
        "business"
    ],
    "wof:name":"Creative Merchandising",
    "wof:placetype":"venue"
},
  "geometry": {"coordinates":[-112.172916,33.633975],"type":"Point"}
}