{
  "type": "Feature",
  "properties": {
    "iso:country":"US",
    "sg:address":"180 N Chaco Trl",
    "sg:city":"Flagstaff",
    "sg:classifiers":[
        {
            "category":"Building & Trades",
            "subcategory":"Construction",
            "type":"Services"
        }
    ],
    "sg:phone":"+1 928 525 9159",
    "sg:postcode":"86001",
    "sg:province":"AZ",
    "sg:tags":[
        "drywall",
        "contractor"
    ],
    "wof:name":"Harry Smith Drywall",
    "wof:placetype":"venue"
},
  "geometry": {"coordinates":[-111.69936,35.099718],"type":"Point"}
}