{
  "type": "Feature",
  "properties": {
    "iso:country":"US",
    "sg:address":"3626 E Southern Ave",
    "sg:city":"Phoenix",
    "sg:classifiers":[
        {
            "category":"Manufacturing",
            "subcategory":"Tools & Machinery",
            "type":"Manufacturing & Wholesale Goods"
        }
    ],
    "sg:phone":"+1 602 431 1400",
    "sg:postcode":"85040",
    "sg:province":"AZ",
    "sg:tags":[
        "commercial",
        "refrigeration",
        "mfg"
    ],
    "wof:name":"Hussmann Corporation",
    "wof:placetype":"venue"
},
  "geometry": {"coordinates":[-112.000318,33.392708],"type":"Point"}
}