{
  "type": "Feature",
  "properties": {
    "iso:country":"US",
    "sg:address":"6237 E 22nd St",
    "sg:city":"Tucson",
    "sg:classifiers":[
        {
            "category":"Wholesale",
            "subcategory":"Electrical",
            "type":"Manufacturing & Wholesale Goods"
        }
    ],
    "sg:phone":"+1 520 748 2222",
    "sg:postcode":"85711",
    "sg:province":"AZ",
    "sg:tags":[
        "parts",
        "appliance"
    ],
    "wof:name":"Arizona Appliance Parts LLC",
    "wof:placetype":"venue"
},
  "geometry": {"coordinates":[-110.85881999999999,32.206937],"type":"Point"}
}