{
  "type": "Feature",
  "properties": {
    "iso:country":"US",
    "sg:address":"528 E Wickenburg Way",
    "sg:city":"Wickenburg",
    "sg:classifiers":[
        {
            "category":"Fast Food",
            "type":"Food & Drink"
        },
        {
            "category":"Restaurant",
            "type":"Food & Drink"
        }
    ],
    "sg:phone":"+1 928 684 9113",
    "sg:postcode":"85390",
    "sg:province":"AZ",
    "sg:tags":[
        "mexican"
    ],
    "sg:website":"http://www.tacobell.com",
    "wof:name":"Taco Bell",
    "wof:placetype":"venue"
},
  "geometry": {"coordinates":[-112.72122400000001,33.97],"type":"Point"}
}