{
  "type": "Feature",
  "properties": {
    "iso:country":"US",
    "sg:address":"1220 W Maximilian Way",
    "sg:city":"Tucson",
    "sg:classifiers":[
        {
            "category":"Professional",
            "subcategory":"Management & Consulting",
            "type":"Services"
        }
    ],
    "sg:phone":"+1 520 797 1000",
    "sg:postcode":"85704",
    "sg:province":"AZ",
    "sg:tags":[
        "consultant",
        "business"
    ],
    "wof:name":"Resource Strategies",
    "wof:placetype":"venue"
},
  "geometry": {"coordinates":[-110.99479,32.335666],"type":"Point"}
}