{
  "type": "Feature",
  "properties": {
    "addr:full":"6341 W Magnolia St Phoenix AZ 85043",
    "addr:housenumber":"6341",
    "addr:postcode":"85043",
    "addr:street":"W Magnolia St",
    "iso:country":"US",
    "sg:address":"6341 W Magnolia St",
    "sg:city":"Phoenix",
    "sg:classifiers":[
        {
            "category":"Real Estate",
            "subcategory":"Real Estate Services",
            "type":"Services"
        }
    ],
    "sg:phone":"+1 601 299 0592",
    "sg:postcode":"85043",
    "sg:province":"AZ",
    "sg:tags":[
        "vacancy",
        "rental",
        "listing"
    ],
    "wof:name":"Antoinette B Grimes",
    "wof:placetype":"venue"
},
  "geometry": {"coordinates":[-112.196231,33.424641],"type":"Point"}
}