{
  "type": "Feature",
  "properties": {
    "addr:full":"830 W Southern Ave Mesa AZ 85210",
    "addr:housenumber":"830",
    "addr:postcode":"85210",
    "addr:street":"W Southern Ave",
    "iso:country":"US",
    "sg:address":"830 W Southern Ave",
    "sg:city":"Mesa",
    "sg:classifiers":[
        {
            "category":"Banks & Credit Unions",
            "subcategory":"Bank",
            "type":"Services"
        }
    ],
    "sg:phone":"+1 480 668 4970",
    "sg:postcode":"85210",
    "sg:province":"AZ",
    "sg:tags":[
        "cashing",
        "check"
    ],
    "wof:name":"Check Advance",
    "wof:placetype":"venue"
},
  "geometry": {"coordinates":[-111.852265,33.393244],"type":"Point"}
}