{
  "type": "Feature",
  "properties": {
    "addr:full":"2122 W Butler Dr Phoenix AZ 85021",
    "addr:housenumber":"2122",
    "addr:postcode":"85021",
    "addr:street":"W Butler Dr",
    "iso:country":"US",
    "sg:address":"2122 W Butler Dr",
    "sg:city":"Phoenix",
    "sg:classifiers":[
        {
            "category":"Real Estate",
            "subcategory":"Real Estate Operator",
            "type":"Services"
        }
    ],
    "sg:phone":"+1 602 997 2988",
    "sg:postcode":"85021",
    "sg:province":"AZ",
    "sg:tags":[
        "building",
        "apartment"
    ],
    "wof:name":"Cedar Ridge Apartments",
    "wof:placetype":"venue"
},
  "geometry": {"coordinates":[-112.10359699999999,33.560419],"type":"Point"}
}