{
  "type": "Feature",
  "properties": {
    "iso:country":"US",
    "sg:address":"2122 W Butler Dr",
    "sg:city":"Phoenix",
    "sg:classifiers":[
        {
            "category":"Real Estate",
            "subcategory":"Real Estate Operator",
            "type":"Services"
        }
    ],
    "sg:phone":"+1 602 997 2988",
    "sg:postcode":"85021",
    "sg:province":"AZ",
    "sg:tags":[
        "building",
        "apartment"
    ],
    "wof:name":"Cedar Ridge Apartments",
    "wof:placetype":"venue"
},
  "geometry": {"coordinates":[-112.103597,33.560419],"type":"Point"}
}