{
  "type": "Feature",
  "properties": {
    "iso:country":"US",
    "sg:address":"3715 W Roosevelt St",
    "sg:city":"Phoenix",
    "sg:classifiers":[
        {
            "category":"Education",
            "subcategory":"School",
            "type":"Public Place"
        }
    ],
    "sg:phone":"+1 602 442 2700",
    "sg:postcode":"85009",
    "sg:province":"AZ",
    "sg:tags":[
        "elementary"
    ],
    "wof:name":"Morris K. Udall Escuela De Bellas Artes Elementary School",
    "wof:placetype":"venue"
},
  "geometry": {"coordinates":[-112.139111,33.458673],"type":"Point"}
}