{
  "type": "Feature",
  "properties": {
    "iso:country":"US",
    "sg:address":"5644 N 27th Ave",
    "sg:city":"Phoenix",
    "sg:classifiers":[
        {
            "category":"Food & Beverages",
            "subcategory":"Groceries & Convenience Stores",
            "type":"Retail Goods"
        }
    ],
    "sg:phone":"+1 602 246 3957",
    "sg:postcode":"85017",
    "sg:province":"AZ",
    "sg:tags":[
        "grocer"
    ],
    "wof:name":"Sunny Mini Mart",
    "wof:placetype":"venue"
},
  "geometry": {"coordinates":[-112.117011,33.518683],"type":"Point"}
}