{
  "type": "Feature",
  "properties": {
    "iso:country":"US",
    "sg:address":"854 W Wickenburg Way",
    "sg:city":"Wickenburg",
    "sg:classifiers":[
        {
            "category":"Shopping",
            "subcategory":"Florist",
            "type":"Retail Goods"
        }
    ],
    "sg:phone":"+1 928 684 5345",
    "sg:postcode":"85390",
    "sg:province":"AZ",
    "wof:name":"Attevy Flowers N Things",
    "wof:placetype":"venue"
},
  "geometry": {"coordinates":[-112.74673,33.96572],"type":"Point"}
}