{
  "type": "Feature",
  "properties": {
    "addr:full":"1245 W 17th Pl Yuma AZ 85364",
    "addr:housenumber":"1245",
    "addr:postcode":"85364",
    "addr:street":"W 17Th Pl",
    "iso:country":"US",
    "sg:address":"1245 W 17th Pl",
    "sg:city":"Yuma",
    "sg:classifiers":[
        {
            "category":"Real Estate",
            "subcategory":"Real Estate Operator",
            "type":"Services"
        }
    ],
    "sg:phone":"+1 928 782 0557",
    "sg:postcode":"85364",
    "sg:province":"AZ",
    "sg:tags":[
        "apartment"
    ],
    "wof:name":"Manchester Apts Trlr Pk",
    "wof:placetype":"venue"
},
  "geometry": {"coordinates":[-114.634263,32.695786],"type":"Point"}
}