{
  "type": "Feature",
  "properties": {
    "iso:country":"US",
    "sg:address":"4630 N Caida Pl",
    "sg:city":"Tucson",
    "sg:classifiers":[
        {
            "category":"Building & Trades",
            "subcategory":"Landscaping Services",
            "type":"Services"
        }
    ],
    "sg:phone":"+1 520 326 6387",
    "sg:postcode":"85718",
    "sg:province":"AZ",
    "sg:tags":[
        "landscape"
    ],
    "wof:name":"R O Landscaping",
    "wof:placetype":"venue"
},
  "geometry": {"coordinates":[-110.901616,32.292194],"type":"Point"}
}