{
  "type": "Feature",
  "properties": {
    "addr:full":"9440 W Northern Ave Glendale AZ 85305",
    "addr:housenumber":"9440",
    "addr:postcode":"85305",
    "addr:street":"W Northern Ave",
    "iso:country":"US",
    "sg:address":"9440 W Northern Ave",
    "sg:city":"Glendale",
    "sg:classifiers":[
        {
            "category":"Shopping",
            "subcategory":"Shoes",
            "type":"Retail Goods"
        }
    ],
    "sg:phone":"+1 623 772 8558",
    "sg:postcode":"85305",
    "sg:province":"AZ",
    "wof:name":"Payless Shoesource Inc",
    "wof:placetype":"venue"
},
  "geometry": {"coordinates":[-112.262005,33.55166],"type":"Point"}
}