{
  "type": "Feature",
  "properties": {
    "addr:full":"4445 E Holmes Ave Mesa AZ 85206",
    "addr:housenumber":"4445",
    "addr:postcode":"85206",
    "addr:street":"E Holmes Ave",
    "iso:country":"US",
    "sg:address":"4445 E Holmes Ave",
    "sg:city":"Mesa",
    "sg:classifiers":[
        {
            "category":"Professional",
            "subcategory":"Accounting & Tax Preparation",
            "type":"Services"
        }
    ],
    "sg:phone":"+1 480 981 3030",
    "sg:postcode":"85206",
    "sg:province":"AZ",
    "sg:tags":[
        "accountant"
    ],
    "wof:name":"Lloyd E Kent CPA",
    "wof:placetype":"venue"
},
  "geometry": {"coordinates":[-111.73469799999999,33.38903],"type":"Point"}
}