{
  "type": "Feature",
  "properties": {
    "addr:full":"5202 N 8th Pl Phoenix AZ 85014",
    "addr:housenumber":"5202",
    "addr:postcode":"85014",
    "addr:street":"N 8Th Pl",
    "iso:country":"US",
    "sg:address":"5202 N 8th Pl",
    "sg:city":"Phoenix",
    "sg:classifiers":[
        {
            "category":"Real Estate",
            "subcategory":"Real Estate Operator",
            "type":"Services"
        }
    ],
    "sg:phone":"+1 602 265 8300",
    "sg:postcode":"85014",
    "sg:province":"AZ",
    "sg:tags":[
        "apartment"
    ],
    "wof:name":"Kensington Garden Condominiums",
    "wof:placetype":"venue"
},
  "geometry": {"coordinates":[-112.062889,33.516449],"type":"Point"}
}