{
  "type": "Feature",
  "properties": {
    "iso:country":"US",
    "sg:address":"1651 E Glenn St",
    "sg:city":"Tucson",
    "sg:classifiers":[
        {
            "category":"Real Estate",
            "subcategory":"Real Estate Agent",
            "type":"Services"
        }
    ],
    "sg:phone":"+1 520 293 5050",
    "sg:postcode":"85719",
    "sg:province":"AZ",
    "sg:tags":[
        "broker"
    ],
    "sg:website":"www.diversified-equity.com",
    "wof:name":"Diversified Equity Corporation",
    "wof:placetype":"venue"
},
  "geometry": {"coordinates":[-110.94746000000001,32.257631],"type":"Point"}
}