{
  "type": "Feature",
  "properties": {
    "addr:full":"130 W Hampton Ave Ste 9 Mesa AZ 85210",
    "addr:housenumber":"130",
    "addr:postcode":"85210",
    "addr:street":"W Hampton Ave Ste 9",
    "iso:country":"US",
    "sg:address":"130 W Hampton Ave Ste 9",
    "sg:city":"Mesa",
    "sg:classifiers":[
        {
            "category":"Home & Garden",
            "subcategory":"Garden Supply",
            "type":"Retail Goods"
        }
    ],
    "sg:phone":"+1 480 827 8803",
    "sg:postcode":"85210",
    "sg:province":"AZ",
    "sg:tags":[
        "nursery",
        "gardening"
    ],
    "wof:name":"Sun Crest Products Inc",
    "wof:placetype":"venue"
},
  "geometry": {"coordinates":[-111.834999,33.387798],"type":"Point"}
}