{
  "type": "Feature",
  "properties": {
    "iso:country":"US",
    "sg:address":"8683 E Via de Negocio",
    "sg:city":"Scottsdale",
    "sg:classifiers":[
        {
            "category":"Building & Trades",
            "subcategory":"Construction",
            "type":"Services"
        }
    ],
    "sg:phone":"+1 480 946 9746",
    "sg:postcode":"85258",
    "sg:province":"AZ",
    "sg:tags":[
        "contractor"
    ],
    "wof:name":"Heritage Master Builders",
    "wof:placetype":"venue"
},
  "geometry": {"coordinates":[-111.895106,33.552081],"type":"Point"}
}