{
  "type": "Feature",
  "properties": {
    "iso:country":"US",
    "sg:address":"701 S Central Ave",
    "sg:city":"Phoenix",
    "sg:classifiers":[
        {
            "category":"Communications",
            "type":"Services"
        }
    ],
    "sg:phone":"+1 602 257 5182",
    "sg:postcode":"85004",
    "sg:province":"AZ",
    "sg:tags":[
        "communication"
    ],
    "wof:name":"Del Sol Communications",
    "wof:placetype":"venue"
},
  "geometry": {"coordinates":[-112.073763,33.43945],"type":"Point"}
}