{
  "type": "Feature",
  "properties": {
    "addr:full":"631 E Lexington Pl Tempe AZ 85281",
    "addr:housenumber":"631",
    "addr:postcode":"85281",
    "addr:street":"E Lexington Pl",
    "iso:country":"US",
    "sg:address":"631 E Lexington Pl",
    "sg:city":"Tempe",
    "sg:classifiers":[
        {
            "category":"Organizations",
            "subcategory":"Community Association",
            "type":"Services"
        }
    ],
    "sg:phone":"+1 480 946 4271",
    "sg:postcode":"85281",
    "sg:province":"AZ",
    "sg:tags":[
        "housing",
        "management",
        "co",
        "membership"
    ],
    "wof:name":"Concord Village",
    "wof:placetype":"venue"
},
  "geometry": {"coordinates":[-111.92903699999999,33.457626],"type":"Point"}
}