{
  "type": "Feature",
  "properties": {
    "iso:country":"US",
    "sg:address":"6298 E Grant Rd",
    "sg:city":"Tucson",
    "sg:classifiers":[
        {
            "category":"Banks & Credit Unions",
            "subcategory":"Bank",
            "type":"Services"
        }
    ],
    "sg:phone":"+1 520 731 2714",
    "sg:postcode":"85712",
    "sg:province":"AZ",
    "wof:name":"First National Bank Of Arizona",
    "wof:placetype":"venue"
},
  "geometry": {"coordinates":[-110.86172000000001,32.250637],"type":"Point"}
}