{
  "type": "Feature",
  "properties": {
    "addr:full":"864 E Hackamore St Mesa AZ 85203",
    "addr:housenumber":"864",
    "addr:postcode":"85203",
    "addr:street":"E Hackamore St",
    "iso:country":"US",
    "sg:address":"864 E Hackamore St",
    "sg:city":"Mesa",
    "sg:classifiers":[
        {
            "category":"Building & Trades",
            "subcategory":"Plumbing",
            "type":"Services"
        }
    ],
    "sg:phone":"+1 480 205 6868",
    "sg:postcode":"85203",
    "sg:province":"AZ",
    "sg:tags":[
        "air",
        "heating",
        "contractor",
        "system",
        "conditioning"
    ],
    "wof:name":"Factory Service AC & Heating",
    "wof:placetype":"venue"
},
  "geometry": {"coordinates":[-111.812608,33.439899],"type":"Point"}
}