{
  "type": "Feature",
  "properties": {
    "iso:country":"US",
    "sg:address":"2725 E Camelback Rd",
    "sg:city":"Phoenix",
    "sg:classifiers":[
        {
            "category":"Banks & Credit Unions",
            "subcategory":"Bank",
            "type":"Services"
        }
    ],
    "sg:phone":"+1 602 852 3500",
    "sg:postcode":"85016",
    "sg:province":"AZ",
    "sg:tags":[
        "depository",
        "banking"
    ],
    "wof:name":"BNC National Bank",
    "wof:placetype":"venue"
},
  "geometry": {"coordinates":[-112.024109,33.509533],"type":"Point"}
}