{
  "type": "Feature",
  "properties": {
    "iso:country":"US",
    "sg:address":"6811 E Cave Creek Rd",
    "sg:city":"Cave Creek",
    "sg:classifiers":[
        {
            "category":"Restaurant",
            "type":"Food & Drink"
        }
    ],
    "sg:phone":"+1 480 488 9118",
    "sg:postcode":"85331",
    "sg:province":"AZ",
    "sg:website":"www.buffalochipsaloon.com/",
    "wof:name":"Buffalo Chip Saloon and Steakhouse",
    "wof:placetype":"venue"
},
  "geometry": {"coordinates":[-111.934729,33.831797],"type":"Point"}
}