{
  "type": "Feature",
  "properties": {
    "iso:country":"US",
    "sg:address":"2303 N 44th St",
    "sg:city":"Phoenix",
    "sg:classifiers":[
        {
            "category":"Deli",
            "type":"Food & Drink"
        }
    ],
    "sg:menulink":"http://www.allmenus.com/az/phoenix/125883-blimpie-subs--sandwiches/menu/",
    "sg:phone":"+1 602 840 6250",
    "sg:postcode":"85008",
    "sg:province":"AZ",
    "sg:tags":[
        "wrap",
        "american",
        "sandwich"
    ],
    "wof:name":"Blimpie Subs & Sandwiches",
    "wof:placetype":"venue"
},
  "geometry": {"coordinates":[-111.98695600000001,33.473257],"type":"Point"}
}