{
  "type": "Feature",
  "properties": {
    "iso:country":"US",
    "sg:address":"1849 E Guadalupe Rd C101",
    "sg:city":"Tempe",
    "sg:classifiers":[
        {
            "category":"Arena",
            "subcategory":"Sports Club",
            "type":"Entertainment"
        }
    ],
    "sg:phone":"+1 480 753 3950",
    "sg:postcode":"85283",
    "sg:province":"AZ",
    "sg:tags":[
        "health"
    ],
    "wof:name":"Roach, Al Sales, Inc.",
    "wof:placetype":"venue"
},
  "geometry": {"coordinates":[-111.908982,33.363771],"type":"Point"}
}