{
  "type": "Feature",
  "properties": {
    "iso:country":"US",
    "sg:address":"470 S Bahama Dr",
    "sg:city":"Mesa",
    "sg:classifiers":[
        {
            "category":"Shopping",
            "subcategory":"Antiques",
            "type":"Retail Goods"
        }
    ],
    "sg:phone":"+1 480 834 3759",
    "sg:postcode":"85296",
    "sg:province":"AZ",
    "wof:name":"Dave's Furniture Service",
    "wof:placetype":"venue"
},
  "geometry": {"coordinates":[-111.753489,33.341549],"type":"Point"}
}