{
  "type": "Feature",
  "properties": {
    "iso:country":"US",
    "sg:address":"10639 N 32nd St",
    "sg:city":"Phoenix",
    "sg:classifiers":[
        {
            "category":"Professional",
            "subcategory":"Business Services",
            "type":"Services"
        },
        {
            "category":"Government",
            "subcategory":"Post Office",
            "type":"Public Place"
        }
    ],
    "sg:phone":"+1 800 275 8777",
    "sg:postcode":"85028",
    "sg:province":"AZ",
    "sg:tags":[
        "mail",
        "shipping"
    ],
    "sg:website":"http://www.usps.com",
    "wof:name":"USPS - United States Post Office - CPU Karens Hallmark Cactus",
    "wof:placetype":"venue"
},
  "geometry": {"coordinates":[-112.013115,33.582878],"type":"Point"}
}