{
  "type": "Feature",
  "properties": {
    "iso:country":"US",
    "sg:address":"2012 N 1st St Ste 2",
    "sg:city":"Flagstaff",
    "sg:classifiers":[
        {
            "category":"Personal",
            "subcategory":"Beauty Salon",
            "type":"Services"
        }
    ],
    "sg:phone":"+1 928 556 9908",
    "sg:postcode":"86004",
    "sg:province":"AZ",
    "wof:name":"Lamp Post Hair Salon",
    "wof:placetype":"venue"
},
  "geometry": {"coordinates":[-111.61702699999999,35.207815],"type":"Point"}
}