{
  "type": "Feature",
  "properties": {
    "iso:country":"US",
    "sg:address":"537 Campbell St",
    "sg:city":"Prescott",
    "sg:classifiers":[
        {
            "category":"Communications",
            "subcategory":"Radio Station",
            "type":"Services"
        }
    ],
    "sg:phone":"+1 928 778 7099",
    "sg:postcode":"86301",
    "sg:province":"AZ",
    "sg:tags":[
        "educational"
    ],
    "wof:name":"Donald K Nelson",
    "wof:placetype":"venue"
},
  "geometry": {"coordinates":[-112.473558,34.553166],"type":"Point"}
}