{
  "type": "Feature",
  "properties": {
    "iso:country":"US",
    "sg:address":"1528 W Palmer Dr",
    "sg:city":"Phoenix",
    "sg:classifiers":[
        {
            "category":"Building & Trades",
            "subcategory":"Construction",
            "type":"Services"
        }
    ],
    "sg:phone":"+1 602 678 1133",
    "sg:postcode":"85021",
    "sg:province":"AZ",
    "sg:tags":[
        "contractor"
    ],
    "wof:name":"Parsons Co Roofing",
    "wof:placetype":"venue"
},
  "geometry": {"coordinates":[-112.09286,33.572041],"type":"Point"}
}