{
  "type": "Feature",
  "properties": {
    "iso:country":"US",
    "sg:address":"7475 E McDowell Rd",
    "sg:city":"Scottsdale",
    "sg:classifiers":[
        {
            "category":"Education",
            "subcategory":"School",
            "type":"Public Place"
        }
    ],
    "sg:phone":"+1 480 874 3332",
    "sg:postcode":"85257",
    "sg:province":"AZ",
    "sg:website":"www.cafa.9f.com",
    "wof:name":"Classics & Four Arts Academy",
    "wof:placetype":"venue"
},
  "geometry": {"coordinates":[-111.921083,33.465667],"type":"Point"}
}