{
  "type": "Feature",
  "properties": {
    "iso:country":"US",
    "sg:address":"1440 S 23rd St",
    "sg:city":"Phoenix",
    "sg:classifiers":[
        {
            "category":"Retail",
            "subcategory":"Auto Rental",
            "type":"Services"
        }
    ],
    "sg:phone":"+1 602 273 3200",
    "sg:postcode":"85034",
    "sg:province":"AZ",
    "sg:tags":[
        "renting",
        "car",
        "automobile"
    ],
    "sg:website":"http://www.avis.com",
    "wof:name":"Avis Rent A Car",
    "wof:placetype":"venue"
},
  "geometry": {"coordinates":[-112.032473,33.435341],"type":"Point"}
}