{
  "type": "Feature",
  "properties": {
    "addr:full":"62 Smoketree Ave S Lake Havasu City AZ 86403",
    "addr:housenumber":"62",
    "addr:postcode":"86403",
    "addr:street":"Smoketree Ave S",
    "iso:country":"US",
    "sg:address":"62 Smoketree Ave S",
    "sg:city":"Lake Havasu City",
    "sg:classifiers":[
        {
            "category":"Home & Garden",
            "subcategory":"Carpets & Floor Coverings",
            "type":"Retail Goods"
        }
    ],
    "sg:phone":"+1 928 855 1497",
    "sg:postcode":"86403",
    "sg:province":"AZ",
    "sg:tags":[
        "dealer",
        "rug"
    ],
    "wof:name":"Rug Hut LTD",
    "wof:placetype":"venue"
},
  "geometry": {"coordinates":[-114.332854,34.474952],"type":"Point"}
}