{
  "type": "Feature",
  "properties": {
    "iso:country":"US",
    "sg:address":"5541 N 61st Ave",
    "sg:city":"Glendale",
    "sg:classifiers":[
        {
            "category":"Building & Trades",
            "subcategory":"Plumbing",
            "type":"Services"
        }
    ],
    "sg:phone":"+1 602 469 3434",
    "sg:postcode":"85301",
    "sg:province":"AZ",
    "sg:tags":[
        "plumber",
        "industrial",
        "contractors-commercial"
    ],
    "wof:name":"Service Plumbing Co",
    "wof:placetype":"venue"
},
  "geometry": {"coordinates":[-112.191144,33.517336],"type":"Point"}
}