{
  "type": "Feature",
  "properties": {
    "addr:full":"3111 W Chandler Blvd Chandler AZ 85226",
    "addr:housenumber":"3111",
    "addr:postcode":"85226",
    "addr:street":"W Chandler Blvd",
    "iso:country":"US",
    "sg:address":"3111 W Chandler Blvd",
    "sg:city":"Chandler",
    "sg:classifiers":[
        {
            "category":"Shopping",
            "subcategory":"Clothing, Apparel, & Fashions",
            "type":"Retail Goods"
        },
        {
            "category":"Personal",
            "subcategory":"Beauty Salon",
            "type":"Services"
        },
        {
            "category":"Personal",
            "subcategory":"Piercing",
            "type":"Services"
        },
        {
            "category":"Personal",
            "subcategory":"Shoe Repair & Shine",
            "type":"Services"
        },
        {
            "category":"Shopping",
            "subcategory":"Beauty & Cosmetics",
            "type":"Retail Goods"
        }
    ],
    "sg:phone":"+1 480 812 4870",
    "sg:postcode":"85226",
    "sg:province":"AZ",
    "sg:tags":[
        "body",
        "accessory",
        "supply",
        "perfume",
        "hair",
        "sunglass",
        "handbag",
        "women's"
    ],
    "sg:website":"http://www.claires.com/",
    "wof:name":"Claire's",
    "wof:placetype":"venue"
},
  "geometry": {"coordinates":[-111.896556,33.30571],"type":"Point"}
}