{
  "type": "Feature",
  "properties": {
    "addr:full":"709 E Guadalupe Rd Tempe AZ 85283",
    "addr:housenumber":"709",
    "addr:postcode":"85283",
    "addr:street":"E Guadalupe Rd",
    "iso:country":"US",
    "sg:address":"709 E Guadalupe Rd",
    "sg:city":"Tempe",
    "sg:classifiers":[
        {
            "category":"Restaurant",
            "type":"Food & Drink"
        }
    ],
    "sg:menulink":"http://www.allmenus.com/az/phoenix/69401-dominos-pizza/menu/",
    "sg:phone":"+1 480 491 3030",
    "sg:postcode":"85283",
    "sg:province":"AZ",
    "sg:tags":[
        "american",
        "wing",
        "pizza"
    ],
    "wof:name":"Domino's Pizza",
    "wof:placetype":"venue"
},
  "geometry": {"coordinates":[-111.930246,33.363756],"type":"Point"}
}