{
  "type": "Feature",
  "properties": {
    "iso:country":"US",
    "sg:address":"14864 N Fayette Dr",
    "sg:city":"Fountain Hills",
    "sg:classifiers":[
        {
            "category":"Wholesale",
            "subcategory":"Machinery & Supplies",
            "type":"Manufacturing & Wholesale Goods"
        }
    ],
    "sg:phone":"+1 480 837 7424",
    "sg:postcode":"85268",
    "sg:province":"AZ",
    "sg:tags":[
        "equipment",
        "spray",
        "industrial",
        "booth"
    ],
    "wof:name":"Spray Tech Equipment Co Inc",
    "wof:placetype":"venue"
},
  "geometry": {"coordinates":[-111.725274,33.620298],"type":"Point"}
}