{
  "type": "Feature",
  "properties": {
    "iso:country":"US",
    "sg:address":"15831 N 33rd Pl",
    "sg:city":"Phoenix",
    "sg:classifiers":[
        {
            "category":"Professional",
            "subcategory":"Research",
            "type":"Services"
        }
    ],
    "sg:phone":"+1 602 992 0744",
    "sg:postcode":"85032",
    "sg:province":"AZ",
    "sg:tags":[
        "educational"
    ],
    "wof:name":"Alfiola Science Group",
    "wof:placetype":"venue"
},
  "geometry": {"coordinates":[-112.0103,33.631053],"type":"Point"}
}