{
  "type": "Feature",
  "properties": {
    "iso:country":"US",
    "sg:address":"5110 E Ramada Dr",
    "sg:city":"Prescott",
    "sg:classifiers":[
        {
            "category":"Professional",
            "subcategory":"Accounting & Tax Preparation",
            "type":"Services"
        }
    ],
    "sg:phone":"+1 928 541 1049",
    "sg:postcode":"86301",
    "sg:province":"AZ",
    "sg:tags":[
        "return",
        "filing"
    ],
    "wof:name":"Accounting & More PC",
    "wof:placetype":"venue"
},
  "geometry": {"coordinates":[-112.375962,34.566203],"type":"Point"}
}