{
  "type": "Feature",
  "properties": {
    "addr:full":"1045 N Kolb Rd Tucson AZ 85710",
    "addr:housenumber":"1045",
    "addr:postcode":"85710",
    "addr:street":"N Kolb Rd",
    "iso:country":"US",
    "sg:address":"1045 N Kolb Rd",
    "sg:city":"Tucson",
    "sg:classifiers":[
        {
            "category":"Travel",
            "subcategory":"Travel Agent",
            "type":"Entertainment"
        }
    ],
    "sg:phone":"+1 520 721 7760",
    "sg:postcode":"85710",
    "sg:province":"AZ",
    "sg:tags":[
        "bureau",
        "passenger",
        "agency",
        "transportation",
        "arrangement"
    ],
    "wof:name":"Sabino Canyon Travel Inc",
    "wof:placetype":"venue"
},
  "geometry": {"coordinates":[-110.841055,32.233966],"type":"Point"}
}