{
  "type": "Feature",
  "properties": {
    "addr:full":"1012 S Stapley Dr Mesa AZ 85204",
    "addr:housenumber":"1012",
    "addr:postcode":"85204",
    "addr:street":"S Stapley Dr",
    "iso:country":"US",
    "sg:address":"1012 S Stapley Dr",
    "sg:city":"Mesa",
    "sg:classifiers":[
        {
            "category":"Insurance",
            "subcategory":"Insurance Agent",
            "type":"Services"
        }
    ],
    "sg:phone":"+1 480 829 7056",
    "sg:postcode":"85204",
    "sg:province":"AZ",
    "wof:name":"Larry Little Insurance",
    "wof:placetype":"venue"
},
  "geometry": {"coordinates":[-111.80550100000001,33.396322],"type":"Point"}
}