{
  "type": "Feature",
  "properties": {
    "iso:country":"US",
    "sg:address":"3211 Tower Rd",
    "sg:city":"Prescott",
    "sg:classifiers":[
        {
            "category":"Communications",
            "subcategory":"Television Station",
            "type":"Services"
        }
    ],
    "sg:phone":"+1 928 778 6770",
    "sg:postcode":"86305",
    "sg:province":"AZ",
    "sg:tags":[
        "broadcast",
        "representative"
    ],
    "wof:name":"Kac Tv",
    "wof:placetype":"venue"
},
  "geometry": {"coordinates":[-112.459686,34.603261],"type":"Point"}
}