{
  "type": "Feature",
  "properties": {
    "iso:country":"US",
    "sg:address":"617 N Alfred Ave",
    "sg:city":"Winslow",
    "sg:classifiers":[
        {
            "category":"Place Of Worship",
            "type":"Public Place"
        },
        {
            "category":"Organizations",
            "subcategory":"Religious Organization",
            "type":"Services"
        }
    ],
    "sg:phone":"+1 928 289 3416",
    "sg:postcode":"86047",
    "sg:province":"AZ",
    "sg:tags":[
        "church"
    ],
    "wof:name":"Maranatha Assembly Of God",
    "wof:placetype":"venue"
},
  "geometry": {"coordinates":[-110.705365,35.030672],"type":"Point"}
}