{
  "type": "Feature",
  "properties": {
    "addr:full":"3291 E Devonshire Ave Gilbert AZ 85297",
    "addr:housenumber":"3291",
    "addr:postcode":"85297",
    "addr:street":"E Devonshire Ave",
    "iso:country":"US",
    "sg:address":"3291 E Devonshire Ave",
    "sg:city":"Gilbert",
    "sg:classifiers":[
        {
            "category":"Home & Garden",
            "subcategory":"Hardware",
            "type":"Retail Goods"
        }
    ],
    "sg:phone":"+1 480 988 7072",
    "sg:postcode":"85297",
    "sg:province":"AZ",
    "sg:tags":[
        "tool",
        "used"
    ],
    "wof:name":"Evans Tools Inc",
    "wof:placetype":"venue"
},
  "geometry": {"coordinates":[-111.71721100000001,33.268175],"type":"Point"}
}