{
  "type": "Feature",
  "properties": {
    "iso:country":"US",
    "sg:address":"900 E Frye Rd",
    "sg:city":"Chandler",
    "sg:classifiers":[
        {
            "category":"Sports & Exercise",
            "subcategory":"Race Track",
            "type":"Entertainment"
        }
    ],
    "sg:phone":"+1 480 963 1053",
    "sg:postcode":"85225",
    "sg:province":"AZ",
    "wof:name":"Chandler BMX",
    "wof:placetype":"venue"
},
  "geometry": {"coordinates":[-111.825078,33.299017],"type":"Point"}
}