{
  "type": "Feature",
  "properties": {
    "iso:country":"US",
    "sg:address":"6549 N 40th Dr",
    "sg:city":"Phoenix",
    "sg:phone":"+1 602 405 2359",
    "sg:postcode":"85019",
    "sg:province":"AZ",
    "wof:name":"Siesta Contracting",
    "wof:placetype":"venue"
},
  "geometry": {"coordinates":[-112.14624000000001,33.53276],"type":"Point"}
}