{
  "type": "Feature",
  "properties": {
    "addr:full":"2830 E Brown Rd Mesa AZ 85213",
    "addr:housenumber":"2830",
    "addr:postcode":"85213",
    "addr:street":"E Brown Rd",
    "iso:country":"US",
    "sg:address":"2830 E Brown Rd",
    "sg:city":"Mesa",
    "sg:classifiers":[
        {
            "category":"Health Services",
            "subcategory":"Doctor",
            "type":"Services"
        }
    ],
    "sg:phone":"+1 480 807 7700",
    "sg:postcode":"85213",
    "sg:province":"AZ",
    "sg:tags":[
        "physician",
        "surgeon"
    ],
    "wof:name":"Mountain View Internal Mdcn",
    "wof:placetype":"venue"
},
  "geometry": {"coordinates":[-111.77026499999999,33.437327],"type":"Point"}
}