{
  "type": "Feature",
  "properties": {
    "iso:country":"US",
    "sg:address":"2974 N Alma School Rd",
    "sg:city":"Chandler",
    "sg:classifiers":[
        {
            "category":"Shopping",
            "subcategory":"Musical Instruments",
            "type":"Retail Goods"
        }
    ],
    "sg:phone":"+1 480 279 0684",
    "sg:postcode":"85224",
    "sg:province":"AZ",
    "sg:tags":[
        "piano"
    ],
    "wof:name":"All Pianos Direct",
    "wof:placetype":"venue"
},
  "geometry": {"coordinates":[-111.859151,33.346821],"type":"Point"}
}