{
  "type": "Feature",
  "properties": {
    "iso:country":"US",
    "sg:address":"6524 E Nelson Dr",
    "sg:city":"Tucson",
    "sg:classifiers":[
        {
            "category":"Building & Trades",
            "subcategory":"Landscaping Services",
            "type":"Services"
        }
    ],
    "sg:phone":"+1 520 400 5146",
    "sg:postcode":"85730",
    "sg:province":"AZ",
    "sg:tags":[
        "tree"
    ],
    "wof:name":"Out In The Desert Tree Trimmng",
    "wof:placetype":"venue"
},
  "geometry": {"coordinates":[-110.849898,32.188505],"type":"Point"}
}