{
  "type": "Feature",
  "properties": {
    "iso:country":"US",
    "sg:address":"1010 N 48th St",
    "sg:city":"Phoenix",
    "sg:classifiers":[
        {
            "category":"Shopping",
            "subcategory":"Hobbies, Toys, & Games",
            "type":"Retail Goods"
        }
    ],
    "sg:phone":"+1 602 685 0815",
    "sg:postcode":"85008",
    "sg:province":"AZ",
    "wof:name":"Benitez Virginia",
    "wof:placetype":"venue"
},
  "geometry": {"coordinates":[-111.978516,33.459883],"type":"Point"}
}