{
  "type": "Feature",
  "properties": {
    "addr:full":"11811 N 33rd Cir Phoenix AZ 85029",
    "addr:housenumber":"11811",
    "addr:postcode":"85029",
    "addr:street":"N 33Rd Cir",
    "iso:country":"US",
    "sg:address":"11811 N 33rd Cir",
    "sg:city":"Phoenix",
    "sg:classifiers":[
        {
            "category":"Real Estate",
            "subcategory":"Real Estate Agent",
            "type":"Services"
        }
    ],
    "sg:phone":"+1 623 572 0542",
    "sg:postcode":"85029",
    "sg:province":"AZ",
    "wof:name":"Jaco Properties",
    "wof:placetype":"venue"
},
  "geometry": {"coordinates":[-112.130426,33.594052],"type":"Point"}
}