{
  "type": "Feature",
  "properties": {
    "iso:country":"US",
    "sg:address":"903 N Beeline Hwy",
    "sg:city":"Payson",
    "sg:classifiers":[
        {
            "category":"Insurance",
            "subcategory":"Insurance Agent",
            "type":"Services"
        },
        {
            "category":"Insurance",
            "subcategory":"Hazard Insurance",
            "type":"Services"
        },
        {
            "category":"Insurance",
            "subcategory":"Title Insurance",
            "type":"Services"
        }
    ],
    "sg:phone":"+1 928 472 6698",
    "sg:postcode":"85541",
    "sg:province":"AZ",
    "sg:tags":[
        "auto",
        "homeowner"
    ],
    "sg:website":"http://apps.amfam.com/agentlocator/GWOLF?sourceid=yp3",
    "wof:name":"American Family Insurance- Geoff Wolf",
    "wof:placetype":"venue"
},
  "geometry": {"coordinates":[-111.322566,34.250616],"type":"Point"}
}