{
  "type": "Feature",
  "properties": {
    "iso:country":"US",
    "sg:address":"1930 Gold Dust Dr",
    "sg:city":"Lake Havasu City",
    "sg:classifiers":[
        {
            "category":"Building & Trades",
            "subcategory":"Plumbing",
            "type":"Services"
        }
    ],
    "sg:phone":"+1 928 855 7197",
    "sg:postcode":"86404",
    "sg:province":"AZ",
    "sg:tags":[
        "septic"
    ],
    "wof:name":"Joe's Septic & Backhoe Svc",
    "wof:placetype":"venue"
},
  "geometry": {"coordinates":[-114.354058,34.520729],"type":"Point"}
}