{
  "type": "Feature",
  "properties": {
    "iso:country":"US",
    "sg:address":"42951 Ave 51 E",
    "sg:city":"Salome",
    "sg:classifiers":[
        {
            "category":"Organizations",
            "subcategory":"Religious Organization",
            "type":"Services"
        }
    ],
    "sg:phone":"+1 928 859 3167",
    "sg:postcode":"85348",
    "sg:province":"AZ",
    "sg:tags":[
        "church"
    ],
    "wof:name":"Friendship Baptist Church",
    "wof:placetype":"venue"
},
  "geometry": {"coordinates":[-113.767239,33.70981],"type":"Point"}
}