{
  "type": "Feature",
  "properties": {
    "iso:country":"US",
    "sg:address":"7502 W Thomas Rd Ste 1",
    "sg:city":"Phoenix",
    "sg:classifiers":[
        {
            "category":"Banks & Credit Unions",
            "subcategory":"Bank",
            "type":"Services"
        }
    ],
    "sg:phone":"+1 602 433 2233",
    "sg:postcode":"85033",
    "sg:province":"AZ",
    "wof:name":"Desert Schools Federal Creditn Union",
    "wof:placetype":"venue"
},
  "geometry": {"coordinates":[-112.221001,33.480301],"type":"Point"}
}