{
  "type": "Feature",
  "properties": {
    "iso:country":"US",
    "sg:address":"2937 E Broadway Rd",
    "sg:city":"Phoenix",
    "sg:classifiers":[
        {
            "category":"Wholesale",
            "subcategory":"Home Furnishings",
            "type":"Manufacturing & Wholesale Goods"
        }
    ],
    "sg:phone":"+1 602 276 4333",
    "sg:postcode":"85040",
    "sg:province":"AZ",
    "wof:name":"L D Brinkman",
    "wof:placetype":"venue"
},
  "geometry": {"coordinates":[-112.019305,33.406893],"type":"Point"}
}