{
  "type": "Feature",
  "properties": {
    "iso:country":"US",
    "sg:address":"1152 W McMillan St",
    "sg:city":"Tucson",
    "sg:classifiers":[
        {
            "category":"Shopping",
            "subcategory":"Beauty & Cosmetics",
            "type":"Retail Goods"
        }
    ],
    "sg:phone":"+1 520 322 5636",
    "sg:postcode":"85705",
    "sg:province":"AZ",
    "sg:tags":[
        "merchandise"
    ],
    "wof:name":"Mary Kay Cosmetics",
    "wof:placetype":"venue"
},
  "geometry": {"coordinates":[-110.992284,32.278473],"type":"Point"}
}