{
  "type": "Feature",
  "properties": {
    "iso:country":"US",
    "sg:address":"11730 W Electra Ln",
    "sg:city":"Sun City",
    "sg:classifiers":[
        {
            "category":"Professional",
            "subcategory":"Business Services",
            "type":"Services"
        }
    ],
    "sg:phone":"+1 602 938 8779",
    "sg:postcode":"85373",
    "sg:province":"AZ",
    "sg:tags":[
        "pool",
        "swimming"
    ],
    "wof:name":"Integrity Pool Care",
    "wof:placetype":"venue"
},
  "geometry": {"coordinates":[-112.312859,33.697349],"type":"Point"}
}