{
  "type": "Feature",
  "properties": {
    "iso:country":"US",
    "sg:address":"13260 W Foxfire Dr",
    "sg:city":"Surprise",
    "sg:classifiers":[
        {
            "category":"Professional",
            "type":"Services"
        }
    ],
    "sg:phone":"+1 623 584 0248",
    "sg:postcode":"85374",
    "sg:province":"AZ",
    "wof:name":"Model Millwork LLC",
    "wof:placetype":"venue"
},
  "geometry": {"coordinates":[-112.346599,33.642073],"type":"Point"}
}