{
  "type": "Feature",
  "properties": {
    "iso:country":"US",
    "sg:address":"21373 W Brittle Bush Ln",
    "sg:city":"Buckeye",
    "sg:classifiers":[
        {
            "category":"Travel",
            "subcategory":"Hotels & Motels",
            "type":"Entertainment"
        }
    ],
    "sg:phone":"+1 623 551 9783",
    "sg:postcode":"85396",
    "sg:province":"AZ",
    "wof:name":"Anthony Marriott",
    "wof:placetype":"venue"
},
  "geometry": {"coordinates":[-112.519831,33.492285],"type":"Point"}
}