{
  "type": "Feature",
  "properties": {
    "addr:full":"155 Oak Creek Blvd Sedona AZ 86336",
    "addr:housenumber":"155",
    "addr:postcode":"86336",
    "addr:street":"Oak Creek Blvd",
    "iso:country":"US",
    "sg:address":"155 Oak Creek Blvd",
    "sg:city":"Sedona",
    "sg:classifiers":[
        {
            "category":"Manufacturing",
            "subcategory":"Metals",
            "type":"Manufacturing & Wholesale Goods"
        }
    ],
    "sg:phone":"+1 928 282 3528",
    "sg:postcode":"86336",
    "sg:province":"AZ",
    "sg:tags":[
        "steel"
    ],
    "wof:name":"Bob's Welding & Steel Supply",
    "wof:placetype":"venue"
},
  "geometry": {"coordinates":[-111.78785000000001,34.86124],"type":"Point"}
}