{
  "type": "Feature",
  "properties": {
    "iso:country":"US",
    "sg:address":"4909 W Villa Rita Dr",
    "sg:city":"Glendale",
    "sg:classifiers":[
        {
            "category":"Local Transit",
            "type":"Transportation"
        }
    ],
    "sg:phone":"+1 602 809 2877",
    "sg:postcode":"85308",
    "sg:province":"AZ",
    "sg:tags":[
        "passenger"
    ],
    "wof:name":"Roys Transportation",
    "wof:placetype":"venue"
},
  "geometry": {"coordinates":[-112.165373,33.649395],"type":"Point"}
}