{
  "type": "Feature",
  "properties": {
    "addr:full":"1251 N Virginia Ave Willcox AZ 85643",
    "addr:housenumber":"1251",
    "addr:postcode":"85643",
    "addr:street":"N Virginia Ave",
    "iso:country":"US",
    "sg:address":"1251 N Virginia Ave",
    "sg:city":"Willcox",
    "sg:classifiers":[
        {
            "category":"Travel",
            "subcategory":"Hotels & Motels",
            "type":"Entertainment"
        },
        {
            "category":"Retail",
            "subcategory":"Event Space",
            "type":"Services"
        }
    ],
    "sg:phone":"+1 800 345 8082",
    "sg:postcode":"85643",
    "sg:province":"AZ",
    "sg:tags":[
        "facility",
        "banquet",
        "reception",
        "lodging",
        "corporate",
        "hall"
    ],
    "sg:website":"http://ad.doubleclick.net/clk;222816988;46581822;v?http://www.hiexpress.com/redirect?path=hd&brandCode=ex&hotelCode=wilaz&_PMID=99601036&cm_mmc=mdpr-_-yellowpages-_-ex-_-wilaz",
    "wof:name":"Holiday Inn Express Hotel & Suites Willcox",
    "wof:placetype":"venue"
},
  "geometry": {"coordinates":[-109.8466,32.274244],"type":"Point"}
}