{
  "type": "Feature",
  "properties": {
    "iso:country":"US",
    "sg:address":"7246 E Joshua Tree Ln",
    "sg:city":"Scottsdale",
    "sg:classifiers":[
        {
            "category":"Building & Trades",
            "subcategory":"Construction",
            "type":"Services"
        }
    ],
    "sg:phone":"+1 480 948 8044",
    "sg:postcode":"85250",
    "sg:province":"AZ",
    "sg:tags":[
        "consultant"
    ],
    "wof:name":"The Normandy Corporation",
    "wof:placetype":"venue"
},
  "geometry": {"coordinates":[-111.924538,33.536496],"type":"Point"}
}