{
  "type": "Feature",
  "properties": {
    "addr:full":"2015 S Beulah Blvd Flagstaff AZ 86001",
    "addr:housenumber":"2015",
    "addr:postcode":"86001",
    "addr:street":"S Beulah Blvd",
    "iso:country":"US",
    "sg:address":"2015 S Beulah Blvd",
    "sg:city":"Flagstaff",
    "sg:classifiers":[
        {
            "category":"Travel",
            "subcategory":"Hotels & Motels",
            "type":"Entertainment"
        }
    ],
    "sg:phone":"+1 928 556 8666",
    "sg:postcode":"86001",
    "sg:province":"AZ",
    "wof:name":"LA Quinta Inn",
    "wof:placetype":"venue"
},
  "geometry": {"coordinates":[-111.663068,35.180248],"type":"Point"}
}