{
  "type": "Feature",
  "properties": {
    "iso:country":"US",
    "sg:address":"960 W Southern Ave",
    "sg:city":"Mesa",
    "sg:classifiers":[
        {
            "category":"Freight",
            "type":"Transportation"
        }
    ],
    "sg:phone":"+1 480 777 3942",
    "sg:postcode":"85210",
    "sg:province":"AZ",
    "wof:name":"A-1 Apartment Movers",
    "wof:placetype":"venue"
},
  "geometry": {"coordinates":[-111.849464,33.393289],"type":"Point"}
}