{
  "type": "Feature",
  "properties": {
    "iso:country":"US",
    "sg:address":"5722 W Latham St",
    "sg:city":"Phoenix",
    "sg:classifiers":[
        {
            "category":"Autos & Motor Vehicles",
            "subcategory":"Auto Supplies",
            "type":"Retail Goods"
        },
        {
            "category":"Retail",
            "subcategory":"Car Wash",
            "type":"Services"
        },
        {
            "category":"Retail",
            "subcategory":"Auto Repair",
            "type":"Services"
        }
    ],
    "sg:phone":"+1 602 484 7046",
    "sg:postcode":"85043",
    "sg:province":"AZ",
    "sg:tags":[
        "truck",
        "washing",
        "cleaning"
    ],
    "sg:website":"http://www.dannysbigrigresort.com",
    "wof:name":"Danny's Truck Wash",
    "wof:placetype":"venue"
},
  "geometry": {"coordinates":[-112.18259999999999,33.460596],"type":"Point"}
}