{
  "type": "Feature",
  "properties": {
    "iso:country":"US",
    "sg:address":"5727 N 7th St",
    "sg:city":"Phoenix",
    "sg:classifiers":[
        {
            "category":"Wholesale",
            "subcategory":"Stationery",
            "type":"Manufacturing & Wholesale Goods"
        }
    ],
    "sg:phone":"+1 602 287 0619",
    "sg:postcode":"85014",
    "sg:province":"AZ",
    "sg:tags":[
        "business",
        "form"
    ],
    "wof:name":"Intraform Inc",
    "wof:placetype":"venue"
},
  "geometry": {"coordinates":[-112.064915,33.521427],"type":"Point"}
}