{
  "type": "Feature",
  "properties": {
    "addr:full":"1650 E Broadway Rd Ste 3 Mesa AZ 85204",
    "addr:housenumber":"1650",
    "addr:postcode":"85204",
    "addr:street":"E Broadway Rd Ste 3",
    "iso:country":"US",
    "sg:address":"1650 E Broadway Rd Ste 3",
    "sg:city":"Mesa",
    "sg:classifiers":[
        {
            "category":"Shopping",
            "subcategory":"Clothing, Apparel, & Fashions",
            "type":"Retail Goods"
        },
        {
            "category":"Shopping",
            "subcategory":"Party Supplies",
            "type":"Retail Goods"
        },
        {
            "category":"Shopping",
            "subcategory":"Bridal",
            "type":"Retail Goods"
        }
    ],
    "sg:phone":"+1 480 615 6772",
    "sg:postcode":"85204",
    "sg:province":"AZ",
    "sg:tags":[
        "shop",
        "tailor",
        "alterations-clothing",
        "wedding"
    ],
    "wof:name":"Miriam's Bridal",
    "wof:placetype":"venue"
},
  "geometry": {"coordinates":[-111.79588,33.408026],"type":"Point"}
}