{
  "type": "Feature",
  "properties": {
    "iso:country":"US",
    "sg:address":"810 W Mingus Ave",
    "sg:city":"Cottonwood",
    "sg:classifiers":[
        {
            "category":"Home & Garden",
            "subcategory":"Hardware",
            "type":"Retail Goods"
        },
        {
            "category":"Home & Garden",
            "subcategory":"Building Materials",
            "type":"Retail Goods"
        }
    ],
    "sg:phone":"+1 928 634 4274",
    "sg:postcode":"86326",
    "sg:province":"AZ",
    "sg:tags":[
        "equipment",
        "electric",
        "supply"
    ],
    "wof:name":"Evergreen Hardware & Electric",
    "wof:placetype":"venue"
},
  "geometry": {"coordinates":[-112.03939699999999,34.735877],"type":"Point"}
}