{
  "type": "Feature",
  "properties": {
    "addr:full":"1711 W University Dr # 156 Tempe AZ 85281",
    "addr:housenumber":"1711",
    "addr:postcode":"85281",
    "addr:street":"W University Dr # 156",
    "iso:country":"US",
    "sg:address":"1711 W University Dr # 156",
    "sg:city":"Tempe",
    "sg:classifiers":[
        {
            "category":"Real Estate",
            "subcategory":"Architect",
            "type":"Services"
        }
    ],
    "sg:phone":"+1 480 858 9299",
    "sg:postcode":"85281",
    "sg:province":"AZ",
    "sg:tags":[
        "specification",
        "construction",
        "architectural",
        "engineer"
    ],
    "sg:website":"http://www.upscaleinc.com",
    "wof:name":"Upscale Architectural Models",
    "wof:placetype":"venue"
},
  "geometry": {"coordinates":[-111.966331,33.42194],"type":"Point"}
}