{
  "type": "Feature",
  "properties": {
    "iso:country":"US",
    "sg:address":"2548 W Broadway Rd",
    "sg:city":"Mesa",
    "sg:classifiers":[
        {
            "category":"Wholesale",
            "subcategory":"Electrical",
            "type":"Manufacturing & Wholesale Goods"
        },
        {
            "category":"Shopping",
            "subcategory":"Computers & Home Electronics",
            "type":"Retail Goods"
        }
    ],
    "sg:phone":"+1 480 636 0048",
    "sg:postcode":"85202",
    "sg:province":"AZ",
    "sg:tags":[
        "equipment",
        "electronic",
        "supply"
    ],
    "wof:name":"Home Entertainment Concepts",
    "wof:placetype":"venue"
},
  "geometry": {"coordinates":[-111.885954,33.4076],"type":"Point"}
}