{
  "type": "Feature",
  "properties": {
    "addr:full":"13070 W Rancho Santa Fe Blvd Avondale AZ 85323",
    "addr:housenumber":"13070",
    "addr:postcode":"85323",
    "addr:street":"W Rancho Santa Fe Blvd",
    "iso:country":"US",
    "sg:address":"13070 W Rancho Santa Fe Blvd",
    "sg:city":"Avondale",
    "sg:classifiers":[
        {
            "category":"Restaurant",
            "type":"Food & Drink"
        }
    ],
    "sg:phone":"+1 623 536 0188",
    "sg:postcode":"85323",
    "sg:province":"AZ",
    "sg:tags":[
        "hawaiian"
    ],
    "sg:website":"www.onohawaiianbbq.com/",
    "wof:name":"Ono Hawaiian BBQ",
    "wof:placetype":"venue"
},
  "geometry": {"coordinates":[-112.339996,33.460701],"type":"Point"}
}