{
  "type": "Feature",
  "properties": {
    "addr:full":"10750 W McDowell Rd Suite D400 Avondale AZ 85323",
    "addr:housenumber":"10750",
    "addr:postcode":"85323",
    "addr:street":"W Mcdowell Rd Suite D400",
    "iso:country":"US",
    "sg:address":"10750 W McDowell Rd Suite D400",
    "sg:city":"Avondale",
    "sg:classifiers":[
        {
            "category":"Health Services",
            "subcategory":"Clinic",
            "type":"Services"
        }
    ],
    "sg:phone":"+1 623 487 3003",
    "sg:postcode":"85323",
    "sg:province":"AZ",
    "sg:tags":[
        "medical"
    ],
    "wof:name":"Arrowhead Dermatology",
    "wof:placetype":"venue"
},
  "geometry": {"coordinates":[-112.29209299999999,33.464438],"type":"Point"}
}