{
  "type": "Feature",
  "properties": {
    "iso:country":"US",
    "sg:address":"11451 E Persimmon Ave",
    "sg:city":"Mesa",
    "sg:classifiers":[
        {
            "category":"Personal",
            "type":"Services"
        }
    ],
    "sg:phone":"+1 480 272 7666",
    "sg:postcode":"85212",
    "sg:province":"AZ",
    "sg:tags":[
        "butlers'",
        "maids'"
    ],
    "wof:name":"Perfect Touch Maid Services",
    "wof:placetype":"venue"
},
  "geometry": {"coordinates":[-111.586962,33.35254],"type":"Point"}
}