{
  "type": "Feature",
  "properties": {
    "iso:country":"US",
    "sg:address":"6102 N 13th Pl",
    "sg:city":"Phoenix",
    "sg:classifiers":[
        {
            "category":"Real Estate",
            "subcategory":"Real Estate Agent",
            "type":"Services"
        }
    ],
    "sg:phone":"+1 602 266 4697",
    "sg:postcode":"85014",
    "sg:province":"AZ",
    "wof:name":"Robert M Wagner",
    "wof:placetype":"venue"
},
  "geometry": {"coordinates":[-112.052365,33.527313],"type":"Point"}
}