{
  "type": "Feature",
  "properties": {
    "addr:full":"526 W Seldon Ln Phoenix AZ 85021",
    "addr:housenumber":"526",
    "addr:postcode":"85021",
    "addr:street":"W Seldon Ln",
    "iso:country":"US",
    "sg:address":"526 W Seldon Ln",
    "sg:city":"Phoenix",
    "sg:classifiers":[
        {
            "category":"Building & Trades",
            "subcategory":"Landscaping Services",
            "type":"Services"
        }
    ],
    "sg:phone":"+1 602 943 7379",
    "sg:postcode":"85021",
    "sg:province":"AZ",
    "wof:name":"S & V Enterprises",
    "wof:placetype":"venue"
},
  "geometry": {"coordinates":[-112.08175300000001,33.56158],"type":"Point"}
}