{
  "type": "Feature",
  "properties": {
    "iso:country":"US",
    "sg:address":"526 W Seldon Ln",
    "sg:city":"Phoenix",
    "sg:classifiers":[
        {
            "category":"Building & Trades",
            "subcategory":"Landscaping Services",
            "type":"Services"
        }
    ],
    "sg:phone":"+1 602 943 7379",
    "sg:postcode":"85021",
    "sg:province":"AZ",
    "wof:name":"S & V Enterprises",
    "wof:placetype":"venue"
},
  "geometry": {"coordinates":[-112.081753,33.56158],"type":"Point"}
}