{
  "type": "Feature",
  "properties": {
    "iso:country":"US",
    "sg:address":"7301 Bong Ln",
    "sg:city":"Luke Afb",
    "sg:classifiers":[
        {
            "category":"Government",
            "subcategory":"Office",
            "type":"Public Place"
        }
    ],
    "sg:phone":"+1 623 935 4953",
    "sg:postcode":"85309",
    "sg:province":"AZ",
    "wof:name":"Luke A Force Base Car Care Ctr",
    "wof:placetype":"venue"
},
  "geometry": {"coordinates":[-112.360059,33.541145],"type":"Point"}
}