{
  "type": "Feature",
  "properties": {
    "addr:full":"3133 S Moreno Mesa AZ 85212",
    "addr:housenumber":"3133",
    "addr:postcode":"85212",
    "addr:street":"S Moreno",
    "iso:country":"US",
    "sg:address":"3133 S Moreno",
    "sg:city":"Mesa",
    "sg:classifiers":[
        {
            "category":"Retail",
            "subcategory":"Auto Repair",
            "type":"Services"
        }
    ],
    "sg:phone":"+1 480 812 8233",
    "sg:postcode":"85212",
    "sg:province":"AZ",
    "sg:tags":[
        "van",
        "conversion",
        "truck",
        "accessory"
    ],
    "wof:name":"Dirt Squirts",
    "wof:placetype":"venue"
},
  "geometry": {"coordinates":[-111.63176799999999,33.358701],"type":"Point"}
}