{
  "type": "Feature",
  "properties": {
    "iso:country":"US",
    "sg:address":"728 E Rose Ln",
    "sg:city":"Phoenix",
    "sg:classifiers":[
        {
            "category":"Manufacturing",
            "subcategory":"Wood Products",
            "type":"Manufacturing & Wholesale Goods"
        }
    ],
    "sg:phone":"+1 602 997 9050",
    "sg:postcode":"85014",
    "sg:province":"AZ",
    "sg:tags":[
        "mfg"
    ],
    "wof:name":"Thinking of You",
    "wof:placetype":"venue"
},
  "geometry": {"coordinates":[-112.063987,33.52744],"type":"Point"}
}