{
  "type": "Feature",
  "properties": {
    "addr:full":"5827 E 36th St Tucson AZ 85711",
    "addr:housenumber":"5827",
    "addr:postcode":"85711",
    "addr:street":"E 36Th St",
    "iso:country":"US",
    "sg:address":"5827 E 36th St",
    "sg:city":"Tucson",
    "sg:classifiers":[
        {
            "category":"Building & Trades",
            "subcategory":"Landscaping Services",
            "type":"Services"
        }
    ],
    "sg:phone":"+1 520 748 7864",
    "sg:postcode":"85711",
    "sg:province":"AZ",
    "sg:tags":[
        "landscape",
        "contractor"
    ],
    "wof:name":"Rose Saguaro Landscape",
    "wof:placetype":"venue"
},
  "geometry": {"coordinates":[-110.86923400000001,32.19298],"type":"Point"}
}