{
  "type": "Feature",
  "properties": {
    "iso:country":"US",
    "sg:address":"1507 W Mission Dr",
    "sg:city":"Chandler",
    "sg:classifiers":[
        {
            "category":"Shopping",
            "type":"Retail Goods"
        }
    ],
    "sg:phone":"+1 480 963 3353",
    "sg:postcode":"85224",
    "sg:province":"AZ",
    "sg:tags":[
        "merchandise"
    ],
    "wof:name":"A Place For Serenity Pet",
    "wof:placetype":"venue"
},
  "geometry": {"coordinates":[-111.867521,33.344477],"type":"Point"}
}