{
  "type": "Feature",
  "properties": {
    "iso:country":"US",
    "sg:address":"18820 N 36th Pl",
    "sg:city":"Phoenix",
    "sg:classifiers":[
        {
            "category":"Shopping",
            "subcategory":"Gifts & Souvenirs",
            "type":"Retail Goods"
        }
    ],
    "sg:phone":"+1 602 494 4362",
    "sg:postcode":"85050",
    "sg:province":"AZ",
    "sg:tags":[
        "party",
        "supply"
    ],
    "wof:name":"Cactus Rita's Frozen Drink",
    "wof:placetype":"venue"
},
  "geometry": {"coordinates":[-112.004163,33.658106],"type":"Point"}
}