{
  "type": "Feature",
  "properties": {
    "addr:full":"4722 S Judd St Tempe AZ 85282",
    "addr:housenumber":"4722",
    "addr:postcode":"85282",
    "addr:street":"S Judd St",
    "iso:country":"US",
    "sg:address":"4722 S Judd St",
    "sg:city":"Tempe",
    "sg:classifiers":[
        {
            "category":"Building & Trades",
            "subcategory":"Construction",
            "type":"Services"
        }
    ],
    "sg:phone":"+1 480 890 2602",
    "sg:postcode":"85282",
    "sg:province":"AZ",
    "sg:tags":[
        "hanging",
        "contractor"
    ],
    "wof:name":"Kato Enterprises Inc",
    "wof:placetype":"venue"
},
  "geometry": {"coordinates":[-111.95190599999999,33.382016],"type":"Point"}
}