{
  "type": "Feature",
  "properties": {
    "addr:full":"6245 N 35th Ave Ste 6 Phoenix AZ 85017",
    "addr:housenumber":"6245",
    "addr:postcode":"85017",
    "addr:street":"N 35Th Ave Ste 6",
    "iso:country":"US",
    "sg:address":"6245 N 35th Ave Ste 6",
    "sg:city":"Phoenix",
    "sg:classifiers":[
        {
            "category":"Wholesale",
            "subcategory":"Office Equipment",
            "type":"Manufacturing & Wholesale Goods"
        }
    ],
    "sg:phone":"+1 602 347 5900",
    "sg:postcode":"85017",
    "sg:province":"AZ",
    "sg:tags":[
        "equipment-wholesale",
        "manufacturer",
        "furniture"
    ],
    "wof:name":"Cardtech",
    "wof:placetype":"venue"
},
  "geometry": {"coordinates":[-112.13427,33.52867],"type":"Point"}
}