{
  "type": "Feature",
  "properties": {
    "iso:country":"US",
    "sg:address":"914 S 27th Ave",
    "sg:city":"Phoenix",
    "sg:classifiers":[
        {
            "category":"Retail",
            "subcategory":"Auto Repair",
            "type":"Services"
        }
    ],
    "sg:phone":"+1 602 447 0069",
    "sg:postcode":"85009",
    "sg:province":"AZ",
    "sg:tags":[
        "repairing",
        "automobile"
    ],
    "wof:name":"Pancho's Auto Repair",
    "wof:placetype":"venue"
},
  "geometry": {"coordinates":[-112.117439,33.439615],"type":"Point"}
}