{
  "type": "Feature",
  "properties": {
    "iso:country":"US",
    "sg:address":"3858 W Clarendon Ave",
    "sg:city":"Phoenix",
    "sg:classifiers":[
        {
            "category":"Manufacturing",
            "subcategory":"Metals",
            "type":"Manufacturing & Wholesale Goods"
        },
        {
            "category":"Manufacturing",
            "subcategory":"Tools & Machinery",
            "type":"Manufacturing & Wholesale Goods"
        },
        {
            "category":"Manufacturing",
            "subcategory":"Printing",
            "type":"Manufacturing & Wholesale Goods"
        }
    ],
    "sg:phone":"+1 602 272 4661",
    "sg:postcode":"85019",
    "sg:province":"AZ",
    "sg:tags":[
        "machine",
        "shop",
        "engraver",
        "engraving"
    ],
    "sg:website":"http://www.precise-metals.com",
    "wof:name":"Precision Marking Co",
    "wof:placetype":"venue"
},
  "geometry": {"coordinates":[-112.141696,33.492222],"type":"Point"}
}