{
  "type": "Feature",
  "properties": {
    "addr:full":"412 N Washington Ave Prescott AZ 86301",
    "addr:housenumber":"412",
    "addr:postcode":"86301",
    "addr:street":"N Washington Ave",
    "iso:country":"US",
    "sg:address":"412 N Washington Ave",
    "sg:city":"Prescott",
    "sg:classifiers":[
        {
            "category":"Health Services",
            "subcategory":"Chiropractor",
            "type":"Services"
        }
    ],
    "sg:phone":"+1 928 778 1554",
    "sg:postcode":"86301",
    "sg:province":"AZ",
    "sg:tags":[
        "chiropractic"
    ],
    "wof:name":"Kramer Jeannette Chiropractor",
    "wof:placetype":"venue"
},
  "geometry": {"coordinates":[-112.46039,34.547147],"type":"Point"}
}