{
  "type": "Feature",
  "properties": {
    "iso:country":"US",
    "sg:address":"2540 W Monte Ave",
    "sg:city":"Mesa",
    "sg:classifiers":[
        {
            "category":"Real Estate",
            "subcategory":"Real Estate Agent",
            "type":"Services"
        }
    ],
    "sg:phone":"+1 480 838 0395",
    "sg:postcode":"85202",
    "sg:province":"AZ",
    "wof:name":"Lakefront",
    "wof:placetype":"venue"
},
  "geometry": {"coordinates":[-111.889442,33.36897],"type":"Point"}
}