{
  "type": "Feature",
  "properties": {
    "iso:country":"US",
    "sg:address":"2058 S Dobson Rd Ste 8",
    "sg:city":"Mesa",
    "sg:classifiers":[
        {
            "category":"Health Services",
            "subcategory":"Dentist",
            "type":"Services"
        }
    ],
    "sg:phone":"+1 480 345 6950",
    "sg:postcode":"85202",
    "sg:province":"AZ",
    "wof:name":"Amazing Dentistry",
    "wof:placetype":"venue"
},
  "geometry": {"coordinates":[-111.87828,33.377318],"type":"Point"}
}