{
  "type": "Feature",
  "properties": {
    "iso:country":"US",
    "sg:address":"14033 N 34th Ave",
    "sg:city":"Phoenix",
    "sg:classifiers":[
        {
            "category":"Building & Trades",
            "subcategory":"Plumbing",
            "type":"Services"
        }
    ],
    "sg:phone":"+1 602 942 8996",
    "sg:postcode":"85053",
    "sg:province":"AZ",
    "sg:tags":[
        "system",
        "equipment",
        "contractor",
        "air conditioning"
    ],
    "sg:website":"http://www.randrrefrigeration.com",
    "wof:name":"R & R Refrigeration",
    "wof:placetype":"venue"
},
  "geometry": {"coordinates":[-112.13096899999999,33.613486],"type":"Point"}
}