{
  "type": "Feature",
  "properties": {
    "iso:country":"US",
    "sg:address":"2309 E Broadway Blvd",
    "sg:city":"Tucson",
    "sg:classifiers":[
        {
            "category":"Real Estate",
            "subcategory":"Surveying",
            "type":"Services"
        }
    ],
    "sg:phone":"+1 520 624 1142",
    "sg:postcode":"85719",
    "sg:province":"AZ",
    "sg:tags":[
        "surveyor"
    ],
    "wof:name":"Resland Surveys Inc",
    "wof:placetype":"venue"
},
  "geometry": {"coordinates":[-110.93800299999999,32.221545],"type":"Point"}
}