{
  "type": "Feature",
  "properties": {
    "addr:full":"6411 E Sharon Dr Scottsdale AZ 85254",
    "addr:housenumber":"6411",
    "addr:postcode":"85254",
    "addr:street":"E Sharon Dr",
    "iso:country":"US",
    "sg:address":"6411 E Sharon Dr",
    "sg:city":"Scottsdale",
    "sg:classifiers":[
        {
            "category":"Professional",
            "type":"Services"
        }
    ],
    "sg:phone":"+1 480 778 0747",
    "sg:postcode":"85254",
    "sg:province":"AZ",
    "wof:name":"Marta Brien P C",
    "wof:placetype":"venue"
},
  "geometry": {"coordinates":[-111.941204,33.610529],"type":"Point"}
}