{
  "type": "Feature",
  "properties": {
    "iso:country":"US",
    "sg:address":"3151 N 31st Ave",
    "sg:city":"Phoenix",
    "sg:classifiers":[
        {
            "category":"Manufacturing",
            "subcategory":"Metals",
            "type":"Manufacturing & Wholesale Goods"
        }
    ],
    "sg:phone":"+1 602 455 8802",
    "sg:postcode":"85017",
    "sg:province":"AZ",
    "sg:tags":[
        "tool"
    ],
    "wof:name":"Streech's Dies",
    "wof:placetype":"venue"
},
  "geometry": {"coordinates":[-112.125602,33.483506],"type":"Point"}
}