{
  "type": "Feature",
  "properties": {
    "iso:country":"US",
    "sg:address":"Serving Statewide",
    "sg:city":"Phoenix",
    "sg:classifiers":[
        {
            "category":"Organizations",
            "subcategory":"Professional Association",
            "type":"Services"
        },
        {
            "category":"Recreation",
            "type":"Entertainment"
        }
    ],
    "sg:phone":"+1 602 327 2001",
    "sg:postcode":"85020",
    "sg:province":"AZ",
    "sg:tags":[
        "bureau",
        "agency",
        "entertainers-family",
        "business"
    ],
    "sg:website":"http://www.jrjuggler.com",
    "wof:name":"James Reid, Juggler Entertainment",
    "wof:placetype":"venue"
},
  "geometry": {"coordinates":[-112.061871,33.583956],"type":"Point"}
}