{
  "type": "Feature",
  "properties": {
    "iso:country":"US",
    "sg:address":"4545 S Wendler Dr",
    "sg:city":"Tempe",
    "sg:classifiers":[
        {
            "category":"Real Estate",
            "subcategory":"Real Estate Services",
            "type":"Services"
        }
    ],
    "sg:phone":"+1 602 943 9702",
    "sg:postcode":"85282",
    "sg:province":"AZ",
    "sg:tags":[
        "company",
        "title"
    ],
    "wof:name":"Netco",
    "wof:placetype":"venue"
},
  "geometry": {"coordinates":[-111.969579,33.384643],"type":"Point"}
}