{
  "type": "Feature",
  "properties": {
    "iso:country":"US",
    "sg:address":"915 N Arizona Ave",
    "sg:city":"Willcox",
    "sg:classifiers":[
        {
            "category":"Retail",
            "subcategory":"Repair Shop",
            "type":"Services"
        }
    ],
    "sg:phone":"+1 520 384 3115",
    "sg:postcode":"85643",
    "sg:province":"AZ",
    "sg:tags":[
        "equipment",
        "video"
    ],
    "wof:name":"CBM Electronics",
    "wof:placetype":"venue"
},
  "geometry": {"coordinates":[-109.837525,32.26527],"type":"Point"}
}