{
  "type": "Feature",
  "properties": {
    "iso:country":"US",
    "sg:address":"4657 S Contractors Way",
    "sg:city":"Tucson",
    "sg:classifiers":[
        {
            "category":"Building & Trades",
            "subcategory":"Plumbing",
            "type":"Services"
        }
    ],
    "sg:phone":"+1 520 327 1311",
    "sg:postcode":"85714",
    "sg:province":"AZ",
    "sg:tags":[
        "conditioning",
        "air",
        "heating",
        "contractor"
    ],
    "sg:website":"www.garefrig.com",
    "wof:name":"G & A Refrigeration Inc",
    "wof:placetype":"venue"
},
  "geometry": {"coordinates":[-110.907999,32.167674],"type":"Point"}
}