{
  "type": "Feature",
  "properties": {
    "addr:full":"7855 S River Pkwy Tempe AZ 85284",
    "addr:housenumber":"7855",
    "addr:postcode":"85284",
    "addr:street":"S River Pkwy",
    "iso:country":"US",
    "sg:address":"7855 S River Pkwy",
    "sg:city":"Tempe",
    "sg:classifiers":[
        {
            "category":"Professional",
            "subcategory":"Computer Services",
            "type":"Services"
        }
    ],
    "sg:phone":"+1 480 756 6777",
    "sg:postcode":"85284",
    "sg:province":"AZ",
    "sg:tags":[
        "consultant",
        "designer"
    ],
    "sg:website":"www.systrends.com",
    "wof:name":"Systrends Inc",
    "wof:placetype":"venue"
},
  "geometry": {"coordinates":[-111.897797,33.347638],"type":"Point"}
}