{
  "type": "Feature",
  "properties": {
    "addr:full":"6632 E Superstition Springs Blvd Mesa AZ 85206",
    "addr:housenumber":"6632",
    "addr:postcode":"85206",
    "addr:street":"E Superstition Springs Blvd",
    "iso:country":"US",
    "sg:address":"6632 E Superstition Springs Blvd",
    "sg:city":"Mesa",
    "sg:classifiers":[
        {
            "category":"Restaurant",
            "type":"Food & Drink"
        }
    ],
    "sg:phone":"+1 480 832 3444",
    "sg:postcode":"85206",
    "sg:province":"AZ",
    "sg:website":"www.redrobin.com",
    "wof:name":"Red Robin Gourmet Burgers",
    "wof:placetype":"venue"
},
  "geometry": {"coordinates":[-111.688795,33.385027],"type":"Point"}
}