{
  "type": "Feature",
  "properties": {
    "iso:country":"US",
    "sg:address":"4935 E Carefree Hwy",
    "sg:city":"Cave Creek",
    "sg:classifiers":[
        {
            "category":"Restaurant",
            "type":"Food & Drink"
        }
    ],
    "sg:menulink":"http://www.allmenus.com/az/deer-valley/110776-quiznos-sub/menu/",
    "sg:phone":"+1 480 437 1080",
    "sg:postcode":"85331",
    "sg:province":"AZ",
    "sg:tags":[
        "wrap",
        "american",
        "sandwich"
    ],
    "wof:name":"Quiznos Sub",
    "wof:placetype":"venue"
},
  "geometry": {"coordinates":[-111.97414999999999,33.798645],"type":"Point"}
}