{
  "type": "Feature",
  "properties": {
    "addr:full":"9180 S Kyrene Rd Tempe AZ 85283",
    "addr:housenumber":"9180",
    "addr:postcode":"85283",
    "addr:street":"S Kyrene Rd",
    "iso:country":"US",
    "sg:address":"9180 S Kyrene Rd",
    "sg:city":"Tempe",
    "sg:classifiers":[
        {
            "category":"Manufacturing",
            "subcategory":"Retail Goods",
            "type":"Manufacturing & Wholesale Goods"
        }
    ],
    "sg:phone":"+1 480 961 7033",
    "sg:postcode":"85283",
    "sg:province":"AZ",
    "sg:tags":[
        "assembly",
        "fabricating"
    ],
    "wof:name":"S T Assembly Test Svc",
    "wof:placetype":"venue"
},
  "geometry": {"coordinates":[-111.94572100000001,33.329826],"type":"Point"}
}