{
  "type": "Feature",
  "properties": {
    "iso:country":"US",
    "sg:address":"3949 E Des Moines St",
    "sg:city":"Mesa",
    "sg:classifiers":[
        {
            "category":"Building & Trades",
            "subcategory":"Construction",
            "type":"Services"
        }
    ],
    "sg:phone":"+1 480 990 0603",
    "sg:postcode":"85205",
    "sg:province":"AZ",
    "sg:tags":[
        "dry wall",
        "contractor"
    ],
    "wof:name":"Above All Drywall",
    "wof:placetype":"venue"
},
  "geometry": {"coordinates":[-111.747129,33.42816],"type":"Point"}
}