{
  "type": "Feature",
  "properties": {
    "iso:country":"US",
    "sg:address":"3342 E Wier Ave",
    "sg:city":"Phoenix",
    "sg:classifiers":[
        {
            "category":"Professional",
            "subcategory":"Business Services",
            "type":"Services"
        }
    ],
    "sg:phone":"+1 602 882 4910",
    "sg:postcode":"85040",
    "sg:province":"AZ",
    "sg:tags":[
        "holding"
    ],
    "wof:name":"S & F Holdings",
    "wof:placetype":"venue"
},
  "geometry": {"coordinates":[-112.009743,33.402871],"type":"Point"}
}