{
  "type": "Feature",
  "properties": {
    "iso:country":"US",
    "sg:address":"3701 W Anthem Way",
    "sg:city":"Anthem",
    "sg:classifiers":[
        {
            "category":"Real Estate",
            "subcategory":"Real Estate Services",
            "type":"Services"
        }
    ],
    "sg:phone":"+1 623 551 6651",
    "sg:postcode":"85086",
    "sg:province":"AZ",
    "sg:tags":[
        "company",
        "title"
    ],
    "wof:name":"Grand Canyon Title Agency",
    "wof:placetype":"venue"
},
  "geometry": {"coordinates":[-112.137118,33.866178],"type":"Point"}
}