{
  "type": "Feature",
  "properties": {
    "addr:full":"7090 N Oracle Rd Tucson AZ 85704",
    "addr:housenumber":"7090",
    "addr:postcode":"85704",
    "addr:street":"N Oracle Rd",
    "iso:country":"US",
    "sg:address":"7090 N Oracle Rd",
    "sg:city":"Tucson",
    "sg:classifiers":[
        {
            "category":"Shopping",
            "subcategory":"Florist",
            "type":"Retail Goods"
        }
    ],
    "sg:phone":"+1 520 297 1165",
    "sg:postcode":"85704",
    "sg:province":"AZ",
    "sg:tags":[
        "flower"
    ],
    "wof:name":"Adobes Flower Shop",
    "wof:placetype":"venue"
},
  "geometry": {"coordinates":[-110.97742599999999,32.336082],"type":"Point"}
}