{
  "type": "Feature",
  "properties": {
    "addr:full":"3003 Hwy 95 Bullhead City AZ 86442",
    "addr:housenumber":"3003",
    "addr:postcode":"86442",
    "addr:street":"Hwy 95",
    "iso:country":"US",
    "sg:address":"3003 Hwy 95",
    "sg:city":"Bullhead City",
    "sg:classifiers":[
        {
            "category":"Shopping",
            "subcategory":"Optical Goods",
            "type":"Retail Goods"
        }
    ],
    "sg:phone":"+1 928 758 6691",
    "sg:postcode":"86442",
    "sg:province":"AZ",
    "sg:tags":[
        "medical"
    ],
    "wof:name":"Mohave Eye Center",
    "wof:placetype":"venue"
},
  "geometry": {"coordinates":[-114.593262,35.076223],"type":"Point"}
}