{
  "type": "Feature",
  "properties": {
    "iso:country":"US",
    "sg:address":"4742 N 24th St",
    "sg:city":"Phoenix",
    "sg:classifiers":[
        {
            "category":"Professional",
            "type":"Services"
        }
    ],
    "sg:phone":"+1 602 468 7666",
    "sg:postcode":"85016",
    "sg:province":"AZ",
    "sg:tags":[
        "establishment"
    ],
    "wof:name":"J W Garrett Bond Dept",
    "wof:placetype":"venue"
},
  "geometry": {"coordinates":[-112.030308,33.507344],"type":"Point"}
}