{
  "type": "Feature",
  "properties": {
    "addr:full":"5151 N 19th Ave Phoenix AZ 85015",
    "addr:housenumber":"5151",
    "addr:postcode":"85015",
    "addr:street":"N 19Th Ave",
    "iso:country":"US",
    "sg:address":"5151 N 19th Ave",
    "sg:city":"Phoenix",
    "sg:classifiers":[
        {
            "category":"Social Services",
            "type":"Services"
        }
    ],
    "sg:phone":"+1 602 973 2212",
    "sg:postcode":"85015",
    "sg:province":"AZ",
    "sg:tags":[
        "organization",
        "welfare"
    ],
    "sg:website":"www.makeadifference.org",
    "wof:name":"Make A Difference Volunteer",
    "wof:placetype":"venue"
},
  "geometry": {"coordinates":[-112.09977499999999,33.511056],"type":"Point"}
}