{
  "type": "Feature",
  "properties": {
    "addr:full":"4900 Hayfield Draw Dr Camp Verde AZ 86322",
    "addr:housenumber":"4900",
    "addr:postcode":"az 86322",
    "addr:street":"Hayfield Draw Dr",
    "iso:country":"US",
    "sg:address":"4900 Hayfield Draw Dr",
    "sg:city":"Camp Verde",
    "sg:classifiers":[
        {
            "category":"Wholesale",
            "subcategory":"Auto Parts",
            "type":"Manufacturing & Wholesale Goods"
        }
    ],
    "sg:phone":"+1 928 567 1607",
    "sg:postcode":"86322",
    "sg:province":"AZ",
    "sg:tags":[
        "paint",
        "repair"
    ],
    "wof:name":"Mark Schaeffers Showstoppers",
    "wof:placetype":"venue"
},
  "geometry": {"coordinates":[-111.932485,34.639237],"type":"Point"}
}