{
  "type": "Feature",
  "properties": {
    "addr:full":"1085 W Queen Creek Road Chandler AZ 85248",
    "addr:housenumber":"1085",
    "addr:postcode":"85248",
    "addr:street":"W Queen Creek Road",
    "iso:country":"US",
    "sg:address":"1085 W Queen Creek Road",
    "sg:city":"Chandler",
    "sg:classifiers":[
        {
            "category":"Arts & Performance",
            "subcategory":"Art Gallery",
            "type":"Entertainment"
        }
    ],
    "sg:phone":"+1 480 782 0948",
    "sg:postcode":"85248",
    "sg:province":"AZ",
    "sg:website":"www.fastframe.com",
    "wof:name":"Fast Frame",
    "wof:placetype":"venue"
},
  "geometry": {"coordinates":[-111.859876,33.261779],"type":"Point"}
}