{
  "type": "Feature",
  "properties": {
    "iso:country":"US",
    "sg:address":"1959 S Val Vista Dr",
    "sg:city":"Mesa",
    "sg:classifiers":[
        {
            "category":"Health Services",
            "subcategory":"Doctor",
            "type":"Services"
        }
    ],
    "sg:phone":"+1 480 545 1398",
    "sg:postcode":"85204",
    "sg:province":"AZ",
    "sg:tags":[
        "clinic"
    ],
    "wof:name":"Concentra Managed Care Inc",
    "wof:placetype":"venue"
},
  "geometry": {"coordinates":[-111.753895,33.38032],"type":"Point"}
}