{
  "type": "Feature",
  "properties": {
    "iso:country":"US",
    "sg:address":"1331 W Melinda Ln",
    "sg:city":"Phoenix",
    "sg:classifiers":[
        {
            "category":"Home & Garden",
            "subcategory":"Building Materials",
            "type":"Retail Goods"
        },
        {
            "category":"Manufacturing",
            "subcategory":"Building Materials",
            "type":"Manufacturing & Wholesale Goods"
        }
    ],
    "sg:phone":"+1 623 869 8288",
    "sg:postcode":"85027",
    "sg:province":"AZ",
    "sg:tags":[
        "door",
        "mfg"
    ],
    "wof:name":"Heritage Custom Door & Mllwrk",
    "wof:placetype":"venue"
},
  "geometry": {"coordinates":[-112.089556,33.681595],"type":"Point"}
}