{
  "type": "Feature",
  "properties": {
    "addr:full":"2045 S 7th Ave Phoenix AZ 85007",
    "addr:housenumber":"2045",
    "addr:postcode":"85007",
    "addr:street":"S 7Th Ave",
    "iso:country":"US",
    "sg:address":"2045 S 7th Ave",
    "sg:city":"Phoenix",
    "sg:classifiers":[
        {
            "category":"Insurance",
            "subcategory":"Insurance Agent",
            "type":"Services"
        }
    ],
    "sg:phone":"+1 602 253 9717",
    "sg:postcode":"85007",
    "sg:province":"AZ",
    "wof:name":"Discount Zone",
    "wof:placetype":"venue"
},
  "geometry": {"coordinates":[-112.082363,33.427378],"type":"Point"}
}