{
  "type": "Feature",
  "properties": {
    "iso:country":"US",
    "sg:address":"188 S Debra Ct",
    "sg:city":"Gilbert",
    "sg:classifiers":[
        {
            "category":"Professional",
            "subcategory":"Engineering",
            "type":"Services"
        }
    ],
    "sg:phone":"+1 480 632 6135",
    "sg:postcode":"85296",
    "sg:province":"AZ",
    "sg:tags":[
        "engineer"
    ],
    "wof:name":"Robert TU Consulting",
    "wof:placetype":"venue"
},
  "geometry": {"coordinates":[-111.742633,33.346627],"type":"Point"}
}