{
  "type": "Feature",
  "properties": {
    "iso:country":"US",
    "sg:address":"1305 N Pomeroy",
    "sg:city":"Mesa",
    "sg:classifiers":[
        {
            "category":"Travel",
            "subcategory":"Travel Agent",
            "type":"Entertainment"
        }
    ],
    "sg:phone":"+1 480 835 6260",
    "sg:postcode":"85201",
    "sg:province":"AZ",
    "sg:tags":[
        "agency"
    ],
    "wof:name":"Lets Go Travel Inc",
    "wof:placetype":"venue"
},
  "geometry": {"coordinates":[-111.823184,33.439265],"type":"Point"}
}