{
  "type": "Feature",
  "properties": {
    "iso:country":"US",
    "sg:address":"2525 E Camelback Rd # 850",
    "sg:city":"Phoenix",
    "sg:classifiers":[
        {
            "category":"Professional",
            "subcategory":"Management & Consulting",
            "type":"Services"
        },
        {
            "category":"Banks & Credit Unions",
            "subcategory":"Financial Services",
            "type":"Services"
        }
    ],
    "sg:phone":"+1 602 224 7870",
    "sg:postcode":"85016",
    "sg:province":"AZ",
    "sg:tags":[
        "consultant",
        "financing",
        "planning"
    ],
    "wof:name":"Allsworth Investments",
    "wof:placetype":"venue"
},
  "geometry": {"coordinates":[-112.027273,33.509326],"type":"Point"}
}