{
  "type": "Feature",
  "properties": {
    "iso:country":"US",
    "sg:address":"3117 S Mill Ave",
    "sg:city":"Tempe",
    "sg:classifiers":[
        {
            "category":"Banks & Credit Unions",
            "subcategory":"Bank",
            "type":"Services"
        }
    ],
    "sg:phone":"+1 480 446 7554",
    "sg:postcode":"85282",
    "sg:province":"AZ",
    "sg:tags":[
        "cashing",
        "check"
    ],
    "wof:name":"Advance America",
    "wof:placetype":"venue"
},
  "geometry": {"coordinates":[-111.939548,33.395752],"type":"Point"}
}