{
  "type": "Feature",
  "properties": {
    "iso:country":"US",
    "sg:address":"250 N Litchfield Rd",
    "sg:city":"Goodyear",
    "sg:classifiers":[
        {
            "category":"Health Services",
            "subcategory":"Medical Lab",
            "type":"Services"
        }
    ],
    "sg:phone":"+1 623 925 0027",
    "sg:postcode":"85338",
    "sg:province":"AZ",
    "sg:tags":[
        "laboratory"
    ],
    "wof:name":"Sonora Quest Laboratories",
    "wof:placetype":"venue"
},
  "geometry": {"coordinates":[-112.358391,33.437356],"type":"Point"}
}