{
  "type": "Feature",
  "properties": {
    "iso:country":"US",
    "sg:address":"3041 S Kinney Rd",
    "sg:city":"Tucson",
    "sg:classifiers":[
        {
            "category":"Banks & Credit Unions",
            "subcategory":"Bank",
            "type":"Services"
        }
    ],
    "sg:phone":"+1 520 883 5527",
    "sg:postcode":"85713",
    "sg:province":"AZ",
    "wof:name":"Bank Of The West",
    "wof:placetype":"venue"
},
  "geometry": {"coordinates":[-111.094285,32.186859],"type":"Point"}
}