{
  "type": "Feature",
  "properties": {
    "iso:country":"US",
    "sg:address":"5516 N 72nd Drive",
    "sg:city":"Glendale",
    "sg:classifiers":[
        {
            "category":"Arts & Performance",
            "subcategory":"Arts Center",
            "type":"Entertainment"
        }
    ],
    "sg:phone":"+1 623 846 7704",
    "sg:postcode":"85303",
    "sg:province":"AZ",
    "sg:tags":[
        "performing"
    ],
    "wof:name":"Arizona Helen Contis Ballroom Repertory",
    "wof:placetype":"venue"
},
  "geometry": {"coordinates":[-112.215165,33.517178],"type":"Point"}
}