{
  "type": "Feature",
  "properties": {
    "iso:country":"US",
    "sg:address":"28534 E Los Angeles Ave",
    "sg:city":"Wellton",
    "sg:classifiers":[
        {
            "category":"Restaurant",
            "type":"Food & Drink"
        }
    ],
    "sg:phone":"+1 928 785 3131",
    "sg:postcode":"85356",
    "sg:province":"AZ",
    "sg:tags":[
        "style",
        "family"
    ],
    "wof:name":"Chuck's Stage Stop Restaurant",
    "wof:placetype":"venue"
},
  "geometry": {"coordinates":[-114.150118,32.671767],"type":"Point"}
}