{
  "type": "Feature",
  "properties": {
    "iso:country":"US",
    "sg:address":"2032 S Industrial Park Ave",
    "sg:city":"Tempe",
    "sg:classifiers":[
        {
            "category":"Professional",
            "subcategory":"Advertising",
            "type":"Services"
        },
        {
            "category":"Wholesale",
            "subcategory":"Non-durable Goods",
            "type":"Manufacturing & Wholesale Goods"
        }
    ],
    "sg:phone":"+1 480 966 7422",
    "sg:postcode":"85282",
    "sg:province":"AZ",
    "wof:name":"Five Star Specialties",
    "wof:placetype":"venue"
},
  "geometry": {"coordinates":[-111.955314,33.404153],"type":"Point"}
}