{
  "type": "Feature",
  "properties": {
    "iso:country":"US",
    "sg:address":"713 E Palo Verde Dr",
    "sg:city":"Phoenix",
    "sg:classifiers":[
        {
            "category":"Restaurant",
            "type":"Food & Drink"
        }
    ],
    "sg:menulink":"http://www.allmenus.com/az/phoenix/268592-fuego-bistro/menu/",
    "sg:phone":"+1 602 277 1151",
    "sg:postcode":"85014",
    "sg:province":"AZ",
    "wof:name":"Fuego Bistro",
    "wof:placetype":"venue"
},
  "geometry": {"coordinates":[-112.064072,33.521931],"type":"Point"}
}