{
  "type": "Feature",
  "properties": {
    "iso:country":"US",
    "sg:address":"2080 W Speedway Blvd",
    "sg:city":"Tucson",
    "sg:classifiers":[
        {
            "category":"Real Estate",
            "subcategory":"Real Estate Services",
            "type":"Services"
        },
        {
            "category":"Real Estate",
            "subcategory":"Real Estate Operator",
            "type":"Services"
        }
    ],
    "sg:phone":"+1 520 628 1401",
    "sg:postcode":"85745",
    "sg:province":"AZ",
    "sg:tags":[
        "vacancy",
        "apartment",
        "rental",
        "finder",
        "listing"
    ],
    "wof:name":"La Lomita Apartments",
    "wof:placetype":"venue"
},
  "geometry": {"coordinates":[-111.01100599999999,32.235601],"type":"Point"}
}