{
  "type": "Feature",
  "properties": {
    "addr:full":"4015 N Black Canyon Hwy Phoenix AZ 85015",
    "addr:housenumber":"4015",
    "addr:postcode":"85015",
    "addr:street":"N Black Canyon Hwy",
    "iso:country":"US",
    "sg:address":"4015 N Black Canyon Hwy",
    "sg:city":"Phoenix",
    "sg:classifiers":[
        {
            "category":"Retail",
            "subcategory":"Auto Repair",
            "type":"Services"
        }
    ],
    "sg:phone":"+1 602 265 2752",
    "sg:postcode":"85015",
    "sg:province":"AZ",
    "sg:tags":[
        "engines-rebuild",
        "repairing",
        "automobile",
        "exchange"
    ],
    "sg:website":"http://www.enginehouse.com",
    "wof:name":"Engine House",
    "wof:placetype":"venue"
},
  "geometry": {"coordinates":[-112.112606,33.494548],"type":"Point"}
}