{
  "type": "Feature",
  "properties": {
    "iso:country":"US",
    "sg:address":"209 E Baseline Rd",
    "sg:city":"Tempe",
    "sg:classifiers":[
        {
            "category":"Real Estate",
            "subcategory":"Real Estate Services",
            "type":"Services"
        }
    ],
    "sg:phone":"+1 480 734 0562",
    "sg:postcode":"85283",
    "sg:province":"AZ",
    "sg:tags":[
        "management",
        "condominium"
    ],
    "wof:name":"Kensington Place Condominium Association",
    "wof:placetype":"venue"
},
  "geometry": {"coordinates":[-111.936487,33.378228],"type":"Point"}
}