{
  "type": "Feature",
  "properties": {
    "iso:country":"US",
    "sg:address":"770 E 4th St",
    "sg:city":"Benson",
    "sg:classifiers":[
        {
            "category":"Retail",
            "subcategory":"Auto Repair",
            "type":"Services"
        }
    ],
    "sg:phone":"+1 520 586 3723",
    "sg:postcode":"85602",
    "sg:province":"AZ",
    "sg:tags":[
        "body",
        "automobile",
        "painting"
    ],
    "wof:name":"Big Sky Collision",
    "wof:placetype":"venue"
},
  "geometry": {"coordinates":[-110.286772,31.965908],"type":"Point"}
}