{
  "type": "Feature",
  "properties": {
    "iso:country":"US",
    "sg:address":"10065 E Mission Ln",
    "sg:city":"Scottsdale",
    "sg:classifiers":[
        {
            "category":"Professional",
            "subcategory":"Management & Consulting",
            "type":"Services"
        }
    ],
    "sg:phone":"+1 480 391 1464",
    "sg:postcode":"85258",
    "sg:province":"AZ",
    "sg:tags":[
        "consultant",
        "business"
    ],
    "sg:website":"www.frontlineadvantage.com",
    "wof:name":"Front Line Advantage",
    "wof:placetype":"venue"
},
  "geometry": {"coordinates":[-111.866372,33.570522],"type":"Point"}
}