{
  "type": "Feature",
  "properties": {
    "addr:full":"4245 W Bethany Home Rd Phoenix AZ 85019",
    "addr:housenumber":"4245",
    "addr:postcode":"85019",
    "addr:street":"W Bethany Home Rd",
    "iso:country":"US",
    "sg:address":"4245 W Bethany Home Rd",
    "sg:city":"Phoenix",
    "sg:classifiers":[
        {
            "category":"Autos & Motor Vehicles",
            "subcategory":"Fuel & Gas Station",
            "type":"Retail Goods"
        }
    ],
    "sg:phone":"+1 602 973 8442",
    "sg:postcode":"85019",
    "sg:province":"AZ",
    "sg:tags":[
        "oil"
    ],
    "wof:name":"Arco",
    "wof:placetype":"venue"
},
  "geometry": {"coordinates":[-112.150533,33.523847],"type":"Point"}
}