{
  "type": "Feature",
  "properties": {
    "iso:country":"US",
    "sg:address":"2080 W Orange Grove Rd",
    "sg:city":"Tucson",
    "sg:classifiers":[
        {
            "category":"Restaurant",
            "type":"Food & Drink"
        }
    ],
    "sg:phone":"+1 520 219 7215",
    "sg:postcode":"85704",
    "sg:province":"AZ",
    "sg:tags":[
        "eating"
    ],
    "wof:name":"Ole Mexican Grill",
    "wof:placetype":"venue"
},
  "geometry": {"coordinates":[-111.008431,32.323214],"type":"Point"}
}