{
  "type": "Feature",
  "properties": {
    "addr:full":"15639 N Dysart Rd Surprise AZ 85374",
    "addr:housenumber":"15639",
    "addr:postcode":"85374",
    "addr:street":"N Dysart Rd",
    "iso:country":"US",
    "sg:address":"15639 N Dysart Rd",
    "sg:city":"Surprise",
    "sg:classifiers":[
        {
            "category":"Wholesale",
            "subcategory":"Machinery & Supplies",
            "type":"Manufacturing & Wholesale Goods"
        },
        {
            "category":"Building & Trades",
            "subcategory":"Equipment Rental",
            "type":"Services"
        }
    ],
    "sg:phone":"+1 623 546 3400",
    "sg:postcode":"85374",
    "sg:province":"AZ",
    "sg:tags":[
        "leasing",
        "industrial",
        "yard",
        "store",
        "contractors'"
    ],
    "wof:name":"Surprise Rental",
    "wof:placetype":"venue"
},
  "geometry": {"coordinates":[-112.342073,33.62684],"type":"Point"}
}