{
  "type": "Feature",
  "properties": {
    "iso:country":"US",
    "sg:address":"1520 S Dobson Rd Ste 202",
    "sg:city":"Mesa",
    "sg:classifiers":[
        {
            "category":"Health Services",
            "subcategory":"Doctor",
            "type":"Services"
        }
    ],
    "sg:phone":"+1 480 835 0709",
    "sg:postcode":"85202",
    "sg:province":"AZ",
    "sg:tags":[
        "physician",
        "surgeon"
    ],
    "wof:name":"Karen Robertson Md",
    "wof:placetype":"venue"
},
  "geometry": {"coordinates":[-111.87462499999999,33.38751],"type":"Point"}
}