{
  "type": "Feature",
  "properties": {
    "iso:country":"US",
    "sg:address":"5546 W Roosevelt St",
    "sg:city":"Phoenix",
    "sg:classifiers":[
        {
            "category":"Health Services",
            "subcategory":"Doctor",
            "type":"Services"
        }
    ],
    "sg:phone":"+1 602 352 1012",
    "sg:postcode":"85043",
    "sg:province":"AZ",
    "sg:tags":[
        "clinic"
    ],
    "wof:name":"Estrella Dialysis",
    "wof:placetype":"venue"
},
  "geometry": {"coordinates":[-112.178521,33.458838],"type":"Point"}
}