{
  "type": "Feature",
  "properties": {
    "addr:full":"1450 N 27th Ave Phoenix AZ 85009",
    "addr:housenumber":"1450",
    "addr:postcode":"85009",
    "addr:street":"N 27Th Ave",
    "iso:country":"US",
    "sg:address":"1450 N 27th Ave",
    "sg:city":"Phoenix",
    "sg:classifiers":[
        {
            "category":"Home & Garden",
            "subcategory":"Furniture",
            "type":"Retail Goods"
        }
    ],
    "sg:phone":"+1 602 299 2144",
    "sg:postcode":"85009",
    "sg:province":"AZ",
    "sg:tags":[
        "store"
    ],
    "wof:name":"D&D Furniture Discounters",
    "wof:placetype":"venue"
},
  "geometry": {"coordinates":[-112.11718,33.464874],"type":"Point"}
}