{
  "type": "Feature",
  "properties": {
    "iso:country":"US",
    "sg:address":"722 E Osborn Rd",
    "sg:city":"Phoenix",
    "sg:classifiers":[
        {
            "category":"Professional",
            "subcategory":"Employment Agencies",
            "type":"Services"
        }
    ],
    "sg:phone":"+1 602 264 0606",
    "sg:postcode":"85014",
    "sg:province":"AZ",
    "sg:tags":[
        "help",
        "contractor"
    ],
    "wof:name":"Childcare Careers",
    "wof:placetype":"venue"
},
  "geometry": {"coordinates":[-112.061654,33.487546],"type":"Point"}
}