{
  "type": "Feature",
  "properties": {
    "iso:country":"US",
    "sg:address":"1222 E Baseline Road Suite 200",
    "sg:city":"Tempe",
    "sg:classifiers":[
        {
            "category":"Professional",
            "subcategory":"Accounting & Tax Preparation",
            "type":"Services"
        }
    ],
    "sg:phone":"+1 480 831 9500",
    "sg:postcode":"85283",
    "sg:province":"AZ",
    "sg:tags":[
        "accountant"
    ],
    "wof:name":"Mansperger Patterson & McMullin Cpa's",
    "wof:placetype":"venue"
},
  "geometry": {"coordinates":[-111.919838,33.378366],"type":"Point"}
}