{
  "type": "Feature",
  "properties": {
    "iso:country":"US",
    "sg:address":"1802 W Saint Marys Rd",
    "sg:city":"Tucson",
    "sg:classifiers":[
        {
            "category":"Professional",
            "type":"Services"
        }
    ],
    "sg:phone":"+1 520 628 1991",
    "sg:postcode":"85745",
    "sg:province":"AZ",
    "sg:tags":[
        "establishment"
    ],
    "wof:name":"Holy Family Ctr",
    "wof:placetype":"venue"
},
  "geometry": {"coordinates":[-111.005064,32.227132],"type":"Point"}
}