{
  "type": "Feature",
  "properties": {
    "addr:full":"4745 N 7th St Phoenix AZ 85014",
    "addr:housenumber":"4745",
    "addr:postcode":"85014",
    "addr:street":"N 7Th St",
    "iso:country":"US",
    "sg:address":"4745 N 7th St",
    "sg:city":"Phoenix",
    "sg:classifiers":[
        {
            "category":"Wholesale",
            "subcategory":"Groceries",
            "type":"Manufacturing & Wholesale Goods"
        }
    ],
    "sg:phone":"+1 602 277 1850",
    "sg:postcode":"85014",
    "sg:province":"AZ",
    "wof:name":"Nabisco",
    "wof:placetype":"venue"
},
  "geometry": {"coordinates":[-112.064948,33.505137],"type":"Point"}
}