{
  "type": "Feature",
  "properties": {
    "iso:country":"US",
    "sg:address":"4406 E McDowell Rd",
    "sg:city":"Phoenix",
    "sg:classifiers":[
        {
            "category":"Personal",
            "subcategory":"Barber",
            "type":"Services"
        }
    ],
    "sg:phone":"+1 602 267 0277",
    "sg:postcode":"85008",
    "sg:province":"AZ",
    "wof:name":"Better Cut Barber Shop",
    "wof:placetype":"venue"
},
  "geometry": {"coordinates":[-111.982401,33.465716],"type":"Point"}
}