{
  "type": "Feature",
  "properties": {
    "addr:full":"161 W Main St Mesa AZ 85201",
    "addr:housenumber":"161",
    "addr:postcode":"85201",
    "addr:street":"W Main St",
    "iso:country":"US",
    "sg:address":"161 W Main St",
    "sg:city":"Mesa",
    "sg:classifiers":[
        {
            "category":"Restaurant",
            "type":"Food & Drink"
        }
    ],
    "sg:menulink":"http://www.allmenus.com/az/phoenix/64035-subway/menu/",
    "sg:phone":"+1 480 644 9590",
    "sg:postcode":"85201",
    "sg:province":"AZ",
    "sg:tags":[
        "american",
        "sandwich"
    ],
    "wof:name":"Subway",
    "wof:placetype":"venue"
},
  "geometry": {"coordinates":[-111.83566,33.414943],"type":"Point"}
}