{
  "type": "Feature",
  "properties": {
    "addr:full":"2111 W University Dr Tempe AZ 85281",
    "addr:housenumber":"2111",
    "addr:postcode":"85281",
    "addr:street":"W University Dr",
    "iso:country":"US",
    "sg:address":"2111 W University Dr",
    "sg:city":"Tempe",
    "sg:classifiers":[
        {
            "category":"Food & Beverages",
            "subcategory":"Groceries & Convenience Stores",
            "type":"Retail Goods"
        }
    ],
    "sg:phone":"+1 480 966 2738",
    "sg:postcode":"85281",
    "sg:province":"AZ",
    "sg:website":"http://www.quiktrip.com",
    "wof:name":"Quiktrip",
    "wof:placetype":"venue"
},
  "geometry": {"coordinates":[-111.970803,33.421937],"type":"Point"}
}