{
  "type": "Feature",
  "properties": {
    "addr:full":"5027 W Sanna St Glendale AZ 85302",
    "addr:housenumber":"5027",
    "addr:postcode":"85302",
    "addr:street":"W Sanna St",
    "iso:country":"US",
    "sg:address":"5027 W Sanna St",
    "sg:city":"Glendale",
    "sg:classifiers":[
        {
            "category":"Building & Trades",
            "subcategory":"Construction",
            "type":"Services"
        }
    ],
    "sg:phone":"+1 623 939 1752",
    "sg:postcode":"85302",
    "sg:province":"AZ",
    "sg:tags":[
        "contractor"
    ],
    "wof:name":"Surface World",
    "wof:placetype":"venue"
},
  "geometry": {"coordinates":[-112.167233,33.569637],"type":"Point"}
}