{
  "type": "Feature",
  "properties": {
    "iso:country":"US",
    "sg:address":"6246 N 27th Ave",
    "sg:city":"Phoenix",
    "sg:classifiers":[
        {
            "category":"Education",
            "subcategory":"Special Training",
            "type":"Public Place"
        }
    ],
    "sg:phone":"+1 602 242 8600",
    "sg:postcode":"85017",
    "sg:province":"AZ",
    "sg:tags":[
        "center"
    ],
    "wof:name":"Huntington Learning Ctr",
    "wof:placetype":"venue"
},
  "geometry": {"coordinates":[-112.11697,33.527929],"type":"Point"}
}