{
  "type": "Feature",
  "properties": {
    "addr:full":"2462 N Indian Ruins Rd Tucson AZ 85715",
    "addr:housenumber":"2462",
    "addr:postcode":"85715",
    "addr:street":"N Indian Ruins Rd",
    "iso:country":"US",
    "sg:address":"2462 N Indian Ruins Rd",
    "sg:city":"Tucson",
    "sg:classifiers":[
        {
            "category":"Wholesale",
            "subcategory":"Durable Goods & Equipment",
            "type":"Manufacturing & Wholesale Goods"
        }
    ],
    "sg:phone":"+1 520 296 0950",
    "sg:postcode":"85715",
    "sg:province":"AZ",
    "sg:tags":[
        "mfg",
        "representative",
        "souvenir"
    ],
    "wof:name":"Welchs and Associates",
    "wof:placetype":"venue"
},
  "geometry": {"coordinates":[-110.84515500000001,32.252931],"type":"Point"}
}