{
  "type": "Feature",
  "properties": {
    "iso:country":"US",
    "sg:address":"3001 E Skyline Dr",
    "sg:city":"Tucson",
    "sg:classifiers":[
        {
            "category":"Restaurant",
            "type":"Food & Drink"
        }
    ],
    "sg:phone":"+1 520 299 3345",
    "sg:postcode":"85718",
    "sg:province":"AZ",
    "sg:website":"www.soleiltucson.com",
    "wof:name":"Soleil Casual-Chic Dining",
    "wof:placetype":"venue"
},
  "geometry": {"coordinates":[-110.924656,32.322691],"type":"Point"}
}