{
  "type": "Feature",
  "properties": {
    "addr:full":"8213 S 7th St Phoenix AZ 85042",
    "addr:housenumber":"8213",
    "addr:postcode":"85042",
    "addr:street":"S 7Th St",
    "iso:country":"US",
    "sg:address":"8213 S 7th St",
    "sg:city":"Phoenix",
    "sg:classifiers":[
        {
            "category":"Organizations",
            "subcategory":"Religious Organization",
            "type":"Services"
        }
    ],
    "sg:phone":"+1 602 323 0144",
    "sg:postcode":"85042",
    "sg:province":"AZ",
    "sg:tags":[
        "church"
    ],
    "wof:name":"Heaven Gate Praise Fellowship",
    "wof:placetype":"venue"
},
  "geometry": {"coordinates":[-112.065979,33.370596],"type":"Point"}
}