{
  "type": "Feature",
  "properties": {
    "addr:full":"4433 E Main St Mesa AZ 85205",
    "addr:housenumber":"4433",
    "addr:postcode":"85205",
    "addr:street":"E Main St",
    "iso:country":"US",
    "sg:address":"4433 E Main St",
    "sg:city":"Mesa",
    "sg:classifiers":[
        {
            "category":"Fast Food",
            "type":"Food & Drink"
        },
        {
            "category":"Restaurant",
            "type":"Food & Drink"
        }
    ],
    "sg:phone":"+1 480 832 2861",
    "sg:postcode":"85205",
    "sg:province":"AZ",
    "sg:tags":[
        "american",
        "hot",
        "hamburger",
        "dog"
    ],
    "sg:website":"http://www.wendys.com",
    "wof:name":"Wendy's",
    "wof:placetype":"venue"
},
  "geometry": {"coordinates":[-111.68781300000001,33.415575],"type":"Point"}
}