{
  "type": "Feature",
  "properties": {
    "addr:full":"2320 W Peoria Ave D133 Phoenix AZ 85029",
    "addr:housenumber":"2320",
    "addr:postcode":"85029",
    "addr:street":"W Peoria Ave",
    "iso:country":"US",
    "sg:address":"2320 W Peoria Ave D133",
    "sg:city":"Phoenix",
    "sg:classifiers":[
        {
            "category":"Social Services",
            "subcategory":"Adult Care",
            "type":"Services"
        }
    ],
    "sg:phone":"+1 602 395 5900",
    "sg:postcode":"85029",
    "sg:province":"AZ",
    "sg:tags":[
        "calibration"
    ],
    "wof:name":"Bell Technologies Calibration Division",
    "wof:placetype":"venue"
},
  "geometry": {"coordinates":[-112.10843300000001,33.582007],"type":"Point"}
}