{
  "type": "Feature",
  "properties": {
    "addr:full":"5602 N 27th Ave Phoenix AZ 85017",
    "addr:housenumber":"5602",
    "addr:postcode":"85017",
    "addr:street":"N 27Th Ave",
    "iso:country":"US",
    "sg:address":"5602 N 27th Ave",
    "sg:city":"Phoenix",
    "sg:classifiers":[
        {
            "category":"Professional",
            "subcategory":"Printing & Photocopies",
            "type":"Services"
        }
    ],
    "sg:phone":"+1 602 249 2900",
    "sg:postcode":"85017",
    "sg:province":"AZ",
    "sg:tags":[
        "blueprinting"
    ],
    "sg:website":"www.fastprint-phx.com",
    "wof:name":"Fastprint Reprographics Inc",
    "wof:placetype":"venue"
},
  "geometry": {"coordinates":[-112.117007,33.519437],"type":"Point"}
}