{
  "type": "Feature",
  "properties": {
    "iso:country":"US",
    "sg:address":"3514 E Indian School Rd",
    "sg:city":"Phoenix",
    "sg:classifiers":[
        {
            "category":"Health Services",
            "subcategory":"Chiropractor",
            "type":"Services"
        }
    ],
    "sg:phone":"+1 602 955 7400",
    "sg:postcode":"85018",
    "sg:province":"AZ",
    "wof:name":"Chiropractic Arts Ctr",
    "wof:placetype":"venue"
},
  "geometry": {"coordinates":[-112.004523,33.495257],"type":"Point"}
}