{
  "type": "Feature",
  "properties": {
    "iso:country":"US",
    "sg:address":"123 N San Francisco St",
    "sg:city":"Flagstaff",
    "sg:classifiers":[
        {
            "category":"Government",
            "subcategory":"Office",
            "type":"Public Place"
        }
    ],
    "sg:phone":"+1 928 556 7060",
    "sg:postcode":"86001",
    "sg:province":"AZ",
    "wof:name":"US Pretrial Svc",
    "wof:placetype":"venue"
},
  "geometry": {"coordinates":[-111.647335,35.198867],"type":"Point"}
}