{
  "type": "Feature",
  "properties": {
    "iso:country":"US",
    "sg:address":"7455 W Cactus Rd",
    "sg:city":"Peoria",
    "sg:classifiers":[
        {
            "category":"Banks & Credit Unions",
            "subcategory":"Bank",
            "type":"Services"
        }
    ],
    "sg:phone":"+1 623 000 1111",
    "sg:postcode":"85381",
    "sg:province":"AZ",
    "wof:name":"Bank One",
    "wof:placetype":"venue"
},
  "geometry": {"coordinates":[-112.218057,33.595833],"type":"Point"}
}