{
  "type": "Feature",
  "properties": {
    "iso:country":"US",
    "sg:address":"320 E Willetta St",
    "sg:city":"Phoenix",
    "sg:classifiers":[
        {
            "category":"Education",
            "subcategory":"Vocational School",
            "type":"Public Place"
        }
    ],
    "sg:phone":"+1 602 253 8589",
    "sg:postcode":"85004",
    "sg:province":"AZ",
    "wof:name":"Southern Arizona Business Schl",
    "wof:placetype":"venue"
},
  "geometry": {"coordinates":[-112.067774,33.463998],"type":"Point"}
}