{
  "type": "Feature",
  "properties": {
    "addr:full":"7535 W Carol Ave Peoria AZ 85345",
    "addr:housenumber":"7535",
    "addr:postcode":"85345",
    "addr:street":"W Carol Ave",
    "iso:country":"US",
    "sg:address":"7535 W Carol Ave",
    "sg:city":"Peoria",
    "sg:classifiers":[
        {
            "category":"Retail",
            "subcategory":"Auto Repair",
            "type":"Services"
        }
    ],
    "sg:phone":"+1 623 334 8388",
    "sg:postcode":"85345",
    "sg:province":"AZ",
    "sg:tags":[
        "body",
        "automobile",
        "painting"
    ],
    "wof:name":"Collisions Solutions Body",
    "wof:placetype":"venue"
},
  "geometry": {"coordinates":[-112.220924,33.571375],"type":"Point"}
}