{
  "type": "Feature",
  "properties": {
    "iso:country":"US",
    "sg:address":"4758 E Grant Rd",
    "sg:city":"Tucson",
    "sg:classifiers":[
        {
            "category":"Manufacturing",
            "subcategory":"Printing",
            "type":"Manufacturing & Wholesale Goods"
        }
    ],
    "sg:phone":"+1 520 327 5708",
    "sg:postcode":"85712",
    "sg:province":"AZ",
    "sg:tags":[
        "copying",
        "offset"
    ],
    "wof:name":"Insty-Prints",
    "wof:placetype":"venue"
},
  "geometry": {"coordinates":[-110.891674,32.250574],"type":"Point"}
}