{
  "type": "Feature",
  "properties": {
    "iso:country":"US",
    "sg:address":"4023 N 47th Ave",
    "sg:city":"Phoenix",
    "sg:classifiers":[
        {
            "category":"Food & Beverages",
            "subcategory":"Groceries & Convenience Stores",
            "type":"Retail Goods"
        }
    ],
    "sg:phone":"+1 602 278 5280",
    "sg:postcode":"85031",
    "sg:province":"AZ",
    "sg:website":"http://www.circlek.com",
    "wof:name":"Circle K",
    "wof:placetype":"venue"
},
  "geometry": {"coordinates":[-112.160263,33.493721],"type":"Point"}
}