{
  "type": "Feature",
  "properties": {
    "addr:full":"7518 E Cam Santo Scottsdale AZ 85260",
    "addr:housenumber":"7518",
    "addr:postcode":"85260",
    "addr:street":"E Cam Santo",
    "iso:country":"US",
    "sg:address":"7518 E Cam Santo",
    "sg:city":"Scottsdale",
    "sg:classifiers":[
        {
            "category":"Building & Trades",
            "subcategory":"Construction",
            "type":"Services"
        }
    ],
    "sg:phone":"+1 480 998 8936",
    "sg:postcode":"85260",
    "sg:province":"AZ",
    "sg:tags":[
        "hanging",
        "contractor"
    ],
    "wof:name":"Jvr Painting",
    "wof:placetype":"venue"
},
  "geometry": {"coordinates":[-111.920051,33.606492],"type":"Point"}
}