{
  "type": "Feature",
  "properties": {
    "iso:country":"US",
    "sg:address":"2318 Navajo Blvd",
    "sg:city":"Holbrook",
    "sg:classifiers":[
        {
            "category":"Restaurant",
            "type":"Food & Drink"
        }
    ],
    "sg:phone":"+1 928 524 6696",
    "sg:postcode":"86025",
    "sg:province":"AZ",
    "sg:tags":[
        "italian"
    ],
    "wof:name":"Mesa Italiana Restaurant",
    "wof:placetype":"venue"
},
  "geometry": {"coordinates":[-110.132579,34.937023],"type":"Point"}
}