{
  "type": "Feature",
  "properties": {
    "addr:full":"2318 Navajo Blvd Holbrook AZ 86025",
    "addr:housenumber":"2318",
    "addr:postcode":"86025",
    "addr:street":"Navajo Blvd",
    "iso:country":"US",
    "sg:address":"2318 Navajo Blvd",
    "sg:city":"Holbrook",
    "sg:classifiers":[
        {
            "category":"Restaurant",
            "type":"Food & Drink"
        }
    ],
    "sg:phone":"+1 928 524 6696",
    "sg:postcode":"86025",
    "sg:province":"AZ",
    "sg:tags":[
        "italian"
    ],
    "wof:name":"Mesa Italiana Restaurant",
    "wof:placetype":"venue"
},
  "geometry": {"coordinates":[-110.13257900000001,34.937023],"type":"Point"}
}