{
  "type": "Feature",
  "properties": {
    "addr:full":"4111 East Valley Auto Drive, Suite 201 Mesa AZ 85206",
    "addr:housenumber":"4111",
    "addr:postcode":"85206",
    "addr:street":"East;Auto Drive Suite 201",
    "iso:country":"US",
    "sg:address":"4111 East Valley Auto Drive, Suite 201",
    "sg:city":"Mesa",
    "sg:classifiers":[
        {
            "category":"Health Services",
            "subcategory":"Clinic",
            "type":"Services"
        }
    ],
    "sg:phone":"+1 480 966 9337",
    "sg:postcode":"85206",
    "sg:province":"AZ",
    "sg:tags":[
        "psychological"
    ],
    "sg:website":"http://www.michaeltansy.com",
    "wof:name":"Michael Tansy, PhD",
    "wof:placetype":"venue"
},
  "geometry": {"coordinates":[-111.744,33.381279],"type":"Point"}
}