{
  "type": "Feature",
  "properties": {
    "iso:country":"US",
    "sg:address":"1937 E Greentree Dr",
    "sg:city":"Tempe",
    "sg:classifiers":[
        {
            "category":"Insurance",
            "subcategory":"Title Insurance",
            "type":"Services"
        }
    ],
    "sg:phone":"+1 480 839 1523",
    "sg:postcode":"85284",
    "sg:province":"AZ",
    "sg:tags":[
        "carrier",
        "real estate"
    ],
    "wof:name":"Rose Brandenberger Ltd",
    "wof:placetype":"venue"
},
  "geometry": {"coordinates":[-111.906114,33.332076],"type":"Point"}
}