{
  "type": "Feature",
  "properties": {
    "iso:country":"US",
    "sg:address":"4931 W Brill St",
    "sg:city":"Phoenix",
    "sg:classifiers":[
        {
            "category":"Manufacturing",
            "subcategory":"Glass & Minerals",
            "type":"Manufacturing & Wholesale Goods"
        }
    ],
    "sg:phone":"+1 602 353 0650",
    "sg:postcode":"85043",
    "sg:province":"AZ",
    "sg:tags":[
        "glass-wholesale",
        "shape",
        "circle",
        "special",
        "manufacturer"
    ],
    "wof:name":"Trainor Glass Company",
    "wof:placetype":"venue"
},
  "geometry": {"coordinates":[-112.164862,33.464648],"type":"Point"}
}