{
  "type": "Feature",
  "properties": {
    "addr:full":"10325 E Riggs Rd Chandler AZ 85248",
    "addr:housenumber":"10325",
    "addr:postcode":"85248",
    "addr:street":"E Riggs Rd",
    "iso:country":"US",
    "sg:address":"10325 E Riggs Rd",
    "sg:city":"Chandler",
    "sg:classifiers":[
        {
            "category":"Restaurant",
            "type":"Food & Drink"
        }
    ],
    "sg:phone":"+1 480 802 9888",
    "sg:postcode":"85248",
    "sg:province":"AZ",
    "sg:tags":[
        "asian"
    ],
    "wof:name":"Asian Grill",
    "wof:placetype":"venue"
},
  "geometry": {"coordinates":[-111.85929400000001,33.21824],"type":"Point"}
}