{
  "type": "Feature",
  "properties": {
    "addr:full":"2501 W Dunlap Ave Phoenix AZ 85021",
    "addr:housenumber":"2501",
    "addr:postcode":"85021",
    "addr:street":"W Dunlap Ave",
    "iso:country":"US",
    "sg:address":"2501 W Dunlap Ave",
    "sg:city":"Phoenix",
    "sg:classifiers":[
        {
            "category":"Wholesale",
            "subcategory":"Meat",
            "type":"Manufacturing & Wholesale Goods"
        }
    ],
    "sg:phone":"+1 602 944 9466",
    "sg:postcode":"85021",
    "sg:province":"AZ",
    "sg:tags":[
        "poultry",
        "broker"
    ],
    "wof:name":"Perishable Mdsg & Mktg",
    "wof:placetype":"venue"
},
  "geometry": {"coordinates":[-112.11684700000001,33.567578],"type":"Point"}
}