{
  "type": "Feature",
  "properties": {
    "addr:full":"1431 W Thatcher Blvd Safford AZ 85546",
    "addr:housenumber":"1431",
    "addr:postcode":"85546",
    "addr:street":"W Thatcher Blvd",
    "iso:country":"US",
    "sg:address":"1431 W Thatcher Blvd",
    "sg:city":"Safford",
    "sg:classifiers":[
        {
            "category":"Social Services",
            "type":"Services"
        }
    ],
    "sg:phone":"+1 928 428 2952",
    "sg:postcode":"85546",
    "sg:province":"AZ",
    "sg:tags":[
        "counselor",
        "marriage",
        "family"
    ],
    "wof:name":"Jorgensen Counseling Inc",
    "wof:placetype":"venue"
},
  "geometry": {"coordinates":[-109.725227,32.834841],"type":"Point"}
}