{
  "type": "Feature",
  "properties": {
    "iso:country":"US",
    "sg:address":"1901 N 16th St",
    "sg:city":"Phoenix",
    "sg:classifiers":[
        {
            "category":"Professional",
            "subcategory":"Business Services",
            "type":"Services"
        }
    ],
    "sg:phone":"+1 602 222 9100",
    "sg:postcode":"85006",
    "sg:province":"AZ",
    "sg:tags":[
        "paralegal"
    ],
    "wof:name":"Quick & Easy Legal Svc",
    "wof:placetype":"venue"
},
  "geometry": {"coordinates":[-112.047664,33.469374],"type":"Point"}
}