{
  "type": "Feature",
  "properties": {
    "iso:country":"US",
    "sg:address":"3910 N 107th Ave",
    "sg:city":"Avondale",
    "sg:classifiers":[
        {
            "category":"Retail",
            "subcategory":"Auto Repair",
            "type":"Services"
        }
    ],
    "sg:phone":"+1 623 877 0767",
    "sg:postcode":"85323",
    "sg:province":"AZ",
    "sg:tags":[
        "repairing",
        "automobile"
    ],
    "wof:name":"Joe's Auto",
    "wof:placetype":"venue"
},
  "geometry": {"coordinates":[-112.290001,33.4916],"type":"Point"}
}