{
  "type": "Feature",
  "properties": {
    "iso:country":"US",
    "sg:address":"5732 W Shannon St",
    "sg:city":"Chandler",
    "sg:classifiers":[
        {
            "category":"Health Services",
            "subcategory":"Clinic",
            "type":"Services"
        }
    ],
    "sg:phone":"+1 480 940 1082",
    "sg:postcode":"85226",
    "sg:province":"AZ",
    "wof:name":"Physico Health Assessments",
    "wof:placetype":"venue"
},
  "geometry": {"coordinates":[-111.938382,33.31804],"type":"Point"}
}