{
  "type": "Feature",
  "properties": {
    "iso:country":"US",
    "sg:address":"8936 N Central Ave",
    "sg:city":"Phoenix",
    "sg:classifiers":[
        {
            "category":"Farming",
            "subcategory":"Livestock Farm",
            "type":"Manufacturing & Wholesale Goods"
        }
    ],
    "sg:phone":"+1 602 346 4500",
    "sg:postcode":"85020",
    "sg:province":"AZ",
    "sg:tags":[
        "veterinary",
        "specialty",
        "animal"
    ],
    "wof:name":"Animal Instinct",
    "wof:placetype":"venue"
},
  "geometry": {"coordinates":[-112.073967,33.566551],"type":"Point"}
}