{
  "type": "Feature",
  "properties": {
    "addr:full":"1702 Jefferson St Kingman AZ 86401",
    "addr:housenumber":"1702",
    "addr:postcode":"86401",
    "addr:street":"Jefferson St",
    "iso:country":"US",
    "sg:address":"1702 Jefferson St",
    "sg:city":"Kingman",
    "sg:classifiers":[
        {
            "category":"Building & Trades",
            "subcategory":"Construction",
            "type":"Services"
        }
    ],
    "sg:phone":"+1 928 753 5389",
    "sg:postcode":"86401",
    "sg:province":"AZ",
    "sg:tags":[
        "contractor",
        "painting",
        "hanging"
    ],
    "wof:name":"S&S Reapir & Painting",
    "wof:placetype":"venue"
},
  "geometry": {"coordinates":[-114.03550199999999,35.19659],"type":"Point"}
}