{
  "type": "Feature",
  "properties": {
    "iso:country":"US",
    "sg:address":"1124 N Main St",
    "sg:city":"Cottonwood",
    "sg:classifiers":[
        {
            "category":"Restaurant",
            "type":"Food & Drink"
        }
    ],
    "sg:phone":"+1 928 649 9680",
    "sg:postcode":"86326",
    "sg:province":"AZ",
    "sg:tags":[
        "mexican"
    ],
    "wof:name":"Concho's Mexican Restaurant",
    "wof:placetype":"venue"
},
  "geometry": {"coordinates":[-112.02824,34.749962],"type":"Point"}
}