{
  "type": "Feature",
  "properties": {
    "addr:full":"2174 E Williams Field Rd Ste 109 Gilbert AZ 85295",
    "addr:housenumber":"2174",
    "addr:postcode":"85295",
    "addr:street":"E Williams Field Rd Ste 109",
    "iso:country":"US",
    "sg:address":"2174 E Williams Field Rd Ste 109",
    "sg:city":"Gilbert",
    "sg:classifiers":[
        {
            "category":"Shopping",
            "subcategory":"Shoes",
            "type":"Retail Goods"
        }
    ],
    "sg:phone":"+1 480 917 2949",
    "sg:postcode":"85295",
    "sg:province":"AZ",
    "sg:tags":[
        "store"
    ],
    "wof:name":"Stride Rite",
    "wof:placetype":"venue"
},
  "geometry": {"coordinates":[-111.744343,33.307005],"type":"Point"}
}