{
  "type": "Feature",
  "properties": {
    "iso:country":"US",
    "sg:address":"3401 N Pleasant View Dr",
    "sg:city":"Prescott Valley",
    "sg:classifiers":[
        {
            "category":"Building & Trades",
            "subcategory":"Construction",
            "type":"Services"
        }
    ],
    "sg:phone":"+1 928 772 8388",
    "sg:postcode":"86314",
    "sg:province":"AZ",
    "sg:tags":[
        "house"
    ],
    "wof:name":"Native Builders",
    "wof:placetype":"venue"
},
  "geometry": {"coordinates":[-112.3439,34.590367],"type":"Point"}
}