{
  "type": "Feature",
  "properties": {
    "iso:country":"US",
    "sg:address":"11639 N 91st Ln",
    "sg:city":"Scottsdale",
    "sg:classifiers":[
        {
            "category":"Wholesale",
            "subcategory":"Stationery",
            "type":"Manufacturing & Wholesale Goods"
        }
    ],
    "sg:phone":"+1 602 569 9154",
    "sg:postcode":"85260",
    "sg:province":"AZ",
    "sg:tags":[
        "business",
        "form",
        "system"
    ],
    "wof:name":"Symphony Business Systems",
    "wof:placetype":"venue"
},
  "geometry": {"coordinates":[-111.883988,33.593307],"type":"Point"}
}