{
  "type": "Feature",
  "properties": {
    "iso:country":"US",
    "sg:address":"2558 E Lehi Rd",
    "sg:city":"Mesa",
    "sg:classifiers":[
        {
            "category":"Wholesale",
            "subcategory":"Plants",
            "type":"Manufacturing & Wholesale Goods"
        },
        {
            "category":"Farming",
            "subcategory":"Nursery",
            "type":"Manufacturing & Wholesale Goods"
        }
    ],
    "sg:phone":"+1 480 830 8000",
    "sg:postcode":"85213",
    "sg:province":"AZ",
    "sg:tags":[
        "ornamental",
        "tree",
        "supply"
    ],
    "sg:website":"www.greenfieldcitrus.com",
    "wof:name":"Greenfield Citrus Nursery Inc",
    "wof:placetype":"venue"
},
  "geometry": {"coordinates":[-111.77721699999999,33.469537],"type":"Point"}
}