{
  "type": "Feature",
  "properties": {
    "addr:full":"101 W Mohave St Phoenix AZ 85003",
    "addr:housenumber":"101",
    "addr:postcode":"85003",
    "addr:street":"W Mohave St",
    "iso:country":"US",
    "sg:address":"101 W Mohave St",
    "sg:city":"Phoenix",
    "sg:classifiers":[
        {
            "category":"Professional",
            "subcategory":"Testing Lab",
            "type":"Services"
        }
    ],
    "sg:phone":"+1 602 253 6515",
    "sg:postcode":"85003",
    "sg:province":"AZ",
    "sg:tags":[
        "laboratory"
    ],
    "sg:website":"www.ctclink.com",
    "wof:name":"CTC Analytical Svc",
    "wof:placetype":"venue"
},
  "geometry": {"coordinates":[-112.07726700000001,33.431143],"type":"Point"}
}