{
  "type": "Feature",
  "properties": {
    "addr:full":"830 N Rd 1 E Chino Valley AZ 86323",
    "addr:housenumber":"830",
    "addr:postcode":"86323",
    "addr:street":"N Rd 1 E Chino Valley",
    "iso:country":"US",
    "sg:address":"830 N Rd 1 E",
    "sg:city":"Chino Valley",
    "sg:classifiers":[
        {
            "category":"Home & Garden",
            "subcategory":"Furniture",
            "type":"Retail Goods"
        }
    ],
    "sg:phone":"+1 928 636 4616",
    "sg:postcode":"86323",
    "sg:province":"AZ",
    "sg:tags":[
        "cabinet"
    ],
    "wof:name":"Walls Of Pride",
    "wof:placetype":"venue"
},
  "geometry": {"coordinates":[-112.44751599999999,34.7549],"type":"Point"}
}