{
  "type": "Feature",
  "properties": {
    "addr:full":"3059 S Kinney Rd Tucson AZ 85713",
    "addr:housenumber":"3059",
    "addr:postcode":"85713",
    "addr:street":"S Kinney Rd",
    "iso:country":"US",
    "sg:address":"3059 S Kinney Rd",
    "sg:city":"Tucson",
    "sg:classifiers":[
        {
            "category":"Retail",
            "subcategory":"Animal Services",
            "type":"Services"
        }
    ],
    "sg:phone":"+1 520 578 2201",
    "sg:postcode":"85713",
    "sg:province":"AZ",
    "sg:tags":[
        "pet",
        "grooming",
        "washing"
    ],
    "wof:name":"A Puppy Bath Pet Grooming Sln",
    "wof:placetype":"venue"
},
  "geometry": {"coordinates":[-111.092556,32.185688],"type":"Point"}
}