{
  "type": "Feature",
  "properties": {
    "iso:country":"US",
    "sg:address":"3335 W Durango St",
    "sg:city":"Phoenix",
    "sg:classifiers":[
        {
            "category":"Professional",
            "subcategory":"Management & Consulting",
            "type":"Services"
        }
    ],
    "sg:phone":"+1 602 506 4839",
    "sg:postcode":"85009",
    "sg:province":"AZ",
    "sg:tags":[
        "executive"
    ],
    "wof:name":"Human Services Dept",
    "wof:placetype":"venue"
},
  "geometry": {"coordinates":[-112.133224,33.42958],"type":"Point"}
}