{
  "type": "Feature",
  "properties": {
    "iso:country":"US",
    "sg:address":"2620 N 24th St",
    "sg:city":"Phoenix",
    "sg:classifiers":[
        {
            "category":"Real Estate",
            "subcategory":"Real Estate Agent",
            "type":"Services"
        }
    ],
    "sg:phone":"+1 602 749 9559",
    "sg:postcode":"85008",
    "sg:province":"AZ",
    "sg:tags":[
        "investment"
    ],
    "wof:name":"D Warner LTD",
    "wof:placetype":"venue"
},
  "geometry": {"coordinates":[-112.030277,33.475844],"type":"Point"}
}