{
  "type": "Feature",
  "properties": {
    "iso:country":"US",
    "sg:address":"16030 N 56th St",
    "sg:city":"Scottsdale",
    "sg:classifiers":[
        {
            "category":"Government",
            "subcategory":"Police Station",
            "type":"Public Place"
        }
    ],
    "sg:phone":"+1 602 495 5006",
    "sg:postcode":"85254",
    "sg:province":"AZ",
    "sg:tags":[
        "department"
    ],
    "sg:website":"www.cityofphoenix.gov",
    "wof:name":"Phoenix Police Dept",
    "wof:placetype":"venue"
},
  "geometry": {"coordinates":[-111.960395,33.631791],"type":"Point"}
}