{
  "type": "Feature",
  "properties": {
    "addr:full":"1728 W Bell Rd Phoenix AZ 85023",
    "addr:housenumber":"1728",
    "addr:postcode":"85023",
    "addr:street":"W Bell Rd",
    "iso:country":"US",
    "sg:address":"1728 W Bell Rd",
    "sg:city":"Phoenix",
    "sg:classifiers":[
        {
            "category":"Banks & Credit Unions",
            "subcategory":"Financial Services",
            "type":"Services"
        }
    ],
    "sg:phone":"+1 877 419 8789",
    "sg:postcode":"85023",
    "sg:province":"AZ",
    "sg:tags":[
        "loan",
        "alternative"
    ],
    "sg:website":"http://phoenix.citysearch.com/profile/external/604356632/phoenix_az/cash1.html?publisher=yellowpages&reference_id=1&placement=ypwebsitemip",
    "wof:name":"Cash1",
    "wof:placetype":"venue"
},
  "geometry": {"coordinates":[-112.096892,33.640221],"type":"Point"}
}