{
  "type": "Feature",
  "properties": {
    "iso:country":"US",
    "sg:address":"412 S 3rd St",
    "sg:city":"Phoenix",
    "sg:classifiers":[
        {
            "category":"Bars & Pubs",
            "type":"Food & Drink"
        },
        {
            "category":"Bars & Pubs",
            "subcategory":"Lounge",
            "type":"Food & Drink"
        },
        {
            "category":"Restaurant",
            "type":"Food & Drink"
        },
        {
            "category":"Bars & Pubs",
            "subcategory":"Sports Bar",
            "type":"Food & Drink"
        }
    ],
    "sg:phone":"+1 602 254 5272",
    "sg:postcode":"85004",
    "sg:province":"AZ",
    "sg:tags":[
        "style",
        "cocktail",
        "family",
        "seafood",
        "brew",
        "barbecue",
        "italian"
    ],
    "wof:name":"Coach & Willie's",
    "wof:placetype":"venue"
},
  "geometry": {"coordinates":[-112.069906,33.444086],"type":"Point"}
}