{
  "type": "Feature",
  "properties": {
    "iso:country":"US",
    "sg:address":"7227 S Central Ave",
    "sg:city":"Phoenix",
    "sg:classifiers":[
        {
            "category":"Food & Beverages",
            "subcategory":"Groceries & Convenience Stores",
            "type":"Retail Goods"
        }
    ],
    "sg:phone":"+1 602 243 6770",
    "sg:postcode":"85042",
    "sg:province":"AZ",
    "sg:website":"http://www.ajsfinefoods.com",
    "wof:name":"Food City",
    "wof:placetype":"venue"
},
  "geometry": {"coordinates":[-112.073274,33.380537],"type":"Point"}
}