{
  "type": "Feature",
  "properties": {
    "addr:full":"1201 S Alma School Rd Mesa AZ 85210",
    "addr:housenumber":"1201",
    "addr:postcode":"85210",
    "addr:street":"S Alma School Rd",
    "iso:country":"US",
    "sg:address":"1201 S Alma School Rd",
    "sg:city":"Mesa",
    "sg:classifiers":[
        {
            "category":"Banks & Credit Unions",
            "subcategory":"Bank",
            "type":"Services"
        }
    ],
    "sg:phone":"+1 480 649 1363",
    "sg:postcode":"85210",
    "sg:province":"AZ",
    "sg:tags":[
        "institution",
        "business"
    ],
    "wof:name":"Borego Springs Bank",
    "wof:placetype":"venue"
},
  "geometry": {"coordinates":[-111.857286,33.390892],"type":"Point"}
}