{
  "type": "Feature",
  "properties": {
    "iso:country":"US",
    "sg:address":"710 S Forest Ave",
    "sg:city":"Tempe",
    "sg:classifiers":[
        {
            "category":"Manufacturing",
            "subcategory":"Printing",
            "type":"Manufacturing & Wholesale Goods"
        }
    ],
    "sg:phone":"+1 480 968 0799",
    "sg:postcode":"85281",
    "sg:province":"AZ",
    "sg:tags":[
        "commercial",
        "offset"
    ],
    "wof:name":"UNI-Print & Design",
    "wof:placetype":"venue"
},
  "geometry": {"coordinates":[-111.93671399999999,33.422025],"type":"Point"}
}