{
  "type": "Feature",
  "properties": {
    "iso:country":"US",
    "sg:address":"702 E Coronado Rd",
    "sg:city":"Phoenix",
    "sg:classifiers":[
        {
            "category":"Professional",
            "subcategory":"Lawyer & Legal Services",
            "type":"Services"
        },
        {
            "category":"Building & Trades",
            "subcategory":"Equipment Rental",
            "type":"Services"
        }
    ],
    "sg:phone":"+1 602 639 4178",
    "sg:postcode":"85006",
    "sg:province":"AZ",
    "sg:tags":[
        "litigation",
        "attorney",
        "criminal",
        "leasing",
        "business",
        "family",
        "personal",
        "divorce",
        "tort",
        "injury",
        "law"
    ],
    "sg:website":"http://phoenix.citysearch.com/profile/external/602009977/phoenix_az/the_baker_law_firm.html?publisher=yellowpages&reference_id=15&placement=ypwebsitemip",
    "wof:name":"The Baker Law Firm",
    "wof:placetype":"venue"
},
  "geometry": {"coordinates":[-112.06505,33.46714],"type":"Point"}
}