{
  "type": "Feature",
  "properties": {
    "iso:country":"US",
    "sg:address":"7123 E Kalil Cir",
    "sg:city":"Scottsdale",
    "sg:classifiers":[
        {
            "category":"Wholesale",
            "subcategory":"Non-durable Goods",
            "type":"Manufacturing & Wholesale Goods"
        }
    ],
    "sg:phone":"+1 480 991 8089",
    "sg:postcode":"85254",
    "sg:province":"AZ",
    "wof:name":"Voices In Ink Creative",
    "wof:placetype":"venue"
},
  "geometry": {"coordinates":[-111.927729,33.590522],"type":"Point"}
}