{
  "type": "Feature",
  "properties": {
    "iso:country":"US",
    "sg:address":"1518 W Lobster Trap Dr",
    "sg:city":"Gilbert",
    "sg:classifiers":[
        {
            "category":"Wholesale",
            "subcategory":"Furniture",
            "type":"Manufacturing & Wholesale Goods"
        }
    ],
    "sg:phone":"+1 480 840 1471",
    "sg:postcode":"85233",
    "sg:province":"AZ",
    "wof:name":"National Business Furniture",
    "wof:placetype":"venue"
},
  "geometry": {"coordinates":[-111.822467,33.333485],"type":"Point"}
}