{
  "type": "Feature",
  "properties": {
    "addr:full":"7652 S Grandview Ave Tempe AZ 85284",
    "addr:housenumber":"7652",
    "addr:postcode":"85284",
    "addr:street":"S Grandview Ave",
    "iso:country":"US",
    "sg:address":"7652 S Grandview Ave",
    "sg:city":"Tempe",
    "sg:classifiers":[
        {
            "category":"Manufacturing",
            "subcategory":"Electronics",
            "type":"Manufacturing & Wholesale Goods"
        }
    ],
    "sg:phone":"+1 480 838 2451",
    "sg:postcode":"85284",
    "sg:province":"AZ",
    "sg:tags":[
        "semiconductor",
        "devices"
    ],
    "wof:name":"Intel Corp",
    "wof:placetype":"venue"
},
  "geometry": {"coordinates":[-111.936533,33.348084],"type":"Point"}
}