{
  "type": "Feature",
  "properties": {
    "addr:full":"11321 W Puget Ave Peoria AZ 85345",
    "addr:housenumber":"11321",
    "addr:postcode":"85345",
    "addr:street":"W Puget Ave",
    "iso:country":"US",
    "sg:address":"11321 W Puget Ave",
    "sg:city":"Peoria",
    "sg:classifiers":[
        {
            "category":"Building & Trades",
            "subcategory":"Landscaping Services",
            "type":"Services"
        }
    ],
    "sg:phone":"+1 623 848 6368",
    "sg:postcode":"85345",
    "sg:province":"AZ",
    "sg:tags":[
        "consultant",
        "lawn",
        "designer",
        "tree",
        "landscape"
    ],
    "wof:name":"Murphy's A-1 Tree Svc",
    "wof:placetype":"venue"
},
  "geometry": {"coordinates":[-112.30213000000001,33.564916],"type":"Point"}
}