{
  "type": "Feature",
  "properties": {
    "iso:country":"US",
    "sg:address":"3324 W Van Buren St",
    "sg:city":"Phoenix",
    "sg:classifiers":[
        {
            "category":"Restaurant",
            "type":"Food & Drink"
        }
    ],
    "sg:phone":"+1 602 278 8929",
    "sg:postcode":"85009",
    "sg:province":"AZ",
    "sg:tags":[
        "eating"
    ],
    "sg:website":"www.churchs.com",
    "wof:name":"Church's Chicken",
    "wof:placetype":"venue"
},
  "geometry": {"coordinates":[-112.13405400000001,33.451497],"type":"Point"}
}