{
  "type": "Feature",
  "properties": {
    "addr:full":"6060 N Desert Sun Ct Tucson AZ 85750",
    "addr:housenumber":"6060",
    "addr:postcode":"85750",
    "addr:street":"N Desert Sun Ct",
    "iso:country":"US",
    "sg:address":"6060 N Desert Sun Ct",
    "sg:city":"Tucson",
    "sg:classifiers":[
        {
            "category":"Real Estate",
            "subcategory":"Real Estate Operator",
            "type":"Services"
        }
    ],
    "sg:phone":"+1 520 577 9034",
    "sg:postcode":"85750",
    "sg:province":"AZ",
    "sg:tags":[
        "building",
        "nonresidential"
    ],
    "wof:name":"Berger Properties LLC",
    "wof:placetype":"venue"
},
  "geometry": {"coordinates":[-110.837177,32.317281],"type":"Point"}
}