{
  "type": "Feature",
  "properties": {
    "iso:country":"US",
    "sg:address":"15631 N Oracle Rd Ste 111",
    "sg:city":"Tucson",
    "sg:classifiers":[
        {
            "category":"Personal",
            "subcategory":"Nail Salon",
            "type":"Services"
        }
    ],
    "sg:phone":"+1 520 869 7953",
    "sg:postcode":"85739",
    "sg:province":"AZ",
    "wof:name":"Jaz Z Nails",
    "wof:placetype":"venue"
},
  "geometry": {"coordinates":[-110.924297,32.489578],"type":"Point"}
}