{
  "type": "Feature",
  "properties": {
    "addr:full":"17750 W Elliot Rd Goodyear AZ 85338",
    "addr:housenumber":"17750",
    "addr:postcode":"85338",
    "addr:street":"W Elliot Rd",
    "iso:country":"US",
    "sg:address":"17750 W Elliot Rd",
    "sg:city":"Goodyear",
    "sg:classifiers":[
        {
            "category":"Restaurant",
            "type":"Food & Drink"
        }
    ],
    "sg:phone":"+1 623 393 8001",
    "sg:postcode":"85338",
    "sg:province":"AZ",
    "sg:tags":[
        "pizzeria"
    ],
    "wof:name":"Hilltop Family Pizzeria",
    "wof:placetype":"venue"
},
  "geometry": {"coordinates":[-112.44817999999999,33.351673],"type":"Point"}
}