{
  "type": "Feature",
  "properties": {
    "iso:country":"US",
    "sg:address":"1455 N Arizona Ave",
    "sg:city":"Chandler",
    "sg:classifiers":[
        {
            "category":"Autos & Motor Vehicles",
            "subcategory":"Automobile Sales",
            "type":"Retail Goods"
        }
    ],
    "sg:phone":"+1 480 821 8833",
    "sg:postcode":"85225",
    "sg:province":"AZ",
    "sg:tags":[
        "car",
        "dealer"
    ],
    "wof:name":"J D Byrider Auto Sales",
    "wof:placetype":"venue"
},
  "geometry": {"coordinates":[-111.841612,33.331021],"type":"Point"}
}