{
  "type": "Feature",
  "properties": {
    "iso:country":"US",
    "sg:address":"1925 E Colt Rd",
    "sg:city":"Tempe",
    "sg:classifiers":[
        {
            "category":"Banks & Credit Unions",
            "subcategory":"Financial Services",
            "type":"Services"
        }
    ],
    "sg:phone":"+1 602 999 6020",
    "sg:postcode":"85284",
    "sg:province":"AZ",
    "sg:tags":[
        "company",
        "holding"
    ],
    "wof:name":"Baroness Holdings LLC",
    "wof:placetype":"venue"
},
  "geometry": {"coordinates":[-111.906737,33.336598],"type":"Point"}
}