{
  "type": "Feature",
  "properties": {
    "iso:country":"US",
    "sg:address":"3340 E Tanglewood Dr",
    "sg:city":"Phoenix",
    "sg:classifiers":[
        {
            "category":"Manufacturing",
            "subcategory":"Textiles",
            "type":"Manufacturing & Wholesale Goods"
        }
    ],
    "sg:phone":"+1 480 704 1072",
    "sg:postcode":"85048",
    "sg:province":"AZ",
    "sg:tags":[
        "textiles-manufacturers"
    ],
    "wof:name":"The Neighbor Ladies",
    "wof:placetype":"venue"
},
  "geometry": {"coordinates":[-112.01094,33.298818],"type":"Point"}
}