{
  "type": "Feature",
  "properties": {
    "iso:country":"US",
    "sg:address":"1431 W Valencia Rd",
    "sg:city":"Tucson",
    "sg:classifiers":[
        {
            "category":"Retail",
            "subcategory":"Auto Repair",
            "type":"Services"
        }
    ],
    "sg:phone":"+1 520 573 9930",
    "sg:postcode":"85746",
    "sg:province":"AZ",
    "sg:tags":[
        "repairing",
        "automobile"
    ],
    "sg:website":"www.holmestuttleford.com",
    "wof:name":"Holmes Tuttle Ford",
    "wof:placetype":"venue"
},
  "geometry": {"coordinates":[-110.99372200000001,32.133681],"type":"Point"}
}