{
  "type": "Feature",
  "properties": {
    "iso:country":"US",
    "sg:address":"5001 E Oakhurst Way",
    "sg:city":"Scottsdale",
    "sg:classifiers":[
        {
            "category":"Health Services",
            "subcategory":"Medical Lab",
            "type":"Services"
        }
    ],
    "sg:phone":"+1 602 279 8241",
    "sg:postcode":"85254",
    "sg:province":"AZ",
    "sg:tags":[
        "laboratory"
    ],
    "wof:name":"Signiture Dental Arts",
    "wof:placetype":"venue"
},
  "geometry": {"coordinates":[-111.973685,33.591063],"type":"Point"}
}