{
  "type": "Feature",
  "properties": {
    "addr:full":"14520 E Riggs Rd Chandler AZ 85249",
    "addr:housenumber":"14520",
    "addr:postcode":"85249",
    "addr:street":"E Riggs Rd",
    "iso:country":"US",
    "sg:address":"14520 E Riggs Rd",
    "sg:city":"Chandler",
    "sg:classifiers":[
        {
            "category":"Manufacturing",
            "subcategory":"Buildings",
            "type":"Manufacturing & Wholesale Goods"
        }
    ],
    "sg:phone":"+1 480 802 6798",
    "sg:postcode":"85249",
    "sg:province":"AZ",
    "sg:tags":[
        "prefab"
    ],
    "wof:name":"Ecker Enterprises Inc",
    "wof:placetype":"venue"
},
  "geometry": {"coordinates":[-111.765244,33.219239],"type":"Point"}
}