{
  "type": "Feature",
  "properties": {
    "iso:country":"US",
    "sg:address":"1455 S Stapley Dr Ste 13",
    "sg:city":"Mesa",
    "sg:classifiers":[
        {
            "category":"Health Services",
            "subcategory":"Doctor",
            "type":"Services"
        },
        {
            "category":"Social Services",
            "type":"Services"
        },
        {
            "category":"Personal",
            "type":"Services"
        },
        {
            "category":"Health Services",
            "subcategory":"Health Practitioner",
            "type":"Services"
        }
    ],
    "sg:phone":"+1 480 539 0670",
    "sg:postcode":"85204",
    "sg:province":"AZ",
    "sg:tags":[
        "individual",
        "family",
        "drug",
        "psychologist",
        "abuse",
        "marriage",
        "counselors-licensed",
        "child",
        "professional",
        "addiction",
        "counselor"
    ],
    "wof:name":"Terros Inc",
    "wof:placetype":"venue"
},
  "geometry": {"coordinates":[-111.80547900000001,33.388813],"type":"Point"}
}