{
  "type": "Feature",
  "properties": {
    "addr:full":"21450 N 23rd Ave Phoenix AZ 85027",
    "addr:housenumber":"21450",
    "addr:postcode":"85027",
    "addr:street":"N 23Rd Ave",
    "iso:country":"US",
    "sg:address":"21450 N 23rd Ave",
    "sg:city":"Phoenix",
    "sg:classifiers":[
        {
            "category":"Real Estate",
            "subcategory":"Real Estate Operator",
            "type":"Services"
        }
    ],
    "sg:phone":"+1 623 581 0983",
    "sg:postcode":"85027",
    "sg:province":"AZ",
    "sg:tags":[
        "building",
        "apartment"
    ],
    "wof:name":"Deer Valley Village Apartments",
    "wof:placetype":"venue"
},
  "geometry": {"coordinates":[-112.10866,33.681953],"type":"Point"}
}