{
  "type": "Feature",
  "properties": {
    "iso:country":"US",
    "sg:address":"5333 N 7th St Ste C224",
    "sg:city":"Phoenix",
    "sg:classifiers":[
        {
            "category":"Manufacturing",
            "subcategory":"Printing",
            "type":"Manufacturing & Wholesale Goods"
        },
        {
            "category":"Wholesale",
            "subcategory":"Books, Periodicals, & Newspapers",
            "type":"Manufacturing & Wholesale Goods"
        }
    ],
    "sg:phone":"+1 602 265 4855",
    "sg:postcode":"85014",
    "sg:province":"AZ",
    "sg:tags":[
        "magazines-distributors",
        "magazine"
    ],
    "sg:website":"http://www.nativepeoples.com",
    "wof:name":"Native Peoples Magazine",
    "wof:placetype":"venue"
},
  "geometry": {"coordinates":[-112.06500200000001,33.515375],"type":"Point"}
}