{
  "type": "Feature",
  "properties": {
    "iso:country":"US",
    "sg:address":"424 E Southern Ave",
    "sg:city":"Tempe",
    "sg:classifiers":[
        {
            "category":"Wholesale",
            "subcategory":"Durable Goods & Equipment",
            "type":"Manufacturing & Wholesale Goods"
        }
    ],
    "sg:phone":"+1 480 557 6566",
    "sg:postcode":"85282",
    "sg:province":"AZ",
    "sg:tags":[
        "fire",
        "extinguisher"
    ],
    "wof:name":"Envirofoam Technologies Inc",
    "wof:placetype":"venue"
},
  "geometry": {"coordinates":[-111.934162,33.392994],"type":"Point"}
}