{
  "type": "Feature",
  "properties": {
    "iso:country":"US",
    "sg:address":"735 Papoose Dr",
    "sg:city":"Lake Havasu City",
    "sg:classifiers":[
        {
            "category":"Building & Trades",
            "subcategory":"Construction",
            "type":"Services"
        }
    ],
    "sg:phone":"+1 928 855 8036",
    "sg:postcode":"86406",
    "sg:province":"AZ",
    "sg:tags":[
        "carpentry",
        "contractor"
    ],
    "wof:name":"Gary Curtis Custom Wood Finshg",
    "wof:placetype":"venue"
},
  "geometry": {"coordinates":[-114.292939,34.462065],"type":"Point"}
}