{
  "type": "Feature",
  "properties": {
    "iso:country":"US",
    "sg:address":"3708 E Columbia St",
    "sg:city":"Tucson",
    "sg:classifiers":[
        {
            "category":"Professional",
            "subcategory":"Research",
            "type":"Services"
        }
    ],
    "sg:phone":"+1 520 749 2062",
    "sg:postcode":"85714",
    "sg:province":"AZ",
    "sg:tags":[
        "development",
        "marketing",
        "product"
    ],
    "sg:website":"www.colorbok.com",
    "wof:name":"Colorbook",
    "wof:placetype":"venue"
},
  "geometry": {"coordinates":[-110.91282,32.172241],"type":"Point"}
}