{
  "type": "Feature",
  "properties": {
    "iso:country":"US",
    "sg:address":"5200 E Farness Dr",
    "sg:city":"Tucson",
    "sg:classifiers":[
        {
            "category":"Health Services",
            "subcategory":"Doctor",
            "type":"Services"
        }
    ],
    "sg:phone":"+1 520 323 3866",
    "sg:postcode":"85712",
    "sg:province":"AZ",
    "sg:tags":[
        "dentist"
    ],
    "wof:name":"Karl Zimmerman DDS",
    "wof:placetype":"venue"
},
  "geometry": {"coordinates":[-110.88257,32.24769],"type":"Point"}
}