{
  "type": "Feature",
  "properties": {
    "iso:country":"US",
    "sg:address":"5958 E McKellips Rd",
    "sg:city":"Mesa",
    "sg:classifiers":[
        {
            "category":"Manufacturing",
            "subcategory":"Tools & Machinery",
            "type":"Manufacturing & Wholesale Goods"
        }
    ],
    "sg:phone":"+1 480 985 8905",
    "sg:postcode":"85215",
    "sg:province":"AZ",
    "sg:tags":[
        "mart",
        "mini"
    ],
    "wof:name":"Mobil",
    "wof:placetype":"venue"
},
  "geometry": {"coordinates":[-111.703833,33.451959],"type":"Point"}
}