{
  "type": "Feature",
  "properties": {
    "iso:country":"US",
    "sg:address":"220 E Wetmore Rd",
    "sg:city":"Tucson",
    "sg:classifiers":[
        {
            "category":"Banks & Credit Unions",
            "subcategory":"Financial Services",
            "type":"Services"
        }
    ],
    "sg:phone":"+1 520 887 7680",
    "sg:postcode":"85705",
    "sg:province":"AZ",
    "sg:tags":[
        "company",
        "holding"
    ],
    "wof:name":"Northwest Holdings Inc",
    "wof:placetype":"venue"
},
  "geometry": {"coordinates":[-110.968093,32.286475],"type":"Point"}
}