{
  "type": "Feature",
  "properties": {
    "iso:country":"US",
    "sg:address":"16727 W Villagio Dr",
    "sg:city":"Surprise",
    "sg:classifiers":[
        {
            "category":"Building & Trades",
            "subcategory":"Construction",
            "type":"Services"
        }
    ],
    "sg:phone":"+1 623 214 0466",
    "sg:postcode":"85387",
    "sg:province":"AZ",
    "sg:tags":[
        "painter"
    ],
    "wof:name":"Pride Painting Inc",
    "wof:placetype":"venue"
},
  "geometry": {"coordinates":[-112.420927,33.653768],"type":"Point"}
}