{
  "type": "Feature",
  "properties": {
    "addr:full":"3839 S 16th St Phoenix AZ 85040",
    "addr:housenumber":"3839",
    "addr:postcode":"85040",
    "addr:street":"S 16Th St",
    "iso:country":"US",
    "sg:address":"3839 S 16th St",
    "sg:city":"Phoenix",
    "sg:classifiers":[
        {
            "category":"Retail",
            "subcategory":"Auto Repair",
            "type":"Services"
        }
    ],
    "sg:phone":"+1 602 268 9505",
    "sg:postcode":"85040",
    "sg:province":"AZ",
    "sg:tags":[
        "repairing",
        "automobile"
    ],
    "wof:name":"Renegado Auto Shop",
    "wof:placetype":"venue"
},
  "geometry": {"coordinates":[-112.047083,33.410308],"type":"Point"}
}