{
  "type": "Feature",
  "properties": {
    "addr:full":"3080 N Civic Center Plz Scottsdale AZ 85251",
    "addr:housenumber":"3080",
    "addr:postcode":"85251",
    "addr:street":"N Civic Center Plz",
    "iso:country":"US",
    "sg:address":"3080 N Civic Center Plz",
    "sg:city":"Scottsdale",
    "sg:classifiers":[
        {
            "category":"Professional",
            "subcategory":"Computer Services",
            "type":"Services"
        }
    ],
    "sg:phone":"+1 480 946 1020",
    "sg:postcode":"85251",
    "sg:province":"AZ",
    "sg:tags":[
        "repair",
        "equipment-service"
    ],
    "wof:name":"Swc Business Pc",
    "wof:placetype":"venue"
},
  "geometry": {"coordinates":[-111.92183799999999,33.483678],"type":"Point"}
}