{
  "type": "Feature",
  "properties": {
    "addr:full":"3130 S Mill Ave Tempe AZ 85282",
    "addr:housenumber":"3130",
    "addr:postcode":"85282",
    "addr:street":"S Mill Ave",
    "iso:country":"US",
    "sg:address":"3130 S Mill Ave",
    "sg:city":"Tempe",
    "sg:classifiers":[
        {
            "category":"Shopping",
            "subcategory":"Discount & Variety Stores",
            "type":"Retail Goods"
        }
    ],
    "sg:phone":"+1 480 829 0059",
    "sg:postcode":"85282",
    "sg:province":"AZ",
    "wof:name":"99 Cent Store",
    "wof:placetype":"venue"
},
  "geometry": {"coordinates":[-111.939701,33.395972],"type":"Point"}
}