{
  "type": "Feature",
  "properties": {
    "iso:country":"US",
    "sg:address":"471 N Kenneth Pl",
    "sg:city":"Chandler",
    "sg:classifiers":[
        {
            "category":"Communications",
            "subcategory":"Film & Video Production",
            "type":"Services"
        }
    ],
    "sg:phone":"+1 480 961 3585",
    "sg:postcode":"85226",
    "sg:province":"AZ",
    "sg:tags":[
        "tv",
        "radio",
        "services-commercial",
        "companies-film"
    ],
    "wof:name":"Bad Productions",
    "wof:placetype":"venue"
},
  "geometry": {"coordinates":[-111.920663,33.310043],"type":"Point"}
}