{
  "type": "Feature",
  "properties": {
    "iso:country":"US",
    "sg:address":"7145 E 1st St",
    "sg:city":"Scottsdale",
    "sg:classifiers":[
        {
            "category":"Professional",
            "type":"Services"
        }
    ],
    "sg:phone":"+1 480 970 8588",
    "sg:postcode":"85251",
    "sg:province":"AZ",
    "sg:tags":[
        "establishment"
    ],
    "wof:name":"All American Roadside Asst",
    "wof:placetype":"venue"
},
  "geometry": {"coordinates":[-111.926969,33.492137],"type":"Point"}
}