{
  "type": "Feature",
  "properties": {
    "iso:country":"US",
    "sg:address":"3334 N 19th Ave",
    "sg:city":"Phoenix",
    "sg:classifiers":[
        {
            "category":"Personal",
            "subcategory":"Beauty Salon",
            "type":"Services"
        }
    ],
    "sg:phone":"+1 602 279 2114",
    "sg:postcode":"85015",
    "sg:province":"AZ",
    "wof:name":"Mary Lou's Beauty Salon",
    "wof:placetype":"venue"
},
  "geometry": {"coordinates":[-112.099953,33.486802],"type":"Point"}
}