{
  "type": "Feature",
  "properties": {
    "iso:country":"US",
    "sg:address":"3700 E Sierra Way",
    "sg:city":"Cave Creek",
    "sg:classifiers":[
        {
            "category":"Wholesale",
            "subcategory":"Hardware",
            "type":"Manufacturing & Wholesale Goods"
        }
    ],
    "sg:phone":"+1 480 575 0244",
    "sg:postcode":"85331",
    "sg:province":"AZ",
    "sg:tags":[
        "refrigeration"
    ],
    "wof:name":"AAA Arcticzona A C & R Inc",
    "wof:placetype":"venue"
},
  "geometry": {"coordinates":[-112.002658,33.799902],"type":"Point"}
}