{
  "type": "Feature",
  "properties": {
    "iso:country":"US",
    "sg:address":"14300 N Northsight Blvd",
    "sg:city":"Scottsdale",
    "sg:classifiers":[
        {
            "category":"Building & Trades",
            "subcategory":"Construction",
            "type":"Services"
        }
    ],
    "sg:phone":"+1 602 867 8422",
    "sg:postcode":"85260",
    "sg:province":"AZ",
    "sg:tags":[
        "home",
        "builder"
    ],
    "wof:name":"Equity Home Builders",
    "wof:placetype":"venue"
},
  "geometry": {"coordinates":[-111.897852,33.614886],"type":"Point"}
}