{
  "type": "Feature",
  "properties": {
    "iso:country":"US",
    "sg:address":"13780 W Waddell Rd",
    "sg:city":"Surprise",
    "sg:classifiers":[
        {
            "category":"Banks & Credit Unions",
            "subcategory":"Bank",
            "type":"Services"
        }
    ],
    "sg:phone":"+1 623 544 4524",
    "sg:postcode":"85379",
    "sg:province":"AZ",
    "wof:name":"Bank Of America",
    "wof:placetype":"venue"
},
  "geometry": {"coordinates":[-112.356888,33.609243],"type":"Point"}
}