{
  "type": "Feature",
  "properties": {
    "addr:full":"8028 S Central Ave Phoenix AZ 85042",
    "addr:housenumber":"8028",
    "addr:postcode":"85042",
    "addr:street":"S Central Ave",
    "iso:country":"US",
    "sg:address":"8028 S Central Ave",
    "sg:city":"Phoenix",
    "sg:classifiers":[
        {
            "category":"Wholesale",
            "subcategory":"Music Publishers",
            "type":"Manufacturing & Wholesale Goods"
        }
    ],
    "sg:phone":"+1 602 412 7845",
    "sg:postcode":"85042",
    "sg:province":"AZ",
    "sg:tags":[
        "distribution"
    ],
    "wof:name":"Yung Face",
    "wof:placetype":"venue"
},
  "geometry": {"coordinates":[-112.07324199999999,33.374067],"type":"Point"}
}