{
  "type": "Feature",
  "properties": {
    "iso:country":"US",
    "sg:address":"9072 E Winchcomb Dr",
    "sg:city":"Scottsdale",
    "sg:classifiers":[
        {
            "category":"Shopping",
            "subcategory":"Music",
            "type":"Retail Goods"
        }
    ],
    "sg:phone":"+1 480 391 1861",
    "sg:postcode":"85260",
    "sg:province":"AZ",
    "sg:tags":[
        "production"
    ],
    "wof:name":"Del Soul Records",
    "wof:placetype":"venue"
},
  "geometry": {"coordinates":[-111.885504,33.616652],"type":"Point"}
}