{
  "type": "Feature",
  "properties": {
    "addr:full":"1920 S Dobson Rd Mesa AZ 85202",
    "addr:housenumber":"1920",
    "addr:postcode":"85202",
    "addr:street":"S Dobson Rd",
    "iso:country":"US",
    "sg:address":"1920 S Dobson Rd",
    "sg:city":"Mesa",
    "sg:phone":"+1 480 820 0237",
    "sg:postcode":"85202",
    "sg:province":"AZ",
    "wof:name":"Macayo's Mexican Kitchen",
    "wof:placetype":"venue"
},
  "geometry": {"coordinates":[-111.877416,33.379982],"type":"Point"}
}