{
  "type": "Feature",
  "properties": {
    "addr:full":"13690 N 82nd Ln Peoria AZ 85381",
    "addr:housenumber":"13690",
    "addr:postcode":"85381",
    "addr:street":"N 82Nd Ln",
    "iso:country":"US",
    "sg:address":"13690 N 82nd Ln",
    "sg:city":"Peoria",
    "sg:classifiers":[
        {
            "category":"Building & Trades",
            "subcategory":"Construction",
            "type":"Services"
        }
    ],
    "sg:phone":"+1 623 486 5758",
    "sg:postcode":"85381",
    "sg:province":"AZ",
    "sg:tags":[
        "house"
    ],
    "wof:name":"Barraza Construction Inc",
    "wof:placetype":"venue"
},
  "geometry": {"coordinates":[-112.23698,33.606937],"type":"Point"}
}