{
  "type": "Feature",
  "properties": {
    "addr:full":"559 S Main St Cottonwood AZ 86326",
    "addr:housenumber":"559",
    "addr:postcode":"86326",
    "addr:street":"S Main St",
    "iso:country":"US",
    "sg:address":"559 S Main St",
    "sg:city":"Cottonwood",
    "sg:classifiers":[
        {
            "category":"Shopping",
            "subcategory":"Clothing, Apparel, & Fashions",
            "type":"Retail Goods"
        }
    ],
    "sg:phone":"+1 928 567 4855",
    "sg:postcode":"86326",
    "sg:province":"AZ",
    "sg:tags":[
        "ready",
        "to",
        "wear"
    ],
    "wof:name":"Leather & Lace",
    "wof:placetype":"venue"
},
  "geometry": {"coordinates":[-112.00944800000001,34.729383],"type":"Point"}
}