{
  "type": "Feature",
  "properties": {
    "iso:country":"US",
    "sg:address":"1806 E Redfield Rd",
    "sg:city":"Phoenix",
    "sg:classifiers":[
        {
            "category":"Manufacturing",
            "subcategory":"Signs",
            "type":"Manufacturing & Wholesale Goods"
        }
    ],
    "sg:phone":"+1 602 404 2734",
    "sg:postcode":"85022",
    "sg:province":"AZ",
    "sg:tags":[
        "specialty",
        "mfg"
    ],
    "wof:name":"Primo Signs Inc",
    "wof:placetype":"venue"
},
  "geometry": {"coordinates":[-112.043646,33.61452],"type":"Point"}
}