{
  "type": "Feature",
  "properties": {
    "addr:full":"5044 W Cactus Rd Glendale AZ 85029",
    "addr:housenumber":"5044",
    "addr:postcode":"85029",
    "addr:street":"W Cactus Rd",
    "iso:country":"US",
    "sg:address":"5044 W Cactus Rd",
    "sg:city":"Glendale",
    "sg:classifiers":[
        {
            "category":"Banks & Credit Unions",
            "subcategory":"Financial Services",
            "type":"Services"
        }
    ],
    "sg:phone":"+1 602 363 8045",
    "sg:postcode":"85029",
    "sg:province":"AZ",
    "sg:tags":[
        "mfg",
        "cabinet"
    ],
    "wof:name":"Finishline Cabinets",
    "wof:placetype":"venue"
},
  "geometry": {"coordinates":[-112.167428,33.596439],"type":"Point"}
}