{
  "type": "Feature",
  "properties": {
    "iso:country":"US",
    "sg:address":"375 W Grant St",
    "sg:city":"Phoenix",
    "sg:classifiers":[
        {
            "category":"Building & Trades",
            "subcategory":"Landscaping Services",
            "type":"Services"
        }
    ],
    "sg:phone":"+1 602 993 4873",
    "sg:postcode":"85003",
    "sg:province":"AZ",
    "sg:tags":[
        "lawn",
        "maintenance",
        "grounds"
    ],
    "wof:name":"Dodson's Lawn Care",
    "wof:placetype":"venue"
},
  "geometry": {"coordinates":[-112.078482,33.44108],"type":"Point"}
}