{
  "type": "Feature",
  "properties": {
    "iso:country":"US",
    "sg:address":"2130 S Rural Rd",
    "sg:city":"Tempe",
    "sg:classifiers":[
        {
            "category":"Insurance",
            "subcategory":"Insurance Agent",
            "type":"Services"
        }
    ],
    "sg:phone":"+1 480 921 3550",
    "sg:postcode":"85282",
    "sg:province":"AZ",
    "wof:name":"ABI Insurance",
    "wof:placetype":"venue"
},
  "geometry": {"coordinates":[-111.926356,33.406573],"type":"Point"}
}