{
  "type": "Feature",
  "properties": {
    "addr:full":"21006 N 22nd St Phoenix AZ 85024",
    "addr:housenumber":"21006",
    "addr:postcode":"85024",
    "addr:street":"N 22Nd St",
    "iso:country":"US",
    "sg:address":"21006 N 22nd St",
    "sg:city":"Phoenix",
    "sg:classifiers":[
        {
            "category":"Building & Trades",
            "subcategory":"Construction",
            "type":"Services"
        }
    ],
    "sg:phone":"+1 602 485 3528",
    "sg:postcode":"85024",
    "sg:province":"AZ",
    "sg:tags":[
        "concrete",
        "contractor"
    ],
    "wof:name":"Bison Concrete",
    "wof:placetype":"venue"
},
  "geometry": {"coordinates":[-112.035476,33.677571],"type":"Point"}
}