{
  "type": "Feature",
  "properties": {
    "iso:country":"US",
    "sg:address":"2160 W Chandler Blvd",
    "sg:city":"Chandler",
    "sg:classifiers":[
        {
            "category":"Health Services",
            "subcategory":"Doctor",
            "type":"Services"
        }
    ],
    "sg:phone":"+1 480 732 7874",
    "sg:postcode":"85224",
    "sg:province":"AZ",
    "sg:tags":[
        "dentist"
    ],
    "wof:name":"Dental Solutions",
    "wof:placetype":"venue"
},
  "geometry": {"coordinates":[-111.87842999999999,33.306055],"type":"Point"}
}