{
  "type": "Feature",
  "properties": {
    "iso:country":"US",
    "sg:address":"6525 W Happy Valley Rd",
    "sg:city":"Glendale",
    "sg:classifiers":[
        {
            "category":"Restaurant",
            "type":"Food & Drink"
        }
    ],
    "sg:menulink":"http://www.allmenus.com/az/deer-valley/25064-fiorellas-ristorante/menu/",
    "sg:phone":"+1 623 561 3200",
    "sg:postcode":"85310",
    "sg:province":"AZ",
    "sg:tags":[
        "italian"
    ],
    "wof:name":"Fiorella's Ristorante",
    "wof:placetype":"venue"
},
  "geometry": {"coordinates":[-112.200355,33.711086],"type":"Point"}
}