{
  "type": "Feature",
  "properties": {
    "iso:country":"US",
    "sg:address":"2071 E Cairo Dr",
    "sg:city":"Tempe",
    "sg:classifiers":[
        {
            "category":"Shopping",
            "subcategory":"Bicycles & Sporting Goods",
            "type":"Retail Goods"
        }
    ],
    "sg:phone":"+1 480 839 8577",
    "sg:postcode":"85282",
    "sg:province":"AZ",
    "sg:tags":[
        "equipment",
        "golf",
        "supply"
    ],
    "wof:name":"Calvin Daane-Golf",
    "wof:placetype":"venue"
},
  "geometry": {"coordinates":[-111.899158,33.398876],"type":"Point"}
}