{
  "type": "Feature",
  "properties": {
    "iso:country":"US",
    "sg:address":"8876 E Pinnacle Peak Rd",
    "sg:city":"Scottsdale",
    "sg:classifiers":[
        {
            "category":"Personal",
            "subcategory":"Beauty Salon",
            "type":"Services"
        }
    ],
    "sg:phone":"+1 480 473 7546",
    "sg:postcode":"85255",
    "sg:province":"AZ",
    "sg:tags":[
        "treatment",
        "skin"
    ],
    "wof:name":"Skin Enrichment Clinic",
    "wof:placetype":"venue"
},
  "geometry": {"coordinates":[-111.888684,33.698511],"type":"Point"}
}