{
  "type": "Feature",
  "properties": {
    "addr:full":"4488 E Thomas Rd Phoenix AZ 85018",
    "addr:housenumber":"4488",
    "addr:postcode":"85018",
    "addr:street":"E Thomas Rd",
    "iso:country":"US",
    "sg:address":"4488 E Thomas Rd",
    "sg:city":"Phoenix",
    "sg:classifiers":[
        {
            "category":"Retail",
            "subcategory":"Car Wash",
            "type":"Services"
        }
    ],
    "sg:phone":"+1 602 973 1300",
    "sg:postcode":"85018",
    "sg:province":"AZ",
    "sg:tags":[
        "automobile",
        "detail",
        "clean"
    ],
    "wof:name":"Domestic Detailing",
    "wof:placetype":"venue"
},
  "geometry": {"coordinates":[-111.986527,33.480327],"type":"Point"}
}