{
  "type": "Feature",
  "properties": {
    "iso:country":"US",
    "sg:address":"2124 E Van Buren St",
    "sg:city":"Phoenix",
    "sg:classifiers":[
        {
            "category":"Building & Trades",
            "subcategory":"Construction",
            "type":"Services"
        }
    ],
    "sg:phone":"+1 602 348 2891",
    "sg:postcode":"85006",
    "sg:province":"AZ",
    "sg:tags":[
        "contractor"
    ],
    "wof:name":"M & M Window Tinting",
    "wof:placetype":"venue"
},
  "geometry": {"coordinates":[-112.03469,33.451468],"type":"Point"}
}