{
  "type": "Feature",
  "properties": {
    "iso:country":"US",
    "sg:address":"2471 W Catalpa Rd",
    "sg:city":"Tucson",
    "sg:classifiers":[
        {
            "category":"Professional",
            "subcategory":"Accounting & Tax Preparation",
            "type":"Services"
        }
    ],
    "sg:phone":"+1 520 531 1111",
    "sg:postcode":"85742",
    "sg:province":"AZ",
    "sg:tags":[
        "return",
        "filing"
    ],
    "wof:name":"Tortolita Tax",
    "wof:placetype":"venue"
},
  "geometry": {"coordinates":[-111.020104,32.374684],"type":"Point"}
}