{
  "type": "Feature",
  "properties": {
    "iso:country":"US",
    "sg:address":"1301 N Sartillion Ave",
    "sg:city":"Ajo",
    "sg:classifiers":[
        {
            "category":"Social Services",
            "type":"Services"
        }
    ],
    "sg:phone":"+1 520 387 5639",
    "sg:postcode":"85321",
    "sg:province":"AZ",
    "sg:tags":[
        "organization",
        "welfare"
    ],
    "wof:name":"Catholic Charities",
    "wof:placetype":"venue"
},
  "geometry": {"coordinates":[-112.87446,32.382761],"type":"Point"}
}