{
  "type": "Feature",
  "properties": {
    "addr:full":"35903 N 32nd Dr Phoenix AZ 85086",
    "addr:housenumber":"35903",
    "addr:postcode":"85086",
    "addr:street":"N 32Nd Dr",
    "iso:country":"US",
    "sg:address":"35903 N 32nd Dr",
    "sg:city":"Phoenix",
    "sg:classifiers":[
        {
            "category":"Banks & Credit Unions",
            "subcategory":"Atm",
            "type":"Services"
        }
    ],
    "sg:phone":"+1 602 722 6269",
    "sg:postcode":"85086",
    "sg:province":"AZ",
    "sg:tags":[
        "location"
    ],
    "wof:name":"Atm Advertising",
    "wof:placetype":"venue"
},
  "geometry": {"coordinates":[-112.129127,33.810745],"type":"Point"}
}