{
  "type": "Feature",
  "properties": {
    "addr:full":"6136 W Pershing Ave Glendale AZ 85304",
    "addr:housenumber":"6136",
    "addr:postcode":"85304",
    "addr:street":"W Pershing Ave",
    "iso:country":"US",
    "sg:address":"6136 W Pershing Ave",
    "sg:city":"Glendale",
    "sg:classifiers":[
        {
            "category":"Manufacturing",
            "subcategory":"Building Materials",
            "type":"Manufacturing & Wholesale Goods"
        }
    ],
    "sg:phone":"+1 623 878 2767",
    "sg:postcode":"85304",
    "sg:province":"AZ",
    "sg:tags":[
        "filtering",
        "supply"
    ],
    "wof:name":"Arnold & Calvina Washington",
    "wof:placetype":"venue"
},
  "geometry": {"coordinates":[-112.190724,33.605835],"type":"Point"}
}