{
  "type": "Feature",
  "properties": {
    "iso:country":"US",
    "sg:address":"Chandler Fashion Sq",
    "sg:city":"Chandler",
    "sg:classifiers":[
        {
            "category":"Home & Garden",
            "subcategory":"Carpets & Floor Coverings",
            "type":"Retail Goods"
        }
    ],
    "sg:phone":"+1 480 214 0240",
    "sg:postcode":"85224",
    "sg:province":"AZ",
    "sg:tags":[
        "mattress"
    ],
    "wof:name":"Sleep Number Store by Select Comfort",
    "wof:placetype":"venue"
},
  "geometry": {"coordinates":[-111.876999,33.3279],"type":"Point"}
}