{
  "type": "Feature",
  "properties": {
    "iso:country":"US",
    "sg:address":"33739 N Scottsdale Rd",
    "sg:city":"Scottsdale",
    "sg:classifiers":[
        {
            "category":"Health Services",
            "subcategory":"Dentist",
            "type":"Services"
        }
    ],
    "sg:phone":"+1 480 718 5676",
    "sg:postcode":"85266",
    "sg:province":"AZ",
    "sg:tags":[
        "dental",
        "clinic"
    ],
    "wof:name":"Epyk Dental Arts",
    "wof:placetype":"venue"
},
  "geometry": {"coordinates":[-111.925813,33.790808],"type":"Point"}
}