{
  "type": "Feature",
  "properties": {
    "iso:country":"US",
    "sg:address":"8139 S Priest Dr",
    "sg:city":"Tempe",
    "sg:classifiers":[
        {
            "category":"Retail",
            "subcategory":"Auto Repair",
            "type":"Services"
        }
    ],
    "sg:phone":"+1 480 777 5503",
    "sg:postcode":"85284",
    "sg:province":"AZ",
    "sg:tags":[
        "body",
        "automobile",
        "painting"
    ],
    "sg:website":"www.elitecollision.com",
    "wof:name":"Elite Auto Repair",
    "wof:placetype":"venue"
},
  "geometry": {"coordinates":[-111.963076,33.341003],"type":"Point"}
}