{
  "type": "Feature",
  "properties": {
    "iso:country":"US",
    "sg:address":"14175 W Indian School Road",
    "sg:city":"Goodyear",
    "sg:classifiers":[
        {
            "category":"Shopping",
            "subcategory":"Mobile Phones",
            "type":"Retail Goods"
        }
    ],
    "sg:phone":"+1 623 536 1300",
    "sg:postcode":"85338",
    "sg:province":"AZ",
    "sg:website":"www.alltel.com",
    "wof:name":"Alltel",
    "wof:placetype":"venue"
},
  "geometry": {"coordinates":[-112.36402699999999,33.485699],"type":"Point"}
}