{
  "type": "Feature",
  "properties": {
    "iso:country":"US",
    "sg:address":"3741 N 303rd Ct",
    "sg:city":"Buckeye",
    "sg:classifiers":[
        {
            "category":"Transit Center",
            "subcategory":"Freight",
            "type":"Transportation"
        },
        {
            "category":"Freight",
            "type":"Transportation"
        }
    ],
    "sg:phone":"+1 623 322 0178",
    "sg:postcode":"85396",
    "sg:province":"AZ",
    "sg:tags":[
        "local",
        "trucking-motor",
        "trucking"
    ],
    "wof:name":"Camatteo Trucking",
    "wof:placetype":"venue"
},
  "geometry": {"coordinates":[-112.70459200000001,33.488799],"type":"Point"}
}