{
  "type": "Feature",
  "properties": {
    "iso:country":"US",
    "sg:address":"5010 E Calavar Rd",
    "sg:city":"Scottsdale",
    "sg:classifiers":[
        {
            "category":"Professional",
            "subcategory":"Advertising",
            "type":"Services"
        }
    ],
    "sg:phone":"+1 602 482 1004",
    "sg:postcode":"85254",
    "sg:province":"AZ",
    "sg:tags":[
        "counselor"
    ],
    "wof:name":"Media Works",
    "wof:placetype":"venue"
},
  "geometry": {"coordinates":[-111.972843,33.612157],"type":"Point"}
}