{
  "type": "Feature",
  "properties": {
    "iso:country":"US",
    "sg:address":"8113 E Palm Ln",
    "sg:city":"Scottsdale",
    "sg:classifiers":[
        {
            "category":"Mining & Drilling",
            "type":"Manufacturing & Wholesale Goods"
        }
    ],
    "sg:phone":"+1 480 970 8830",
    "sg:postcode":"85257",
    "sg:province":"AZ",
    "sg:tags":[
        "company"
    ],
    "wof:name":"A F Budge Mining LTD",
    "wof:placetype":"venue"
},
  "geometry": {"coordinates":[-111.906746,33.469728],"type":"Point"}
}