{
  "type": "Feature",
  "properties": {
    "addr:full":"135 E Ray Road Chandler AZ 85225",
    "addr:housenumber":"135",
    "addr:postcode":"85225",
    "addr:street":"E Ray Road",
    "iso:country":"US",
    "sg:address":"135 E Ray Road",
    "sg:city":"Chandler",
    "sg:classifiers":[
        {
            "category":"Restaurant",
            "type":"Food & Drink"
        }
    ],
    "sg:phone":"+1 480 732 9191",
    "sg:postcode":"85225",
    "sg:province":"AZ",
    "sg:tags":[
        "pizza",
        "italian"
    ],
    "sg:website":"www.pizzapatron.com",
    "wof:name":"Pizza Patron",
    "wof:placetype":"venue"
},
  "geometry": {"coordinates":[-111.839631,33.320555],"type":"Point"}
}