{
  "type": "Feature",
  "properties": {
    "iso:country":"US",
    "sg:address":"3313 N 40th St",
    "sg:city":"Phoenix",
    "sg:classifiers":[
        {
            "category":"Place Of Worship",
            "subcategory":"Church",
            "type":"Public Place"
        },
        {
            "category":"Place Of Worship",
            "type":"Public Place"
        }
    ],
    "sg:phone":"+1 602 955 5484",
    "sg:postcode":"85018",
    "sg:province":"AZ",
    "sg:tags":[
        "nazarene",
        "churches-church",
        "churches-nazarene"
    ],
    "wof:name":"Monte Vista Church-Nazarene",
    "wof:placetype":"venue"
},
  "geometry": {"coordinates":[-111.995506,33.48687],"type":"Point"}
}