{
  "type": "Feature",
  "properties": {
    "addr:full":"13732 W Bell Rd Surprise AZ 85374",
    "addr:housenumber":"13732",
    "addr:postcode":"85374",
    "addr:street":"W Bell Rd",
    "iso:country":"US",
    "sg:address":"13732 W Bell Rd",
    "sg:city":"Surprise",
    "sg:classifiers":[
        {
            "category":"Manufacturing",
            "subcategory":"Food",
            "type":"Manufacturing & Wholesale Goods"
        },
        {
            "category":"Restaurant",
            "type":"Food & Drink"
        }
    ],
    "sg:phone":"+1 623 877 1026",
    "sg:postcode":"85374",
    "sg:province":"AZ",
    "sg:tags":[
        "butter",
        "mfg",
        "creamery",
        "ice",
        "parlor",
        "cream"
    ],
    "wof:name":"Karen's Kreamery",
    "wof:placetype":"venue"
},
  "geometry": {"coordinates":[-112.35871299999999,33.638796],"type":"Point"}
}