{
  "type": "Feature",
  "properties": {
    "addr:full":"1921 Club Ave Kingman AZ 86401",
    "addr:housenumber":"1921",
    "addr:postcode":"86401",
    "addr:street":"Club Ave",
    "iso:country":"US",
    "sg:address":"1921 Club Ave",
    "sg:city":"Kingman",
    "sg:classifiers":[
        {
            "category":"Restaurant",
            "type":"Food & Drink"
        }
    ],
    "sg:phone":"+1 928 718 3300",
    "sg:postcode":"86401",
    "sg:province":"AZ",
    "sg:tags":[
        "eating"
    ],
    "wof:name":"Cappellos",
    "wof:placetype":"venue"
},
  "geometry": {"coordinates":[-114.03197,35.207604],"type":"Point"}
}