{
  "type": "Feature",
  "properties": {
    "addr:full":"11533 E Quintana Ave Mesa AZ 85212",
    "addr:housenumber":"11533",
    "addr:postcode":"85212",
    "addr:street":"E Quintana Ave",
    "iso:country":"US",
    "sg:address":"11533 E Quintana Ave",
    "sg:city":"Mesa",
    "sg:classifiers":[
        {
            "category":"Shopping",
            "type":"Retail Goods"
        }
    ],
    "sg:phone":"+1 480 986 2772",
    "sg:postcode":"85212",
    "sg:province":"AZ",
    "sg:tags":[
        "installs",
        "intercom",
        "alarm",
        "system"
    ],
    "wof:name":"Aware Security Incorporated",
    "wof:placetype":"venue"
},
  "geometry": {"coordinates":[-111.585627,33.346108],"type":"Point"}
}