{
  "type": "Feature",
  "properties": {
    "iso:country":"US",
    "sg:address":"100 S Sarnoff Dr",
    "sg:city":"Tucson",
    "sg:classifiers":[
        {
            "category":"Ice Cream",
            "type":"Food & Drink"
        }
    ],
    "sg:menulink":"http://www.allmenus.com/az/tucson/164663-dairy-queen/menu/",
    "sg:phone":"+1 520 296 4281",
    "sg:postcode":"85710",
    "sg:province":"AZ",
    "sg:tags":[
        "burger",
        "american"
    ],
    "wof:name":"Dairy Queen",
    "wof:placetype":"venue"
},
  "geometry": {"coordinates":[-110.81537299999999,32.220867],"type":"Point"}
}