{
  "type": "Feature",
  "properties": {
    "addr:full":"11361 N 99th Ave Peoria AZ 85345",
    "addr:housenumber":"11361",
    "addr:postcode":"85345",
    "addr:street":"N 99Th Ave",
    "iso:country":"US",
    "sg:address":"11361 N 99th Ave",
    "sg:city":"Peoria",
    "sg:classifiers":[
        {
            "category":"Real Estate",
            "subcategory":"Real Estate Agent",
            "type":"Services"
        }
    ],
    "sg:phone":"+1 623 977 1938",
    "sg:postcode":"85345",
    "sg:province":"AZ",
    "sg:tags":[
        "management"
    ],
    "wof:name":"Camelot Plaza",
    "wof:placetype":"venue"
},
  "geometry": {"coordinates":[-112.272537,33.585539],"type":"Point"}
}