{
  "type": "Feature",
  "properties": {
    "addr:full":"1637 E Missouri Ave Phoenix AZ 85016",
    "addr:housenumber":"1637",
    "addr:postcode":"85016",
    "addr:street":"E Missouri Ave",
    "iso:country":"US",
    "sg:address":"1637 E Missouri Ave",
    "sg:city":"Phoenix",
    "sg:classifiers":[
        {
            "category":"Sports & Exercise",
            "subcategory":"Swimming Pool",
            "type":"Entertainment"
        }
    ],
    "sg:phone":"+1 480 274 8514",
    "sg:postcode":"85016",
    "sg:province":"AZ",
    "wof:name":"S And S Pools",
    "wof:placetype":"venue"
},
  "geometry": {"coordinates":[-112.046693,33.516467],"type":"Point"}
}