{
  "type": "Feature",
  "properties": {
    "addr:full":"3051 W Sousa Ct Anthem AZ 85086",
    "addr:housenumber":"3051",
    "addr:postcode":"85086",
    "addr:street":"W Sousa Ct",
    "iso:country":"US",
    "sg:address":"3051 W Sousa Ct",
    "sg:city":"Anthem",
    "sg:classifiers":[
        {
            "category":"Wholesale",
            "subcategory":"Electrical",
            "type":"Manufacturing & Wholesale Goods"
        }
    ],
    "sg:phone":"+1 623 551 8595",
    "sg:postcode":"85086",
    "sg:province":"AZ",
    "sg:tags":[
        "telecommunication"
    ],
    "wof:name":"Jett Enterprises",
    "wof:placetype":"venue"
},
  "geometry": {"coordinates":[-112.125877,33.851999],"type":"Point"}
}