{
  "type": "Feature",
  "properties": {
    "iso:country":"US",
    "sg:address":"1121 E Missouri Ave",
    "sg:city":"Phoenix",
    "sg:classifiers":[
        {
            "category":"Real Estate",
            "subcategory":"Developer",
            "type":"Services"
        }
    ],
    "sg:phone":"+1 602 604 0878",
    "sg:postcode":"85014",
    "sg:province":"AZ",
    "wof:name":"Biltmore Associates",
    "wof:placetype":"venue"
},
  "geometry": {"coordinates":[-112.058701,33.516419],"type":"Point"}
}