{
  "type": "Feature",
  "properties": {
    "addr:full":"6501 W Frye Rd Chandler AZ 85226",
    "addr:housenumber":"6501",
    "addr:postcode":"85226",
    "addr:street":"W Frye Rd",
    "iso:country":"US",
    "sg:address":"6501 W Frye Rd",
    "sg:city":"Chandler",
    "sg:classifiers":[
        {
            "category":"Shopping",
            "subcategory":"Musical Instruments",
            "type":"Retail Goods"
        }
    ],
    "sg:phone":"+1 602 438 7094",
    "sg:postcode":"85226",
    "sg:province":"AZ",
    "sg:tags":[
        "music",
        "dealer"
    ],
    "wof:name":"Crash Music",
    "wof:placetype":"venue"
},
  "geometry": {"coordinates":[-111.956441,33.298857],"type":"Point"}
}