{
  "type": "Feature",
  "properties": {
    "iso:country":"US",
    "sg:address":"2540 E Indian School Rd",
    "sg:city":"Phoenix",
    "sg:classifiers":[
        {
            "category":"Personal",
            "subcategory":"Beauty Salon",
            "type":"Services"
        }
    ],
    "sg:phone":"+1 602 312 5674",
    "sg:postcode":"85016",
    "sg:province":"AZ",
    "wof:name":"Styles By Lori",
    "wof:placetype":"venue"
},
  "geometry": {"coordinates":[-112.027162,33.494886],"type":"Point"}
}