{
  "type": "Feature",
  "properties": {
    "iso:country":"US",
    "sg:address":"415 E Thunderbird Trl",
    "sg:city":"Phoenix",
    "sg:classifiers":[
        {
            "category":"Building & Trades",
            "subcategory":"Construction",
            "type":"Services"
        }
    ],
    "sg:phone":"+1 602 305 6815",
    "sg:postcode":"85042",
    "sg:province":"AZ",
    "sg:tags":[
        "concrete",
        "contractor"
    ],
    "wof:name":"Eagle Concrete & Construction",
    "wof:placetype":"venue"
},
  "geometry": {"coordinates":[-112.06623999999999,33.358097],"type":"Point"}
}