{
  "type": "Feature",
  "properties": {
    "iso:country":"US",
    "sg:address":"18737 E Swan Dr",
    "sg:city":"Queen Creek",
    "sg:classifiers":[
        {
            "category":"Home & Garden",
            "subcategory":"Building Materials",
            "type":"Retail Goods"
        }
    ],
    "sg:phone":"+1 480 457 8706",
    "sg:postcode":"85242",
    "sg:province":"AZ",
    "sg:tags":[
        "stone"
    ],
    "wof:name":"Cortina Stone Creations",
    "wof:placetype":"venue"
},
  "geometry": {"coordinates":[-111.678764,33.276309],"type":"Point"}
}