{
  "type": "Feature",
  "properties": {
    "iso:country":"US",
    "sg:address":"6302 W Bell Rd",
    "sg:city":"Glendale",
    "sg:classifiers":[
        {
            "category":"Food & Beverages",
            "subcategory":"Liquor & Beverages",
            "type":"Retail Goods"
        }
    ],
    "sg:phone":"+1 623 878 7730",
    "sg:postcode":"85308",
    "sg:province":"AZ",
    "sg:tags":[
        "store"
    ],
    "wof:name":"Bell Tower Liquors",
    "wof:placetype":"venue"
},
  "geometry": {"coordinates":[-112.202896,33.638356],"type":"Point"}
}