{
  "type": "Feature",
  "properties": {
    "iso:country":"US",
    "sg:address":"5819 W Camelback Rd",
    "sg:city":"Phoenix",
    "sg:classifiers":[
        {
            "category":"Manufacturing",
            "subcategory":"Jewelry",
            "type":"Manufacturing & Wholesale Goods"
        },
        {
            "category":"Banks & Credit Unions",
            "subcategory":"Financial Services",
            "type":"Services"
        }
    ],
    "sg:phone":"+1 623 845 1911",
    "sg:postcode":"85031",
    "sg:province":"AZ",
    "sg:tags":[
        "platinum",
        "gold",
        "cashing",
        "loan",
        "silver",
        "payday",
        "buyer",
        "alternative",
        "check"
    ],
    "sg:website":"http://www.speedycash.com",
    "wof:name":"Speedy Cash",
    "wof:placetype":"venue"
},
  "geometry": {"coordinates":[-112.18469899999999,33.50943],"type":"Point"}
}