{
  "type": "Feature",
  "properties": {
    "addr:full":"4554 E Broadway Blvd Tucson AZ 85711",
    "addr:housenumber":"4554",
    "addr:postcode":"85711",
    "addr:street":"E Broadway Blvd",
    "iso:country":"US",
    "sg:address":"4554 E Broadway Blvd",
    "sg:city":"Tucson",
    "sg:classifiers":[
        {
            "category":"Government",
            "subcategory":"Office",
            "type":"Public Place"
        }
    ],
    "sg:phone":"+1 520 886 8723",
    "sg:postcode":"85711",
    "sg:province":"AZ",
    "sg:tags":[
        "armed",
        "force",
        "recruiting"
    ],
    "wof:name":"US Air Force Recruiting",
    "wof:placetype":"venue"
},
  "geometry": {"coordinates":[-110.895529,32.221438],"type":"Point"}
}