{
  "type": "Feature",
  "properties": {
    "iso:country":"US",
    "sg:address":"2630 W Deer Valley Rd",
    "sg:city":"Phoenix",
    "sg:classifiers":[
        {
            "category":"Building & Trades",
            "subcategory":"Landscaping Services",
            "type":"Services"
        }
    ],
    "sg:phone":"+1 623 587 1364",
    "sg:postcode":"85027",
    "sg:province":"AZ",
    "sg:tags":[
        "landscape"
    ],
    "wof:name":"Backyard Mall",
    "wof:placetype":"venue"
},
  "geometry": {"coordinates":[-112.1164,33.683866],"type":"Point"}
}