{
  "type": "Feature",
  "properties": {
    "addr:full":"5925 Wagon Wheel Ln Lakeside AZ 85929",
    "addr:housenumber":"5925",
    "addr:postcode":"85929",
    "addr:street":"Wagon Wheel Ln",
    "iso:country":"US",
    "sg:address":"5925 Wagon Wheel Ln",
    "sg:city":"Lakeside",
    "sg:classifiers":[
        {
            "category":"Manufacturing",
            "subcategory":"Apparel",
            "type":"Manufacturing & Wholesale Goods"
        }
    ],
    "sg:phone":"+1 928 537 3847",
    "sg:postcode":"85929",
    "sg:province":"AZ",
    "wof:name":"Pine Needle Embroidery",
    "wof:placetype":"venue"
},
  "geometry": {"coordinates":[-110.019323,34.190815],"type":"Point"}
}