{
  "type": "Feature",
  "properties": {
    "iso:country":"US",
    "sg:address":"4323 W Cactus Rd",
    "sg:city":"Glendale",
    "sg:classifiers":[
        {
            "category":"Insurance",
            "subcategory":"Insurance Agent",
            "type":"Services"
        }
    ],
    "sg:phone":"+1 623 847 7500",
    "sg:postcode":"85304",
    "sg:province":"AZ",
    "wof:name":"Sam Ramirez Insurance",
    "wof:placetype":"venue"
},
  "geometry": {"coordinates":[-112.153871,33.596265],"type":"Point"}
}