{
  "type": "Feature",
  "properties": {
    "iso:country":"US",
    "sg:address":"7777 E Valencia Rd",
    "sg:city":"Tucson",
    "sg:classifiers":[
        {
            "category":"Freight",
            "type":"Transportation"
        }
    ],
    "sg:phone":"+1 520 574 4325",
    "sg:postcode":"85747",
    "sg:province":"AZ",
    "sg:tags":[
        "trucking"
    ],
    "wof:name":"Eagle KMC LLC",
    "wof:placetype":"venue"
},
  "geometry": {"coordinates":[-110.829357,32.128702],"type":"Point"}
}