{
  "type": "Feature",
  "properties": {
    "iso:country":"US",
    "sg:address":"1217 W Nidito Pl",
    "sg:city":"Tucson",
    "sg:classifiers":[
        {
            "category":"Professional",
            "type":"Services"
        }
    ],
    "sg:phone":"+1 520 888 2391",
    "sg:postcode":"85705",
    "sg:province":"AZ",
    "wof:name":"Robin M Peru",
    "wof:placetype":"venue"
},
  "geometry": {"coordinates":[-110.991272,32.281713],"type":"Point"}
}