{
  "type": "Feature",
  "properties": {
    "addr:full":"1245 W Baseline Rd Tempe AZ 85283",
    "addr:housenumber":"1245",
    "addr:postcode":"85283",
    "addr:street":"W Baseline Rd",
    "iso:country":"US",
    "sg:address":"1245 W Baseline Rd",
    "sg:city":"Tempe",
    "sg:classifiers":[
        {
            "category":"Restaurant",
            "type":"Food & Drink"
        }
    ],
    "sg:phone":"+1 480 730 6894",
    "sg:postcode":"85283",
    "sg:province":"AZ",
    "sg:tags":[
        "eating"
    ],
    "wof:name":"Titos Pizza & Wings",
    "wof:placetype":"venue"
},
  "geometry": {"coordinates":[-111.956925,33.37824],"type":"Point"}
}