{
  "type": "Feature",
  "properties": {
    "iso:country":"US",
    "sg:address":"5899 W Jefferson St",
    "sg:city":"Phoenix",
    "sg:classifiers":[
        {
            "category":"Professional",
            "subcategory":"Computer Services",
            "type":"Services"
        }
    ],
    "sg:phone":"+1 480 907 3523",
    "sg:postcode":"85043",
    "sg:province":"AZ",
    "sg:tags":[
        "repair",
        "equipment-service"
    ],
    "wof:name":"Computer Repair Phoenix AZ - Geeks Mobile",
    "wof:placetype":"venue"
},
  "geometry": {"coordinates":[-112.18654600000001,33.446201],"type":"Point"}
}