{
  "type": "Feature",
  "properties": {
    "iso:country":"US",
    "sg:address":"2727 E Cortez St",
    "sg:city":"Phoenix",
    "sg:classifiers":[
        {
            "category":"Building & Trades",
            "subcategory":"Construction",
            "type":"Services"
        }
    ],
    "sg:phone":"+1 602 992 3381",
    "sg:postcode":"85028",
    "sg:province":"AZ",
    "sg:tags":[
        "product",
        "asphalt"
    ],
    "wof:name":"Sinagua Paving Inc",
    "wof:placetype":"venue"
},
  "geometry": {"coordinates":[-112.022251,33.591345],"type":"Point"}
}