{
  "type": "Feature",
  "properties": {
    "addr:full":"500 W 10th Pl Mesa AZ 85201",
    "addr:housenumber":"500",
    "addr:postcode":"85201",
    "addr:street":"W 10Th Pl",
    "iso:country":"US",
    "sg:address":"500 W 10th Pl",
    "sg:city":"Mesa",
    "sg:classifiers":[
        {
            "category":"Health Services",
            "subcategory":"Clinic",
            "type":"Services"
        }
    ],
    "sg:phone":"+1 480 461 2830",
    "sg:postcode":"85201",
    "sg:province":"AZ",
    "sg:tags":[
        "allied"
    ],
    "wof:name":"Employee Health",
    "wof:placetype":"venue"
},
  "geometry": {"coordinates":[-111.841491,33.434235],"type":"Point"}
}