{
  "type": "Feature",
  "properties": {
    "iso:country":"US",
    "sg:address":"4940 S Park Ave",
    "sg:city":"Tucson",
    "sg:classifiers":[
        {
            "category":"Food & Beverages",
            "subcategory":"Liquor & Beverages",
            "type":"Retail Goods"
        }
    ],
    "sg:phone":"+1 520 294 3485",
    "sg:postcode":"85706",
    "sg:province":"AZ",
    "sg:tags":[
        "alcoholic"
    ],
    "wof:name":"Liquor Express II",
    "wof:placetype":"venue"
},
  "geometry": {"coordinates":[-110.956231,32.163253],"type":"Point"}
}