{
  "type": "Feature",
  "properties": {
    "iso:country":"US",
    "sg:address":"19900 State Hwy 85",
    "sg:city":"Buckeye",
    "sg:classifiers":[
        {
            "category":"Organizations",
            "subcategory":"Religious Organization",
            "type":"Services"
        }
    ],
    "sg:phone":"+1 623 386 4090",
    "sg:postcode":"85326",
    "sg:province":"AZ",
    "sg:tags":[
        "church"
    ],
    "wof:name":"Liberty United Methodist Chr",
    "wof:placetype":"venue"
},
  "geometry": {"coordinates":[-112.637142,33.252314],"type":"Point"}
}