{
  "type": "Feature",
  "properties": {
    "iso:country":"US",
    "sg:address":"2699 Poseidon Dr",
    "sg:city":"Lake Havasu City",
    "sg:classifiers":[
        {
            "category":"Building & Trades",
            "subcategory":"Electrical",
            "type":"Services"
        }
    ],
    "sg:phone":"+1 928 854 2471",
    "sg:postcode":"86403",
    "sg:province":"AZ",
    "sg:tags":[
        "electric",
        "contractor"
    ],
    "wof:name":"PCH Electric",
    "wof:placetype":"venue"
},
  "geometry": {"coordinates":[-114.320101,34.503042],"type":"Point"}
}