{
  "type": "Feature",
  "properties": {
    "iso:country":"US",
    "sg:address":"4418 N Agua Fria Dr",
    "sg:city":"Prescott Valley",
    "sg:classifiers":[
        {
            "category":"Organizations",
            "subcategory":"Religious Organization",
            "type":"Services"
        }
    ],
    "sg:phone":"+1 928 775 3314",
    "sg:postcode":"86314",
    "sg:province":"AZ",
    "sg:tags":[
        "church"
    ],
    "sg:website":"www.victoryworshipcenteraz.org",
    "wof:name":"Victory Worship Ctr",
    "wof:placetype":"venue"
},
  "geometry": {"coordinates":[-112.337817,34.60615],"type":"Point"}
}