{
  "type": "Feature",
  "properties": {
    "iso:country":"US",
    "sg:address":"22543 N 77th Pl",
    "sg:city":"Scottsdale",
    "sg:classifiers":[
        {
            "category":"Professional",
            "type":"Services"
        }
    ],
    "sg:phone":"+1 480 502 9111",
    "sg:postcode":"85255",
    "sg:province":"AZ",
    "wof:name":"Tom Schoenbeck",
    "wof:placetype":"venue"
},
  "geometry": {"coordinates":[-111.91275,33.689954],"type":"Point"}
}