{
  "type": "Feature",
  "properties": {
    "iso:country":"US",
    "sg:address":"3408 E Grant Rd",
    "sg:city":"Tucson",
    "sg:classifiers":[
        {
            "category":"Shopping",
            "subcategory":"Used Merchandise",
            "type":"Retail Goods"
        }
    ],
    "sg:phone":"+1 520 326 6502",
    "sg:postcode":"85716",
    "sg:province":"AZ",
    "sg:tags":[
        "antique"
    ],
    "wof:name":"Antique Mini-Mall",
    "wof:placetype":"venue"
},
  "geometry": {"coordinates":[-110.919029,32.25041],"type":"Point"}
}