{
  "type": "Feature",
  "properties": {
    "iso:country":"US",
    "sg:address":"4435 E Chandler Blvd Ste 200",
    "sg:city":"Phoenix",
    "sg:classifiers":[
        {
            "category":"Real Estate",
            "subcategory":"Real Estate Services",
            "type":"Services"
        },
        {
            "category":"Real Estate",
            "subcategory":"Real Estate Agent",
            "type":"Services"
        }
    ],
    "sg:phone":"+1 480 961 5800",
    "sg:postcode":"85048",
    "sg:province":"AZ",
    "sg:tags":[
        "buyer",
        "broker"
    ],
    "sg:website":"http://www.pameagan.com",
    "wof:name":"Realty Executives",
    "wof:placetype":"venue"
},
  "geometry": {"coordinates":[-111.987869,33.305141],"type":"Point"}
}