{
  "type": "Feature",
  "properties": {
    "iso:country":"US",
    "sg:address":"1048 E Rd 4 S",
    "sg:city":"Chino Valley",
    "sg:classifiers":[
        {
            "category":"Building & Trades",
            "subcategory":"Construction",
            "type":"Services"
        }
    ],
    "sg:phone":"+1 928 636 0548",
    "sg:postcode":"86323",
    "sg:province":"AZ",
    "sg:tags":[
        "house"
    ],
    "wof:name":"Hands On Builder Inc",
    "wof:placetype":"venue"
},
  "geometry": {"coordinates":[-112.443663,34.716664],"type":"Point"}
}