{
  "type": "Feature",
  "properties": {
    "iso:country":"US",
    "sg:address":"345 N Arizona Ave",
    "sg:city":"Chandler",
    "sg:classifiers":[
        {
            "category":"Professional",
            "subcategory":"Lawyer & Legal Services",
            "type":"Services"
        }
    ],
    "sg:phone":"+1 480 899 8931",
    "sg:postcode":"85225",
    "sg:province":"AZ",
    "sg:tags":[
        "attorney"
    ],
    "wof:name":"William A Mundell",
    "wof:placetype":"venue"
},
  "geometry": {"coordinates":[-111.84136599999999,33.308986],"type":"Point"}
}