{
  "type": "Feature",
  "properties": {
    "addr:full":"1285 E Prince Rd Tucson AZ 85719",
    "addr:housenumber":"1285",
    "addr:postcode":"85719",
    "addr:street":"E Prince Rd",
    "iso:country":"US",
    "sg:address":"1285 E Prince Rd",
    "sg:city":"Tucson",
    "sg:classifiers":[
        {
            "category":"Food & Beverages",
            "subcategory":"Liquor & Beverages",
            "type":"Retail Goods"
        }
    ],
    "sg:phone":"+1 520 887 7130",
    "sg:postcode":"85719",
    "sg:province":"AZ",
    "sg:tags":[
        "alcoholic"
    ],
    "wof:name":"Lucky J Market",
    "wof:placetype":"venue"
},
  "geometry": {"coordinates":[-110.95342100000001,32.272198],"type":"Point"}
}