{
  "type": "Feature",
  "properties": {
    "iso:country":"US",
    "sg:address":"6282 E Lord Cir",
    "sg:city":"Prescott Valley",
    "sg:classifiers":[
        {
            "category":"Building & Trades",
            "subcategory":"Plumbing",
            "type":"Services"
        }
    ],
    "sg:phone":"+1 928 775 5903",
    "sg:postcode":"86314",
    "sg:province":"AZ",
    "sg:tags":[
        "contractor"
    ],
    "wof:name":"Vjs Plumbing Contracts Inc",
    "wof:placetype":"venue"
},
  "geometry": {"coordinates":[-112.355147,34.588905],"type":"Point"}
}