{
  "type": "Feature",
  "properties": {
    "addr:full":"28234 N Tatum Blvd Cave Creek AZ 85331",
    "addr:housenumber":"28234",
    "addr:postcode":"85331",
    "addr:street":"N Tatum Blvd",
    "iso:country":"US",
    "sg:address":"28234 N Tatum Blvd",
    "sg:city":"Cave Creek",
    "sg:classifiers":[
        {
            "category":"Restaurant",
            "type":"Food & Drink"
        }
    ],
    "sg:phone":"+1 480 794 1469",
    "sg:postcode":"85331",
    "sg:province":"AZ",
    "wof:name":"Ten Restaurant",
    "wof:placetype":"venue"
},
  "geometry": {"coordinates":[-111.978106,33.741591],"type":"Point"}
}