{
  "type": "Feature",
  "properties": {
    "iso:country":"US",
    "sg:address":"4509 E Downing St",
    "sg:city":"Mesa",
    "sg:classifiers":[
        {
            "category":"Building & Trades",
            "subcategory":"Construction",
            "type":"Services"
        }
    ],
    "sg:phone":"+1 480 832 0331",
    "sg:postcode":"85205",
    "sg:province":"AZ",
    "sg:tags":[
        "roofing",
        "contractor"
    ],
    "wof:name":"Mountainside Roofing & Insptn",
    "wof:placetype":"venue"
},
  "geometry": {"coordinates":[-111.73139999999999,33.429357],"type":"Point"}
}