{
  "type": "Feature",
  "properties": {
    "iso:country":"US",
    "sg:address":"2117 S 48th St",
    "sg:city":"Tempe",
    "sg:classifiers":[
        {
            "category":"Retail",
            "subcategory":"Portrait Studio",
            "type":"Services"
        },
        {
            "category":"Professional",
            "subcategory":"Art Services",
            "type":"Services"
        },
        {
            "category":"Professional",
            "subcategory":"Printing & Photocopies",
            "type":"Services"
        }
    ],
    "sg:phone":"+1 602 438 0770",
    "sg:postcode":"85282",
    "sg:province":"AZ",
    "sg:tags":[
        "photographic",
        "photographers-portrait",
        "photographers-commercial",
        "rental",
        "darkroom"
    ],
    "wof:name":"Dorian Studio",
    "wof:placetype":"venue"
},
  "geometry": {"coordinates":[-111.97828699999999,33.405515],"type":"Point"}
}