{
  "type": "Feature",
  "properties": {
    "iso:country":"US",
    "sg:address":"2605 S Tomahawk Rd",
    "sg:city":"Apache Junction",
    "sg:classifiers":[
        {
            "category":"Real Estate",
            "subcategory":"Real Estate Operator",
            "type":"Services"
        }
    ],
    "sg:phone":"+1 480 982 1886",
    "sg:postcode":"85219",
    "sg:province":"AZ",
    "sg:tags":[
        "mobile",
        "residential",
        "site",
        "home"
    ],
    "wof:name":"Raindance Mobile Park",
    "wof:placetype":"venue"
},
  "geometry": {"coordinates":[-111.528704,33.39141],"type":"Point"}
}