{
  "type": "Feature",
  "properties": {
    "iso:country":"US",
    "sg:address":"18820 N 83rd Ave",
    "sg:city":"Peoria",
    "sg:classifiers":[
        {
            "category":"Social Services",
            "subcategory":"Child Care",
            "type":"Services"
        },
        {
            "category":"Education",
            "subcategory":"Preschool",
            "type":"Public Place"
        },
        {
            "category":"Education",
            "subcategory":"School",
            "type":"Public Place"
        }
    ],
    "sg:phone":"+1 623 561 0212",
    "sg:postcode":"85382",
    "sg:province":"AZ",
    "sg:tags":[
        "k-",
        "kindergarten",
        "nursery",
        "private",
        "day"
    ],
    "sg:website":"http://www.pcapreschool.com",
    "wof:name":"Phoenix Children's Academy Private Preschool",
    "wof:placetype":"venue"
},
  "geometry": {"coordinates":[-112.23779399999999,33.654722],"type":"Point"}
}