{
  "type": "Feature",
  "properties": {
    "addr:full":"31591 Storage Pl Parker AZ 85344",
    "addr:housenumber":"31591",
    "addr:postcode":"az 85344",
    "addr:street":"Storage Pl",
    "iso:country":"US",
    "sg:address":"31591 Storage Pl",
    "sg:city":"Parker",
    "sg:classifiers":[
        {
            "category":"Freight",
            "type":"Transportation"
        }
    ],
    "sg:phone":"+1 928 667 2811",
    "sg:postcode":"85344",
    "sg:province":"AZ",
    "sg:tags":[
        "commercial",
        "storage"
    ],
    "wof:name":"Lakeside Boat & Mini Storage",
    "wof:placetype":"venue"
},
  "geometry": {"coordinates":[-114.222043,34.187002],"type":"Point"}
}