{
  "type": "Feature",
  "properties": {
    "iso:country":"US",
    "sg:address":"5501 N Robles Ct",
    "sg:city":"Litchfield Park",
    "sg:classifiers":[
        {
            "category":"Building & Trades",
            "subcategory":"Locksmith",
            "type":"Services"
        }
    ],
    "sg:phone":"+1 623 476 4937",
    "sg:postcode":"85340",
    "sg:province":"AZ",
    "sg:tags":[
        "key"
    ],
    "wof:name":"Ahour 24 Hour All Day Avondale A Emergen",
    "wof:placetype":"venue"
},
  "geometry": {"coordinates":[-112.351127,33.515501],"type":"Point"}
}