{
  "type": "Feature",
  "properties": {
    "iso:country":"US",
    "sg:address":"3101 W Thomas Rd",
    "sg:city":"Phoenix",
    "sg:classifiers":[
        {
            "category":"Manufacturing",
            "subcategory":"Musical Instruments",
            "type":"Manufacturing & Wholesale Goods"
        }
    ],
    "sg:phone":"+1 602 973 1395",
    "sg:postcode":"85017",
    "sg:province":"AZ",
    "sg:website":"www.classical-devtronix.com",
    "wof:name":"Classical Organ Inc",
    "wof:placetype":"venue"
},
  "geometry": {"coordinates":[-112.127538,33.480438],"type":"Point"}
}