{
  "type": "Feature",
  "properties": {
    "iso:country":"US",
    "sg:address":"4001 W Indian School Rd",
    "sg:city":"Phoenix",
    "sg:classifiers":[
        {
            "category":"Manufacturing",
            "subcategory":"Retail Goods",
            "type":"Manufacturing & Wholesale Goods"
        }
    ],
    "sg:phone":"+1 602 233 0818",
    "sg:postcode":"85019",
    "sg:province":"AZ",
    "sg:tags":[
        "product",
        "electric",
        "mfg",
        "residential",
        "li",
        "lamp"
    ],
    "wof:name":"Nicole Corp",
    "wof:placetype":"venue"
},
  "geometry": {"coordinates":[-112.151688,33.494959],"type":"Point"}
}