{
  "type": "Feature",
  "properties": {
    "iso:country":"US",
    "sg:address":"2532 N 4th St",
    "sg:city":"Flagstaff",
    "sg:classifiers":[
        {
            "category":"Manufacturing",
            "subcategory":"Printing",
            "type":"Manufacturing & Wholesale Goods"
        }
    ],
    "sg:phone":"+1 928 522 9228",
    "sg:postcode":"86004",
    "sg:province":"AZ",
    "sg:tags":[
        "organization",
        "religious",
        "publishing"
    ],
    "wof:name":"Gotosimpletruth Co Inc",
    "wof:placetype":"venue"
},
  "geometry": {"coordinates":[-111.61340300000001,35.212135],"type":"Point"}
}