{
  "type": "Feature",
  "properties": {
    "addr:full":"9105 N 13th St Phoenix AZ 85020",
    "addr:housenumber":"9105",
    "addr:postcode":"85020",
    "addr:street":"N 13Th St",
    "iso:country":"US",
    "sg:address":"9105 N 13th St",
    "sg:city":"Phoenix",
    "sg:classifiers":[
        {
            "category":"Professional",
            "subcategory":"Management & Consulting",
            "type":"Services"
        }
    ],
    "sg:phone":"+1 602 371 4956",
    "sg:postcode":"85020",
    "sg:province":"AZ",
    "sg:tags":[
        "scooters-repairing",
        "construction",
        "motorcycle",
        "motor"
    ],
    "wof:name":"Cyclops Enterprises",
    "wof:placetype":"venue"
},
  "geometry": {"coordinates":[-112.054598,33.568794],"type":"Point"}
}