{
  "type": "Feature",
  "properties": {
    "iso:country":"US",
    "sg:address":"2326 E Roeser Rd",
    "sg:city":"Phoenix",
    "sg:classifiers":[
        {
            "category":"Social Services",
            "subcategory":"Child Care",
            "type":"Services"
        }
    ],
    "sg:phone":"+1 602 276 5562",
    "sg:postcode":"85040",
    "sg:province":"AZ",
    "wof:name":"Granny's Daycare",
    "wof:placetype":"venue"
},
  "geometry": {"coordinates":[-112.031266,33.399658],"type":"Point"}
}