{
  "type": "Feature",
  "properties": {
    "iso:country":"US",
    "sg:address":"5539 N 7th St",
    "sg:city":"Phoenix",
    "sg:classifiers":[
        {
            "category":"Shopping",
            "subcategory":"Gifts & Souvenirs",
            "type":"Retail Goods"
        }
    ],
    "sg:phone":"+1 602 265 0366",
    "sg:postcode":"85014",
    "sg:province":"AZ",
    "sg:tags":[
        "book"
    ],
    "wof:name":"Jewish Books & Gifts",
    "wof:placetype":"venue"
},
  "geometry": {"coordinates":[-112.064921,33.518165],"type":"Point"}
}