{
  "type": "Feature",
  "properties": {
    "iso:country":"US",
    "sg:address":"515 W Johnson Dr",
    "sg:city":"Payson",
    "sg:classifiers":[
        {
            "category":"Insurance",
            "subcategory":"Insurance Agent",
            "type":"Services"
        }
    ],
    "sg:phone":"+1 928 474 8060",
    "sg:postcode":"85541",
    "sg:province":"AZ",
    "wof:name":"Hartford Insurance",
    "wof:placetype":"venue"
},
  "geometry": {"coordinates":[-111.330234,34.267779],"type":"Point"}
}