{
  "type": "Feature",
  "properties": {
    "iso:country":"US",
    "sg:address":"891 S Main St",
    "sg:city":"Cottonwood",
    "sg:classifiers":[
        {
            "category":"Restaurant",
            "type":"Food & Drink"
        }
    ],
    "sg:phone":"+1 928 634 0043",
    "sg:postcode":"86326",
    "sg:province":"AZ",
    "wof:name":"Randall's Restaurant",
    "wof:placetype":"venue"
},
  "geometry": {"coordinates":[-112.00534500000001,34.723437],"type":"Point"}
}