{
  "type": "Feature",
  "properties": {
    "iso:country":"US",
    "sg:address":"4560 N Jay Ave",
    "sg:city":"Tucson",
    "sg:classifiers":[
        {
            "category":"Building & Trades",
            "subcategory":"Construction",
            "type":"Services"
        }
    ],
    "sg:phone":"+1 520 888 1310",
    "sg:postcode":"85705",
    "sg:province":"AZ",
    "sg:tags":[
        "house"
    ],
    "wof:name":"Ryans New Life Remodeling LLC",
    "wof:placetype":"venue"
},
  "geometry": {"coordinates":[-111.00944699999999,32.290183],"type":"Point"}
}