{
  "type": "Feature",
  "properties": {
    "iso:country":"US",
    "sg:address":"37 W Iron Ave",
    "sg:city":"Mesa",
    "sg:classifiers":[
        {
            "category":"Wholesale",
            "subcategory":"Machinery & Supplies",
            "type":"Manufacturing & Wholesale Goods"
        }
    ],
    "sg:phone":"+1 480 633 4300",
    "sg:postcode":"85210",
    "sg:province":"AZ",
    "sg:tags":[
        "agricultural"
    ],
    "wof:name":"Empire Hydraulic Service",
    "wof:placetype":"venue"
},
  "geometry": {"coordinates":[-111.838982,33.384196],"type":"Point"}
}