{
  "type": "Feature",
  "properties": {
    "iso:country":"US",
    "sg:address":"901 E Broadway Rd",
    "sg:city":"Mesa",
    "sg:classifiers":[
        {
            "category":"Personal",
            "subcategory":"Beauty Salon",
            "type":"Services"
        }
    ],
    "sg:phone":"+1 480 962 8841",
    "sg:postcode":"85204",
    "sg:province":"AZ",
    "wof:name":"Dynamite Shack",
    "wof:placetype":"venue"
},
  "geometry": {"coordinates":[-111.81079800000001,33.407866],"type":"Point"}
}