{
  "type": "Feature",
  "properties": {
    "iso:country":"US",
    "sg:address":"3602 E Southern Ave Ste 1",
    "sg:city":"Phoenix",
    "sg:classifiers":[
        {
            "category":"Building & Trades",
            "subcategory":"Construction",
            "type":"Services"
        }
    ],
    "sg:phone":"+1 520 622 2202",
    "sg:postcode":"85040",
    "sg:province":"AZ",
    "sg:tags":[
        "system",
        "contractor",
        "air conditioning"
    ],
    "sg:website":"http://www.cxconcepts.com",
    "wof:name":"The Linc Group",
    "wof:placetype":"venue"
},
  "geometry": {"coordinates":[-112.00408400000001,33.39259],"type":"Point"}
}