{
  "type": "Feature",
  "properties": {
    "addr:full":"3489 E Cuadrilla Ln Yuma AZ 85365",
    "addr:housenumber":"3489",
    "addr:postcode":"85365",
    "addr:street":"E Cuadrilla Ln",
    "iso:country":"US",
    "sg:address":"3489 E Cuadrilla Ln",
    "sg:city":"Yuma",
    "sg:classifiers":[
        {
            "category":"Farming",
            "subcategory":"Orchard",
            "type":"Manufacturing & Wholesale Goods"
        }
    ],
    "sg:phone":"+1 928 726 8284",
    "sg:postcode":"85365",
    "sg:province":"AZ",
    "sg:tags":[
        "citrus",
        "grove",
        "fruit"
    ],
    "wof:name":"Kuechel Farms",
    "wof:placetype":"venue"
},
  "geometry": {"coordinates":[-114.573356,32.627356],"type":"Point"}
}