{
  "type": "Feature",
  "properties": {
    "addr:full":"501 E Monroe Ave Buckeye AZ 85326",
    "addr:housenumber":"501",
    "addr:postcode":"85326",
    "addr:street":"E Monroe Ave",
    "iso:country":"US",
    "sg:address":"501 E Monroe Ave",
    "sg:city":"Buckeye",
    "sg:classifiers":[
        {
            "category":"Retail",
            "subcategory":"Auto Rental",
            "type":"Services"
        }
    ],
    "sg:phone":"+1 623 327 9442",
    "sg:postcode":"85326",
    "sg:province":"AZ",
    "sg:tags":[
        "renting",
        "truck",
        "leasing"
    ],
    "wof:name":"Budget Truck Rental",
    "wof:placetype":"venue"
},
  "geometry": {"coordinates":[-112.58358200000001,33.370492],"type":"Point"}
}