{
  "type": "Feature",
  "properties": {
    "addr:full":"3619 E Monterosa St # 111 Phoenix AZ 85018",
    "addr:housenumber":"3619",
    "addr:postcode":"85018",
    "addr:street":"E Monterosa St # 111",
    "iso:country":"US",
    "sg:address":"3619 E Monterosa St # 111",
    "sg:city":"Phoenix",
    "sg:classifiers":[
        {
            "category":"Real Estate",
            "subcategory":"Real Estate Services",
            "type":"Services"
        }
    ],
    "sg:phone":"+1 602 682 7358",
    "sg:postcode":"85018",
    "sg:province":"AZ",
    "sg:tags":[
        "management",
        "condominium"
    ],
    "wof:name":"Mountain Ridge Condominium Assoc",
    "wof:placetype":"venue"
},
  "geometry": {"coordinates":[-112.001806,33.496552],"type":"Point"}
}