{
  "type": "Feature",
  "properties": {
    "iso:country":"US",
    "sg:address":"3720 N Tohono Dr",
    "sg:city":"Eloy",
    "sg:classifiers":[
        {
            "category":"Restaurant",
            "type":"Food & Drink"
        }
    ],
    "sg:menulink":"http://www.allmenus.com/az/eloy/74787-pizza-hut/menu/",
    "sg:phone":"+1 520 466 9407",
    "sg:postcode":"85231",
    "sg:province":"AZ",
    "sg:tags":[
        "american",
        "pizza"
    ],
    "wof:name":"Pizza Hut",
    "wof:placetype":"venue"
},
  "geometry": {"coordinates":[-111.61506,32.773751],"type":"Point"}
}