{
  "type": "Feature",
  "properties": {
    "addr:full":"5042 E McDowell Rd Phoenix AZ 85008",
    "addr:housenumber":"5042",
    "addr:postcode":"85008",
    "addr:street":"E Mcdowell Rd",
    "iso:country":"US",
    "sg:address":"5042 E McDowell Rd",
    "sg:city":"Phoenix",
    "sg:classifiers":[
        {
            "category":"Wholesale",
            "subcategory":"Jewelry",
            "type":"Manufacturing & Wholesale Goods"
        }
    ],
    "sg:phone":"+1 602 231 8709",
    "sg:postcode":"85008",
    "sg:province":"AZ",
    "sg:tags":[
        "beads"
    ],
    "wof:name":"SII Findings",
    "wof:placetype":"venue"
},
  "geometry": {"coordinates":[-111.972628,33.465653],"type":"Point"}
}