{
  "type": "Feature",
  "properties": {
    "iso:country":"US",
    "sg:address":"3160 W Apache Trl",
    "sg:city":"Apache Junction",
    "sg:classifiers":[
        {
            "category":"Banks & Credit Unions",
            "subcategory":"Bank",
            "type":"Services"
        }
    ],
    "sg:phone":"+1 480 827 6795",
    "sg:postcode":"85220",
    "sg:province":"AZ",
    "sg:tags":[
        "state",
        "commercial"
    ],
    "wof:name":"Bank of America",
    "wof:placetype":"venue"
},
  "geometry": {"coordinates":[-111.580192,33.415129],"type":"Point"}
}