{
  "type": "Feature",
  "properties": {
    "iso:country":"US",
    "sg:address":"19430 E Thornton Rd",
    "sg:city":"Queen Creek",
    "sg:classifiers":[
        {
            "category":"Professional",
            "type":"Services"
        }
    ],
    "sg:phone":"+1 480 888 7806",
    "sg:postcode":"85242",
    "sg:province":"AZ",
    "sg:tags":[
        "establishment"
    ],
    "wof:name":"Madison Components Inc",
    "wof:placetype":"venue"
},
  "geometry": {"coordinates":[-111.663272,33.264054],"type":"Point"}
}