{
  "type": "Feature",
  "properties": {
    "iso:country":"US",
    "sg:address":"1551 S Hale Dr",
    "sg:city":"Apache Junction",
    "sg:classifiers":[
        {
            "category":"Building & Trades",
            "subcategory":"Construction",
            "type":"Services"
        }
    ],
    "sg:phone":"+1 480 983 6438",
    "sg:postcode":"85220",
    "sg:province":"AZ",
    "wof:name":"Gerola Grading",
    "wof:placetype":"venue"
},
  "geometry": {"coordinates":[-111.572478,33.403718],"type":"Point"}
}