{
  "type": "Feature",
  "properties": {
    "iso:country":"US",
    "sg:address":"7135 E Main St",
    "sg:city":"Scottsdale",
    "sg:classifiers":[
        {
            "category":"Shopping",
            "type":"Retail Goods"
        }
    ],
    "sg:phone":"+1 480 947 3548",
    "sg:postcode":"85251",
    "sg:province":"AZ",
    "sg:tags":[
        "consultant",
        "galleries",
        "art",
        "gallery",
        "merchandise"
    ],
    "sg:website":"http://www.jcgltd.com",
    "wof:name":"Joan Cawley Gallery",
    "wof:placetype":"venue"
},
  "geometry": {"coordinates":[-111.927515,33.493111],"type":"Point"}
}