{
  "type": "Feature",
  "properties": {
    "iso:country":"US",
    "sg:address":"415 S May Ave",
    "sg:city":"Yuma",
    "sg:classifiers":[
        {
            "category":"Building & Trades",
            "subcategory":"Construction",
            "type":"Services"
        },
        {
            "category":"Recreation",
            "subcategory":"Campground",
            "type":"Entertainment"
        }
    ],
    "sg:phone":"+1 928 783 1925",
    "sg:postcode":"85364",
    "sg:province":"AZ",
    "sg:tags":[
        "manufactured",
        "housing-communities",
        "recreational",
        "park",
        "vehicle"
    ],
    "wof:name":"Atlasta Trailer Park",
    "wof:placetype":"venue"
},
  "geometry": {"coordinates":[-114.659012,32.719639],"type":"Point"}
}