{
  "type": "Feature",
  "properties": {
    "iso:country":"US",
    "sg:address":"7339 E Acoma Dr Ste 2",
    "sg:city":"Scottsdale",
    "sg:classifiers":[
        {
            "category":"Manufacturing",
            "subcategory":"Building Materials",
            "type":"Manufacturing & Wholesale Goods"
        },
        {
            "category":"Home & Garden",
            "subcategory":"Carpets & Floor Coverings",
            "type":"Retail Goods"
        }
    ],
    "sg:phone":"+1 480 607 1215",
    "sg:postcode":"85260",
    "sg:province":"AZ",
    "sg:tags":[
        "materials-wholesale",
        "manufacturer"
    ],
    "wof:name":"Valley Wholesale",
    "wof:placetype":"venue"
},
  "geometry": {"coordinates":[-111.92282,33.618009],"type":"Point"}
}