{
  "type": "Feature",
  "properties": {
    "iso:country":"US",
    "sg:address":"3623 E Hartford Ave",
    "sg:city":"Phoenix",
    "sg:classifiers":[
        {
            "category":"Wholesale",
            "subcategory":"Vending Machines",
            "type":"Manufacturing & Wholesale Goods"
        }
    ],
    "sg:phone":"+1 602 788 1249",
    "sg:postcode":"85032",
    "sg:province":"AZ",
    "sg:tags":[
        "operator"
    ],
    "wof:name":"M&P Vending",
    "wof:placetype":"venue"
},
  "geometry": {"coordinates":[-112.00410100000001,33.642111],"type":"Point"}
}