{
  "type": "Feature",
  "properties": {
    "iso:country":"US",
    "sg:address":"1704 W Bethany Home Rd",
    "sg:city":"Phoenix",
    "sg:classifiers":[
        {
            "category":"Insurance",
            "subcategory":"Hazard Insurance",
            "type":"Services"
        }
    ],
    "sg:phone":"+1 602 249 1037",
    "sg:postcode":"85015",
    "sg:province":"AZ",
    "sg:website":"http://statefarm.mqgroup.com/url.asp?usr=031716",
    "wof:name":"State Farm Insurance Agent-Andra Jeffress",
    "wof:placetype":"venue"
},
  "geometry": {"coordinates":[-112.095544,33.524061],"type":"Point"}
}