{
  "type": "Feature",
  "properties": {
    "addr:full":"3430 N 1st Ave Tucson AZ 85719",
    "addr:housenumber":"3430",
    "addr:postcode":"85719",
    "addr:street":"N 1St Ave",
    "iso:country":"US",
    "sg:address":"3430 N 1st Ave",
    "sg:city":"Tucson",
    "sg:classifiers":[
        {
            "category":"Insurance",
            "subcategory":"Insurance Agent",
            "type":"Services"
        }
    ],
    "sg:phone":"+1 520 887 5566",
    "sg:postcode":"85719",
    "sg:province":"AZ",
    "wof:name":"Sountywest Consolidated Asrn",
    "wof:placetype":"venue"
},
  "geometry": {"coordinates":[-110.960937,32.269571],"type":"Point"}
}