{
  "type": "Feature",
  "properties": {
    "iso:country":"US",
    "sg:address":"4558 W Lord Redman Loop",
    "sg:city":"Tucson",
    "sg:classifiers":[
        {
            "category":"Banks & Credit Unions",
            "subcategory":"Bank",
            "type":"Services"
        }
    ],
    "sg:phone":"+1 520 744 0331",
    "sg:postcode":"85741",
    "sg:province":"AZ",
    "sg:tags":[
        "other",
        "plan",
        "card"
    ],
    "wof:name":"Bankcard Central Inc",
    "wof:placetype":"venue"
},
  "geometry": {"coordinates":[-111.062429,32.355435],"type":"Point"}
}