{
  "type": "Feature",
  "properties": {
    "iso:country":"US",
    "sg:address":"1425 W Southern Ave",
    "sg:city":"Mesa",
    "sg:classifiers":[
        {
            "category":"Personal",
            "type":"Services"
        }
    ],
    "sg:phone":"+1 480 833 6785",
    "sg:postcode":"85202",
    "sg:province":"AZ",
    "sg:tags":[
        "wear",
        "formal"
    ],
    "wof:name":"Gary's Tux Shop",
    "wof:placetype":"venue"
},
  "geometry": {"coordinates":[-111.861496,33.393025],"type":"Point"}
}