{
  "type": "Feature",
  "properties": {
    "iso:country":"US",
    "sg:address":"7831 N 67th Ave",
    "sg:city":"Glendale",
    "sg:classifiers":[
        {
            "category":"Manufacturing",
            "subcategory":"Signs",
            "type":"Manufacturing & Wholesale Goods"
        }
    ],
    "sg:phone":"+1 623 215 2738",
    "sg:postcode":"85301",
    "sg:province":"AZ",
    "sg:tags":[
        "truss",
        "construction-wholesale",
        "manufacturer"
    ],
    "wof:name":"Truss Fab",
    "wof:placetype":"venue"
},
  "geometry": {"coordinates":[-112.20287399999999,33.550966],"type":"Point"}
}