{
  "type": "Feature",
  "properties": {
    "iso:country":"US",
    "sg:address":"6710 W Chicago St",
    "sg:city":"Chandler",
    "sg:classifiers":[
        {
            "category":"Manufacturing",
            "subcategory":"Tools & Machinery",
            "type":"Manufacturing & Wholesale Goods"
        }
    ],
    "sg:phone":"+1 480 753 1776",
    "sg:postcode":"85226",
    "sg:province":"AZ",
    "sg:tags":[
        "machine",
        "shop",
        "mfg"
    ],
    "wof:name":"Allset Precision",
    "wof:placetype":"venue"
},
  "geometry": {"coordinates":[-111.959172,33.300415],"type":"Point"}
}