{
  "type": "Feature",
  "properties": {
    "iso:country":"US",
    "sg:address":"317 N Huachuca Blvd",
    "sg:city":"Huachuca City",
    "sg:classifiers":[
        {
            "category":"Autos & Motor Vehicles",
            "subcategory":"Motorcycle Sales",
            "type":"Retail Goods"
        }
    ],
    "sg:phone":"+1 520 456 2237",
    "sg:postcode":"85616",
    "sg:province":"AZ",
    "sg:tags":[
        "repair"
    ],
    "wof:name":"Desert Donkey Cstm Mtcyc & ACC",
    "wof:placetype":"venue"
},
  "geometry": {"coordinates":[-110.335612,31.626549],"type":"Point"}
}