{
  "type": "Feature",
  "properties": {
    "iso:country":"US",
    "sg:address":"6112 N 27th Ave",
    "sg:city":"Phoenix",
    "sg:classifiers":[
        {
            "category":"Shopping",
            "subcategory":"Jewelry",
            "type":"Retail Goods"
        }
    ],
    "sg:phone":"+1 602 249 6202",
    "sg:postcode":"85017",
    "sg:province":"AZ",
    "sg:tags":[
        "jeweler"
    ],
    "wof:name":"Alport Fine Jewelers-Watchmkrs",
    "wof:placetype":"venue"
},
  "geometry": {"coordinates":[-112.11696600000001,33.52528],"type":"Point"}
}