{
  "type": "Feature",
  "properties": {
    "iso:country":"US",
    "sg:address":"558 W Princeton Ave",
    "sg:city":"Gilbert",
    "sg:classifiers":[
        {
            "category":"Professional",
            "subcategory":"Lawyer & Legal Services",
            "type":"Services"
        }
    ],
    "sg:phone":"+1 480 926 5745",
    "sg:postcode":"85233",
    "sg:province":"AZ",
    "sg:tags":[
        "convention",
        "reporters-court"
    ],
    "wof:name":"Sanborn Reporting Inc",
    "wof:placetype":"venue"
},
  "geometry": {"coordinates":[-111.801486,33.364977],"type":"Point"}
}