{
  "type": "Feature",
  "properties": {
    "iso:country":"US",
    "sg:address":"1740 Grand Ave",
    "sg:city":"Phoenix",
    "sg:classifiers":[
        {
            "category":"Manufacturing",
            "subcategory":"Glass & Minerals",
            "type":"Manufacturing & Wholesale Goods"
        }
    ],
    "sg:phone":"+1 602 716 8500",
    "sg:postcode":"85007",
    "sg:province":"AZ",
    "sg:tags":[
        "ready",
        "concrete",
        "mfg"
    ],
    "wof:name":"Auto Mix Motor Co",
    "wof:placetype":"venue"
},
  "geometry": {"coordinates":[-112.097657,33.464029],"type":"Point"}
}