{
  "type": "Feature",
  "properties": {
    "iso:country":"US",
    "sg:address":"777 N Desert Breeze Boulevard E",
    "sg:city":"Chandler",
    "sg:classifiers":[
        {
            "category":"Education",
            "subcategory":"School",
            "type":"Public Place"
        }
    ],
    "sg:phone":"+1 480 783 2200",
    "sg:postcode":"85226",
    "sg:province":"AZ",
    "sg:tags":[
        "high",
        "middle",
        "elementary"
    ],
    "sg:website":"www.kyrene.org",
    "wof:name":"Kyrene Elementary School District",
    "wof:placetype":"venue"
},
  "geometry": {"coordinates":[-111.91964400000001,33.319531],"type":"Point"}
}