{
  "type": "Feature",
  "properties": {
    "iso:country":"US",
    "sg:address":"9605 S 48th St Apt 1019",
    "sg:city":"Phoenix",
    "sg:classifiers":[
        {
            "category":"Manufacturing",
            "subcategory":"Electronics",
            "type":"Manufacturing & Wholesale Goods"
        },
        {
            "category":"Shopping",
            "subcategory":"Computers & Home Electronics",
            "type":"Retail Goods"
        }
    ],
    "sg:phone":"+1 480 747 2444",
    "sg:postcode":"85044",
    "sg:province":"AZ",
    "sg:tags":[
        "audio-visual",
        "stereo",
        "equipment-wholesale",
        "video",
        "equipment-dealers",
        "audio",
        "manufacturer"
    ],
    "wof:name":"Shock.Wav Productions",
    "wof:placetype":"venue"
},
  "geometry": {"coordinates":[-111.976472,33.359563],"type":"Point"}
}