{
  "type": "Feature",
  "properties": {
    "iso:country":"US",
    "sg:address":"7441 E Butherus Dr",
    "sg:city":"Scottsdale",
    "sg:classifiers":[
        {
            "category":"Manufacturing",
            "subcategory":"Chemicals & Compounds",
            "type":"Manufacturing & Wholesale Goods"
        }
    ],
    "sg:phone":"+1 480 951 5847",
    "sg:postcode":"85260",
    "sg:province":"AZ",
    "sg:tags":[
        "preparation",
        "pharmaceutical",
        "mfg"
    ],
    "wof:name":"R X Equipment",
    "wof:placetype":"venue"
},
  "geometry": {"coordinates":[-111.918746,33.622544],"type":"Point"}
}