{
  "type": "Feature",
  "properties": {
    "iso:country":"US",
    "sg:address":"120 N San Francisco St",
    "sg:city":"Flagstaff",
    "sg:classifiers":[
        {
            "category":"Professional",
            "subcategory":"Lawyer & Legal Services",
            "type":"Services"
        }
    ],
    "sg:phone":"+1 928 226 8586",
    "sg:postcode":"86001",
    "sg:province":"AZ",
    "sg:tags":[
        "attorney"
    ],
    "wof:name":"Wendy Morgan",
    "wof:placetype":"venue"
},
  "geometry": {"coordinates":[-111.647188,35.198833],"type":"Point"}
}