{
  "type": "Feature",
  "properties": {
    "addr:full":"183 W Apache Trl Apache Junction AZ 85220",
    "addr:housenumber":"183",
    "addr:postcode":"85220",
    "addr:street":"W Apache Trl",
    "iso:country":"US",
    "sg:address":"183 W Apache Trl",
    "sg:city":"Apache Junction",
    "sg:classifiers":[
        {
            "category":"Restaurant",
            "type":"Food & Drink"
        }
    ],
    "sg:menulink":"http://www.allmenus.com/az/north-pinal/69332-dominos-pizza/menu/",
    "sg:phone":"+1 480 474 0300",
    "sg:postcode":"85220",
    "sg:province":"AZ",
    "sg:tags":[
        "american",
        "wing",
        "pizza"
    ],
    "wof:name":"Domino's Pizza",
    "wof:placetype":"venue"
},
  "geometry": {"coordinates":[-111.549922,33.41255],"type":"Point"}
}