{
  "type": "Feature",
  "properties": {
    "iso:country":"US",
    "sg:address":"12995 N Oracle Rd Ste 171",
    "sg:city":"Tucson",
    "sg:classifiers":[
        {
            "category":"Retail",
            "subcategory":"Laundry & Dry Cleaning",
            "type":"Services"
        }
    ],
    "sg:phone":"+1 520 825 1921",
    "sg:postcode":"85739",
    "sg:province":"AZ",
    "wof:name":"Sun Cleaners",
    "wof:placetype":"venue"
},
  "geometry": {"coordinates":[-110.933998,32.441299],"type":"Point"}
}