{
  "type": "Feature",
  "properties": {
    "iso:country":"US",
    "sg:address":"261 W Liberty Lane",
    "sg:city":"Gilbert",
    "sg:classifiers":[
        {
            "category":"Building & Trades",
            "subcategory":"Cleaning & Sanitation",
            "type":"Services"
        }
    ],
    "sg:phone":"+1 480 812 3747",
    "sg:postcode":"85233",
    "sg:province":"AZ",
    "sg:tags":[
        "home"
    ],
    "wof:name":"Sparkling Services",
    "wof:placetype":"venue"
},
  "geometry": {"coordinates":[-111.795903,33.321389],"type":"Point"}
}