{
  "type": "Feature",
  "properties": {
    "iso:country":"US",
    "sg:address":"2698 E Silk Oak Dr",
    "sg:city":"Tempe",
    "sg:classifiers":[
        {
            "category":"Home & Garden",
            "subcategory":"Furniture",
            "type":"Retail Goods"
        }
    ],
    "sg:phone":"+1 480 890 1015",
    "sg:postcode":"85281",
    "sg:province":"AZ",
    "wof:name":"Classic Style Inc",
    "wof:placetype":"venue"
},
  "geometry": {"coordinates":[-111.880965,33.421323],"type":"Point"}
}