{
  "type": "Feature",
  "properties": {
    "addr:full":"3237 E Clinton Ln Camp Verde AZ 86322",
    "addr:housenumber":"3237",
    "addr:postcode":"az 86322",
    "addr:street":"E Clinton Ln",
    "iso:country":"US",
    "sg:address":"3237 E Clinton Ln",
    "sg:city":"Camp Verde",
    "sg:classifiers":[
        {
            "category":"Professional",
            "type":"Services"
        }
    ],
    "sg:phone":"+1 928 301 2238",
    "sg:postcode":"86322",
    "sg:province":"AZ",
    "wof:name":"Donna M Ullmer",
    "wof:placetype":"venue"
},
  "geometry": {"coordinates":[-111.793502,34.51789],"type":"Point"}
}