{
  "type": "Feature",
  "properties": {
    "addr:full":"1695 Verde Dr Wickenburg AZ 85390",
    "addr:housenumber":"1695",
    "addr:postcode":"85390",
    "addr:street":"Verde Dr",
    "iso:country":"US",
    "sg:address":"1695 Verde Dr",
    "sg:city":"Wickenburg",
    "sg:classifiers":[
        {
            "category":"Freight",
            "type":"Transportation"
        }
    ],
    "sg:phone":"+1 928 684 5190",
    "sg:postcode":"85390",
    "sg:province":"AZ",
    "sg:tags":[
        "operator",
        "local",
        "trucking"
    ],
    "wof:name":"Mulligan Trucking Lynn",
    "wof:placetype":"venue"
},
  "geometry": {"coordinates":[-112.76553199999999,33.960675],"type":"Point"}
}