{
  "type": "Feature",
  "properties": {
    "addr:full":"3816 N 32nd St Phoenix AZ 85018",
    "addr:housenumber":"3816",
    "addr:postcode":"85018",
    "addr:street":"N 32Nd St",
    "iso:country":"US",
    "sg:address":"3816 N 32nd St",
    "sg:city":"Phoenix",
    "sg:classifiers":[
        {
            "category":"Real Estate",
            "subcategory":"Real Estate Operator",
            "type":"Services"
        }
    ],
    "sg:phone":"+1 602 468 1907",
    "sg:postcode":"85018",
    "sg:province":"AZ",
    "sg:tags":[
        "building",
        "apartment"
    ],
    "wof:name":"Granada Villa Apartments",
    "wof:placetype":"venue"
},
  "geometry": {"coordinates":[-112.01304500000001,33.4931],"type":"Point"}
}