{
  "type": "Feature",
  "properties": {
    "addr:full":"7980 N 51st Ave Glendale AZ 85301",
    "addr:housenumber":"7980",
    "addr:postcode":"85301",
    "addr:street":"N 51St Ave",
    "iso:country":"US",
    "sg:address":"7980 N 51st Ave",
    "sg:city":"Glendale",
    "sg:classifiers":[
        {
            "category":"Banks & Credit Unions",
            "subcategory":"Bank",
            "type":"Services"
        }
    ],
    "sg:phone":"+1 623 934 0104",
    "sg:postcode":"85301",
    "sg:province":"AZ",
    "sg:tags":[
        "cashing",
        "check"
    ],
    "sg:website":"www.acecashexpress.com",
    "wof:name":"ACE Cash Express",
    "wof:placetype":"venue"
},
  "geometry": {"coordinates":[-112.16886599999999,33.551166],"type":"Point"}
}