{
  "type": "Feature",
  "properties": {
    "addr:full":"543 W Coronado Rd Phoenix AZ 85003",
    "addr:housenumber":"543",
    "addr:postcode":"85003",
    "addr:street":"W Coronado Rd",
    "iso:country":"US",
    "sg:address":"543 W Coronado Rd",
    "sg:city":"Phoenix",
    "sg:classifiers":[
        {
            "category":"Real Estate",
            "subcategory":"Real Estate Services",
            "type":"Services"
        }
    ],
    "sg:phone":"+1 602 264 0566",
    "sg:postcode":"85003",
    "sg:province":"AZ",
    "sg:tags":[
        "management",
        "condominium"
    ],
    "wof:name":"Willo Palms Condominium Association",
    "wof:placetype":"venue"
},
  "geometry": {"coordinates":[-112.082387,33.467669],"type":"Point"}
}