{
  "type": "Feature",
  "properties": {
    "iso:country":"US",
    "sg:address":"3140 N Arizona Ave",
    "sg:city":"Chandler",
    "sg:classifiers":[
        {
            "category":"Personal",
            "type":"Services"
        }
    ],
    "sg:phone":"+1 480 981 8800",
    "sg:postcode":"85225",
    "sg:province":"AZ",
    "sg:tags":[
        "bankruptcy"
    ],
    "wof:name":"Hickman & Martens",
    "wof:placetype":"venue"
},
  "geometry": {"coordinates":[-111.841852,33.350118],"type":"Point"}
}