{
  "type": "Feature",
  "properties": {
    "iso:country":"US",
    "sg:address":"3501 W McKinley St",
    "sg:city":"Phoenix",
    "sg:classifiers":[
        {
            "category":"Retail",
            "subcategory":"Auto Repair",
            "type":"Services"
        }
    ],
    "sg:phone":"+1 602 442 0711",
    "sg:postcode":"85009",
    "sg:province":"AZ",
    "sg:tags":[
        "repairing",
        "automobile"
    ],
    "wof:name":"Maxflow Auto Specialist",
    "wof:placetype":"venue"
},
  "geometry": {"coordinates":[-112.136666,33.456862],"type":"Point"}
}