{
  "type": "Feature",
  "properties": {
    "iso:country":"US",
    "sg:address":"11965 N 136th Way",
    "sg:city":"Scottsdale",
    "sg:classifiers":[
        {
            "category":"Professional",
            "subcategory":"Business Services",
            "type":"Services"
        }
    ],
    "sg:phone":"+1 480 699 9094",
    "sg:postcode":"85259",
    "sg:province":"AZ",
    "sg:tags":[
        "telemarketing"
    ],
    "wof:name":"Alliant Business Solutions Inc",
    "wof:placetype":"venue"
},
  "geometry": {"coordinates":[-111.786092,33.594167],"type":"Point"}
}