{
  "type": "Feature",
  "properties": {
    "iso:country":"US",
    "sg:address":"1915 Robinson Ave",
    "sg:city":"Kingman",
    "sg:classifiers":[
        {
            "category":"Organizations",
            "subcategory":"Religious Organization",
            "type":"Services"
        }
    ],
    "sg:phone":"+1 928 753 5600",
    "sg:postcode":"86401",
    "sg:province":"AZ",
    "sg:tags":[
        "church"
    ],
    "wof:name":"Church Of Christ",
    "wof:placetype":"venue"
},
  "geometry": {"coordinates":[-114.03164,35.205342],"type":"Point"}
}