{
  "type": "Feature",
  "properties": {
    "addr:full":"2201 E McDowell Rd Phoenix AZ 85006",
    "addr:housenumber":"2201",
    "addr:postcode":"85006",
    "addr:street":"E Mcdowell Rd",
    "iso:country":"US",
    "sg:address":"2201 E McDowell Rd",
    "sg:city":"Phoenix",
    "sg:classifiers":[
        {
            "category":"Wholesale",
            "subcategory":"Meat",
            "type":"Manufacturing & Wholesale Goods"
        }
    ],
    "sg:phone":"+1 602 275 8788",
    "sg:postcode":"85006",
    "sg:province":"AZ",
    "sg:tags":[
        "sausage",
        "mfg"
    ],
    "wof:name":"Stanleys Homemade Sausages",
    "wof:placetype":"venue"
},
  "geometry": {"coordinates":[-112.033602,33.46577],"type":"Point"}
}