{
  "type": "Feature",
  "properties": {
    "iso:country":"US",
    "sg:address":"4444 N 19th Ave",
    "sg:city":"Phoenix",
    "sg:classifiers":[
        {
            "category":"Retail",
            "subcategory":"Auto Repair",
            "type":"Services"
        }
    ],
    "sg:phone":"+1 602 274 2459",
    "sg:postcode":"85015",
    "sg:province":"AZ",
    "wof:name":"Ricks Automotive Service",
    "wof:placetype":"venue"
},
  "geometry": {"coordinates":[-112.09989899999999,33.501697],"type":"Point"}
}