{
  "type": "Feature",
  "properties": {
    "iso:country":"US",
    "sg:address":"323 N Gilbert Rd",
    "sg:city":"Mesa",
    "sg:classifiers":[
        {
            "category":"Retail",
            "subcategory":"Auto Rental",
            "type":"Services"
        }
    ],
    "sg:phone":"+1 800 468 4285",
    "sg:postcode":"85203",
    "sg:province":"AZ",
    "sg:tags":[
        "renting",
        "truck",
        "leasing",
        "trailer"
    ],
    "wof:name":"U-Haul Co.",
    "wof:placetype":"venue"
},
  "geometry": {"coordinates":[-111.788186,33.421589],"type":"Point"}
}