{
  "type": "Feature",
  "properties": {
    "addr:full":"613 W Cherry Ave Flagstaff AZ 86001",
    "addr:housenumber":"613",
    "addr:postcode":"86001",
    "addr:street":"W Cherry Ave",
    "iso:country":"US",
    "sg:address":"613 W Cherry Ave",
    "sg:city":"Flagstaff",
    "sg:classifiers":[
        {
            "category":"Shopping",
            "subcategory":"Books",
            "type":"Retail Goods"
        }
    ],
    "sg:phone":"+1 928 779 2620",
    "sg:postcode":"86001",
    "sg:province":"AZ",
    "wof:name":"Bluff City Books",
    "wof:placetype":"venue"
},
  "geometry": {"coordinates":[-111.655427,35.202619],"type":"Point"}
}