{
  "type": "Feature",
  "properties": {
    "addr:full":"2980 N 73rd St Ste 7 Scottsdale AZ 85251",
    "addr:housenumber":"2980",
    "addr:postcode":"85251",
    "addr:street":"N 73Rd St Ste 7",
    "iso:country":"US",
    "sg:address":"2980 N 73rd St Ste 7",
    "sg:city":"Scottsdale",
    "sg:classifiers":[
        {
            "category":"Personal",
            "subcategory":"Adult",
            "type":"Services"
        }
    ],
    "sg:phone":"+1 480 990 1454",
    "sg:postcode":"85251",
    "sg:province":"AZ",
    "sg:tags":[
        "escort"
    ],
    "wof:name":"Becky's Escort",
    "wof:placetype":"venue"
},
  "geometry": {"coordinates":[-111.924008,33.481829],"type":"Point"}
}