{
  "type": "Feature",
  "properties": {
    "iso:country":"US",
    "sg:address":"8429 N 35th Dr",
    "sg:city":"Phoenix",
    "sg:classifiers":[
        {
            "category":"Building & Trades",
            "subcategory":"Construction",
            "type":"Services"
        }
    ],
    "sg:phone":"+1 602 995 6717",
    "sg:postcode":"85051",
    "sg:province":"AZ",
    "sg:tags":[
        "house"
    ],
    "wof:name":"Home Improvements By Denn",
    "wof:placetype":"venue"
},
  "geometry": {"coordinates":[-112.135174,33.559011],"type":"Point"}
}