{
  "type": "Feature",
  "properties": {
    "iso:country":"US",
    "sg:address":"5043 W Tuckey Ln",
    "sg:city":"Glendale",
    "sg:classifiers":[
        {
            "category":"Building & Trades",
            "subcategory":"Construction",
            "type":"Services"
        }
    ],
    "sg:phone":"+1 623 297 7668",
    "sg:postcode":"85301",
    "sg:province":"AZ",
    "sg:tags":[
        "painter"
    ],
    "wof:name":"Mc Phall Painting Inc",
    "wof:placetype":"venue"
},
  "geometry": {"coordinates":[-112.164318,33.533631],"type":"Point"}
}