{
  "type": "Feature",
  "properties": {
    "iso:country":"US",
    "sg:address":"4839 W Brill St",
    "sg:city":"Phoenix",
    "sg:classifiers":[
        {
            "category":"Building & Trades",
            "subcategory":"Construction",
            "type":"Services"
        }
    ],
    "sg:phone":"+1 602 233 3334",
    "sg:postcode":"85043",
    "sg:province":"AZ",
    "sg:tags":[
        "concrete",
        "subcontractor"
    ],
    "wof:name":"Hardrock Con Placement Co Inc",
    "wof:placetype":"venue"
},
  "geometry": {"coordinates":[-112.163946,33.464567],"type":"Point"}
}