{
  "type": "Feature",
  "properties": {
    "iso:country":"US",
    "sg:address":"756 N Orlando Cir",
    "sg:city":"Mesa",
    "sg:classifiers":[
        {
            "category":"Communications",
            "type":"Services"
        },
        {
            "category":"Wholesale",
            "subcategory":"Electrical",
            "type":"Manufacturing & Wholesale Goods"
        }
    ],
    "sg:phone":"+1 480 985 6550",
    "sg:postcode":"85205",
    "sg:province":"AZ",
    "sg:tags":[
        "communication",
        "radio",
        "system"
    ],
    "wof:name":"Pro TEC Mobile Communications",
    "wof:placetype":"venue"
},
  "geometry": {"coordinates":[-111.737102,33.4296],"type":"Point"}
}