{
  "type": "Feature",
  "properties": {
    "iso:country":"US",
    "sg:address":"878 Valley St",
    "sg:city":"Prescott",
    "sg:classifiers":[
        {
            "category":"Professional",
            "type":"Services"
        }
    ],
    "sg:phone":"+1 928 443 8707",
    "sg:postcode":"86305",
    "sg:province":"AZ",
    "wof:name":"Brenda Baca",
    "wof:placetype":"venue"
},
  "geometry": {"coordinates":[-112.483251,34.554061],"type":"Point"}
}