{
  "type": "Feature",
  "properties": {
    "iso:country":"US",
    "sg:address":"6802 W Polk St",
    "sg:city":"Phoenix",
    "sg:classifiers":[
        {
            "category":"Building & Trades",
            "subcategory":"Construction",
            "type":"Services"
        }
    ],
    "sg:phone":"+1 623 907 5995",
    "sg:postcode":"85043",
    "sg:province":"AZ",
    "sg:tags":[
        "contractor"
    ],
    "wof:name":"Steven E Penoyer",
    "wof:placetype":"venue"
},
  "geometry": {"coordinates":[-112.206153,33.453762],"type":"Point"}
}