{
  "type": "Feature",
  "properties": {
    "iso:country":"US",
    "sg:address":"23331 N 90th Dr",
    "sg:city":"Peoria",
    "sg:classifiers":[
        {
            "category":"Professional",
            "subcategory":"Secretarial Services",
            "type":"Services"
        }
    ],
    "sg:phone":"+1 623 561 8046",
    "sg:postcode":"85383",
    "sg:province":"AZ",
    "sg:tags":[
        "convention",
        "court",
        "reporter"
    ],
    "wof:name":"Brush & Terrell PC",
    "wof:placetype":"venue"
},
  "geometry": {"coordinates":[-112.25328,33.695445],"type":"Point"}
}