{
  "type": "Feature",
  "properties": {
    "addr:full":"310 S 6th St Cottonwood AZ 86326",
    "addr:housenumber":"310",
    "addr:postcode":"86326",
    "addr:street":"S 6Th St",
    "iso:country":"US",
    "sg:address":"310 S 6th St",
    "sg:city":"Cottonwood",
    "sg:classifiers":[
        {
            "category":"Retail",
            "subcategory":"Auto Repair",
            "type":"Services"
        }
    ],
    "sg:phone":"+1 928 634 8796",
    "sg:postcode":"86326",
    "sg:province":"AZ",
    "sg:tags":[
        "muffler",
        "exhaust",
        "system"
    ],
    "wof:name":"Custom Muffler & Driveline",
    "wof:placetype":"venue"
},
  "geometry": {"coordinates":[-112.022831,34.733739],"type":"Point"}
}