{
  "type": "Feature",
  "properties": {
    "iso:country":"US",
    "sg:address":"5541 S Guadalupe Rd",
    "sg:city":"Sierra Vista",
    "sg:classifiers":[
        {
            "category":"Building & Trades",
            "subcategory":"Construction",
            "type":"Services"
        }
    ],
    "sg:phone":"+1 520 378 1957",
    "sg:postcode":"85650",
    "sg:province":"AZ",
    "sg:tags":[
        "hanging",
        "contractor"
    ],
    "wof:name":"Dagnino Brothers Painting Co",
    "wof:placetype":"venue"
},
  "geometry": {"coordinates":[-110.178432,31.468],"type":"Point"}
}