{
  "type": "Feature",
  "properties": {
    "addr:full":"23079 N 90th Way Scottsdale AZ 85255",
    "addr:housenumber":"23079",
    "addr:postcode":"85255",
    "addr:street":"N 90Th Way",
    "iso:country":"US",
    "sg:address":"23079 N 90th Way",
    "sg:city":"Scottsdale",
    "sg:classifiers":[
        {
            "category":"Real Estate",
            "subcategory":"Real Estate Agent",
            "type":"Services"
        }
    ],
    "sg:phone":"+1 480 585 3003",
    "sg:postcode":"85255",
    "sg:province":"AZ",
    "wof:name":"Maynard B Dauward Real Estate",
    "wof:placetype":"venue"
},
  "geometry": {"coordinates":[-111.88624799999999,33.694514],"type":"Point"}
}