{
  "type": "Feature",
  "properties": {
    "iso:country":"US",
    "sg:address":"902 S 20th Ave",
    "sg:city":"Yuma",
    "sg:classifiers":[
        {
            "category":"Building & Trades",
            "subcategory":"Landscaping Services",
            "type":"Services"
        }
    ],
    "sg:phone":"+1 928 782 3808",
    "sg:postcode":"85364",
    "sg:province":"AZ",
    "wof:name":"Garcia Lawn Care",
    "wof:placetype":"venue"
},
  "geometry": {"coordinates":[-114.644387,32.709501],"type":"Point"}
}