{
  "type": "Feature",
  "properties": {
    "iso:country":"US",
    "sg:address":"170 S Ash Ave",
    "sg:city":"Tempe",
    "sg:classifiers":[
        {
            "category":"Health Services",
            "subcategory":"Doctor",
            "type":"Services"
        }
    ],
    "sg:phone":"+1 480 967 4204",
    "sg:postcode":"85281",
    "sg:province":"AZ",
    "sg:tags":[
        "dentist"
    ],
    "wof:name":"David G Lewis DDS",
    "wof:placetype":"venue"
},
  "geometry": {"coordinates":[-111.942589,33.428752],"type":"Point"}
}