{
  "type": "Feature",
  "properties": {
    "iso:country":"US",
    "sg:address":"6127 W Wagoner Rd",
    "sg:city":"Glendale",
    "sg:classifiers":[
        {
            "category":"Building & Trades",
            "subcategory":"Construction",
            "type":"Services"
        }
    ],
    "sg:phone":"+1 602 863 1240",
    "sg:postcode":"85308",
    "sg:province":"AZ",
    "sg:tags":[
        "home",
        "builder"
    ],
    "wof:name":"North Valley Care Homes",
    "wof:placetype":"venue"
},
  "geometry": {"coordinates":[-112.19125099999999,33.651766],"type":"Point"}
}