{
  "type": "Feature",
  "properties": {
    "addr:full":"10893 N Scottsdale Rd Scottsdale AZ 85254",
    "addr:housenumber":"10893",
    "addr:postcode":"85254",
    "addr:street":"N Scottsdale Rd",
    "iso:country":"US",
    "sg:address":"10893 N Scottsdale Rd",
    "sg:city":"Scottsdale",
    "sg:classifiers":[
        {
            "category":"Food & Beverages",
            "subcategory":"Liquor & Beverages",
            "type":"Retail Goods"
        }
    ],
    "sg:phone":"+1 480 861 6362",
    "sg:postcode":"85254",
    "sg:province":"AZ",
    "sg:tags":[
        "bartending"
    ],
    "wof:name":"Saloon Plus",
    "wof:placetype":"venue"
},
  "geometry": {"coordinates":[-111.925926,33.585343],"type":"Point"}
}