{
  "type": "Feature",
  "properties": {
    "iso:country":"US",
    "sg:address":"15249 N 59th Ave",
    "sg:city":"Glendale",
    "sg:classifiers":[
        {
            "category":"Shopping",
            "type":"Retail Goods"
        }
    ],
    "sg:phone":"+1 602 993 5239",
    "sg:postcode":"85306",
    "sg:province":"AZ",
    "sg:tags":[
        "merchandise"
    ],
    "wof:name":"Roushdy & Sons",
    "wof:placetype":"venue"
},
  "geometry": {"coordinates":[-112.185647,33.622926],"type":"Point"}
}