{
  "type": "Feature",
  "properties": {
    "iso:country":"US",
    "sg:address":"2250 E Indigo Bay Dr",
    "sg:city":"Gilbert",
    "sg:classifiers":[
        {
            "category":"Professional",
            "subcategory":"Management & Consulting",
            "type":"Services"
        }
    ],
    "sg:phone":"+1 480 497 1199",
    "sg:postcode":"85234",
    "sg:province":"AZ",
    "sg:tags":[
        "retail",
        "direct",
        "sales"
    ],
    "wof:name":"Alchamy Marketing",
    "wof:placetype":"venue"
},
  "geometry": {"coordinates":[-111.741886,33.372531],"type":"Point"}
}