{
  "type": "Feature",
  "properties": {
    "iso:country":"US",
    "sg:address":"8331 E Via Arboleda",
    "sg:city":"Tucson",
    "sg:classifiers":[
        {
            "category":"Shopping",
            "subcategory":"Clothing, Apparel, & Fashions",
            "type":"Retail Goods"
        }
    ],
    "sg:phone":"+1 520 721 6767",
    "sg:postcode":"85710",
    "sg:province":"AZ",
    "sg:tags":[
        "designer"
    ],
    "wof:name":"Lily's",
    "wof:placetype":"venue"
},
  "geometry": {"coordinates":[-110.815364,32.19917],"type":"Point"}
}