{
  "type": "Feature",
  "properties": {
    "iso:country":"US",
    "sg:address":"3401 W Mcdowell Rd Ste 105",
    "sg:city":"Phoenix",
    "sg:classifiers":[
        {
            "category":"Home & Garden",
            "subcategory":"Household Appliances",
            "type":"Retail Goods"
        },
        {
            "category":"Retail",
            "subcategory":"Repair Shop",
            "type":"Services"
        },
        {
            "category":"Wholesale",
            "subcategory":"Durable Goods & Equipment",
            "type":"Manufacturing & Wholesale Goods"
        }
    ],
    "sg:phone":"+1 602 455 4990",
    "sg:postcode":"85009",
    "sg:province":"AZ",
    "sg:tags":[
        "major",
        "refinishing",
        "appliances-small",
        "small",
        "appliances-major-wholesale",
        "manufacturer"
    ],
    "wof:name":"Sanchez Appliance",
    "wof:placetype":"venue"
},
  "geometry": {"coordinates":[-112.132179,33.465961],"type":"Point"}
}