{
  "type": "Feature",
  "properties": {
    "iso:country":"US",
    "sg:address":"1818 S Ave del Sol",
    "sg:city":"Tucson",
    "sg:classifiers":[
        {
            "category":"Education",
            "subcategory":"School",
            "type":"Public Place"
        }
    ],
    "sg:phone":"+1 520 584 5500",
    "sg:postcode":"85710",
    "sg:province":"AZ",
    "wof:name":"Wheeler Elementary School",
    "wof:placetype":"venue"
},
  "geometry": {"coordinates":[-110.849598,32.199168],"type":"Point"}
}