{
  "type": "Feature",
  "properties": {
    "addr:full":"3519 N Piedra Cir Mesa AZ 85207",
    "addr:housenumber":"3519",
    "addr:postcode":"85207",
    "addr:street":"N Piedra Cir",
    "iso:country":"US",
    "sg:address":"3519 N Piedra Cir",
    "sg:city":"Mesa",
    "sg:classifiers":[
        {
            "category":"Building & Trades",
            "subcategory":"Electrical",
            "type":"Services"
        }
    ],
    "sg:phone":"+1 480 854 2652",
    "sg:postcode":"85207",
    "sg:province":"AZ",
    "sg:tags":[
        "security",
        "safety",
        "specialization"
    ],
    "wof:name":"Electric Utility Safety Cons",
    "wof:placetype":"venue"
},
  "geometry": {"coordinates":[-111.661131,33.479006],"type":"Point"}
}