{
  "type": "Feature",
  "properties": {
    "addr:full":"5404 E Cortland Blvd Flagstaff AZ 86004",
    "addr:housenumber":"5404",
    "addr:postcode":"86004",
    "addr:street":"E Cortland Blvd",
    "iso:country":"US",
    "sg:address":"5404 E Cortland Blvd",
    "sg:city":"Flagstaff",
    "sg:classifiers":[
        {
            "category":"Real Estate",
            "subcategory":"Real Estate Operator",
            "type":"Services"
        }
    ],
    "sg:phone":"+1 928 527 8120",
    "sg:postcode":"86004",
    "sg:province":"AZ",
    "sg:tags":[
        "building",
        "apartment"
    ],
    "wof:name":"Country Club Terrace",
    "wof:placetype":"venue"
},
  "geometry": {"coordinates":[-111.576339,35.214607],"type":"Point"}
}