{
  "type": "Feature",
  "properties": {
    "iso:country":"US",
    "sg:address":"9299 W Olive Ave Ste 212",
    "sg:city":"Peoria",
    "sg:classifiers":[
        {
            "category":"Organizations",
            "subcategory":"Religious Organization",
            "type":"Services"
        }
    ],
    "sg:phone":"+1 623 236 8064",
    "sg:postcode":"85345",
    "sg:province":"AZ",
    "wof:name":"Grupo Amistad Phoenix",
    "wof:placetype":"venue"
},
  "geometry": {"coordinates":[-112.259365,33.566154],"type":"Point"}
}