{
  "type": "Feature",
  "properties": {
    "iso:country":"US",
    "sg:address":"401 S Alvernon Way",
    "sg:city":"Tucson",
    "sg:classifiers":[
        {
            "category":"Food & Beverages",
            "subcategory":"Groceries & Convenience Stores",
            "type":"Retail Goods"
        }
    ],
    "sg:phone":"+1 520 326 5992",
    "sg:postcode":"85711",
    "sg:province":"AZ",
    "sg:tags":[
        "station",
        "gasoline"
    ],
    "wof:name":"Circle K",
    "wof:placetype":"venue"
},
  "geometry": {"coordinates":[-110.9096,32.21505],"type":"Point"}
}