{
  "type": "Feature",
  "properties": {
    "addr:full":"5830 W Thunderbird Rd Glendale AZ 85306",
    "addr:housenumber":"5830",
    "addr:postcode":"85306",
    "addr:street":"W Thunderbird Rd",
    "iso:country":"US",
    "sg:address":"5830 W Thunderbird Rd",
    "sg:city":"Glendale",
    "sg:classifiers":[
        {
            "category":"Professional",
            "subcategory":"Secretarial Services",
            "type":"Services"
        }
    ],
    "sg:phone":"+1 602 620 1978",
    "sg:postcode":"85306",
    "sg:province":"AZ",
    "sg:tags":[
        "resume"
    ],
    "wof:name":"ABC Resume Svc",
    "wof:placetype":"venue"
},
  "geometry": {"coordinates":[-112.18450900000001,33.610832],"type":"Point"}
}