{
  "type": "Feature",
  "properties": {
    "addr:full":"336 E Dunlap Ave Phoenix AZ 85020",
    "addr:housenumber":"336",
    "addr:postcode":"85020",
    "addr:street":"E Dunlap Ave",
    "iso:country":"US",
    "sg:address":"336 E Dunlap Ave",
    "sg:city":"Phoenix",
    "sg:classifiers":[
        {
            "category":"Organizations",
            "subcategory":"Religious Organization",
            "type":"Services"
        }
    ],
    "sg:phone":"+1 602 944 5858",
    "sg:postcode":"85020",
    "sg:province":"AZ",
    "sg:tags":[
        "membership",
        "used"
    ],
    "wof:name":"Salvation Army The",
    "wof:placetype":"venue"
},
  "geometry": {"coordinates":[-112.06805,33.567837],"type":"Point"}
}