{
  "type": "Feature",
  "properties": {
    "iso:country":"US",
    "sg:address":"1651 Discovery Park Blvd",
    "sg:city":"Safford",
    "sg:classifiers":[
        {
            "category":"Professional",
            "subcategory":"Research",
            "type":"Services"
        }
    ],
    "sg:phone":"+1 928 428 6260",
    "sg:postcode":"85546",
    "sg:province":"AZ",
    "sg:tags":[
        "observatory"
    ],
    "wof:name":"Discovery Park",
    "wof:placetype":"venue"
},
  "geometry": {"coordinates":[-109.72815300000001,32.80227],"type":"Point"}
}