{
  "type": "Feature",
  "properties": {
    "addr:full":"1009 W 12th St Parker AZ 85344",
    "addr:housenumber":"1009",
    "addr:postcode":"az 85344",
    "addr:street":"W 12Th St",
    "iso:country":"US",
    "sg:address":"1009 W 12th St",
    "sg:city":"Parker",
    "sg:classifiers":[
        {
            "category":"Professional",
            "type":"Services"
        },
        {
            "category":"Professional",
            "subcategory":"Lawyer & Legal Services",
            "type":"Services"
        }
    ],
    "sg:phone":"+1 928 669 5892",
    "sg:postcode":"85344",
    "sg:province":"AZ",
    "sg:tags":[
        "attorney"
    ],
    "wof:name":"Fred H Welch Pllc",
    "wof:placetype":"venue"
},
  "geometry": {"coordinates":[-114.289204,34.147796],"type":"Point"}
}