{
  "type": "Feature",
  "properties": {
    "iso:country":"US",
    "sg:address":"8334 E Jenan Dr",
    "sg:city":"Scottsdale",
    "sg:classifiers":[
        {
            "category":"Insurance",
            "subcategory":"Insurance Agent",
            "type":"Services"
        }
    ],
    "sg:phone":"+1 480 998 3006",
    "sg:postcode":"85260",
    "sg:province":"AZ",
    "wof:name":"Izard Insurance",
    "wof:placetype":"venue"
},
  "geometry": {"coordinates":[-111.903934,33.593955],"type":"Point"}
}