{
  "type": "Feature",
  "properties": {
    "iso:country":"US",
    "sg:address":"1918 E Colter St",
    "sg:city":"Phoenix",
    "sg:classifiers":[
        {
            "category":"Community Center",
            "type":"Public Place"
        }
    ],
    "sg:phone":"+1 602 262 6696",
    "sg:postcode":"85016",
    "sg:province":"AZ",
    "sg:tags":[
        "recreation"
    ],
    "sg:website":"http://www.realestatedivision.com",
    "wof:name":"Parks And Recreation Dept",
    "wof:placetype":"venue"
},
  "geometry": {"coordinates":[-112.040986,33.512888],"type":"Point"}
}