{
  "type": "Feature",
  "properties": {
    "iso:country":"US",
    "sg:address":"16842 N 7th St",
    "sg:city":"Phoenix",
    "sg:classifiers":[
        {
            "category":"Bagels",
            "type":"Food & Drink"
        }
    ],
    "sg:menulink":"http://www.allmenus.com/az/phoenix/149455-einstein-bros/menu/",
    "sg:phone":"+1 602 866 8010",
    "sg:postcode":"85022",
    "sg:province":"AZ",
    "sg:tags":[
        "wrap",
        "soup",
        "american",
        "sandwich",
        "salad"
    ],
    "wof:name":"Einstein Bros",
    "wof:placetype":"venue"
},
  "geometry": {"coordinates":[-112.065589,33.639321],"type":"Point"}
}