{
  "type": "Feature",
  "properties": {
    "iso:country":"US",
    "sg:address":"700 S Blackbird Roost St",
    "sg:city":"Flagstaff",
    "sg:classifiers":[
        {
            "category":"Real Estate",
            "subcategory":"Real Estate Operator",
            "type":"Services"
        }
    ],
    "sg:phone":"+1 928 774 8634",
    "sg:postcode":"86001",
    "sg:province":"AZ",
    "sg:tags":[
        "apartment"
    ],
    "wof:name":"University Roost Apartment",
    "wof:placetype":"venue"
},
  "geometry": {"coordinates":[-111.660526,35.19383],"type":"Point"}
}