{
  "type": "Feature",
  "properties": {
    "addr:full":"3240 E Camelback Rd Ste 100 Phoenix AZ 85018",
    "addr:housenumber":"3240",
    "addr:postcode":"85018",
    "addr:street":"E Camelback Rd Ste 100",
    "iso:country":"US",
    "sg:address":"3240 E Camelback Rd Ste 100",
    "sg:city":"Phoenix",
    "sg:classifiers":[
        {
            "category":"Shopping",
            "subcategory":"Clothing, Apparel, & Fashions",
            "type":"Retail Goods"
        }
    ],
    "sg:phone":"+1 602 952 1444",
    "sg:postcode":"85018",
    "sg:province":"AZ",
    "sg:tags":[
        "rental",
        "men's",
        "sale",
        "wear",
        "clothing",
        "boys'",
        "formal"
    ],
    "sg:website":"http://www.rochesterclothing.com/",
    "wof:name":"Rochester Big & Tall Clothing",
    "wof:placetype":"venue"
},
  "geometry": {"coordinates":[-112.011421,33.510052],"type":"Point"}
}