{
  "type": "Feature",
  "properties": {
    "iso:country":"US",
    "sg:address":"16405 N Scottsdale Rd",
    "sg:city":"Scottsdale",
    "sg:classifiers":[
        {
            "category":"Restaurant",
            "type":"Food & Drink"
        }
    ],
    "sg:menulink":"http://www.allmenus.com/az/phoenix/229237-maggianos-little-italy/menu/",
    "sg:phone":"+1 480 333 4100",
    "sg:postcode":"85254",
    "sg:province":"AZ",
    "sg:tags":[
        "italian"
    ],
    "wof:name":"Maggiano's Little Italy",
    "wof:placetype":"venue"
},
  "geometry": {"coordinates":[-111.925313,33.635719],"type":"Point"}
}