{
  "type": "Feature",
  "properties": {
    "iso:country":"US",
    "sg:address":"4650 W Aire Libre Ave",
    "sg:city":"Glendale",
    "sg:classifiers":[
        {
            "category":"Wholesale",
            "subcategory":"Electrical",
            "type":"Manufacturing & Wholesale Goods"
        }
    ],
    "sg:phone":"+1 602 739 0372",
    "sg:postcode":"85306",
    "sg:province":"AZ",
    "sg:tags":[
        "searchlight"
    ],
    "wof:name":"Attraction Lights Of Phoenix",
    "wof:placetype":"venue"
},
  "geometry": {"coordinates":[-112.158626,33.636548],"type":"Point"}
}