{
  "type": "Feature",
  "properties": {
    "iso:country":"US",
    "sg:address":"4765 E Speedway Blvd",
    "sg:city":"Tucson",
    "sg:classifiers":[
        {
            "category":"Home & Garden",
            "subcategory":"Carpets & Floor Coverings",
            "type":"Retail Goods"
        }
    ],
    "sg:phone":"+1 520 323 0229",
    "sg:postcode":"85712",
    "sg:province":"AZ",
    "sg:tags":[
        "dealer",
        "rug"
    ],
    "wof:name":"AAA1 Flooring",
    "wof:placetype":"venue"
},
  "geometry": {"coordinates":[-110.89171,32.236281],"type":"Point"}
}