{
  "type": "Feature",
  "properties": {
    "iso:country":"US",
    "sg:address":"5221 W Montebello Ave # 13",
    "sg:city":"Glendale",
    "sg:classifiers":[
        {
            "category":"Wholesale",
            "subcategory":"Auto Parts",
            "type":"Manufacturing & Wholesale Goods"
        }
    ],
    "sg:phone":"+1 623 931 7702",
    "sg:postcode":"85301",
    "sg:province":"AZ",
    "sg:tags":[
        "automobile",
        "rebuilt-wholesale",
        "supplies-used",
        "manufacturer"
    ],
    "wof:name":"Manufacturers Acces Outlet",
    "wof:placetype":"venue"
},
  "geometry": {"coordinates":[-112.171101,33.520322],"type":"Point"}
}