{
  "type": "Feature",
  "properties": {
    "addr:full":"10210 W McDowell Road Avondale AZ 85323",
    "addr:housenumber":"10210",
    "addr:postcode":"85323",
    "addr:street":"W Mcdowell Road",
    "iso:country":"US",
    "sg:address":"10210 W McDowell Road",
    "sg:city":"Avondale",
    "sg:classifiers":[
        {
            "category":"Health Services",
            "subcategory":"Dentist",
            "type":"Services"
        }
    ],
    "sg:phone":"+1 623 478 5435",
    "sg:postcode":"85323",
    "sg:province":"AZ",
    "wof:name":"Nieh Shunyu DDS",
    "wof:placetype":"venue"
},
  "geometry": {"coordinates":[-112.28138199999999,33.464649],"type":"Point"}
}