{
  "type": "Feature",
  "properties": {
    "iso:country":"US",
    "sg:address":"9021 N 59th Ave",
    "sg:city":"Glendale",
    "sg:classifiers":[
        {
            "category":"Fast Food",
            "type":"Food & Drink"
        },
        {
            "category":"Restaurant",
            "type":"Food & Drink"
        }
    ],
    "sg:phone":"+1 623 937 0491",
    "sg:postcode":"85302",
    "sg:province":"AZ",
    "sg:tags":[
        "american",
        "hot",
        "hamburger",
        "dog"
    ],
    "sg:website":"http://www.jackinthebox.com",
    "wof:name":"Jack in the Box",
    "wof:placetype":"venue"
},
  "geometry": {"coordinates":[-112.186284,33.567764],"type":"Point"}
}