{
  "type": "Feature",
  "properties": {
    "iso:country":"US",
    "sg:address":"21620 N 46th Pl",
    "sg:city":"Phoenix",
    "sg:classifiers":[
        {
            "category":"Building & Trades",
            "subcategory":"Landscaping Services",
            "type":"Services"
        }
    ],
    "sg:phone":"+1 480 473 1838",
    "sg:postcode":"85050",
    "sg:province":"AZ",
    "wof:name":"Vision Landscape Management LL",
    "wof:placetype":"venue"
},
  "geometry": {"coordinates":[-111.979002,33.682464],"type":"Point"}
}