{
  "type": "Feature",
  "properties": {
    "iso:country":"US",
    "sg:address":"7972 W Thunderbird Rd",
    "sg:city":"Peoria",
    "sg:classifiers":[
        {
            "category":"Professional",
            "subcategory":"Lawyer & Legal Services",
            "type":"Services"
        }
    ],
    "sg:phone":"+1 623 979 7260",
    "sg:postcode":"85381",
    "sg:province":"AZ",
    "sg:tags":[
        "attorney"
    ],
    "wof:name":"Kevin Garrison Law Offices",
    "wof:placetype":"venue"
},
  "geometry": {"coordinates":[-112.229681,33.610212],"type":"Point"}
}