{
  "type": "Feature",
  "properties": {
    "iso:country":"US",
    "sg:address":"4850 W Jefferson St",
    "sg:city":"Phoenix",
    "sg:classifiers":[
        {
            "category":"Manufacturing",
            "subcategory":"Paper Products",
            "type":"Manufacturing & Wholesale Goods"
        }
    ],
    "sg:phone":"+1 602 269 9640",
    "sg:postcode":"85043",
    "sg:province":"AZ",
    "sg:tags":[
        "converter"
    ],
    "sg:website":"www.grnleaf.com",
    "wof:name":"Greenleaf",
    "wof:placetype":"venue"
},
  "geometry": {"coordinates":[-112.165612,33.446678],"type":"Point"}
}