{
  "type": "Feature",
  "properties": {
    "addr:full":"9633 N 17th Ave Apt 20 Phoenix AZ 85021",
    "addr:housenumber":"9633;20",
    "addr:postcode":"85021",
    "addr:street":"N 17Th Ave Apt",
    "iso:country":"US",
    "sg:address":"9633 N 17th Ave Apt 20",
    "sg:city":"Phoenix",
    "sg:classifiers":[
        {
            "category":"Professional",
            "subcategory":"Business Services",
            "type":"Services"
        }
    ],
    "sg:phone":"+1 623 262 6545",
    "sg:postcode":"85021",
    "sg:province":"AZ",
    "sg:tags":[
        "repossessing"
    ],
    "wof:name":"Magnum Repossesion",
    "wof:placetype":"venue"
},
  "geometry": {"coordinates":[-112.095558,33.574047],"type":"Point"}
}