{
  "type": "Feature",
  "properties": {
    "addr:full":"4620 E 9th St Tucson AZ 85711",
    "addr:housenumber":"4620",
    "addr:postcode":"85711",
    "addr:street":"E 9Th St",
    "iso:country":"US",
    "sg:address":"4620 E 9th St",
    "sg:city":"Tucson",
    "sg:classifiers":[
        {
            "category":"Health Services",
            "subcategory":"Nursing And Care Facility",
            "type":"Services"
        }
    ],
    "sg:phone":"+1 520 795 7709",
    "sg:postcode":"85711",
    "sg:province":"AZ",
    "sg:tags":[
        "home",
        "retirement",
        "community"
    ],
    "wof:name":"Lopez Home Care",
    "wof:placetype":"venue"
},
  "geometry": {"coordinates":[-110.893463,32.223952],"type":"Point"}
}