{
  "type": "Feature",
  "properties": {
    "iso:country":"US",
    "sg:address":"1716 E Todd Dr",
    "sg:city":"Tempe",
    "sg:classifiers":[
        {
            "category":"Utilities",
            "subcategory":"Telephone",
            "type":"Services"
        }
    ],
    "sg:phone":"+1 480 756 0052",
    "sg:postcode":"85283",
    "sg:province":"AZ",
    "sg:tags":[
        "systems-wholesale",
        "manufacturer",
        "system",
        "equipment"
    ],
    "wof:name":"Words Worth",
    "wof:placetype":"venue"
},
  "geometry": {"coordinates":[-111.913193,33.352795],"type":"Point"}
}