{
  "type": "Feature",
  "properties": {
    "addr:full":"4516 W Boston St Chandler AZ 85226",
    "addr:housenumber":"4516",
    "addr:postcode":"85226",
    "addr:street":"W Boston St",
    "iso:country":"US",
    "sg:address":"4516 W Boston St",
    "sg:city":"Chandler",
    "sg:classifiers":[
        {
            "category":"Freight",
            "type":"Transportation"
        }
    ],
    "sg:phone":"+1 480 456 9553",
    "sg:postcode":"85226",
    "sg:province":"AZ",
    "sg:tags":[
        "operator",
        "local",
        "trucking"
    ],
    "wof:name":"Simple Movers",
    "wof:placetype":"venue"
},
  "geometry": {"coordinates":[-111.92012099999999,33.30188],"type":"Point"}
}