{
  "type": "Feature",
  "properties": {
    "iso:country":"US",
    "sg:address":"1946 E Lee St",
    "sg:city":"Tucson",
    "sg:classifiers":[
        {
            "category":"Organizations",
            "subcategory":"Religious Organization",
            "type":"Services"
        }
    ],
    "sg:phone":"+1 520 327 6015",
    "sg:postcode":"85719",
    "sg:province":"AZ",
    "sg:tags":[
        "church"
    ],
    "wof:name":"S S Peter & Paul Church",
    "wof:placetype":"venue"
},
  "geometry": {"coordinates":[-110.943165,32.241596],"type":"Point"}
}