{
  "type": "Feature",
  "properties": {
    "iso:country":"US",
    "sg:address":"3707 N Oracle Rd",
    "sg:city":"Tucson",
    "sg:classifiers":[
        {
            "category":"Restaurant",
            "type":"Food & Drink"
        }
    ],
    "sg:menulink":"http://www.allmenus.com/az/tucson/161021-carls-jr/menu/",
    "sg:phone":"+1 520 888 4032",
    "sg:postcode":"85705",
    "sg:province":"AZ",
    "sg:tags":[
        "burger",
        "american"
    ],
    "wof:name":"Carl's Jr.",
    "wof:placetype":"venue"
},
  "geometry": {"coordinates":[-110.978562,32.273974],"type":"Point"}
}