{
  "type": "Feature",
  "properties": {
    "iso:country":"US",
    "sg:address":"731 W Commerce Ave",
    "sg:city":"Gilbert",
    "sg:classifiers":[
        {
            "category":"Manufacturing",
            "subcategory":"Metals",
            "type":"Manufacturing & Wholesale Goods"
        }
    ],
    "sg:phone":"+1 480 926 1125",
    "sg:postcode":"85233",
    "sg:province":"AZ",
    "sg:tags":[
        "vent",
        "curb",
        "gravity",
        "roof"
    ],
    "wof:name":"Western Vents & Curbs",
    "wof:placetype":"venue"
},
  "geometry": {"coordinates":[-111.805486,33.358118],"type":"Point"}
}