{
  "type": "Feature",
  "properties": {
    "iso:country":"US",
    "sg:address":"3011 N Grand Ave",
    "sg:city":"Nogales",
    "sg:classifiers":[
        {
            "category":"Freight",
            "type":"Transportation"
        }
    ],
    "sg:phone":"+1 520 761 9885",
    "sg:postcode":"85621",
    "sg:province":"AZ",
    "wof:name":"L & M Transportation Svc",
    "wof:placetype":"venue"
},
  "geometry": {"coordinates":[-110.950855,31.387801],"type":"Point"}
}