{
  "type": "Feature",
  "properties": {
    "iso:country":"US",
    "sg:address":"12 W Main St",
    "sg:city":"Mesa",
    "sg:classifiers":[
        {
            "category":"Organizations",
            "subcategory":"Professional Association",
            "type":"Services"
        }
    ],
    "sg:phone":"+1 480 844 3793",
    "sg:postcode":"85201",
    "sg:province":"AZ",
    "sg:tags":[
        "business",
        "trade"
    ],
    "wof:name":"Twelve West Main",
    "wof:placetype":"venue"
},
  "geometry": {"coordinates":[-111.831844,33.415138],"type":"Point"}
}