{
  "type": "Feature",
  "properties": {
    "addr:full":"4048 E Hancock Dr Phoenix AZ 85028",
    "addr:housenumber":"4048",
    "addr:postcode":"85028",
    "addr:street":"E Hancock Dr",
    "iso:country":"US",
    "sg:address":"4048 E Hancock Dr",
    "sg:city":"Phoenix",
    "sg:classifiers":[
        {
            "category":"Manufacturing",
            "subcategory":"Metals",
            "type":"Manufacturing & Wholesale Goods"
        }
    ],
    "sg:phone":"+1 602 494 7429",
    "sg:postcode":"85028",
    "sg:province":"AZ",
    "sg:tags":[
        "steel",
        "erectors"
    ],
    "wof:name":"American Pool Steelers Inc",
    "wof:placetype":"venue"
},
  "geometry": {"coordinates":[-111.995446,33.583317],"type":"Point"}
}