{
  "type": "Feature",
  "properties": {
    "iso:country":"US",
    "sg:address":"820 S Farmer Ave",
    "sg:city":"Tempe",
    "sg:classifiers":[
        {
            "category":"Professional",
            "type":"Services"
        }
    ],
    "sg:phone":"+1 480 967 3529",
    "sg:postcode":"85281",
    "sg:province":"AZ",
    "wof:name":"P A Alexander",
    "wof:placetype":"venue"
},
  "geometry": {"coordinates":[-111.944316,33.4209],"type":"Point"}
}