{
  "type": "Feature",
  "properties": {
    "iso:country":"US",
    "sg:address":"4312 W Larkspur Dr",
    "sg:city":"Glendale",
    "sg:classifiers":[
        {
            "category":"Building & Trades",
            "subcategory":"Plumbing",
            "type":"Services"
        }
    ],
    "sg:phone":"+1 602 547 2014",
    "sg:postcode":"85304",
    "sg:province":"AZ",
    "sg:tags":[
        "contractor"
    ],
    "wof:name":"Voss Pool Plumbing Inc",
    "wof:placetype":"venue"
},
  "geometry": {"coordinates":[-112.15172099999999,33.600017],"type":"Point"}
}