{
  "type": "Feature",
  "properties": {
    "addr:full":"1221 S 2nd Ave Tucson AZ 85713",
    "addr:housenumber":"1221",
    "addr:postcode":"85713",
    "addr:street":"S 2Nd Ave",
    "iso:country":"US",
    "sg:address":"1221 S 2nd Ave",
    "sg:city":"Tucson",
    "sg:classifiers":[
        {
            "category":"Government",
            "subcategory":"Office",
            "type":"Public Place"
        }
    ],
    "sg:phone":"+1 520 620 5412",
    "sg:postcode":"85713",
    "sg:province":"AZ",
    "sg:tags":[
        "transportation"
    ],
    "wof:name":"Tucson District",
    "wof:placetype":"venue"
},
  "geometry": {"coordinates":[-110.962262,32.206006],"type":"Point"}
}