{
  "type": "Feature",
  "properties": {
    "addr:full":"600 E Gurley St Prescott AZ 86301",
    "addr:housenumber":"600",
    "addr:postcode":"86301",
    "addr:street":"E Gurley St",
    "iso:country":"US",
    "sg:address":"600 E Gurley St",
    "sg:city":"Prescott",
    "sg:classifiers":[
        {
            "category":"Real Estate",
            "subcategory":"Real Estate Agent",
            "type":"Services"
        }
    ],
    "sg:phone":"+1 928 771 1111",
    "sg:postcode":"86301",
    "sg:province":"AZ",
    "wof:name":"Russ Lyon Realty Co",
    "wof:placetype":"venue"
},
  "geometry": {"coordinates":[-112.461821,34.541834],"type":"Point"}
}