{
  "type": "Feature",
  "properties": {
    "iso:country":"US",
    "sg:address":"24903 S 194th St",
    "sg:city":"Queen Creek",
    "sg:classifiers":[
        {
            "category":"Wholesale",
            "subcategory":"Auto Parts",
            "type":"Manufacturing & Wholesale Goods"
        }
    ],
    "sg:phone":"+1 480 924 1640",
    "sg:postcode":"85242",
    "sg:province":"AZ",
    "sg:tags":[
        "automotive",
        "specialty",
        "supply"
    ],
    "wof:name":"Desert View Enterprises Inc",
    "wof:placetype":"venue"
},
  "geometry": {"coordinates":[-111.664574,33.219505],"type":"Point"}
}