{
  "type": "Feature",
  "properties": {
    "addr:full":"1614 Mohican Dr Lake Havasu City AZ 86406",
    "addr:housenumber":"1614",
    "addr:postcode":"86406",
    "addr:street":"Mohican Dr",
    "iso:country":"US",
    "sg:address":"1614 Mohican Dr",
    "sg:city":"Lake Havasu City",
    "sg:classifiers":[
        {
            "category":"Real Estate",
            "subcategory":"Real Estate Agent",
            "type":"Services"
        }
    ],
    "sg:phone":"+1 928 453 4535",
    "sg:postcode":"86406",
    "sg:province":"AZ",
    "wof:name":"Roy Wheeler",
    "wof:placetype":"venue"
},
  "geometry": {"coordinates":[-114.256225,34.461904],"type":"Point"}
}