{
  "type": "Feature",
  "properties": {
    "iso:country":"US",
    "sg:address":"3400 S Mill Avenue Suite 338",
    "sg:city":"Tempe",
    "sg:classifiers":[
        {
            "category":"Sports & Exercise",
            "subcategory":"Gym",
            "type":"Entertainment"
        }
    ],
    "sg:phone":"+1 480 921 2990",
    "sg:postcode":"85282",
    "sg:province":"AZ",
    "wof:name":"Grecian Bodies",
    "wof:placetype":"venue"
},
  "geometry": {"coordinates":[-111.939578,33.391988],"type":"Point"}
}