{
  "type": "Feature",
  "properties": {
    "addr:full":"PO Box 5151 Carefree AZ 85377",
    "addr:housenumber":"po",
    "addr:postcode":"az 85377",
    "addr:street":"Box 5151",
    "iso:country":"US",
    "sg:address":"PO Box 5151",
    "sg:city":"Carefree",
    "sg:classifiers":[
        {
            "category":"Real Estate",
            "subcategory":"Real Estate Services",
            "type":"Services"
        }
    ],
    "sg:phone":"+1 480 488 9988",
    "sg:postcode":"85377",
    "sg:province":"AZ",
    "wof:name":"Town & Mountain Real Estate",
    "wof:placetype":"venue"
},
  "geometry": {"coordinates":[-111.952003,33.833099],"type":"Point"}
}