{
  "type": "Feature",
  "properties": {
    "iso:country":"US",
    "sg:address":"3641 Hwy 95",
    "sg:city":"Bullhead City",
    "sg:classifiers":[
        {
            "category":"Building & Trades",
            "subcategory":"Construction",
            "type":"Services"
        }
    ],
    "sg:phone":"+1 928 763 6909",
    "sg:postcode":"86442",
    "sg:province":"AZ",
    "sg:tags":[
        "general",
        "contractor"
    ],
    "wof:name":"Palmer Investments A Dev Co",
    "wof:placetype":"venue"
},
  "geometry": {"coordinates":[-114.589116,35.052043],"type":"Point"}
}