{
  "type": "Feature",
  "properties": {
    "addr:full":"3450 W Bell Rd Phoenix AZ 85053",
    "addr:housenumber":"3450",
    "addr:postcode":"85053",
    "addr:street":"W Bell Rd",
    "iso:country":"US",
    "sg:address":"3450 W Bell Rd",
    "sg:city":"Phoenix",
    "sg:classifiers":[
        {
            "category":"Professional",
            "subcategory":"Accounting & Tax Preparation",
            "type":"Services"
        }
    ],
    "sg:phone":"+1 602 256 0700",
    "sg:postcode":"85053",
    "sg:province":"AZ",
    "sg:tags":[
        "return",
        "filing"
    ],
    "wof:name":"H & R Block Tax Svc",
    "wof:placetype":"venue"
},
  "geometry": {"coordinates":[-112.13117,33.639728],"type":"Point"}
}