{
  "type": "Feature",
  "properties": {
    "iso:country":"US",
    "sg:address":"5424 S 40th St",
    "sg:city":"Phoenix",
    "sg:classifiers":[
        {
            "category":"Professional",
            "subcategory":"Management & Consulting",
            "type":"Services"
        }
    ],
    "sg:phone":"+1 602 414 9807",
    "sg:postcode":"85040",
    "sg:province":"AZ",
    "sg:tags":[
        "consultant",
        "business"
    ],
    "wof:name":"Grupo N Advertising",
    "wof:placetype":"venue"
},
  "geometry": {"coordinates":[-111.995544,33.399359],"type":"Point"}
}