{
  "type": "Feature",
  "properties": {
    "iso:country":"US",
    "sg:address":"1201 N Pinal Ave",
    "sg:city":"Casa Grande",
    "sg:classifiers":[
        {
            "category":"Recreation",
            "type":"Entertainment"
        }
    ],
    "sg:phone":"+1 520 836 4723",
    "sg:postcode":"85222",
    "sg:province":"AZ",
    "sg:tags":[
        "shoes"
    ],
    "wof:name":"OOdham Tash Office",
    "wof:placetype":"venue"
},
  "geometry": {"coordinates":[-111.757289,32.88489],"type":"Point"}
}