{
  "type": "Feature",
  "properties": {
    "addr:full":"22700 S 194th Pl Queen Creek AZ 85242",
    "addr:housenumber":"22700",
    "addr:postcode":"85242",
    "addr:street":"S 194Th Pl",
    "iso:country":"US",
    "sg:address":"22700 S 194th Pl",
    "sg:city":"Queen Creek",
    "sg:classifiers":[
        {
            "category":"Banks & Credit Unions",
            "subcategory":"Investment Brokerage",
            "type":"Services"
        }
    ],
    "sg:phone":"+1 480 987 9811",
    "sg:postcode":"85242",
    "sg:province":"AZ",
    "sg:tags":[
        "consultant",
        "planning",
        "financial"
    ],
    "wof:name":"Murset Financial Group PLC",
    "wof:placetype":"venue"
},
  "geometry": {"coordinates":[-111.664648,33.242279],"type":"Point"}
}