{
  "type": "Feature",
  "properties": {
    "addr:full":"5400 E Railhead Ave Flagstaff AZ 86004",
    "addr:housenumber":"5400",
    "addr:postcode":"86004",
    "addr:street":"E Railhead Ave",
    "iso:country":"US",
    "sg:address":"5400 E Railhead Ave",
    "sg:city":"Flagstaff",
    "sg:classifiers":[
        {
            "category":"Education",
            "subcategory":"School",
            "type":"Public Place"
        }
    ],
    "sg:phone":"+1 928 526 3712",
    "sg:postcode":"86004",
    "sg:province":"AZ",
    "wof:name":"Flagstaff Public Schools",
    "wof:placetype":"venue"
},
  "geometry": {"coordinates":[-111.57524600000001,35.225247],"type":"Point"}
}