{
  "type": "Feature",
  "properties": {
    "iso:country":"US",
    "sg:address":"7835 E Evans Rd",
    "sg:city":"Scottsdale",
    "sg:classifiers":[
        {
            "category":"Professional",
            "type":"Services"
        }
    ],
    "sg:phone":"+1 480 905 7219",
    "sg:postcode":"85260",
    "sg:province":"AZ",
    "sg:tags":[
        "establishment"
    ],
    "wof:name":"Slepicoff Hy",
    "wof:placetype":"venue"
},
  "geometry": {"coordinates":[-111.911891,33.616412],"type":"Point"}
}