{
  "type": "Feature",
  "properties": {
    "addr:full":"260 S Alma School Road Chandler AZ 85224",
    "addr:housenumber":"260",
    "addr:postcode":"85224",
    "addr:street":"S Alma School Road",
    "iso:country":"US",
    "sg:address":"260 S Alma School Road",
    "sg:city":"Chandler",
    "sg:classifiers":[
        {
            "category":"Autos & Motor Vehicles",
            "subcategory":"Auto Supplies",
            "type":"Retail Goods"
        }
    ],
    "sg:phone":"+1 602 679 4284",
    "sg:postcode":"85224",
    "sg:province":"AZ",
    "sg:tags":[
        "glass"
    ],
    "wof:name":"Apex Auto Glass",
    "wof:placetype":"venue"
},
  "geometry": {"coordinates":[-111.859116,33.299504],"type":"Point"}
}