{
  "type": "Feature",
  "properties": {
    "addr:full":"12211 W Bell Rd Surprise AZ 85374",
    "addr:housenumber":"12211",
    "addr:postcode":"85374",
    "addr:street":"W Bell Rd",
    "iso:country":"US",
    "sg:address":"12211 W Bell Rd",
    "sg:city":"Surprise",
    "sg:classifiers":[
        {
            "category":"Professional",
            "subcategory":"Accounting & Tax Preparation",
            "type":"Services"
        }
    ],
    "sg:phone":"+1 623 875 8119",
    "sg:postcode":"85374",
    "sg:province":"AZ",
    "sg:tags":[
        "accountant"
    ],
    "wof:name":"Patricia A Painter CPA",
    "wof:placetype":"venue"
},
  "geometry": {"coordinates":[-112.32229,33.638679],"type":"Point"}
}