{
  "type": "Feature",
  "properties": {
    "iso:country":"US",
    "sg:address":"13212 N Saguaro Blvd",
    "sg:city":"Fountain Hills",
    "sg:classifiers":[
        {
            "category":"Restaurant",
            "type":"Food & Drink"
        }
    ],
    "sg:phone":"+1 480 837 1661",
    "sg:postcode":"85268",
    "sg:province":"AZ",
    "sg:tags":[
        "parlor",
        "ice",
        "cream"
    ],
    "wof:name":"Dairy Queen",
    "wof:placetype":"venue"
},
  "geometry": {"coordinates":[-111.714403,33.605553],"type":"Point"}
}