{
  "type": "Feature",
  "properties": {
    "addr:full":"16816 N 35th Ave Phoenix AZ 85053",
    "addr:housenumber":"16816",
    "addr:postcode":"85053",
    "addr:street":"N 35Th Ave",
    "iso:country":"US",
    "sg:address":"16816 N 35th Ave",
    "sg:city":"Phoenix",
    "sg:classifiers":[
        {
            "category":"Personal",
            "subcategory":"Tanning Parlor",
            "type":"Services"
        }
    ],
    "sg:phone":"+1 602 439 3200",
    "sg:postcode":"85053",
    "sg:province":"AZ",
    "sg:tags":[
        "salon"
    ],
    "wof:name":"ABS Tan",
    "wof:placetype":"venue"
},
  "geometry": {"coordinates":[-112.134258,33.637558],"type":"Point"}
}