{
  "type": "Feature",
  "properties": {
    "iso:country":"US",
    "sg:address":"5054 S 40th St",
    "sg:city":"Phoenix",
    "sg:classifiers":[
        {
            "category":"Autos & Motor Vehicles",
            "subcategory":"Boat Sales",
            "type":"Retail Goods"
        }
    ],
    "sg:phone":"+1 602 437 3404",
    "sg:postcode":"85040",
    "sg:province":"AZ",
    "wof:name":"Foothills RV & Marine",
    "wof:placetype":"venue"
},
  "geometry": {"coordinates":[-111.995457,33.400132],"type":"Point"}
}