{
  "type": "Feature",
  "properties": {
    "iso:country":"US",
    "sg:address":"5646 N 51st Ave",
    "sg:city":"Glendale",
    "sg:classifiers":[
        {
            "category":"Food & Beverages",
            "subcategory":"Groceries & Convenience Stores",
            "type":"Retail Goods"
        }
    ],
    "sg:phone":"+1 623 937 3115",
    "sg:postcode":"85301",
    "sg:province":"AZ",
    "wof:name":"Convenience Sales Co",
    "wof:placetype":"venue"
},
  "geometry": {"coordinates":[-112.168757,33.519394],"type":"Point"}
}