{
  "type": "Feature",
  "properties": {
    "iso:country":"US",
    "sg:address":"680 W Deuce of Clubs",
    "sg:city":"Show Low",
    "sg:classifiers":[
        {
            "category":"Restaurant",
            "type":"Food & Drink"
        }
    ],
    "sg:menulink":"http://www.allmenus.com/az/snowflake/159843-arbys/menu/",
    "sg:phone":"+1 928 537 4413",
    "sg:postcode":"85901",
    "sg:province":"AZ",
    "sg:tags":[
        "burger",
        "american"
    ],
    "wof:name":"Arby's",
    "wof:placetype":"venue"
},
  "geometry": {"coordinates":[-110.05082400000001,34.245914],"type":"Point"}
}