{
  "type": "Feature",
  "properties": {
    "iso:country":"US",
    "sg:address":"12004 N 63rd Pl",
    "sg:city":"Scottsdale",
    "sg:classifiers":[
        {
            "category":"Professional",
            "subcategory":"Management & Consulting",
            "type":"Services"
        }
    ],
    "sg:phone":"+1 480 474 4032",
    "sg:postcode":"85024",
    "sg:province":"AZ",
    "sg:tags":[
        "consultant",
        "business"
    ],
    "wof:name":"Jimenez Consulting Solutions",
    "wof:placetype":"venue"
},
  "geometry": {"coordinates":[-111.944567,33.595163],"type":"Point"}
}