{
  "type": "Feature",
  "properties": {
    "iso:country":"US",
    "sg:address":"9991 N Woodstone Trl",
    "sg:city":"Tucson",
    "sg:classifiers":[
        {
            "category":"Shopping",
            "subcategory":"Beauty & Cosmetics",
            "type":"Retail Goods"
        }
    ],
    "sg:phone":"+1 520 744 4016",
    "sg:postcode":"85742",
    "sg:province":"AZ",
    "sg:tags":[
        "merchandise",
        "general"
    ],
    "wof:name":"Mary Kay Cosmetics",
    "wof:placetype":"venue"
},
  "geometry": {"coordinates":[-111.04071,32.38714],"type":"Point"}
}