{
  "type": "Feature",
  "properties": {
    "iso:country":"US",
    "sg:address":"14450 S 4th Ave",
    "sg:city":"Yuma",
    "sg:classifiers":[
        {
            "category":"Farming",
            "subcategory":"Orchard",
            "type":"Manufacturing & Wholesale Goods"
        },
        {
            "category":"Farming",
            "subcategory":"Farm",
            "type":"Manufacturing & Wholesale Goods"
        }
    ],
    "sg:phone":"+1 928 726 4506",
    "sg:postcode":"85365",
    "sg:province":"AZ",
    "wof:name":"Waldrip Bros Citrus Co",
    "wof:placetype":"venue"
},
  "geometry": {"coordinates":[-114.62389899999999,32.611773],"type":"Point"}
}