{
  "type": "Feature",
  "properties": {
    "iso:country":"US",
    "sg:address":"4585 S Coach Dr",
    "sg:city":"Tucson",
    "sg:classifiers":[
        {
            "category":"Wholesale",
            "subcategory":"Wine & Distilled Alcoholic Beverages",
            "type":"Manufacturing & Wholesale Goods"
        }
    ],
    "sg:phone":"+1 520 628 7226",
    "sg:postcode":"85714",
    "sg:province":"AZ",
    "wof:name":"Southern Wine & Spirits",
    "wof:placetype":"venue"
},
  "geometry": {"coordinates":[-110.913604,32.166652],"type":"Point"}
}