{
  "type": "Feature",
  "properties": {
    "addr:full":"8662 N 78th Ave Peoria AZ 85345",
    "addr:housenumber":"8662",
    "addr:postcode":"85345",
    "addr:street":"N 78Th Ave",
    "iso:country":"US",
    "sg:address":"8662 N 78th Ave",
    "sg:city":"Peoria",
    "sg:classifiers":[
        {
            "category":"Autos & Motor Vehicles",
            "subcategory":"Automobile Sales",
            "type":"Retail Goods"
        },
        {
            "category":"Autos & Motor Vehicles",
            "subcategory":"Auto Supplies",
            "type":"Retail Goods"
        },
        {
            "category":"Wholesale",
            "subcategory":"Auto Parts",
            "type":"Manufacturing & Wholesale Goods"
        }
    ],
    "sg:phone":"+1 623 486 1618",
    "sg:postcode":"85345",
    "sg:province":"AZ",
    "sg:tags":[
        "classic"
    ],
    "wof:name":"Arrowhead Truck Parts Inc",
    "wof:placetype":"venue"
},
  "geometry": {"coordinates":[-112.227323,33.562419],"type":"Point"}
}