{
  "type": "Feature",
  "properties": {
    "iso:country":"US",
    "sg:address":"2450 W 12th St",
    "sg:city":"Tempe",
    "sg:classifiers":[
        {
            "category":"Building & Trades",
            "subcategory":"Construction",
            "type":"Services"
        }
    ],
    "sg:phone":"+1 480 736 0690",
    "sg:postcode":"85281",
    "sg:province":"AZ",
    "sg:tags":[
        "general",
        "contractor"
    ],
    "wof:name":"JMW Construction",
    "wof:placetype":"venue"
},
  "geometry": {"coordinates":[-111.974637,33.415951],"type":"Point"}
}