{
  "type": "Feature",
  "properties": {
    "iso:country":"US",
    "sg:address":"4705 E Cochise Dr",
    "sg:city":"Rimrock",
    "sg:classifiers":[
        {
            "category":"Building & Trades",
            "subcategory":"Construction",
            "type":"Services"
        }
    ],
    "sg:phone":"+1 928 567 5425",
    "sg:postcode":"86335",
    "sg:province":"AZ",
    "sg:tags":[
        "contractor"
    ],
    "wof:name":"Newton Masonry",
    "wof:placetype":"venue"
},
  "geometry": {"coordinates":[-111.769997,34.630279],"type":"Point"}
}