{
  "type": "Feature",
  "properties": {
    "iso:country":"US",
    "sg:address":"4301 N 24th St",
    "sg:city":"Phoenix",
    "sg:classifiers":[
        {
            "category":"Real Estate",
            "subcategory":"Real Estate Operator",
            "type":"Services"
        }
    ],
    "sg:phone":"+1 602 954 9220",
    "sg:postcode":"85016",
    "sg:province":"AZ",
    "sg:tags":[
        "apartment"
    ],
    "wof:name":"Falling Waters Biltmore",
    "wof:placetype":"venue"
},
  "geometry": {"coordinates":[-112.030203,33.49917],"type":"Point"}
}