{
  "type": "Feature",
  "properties": {
    "iso:country":"US",
    "sg:address":"15111 N Hayden Rd",
    "sg:city":"Scottsdale",
    "sg:classifiers":[
        {
            "category":"Wholesale",
            "subcategory":"Apparel",
            "type":"Manufacturing & Wholesale Goods"
        }
    ],
    "sg:phone":"+1 480 251 0532",
    "sg:postcode":"85260",
    "sg:province":"AZ",
    "sg:tags":[
        "clothing"
    ],
    "wof:name":"Crown Jules Purse Designs",
    "wof:placetype":"venue"
},
  "geometry": {"coordinates":[-111.903104,33.623488],"type":"Point"}
}