{
  "type": "Feature",
  "properties": {
    "iso:country":"US",
    "sg:address":"1630 S Cathay Pl",
    "sg:city":"Tucson",
    "sg:classifiers":[
        {
            "category":"Building & Trades",
            "subcategory":"Plumbing",
            "type":"Services"
        }
    ],
    "sg:phone":"+1 520 885 1988",
    "sg:postcode":"85748",
    "sg:province":"AZ",
    "sg:tags":[
        "plumbing",
        "contractor"
    ],
    "wof:name":"Le Blanc Plumbing",
    "wof:placetype":"venue"
},
  "geometry": {"coordinates":[-110.779106,32.201862],"type":"Point"}
}