{
  "type": "Feature",
  "properties": {
    "addr:full":"17787 N Perimeter Dr Scottsdale AZ 85255",
    "addr:housenumber":"17787",
    "addr:postcode":"85255",
    "addr:street":"N Perimeter Dr",
    "iso:country":"US",
    "sg:address":"17787 N Perimeter Dr",
    "sg:city":"Scottsdale",
    "sg:classifiers":[
        {
            "category":"Banks & Credit Unions",
            "subcategory":"Bank",
            "type":"Services"
        }
    ],
    "sg:phone":"+1 480 585 1616",
    "sg:postcode":"85255",
    "sg:province":"AZ",
    "sg:tags":[
        "loan",
        "broker",
        "mortgage"
    ],
    "wof:name":"Sun State Savings",
    "wof:placetype":"venue"
},
  "geometry": {"coordinates":[-111.89877300000001,33.647123],"type":"Point"}
}