{
  "type": "Feature",
  "properties": {
    "iso:country":"US",
    "sg:address":"10852 E Linden St",
    "sg:city":"Tucson",
    "sg:classifiers":[
        {
            "category":"Wholesale",
            "subcategory":"Home Furnishings",
            "type":"Manufacturing & Wholesale Goods"
        }
    ],
    "sg:phone":"+1 520 749 5366",
    "sg:postcode":"85749",
    "sg:province":"AZ",
    "sg:tags":[
        "furniture"
    ],
    "wof:name":"John Dytko Artistry",
    "wof:placetype":"venue"
},
  "geometry": {"coordinates":[-110.761915,32.244938],"type":"Point"}
}