{
  "type": "Feature",
  "properties": {
    "addr:full":"2261 E 15th Pl Yuma AZ 85365",
    "addr:housenumber":"2261",
    "addr:postcode":"85365",
    "addr:street":"E 15Th Pl",
    "iso:country":"US",
    "sg:address":"2261 E 15th Pl",
    "sg:city":"Yuma",
    "sg:classifiers":[
        {
            "category":"Wholesale",
            "subcategory":"Electrical",
            "type":"Manufacturing & Wholesale Goods"
        }
    ],
    "sg:phone":"+1 928 782 9532",
    "sg:postcode":"85365",
    "sg:province":"AZ",
    "sg:tags":[
        "equipment",
        "merchandise",
        "armature"
    ],
    "wof:name":"Yuma Electric Motor Pumps",
    "wof:placetype":"venue"
},
  "geometry": {"coordinates":[-114.594688,32.699559],"type":"Point"}
}