{
  "type": "Feature",
  "properties": {
    "iso:country":"US",
    "sg:address":"5000 S Arizona Mills Cir",
    "sg:city":"Tempe",
    "sg:classifiers":[
        {
            "category":"Shopping",
            "subcategory":"Clothing, Apparel, & Fashions",
            "type":"Retail Goods"
        }
    ],
    "sg:phone":"+1 480 756 8886",
    "sg:postcode":"85282",
    "sg:province":"AZ",
    "sg:tags":[
        "uniform"
    ],
    "sg:website":"www.smartscrubs.com",
    "wof:name":"Smartscrubs",
    "wof:placetype":"venue"
},
  "geometry": {"coordinates":[-111.967141,33.382202],"type":"Point"}
}