{
  "type": "Feature",
  "properties": {
    "addr:full":"1412 E Hudson Dr Tempe AZ 85281",
    "addr:housenumber":"1412",
    "addr:postcode":"85281",
    "addr:street":"E Hudson Dr",
    "iso:country":"US",
    "sg:address":"1412 E Hudson Dr",
    "sg:city":"Tempe",
    "sg:classifiers":[
        {
            "category":"Manufacturing",
            "subcategory":"Metals",
            "type":"Manufacturing & Wholesale Goods"
        },
        {
            "category":"Building & Trades",
            "subcategory":"Construction",
            "type":"Services"
        }
    ],
    "sg:phone":"+1 480 317 9900",
    "sg:postcode":"85281",
    "sg:province":"AZ",
    "sg:tags":[
        "steel",
        "detailers",
        "structural",
        "manufacturer",
        "metal-wholesale"
    ],
    "wof:name":"American Precision",
    "wof:placetype":"venue"
},
  "geometry": {"coordinates":[-111.915708,33.413559],"type":"Point"}
}