{
  "type": "Feature",
  "properties": {
    "iso:country":"US",
    "sg:address":"2343 S Craycroft Rd",
    "sg:city":"Tucson",
    "sg:classifiers":[
        {
            "category":"Professional",
            "type":"Services"
        }
    ],
    "sg:phone":"+1 520 747 3300",
    "sg:postcode":"85711",
    "sg:province":"AZ",
    "sg:tags":[
        "establishment"
    ],
    "wof:name":"Budd Schmoll & Assoc",
    "wof:placetype":"venue"
},
  "geometry": {"coordinates":[-110.875033,32.196147],"type":"Point"}
}