{
  "type": "Feature",
  "properties": {
    "iso:country":"US",
    "sg:address":"5829 N 7th St",
    "sg:city":"Phoenix",
    "sg:classifiers":[
        {
            "category":"Professional",
            "subcategory":"Accounting & Tax Preparation",
            "type":"Services"
        }
    ],
    "sg:phone":"+1 602 266 3544",
    "sg:postcode":"85014",
    "sg:province":"AZ",
    "sg:tags":[
        "consultant"
    ],
    "sg:website":"www.geislerassociates.com",
    "wof:name":"Geisler & Assoc",
    "wof:placetype":"venue"
},
  "geometry": {"coordinates":[-112.064914,33.523214],"type":"Point"}
}