{
  "type": "Feature",
  "properties": {
    "iso:country":"US",
    "sg:address":"9226 N 5th Ave",
    "sg:city":"Phoenix",
    "sg:classifiers":[
        {
            "category":"Retail",
            "subcategory":"Repair Shop",
            "type":"Services"
        }
    ],
    "sg:phone":"+1 602 371 0306",
    "sg:postcode":"85021",
    "sg:province":"AZ",
    "sg:tags":[
        "upholsterer"
    ],
    "wof:name":"Manny's Upholstery",
    "wof:placetype":"venue"
},
  "geometry": {"coordinates":[-112.080992,33.571196],"type":"Point"}
}