{
  "type": "Feature",
  "properties": {
    "iso:country":"US",
    "sg:address":"2860 W Peoria Ave",
    "sg:city":"Phoenix",
    "sg:classifiers":[
        {
            "category":"Professional",
            "subcategory":"Lawyer & Legal Services",
            "type":"Services"
        }
    ],
    "sg:phone":"+1 602 234 1111",
    "sg:postcode":"85029",
    "sg:province":"AZ",
    "sg:tags":[
        "attorney"
    ],
    "wof:name":"Goldberg & Osborne",
    "wof:placetype":"venue"
},
  "geometry": {"coordinates":[-112.12323,33.582024],"type":"Point"}
}