{
  "type": "Feature",
  "properties": {
    "addr:full":"4906 E 23rd St Tucson AZ 85711",
    "addr:housenumber":"4906",
    "addr:postcode":"85711",
    "addr:street":"E 23Rd St",
    "iso:country":"US",
    "sg:address":"4906 E 23rd St",
    "sg:city":"Tucson",
    "sg:classifiers":[
        {
            "category":"Professional",
            "subcategory":"Management & Consulting",
            "type":"Services"
        }
    ],
    "sg:phone":"+1 520 790 8854",
    "sg:postcode":"85711",
    "sg:province":"AZ",
    "sg:tags":[
        "consultant",
        "safety"
    ],
    "wof:name":"Amcass Inc",
    "wof:placetype":"venue"
},
  "geometry": {"coordinates":[-110.886433,32.20548],"type":"Point"}
}