{
  "type": "Feature",
  "properties": {
    "iso:country":"US",
    "sg:address":"3205 W McDowell Rd",
    "sg:city":"Phoenix",
    "sg:classifiers":[
        {
            "category":"Food & Beverages",
            "subcategory":"Groceries & Convenience Stores",
            "type":"Retail Goods"
        }
    ],
    "sg:phone":"+1 602 278 8016",
    "sg:postcode":"85009",
    "sg:province":"AZ",
    "sg:tags":[
        "grocer"
    ],
    "wof:name":"Carniceria El Camino",
    "wof:placetype":"venue"
},
  "geometry": {"coordinates":[-112.127919,33.465864],"type":"Point"}
}