{
  "type": "Feature",
  "properties": {
    "addr:full":"840 E 19th St Yuma AZ 85364",
    "addr:housenumber":"840",
    "addr:postcode":"85364",
    "addr:street":"E 19Th St",
    "iso:country":"US",
    "sg:address":"840 E 19th St",
    "sg:city":"Yuma",
    "sg:classifiers":[
        {
            "category":"Manufacturing",
            "subcategory":"Food",
            "type":"Manufacturing & Wholesale Goods"
        }
    ],
    "sg:phone":"+1 928 782 5124",
    "sg:postcode":"85364",
    "sg:province":"AZ",
    "sg:tags":[
        "grocery",
        "drink",
        "soft",
        "mfg"
    ],
    "wof:name":"Coca-Cola",
    "wof:placetype":"venue"
},
  "geometry": {"coordinates":[-114.612877,32.693113],"type":"Point"}
}