{
  "type": "Feature",
  "properties": {
    "addr:full":"3850 N Fanning Dr Flagstaff AZ 86004",
    "addr:housenumber":"3850",
    "addr:postcode":"86004",
    "addr:street":"N Fanning Dr",
    "iso:country":"US",
    "sg:address":"3850 N Fanning Dr",
    "sg:city":"Flagstaff",
    "sg:classifiers":[
        {
            "category":"Food & Beverages",
            "subcategory":"Groceries & Convenience Stores",
            "type":"Retail Goods"
        }
    ],
    "sg:phone":"+1 928 527 1854",
    "sg:postcode":"86004",
    "sg:province":"AZ",
    "sg:tags":[
        "eating"
    ],
    "wof:name":"My American Market",
    "wof:placetype":"venue"
},
  "geometry": {"coordinates":[-111.59567699999999,35.220458],"type":"Point"}
}