{
  "type": "Feature",
  "properties": {
    "addr:full":"9831 S 51st Street Suite C-108 Phoenix  AZ 85044",
    "addr:housenumber":"9831",
    "addr:postcode":"85044",
    "addr:street":"S 51St Street Suite C-108",
    "iso:country":"US",
    "sg:address":"9831 S 51st Street Suite C-108",
    "sg:city":"Phoenix ",
    "sg:classifiers":[
        {
            "category":"Professional",
            "subcategory":"Computer Services",
            "type":"Services"
        }
    ],
    "sg:phone":"+1 216 458 4122",
    "sg:postcode":"85044",
    "sg:province":"AZ",
    "sg:tags":[
        "help-desk",
        "call-center",
        "customer-service",
        "it-support",
        "outsourcing",
        "universities",
        "colleges",
        "higher-education",
        "distance-learning"
    ],
    "sg:website":"http://www.perceptis.com",
    "wof:name":"Perceptis",
    "wof:placetype":"venue"
},
  "geometry": {"coordinates":[-111.97476399999999,33.358257],"type":"Point"}
}