{
  "type": "Feature",
  "properties": {
    "iso:country":"US",
    "sg:address":"1831 W Rose Garden Ln",
    "sg:city":"Phoenix",
    "sg:classifiers":[
        {
            "category":"Real Estate",
            "subcategory":"Real Estate Agent",
            "type":"Services"
        }
    ],
    "sg:phone":"+1 623 580 1800",
    "sg:postcode":"85027",
    "sg:province":"AZ",
    "sg:website":"www.nexusarizona.com",
    "wof:name":"Nexus Arizona Realty Group",
    "wof:placetype":"venue"
},
  "geometry": {"coordinates":[-112.094465,33.676408],"type":"Point"}
}