{
  "type": "Feature",
  "properties": {
    "iso:country":"US",
    "sg:address":"5820 W Greenway Rd",
    "sg:city":"Glendale",
    "sg:classifiers":[
        {
            "category":"Professional",
            "subcategory":"Printing & Photocopies",
            "type":"Services"
        }
    ],
    "sg:phone":"+1 602 978 8382",
    "sg:postcode":"85306",
    "sg:province":"AZ",
    "sg:tags":[
        "duplicating",
        "copying"
    ],
    "wof:name":"Alpha Omega Copies",
    "wof:placetype":"venue"
},
  "geometry": {"coordinates":[-112.18526300000001,33.625261],"type":"Point"}
}