{
  "type": "Feature",
  "properties": {
    "iso:country":"US",
    "sg:address":"1035 N McQueen Road Suite 109",
    "sg:city":"Gilbert",
    "sg:classifiers":[
        {
            "category":"Personal",
            "type":"Services"
        }
    ],
    "sg:phone":"+1 480 507 0786",
    "sg:postcode":"85233",
    "sg:province":"AZ",
    "sg:tags":[
        "sewing",
        "alteration"
    ],
    "sg:website":"www.swxpress.com",
    "wof:name":"Sportswear Express",
    "wof:placetype":"venue"
},
  "geometry": {"coordinates":[-111.82459299999999,33.369064],"type":"Point"}
}