{
  "type": "Feature",
  "properties": {
    "iso:country":"US",
    "sg:address":"3614 E Palm St",
    "sg:city":"Mesa",
    "sg:classifiers":[
        {
            "category":"Building & Trades",
            "subcategory":"Construction",
            "type":"Services"
        }
    ],
    "sg:phone":"+1 480 981 3061",
    "sg:postcode":"85215",
    "sg:province":"AZ",
    "wof:name":"Bhc Construction Inc",
    "wof:placetype":"venue"
},
  "geometry": {"coordinates":[-111.750709,33.470186],"type":"Point"}
}