{
  "type": "Feature",
  "properties": {
    "iso:country":"US",
    "sg:address":"761 E University Dr Ste C",
    "sg:city":"Mesa",
    "sg:classifiers":[
        {
            "category":"Health Services",
            "subcategory":"Clinic",
            "type":"Services"
        }
    ],
    "sg:phone":"+1 480 655 8888",
    "sg:postcode":"85203",
    "sg:province":"AZ",
    "sg:tags":[
        "outpatient"
    ],
    "wof:name":"Natural Theraputics, Inc",
    "wof:placetype":"venue"
},
  "geometry": {"coordinates":[-111.814858,33.422385],"type":"Point"}
}