{
  "type": "Feature",
  "properties": {
    "iso:country":"US",
    "sg:address":"122 N Cortez St",
    "sg:city":"Prescott",
    "sg:classifiers":[
        {
            "category":"Professional",
            "subcategory":"Lawyer & Legal Services",
            "type":"Services"
        }
    ],
    "sg:phone":"+1 928 541 9702",
    "sg:postcode":"86301",
    "sg:province":"AZ",
    "sg:tags":[
        "practice",
        "attorney",
        "criminal",
        "law"
    ],
    "sg:website":"http://www.prescottdui.com",
    "wof:name":"Law Office Of Lauren Vanpelt",
    "wof:placetype":"venue"
},
  "geometry": {"coordinates":[-112.468682,34.542325],"type":"Point"}
}