{
  "type": "Feature",
  "properties": {
    "addr:full":"101 E Gurley St Prescott AZ 86301",
    "addr:housenumber":"101",
    "addr:postcode":"86301",
    "addr:street":"E Gurley St",
    "iso:country":"US",
    "sg:address":"101 E Gurley St",
    "sg:city":"Prescott",
    "sg:classifiers":[
        {
            "category":"Banks & Credit Unions",
            "subcategory":"Bank",
            "type":"Services"
        }
    ],
    "sg:phone":"+1 928 445 9163",
    "sg:postcode":"86301",
    "sg:province":"AZ",
    "sg:tags":[
        "commercial"
    ],
    "wof:name":"Wells Fargo Bank N A",
    "wof:placetype":"venue"
},
  "geometry": {"coordinates":[-112.468711,34.541885],"type":"Point"}
}