{
  "type": "Feature",
  "properties": {
    "addr:full":"18433 S Arizona Ave Chandler AZ 85286",
    "addr:housenumber":"18433",
    "addr:postcode":"85286",
    "addr:street":"S Arizona Ave",
    "iso:country":"US",
    "sg:address":"18433 S Arizona Ave",
    "sg:city":"Chandler",
    "sg:classifiers":[
        {
            "category":"Home & Garden",
            "subcategory":"Garden Supply",
            "type":"Retail Goods"
        }
    ],
    "sg:phone":"+1 602 493 0403",
    "sg:postcode":"85286",
    "sg:province":"AZ",
    "sg:tags":[
        "nurseryman"
    ],
    "wof:name":"Moon Valley Nursery",
    "wof:placetype":"venue"
},
  "geometry": {"coordinates":[-111.841525,33.278249],"type":"Point"}
}