{
  "type": "Feature",
  "properties": {
    "iso:country":"US",
    "sg:address":"8209 E Cypress St",
    "sg:city":"Scottsdale",
    "sg:classifiers":[
        {
            "category":"Building & Trades",
            "subcategory":"Construction",
            "type":"Services"
        }
    ],
    "sg:phone":"+1 480 949 7813",
    "sg:postcode":"85257",
    "sg:province":"AZ",
    "sg:tags":[
        "hanging",
        "contractor"
    ],
    "wof:name":"Biltmore Wallcovering",
    "wof:placetype":"venue"
},
  "geometry": {"coordinates":[-111.904154,33.471362],"type":"Point"}
}