{
  "type": "Feature",
  "properties": {
    "addr:full":"1413 W Park Ave Gilbert AZ 85233",
    "addr:housenumber":"1413",
    "addr:postcode":"85233",
    "addr:street":"W Park Ave",
    "iso:country":"US",
    "sg:address":"1413 W Park Ave",
    "sg:city":"Gilbert",
    "sg:classifiers":[
        {
            "category":"Professional",
            "type":"Services"
        }
    ],
    "sg:phone":"+1 480 507 2048",
    "sg:postcode":"85233",
    "sg:province":"AZ",
    "wof:name":"Aram Chomina-Chavez",
    "wof:placetype":"venue"
},
  "geometry": {"coordinates":[-111.820519,33.351828],"type":"Point"}
}