{
  "type": "Feature",
  "properties": {
    "iso:country":"US",
    "sg:address":"8 N Leroux St",
    "sg:city":"Flagstaff",
    "sg:classifiers":[
        {
            "category":"Shopping",
            "subcategory":"Gifts & Souvenirs",
            "type":"Retail Goods"
        }
    ],
    "sg:phone":"+1 928 774 6234",
    "sg:postcode":"86001",
    "sg:province":"AZ",
    "sg:tags":[
        "shop"
    ],
    "wof:name":"All That Jazz",
    "wof:placetype":"venue"
},
  "geometry": {"coordinates":[-111.648648,35.198382],"type":"Point"}
}