{
  "type": "Feature",
  "properties": {
    "addr:full":"2659 W Guadalupe Rd Mesa AZ 85202",
    "addr:housenumber":"2659",
    "addr:postcode":"85202",
    "addr:street":"W Guadalupe Rd",
    "iso:country":"US",
    "sg:address":"2659 W Guadalupe Rd",
    "sg:city":"Mesa",
    "sg:classifiers":[
        {
            "category":"Community Center",
            "type":"Public Place"
        }
    ],
    "sg:phone":"+1 480 313 9500",
    "sg:postcode":"85202",
    "sg:province":"AZ",
    "sg:tags":[
        "medical"
    ],
    "wof:name":"Nurse 2U",
    "wof:placetype":"venue"
},
  "geometry": {"coordinates":[-111.89093200000001,33.363739],"type":"Point"}
}