{
  "type": "Feature",
  "properties": {
    "iso:country":"US",
    "sg:address":"3511 E Elm St",
    "sg:city":"Phoenix",
    "sg:classifiers":[
        {
            "category":"Professional",
            "subcategory":"Computer Services",
            "type":"Services"
        },
        {
            "category":"Internet Cafe",
            "subcategory":"None",
            "type":"Food & Drink"
        }
    ],
    "sg:phone":"+1 602 955 9050",
    "sg:postcode":"85018",
    "sg:province":"AZ",
    "sg:tags":[
        "product",
        "software"
    ],
    "sg:website":"http://www.copperbyte.com",
    "wof:name":"S S V Arizona Spt Tickets Exch",
    "wof:placetype":"venue"
},
  "geometry": {"coordinates":[-112.00653800000001,33.507737],"type":"Point"}
}