{
  "type": "Feature",
  "properties": {
    "iso:country":"US",
    "sg:address":"7032 S 17th St",
    "sg:city":"Phoenix",
    "sg:classifiers":[
        {
            "category":"Professional",
            "type":"Services"
        }
    ],
    "sg:phone":"+1 602 276 4894",
    "sg:postcode":"85042",
    "sg:province":"AZ",
    "wof:name":"Sallis & Sallis",
    "wof:placetype":"venue"
},
  "geometry": {"coordinates":[-112.04454,33.382179],"type":"Point"}
}