{
  "type": "Feature",
  "properties": {
    "iso:country":"US",
    "sg:address":"1700 N 23rd Ave",
    "sg:city":"Phoenix",
    "sg:classifiers":[
        {
            "category":"Autos & Motor Vehicles",
            "subcategory":"Auto Supplies",
            "type":"Retail Goods"
        }
    ],
    "sg:phone":"+1 602 340 1054",
    "sg:postcode":"85009",
    "sg:province":"AZ",
    "sg:tags":[
        "automobile",
        "parts",
        "part",
        "accessories-wholesale",
        "manufacturer"
    ],
    "wof:name":"Mighty Parts Systems",
    "wof:placetype":"venue"
},
  "geometry": {"coordinates":[-112.108521,33.466881],"type":"Point"}
}