{
  "type": "Feature",
  "properties": {
    "iso:country":"US",
    "sg:address":"18912 W Hays Ranch Rd",
    "sg:city":"Kirkland",
    "sg:classifiers":[
        {
            "category":"Education",
            "subcategory":"School",
            "type":"Public Place"
        }
    ],
    "sg:phone":"+1 928 427 3347",
    "sg:postcode":"86332",
    "sg:province":"AZ",
    "sg:tags":[
        "elementary"
    ],
    "wof:name":"Yarnell Elementary School",
    "wof:placetype":"venue"
},
  "geometry": {"coordinates":[-112.750572,34.27102],"type":"Point"}
}