{
  "type": "Feature",
  "properties": {
    "addr:full":"9132 W Cactus Rd Peoria AZ 85381",
    "addr:housenumber":"9132",
    "addr:postcode":"85381",
    "addr:street":"W Cactus Rd",
    "iso:country":"US",
    "sg:address":"9132 W Cactus Rd",
    "sg:city":"Peoria",
    "sg:classifiers":[
        {
            "category":"Banks & Credit Unions",
            "subcategory":"Bank",
            "type":"Services"
        }
    ],
    "sg:phone":"+1 623 878 1974",
    "sg:postcode":"85381",
    "sg:province":"AZ",
    "sg:tags":[
        "loan",
        "real estate"
    ],
    "wof:name":"Cash Flow Financial Svc",
    "wof:placetype":"venue"
},
  "geometry": {"coordinates":[-112.25738800000001,33.595358],"type":"Point"}
}