{
  "type": "Feature",
  "properties": {
    "iso:country":"US",
    "sg:address":"659 W Ingram St",
    "sg:city":"Mesa",
    "sg:classifiers":[
        {
            "category":"Building & Trades",
            "subcategory":"Construction",
            "type":"Services"
        }
    ],
    "sg:phone":"+1 480 834 1628",
    "sg:postcode":"85201",
    "sg:province":"AZ",
    "sg:tags":[
        "painter"
    ],
    "wof:name":"Already Done Custom Home Paint",
    "wof:placetype":"venue"
},
  "geometry": {"coordinates":[-111.846743,33.446551],"type":"Point"}
}