{
  "type": "Feature",
  "properties": {
    "addr:full":"5039 N 44th St Phoenix AZ 85018",
    "addr:housenumber":"5039",
    "addr:postcode":"85018",
    "addr:street":"N 44Th St",
    "iso:country":"US",
    "sg:address":"5039 N 44th St",
    "sg:city":"Phoenix",
    "sg:classifiers":[
        {
            "category":"Shopping",
            "subcategory":"Clothing, Apparel, & Fashions",
            "type":"Retail Goods"
        }
    ],
    "sg:phone":"+1 602 840 6173",
    "sg:postcode":"85018",
    "sg:province":"AZ",
    "wof:name":"Kiss Me Kate",
    "wof:placetype":"venue"
},
  "geometry": {"coordinates":[-111.986594,33.510764],"type":"Point"}
}