{
  "type": "Feature",
  "properties": {
    "iso:country":"US",
    "sg:address":"19989 E Julius Rd",
    "sg:city":"Queen Creek",
    "sg:classifiers":[
        {
            "category":"Building & Trades",
            "subcategory":"Construction",
            "type":"Services"
        }
    ],
    "sg:phone":"+1 480 888 0349",
    "sg:postcode":"85242",
    "sg:province":"AZ",
    "sg:tags":[
        "house"
    ],
    "wof:name":"Southwest Home Builders Inc",
    "wof:placetype":"venue"
},
  "geometry": {"coordinates":[-111.655628,33.256527],"type":"Point"}
}