{
  "type": "Feature",
  "properties": {
    "iso:country":"US",
    "sg:address":"2000 Ramar Rd",
    "sg:city":"Bullhead City",
    "sg:classifiers":[
        {
            "category":"Retail",
            "subcategory":"Repair Shop",
            "type":"Services"
        }
    ],
    "sg:phone":"+1 928 763 5070",
    "sg:postcode":"86442",
    "sg:province":"AZ",
    "sg:tags":[
        "lock",
        "locksmith"
    ],
    "wof:name":"Don's Mobile Locksmithing",
    "wof:placetype":"venue"
},
  "geometry": {"coordinates":[-114.577759,35.111347],"type":"Point"}
}