{
  "type": "Feature",
  "properties": {
    "iso:country":"US",
    "sg:address":"9175 E Tanque Verde Rd",
    "sg:city":"Tucson",
    "sg:classifiers":[
        {
            "category":"Cinema",
            "subcategory":"Movie Rental",
            "type":"Entertainment"
        }
    ],
    "sg:phone":"+1 520 760 2700",
    "sg:postcode":"85749",
    "sg:province":"AZ",
    "sg:tags":[
        "leasing",
        "video",
        "disc",
        "tape"
    ],
    "wof:name":"Blockbuster Video",
    "wof:placetype":"venue"
},
  "geometry": {"coordinates":[-110.79747500000001,32.25774],"type":"Point"}
}