{
  "type": "Feature",
  "properties": {
    "addr:full":"5624 E Aster Dr Scottsdale AZ 85254",
    "addr:housenumber":"5624",
    "addr:postcode":"85254",
    "addr:street":"E Aster Dr",
    "iso:country":"US",
    "sg:address":"5624 E Aster Dr",
    "sg:city":"Scottsdale",
    "sg:classifiers":[
        {
            "category":"Autos & Motor Vehicles",
            "subcategory":"Motorcycle Sales",
            "type":"Retail Goods"
        }
    ],
    "sg:phone":"+1 480 628 4606",
    "sg:postcode":"85254",
    "sg:province":"AZ",
    "sg:tags":[
        "car",
        "golf",
        "cart"
    ],
    "wof:name":"Arizona Mobil Golf Car Svc",
    "wof:placetype":"venue"
},
  "geometry": {"coordinates":[-111.958288,33.603591],"type":"Point"}
}