{
  "type": "Feature",
  "properties": {
    "iso:country":"US",
    "sg:address":"3939 W Windmills Blvd",
    "sg:city":"Chandler",
    "sg:classifiers":[
        {
            "category":"Professional",
            "subcategory":"Computer Services",
            "type":"Services"
        }
    ],
    "sg:phone":"+1 602 720 2747",
    "sg:postcode":"85226",
    "sg:province":"AZ",
    "sg:tags":[
        "credit",
        "card"
    ],
    "wof:name":"Card Payment Solutions",
    "wof:placetype":"venue"
},
  "geometry": {"coordinates":[-111.910945,33.323972],"type":"Point"}
}