{
  "type": "Feature",
  "properties": {
    "iso:country":"US",
    "sg:address":"1980 W Hospital Dr",
    "sg:city":"Tucson",
    "sg:classifiers":[
        {
            "category":"Health Services",
            "subcategory":"Doctor",
            "type":"Services"
        }
    ],
    "sg:phone":"+1 520 575 1272",
    "sg:postcode":"85704",
    "sg:province":"AZ",
    "sg:tags":[
        "physician",
        "surgeon"
    ],
    "sg:website":"www.tucsonent.com",
    "wof:name":"Tucson Ear Nose & Throat",
    "wof:placetype":"venue"
},
  "geometry": {"coordinates":[-111.00953699999999,32.319355],"type":"Point"}
}