{
  "type": "Feature",
  "properties": {
    "iso:country":"US",
    "sg:address":"7128 W Becker Ln",
    "sg:city":"Peoria",
    "sg:classifiers":[
        {
            "category":"Manufacturing",
            "subcategory":"Building Materials",
            "type":"Manufacturing & Wholesale Goods"
        }
    ],
    "sg:phone":"+1 602 920 9872",
    "sg:postcode":"85345",
    "sg:province":"AZ",
    "sg:tags":[
        "dock",
        "builder"
    ],
    "wof:name":"Jumbo Dry Wall",
    "wof:placetype":"venue"
},
  "geometry": {"coordinates":[-112.212346,33.582848],"type":"Point"}
}