{
  "type": "Feature",
  "properties": {
    "iso:country":"US",
    "sg:address":"4302 E Ray Rd",
    "sg:city":"Phoenix",
    "sg:classifiers":[
        {
            "category":"Health Services",
            "subcategory":"Optometrist",
            "type":"Services"
        }
    ],
    "sg:phone":"+1 480 704 0626",
    "sg:postcode":"85044",
    "sg:province":"AZ",
    "sg:website":"www.nationwidevision.com",
    "wof:name":"Nationwide Vision Ctr",
    "wof:placetype":"venue"
},
  "geometry": {"coordinates":[-111.989173,33.320435],"type":"Point"}
}