{
  "type": "Feature",
  "properties": {
    "addr:full":"749 N Meadows Dr Chandler AZ 85224",
    "addr:housenumber":"749",
    "addr:postcode":"85224",
    "addr:street":"N Meadows Dr",
    "iso:country":"US",
    "sg:address":"749 N Meadows Dr",
    "sg:city":"Chandler",
    "sg:classifiers":[
        {
            "category":"Building & Trades",
            "subcategory":"Construction",
            "type":"Services"
        }
    ],
    "sg:phone":"+1 480 786 3757",
    "sg:postcode":"85224",
    "sg:province":"AZ",
    "wof:name":"Road Runner Racing",
    "wof:placetype":"venue"
},
  "geometry": {"coordinates":[-111.866407,33.316433],"type":"Point"}
}