{
  "type": "Feature",
  "properties": {
    "iso:country":"US",
    "sg:address":"8529 E Pinchot Ave",
    "sg:city":"Scottsdale",
    "sg:classifiers":[
        {
            "category":"Bars & Pubs",
            "type":"Food & Drink"
        }
    ],
    "sg:phone":"+1 480 941 2685",
    "sg:postcode":"85251",
    "sg:province":"AZ",
    "sg:tags":[
        "drinking"
    ],
    "wof:name":"A Rent A Tender Inc",
    "wof:placetype":"venue"
},
  "geometry": {"coordinates":[-111.896482,33.48232],"type":"Point"}
}