{
  "type": "Feature",
  "properties": {
    "iso:country":"US",
    "sg:address":"3840 E Baseline Road",
    "sg:city":"Mesa",
    "sg:classifiers":[
        {
            "category":"Home & Garden",
            "subcategory":"Home Furnishings",
            "type":"Retail Goods"
        }
    ],
    "sg:phone":"+1 480 926 4868",
    "sg:postcode":"85206",
    "sg:province":"AZ",
    "sg:tags":[
        "decor"
    ],
    "wof:name":"Storage Masters At Val Vista Lakes",
    "wof:placetype":"venue"
},
  "geometry": {"coordinates":[-111.750248,33.379238],"type":"Point"}
}