{
  "type": "Feature",
  "properties": {
    "iso:country":"US",
    "sg:address":"19820 N 7th St",
    "sg:city":"Phoenix",
    "sg:classifiers":[
        {
            "category":"Real Estate",
            "subcategory":"Developer",
            "type":"Services"
        }
    ],
    "sg:phone":"+1 623 581 8558",
    "sg:postcode":"85024",
    "sg:province":"AZ",
    "sg:tags":[
        "development",
        "land",
        "sale",
        "retail"
    ],
    "wof:name":"Starlight Pines Land Company",
    "wof:placetype":"venue"
},
  "geometry": {"coordinates":[-112.065702,33.668191],"type":"Point"}
}