{
  "type": "Feature",
  "properties": {
    "addr:full":"4395 S Price Rd Tempe AZ 85282",
    "addr:housenumber":"4395",
    "addr:postcode":"85282",
    "addr:street":"S Price Rd",
    "iso:country":"US",
    "sg:address":"4395 S Price Rd",
    "sg:city":"Tempe",
    "sg:classifiers":[
        {
            "category":"Wholesale",
            "subcategory":"Machinery & Supplies",
            "type":"Manufacturing & Wholesale Goods"
        }
    ],
    "sg:phone":"+1 602 261 6731",
    "sg:postcode":"85282",
    "sg:province":"AZ",
    "wof:name":"Granite Construction Co",
    "wof:placetype":"venue"
},
  "geometry": {"coordinates":[-111.890097,33.384178],"type":"Point"}
}