{
  "type": "Feature",
  "properties": {
    "iso:country":"US",
    "sg:address":"2826 E Blacklidge Dr",
    "sg:city":"Tucson",
    "sg:classifiers":[
        {
            "category":"Shopping",
            "subcategory":"Gifts & Souvenirs",
            "type":"Retail Goods"
        }
    ],
    "sg:phone":"+1 520 977 4828",
    "sg:postcode":"85716",
    "sg:province":"AZ",
    "sg:tags":[
        "basket"
    ],
    "wof:name":"Brandies Gift Baskets",
    "wof:placetype":"venue"
},
  "geometry": {"coordinates":[-110.930682,32.261301],"type":"Point"}
}