{
  "type": "Feature",
  "properties": {
    "addr:full":"1845 E Broadway Rd Tempe AZ 85282",
    "addr:housenumber":"1845",
    "addr:postcode":"85282",
    "addr:street":"E Broadway Rd",
    "iso:country":"US",
    "sg:address":"1845 E Broadway Rd",
    "sg:city":"Tempe",
    "sg:classifiers":[
        {
            "category":"Recreation",
            "type":"Entertainment"
        }
    ],
    "sg:phone":"+1 480 968 2068",
    "sg:postcode":"85282",
    "sg:province":"AZ",
    "sg:tags":[
        "martial",
        "arts",
        "instruction"
    ],
    "sg:website":"www.acskarate.com",
    "wof:name":"ACS Karate",
    "wof:placetype":"venue"
},
  "geometry": {"coordinates":[-111.905331,33.407427],"type":"Point"}
}