{
  "type": "Feature",
  "properties": {
    "addr:full":"6323 W Van Buren Street Phoenix AZ 85043",
    "addr:housenumber":"6323",
    "addr:postcode":"85043",
    "addr:street":"W Van Buren Street",
    "iso:country":"US",
    "sg:address":"6323 W Van Buren Street",
    "sg:city":"Phoenix",
    "sg:classifiers":[
        {
            "category":"Building & Trades",
            "subcategory":"Construction",
            "type":"Services"
        }
    ],
    "sg:phone":"+1 623 907 0622",
    "sg:postcode":"85043",
    "sg:province":"AZ",
    "sg:tags":[
        "contractor"
    ],
    "wof:name":"Raj Construction",
    "wof:placetype":"venue"
},
  "geometry": {"coordinates":[-112.195492,33.451428],"type":"Point"}
}