{
  "type": "Feature",
  "properties": {
    "iso:country":"US",
    "sg:address":"7225 N 110th Ave",
    "sg:city":"Glendale",
    "sg:classifiers":[
        {
            "category":"Retail",
            "subcategory":"Auto Repair",
            "type":"Services"
        },
        {
            "category":"Autos & Motor Vehicles",
            "subcategory":"Recreational Vehicle Sales",
            "type":"Retail Goods"
        }
    ],
    "sg:phone":"+1 623 206 8617",
    "sg:postcode":"85307",
    "sg:province":"AZ",
    "sg:tags":[
        "automobile",
        "diagnostic",
        "equipment-service"
    ],
    "wof:name":"The Kar Store",
    "wof:placetype":"venue"
},
  "geometry": {"coordinates":[-112.296832,33.540477],"type":"Point"}
}