{
  "type": "Feature",
  "properties": {
    "iso:country":"US",
    "sg:address":"961 W Ray Rd",
    "sg:city":"Chandler",
    "sg:classifiers":[
        {
            "category":"Food & Beverages",
            "subcategory":"Meat & Fish",
            "type":"Retail Goods"
        }
    ],
    "sg:phone":"+1 480 855 8676",
    "sg:postcode":"85225",
    "sg:province":"AZ",
    "wof:name":"Carneceria Los Toros Chan",
    "wof:placetype":"venue"
},
  "geometry": {"coordinates":[-111.858248,33.320537],"type":"Point"}
}