{
  "type": "Feature",
  "properties": {
    "iso:country":"US",
    "sg:address":"8615 E Main St Lot S15",
    "sg:city":"Mesa",
    "sg:classifiers":[
        {
            "category":"Education",
            "subcategory":"Junior College",
            "type":"Public Place"
        }
    ],
    "sg:phone":"+1 480 380 1026",
    "sg:postcode":"85207",
    "sg:province":"AZ",
    "sg:tags":[
        "doll"
    ],
    "wof:name":"Dots Dolls",
    "wof:placetype":"venue"
},
  "geometry": {"coordinates":[-111.683865,33.415741],"type":"Point"}
}