{
  "type": "Feature",
  "properties": {
    "iso:country":"US",
    "sg:address":"5955 W Peoria Ave",
    "sg:city":"Glendale",
    "sg:classifiers":[
        {
            "category":"Government",
            "subcategory":"Post Office",
            "type":"Public Place"
        }
    ],
    "sg:phone":"+1 623 486 2029",
    "sg:postcode":"85302",
    "sg:province":"AZ",
    "sg:website":"http://www.usps.com",
    "wof:name":"USPS - United States Post Office - Glendale Main",
    "wof:placetype":"venue"
},
  "geometry": {"coordinates":[-112.187752,33.581829],"type":"Point"}
}