{
  "type": "Feature",
  "properties": {
    "iso:country":"US",
    "sg:address":"23029 E Munoz St",
    "sg:city":"Queen Creek",
    "sg:classifiers":[
        {
            "category":"Building & Trades",
            "subcategory":"Construction",
            "type":"Services"
        }
    ],
    "sg:phone":"+1 480 987 9227",
    "sg:postcode":"85242",
    "sg:province":"AZ",
    "sg:tags":[
        "general",
        "contractor"
    ],
    "wof:name":"Smith & Son Custom Contracting",
    "wof:placetype":"venue"
},
  "geometry": {"coordinates":[-111.58971200000001,33.246062],"type":"Point"}
}