{
  "type": "Feature",
  "properties": {
    "iso:country":"US",
    "sg:address":"6415 S Lakeshore Drive",
    "sg:city":"Tempe",
    "sg:classifiers":[
        {
            "category":"Organizations",
            "subcategory":"Religious Organization",
            "type":"Services"
        }
    ],
    "sg:phone":"+1 480 838 4240",
    "sg:postcode":"85283",
    "sg:province":"AZ",
    "sg:website":"www.churchofgod.cc",
    "wof:name":"Lakeshore Bible Church of God",
    "wof:placetype":"venue"
},
  "geometry": {"coordinates":[-111.91990800000001,33.366594],"type":"Point"}
}