{
  "type": "Feature",
  "properties": {
    "iso:country":"US",
    "sg:address":"7926 S Priest Dr",
    "sg:city":"Tempe",
    "sg:classifiers":[
        {
            "category":"Manufacturing",
            "subcategory":"Petroleum Products",
            "type":"Manufacturing & Wholesale Goods"
        }
    ],
    "sg:phone":"+1 602 460 4595",
    "sg:postcode":"85284",
    "sg:province":"AZ",
    "sg:tags":[
        "lubricating",
        "mfg"
    ],
    "wof:name":"Valvoline Instant Oil Change",
    "wof:placetype":"venue"
},
  "geometry": {"coordinates":[-111.963138,33.345483],"type":"Point"}
}