{
  "type": "Feature",
  "properties": {
    "iso:country":"US",
    "sg:address":"2923 W Charter Oak Rd",
    "sg:city":"Phoenix",
    "sg:classifiers":[
        {
            "category":"Building & Trades",
            "subcategory":"Construction",
            "type":"Services"
        }
    ],
    "sg:phone":"+1 602 942 6860",
    "sg:postcode":"85029",
    "sg:province":"AZ",
    "sg:tags":[
        "coping",
        "plastering",
        "tiling",
        "pool",
        "swimming"
    ],
    "wof:name":"Crystal Pool Svc",
    "wof:placetype":"venue"
},
  "geometry": {"coordinates":[-112.121689,33.597923],"type":"Point"}
}