{
  "type": "Feature",
  "properties": {
    "addr:full":"1804 E Citation Ln Tempe AZ 85284",
    "addr:housenumber":"1804",
    "addr:postcode":"85284",
    "addr:street":"E Citation Ln",
    "iso:country":"US",
    "sg:address":"1804 E Citation Ln",
    "sg:city":"Tempe",
    "sg:classifiers":[
        {
            "category":"Professional",
            "type":"Services"
        }
    ],
    "sg:phone":"+1 480 345 7504",
    "sg:postcode":"85284",
    "sg:province":"AZ",
    "wof:name":"Chacon",
    "wof:placetype":"venue"
},
  "geometry": {"coordinates":[-111.91043000000001,33.342857],"type":"Point"}
}