{
  "type": "Feature",
  "properties": {
    "iso:country":"US",
    "sg:address":"2418 W Peak View Rd",
    "sg:city":"Phoenix",
    "sg:classifiers":[
        {
            "category":"Wholesale",
            "subcategory":"Office Equipment",
            "type":"Manufacturing & Wholesale Goods"
        },
        {
            "category":"Manufacturing",
            "subcategory":"Building Materials",
            "type":"Manufacturing & Wholesale Goods"
        }
    ],
    "sg:phone":"+1 602 885 1418",
    "sg:postcode":"85085",
    "sg:province":"AZ",
    "sg:tags":[
        "cabinetmakers-commercial",
        "industrial",
        "equipment-installation",
        "furniture"
    ],
    "wof:name":"Royal Designs",
    "wof:placetype":"venue"
},
  "geometry": {"coordinates":[-112.109895,33.747114],"type":"Point"}
}