{
  "type": "Feature",
  "properties": {
    "addr:full":"4912 E Shea Blvd Scottsdale AZ 85254",
    "addr:housenumber":"4912",
    "addr:postcode":"85254",
    "addr:street":"E Shea Blvd",
    "iso:country":"US",
    "sg:address":"4912 E Shea Blvd",
    "sg:city":"Scottsdale",
    "sg:classifiers":[
        {
            "category":"Personal",
            "subcategory":"Beauty Salon",
            "type":"Services"
        }
    ],
    "sg:phone":"+1 480 778 1543",
    "sg:postcode":"85254",
    "sg:province":"AZ",
    "wof:name":"Prova Salon",
    "wof:placetype":"venue"
},
  "geometry": {"coordinates":[-111.976669,33.582777],"type":"Point"}
}