{
  "type": "Feature",
  "properties": {
    "iso:country":"US",
    "sg:address":"5781 N Echo Canyon Cir",
    "sg:city":"Phoenix",
    "sg:classifiers":[
        {
            "category":"Wholesale",
            "subcategory":"Machinery & Supplies",
            "type":"Manufacturing & Wholesale Goods"
        }
    ],
    "sg:phone":"+1 602 952 2766",
    "sg:postcode":"85018",
    "sg:province":"AZ",
    "sg:tags":[
        "equipment",
        "industrial"
    ],
    "wof:name":"Pearson Enterprises",
    "wof:placetype":"venue"
},
  "geometry": {"coordinates":[-111.976831,33.518973],"type":"Point"}
}