{
  "type": "Feature",
  "properties": {
    "iso:country":"US",
    "sg:address":"2010 W Lower Buckeye Rd",
    "sg:city":"Phoenix",
    "sg:classifiers":[
        {
            "category":"Wholesale",
            "subcategory":"Scrap",
            "type":"Manufacturing & Wholesale Goods"
        }
    ],
    "sg:phone":"+1 602 257 9400",
    "sg:postcode":"85009",
    "sg:province":"AZ",
    "sg:tags":[
        "recycling",
        "center"
    ],
    "wof:name":"Arizona Recycling",
    "wof:placetype":"venue"
},
  "geometry": {"coordinates":[-112.106181,33.422355],"type":"Point"}
}