{
  "type": "Feature",
  "properties": {
    "addr:full":"1600 W Monroe St Phoenix AZ 85007",
    "addr:housenumber":"1600",
    "addr:postcode":"85007",
    "addr:street":"W Monroe St",
    "iso:country":"US",
    "sg:address":"1600 W Monroe St",
    "sg:city":"Phoenix",
    "sg:classifiers":[
        {
            "category":"Restaurant",
            "type":"Food & Drink"
        }
    ],
    "sg:phone":"+1 602 258 4382",
    "sg:postcode":"85007",
    "sg:province":"AZ",
    "sg:tags":[
        "cafeteria"
    ],
    "wof:name":"Ac Cafeteria",
    "wof:placetype":"venue"
},
  "geometry": {"coordinates":[-112.093597,33.450291],"type":"Point"}
}