{
  "type": "Feature",
  "properties": {
    "iso:country":"US",
    "sg:address":"35416 W Miller Rd",
    "sg:city":"Stanfield",
    "sg:classifiers":[
        {
            "category":"Building & Trades",
            "subcategory":"Construction",
            "type":"Services"
        }
    ],
    "sg:phone":"+1 520 424 3171",
    "sg:postcode":"85272",
    "sg:province":"AZ",
    "sg:tags":[
        "concrete",
        "contractor"
    ],
    "wof:name":"Salt River Asphalt & Striping",
    "wof:placetype":"venue"
},
  "geometry": {"coordinates":[-111.949212,32.938175],"type":"Point"}
}