{
  "type": "Feature",
  "properties": {
    "iso:country":"US",
    "sg:address":"8700 S Price Rd",
    "sg:city":"Tempe",
    "sg:classifiers":[
        {
            "category":"Wholesale",
            "subcategory":"Computers",
            "type":"Manufacturing & Wholesale Goods"
        }
    ],
    "sg:phone":"+1 480 794 6900",
    "sg:postcode":"85284",
    "sg:province":"AZ",
    "wof:name":"Avnet Computer Marketing",
    "wof:placetype":"venue"
},
  "geometry": {"coordinates":[-111.893997,33.335899],"type":"Point"}
}