{
  "type": "Feature",
  "properties": {
    "iso:country":"US",
    "sg:address":"7375 E Stetson Dr",
    "sg:city":"Scottsdale",
    "sg:classifiers":[
        {
            "category":"Health Services",
            "subcategory":"Health Practitioner",
            "type":"Services"
        }
    ],
    "sg:phone":"+1 480 423 3525",
    "sg:postcode":"85251",
    "sg:province":"AZ",
    "sg:tags":[
        "acupuncture"
    ],
    "wof:name":"Acupuncture & Oriental",
    "wof:placetype":"venue"
},
  "geometry": {"coordinates":[-111.921874,33.499485],"type":"Point"}
}