{
  "type": "Feature",
  "properties": {
    "addr:full":"2159 McCulloch Blvd N Lake Havasu City AZ 86403",
    "addr:housenumber":"2159",
    "addr:postcode":"86403",
    "addr:street":"Mcculloch Blvd N",
    "iso:country":"US",
    "sg:address":"2159 McCulloch Blvd N",
    "sg:city":"Lake Havasu City",
    "sg:classifiers":[
        {
            "category":"Wholesale",
            "subcategory":"Office Equipment",
            "type":"Manufacturing & Wholesale Goods"
        }
    ],
    "sg:phone":"+1 928 680 1113",
    "sg:postcode":"86403",
    "sg:province":"AZ",
    "sg:tags":[
        "machine",
        "duplicating",
        "copying"
    ],
    "wof:name":"Image Services & Machines",
    "wof:placetype":"venue"
},
  "geometry": {"coordinates":[-114.322957,34.475402],"type":"Point"}
}