{
  "type": "Feature",
  "properties": {
    "iso:country":"US",
    "sg:address":"701 White Spar Rd",
    "sg:city":"Prescott",
    "sg:classifiers":[
        {
            "category":"Real Estate",
            "subcategory":"Real Estate Operator",
            "type":"Services"
        }
    ],
    "sg:phone":"+1 928 445 8963",
    "sg:postcode":"86303",
    "sg:province":"AZ",
    "sg:tags":[
        "apartment"
    ],
    "wof:name":"Canyon Run Village Apts",
    "wof:placetype":"venue"
},
  "geometry": {"coordinates":[-112.476889,34.528546],"type":"Point"}
}