{
  "type": "Feature",
  "properties": {
    "iso:country":"US",
    "sg:address":"4743 N 20th St",
    "sg:city":"Phoenix",
    "sg:classifiers":[
        {
            "category":"Restaurant",
            "type":"Food & Drink"
        }
    ],
    "sg:menulink":"http://www.allmenus.com/az/phoenix/283061-pie-zanos-kitchen/menu/",
    "sg:phone":"+1 602 955 4225",
    "sg:postcode":"85016",
    "sg:province":"AZ",
    "sg:tags":[
        "american",
        "pizza"
    ],
    "wof:name":"Pie Zanos Kitchen",
    "wof:placetype":"venue"
},
  "geometry": {"coordinates":[-112.03873400000001,33.506222],"type":"Point"}
}