{
  "type": "Feature",
  "properties": {
    "iso:country":"US",
    "sg:address":"4144 N 44th St",
    "sg:city":"Phoenix",
    "sg:classifiers":[
        {
            "category":"Professional",
            "subcategory":"Advertising",
            "type":"Services"
        }
    ],
    "sg:phone":"+1 602 957 7323",
    "sg:postcode":"85018",
    "sg:province":"AZ",
    "sg:tags":[
        "counselor"
    ],
    "sg:website":"www.parkandco.com",
    "wof:name":"Edit 2 Go",
    "wof:placetype":"venue"
},
  "geometry": {"coordinates":[-111.986977,33.49565],"type":"Point"}
}