{
  "type": "Feature",
  "properties": {
    "addr:full":"2501 W Happy Valley Rd Suite 18-1000 Phoenix AZ 85085",
    "addr:housenumber":"2501",
    "addr:postcode":"85085",
    "addr:street":"W Happy Valley Rd Suite 18-1000",
    "iso:country":"US",
    "sg:address":"2501 W Happy Valley Rd Suite 18-1000",
    "sg:city":"Phoenix",
    "sg:classifiers":[
        {
            "category":"Utilities",
            "subcategory":"Mobile Phone",
            "type":"Services"
        },
        {
            "category":"Shopping",
            "subcategory":"Mobile Phones",
            "type":"Retail Goods"
        }
    ],
    "sg:phone":"+1 623 582 1111",
    "sg:postcode":"85085",
    "sg:province":"AZ",
    "sg:tags":[
        "supply",
        "communication",
        "telephone",
        "wireless",
        "equipment",
        "cellular"
    ],
    "sg:website":"http://www.sprint.com",
    "wof:name":"Sprint Store",
    "wof:placetype":"venue"
},
  "geometry": {"coordinates":[-112.11174,33.712799],"type":"Point"}
}