{
  "type": "Feature",
  "properties": {
    "addr:full":"201 S Beeline Hwy Payson AZ 85541",
    "addr:housenumber":"201",
    "addr:postcode":"85541",
    "addr:street":"S Beeline Hwy",
    "iso:country":"US",
    "sg:address":"201 S Beeline Hwy",
    "sg:city":"Payson",
    "sg:classifiers":[
        {
            "category":"Banks & Credit Unions",
            "subcategory":"Bank",
            "type":"Services"
        },
        {
            "category":"Banks & Credit Unions",
            "subcategory":"Financial Services",
            "type":"Services"
        }
    ],
    "sg:phone":"+1 928 474 2287",
    "sg:postcode":"85541",
    "sg:province":"AZ",
    "sg:tags":[
        "commercial",
        "loan",
        "saving"
    ],
    "sg:website":"https://www.chase.com/",
    "wof:name":"Chase",
    "wof:placetype":"venue"
},
  "geometry": {"coordinates":[-111.32300600000001,34.237924],"type":"Point"}
}