{
  "type": "Feature",
  "properties": {
    "iso:country":"US",
    "sg:address":"1147 Hodges Cir",
    "sg:city":"Rio Rico",
    "sg:classifiers":[
        {
            "category":"Professional",
            "type":"Services"
        }
    ],
    "sg:phone":"+1 520 907 0408",
    "sg:postcode":"85648",
    "sg:province":"AZ",
    "wof:name":"Eclectic Concepts",
    "wof:placetype":"venue"
},
  "geometry": {"coordinates":[-110.976781,31.468858],"type":"Point"}
}