{
  "type": "Feature",
  "properties": {
    "iso:country":"US",
    "sg:address":"1345 E Main St",
    "sg:city":"Mesa",
    "sg:classifiers":[
        {
            "category":"Real Estate",
            "subcategory":"Real Estate Agent",
            "type":"Services"
        }
    ],
    "sg:phone":"+1 480 835 0275",
    "sg:postcode":"85203",
    "sg:province":"AZ",
    "wof:name":"Erwin Standing Sra",
    "wof:placetype":"venue"
},
  "geometry": {"coordinates":[-111.802878,33.415144],"type":"Point"}
}