{
  "type": "Feature",
  "properties": {
    "iso:country":"US",
    "sg:address":"5805 E Cll Fortunato Serrano",
    "sg:city":"Guadalupe",
    "sg:classifiers":[
        {
            "category":"Real Estate",
            "subcategory":"Real Estate Operator",
            "type":"Services"
        }
    ],
    "sg:phone":"+1 480 820 2772",
    "sg:postcode":"85283",
    "sg:province":"AZ",
    "sg:tags":[
        "apartment"
    ],
    "wof:name":"Guadalupe Barrio Nuevo",
    "wof:placetype":"venue"
},
  "geometry": {"coordinates":[-111.95937,33.361759],"type":"Point"}
}