{
  "type": "Feature",
  "properties": {
    "iso:country":"US",
    "sg:address":"3618 W Camelback Rd",
    "sg:city":"Phoenix",
    "sg:classifiers":[
        {
            "category":"Autos & Motor Vehicles",
            "subcategory":"Motorcycle Sales",
            "type":"Retail Goods"
        },
        {
            "category":"Retail",
            "subcategory":"Auto Repair",
            "type":"Services"
        }
    ],
    "sg:phone":"+1 602 748 4817",
    "sg:postcode":"85019",
    "sg:province":"AZ",
    "sg:tags":[
        "scooters-repairing",
        "scooters-parts",
        "supply"
    ],
    "sg:website":"http://www.apachemotorcycles.com",
    "wof:name":"Apache Motorcycles",
    "wof:placetype":"venue"
},
  "geometry": {"coordinates":[-112.136933,33.509449],"type":"Point"}
}