{
  "type": "Feature",
  "properties": {
    "addr:full":"4650 E Cotton Center Blvd Phoenix AZ 85040",
    "addr:housenumber":"4650",
    "addr:postcode":"85040",
    "addr:street":"E Cotton Center Blvd",
    "iso:country":"US",
    "sg:address":"4650 E Cotton Center Blvd",
    "sg:city":"Phoenix",
    "sg:classifiers":[
        {
            "category":"Professional",
            "subcategory":"Art Services",
            "type":"Services"
        }
    ],
    "sg:phone":"+1 602 286 9300",
    "sg:postcode":"85040",
    "sg:province":"AZ",
    "sg:tags":[
        "designer",
        "display",
        "producer"
    ],
    "wof:name":"Optimus Civil Design Group-Phoenix, Inc.",
    "wof:placetype":"venue"
},
  "geometry": {"coordinates":[-111.982209,33.403022],"type":"Point"}
}