{
  "type": "Feature",
  "properties": {
    "iso:country":"US",
    "sg:address":"6025 S Morris Blvd",
    "sg:city":"Tucson",
    "sg:classifiers":[
        {
            "category":"Taxi",
            "type":"Transportation"
        }
    ],
    "sg:phone":"+1 520 620 0200",
    "sg:postcode":"85706",
    "sg:province":"AZ",
    "sg:tags":[
        "taxicab"
    ],
    "wof:name":"Cobras Radio Taxi",
    "wof:placetype":"venue"
},
  "geometry": {"coordinates":[-110.957819,32.143608],"type":"Point"}
}