{
  "type": "Feature",
  "properties": {
    "addr:full":"1900 S Don Carlos Mesa AZ 85202",
    "addr:housenumber":"1900",
    "addr:postcode":"85202",
    "addr:street":"S Don Carlos Mesa",
    "iso:country":"US",
    "sg:address":"1900 S Don Carlos",
    "sg:city":"Mesa",
    "sg:classifiers":[
        {
            "category":"Building & Trades",
            "subcategory":"Locksmith",
            "type":"Services"
        }
    ],
    "sg:phone":"+1 480 718 2160",
    "sg:postcode":"85202",
    "sg:province":"AZ",
    "sg:tags":[
        "key"
    ],
    "wof:name":"23 7 A Locksmith",
    "wof:placetype":"venue"
},
  "geometry": {"coordinates":[-111.890086,33.380145],"type":"Point"}
}