{
  "type": "Feature",
  "properties": {
    "addr:full":"6480 N Oracle Rd Tucson AZ 85704",
    "addr:housenumber":"6480",
    "addr:postcode":"85704",
    "addr:street":"N Oracle Rd",
    "iso:country":"US",
    "sg:address":"6480 N Oracle Rd",
    "sg:city":"Tucson",
    "sg:classifiers":[
        {
            "category":"Organizations",
            "subcategory":"Religious Organization",
            "type":"Services"
        }
    ],
    "sg:phone":"+1 520 297 7683",
    "sg:postcode":"85704",
    "sg:province":"AZ",
    "sg:tags":[
        "church"
    ],
    "wof:name":"Christian Science Reading Room",
    "wof:placetype":"venue"
},
  "geometry": {"coordinates":[-110.97475900000001,32.32308],"type":"Point"}
}