{
  "type": "Feature",
  "properties": {
    "addr:full":"1034 S Lewis Mesa AZ 85210",
    "addr:housenumber":"1034",
    "addr:postcode":"85210",
    "addr:street":"S Lewis",
    "iso:country":"US",
    "sg:address":"1034 S Lewis",
    "sg:city":"Mesa",
    "sg:classifiers":[
        {
            "category":"Building & Trades",
            "subcategory":"Construction",
            "type":"Services"
        }
    ],
    "sg:phone":"+1 480 461 3800",
    "sg:postcode":"85210",
    "sg:province":"AZ",
    "sg:tags":[
        "excavation",
        "contractor"
    ],
    "wof:name":"Vw Dig Underground Inc",
    "wof:placetype":"venue"
},
  "geometry": {"coordinates":[-111.829199,33.393953],"type":"Point"}
}