{
  "type": "Feature",
  "properties": {
    "iso:country":"US",
    "sg:address":"1926 W Berridge Ln",
    "sg:city":"Phoenix",
    "sg:classifiers":[
        {
            "category":"Professional",
            "type":"Services"
        }
    ],
    "sg:phone":"+1 602 995 0168",
    "sg:postcode":"85015",
    "sg:province":"AZ",
    "wof:name":"Almus Inc",
    "wof:placetype":"venue"
},
  "geometry": {"coordinates":[-112.103512,33.526495],"type":"Point"}
}