{
  "type": "Feature",
  "properties": {
    "iso:country":"US",
    "sg:address":"2600 W Kiltie Ln",
    "sg:city":"Flagstaff",
    "sg:classifiers":[
        {
            "category":"Recreation",
            "type":"Entertainment"
        }
    ],
    "sg:phone":"+1 928 774 1000",
    "sg:postcode":"86001",
    "sg:province":"AZ",
    "sg:tags":[
        "stable"
    ],
    "sg:website":"www.flagstaffridingcenter.com",
    "wof:name":"Flagstaff Riding Ctr",
    "wof:placetype":"venue"
},
  "geometry": {"coordinates":[-111.691048,35.177506],"type":"Point"}
}