{
  "type": "Feature",
  "properties": {
    "addr:full":"2600 W Kiltie Ln Flagstaff AZ 86001",
    "addr:housenumber":"2600",
    "addr:postcode":"86001",
    "addr:street":"W Kiltie Ln",
    "iso:country":"US",
    "sg:address":"2600 W Kiltie Ln",
    "sg:city":"Flagstaff",
    "sg:classifiers":[
        {
            "category":"Recreation",
            "type":"Entertainment"
        }
    ],
    "sg:phone":"+1 928 774 1000",
    "sg:postcode":"86001",
    "sg:province":"AZ",
    "sg:tags":[
        "stable"
    ],
    "sg:website":"www.flagstaffridingcenter.com",
    "wof:name":"Flagstaff Riding Ctr",
    "wof:placetype":"venue"
},
  "geometry": {"coordinates":[-111.69104799999999,35.177506],"type":"Point"}
}