{
  "type": "Feature",
  "properties": {
    "addr:full":"3714 W Tonopah Dr Glendale AZ 85308",
    "addr:housenumber":"3714",
    "addr:postcode":"85308",
    "addr:street":"W Tonopah Dr",
    "iso:country":"US",
    "sg:address":"3714 W Tonopah Dr",
    "sg:city":"Glendale",
    "sg:classifiers":[
        {
            "category":"Organizations",
            "subcategory":"Religious Organization",
            "type":"Services"
        }
    ],
    "sg:phone":"+1 623 516 8734",
    "sg:postcode":"85308",
    "sg:province":"AZ",
    "sg:tags":[
        "church"
    ],
    "wof:name":"North Valley Assembly-God Chr",
    "wof:placetype":"venue"
},
  "geometry": {"coordinates":[-112.142577,33.671576],"type":"Point"}
}