{
  "type": "Feature",
  "properties": {
    "iso:country":"US",
    "sg:address":"3045 S 22nd Ave",
    "sg:city":"Phoenix",
    "sg:classifiers":[
        {
            "category":"Building & Trades",
            "subcategory":"Construction",
            "type":"Services"
        }
    ],
    "sg:phone":"+1 602 262 6441",
    "sg:postcode":"85009",
    "sg:province":"AZ",
    "sg:tags":[
        "street",
        "maintenance"
    ],
    "wof:name":"Streets & Transportation Dept",
    "wof:placetype":"venue"
},
  "geometry": {"coordinates":[-112.106988,33.420833],"type":"Point"}
}