{
  "type": "Feature",
  "properties": {
    "iso:country":"US",
    "sg:address":"2625 W Baseline Rd",
    "sg:city":"Tempe",
    "sg:classifiers":[
        {
            "category":"Restaurant",
            "type":"Food & Drink"
        }
    ],
    "sg:phone":"+1 602 383 8228",
    "sg:postcode":"85283",
    "sg:province":"AZ",
    "sg:tags":[
        "eating"
    ],
    "wof:name":"Petes Cuban Cafe",
    "wof:placetype":"venue"
},
  "geometry": {"coordinates":[-111.975534,33.37813],"type":"Point"}
}