{
  "type": "Feature",
  "properties": {
    "iso:country":"US",
    "sg:address":"13215 N 35th St",
    "sg:city":"Phoenix",
    "sg:classifiers":[
        {
            "category":"Manufacturing",
            "subcategory":"Tools & Machinery",
            "type":"Manufacturing & Wholesale Goods"
        }
    ],
    "sg:phone":"+1 602 404 1712",
    "sg:postcode":"85032",
    "sg:province":"AZ",
    "sg:tags":[
        "machine",
        "shop",
        "jobbing",
        "repair"
    ],
    "wof:name":"Tribond Industries Inc",
    "wof:placetype":"venue"
},
  "geometry": {"coordinates":[-112.006264,33.604703],"type":"Point"}
}