{
  "type": "Feature",
  "properties": {
    "iso:country":"US",
    "sg:address":"120 W Warner Rd",
    "sg:city":"Tempe",
    "sg:classifiers":[
        {
            "category":"Professional",
            "subcategory":"Management & Consulting",
            "type":"Services"
        }
    ],
    "sg:phone":"+1 480 606 9300",
    "sg:postcode":"85284",
    "sg:province":"AZ",
    "sg:tags":[
        "marketing",
        "program"
    ],
    "sg:website":"www.cpginc.com",
    "wof:name":"Continental Promotions Group",
    "wof:placetype":"venue"
},
  "geometry": {"coordinates":[-111.939233,33.334702],"type":"Point"}
}