{
  "type": "Feature",
  "properties": {
    "addr:full":"707 S Broad St Globe AZ 85501",
    "addr:housenumber":"707",
    "addr:postcode":"85501",
    "addr:street":"S Broad St",
    "iso:country":"US",
    "sg:address":"707 S Broad St",
    "sg:city":"Globe",
    "sg:classifiers":[
        {
            "category":"Organizations",
            "subcategory":"Community Association",
            "type":"Services"
        }
    ],
    "sg:phone":"+1 928 425 0888",
    "sg:postcode":"85501",
    "sg:province":"AZ",
    "sg:tags":[
        "military"
    ],
    "sg:website":"www.vfw.org",
    "wof:name":"Veterans Of Foreign Wars",
    "wof:placetype":"venue"
},
  "geometry": {"coordinates":[-110.781634,33.391041],"type":"Point"}
}