{
  "type": "Feature",
  "properties": {
    "iso:country":"US",
    "sg:address":"16673 N Avenida Del Oro",
    "sg:city":"Tucson",
    "sg:classifiers":[
        {
            "category":"Building & Trades",
            "subcategory":"Plumbing",
            "type":"Services"
        }
    ],
    "sg:phone":"+1 520 818 2137",
    "sg:postcode":"85739",
    "sg:province":"AZ",
    "wof:name":"Tucson Plumbing",
    "wof:placetype":"venue"
},
  "geometry": {"coordinates":[-110.925003,32.508598],"type":"Point"}
}