{
  "type": "Feature",
  "properties": {
    "iso:country":"US",
    "sg:address":"150 E Terminal Produce Dr",
    "sg:city":"Nogales",
    "sg:classifiers":[
        {
            "category":"Food & Beverages",
            "subcategory":"Fruits & Vegetables",
            "type":"Retail Goods"
        }
    ],
    "sg:phone":"+1 520 377 9900",
    "sg:postcode":"85621",
    "sg:province":"AZ",
    "sg:tags":[
        "produce"
    ],
    "wof:name":"Kenny's Produce Inc",
    "wof:placetype":"venue"
},
  "geometry": {"coordinates":[-110.928276,31.3709],"type":"Point"}
}