{
  "type": "Feature",
  "properties": {
    "iso:country":"US",
    "sg:address":"8834 W Mission Ln",
    "sg:city":"Peoria",
    "sg:classifiers":[
        {
            "category":"Building & Trades",
            "subcategory":"Construction",
            "type":"Services"
        }
    ],
    "sg:phone":"+1 623 878 1928",
    "sg:postcode":"85345",
    "sg:province":"AZ",
    "sg:tags":[
        "house"
    ],
    "wof:name":"Construction Connection Inc",
    "wof:placetype":"venue"
},
  "geometry": {"coordinates":[-112.250576,33.568704],"type":"Point"}
}