{
  "type": "Feature",
  "properties": {
    "iso:country":"US",
    "sg:address":"9004 E Meadow Hill Dr",
    "sg:city":"Scottsdale",
    "sg:classifiers":[
        {
            "category":"Building & Trades",
            "subcategory":"Landscaping Services",
            "type":"Services"
        }
    ],
    "sg:phone":"+1 480 661 7791",
    "sg:postcode":"85260",
    "sg:province":"AZ",
    "sg:tags":[
        "horticulture",
        "product",
        "landscape"
    ],
    "sg:website":"http://www.inspection1st.com",
    "wof:name":"Insp 1st",
    "wof:placetype":"venue"
},
  "geometry": {"coordinates":[-111.887417,33.61513],"type":"Point"}
}