{
  "type": "Feature",
  "properties": {
    "iso:country":"US",
    "sg:address":"502 W 29th St",
    "sg:city":"Tucson",
    "sg:classifiers":[
        {
            "category":"Organizations",
            "subcategory":"Non-profit Organization",
            "type":"Services"
        }
    ],
    "sg:phone":"+1 520 838 3913",
    "sg:postcode":"85713",
    "sg:province":"AZ",
    "wof:name":"Tucson International Mariachi",
    "wof:placetype":"venue"
},
  "geometry": {"coordinates":[-110.97763399999999,32.199575],"type":"Point"}
}