{
  "type": "Feature",
  "properties": {
    "iso:country":"US",
    "sg:address":"8944 W Patrick Ln",
    "sg:city":"Peoria",
    "sg:classifiers":[
        {
            "category":"Insurance",
            "subcategory":"Insurance Agent",
            "type":"Services"
        }
    ],
    "sg:phone":"+1 602 274 5667",
    "sg:postcode":"85383",
    "sg:province":"AZ",
    "wof:name":"Sun Adjusters Of Arizona Inc",
    "wof:placetype":"venue"
},
  "geometry": {"coordinates":[-112.253609,33.692187],"type":"Point"}
}