{
  "type": "Feature",
  "properties": {
    "iso:country":"US",
    "sg:address":"2139 W Madero Ave",
    "sg:city":"Mesa",
    "sg:classifiers":[
        {
            "category":"Building & Trades",
            "subcategory":"Construction",
            "type":"Services"
        }
    ],
    "sg:phone":"+1 602 692 8488",
    "sg:postcode":"85202",
    "sg:province":"AZ",
    "sg:tags":[
        "house"
    ],
    "wof:name":"Hobbs Construction LLC",
    "wof:placetype":"venue"
},
  "geometry": {"coordinates":[-111.881533,33.36927],"type":"Point"}
}