{
  "type": "Feature",
  "properties": {
    "iso:country":"US",
    "sg:address":"2904 E Roosevelt St",
    "sg:city":"Phoenix",
    "sg:classifiers":[
        {
            "category":"Social Services",
            "subcategory":"Child Care",
            "type":"Services"
        }
    ],
    "sg:phone":"+1 602 273 7949",
    "sg:postcode":"85008",
    "sg:province":"AZ",
    "wof:name":"New Creations Day Care",
    "wof:placetype":"venue"
},
  "geometry": {"coordinates":[-112.019215,33.458549],"type":"Point"}
}