{
  "type": "Feature",
  "properties": {
    "iso:country":"US",
    "sg:address":"2702 E Amberwood Dr",
    "sg:city":"Phoenix",
    "sg:classifiers":[
        {
            "category":"Manufacturing",
            "subcategory":"Electronics",
            "type":"Manufacturing & Wholesale Goods"
        }
    ],
    "sg:phone":"+1 480 706 7987",
    "sg:postcode":"85048",
    "sg:province":"AZ",
    "sg:tags":[
        "equipment",
        "mfg",
        "communications"
    ],
    "wof:name":"SW Traffic Systems Inc",
    "wof:placetype":"venue"
},
  "geometry": {"coordinates":[-112.024951,33.299545],"type":"Point"}
}