{
  "type": "Feature",
  "properties": {
    "addr:full":"1939 S Val Vista Drive Mesa AZ 85204",
    "addr:housenumber":"1939",
    "addr:postcode":"85204",
    "addr:street":"S Val Vista Drive",
    "iso:country":"US",
    "sg:address":"1939 S Val Vista Drive",
    "sg:city":"Mesa",
    "sg:classifiers":[
        {
            "category":"Personal",
            "subcategory":"Nail Salon",
            "type":"Services"
        }
    ],
    "sg:phone":"+1 480 635 8467",
    "sg:postcode":"85204",
    "sg:province":"AZ",
    "wof:name":"Valley Nail",
    "wof:placetype":"venue"
},
  "geometry": {"coordinates":[-111.75388599999999,33.380064],"type":"Point"}
}