{
  "type": "Feature",
  "properties": {
    "iso:country":"US",
    "sg:address":"116 N Roosevelt Ave",
    "sg:city":"Chandler",
    "sg:classifiers":[
        {
            "category":"Wholesale",
            "subcategory":"Groceries",
            "type":"Manufacturing & Wholesale Goods"
        },
        {
            "category":"Wholesale",
            "subcategory":"Non-durable Goods",
            "type":"Manufacturing & Wholesale Goods"
        }
    ],
    "sg:phone":"+1 480 961 0175",
    "sg:postcode":"85226",
    "sg:province":"AZ",
    "sg:tags":[
        "candy",
        "souvenir"
    ],
    "sg:website":"www.desertgatherings.com",
    "wof:name":"Desert Gatherings Inc",
    "wof:placetype":"venue"
},
  "geometry": {"coordinates":[-111.951125,33.304026],"type":"Point"}
}