{
  "type": "Feature",
  "properties": {
    "iso:country":"US",
    "sg:address":"6635 W Carol Ann Way",
    "sg:city":"Glendale",
    "sg:classifiers":[
        {
            "category":"Professional",
            "type":"Services"
        }
    ],
    "sg:phone":"+1 623 979 9147",
    "sg:postcode":"85306",
    "sg:province":"AZ",
    "wof:name":"It Profits & Designs LLC",
    "wof:placetype":"venue"
},
  "geometry": {"coordinates":[-112.201487,33.627854],"type":"Point"}
}