{
  "type": "Feature",
  "properties": {
    "iso:country":"US",
    "sg:address":"76 Erie St",
    "sg:city":"Bisbee",
    "sg:classifiers":[
        {
            "category":"Home & Garden",
            "subcategory":"Building Materials",
            "type":"Retail Goods"
        }
    ],
    "sg:phone":"+1 520 432 2205",
    "sg:postcode":"85603",
    "sg:province":"AZ",
    "sg:tags":[
        "lumber"
    ],
    "wof:name":"Bisbee Lumber Co Inc",
    "wof:placetype":"venue"
},
  "geometry": {"coordinates":[-109.894058,31.430181],"type":"Point"}
}