{
  "type": "Feature",
  "properties": {
    "iso:country":"US",
    "sg:address":"1535 W Parkside Ln Ste E",
    "sg:city":"Phoenix",
    "sg:classifiers":[
        {
            "category":"Retail",
            "subcategory":"Auto Repair",
            "type":"Services"
        }
    ],
    "sg:phone":"+1 623 581 6200",
    "sg:postcode":"85027",
    "sg:province":"AZ",
    "sg:tags":[
        "automobile",
        "machine",
        "shop"
    ],
    "wof:name":"Evans Precision Machining Inc",
    "wof:placetype":"venue"
},
  "geometry": {"coordinates":[-112.093273,33.695308],"type":"Point"}
}