{
  "type": "Feature",
  "properties": {
    "iso:country":"US",
    "sg:address":"1820 N 75th Ave Ste 110",
    "sg:city":"Phoenix",
    "sg:classifiers":[
        {
            "category":"Restaurant",
            "type":"Food & Drink"
        }
    ],
    "sg:phone":"+1 623 848 0991",
    "sg:postcode":"85035",
    "sg:province":"AZ",
    "sg:tags":[
        "thai",
        "asian",
        "pan"
    ],
    "wof:name":"75th Thai Taste Restaurant",
    "wof:placetype":"venue"
},
  "geometry": {"coordinates":[-112.220749,33.46792],"type":"Point"}
}