{
  "type": "Feature",
  "properties": {
    "iso:country":"US",
    "sg:address":"11305 E Roscoe Ave",
    "sg:city":"Mesa",
    "sg:classifiers":[
        {
            "category":"Building & Trades",
            "subcategory":"Construction",
            "type":"Services"
        }
    ],
    "sg:phone":"+1 480 357 2463",
    "sg:postcode":"85212",
    "sg:province":"AZ",
    "sg:tags":[
        "roofing",
        "contractor"
    ],
    "wof:name":"Klinedog Roofing Repair",
    "wof:placetype":"venue"
},
  "geometry": {"coordinates":[-111.589912,33.336741],"type":"Point"}
}