{
  "type": "Feature",
  "properties": {
    "iso:country":"US",
    "sg:address":"6615 W Chandler Blvd Ste 8",
    "sg:city":"Chandler",
    "sg:classifiers":[
        {
            "category":"Autos & Motor Vehicles",
            "subcategory":"Auto Supplies",
            "type":"Retail Goods"
        },
        {
            "category":"Manufacturing",
            "subcategory":"Glass & Minerals",
            "type":"Manufacturing & Wholesale Goods"
        },
        {
            "category":"Retail",
            "subcategory":"Auto Repair",
            "type":"Services"
        }
    ],
    "sg:phone":"+1 480 940 9577",
    "sg:postcode":"85226",
    "sg:province":"AZ",
    "sg:tags":[
        "plate",
        "coating",
        "glass-auto",
        "tinting",
        "window",
        "windshield"
    ],
    "sg:website":"http://www.starwindshieldrepair.com",
    "wof:name":"Star Windshield Repair",
    "wof:placetype":"venue"
},
  "geometry": {"coordinates":[-111.956691,33.305221],"type":"Point"}
}