{
  "type": "Feature",
  "properties": {
    "addr:full":"6125 N 35th Ave Phoenix AZ 85017",
    "addr:housenumber":"6125",
    "addr:postcode":"85017",
    "addr:street":"N 35Th Ave",
    "iso:country":"US",
    "sg:address":"6125 N 35th Ave",
    "sg:city":"Phoenix",
    "sg:classifiers":[
        {
            "category":"Manufacturing",
            "subcategory":"Printing",
            "type":"Manufacturing & Wholesale Goods"
        }
    ],
    "sg:phone":"+1 480 777 7868",
    "sg:postcode":"85017",
    "sg:province":"AZ",
    "sg:tags":[
        "publisher",
        "music"
    ],
    "wof:name":"JLJ Music Publishing",
    "wof:placetype":"venue"
},
  "geometry": {"coordinates":[-112.134186,33.526235],"type":"Point"}
}