{
  "type": "Feature",
  "properties": {
    "addr:full":"89 Biltmore Est Phoenix AZ 85016",
    "addr:housenumber":"89",
    "addr:postcode":"85016",
    "addr:street":"Biltmore Est",
    "iso:country":"US",
    "sg:address":"89 Biltmore Est",
    "sg:city":"Phoenix",
    "sg:classifiers":[
        {
            "category":"Health Services",
            "subcategory":"Doctor",
            "type":"Services"
        }
    ],
    "sg:phone":"+1 480 893 8366",
    "sg:postcode":"85016",
    "sg:province":"AZ",
    "sg:tags":[
        "physician",
        "radiology",
        "pediatrics-radiology",
        "surgeons",
        "surgeon"
    ],
    "wof:name":"C C Sabal",
    "wof:placetype":"venue"
},
  "geometry": {"coordinates":[-112.01737199999999,33.515369],"type":"Point"}
}