{
  "type": "Feature",
  "properties": {
    "iso:country":"US",
    "sg:address":"5455 Brandis Way",
    "sg:city":"Flagstaff",
    "sg:classifiers":[
        {
            "category":"Government",
            "subcategory":"Office",
            "type":"Public Place"
        }
    ],
    "sg:phone":"+1 928 526 5830",
    "sg:postcode":"86004",
    "sg:province":"AZ",
    "sg:tags":[
        "administrative",
        "program",
        "health"
    ],
    "wof:name":"Coleman Cancer Wellness",
    "wof:placetype":"venue"
},
  "geometry": {"coordinates":[-111.549467,35.327708],"type":"Point"}
}