{
  "type": "Feature",
  "properties": {
    "iso:country":"US",
    "sg:address":"1904 W Glendale Ave",
    "sg:city":"Phoenix",
    "sg:classifiers":[
        {
            "category":"Food & Beverages",
            "subcategory":"Groceries & Convenience Stores",
            "type":"Retail Goods"
        }
    ],
    "sg:phone":"+1 602 995 2651",
    "sg:postcode":"85021",
    "sg:province":"AZ",
    "wof:name":"Dillions",
    "wof:placetype":"venue"
},
  "geometry": {"coordinates":[-112.100656,33.538712],"type":"Point"}
}