{
  "type": "Feature",
  "properties": {
    "iso:country":"US",
    "sg:address":"7144 E Acoma Dr",
    "sg:city":"Scottsdale",
    "sg:classifiers":[
        {
            "category":"Shopping",
            "subcategory":"Gifts & Souvenirs",
            "type":"Retail Goods"
        },
        {
            "category":"Shopping",
            "subcategory":"Jewelry",
            "type":"Retail Goods"
        },
        {
            "category":"Manufacturing",
            "subcategory":"Jewelry",
            "type":"Manufacturing & Wholesale Goods"
        }
    ],
    "sg:phone":"+1 480 348 5700",
    "sg:postcode":"85254",
    "sg:province":"AZ",
    "sg:tags":[
        "shop",
        "stone",
        "designer",
        "jewelers-wholesale",
        "jeweler",
        "precious",
        "semi-precious",
        "manufacturer"
    ],
    "sg:website":"http://www.shaneco.com",
    "wof:name":"Shane Co.",
    "wof:placetype":"venue"
},
  "geometry": {"coordinates":[-111.92634,33.618002],"type":"Point"}
}