{
  "type": "Feature",
  "properties": {
    "iso:country":"US",
    "sg:address":"7500 E Deer Valley Rd",
    "sg:city":"Scottsdale",
    "sg:classifiers":[
        {
            "category":"Professional",
            "subcategory":"Accounting & Tax Preparation",
            "type":"Services"
        }
    ],
    "sg:phone":"+1 480 563 9683",
    "sg:postcode":"85255",
    "sg:province":"AZ",
    "sg:tags":[
        "billing"
    ],
    "wof:name":"Physician Billing",
    "wof:placetype":"venue"
},
  "geometry": {"coordinates":[-111.916869,33.684273],"type":"Point"}
}