{
  "type": "Feature",
  "properties": {
    "addr:full":"21154 E Alyssa Rd Queen Creek AZ 85242",
    "addr:housenumber":"21154",
    "addr:postcode":"85242",
    "addr:street":"E Alyssa Rd",
    "iso:country":"US",
    "sg:address":"21154 E Alyssa Rd",
    "sg:city":"Queen Creek",
    "sg:classifiers":[
        {
            "category":"Professional",
            "subcategory":"Business Services",
            "type":"Services"
        }
    ],
    "sg:phone":"+1 480 677 2383",
    "sg:postcode":"85242",
    "sg:province":"AZ",
    "sg:tags":[
        "paper"
    ],
    "wof:name":"Sonoran Shredders",
    "wof:placetype":"venue"
},
  "geometry": {"coordinates":[-111.626515,33.25768],"type":"Point"}
}