{
  "type": "Feature",
  "properties": {
    "iso:country":"US",
    "sg:address":"13829 N 19th Ave",
    "sg:city":"Phoenix",
    "sg:classifiers":[
        {
            "category":"Personal",
            "subcategory":"Beauty Salon",
            "type":"Services"
        }
    ],
    "sg:phone":"+1 602 564 6550",
    "sg:postcode":"85023",
    "sg:province":"AZ",
    "wof:name":"Hair Stylist Barber & Beauty",
    "wof:placetype":"venue"
},
  "geometry": {"coordinates":[-112.099571,33.613497],"type":"Point"}
}