{
  "type": "Feature",
  "properties": {
    "iso:country":"US",
    "sg:address":"28800 S Nogales Hwy",
    "sg:city":"Amado",
    "sg:classifiers":[
        {
            "category":"Shopping",
            "subcategory":"Gifts & Souvenirs",
            "type":"Retail Goods"
        }
    ],
    "sg:phone":"+1 520 398 2168",
    "sg:postcode":"85645",
    "sg:province":"AZ",
    "sg:tags":[
        "shop"
    ],
    "wof:name":"Amado Gift Shop",
    "wof:placetype":"venue"
},
  "geometry": {"coordinates":[-111.06111900000001,31.727631],"type":"Point"}
}