{
  "type": "Feature",
  "properties": {
    "iso:country":"US",
    "sg:address":"922 W Grant St Apt A",
    "sg:city":"Phoenix",
    "sg:classifiers":[
        {
            "category":"Personal",
            "subcategory":"Beauty Salon",
            "type":"Services"
        }
    ],
    "sg:phone":"+1 602 252 3670",
    "sg:postcode":"85007",
    "sg:province":"AZ",
    "wof:name":"Pinkie's Beauty Salon",
    "wof:placetype":"venue"
},
  "geometry": {"coordinates":[-112.086107,33.440899],"type":"Point"}
}