{
  "type": "Feature",
  "properties": {
    "iso:country":"US",
    "sg:address":"23027 N 15th Ln",
    "sg:city":"Phoenix",
    "sg:classifiers":[
        {
            "category":"Building & Trades",
            "subcategory":"Plumbing",
            "type":"Services"
        }
    ],
    "sg:phone":"+1 623 298 0611",
    "sg:postcode":"85027",
    "sg:province":"AZ",
    "sg:tags":[
        "conditioning",
        "air",
        "system",
        "contractor"
    ],
    "wof:name":"Alpine Mechanical & Svc",
    "wof:placetype":"venue"
},
  "geometry": {"coordinates":[-112.093377,33.695726],"type":"Point"}
}