{
  "type": "Feature",
  "properties": {
    "addr:full":"11158 W Madisen Ellise Dr Surprise AZ 85374",
    "addr:housenumber":"11158",
    "addr:postcode":"85374",
    "addr:street":"W Madisen Ellise Dr",
    "iso:country":"US",
    "sg:address":"11158 W Madisen Ellise Dr",
    "sg:city":"Surprise",
    "sg:classifiers":[
        {
            "category":"Restaurant",
            "type":"Food & Drink"
        }
    ],
    "sg:phone":"+1 623 933 5740",
    "sg:postcode":"85374",
    "sg:province":"AZ",
    "sg:tags":[
        "eating"
    ],
    "wof:name":"MA & Pas Kettle Korn",
    "wof:placetype":"venue"
},
  "geometry": {"coordinates":[-112.299954,33.649895],"type":"Point"}
}