{
  "type": "Feature",
  "properties": {
    "iso:country":"US",
    "sg:address":"3484 E Britannia Dr",
    "sg:city":"Tucson",
    "sg:classifiers":[
        {
            "category":"Wholesale",
            "subcategory":"Machinery & Supplies",
            "type":"Manufacturing & Wholesale Goods"
        }
    ],
    "sg:phone":"+1 520 889 7000",
    "sg:postcode":"85706",
    "sg:province":"AZ",
    "sg:tags":[
        "engineering",
        "industrial"
    ],
    "wof:name":"Kaman Industrial Supplies",
    "wof:placetype":"venue"
},
  "geometry": {"coordinates":[-110.917983,32.136408],"type":"Point"}
}