{
  "type": "Feature",
  "properties": {
    "iso:country":"US",
    "sg:address":"3126 W Thomas Rd",
    "sg:city":"Phoenix",
    "sg:classifiers":[
        {
            "category":"Home & Garden",
            "subcategory":"Furniture",
            "type":"Retail Goods"
        }
    ],
    "sg:phone":"+1 602 233 1232",
    "sg:postcode":"85017",
    "sg:province":"AZ",
    "wof:name":"Muebleria San Jose",
    "wof:placetype":"venue"
},
  "geometry": {"coordinates":[-112.126946,33.480512],"type":"Point"}
}