{
  "type": "Feature",
  "properties": {
    "iso:country":"US",
    "sg:address":"1220 W 24th St Suite 1",
    "sg:city":"Yuma",
    "sg:classifiers":[
        {
            "category":"Health Services",
            "subcategory":"Doctor",
            "type":"Services"
        }
    ],
    "sg:phone":"+1 928 329 8331",
    "sg:postcode":"85364",
    "sg:province":"AZ",
    "sg:tags":[
        "physician",
        "family",
        "practice",
        "surgeons",
        "medicine",
        "surgeon"
    ],
    "wof:name":"Yuma Nephrology PC",
    "wof:placetype":"venue"
},
  "geometry": {"coordinates":[-114.63410500000001,32.683957],"type":"Point"}
}