{
  "type": "Feature",
  "properties": {
    "addr:full":"2633 E Air Ln Phoenix AZ 85034",
    "addr:housenumber":"2633",
    "addr:postcode":"85034",
    "addr:street":"E Air Ln",
    "iso:country":"US",
    "sg:address":"2633 E Air Ln",
    "sg:city":"Phoenix",
    "sg:classifiers":[
        {
            "category":"Restaurant",
            "type":"Food & Drink"
        }
    ],
    "sg:phone":"+1 602 220 9307",
    "sg:postcode":"85034",
    "sg:province":"AZ",
    "sg:tags":[
        "eating"
    ],
    "wof:name":"Left Seat Restaurant",
    "wof:placetype":"venue"
},
  "geometry": {"coordinates":[-112.017151,33.443907],"type":"Point"}
}