{
  "type": "Feature",
  "properties": {
    "iso:country":"US",
    "sg:address":"15849 N 71st St",
    "sg:city":"Scottsdale",
    "sg:classifiers":[
        {
            "category":"Professional",
            "subcategory":"Management & Consulting",
            "type":"Services"
        }
    ],
    "sg:phone":"+1 480 281 1550",
    "sg:postcode":"85254",
    "sg:province":"AZ",
    "sg:tags":[
        "consultant"
    ],
    "wof:name":"Crippen Consulting Group",
    "wof:placetype":"venue"
},
  "geometry": {"coordinates":[-111.927696,33.632737],"type":"Point"}
}