{
  "type": "Feature",
  "properties": {
    "iso:country":"US",
    "sg:address":"2832 N 69th St",
    "sg:city":"Scottsdale",
    "sg:classifiers":[
        {
            "category":"Organizations",
            "subcategory":"Religious Organization",
            "type":"Services"
        }
    ],
    "sg:phone":"+1 480 994 3459",
    "sg:postcode":"85257",
    "sg:province":"AZ",
    "sg:tags":[
        "church"
    ],
    "wof:name":"Church Of Jesus Christ Of Lds",
    "wof:placetype":"venue"
},
  "geometry": {"coordinates":[-111.931935,33.478714],"type":"Point"}
}