{
  "type": "Feature",
  "properties": {
    "addr:full":"7150 E 22nd St Tucson AZ 85710",
    "addr:housenumber":"7150",
    "addr:postcode":"85710",
    "addr:street":"E 22Nd St",
    "iso:country":"US",
    "sg:address":"7150 E 22nd St",
    "sg:city":"Tucson",
    "sg:phone":"+1 520 296 8535",
    "sg:postcode":"85710",
    "sg:province":"AZ",
    "wof:name":"Desert Toyota Scion",
    "wof:placetype":"venue"
},
  "geometry": {"coordinates":[-110.83981199999999,32.206409],"type":"Point"}
}