{
  "type": "Feature",
  "properties": {
    "addr:full":"10 Tubac Rd Tumacacori AZ 85646",
    "addr:housenumber":"10",
    "addr:postcode":"85646",
    "addr:street":"Tubac Rd",
    "iso:country":"US",
    "sg:address":"10 Tubac Rd",
    "sg:city":"Tumacacori",
    "sg:classifiers":[
        {
            "category":"Shopping",
            "type":"Retail Goods"
        }
    ],
    "sg:phone":"+1 520 398 2070",
    "sg:postcode":"85646",
    "sg:province":"AZ",
    "sg:tags":[
        "miscellaneous",
        "store"
    ],
    "wof:name":"Beads Of Tubac",
    "wof:placetype":"venue"
},
  "geometry": {"coordinates":[-111.05128499999999,31.61234],"type":"Point"}
}