{
  "type": "Feature",
  "properties": {
    "iso:country":"US",
    "sg:address":"4208 W Villa Linda Dr",
    "sg:city":"Glendale",
    "sg:classifiers":[
        {
            "category":"Shopping",
            "subcategory":"Clothing, Apparel, & Fashions",
            "type":"Retail Goods"
        }
    ],
    "sg:phone":"+1 623 434 0854",
    "sg:postcode":"85310",
    "sg:province":"AZ",
    "wof:name":"Goya Athletic Wear",
    "wof:placetype":"venue"
},
  "geometry": {"coordinates":[-112.150111,33.71226],"type":"Point"}
}