{
  "type": "Feature",
  "properties": {
    "iso:country":"US",
    "sg:address":"573 E Fry Blvd",
    "sg:city":"Sierra Vista",
    "sg:classifiers":[
        {
            "category":"Shopping",
            "subcategory":"Tobacco",
            "type":"Retail Goods"
        }
    ],
    "sg:phone":"+1 520 417 2029",
    "sg:postcode":"85635",
    "sg:province":"AZ",
    "sg:tags":[
        "cigarette",
        "cigar",
        "dealer"
    ],
    "wof:name":"Glass Bottom Smoke Emporium",
    "wof:placetype":"venue"
},
  "geometry": {"coordinates":[-110.293838,31.554716],"type":"Point"}
}