{
  "type": "Feature",
  "properties": {
    "addr:full":"1442 E Glendale Ave Phoenix AZ 85020",
    "addr:housenumber":"1442",
    "addr:postcode":"85020",
    "addr:street":"E Glendale Ave",
    "iso:country":"US",
    "sg:address":"1442 E Glendale Ave",
    "sg:city":"Phoenix",
    "sg:classifiers":[
        {
            "category":"Insurance",
            "subcategory":"Insurance Agent",
            "type":"Services"
        }
    ],
    "sg:phone":"+1 602 943 1463",
    "sg:postcode":"85020",
    "sg:province":"AZ",
    "wof:name":"Denzil F Marley",
    "wof:placetype":"venue"
},
  "geometry": {"coordinates":[-112.050999,33.538299],"type":"Point"}
}