{
  "type": "Feature",
  "properties": {
    "addr:full":"15850 S 29th St Phoenix AZ 85048",
    "addr:housenumber":"15850",
    "addr:postcode":"85048",
    "addr:street":"S 29Th St",
    "iso:country":"US",
    "sg:address":"15850 S 29th St",
    "sg:city":"Phoenix",
    "sg:classifiers":[
        {
            "category":"Wholesale",
            "subcategory":"Electrical",
            "type":"Manufacturing & Wholesale Goods"
        }
    ],
    "sg:phone":"+1 480 768 1118",
    "sg:postcode":"85048",
    "sg:province":"AZ",
    "sg:tags":[
        "control",
        "security",
        "system"
    ],
    "wof:name":"Compass Fire & Security",
    "wof:placetype":"venue"
},
  "geometry": {"coordinates":[-112.02009200000001,33.301761],"type":"Point"}
}