{
  "type": "Feature",
  "properties": {
    "addr:full":"4245 N Craftsmans Ct Scottsdale AZ 85251",
    "addr:housenumber":"4245",
    "addr:postcode":"85251",
    "addr:street":"N Craftsmans Ct",
    "iso:country":"US",
    "sg:address":"4245 N Craftsmans Ct",
    "sg:city":"Scottsdale",
    "sg:classifiers":[
        {
            "category":"Bars & Pubs",
            "type":"Food & Drink"
        }
    ],
    "sg:phone":"+1 480 990 7111",
    "sg:postcode":"85251",
    "sg:province":"AZ",
    "sg:website":"www.acmebar.com",
    "wof:name":"Acme Bar & Grill",
    "wof:placetype":"venue"
},
  "geometry": {"coordinates":[-111.92765199999999,33.496845],"type":"Point"}
}