{
  "type": "Feature",
  "properties": {
    "addr:full":"124 N Montezuma St Prescott AZ 86301",
    "addr:housenumber":"124",
    "addr:postcode":"86301",
    "addr:street":"N Montezuma St",
    "iso:country":"US",
    "sg:address":"124 N Montezuma St",
    "sg:city":"Prescott",
    "sg:classifiers":[
        {
            "category":"Restaurant",
            "type":"Food & Drink"
        }
    ],
    "sg:phone":"+1 928 541 1400",
    "sg:postcode":"86301",
    "sg:province":"AZ",
    "sg:website":"www.fourcornersrestaurant.com",
    "wof:name":"N'Awlins On Montezuma",
    "wof:placetype":"venue"
},
  "geometry": {"coordinates":[-112.470169,34.543361],"type":"Point"}
}