{
  "type": "Feature",
  "properties": {
    "iso:country":"US",
    "sg:address":"8310 W Daley Ln",
    "sg:city":"Peoria",
    "sg:classifiers":[
        {
            "category":"Manufacturing",
            "subcategory":"Electronics",
            "type":"Manufacturing & Wholesale Goods"
        }
    ],
    "sg:phone":"+1 623 362 1620",
    "sg:postcode":"85383",
    "sg:province":"AZ",
    "sg:tags":[
        "equipment",
        "mfg",
        "home"
    ],
    "wof:name":"Music Wholesalers Inc",
    "wof:placetype":"venue"
},
  "geometry": {"coordinates":[-112.24182,33.690843],"type":"Point"}
}