{
  "type": "Feature",
  "properties": {
    "iso:country":"US",
    "sg:address":"3560 N Stone Ave",
    "sg:city":"Tucson",
    "sg:classifiers":[
        {
            "category":"Home & Garden",
            "subcategory":"Furniture",
            "type":"Retail Goods"
        }
    ],
    "sg:phone":"+1 520 887 7004",
    "sg:postcode":"85705",
    "sg:province":"AZ",
    "wof:name":"Old Stone Trading Co",
    "wof:placetype":"venue"
},
  "geometry": {"coordinates":[-110.972019,32.271557],"type":"Point"}
}