{
  "type": "Feature",
  "properties": {
    "iso:country":"US",
    "sg:address":"1202 S Laguna Ave",
    "sg:city":"Parker",
    "sg:classifiers":[
        {
            "category":"Insurance",
            "subcategory":"Insurance Agent",
            "type":"Services"
        }
    ],
    "sg:phone":"+1 928 669 9999",
    "sg:postcode":"85344",
    "sg:province":"AZ",
    "wof:name":"Maura's Insurance LLC",
    "wof:placetype":"venue"
},
  "geometry": {"coordinates":[-114.29166499999999,34.146788],"type":"Point"}
}