{
  "type": "Feature",
  "properties": {
    "addr:full":"5036 E Golder Ranch Rd Tucson AZ 85739",
    "addr:housenumber":"5036",
    "addr:postcode":"85739",
    "addr:street":"E Golder Ranch Rd",
    "iso:country":"US",
    "sg:address":"5036 E Golder Ranch Rd",
    "sg:city":"Tucson",
    "sg:classifiers":[
        {
            "category":"Professional",
            "subcategory":"Research",
            "type":"Services"
        }
    ],
    "sg:phone":"+1 520 825 3536",
    "sg:postcode":"85739",
    "sg:province":"AZ",
    "sg:tags":[
        "archaeologist"
    ],
    "wof:name":"PAST",
    "wof:placetype":"venue"
},
  "geometry": {"coordinates":[-110.88498800000001,32.476563],"type":"Point"}
}