{
  "type": "Feature",
  "properties": {
    "iso:country":"US",
    "sg:address":"632 W Greentree Dr",
    "sg:city":"Chandler",
    "sg:classifiers":[
        {
            "category":"Building & Trades",
            "subcategory":"Construction",
            "type":"Services"
        }
    ],
    "sg:phone":"+1 480 963 2132",
    "sg:postcode":"85225",
    "sg:province":"AZ",
    "sg:tags":[
        "excavation",
        "contractor"
    ],
    "wof:name":"Hampton Backhoe Service",
    "wof:placetype":"venue"
},
  "geometry": {"coordinates":[-111.851884,33.331113],"type":"Point"}
}