{
  "type": "Feature",
  "properties": {
    "iso:country":"US",
    "sg:address":"5245 E Washington St",
    "sg:city":"Phoenix",
    "sg:classifiers":[
        {
            "category":"Retail",
            "subcategory":"Auto Repair",
            "type":"Services"
        }
    ],
    "sg:phone":"+1 602 225 9102",
    "sg:postcode":"85034",
    "sg:province":"AZ",
    "sg:tags":[
        "repairing",
        "automobile"
    ],
    "wof:name":"Damien Auto Repair & Towing",
    "wof:placetype":"venue"
},
  "geometry": {"coordinates":[-111.968773,33.446222],"type":"Point"}
}