{
  "type": "Feature",
  "properties": {
    "iso:country":"US",
    "sg:address":"3628 N 69th Ave",
    "sg:city":"Phoenix",
    "sg:classifiers":[
        {
            "category":"Building & Trades",
            "subcategory":"Locksmith",
            "type":"Services"
        }
    ],
    "sg:phone":"+1 623 476 4974",
    "sg:postcode":"85033",
    "sg:province":"AZ",
    "sg:tags":[
        "key"
    ],
    "wof:name":"Available Emergency A Locksmith",
    "wof:placetype":"venue"
},
  "geometry": {"coordinates":[-112.207714,33.49024],"type":"Point"}
}