{
  "type": "Feature",
  "properties": {
    "iso:country":"US",
    "sg:address":"211 W Monroe St",
    "sg:city":"Phoenix",
    "sg:classifiers":[
        {
            "category":"Wholesale",
            "subcategory":"Machinery & Supplies",
            "type":"Manufacturing & Wholesale Goods"
        }
    ],
    "sg:phone":"+1 602 253 3667",
    "sg:postcode":"85003",
    "sg:province":"AZ",
    "sg:tags":[
        "valve"
    ],
    "wof:name":"Capital Westward Systems & Controls",
    "wof:placetype":"venue"
},
  "geometry": {"coordinates":[-112.076554,33.450359],"type":"Point"}
}