{
  "type": "Feature",
  "properties": {
    "iso:country":"US",
    "sg:address":"230 W Continental Rd",
    "sg:city":"Green Valley",
    "sg:classifiers":[
        {
            "category":"Shopping",
            "subcategory":"Musical Instruments",
            "type":"Retail Goods"
        }
    ],
    "sg:phone":"+1 520 399 2648",
    "sg:postcode":"85614",
    "sg:province":"AZ",
    "wof:name":"Fletcher Organs Studios",
    "wof:placetype":"venue"
},
  "geometry": {"coordinates":[-110.996011,31.851602],"type":"Point"}
}