{
  "type": "Feature",
  "properties": {
    "iso:country":"US",
    "sg:address":"4908 E McDowell Rd",
    "sg:city":"Phoenix",
    "sg:classifiers":[
        {
            "category":"Manufacturing",
            "subcategory":"Paper Products",
            "type":"Manufacturing & Wholesale Goods"
        }
    ],
    "sg:phone":"+1 602 220 0005",
    "sg:postcode":"85008",
    "sg:province":"AZ",
    "sg:tags":[
        "pr",
        "adhesive",
        "mfg",
        "sensitive",
        "pressure",
        "health",
        "tape",
        "care"
    ],
    "wof:name":"3m",
    "wof:placetype":"venue"
},
  "geometry": {"coordinates":[-111.975936,33.465711],"type":"Point"}
}