{
  "type": "Feature",
  "properties": {
    "addr:full":"3285 E 44th St Tucson AZ 85713",
    "addr:housenumber":"3285",
    "addr:postcode":"85713",
    "addr:street":"E 44Th St",
    "iso:country":"US",
    "sg:address":"3285 E 44th St",
    "sg:city":"Tucson",
    "sg:classifiers":[
        {
            "category":"Retail",
            "subcategory":"Repair Shop",
            "type":"Services"
        }
    ],
    "sg:phone":"+1 520 623 8681",
    "sg:postcode":"85713",
    "sg:province":"AZ",
    "sg:tags":[
        "equipment",
        "hydraulic"
    ],
    "sg:website":"www.roadmachinery.com",
    "wof:name":"ROAD Machinery",
    "wof:placetype":"venue"
},
  "geometry": {"coordinates":[-110.926104,32.184419],"type":"Point"}
}