{
  "type": "Feature",
  "properties": {
    "iso:country":"US",
    "sg:address":"42029 N Anthem Heights Dr",
    "sg:city":"Phoenix",
    "sg:classifiers":[
        {
            "category":"Building & Trades",
            "subcategory":"Electrical",
            "type":"Services"
        }
    ],
    "sg:phone":"+1 623 879 2120",
    "sg:postcode":"85086",
    "sg:province":"AZ",
    "sg:tags":[
        "system",
        "home",
        "integrated",
        "contractor"
    ],
    "wof:name":"Bolt Security & Sound",
    "wof:placetype":"venue"
},
  "geometry": {"coordinates":[-112.116407,33.867259],"type":"Point"}
}