{
  "type": "Feature",
  "properties": {
    "addr:full":"4413 E Broadway Blvd Tucson AZ 85711",
    "addr:housenumber":"4413",
    "addr:postcode":"85711",
    "addr:street":"E Broadway Blvd",
    "iso:country":"US",
    "sg:address":"4413 E Broadway Blvd",
    "sg:city":"Tucson",
    "sg:classifiers":[
        {
            "category":"Personal",
            "subcategory":"Beauty Salon",
            "type":"Services"
        }
    ],
    "sg:phone":"+1 520 881 4470",
    "sg:postcode":"85711",
    "sg:province":"AZ",
    "wof:name":"Accent Salon Of Beauty",
    "wof:placetype":"venue"
},
  "geometry": {"coordinates":[-110.89680199999999,32.221579],"type":"Point"}
}