{
  "type": "Feature",
  "properties": {
    "iso:country":"US",
    "sg:address":"6502 N Villa Manana Dr",
    "sg:city":"Phoenix",
    "sg:classifiers":[
        {
            "category":"Banks & Credit Unions",
            "subcategory":"Financial Services",
            "type":"Services"
        }
    ],
    "sg:phone":"+1 602 265 3704",
    "sg:postcode":"85014",
    "sg:province":"AZ",
    "sg:tags":[
        "card-merchant"
    ],
    "sg:website":"http://www.americanexpress.com",
    "wof:name":"American Express",
    "wof:placetype":"venue"
},
  "geometry": {"coordinates":[-112.05873099999999,33.530994],"type":"Point"}
}