{
  "type": "Feature",
  "properties": {
    "addr:full":"11201 N el Mirage Rd El Mirage AZ 85335",
    "addr:housenumber":"11201",
    "addr:postcode":"85335",
    "addr:street":"N El Mirage Rd",
    "iso:country":"US",
    "sg:address":"11201 N el Mirage Rd",
    "sg:city":"El Mirage",
    "sg:classifiers":[
        {
            "category":"Real Estate",
            "subcategory":"Real Estate Agent",
            "type":"Services"
        },
        {
            "category":"Home & Garden",
            "subcategory":"Mobile Homes",
            "type":"Retail Goods"
        }
    ],
    "sg:phone":"+1 602 214 5997",
    "sg:postcode":"85335",
    "sg:province":"AZ",
    "wof:name":"Leisure Home Sales LLC",
    "wof:placetype":"venue"
},
  "geometry": {"coordinates":[-112.324474,33.5859],"type":"Point"}
}