{
  "type": "Feature",
  "properties": {
    "iso:country":"US",
    "sg:address":"1001 S 4th Ave",
    "sg:city":"Yuma",
    "sg:classifiers":[
        {
            "category":"Home & Garden",
            "subcategory":"Carpets & Floor Coverings",
            "type":"Retail Goods"
        }
    ],
    "sg:phone":"+1 928 783 5085",
    "sg:postcode":"85364",
    "sg:province":"AZ",
    "sg:tags":[
        "tile"
    ],
    "wof:name":"Johnnys Carpet Warehouse",
    "wof:placetype":"venue"
},
  "geometry": {"coordinates":[-114.624663,32.707575],"type":"Point"}
}