{
  "type": "Feature",
  "properties": {
    "iso:country":"US",
    "sg:address":"2347 N Grand Ave",
    "sg:city":"Nogales",
    "sg:classifiers":[
        {
            "category":"Retail",
            "subcategory":"Auto Rental",
            "type":"Services"
        }
    ],
    "sg:phone":"+1 520 377 2901",
    "sg:postcode":"85621",
    "sg:province":"AZ",
    "sg:tags":[
        "renting",
        "truck",
        "leasing"
    ],
    "wof:name":"U-Haul Co",
    "wof:placetype":"venue"
},
  "geometry": {"coordinates":[-110.932236,31.371437],"type":"Point"}
}