{
  "type": "Feature",
  "properties": {
    "iso:country":"US",
    "sg:address":"203 W Adams St",
    "sg:city":"Phoenix",
    "sg:classifiers":[
        {
            "category":"Arts & Performance",
            "subcategory":"Theater",
            "type":"Entertainment"
        }
    ],
    "sg:phone":"+1 602 952 2881",
    "sg:postcode":"85003",
    "sg:province":"AZ",
    "wof:name":"Theater League Inc",
    "wof:placetype":"venue"
},
  "geometry": {"coordinates":[-112.077638,33.449224],"type":"Point"}
}