{
  "type": "Feature",
  "properties": {
    "addr:full":"2727 E Cactus Rd Phoenix AZ 85032",
    "addr:housenumber":"2727",
    "addr:postcode":"85032",
    "addr:street":"E Cactus Rd",
    "iso:country":"US",
    "sg:address":"2727 E Cactus Rd",
    "sg:city":"Phoenix",
    "sg:classifiers":[
        {
            "category":"Organizations",
            "subcategory":"Religious Organization",
            "type":"Services"
        }
    ],
    "sg:phone":"+1 602 971 6010",
    "sg:postcode":"85032",
    "sg:province":"AZ",
    "sg:tags":[
        "church"
    ],
    "wof:name":"Paradise Valley Seventh Day",
    "wof:placetype":"venue"
},
  "geometry": {"coordinates":[-112.023589,33.596771],"type":"Point"}
}