{
  "type": "Feature",
  "properties": {
    "addr:full":"25 Last Wagon Cir Sedona AZ 86336",
    "addr:housenumber":"25",
    "addr:postcode":"86336",
    "addr:street":"Last Wagon Cir",
    "iso:country":"US",
    "sg:address":"25 Last Wagon Cir",
    "sg:city":"Sedona",
    "sg:classifiers":[
        {
            "category":"Utilities",
            "subcategory":"Telephone",
            "type":"Services"
        }
    ],
    "sg:phone":"+1 928 203 0444",
    "sg:postcode":"86336",
    "sg:province":"AZ",
    "sg:tags":[
        "communications"
    ],
    "wof:name":"Black Jade Arena",
    "wof:placetype":"venue"
},
  "geometry": {"coordinates":[-111.791893,34.86837],"type":"Point"}
}