{
  "type": "Feature",
  "properties": {
    "iso:country":"US",
    "sg:address":"5432 W Apollo Rd",
    "sg:city":"Laveen",
    "sg:classifiers":[
        {
            "category":"Wholesale",
            "subcategory":"Medical Equipment & Supplies",
            "type":"Manufacturing & Wholesale Goods"
        },
        {
            "category":"Retail",
            "subcategory":"Repair Shop",
            "type":"Services"
        }
    ],
    "sg:phone":"+1 602 253 3020",
    "sg:postcode":"85339",
    "sg:province":"AZ",
    "sg:tags":[
        "physician",
        "surgeon",
        "refinishing",
        "equipment-repairing"
    ],
    "wof:name":"Eclectech",
    "wof:placetype":"venue"
},
  "geometry": {"coordinates":[-112.174905,33.386169],"type":"Point"}
}