{
  "type": "Feature",
  "properties": {
    "iso:country":"US",
    "sg:address":"606 S Plumer Ave",
    "sg:city":"Tucson",
    "sg:classifiers":[
        {
            "category":"Building & Trades",
            "subcategory":"Construction",
            "type":"Services"
        }
    ],
    "sg:phone":"+1 520 670 0070",
    "sg:postcode":"85719",
    "sg:province":"AZ",
    "sg:tags":[
        "carpenter"
    ],
    "wof:name":"S W Reg Council Of Carpenters",
    "wof:placetype":"venue"
},
  "geometry": {"coordinates":[-110.939493,32.213315],"type":"Point"}
}