{
  "type": "Feature",
  "properties": {
    "iso:country":"US",
    "sg:address":"8214 W Indian School Rd",
    "sg:city":"Phoenix",
    "sg:classifiers":[
        {
            "category":"Banks & Credit Unions",
            "subcategory":"Bank",
            "type":"Services"
        }
    ],
    "sg:phone":"+1 623 846 4084",
    "sg:postcode":"85033",
    "sg:province":"AZ",
    "sg:tags":[
        "cashing",
        "check"
    ],
    "wof:name":"Rapid Cash",
    "wof:placetype":"venue"
},
  "geometry": {"coordinates":[-112.237438,33.494365],"type":"Point"}
}