{
  "type": "Feature",
  "properties": {
    "iso:country":"US",
    "sg:address":"1967 Cliffrose Dr",
    "sg:city":"Lake Havasu City",
    "sg:classifiers":[
        {
            "category":"Shopping",
            "subcategory":"Gifts & Souvenirs",
            "type":"Retail Goods"
        }
    ],
    "sg:phone":"+1 928 505 5120",
    "sg:postcode":"86403",
    "sg:province":"AZ",
    "wof:name":"Bear Track & Gallery",
    "wof:placetype":"venue"
},
  "geometry": {"coordinates":[-114.331682,34.472753],"type":"Point"}
}