{
  "type": "Feature",
  "properties": {
    "iso:country":"US",
    "sg:address":"5240 W Cactus Rd",
    "sg:city":"Glendale",
    "sg:classifiers":[
        {
            "category":"Freight",
            "type":"Transportation"
        }
    ],
    "sg:phone":"+1 602 285 1899",
    "sg:postcode":"85029",
    "sg:province":"AZ",
    "sg:tags":[
        "commercial",
        "storage",
        "special"
    ],
    "wof:name":"Central Self Storage",
    "wof:placetype":"venue"
},
  "geometry": {"coordinates":[-112.17249099999999,33.596416],"type":"Point"}
}