{
  "type": "Feature",
  "properties": {
    "iso:country":"US",
    "sg:address":"3402 E Shangri la Rd",
    "sg:city":"Phoenix",
    "sg:classifiers":[
        {
            "category":"Organizations",
            "subcategory":"Community Association",
            "type":"Services"
        }
    ],
    "sg:phone":"+1 602 371 6036",
    "sg:postcode":"85028",
    "sg:province":"AZ",
    "wof:name":"Arizona Public Service Operations",
    "wof:placetype":"venue"
},
  "geometry": {"coordinates":[-112.007718,33.588405],"type":"Point"}
}