{
  "type": "Feature",
  "properties": {
    "iso:country":"US",
    "sg:address":"1251 N Industrial Park Ave",
    "sg:city":"Nogales",
    "sg:classifiers":[
        {
            "category":"Freight",
            "type":"Transportation"
        }
    ],
    "sg:phone":"+1 520 281 1777",
    "sg:postcode":"85621",
    "sg:province":"AZ",
    "sg:tags":[
        "trucking"
    ],
    "wof:name":"Alzua Inc",
    "wof:placetype":"venue"
},
  "geometry": {"coordinates":[-110.958842,31.352717],"type":"Point"}
}