{
  "type": "Feature",
  "properties": {
    "addr:full":"2526 E Camelback Rd Phoenix AZ 85016",
    "addr:housenumber":"2526",
    "addr:postcode":"85016",
    "addr:street":"E Camelback Rd",
    "iso:country":"US",
    "sg:address":"2526 E Camelback Rd",
    "sg:city":"Phoenix",
    "sg:classifiers":[
        {
            "category":"Shopping",
            "subcategory":"Clothing, Apparel, & Fashions",
            "type":"Retail Goods"
        }
    ],
    "sg:phone":"+1 602 778 9050",
    "sg:postcode":"85016",
    "sg:province":"AZ",
    "sg:website":"www.betsyjohnson.com",
    "wof:name":"Betsey Johnson's",
    "wof:placetype":"venue"
},
  "geometry": {"coordinates":[-112.028763,33.509435],"type":"Point"}
}