{
  "type": "Feature",
  "properties": {
    "iso:country":"US",
    "sg:address":"10227 N 32nd Ln",
    "sg:city":"Phoenix",
    "sg:classifiers":[
        {
            "category":"Building & Trades",
            "subcategory":"Cleaning & Sanitation",
            "type":"Services"
        }
    ],
    "sg:phone":"+1 602 992 1401",
    "sg:postcode":"85051",
    "sg:province":"AZ",
    "sg:tags":[
        "janitor"
    ],
    "wof:name":"Castaways Janitorial & Carpet",
    "wof:placetype":"venue"
},
  "geometry": {"coordinates":[-112.128868,33.578475],"type":"Point"}
}