{
  "type": "Feature",
  "properties": {
    "iso:country":"US",
    "sg:address":"8000 E Hardy St",
    "sg:city":"Tucson",
    "sg:classifiers":[
        {
            "category":"Building & Trades",
            "subcategory":"Construction",
            "type":"Services"
        }
    ],
    "sg:phone":"+1 520 751 0092",
    "sg:postcode":"85750",
    "sg:province":"AZ",
    "sg:tags":[
        "contractor"
    ],
    "wof:name":"Tabcon Builders",
    "wof:placetype":"venue"
},
  "geometry": {"coordinates":[-110.822676,32.267785],"type":"Point"}
}