{
  "type": "Feature",
  "properties": {
    "addr:full":"7724 N 67th Ave Glendale AZ 85301",
    "addr:housenumber":"7724",
    "addr:postcode":"85301",
    "addr:street":"N 67Th Ave",
    "iso:country":"US",
    "sg:address":"7724 N 67th Ave",
    "sg:city":"Glendale",
    "sg:classifiers":[
        {
            "category":"Building & Trades",
            "subcategory":"Construction",
            "type":"Services"
        }
    ],
    "sg:phone":"+1 623 934 2060",
    "sg:postcode":"85301",
    "sg:province":"AZ",
    "sg:tags":[
        "house"
    ],
    "wof:name":"Advance Pool Remodeling",
    "wof:placetype":"venue"
},
  "geometry": {"coordinates":[-112.20308,33.54879],"type":"Point"}
}