{
  "type": "Feature",
  "properties": {
    "iso:country":"US",
    "sg:address":"2720 E Thomas Rd",
    "sg:city":"Phoenix",
    "sg:classifiers":[
        {
            "category":"Insurance",
            "subcategory":"Insurance Agent",
            "type":"Services"
        },
        {
            "category":"Banks & Credit Unions",
            "subcategory":"Financial Services",
            "type":"Services"
        }
    ],
    "sg:phone":"+1 602 368 4035",
    "sg:postcode":"85016",
    "sg:province":"AZ",
    "sg:tags":[
        "counseling",
        "debt",
        "adjuster"
    ],
    "wof:name":"Infiniti Debt Solutions",
    "wof:placetype":"venue"
},
  "geometry": {"coordinates":[-112.023273,33.480391],"type":"Point"}
}