{
  "type": "Feature",
  "properties": {
    "iso:country":"US",
    "sg:address":"1834 N Desmond Ln",
    "sg:city":"Tucson",
    "sg:classifiers":[
        {
            "category":"Building & Trades",
            "subcategory":"Construction",
            "type":"Services"
        }
    ],
    "sg:phone":"+1 520 440 7644",
    "sg:postcode":"85712",
    "sg:province":"AZ",
    "sg:tags":[
        "maintenance",
        "contractor"
    ],
    "wof:name":"Aaron's Handyman Svc",
    "wof:placetype":"venue"
},
  "geometry": {"coordinates":[-110.905528,32.24419],"type":"Point"}
}