{
  "type": "Feature",
  "properties": {
    "iso:country":"US",
    "sg:address":"3027 E Pine Dr",
    "sg:city":"Flagstaff",
    "sg:classifiers":[
        {
            "category":"Building & Trades",
            "subcategory":"Construction",
            "type":"Services"
        }
    ],
    "sg:phone":"+1 928 526 4425",
    "sg:postcode":"86004",
    "sg:province":"AZ",
    "sg:tags":[
        "masonry",
        "contractor"
    ],
    "wof:name":"Big T Masonry Inc",
    "wof:placetype":"venue"
},
  "geometry": {"coordinates":[-111.60378900000001,35.213928],"type":"Point"}
}