{
  "type": "Feature",
  "properties": {
    "iso:country":"US",
    "sg:address":"1605 E Adams St",
    "sg:city":"Phoenix",
    "sg:classifiers":[
        {
            "category":"Autos & Motor Vehicles",
            "subcategory":"Auto Supplies",
            "type":"Retail Goods"
        }
    ],
    "sg:phone":"+1 602 252 4119",
    "sg:postcode":"85034",
    "sg:province":"AZ",
    "sg:tags":[
        "upholstery-wholesale",
        "upholstery",
        "automobile",
        "top",
        "covers",
        "seat",
        "manufacturer"
    ],
    "sg:website":"http://www.yogisupholstery.com",
    "wof:name":"Yogis Upholstery",
    "wof:placetype":"venue"
},
  "geometry": {"coordinates":[-112.047722,33.449452],"type":"Point"}
}