{
  "type": "Feature",
  "properties": {
    "iso:country":"US",
    "sg:address":"701 W Las Palmaritas Dr",
    "sg:city":"Phoenix",
    "sg:classifiers":[
        {
            "category":"Building & Trades",
            "subcategory":"Construction",
            "type":"Services"
        }
    ],
    "sg:phone":"+1 602 944 8954",
    "sg:postcode":"85021",
    "sg:province":"AZ",
    "sg:tags":[
        "tile",
        "dealer"
    ],
    "wof:name":"Ike Dunshee Ceramic Tile Inc",
    "wof:placetype":"venue"
},
  "geometry": {"coordinates":[-112.084002,33.557922],"type":"Point"}
}