{
  "type": "Feature",
  "properties": {
    "iso:country":"US",
    "sg:address":"505 W Parkway Blvd",
    "sg:city":"Tempe",
    "sg:classifiers":[
        {
            "category":"Communications",
            "subcategory":"Film & Video Production",
            "type":"Services"
        },
        {
            "category":"Communications",
            "subcategory":"Radio Station",
            "type":"Services"
        }
    ],
    "sg:phone":"+1 480 968 6565",
    "sg:postcode":"85281",
    "sg:province":"AZ",
    "sg:tags":[
        "picture",
        "medium",
        "motion",
        "broker"
    ],
    "wof:name":"4tv Media",
    "wof:placetype":"venue"
},
  "geometry": {"coordinates":[-111.945241,33.413159],"type":"Point"}
}