{
  "type": "Feature",
  "properties": {
    "iso:country":"US",
    "sg:address":"3961 E Chandler Blvd Ste 102",
    "sg:city":"Phoenix",
    "sg:classifiers":[
        {
            "category":"Personal",
            "subcategory":"Beauty Salon",
            "type":"Services"
        },
        {
            "category":"Personal",
            "subcategory":"Nail Salon",
            "type":"Services"
        }
    ],
    "sg:phone":"+1 480 704 8300",
    "sg:postcode":"85048",
    "sg:province":"AZ",
    "wof:name":"Ahwatukee Nail Spa",
    "wof:placetype":"venue"
},
  "geometry": {"coordinates":[-111.998625,33.305119],"type":"Point"}
}