{
  "type": "Feature",
  "properties": {
    "addr:full":"1501 W Bethany Home Rd Phoenix AZ 85015",
    "addr:housenumber":"1501",
    "addr:postcode":"85015",
    "addr:street":"W Bethany Home Rd",
    "iso:country":"US",
    "sg:address":"1501 W Bethany Home Rd",
    "sg:city":"Phoenix",
    "sg:classifiers":[
        {
            "category":"Restaurant",
            "type":"Food & Drink"
        }
    ],
    "sg:menulink":"http://www.allmenus.com/az/phoenix/104493-hometown-buffet/menu/",
    "sg:phone":"+1 602 242 5882",
    "sg:postcode":"85015",
    "sg:province":"AZ",
    "sg:tags":[
        "new",
        "american"
    ],
    "wof:name":"Hometown Buffet",
    "wof:placetype":"venue"
},
  "geometry": {"coordinates":[-112.092534,33.524004],"type":"Point"}
}