{
  "type": "Feature",
  "properties": {
    "addr:full":"10507 W Zak Rd Tolleson AZ 85353",
    "addr:housenumber":"10507",
    "addr:postcode":"85353",
    "addr:street":"W Zak Rd",
    "iso:country":"US",
    "sg:address":"10507 W Zak Rd",
    "sg:city":"Tolleson",
    "sg:classifiers":[
        {
            "category":"Real Estate",
            "subcategory":"Real Estate Services",
            "type":"Services"
        },
        {
            "category":"Building & Trades",
            "subcategory":"Cleaning & Sanitation",
            "type":"Services"
        }
    ],
    "sg:phone":"+1 623 340 1810",
    "sg:postcode":"85353",
    "sg:province":"AZ",
    "sg:tags":[
        "maintenance",
        "cleaners-interior"
    ],
    "wof:name":"Teresa Cleaning Service",
    "wof:placetype":"venue"
},
  "geometry": {"coordinates":[-112.285629,33.42456],"type":"Point"}
}