{
  "type": "Feature",
  "properties": {
    "addr:full":"315 W Elliot Rd Tempe AZ 85284",
    "addr:housenumber":"315",
    "addr:postcode":"85284",
    "addr:street":"W Elliot Rd",
    "iso:country":"US",
    "sg:address":"315 W Elliot Rd",
    "sg:city":"Tempe",
    "sg:classifiers":[
        {
            "category":"Banks & Credit Unions",
            "subcategory":"Bank",
            "type":"Services"
        }
    ],
    "sg:phone":"+1 480 755 0987",
    "sg:postcode":"85284",
    "sg:province":"AZ",
    "sg:tags":[
        "cashing",
        "check"
    ],
    "wof:name":"Check Into Cash",
    "wof:placetype":"venue"
},
  "geometry": {"coordinates":[-111.950025,33.349105],"type":"Point"}
}