{
  "type": "Feature",
  "properties": {
    "addr:full":"1337 W Mckinley St Phoenix AZ 85007",
    "addr:housenumber":"1337",
    "addr:postcode":"85007",
    "addr:street":"W Mckinley St",
    "iso:country":"US",
    "sg:address":"1337 W Mckinley St",
    "sg:city":"Phoenix",
    "sg:classifiers":[
        {
            "category":"Education",
            "subcategory":"Library",
            "type":"Public Place"
        }
    ],
    "sg:phone":"+1 602 253 1861",
    "sg:postcode":"85007",
    "sg:province":"AZ",
    "wof:name":"Arizona Library Binding Co",
    "wof:placetype":"venue"
},
  "geometry": {"coordinates":[-112.08991,33.456893],"type":"Point"}
}