{
  "type": "Feature",
  "properties": {
    "addr:full":"350 W Thomas Rd Phoenix AZ 85013",
    "addr:housenumber":"350",
    "addr:postcode":"85013",
    "addr:street":"W Thomas Rd",
    "iso:country":"US",
    "sg:address":"350 W Thomas Rd",
    "sg:city":"Phoenix",
    "sg:classifiers":[
        {
            "category":"Health Services",
            "subcategory":"Hospital",
            "type":"Services"
        },
        {
            "category":"Community Center",
            "type":"Public Place"
        }
    ],
    "sg:phone":"+1 602 406 3000",
    "sg:postcode":"85013",
    "sg:province":"AZ",
    "sg:tags":[
        "medical"
    ],
    "sg:website":"http://www.stjosephs-phx.org",
    "wof:name":"St Josephs Hospital and Medical Center",
    "wof:placetype":"venue"
},
  "geometry": {"coordinates":[-112.07933,33.480311],"type":"Point"}
}