{
  "type": "Feature",
  "properties": {
    "iso:country":"US",
    "sg:address":"7661 E Gray Rd",
    "sg:city":"Scottsdale",
    "sg:classifiers":[
        {
            "category":"Building & Trades",
            "subcategory":"Construction",
            "type":"Services"
        }
    ],
    "sg:phone":"+1 480 889 7200",
    "sg:postcode":"85260",
    "sg:province":"AZ",
    "sg:tags":[
        "home",
        "builder"
    ],
    "wof:name":"Elite Homes",
    "wof:placetype":"venue"
},
  "geometry": {"coordinates":[-111.911186,33.612373],"type":"Point"}
}