{
  "type": "Feature",
  "properties": {
    "addr:full":"63701 E Saddlebrooke Blvd Tucson AZ 85739",
    "addr:housenumber":"63701",
    "addr:postcode":"85739",
    "addr:street":"E Saddlebrooke Blvd",
    "iso:country":"US",
    "sg:address":"63701 E Saddlebrooke Blvd",
    "sg:city":"Tucson",
    "sg:classifiers":[
        {
            "category":"Banks & Credit Unions",
            "subcategory":"Bank",
            "type":"Services"
        }
    ],
    "sg:phone":"+1 520 825 8285",
    "sg:postcode":"85739",
    "sg:province":"AZ",
    "wof:name":"Bank Of The West",
    "wof:placetype":"venue"
},
  "geometry": {"coordinates":[-110.88427799999999,32.535814],"type":"Point"}
}