{
  "type": "Feature",
  "properties": {
    "addr:full":"5308 S Heather Dr Tempe AZ 85283",
    "addr:housenumber":"5308",
    "addr:postcode":"85283",
    "addr:street":"S Heather Dr",
    "iso:country":"US",
    "sg:address":"5308 S Heather Dr",
    "sg:city":"Tempe",
    "sg:classifiers":[
        {
            "category":"Wholesale",
            "subcategory":"Home Furnishings",
            "type":"Manufacturing & Wholesale Goods"
        }
    ],
    "sg:phone":"+1 480 820 6294",
    "sg:postcode":"85283",
    "sg:province":"AZ",
    "wof:name":"Calloway Wholesale Flooring",
    "wof:placetype":"venue"
},
  "geometry": {"coordinates":[-111.910005,33.37515],"type":"Point"}
}