{
  "type": "Feature",
  "properties": {
    "iso:country":"US",
    "sg:address":"80 E Highland St",
    "sg:city":"Chandler",
    "sg:classifiers":[
        {
            "category":"Autos & Motor Vehicles",
            "subcategory":"Auto Supplies",
            "type":"Retail Goods"
        },
        {
            "category":"Military Area",
            "subcategory":"Naval Base",
            "type":"Public Place"
        },
        {
            "category":"Building & Trades",
            "subcategory":"Construction",
            "type":"Services"
        }
    ],
    "sg:phone":"+1 480 786 1516",
    "sg:postcode":"85225",
    "sg:province":"AZ",
    "sg:tags":[
        "automobile",
        "hitch",
        "equipment",
        "part",
        "accessory",
        "welder",
        "trailer",
        "utility"
    ],
    "sg:website":"http://www.lewishitches.com",
    "wof:name":"Lewis Hitches",
    "wof:placetype":"venue"
},
  "geometry": {"coordinates":[-111.840559,33.331489],"type":"Point"}
}