{
  "type": "Feature",
  "properties": {
    "addr:full":"9700 E Millmar Rd Tucson AZ 85730",
    "addr:housenumber":"9700",
    "addr:postcode":"85730",
    "addr:street":"E Millmar Rd",
    "iso:country":"US",
    "sg:address":"9700 E Millmar Rd",
    "sg:city":"Tucson",
    "sg:classifiers":[
        {
            "category":"Recreation",
            "subcategory":"Dog Park",
            "type":"Entertainment"
        },
        {
            "category":"Shopping",
            "subcategory":"Pets & Pet Supplies",
            "type":"Retail Goods"
        },
        {
            "category":"Retail",
            "subcategory":"Pet Boarding",
            "type":"Services"
        },
        {
            "category":"Retail",
            "subcategory":"Animal Services",
            "type":"Services"
        }
    ],
    "sg:phone":"+1 520 401 0700",
    "sg:postcode":"85730",
    "sg:province":"AZ",
    "sg:tags":[
        "training",
        "exercising",
        "kennel",
        "sitting"
    ],
    "wof:name":"Wolf Whisperer Dog Training",
    "wof:placetype":"venue"
},
  "geometry": {"coordinates":[-110.785538,32.17004],"type":"Point"}
}