{
  "type": "Feature",
  "properties": {
    "iso:country":"US",
    "sg:address":"10002 N 12th St",
    "sg:city":"Phoenix",
    "sg:classifiers":[
        {
            "category":"Recreation",
            "type":"Entertainment"
        }
    ],
    "sg:phone":"+1 602 997 7798",
    "sg:postcode":"85020",
    "sg:province":"AZ",
    "sg:tags":[
        "range",
        "baseball",
        "batting"
    ],
    "wof:name":"Bataway",
    "wof:placetype":"venue"
},
  "geometry": {"coordinates":[-112.056658,33.577343],"type":"Point"}
}