{
  "type": "Feature",
  "properties": {
    "iso:country":"US",
    "sg:address":"955 Kiowa Ave",
    "sg:city":"Lake Havasu City",
    "sg:classifiers":[
        {
            "category":"Building & Trades",
            "subcategory":"Construction",
            "type":"Services"
        }
    ],
    "sg:phone":"+1 928 855 0200",
    "sg:postcode":"86403",
    "sg:province":"AZ",
    "sg:tags":[
        "installation",
        "floor",
        "cover",
        "window",
        "tile",
        "carpet"
    ],
    "wof:name":"Fanning Cary Crpt Installation",
    "wof:placetype":"venue"
},
  "geometry": {"coordinates":[-114.354233,34.496933],"type":"Point"}
}