{
  "type": "Feature",
  "properties": {
    "iso:country":"US",
    "sg:address":"5825 W Peoria Ave",
    "sg:city":"Glendale",
    "sg:phone":"+1 623 915 2900",
    "sg:postcode":"85302",
    "sg:province":"AZ",
    "sg:website":"http://www.bostonmarket.com",
    "wof:name":"Boston Market - Catering Restaurants",
    "wof:placetype":"venue"
},
  "geometry": {"coordinates":[-112.184189,33.581848],"type":"Point"}
}