{
  "type": "Feature",
  "properties": {
    "addr:full":"201 W Sweetwater Ave Phoenix AZ 85029",
    "addr:housenumber":"201",
    "addr:postcode":"85029",
    "addr:street":"W Sweetwater Ave",
    "iso:country":"US",
    "sg:address":"201 W Sweetwater Ave",
    "sg:city":"Phoenix",
    "sg:classifiers":[
        {
            "category":"Real Estate",
            "subcategory":"Architect",
            "type":"Services"
        }
    ],
    "sg:phone":"+1 602 548 1549",
    "sg:postcode":"85029",
    "sg:province":"AZ",
    "wof:name":"Littler Associates Consulting",
    "wof:placetype":"venue"
},
  "geometry": {"coordinates":[-112.078577,33.604679],"type":"Point"}
}