{
  "type": "Feature",
  "properties": {
    "iso:country":"US",
    "sg:address":"1616 N 75th Ave",
    "sg:city":"Phoenix",
    "sg:classifiers":[
        {
            "category":"Restaurant",
            "type":"Food & Drink"
        }
    ],
    "sg:phone":"+1 623 247 4061",
    "sg:postcode":"85035",
    "sg:province":"AZ",
    "sg:tags":[
        "barbeque"
    ],
    "sg:website":"www.texasroadhouse.com",
    "wof:name":"Texas Roadhouse",
    "wof:placetype":"venue"
},
  "geometry": {"coordinates":[-112.221001,33.465698],"type":"Point"}
}