{
  "type": "Feature",
  "properties": {
    "iso:country":"US",
    "sg:address":"505 S Avenue A B",
    "sg:city":"Yuma",
    "sg:classifiers":[
        {
            "category":"Place Of Worship",
            "subcategory":"Church",
            "type":"Public Place"
        },
        {
            "category":"Place Of Worship",
            "type":"Public Place"
        }
    ],
    "sg:phone":"+1 928 782 7516",
    "sg:postcode":"85364",
    "sg:province":"AZ",
    "sg:tags":[
        "churches-catholic-traditional",
        "churches-catholic"
    ],
    "sg:website":"http://www.mhtparish.org",
    "wof:name":"Immaculate Conception Church",
    "wof:placetype":"venue"
},
  "geometry": {"coordinates":[-114.633232,32.717844],"type":"Point"}
}