{
  "type": "Feature",
  "properties": {
    "addr:full":"7539 W Peoria Ave Peoria AZ 85345",
    "addr:housenumber":"7539",
    "addr:postcode":"85345",
    "addr:street":"W Peoria Ave",
    "iso:country":"US",
    "sg:address":"7539 W Peoria Ave",
    "sg:city":"Peoria",
    "sg:classifiers":[
        {
            "category":"Restaurant",
            "type":"Food & Drink"
        }
    ],
    "sg:phone":"+1 623 878 8080",
    "sg:postcode":"85345",
    "sg:province":"AZ",
    "sg:tags":[
        "pizza"
    ],
    "sg:website":"www.papajohns.com",
    "wof:name":"Papa John's Pizza",
    "wof:placetype":"venue"
},
  "geometry": {"coordinates":[-112.22290700000001,33.581256],"type":"Point"}
}