{
  "type": "Feature",
  "properties": {
    "iso:country":"US",
    "sg:address":"3445 N Valencia Ln",
    "sg:city":"Phoenix",
    "sg:classifiers":[
        {
            "category":"Building & Trades",
            "subcategory":"Construction",
            "type":"Services"
        }
    ],
    "sg:phone":"+1 480 945 3763",
    "sg:postcode":"85018",
    "sg:province":"AZ",
    "sg:tags":[
        "industrial",
        "commercial",
        "contractor"
    ],
    "wof:name":"W I C C",
    "wof:placetype":"venue"
},
  "geometry": {"coordinates":[-111.959534,33.488172],"type":"Point"}
}