{
  "type": "Feature",
  "properties": {
    "addr:full":"4367 S Maverick Ave Gilbert AZ 85297",
    "addr:housenumber":"4367",
    "addr:postcode":"85297",
    "addr:street":"S Maverick Ave",
    "iso:country":"US",
    "sg:address":"4367 S Maverick Ave",
    "sg:city":"Gilbert",
    "sg:classifiers":[
        {
            "category":"Health Services",
            "subcategory":"Health Practitioner",
            "type":"Services"
        }
    ],
    "sg:phone":"+1 480 659 7343",
    "sg:postcode":"85297",
    "sg:province":"AZ",
    "sg:tags":[
        "psychologist"
    ],
    "wof:name":"Summit Advantage Inc",
    "wof:placetype":"venue"
},
  "geometry": {"coordinates":[-111.701802,33.272216],"type":"Point"}
}