{
  "type": "Feature",
  "properties": {
    "addr:full":"9431 E Impala Ave Mesa AZ 85209",
    "addr:housenumber":"9431",
    "addr:postcode":"85209",
    "addr:street":"E Impala Ave",
    "iso:country":"US",
    "sg:address":"9431 E Impala Ave",
    "sg:city":"Mesa",
    "sg:classifiers":[
        {
            "category":"Insurance",
            "subcategory":"Insurance Agent",
            "type":"Services"
        }
    ],
    "sg:phone":"+1 480 357 8200",
    "sg:postcode":"85209",
    "sg:province":"AZ",
    "wof:name":"Kevin F Smith Insurance Svc",
    "wof:placetype":"venue"
},
  "geometry": {"coordinates":[-111.626758,33.383475],"type":"Point"}
}