{
  "type": "Feature",
  "properties": {
    "addr:full":"5600 S 12th Ave Tucson AZ 85706",
    "addr:housenumber":"5600",
    "addr:postcode":"85706",
    "addr:street":"S 12Th Ave",
    "iso:country":"US",
    "sg:address":"5600 S 12th Ave",
    "sg:city":"Tucson",
    "sg:classifiers":[
        {
            "category":"Retail",
            "subcategory":"Auto Rental",
            "type":"Services"
        }
    ],
    "sg:phone":"+1 520 889 2285",
    "sg:postcode":"85706",
    "sg:province":"AZ",
    "sg:tags":[
        "renting",
        "truck",
        "leasing"
    ],
    "wof:name":"U-Haul Co",
    "wof:placetype":"venue"
},
  "geometry": {"coordinates":[-110.977557,32.148674],"type":"Point"}
}