{
  "type": "Feature",
  "properties": {
    "iso:country":"US",
    "sg:address":"461 Forest Rd",
    "sg:city":"Sedona",
    "sg:classifiers":[
        {
            "category":"Real Estate",
            "subcategory":"Real Estate Agent",
            "type":"Services"
        }
    ],
    "sg:phone":"+1 928 204 1379",
    "sg:postcode":"86336",
    "sg:province":"AZ",
    "wof:name":"Sedona Vacation Homes",
    "wof:placetype":"venue"
},
  "geometry": {"coordinates":[-111.765975,34.868258],"type":"Point"}
}