{
  "type": "Feature",
  "properties": {
    "iso:country":"US",
    "sg:address":"2031 N Nevada Cir",
    "sg:city":"Mesa",
    "sg:classifiers":[
        {
            "category":"Professional",
            "type":"Services"
        }
    ],
    "sg:phone":"+1 480 668 8300",
    "sg:postcode":"85203",
    "sg:province":"AZ",
    "sg:tags":[
        "establishment"
    ],
    "wof:name":"Daryl Rosen Inc",
    "wof:placetype":"venue"
},
  "geometry": {"coordinates":[-111.812673,33.452778],"type":"Point"}
}