{
  "type": "Feature",
  "properties": {
    "iso:country":"US",
    "sg:address":"500 S Langley Ave",
    "sg:city":"Tucson",
    "sg:classifiers":[
        {
            "category":"Organizations",
            "subcategory":"Religious Organization",
            "type":"Services"
        }
    ],
    "sg:phone":"+1 520 298 0905",
    "sg:postcode":"85710",
    "sg:province":"AZ",
    "sg:tags":[
        "church"
    ],
    "wof:name":"Family History Ctr",
    "wof:placetype":"venue"
},
  "geometry": {"coordinates":[-110.84381399999999,32.212725],"type":"Point"}
}