{
  "type": "Feature",
  "properties": {
    "iso:country":"US",
    "sg:address":"867 Navajo Blvd",
    "sg:city":"Holbrook",
    "sg:classifiers":[
        {
            "category":"Restaurant",
            "type":"Food & Drink"
        }
    ],
    "sg:phone":"+1 928 524 3332",
    "sg:postcode":"86025",
    "sg:province":"AZ",
    "sg:tags":[
        "mexican"
    ],
    "wof:name":"El Rancho Restaurant & Motel",
    "wof:placetype":"venue"
},
  "geometry": {"coordinates":[-110.158053,34.907687],"type":"Point"}
}