{
  "type": "Feature",
  "properties": {
    "addr:full":"8980 E Indian Bend Rd Scottsdale AZ 85250",
    "addr:housenumber":"8980",
    "addr:postcode":"85250",
    "addr:street":"E Indian Bend Rd",
    "iso:country":"US",
    "sg:address":"8980 E Indian Bend Rd",
    "sg:city":"Scottsdale",
    "sg:classifiers":[
        {
            "category":"Shopping",
            "subcategory":"Optical Goods",
            "type":"Retail Goods"
        }
    ],
    "sg:phone":"+1 480 951 0288",
    "sg:postcode":"85250",
    "sg:province":"AZ",
    "wof:name":"Paris Optique Via USA Ltd Inc",
    "wof:placetype":"venue"
},
  "geometry": {"coordinates":[-111.89031199999999,33.538343],"type":"Point"}
}