{
  "type": "Feature",
  "properties": {
    "iso:country":"US",
    "sg:address":"908 E Claremont St",
    "sg:city":"Phoenix",
    "sg:classifiers":[
        {
            "category":"Professional",
            "type":"Services"
        }
    ],
    "sg:phone":"+1 602 279 0678",
    "sg:postcode":"85014",
    "sg:province":"AZ",
    "wof:name":"Caven P Clark",
    "wof:placetype":"venue"
},
  "geometry": {"coordinates":[-112.063873,33.528375],"type":"Point"}
}