{
  "type": "Feature",
  "properties": {
    "iso:country":"US",
    "sg:address":"2304 N 4th St",
    "sg:city":"Flagstaff",
    "sg:classifiers":[
        {
            "category":"Manufacturing",
            "subcategory":"Signs",
            "type":"Manufacturing & Wholesale Goods"
        }
    ],
    "sg:phone":"+1 928 527 0337",
    "sg:postcode":"86004",
    "sg:province":"AZ",
    "sg:tags":[
        "advertising",
        "specialty"
    ],
    "wof:name":"B & W Sign & Graphics",
    "wof:placetype":"venue"
},
  "geometry": {"coordinates":[-111.613398,35.211598],"type":"Point"}
}