{
  "type": "Feature",
  "properties": {
    "iso:country":"US",
    "sg:address":"3160 Shangrila Dr",
    "sg:city":"Kingman",
    "sg:classifiers":[
        {
            "category":"Professional",
            "subcategory":"Management & Consulting",
            "type":"Services"
        }
    ],
    "sg:phone":"+1 928 692 6970",
    "sg:postcode":"86409",
    "sg:province":"AZ",
    "sg:tags":[
        "development",
        "economic",
        "agency"
    ],
    "wof:name":"Mohave County Economic Dev",
    "wof:placetype":"venue"
},
  "geometry": {"coordinates":[-114.004882,35.226236],"type":"Point"}
}