{
  "type": "Feature",
  "properties": {
    "addr:full":"4002 E McDowell Rd Phoenix AZ 85008",
    "addr:housenumber":"4002",
    "addr:postcode":"85008",
    "addr:street":"E Mcdowell Rd",
    "iso:country":"US",
    "sg:address":"4002 E McDowell Rd",
    "sg:city":"Phoenix",
    "sg:classifiers":[
        {
            "category":"Food & Beverages",
            "subcategory":"Groceries & Convenience Stores",
            "type":"Retail Goods"
        }
    ],
    "sg:phone":"+1 602 244 1799",
    "sg:postcode":"85008",
    "sg:province":"AZ",
    "sg:website":"www.7-eleven.com",
    "wof:name":"7-Eleven",
    "wof:placetype":"venue"
},
  "geometry": {"coordinates":[-111.99487000000001,33.465732],"type":"Point"}
}