{
  "type": "Feature",
  "properties": {
    "iso:country":"US",
    "sg:address":"1133 E Redmon Dr",
    "sg:city":"Tempe",
    "sg:classifiers":[
        {
            "category":"Manufacturing",
            "subcategory":"Metals",
            "type":"Manufacturing & Wholesale Goods"
        }
    ],
    "sg:phone":"+1 480 897 6250",
    "sg:postcode":"85283",
    "sg:province":"AZ",
    "sg:tags":[
        "plumbing",
        "fitting",
        "fixture",
        "mfg"
    ],
    "wof:name":"Lloyds Lawn Sprinklers",
    "wof:placetype":"venue"
},
  "geometry": {"coordinates":[-111.922629,33.362431],"type":"Point"}
}