{
  "type": "Feature",
  "properties": {
    "iso:country":"US",
    "sg:address":"4036 E Woodland Dr",
    "sg:city":"Phoenix",
    "sg:classifiers":[
        {
            "category":"Building & Trades",
            "subcategory":"Construction",
            "type":"Services"
        }
    ],
    "sg:phone":"+1 602 451 0258",
    "sg:postcode":"85048",
    "sg:province":"AZ",
    "sg:tags":[
        "wallcoverings-installation",
        "wallpaper",
        "painting",
        "contractor"
    ],
    "wof:name":"Custom Painting By Fritz",
    "wof:placetype":"venue"
},
  "geometry": {"coordinates":[-111.996205,33.301867],"type":"Point"}
}