{
  "type": "Feature",
  "properties": {
    "addr:full":"3800 N Central Ave Phoenix AZ 85012",
    "addr:housenumber":"3800",
    "addr:postcode":"85012",
    "addr:street":"N Central Ave",
    "iso:country":"US",
    "sg:address":"3800 N Central Ave",
    "sg:city":"Phoenix",
    "sg:classifiers":[
        {
            "category":"Professional",
            "subcategory":"Engineering",
            "type":"Services"
        },
        {
            "category":"Professional",
            "subcategory":"Business Services",
            "type":"Services"
        }
    ],
    "sg:phone":"+1 602 635 4226",
    "sg:postcode":"85012",
    "sg:province":"AZ",
    "sg:tags":[
        "consultant",
        "consulting",
        "coach",
        "engineer"
    ],
    "wof:name":"Lloyd Counsulting Group",
    "wof:placetype":"venue"
},
  "geometry": {"coordinates":[-112.073914,33.491138],"type":"Point"}
}