{
  "type": "Feature",
  "properties": {
    "addr:full":"4182 N Quail Canyon Dr Tucson AZ 85750",
    "addr:housenumber":"4182",
    "addr:postcode":"85750",
    "addr:street":"N Quail Canyon Dr",
    "iso:country":"US",
    "sg:address":"4182 N Quail Canyon Dr",
    "sg:city":"Tucson",
    "sg:classifiers":[
        {
            "category":"Building & Trades",
            "subcategory":"Construction",
            "type":"Services"
        }
    ],
    "sg:phone":"+1 520 749 6051",
    "sg:postcode":"85750",
    "sg:province":"AZ",
    "sg:tags":[
        "contractor"
    ],
    "wof:name":"Sundown Builders Inc",
    "wof:placetype":"venue"
},
  "geometry": {"coordinates":[-110.82201499999999,32.281258],"type":"Point"}
}