{
  "type": "Feature",
  "properties": {
    "addr:full":"1818 E Southern Ave Mesa AZ 85204",
    "addr:housenumber":"1818",
    "addr:postcode":"85204",
    "addr:street":"E Southern Ave",
    "iso:country":"US",
    "sg:address":"1818 E Southern Ave",
    "sg:city":"Mesa",
    "sg:classifiers":[
        {
            "category":"Banks & Credit Unions",
            "subcategory":"Bank",
            "type":"Services"
        }
    ],
    "sg:phone":"+1 480 926 8800",
    "sg:postcode":"85204",
    "sg:province":"AZ",
    "sg:tags":[
        "broker",
        "mortgage"
    ],
    "wof:name":"Ameriwest Home Loans",
    "wof:placetype":"venue"
},
  "geometry": {"coordinates":[-111.793212,33.393575],"type":"Point"}
}