{
  "type": "Feature",
  "properties": {
    "addr:full":"8502 E Vista Dr de Ventura de Ventura Ste Scottsdale AZ 85250",
    "addr:housenumber":"8502",
    "addr:postcode":"85250",
    "addr:street":"E Vista Dr De Ventura De Ventura Ste",
    "iso:country":"US",
    "sg:address":"8502 E Vista Dr de Ventura de Ventura Ste",
    "sg:city":"Scottsdale",
    "sg:classifiers":[
        {
            "category":"Manufacturing",
            "subcategory":"Petroleum Products",
            "type":"Manufacturing & Wholesale Goods"
        },
        {
            "category":"Wholesale",
            "subcategory":"Petroleum",
            "type":"Manufacturing & Wholesale Goods"
        }
    ],
    "sg:phone":"+1 480 624 5800",
    "sg:postcode":"85250",
    "sg:province":"AZ",
    "sg:tags":[
        "manufacturer",
        "products-wholesale",
        "oils-petroleum"
    ],
    "sg:website":"http://www.northamericanlubricants.com",
    "wof:name":"North American Lubricants Company",
    "wof:placetype":"venue"
},
  "geometry": {"coordinates":[-111.89799499999999,33.512998],"type":"Point"}
}