{
  "type": "Feature",
  "properties": {
    "iso:country":"US",
    "sg:address":"1734 N 22nd Ave",
    "sg:city":"Phoenix",
    "sg:classifiers":[
        {
            "category":"Building & Trades",
            "subcategory":"Equipment Rental",
            "type":"Services"
        }
    ],
    "sg:phone":"+1 602 258 4911",
    "sg:postcode":"85009",
    "sg:province":"AZ",
    "sg:tags":[
        "leasing",
        "stereo",
        "audio",
        "video",
        "equipment-renting"
    ],
    "sg:website":"http://www.swav.net",
    "wof:name":"Southwest Audio Visual, Inc.",
    "wof:placetype":"venue"
},
  "geometry": {"coordinates":[-112.106387,33.46737],"type":"Point"}
}