{
  "type": "Feature",
  "properties": {
    "addr:full":"18002 N 40th Pl Phoenix AZ 85032",
    "addr:housenumber":"18002",
    "addr:postcode":"85032",
    "addr:street":"N 40Th Pl",
    "iso:country":"US",
    "sg:address":"18002 N 40th Pl",
    "sg:city":"Phoenix",
    "sg:classifiers":[
        {
            "category":"Professional",
            "subcategory":"Management & Consulting",
            "type":"Services"
        }
    ],
    "sg:phone":"+1 602 308 0404",
    "sg:postcode":"85032",
    "sg:province":"AZ",
    "sg:tags":[
        "consultant",
        "automation"
    ],
    "wof:name":"Active Arizona Automation",
    "wof:placetype":"venue"
},
  "geometry": {"coordinates":[-111.995155,33.650722],"type":"Point"}
}