{
  "type": "Feature",
  "properties": {
    "iso:country":"US",
    "sg:address":"8526 E Pecos Ln",
    "sg:city":"Scottsdale",
    "sg:classifiers":[
        {
            "category":"Building & Trades",
            "subcategory":"Electrical",
            "type":"Services"
        }
    ],
    "sg:phone":"+1 480 941 5789",
    "sg:postcode":"85250",
    "sg:province":"AZ",
    "sg:tags":[
        "electric",
        "contractor"
    ],
    "wof:name":"Intelligent Technologies",
    "wof:placetype":"venue"
},
  "geometry": {"coordinates":[-111.896398,33.515987],"type":"Point"}
}