{
  "type": "Feature",
  "properties": {
    "iso:country":"US",
    "sg:address":"2520 N Stewart Ave",
    "sg:city":"Tucson",
    "sg:classifiers":[
        {
            "category":"Real Estate",
            "subcategory":"Real Estate Operator",
            "type":"Services"
        }
    ],
    "sg:phone":"+1 520 323 0812",
    "sg:postcode":"85716",
    "sg:province":"AZ",
    "sg:tags":[
        "building",
        "nonresidential"
    ],
    "wof:name":"Jmc Properties LLC",
    "wof:placetype":"venue"
},
  "geometry": {"coordinates":[-110.930011,32.25281],"type":"Point"}
}