{
  "type": "Feature",
  "properties": {
    "iso:country":"US",
    "sg:address":"6197 S Rural Rd Ste 101",
    "sg:city":"Tempe",
    "sg:classifiers":[
        {
            "category":"Arts & Performance",
            "subcategory":"Music",
            "type":"Entertainment"
        }
    ],
    "sg:phone":"+1 480 699 4326",
    "sg:postcode":"85283",
    "sg:province":"AZ",
    "sg:tags":[
        "band",
        "orchestra"
    ],
    "wof:name":"Phoenix Jazz Orchestra Assoc",
    "wof:placetype":"venue"
},
  "geometry": {"coordinates":[-111.928612,33.365619],"type":"Point"}
}