{
  "type": "Feature",
  "properties": {
    "iso:country":"US",
    "sg:address":"105 N 5th Ave",
    "sg:city":"Holbrook",
    "sg:classifiers":[
        {
            "category":"Government",
            "subcategory":"Office",
            "type":"Public Place"
        }
    ],
    "sg:phone":"+1 928 524 2811",
    "sg:postcode":"86025",
    "sg:province":"AZ",
    "sg:tags":[
        "program",
        "administrative"
    ],
    "wof:name":"Winslow Child Protective Svcs",
    "wof:placetype":"venue"
},
  "geometry": {"coordinates":[-110.165901,34.90155],"type":"Point"}
}