{
  "type": "Feature",
  "properties": {
    "iso:country":"US",
    "sg:address":"2101 Harrison St",
    "sg:city":"Kingman",
    "sg:classifiers":[
        {
            "category":"Social Services",
            "subcategory":"Child Care",
            "type":"Services"
        }
    ],
    "sg:phone":"+1 928 753 3068",
    "sg:postcode":"86401",
    "sg:province":"AZ",
    "sg:tags":[
        "kindergarten",
        "academic",
        "school"
    ],
    "sg:website":"www.gracekingman.org",
    "wof:name":"Grace Lutheran Church",
    "wof:placetype":"venue"
},
  "geometry": {"coordinates":[-114.02473500000001,35.206731],"type":"Point"}
}