{
  "type": "Feature",
  "properties": {
    "addr:full":"53277 W Dune Shadow Rd Maricopa AZ 85239",
    "addr:housenumber":"53277",
    "addr:postcode":"85239",
    "addr:street":"W Dune Shadow Rd",
    "iso:country":"US",
    "sg:address":"53277 W Dune Shadow Rd",
    "sg:city":"Maricopa",
    "sg:classifiers":[
        {
            "category":"Manufacturing",
            "subcategory":"Printing",
            "type":"Manufacturing & Wholesale Goods"
        }
    ],
    "sg:phone":"+1 520 424 3500",
    "sg:postcode":"85239",
    "sg:province":"AZ",
    "sg:tags":[
        "book",
        "publishing"
    ],
    "wof:name":"Celfijo Inc",
    "wof:placetype":"venue"
},
  "geometry": {"coordinates":[-112.139669,32.88388],"type":"Point"}
}