{
  "type": "Feature",
  "properties": {
    "addr:full":"3051 S White Mountain Rd Show Low AZ 85901",
    "addr:housenumber":"3051",
    "addr:postcode":"85901",
    "addr:street":"S White Mountain Rd",
    "iso:country":"US",
    "sg:address":"3051 S White Mountain Rd",
    "sg:city":"Show Low",
    "sg:classifiers":[
        {
            "category":"Home & Garden",
            "subcategory":"Building Materials",
            "type":"Retail Goods"
        }
    ],
    "sg:phone":"+1 928 537 7820",
    "sg:postcode":"85901",
    "sg:province":"AZ",
    "wof:name":"Painters Supply & Dctg Ctr",
    "wof:placetype":"venue"
},
  "geometry": {"coordinates":[-110.029326,34.223626],"type":"Point"}
}