{
  "type": "Feature",
  "properties": {
    "iso:country":"US",
    "sg:address":"2505 E Desert Ln",
    "sg:city":"Gilbert",
    "sg:classifiers":[
        {
            "category":"Professional",
            "subcategory":"Lawyer & Legal Services",
            "type":"Services"
        }
    ],
    "sg:phone":"+1 480 223 0234",
    "sg:postcode":"85234",
    "sg:province":"AZ",
    "sg:tags":[
        "attorney"
    ],
    "wof:name":"Cluff & Assoc",
    "wof:placetype":"venue"
},
  "geometry": {"coordinates":[-111.73746300000001,33.373716],"type":"Point"}
}