{
  "type": "Feature",
  "properties": {
    "iso:country":"US",
    "sg:address":"903 N Beeline Hwy",
    "sg:city":"Payson",
    "sg:classifiers":[
        {
            "category":"Health Services",
            "subcategory":"Chiropractor",
            "type":"Services"
        }
    ],
    "sg:phone":"+1 928 474 7070",
    "sg:postcode":"85541",
    "sg:province":"AZ",
    "wof:name":"Anderson Chiropractic",
    "wof:placetype":"venue"
},
  "geometry": {"coordinates":[-111.322483,34.252606],"type":"Point"}
}