{
  "type": "Feature",
  "properties": {
    "iso:country":"US",
    "sg:address":"1045 Sandretto Dr",
    "sg:city":"Prescott",
    "sg:classifiers":[
        {
            "category":"Health Services",
            "subcategory":"Nursing And Care Facility",
            "type":"Services"
        }
    ],
    "sg:phone":"+1 928 778 4837",
    "sg:postcode":"86305",
    "sg:province":"AZ",
    "sg:tags":[
        "home",
        "convalescent"
    ],
    "wof:name":"Mountain View Manor",
    "wof:placetype":"venue"
},
  "geometry": {"coordinates":[-112.458337,34.602369],"type":"Point"}
}