{
  "type": "Feature",
  "properties": {
    "iso:country":"US",
    "sg:address":"5095 Brandis Way",
    "sg:city":"Flagstaff",
    "sg:classifiers":[
        {
            "category":"Building & Trades",
            "subcategory":"Construction",
            "type":"Services"
        }
    ],
    "sg:phone":"+1 928 526 3696",
    "sg:postcode":"86004",
    "sg:province":"AZ",
    "sg:tags":[
        "nonresidential"
    ],
    "wof:name":"Robertson Management Svcs Inc",
    "wof:placetype":"venue"
},
  "geometry": {"coordinates":[-111.55781,35.327608],"type":"Point"}
}