{
  "type": "Feature",
  "properties": {
    "iso:country":"US",
    "sg:address":"20822 S Tiberius Dr",
    "sg:city":"Queen Creek",
    "sg:classifiers":[
        {
            "category":"Professional",
            "type":"Services"
        }
    ],
    "sg:phone":"+1 480 888 2254",
    "sg:postcode":"85242",
    "sg:province":"AZ",
    "wof:name":"Focused On Blinds LLC",
    "wof:placetype":"venue"
},
  "geometry": {"coordinates":[-111.653971,33.257945],"type":"Point"}
}