{
  "type": "Feature",
  "properties": {
    "iso:country":"US",
    "sg:address":"3713 E Windsong Dr",
    "sg:city":"Phoenix",
    "sg:classifiers":[
        {
            "category":"Professional",
            "type":"Services"
        }
    ],
    "sg:phone":"+1 480 759 9439",
    "sg:postcode":"85048",
    "sg:province":"AZ",
    "sg:tags":[
        "pilot"
    ],
    "wof:name":"Cavu Aviation",
    "wof:placetype":"venue"
},
  "geometry": {"coordinates":[-112.00293000000001,33.29472],"type":"Point"}
}