{
  "type": "Feature",
  "properties": {
    "addr:full":"5110 N Dysart Rd Ste 124 Litchfield Park AZ 85340",
    "addr:housenumber":"5110",
    "addr:postcode":"85340",
    "addr:street":"N Dysart Rd Ste 124",
    "iso:country":"US",
    "sg:address":"5110 N Dysart Rd Ste 124",
    "sg:city":"Litchfield Park",
    "sg:classifiers":[
        {
            "category":"Food & Beverages",
            "subcategory":"Liquor & Beverages",
            "type":"Retail Goods"
        }
    ],
    "sg:phone":"+1 623 547 2227",
    "sg:postcode":"85340",
    "sg:province":"AZ",
    "sg:tags":[
        "beer",
        "spirit",
        "wine"
    ],
    "wof:name":"TailGaters Sports Grill And IL Primo Pizza & Wings",
    "wof:placetype":"venue"
},
  "geometry": {"coordinates":[-112.34101,33.510425],"type":"Point"}
}