{
  "type": "Feature",
  "properties": {
    "iso:country":"US",
    "sg:address":"6120 W Bell Rd",
    "sg:city":"Glendale",
    "sg:classifiers":[
        {
            "category":"Professional",
            "subcategory":"Management & Consulting",
            "type":"Services"
        }
    ],
    "sg:phone":"+1 602 374 4923",
    "sg:postcode":"85308",
    "sg:province":"AZ",
    "sg:tags":[
        "marketing",
        "program"
    ],
    "wof:name":"Marketing With A Flair",
    "wof:placetype":"venue"
},
  "geometry": {"coordinates":[-112.194737,33.638658],"type":"Point"}
}