{
  "type": "Feature",
  "properties": {
    "addr:full":"706 E 46th St Tucson AZ 85713",
    "addr:housenumber":"706",
    "addr:postcode":"85713",
    "addr:street":"E 46Th St",
    "iso:country":"US",
    "sg:address":"706 E 46th St",
    "sg:city":"Tucson",
    "sg:classifiers":[
        {
            "category":"Manufacturing",
            "subcategory":"Chemicals & Compounds",
            "type":"Manufacturing & Wholesale Goods"
        }
    ],
    "sg:phone":"+1 520 622 4087",
    "sg:postcode":"85713",
    "sg:province":"AZ",
    "sg:tags":[
        "chemicals-wholesale",
        "manufacturer"
    ],
    "wof:name":"Esp Chemicals Inc",
    "wof:placetype":"venue"
},
  "geometry": {"coordinates":[-110.95934800000001,32.181003],"type":"Point"}
}