{
  "type": "Feature",
  "properties": {
    "iso:country":"US",
    "sg:address":"14230 N 70th Pl",
    "sg:city":"Scottsdale",
    "sg:classifiers":[
        {
            "category":"Professional",
            "type":"Services"
        },
        {
            "category":"Arts & Performance",
            "subcategory":"Music",
            "type":"Entertainment"
        }
    ],
    "sg:phone":"+1 480 922 3177",
    "sg:postcode":"85254",
    "sg:province":"AZ",
    "sg:tags":[
        "record",
        "producer",
        "label"
    ],
    "wof:name":"Musicanvas Recording Studio Inc",
    "wof:placetype":"venue"
},
  "geometry": {"coordinates":[-111.929626,33.615706],"type":"Point"}
}