{
  "type": "Feature",
  "properties": {
    "iso:country":"US",
    "sg:address":"521 N Country Club Rd",
    "sg:city":"Tucson",
    "sg:classifiers":[
        {
            "category":"Organizations",
            "subcategory":"Professional Association",
            "type":"Services"
        }
    ],
    "sg:phone":"+1 520 327 3354",
    "sg:postcode":"85716",
    "sg:province":"AZ",
    "wof:name":"Villa Catalina Homeowners",
    "wof:placetype":"venue"
},
  "geometry": {"coordinates":[-110.926772,32.227386],"type":"Point"}
}