{
  "type": "Feature",
  "properties": {
    "addr:full":"6202 W Oregon Ave Glendale AZ 85301",
    "addr:housenumber":"6202",
    "addr:postcode":"85301",
    "addr:street":"W Oregon Ave",
    "iso:country":"US",
    "sg:address":"6202 W Oregon Ave",
    "sg:city":"Glendale",
    "sg:classifiers":[
        {
            "category":"Professional",
            "type":"Services"
        }
    ],
    "sg:phone":"+1 623 934 8995",
    "sg:postcode":"85301",
    "sg:province":"AZ",
    "wof:name":"Home Away From Home",
    "wof:placetype":"venue"
},
  "geometry": {"coordinates":[-112.19498400000001,33.513858],"type":"Point"}
}