{
  "type": "Feature",
  "properties": {
    "iso:country":"US",
    "sg:address":"1810 W Northern Ave Ste A3",
    "sg:city":"Phoenix",
    "sg:classifiers":[
        {
            "category":"Retail",
            "subcategory":"Laundry & Dry Cleaning",
            "type":"Services"
        }
    ],
    "sg:phone":"+1 602 371 1785",
    "sg:postcode":"85021",
    "sg:province":"AZ",
    "sg:tags":[
        "cleaner"
    ],
    "wof:name":"Tower Cleaning Systems",
    "wof:placetype":"venue"
},
  "geometry": {"coordinates":[-112.098246,33.553096],"type":"Point"}
}