{
  "type": "Feature",
  "properties": {
    "addr:full":"100 N 1st St Phoenix AZ 85004",
    "addr:housenumber":"100",
    "addr:postcode":"85004",
    "addr:street":"N 1St St",
    "iso:country":"US",
    "sg:address":"100 N 1st St",
    "sg:city":"Phoenix",
    "sg:classifiers":[
        {
            "category":"Coffee & Tea",
            "type":"Food & Drink"
        }
    ],
    "sg:menulink":"http://www.allmenus.com/az/phoenix/108340-starbucks-coffee/menu/",
    "sg:phone":"+1 602 340 0455",
    "sg:postcode":"85004",
    "sg:province":"AZ",
    "sg:tags":[
        "american"
    ],
    "wof:name":"Starbucks Coffee",
    "wof:placetype":"venue"
},
  "geometry": {"coordinates":[-112.073455,33.44962],"type":"Point"}
}