{
  "type": "Feature",
  "properties": {
    "addr:full":"9249 N 36th Ave Phoenix AZ 85051",
    "addr:housenumber":"9249",
    "addr:postcode":"85051",
    "addr:street":"N 36Th Ave",
    "iso:country":"US",
    "sg:address":"9249 N 36th Ave",
    "sg:city":"Phoenix",
    "sg:classifiers":[
        {
            "category":"Manufacturing",
            "subcategory":"Building Materials",
            "type":"Manufacturing & Wholesale Goods"
        }
    ],
    "sg:phone":"+1 602 403 6518",
    "sg:postcode":"85051",
    "sg:province":"AZ",
    "sg:tags":[
        "mfg"
    ],
    "wof:name":"Professnal Mllwk Instllers LLC",
    "wof:placetype":"venue"
},
  "geometry": {"coordinates":[-112.136207,33.571206],"type":"Point"}
}