{
  "type": "Feature",
  "properties": {
    "iso:country":"US",
    "sg:address":"5248 Wood Owl Dr",
    "sg:city":"Tucson",
    "sg:classifiers":[
        {
            "category":"Professional",
            "subcategory":"Research",
            "type":"Services"
        }
    ],
    "sg:phone":"+1 520 744 7523",
    "sg:postcode":"85742",
    "sg:province":"AZ",
    "wof:name":"PPD Development",
    "wof:placetype":"venue"
},
  "geometry": {"coordinates":[-111.075895,32.377949],"type":"Point"}
}