{
  "type": "Feature",
  "properties": {
    "iso:country":"US",
    "sg:address":"6123 E Hearn Rd",
    "sg:city":"Scottsdale",
    "sg:classifiers":[
        {
            "category":"Conference Center",
            "type":"Public Place"
        }
    ],
    "sg:phone":"+1 480 998 9411",
    "sg:postcode":"85254",
    "sg:province":"AZ",
    "sg:tags":[
        "coordinator",
        "seminar"
    ],
    "wof:name":"Celebratelove.Com",
    "wof:placetype":"venue"
},
  "geometry": {"coordinates":[-111.948779,33.615008],"type":"Point"}
}