{
  "type": "Feature",
  "properties": {
    "iso:country":"US",
    "sg:address":"2137 Acoma Blvd W",
    "sg:city":"Lake Havasu City",
    "sg:classifiers":[
        {
            "category":"Restaurant",
            "type":"Food & Drink"
        }
    ],
    "sg:phone":"+1 928 680 3868",
    "sg:postcode":"86403",
    "sg:province":"AZ",
    "sg:tags":[
        "eating"
    ],
    "wof:name":"Angelina's Italian Kitchen",
    "wof:placetype":"venue"
},
  "geometry": {"coordinates":[-114.334043,34.496744],"type":"Point"}
}