{
  "type": "Feature",
  "properties": {
    "iso:country":"US",
    "sg:address":"1733 E McKellips Rd",
    "sg:city":"Tempe",
    "sg:classifiers":[
        {
            "category":"Professional",
            "type":"Services"
        }
    ],
    "sg:phone":"+1 480 332 6304",
    "sg:postcode":"85281",
    "sg:province":"AZ",
    "wof:name":"Pacific States Window & Door",
    "wof:placetype":"venue"
},
  "geometry": {"coordinates":[-111.911499,33.451201],"type":"Point"}
}