{
  "type": "Feature",
  "properties": {
    "iso:country":"US",
    "sg:address":"6113 W Mulberry Dr",
    "sg:city":"Phoenix",
    "sg:classifiers":[
        {
            "category":"Professional",
            "subcategory":"Art Services",
            "type":"Services"
        }
    ],
    "sg:phone":"+1 602 361 1897",
    "sg:postcode":"85033",
    "sg:province":"AZ",
    "sg:tags":[
        "designer",
        "display",
        "producer"
    ],
    "wof:name":"Bright Idea Gift Design",
    "wof:placetype":"venue"
},
  "geometry": {"coordinates":[-112.192879,33.486972],"type":"Point"}
}