{
  "type": "Feature",
  "properties": {
    "iso:country":"US",
    "sg:address":"20244 N 31st Ave",
    "sg:city":"Phoenix",
    "sg:classifiers":[
        {
            "category":"Real Estate",
            "subcategory":"Real Estate Operator",
            "type":"Services"
        }
    ],
    "sg:phone":"+1 623 434 8000",
    "sg:postcode":"85027",
    "sg:province":"AZ",
    "sg:tags":[
        "apartment"
    ],
    "wof:name":"Deer Creek Village",
    "wof:placetype":"venue"
},
  "geometry": {"coordinates":[-112.125998,33.669355],"type":"Point"}
}