{
  "type": "Feature",
  "properties": {
    "iso:country":"US",
    "sg:address":"1732 E Potter Dr",
    "sg:city":"Phoenix",
    "sg:classifiers":[
        {
            "category":"Personal",
            "type":"Services"
        }
    ],
    "sg:phone":"+1 623 516 0714",
    "sg:postcode":"85024",
    "sg:province":"AZ",
    "sg:tags":[
        "control",
        "weight"
    ],
    "wof:name":"K T Concepts",
    "wof:placetype":"venue"
},
  "geometry": {"coordinates":[-112.048164,33.674887],"type":"Point"}
}