{
  "type": "Feature",
  "properties": {
    "iso:country":"US",
    "sg:address":"10277 N Mineral Spring Way",
    "sg:city":"Tucson",
    "sg:classifiers":[
        {
            "category":"Building & Trades",
            "subcategory":"Construction",
            "type":"Services"
        }
    ],
    "sg:phone":"+1 520 400 4305",
    "sg:postcode":"85737",
    "sg:province":"AZ",
    "sg:tags":[
        "residential"
    ],
    "wof:name":"Newrand Development LLC",
    "wof:placetype":"venue"
},
  "geometry": {"coordinates":[-110.983402,32.393531],"type":"Point"}
}