{
  "type": "Feature",
  "properties": {
    "addr:full":"3051 W Cll Rosalinda Tucson AZ 85746",
    "addr:housenumber":"3051",
    "addr:postcode":"85746",
    "addr:street":"W Cll",
    "iso:country":"US",
    "sg:address":"3051 W Cll Rosalinda",
    "sg:city":"Tucson",
    "sg:classifiers":[
        {
            "category":"Building & Trades",
            "subcategory":"Construction",
            "type":"Services"
        }
    ],
    "sg:phone":"+1 520 440 1176",
    "sg:postcode":"85746",
    "sg:province":"AZ",
    "sg:tags":[
        "house"
    ],
    "wof:name":"Eugene P Bockstedt",
    "wof:placetype":"venue"
},
  "geometry": {"coordinates":[-111.032122,32.14921],"type":"Point"}
}