{
  "type": "Feature",
  "properties": {
    "addr:full":"4864 E Baseline Rd Gilbert AZ 85234",
    "addr:housenumber":"4864",
    "addr:postcode":"85234",
    "addr:street":"E Baseline Rd",
    "iso:country":"US",
    "sg:address":"4864 E Baseline Rd",
    "sg:city":"Gilbert",
    "sg:classifiers":[
        {
            "category":"Professional",
            "type":"Services"
        }
    ],
    "sg:phone":"+1 480 830 2900",
    "sg:postcode":"85234",
    "sg:province":"AZ",
    "wof:name":"Windermere",
    "wof:placetype":"venue"
},
  "geometry": {"coordinates":[-111.72672300000001,33.379247],"type":"Point"}
}