{
  "type": "Feature",
  "properties": {
    "addr:full":"2609 E Roosevelt St Phoenix AZ 85008",
    "addr:housenumber":"2609",
    "addr:postcode":"85008",
    "addr:street":"E Roosevelt St",
    "iso:country":"US",
    "sg:address":"2609 E Roosevelt St",
    "sg:city":"Phoenix",
    "sg:classifiers":[
        {
            "category":"Utilities",
            "subcategory":"Refuse",
            "type":"Services"
        }
    ],
    "sg:phone":"+1 602 273 0971",
    "sg:postcode":"85008",
    "sg:province":"AZ",
    "sg:tags":[
        "system"
    ],
    "wof:name":"BFI",
    "wof:placetype":"venue"
},
  "geometry": {"coordinates":[-112.02512,33.458482],"type":"Point"}
}