{
  "type": "Feature",
  "properties": {
    "iso:country":"US",
    "sg:address":"6230 N 89th Ave",
    "sg:city":"Glendale",
    "sg:classifiers":[
        {
            "category":"Wholesale",
            "subcategory":"Durable Goods & Equipment",
            "type":"Manufacturing & Wholesale Goods"
        }
    ],
    "sg:phone":"+1 623 872 4923",
    "sg:postcode":"85305",
    "sg:province":"AZ",
    "wof:name":"Jenard Enterprises",
    "wof:placetype":"venue"
},
  "geometry": {"coordinates":[-112.251385,33.526915],"type":"Point"}
}