{
  "type": "Feature",
  "properties": {
    "iso:country":"US",
    "sg:address":"7595 N Overfield Rd",
    "sg:city":"Casa Grande",
    "sg:classifiers":[
        {
            "category":"Professional",
            "type":"Services"
        }
    ],
    "sg:phone":"+1 520 723 3350",
    "sg:postcode":"85294",
    "sg:province":"AZ",
    "wof:name":"Edie Girl Incorporated",
    "wof:placetype":"venue"
},
  "geometry": {"coordinates":[-111.653014,32.947691],"type":"Point"}
}