{
  "type": "Feature",
  "properties": {
    "addr:full":"3777 Grand Ave Phoenix AZ 85019",
    "addr:housenumber":"3777",
    "addr:postcode":"85019",
    "addr:street":"Grand Ave",
    "iso:country":"US",
    "sg:address":"3777 Grand Ave",
    "sg:city":"Phoenix",
    "sg:classifiers":[
        {
            "category":"Shopping",
            "subcategory":"Discount & Variety Stores",
            "type":"Retail Goods"
        }
    ],
    "sg:phone":"+1 602 864 5005",
    "sg:postcode":"85019",
    "sg:province":"AZ",
    "sg:tags":[
        "liquidator"
    ],
    "wof:name":"Vehicle Liquidators",
    "wof:placetype":"venue"
},
  "geometry": {"coordinates":[-112.14022199999999,33.499846],"type":"Point"}
}