{
  "type": "Feature",
  "properties": {
    "iso:country":"US",
    "sg:address":"10700 N 85th Ave",
    "sg:city":"Peoria",
    "sg:classifiers":[
        {
            "category":"Government",
            "subcategory":"Post Office",
            "type":"Public Place"
        }
    ],
    "sg:phone":"+1 623 486 4187",
    "sg:postcode":"85345",
    "sg:province":"AZ",
    "sg:tags":[
        "postal",
        "us"
    ],
    "wof:name":"Peoria Post Office",
    "wof:placetype":"venue"
},
  "geometry": {"coordinates":[-112.242108,33.583629],"type":"Point"}
}