{
  "type": "Feature",
  "properties": {
    "iso:country":"US",
    "sg:address":"5326 E Edwin Rd",
    "sg:city":"Tucson",
    "sg:classifiers":[
        {
            "category":"Professional",
            "subcategory":"Computer Services",
            "type":"Services"
        }
    ],
    "sg:phone":"+1 520 825 4458",
    "sg:postcode":"85739",
    "sg:province":"AZ",
    "sg:tags":[
        "house",
        "design",
        "system"
    ],
    "wof:name":"Progressive CAD",
    "wof:placetype":"venue"
},
  "geometry": {"coordinates":[-110.879138,32.511364],"type":"Point"}
}