{
  "type": "Feature",
  "properties": {
    "iso:country":"US",
    "sg:address":"7014 E 1st Ave",
    "sg:city":"Scottsdale",
    "sg:classifiers":[
        {
            "category":"Restaurant",
            "type":"Food & Drink"
        }
    ],
    "sg:menulink":"http://www.allmenus.com/az/phoenix/267714-arcadia-farms/menu/",
    "sg:phone":"+1 480 941 5665",
    "sg:postcode":"85251",
    "sg:province":"AZ",
    "wof:name":"Arcadia Farms",
    "wof:placetype":"venue"
},
  "geometry": {"coordinates":[-111.92973000000001,33.494243],"type":"Point"}
}