{
  "type": "Feature",
  "properties": {
    "iso:country":"US",
    "sg:address":"1561 N Dysart Rd",
    "sg:city":"Litchfield Park",
    "sg:classifiers":[
        {
            "category":"Retail",
            "subcategory":"Veterinary Services",
            "type":"Services"
        }
    ],
    "sg:phone":"+1 623 935 0044",
    "sg:postcode":"85340",
    "sg:province":"AZ",
    "sg:tags":[
        "veterinarian"
    ],
    "sg:website":"www.banfield.net",
    "wof:name":"Banfield the Pet Hospital",
    "wof:placetype":"venue"
},
  "geometry": {"coordinates":[-112.340426,33.459684],"type":"Point"}
}