{
  "type": "Feature",
  "properties": {
    "iso:country":"US",
    "sg:address":"3333 S 12th Ave",
    "sg:city":"Tucson",
    "sg:classifiers":[
        {
            "category":"Retail",
            "subcategory":"Auto Repair",
            "type":"Services"
        }
    ],
    "sg:phone":"+1 520 622 0886",
    "sg:postcode":"85713",
    "sg:province":"AZ",
    "sg:tags":[
        "transmission"
    ],
    "wof:name":"Pueblo Transmission",
    "wof:placetype":"venue"
},
  "geometry": {"coordinates":[-110.977474,32.185348],"type":"Point"}
}