{
  "type": "Feature",
  "properties": {
    "iso:country":"US",
    "sg:address":"4480 W Peoria Ave",
    "sg:city":"Glendale",
    "sg:classifiers":[
        {
            "category":"Real Estate",
            "subcategory":"Real Estate Services",
            "type":"Services"
        },
        {
            "category":"Real Estate",
            "subcategory":"Real Estate Agent",
            "type":"Services"
        }
    ],
    "sg:phone":"+1 623 533 6418",
    "sg:postcode":"85302",
    "sg:province":"AZ",
    "sg:tags":[
        "management"
    ],
    "wof:name":"Champs Realty",
    "wof:placetype":"venue"
},
  "geometry": {"coordinates":[-112.154994,33.581921],"type":"Point"}
}