{
  "type": "Feature",
  "properties": {
    "iso:country":"US",
    "sg:address":"501 N 4th Ave",
    "sg:city":"Tucson",
    "sg:classifiers":[
        {
            "category":"Ice Cream",
            "type":"Food & Drink"
        }
    ],
    "sg:menulink":"http://www.allmenus.com/az/tucson/164939-dairy-queen/menu/",
    "sg:phone":"+1 520 882 0959",
    "sg:postcode":"85705",
    "sg:province":"AZ",
    "sg:tags":[
        "burger",
        "american"
    ],
    "wof:name":"Dairy Queen",
    "wof:placetype":"venue"
},
  "geometry": {"coordinates":[-110.965932,32.227952],"type":"Point"}
}