{
  "type": "Feature",
  "properties": {
    "iso:country":"US",
    "sg:address":"1000 E Apache Blvd",
    "sg:city":"Tempe",
    "sg:classifiers":[
        {
            "category":"Professional",
            "subcategory":"Management & Consulting",
            "type":"Services"
        }
    ],
    "sg:phone":"+1 480 736 0034",
    "sg:postcode":"85281",
    "sg:province":"AZ",
    "sg:tags":[
        "marketing",
        "program"
    ],
    "sg:website":"www.premiersavings.com",
    "wof:name":"Premier Nationwide Corp",
    "wof:placetype":"venue"
},
  "geometry": {"coordinates":[-111.924459,33.414853],"type":"Point"}
}