{
  "type": "Feature",
  "properties": {
    "iso:country":"US",
    "sg:address":"606 S Plumer Ave",
    "sg:city":"Tucson",
    "sg:classifiers":[
        {
            "category":"Government",
            "subcategory":"Police Station",
            "type":"Public Place"
        }
    ],
    "sg:phone":"+1 520 798 0892",
    "sg:postcode":"85719",
    "sg:province":"AZ",
    "sg:tags":[
        "sheriff"
    ],
    "wof:name":"Pima County Deputy Sheriff",
    "wof:placetype":"venue"
},
  "geometry": {"coordinates":[-110.939493,32.213315],"type":"Point"}
}