{
  "type": "Feature",
  "properties": {
    "iso:country":"US",
    "sg:address":"1827 E Southern Ave",
    "sg:city":"Tempe",
    "sg:classifiers":[
        {
            "category":"Shopping",
            "subcategory":"Computers & Home Electronics",
            "type":"Retail Goods"
        }
    ],
    "sg:phone":"+1 480 838 4306",
    "sg:postcode":"85282",
    "sg:province":"AZ",
    "sg:tags":[
        "consumer"
    ],
    "sg:website":"http://www.shavtronics.com",
    "wof:name":"Shav-Tronics",
    "wof:placetype":"venue"
},
  "geometry": {"coordinates":[-111.907219,33.392977],"type":"Point"}
}