{
  "type": "Feature",
  "properties": {
    "addr:full":"1930 S Roosevelt St Tempe AZ 85281",
    "addr:housenumber":"1930",
    "addr:postcode":"85281",
    "addr:street":"S Roosevelt St",
    "iso:country":"US",
    "sg:address":"1930 S Roosevelt St",
    "sg:city":"Tempe",
    "sg:classifiers":[
        {
            "category":"Manufacturing",
            "subcategory":"Retail Goods",
            "type":"Manufacturing & Wholesale Goods"
        }
    ],
    "sg:phone":"+1 480 968 1328",
    "sg:postcode":"85281",
    "sg:province":"AZ",
    "sg:tags":[
        "product",
        "architectural",
        "mfg"
    ],
    "wof:name":"Russell De Jong",
    "wof:placetype":"venue"
},
  "geometry": {"coordinates":[-111.947919,33.407657],"type":"Point"}
}