{
  "type": "Feature",
  "properties": {
    "iso:country":"US",
    "sg:address":"3037 N 52nd Pl",
    "sg:city":"Phoenix",
    "sg:classifiers":[
        {
            "category":"Building & Trades",
            "subcategory":"Construction",
            "type":"Services"
        }
    ],
    "sg:phone":"+1 602 956 1146",
    "sg:postcode":"85018",
    "sg:province":"AZ",
    "sg:tags":[
        "house"
    ],
    "wof:name":"Todd Alan Cnstr & Dev LL",
    "wof:placetype":"venue"
},
  "geometry": {"coordinates":[-111.968417,33.4835],"type":"Point"}
}