{
  "type": "Feature",
  "properties": {
    "iso:country":"US",
    "sg:address":"4550 E Broadway Blvd",
    "sg:city":"Tucson",
    "sg:classifiers":[
        {
            "category":"Government",
            "subcategory":"Office",
            "type":"Public Place"
        }
    ],
    "sg:phone":"+1 520 318 0326",
    "sg:postcode":"85711",
    "sg:province":"AZ",
    "sg:tags":[
        "armed",
        "force",
        "recruiting"
    ],
    "wof:name":"US Navy Recruiting",
    "wof:placetype":"venue"
},
  "geometry": {"coordinates":[-110.895454,32.221439],"type":"Point"}
}