{
  "type": "Feature",
  "properties": {
    "addr:full":"1795 E Bartlett Pl Chandler AZ 85249",
    "addr:housenumber":"1795",
    "addr:postcode":"85249",
    "addr:street":"E Bartlett Pl",
    "iso:country":"US",
    "sg:address":"1795 E Bartlett Pl",
    "sg:city":"Chandler",
    "sg:classifiers":[
        {
            "category":"Shopping",
            "subcategory":"Clothing, Apparel, & Fashions",
            "type":"Retail Goods"
        }
    ],
    "sg:phone":"+1 480 963 4444",
    "sg:postcode":"85249",
    "sg:province":"AZ",
    "sg:tags":[
        "handbag"
    ],
    "wof:name":"Designer Doubles",
    "wof:placetype":"venue"
},
  "geometry": {"coordinates":[-111.808196,33.234097],"type":"Point"}
}