{
  "type": "Feature",
  "properties": {
    "addr:full":"1425 E Indigo Cir Mesa AZ 85203",
    "addr:housenumber":"1425",
    "addr:postcode":"85203",
    "addr:street":"E Indigo Cir",
    "iso:country":"US",
    "sg:address":"1425 E Indigo Cir",
    "sg:city":"Mesa",
    "sg:classifiers":[
        {
            "category":"Building & Trades",
            "subcategory":"Landscaping Services",
            "type":"Services"
        }
    ],
    "sg:phone":"+1 480 833 4957",
    "sg:postcode":"85203",
    "sg:province":"AZ",
    "sg:tags":[
        "lawn",
        "maintenance",
        "grounds"
    ],
    "wof:name":"Caddy Brothers",
    "wof:placetype":"venue"
},
  "geometry": {"coordinates":[-111.80212400000001,33.445372],"type":"Point"}
}