{
  "type": "Feature",
  "properties": {
    "addr:full":"405 S. Campbell Ave Tucson AZ 85719",
    "addr:housenumber":"405",
    "addr:postcode":"85719",
    "addr:street":"S. Campbell Ave",
    "iso:country":"US",
    "sg:address":"405 S. Campbell Ave",
    "sg:city":"Tucson",
    "sg:classifiers":[
        {
            "category":"Home & Garden",
            "subcategory":"Home Furnishings",
            "type":"Retail Goods"
        },
        {
            "category":"Building & Trades",
            "subcategory":"Construction",
            "type":"Services"
        },
        {
            "category":"Home & Garden",
            "subcategory":"Furniture",
            "type":"Retail Goods"
        },
        {
            "category":"Home & Garden",
            "subcategory":"Building Materials",
            "type":"Retail Goods"
        },
        {
            "category":"Manufacturing",
            "subcategory":"Wood Products",
            "type":"Manufacturing & Wholesale Goods"
        },
        {
            "category":"Manufacturing",
            "subcategory":"Building Materials",
            "type":"Manufacturing & Wholesale Goods"
        }
    ],
    "sg:phone":"+1 520 792 1445",
    "sg:postcode":"85719",
    "sg:province":"AZ",
    "sg:tags":[
        "bathroom",
        "manufacturer",
        "cabinets-wholesale",
        "solid",
        "equipment-household",
        "top",
        "counter",
        "surface",
        "improvement",
        "refacing",
        "resurfacing",
        "planning",
        "granite",
        "cabinet",
        "remodeling",
        "cabinets-refinishing",
        "kitchen"
    ],
    "sg:website":"http://www.graniteguysandcabinets.com",
    "wof:name":"Granite Guys & Cabinets",
    "wof:placetype":"venue"
},
  "geometry": {"coordinates":[-110.943741,32.217377],"type":"Point"}
}