{
  "type": "Feature",
  "properties": {
    "iso:country":"US",
    "sg:address":"3215 North Arizona Ave",
    "sg:city":"Chandler",
    "sg:classifiers":[
        {
            "category":"Building & Trades",
            "subcategory":"Construction",
            "type":"Services"
        }
    ],
    "sg:phone":"+1 602 648 2267",
    "sg:postcode":"85225",
    "sg:province":"AZ",
    "sg:tags":[
        "contractor",
        "handyman",
        "heating",
        "conditioning/hvac",
        "air"
    ],
    "sg:website":"appliance-repair-installs.phoeni...",
    "wof:name":"P & A Services",
    "wof:placetype":"venue"
},
  "geometry": {"coordinates":[-111.841775,33.353791],"type":"Point"}
}