{
  "type": "Feature",
  "properties": {
    "iso:country":"US",
    "sg:address":"63662 E Whispering Tree Ln",
    "sg:city":"Tucson",
    "sg:classifiers":[
        {
            "category":"Building & Trades",
            "subcategory":"Construction",
            "type":"Services"
        }
    ],
    "sg:phone":"+1 520 825 6761",
    "sg:postcode":"85739",
    "sg:province":"AZ",
    "sg:tags":[
        "house"
    ],
    "wof:name":"Trb Inc",
    "wof:placetype":"venue"
},
  "geometry": {"coordinates":[-110.88057499999999,32.538079],"type":"Point"}
}