{
  "type": "Feature",
  "properties": {
    "iso:country":"US",
    "sg:address":"999 W Bell Rd",
    "sg:city":"Phoenix",
    "sg:classifiers":[
        {
            "category":"Retail",
            "subcategory":"Auto Repair",
            "type":"Services"
        }
    ],
    "sg:phone":"+1 877 489 1536",
    "sg:postcode":"85023",
    "sg:province":"AZ",
    "sg:tags":[
        "engine",
        "installation",
        "exchange"
    ],
    "sg:website":"http://www.chapmanhyundaiaz.com",
    "wof:name":"Chapman Hyundai of Bell Road",
    "wof:placetype":"venue"
},
  "geometry": {"coordinates":[-112.086334,33.640126],"type":"Point"}
}