{
  "type": "Feature",
  "properties": {
    "addr:full":"400 N Ocotillo Rd Benson AZ 85602",
    "addr:housenumber":"400",
    "addr:postcode":"85602",
    "addr:street":"N Ocotillo Rd",
    "iso:country":"US",
    "sg:address":"400 N Ocotillo Rd",
    "sg:city":"Benson",
    "sg:classifiers":[
        {
            "category":"Fast Food",
            "type":"Food & Drink"
        },
        {
            "category":"Restaurant",
            "type":"Food & Drink"
        }
    ],
    "sg:phone":"+1 520 586 3871",
    "sg:postcode":"85602",
    "sg:province":"AZ",
    "sg:tags":[
        "american",
        "hot",
        "hamburger",
        "dog"
    ],
    "sg:website":"http://www.bk.com",
    "wof:name":"Burger King",
    "wof:placetype":"venue"
},
  "geometry": {"coordinates":[-110.307076,31.979084],"type":"Point"}
}