{
  "type": "Feature",
  "properties": {
    "iso:country":"US",
    "sg:address":"5059 W. Mercury Way",
    "sg:city":"Chandler",
    "sg:classifiers":[
        {
            "category":"Education",
            "subcategory":"Music School",
            "type":"Public Place"
        },
        {
            "category":"Education",
            "subcategory":"Special Training",
            "type":"Public Place"
        }
    ],
    "sg:phone":"+1 480 678 5840",
    "sg:postcode":"85226",
    "sg:province":"AZ",
    "sg:tags":[
        "instrument",
        "teacher",
        "musical",
        "private",
        "tutor"
    ],
    "sg:website":"www.micahbeverly.com",
    "wof:name":"Guitar Lessons with Micah Beverly",
    "wof:placetype":"venue"
},
  "geometry": {"coordinates":[-111.930036,33.302299],"type":"Point"}
}