{
  "type": "Feature",
  "properties": {
    "iso:country":"US",
    "sg:address":"4835 E Exeter Blvd",
    "sg:city":"Phoenix",
    "sg:classifiers":[
        {
            "category":"Banks & Credit Unions",
            "subcategory":"Bank",
            "type":"Services"
        }
    ],
    "sg:phone":"+1 480 557 1745",
    "sg:postcode":"85018",
    "sg:province":"AZ",
    "wof:name":"Genetic Savings & Clone, Inc.",
    "wof:placetype":"venue"
},
  "geometry": {"coordinates":[-111.976498,33.504152],"type":"Point"}
}