{
  "type": "Feature",
  "properties": {
    "iso:country":"US",
    "sg:address":"401 S Willow St",
    "sg:city":"Tucson",
    "sg:classifiers":[
        {
            "category":"Building & Trades",
            "subcategory":"Locksmith",
            "type":"Services"
        }
    ],
    "sg:phone":"+1 866 589 8782",
    "sg:postcode":"85705",
    "sg:province":"AZ",
    "sg:tags":[
        "key"
    ],
    "wof:name":"A 1 Emergency Locksmith",
    "wof:placetype":"venue"
},
  "geometry": {"coordinates":[-110.958046,32.460915],"type":"Point"}
}