{
  "type": "Feature",
  "properties": {
    "iso:country":"US",
    "sg:address":"423 N Country Club Dr",
    "sg:city":"Mesa",
    "sg:classifiers":[
        {
            "category":"Recreation",
            "type":"Entertainment"
        }
    ],
    "sg:phone":"+1 480 668 8888",
    "sg:postcode":"85201",
    "sg:province":"AZ",
    "sg:tags":[
        "psychic",
        "medium"
    ],
    "wof:name":"Mystical Magic-Phsychic Rdng",
    "wof:placetype":"venue"
},
  "geometry": {"coordinates":[-111.83986899999999,33.4231],"type":"Point"}
}