{
  "type": "Feature",
  "properties": {
    "iso:country":"US",
    "sg:address":"4305 W Saturn Way",
    "sg:city":"Chandler",
    "sg:classifiers":[
        {
            "category":"Shopping",
            "type":"Retail Goods"
        }
    ],
    "sg:phone":"+1 480 961 4424",
    "sg:postcode":"85226",
    "sg:province":"AZ",
    "sg:tags":[
        "educational",
        "material"
    ],
    "wof:name":"Zephyr Inc",
    "wof:placetype":"venue"
},
  "geometry": {"coordinates":[-111.918706,33.300906],"type":"Point"}
}