{
  "type": "Feature",
  "properties": {
    "iso:country":"US",
    "sg:address":"908 W Coconino Ave",
    "sg:city":"Flagstaff",
    "sg:classifiers":[
        {
            "category":"Real Estate",
            "subcategory":"Architect",
            "type":"Services"
        }
    ],
    "sg:phone":"+1 928 214 7236",
    "sg:postcode":"86001",
    "sg:province":"AZ",
    "sg:tags":[
        "building",
        "designer"
    ],
    "wof:name":"Access Design",
    "wof:placetype":"venue"
},
  "geometry": {"coordinates":[-111.659206,35.197944],"type":"Point"}
}