{
  "type": "Feature",
  "properties": {
    "addr:full":"4791 S. Hudson Pl Chandler AZ 85249",
    "addr:housenumber":"4791",
    "addr:postcode":"85249",
    "addr:street":"S. Hudson Pl",
    "iso:country":"US",
    "sg:address":"4791 S. Hudson Pl",
    "sg:city":"Chandler",
    "sg:classifiers":[
        {
            "category":"Building & Trades",
            "subcategory":"Landscaping Services",
            "type":"Services"
        }
    ],
    "sg:phone":"+1 602 882 2820",
    "sg:postcode":"85249",
    "sg:province":"AZ",
    "sg:website":"www.hshlandscape.com",
    "wof:name":"Home Sweet Home Landscaping",
    "wof:placetype":"venue"
},
  "geometry": {"coordinates":[-111.81858699999999,33.236344],"type":"Point"}
}