{
  "type": "Feature",
  "properties": {
    "iso:country":"US",
    "sg:address":"1500 Acoma Ln W",
    "sg:city":"Lake Havasu City",
    "sg:classifiers":[
        {
            "category":"Building & Trades",
            "subcategory":"Construction",
            "type":"Services"
        }
    ],
    "sg:phone":"+1 928 855 6871",
    "sg:postcode":"86403",
    "sg:province":"AZ",
    "sg:tags":[
        "concrete",
        "contractor"
    ],
    "wof:name":"Querry & Querry Concrete Inc",
    "wof:placetype":"venue"
},
  "geometry": {"coordinates":[-114.355774,34.496227],"type":"Point"}
}