{
  "type": "Feature",
  "properties": {
    "iso:country":"US",
    "sg:address":"1850 E 20th St",
    "sg:city":"Yuma",
    "sg:classifiers":[
        {
            "category":"Utilities",
            "subcategory":"Telephone",
            "type":"Services"
        }
    ],
    "sg:phone":"+1 928 343 8994",
    "sg:postcode":"85365",
    "sg:province":"AZ",
    "sg:tags":[
        "communications"
    ],
    "wof:name":"Qwest",
    "wof:placetype":"venue"
},
  "geometry": {"coordinates":[-114.60355199999999,32.691375],"type":"Point"}
}