{
  "type": "Feature",
  "properties": {
    "iso:country":"US",
    "sg:address":"7133 W Wier Ave",
    "sg:city":"Phoenix",
    "sg:classifiers":[
        {
            "category":"Autos & Motor Vehicles",
            "subcategory":"Fuel & Gas Station",
            "type":"Retail Goods"
        }
    ],
    "sg:phone":"+1 623 936 3808",
    "sg:postcode":"85043",
    "sg:province":"AZ",
    "sg:tags":[
        "station",
        "gasoline"
    ],
    "wof:name":"Pioneer Truck Sales Salv & Svc",
    "wof:placetype":"venue"
},
  "geometry": {"coordinates":[-112.216427,33.404516],"type":"Point"}
}