{
  "type": "Feature",
  "properties": {
    "iso:country":"US",
    "sg:address":"3250 US Hwy 70",
    "sg:city":"Thatcher",
    "sg:classifiers":[
        {
            "category":"Home & Garden",
            "subcategory":"Hardware",
            "type":"Retail Goods"
        }
    ],
    "sg:phone":"+1 928 428 4431",
    "sg:postcode":"85552",
    "sg:province":"AZ",
    "wof:name":"Thatcher Building Supply",
    "wof:placetype":"venue"
},
  "geometry": {"coordinates":[-109.75411099999999,32.849199],"type":"Point"}
}