{
  "type": "Feature",
  "properties": {
    "addr:full":"200 W Cooley St Show Low AZ 85901",
    "addr:housenumber":"200",
    "addr:postcode":"85901",
    "addr:street":"W Cooley St",
    "iso:country":"US",
    "sg:address":"200 W Cooley St",
    "sg:city":"Show Low",
    "sg:classifiers":[
        {
            "category":"Building & Trades",
            "subcategory":"Construction",
            "type":"Services"
        }
    ],
    "sg:phone":"+1 928 532 4080",
    "sg:postcode":"85901",
    "sg:province":"AZ",
    "sg:tags":[
        "marking",
        "maintenance",
        "parking"
    ],
    "sg:website":"www.ci.show-low.az.us",
    "wof:name":"Show Low City Public Works",
    "wof:placetype":"venue"
},
  "geometry": {"coordinates":[-110.04610700000001,34.25325],"type":"Point"}
}