{
  "type": "Feature",
  "properties": {
    "iso:country":"US",
    "sg:address":"310 W Frontier St",
    "sg:city":"Eloy",
    "sg:classifiers":[
        {
            "category":"Restaurant",
            "type":"Food & Drink"
        }
    ],
    "sg:phone":"+1 520 466 3473",
    "sg:postcode":"85231",
    "sg:province":"AZ",
    "sg:tags":[
        "eating"
    ],
    "wof:name":"Encore Drive-In",
    "wof:placetype":"venue"
},
  "geometry": {"coordinates":[-111.561339,32.756052],"type":"Point"}
}