{
  "type": "Feature",
  "properties": {
    "addr:full":"6063 E Arbor Ave Mesa AZ 85206",
    "addr:housenumber":"6063",
    "addr:postcode":"85206",
    "addr:street":"E Arbor Ave",
    "iso:country":"US",
    "sg:address":"6063 E Arbor Ave",
    "sg:city":"Mesa",
    "sg:classifiers":[
        {
            "category":"Social Services",
            "subcategory":"Adult Care",
            "type":"Services"
        }
    ],
    "sg:phone":"+1 480 654 8200",
    "sg:postcode":"85206",
    "sg:province":"AZ",
    "sg:tags":[
        "home",
        "residential"
    ],
    "sg:website":"www.seniorhousing.net",
    "wof:name":"Arbor Rose",
    "wof:placetype":"venue"
},
  "geometry": {"coordinates":[-111.700354,33.413643],"type":"Point"}
}