{
  "type": "Feature",
  "properties": {
    "iso:country":"US",
    "sg:address":"18622 N 90th Way",
    "sg:city":"Scottsdale",
    "sg:classifiers":[
        {
            "category":"Shopping",
            "subcategory":"Computers & Home Electronics",
            "type":"Retail Goods"
        }
    ],
    "sg:phone":"+1 480 634 5820",
    "sg:postcode":"85255",
    "sg:province":"AZ",
    "sg:tags":[
        "software"
    ],
    "wof:name":"Krystalsky Software Inc",
    "wof:placetype":"venue"
},
  "geometry": {"coordinates":[-111.885842,33.65522],"type":"Point"}
}