{
  "type": "Feature",
  "properties": {
    "iso:country":"US",
    "sg:address":"3555 W Van Buren St",
    "sg:city":"Phoenix",
    "sg:classifiers":[
        {
            "category":"Personal",
            "subcategory":"Beauty Salon",
            "type":"Services"
        }
    ],
    "sg:phone":"+1 602 415 0200",
    "sg:postcode":"85009",
    "sg:province":"AZ",
    "wof:name":"Yolis Sala De Delleza",
    "wof:placetype":"venue"
},
  "geometry": {"coordinates":[-112.13673799999999,33.4514],"type":"Point"}
}