{
  "type": "Feature",
  "properties": {
    "iso:country":"US",
    "sg:address":"425 S Muleshoe Rd",
    "sg:city":"Apache Junction",
    "sg:classifiers":[
        {
            "category":"Building & Trades",
            "subcategory":"Landscaping Services",
            "type":"Services"
        }
    ],
    "sg:phone":"+1 480 671 0023",
    "sg:postcode":"85219",
    "sg:province":"AZ",
    "sg:tags":[
        "heavy",
        "construction"
    ],
    "wof:name":"J B Trenching",
    "wof:placetype":"venue"
},
  "geometry": {"coordinates":[-111.496222,33.411311],"type":"Point"}
}