{
  "type": "Feature",
  "properties": {
    "iso:country":"US",
    "sg:address":"6030 E Ridge Road",
    "sg:city":"Cave Creek",
    "sg:classifiers":[
        {
            "category":"Building & Trades",
            "subcategory":"Construction",
            "type":"Services"
        }
    ],
    "sg:phone":"+1 480 575 9005",
    "sg:postcode":"85331",
    "sg:province":"AZ",
    "sg:tags":[
        "contractor"
    ],
    "wof:name":"Carneal Jeff Contractor",
    "wof:placetype":"venue"
},
  "geometry": {"coordinates":[-111.950165,33.830241],"type":"Point"}
}