{
  "type": "Feature",
  "properties": {
    "addr:full":"11212 N 37th Ave Phoenix AZ 85029",
    "addr:housenumber":"11212",
    "addr:postcode":"85029",
    "addr:street":"N 37Th Ave",
    "iso:country":"US",
    "sg:address":"11212 N 37th Ave",
    "sg:city":"Phoenix",
    "sg:classifiers":[
        {
            "category":"Travel",
            "subcategory":"Travel Agent",
            "type":"Entertainment"
        }
    ],
    "sg:phone":"+1 623 329 4753",
    "sg:postcode":"85029",
    "sg:province":"AZ",
    "sg:tags":[
        "agency",
        "services-commercial"
    ],
    "wof:name":"Tranquil Travel",
    "wof:placetype":"venue"
},
  "geometry": {"coordinates":[-112.138395,33.587671],"type":"Point"}
}