{
  "type": "Feature",
  "properties": {
    "addr:full":"1788 Hwy 95 Bullhead City AZ 86442",
    "addr:housenumber":"1788",
    "addr:postcode":"86442",
    "addr:street":"Hwy 95",
    "iso:country":"US",
    "sg:address":"1788 Hwy 95",
    "sg:city":"Bullhead City",
    "sg:classifiers":[
        {
            "category":"Retail",
            "subcategory":"Portrait Studio",
            "type":"Services"
        }
    ],
    "sg:phone":"+1 928 763 8757",
    "sg:postcode":"86442",
    "sg:province":"AZ",
    "sg:tags":[
        "photographer"
    ],
    "sg:website":"www.camworksphoto.com",
    "wof:name":"Camera Works Photography",
    "wof:placetype":"venue"
},
  "geometry": {"coordinates":[-114.588626,35.120732],"type":"Point"}
}