{
  "type": "Feature",
  "properties": {
    "iso:country":"US",
    "sg:address":"108 E Bonita St",
    "sg:city":"Payson",
    "sg:classifiers":[
        {
            "category":"Shopping",
            "subcategory":"Florist",
            "type":"Retail Goods"
        }
    ],
    "sg:phone":"+1 928 474 8736",
    "sg:postcode":"85541",
    "sg:province":"AZ",
    "wof:name":"Finishing Touch Flowers & Gfts",
    "wof:placetype":"venue"
},
  "geometry": {"coordinates":[-111.32254,34.236532],"type":"Point"}
}