{
  "type": "Feature",
  "properties": {
    "iso:country":"US",
    "sg:address":"9633 S 48th St",
    "sg:city":"Phoenix",
    "sg:classifiers":[
        {
            "category":"Professional",
            "subcategory":"Computer Services",
            "type":"Services"
        }
    ],
    "sg:phone":"+1 480 785 2262",
    "sg:postcode":"85044",
    "sg:province":"AZ",
    "sg:tags":[
        "processing",
        "datum"
    ],
    "sg:website":"www.checkgateway.com",
    "wof:name":"First American Payment Prcssng",
    "wof:placetype":"venue"
},
  "geometry": {"coordinates":[-111.976701,33.359144],"type":"Point"}
}