{
  "type": "Feature",
  "properties": {
    "iso:country":"US",
    "sg:address":"20 N Rogers",
    "sg:city":"Mesa",
    "sg:classifiers":[
        {
            "category":"Wholesale",
            "subcategory":"Machinery & Supplies",
            "type":"Manufacturing & Wholesale Goods"
        }
    ],
    "sg:phone":"+1 480 529 0279",
    "sg:postcode":"85201",
    "sg:province":"AZ",
    "sg:tags":[
        "equipment",
        "industrial"
    ],
    "wof:name":"Decker Auto & Equipment",
    "wof:placetype":"venue"
},
  "geometry": {"coordinates":[-111.862247,33.415911],"type":"Point"}
}