{
  "type": "Feature",
  "properties": {
    "iso:country":"US",
    "sg:address":"5055 W Ray Rd Suite 9/10",
    "sg:city":"Chandler",
    "sg:classifiers":[
        {
            "category":"Arena",
            "subcategory":"Sports Club",
            "type":"Entertainment"
        }
    ],
    "sg:phone":"+1 602 485 5728",
    "sg:postcode":"85226",
    "sg:province":"AZ",
    "sg:tags":[
        "martial art"
    ],
    "sg:website":"www.reactdefense.com",
    "wof:name":"R.E.A.C.T. Defense Systems",
    "wof:placetype":"venue"
},
  "geometry": {"coordinates":[-111.929312,33.319375],"type":"Point"}
}