{
  "type": "Feature",
  "properties": {
    "iso:country":"US",
    "sg:address":"1239 E Cheryl Dr",
    "sg:city":"Phoenix",
    "sg:classifiers":[
        {
            "category":"Building & Trades",
            "subcategory":"Plumbing",
            "type":"Services"
        }
    ],
    "sg:phone":"+1 602 870 3621",
    "sg:postcode":"85020",
    "sg:province":"AZ",
    "sg:tags":[
        "irrigation",
        "contractor"
    ],
    "wof:name":"Jsa Company",
    "wof:placetype":"venue"
},
  "geometry": {"coordinates":[-112.055237,33.578517],"type":"Point"}
}