{
  "type": "Feature",
  "properties": {
    "iso:country":"US",
    "sg:address":"49 S Sycamore",
    "sg:city":"Mesa",
    "sg:classifiers":[
        {
            "category":"Professional",
            "type":"Services"
        }
    ],
    "sg:phone":"+1 480 655 1888",
    "sg:postcode":"85202",
    "sg:province":"AZ",
    "wof:name":"Windhawk",
    "wof:placetype":"venue"
},
  "geometry": {"coordinates":[-111.869933,33.413515],"type":"Point"}
}