{
  "type": "Feature",
  "properties": {
    "iso:country":"US",
    "sg:address":"4727 E Southern Ave",
    "sg:city":"Phoenix",
    "sg:classifiers":[
        {
            "category":"Shopping",
            "subcategory":"Jewelry",
            "type":"Retail Goods"
        }
    ],
    "sg:phone":"+1 602 438 1360",
    "sg:postcode":"85042",
    "sg:province":"AZ",
    "sg:tags":[
        "item",
        "gift"
    ],
    "wof:name":"Moriah",
    "wof:placetype":"venue"
},
  "geometry": {"coordinates":[-111.979089,33.392698],"type":"Point"}
}