{
  "type": "Feature",
  "properties": {
    "addr:full":"6360 E Thomas Rd Scottsdale AZ 85251",
    "addr:housenumber":"6360",
    "addr:postcode":"85251",
    "addr:street":"E Thomas Rd",
    "iso:country":"US",
    "sg:address":"6360 E Thomas Rd",
    "sg:city":"Scottsdale",
    "sg:classifiers":[
        {
            "category":"Real Estate",
            "subcategory":"Architect",
            "type":"Services"
        }
    ],
    "sg:phone":"+1 602 272 9406",
    "sg:postcode":"85251",
    "sg:province":"AZ",
    "sg:tags":[
        "building",
        "construction"
    ],
    "wof:name":"JQC Development Co LLC",
    "wof:placetype":"venue"
},
  "geometry": {"coordinates":[-111.946268,33.480234],"type":"Point"}
}