{
  "type": "Feature",
  "properties": {
    "iso:country":"US",
    "sg:address":"614 Kinglet Ct",
    "sg:city":"Prescott",
    "sg:classifiers":[
        {
            "category":"Building & Trades",
            "subcategory":"Construction",
            "type":"Services"
        }
    ],
    "sg:phone":"+1 928 776 8800",
    "sg:postcode":"86301",
    "sg:province":"AZ",
    "sg:tags":[
        "home",
        "builder"
    ],
    "wof:name":"Pinon Homes",
    "wof:placetype":"venue"
},
  "geometry": {"coordinates":[-112.394359,34.553705],"type":"Point"}
}