{
  "type": "Feature",
  "properties": {
    "addr:full":"1750 W Frye Rd Chandler AZ 85224",
    "addr:housenumber":"1750",
    "addr:postcode":"85224",
    "addr:street":"W Frye Rd",
    "iso:country":"US",
    "sg:address":"1750 W Frye Rd",
    "sg:city":"Chandler",
    "sg:classifiers":[
        {
            "category":"Professional",
            "type":"Services"
        }
    ],
    "sg:phone":"+1 480 812 9874",
    "sg:postcode":"85224",
    "sg:province":"AZ",
    "sg:tags":[
        "establishment"
    ],
    "wof:name":"Chandler Med Ind LTD",
    "wof:placetype":"venue"
},
  "geometry": {"coordinates":[-111.87591500000001,33.298761],"type":"Point"}
}