{
  "type": "Feature",
  "properties": {
    "addr:full":"4000 N 7th St Phoenix AZ 85014",
    "addr:housenumber":"4000",
    "addr:postcode":"85014",
    "addr:street":"N 7Th St",
    "iso:country":"US",
    "sg:address":"4000 N 7th St",
    "sg:city":"Phoenix",
    "sg:classifiers":[
        {
            "category":"Utilities",
            "subcategory":"Cable",
            "type":"Services"
        }
    ],
    "sg:phone":"+1 602 248 8333",
    "sg:postcode":"85014",
    "sg:province":"AZ",
    "sg:tags":[
        "television"
    ],
    "wof:name":"Indevideo Company Inc",
    "wof:placetype":"venue"
},
  "geometry": {"coordinates":[-112.065119,33.493075],"type":"Point"}
}