{
  "type": "Feature",
  "properties": {
    "addr:full":"2704 W 16th St Yuma AZ 85364",
    "addr:housenumber":"2704",
    "addr:postcode":"85364",
    "addr:street":"W 16Th St",
    "iso:country":"US",
    "sg:address":"2704 W 16th St",
    "sg:city":"Yuma",
    "sg:classifiers":[
        {
            "category":"Shopping",
            "subcategory":"Pharmacy",
            "type":"Retail Goods"
        }
    ],
    "sg:phone":"+1 928 782 9566",
    "sg:postcode":"85364",
    "sg:province":"AZ",
    "wof:name":"Rite Aid",
    "wof:placetype":"venue"
},
  "geometry": {"coordinates":[-114.65299,32.698524],"type":"Point"}
}