{
  "type": "Feature",
  "properties": {
    "iso:country":"US",
    "sg:address":"901 W Congress St",
    "sg:city":"Tucson",
    "sg:classifiers":[
        {
            "category":"Retail",
            "subcategory":"Portrait Studio",
            "type":"Services"
        }
    ],
    "sg:phone":"+1 520 882 3700",
    "sg:postcode":"85745",
    "sg:province":"AZ",
    "sg:tags":[
        "identification",
        "card"
    ],
    "wof:name":"Sterling Cards",
    "wof:placetype":"venue"
},
  "geometry": {"coordinates":[-110.98845,32.220053],"type":"Point"}
}