{
  "type": "Feature",
  "properties": {
    "iso:country":"US",
    "sg:address":"20701 N Scottsdale Rd",
    "sg:city":"Scottsdale",
    "sg:classifiers":[
        {
            "category":"Bars & Pubs",
            "type":"Food & Drink"
        }
    ],
    "sg:menulink":"http://www.allmenus.com/az/phoenix/4589-everetts-steakhouse--blues-bar/menu/",
    "sg:phone":"+1 480 515 5891",
    "sg:postcode":"85255",
    "sg:province":"AZ",
    "sg:tags":[
        "american",
        "steakhouse"
    ],
    "wof:name":"Everett's Steakhouse & Blues Bar",
    "wof:placetype":"venue"
},
  "geometry": {"coordinates":[-111.92542899999999,33.6757],"type":"Point"}
}