{
  "type": "Feature",
  "properties": {
    "addr:full":"2840 W Chandler Boulevard Chandler AZ 85224",
    "addr:housenumber":"2840",
    "addr:postcode":"85224",
    "addr:street":"W Chandler Boulevard",
    "iso:country":"US",
    "sg:address":"2840 W Chandler Boulevard",
    "sg:city":"Chandler",
    "sg:classifiers":[
        {
            "category":"Retail",
            "subcategory":"Veterinary Services",
            "type":"Services"
        }
    ],
    "sg:phone":"+1 480 814 7636",
    "sg:postcode":"85224",
    "sg:province":"AZ",
    "sg:tags":[
        "veterinarian"
    ],
    "wof:name":"Banfield the Pet Hospital",
    "wof:placetype":"venue"
},
  "geometry": {"coordinates":[-111.891864,33.306067],"type":"Point"}
}