{
  "type": "Feature",
  "properties": {
    "iso:country":"US",
    "sg:address":"2323 E Greenlaw Ln Ste 9",
    "sg:city":"Flagstaff",
    "sg:classifiers":[
        {
            "category":"Professional",
            "subcategory":"Accounting & Tax Preparation",
            "type":"Services"
        }
    ],
    "sg:phone":"+1 928 526 8700",
    "sg:postcode":"86004",
    "sg:province":"AZ",
    "sg:tags":[
        "bookkeeping",
        "return",
        "preparation-business"
    ],
    "wof:name":"Northern Az Tax And Accounting P",
    "wof:placetype":"venue"
},
  "geometry": {"coordinates":[-111.612047,35.215464],"type":"Point"}
}