{
  "type": "Feature",
  "properties": {
    "iso:country":"US",
    "sg:address":"1313 S Val Vista Dr Ofc",
    "sg:city":"Mesa",
    "sg:classifiers":[
        {
            "category":"Real Estate",
            "subcategory":"Real Estate Operator",
            "type":"Services"
        }
    ],
    "sg:phone":"+1 480 830 2988",
    "sg:postcode":"85204",
    "sg:province":"AZ",
    "sg:tags":[
        "apartment"
    ],
    "sg:website":"www.gentryswalkapts.com",
    "wof:name":"Gentry's Walk",
    "wof:placetype":"venue"
},
  "geometry": {"coordinates":[-111.753998,33.391602],"type":"Point"}
}