{
  "type": "Feature",
  "properties": {
    "addr:full":"2146 S 8th Ave Yuma AZ 85364",
    "addr:housenumber":"2146",
    "addr:postcode":"85364",
    "addr:street":"S 8Th Ave",
    "iso:country":"US",
    "sg:address":"2146 S 8th Ave",
    "sg:city":"Yuma",
    "sg:classifiers":[
        {
            "category":"Building & Trades",
            "subcategory":"Construction",
            "type":"Services"
        }
    ],
    "sg:phone":"+1 928 782 9716",
    "sg:postcode":"85364",
    "sg:province":"AZ",
    "sg:tags":[
        "industrial"
    ],
    "wof:name":"Forever Living Products",
    "wof:placetype":"venue"
},
  "geometry": {"coordinates":[-114.629031,32.689133],"type":"Point"}
}