{
  "type": "Feature",
  "properties": {
    "iso:country":"US",
    "sg:address":"7076 E Golf Links Rd",
    "sg:city":"Tucson",
    "sg:classifiers":[
        {
            "category":"Restaurant",
            "type":"Food & Drink"
        }
    ],
    "sg:menulink":"http://www.allmenus.com/az/tucson/87671-little-caesars-pizza/menu/",
    "sg:phone":"+1 520 747 4956",
    "sg:postcode":"85730",
    "sg:province":"AZ",
    "sg:tags":[
        "american",
        "pizza"
    ],
    "wof:name":"Little Caesar's Pizza",
    "wof:placetype":"venue"
},
  "geometry": {"coordinates":[-110.841526,32.190605],"type":"Point"}
}