{
  "type": "Feature",
  "properties": {
    "iso:country":"US",
    "sg:address":"1111 E Limberlost Dr",
    "sg:city":"Tucson",
    "sg:classifiers":[
        {
            "category":"Professional",
            "subcategory":"Business Services",
            "type":"Services"
        }
    ],
    "sg:phone":"+1 520 292 1350",
    "sg:postcode":"85719",
    "sg:province":"AZ",
    "sg:tags":[
        "paper"
    ],
    "wof:name":"Impulses Unlimited",
    "wof:placetype":"venue"
},
  "geometry": {"coordinates":[-110.953122,32.28304],"type":"Point"}
}