{
  "type": "Feature",
  "properties": {
    "iso:country":"US",
    "sg:address":"638 W Broadway Rd Ste 305",
    "sg:city":"Mesa",
    "sg:classifiers":[
        {
            "category":"Health Services",
            "subcategory":"Medical Lab",
            "type":"Services"
        }
    ],
    "sg:phone":"+1 480 610 1800",
    "sg:postcode":"85210",
    "sg:province":"AZ",
    "sg:tags":[
        "laboratory",
        "dental"
    ],
    "wof:name":"Signature Dental Studio",
    "wof:placetype":"venue"
},
  "geometry": {"coordinates":[-111.845665,33.407759],"type":"Point"}
}