{
  "type": "Feature",
  "properties": {
    "iso:country":"US",
    "sg:address":"20034 N 27th Pl",
    "sg:city":"Phoenix",
    "sg:classifiers":[
        {
            "category":"Building & Trades",
            "subcategory":"Construction",
            "type":"Services"
        }
    ],
    "sg:phone":"+1 602 569 6488",
    "sg:postcode":"85050",
    "sg:province":"AZ",
    "sg:tags":[
        "general",
        "contractor"
    ],
    "wof:name":"Bme Development",
    "wof:placetype":"venue"
},
  "geometry": {"coordinates":[-112.023971,33.66759],"type":"Point"}
}