{
  "type": "Feature",
  "properties": {
    "iso:country":"US",
    "sg:address":"3131 N Black Canyon Hwy",
    "sg:city":"Phoenix",
    "sg:classifiers":[
        {
            "category":"Professional",
            "subcategory":"Business Services",
            "type":"Services"
        }
    ],
    "sg:phone":"+1 602 954 3634",
    "sg:postcode":"85015",
    "sg:province":"AZ",
    "sg:tags":[
        "holding"
    ],
    "wof:name":"De Novo Holdings",
    "wof:placetype":"venue"
},
  "geometry": {"coordinates":[-112.112732,33.482137],"type":"Point"}
}