{
  "type": "Feature",
  "properties": {
    "addr:full":"1506 E Malibu Dr Tempe AZ 85282",
    "addr:housenumber":"1506",
    "addr:postcode":"85282",
    "addr:street":"E Malibu Dr",
    "iso:country":"US",
    "sg:address":"1506 E Malibu Dr",
    "sg:city":"Tempe",
    "sg:classifiers":[
        {
            "category":"Home & Garden",
            "subcategory":"Building Materials",
            "type":"Retail Goods"
        }
    ],
    "sg:phone":"+1 480 839 2771",
    "sg:postcode":"85282",
    "sg:province":"AZ",
    "sg:tags":[
        "windows"
    ],
    "wof:name":"Progressive Millwork",
    "wof:placetype":"venue"
},
  "geometry": {"coordinates":[-111.913562,33.391671],"type":"Point"}
}