{
  "type": "Feature",
  "properties": {
    "addr:full":"405 W Secretariat Dr Tempe AZ 85284",
    "addr:housenumber":"405",
    "addr:postcode":"85284",
    "addr:street":"W Secretariat Dr",
    "iso:country":"US",
    "sg:address":"405 W Secretariat Dr",
    "sg:city":"Tempe",
    "sg:classifiers":[
        {
            "category":"Freight",
            "type":"Transportation"
        }
    ],
    "sg:phone":"+1 480 730 0006",
    "sg:postcode":"85284",
    "sg:province":"AZ",
    "sg:tags":[
        "shipping",
        "agent"
    ],
    "wof:name":"Shipping Center",
    "wof:placetype":"venue"
},
  "geometry": {"coordinates":[-111.943759,33.343469],"type":"Point"}
}