{
  "type": "Feature",
  "properties": {
    "addr:full":"219 S William Dillard Dr Gilbert AZ 85233",
    "addr:housenumber":"219",
    "addr:postcode":"85233",
    "addr:street":"S William Dillard Dr",
    "iso:country":"US",
    "sg:address":"219 S William Dillard Dr",
    "sg:city":"Gilbert",
    "sg:classifiers":[
        {
            "category":"Building & Trades",
            "subcategory":"Locksmith",
            "type":"Services"
        }
    ],
    "sg:phone":"+1 800 729 4902",
    "sg:postcode":"85233",
    "sg:province":"AZ",
    "sg:tags":[
        "key"
    ],
    "wof:name":"A 1 Emergency Locksmith",
    "wof:placetype":"venue"
},
  "geometry": {"coordinates":[-111.830522,33.346754],"type":"Point"}
}