{
  "type": "Feature",
  "properties": {
    "iso:country":"US",
    "sg:address":"7856 E Cam Vivaz",
    "sg:city":"Scottsdale",
    "sg:classifiers":[
        {
            "category":"Travel",
            "subcategory":"Hotels & Motels",
            "type":"Entertainment"
        }
    ],
    "sg:phone":"+1 480 419 5816",
    "sg:postcode":"85255",
    "sg:province":"AZ",
    "sg:tags":[
        "resort"
    ],
    "wof:name":"Resort Group Inc",
    "wof:placetype":"venue"
},
  "geometry": {"coordinates":[-111.909927,33.699938],"type":"Point"}
}