{
  "type": "Feature",
  "properties": {
    "iso:country":"US",
    "sg:address":"7231 N 13th Pl",
    "sg:city":"Phoenix",
    "sg:classifiers":[
        {
            "category":"Shopping",
            "subcategory":"Gifts & Souvenirs",
            "type":"Retail Goods"
        }
    ],
    "sg:phone":"+1 602 943 9300",
    "sg:postcode":"85020",
    "sg:province":"AZ",
    "wof:name":"Gwenhwyfars Garden LLC",
    "wof:placetype":"venue"
},
  "geometry": {"coordinates":[-112.05242699999999,33.543285],"type":"Point"}
}