{
  "type": "Feature",
  "properties": {
    "iso:country":"US",
    "sg:address":"12801 W Bell Rd",
    "sg:city":"Surprise",
    "sg:classifiers":[
        {
            "category":"Health Services",
            "subcategory":"Doctor",
            "type":"Services"
        }
    ],
    "sg:phone":"+1 623 933 2040",
    "sg:postcode":"85374",
    "sg:province":"AZ",
    "sg:tags":[
        "physician",
        "surgeon"
    ],
    "wof:name":"Kl Family Medical Care",
    "wof:placetype":"venue"
},
  "geometry": {"coordinates":[-112.336465,33.638562],"type":"Point"}
}