{
  "type": "Feature",
  "properties": {
    "iso:country":"US",
    "sg:address":"10333 W Coggins Dr",
    "sg:city":"Sun City",
    "sg:classifiers":[
        {
            "category":"Health Services",
            "subcategory":"Doctor",
            "type":"Services"
        }
    ],
    "sg:phone":"+1 623 933 0078",
    "sg:postcode":"85351",
    "sg:province":"AZ",
    "sg:tags":[
        "dentist"
    ],
    "wof:name":"Sun City Dental & Denture Ctr",
    "wof:placetype":"venue"
},
  "geometry": {"coordinates":[-112.280359,33.59834],"type":"Point"}
}