{
  "type": "Feature",
  "properties": {
    "iso:country":"US",
    "sg:address":"3441 W Golden Ln",
    "sg:city":"Chandler",
    "sg:classifiers":[
        {
            "category":"Wholesale",
            "subcategory":"Stationery",
            "type":"Manufacturing & Wholesale Goods"
        }
    ],
    "sg:phone":"+1 480 917 5744",
    "sg:postcode":"85226",
    "sg:province":"AZ",
    "sg:tags":[
        "sport",
        "book",
        "memory"
    ],
    "wof:name":"Bob Gryder Autographs",
    "wof:placetype":"venue"
},
  "geometry": {"coordinates":[-111.900256,33.324715],"type":"Point"}
}