{
  "type": "Feature",
  "properties": {
    "addr:full":"2106 Hwy 95 Bullhead City AZ 86442",
    "addr:housenumber":"2106",
    "addr:postcode":"86442",
    "addr:street":"Hwy 95",
    "iso:country":"US",
    "sg:address":"2106 Hwy 95",
    "sg:city":"Bullhead City",
    "sg:classifiers":[
        {
            "category":"Autos & Motor Vehicles",
            "subcategory":"Automobile Sales",
            "type":"Retail Goods"
        }
    ],
    "sg:phone":"+1 928 754 4505",
    "sg:postcode":"86442",
    "sg:province":"AZ",
    "sg:tags":[
        "car",
        "dealer"
    ],
    "wof:name":"Colorado River Ford Budget Sls",
    "wof:placetype":"venue"
},
  "geometry": {"coordinates":[-114.598039,35.111842],"type":"Point"}
}