{
  "type": "Feature",
  "properties": {
    "addr:full":"1111 W Bell Rd Phoenix AZ 85023",
    "addr:housenumber":"1111",
    "addr:postcode":"85023",
    "addr:street":"W Bell Rd",
    "iso:country":"US",
    "sg:address":"1111 W Bell Rd",
    "sg:city":"Phoenix",
    "sg:classifiers":[
        {
            "category":"Restaurant",
            "type":"Food & Drink"
        }
    ],
    "sg:menulink":"http://www.allmenus.com/az/phoenix/232162-manuels-mexican/menu/",
    "sg:phone":"+1 866 219 7967",
    "sg:postcode":"85023",
    "sg:province":"AZ",
    "sg:tags":[
        "mexican"
    ],
    "wof:name":"Manuel's Mexican",
    "wof:placetype":"venue"
},
  "geometry": {"coordinates":[-112.087532,33.639692],"type":"Point"}
}