{
  "type": "Feature",
  "properties": {
    "iso:country":"US",
    "sg:address":"4990 N Kolb Rd",
    "sg:city":"Tucson",
    "sg:classifiers":[
        {
            "category":"Wholesale",
            "subcategory":"Vending Machines",
            "type":"Manufacturing & Wholesale Goods"
        }
    ],
    "sg:phone":"+1 520 577 9280",
    "sg:postcode":"85750",
    "sg:province":"AZ",
    "wof:name":"Best Vend",
    "wof:placetype":"venue"
},
  "geometry": {"coordinates":[-110.839797,32.298913],"type":"Point"}
}