{
  "type": "Feature",
  "properties": {
    "addr:full":"5931 W Quail Trl Queen Creek AZ 85242",
    "addr:housenumber":"5931",
    "addr:postcode":"85242",
    "addr:street":"W Quail Trl",
    "iso:country":"US",
    "sg:address":"5931 W Quail Trl",
    "sg:city":"Queen Creek",
    "sg:classifiers":[
        {
            "category":"Wholesale",
            "subcategory":"Construction Materials",
            "type":"Manufacturing & Wholesale Goods"
        }
    ],
    "sg:phone":"+1 480 987 3050",
    "sg:postcode":"85242",
    "sg:province":"AZ",
    "sg:tags":[
        "building"
    ],
    "wof:name":"San Tan Adobe",
    "wof:placetype":"venue"
},
  "geometry": {"coordinates":[-111.628129,33.195434],"type":"Point"}
}