{
  "type": "Feature",
  "properties": {
    "iso:country":"US",
    "sg:address":"1153 Paar Dr",
    "sg:city":"Prescott",
    "sg:classifiers":[
        {
            "category":"Building & Trades",
            "subcategory":"Construction",
            "type":"Services"
        }
    ],
    "sg:phone":"+1 928 445 7149",
    "sg:postcode":"86305",
    "sg:province":"AZ",
    "sg:tags":[
        "house"
    ],
    "wof:name":"Kopavi Construction",
    "wof:placetype":"venue"
},
  "geometry": {"coordinates":[-112.48764199999999,34.548687],"type":"Point"}
}