{
  "type": "Feature",
  "properties": {
    "iso:country":"US",
    "sg:address":"35636 N 16th St",
    "sg:city":"Phoenix",
    "sg:classifiers":[
        {
            "category":"Manufacturing",
            "subcategory":"Metals",
            "type":"Manufacturing & Wholesale Goods"
        }
    ],
    "sg:phone":"+1 602 909 2556",
    "sg:postcode":"85086",
    "sg:province":"AZ",
    "sg:tags":[
        "steel",
        "distributor",
        "warehouse",
        "mill"
    ],
    "wof:name":"Purcella Steel",
    "wof:placetype":"venue"
},
  "geometry": {"coordinates":[-112.048018,33.811818],"type":"Point"}
}