{
  "type": "Feature",
  "properties": {
    "addr:full":"3711 W Clarendon Ave Phoenix AZ 85019",
    "addr:housenumber":"3711",
    "addr:postcode":"85019",
    "addr:street":"W Clarendon Ave",
    "iso:country":"US",
    "sg:address":"3711 W Clarendon Ave",
    "sg:city":"Phoenix",
    "sg:classifiers":[
        {
            "category":"Utilities",
            "subcategory":"Recycling",
            "type":"Services"
        },
        {
            "category":"Building & Trades",
            "subcategory":"Construction",
            "type":"Services"
        }
    ],
    "sg:phone":"+1 602 470 8137",
    "sg:postcode":"85019",
    "sg:province":"AZ",
    "sg:tags":[
        "demolition",
        "contractor"
    ],
    "wof:name":"Sports Car Rcyclg",
    "wof:placetype":"venue"
},
  "geometry": {"coordinates":[-112.138572,33.492212],"type":"Point"}
}