{
  "type": "Feature",
  "properties": {
    "iso:country":"US",
    "sg:address":"12902 W Peoria Ave",
    "sg:city":"El Mirage",
    "sg:classifiers":[
        {
            "category":"Building & Trades",
            "subcategory":"Construction",
            "type":"Services"
        }
    ],
    "sg:phone":"+1 623 583 8579",
    "sg:postcode":"85335",
    "sg:province":"AZ",
    "sg:tags":[
        "concrete",
        "contractor"
    ],
    "wof:name":"RCP Concrete Placements Inc",
    "wof:placetype":"venue"
},
  "geometry": {"coordinates":[-112.341742,33.580153],"type":"Point"}
}