{
  "type": "Feature",
  "properties": {
    "addr:full":"6490 Wilkinson Dr Prescott AZ 86301",
    "addr:housenumber":"6490",
    "addr:postcode":"86301",
    "addr:street":"Wilkinson Dr",
    "iso:country":"US",
    "sg:address":"6490 Wilkinson Dr",
    "sg:city":"Prescott",
    "sg:classifiers":[
        {
            "category":"Government",
            "subcategory":"Office",
            "type":"Public Place"
        }
    ],
    "sg:phone":"+1 928 778 7810",
    "sg:postcode":"86301",
    "sg:province":"AZ",
    "sg:tags":[
        "station",
        "flight"
    ],
    "wof:name":"Automated Flight Service Stn",
    "wof:placetype":"venue"
},
  "geometry": {"coordinates":[-112.41770699999999,34.647288],"type":"Point"}
}