{
  "type": "Feature",
  "properties": {
    "iso:country":"US",
    "sg:address":"9776 E Sheena Dr",
    "sg:city":"Scottsdale",
    "sg:classifiers":[
        {
            "category":"Professional",
            "subcategory":"Management & Consulting",
            "type":"Services"
        }
    ],
    "sg:phone":"+1 480 443 3631",
    "sg:postcode":"85260",
    "sg:province":"AZ",
    "sg:tags":[
        "consultant",
        "energy",
        "conservation"
    ],
    "wof:name":"Intelligent Resources",
    "wof:placetype":"venue"
},
  "geometry": {"coordinates":[-111.870849,33.613805],"type":"Point"}
}