{
  "type": "Feature",
  "properties": {
    "iso:country":"US",
    "sg:address":"18038 W Turquoise Ave",
    "sg:city":"Waddell",
    "sg:classifiers":[
        {
            "category":"Cinema",
            "subcategory":"Movie Rental",
            "type":"Entertainment"
        }
    ],
    "sg:phone":"+1 623 521 5495",
    "sg:postcode":"85355",
    "sg:province":"AZ",
    "sg:tags":[
        "motion",
        "picture",
        "distributor",
        "film",
        "exchange"
    ],
    "wof:name":"Mirage Productions",
    "wof:placetype":"venue"
},
  "geometry": {"coordinates":[-112.45394400000001,33.574001],"type":"Point"}
}