{
  "type": "Feature",
  "properties": {
    "iso:country":"US",
    "sg:address":"2348 E Pierce St",
    "sg:city":"Phoenix",
    "sg:classifiers":[
        {
            "category":"Retail",
            "subcategory":"Car Wash",
            "type":"Services"
        }
    ],
    "sg:phone":"+1 602 299 6056",
    "sg:postcode":"85006",
    "sg:province":"AZ",
    "sg:tags":[
        "polishing",
        "washing"
    ],
    "wof:name":"Hampton's A-1 Car Wash",
    "wof:placetype":"venue"
},
  "geometry": {"coordinates":[-112.03097699999999,33.456505],"type":"Point"}
}