{
  "type": "Feature",
  "properties": {
    "iso:country":"US",
    "sg:address":"632 N Beeline Hwy",
    "sg:city":"Payson",
    "sg:classifiers":[
        {
            "category":"Food & Beverages",
            "subcategory":"Candy",
            "type":"Retail Goods"
        }
    ],
    "sg:phone":"+1 928 474 3254",
    "sg:postcode":"85541",
    "sg:province":"AZ",
    "sg:tags":[
        "confectionery"
    ],
    "wof:name":"Sugar Shack",
    "wof:placetype":"venue"
},
  "geometry": {"coordinates":[-111.322788,34.248607],"type":"Point"}
}