{
  "type": "Feature",
  "properties": {
    "addr:full":"1337 E Rock Wren Rd Phoenix AZ 85048",
    "addr:housenumber":"1337",
    "addr:postcode":"85048",
    "addr:street":"E Rock Wren Rd",
    "iso:country":"US",
    "sg:address":"1337 E Rock Wren Rd",
    "sg:city":"Phoenix",
    "sg:classifiers":[
        {
            "category":"Freight",
            "type":"Transportation"
        }
    ],
    "sg:phone":"+1 480 460 3992",
    "sg:postcode":"85048",
    "sg:province":"AZ",
    "sg:tags":[
        "arrangement"
    ],
    "wof:name":"Interntnal Logistics Solutions",
    "wof:placetype":"venue"
},
  "geometry": {"coordinates":[-112.054081,33.312864],"type":"Point"}
}