{
  "type": "Feature",
  "properties": {
    "iso:country":"US",
    "sg:address":"555 N Pantano Rd",
    "sg:city":"Tucson",
    "sg:classifiers":[
        {
            "category":"Shopping",
            "subcategory":"Used Merchandise",
            "type":"Retail Goods"
        }
    ],
    "sg:phone":"+1 520 722 7463",
    "sg:postcode":"85710",
    "sg:province":"AZ",
    "wof:name":"D&J Antiques",
    "wof:placetype":"venue"
},
  "geometry": {"coordinates":[-110.823899,32.226964],"type":"Point"}
}