{
  "type": "Feature",
  "properties": {
    "addr:full":"1660 S Alma School Rd Ste 101 Mesa AZ 85210",
    "addr:housenumber":"1660",
    "addr:postcode":"85210",
    "addr:street":"S Alma School Rd Ste 101",
    "iso:country":"US",
    "sg:address":"1660 S Alma School Rd Ste 101",
    "sg:city":"Mesa",
    "sg:classifiers":[
        {
            "category":"Health Services",
            "subcategory":"Optometrist",
            "type":"Services"
        }
    ],
    "sg:phone":"+1 480 345 9913",
    "sg:postcode":"85210",
    "sg:province":"AZ",
    "wof:name":"Eye Masters",
    "wof:placetype":"venue"
},
  "geometry": {"coordinates":[-111.85900100000001,33.3815],"type":"Point"}
}