{
  "type": "Feature",
  "properties": {
    "iso:country":"US",
    "sg:address":"7734 N 33rd Ave",
    "sg:city":"Phoenix",
    "sg:classifiers":[
        {
            "category":"Wholesale",
            "subcategory":"Home Furnishings",
            "type":"Manufacturing & Wholesale Goods"
        }
    ],
    "sg:phone":"+1 602 841 1286",
    "sg:postcode":"85051",
    "sg:province":"AZ",
    "sg:tags":[
        "manufacturer",
        "baskets-wholesale"
    ],
    "wof:name":"Baskets By Lory",
    "wof:placetype":"venue"
},
  "geometry": {"coordinates":[-112.12976500000001,33.550334],"type":"Point"}
}