{
  "type": "Feature",
  "properties": {
    "iso:country":"US",
    "sg:address":"5200 E Railhead Ave",
    "sg:city":"Flagstaff",
    "sg:classifiers":[
        {
            "category":"Home & Garden",
            "subcategory":"Building Materials",
            "type":"Retail Goods"
        },
        {
            "category":"Manufacturing",
            "subcategory":"Glass & Minerals",
            "type":"Manufacturing & Wholesale Goods"
        }
    ],
    "sg:phone":"+1 602 220 5000",
    "sg:postcode":"86004",
    "sg:province":"AZ",
    "sg:tags":[
        "ready",
        "concrete",
        "mixed",
        "mfg"
    ],
    "wof:name":"Rinker Materials Corporation",
    "wof:placetype":"venue"
},
  "geometry": {"coordinates":[-111.576865,35.22527],"type":"Point"}
}