{
  "type": "Feature",
  "properties": {
    "addr:full":"8820 E Lupine Ave Scottsdale AZ 85260",
    "addr:housenumber":"8820",
    "addr:postcode":"85260",
    "addr:street":"E Lupine Ave",
    "iso:country":"US",
    "sg:address":"8820 E Lupine Ave",
    "sg:city":"Scottsdale",
    "sg:classifiers":[
        {
            "category":"Wholesale",
            "subcategory":"Stationery",
            "type":"Manufacturing & Wholesale Goods"
        }
    ],
    "sg:phone":"+1 480 551 7017",
    "sg:postcode":"85260",
    "sg:province":"AZ",
    "sg:tags":[
        "business",
        "form",
        "system"
    ],
    "wof:name":"Paces Group Inc",
    "wof:placetype":"venue"
},
  "geometry": {"coordinates":[-111.889692,33.590606],"type":"Point"}
}