{
  "type": "Feature",
  "properties": {
    "iso:country":"US",
    "sg:address":"2102 E Eastland St",
    "sg:city":"Tucson",
    "sg:classifiers":[
        {
            "category":"Building & Trades",
            "subcategory":"Construction",
            "type":"Services"
        }
    ],
    "sg:phone":"+1 520 319 6799",
    "sg:postcode":"85719",
    "sg:province":"AZ",
    "sg:tags":[
        "painter"
    ],
    "wof:name":"Prime Finishing",
    "wof:placetype":"venue"
},
  "geometry": {"coordinates":[-110.942299,32.211392],"type":"Point"}
}