{
  "type": "Feature",
  "properties": {
    "iso:country":"US",
    "sg:address":"1920 E Cambridge Ave",
    "sg:city":"Phoenix",
    "sg:classifiers":[
        {
            "category":"Health Services",
            "subcategory":"Doctor",
            "type":"Services"
        }
    ],
    "sg:phone":"+1 602 254 5561",
    "sg:postcode":"85006",
    "sg:province":"AZ",
    "sg:tags":[
        "physician",
        "surgeon"
    ],
    "wof:name":"Pediatric Surgeons Of Phoenix",
    "wof:placetype":"venue"
},
  "geometry": {"coordinates":[-112.040172,33.477606],"type":"Point"}
}