{
  "type": "Feature",
  "properties": {
    "iso:country":"US",
    "sg:address":"1425 W Prince Rd",
    "sg:city":"Tucson",
    "sg:classifiers":[
        {
            "category":"Autos & Motor Vehicles",
            "subcategory":"Fuel & Gas Station",
            "type":"Retail Goods"
        },
        {
            "category":"Retail",
            "subcategory":"Auto Repair",
            "type":"Services"
        }
    ],
    "sg:phone":"+1 520 887 2003",
    "sg:postcode":"85705",
    "sg:province":"AZ",
    "sg:tags":[
        "repairing",
        "automobile",
        "station",
        "gasoline"
    ],
    "wof:name":"Munson's Service",
    "wof:placetype":"venue"
},
  "geometry": {"coordinates":[-110.995834,32.272073],"type":"Point"}
}