{
  "type": "Feature",
  "properties": {
    "iso:country":"US",
    "sg:address":"7300 Kavanaugh Way",
    "sg:city":"Flagstaff",
    "sg:classifiers":[
        {
            "category":"Professional",
            "type":"Services"
        }
    ],
    "sg:phone":"+1 928 527 6876",
    "sg:postcode":"86004",
    "sg:province":"AZ",
    "wof:name":"Posterville",
    "wof:placetype":"venue"
},
  "geometry": {"coordinates":[-111.518469,35.257808],"type":"Point"}
}