{
  "type": "Feature",
  "properties": {
    "addr:full":"3519 W Northern Ave Phoenix AZ 85051",
    "addr:housenumber":"3519",
    "addr:postcode":"85051",
    "addr:street":"W Northern Ave",
    "iso:country":"US",
    "sg:address":"3519 W Northern Ave",
    "sg:city":"Phoenix",
    "sg:classifiers":[
        {
            "category":"Real Estate",
            "subcategory":"Real Estate Agent",
            "type":"Services"
        }
    ],
    "sg:phone":"+1 602 973 3900",
    "sg:postcode":"85051",
    "sg:province":"AZ",
    "wof:name":"Ed Ellison Realty & Assoc",
    "wof:placetype":"venue"
},
  "geometry": {"coordinates":[-112.137086,33.553019],"type":"Point"}
}