{
  "type": "Feature",
  "properties": {
    "iso:country":"US",
    "sg:address":"7003 N 58th Ave",
    "sg:city":"Glendale",
    "sg:classifiers":[
        {
            "category":"Shopping",
            "subcategory":"Clothing, Apparel, & Fashions",
            "type":"Retail Goods"
        }
    ],
    "sg:phone":"+1 623 931 3393",
    "sg:postcode":"85301",
    "sg:province":"AZ",
    "wof:name":"Normas Paris Boutique",
    "wof:placetype":"venue"
},
  "geometry": {"coordinates":[-112.183634,33.539192],"type":"Point"}
}