{
  "type": "Feature",
  "properties": {
    "iso:country":"US",
    "sg:address":"15 Glen Oaks Dr",
    "sg:city":"Prescott",
    "sg:classifiers":[
        {
            "category":"Building & Trades",
            "subcategory":"Construction",
            "type":"Services"
        }
    ],
    "sg:phone":"+1 928 442 0428",
    "sg:postcode":"86305",
    "sg:province":"AZ",
    "sg:tags":[
        "house"
    ],
    "wof:name":"All In One Construction",
    "wof:placetype":"venue"
},
  "geometry": {"coordinates":[-112.517843,34.578179],"type":"Point"}
}