{
  "type": "Feature",
  "properties": {
    "iso:country":"US",
    "sg:address":"87 S William Dillard Dr",
    "sg:city":"Gilbert",
    "sg:classifiers":[
        {
            "category":"Home & Garden",
            "subcategory":"Carpets & Floor Coverings",
            "type":"Retail Goods"
        }
    ],
    "sg:phone":"+1 480 820 8128",
    "sg:postcode":"85233",
    "sg:province":"AZ",
    "sg:tags":[
        "carpeting"
    ],
    "wof:name":"Floor Co",
    "wof:placetype":"venue"
},
  "geometry": {"coordinates":[-111.83034600000001,33.348101],"type":"Point"}
}