{
  "type": "Feature",
  "properties": {
    "iso:country":"US",
    "sg:address":"437 S Main St Ste 10",
    "sg:city":"Cottonwood",
    "sg:classifiers":[
        {
            "category":"Retail",
            "subcategory":"Veterinary Services",
            "type":"Services"
        }
    ],
    "sg:phone":"+1 928 634 3310",
    "sg:postcode":"86326",
    "sg:province":"AZ",
    "sg:tags":[
        "clinic",
        "hospital",
        "specialty"
    ],
    "wof:name":"Tumbleweed Vetenirary Clinic Inc",
    "wof:placetype":"venue"
},
  "geometry": {"coordinates":[-112.009791,34.73093],"type":"Point"}
}