{
  "type": "Feature",
  "properties": {
    "iso:country":"US",
    "sg:address":"817 S Beeline Hwy",
    "sg:city":"Payson",
    "sg:classifiers":[
        {
            "category":"Building & Trades",
            "subcategory":"Plumbing",
            "type":"Services"
        }
    ],
    "sg:phone":"+1 928 474 1760",
    "sg:postcode":"85541",
    "sg:province":"AZ",
    "sg:tags":[
        "contractor"
    ],
    "wof:name":"Beeline Heating & Cooling",
    "wof:placetype":"venue"
},
  "geometry": {"coordinates":[-111.325375,34.230356],"type":"Point"}
}