{
  "type": "Feature",
  "properties": {
    "addr:full":"1511 N Hayden Rd Scottsdale AZ 85257",
    "addr:housenumber":"1511",
    "addr:postcode":"85257",
    "addr:street":"N Hayden Rd",
    "iso:country":"US",
    "sg:address":"1511 N Hayden Rd",
    "sg:city":"Scottsdale",
    "sg:classifiers":[
        {
            "category":"Freight",
            "type":"Transportation"
        }
    ],
    "sg:phone":"+1 480 483 0200",
    "sg:postcode":"85257",
    "sg:province":"AZ",
    "sg:tags":[
        "postal",
        "shipping"
    ],
    "wof:name":"UPS Stores The",
    "wof:placetype":"venue"
},
  "geometry": {"coordinates":[-111.908767,33.465665],"type":"Point"}
}