{
  "type": "Feature",
  "properties": {
    "iso:country":"US",
    "sg:address":"2413 S Marion Ave",
    "sg:city":"Yuma",
    "sg:classifiers":[
        {
            "category":"Real Estate",
            "subcategory":"Real Estate Operator",
            "type":"Services"
        }
    ],
    "sg:phone":"+1 928 726 8931",
    "sg:postcode":"85365",
    "sg:province":"AZ",
    "sg:tags":[
        "mobile",
        "home",
        "site"
    ],
    "wof:name":"Melody Mobile Court",
    "wof:placetype":"venue"
},
  "geometry": {"coordinates":[-114.597673,32.683231],"type":"Point"}
}