{
  "type": "Feature",
  "properties": {
    "iso:country":"US",
    "sg:address":"2207 E Fry Blvd",
    "sg:city":"Sierra Vista",
    "sg:classifiers":[
        {
            "category":"Shopping",
            "subcategory":"Books",
            "type":"Retail Goods"
        }
    ],
    "sg:phone":"+1 520 439 9792",
    "sg:postcode":"85635",
    "sg:province":"AZ",
    "sg:tags":[
        "dealer"
    ],
    "wof:name":"Ecclisa Books & Stuff",
    "wof:placetype":"venue"
},
  "geometry": {"coordinates":[-110.275682,31.55471],"type":"Point"}
}