{
  "type": "Feature",
  "properties": {
    "iso:country":"US",
    "sg:address":"635 W Indian School Rd",
    "sg:city":"Phoenix",
    "sg:classifiers":[
        {
            "category":"Shopping",
            "type":"Retail Goods"
        }
    ],
    "sg:phone":"+1 602 636 1039",
    "sg:postcode":"85013",
    "sg:province":"AZ",
    "sg:tags":[
        "merchandise"
    ],
    "wof:name":"Aquakleen Products Inc",
    "wof:placetype":"venue"
},
  "geometry": {"coordinates":[-112.081895,33.494801],"type":"Point"}
}