{
  "type": "Feature",
  "properties": {
    "addr:full":"13431 W Westgate Dr Surprise AZ 85374",
    "addr:housenumber":"13431",
    "addr:postcode":"85374",
    "addr:street":"W Westgate Dr",
    "iso:country":"US",
    "sg:address":"13431 W Westgate Dr",
    "sg:city":"Surprise",
    "sg:classifiers":[
        {
            "category":"Autos & Motor Vehicles",
            "subcategory":"Auto Supplies",
            "type":"Retail Goods"
        }
    ],
    "sg:phone":"+1 623 474 3344",
    "sg:postcode":"85374",
    "sg:province":"AZ",
    "sg:tags":[
        "automobile",
        "stereo",
        "radio"
    ],
    "wof:name":"Listen Up",
    "wof:placetype":"venue"
},
  "geometry": {"coordinates":[-112.349166,33.64053],"type":"Point"}
}