{
  "type": "Feature",
  "properties": {
    "iso:country":"US",
    "sg:address":"3427 N 70th St",
    "sg:city":"Scottsdale",
    "sg:classifiers":[
        {
            "category":"Personal",
            "subcategory":"Barber",
            "type":"Services"
        }
    ],
    "sg:phone":"+1 480 946 0860",
    "sg:postcode":"85251",
    "sg:province":"AZ",
    "wof:name":"Dave's Barber Shop",
    "wof:placetype":"venue"
},
  "geometry": {"coordinates":[-111.930353,33.488293],"type":"Point"}
}