{
  "type": "Feature",
  "properties": {
    "addr:full":"5601 W Dobbins Rd Laveen AZ 85339",
    "addr:housenumber":"5601",
    "addr:postcode":"85339",
    "addr:street":"W Dobbins Rd",
    "iso:country":"US",
    "sg:address":"5601 W Dobbins Rd",
    "sg:city":"Laveen",
    "sg:classifiers":[
        {
            "category":"Professional",
            "type":"Services"
        }
    ],
    "sg:phone":"+1 602 237 4991",
    "sg:postcode":"85339",
    "sg:province":"AZ",
    "wof:name":"Suidar LLC",
    "wof:placetype":"venue"
},
  "geometry": {"coordinates":[-112.177824,33.362906],"type":"Point"}
}