{
  "type": "Feature",
  "properties": {
    "iso:country":"US",
    "sg:address":"716 W 2nd Pl",
    "sg:city":"Mesa",
    "sg:classifiers":[
        {
            "category":"Manufacturing",
            "subcategory":"Toys & Sporting Goods",
            "type":"Manufacturing & Wholesale Goods"
        }
    ],
    "sg:phone":"+1 480 844 5018",
    "sg:postcode":"85201",
    "sg:province":"AZ",
    "sg:tags":[
        "mfg"
    ],
    "wof:name":"Charm Willows",
    "wof:placetype":"venue"
},
  "geometry": {"coordinates":[-111.847977,33.420056],"type":"Point"}
}