{
  "type": "Feature",
  "properties": {
    "addr:full":"8332 N 7th St Phoenix AZ 85020",
    "addr:housenumber":"8332",
    "addr:postcode":"85020",
    "addr:street":"N 7Th St",
    "iso:country":"US",
    "sg:address":"8332 N 7th St",
    "sg:city":"Phoenix",
    "sg:classifiers":[
        {
            "category":"Health Services",
            "subcategory":"Optometrist",
            "type":"Services"
        }
    ],
    "sg:phone":"+1 602 944 2656",
    "sg:postcode":"85020",
    "sg:province":"AZ",
    "wof:name":"Lowell P Branson OD",
    "wof:placetype":"venue"
},
  "geometry": {"coordinates":[-112.065354,33.560177],"type":"Point"}
}