{
  "type": "Feature",
  "properties": {
    "iso:country":"US",
    "sg:address":"2003 W 8th St",
    "sg:city":"Yuma",
    "sg:classifiers":[
        {
            "category":"Autos & Motor Vehicles",
            "subcategory":"Fuel & Gas Station",
            "type":"Retail Goods"
        }
    ],
    "sg:phone":"+1 928 783 6323",
    "sg:postcode":"85364",
    "sg:province":"AZ",
    "sg:tags":[
        "station",
        "gasoline"
    ],
    "wof:name":"Chevron",
    "wof:placetype":"venue"
},
  "geometry": {"coordinates":[-114.64465199999999,32.712987],"type":"Point"}
}