{
  "type": "Feature",
  "properties": {
    "addr:full":"6021 E Shea Blvd Scottsdale AZ 85254",
    "addr:housenumber":"6021",
    "addr:postcode":"85254",
    "addr:street":"E Shea Blvd",
    "iso:country":"US",
    "sg:address":"6021 E Shea Blvd",
    "sg:city":"Scottsdale",
    "sg:classifiers":[
        {
            "category":"Real Estate",
            "subcategory":"Real Estate Agent",
            "type":"Services"
        }
    ],
    "sg:phone":"+1 480 998 9200",
    "sg:postcode":"85254",
    "sg:province":"AZ",
    "wof:name":"Steve Wallace",
    "wof:placetype":"venue"
},
  "geometry": {"coordinates":[-111.94922200000001,33.582211],"type":"Point"}
}