{
  "type": "Feature",
  "properties": {
    "addr:full":"13637 N Tatum Blvd # 25 Phoenix AZ 85032",
    "addr:housenumber":"13637",
    "addr:postcode":"85032",
    "addr:street":"N Tatum Blvd # 25",
    "iso:country":"US",
    "sg:address":"13637 N Tatum Blvd # 25",
    "sg:city":"Phoenix",
    "sg:classifiers":[
        {
            "category":"Professional",
            "subcategory":"Computer Services",
            "type":"Services"
        }
    ],
    "sg:phone":"+1 602 237 6623",
    "sg:postcode":"85032",
    "sg:province":"AZ",
    "sg:tags":[
        "repair",
        "designer",
        "technical",
        "consultant",
        "assistance",
        "system",
        "equipment-service",
        "support"
    ],
    "sg:website":"http://www.ditaz.com",
    "wof:name":"Diamond IT Technical Services",
    "wof:placetype":"venue"
},
  "geometry": {"coordinates":[-111.977814,33.61066],"type":"Point"}
}