{
  "type": "Feature",
  "properties": {
    "addr:full":"3637 N 73rd Ave Phoenix AZ 85033",
    "addr:housenumber":"3637",
    "addr:postcode":"85033",
    "addr:street":"N 73Rd Ave",
    "iso:country":"US",
    "sg:address":"3637 N 73rd Ave",
    "sg:city":"Phoenix",
    "sg:classifiers":[
        {
            "category":"Manufacturing",
            "subcategory":"Printing",
            "type":"Manufacturing & Wholesale Goods"
        }
    ],
    "sg:phone":"+1 623 873 3350",
    "sg:postcode":"85033",
    "sg:province":"AZ",
    "sg:tags":[
        "periodical"
    ],
    "sg:website":"www.showwestmag.com",
    "wof:name":"Show West Inc",
    "wof:placetype":"venue"
},
  "geometry": {"coordinates":[-112.216098,33.489978],"type":"Point"}
}