{
  "type": "Feature",
  "properties": {
    "addr:full":"1125 E Rio Salado Pkwy Tempe AZ 85281",
    "addr:housenumber":"1125",
    "addr:postcode":"85281",
    "addr:street":"E Rio Salado Pkwy",
    "iso:country":"US",
    "sg:address":"1125 E Rio Salado Pkwy",
    "sg:city":"Tempe",
    "sg:classifiers":[
        {
            "category":"Organizations",
            "subcategory":"Community Association",
            "type":"Services"
        }
    ],
    "sg:phone":"+1 480 784 4834",
    "sg:postcode":"85281",
    "sg:province":"AZ",
    "sg:tags":[
        "golf",
        "support",
        "financial",
        "course"
    ],
    "wof:name":"Asu Karsten Golf Course The",
    "wof:placetype":"venue"
},
  "geometry": {"coordinates":[-111.91333,33.429227],"type":"Point"}
}