{
  "type": "Feature",
  "properties": {
    "iso:country":"US",
    "sg:address":"7842 E Gray Rd Ste 7",
    "sg:city":"Scottsdale",
    "sg:classifiers":[
        {
            "category":"Personal",
            "type":"Services"
        },
        {
            "category":"Professional",
            "subcategory":"Detective & Security Services",
            "type":"Services"
        },
        {
            "category":"Manufacturing",
            "subcategory":"Electronics",
            "type":"Manufacturing & Wholesale Goods"
        },
        {
            "category":"Shopping",
            "subcategory":"Computers & Home Electronics",
            "type":"Retail Goods"
        },
        {
            "category":"Manufacturing",
            "subcategory":"Building Materials",
            "type":"Manufacturing & Wholesale Goods"
        }
    ],
    "sg:phone":"+1 480 991 6266",
    "sg:postcode":"85260",
    "sg:province":"AZ",
    "sg:tags":[
        "control",
        "monitoring",
        "fire",
        "consultant",
        "alarm",
        "system",
        "surveillance",
        "systems-wholesale",
        "equipment",
        "equipment-wholesale",
        "medical",
        "manufacturer"
    ],
    "wof:name":"Scottsdale Security Systems",
    "wof:placetype":"venue"
},
  "geometry": {"coordinates":[-111.910039,33.612471],"type":"Point"}
}