{
  "type": "Feature",
  "properties": {
    "iso:country":"US",
    "sg:address":"11239 E Ramona Ave",
    "sg:city":"Mesa",
    "sg:classifiers":[
        {
            "category":"Building & Trades",
            "subcategory":"Construction",
            "type":"Services"
        }
    ],
    "sg:phone":"+1 480 357 3080",
    "sg:postcode":"85212",
    "sg:province":"AZ",
    "sg:tags":[
        "home",
        "builder"
    ],
    "wof:name":"Providence Homes At Parkwood",
    "wof:placetype":"venue"
},
  "geometry": {"coordinates":[-111.58958800000001,33.338442],"type":"Point"}
}