{
  "type": "Feature",
  "properties": {
    "addr:full":"10030 N 124th St Scottsdale AZ 85259",
    "addr:housenumber":"10030",
    "addr:postcode":"85259",
    "addr:street":"N 124Th St",
    "iso:country":"US",
    "sg:address":"10030 N 124th St",
    "sg:city":"Scottsdale",
    "sg:classifiers":[
        {
            "category":"Farming",
            "subcategory":"Livestock Farm",
            "type":"Manufacturing & Wholesale Goods"
        }
    ],
    "sg:phone":"+1 480 391 3698",
    "sg:postcode":"85259",
    "sg:province":"AZ",
    "sg:tags":[
        "animal",
        "general"
    ],
    "wof:name":"Emerald Hills Ranch",
    "wof:placetype":"venue"
},
  "geometry": {"coordinates":[-111.813433,33.577143],"type":"Point"}
}