{
  "type": "Feature",
  "properties": {
    "addr:full":"938 E Navajo Ave Apache Junction AZ 85219",
    "addr:housenumber":"938",
    "addr:postcode":"85219",
    "addr:street":"E Navajo Ave",
    "iso:country":"US",
    "sg:address":"938 E Navajo Ave",
    "sg:city":"Apache Junction",
    "sg:classifiers":[
        {
            "category":"Building & Trades",
            "subcategory":"Plumbing",
            "type":"Services"
        }
    ],
    "sg:phone":"+1 480 982 1751",
    "sg:postcode":"85219",
    "sg:province":"AZ",
    "sg:tags":[
        "contractor"
    ],
    "wof:name":"Skis A/C & Plumbing Inc",
    "wof:placetype":"venue"
},
  "geometry": {"coordinates":[-111.535798,33.396682],"type":"Point"}
}