{
  "type": "Feature",
  "properties": {
    "addr:full":"14795 N 78th Way Scottsdale AZ 85260",
    "addr:housenumber":"14795",
    "addr:postcode":"85260",
    "addr:street":"N 78Th Way",
    "iso:country":"US",
    "sg:address":"14795 N 78th Way",
    "sg:city":"Scottsdale",
    "sg:classifiers":[
        {
            "category":"Home & Garden",
            "subcategory":"Home Furnishings",
            "type":"Retail Goods"
        }
    ],
    "sg:phone":"+1 480 922 9555",
    "sg:postcode":"85260",
    "sg:province":"AZ",
    "sg:tags":[
        "venetian",
        "blind"
    ],
    "wof:name":"AAA Wisely Blinds Shades",
    "wof:placetype":"venue"
},
  "geometry": {"coordinates":[-111.907419,33.621958],"type":"Point"}
}