{
  "type": "Feature",
  "properties": {
    "iso:country":"US",
    "sg:address":"929 N Val Vista Dr",
    "sg:city":"Gilbert",
    "sg:classifiers":[
        {
            "category":"Freight",
            "type":"Transportation"
        }
    ],
    "sg:phone":"+1 480 813 8710",
    "sg:postcode":"85234",
    "sg:province":"AZ",
    "sg:tags":[
        "agent",
        "shipping"
    ],
    "wof:name":"Power Postal",
    "wof:placetype":"venue"
},
  "geometry": {"coordinates":[-111.756151,33.367364],"type":"Point"}
}