{
  "type": "Feature",
  "properties": {
    "iso:country":"US",
    "sg:address":"5351 W Oasis Rd",
    "sg:city":"Tucson",
    "sg:classifiers":[
        {
            "category":"Wholesale",
            "subcategory":"Machinery & Supplies",
            "type":"Manufacturing & Wholesale Goods"
        }
    ],
    "sg:phone":"+1 520 744 7255",
    "sg:postcode":"85742",
    "sg:province":"AZ",
    "sg:tags":[
        "equipment",
        "vacuum",
        "establishment",
        "system",
        "cleaning"
    ],
    "wof:name":"All Home Central Vacuum",
    "wof:placetype":"venue"
},
  "geometry": {"coordinates":[-111.077127,32.388205],"type":"Point"}
}