{
  "type": "Feature",
  "properties": {
    "addr:full":"2330 N Alma School Rd Ste 112 Chandler AZ 85224",
    "addr:housenumber":"2330",
    "addr:postcode":"85224",
    "addr:street":"N Alma School Rd Ste 112",
    "iso:country":"US",
    "sg:address":"2330 N Alma School Rd Ste 112",
    "sg:city":"Chandler",
    "sg:classifiers":[
        {
            "category":"Home & Garden",
            "subcategory":"Furniture",
            "type":"Retail Goods"
        }
    ],
    "sg:phone":"+1 480 899 4098",
    "sg:postcode":"85224",
    "sg:province":"AZ",
    "sg:tags":[
        "store"
    ],
    "wof:name":"Rocker World & Curios",
    "wof:placetype":"venue"
},
  "geometry": {"coordinates":[-111.859233,33.339502],"type":"Point"}
}