{
  "type": "Feature",
  "properties": {
    "iso:country":"US",
    "sg:address":"945 E Grant Rd",
    "sg:city":"Tucson",
    "sg:classifiers":[
        {
            "category":"Banks & Credit Unions",
            "subcategory":"Bank",
            "type":"Services"
        }
    ],
    "sg:phone":"+1 520 624 4366",
    "sg:postcode":"85719",
    "sg:province":"AZ",
    "sg:tags":[
        "state"
    ],
    "sg:website":"www.compassbank.com",
    "wof:name":"Compass Bank",
    "wof:placetype":"venue"
},
  "geometry": {"coordinates":[-110.958879,32.250209],"type":"Point"}
}