{
  "type": "Feature",
  "properties": {
    "addr:full":"10640 N 28th Dr Phoenix AZ 85029",
    "addr:housenumber":"10640",
    "addr:postcode":"85029",
    "addr:street":"N 28Th Dr",
    "iso:country":"US",
    "sg:address":"10640 N 28th Dr",
    "sg:city":"Phoenix",
    "sg:classifiers":[
        {
            "category":"Health Services",
            "subcategory":"Clinic",
            "type":"Services"
        }
    ],
    "sg:phone":"+1 602 504 8888",
    "sg:postcode":"85029",
    "sg:province":"AZ",
    "sg:tags":[
        "home"
    ],
    "wof:name":"Comfort Keepers Glendale",
    "wof:placetype":"venue"
},
  "geometry": {"coordinates":[-112.122134,33.583631],"type":"Point"}
}