{
  "type": "Feature",
  "properties": {
    "iso:country":"US",
    "sg:address":"6245 E Bell Rd",
    "sg:city":"Scottsdale",
    "sg:classifiers":[
        {
            "category":"Recreation",
            "type":"Entertainment"
        }
    ],
    "sg:phone":"+1 480 951 2236",
    "sg:postcode":"85254",
    "sg:province":"AZ",
    "sg:tags":[
        "martial",
        "arts",
        "instruction"
    ],
    "wof:name":"Goshin Karate & Judo Academy",
    "wof:placetype":"venue"
},
  "geometry": {"coordinates":[-111.944999,33.640363],"type":"Point"}
}