{
  "type": "Feature",
  "properties": {
    "iso:country":"US",
    "sg:address":"6060 N Fountain Plaza Dr",
    "sg:city":"Tucson",
    "sg:classifiers":[
        {
            "category":"Health Services",
            "subcategory":"Doctor",
            "type":"Services"
        }
    ],
    "sg:phone":"+1 520 874 7320",
    "sg:postcode":"85704",
    "sg:province":"AZ",
    "sg:tags":[
        "physician",
        "surgeon"
    ],
    "wof:name":"Northwest Specialty Care Ctr",
    "wof:placetype":"venue"
},
  "geometry": {"coordinates":[-111.00995399999999,32.316148],"type":"Point"}
}