{
  "type": "Feature",
  "properties": {
    "iso:country":"US",
    "sg:address":"201 Easy St Ste 103",
    "sg:city":"Carefree",
    "sg:classifiers":[
        {
            "category":"Tea Room",
            "subcategory":"None",
            "type":"Food & Drink"
        },
        {
            "category":"Restaurant",
            "type":"Food & Drink"
        }
    ],
    "sg:phone":"+1 480 488 4812",
    "sg:postcode":"85377",
    "sg:province":"AZ",
    "sg:tags":[
        "british"
    ],
    "sg:website":"www.carefreetea.com",
    "wof:name":"English Rose Tea Room",
    "wof:placetype":"venue"
},
  "geometry": {"coordinates":[-111.92348,33.824815],"type":"Point"}
}