{
  "type": "Feature",
  "properties": {
    "iso:country":"US",
    "sg:address":"2450 W 4th St",
    "sg:city":"Yuma",
    "sg:classifiers":[
        {
            "category":"Insurance",
            "subcategory":"Insurance Agent",
            "type":"Services"
        }
    ],
    "sg:phone":"+1 928 726 5630",
    "sg:postcode":"85364",
    "sg:province":"AZ",
    "wof:name":"Prudential",
    "wof:placetype":"venue"
},
  "geometry": {"coordinates":[-114.649641,32.720037],"type":"Point"}
}