{
  "type": "Feature",
  "properties": {
    "addr:full":"3419 E University Dr Phoenix AZ 85034",
    "addr:housenumber":"3419",
    "addr:postcode":"85034",
    "addr:street":"E University Dr",
    "iso:country":"US",
    "sg:address":"3419 E University Dr",
    "sg:city":"Phoenix",
    "sg:classifiers":[
        {
            "category":"Wholesale",
            "subcategory":"Groceries",
            "type":"Manufacturing & Wholesale Goods"
        }
    ],
    "sg:phone":"+1 602 437 8333",
    "sg:postcode":"85034",
    "sg:province":"AZ",
    "sg:tags":[
        "food",
        "broker"
    ],
    "sg:website":"www.asmphx.com",
    "wof:name":"ADVANTAGE Sales & Marketing",
    "wof:placetype":"venue"
},
  "geometry": {"coordinates":[-112.008529,33.415493],"type":"Point"}
}