{
  "type": "Feature",
  "properties": {
    "addr:full":"1354 W Prince Rd Tucson AZ 85705",
    "addr:housenumber":"1354",
    "addr:postcode":"85705",
    "addr:street":"W Prince Rd",
    "iso:country":"US",
    "sg:address":"1354 W Prince Rd",
    "sg:city":"Tucson",
    "sg:classifiers":[
        {
            "category":"Shopping",
            "subcategory":"Discount & Variety Stores",
            "type":"Retail Goods"
        }
    ],
    "sg:phone":"+1 520 888 2726",
    "sg:postcode":"85705",
    "sg:province":"AZ",
    "sg:website":"http://www.familydollar.com",
    "wof:name":"Family Dollar Stores",
    "wof:placetype":"venue"
},
  "geometry": {"coordinates":[-110.994491,32.272132],"type":"Point"}
}