{
  "type": "Feature",
  "properties": {
    "iso:country":"US",
    "sg:address":"9024 W Thomas Road",
    "sg:city":"Phoenix",
    "sg:classifiers":[
        {
            "category":"Utilities",
            "subcategory":"Water",
            "type":"Services"
        },
        {
            "category":"Food & Beverages",
            "subcategory":"Liquor & Beverages",
            "type":"Retail Goods"
        },
        {
            "category":"Ice Cream",
            "type":"Food & Drink"
        }
    ],
    "sg:phone":"+1 623 877 9455",
    "sg:postcode":"85037",
    "sg:province":"AZ",
    "sg:tags":[
        "company-utility",
        "supply",
        "frozen",
        "companies-bottled",
        "system",
        "bulk",
        "yogurt"
    ],
    "wof:name":"Watertyme",
    "wof:placetype":"venue"
},
  "geometry": {"coordinates":[-112.25374600000001,33.479811],"type":"Point"}
}