{
  "type": "Feature",
  "properties": {
    "iso:country":"US",
    "sg:address":"8669 W Monte Vista Rd",
    "sg:city":"Phoenix",
    "sg:classifiers":[
        {
            "category":"Shopping",
            "subcategory":"Beauty & Cosmetics",
            "type":"Retail Goods"
        }
    ],
    "sg:phone":"+1 623 936 7001",
    "sg:postcode":"85037",
    "sg:province":"AZ",
    "sg:tags":[
        "perfume",
        "salons-equipment",
        "supply"
    ],
    "wof:name":"Lizzy Cosmetics",
    "wof:placetype":"venue"
},
  "geometry": {"coordinates":[-112.246278,33.470209],"type":"Point"}
}