{
  "type": "Feature",
  "properties": {
    "iso:country":"US",
    "sg:address":"4435 E Chandler Blvd",
    "sg:city":"Phoenix",
    "sg:classifiers":[
        {
            "category":"Banks & Credit Unions",
            "subcategory":"Bank",
            "type":"Services"
        }
    ],
    "sg:phone":"+1 480 705 8900",
    "sg:postcode":"85048",
    "sg:province":"AZ",
    "sg:tags":[
        "loan",
        "real estate"
    ],
    "wof:name":"Chase Manhattan Mortgage Corp",
    "wof:placetype":"venue"
},
  "geometry": {"coordinates":[-111.987193,33.30517],"type":"Point"}
}