{
  "type": "Feature",
  "properties": {
    "iso:country":"US",
    "sg:address":"17715 US Hwy 93",
    "sg:city":"Wikieup",
    "sg:classifiers":[
        {
            "category":"Travel",
            "subcategory":"Campground",
            "type":"Entertainment"
        }
    ],
    "sg:phone":"+1 928 764 2243",
    "sg:postcode":"85360",
    "sg:province":"AZ",
    "wof:name":"Cindy's Country Store & Rv Prk",
    "wof:placetype":"venue"
},
  "geometry": {"coordinates":[-113.614652,34.716987],"type":"Point"}
}