{
  "type": "Feature",
  "properties": {
    "iso:country":"US",
    "sg:address":"602 W Ajo Way",
    "sg:city":"Tucson",
    "sg:classifiers":[
        {
            "category":"Social Services",
            "type":"Services"
        }
    ],
    "sg:phone":"+1 520 798 0834",
    "sg:postcode":"85713",
    "sg:province":"AZ",
    "sg:tags":[
        "organization",
        "welfare"
    ],
    "wof:name":"Casa San Juan",
    "wof:placetype":"venue"
},
  "geometry": {"coordinates":[-110.97966599999999,32.177877],"type":"Point"}
}