{
  "type": "Feature",
  "properties": {
    "addr:full":"221 E Woodman Dr Tempe AZ 85283",
    "addr:housenumber":"221",
    "addr:postcode":"85283",
    "addr:street":"E Woodman Dr",
    "iso:country":"US",
    "sg:address":"221 E Woodman Dr",
    "sg:city":"Tempe",
    "sg:classifiers":[
        {
            "category":"Professional",
            "type":"Services"
        }
    ],
    "sg:phone":"+1 480 491 6931",
    "sg:postcode":"85283",
    "sg:province":"AZ",
    "wof:name":"Amanda Joshlin",
    "wof:placetype":"venue"
},
  "geometry": {"coordinates":[-111.934003,33.362424],"type":"Point"}
}