{
  "type": "Feature",
  "properties": {
    "addr:full":"270 E Hunt Hwy Queen Creek AZ 85243",
    "addr:housenumber":"270",
    "addr:postcode":"85243",
    "addr:street":"E Hunt Hwy",
    "iso:country":"US",
    "sg:address":"270 E Hunt Hwy",
    "sg:city":"Queen Creek",
    "sg:classifiers":[
        {
            "category":"Restaurant",
            "type":"Food & Drink"
        }
    ],
    "sg:phone":"+1 480 882 9998",
    "sg:postcode":"85243",
    "sg:province":"AZ",
    "wof:name":"R & R Pizza Express",
    "wof:placetype":"venue"
},
  "geometry": {"coordinates":[-111.56715699999999,33.166051],"type":"Point"}
}