{
  "type": "Feature",
  "properties": {
    "iso:country":"US",
    "sg:address":"6036 W Muriel Dr",
    "sg:city":"Glendale",
    "sg:classifiers":[
        {
            "category":"Professional",
            "type":"Services"
        }
    ],
    "sg:phone":"+1 602 547 8728",
    "sg:postcode":"85308",
    "sg:province":"AZ",
    "wof:name":"Vincent Jasperson",
    "wof:placetype":"venue"
},
  "geometry": {"coordinates":[-112.18859999999999,33.64584],"type":"Point"}
}