{
  "type": "Feature",
  "properties": {
    "addr:full":"9925 W Camelback Rd Phoenix AZ 85037",
    "addr:housenumber":"9925",
    "addr:postcode":"85037",
    "addr:street":"W Camelback Rd",
    "iso:country":"US",
    "sg:address":"9925 W Camelback Rd",
    "sg:city":"Phoenix",
    "sg:classifiers":[
        {
            "category":"Coffee & Tea",
            "type":"Food & Drink"
        }
    ],
    "sg:menulink":"http://www.allmenus.com/az/phoenix/108335-starbucks-coffee/menu/",
    "sg:phone":"+1 623 872 6172",
    "sg:postcode":"85037",
    "sg:province":"AZ",
    "sg:tags":[
        "american"
    ],
    "wof:name":"Starbucks Coffee",
    "wof:placetype":"venue"
},
  "geometry": {"coordinates":[-112.273691,33.508318],"type":"Point"}
}