{
  "type": "Feature",
  "properties": {
    "addr:full":"219 N Parkwood Rd Payson AZ 85541",
    "addr:housenumber":"219",
    "addr:postcode":"85541",
    "addr:street":"N Parkwood Rd",
    "iso:country":"US",
    "sg:address":"219 N Parkwood Rd",
    "sg:city":"Payson",
    "sg:classifiers":[
        {
            "category":"Professional",
            "subcategory":"Art Services",
            "type":"Services"
        }
    ],
    "sg:phone":"+1 928 474 7467",
    "sg:postcode":"85541",
    "sg:province":"AZ",
    "sg:tags":[
        "designer",
        "display",
        "producer"
    ],
    "wof:name":"Diane Designs/Christeph Creations",
    "wof:placetype":"venue"
},
  "geometry": {"coordinates":[-111.331357,34.241639],"type":"Point"}
}