{
  "type": "Feature",
  "properties": {
    "iso:country":"US",
    "sg:address":"8665 E Hartford Dr",
    "sg:city":"Scottsdale",
    "sg:classifiers":[
        {
            "category":"Insurance",
            "subcategory":"Title Insurance",
            "type":"Services"
        }
    ],
    "sg:phone":"+1 480 473 0961",
    "sg:postcode":"85255",
    "sg:province":"AZ",
    "sg:tags":[
        "real estate"
    ],
    "wof:name":"Commerce Title Company",
    "wof:placetype":"venue"
},
  "geometry": {"coordinates":[-111.892302,33.643421],"type":"Point"}
}