{
  "type": "Feature",
  "properties": {
    "iso:country":"US",
    "sg:address":"1115 W Oregon Ave",
    "sg:city":"Phoenix",
    "sg:classifiers":[
        {
            "category":"Education",
            "subcategory":"Special Training",
            "type":"Public Place"
        }
    ],
    "sg:phone":"+1 602 222 5421",
    "sg:postcode":"85013",
    "sg:province":"AZ",
    "sg:tags":[
        "educational"
    ],
    "wof:name":"Scholastics Plus Inc",
    "wof:placetype":"venue"
},
  "geometry": {"coordinates":[-112.087029,33.514451],"type":"Point"}
}