{
  "type": "Feature",
  "properties": {
    "addr:full":"5533 N 7th St Phoenix AZ 85014",
    "addr:housenumber":"5533",
    "addr:postcode":"85014",
    "addr:street":"N 7Th St",
    "iso:country":"US",
    "sg:address":"5533 N 7th St",
    "sg:city":"Phoenix",
    "sg:classifiers":[
        {
            "category":"Wholesale",
            "subcategory":"Machinery & Supplies",
            "type":"Manufacturing & Wholesale Goods"
        }
    ],
    "sg:phone":"+1 602 212 5255",
    "sg:postcode":"85014",
    "sg:province":"AZ",
    "sg:tags":[
        "equipment",
        "salon",
        "establishment",
        "beauty"
    ],
    "wof:name":"Design Dimensions Direct",
    "wof:placetype":"venue"
},
  "geometry": {"coordinates":[-112.064922,33.518246],"type":"Point"}
}