{
  "type": "Feature",
  "properties": {
    "iso:country":"US",
    "sg:address":"915 E Broadway Rd",
    "sg:city":"Mesa",
    "sg:classifiers":[
        {
            "category":"Shopping",
            "subcategory":"Used Merchandise",
            "type":"Retail Goods"
        }
    ],
    "sg:phone":"+1 480 898 7330",
    "sg:postcode":"85204",
    "sg:province":"AZ",
    "sg:tags":[
        "shop",
        "thrift"
    ],
    "wof:name":"J & S Thrift Store",
    "wof:placetype":"venue"
},
  "geometry": {"coordinates":[-111.81122999999999,33.407787],"type":"Point"}
}