{
  "type": "Feature",
  "properties": {
    "addr:full":"1717 S Dorsey Ln Tempe AZ 85281",
    "addr:housenumber":"1717",
    "addr:postcode":"85281",
    "addr:street":"S Dorsey Ln",
    "iso:country":"US",
    "sg:address":"1717 S Dorsey Ln",
    "sg:city":"Tempe",
    "sg:classifiers":[
        {
            "category":"Shopping",
            "subcategory":"Computers & Home Electronics",
            "type":"Retail Goods"
        }
    ],
    "sg:phone":"+1 480 699 7926",
    "sg:postcode":"85281",
    "sg:province":"AZ",
    "wof:name":"Vandalet Computers LLC",
    "wof:placetype":"venue"
},
  "geometry": {"coordinates":[-111.917726,33.409467],"type":"Point"}
}