{
  "type": "Feature",
  "properties": {
    "addr:full":"1355 N McQueen Rd Gilbert AZ 85233",
    "addr:housenumber":"1355",
    "addr:postcode":"85233",
    "addr:street":"N Mcqueen Rd",
    "iso:country":"US",
    "sg:address":"1355 N McQueen Rd",
    "sg:city":"Gilbert",
    "sg:classifiers":[
        {
            "category":"Building & Trades",
            "subcategory":"Construction",
            "type":"Services"
        }
    ],
    "sg:phone":"+1 480 503 1354",
    "sg:postcode":"85233",
    "sg:province":"AZ",
    "sg:tags":[
        "house",
        "nonresidential",
        "general",
        "contractor"
    ],
    "wof:name":"Mc Intyre Construction Inc",
    "wof:placetype":"venue"
},
  "geometry": {"coordinates":[-111.824589,33.372191],"type":"Point"}
}