{
  "type": "Feature",
  "properties": {
    "iso:country":"US",
    "sg:address":"4916 W Joyce Cir",
    "sg:city":"Glendale",
    "sg:classifiers":[
        {
            "category":"Organizations",
            "subcategory":"Non-profit Organization",
            "type":"Services"
        }
    ],
    "sg:phone":"+1 602 978 3306",
    "sg:postcode":"85308",
    "sg:province":"AZ",
    "sg:tags":[
        "charity",
        "foundations-educational",
        "philanthropic",
        "research"
    ],
    "wof:name":"Manna Enterprises",
    "wof:placetype":"venue"
},
  "geometry": {"coordinates":[-112.163177,33.640659],"type":"Point"}
}