{
  "type": "Feature",
  "properties": {
    "iso:country":"US",
    "sg:address":"7038 E Adobe St",
    "sg:city":"Mesa",
    "sg:classifiers":[
        {
            "category":"Education",
            "subcategory":"School",
            "type":"Public Place"
        }
    ],
    "sg:phone":"+1 480 472 8990",
    "sg:postcode":"85207",
    "sg:province":"AZ",
    "wof:name":"Power Middle School",
    "wof:placetype":"venue"
},
  "geometry": {"coordinates":[-111.681545,33.429999],"type":"Point"}
}