{
  "type": "Feature",
  "properties": {
    "iso:country":"US",
    "sg:address":"1730 W Sunrise Blvd",
    "sg:city":"Gilbert",
    "sg:classifiers":[
        {
            "category":"Manufacturing",
            "subcategory":"Retail Goods",
            "type":"Manufacturing & Wholesale Goods"
        },
        {
            "category":"Manufacturing",
            "subcategory":"Rubber & Plastics",
            "type":"Manufacturing & Wholesale Goods"
        }
    ],
    "sg:phone":"+1 480 892 9395",
    "sg:postcode":"85233",
    "sg:province":"AZ",
    "sg:tags":[
        "plate",
        "product",
        "assembly",
        "mfg",
        "work",
        "fabricated",
        "fabricating"
    ],
    "wof:name":"Pure Logic Industries",
    "wof:placetype":"venue"
},
  "geometry": {"coordinates":[-111.825925,33.355451],"type":"Point"}
}