{
  "type": "Feature",
  "properties": {
    "iso:country":"US",
    "sg:address":"318 S Crismon Rd",
    "sg:city":"Mesa",
    "sg:classifiers":[
        {
            "category":"Real Estate",
            "subcategory":"Developer",
            "type":"Services"
        },
        {
            "category":"Real Estate",
            "subcategory":"Real Estate Operator",
            "type":"Services"
        }
    ],
    "sg:phone":"+1 480 984 2611",
    "sg:postcode":"85208",
    "sg:province":"AZ",
    "sg:tags":[
        "mobile",
        "home",
        "site"
    ],
    "wof:name":"Patio Gardens Mobile Home Park",
    "wof:placetype":"venue"
},
  "geometry": {"coordinates":[-111.615448,33.408049],"type":"Point"}
}