{
  "type": "Feature",
  "properties": {
    "iso:country":"US",
    "sg:address":"11221 N 58th Ave",
    "sg:city":"Glendale",
    "sg:classifiers":[
        {
            "category":"Restaurant",
            "type":"Food & Drink"
        }
    ],
    "sg:phone":"+1 623 934 8071",
    "sg:postcode":"85304",
    "sg:province":"AZ",
    "wof:name":"Top Rack",
    "wof:placetype":"venue"
},
  "geometry": {"coordinates":[-112.184499,33.588995],"type":"Point"}
}