{
  "type": "Feature",
  "properties": {
    "iso:country":"US",
    "sg:address":"24815 S Lakestar Dr",
    "sg:city":"Chandler",
    "sg:classifiers":[
        {
            "category":"Manufacturing",
            "subcategory":"Jewelry",
            "type":"Manufacturing & Wholesale Goods"
        }
    ],
    "sg:phone":"+1 480 802 7112",
    "sg:postcode":"85248",
    "sg:province":"AZ",
    "sg:tags":[
        "material",
        "mfg"
    ],
    "wof:name":"Howill Designs",
    "wof:placetype":"venue"
},
  "geometry": {"coordinates":[-111.88593899999999,33.2216],"type":"Point"}
}