{
  "type": "Feature",
  "properties": {
    "iso:country":"US",
    "sg:address":"299 S Willard St",
    "sg:city":"Cottonwood",
    "sg:classifiers":[
        {
            "category":"Health Services",
            "subcategory":"Doctor",
            "type":"Services"
        }
    ],
    "sg:phone":"+1 928 649 9000",
    "sg:postcode":"86326",
    "sg:province":"AZ",
    "sg:tags":[
        "physician",
        "surgeon"
    ],
    "wof:name":"Northern Arizona Eye Spec",
    "wof:placetype":"venue"
},
  "geometry": {"coordinates":[-112.027299,34.734143],"type":"Point"}
}