{
  "type": "Feature",
  "properties": {
    "addr:full":"2640 W Palomino Dr Chandler AZ 85224",
    "addr:housenumber":"2640",
    "addr:postcode":"85224",
    "addr:street":"W Palomino Dr",
    "iso:country":"US",
    "sg:address":"2640 W Palomino Dr",
    "sg:city":"Chandler",
    "sg:classifiers":[
        {
            "category":"Personal",
            "type":"Services"
        }
    ],
    "sg:phone":"+1 480 756 2522",
    "sg:postcode":"85224",
    "sg:province":"AZ",
    "sg:tags":[
        "therapist",
        "massage",
        "physical"
    ],
    "wof:name":"Arizona Natural Health Svc",
    "wof:placetype":"venue"
},
  "geometry": {"coordinates":[-111.88791399999999,33.341178],"type":"Point"}
}