{
  "type": "Feature",
  "properties": {
    "iso:country":"US",
    "sg:address":"574 N Yucca St",
    "sg:city":"Chandler",
    "sg:classifiers":[
        {
            "category":"Wholesale",
            "subcategory":"Medical Equipment & Supplies",
            "type":"Manufacturing & Wholesale Goods"
        }
    ],
    "sg:phone":"+1 480 786 4458",
    "sg:postcode":"85224",
    "sg:province":"AZ",
    "sg:tags":[
        "hospital"
    ],
    "wof:name":"EMS Specialists",
    "wof:placetype":"venue"
},
  "geometry": {"coordinates":[-111.873839,33.312398],"type":"Point"}
}