{
  "type": "Feature",
  "properties": {
    "addr:full":"2752 E Harwell Rd Gilbert AZ 85234",
    "addr:housenumber":"2752",
    "addr:postcode":"85234",
    "addr:street":"E Harwell Rd",
    "iso:country":"US",
    "sg:address":"2752 E Harwell Rd",
    "sg:city":"Gilbert",
    "sg:classifiers":[
        {
            "category":"Retail",
            "subcategory":"Laundry & Dry Cleaning",
            "type":"Services"
        }
    ],
    "sg:phone":"+1 602 908 4074",
    "sg:postcode":"85234",
    "sg:province":"AZ",
    "sg:tags":[
        "cleaners",
        "rug",
        "carpet"
    ],
    "wof:name":"Ideal Professional Carpet",
    "wof:placetype":"venue"
},
  "geometry": {"coordinates":[-111.730659,33.377526],"type":"Point"}
}