{
  "type": "Feature",
  "properties": {
    "addr:full":"4446 E University Dr Mesa AZ 85205",
    "addr:housenumber":"4446",
    "addr:postcode":"85205",
    "addr:street":"E University Dr",
    "iso:country":"US",
    "sg:address":"4446 E University Dr",
    "sg:city":"Mesa",
    "sg:classifiers":[
        {
            "category":"Banks & Credit Unions",
            "subcategory":"Investment Brokerage",
            "type":"Services"
        }
    ],
    "sg:phone":"+1 480 807 8640",
    "sg:postcode":"85205",
    "sg:province":"AZ",
    "sg:tags":[
        "security"
    ],
    "sg:website":"www.edwardjones.com",
    "wof:name":"Edward Jones Co",
    "wof:placetype":"venue"
},
  "geometry": {"coordinates":[-111.733161,33.422886],"type":"Point"}
}