{
  "type": "Feature",
  "properties": {
    "iso:country":"US",
    "sg:address":"45 W Boston St",
    "sg:city":"Chandler",
    "sg:classifiers":[
        {
            "category":"Real Estate",
            "subcategory":"Real Estate Agent",
            "type":"Services"
        }
    ],
    "sg:phone":"+1 480 786 6567",
    "sg:postcode":"85225",
    "sg:province":"AZ",
    "wof:name":"Jon Terrigino Rentals",
    "wof:placetype":"venue"
},
  "geometry": {"coordinates":[-111.8416,33.302228],"type":"Point"}
}