{
  "type": "Feature",
  "properties": {
    "addr:full":"2604 N 36th St Phoenix AZ 85008",
    "addr:housenumber":"2604",
    "addr:postcode":"85008",
    "addr:street":"N 36Th St",
    "iso:country":"US",
    "sg:address":"2604 N 36th St",
    "sg:city":"Phoenix",
    "sg:classifiers":[
        {
            "category":"Manufacturing",
            "subcategory":"Glass & Minerals",
            "type":"Manufacturing & Wholesale Goods"
        }
    ],
    "sg:phone":"+1 602 956 5579",
    "sg:postcode":"85008",
    "sg:province":"AZ",
    "sg:tags":[
        "brick",
        "common"
    ],
    "wof:name":"Arizona Brick Source",
    "wof:placetype":"venue"
},
  "geometry": {"coordinates":[-112.004267,33.47765],"type":"Point"}
}