{
  "type": "Feature",
  "properties": {
    "iso:country":"US",
    "sg:address":"10607 E Paradise Ln",
    "sg:city":"Scottsdale",
    "sg:classifiers":[
        {
            "category":"Real Estate",
            "subcategory":"Real Estate Agent",
            "type":"Services"
        }
    ],
    "sg:phone":"+1 480 473 0877",
    "sg:postcode":"85255",
    "sg:province":"AZ",
    "sg:tags":[
        "management"
    ],
    "wof:name":"Mcdowell Mountain Ranch HOA",
    "wof:placetype":"venue"
},
  "geometry": {"coordinates":[-111.85203,33.634185],"type":"Point"}
}