{
  "type": "Feature",
  "properties": {
    "addr:full":"3464 W Earll Dr Phoenix AZ 85017",
    "addr:housenumber":"3464",
    "addr:postcode":"85017",
    "addr:street":"W Earll Dr",
    "iso:country":"US",
    "sg:address":"3464 W Earll Dr",
    "sg:city":"Phoenix",
    "sg:classifiers":[
        {
            "category":"Wholesale",
            "subcategory":"Poultry",
            "type":"Manufacturing & Wholesale Goods"
        },
        {
            "category":"Wholesale",
            "subcategory":"Meat",
            "type":"Manufacturing & Wholesale Goods"
        }
    ],
    "sg:phone":"+1 602 269 3654",
    "sg:postcode":"85017",
    "sg:province":"AZ",
    "wof:name":"Butcher Shop",
    "wof:placetype":"venue"
},
  "geometry": {"coordinates":[-112.134248,33.484137],"type":"Point"}
}