{
  "type": "Feature",
  "properties": {
    "addr:full":"684 N Grand Ave Nogales AZ 85621",
    "addr:housenumber":"684",
    "addr:postcode":"85621",
    "addr:street":"N Grand Ave",
    "iso:country":"US",
    "sg:address":"684 N Grand Ave",
    "sg:city":"Nogales",
    "sg:classifiers":[
        {
            "category":"Autos & Motor Vehicles",
            "subcategory":"Auto Supplies",
            "type":"Retail Goods"
        }
    ],
    "sg:phone":"+1 520 287 2834",
    "sg:postcode":"85621",
    "sg:province":"AZ",
    "sg:tags":[
        "tire"
    ],
    "wof:name":"Super Tire",
    "wof:placetype":"venue"
},
  "geometry": {"coordinates":[-110.931561,31.343986],"type":"Point"}
}