{
  "type": "Feature",
  "properties": {
    "iso:country":"US",
    "sg:address":"4934 W Crittenden Ln",
    "sg:city":"Phoenix",
    "sg:classifiers":[
        {
            "category":"Shopping",
            "subcategory":"Jewelry",
            "type":"Retail Goods"
        },
        {
            "category":"Manufacturing",
            "subcategory":"Jewelry",
            "type":"Manufacturing & Wholesale Goods"
        }
    ],
    "sg:phone":"+1 623 691 9056",
    "sg:postcode":"85031",
    "sg:province":"AZ",
    "sg:tags":[
        "manufacturer",
        "jewelers-wholesale",
        "jeweler"
    ],
    "wof:name":"Avelinas Accessories",
    "wof:placetype":"venue"
},
  "geometry": {"coordinates":[-112.166558,33.488574],"type":"Point"}
}