{
  "type": "Feature",
  "properties": {
    "iso:country":"US",
    "sg:address":"6750 E Noyes St",
    "sg:city":"Sahuarita",
    "sg:classifiers":[
        {
            "category":"Building & Trades",
            "subcategory":"Construction",
            "type":"Services"
        }
    ],
    "sg:phone":"+1 520 762 9451",
    "sg:postcode":"85629",
    "sg:province":"AZ",
    "sg:tags":[
        "carpentry",
        "contractor"
    ],
    "wof:name":"Golden Oak Carpentry LLC",
    "wof:placetype":"venue"
},
  "geometry": {"coordinates":[-110.84489,31.973891],"type":"Point"}
}