{
  "type": "Feature",
  "properties": {
    "iso:country":"US",
    "sg:address":"2912 E Indian School",
    "sg:city":"Phoenix",
    "sg:classifiers":[
        {
            "category":"Marine",
            "type":"Transportation"
        }
    ],
    "sg:phone":"+1 602 957 4591",
    "sg:postcode":"85016",
    "sg:province":"AZ",
    "sg:tags":[
        "cruise"
    ],
    "sg:website":"http://bigjimsailing.cruisebrothers.com",
    "wof:name":"BIGJIM SAILING CRUISE BROTHERS",
    "wof:placetype":"venue"
},
  "geometry": {"coordinates":[-112.019129,33.49508],"type":"Point"}
}