{
  "type": "Feature",
  "properties": {
    "iso:country":"US",
    "sg:address":"6328 N 7th St",
    "sg:city":"Phoenix",
    "sg:classifiers":[
        {
            "category":"Retail",
            "subcategory":"Auto Repair",
            "type":"Services"
        }
    ],
    "sg:phone":"+1 602 265 2249",
    "sg:postcode":"85014",
    "sg:province":"AZ",
    "sg:tags":[
        "repairing",
        "automobile"
    ],
    "wof:name":"Prentice Garage",
    "wof:placetype":"venue"
},
  "geometry": {"coordinates":[-112.065012,33.528301],"type":"Point"}
}