{
  "type": "Feature",
  "properties": {
    "iso:country":"US",
    "sg:address":"2472 S Mary Ave",
    "sg:city":"Yuma",
    "sg:classifiers":[
        {
            "category":"Shopping",
            "subcategory":"Bicycles & Sporting Goods",
            "type":"Retail Goods"
        }
    ],
    "sg:phone":"+1 928 726 0953",
    "sg:postcode":"85365",
    "sg:province":"AZ",
    "sg:tags":[
        "repair"
    ],
    "wof:name":"Bow Shop",
    "wof:placetype":"venue"
},
  "geometry": {"coordinates":[-114.606926,32.682561],"type":"Point"}
}