{
  "type": "Feature",
  "properties": {
    "addr:full":"7607 E Greenway Rd Scottsdale AZ 85260",
    "addr:housenumber":"7607",
    "addr:postcode":"85260",
    "addr:street":"E Greenway Rd",
    "iso:country":"US",
    "sg:address":"7607 E Greenway Rd",
    "sg:city":"Scottsdale",
    "sg:classifiers":[
        {
            "category":"Autos & Motor Vehicles",
            "subcategory":"Auto Supplies",
            "type":"Retail Goods"
        }
    ],
    "sg:phone":"+1 480 998 0521",
    "sg:postcode":"85260",
    "sg:province":"AZ",
    "sg:tags":[
        "tire"
    ],
    "wof:name":"Discount Tire Co",
    "wof:placetype":"venue"
},
  "geometry": {"coordinates":[-111.91542200000001,33.625604],"type":"Point"}
}