{
  "type": "Feature",
  "properties": {
    "iso:country":"US",
    "sg:address":"1643 N Alvernon Way",
    "sg:city":"Tucson",
    "sg:classifiers":[
        {
            "category":"Health Services",
            "subcategory":"Doctor",
            "type":"Services"
        }
    ],
    "sg:phone":"+1 520 743 4660",
    "sg:postcode":"85712",
    "sg:province":"AZ",
    "sg:tags":[
        "physician",
        "surgeon"
    ],
    "wof:name":"Arizona Homeopathy Ctr",
    "wof:placetype":"venue"
},
  "geometry": {"coordinates":[-110.909741,32.242665],"type":"Point"}
}