{
  "type": "Feature",
  "properties": {
    "iso:country":"US",
    "sg:address":"323 N San Francisco St",
    "sg:city":"Flagstaff",
    "sg:classifiers":[
        {
            "category":"Professional",
            "subcategory":"Management & Consulting",
            "type":"Services"
        }
    ],
    "sg:phone":"+1 928 774 8485",
    "sg:postcode":"86001",
    "sg:province":"AZ",
    "sg:tags":[
        "medical",
        "administration",
        "business"
    ],
    "wof:name":"Healthcare Management Partners",
    "wof:placetype":"venue"
},
  "geometry": {"coordinates":[-111.64667300000001,35.200288],"type":"Point"}
}