{
  "type": "Feature",
  "properties": {
    "iso:country":"US",
    "sg:address":"500 W Cam Encanto",
    "sg:city":"Green Valley",
    "sg:classifiers":[
        {
            "category":"Social Services",
            "subcategory":"Adult Care",
            "type":"Services"
        }
    ],
    "sg:phone":"+1 520 399 3620",
    "sg:postcode":"85614",
    "sg:province":"AZ",
    "sg:tags":[
        "home",
        "residential"
    ],
    "sg:website":"www.srgseniorliving.com",
    "wof:name":"Silver Springs Retirement",
    "wof:placetype":"venue"
},
  "geometry": {"coordinates":[-110.996945,31.825343],"type":"Point"}
}