{
  "type": "Feature",
  "properties": {
    "iso:country":"US",
    "sg:address":"3430 N Mountain Ridge",
    "sg:city":"Mesa",
    "sg:classifiers":[
        {
            "category":"Wholesale",
            "subcategory":"Computers",
            "type":"Manufacturing & Wholesale Goods"
        }
    ],
    "sg:phone":"+1 480 985 4854",
    "sg:postcode":"85207",
    "sg:province":"AZ",
    "sg:tags":[
        "product",
        "software"
    ],
    "wof:name":"Netward Software Inc",
    "wof:placetype":"venue"
},
  "geometry": {"coordinates":[-111.667293,33.480266],"type":"Point"}
}