{
  "type": "Feature",
  "properties": {
    "iso:country":"US",
    "sg:address":"725 N Central Ave Ste 101",
    "sg:city":"Avondale",
    "sg:classifiers":[
        {
            "category":"Restaurant",
            "type":"Food & Drink"
        }
    ],
    "sg:phone":"+1 623 925 8574",
    "sg:postcode":"85323",
    "sg:province":"AZ",
    "sg:tags":[
        "mexican"
    ],
    "wof:name":"Chabely's Mexican Food",
    "wof:placetype":"venue"
},
  "geometry": {"coordinates":[-112.349198,33.442683],"type":"Point"}
}