{
  "type": "Feature",
  "properties": {
    "addr:full":"1375 N Litchfield Road Suite 101 Goodyear AZ 85338",
    "addr:housenumber":"1375",
    "addr:postcode":"85338",
    "addr:street":"N Litchfield Road Suite 101",
    "iso:country":"US",
    "sg:address":"1375 N Litchfield Road Suite 101",
    "sg:city":"Goodyear",
    "sg:classifiers":[
        {
            "category":"Restaurant",
            "type":"Food & Drink"
        }
    ],
    "sg:phone":"+1 623 535 7373",
    "sg:postcode":"85338",
    "sg:province":"AZ",
    "sg:tags":[
        "pizza"
    ],
    "wof:name":"Palm Valley Rosati's Pizza",
    "wof:placetype":"venue"
},
  "geometry": {"coordinates":[-112.358176,33.449549],"type":"Point"}
}