{
  "type": "Feature",
  "properties": {
    "iso:country":"US",
    "sg:address":"4731 W Acoma Dr",
    "sg:city":"Glendale",
    "sg:classifiers":[
        {
            "category":"Building & Trades",
            "subcategory":"Plumbing",
            "type":"Services"
        }
    ],
    "sg:phone":"+1 602 547 9946",
    "sg:postcode":"85306",
    "sg:province":"AZ",
    "sg:tags":[
        "contractor"
    ],
    "wof:name":"Schuetz Plumbing",
    "wof:placetype":"venue"
},
  "geometry": {"coordinates":[-112.163562,33.617868],"type":"Point"}
}