{
  "type": "Feature",
  "properties": {
    "iso:country":"US",
    "sg:address":"1034 E Verde Lane",
    "sg:city":"Tempe",
    "sg:classifiers":[
        {
            "category":"Professional",
            "subcategory":"Accounting & Tax Preparation",
            "type":"Services"
        }
    ],
    "sg:phone":"+1 480 777 8777",
    "sg:postcode":"85284",
    "sg:province":"AZ",
    "sg:tags":[
        "accountant"
    ],
    "wof:name":"Lavoy Lynn M",
    "wof:placetype":"venue"
},
  "geometry": {"coordinates":[-111.924766,33.345275],"type":"Point"}
}