{
  "type": "Feature",
  "properties": {
    "iso:country":"US",
    "sg:address":"2121 S Priest Dr",
    "sg:city":"Tempe",
    "sg:classifiers":[
        {
            "category":"Social Services",
            "subcategory":"Job Training",
            "type":"Services"
        },
        {
            "category":"Education",
            "subcategory":"Vocational School",
            "type":"Public Place"
        }
    ],
    "sg:phone":"+1 480 829 0620",
    "sg:postcode":"85282",
    "sg:province":"AZ",
    "sg:tags":[
        "consultant",
        "business"
    ],
    "wof:name":"On Stage Marketing",
    "wof:placetype":"venue"
},
  "geometry": {"coordinates":[-111.96077,33.405668],"type":"Point"}
}