{
  "type": "Feature",
  "properties": {
    "addr:full":"7919 E 3rd Ave Mesa AZ 85208",
    "addr:housenumber":"7919",
    "addr:postcode":"85208",
    "addr:street":"E 3Rd Ave",
    "iso:country":"US",
    "sg:address":"7919 E 3rd Ave",
    "sg:city":"Mesa",
    "sg:classifiers":[
        {
            "category":"Taxi",
            "type":"Transportation"
        }
    ],
    "sg:phone":"+1 480 984 0000",
    "sg:postcode":"85208",
    "sg:province":"AZ",
    "wof:name":"Prince & Princess Ako Taxicab",
    "wof:placetype":"venue"
},
  "geometry": {"coordinates":[-111.66007999999999,33.412028],"type":"Point"}
}