{
  "type": "Feature",
  "properties": {
    "iso:country":"US",
    "sg:address":"5480 E Pla de Royale",
    "sg:city":"Tucson",
    "sg:classifiers":[
        {
            "category":"Shopping",
            "subcategory":"Gifts & Souvenirs",
            "type":"Retail Goods"
        }
    ],
    "sg:phone":"+1 520 577 8209",
    "sg:postcode":"85718",
    "sg:province":"AZ",
    "wof:name":"Southwest Sport Cards",
    "wof:placetype":"venue"
},
  "geometry": {"coordinates":[-110.875477,32.281677],"type":"Point"}
}