{
  "type": "Feature",
  "properties": {
    "iso:country":"US",
    "sg:address":"3820 S Palo Verde Rd",
    "sg:city":"Tucson",
    "sg:classifiers":[
        {
            "category":"Restaurant",
            "type":"Food & Drink"
        }
    ],
    "sg:phone":"+1 520 294 3917",
    "sg:postcode":"85714",
    "sg:province":"AZ",
    "sg:tags":[
        "shop",
        "coffee"
    ],
    "wof:name":"Java Edge",
    "wof:placetype":"venue"
},
  "geometry": {"coordinates":[-110.91777500000001,32.176076],"type":"Point"}
}