{
  "type": "Feature",
  "properties": {
    "iso:country":"US",
    "sg:address":"3964 N Oracle Rd",
    "sg:city":"Tucson",
    "sg:classifiers":[
        {
            "category":"Wholesale",
            "subcategory":"Electrical",
            "type":"Manufacturing & Wholesale Goods"
        }
    ],
    "sg:phone":"+1 520 623 2545",
    "sg:postcode":"85705",
    "sg:province":"AZ",
    "sg:tags":[
        "radio"
    ],
    "wof:name":"Air Touch Paging",
    "wof:placetype":"venue"
},
  "geometry": {"coordinates":[-110.978077,32.278081],"type":"Point"}
}