{
  "type": "Feature",
  "properties": {
    "iso:country":"US",
    "sg:address":"3310 W Ironwood Dr",
    "sg:city":"Phoenix",
    "sg:classifiers":[
        {
            "category":"Professional",
            "type":"Services"
        }
    ],
    "sg:phone":"+1 602 863 3504",
    "sg:postcode":"85051",
    "sg:province":"AZ",
    "wof:name":"S A Mirbes",
    "wof:placetype":"venue"
},
  "geometry": {"coordinates":[-112.131201,33.576581],"type":"Point"}
}