{
  "type": "Feature",
  "properties": {
    "iso:country":"US",
    "sg:address":"4700 S Mill Ave",
    "sg:city":"Tempe",
    "sg:classifiers":[
        {
            "category":"Social Services",
            "type":"Services"
        }
    ],
    "sg:phone":"+1 480 941 0940",
    "sg:postcode":"85282",
    "sg:province":"AZ",
    "sg:tags":[
        "counselor",
        "marriage",
        "family"
    ],
    "wof:name":"Beverly Janowitz-Price",
    "wof:placetype":"venue"
},
  "geometry": {"coordinates":[-111.939388,33.380638],"type":"Point"}
}