{
  "type": "Feature",
  "properties": {
    "addr:full":"4648 N 7th Ave Phoenix AZ 85013",
    "addr:housenumber":"4648",
    "addr:postcode":"85013",
    "addr:street":"N 7Th Ave",
    "iso:country":"US",
    "sg:address":"4648 N 7th Ave",
    "sg:city":"Phoenix",
    "sg:classifiers":[
        {
            "category":"Wholesale",
            "subcategory":"Machinery & Supplies",
            "type":"Manufacturing & Wholesale Goods"
        }
    ],
    "sg:phone":"+1 602 277 5410",
    "sg:postcode":"85013",
    "sg:province":"AZ",
    "sg:tags":[
        "janitor"
    ],
    "wof:name":"Maintenance Mart",
    "wof:placetype":"venue"
},
  "geometry": {"coordinates":[-112.082534,33.505398],"type":"Point"}
}