{
  "type": "Feature",
  "properties": {
    "iso:country":"US",
    "sg:address":"1107 E Bell Rd Suite 8A",
    "sg:city":"Phoenix",
    "sg:classifiers":[
        {
            "category":"Manufacturing",
            "subcategory":"Signs",
            "type":"Manufacturing & Wholesale Goods"
        }
    ],
    "sg:phone":"+1 602 504 6070",
    "sg:postcode":"85022",
    "sg:province":"AZ",
    "sg:website":"http://www.signarama.com",
    "wof:name":"SIGN-A-RAMA",
    "wof:placetype":"venue"
},
  "geometry": {"coordinates":[-112.058202,33.64026],"type":"Point"}
}