{
  "type": "Feature",
  "properties": {
    "iso:country":"US",
    "sg:address":"6947 N Galaxy Dr",
    "sg:city":"Tucson",
    "sg:classifiers":[
        {
            "category":"Real Estate",
            "subcategory":"Real Estate Agent",
            "type":"Services"
        }
    ],
    "sg:phone":"+1 520 877 9220",
    "sg:postcode":"85741",
    "sg:province":"AZ",
    "wof:name":"Matthew Tennyson Realtor",
    "wof:placetype":"venue"
},
  "geometry": {"coordinates":[-111.04249299999999,32.333044],"type":"Point"}
}