{
  "type": "Feature",
  "properties": {
    "iso:country":"US",
    "sg:address":"13448 N 7th St",
    "sg:city":"Phoenix",
    "sg:classifiers":[
        {
            "category":"Personal",
            "subcategory":"Beauty Salon",
            "type":"Services"
        }
    ],
    "sg:phone":"+1 602 375 0049",
    "sg:postcode":"85022",
    "sg:province":"AZ",
    "sg:tags":[
        "manicuring"
    ],
    "wof:name":"Jewelry Nail & Spa",
    "wof:placetype":"venue"
},
  "geometry": {"coordinates":[-112.065259,33.608648],"type":"Point"}
}