{
  "type": "Feature",
  "properties": {
    "iso:country":"US",
    "sg:address":"596 Shalimar Dr",
    "sg:city":"Prescott",
    "sg:classifiers":[
        {
            "category":"Personal",
            "type":"Services"
        },
        {
            "category":"Professional",
            "subcategory":"Art Services",
            "type":"Services"
        }
    ],
    "sg:phone":"+1 928 445 0884",
    "sg:postcode":"86303",
    "sg:province":"AZ",
    "sg:tags":[
        "photography",
        "videography",
        "wedding"
    ],
    "wof:name":"Jon Gipe Photo, Inc.",
    "wof:placetype":"venue"
},
  "geometry": {"coordinates":[-112.487188,34.534659],"type":"Point"}
}