{
  "type": "Feature",
  "properties": {
    "addr:full":"10561 E Roger Rd Tucson AZ 85749",
    "addr:housenumber":"10561",
    "addr:postcode":"85749",
    "addr:street":"E Roger Rd",
    "iso:country":"US",
    "sg:address":"10561 E Roger Rd",
    "sg:city":"Tucson",
    "sg:classifiers":[
        {
            "category":"Health Services",
            "subcategory":"Nursing And Care Facility",
            "type":"Services"
        }
    ],
    "sg:phone":"+1 520 829 6047",
    "sg:postcode":"85749",
    "sg:province":"AZ",
    "sg:tags":[
        "home",
        "convalescent"
    ],
    "wof:name":"Dempsey's Adult Care Home",
    "wof:placetype":"venue"
},
  "geometry": {"coordinates":[-110.76705800000001,32.280572],"type":"Point"}
}