{
  "type": "Feature",
  "properties": {
    "iso:country":"US",
    "sg:address":"1533 N Alma School Rd",
    "sg:city":"Mesa",
    "sg:classifiers":[
        {
            "category":"Shopping",
            "subcategory":"Computers & Home Electronics",
            "type":"Retail Goods"
        }
    ],
    "sg:phone":"+1 480 649 2779",
    "sg:postcode":"85201",
    "sg:province":"AZ",
    "sg:tags":[
        "equipment",
        "dealer"
    ],
    "wof:name":"New-Used P C's & Monitors",
    "wof:placetype":"venue"
},
  "geometry": {"coordinates":[-111.856222,33.441125],"type":"Point"}
}