{
  "type": "Feature",
  "properties": {
    "iso:country":"US",
    "sg:address":"1808 S 1st Ave",
    "sg:city":"Phoenix",
    "sg:classifiers":[
        {
            "category":"Manufacturing",
            "subcategory":"Retail Goods",
            "type":"Manufacturing & Wholesale Goods"
        }
    ],
    "sg:phone":"+1 602 254 6009",
    "sg:postcode":"85003",
    "sg:province":"AZ",
    "sg:tags":[
        "umbrella"
    ],
    "wof:name":"Solar Eclipses Umbrellas LLC",
    "wof:placetype":"venue"
},
  "geometry": {"coordinates":[-112.075169,33.430201],"type":"Point"}
}