{
  "type": "Feature",
  "properties": {
    "iso:country":"US",
    "sg:address":"651 S Kolb Rd",
    "sg:city":"Tucson",
    "sg:classifiers":[
        {
            "category":"Organizations",
            "subcategory":"Religious Organization",
            "type":"Services"
        }
    ],
    "sg:phone":"+1 520 886 1295",
    "sg:postcode":"85710",
    "sg:province":"AZ",
    "sg:tags":[
        "place",
        "worship",
        "church"
    ],
    "sg:website":"http://www.paloverdechurch.org",
    "wof:name":"Palo Verde Church Of Christ",
    "wof:placetype":"venue"
},
  "geometry": {"coordinates":[-110.840881,32.213509],"type":"Point"}
}