{
  "type": "Feature",
  "properties": {
    "addr:full":"4601 N 76th Ave Phoenix AZ 85033",
    "addr:housenumber":"4601",
    "addr:postcode":"85033",
    "addr:street":"N 76Th Ave",
    "iso:country":"US",
    "sg:address":"4601 N 76th Ave",
    "sg:city":"Phoenix",
    "sg:classifiers":[
        {
            "category":"Building & Trades",
            "subcategory":"Locksmith",
            "type":"Services"
        }
    ],
    "sg:phone":"+1 623 255 3098",
    "sg:postcode":"85033",
    "sg:province":"AZ",
    "sg:tags":[
        "key"
    ],
    "wof:name":"A Locksmith A 24 Hour",
    "wof:placetype":"venue"
},
  "geometry": {"coordinates":[-112.22252,33.504431],"type":"Point"}
}