{
  "type": "Feature",
  "properties": {
    "iso:country":"US",
    "sg:address":"4515 S McClintock Dr Ste 101",
    "sg:city":"Tempe",
    "sg:classifiers":[
        {
            "category":"Health Services",
            "subcategory":"Doctor",
            "type":"Services"
        },
        {
            "category":"Community Center",
            "type":"Public Place"
        }
    ],
    "sg:phone":"+1 480 860 6455",
    "sg:postcode":"85282",
    "sg:province":"AZ",
    "sg:tags":[
        "medical"
    ],
    "sg:website":"morrisonvein.com",
    "wof:name":"Morrison Vein Institute",
    "wof:placetype":"venue"
},
  "geometry": {"coordinates":[-111.908262,33.384686],"type":"Point"}
}