{
  "type": "Feature",
  "properties": {
    "iso:country":"US",
    "sg:address":"21 Cochise St",
    "sg:city":"Wickenburg",
    "sg:classifiers":[
        {
            "category":"Local Transit",
            "type":"Transportation"
        }
    ],
    "sg:phone":"+1 928 684 2888",
    "sg:postcode":"85390",
    "sg:province":"AZ",
    "wof:name":"Wickenburg Taxi",
    "wof:placetype":"venue"
},
  "geometry": {"coordinates":[-112.72824,33.967526],"type":"Point"}
}