{
  "type": "Feature",
  "properties": {
    "addr:full":"3300 N Central Ave Phoenix AZ 85012",
    "addr:housenumber":"3300",
    "addr:postcode":"85012",
    "addr:street":"N Central Ave",
    "iso:country":"US",
    "sg:address":"3300 N Central Ave",
    "sg:city":"Phoenix",
    "sg:classifiers":[
        {
            "category":"Professional",
            "subcategory":"Detective & Security Services",
            "type":"Services"
        }
    ],
    "sg:phone":"+1 602 778 6700",
    "sg:postcode":"85012",
    "sg:province":"AZ",
    "sg:tags":[
        "guard",
        "patrol"
    ],
    "wof:name":"TBV Interprises Inc",
    "wof:placetype":"venue"
},
  "geometry": {"coordinates":[-112.07385499999999,33.485478],"type":"Point"}
}