{
  "type": "Feature",
  "properties": {
    "iso:country":"US",
    "sg:address":"7625 E Redfield Rd",
    "sg:city":"Scottsdale",
    "sg:classifiers":[
        {
            "category":"Manufacturing",
            "subcategory":"Glass & Minerals",
            "type":"Manufacturing & Wholesale Goods"
        }
    ],
    "sg:phone":"+1 480 596 9079",
    "sg:postcode":"85260",
    "sg:province":"AZ",
    "sg:tags":[
        "product",
        "marble"
    ],
    "wof:name":"Marble & Granite Traditions",
    "wof:placetype":"venue"
},
  "geometry": {"coordinates":[-111.916535,33.613886],"type":"Point"}
}