{
  "type": "Feature",
  "properties": {
    "addr:full":"4120 N Goldwater Blvd Scottsdale AZ 85251",
    "addr:housenumber":"4120",
    "addr:postcode":"85251",
    "addr:street":"N Goldwater Blvd",
    "iso:country":"US",
    "sg:address":"4120 N Goldwater Blvd",
    "sg:city":"Scottsdale",
    "sg:classifiers":[
        {
            "category":"Professional",
            "subcategory":"Business Services",
            "type":"Services"
        }
    ],
    "sg:phone":"+1 480 446 0362",
    "sg:postcode":"85251",
    "sg:province":"AZ",
    "sg:tags":[
        "drafting"
    ],
    "wof:name":"Scale Drawings",
    "wof:placetype":"venue"
},
  "geometry": {"coordinates":[-111.930468,33.496004],"type":"Point"}
}