{
  "type": "Feature",
  "properties": {
    "iso:country":"US",
    "sg:address":"10250 W. McDowell Rd",
    "sg:city":"Avondale",
    "sg:classifiers":[
        {
            "category":"Cinema",
            "subcategory":"Movie Theater",
            "type":"Entertainment"
        }
    ],
    "sg:phone":"+1 623 478 9411",
    "sg:postcode":"85323",
    "sg:province":"AZ",
    "sg:website":"harkinstheatres.moviefone.com/sh...",
    "wof:name":"Harkins Gateway Pavilions 18",
    "wof:placetype":"venue"
},
  "geometry": {"coordinates":[-112.282,33.464639],"type":"Point"}
}