{
  "type": "Feature",
  "properties": {
    "addr:full":"9401 S Stanley Pl Tempe AZ 85284",
    "addr:housenumber":"9401",
    "addr:postcode":"85284",
    "addr:street":"S Stanley Pl",
    "iso:country":"US",
    "sg:address":"9401 S Stanley Pl",
    "sg:city":"Tempe",
    "sg:classifiers":[
        {
            "category":"Manufacturing",
            "subcategory":"Tools & Machinery",
            "type":"Manufacturing & Wholesale Goods"
        }
    ],
    "sg:phone":"+1 480 755 0051",
    "sg:postcode":"85284",
    "sg:province":"AZ",
    "sg:tags":[
        "electrical",
        "mfg"
    ],
    "wof:name":"Reynolds Mfg",
    "wof:placetype":"venue"
},
  "geometry": {"coordinates":[-111.921525,33.327345],"type":"Point"}
}