{
  "type": "Feature",
  "properties": {
    "addr:full":"1305 S Mission Rd Tucson AZ 85713",
    "addr:housenumber":"1305",
    "addr:postcode":"85713",
    "addr:street":"S Mission Rd",
    "iso:country":"US",
    "sg:address":"1305 S Mission Rd",
    "sg:city":"Tucson",
    "sg:classifiers":[
        {
            "category":"Government",
            "subcategory":"Office",
            "type":"Public Place"
        }
    ],
    "sg:phone":"+1 520 740 2646",
    "sg:postcode":"85713",
    "sg:province":"AZ",
    "sg:website":"www.co.pima.az.us",
    "wof:name":"Pima County Records Ctr-Archvs",
    "wof:placetype":"venue"
},
  "geometry": {"coordinates":[-110.99471800000001,32.204021],"type":"Point"}
}