{
  "type": "Feature",
  "properties": {
    "iso:country":"US",
    "sg:address":"15408 S 36th Pl",
    "sg:city":"Phoenix",
    "sg:classifiers":[
        {
            "category":"Home & Garden",
            "subcategory":"Home Furnishings",
            "type":"Retail Goods"
        }
    ],
    "sg:phone":"+1 480 704 8448",
    "sg:postcode":"85044",
    "sg:province":"AZ",
    "sg:tags":[
        "draperies",
        "window",
        "treatment",
        "curtain"
    ],
    "wof:name":"Shades Of Elegance",
    "wof:placetype":"venue"
},
  "geometry": {"coordinates":[-112.006993,33.307439],"type":"Point"}
}