{
  "type": "Feature",
  "properties": {
    "iso:country":"US",
    "sg:address":"5848 E Ingram St",
    "sg:city":"Mesa",
    "sg:classifiers":[
        {
            "category":"Professional",
            "subcategory":"Business Services",
            "type":"Services"
        }
    ],
    "sg:phone":"+1 480 641 7174",
    "sg:postcode":"85205",
    "sg:province":"AZ",
    "sg:tags":[
        "translator",
        "interpreter"
    ],
    "wof:name":"Precise Translations",
    "wof:placetype":"venue"
},
  "geometry": {"coordinates":[-111.703902,33.447011],"type":"Point"}
}