{
  "type": "Feature",
  "properties": {
    "iso:country":"US",
    "sg:address":"4610 W Camelback Rd",
    "sg:city":"Glendale",
    "sg:classifiers":[
        {
            "category":"Autos & Motor Vehicles",
            "subcategory":"Automobile Sales",
            "type":"Retail Goods"
        }
    ],
    "sg:phone":"+1 623 931 5970",
    "sg:postcode":"85301",
    "sg:province":"AZ",
    "sg:tags":[
        "truck"
    ],
    "wof:name":"Frontline Trucks",
    "wof:placetype":"venue"
},
  "geometry": {"coordinates":[-112.157659,33.509517],"type":"Point"}
}