{
  "type": "Feature",
  "properties": {
    "iso:country":"US",
    "sg:address":"1110 White House Canyon Rd",
    "sg:city":"Green Valley",
    "sg:classifiers":[
        {
            "category":"Government",
            "subcategory":"Office",
            "type":"Public Place"
        }
    ],
    "sg:phone":"+1 520 877 6290",
    "sg:postcode":"85614",
    "sg:province":"AZ",
    "wof:name":"Continental Green Valley Comm",
    "wof:placetype":"venue"
},
  "geometry": {"coordinates":[-110.965277,31.844593],"type":"Point"}
}