{
  "type": "Feature",
  "properties": {
    "iso:country":"US",
    "sg:address":"1224 W Cheyenne Dr",
    "sg:city":"Chandler",
    "sg:classifiers":[
        {
            "category":"Health Services",
            "subcategory":"Dentist",
            "type":"Services"
        }
    ],
    "sg:phone":"+1 480 540 9292",
    "sg:postcode":"85224",
    "sg:province":"AZ",
    "sg:tags":[
        "equipment",
        "dental",
        "supply"
    ],
    "wof:name":"Cheyenne Dental",
    "wof:placetype":"venue"
},
  "geometry": {"coordinates":[-111.864037,33.34747],"type":"Point"}
}