{
  "type": "Feature",
  "properties": {
    "iso:country":"US",
    "sg:address":"2834 N 72nd Ave",
    "sg:city":"Phoenix",
    "sg:classifiers":[
        {
            "category":"Shopping",
            "type":"Retail Goods"
        },
        {
            "category":"Professional",
            "subcategory":"Management & Consulting",
            "type":"Services"
        }
    ],
    "sg:phone":"+1 623 873 4669",
    "sg:postcode":"85035",
    "sg:province":"AZ",
    "sg:tags":[
        "direct",
        "sales",
        "store",
        "miscellaneous"
    ],
    "wof:name":"It Becomes You",
    "wof:placetype":"venue"
},
  "geometry": {"coordinates":[-112.214912,33.479075],"type":"Point"}
}