{
  "type": "Feature",
  "properties": {
    "iso:country":"US",
    "sg:address":"5109 W Citrine Pl",
    "sg:city":"Tucson",
    "sg:classifiers":[
        {
            "category":"Building & Trades",
            "subcategory":"Construction",
            "type":"Services"
        }
    ],
    "sg:phone":"+1 520 572 1578",
    "sg:postcode":"85742",
    "sg:province":"AZ",
    "sg:tags":[
        "house"
    ],
    "wof:name":"Gamut Builders Inc",
    "wof:placetype":"venue"
},
  "geometry": {"coordinates":[-111.074113,32.37127],"type":"Point"}
}