{
  "type": "Feature",
  "properties": {
    "iso:country":"US",
    "sg:address":"1400 W Washington St # 300",
    "sg:city":"Phoenix",
    "sg:classifiers":[
        {
            "category":"Government",
            "subcategory":"Office",
            "type":"Public Place"
        }
    ],
    "sg:phone":"+1 602 542 8242",
    "sg:postcode":"85007",
    "sg:province":"AZ",
    "wof:name":"Massage Therapy Board",
    "wof:placetype":"venue"
},
  "geometry": {"coordinates":[-112.090347,33.448181],"type":"Point"}
}