{
  "type": "Feature",
  "properties": {
    "iso:country":"US",
    "sg:address":"10105 E Via Linda Linda Ste 103",
    "sg:city":"Scottsdale",
    "sg:classifiers":[
        {
            "category":"Government",
            "subcategory":"Post Office",
            "type":"Public Place"
        }
    ],
    "sg:phone":"+1 480 860 4500",
    "sg:postcode":"85258",
    "sg:province":"AZ",
    "sg:tags":[
        "receiving",
        "mailbox-rental"
    ],
    "wof:name":"Mail N Office",
    "wof:placetype":"venue"
},
  "geometry": {"coordinates":[-111.864062,33.574176],"type":"Point"}
}