{
  "type": "Feature",
  "properties": {
    "iso:country":"US",
    "sg:address":"72 Erie St",
    "sg:city":"Bisbee",
    "sg:classifiers":[
        {
            "category":"Food & Beverages",
            "subcategory":"Groceries & Convenience Stores",
            "type":"Retail Goods"
        }
    ],
    "sg:phone":"+1 520 432 4011",
    "sg:postcode":"85603",
    "sg:province":"AZ",
    "wof:name":"Bisbee Food Co-Op",
    "wof:placetype":"venue"
},
  "geometry": {"coordinates":[-109.893773,31.430113],"type":"Point"}
}