{
  "type": "Feature",
  "properties": {
    "iso:country":"US",
    "sg:address":"3295 E Andy Devine Ave",
    "sg:city":"Kingman",
    "sg:classifiers":[
        {
            "category":"Restaurant",
            "type":"Food & Drink"
        }
    ],
    "sg:menulink":"http://www.allmenus.com/az/kingman-north/74763-pizza-hut/menu/",
    "sg:phone":"+1 928 757 3292",
    "sg:postcode":"86401",
    "sg:province":"AZ",
    "sg:tags":[
        "american",
        "pizza"
    ],
    "wof:name":"Pizza Hut",
    "wof:placetype":"venue"
},
  "geometry": {"coordinates":[-114.00875000000001,35.219387],"type":"Point"}
}