{
  "type": "Feature",
  "properties": {
    "addr:full":"14980 N 78th Way Scottsdale AZ 85260",
    "addr:housenumber":"14980",
    "addr:postcode":"85260",
    "addr:street":"N 78Th Way",
    "iso:country":"US",
    "sg:address":"14980 N 78th Way",
    "sg:city":"Scottsdale",
    "sg:classifiers":[
        {
            "category":"Professional",
            "subcategory":"Advertising",
            "type":"Services"
        }
    ],
    "sg:phone":"+1 480 922 0060",
    "sg:postcode":"85260",
    "sg:province":"AZ",
    "sg:website":"www.thebuildersource.com",
    "wof:name":"Builder's Source",
    "wof:placetype":"venue"
},
  "geometry": {"coordinates":[-111.906795,33.622712],"type":"Point"}
}