{
  "type": "Feature",
  "properties": {
    "iso:country":"US",
    "sg:address":"1325 E Main St",
    "sg:city":"Mesa",
    "sg:classifiers":[
        {
            "category":"Retail",
            "subcategory":"Auto Repair",
            "type":"Services"
        }
    ],
    "sg:phone":"+1 480 374 5460",
    "sg:postcode":"85203",
    "sg:province":"AZ",
    "sg:tags":[
        "repairing",
        "automobile"
    ],
    "sg:website":"http://www.thompsonsautorepair.net",
    "wof:name":"Thompson's Auto Repair & Towing",
    "wof:placetype":"venue"
},
  "geometry": {"coordinates":[-111.80298000000001,33.415157],"type":"Point"}
}