{
  "type": "Feature",
  "properties": {
    "iso:country":"US",
    "sg:address":"3737 E Kleindale Rd",
    "sg:city":"Tucson",
    "sg:classifiers":[
        {
            "category":"Building & Trades",
            "subcategory":"Construction",
            "type":"Services"
        }
    ],
    "sg:phone":"+1 520 795 7667",
    "sg:postcode":"85716",
    "sg:province":"AZ",
    "sg:tags":[
        "contractor"
    ],
    "wof:name":"Concrete Coring Co",
    "wof:placetype":"venue"
},
  "geometry": {"coordinates":[-110.913686,32.26881],"type":"Point"}
}