{
  "type": "Feature",
  "properties": {
    "iso:country":"US",
    "sg:address":"16 E Broadway Rd",
    "sg:city":"Phoenix",
    "sg:classifiers":[
        {
            "category":"Personal",
            "subcategory":"Beauty Salon",
            "type":"Services"
        },
        {
            "category":"Personal",
            "subcategory":"Barber",
            "type":"Services"
        }
    ],
    "sg:phone":"+1 602 268 3557",
    "sg:postcode":"85040",
    "sg:province":"AZ",
    "sg:tags":[
        "hair",
        "stylist"
    ],
    "wof:name":"Fiesta Haircutting Studio",
    "wof:placetype":"venue"
},
  "geometry": {"coordinates":[-112.07312,33.406712],"type":"Point"}
}