{
  "type": "Feature",
  "properties": {
    "iso:country":"US",
    "sg:address":"1735 Combat Dr",
    "sg:city":"Lake Havasu City",
    "sg:classifiers":[
        {
            "category":"Banks & Credit Unions",
            "subcategory":"Financial Services",
            "type":"Services"
        }
    ],
    "sg:phone":"+1 928 680 6958",
    "sg:postcode":"86403",
    "sg:province":"AZ",
    "sg:tags":[
        "investor"
    ],
    "wof:name":"Salco Investments LLC",
    "wof:placetype":"venue"
},
  "geometry": {"coordinates":[-114.333707,34.464659],"type":"Point"}
}