{
  "type": "Feature",
  "properties": {
    "iso:country":"US",
    "sg:address":"7426 E Stetson Dr",
    "sg:city":"Scottsdale",
    "sg:classifiers":[
        {
            "category":"Professional",
            "subcategory":"Employment Agencies",
            "type":"Services"
        }
    ],
    "sg:phone":"+1 480 941 4941",
    "sg:postcode":"85251",
    "sg:province":"AZ",
    "sg:tags":[
        "modeling"
    ],
    "wof:name":"Model & Talent Management",
    "wof:placetype":"venue"
},
  "geometry": {"coordinates":[-111.920366,33.499634],"type":"Point"}
}