{
  "type": "Feature",
  "properties": {
    "iso:country":"US",
    "sg:address":"5918 W Louise Dr",
    "sg:city":"Glendale",
    "sg:classifiers":[
        {
            "category":"Professional",
            "subcategory":"Accounting & Tax Preparation",
            "type":"Services"
        }
    ],
    "sg:phone":"+1 623 561 5018",
    "sg:postcode":"85310",
    "sg:province":"AZ",
    "sg:tags":[
        "return",
        "filing"
    ],
    "wof:name":"Moods Of A Different Kind",
    "wof:placetype":"venue"
},
  "geometry": {"coordinates":[-112.187521,33.685313],"type":"Point"}
}