{
  "type": "Feature",
  "properties": {
    "iso:country":"US",
    "sg:address":"3500 E Lincoln Dr",
    "sg:city":"Phoenix",
    "sg:classifiers":[
        {
            "category":"Insurance",
            "subcategory":"Insurance Agent",
            "type":"Services"
        }
    ],
    "sg:phone":"+1 602 955 2114",
    "sg:postcode":"85018",
    "sg:province":"AZ",
    "wof:name":"Securance Marketing Corp",
    "wof:placetype":"venue"
},
  "geometry": {"coordinates":[-112.01319,33.531821],"type":"Point"}
}