{
  "type": "Feature",
  "properties": {
    "iso:country":"US",
    "sg:address":"5050 E Lone Mountain Rd",
    "sg:city":"Cave Creek",
    "sg:classifiers":[
        {
            "category":"Professional",
            "subcategory":"Management & Consulting",
            "type":"Services"
        }
    ],
    "sg:phone":"+1 480 585 7858",
    "sg:postcode":"85331",
    "sg:province":"AZ",
    "sg:tags":[
        "consultant",
        "business"
    ],
    "wof:name":"M D Review",
    "wof:placetype":"venue"
},
  "geometry": {"coordinates":[-111.970921,33.770092],"type":"Point"}
}