{
  "type": "Feature",
  "properties": {
    "iso:country":"US",
    "sg:address":"560 W Brown Rd",
    "sg:city":"Mesa",
    "sg:classifiers":[
        {
            "category":"Professional",
            "subcategory":"Art Services",
            "type":"Services"
        },
        {
            "category":"Building & Trades",
            "subcategory":"Construction",
            "type":"Services"
        }
    ],
    "sg:phone":"+1 866 350 8385",
    "sg:postcode":"85201",
    "sg:province":"AZ",
    "sg:tags":[
        "faux",
        "finishing",
        "painting",
        "contractor"
    ],
    "wof:name":"Dumac",
    "wof:placetype":"venue"
},
  "geometry": {"coordinates":[-111.842911,33.435139],"type":"Point"}
}