{
  "type": "Feature",
  "properties": {
    "iso:country":"US",
    "sg:address":"3911 E Thomas Rd Ste 103",
    "sg:city":"Phoenix",
    "sg:classifiers":[
        {
            "category":"Banks & Credit Unions",
            "subcategory":"Financial Services",
            "type":"Services"
        }
    ],
    "sg:phone":"+1 602 275 3188",
    "sg:postcode":"85018",
    "sg:province":"AZ",
    "sg:tags":[
        "cashing",
        "check"
    ],
    "wof:name":"Loan Mart 3420",
    "wof:placetype":"venue"
},
  "geometry": {"coordinates":[-111.997444,33.480438],"type":"Point"}
}