{
  "type": "Feature",
  "properties": {
    "iso:country":"US",
    "sg:address":"34900 Westridge Ln",
    "sg:city":"Black Cyn City",
    "sg:classifiers":[
        {
            "category":"Real Estate",
            "subcategory":"Real Estate Agent",
            "type":"Services"
        }
    ],
    "sg:phone":"+1 623 551 2778",
    "sg:postcode":"85324",
    "sg:province":"AZ",
    "sg:tags":[
        "agency",
        "rental"
    ],
    "sg:website":"www.photoboothscrapbooks.com",
    "wof:name":"Photobooth Scrapbooks",
    "wof:placetype":"venue"
},
  "geometry": {"coordinates":[-112.151563,34.061493],"type":"Point"}
}