{
  "type": "Feature",
  "properties": {
    "iso:country":"US",
    "sg:address":"4163 E Glade Cir",
    "sg:city":"Mesa",
    "sg:classifiers":[
        {
            "category":"Arts & Performance",
            "subcategory":"Theater",
            "type":"Entertainment"
        }
    ],
    "sg:phone":"+1 480 755 4200",
    "sg:postcode":"85206",
    "sg:province":"AZ",
    "sg:tags":[
        "live",
        "music"
    ],
    "wof:name":"Bristol's Interactive Entrtnmt",
    "wof:placetype":"venue"
},
  "geometry": {"coordinates":[-111.740733,33.391593],"type":"Point"}
}