{
  "type": "Feature",
  "properties": {
    "iso:country":"US",
    "sg:address":"4215 N 38th Dr",
    "sg:city":"Phoenix",
    "sg:classifiers":[
        {
            "category":"Manufacturing",
            "subcategory":"Electronics",
            "type":"Manufacturing & Wholesale Goods"
        }
    ],
    "sg:phone":"+1 602 269 7801",
    "sg:postcode":"85019",
    "sg:province":"AZ",
    "sg:tags":[
        "warehouse",
        "location"
    ],
    "wof:name":"Lucent Technologies Inc",
    "wof:placetype":"venue"
},
  "geometry": {"coordinates":[-112.14067900000001,33.497685],"type":"Point"}
}