{
  "type": "Feature",
  "properties": {
    "iso:country":"US",
    "sg:address":"480 N Arizona Ave",
    "sg:city":"Chandler",
    "sg:classifiers":[
        {
            "category":"Bars & Pubs",
            "type":"Food & Drink"
        }
    ],
    "sg:phone":"+1 480 899 2268",
    "sg:postcode":"85225",
    "sg:province":"AZ",
    "sg:tags":[
        "nightlife"
    ],
    "sg:website":"www.480bar.com/",
    "wof:name":"Max & Ted's 480",
    "wof:placetype":"venue"
},
  "geometry": {"coordinates":[-111.84188399999999,33.311114],"type":"Point"}
}