{
  "type": "Feature",
  "properties": {
    "addr:full":"3025 E Neal Ave Kingman AZ 86409",
    "addr:housenumber":"3025",
    "addr:postcode":"86409",
    "addr:street":"E Neal Ave",
    "iso:country":"US",
    "sg:address":"3025 E Neal Ave",
    "sg:city":"Kingman",
    "sg:classifiers":[
        {
            "category":"Real Estate",
            "subcategory":"Real Estate Services",
            "type":"Services"
        },
        {
            "category":"Real Estate",
            "subcategory":"Real Estate Agent",
            "type":"Services"
        }
    ],
    "sg:phone":"+1 928 757 5900",
    "sg:postcode":"86409",
    "sg:province":"AZ",
    "sg:tags":[
        "management"
    ],
    "wof:name":"Fred F Wood",
    "wof:placetype":"venue"
},
  "geometry": {"coordinates":[-113.99054,35.255306],"type":"Point"}
}