{
  "type": "Feature",
  "properties": {
    "addr:full":"10172 E Queensgate Way Tucson AZ 85748",
    "addr:housenumber":"10172",
    "addr:postcode":"85748",
    "addr:street":"E Queensgate Way",
    "iso:country":"US",
    "sg:address":"10172 E Queensgate Way",
    "sg:city":"Tucson",
    "sg:classifiers":[
        {
            "category":"Shopping",
            "type":"Retail Goods"
        }
    ],
    "sg:phone":"+1 520 298 8142",
    "sg:postcode":"85748",
    "sg:province":"AZ",
    "sg:tags":[
        "wedding",
        "supply"
    ],
    "wof:name":"Kahuna Productions",
    "wof:placetype":"venue"
},
  "geometry": {"coordinates":[-110.775389,32.220217],"type":"Point"}
}