{
  "type": "Feature",
  "properties": {
    "iso:country":"US",
    "sg:address":"1616 N Litchfield Road Suite 140",
    "sg:city":"Goodyear",
    "sg:classifiers":[
        {
            "category":"Health Services",
            "subcategory":"Doctor",
            "type":"Services"
        }
    ],
    "sg:phone":"+1 623 536 2000",
    "sg:postcode":"85338",
    "sg:province":"AZ",
    "wof:name":"Tmc Advanced Imaging",
    "wof:placetype":"venue"
},
  "geometry": {"coordinates":[-112.358238,33.464635],"type":"Point"}
}