{
  "type": "Feature",
  "properties": {
    "addr:full":"1798 S 4th Ave Yuma AZ 85364",
    "addr:housenumber":"1798",
    "addr:postcode":"85364",
    "addr:street":"S 4Th Ave",
    "iso:country":"US",
    "sg:address":"1798 S 4th Ave",
    "sg:city":"Yuma",
    "sg:classifiers":[
        {
            "category":"Food & Beverages",
            "subcategory":"Groceries & Convenience Stores",
            "type":"Retail Goods"
        }
    ],
    "sg:phone":"+1 928 783 8534",
    "sg:postcode":"85364",
    "sg:province":"AZ",
    "sg:tags":[
        "station",
        "gasoline"
    ],
    "wof:name":"Circle K Store",
    "wof:placetype":"venue"
},
  "geometry": {"coordinates":[-114.624645,32.69533],"type":"Point"}
}