{
  "type": "Feature",
  "properties": {
    "iso:country":"US",
    "sg:address":"3030 E 4th St",
    "sg:city":"Tucson",
    "sg:classifiers":[
        {
            "category":"Manufacturing",
            "subcategory":"Chemicals & Compounds",
            "type":"Manufacturing & Wholesale Goods"
        }
    ],
    "sg:phone":"+1 520 795 8276",
    "sg:postcode":"85716",
    "sg:province":"AZ",
    "sg:tags":[
        "preparation",
        "pharmaceutical",
        "mfg"
    ],
    "wof:name":"J H Bloch Laboratory Inc",
    "wof:placetype":"venue"
},
  "geometry": {"coordinates":[-110.927131,32.230467],"type":"Point"}
}