{
  "type": "Feature",
  "properties": {
    "iso:country":"US",
    "sg:address":"8981 E 3rd St",
    "sg:city":"Tucson",
    "sg:classifiers":[
        {
            "category":"Shopping",
            "type":"Retail Goods"
        }
    ],
    "sg:phone":"+1 520 750 1022",
    "sg:postcode":"85710",
    "sg:province":"AZ",
    "sg:tags":[
        "wedding",
        "supply"
    ],
    "sg:website":"www.wedj4tucson.com",
    "wof:name":"Excalibur Entertainment Etc",
    "wof:placetype":"venue"
},
  "geometry": {"coordinates":[-110.802188,32.23104],"type":"Point"}
}