{
  "type": "Feature",
  "properties": {
    "iso:country":"US",
    "sg:address":"254 N Fraser Dr E",
    "sg:city":"Mesa",
    "sg:classifiers":[
        {
            "category":"Real Estate",
            "subcategory":"Real Estate Agent",
            "type":"Services"
        }
    ],
    "sg:phone":"+1 480 833 3540",
    "sg:postcode":"85203",
    "sg:province":"AZ",
    "sg:tags":[
        "management"
    ],
    "wof:name":"JLA Property Management LLC",
    "wof:placetype":"venue"
},
  "geometry": {"coordinates":[-111.810865,33.420384],"type":"Point"}
}