{
  "type": "Feature",
  "properties": {
    "iso:country":"US",
    "sg:address":"3693 S Old Spanish Trl",
    "sg:city":"Tucson",
    "sg:classifiers":[
        {
            "category":"Shopping",
            "subcategory":"Books",
            "type":"Retail Goods"
        }
    ],
    "sg:phone":"+1 520 885 6944",
    "sg:postcode":"85730",
    "sg:province":"AZ",
    "sg:tags":[
        "store"
    ],
    "wof:name":"Saguaro National Monu - Rmd",
    "wof:placetype":"venue"
},
  "geometry": {"coordinates":[-110.737938,32.179303],"type":"Point"}
}