{
  "type": "Feature",
  "properties": {
    "addr:full":"6534 E Stella Rd Tucson AZ 85730",
    "addr:housenumber":"6534",
    "addr:postcode":"85730",
    "addr:street":"E Stella Rd",
    "iso:country":"US",
    "sg:address":"6534 E Stella Rd",
    "sg:city":"Tucson",
    "sg:classifiers":[
        {
            "category":"Real Estate",
            "subcategory":"Real Estate Operator",
            "type":"Services"
        }
    ],
    "sg:phone":"+1 520 790 0881",
    "sg:postcode":"85730",
    "sg:province":"AZ",
    "sg:tags":[
        "building",
        "apartment"
    ],
    "wof:name":"Sherwood Garden Apartments",
    "wof:placetype":"venue"
},
  "geometry": {"coordinates":[-110.850086,32.184621],"type":"Point"}
}