{
  "type": "Feature",
  "properties": {
    "iso:country":"US",
    "sg:address":"2818 N Country Club Rd",
    "sg:city":"Tucson",
    "sg:classifiers":[
        {
            "category":"Personal",
            "subcategory":"Beauty Salon",
            "type":"Services"
        }
    ],
    "sg:phone":"+1 520 982 7645",
    "sg:postcode":"85716",
    "sg:province":"AZ",
    "wof:name":"Hollywood Smiles Desert Faces",
    "wof:placetype":"venue"
},
  "geometry": {"coordinates":[-110.92669600000001,32.259078],"type":"Point"}
}