{
  "type": "Feature",
  "properties": {
    "iso:country":"US",
    "sg:address":"3216 N 3rd St",
    "sg:city":"Phoenix",
    "sg:classifiers":[
        {
            "category":"Banks & Credit Unions",
            "subcategory":"Investment Brokerage",
            "type":"Services"
        }
    ],
    "sg:phone":"+1 602 222 5757",
    "sg:postcode":"85012",
    "sg:province":"AZ",
    "sg:tags":[
        "consultant",
        "planning",
        "financial"
    ],
    "wof:name":"Rosen Investment Advisors",
    "wof:placetype":"venue"
},
  "geometry": {"coordinates":[-112.06949899999999,33.484564],"type":"Point"}
}