{
  "type": "Feature",
  "properties": {
    "addr:full":"951 W Watkins St Phoenix AZ 85007",
    "addr:housenumber":"951",
    "addr:postcode":"85007",
    "addr:street":"W Watkins St",
    "iso:country":"US",
    "sg:address":"951 W Watkins St",
    "sg:city":"Phoenix",
    "sg:classifiers":[
        {
            "category":"Personal",
            "type":"Services"
        },
        {
            "category":"Professional",
            "subcategory":"Business Services",
            "type":"Services"
        },
        {
            "category":"Shopping",
            "subcategory":"Discount & Variety Stores",
            "type":"Retail Goods"
        }
    ],
    "sg:phone":"+1 866 319 1878",
    "sg:postcode":"85007",
    "sg:province":"AZ",
    "sg:tags":[
        "liquidation",
        "liquidator",
        "auction",
        "estates-sales",
        "appraisal"
    ],
    "sg:website":"http://www.auctionandappraise.com",
    "wof:name":"Auction Systems Auctioneers & Appraisers",
    "wof:placetype":"venue"
},
  "geometry": {"coordinates":[-112.084323,33.425804],"type":"Point"}
}