{
  "type": "Feature",
  "properties": {
    "iso:country":"US",
    "sg:address":"1151 E Hermans Rd",
    "sg:city":"Tucson",
    "sg:classifiers":[
        {
            "category":"Manufacturing",
            "subcategory":"Metals",
            "type":"Manufacturing & Wholesale Goods"
        }
    ],
    "sg:phone":"+1 520 663 6941",
    "sg:postcode":"85706",
    "sg:province":"AZ",
    "sg:tags":[
        "mfg",
        "forging",
        "nonferrous"
    ],
    "wof:name":"Raythoan Missiles Systems",
    "wof:placetype":"venue"
},
  "geometry": {"coordinates":[-110.948078,32.105106],"type":"Point"}
}