{
  "type": "Feature",
  "properties": {
    "iso:country":"US",
    "sg:address":"625 S Sahuaro St",
    "sg:city":"Ajo",
    "sg:classifiers":[
        {
            "category":"Utilities",
            "subcategory":"Water",
            "type":"Services"
        }
    ],
    "sg:phone":"+1 520 387 6668",
    "sg:postcode":"85321",
    "sg:province":"AZ",
    "sg:tags":[
        "supply"
    ],
    "wof:name":"Arizona Water Company",
    "wof:placetype":"venue"
},
  "geometry": {"coordinates":[-112.871525,32.365511],"type":"Point"}
}