{
  "type": "Feature",
  "properties": {
    "addr:full":"2255 W Desert Cove Ave Phoenix AZ 85029",
    "addr:housenumber":"2255",
    "addr:postcode":"85029",
    "addr:street":"W Desert Cove Ave",
    "iso:country":"US",
    "sg:address":"2255 W Desert Cove Ave",
    "sg:city":"Phoenix",
    "sg:classifiers":[
        {
            "category":"Building & Trades",
            "subcategory":"Construction",
            "type":"Services"
        }
    ],
    "sg:phone":"+1 602 944 4285",
    "sg:postcode":"85029",
    "sg:province":"AZ",
    "sg:tags":[
        "resurfacing",
        "laying",
        "refinishing",
        "floor"
    ],
    "wof:name":"El Sol Floor & Supply",
    "wof:placetype":"venue"
},
  "geometry": {"coordinates":[-112.106602,33.585693],"type":"Point"}
}