{
  "type": "Feature",
  "properties": {
    "iso:country":"US",
    "sg:address":"1164 Fiesta Mall",
    "sg:city":"Mesa",
    "sg:classifiers":[
        {
            "category":"Shopping",
            "subcategory":"Clothing, Apparel, & Fashions",
            "type":"Retail Goods"
        }
    ],
    "sg:phone":"+1 480 827 1486",
    "sg:postcode":"85202",
    "sg:province":"AZ",
    "wof:name":"Guess 22",
    "wof:placetype":"venue"
},
  "geometry": {"coordinates":[-111.858854,33.392281],"type":"Point"}
}