{
  "type": "Feature",
  "properties": {
    "iso:country":"US",
    "sg:address":"2336 E Mulberry Dr",
    "sg:city":"Phoenix",
    "sg:classifiers":[
        {
            "category":"Professional",
            "subcategory":"Lawyer & Legal Services",
            "type":"Services"
        }
    ],
    "sg:phone":"+1 602 390 1983",
    "sg:postcode":"85016",
    "sg:province":"AZ",
    "sg:tags":[
        "living",
        "estate",
        "planning",
        "trust",
        "probate"
    ],
    "wof:name":"Vnsa Volunteer Nonprofit Service Association",
    "wof:placetype":"venue"
},
  "geometry": {"coordinates":[-112.03157,33.486634],"type":"Point"}
}