{
  "type": "Feature",
  "properties": {
    "iso:country":"US",
    "sg:address":"2020 S Mill Ave Ste 108",
    "sg:city":"Tempe",
    "sg:classifiers":[
        {
            "category":"Health Services",
            "subcategory":"Doctor",
            "type":"Services"
        },
        {
            "category":"Health Services",
            "subcategory":"Hospital",
            "type":"Services"
        }
    ],
    "sg:phone":"+1 480 446 0767",
    "sg:postcode":"85282",
    "sg:province":"AZ",
    "sg:tags":[
        "nursing",
        "consultant",
        "medical",
        "practice",
        "home"
    ],
    "sg:website":"http://www.adultcareconsultants.com",
    "wof:name":"Adult Care Consultants",
    "wof:placetype":"venue"
},
  "geometry": {"coordinates":[-111.939796,33.407082],"type":"Point"}
}