{
  "type": "Feature",
  "properties": {
    "iso:country":"US",
    "sg:address":"16649 S 29th St",
    "sg:city":"Phoenix",
    "sg:classifiers":[
        {
            "category":"Professional",
            "type":"Services"
        }
    ],
    "sg:phone":"+1 480 759 9312",
    "sg:postcode":"85048",
    "sg:province":"AZ",
    "wof:name":"Coombs Dent & Velora",
    "wof:placetype":"venue"
},
  "geometry": {"coordinates":[-112.021226,33.293196],"type":"Point"}
}