{
  "type": "Feature",
  "properties": {
    "iso:country":"US",
    "sg:address":"4858 E Baker St",
    "sg:city":"Tucson",
    "sg:classifiers":[
        {
            "category":"Shopping",
            "subcategory":"Hobbies, Toys, & Games",
            "type":"Retail Goods"
        }
    ],
    "sg:phone":"+1 520 323 1446",
    "sg:postcode":"85711",
    "sg:province":"AZ",
    "sg:tags":[
        "equipment",
        "ceramic",
        "supply"
    ],
    "wof:name":"Tucson Ceramic Inc",
    "wof:placetype":"venue"
},
  "geometry": {"coordinates":[-110.891429,32.229736],"type":"Point"}
}