{
  "type": "Feature",
  "properties": {
    "iso:country":"US",
    "sg:address":"2947 N Scottsdale Rd",
    "sg:city":"Scottsdale",
    "sg:classifiers":[
        {
            "category":"Personal",
            "subcategory":"Tattoo Parlor",
            "type":"Services"
        }
    ],
    "sg:phone":"+1 480 970 5042",
    "sg:postcode":"85251",
    "sg:province":"AZ",
    "sg:tags":[
        "tattooing"
    ],
    "wof:name":"Divinity Tattoo",
    "wof:placetype":"venue"
},
  "geometry": {"coordinates":[-111.92608300000001,33.483336],"type":"Point"}
}