{
  "type": "Feature",
  "properties": {
    "iso:country":"US",
    "sg:address":"27050 N 103rd St",
    "sg:city":"Scottsdale",
    "sg:classifiers":[
        {
            "category":"Building & Trades",
            "subcategory":"Construction",
            "type":"Services"
        }
    ],
    "sg:phone":"+1 480 513 8184",
    "sg:postcode":"85262",
    "sg:province":"AZ",
    "sg:tags":[
        "home",
        "builder"
    ],
    "wof:name":"R Net Custom Homes",
    "wof:placetype":"venue"
},
  "geometry": {"coordinates":[-111.856902,33.73107],"type":"Point"}
}