{
  "type": "Feature",
  "properties": {
    "iso:country":"US",
    "sg:address":"8630 E Via de Ventura",
    "sg:city":"Scottsdale",
    "sg:classifiers":[
        {
            "category":"Professional",
            "type":"Services"
        }
    ],
    "sg:phone":"+1 480 556 0777",
    "sg:postcode":"85258",
    "sg:province":"AZ",
    "wof:name":"Ed P Recruiting Svc",
    "wof:placetype":"venue"
},
  "geometry": {"coordinates":[-111.895585,33.553923],"type":"Point"}
}