{
  "type": "Feature",
  "properties": {
    "addr:full":"455 S Mesa Dr Mesa AZ 85210",
    "addr:housenumber":"455",
    "addr:postcode":"85210",
    "addr:street":"S Mesa Dr",
    "iso:country":"US",
    "sg:address":"455 S Mesa Dr",
    "sg:city":"Mesa",
    "sg:classifiers":[
        {
            "category":"Professional",
            "type":"Services"
        }
    ],
    "sg:phone":"+1 480 668 7014",
    "sg:postcode":"85210",
    "sg:province":"AZ",
    "sg:tags":[
        "establishment"
    ],
    "wof:name":"Hafley & Stage",
    "wof:placetype":"venue"
},
  "geometry": {"coordinates":[-111.822885,33.406528],"type":"Point"}
}