{
  "type": "Feature",
  "properties": {
    "addr:full":"1514 W Kiowa Ave Mesa AZ 85202",
    "addr:housenumber":"1514",
    "addr:postcode":"85202",
    "addr:street":"W Kiowa Ave",
    "iso:country":"US",
    "sg:address":"1514 W Kiowa Ave",
    "sg:city":"Mesa",
    "sg:classifiers":[
        {
            "category":"Professional",
            "type":"Services"
        },
        {
            "category":"Banks & Credit Unions",
            "subcategory":"Bank",
            "type":"Services"
        }
    ],
    "sg:phone":"+1 480 838 6500",
    "sg:postcode":"85202",
    "sg:province":"AZ",
    "sg:tags":[
        "establishment",
        "mortgage"
    ],
    "wof:name":"Jimenez & Assoc Internati",
    "wof:placetype":"venue"
},
  "geometry": {"coordinates":[-111.867846,33.375406],"type":"Point"}
}