{
  "type": "Feature",
  "properties": {
    "iso:country":"US",
    "sg:address":"205 E 22nd St",
    "sg:city":"Tucson",
    "sg:classifiers":[
        {
            "category":"Retail",
            "subcategory":"Laundry & Dry Cleaning",
            "type":"Services"
        }
    ],
    "sg:phone":"+1 520 622 8174",
    "sg:postcode":"85713",
    "sg:province":"AZ",
    "sg:tags":[
        "cleaner",
        "commercial"
    ],
    "wof:name":"Garcia Cleaners & Shirt Ldry",
    "wof:placetype":"venue"
},
  "geometry": {"coordinates":[-110.96672700000001,32.206841],"type":"Point"}
}