{
  "type": "Feature",
  "properties": {
    "iso:country":"US",
    "sg:address":"1720 E Warner Road",
    "sg:city":"Tempe",
    "sg:classifiers":[
        {
            "category":"Personal",
            "type":"Services"
        }
    ],
    "sg:phone":"+1 480 820 7522",
    "sg:postcode":"85284",
    "sg:province":"AZ",
    "sg:tags":[
        "sewing",
        "alteration"
    ],
    "sg:website":"www.lees-tailoring.com",
    "wof:name":"Lee's Tailoring",
    "wof:placetype":"venue"
},
  "geometry": {"coordinates":[-111.914573,33.334572],"type":"Point"}
}