{
  "type": "Feature",
  "properties": {
    "iso:country":"US",
    "sg:address":"9190 E Kayenta Dr",
    "sg:city":"Tucson",
    "sg:classifiers":[
        {
            "category":"Shopping",
            "subcategory":"Bicycles & Sporting Goods",
            "type":"Retail Goods"
        }
    ],
    "sg:phone":"+1 520 907 3833",
    "sg:postcode":"85749",
    "sg:province":"AZ",
    "wof:name":"Barrett Tctical Systems Tucson",
    "wof:placetype":"venue"
},
  "geometry": {"coordinates":[-110.793523,32.283667],"type":"Point"}
}