{
  "type": "Feature",
  "properties": {
    "iso:country":"US",
    "sg:address":"6838 N 25th Dr",
    "sg:city":"Phoenix",
    "sg:classifiers":[
        {
            "category":"Health Services",
            "subcategory":"Clinic",
            "type":"Services"
        }
    ],
    "sg:phone":"+1 602 841 1483",
    "sg:postcode":"85017",
    "sg:province":"AZ",
    "sg:tags":[
        "welfare"
    ],
    "wof:name":"Cabital Medical Trans",
    "wof:placetype":"venue"
},
  "geometry": {"coordinates":[-112.113631,33.5375],"type":"Point"}
}