{
  "type": "Feature",
  "properties": {
    "iso:country":"US",
    "sg:address":"4419 W Glendale Ave",
    "sg:city":"Glendale",
    "sg:classifiers":[
        {
            "category":"Health Services",
            "subcategory":"Doctor",
            "type":"Services"
        }
    ],
    "sg:phone":"+1 623 939 6549",
    "sg:postcode":"85301",
    "sg:province":"AZ",
    "sg:tags":[
        "dentist"
    ],
    "wof:name":"Glendale Dental Group",
    "wof:placetype":"venue"
},
  "geometry": {"coordinates":[-112.153551,33.538372],"type":"Point"}
}