{
  "type": "Feature",
  "properties": {
    "iso:country":"US",
    "sg:address":"5973 W Morelos St",
    "sg:city":"Chandler",
    "sg:classifiers":[
        {
            "category":"Manufacturing",
            "subcategory":"Printing",
            "type":"Manufacturing & Wholesale Goods"
        }
    ],
    "sg:phone":"+1 480 753 7137",
    "sg:postcode":"85226",
    "sg:province":"AZ",
    "sg:tags":[
        "periodical"
    ],
    "wof:name":"Smart Printing & Publishing",
    "wof:placetype":"venue"
},
  "geometry": {"coordinates":[-111.944827,33.295094],"type":"Point"}
}