{
  "type": "Feature",
  "properties": {
    "addr:full":"1056 S Riata St Gilbert AZ 85296",
    "addr:housenumber":"1056",
    "addr:postcode":"85296",
    "addr:street":"S Riata St",
    "iso:country":"US",
    "sg:address":"1056 S Riata St",
    "sg:city":"Gilbert",
    "sg:classifiers":[
        {
            "category":"Real Estate",
            "subcategory":"Real Estate Agent",
            "type":"Services"
        }
    ],
    "sg:phone":"+1 480 628 1207",
    "sg:postcode":"85296",
    "sg:province":"AZ",
    "wof:name":"Matthew Moellering Realty",
    "wof:placetype":"venue"
},
  "geometry": {"coordinates":[-111.777687,33.33067],"type":"Point"}
}