{
  "type": "Feature",
  "properties": {
    "addr:full":"2514 W Pershing Ave Phoenix AZ 85029",
    "addr:housenumber":"2514",
    "addr:postcode":"85029",
    "addr:street":"W Pershing Ave",
    "iso:country":"US",
    "sg:address":"2514 W Pershing Ave",
    "sg:city":"Phoenix",
    "sg:classifiers":[
        {
            "category":"Professional",
            "type":"Services"
        }
    ],
    "sg:phone":"+1 602 866 9437",
    "sg:postcode":"85029",
    "sg:province":"AZ",
    "wof:name":"Cherokee N16412 LLC",
    "wof:placetype":"venue"
},
  "geometry": {"coordinates":[-112.113266,33.606894],"type":"Point"}
}