{
  "type": "Feature",
  "properties": {
    "iso:country":"US",
    "sg:address":"1352 S Gilbert Rd",
    "sg:city":"Mesa",
    "sg:classifiers":[
        {
            "category":"Restaurant",
            "type":"Food & Drink"
        }
    ],
    "sg:menulink":"http://www.allmenus.com/az/phoenix/160996-carls-jr/menu/",
    "sg:phone":"+1 480 892 4793",
    "sg:postcode":"85204",
    "sg:province":"AZ",
    "sg:tags":[
        "burger",
        "american"
    ],
    "wof:name":"Carl's Jr.",
    "wof:placetype":"venue"
},
  "geometry": {"coordinates":[-111.788374,33.390696],"type":"Point"}
}