{
  "type": "Feature",
  "properties": {
    "addr:full":"802 E Union Hills Dr Phoenix AZ 85024",
    "addr:housenumber":"802",
    "addr:postcode":"85024",
    "addr:street":"E Union Hills Dr",
    "iso:country":"US",
    "sg:address":"802 E Union Hills Dr",
    "sg:city":"Phoenix",
    "sg:classifiers":[
        {
            "category":"Shopping",
            "subcategory":"Pharmacy",
            "type":"Retail Goods"
        }
    ],
    "sg:phone":"+1 623 582 8981",
    "sg:postcode":"85024",
    "sg:province":"AZ",
    "wof:name":"Osco Drug",
    "wof:placetype":"venue"
},
  "geometry": {"coordinates":[-112.06417999999999,33.654929],"type":"Point"}
}