{
  "type": "Feature",
  "properties": {
    "addr:full":"6601 W Thomas Rd Phoenix AZ 85033",
    "addr:housenumber":"6601",
    "addr:postcode":"85033",
    "addr:street":"W Thomas Rd",
    "iso:country":"US",
    "sg:address":"6601 W Thomas Rd",
    "sg:city":"Phoenix",
    "sg:classifiers":[
        {
            "category":"Wholesale",
            "subcategory":"Vending Machines",
            "type":"Manufacturing & Wholesale Goods"
        }
    ],
    "sg:phone":"+1 602 942 7765",
    "sg:postcode":"85033",
    "sg:province":"AZ",
    "sg:tags":[
        "operator",
        "financial"
    ],
    "wof:name":"Atlas Computer",
    "wof:placetype":"venue"
},
  "geometry": {"coordinates":[-112.202434,33.480278],"type":"Point"}
}