{
  "type": "Feature",
  "properties": {
    "addr:full":"3859 N Oracle Rd Tucson AZ 85705",
    "addr:housenumber":"3859",
    "addr:postcode":"85705",
    "addr:street":"N Oracle Rd",
    "iso:country":"US",
    "sg:address":"3859 N Oracle Rd",
    "sg:city":"Tucson",
    "sg:classifiers":[
        {
            "category":"Building & Trades",
            "subcategory":"Cleaning & Sanitation",
            "type":"Services"
        },
        {
            "category":"Retail",
            "subcategory":"Laundry & Dry Cleaning",
            "type":"Services"
        },
        {
            "category":"Home & Garden",
            "subcategory":"Carpets & Floor Coverings",
            "type":"Retail Goods"
        }
    ],
    "sg:phone":"+1 520 292 2930",
    "sg:postcode":"85705",
    "sg:province":"AZ",
    "sg:tags":[
        "cleaner",
        "upholstery",
        "fabric",
        "rug",
        "protection",
        "furniture"
    ],
    "wof:name":"Regal Carpet",
    "wof:placetype":"venue"
},
  "geometry": {"coordinates":[-110.97825400000001,32.276787],"type":"Point"}
}