{
  "type": "Feature",
  "properties": {
    "iso:country":"US",
    "sg:address":"22211 N Los Caballos Dr",
    "sg:city":"Scottsdale",
    "sg:classifiers":[
        {
            "category":"Manufacturing",
            "subcategory":"Printing",
            "type":"Manufacturing & Wholesale Goods"
        }
    ],
    "sg:phone":"+1 480 948 4233",
    "sg:postcode":"85255",
    "sg:province":"AZ",
    "sg:tags":[
        "publishing"
    ],
    "wof:name":"Camelback Design Group Inc",
    "wof:placetype":"venue"
},
  "geometry": {"coordinates":[-111.89139400000001,33.685747],"type":"Point"}
}