{
  "type": "Feature",
  "properties": {
    "addr:full":"2693 N Industrial Way Prescott Valley AZ 86314",
    "addr:housenumber":"2693",
    "addr:postcode":"86314",
    "addr:street":"N Industrial Way",
    "iso:country":"US",
    "sg:address":"2693 N Industrial Way",
    "sg:city":"Prescott Valley",
    "sg:classifiers":[
        {
            "category":"Organizations",
            "subcategory":"Religious Organization",
            "type":"Services"
        }
    ],
    "sg:phone":"+1 928 759 9972",
    "sg:postcode":"86314",
    "sg:province":"AZ",
    "sg:tags":[
        "church"
    ],
    "wof:name":"Cornerstone & G-12 Ministries",
    "wof:placetype":"venue"
},
  "geometry": {"coordinates":[-112.298402,34.582129],"type":"Point"}
}