{
  "type": "Feature",
  "properties": {
    "iso:country":"US",
    "sg:address":"5669 E Speedway Blvd",
    "sg:city":"Tucson",
    "sg:classifiers":[
        {
            "category":"Government",
            "subcategory":"Department Of Motor Vehicles",
            "type":"Public Place"
        }
    ],
    "sg:phone":"+1 520 750 7572",
    "sg:postcode":"85712",
    "sg:province":"AZ",
    "sg:tags":[
        "license",
        "registration"
    ],
    "wof:name":"Drivers License Center",
    "wof:placetype":"venue"
},
  "geometry": {"coordinates":[-110.871654,32.236252],"type":"Point"}
}