{
  "type": "Feature",
  "properties": {
    "iso:country":"US",
    "sg:address":"7047 E Greenway Pkwy",
    "sg:city":"Scottsdale",
    "sg:classifiers":[
        {
            "category":"Banks & Credit Unions",
            "subcategory":"Financial Services",
            "type":"Services"
        }
    ],
    "sg:phone":"+1 602 224 9333",
    "sg:postcode":"85254",
    "sg:province":"AZ",
    "sg:tags":[
        "franchising"
    ],
    "sg:website":"www.franchiseresource.com",
    "wof:name":"Franchise Resource",
    "wof:placetype":"venue"
},
  "geometry": {"coordinates":[-111.932451,33.622748],"type":"Point"}
}