{
  "type": "Feature",
  "properties": {
    "iso:country":"US",
    "sg:address":"8560 E 22nd St",
    "sg:city":"Tucson",
    "sg:classifiers":[
        {
            "category":"Wholesale",
            "subcategory":"Machinery & Supplies",
            "type":"Manufacturing & Wholesale Goods"
        }
    ],
    "sg:phone":"+1 520 290 6797",
    "sg:postcode":"85710",
    "sg:province":"AZ",
    "sg:tags":[
        "tool",
        "broker",
        "contractor"
    ],
    "wof:name":"Edco",
    "wof:placetype":"venue"
},
  "geometry": {"coordinates":[-110.810001,32.206318],"type":"Point"}
}