{
  "type": "Feature",
  "properties": {
    "addr:full":"2191 E 32nd St Yuma AZ 85365",
    "addr:housenumber":"2191",
    "addr:postcode":"85365",
    "addr:street":"E 32Nd St",
    "iso:country":"US",
    "sg:address":"2191 E 32nd St",
    "sg:city":"Yuma",
    "sg:classifiers":[
        {
            "category":"Airport",
            "type":"Transportation"
        }
    ],
    "sg:phone":"+1 928 726 5882",
    "sg:postcode":"85365",
    "sg:province":"AZ",
    "sg:tags":[
        "international"
    ],
    "wof:name":"Yuma International Airport",
    "wof:placetype":"venue"
},
  "geometry": {"coordinates":[-114.598697,32.669491],"type":"Point"}
}