{
  "type": "Feature",
  "properties": {
    "addr:full":"1570 Plantation Rd Mohave Valley AZ 86446",
    "addr:housenumber":"1570",
    "addr:postcode":"86446",
    "addr:street":"Plantation Rd",
    "iso:country":"US",
    "sg:address":"1570 Plantation Rd",
    "sg:city":"Mohave Valley",
    "sg:classifiers":[
        {
            "category":"Retail",
            "subcategory":"Auto Repair",
            "type":"Services"
        }
    ],
    "sg:phone":"+1 928 768 4959",
    "sg:postcode":"86446",
    "sg:province":"AZ",
    "sg:tags":[
        "transmission"
    ],
    "wof:name":"Kenny's Transmission",
    "wof:placetype":"venue"
},
  "geometry": {"coordinates":[-114.594835,34.851502],"type":"Point"}
}