{
  "type": "Feature",
  "properties": {
    "iso:country":"US",
    "sg:address":"15230 N 75th St",
    "sg:city":"Scottsdale",
    "sg:classifiers":[
        {
            "category":"Real Estate",
            "subcategory":"Real Estate Agent",
            "type":"Services"
        }
    ],
    "sg:phone":"+1 480 736 1111",
    "sg:postcode":"85260",
    "sg:province":"AZ",
    "wof:name":"Denali Investment Group",
    "wof:placetype":"venue"
},
  "geometry": {"coordinates":[-111.915963,33.62406],"type":"Point"}
}