{
  "type": "Feature",
  "properties": {
    "iso:country":"US",
    "sg:address":"8781 E Broadway Blvd",
    "sg:city":"Tucson",
    "sg:classifiers":[
        {
            "category":"Personal",
            "subcategory":"Beauty Salon",
            "type":"Services"
        }
    ],
    "sg:phone":"+1 520 885 2554",
    "sg:postcode":"85710",
    "sg:province":"AZ",
    "wof:name":"Camino Cuts",
    "wof:placetype":"venue"
},
  "geometry": {"coordinates":[-110.804975,32.220968],"type":"Point"}
}