{
  "type": "Feature",
  "properties": {
    "iso:country":"US",
    "sg:address":"4397 W Bethany Home Rd",
    "sg:city":"Glendale",
    "sg:classifiers":[
        {
            "category":"Real Estate",
            "subcategory":"Real Estate Services",
            "type":"Services"
        }
    ],
    "sg:phone":"+1 602 750 8935",
    "sg:postcode":"85301",
    "sg:province":"AZ",
    "sg:tags":[
        "inspection"
    ],
    "wof:name":"Ecos Home Inspection Services",
    "wof:placetype":"venue"
},
  "geometry": {"coordinates":[-112.153774,33.523929],"type":"Point"}
}