{
  "type": "Feature",
  "properties": {
    "addr:full":"1440 N Saddle St Gilbert AZ 85233",
    "addr:housenumber":"1440",
    "addr:postcode":"85233",
    "addr:street":"N Saddle St",
    "iso:country":"US",
    "sg:address":"1440 N Saddle St",
    "sg:city":"Gilbert",
    "sg:classifiers":[
        {
            "category":"Building & Trades",
            "subcategory":"Construction",
            "type":"Services"
        }
    ],
    "sg:phone":"+1 480 633 6619",
    "sg:postcode":"85233",
    "sg:province":"AZ",
    "sg:tags":[
        "house"
    ],
    "wof:name":"Coastal Construction Frmng LLC",
    "wof:placetype":"venue"
},
  "geometry": {"coordinates":[-111.806485,33.375214],"type":"Point"}
}