{
  "type": "Feature",
  "properties": {
    "iso:country":"US",
    "sg:address":"27901 W Hazen Rd",
    "sg:city":"Buckeye",
    "sg:classifiers":[
        {
            "category":"Building & Trades",
            "subcategory":"Construction",
            "type":"Services"
        }
    ],
    "sg:phone":"+1 602 882 9698",
    "sg:postcode":"85326",
    "sg:province":"AZ",
    "sg:tags":[
        "repair",
        "fence"
    ],
    "sg:website":"http://www.brucehunterfamilylaw.com",
    "wof:name":"Michael Hunter",
    "wof:placetype":"venue"
},
  "geometry": {"coordinates":[-112.651207,33.355572],"type":"Point"}
}