{
  "type": "Feature",
  "properties": {
    "iso:country":"US",
    "sg:address":"12222 N Paradise Village Pkwy S 42",
    "sg:city":"Phoenix",
    "sg:classifiers":[
        {
            "category":"Personal",
            "subcategory":"Psychics & Astrologers",
            "type":"Services"
        }
    ],
    "sg:phone":"+1 602 494 7985",
    "sg:postcode":"85032",
    "sg:province":"AZ",
    "sg:website":"http://www.eclipseastrologyaz.com",
    "wof:name":"Eclipse Astrology",
    "wof:placetype":"venue"
},
  "geometry": {"coordinates":[-111.987334,33.598363],"type":"Point"}
}