{
  "type": "Feature",
  "properties": {
    "iso:country":"US",
    "sg:address":"595 N Dobson Rd Ste 48",
    "sg:city":"Chandler",
    "sg:classifiers":[
        {
            "category":"Health Services",
            "subcategory":"Doctor",
            "type":"Services"
        }
    ],
    "sg:phone":"+1 480 786 8109",
    "sg:postcode":"85224",
    "sg:province":"AZ",
    "sg:tags":[
        "physician",
        "pediatrics-otorhinolaryngology",
        "surgeons",
        "otorhinolaryngology",
        "nose",
        "throat",
        "surgeon",
        "ear"
    ],
    "wof:name":"Maricopa Ear Nose & Throat",
    "wof:placetype":"venue"
},
  "geometry": {"coordinates":[-111.876385,33.312275],"type":"Point"}
}