{
  "type": "Feature",
  "properties": {
    "addr:full":"6933 W Bloomfield Rd Peoria AZ 85381",
    "addr:housenumber":"6933",
    "addr:postcode":"85381",
    "addr:street":"W Bloomfield Rd",
    "iso:country":"US",
    "sg:address":"6933 W Bloomfield Rd",
    "sg:city":"Peoria",
    "sg:classifiers":[
        {
            "category":"Professional",
            "subcategory":"Business Services",
            "type":"Services"
        }
    ],
    "sg:phone":"+1 623 334 3077",
    "sg:postcode":"85381",
    "sg:province":"AZ",
    "sg:tags":[
        "embroidery"
    ],
    "wof:name":"Xtreme Fx",
    "wof:placetype":"venue"
},
  "geometry": {"coordinates":[-112.206988,33.598533],"type":"Point"}
}