{
  "type": "Feature",
  "properties": {
    "addr:full":"15014 N 20th St Phoenix AZ 85022",
    "addr:housenumber":"15014",
    "addr:postcode":"85022",
    "addr:street":"N 20Th St",
    "iso:country":"US",
    "sg:address":"15014 N 20th St",
    "sg:city":"Phoenix",
    "sg:classifiers":[
        {
            "category":"Building & Trades",
            "subcategory":"Landscaping Services",
            "type":"Services"
        },
        {
            "category":"Social Services",
            "subcategory":"Job Training",
            "type":"Services"
        },
        {
            "category":"Manufacturing",
            "subcategory":"Buildings",
            "type":"Manufacturing & Wholesale Goods"
        }
    ],
    "sg:phone":"+1 602 410 9102",
    "sg:postcode":"85022",
    "sg:province":"AZ",
    "sg:tags":[
        "nursing",
        "homes-skilled",
        "facility",
        "builder",
        "homes-institutional",
        "home",
        "aged"
    ],
    "wof:name":"Lookout Mountain Assisted Living Home",
    "wof:placetype":"venue"
},
  "geometry": {"coordinates":[-112.03939800000001,33.622878],"type":"Point"}
}