{
  "type": "Feature",
  "properties": {
    "iso:country":"US",
    "sg:address":"3950 State Hwy 77",
    "sg:city":"Oracle",
    "sg:classifiers":[
        {
            "category":"Autos & Motor Vehicles",
            "subcategory":"Automobile Sales",
            "type":"Retail Goods"
        }
    ],
    "sg:phone":"+1 520 896 3673",
    "sg:postcode":"85623",
    "sg:province":"AZ",
    "sg:tags":[
        "car",
        "rental",
        "passenger"
    ],
    "wof:name":"Oracel Mercury",
    "wof:placetype":"venue"
},
  "geometry": {"coordinates":[-110.815788,32.617787],"type":"Point"}
}