{
  "type": "Feature",
  "properties": {
    "addr:full":"5550 S Arcadia Ave Tucson AZ 85706",
    "addr:housenumber":"5550",
    "addr:postcode":"85706",
    "addr:street":"S Arcadia Ave",
    "iso:country":"US",
    "sg:address":"5550 S Arcadia Ave",
    "sg:city":"Tucson",
    "sg:classifiers":[
        {
            "category":"Real Estate",
            "subcategory":"Real Estate Agent",
            "type":"Services"
        }
    ],
    "sg:phone":"+1 520 574 9216",
    "sg:postcode":"85706",
    "sg:province":"AZ",
    "wof:name":"Kms Enterprises",
    "wof:placetype":"venue"
},
  "geometry": {"coordinates":[-110.88799299999999,32.149762],"type":"Point"}
}