{
  "type": "Feature",
  "properties": {
    "iso:country":"US",
    "sg:address":"5550 S Arcadia Ave",
    "sg:city":"Tucson",
    "sg:classifiers":[
        {
            "category":"Real Estate",
            "subcategory":"Real Estate Agent",
            "type":"Services"
        }
    ],
    "sg:phone":"+1 520 574 9216",
    "sg:postcode":"85706",
    "sg:province":"AZ",
    "wof:name":"Kms Enterprises",
    "wof:placetype":"venue"
},
  "geometry": {"coordinates":[-110.887993,32.149762],"type":"Point"}
}