{
  "type": "Feature",
  "properties": {
    "iso:country":"US",
    "sg:address":"17015 N Scottsdale Rd",
    "sg:city":"Scottsdale",
    "sg:classifiers":[
        {
            "category":"Insurance",
            "subcategory":"Hazard Insurance",
            "type":"Services"
        },
        {
            "category":"Banks & Credit Unions",
            "subcategory":"Investment Brokerage",
            "type":"Services"
        },
        {
            "category":"Insurance",
            "subcategory":"Life Insurance",
            "type":"Services"
        },
        {
            "category":"Banks & Credit Unions",
            "subcategory":"Financial Services",
            "type":"Services"
        }
    ],
    "sg:phone":"+1 708 226 1111",
    "sg:postcode":"85255",
    "sg:province":"AZ",
    "sg:website":"http://phoenix.citysearch.com/profile/external/1687110/scottsdale_az/country_financial_rocky_dellamano.html?publisher=yellowpages&reference_id=1&placement=ypwebsitemip",
    "wof:name":"COUNTRY Financial - Rocky Dellamano",
    "wof:placetype":"venue"
},
  "geometry": {"coordinates":[-111.925392,33.639856],"type":"Point"}
}