{
  "type": "Feature",
  "properties": {
    "addr:full":"6885 Rio Verde Dr Kingman AZ 86401",
    "addr:housenumber":"6885",
    "addr:postcode":"86401",
    "addr:street":"Rio Verde Dr",
    "iso:country":"US",
    "sg:address":"6885 Rio Verde Dr",
    "sg:city":"Kingman",
    "sg:classifiers":[
        {
            "category":"Shopping",
            "subcategory":"Computers & Home Electronics",
            "type":"Retail Goods"
        }
    ],
    "sg:phone":"+1 928 692 1544",
    "sg:postcode":"86401",
    "sg:province":"AZ",
    "sg:tags":[
        "software"
    ],
    "wof:name":"4-1-1 Systems Inc",
    "wof:placetype":"venue"
},
  "geometry": {"coordinates":[-113.859943,35.390921],"type":"Point"}
}