{
  "type": "Feature",
  "properties": {
    "iso:country":"US",
    "sg:address":"1229 E Curry Rd",
    "sg:city":"Tempe",
    "sg:classifiers":[
        {
            "category":"Retail",
            "subcategory":"Auto Repair",
            "type":"Services"
        }
    ],
    "sg:phone":"+1 480 968 8851",
    "sg:postcode":"85281",
    "sg:province":"AZ",
    "sg:tags":[
        "wrecker"
    ],
    "wof:name":"Mesa Tempe Chandler Towing",
    "wof:placetype":"venue"
},
  "geometry": {"coordinates":[-111.918098,33.440307],"type":"Point"}
}