{
  "type": "Feature",
  "properties": {
    "iso:country":"US",
    "sg:address":"10305 W Papago Fwy",
    "sg:city":"Avondale",
    "sg:classifiers":[
        {
            "category":"Autos & Motor Vehicles",
            "subcategory":"Automobile Sales",
            "type":"Retail Goods"
        },
        {
            "category":"Retail",
            "subcategory":"Auto Repair",
            "type":"Services"
        }
    ],
    "sg:phone":"+1 623 907 5000",
    "sg:postcode":"85323",
    "sg:province":"AZ",
    "sg:tags":[
        "used",
        "leasing",
        "car",
        "truck",
        "new"
    ],
    "sg:website":"www.avondalenissan.com",
    "wof:name":"Avondale Nissan",
    "wof:placetype":"venue"
},
  "geometry": {"coordinates":[-112.280881,33.460708],"type":"Point"}
}