{
  "type": "Feature",
  "properties": {
    "addr:full":"3855 E Sioux Dr Flagstaff AZ 86001",
    "addr:housenumber":"3855",
    "addr:postcode":"86001",
    "addr:street":"E Sioux Dr",
    "iso:country":"US",
    "sg:address":"3855 E Sioux Dr",
    "sg:city":"Flagstaff",
    "sg:classifiers":[
        {
            "category":"Professional",
            "type":"Services"
        },
        {
            "category":"Organizations",
            "subcategory":"Professional Association",
            "type":"Services"
        }
    ],
    "sg:phone":"+1 928 226 8713",
    "sg:postcode":"86001",
    "sg:province":"AZ",
    "wof:name":"Student Conservation Assn",
    "wof:placetype":"venue"
},
  "geometry": {"coordinates":[-111.658441,35.15948],"type":"Point"}
}