{
  "type": "Feature",
  "properties": {
    "addr:full":"215 N Humphreys St Flagstaff AZ 86001",
    "addr:housenumber":"215",
    "addr:postcode":"86001",
    "addr:street":"N Humphreys St",
    "iso:country":"US",
    "sg:address":"215 N Humphreys St",
    "sg:city":"Flagstaff",
    "sg:classifiers":[
        {
            "category":"Shopping",
            "type":"Retail Goods"
        }
    ],
    "sg:phone":"+1 928 214 7303",
    "sg:postcode":"86001",
    "sg:province":"AZ",
    "sg:tags":[
        "merchandise"
    ],
    "wof:name":"The Body Shop P T",
    "wof:placetype":"venue"
},
  "geometry": {"coordinates":[-111.650256,35.200588],"type":"Point"}
}