{
  "type": "Feature",
  "properties": {
    "addr:full":"11235 E Beryl Ave Scottsdale AZ 85259",
    "addr:housenumber":"11235",
    "addr:postcode":"85259",
    "addr:street":"E Beryl Ave",
    "iso:country":"US",
    "sg:address":"11235 E Beryl Ave",
    "sg:city":"Scottsdale",
    "sg:classifiers":[
        {
            "category":"Professional",
            "subcategory":"Computer Services",
            "type":"Services"
        }
    ],
    "sg:phone":"+1 480 767 6936",
    "sg:postcode":"85259",
    "sg:province":"AZ",
    "sg:tags":[
        "graphic"
    ],
    "wof:name":"Samuel Petulla",
    "wof:placetype":"venue"
},
  "geometry": {"coordinates":[-111.83768499999999,33.579382],"type":"Point"}
}