{
  "type": "Feature",
  "properties": {
    "addr:full":"8527 W Whitton Ave Phoenix AZ 85037",
    "addr:housenumber":"8527",
    "addr:postcode":"85037",
    "addr:street":"W Whitton Ave",
    "iso:country":"US",
    "sg:address":"8527 W Whitton Ave",
    "sg:city":"Phoenix",
    "sg:classifiers":[
        {
            "category":"Personal",
            "subcategory":"Beauty Salon",
            "type":"Services"
        }
    ],
    "sg:phone":"+1 623 694 5087",
    "sg:postcode":"85037",
    "sg:province":"AZ",
    "wof:name":"Sparks Of Color By Donna Rae",
    "wof:placetype":"venue"
},
  "geometry": {"coordinates":[-112.24263500000001,33.488369],"type":"Point"}
}