{
  "type": "Feature",
  "properties": {
    "iso:country":"US",
    "sg:address":"1598 E Susan St",
    "sg:city":"Chino Valley",
    "sg:classifiers":[
        {
            "category":"Health Services",
            "subcategory":"Doctor",
            "type":"Services"
        }
    ],
    "sg:phone":"+1 928 636 6872",
    "sg:postcode":"86323",
    "sg:province":"AZ",
    "sg:tags":[
        "dentist"
    ],
    "wof:name":"Vr Mckerlie DDS",
    "wof:placetype":"venue"
},
  "geometry": {"coordinates":[-112.432658,34.750775],"type":"Point"}
}