{
  "type": "Feature",
  "properties": {
    "addr:full":"5032 S Ash Ave Tempe AZ 85282",
    "addr:housenumber":"5032",
    "addr:postcode":"85282",
    "addr:street":"S Ash Ave",
    "iso:country":"US",
    "sg:address":"5032 S Ash Ave",
    "sg:city":"Tempe",
    "sg:classifiers":[
        {
            "category":"Insurance",
            "subcategory":"Insurance Agent",
            "type":"Services"
        }
    ],
    "sg:phone":"+1 480 491 4194",
    "sg:postcode":"85282",
    "sg:province":"AZ",
    "wof:name":"Primerica Financial Svc",
    "wof:placetype":"venue"
},
  "geometry": {"coordinates":[-111.941603,33.379523],"type":"Point"}
}