{
  "type": "Feature",
  "properties": {
    "iso:country":"US",
    "sg:address":"8466 W Peoria Ave",
    "sg:city":"Peoria",
    "sg:classifiers":[
        {
            "category":"Shopping",
            "subcategory":"Tobacco",
            "type":"Retail Goods"
        }
    ],
    "sg:phone":"+1 623 334 0690",
    "sg:postcode":"85345",
    "sg:province":"AZ",
    "sg:tags":[
        "cigarette",
        "cigar",
        "dealer"
    ],
    "wof:name":"Cigarettes Savings Ctr",
    "wof:placetype":"venue"
},
  "geometry": {"coordinates":[-112.240557,33.581735],"type":"Point"}
}