{
  "type": "Feature",
  "properties": {
    "iso:country":"US",
    "sg:address":"460 N Gilbert Road",
    "sg:city":"Gilbert",
    "sg:classifiers":[
        {
            "category":"Building & Trades",
            "subcategory":"Locksmith",
            "type":"Services"
        }
    ],
    "sg:phone":"+1 480 649 3134",
    "sg:postcode":"85234",
    "sg:province":"AZ",
    "sg:tags":[
        "key"
    ],
    "wof:name":"0 & 0 1 24 Hour A-1 Emergency Locksmith",
    "wof:placetype":"venue"
},
  "geometry": {"coordinates":[-111.789595,33.358707],"type":"Point"}
}