{
  "type": "Feature",
  "properties": {
    "iso:country":"US",
    "sg:address":"2001 S Beverly Ave",
    "sg:city":"Tucson",
    "sg:classifiers":[
        {
            "category":"Professional",
            "subcategory":"Computer Services",
            "type":"Services"
        }
    ],
    "sg:phone":"+1 520 235 2450",
    "sg:postcode":"85711",
    "sg:province":"AZ",
    "sg:tags":[
        "technical",
        "assistance",
        "support"
    ],
    "wof:name":"Martins Networking And Cmpt",
    "wof:placetype":"venue"
},
  "geometry": {"coordinates":[-110.879204,32.19791],"type":"Point"}
}