{
  "type": "Feature",
  "properties": {
    "addr:full":"15620 E Chandler Heights Rd Chandler AZ 85298",
    "addr:housenumber":"15620",
    "addr:postcode":"85298",
    "addr:street":"E Chandler Heights Rd",
    "iso:country":"US",
    "sg:address":"15620 E Chandler Heights Rd",
    "sg:city":"Chandler",
    "sg:classifiers":[
        {
            "category":"Building & Trades",
            "subcategory":"Landscaping Services",
            "type":"Services"
        }
    ],
    "sg:phone":"+1 480 926 3325",
    "sg:postcode":"85298",
    "sg:province":"AZ",
    "sg:tags":[
        "landscape",
        "contractor"
    ],
    "wof:name":"Sonoran Design Concepts",
    "wof:placetype":"venue"
},
  "geometry": {"coordinates":[-111.907214,33.305484],"type":"Point"}
}