{
  "type": "Feature",
  "properties": {
    "iso:country":"US",
    "sg:address":"7720 N 16th St",
    "sg:city":"Phoenix",
    "sg:classifiers":[
        {
            "category":"Real Estate",
            "subcategory":"Developer",
            "type":"Services"
        }
    ],
    "sg:phone":"+1 623 516 4838",
    "sg:postcode":"85020",
    "sg:province":"AZ",
    "wof:name":"Tramonto Development LLC",
    "wof:placetype":"venue"
},
  "geometry": {"coordinates":[-112.048087,33.54978],"type":"Point"}
}