{
  "type": "Feature",
  "properties": {
    "iso:country":"US",
    "sg:address":"348 S Main St",
    "sg:city":"Camp Verde",
    "sg:classifiers":[
        {
            "category":"Personal",
            "subcategory":"Beauty Salon",
            "type":"Services"
        }
    ],
    "sg:phone":"+1 928 567 6788",
    "sg:postcode":"86322",
    "sg:province":"AZ",
    "wof:name":"Shear Impression's",
    "wof:placetype":"venue"
},
  "geometry": {"coordinates":[-111.85477299999999,34.56446],"type":"Point"}
}