{
  "type": "Feature",
  "properties": {
    "iso:country":"US",
    "sg:address":"2525 E Arizona Biltmore Cir",
    "sg:city":"Phoenix",
    "sg:classifiers":[
        {
            "category":"Organizations",
            "subcategory":"Community Association",
            "type":"Services"
        }
    ],
    "sg:phone":"+1 602 230 0600",
    "sg:postcode":"85016",
    "sg:province":"AZ",
    "wof:name":"Law Enforcement Association Of Pinal County",
    "wof:placetype":"venue"
},
  "geometry": {"coordinates":[-112.024356,33.525219],"type":"Point"}
}