{
  "type": "Feature",
  "properties": {
    "iso:country":"US",
    "sg:address":"7340 E Sweetwater Ave",
    "sg:city":"Scottsdale",
    "sg:classifiers":[
        {
            "category":"Health Services",
            "subcategory":"Nursing And Care Facility",
            "type":"Services"
        },
        {
            "category":"Social Services",
            "subcategory":"Retirement Home",
            "type":"Services"
        }
    ],
    "sg:phone":"+1 480 607 9219",
    "sg:postcode":"85260",
    "sg:province":"AZ",
    "sg:tags":[
        "living",
        "assisted",
        "convalescent",
        "residential"
    ],
    "wof:name":"Las Fuentes Assisted Living",
    "wof:placetype":"venue"
},
  "geometry": {"coordinates":[-111.922476,33.603975],"type":"Point"}
}