{
  "type": "Feature",
  "properties": {
    "addr:full":"2863 E Mallory St Mesa AZ 85213",
    "addr:housenumber":"2863",
    "addr:postcode":"85213",
    "addr:street":"E Mallory St",
    "iso:country":"US",
    "sg:address":"2863 E Mallory St",
    "sg:city":"Mesa",
    "sg:classifiers":[
        {
            "category":"Building & Trades",
            "subcategory":"Plumbing",
            "type":"Services"
        }
    ],
    "sg:phone":"+1 602 451 7567",
    "sg:postcode":"85213",
    "sg:province":"AZ",
    "sg:tags":[
        "contractor"
    ],
    "wof:name":"BTS A/C & Htg LLC",
    "wof:placetype":"venue"
},
  "geometry": {"coordinates":[-111.769082,33.460579],"type":"Point"}
}