{
  "type": "Feature",
  "properties": {
    "iso:country":"US",
    "sg:address":"21054 N 90th Ln",
    "sg:city":"Peoria",
    "sg:classifiers":[
        {
            "category":"Professional",
            "type":"Services"
        }
    ],
    "sg:phone":"+1 623 825 1188",
    "sg:postcode":"85382",
    "sg:province":"AZ",
    "wof:name":"Cobblestone USA",
    "wof:placetype":"venue"
},
  "geometry": {"coordinates":[-112.254443,33.676084],"type":"Point"}
}