{
  "type": "Feature",
  "properties": {
    "iso:country":"US",
    "sg:address":"1333 W Iron Springs Rd",
    "sg:city":"Prescott",
    "sg:classifiers":[
        {
            "category":"Restaurant",
            "type":"Food & Drink"
        }
    ],
    "sg:menulink":"http://www.allmenus.com/az/prescott/77739-papa-murphys/menu/",
    "sg:phone":"+1 928 708 9100",
    "sg:postcode":"86305",
    "sg:province":"AZ",
    "sg:tags":[
        "american",
        "pizza"
    ],
    "wof:name":"Papa Murphy's",
    "wof:placetype":"venue"
},
  "geometry": {"coordinates":[-112.488849,34.5628],"type":"Point"}
}