{
  "type": "Feature",
  "properties": {
    "addr:full":"505 S Milton Rd Flagstaff AZ 86001",
    "addr:housenumber":"505",
    "addr:postcode":"86001",
    "addr:street":"S Milton Rd",
    "iso:country":"US",
    "sg:address":"505 S Milton Rd",
    "sg:city":"Flagstaff",
    "sg:classifiers":[
        {
            "category":"Restaurant",
            "type":"Food & Drink"
        }
    ],
    "sg:menulink":"http://www.allmenus.com/az/coconino/180180-jack-in-the-box/menu/",
    "sg:phone":"+1 928 774 1723",
    "sg:postcode":"86001",
    "sg:province":"AZ",
    "sg:tags":[
        "burger",
        "american"
    ],
    "wof:name":"Jack in the Box",
    "wof:placetype":"venue"
},
  "geometry": {"coordinates":[-111.656953,35.193926],"type":"Point"}
}