{
  "type": "Feature",
  "properties": {
    "iso:country":"US",
    "sg:address":"5185 E Hickory Dr",
    "sg:city":"Flagstaff",
    "sg:classifiers":[
        {
            "category":"Building & Trades",
            "subcategory":"Construction",
            "type":"Services"
        }
    ],
    "sg:phone":"+1 928 527 1386",
    "sg:postcode":"86004",
    "sg:province":"AZ",
    "sg:tags":[
        "general",
        "contractor"
    ],
    "wof:name":"Tom Ramsey Construction",
    "wof:placetype":"venue"
},
  "geometry": {"coordinates":[-111.588196,35.190721],"type":"Point"}
}