{
  "type": "Feature",
  "properties": {
    "iso:country":"US",
    "sg:address":"1 N 4th Ave",
    "sg:city":"Tucson",
    "sg:classifiers":[
        {
            "category":"Restaurant",
            "type":"Food & Drink"
        }
    ],
    "sg:phone":"+1 520 903 0305",
    "sg:postcode":"85705",
    "sg:province":"AZ",
    "sg:website":"www.casbahteahouse.com",
    "wof:name":"Casbah Cafe & Bakery",
    "wof:placetype":"venue"
},
  "geometry": {"coordinates":[-110.965881,32.222809],"type":"Point"}
}