{
  "type": "Feature",
  "properties": {
    "addr:full":"2601 W Dunlap Ave Ste 1 Phoenix AZ 85021",
    "addr:housenumber":"2601",
    "addr:postcode":"85021",
    "addr:street":"W Dunlap Ave Ste 1",
    "iso:country":"US",
    "sg:address":"2601 W Dunlap Ave Ste 1",
    "sg:city":"Phoenix",
    "sg:classifiers":[
        {
            "category":"Fast Food",
            "type":"Food & Drink"
        },
        {
            "category":"Restaurant",
            "type":"Food & Drink"
        },
        {
            "category":"Food & Beverages",
            "subcategory":"Groceries & Convenience Stores",
            "type":"Retail Goods"
        }
    ],
    "sg:phone":"+1 602 870 6989",
    "sg:postcode":"85021",
    "sg:province":"AZ",
    "sg:tags":[
        "shop",
        "sandwich",
        "take"
    ],
    "sg:website":"http://www.blimpie.com",
    "wof:name":"BLIMPIE Subs & Salads",
    "wof:placetype":"venue"
},
  "geometry": {"coordinates":[-112.115537,33.567551],"type":"Point"}
}