{
  "type": "Feature",
  "properties": {
    "addr:full":"3860 N el Moraga Dr Tucson AZ 85745",
    "addr:housenumber":"3860",
    "addr:postcode":"85745",
    "addr:street":"N El Moraga Dr",
    "iso:country":"US",
    "sg:address":"3860 N el Moraga Dr",
    "sg:city":"Tucson",
    "sg:classifiers":[
        {
            "category":"Home & Garden",
            "subcategory":"Home Furnishings",
            "type":"Retail Goods"
        }
    ],
    "sg:phone":"+1 520 743 0391",
    "sg:postcode":"85745",
    "sg:province":"AZ",
    "sg:tags":[
        "business"
    ],
    "wof:name":"Quilters Bee",
    "wof:placetype":"venue"
},
  "geometry": {"coordinates":[-111.045886,32.273117],"type":"Point"}
}