{
  "type": "Feature",
  "properties": {
    "addr:full":"714 White Spar Rd Prescott AZ 86303",
    "addr:housenumber":"714",
    "addr:postcode":"86303",
    "addr:street":"White Spar Rd",
    "iso:country":"US",
    "sg:address":"714 White Spar Rd",
    "sg:city":"Prescott",
    "sg:classifiers":[
        {
            "category":"Real Estate",
            "subcategory":"Real Estate Operator",
            "type":"Services"
        }
    ],
    "sg:phone":"+1 928 778 5555",
    "sg:postcode":"86303",
    "sg:province":"AZ",
    "sg:tags":[
        "mobile",
        "home",
        "community"
    ],
    "wof:name":"Thunderbird Mobile Home Park",
    "wof:placetype":"venue"
},
  "geometry": {"coordinates":[-112.477114,34.52859],"type":"Point"}
}