{
  "type": "Feature",
  "properties": {
    "iso:country":"US",
    "sg:address":"1131 N Jones Blvd",
    "sg:city":"Tucson",
    "sg:classifiers":[
        {
            "category":"Wholesale",
            "subcategory":"Apparel",
            "type":"Manufacturing & Wholesale Goods"
        }
    ],
    "sg:phone":"+1 520 327 1314",
    "sg:postcode":"85716",
    "sg:province":"AZ",
    "sg:tags":[
        "carpet",
        "fabric",
        "furniture"
    ],
    "wof:name":"Design Center",
    "wof:placetype":"venue"
},
  "geometry": {"coordinates":[-110.920424,32.23619],"type":"Point"}
}