{
  "type": "Feature",
  "properties": {
    "iso:country":"US",
    "sg:address":"206 E 3rd St",
    "sg:city":"Douglas",
    "sg:classifiers":[
        {
            "category":"Home & Garden",
            "subcategory":"Building Materials",
            "type":"Retail Goods"
        }
    ],
    "sg:phone":"+1 520 805 9915",
    "sg:postcode":"85607",
    "sg:province":"AZ",
    "wof:name":"Double H",
    "wof:placetype":"venue"
},
  "geometry": {"coordinates":[-109.558446,31.337296],"type":"Point"}
}