{
  "type": "Feature",
  "properties": {
    "iso:country":"US",
    "sg:address":"7975 N Hayden Rd",
    "sg:city":"Scottsdale",
    "sg:classifiers":[
        {
            "category":"Insurance",
            "subcategory":"Insurance Agent",
            "type":"Services"
        }
    ],
    "sg:phone":"+1 480 991 5040",
    "sg:postcode":"85250",
    "sg:province":"AZ",
    "wof:name":"Empire Insurance Co",
    "wof:placetype":"venue"
},
  "geometry": {"coordinates":[-111.898848,33.552638],"type":"Point"}
}