{
  "type": "Feature",
  "properties": {
    "addr:full":"1707 E Weber Dr Tempe AZ 85281",
    "addr:housenumber":"1707",
    "addr:postcode":"85281",
    "addr:street":"E Weber Dr",
    "iso:country":"US",
    "sg:address":"1707 E Weber Dr",
    "sg:city":"Tempe",
    "sg:classifiers":[
        {
            "category":"Manufacturing",
            "subcategory":"Signs",
            "type":"Manufacturing & Wholesale Goods"
        },
        {
            "category":"Professional",
            "subcategory":"Business Services",
            "type":"Services"
        }
    ],
    "sg:phone":"+1 480 894 8180",
    "sg:postcode":"85281",
    "sg:province":"AZ",
    "sg:tags":[
        "display",
        "painter",
        "advertising"
    ],
    "wof:name":"Fiesta Signs",
    "wof:placetype":"venue"
},
  "geometry": {"coordinates":[-111.911281,33.443947],"type":"Point"}
}