{
  "type": "Feature",
  "properties": {
    "iso:country":"US",
    "sg:address":"812 E University Dr",
    "sg:city":"Mesa",
    "sg:classifiers":[
        {
            "category":"Food & Beverages",
            "subcategory":"Groceries & Convenience Stores",
            "type":"Retail Goods"
        }
    ],
    "sg:phone":"+1 480 834 3499",
    "sg:postcode":"85203",
    "sg:province":"AZ",
    "wof:name":"CLG Food Marts",
    "wof:placetype":"venue"
},
  "geometry": {"coordinates":[-111.812071,33.422462],"type":"Point"}
}