{
  "type": "Feature",
  "properties": {
    "iso:country":"US",
    "sg:address":"4377 E Bell Rd",
    "sg:city":"Phoenix",
    "sg:classifiers":[
        {
            "category":"Home & Garden",
            "subcategory":"Hardware",
            "type":"Retail Goods"
        }
    ],
    "sg:phone":"+1 602 843 3233",
    "sg:postcode":"85032",
    "sg:province":"AZ",
    "wof:name":"Dave's Ace Hardware",
    "wof:placetype":"venue"
},
  "geometry": {"coordinates":[-111.98695499999999,33.640562],"type":"Point"}
}