{
  "type": "Feature",
  "properties": {
    "iso:country":"US",
    "sg:address":"3750 E Superior Ave",
    "sg:city":"Phoenix",
    "sg:classifiers":[
        {
            "category":"Wholesale",
            "subcategory":"Construction Materials",
            "type":"Manufacturing & Wholesale Goods"
        },
        {
            "category":"Building & Trades",
            "subcategory":"Construction",
            "type":"Services"
        }
    ],
    "sg:phone":"+1 602 453 0071",
    "sg:postcode":"85040",
    "sg:province":"AZ",
    "sg:tags":[
        "commercial",
        "design",
        "fence",
        "contractor"
    ],
    "sg:website":"www.artisticirondesignsinc.com",
    "wof:name":"Artistic Iron Designs Inc",
    "wof:placetype":"venue"
},
  "geometry": {"coordinates":[-112.002461,33.416461],"type":"Point"}
}