{
  "type": "Feature",
  "properties": {
    "iso:country":"US",
    "sg:address":"16991 N Boswell Blvd",
    "sg:city":"Sun City",
    "sg:classifiers":[
        {
            "category":"Real Estate",
            "subcategory":"Real Estate Agent",
            "type":"Services"
        }
    ],
    "sg:phone":"+1 623 974 1888",
    "sg:postcode":"85351",
    "sg:province":"AZ",
    "sg:tags":[
        "residential",
        "agency"
    ],
    "sg:website":"www.kenmeaderealty.com",
    "wof:name":"Ken Meade Realty Inc",
    "wof:placetype":"venue"
},
  "geometry": {"coordinates":[-112.277768,33.638115],"type":"Point"}
}