{
  "type": "Feature",
  "properties": {
    "addr:full":"2340 Grand Ave Phoenix AZ 85009",
    "addr:housenumber":"2340",
    "addr:postcode":"85009",
    "addr:street":"Grand Ave",
    "iso:country":"US",
    "sg:address":"2340 Grand Ave",
    "sg:city":"Phoenix",
    "sg:classifiers":[
        {
            "category":"Building & Trades",
            "subcategory":"Construction",
            "type":"Services"
        }
    ],
    "sg:phone":"+1 602 256 0190",
    "sg:postcode":"85009",
    "sg:province":"AZ",
    "sg:tags":[
        "repairing",
        "remodeling",
        "painter",
        "contractor"
    ],
    "wof:name":"Riester Brothers Contracting",
    "wof:placetype":"venue"
},
  "geometry": {"coordinates":[-112.10937800000001,33.473988],"type":"Point"}
}