{
  "type": "Feature",
  "properties": {
    "iso:country":"US",
    "sg:address":"15699 W Morning Vista Ln",
    "sg:city":"Surprise",
    "sg:classifiers":[
        {
            "category":"Manufacturing",
            "subcategory":"Metals",
            "type":"Manufacturing & Wholesale Goods"
        }
    ],
    "sg:phone":"+1 623 975 4184",
    "sg:postcode":"85387",
    "sg:province":"AZ",
    "sg:tags":[
        "metalwork",
        "sheet",
        "mfg"
    ],
    "wof:name":"D & G Enterprises",
    "wof:placetype":"venue"
},
  "geometry": {"coordinates":[-112.402919,33.749465],"type":"Point"}
}