{
  "type": "Feature",
  "properties": {
    "iso:country":"US",
    "sg:address":"932 Marina Blvd",
    "sg:city":"Bullhead City",
    "sg:classifiers":[
        {
            "category":"Restaurant",
            "type":"Food & Drink"
        }
    ],
    "sg:phone":"+1 928 763 0800",
    "sg:postcode":"86442",
    "sg:province":"AZ",
    "wof:name":"G & L Burgers",
    "wof:placetype":"venue"
},
  "geometry": {"coordinates":[-114.615712,35.100461],"type":"Point"}
}