{
  "type": "Feature",
  "properties": {
    "addr:full":"7415 E Norwood St Mesa AZ 85207",
    "addr:housenumber":"7415",
    "addr:postcode":"85207",
    "addr:street":"E Norwood St",
    "iso:country":"US",
    "sg:address":"7415 E Norwood St",
    "sg:city":"Mesa",
    "sg:classifiers":[
        {
            "category":"Shopping",
            "subcategory":"Clothing, Apparel, & Fashions",
            "type":"Retail Goods"
        }
    ],
    "sg:phone":"+1 480 854 3711",
    "sg:postcode":"85207",
    "sg:province":"AZ",
    "sg:tags":[
        "sales"
    ],
    "wof:name":"Fashion Destiny Inc",
    "wof:placetype":"venue"
},
  "geometry": {"coordinates":[-111.671429,33.463109],"type":"Point"}
}