{
  "type": "Feature",
  "properties": {
    "iso:country":"US",
    "sg:address":"6156 W Townley Ave",
    "sg:city":"Glendale",
    "sg:classifiers":[
        {
            "category":"Freight",
            "type":"Transportation"
        }
    ],
    "sg:phone":"+1 623 435 1085",
    "sg:postcode":"85302",
    "sg:province":"AZ",
    "sg:tags":[
        "mover"
    ],
    "wof:name":"Big Dog Moving",
    "wof:placetype":"venue"
},
  "geometry": {"coordinates":[-112.191037,33.565698],"type":"Point"}
}