{
  "type": "Feature",
  "properties": {
    "addr:full":"550 E Cottonwood Ln Casa Grande AZ 85222",
    "addr:housenumber":"550",
    "addr:postcode":"85222",
    "addr:street":"E Cottonwood Ln",
    "iso:country":"US",
    "sg:address":"550 E Cottonwood Ln",
    "sg:city":"Casa Grande",
    "sg:classifiers":[
        {
            "category":"Restaurant",
            "type":"Food & Drink"
        }
    ],
    "sg:menulink":"http://www.allmenus.com/az/casa-grande/198769-kfc---kentucky-fried-chicken/menu/",
    "sg:phone":"+1 520 836 7571",
    "sg:postcode":"85222",
    "sg:province":"AZ",
    "sg:tags":[
        "american",
        "chicken"
    ],
    "wof:name":"KFC - Kentucky Fried Chicken",
    "wof:placetype":"venue"
},
  "geometry": {"coordinates":[-111.74723,32.894129],"type":"Point"}
}