{
  "type": "Feature",
  "properties": {
    "iso:country":"US",
    "sg:address":"16148 N 83rd Ave",
    "sg:city":"Peoria",
    "sg:classifiers":[
        {
            "category":"Restaurant",
            "type":"Food & Drink"
        }
    ],
    "sg:menulink":"http://www.allmenus.com/az/phoenix/9996-famous-daves-legendary-pit-bbq/menu/",
    "sg:phone":"+1 623 979 3706",
    "sg:postcode":"85382",
    "sg:province":"AZ",
    "sg:tags":[
        "barbecue",
        "american"
    ],
    "wof:name":"Famous Dave's Legendary Pit BBQ",
    "wof:placetype":"venue"
},
  "geometry": {"coordinates":[-112.23514400000001,33.633522],"type":"Point"}
}