{
  "type": "Feature",
  "properties": {
    "iso:country":"US",
    "sg:address":"7361 E Diamond St",
    "sg:city":"Scottsdale",
    "sg:classifiers":[
        {
            "category":"Building & Trades",
            "subcategory":"Plumbing",
            "type":"Services"
        }
    ],
    "sg:phone":"+1 480 655 9380",
    "sg:postcode":"85257",
    "sg:province":"AZ",
    "sg:tags":[
        "contractor"
    ],
    "wof:name":"Road Runner Plumbing",
    "wof:placetype":"venue"
},
  "geometry": {"coordinates":[-111.921235,33.459153],"type":"Point"}
}