{
  "type": "Feature",
  "properties": {
    "addr:full":"112 W Mcdowell Rd Phoenix AZ 85003",
    "addr:housenumber":"112",
    "addr:postcode":"85003",
    "addr:street":"W Mcdowell Rd",
    "iso:country":"US",
    "sg:address":"112 W Mcdowell Rd",
    "sg:city":"Phoenix",
    "sg:classifiers":[
        {
            "category":"Health Services",
            "subcategory":"Optometrist",
            "type":"Services"
        },
        {
            "category":"Shopping",
            "subcategory":"Optical Goods",
            "type":"Retail Goods"
        }
    ],
    "sg:phone":"+1 602 254 3169",
    "sg:postcode":"85003",
    "sg:province":"AZ",
    "sg:tags":[
        "eyeglass"
    ],
    "wof:name":"Optical Expressions",
    "wof:placetype":"venue"
},
  "geometry": {"coordinates":[-112.076156,33.465744],"type":"Point"}
}