{
  "type": "Feature",
  "properties": {
    "addr:full":"11250 N 92nd St Scottsdale AZ 85260",
    "addr:housenumber":"11250",
    "addr:postcode":"85260",
    "addr:street":"N 92Nd St",
    "iso:country":"US",
    "sg:address":"11250 N 92nd St",
    "sg:city":"Scottsdale",
    "sg:classifiers":[
        {
            "category":"Social Services",
            "subcategory":"Job Training",
            "type":"Services"
        }
    ],
    "sg:phone":"+1 480 391 4040",
    "sg:postcode":"85260",
    "sg:province":"AZ",
    "sg:tags":[
        "nursing",
        "homes-skilled",
        "facility"
    ],
    "sg:website":"http://www.salemhaven.com",
    "wof:name":"Kindred Healthcare Operating, Inc.",
    "wof:placetype":"venue"
},
  "geometry": {"coordinates":[-111.88275899999999,33.588216],"type":"Point"}
}