{
  "type": "Feature",
  "properties": {
    "iso:country":"US",
    "sg:address":"600 W Ray Rd",
    "sg:city":"Chandler",
    "sg:classifiers":[
        {
            "category":"Professional",
            "subcategory":"Accounting & Tax Preparation",
            "type":"Services"
        }
    ],
    "sg:phone":"+1 480 812 8966",
    "sg:postcode":"85225",
    "sg:province":"AZ",
    "sg:tags":[
        "accountant"
    ],
    "wof:name":"Century Small Business Sltns",
    "wof:placetype":"venue"
},
  "geometry": {"coordinates":[-111.85257300000001,33.320639],"type":"Point"}
}