{
  "type": "Feature",
  "properties": {
    "iso:country":"US",
    "sg:address":"600 W 4th St",
    "sg:city":"Benson",
    "sg:classifiers":[
        {
            "category":"Autos & Motor Vehicles",
            "subcategory":"Automobile Sales",
            "type":"Retail Goods"
        }
    ],
    "sg:phone":"+1 520 586 3259",
    "sg:postcode":"85602",
    "sg:province":"AZ",
    "sg:tags":[
        "car",
        "dealer"
    ],
    "wof:name":"Barney's Auto",
    "wof:placetype":"venue"
},
  "geometry": {"coordinates":[-110.311716,31.970826],"type":"Point"}
}