{
  "type": "Feature",
  "properties": {
    "iso:country":"US",
    "sg:address":"1 E Camelback Rd Ste 770",
    "sg:city":"Phoenix",
    "sg:classifiers":[
        {
            "category":"Professional",
            "subcategory":"Management & Consulting",
            "type":"Services"
        },
        {
            "category":"Professional",
            "subcategory":"Employment Agencies",
            "type":"Services"
        }
    ],
    "sg:phone":"+1 602 264 7717",
    "sg:postcode":"85012",
    "sg:province":"AZ",
    "sg:tags":[
        "consultant",
        "search",
        "executive"
    ],
    "wof:name":"Cdr Group Inc",
    "wof:placetype":"venue"
},
  "geometry": {"coordinates":[-112.073761,33.509281],"type":"Point"}
}