{
  "type": "Feature",
  "properties": {
    "addr:full":"350 N Beck Ave Chandler AZ 85226",
    "addr:housenumber":"350",
    "addr:postcode":"85226",
    "addr:street":"N Beck Ave",
    "iso:country":"US",
    "sg:address":"350 N Beck Ave",
    "sg:city":"Chandler",
    "sg:classifiers":[
        {
            "category":"Manufacturing",
            "subcategory":"Building Materials",
            "type":"Manufacturing & Wholesale Goods"
        }
    ],
    "sg:phone":"+1 480 627 1130",
    "sg:postcode":"85226",
    "sg:province":"AZ",
    "sg:tags":[
        "door",
        "unit",
        "mfg"
    ],
    "wof:name":"Door Sales Inc",
    "wof:placetype":"venue"
},
  "geometry": {"coordinates":[-111.956553,33.305437],"type":"Point"}
}