{
  "type": "Feature",
  "properties": {
    "addr:full":"14255 N 76th Pl Scottsdale AZ 85260",
    "addr:housenumber":"14255",
    "addr:postcode":"85260",
    "addr:street":"N 76Th Pl",
    "iso:country":"US",
    "sg:address":"14255 N 76th Pl",
    "sg:city":"Scottsdale",
    "sg:classifiers":[
        {
            "category":"Education",
            "subcategory":"School",
            "type":"Public Place"
        }
    ],
    "sg:phone":"+1 480 998 1071",
    "sg:postcode":"85260",
    "sg:province":"AZ",
    "sg:tags":[
        "academic",
        "special"
    ],
    "wof:name":"Gateway Academy",
    "wof:placetype":"venue"
},
  "geometry": {"coordinates":[-111.916022,33.614671],"type":"Point"}
}