{
  "type": "Feature",
  "properties": {
    "iso:country":"US",
    "sg:address":"4715 N 32nd St",
    "sg:city":"Phoenix",
    "sg:classifiers":[
        {
            "category":"Banks & Credit Unions",
            "subcategory":"Bank",
            "type":"Services"
        }
    ],
    "sg:phone":"+1 602 224 9900",
    "sg:postcode":"85018",
    "sg:province":"AZ",
    "sg:tags":[
        "federal",
        "savings",
        "institution"
    ],
    "wof:name":"Washington Mutual Bank",
    "wof:placetype":"venue"
},
  "geometry": {"coordinates":[-112.012912,33.505717],"type":"Point"}
}