{
  "type": "Feature",
  "properties": {
    "addr:full":"2610 E Washington St Phoenix AZ 85034",
    "addr:housenumber":"2610",
    "addr:postcode":"85034",
    "addr:street":"E Washington St",
    "iso:country":"US",
    "sg:address":"2610 E Washington St",
    "sg:city":"Phoenix",
    "sg:classifiers":[
        {
            "category":"Manufacturing",
            "subcategory":"Tools & Machinery",
            "type":"Manufacturing & Wholesale Goods"
        }
    ],
    "sg:phone":"+1 602 273 9131",
    "sg:postcode":"85034",
    "sg:province":"AZ",
    "sg:tags":[
        "machine",
        "shop",
        "job"
    ],
    "wof:name":"Vulcan Industries Inc",
    "wof:placetype":"venue"
},
  "geometry": {"coordinates":[-112.02399699999999,33.448316],"type":"Point"}
}