{
  "type": "Feature",
  "properties": {
    "iso:country":"US",
    "sg:address":"15825 S 23rd Pl",
    "sg:city":"Phoenix",
    "sg:classifiers":[
        {
            "category":"Government",
            "subcategory":"Post Office",
            "type":"Public Place"
        }
    ],
    "sg:phone":"+1 480 621 6707",
    "sg:postcode":"85048",
    "sg:province":"AZ",
    "sg:tags":[
        "distributor",
        "manufacturer",
        "pool",
        "swimming"
    ],
    "wof:name":"B Squared Pools",
    "wof:placetype":"venue"
},
  "geometry": {"coordinates":[-112.03421899999999,33.30196],"type":"Point"}
}