{
  "type": "Feature",
  "properties": {
    "iso:country":"US",
    "sg:address":"27227 N Miller Rd",
    "sg:city":"Scottsdale",
    "sg:classifiers":[
        {
            "category":"Manufacturing",
            "subcategory":"Buildings",
            "type":"Manufacturing & Wholesale Goods"
        },
        {
            "category":"Building & Trades",
            "subcategory":"Construction",
            "type":"Services"
        }
    ],
    "sg:phone":"+1 602 750 0546",
    "sg:postcode":"85266",
    "sg:province":"AZ",
    "sg:tags":[
        "bathroom",
        "altering",
        "consultant",
        "builder",
        "contractor",
        "planning",
        "home",
        "remodeling",
        "kitchen"
    ],
    "wof:name":"Nor' easter Development",
    "wof:placetype":"venue"
},
  "geometry": {"coordinates":[-111.91719399999999,33.733499],"type":"Point"}
}