{
  "type": "Feature",
  "properties": {
    "addr:full":"2217 E Rockledge Rd Phoenix AZ 85048",
    "addr:housenumber":"2217",
    "addr:postcode":"85048",
    "addr:street":"E Rockledge Rd",
    "iso:country":"US",
    "sg:address":"2217 E Rockledge Rd",
    "sg:city":"Phoenix",
    "sg:classifiers":[
        {
            "category":"Manufacturing",
            "subcategory":"Jewelry",
            "type":"Manufacturing & Wholesale Goods"
        }
    ],
    "sg:phone":"+1 602 437 1222",
    "sg:postcode":"85048",
    "sg:province":"AZ",
    "sg:tags":[
        "costume",
        "mfg"
    ],
    "wof:name":"Squaw Wrap Indian Jewelry",
    "wof:placetype":"venue"
},
  "geometry": {"coordinates":[-112.03349300000001,33.315445],"type":"Point"}
}