{
  "type": "Feature",
  "properties": {
    "iso:country":"US",
    "sg:address":"19555 N 59th Ave",
    "sg:city":"Glendale",
    "sg:classifiers":[
        {
            "category":"Shopping",
            "subcategory":"Books",
            "type":"Retail Goods"
        }
    ],
    "sg:phone":"+1 623 362 0061",
    "sg:postcode":"85308",
    "sg:province":"AZ",
    "wof:name":"Matthews Azcom Bookstore",
    "wof:placetype":"venue"
},
  "geometry": {"coordinates":[-112.186595,33.661595],"type":"Point"}
}