{
  "type": "Feature",
  "properties": {
    "iso:country":"US",
    "sg:address":"362 W Crawford St",
    "sg:city":"Nogales",
    "sg:classifiers":[
        {
            "category":"Home & Garden",
            "subcategory":"Building Materials",
            "type":"Retail Goods"
        },
        {
            "category":"Wholesale",
            "subcategory":"Electrical",
            "type":"Manufacturing & Wholesale Goods"
        }
    ],
    "sg:phone":"+1 520 287 6817",
    "sg:postcode":"85621",
    "sg:province":"AZ",
    "sg:tags":[
        "gate",
        "operating",
        "door",
        "devices"
    ],
    "wof:name":"Vega's Doors",
    "wof:placetype":"venue"
},
  "geometry": {"coordinates":[-110.943688,31.335011],"type":"Point"}
}