{
  "type": "Feature",
  "properties": {
    "iso:country":"US",
    "sg:address":"8802 E Broadway Blvd",
    "sg:city":"Tucson",
    "sg:classifiers":[
        {
            "category":"Real Estate",
            "subcategory":"Real Estate Agent",
            "type":"Services"
        }
    ],
    "sg:phone":"+1 520 750 0422",
    "sg:postcode":"85710",
    "sg:province":"AZ",
    "wof:name":"Edmonds Real Estate Management",
    "wof:placetype":"venue"
},
  "geometry": {"coordinates":[-110.805722,32.220833],"type":"Point"}
}