{
  "type": "Feature",
  "properties": {
    "iso:country":"US",
    "sg:address":"14401 E Pecos Rd",
    "sg:city":"Gilbert",
    "sg:classifiers":[
        {
            "category":"Building & Trades",
            "subcategory":"Locksmith",
            "type":"Services"
        }
    ],
    "sg:phone":"+1 480 282 9447",
    "sg:postcode":"85295",
    "sg:province":"AZ",
    "sg:tags":[
        "key"
    ],
    "wof:name":"AA Locksmith 24 Hours",
    "wof:placetype":"venue"
},
  "geometry": {"coordinates":[-111.772796,33.291893],"type":"Point"}
}