{
  "type": "Feature",
  "properties": {
    "iso:country":"US",
    "sg:address":"1661 W Prince Rd",
    "sg:city":"Tucson",
    "sg:classifiers":[
        {
            "category":"Government",
            "subcategory":"Office",
            "type":"Public Place"
        }
    ],
    "sg:phone":"+1 520 887 2600",
    "sg:postcode":"85705",
    "sg:province":"AZ",
    "sg:tags":[
        "educational",
        "program"
    ],
    "wof:name":"Flowing Wells EXT Programs",
    "wof:placetype":"venue"
},
  "geometry": {"coordinates":[-111.00022,32.272163],"type":"Point"}
}