{
  "type": "Feature",
  "properties": {
    "addr:full":"2525 E Jefferson St Phoenix AZ 85034",
    "addr:housenumber":"2525",
    "addr:postcode":"85034",
    "addr:street":"E Jefferson St",
    "iso:country":"US",
    "sg:address":"2525 E Jefferson St",
    "sg:city":"Phoenix",
    "sg:classifiers":[
        {
            "category":"Taxi",
            "type":"Transportation"
        }
    ],
    "sg:phone":"+1 602 244 2441",
    "sg:postcode":"85034",
    "sg:province":"AZ",
    "sg:tags":[
        "taxicab"
    ],
    "wof:name":"Patient Express",
    "wof:placetype":"venue"
},
  "geometry": {"coordinates":[-112.026284,33.447151],"type":"Point"}
}