{
  "type": "Feature",
  "properties": {
    "addr:full":"6750 W Olive Ave Peoria AZ 85345",
    "addr:housenumber":"6750",
    "addr:postcode":"85345",
    "addr:street":"W Olive Ave",
    "iso:country":"US",
    "sg:address":"6750 W Olive Ave",
    "sg:city":"Peoria",
    "sg:classifiers":[
        {
            "category":"Health Services",
            "subcategory":"Health Practitioner",
            "type":"Services"
        }
    ],
    "sg:phone":"+1 623 334 9148",
    "sg:postcode":"85345",
    "sg:province":"AZ",
    "sg:tags":[
        "hypnotherapy",
        "hypnotist"
    ],
    "wof:name":"Delta Hypnosis Clinic",
    "wof:placetype":"venue"
},
  "geometry": {"coordinates":[-112.204345,33.567147],"type":"Point"}
}