{
  "type": "Feature",
  "properties": {
    "iso:country":"US",
    "sg:address":"1785 E Skyline Dr",
    "sg:city":"Tucson",
    "sg:classifiers":[
        {
            "category":"Banks & Credit Unions",
            "subcategory":"Bank",
            "type":"Services"
        }
    ],
    "sg:phone":"+1 520 498 1500",
    "sg:postcode":"85718",
    "sg:province":"AZ",
    "sg:tags":[
        "loan",
        "real estate"
    ],
    "sg:website":"www.paonemortgage.com",
    "wof:name":"Paone Mortgage Corp",
    "wof:placetype":"venue"
},
  "geometry": {"coordinates":[-110.946291,32.3349],"type":"Point"}
}