{
  "type": "Feature",
  "properties": {
    "addr:full":"18205 N 51st Pl Scottsdale AZ 85254",
    "addr:housenumber":"18205",
    "addr:postcode":"85254",
    "addr:street":"N 51St Pl",
    "iso:country":"US",
    "sg:address":"18205 N 51st Pl",
    "sg:city":"Scottsdale",
    "sg:classifiers":[
        {
            "category":"Real Estate",
            "subcategory":"Real Estate Services",
            "type":"Services"
        }
    ],
    "sg:phone":"+1 623 385 3440",
    "sg:postcode":"85254",
    "sg:province":"AZ",
    "sg:tags":[
        "company",
        "title"
    ],
    "wof:name":"Magnus Title Agency",
    "wof:placetype":"venue"
},
  "geometry": {"coordinates":[-111.970309,33.650705],"type":"Point"}
}