{
  "type": "Feature",
  "properties": {
    "iso:country":"US",
    "sg:address":"28633 W Patterson Rd",
    "sg:city":"Buckeye",
    "sg:classifiers":[
        {
            "category":"Wholesale",
            "subcategory":"Farm Supplies",
            "type":"Manufacturing & Wholesale Goods"
        }
    ],
    "sg:phone":"+1 623 386 1560",
    "sg:postcode":"85326",
    "sg:province":"AZ",
    "sg:tags":[
        "fertilizer"
    ],
    "wof:name":"Green Acres",
    "wof:placetype":"venue"
},
  "geometry": {"coordinates":[-112.669359,33.189263],"type":"Point"}
}