{
  "type": "Feature",
  "properties": {
    "iso:country":"US",
    "sg:address":"207 Bisbee Rd",
    "sg:city":"Bisbee",
    "sg:classifiers":[
        {
            "category":"Government",
            "subcategory":"Office",
            "type":"Public Place"
        }
    ],
    "sg:phone":"+1 520 432 2208",
    "sg:postcode":"85603",
    "sg:province":"AZ",
    "wof:name":"JOBS",
    "wof:placetype":"venue"
},
  "geometry": {"coordinates":[-109.887557,31.422855],"type":"Point"}
}