{
  "type": "Feature",
  "properties": {
    "iso:country":"US",
    "sg:address":"4044 S 16th St",
    "sg:city":"Phoenix",
    "sg:classifiers":[
        {
            "category":"Restaurant",
            "type":"Food & Drink"
        }
    ],
    "sg:phone":"+1 602 232 2657",
    "sg:postcode":"85040",
    "sg:province":"AZ",
    "sg:tags":[
        "eating"
    ],
    "wof:name":"Susie's Mexican Cafe & Lunch",
    "wof:placetype":"venue"
},
  "geometry": {"coordinates":[-112.047088,33.409522],"type":"Point"}
}