{
  "type": "Feature",
  "properties": {
    "addr:full":"809 W Chapel Rd Sedona AZ 86336",
    "addr:housenumber":"809",
    "addr:postcode":"86336",
    "addr:street":"W Chapel Rd",
    "iso:country":"US",
    "sg:address":"809 W Chapel Rd",
    "sg:city":"Sedona",
    "sg:classifiers":[
        {
            "category":"Real Estate",
            "subcategory":"Real Estate Services",
            "type":"Services"
        },
        {
            "category":"Real Estate",
            "subcategory":"Real Estate Agent",
            "type":"Services"
        }
    ],
    "sg:phone":"+1 928 282 2683",
    "sg:postcode":"86336",
    "sg:province":"AZ",
    "sg:tags":[
        "buyer",
        "broker"
    ],
    "wof:name":"Bob Davis Realator",
    "wof:placetype":"venue"
},
  "geometry": {"coordinates":[-111.77816799999999,34.833981],"type":"Point"}
}