{
  "type": "Feature",
  "properties": {
    "iso:country":"US",
    "sg:address":"4972 S Power Rd",
    "sg:city":"Mesa",
    "sg:classifiers":[
        {
            "category":"Restaurant",
            "type":"Food & Drink"
        }
    ],
    "sg:menulink":"http://www.allmenus.com/az/chandler/135405-jamba-juice/menu/",
    "sg:phone":"+1 480 840 3448",
    "sg:postcode":"85212",
    "sg:province":"AZ",
    "sg:tags":[
        "smoothy",
        "juice",
        "american"
    ],
    "wof:name":"Jamba Juice",
    "wof:placetype":"venue"
},
  "geometry": {"coordinates":[-111.687139,33.33518],"type":"Point"}
}