{
  "type": "Feature",
  "properties": {
    "addr:full":"48 W Baseline Rd Tempe AZ 85283",
    "addr:housenumber":"48",
    "addr:postcode":"85283",
    "addr:street":"W Baseline Rd",
    "iso:country":"US",
    "sg:address":"48 W Baseline Rd",
    "sg:city":"Tempe",
    "sg:classifiers":[
        {
            "category":"Shopping",
            "subcategory":"Discount & Variety Stores",
            "type":"Retail Goods"
        }
    ],
    "sg:phone":"+1 866 434 2226",
    "sg:postcode":"85283",
    "sg:province":"AZ",
    "wof:name":"Dollar Tree",
    "wof:placetype":"venue"
},
  "geometry": {"coordinates":[-111.940647,33.378304],"type":"Point"}
}