{
  "type": "Feature",
  "properties": {
    "iso:country":"US",
    "sg:address":"1446 US Hwy 89 Alt Scn",
    "sg:city":"Fredonia",
    "sg:classifiers":[
        {
            "category":"Building & Trades",
            "subcategory":"Construction",
            "type":"Services"
        }
    ],
    "sg:phone":"+1 928 643 7113",
    "sg:postcode":"86022",
    "sg:province":"AZ",
    "sg:tags":[
        "product",
        "asphalt"
    ],
    "wof:name":"JDM Sand & Rock Inc",
    "wof:placetype":"venue"
},
  "geometry": {"coordinates":[-112.530269,36.997254],"type":"Point"}
}