{
  "type": "Feature",
  "properties": {
    "iso:country":"US",
    "sg:address":"514 N 24th St",
    "sg:city":"Phoenix",
    "sg:classifiers":[
        {
            "category":"Autos & Motor Vehicles",
            "subcategory":"Automobile Sales",
            "type":"Retail Goods"
        }
    ],
    "sg:phone":"+1 602 231 8660",
    "sg:postcode":"85008",
    "sg:province":"AZ",
    "wof:name":"Socios Auto Sales 2",
    "wof:placetype":"venue"
},
  "geometry": {"coordinates":[-112.030242,33.455003],"type":"Point"}
}