{
  "type": "Feature",
  "properties": {
    "iso:country":"US",
    "sg:address":"9305 W Thomas Rd Ste 305",
    "sg:city":"Phoenix",
    "sg:classifiers":[
        {
            "category":"Health Services",
            "subcategory":"Clinic",
            "type":"Services"
        }
    ],
    "sg:phone":"+1 623 271 9323",
    "sg:postcode":"85037",
    "sg:province":"AZ",
    "sg:tags":[
        "medical"
    ],
    "sg:website":"www.remmedical.com/locations/wes...",
    "wof:name":"REM Medical",
    "wof:placetype":"venue"
},
  "geometry": {"coordinates":[-112.25868199999999,33.47959],"type":"Point"}
}