{
  "type": "Feature",
  "properties": {
    "addr:full":"4718 W Dobbins Rd Laveen AZ 85339",
    "addr:housenumber":"4718",
    "addr:postcode":"85339",
    "addr:street":"W Dobbins Rd",
    "iso:country":"US",
    "sg:address":"4718 W Dobbins Rd",
    "sg:city":"Laveen",
    "sg:classifiers":[
        {
            "category":"Government",
            "subcategory":"Fire Station",
            "type":"Public Place"
        },
        {
            "category":"Government",
            "subcategory":"Office",
            "type":"Public Place"
        }
    ],
    "sg:phone":"+1 602 237 2083",
    "sg:postcode":"85339",
    "sg:province":"AZ",
    "sg:tags":[
        "protection",
        "village",
        "department",
        "township",
        "government-city"
    ],
    "wof:name":"Laveen Fire District",
    "wof:placetype":"venue"
},
  "geometry": {"coordinates":[-112.161047,33.362942],"type":"Point"}
}