{
  "type": "Feature",
  "properties": {
    "iso:country":"US",
    "sg:address":"1788 Hwy 95",
    "sg:city":"Bullhead City",
    "sg:classifiers":[
        {
            "category":"Personal",
            "subcategory":"Beauty Salon",
            "type":"Services"
        }
    ],
    "sg:phone":"+1 928 763 9777",
    "sg:postcode":"86442",
    "sg:province":"AZ",
    "wof:name":"Shellys Beauty Zone",
    "wof:placetype":"venue"
},
  "geometry": {"coordinates":[-114.588626,35.120732],"type":"Point"}
}