{
  "type": "Feature",
  "properties": {
    "addr:full":"8701 W Van Buren St Tolleson AZ 85353",
    "addr:housenumber":"8701",
    "addr:postcode":"85353",
    "addr:street":"W Van Buren St",
    "iso:country":"US",
    "sg:address":"8701 W Van Buren St",
    "sg:city":"Tolleson",
    "sg:classifiers":[
        {
            "category":"Wholesale",
            "subcategory":"Computers",
            "type":"Manufacturing & Wholesale Goods"
        }
    ],
    "sg:phone":"+1 602 481 3877",
    "sg:postcode":"85353",
    "sg:province":"AZ",
    "sg:tags":[
        "equipment"
    ],
    "wof:name":"Mitchell Computers",
    "wof:placetype":"venue"
},
  "geometry": {"coordinates":[-112.24812300000001,33.450981],"type":"Point"}
}