{
  "type": "Feature",
  "properties": {
    "iso:country":"US",
    "sg:address":"2020 Contractors Rd Ste 8",
    "sg:city":"Sedona",
    "sg:classifiers":[
        {
            "category":"Home & Garden",
            "subcategory":"Furniture",
            "type":"Retail Goods"
        },
        {
            "category":"Home & Garden",
            "subcategory":"Carpets & Floor Coverings",
            "type":"Retail Goods"
        }
    ],
    "sg:phone":"+1 928 282 5848",
    "sg:postcode":"86336",
    "sg:province":"AZ",
    "sg:tags":[
        "material",
        "store"
    ],
    "wof:name":"Blackmarr's",
    "wof:placetype":"venue"
},
  "geometry": {"coordinates":[-111.795469,34.865152],"type":"Point"}
}