{
  "type": "Feature",
  "properties": {
    "iso:country":"US",
    "sg:address":"1434 S 6th Ave",
    "sg:city":"Tucson",
    "sg:classifiers":[
        {
            "category":"Real Estate",
            "subcategory":"Real Estate Services",
            "type":"Services"
        }
    ],
    "sg:phone":"+1 520 628 1144",
    "sg:postcode":"85713",
    "sg:province":"AZ",
    "sg:tags":[
        "company",
        "title"
    ],
    "wof:name":"Advantage Titles Etc",
    "wof:placetype":"venue"
},
  "geometry": {"coordinates":[-110.968541,32.204042],"type":"Point"}
}