{
  "type": "Feature",
  "properties": {
    "iso:country":"US",
    "sg:address":"350 S Freeway Rd",
    "sg:city":"Tucson",
    "sg:classifiers":[
        {
            "category":"Travel",
            "subcategory":"Hotels & Motels",
            "type":"Entertainment"
        }
    ],
    "sg:phone":"+1 520 622 6611",
    "sg:postcode":"85745",
    "sg:province":"AZ",
    "wof:name":"Riverpark Inn",
    "wof:placetype":"venue"
},
  "geometry": {"coordinates":[-110.980334,32.218592],"type":"Point"}
}