{
  "type": "Feature",
  "properties": {
    "iso:country":"US",
    "sg:address":"20401 N 29th Ave",
    "sg:city":"Phoenix",
    "sg:classifiers":[
        {
            "category":"Utilities",
            "subcategory":"Cable",
            "type":"Services"
        }
    ],
    "sg:phone":"+1 602 866 0072",
    "sg:postcode":"85027",
    "sg:province":"AZ",
    "sg:tags":[
        "tv",
        "information",
        "retrieval"
    ],
    "wof:name":"Cox Communications",
    "wof:placetype":"venue"
},
  "geometry": {"coordinates":[-112.121512,33.670459],"type":"Point"}
}