{
  "type": "Feature",
  "properties": {
    "iso:country":"US",
    "sg:address":"1 W University Blvd",
    "sg:city":"Tucson",
    "sg:classifiers":[
        {
            "category":"Real Estate",
            "subcategory":"Real Estate Operator",
            "type":"Services"
        }
    ],
    "sg:phone":"+1 520 624 6764",
    "sg:postcode":"85705",
    "sg:province":"AZ",
    "sg:tags":[
        "building",
        "apartment"
    ],
    "wof:name":"Entrada Real Apartments",
    "wof:placetype":"venue"
},
  "geometry": {"coordinates":[-110.972509,32.231602],"type":"Point"}
}