{
  "type": "Feature",
  "properties": {
    "iso:country":"US",
    "sg:address":"3218 E Jagerson Ave",
    "sg:city":"Kingman",
    "sg:classifiers":[
        {
            "category":"Health Services",
            "subcategory":"Chiropractor",
            "type":"Services"
        }
    ],
    "sg:phone":"+1 928 692 0524",
    "sg:postcode":"86409",
    "sg:province":"AZ",
    "sg:tags":[
        "chiropractic"
    ],
    "wof:name":"Richard E Stanford Dc",
    "wof:placetype":"venue"
},
  "geometry": {"coordinates":[-114.043035,35.268119],"type":"Point"}
}