{
  "type": "Feature",
  "properties": {
    "iso:country":"US",
    "sg:address":"208 S Mckemy Ave",
    "sg:city":"Chandler",
    "sg:classifiers":[
        {
            "category":"Manufacturing",
            "subcategory":"Metals",
            "type":"Manufacturing & Wholesale Goods"
        },
        {
            "category":"Building & Trades",
            "subcategory":"Construction",
            "type":"Services"
        }
    ],
    "sg:phone":"+1 480 961 1300",
    "sg:postcode":"85226",
    "sg:province":"AZ",
    "sg:tags":[
        "metal-wholesale",
        "plating",
        "stamping",
        "manufacturer"
    ],
    "sg:website":"http://www.oberg.com",
    "wof:name":"Oberg Arizona",
    "wof:placetype":"venue"
},
  "geometry": {"coordinates":[-111.95348300000001,33.301502],"type":"Point"}
}