{
  "type": "Feature",
  "properties": {
    "iso:country":"US",
    "sg:address":"3807 E Covina St",
    "sg:city":"Mesa",
    "sg:classifiers":[
        {
            "category":"Building & Trades",
            "subcategory":"Construction",
            "type":"Services"
        }
    ],
    "sg:phone":"+1 480 807 0200",
    "sg:postcode":"85205",
    "sg:province":"AZ",
    "sg:tags":[
        "excavating",
        "contractor"
    ],
    "wof:name":"Premier Concrete Works",
    "wof:placetype":"venue"
},
  "geometry": {"coordinates":[-111.748477,33.425526],"type":"Point"}
}