{
  "type": "Feature",
  "properties": {
    "iso:country":"US",
    "sg:address":"5013 S 22nd St",
    "sg:city":"Phoenix",
    "sg:classifiers":[
        {
            "category":"Professional",
            "type":"Services"
        }
    ],
    "sg:phone":"+1 602 276 5932",
    "sg:postcode":"85040",
    "sg:province":"AZ",
    "wof:name":"22 Wayz",
    "wof:placetype":"venue"
},
  "geometry": {"coordinates":[-112.034173,33.39989],"type":"Point"}
}