{
  "type": "Feature",
  "properties": {
    "iso:country":"US",
    "sg:address":"1422 E Joseph Way",
    "sg:city":"Gilbert",
    "sg:classifiers":[
        {
            "category":"Shopping",
            "subcategory":"Clothing, Apparel, & Fashions",
            "type":"Retail Goods"
        },
        {
            "category":"Wholesale",
            "subcategory":"Apparel",
            "type":"Manufacturing & Wholesale Goods"
        }
    ],
    "sg:phone":"+1 480 309 8645",
    "sg:postcode":"85295",
    "sg:province":"AZ",
    "sg:tags":[
        "sportswear-wholesale",
        "sportswear",
        "manufacturer"
    ],
    "wof:name":"Garmatelly Clothing Company",
    "wof:placetype":"venue"
},
  "geometry": {"coordinates":[-111.759578,33.298901],"type":"Point"}
}