{
  "type": "Feature",
  "properties": {
    "iso:country":"US",
    "sg:address":"604 N Beaver St",
    "sg:city":"Flagstaff",
    "sg:classifiers":[
        {
            "category":"Real Estate",
            "subcategory":"Real Estate Agent",
            "type":"Services"
        }
    ],
    "sg:phone":"+1 928 526 3737",
    "sg:postcode":"86001",
    "sg:province":"AZ",
    "wof:name":"National Flagstaff Connection",
    "wof:placetype":"venue"
},
  "geometry": {"coordinates":[-111.64715700000001,35.204288],"type":"Point"}
}