{
  "type": "Feature",
  "properties": {
    "iso:country":"US",
    "sg:address":"2650 N 32nd Ave",
    "sg:city":"Phoenix",
    "sg:classifiers":[
        {
            "category":"Real Estate",
            "subcategory":"Real Estate Agent",
            "type":"Services"
        }
    ],
    "sg:phone":"+1 602 278 6281",
    "sg:postcode":"85009",
    "sg:province":"AZ",
    "wof:name":"32nd Avenue Property",
    "wof:placetype":"venue"
},
  "geometry": {"coordinates":[-112.128427,33.479841],"type":"Point"}
}