{
  "type": "Feature",
  "properties": {
    "iso:country":"US",
    "sg:address":"14226 E Cheryl Dr",
    "sg:city":"Scottsdale",
    "sg:classifiers":[
        {
            "category":"Building & Trades",
            "subcategory":"Cleaning & Sanitation",
            "type":"Services"
        }
    ],
    "sg:phone":"+1 480 483 6842",
    "sg:postcode":"85259",
    "sg:province":"AZ",
    "sg:tags":[
        "house"
    ],
    "wof:name":"Claudia's Adult Day Care",
    "wof:placetype":"venue"
},
  "geometry": {"coordinates":[-111.773686,33.57639],"type":"Point"}
}