{
  "type": "Feature",
  "properties": {
    "addr:full":"7333 E Helm Dr Scottsdale AZ 85260",
    "addr:housenumber":"7333",
    "addr:postcode":"85260",
    "addr:street":"E Helm Dr",
    "iso:country":"US",
    "sg:address":"7333 E Helm Dr",
    "sg:city":"Scottsdale",
    "sg:classifiers":[
        {
            "category":"Shopping",
            "subcategory":"Catalog Store",
            "type":"Retail Goods"
        },
        {
            "category":"Autos & Motor Vehicles",
            "subcategory":"Auto Supplies",
            "type":"Retail Goods"
        }
    ],
    "sg:phone":"+1 480 443 5621",
    "sg:postcode":"85260",
    "sg:province":"AZ",
    "sg:tags":[
        "mail",
        "order",
        "tire",
        "automotive"
    ],
    "sg:website":"www.tires.com",
    "wof:name":"Discount Tire Co",
    "wof:placetype":"venue"
},
  "geometry": {"coordinates":[-111.922526,33.619695],"type":"Point"}
}