{
  "type": "Feature",
  "properties": {
    "iso:country":"US",
    "sg:address":"1749 E Boston Cir",
    "sg:city":"Chandler",
    "sg:classifiers":[
        {
            "category":"Building & Trades",
            "subcategory":"Pest Control",
            "type":"Services"
        }
    ],
    "sg:phone":"+1 480 857 7376",
    "sg:postcode":"85225",
    "sg:province":"AZ",
    "sg:website":"http://www.arizonapestprevention.com",
    "wof:name":"Arizona Pest Prevention Inc",
    "wof:placetype":"venue"
},
  "geometry": {"coordinates":[-111.80923799999999,33.301262],"type":"Point"}
}