{
  "type": "Feature",
  "properties": {
    "addr:full":"2224 N 78th St Scottsdale AZ 85257",
    "addr:housenumber":"2224",
    "addr:postcode":"85257",
    "addr:street":"N 78Th St",
    "iso:country":"US",
    "sg:address":"2224 N 78th St",
    "sg:city":"Scottsdale",
    "sg:classifiers":[
        {
            "category":"Professional",
            "type":"Services"
        }
    ],
    "sg:phone":"+1 480 947 7277",
    "sg:postcode":"85257",
    "sg:province":"AZ",
    "wof:name":"Time On My Hands",
    "wof:placetype":"venue"
},
  "geometry": {"coordinates":[-111.91282,33.472363],"type":"Point"}
}