{
  "type": "Feature",
  "properties": {
    "iso:country":"US",
    "sg:address":"203 1st St",
    "sg:city":"Douglas",
    "sg:classifiers":[
        {
            "category":"Banks & Credit Unions",
            "subcategory":"Bank",
            "type":"Services"
        }
    ],
    "sg:phone":"+1 520 364 4314",
    "sg:postcode":"85607",
    "sg:province":"AZ",
    "sg:tags":[
        "depository",
        "banking"
    ],
    "wof:name":"Frontera Check Cashing",
    "wof:placetype":"venue"
},
  "geometry": {"coordinates":[-109.559071,31.335116],"type":"Point"}
}