{
  "type": "Feature",
  "properties": {
    "iso:country":"US",
    "sg:address":"10488 W Steamboat St",
    "sg:city":"Somerton",
    "sg:classifiers":[
        {
            "category":"Real Estate",
            "subcategory":"Real Estate Services",
            "type":"Services"
        },
        {
            "category":"Government",
            "subcategory":"Office",
            "type":"Public Place"
        }
    ],
    "sg:phone":"+1 928 627 8863",
    "sg:postcode":"85350",
    "sg:province":"AZ",
    "sg:tags":[
        "consultant",
        "housing",
        "referral"
    ],
    "wof:name":"Cocopah Indian Housing & Development",
    "wof:placetype":"venue"
},
  "geometry": {"coordinates":[-114.77103200000001,32.615023],"type":"Point"}
}