{
  "type": "Feature",
  "properties": {
    "addr:full":"415 E Milada Dr Phoenix AZ 85042",
    "addr:housenumber":"415",
    "addr:postcode":"85042",
    "addr:street":"E Milada Dr",
    "iso:country":"US",
    "sg:address":"415 E Milada Dr",
    "sg:city":"Phoenix",
    "sg:classifiers":[
        {
            "category":"Building & Trades",
            "subcategory":"Electrical",
            "type":"Services"
        }
    ],
    "sg:phone":"+1 623 434 9369",
    "sg:postcode":"85042",
    "sg:province":"AZ",
    "sg:tags":[
        "electrician"
    ],
    "wof:name":"Electric On Demand",
    "wof:placetype":"venue"
},
  "geometry": {"coordinates":[-112.069138,33.363831],"type":"Point"}
}