{
  "type": "Feature",
  "properties": {
    "iso:country":"US",
    "sg:address":"5885 W Ver del Coyotito",
    "sg:city":"Tucson",
    "sg:classifiers":[
        {
            "category":"Professional",
            "type":"Services"
        }
    ],
    "sg:phone":"+1 520 743 0147",
    "sg:postcode":"85745",
    "sg:province":"AZ",
    "sg:tags":[
        "establishment"
    ],
    "wof:name":"BDP Intl",
    "wof:placetype":"venue"
},
  "geometry": {"coordinates":[-111.091337,32.302324],"type":"Point"}
}