{
  "type": "Feature",
  "properties": {
    "iso:country":"US",
    "sg:address":"1818 S 16th St",
    "sg:city":"Phoenix",
    "sg:classifiers":[
        {
            "category":"Organizations",
            "subcategory":"Community Association",
            "type":"Services"
        }
    ],
    "sg:phone":"+1 602 257 8987",
    "sg:postcode":"85034",
    "sg:province":"AZ",
    "wof:name":"Arizona Tenants Association",
    "wof:placetype":"venue"
},
  "geometry": {"coordinates":[-112.047798,33.430338],"type":"Point"}
}