{
  "type": "Feature",
  "properties": {
    "iso:country":"US",
    "sg:address":"3826 W Laredo Street",
    "sg:city":"Chandler",
    "sg:classifiers":[
        {
            "category":"Building & Trades",
            "subcategory":"Construction",
            "type":"Services"
        }
    ],
    "sg:phone":"+1 480 899 1070",
    "sg:postcode":"85226",
    "sg:province":"AZ",
    "sg:tags":[
        "interior",
        "design"
    ],
    "wof:name":"Hansen Wilford & Jill",
    "wof:placetype":"venue"
},
  "geometry": {"coordinates":[-111.9076,33.313271],"type":"Point"}
}