{
  "type": "Feature",
  "properties": {
    "addr:full":"8229 N 53rd St Paradise Valley AZ 85253",
    "addr:housenumber":"8229",
    "addr:postcode":"85253",
    "addr:street":"N 53Rd St",
    "iso:country":"US",
    "sg:address":"8229 N 53rd St",
    "sg:city":"Paradise Valley",
    "sg:classifiers":[
        {
            "category":"Building & Trades",
            "subcategory":"Construction",
            "type":"Services"
        }
    ],
    "sg:phone":"+1 480 695 5100",
    "sg:postcode":"85253",
    "sg:province":"AZ",
    "sg:tags":[
        "general",
        "contractor"
    ],
    "wof:name":"Cliftwood Homes Inc",
    "wof:placetype":"venue"
},
  "geometry": {"coordinates":[-111.96744700000001,33.560489],"type":"Point"}
}