{
  "type": "Feature",
  "properties": {
    "iso:country":"US",
    "sg:address":"4126 E Indian School Rd",
    "sg:city":"Phoenix",
    "sg:classifiers":[
        {
            "category":"Retail",
            "subcategory":"Veterinary Services",
            "type":"Services"
        }
    ],
    "sg:phone":"+1 602 955 5500",
    "sg:postcode":"85018",
    "sg:province":"AZ",
    "sg:tags":[
        "clinic",
        "hospital",
        "specialty"
    ],
    "sg:website":"http://www.hpahrx.com",
    "wof:name":"Desert View Animal Hospital",
    "wof:placetype":"venue"
},
  "geometry": {"coordinates":[-111.992362,33.495004],"type":"Point"}
}