{
  "type": "Feature",
  "properties": {
    "addr:full":"10246 W Beardsley Rd Peoria AZ 85382",
    "addr:housenumber":"10246",
    "addr:postcode":"85382",
    "addr:street":"W Beardsley Rd",
    "iso:country":"US",
    "sg:address":"10246 W Beardsley Rd",
    "sg:city":"Peoria",
    "sg:classifiers":[
        {
            "category":"Restaurant",
            "type":"Food & Drink"
        }
    ],
    "sg:menulink":"http://www.allmenus.com/az/deer-valley/231423-sonic/menu/",
    "sg:phone":"+1 623 566 2440",
    "sg:postcode":"85382",
    "sg:province":"AZ",
    "sg:tags":[
        "burger",
        "american"
    ],
    "wof:name":"Sonic",
    "wof:placetype":"venue"
},
  "geometry": {"coordinates":[-112.27894999999999,33.667208],"type":"Point"}
}