{
  "type": "Feature",
  "properties": {
    "addr:full":"10225 W Thunderbird Blvd Sun City AZ 85351",
    "addr:housenumber":"10225",
    "addr:postcode":"85351",
    "addr:street":"W Thunderbird Blvd",
    "iso:country":"US",
    "sg:address":"10225 W Thunderbird Blvd",
    "sg:city":"Sun City",
    "sg:classifiers":[
        {
            "category":"Banks & Credit Unions",
            "subcategory":"Investment Brokerage",
            "type":"Services"
        }
    ],
    "sg:phone":"+1 623 977 7980",
    "sg:postcode":"85351",
    "sg:province":"AZ",
    "sg:tags":[
        "security"
    ],
    "wof:name":"Janet E Meilke",
    "wof:placetype":"venue"
},
  "geometry": {"coordinates":[-112.280474,33.604815],"type":"Point"}
}