{
  "type": "Feature",
  "properties": {
    "addr:full":"10037 N 12th St Phoenix AZ 85020",
    "addr:housenumber":"10037",
    "addr:postcode":"85020",
    "addr:street":"N 12Th St",
    "iso:country":"US",
    "sg:address":"10037 N 12th St",
    "sg:city":"Phoenix",
    "sg:classifiers":[
        {
            "category":"Building & Trades",
            "subcategory":"Construction",
            "type":"Services"
        }
    ],
    "sg:phone":"+1 602 997 0000",
    "sg:postcode":"85020",
    "sg:province":"AZ",
    "sg:tags":[
        "interior",
        "finish",
        "contractor"
    ],
    "sg:website":"www.sis-corporation.com",
    "wof:name":"Skinner Interior Systems Inc",
    "wof:placetype":"venue"
},
  "geometry": {"coordinates":[-112.056479,33.578532],"type":"Point"}
}