{
  "type": "Feature",
  "properties": {
    "addr:full":"1701 E Speedway Blvd Tucson AZ 85719",
    "addr:housenumber":"1701",
    "addr:postcode":"85719",
    "addr:street":"E Speedway Blvd",
    "iso:country":"US",
    "sg:address":"1701 E Speedway Blvd",
    "sg:city":"Tucson",
    "sg:classifiers":[
        {
            "category":"Banks & Credit Unions",
            "subcategory":"Bank",
            "type":"Services"
        }
    ],
    "sg:phone":"+1 520 792 5077",
    "sg:postcode":"85719",
    "sg:province":"AZ",
    "sg:website":"www.wellsfargo.com",
    "wof:name":"Wells Fargo Bank",
    "wof:placetype":"venue"
},
  "geometry": {"coordinates":[-110.94503400000001,32.236043],"type":"Point"}
}