{
  "type": "Feature",
  "properties": {
    "iso:country":"US",
    "sg:address":"3004 W Thomas Rd",
    "sg:city":"Phoenix",
    "sg:classifiers":[
        {
            "category":"Wholesale",
            "subcategory":"Vending Machines",
            "type":"Manufacturing & Wholesale Goods"
        }
    ],
    "sg:phone":"+1 602 904 6673",
    "sg:postcode":"85017",
    "sg:province":"AZ",
    "sg:tags":[
        "machines-parts",
        "supply"
    ],
    "sg:website":"http://www.americaneaglevending.com",
    "wof:name":"American Eagle Vending Machine Service & Repair",
    "wof:placetype":"venue"
},
  "geometry": {"coordinates":[-112.12403399999999,33.480431],"type":"Point"}
}