{
  "type": "Feature",
  "properties": {
    "iso:country":"US",
    "sg:address":"880 E Continental Rd",
    "sg:city":"Green Valley",
    "sg:classifiers":[
        {
            "category":"Restaurant",
            "type":"Food & Drink"
        }
    ],
    "sg:phone":"+1 520 625 1329",
    "sg:postcode":"85614",
    "sg:province":"AZ",
    "wof:name":"Continental Feedlot Cafe",
    "wof:placetype":"venue"
},
  "geometry": {"coordinates":[-110.975551,31.856361],"type":"Point"}
}