{
  "type": "Feature",
  "properties": {
    "iso:country":"US",
    "sg:address":"2602 W Townley Ave",
    "sg:city":"Phoenix",
    "sg:classifiers":[
        {
            "category":"Manufacturing",
            "subcategory":"Metals",
            "type":"Manufacturing & Wholesale Goods"
        }
    ],
    "sg:phone":"+1 602 674 9279",
    "sg:postcode":"85021",
    "sg:province":"AZ",
    "sg:tags":[
        "tool"
    ],
    "wof:name":"Sankyo Reels",
    "wof:placetype":"venue"
},
  "geometry": {"coordinates":[-112.111337,33.565762],"type":"Point"}
}