{
  "type": "Feature",
  "properties": {
    "iso:country":"US",
    "sg:address":"201 N Bonita Ave",
    "sg:city":"Tucson",
    "sg:classifiers":[
        {
            "category":"Professional",
            "subcategory":"Engineering",
            "type":"Services"
        }
    ],
    "sg:phone":"+1 520 750 7474",
    "sg:postcode":"85745",
    "sg:province":"AZ",
    "sg:tags":[
        "engineer"
    ],
    "sg:website":"www.stantec.com",
    "wof:name":"Stantec Inc",
    "wof:placetype":"venue"
},
  "geometry": {"coordinates":[-110.98294,32.22315],"type":"Point"}
}