{
  "type": "Feature",
  "properties": {
    "iso:country":"US",
    "sg:address":"36003 N 7th St",
    "sg:city":"Phoenix",
    "sg:classifiers":[
        {
            "category":"Building & Trades",
            "subcategory":"Construction",
            "type":"Services"
        }
    ],
    "sg:phone":"+1 623 780 0655",
    "sg:postcode":"85086",
    "sg:province":"AZ",
    "sg:tags":[
        "house"
    ],
    "wof:name":"L&L Home Builders Inc",
    "wof:placetype":"venue"
},
  "geometry": {"coordinates":[-112.065358,33.813669],"type":"Point"}
}