{
  "type": "Feature",
  "properties": {
    "iso:country":"US",
    "sg:address":"4029 N 31st Ave",
    "sg:city":"Phoenix",
    "sg:classifiers":[
        {
            "category":"Organizations",
            "subcategory":"Professional Association",
            "type":"Services"
        }
    ],
    "sg:phone":"+1 602 200 8883",
    "sg:postcode":"85017",
    "sg:province":"AZ",
    "wof:name":"IECA Of Az",
    "wof:placetype":"venue"
},
  "geometry": {"coordinates":[-112.12555999999999,33.494555],"type":"Point"}
}