{
  "type": "Feature",
  "properties": {
    "addr:full":"454 W Valencia Rd Tucson AZ 85706",
    "addr:housenumber":"454",
    "addr:postcode":"85706",
    "addr:street":"W Valencia Rd",
    "iso:country":"US",
    "sg:address":"454 W Valencia Rd",
    "sg:city":"Tucson",
    "sg:classifiers":[
        {
            "category":"Banks & Credit Unions",
            "subcategory":"Bank",
            "type":"Services"
        }
    ],
    "sg:phone":"+1 520 294 4464",
    "sg:postcode":"85706",
    "sg:province":"AZ",
    "sg:tags":[
        "depository",
        "banking"
    ],
    "wof:name":"Ace Cash Express",
    "wof:placetype":"venue"
},
  "geometry": {"coordinates":[-110.976696,32.134048],"type":"Point"}
}