{
  "type": "Feature",
  "properties": {
    "addr:full":"3125 E Desert Ln Gilbert AZ 85234",
    "addr:housenumber":"3125",
    "addr:postcode":"85234",
    "addr:street":"E Desert Ln",
    "iso:country":"US",
    "sg:address":"3125 E Desert Ln",
    "sg:city":"Gilbert",
    "sg:classifiers":[
        {
            "category":"Professional",
            "subcategory":"Computer Services",
            "type":"Services"
        }
    ],
    "sg:phone":"+1 480 985 1728",
    "sg:postcode":"85234",
    "sg:province":"AZ",
    "sg:tags":[
        "information",
        "technology"
    ],
    "wof:name":"Abic Online",
    "wof:placetype":"venue"
},
  "geometry": {"coordinates":[-111.723938,33.373245],"type":"Point"}
}