{
  "type": "Feature",
  "properties": {
    "iso:country":"US",
    "sg:address":"3349 E McDowell Rd",
    "sg:city":"Phoenix",
    "sg:classifiers":[
        {
            "category":"Professional",
            "subcategory":"Printing & Photocopies",
            "type":"Services"
        }
    ],
    "sg:phone":"+1 602 273 1832",
    "sg:postcode":"85008",
    "sg:province":"AZ",
    "sg:tags":[
        "duplicating",
        "copying"
    ],
    "wof:name":"ABC Secretarial-Printing Inc",
    "wof:placetype":"venue"
},
  "geometry": {"coordinates":[-112.008117,33.465633],"type":"Point"}
}