{
  "type": "Feature",
  "properties": {
    "iso:country":"US",
    "sg:address":"8940 W Bell Rd",
    "sg:city":"Peoria",
    "sg:classifiers":[
        {
            "category":"Personal",
            "subcategory":"Beauty Salon",
            "type":"Services"
        }
    ],
    "sg:phone":"+1 623 933 9417",
    "sg:postcode":"85382",
    "sg:province":"AZ",
    "sg:tags":[
        "manicuring"
    ],
    "wof:name":"Lan Nails",
    "wof:placetype":"venue"
},
  "geometry": {"coordinates":[-112.25209700000001,33.638192],"type":"Point"}
}