{
  "type": "Feature",
  "properties": {
    "iso:country":"US",
    "sg:address":"225 W University Dr",
    "sg:city":"Tempe",
    "sg:classifiers":[
        {
            "category":"Shopping",
            "subcategory":"Clothing, Apparel, & Fashions",
            "type":"Retail Goods"
        }
    ],
    "sg:phone":"+1 480 966 9933",
    "sg:postcode":"85281",
    "sg:province":"AZ",
    "sg:tags":[
        "apparel",
        "women's"
    ],
    "wof:name":"Ghosticorn Apparel",
    "wof:placetype":"venue"
},
  "geometry": {"coordinates":[-111.94296,33.421921],"type":"Point"}
}