{
  "type": "Feature",
  "properties": {
    "iso:country":"US",
    "sg:address":"1014 N Madison St",
    "sg:city":"Benson",
    "sg:classifiers":[
        {
            "category":"Retail",
            "subcategory":"Auto Repair",
            "type":"Services"
        }
    ],
    "sg:phone":"+1 520 586 2948",
    "sg:postcode":"85602",
    "sg:province":"AZ",
    "sg:tags":[
        "wrecker"
    ],
    "wof:name":"Valley Auto & Wrecker Svc",
    "wof:placetype":"venue"
},
  "geometry": {"coordinates":[-110.298522,31.984714],"type":"Point"}
}