{
  "type": "Feature",
  "properties": {
    "iso:country":"US",
    "sg:address":"8235 W Foothill Dr",
    "sg:city":"Peoria",
    "sg:classifiers":[
        {
            "category":"Professional",
            "type":"Services"
        }
    ],
    "sg:phone":"+1 623 825 5702",
    "sg:postcode":"85383",
    "sg:province":"AZ",
    "wof:name":"Jorge & Clara Fajardo",
    "wof:placetype":"venue"
},
  "geometry": {"coordinates":[-112.235102,33.686741],"type":"Point"}
}