{
  "type": "Feature",
  "properties": {
    "iso:country":"US",
    "sg:address":"14404 S 12th St",
    "sg:city":"Phoenix",
    "sg:classifiers":[
        {
            "category":"Professional",
            "subcategory":"Business Services",
            "type":"Services"
        }
    ],
    "sg:phone":"+1 480 460 3829",
    "sg:postcode":"85048",
    "sg:province":"AZ",
    "sg:tags":[
        "consultant",
        "coach"
    ],
    "wof:name":"Souders & Assoc Inc",
    "wof:placetype":"venue"
},
  "geometry": {"coordinates":[-112.05916000000001,33.315265],"type":"Point"}
}