{
  "type": "Feature",
  "properties": {
    "addr:full":"3955 E Speedway Blvd Tucson AZ 85712",
    "addr:housenumber":"3955",
    "addr:postcode":"85712",
    "addr:street":"E Speedway Blvd",
    "iso:country":"US",
    "sg:address":"3955 E Speedway Blvd",
    "sg:city":"Tucson",
    "sg:classifiers":[
        {
            "category":"Banks & Credit Unions",
            "subcategory":"Bank",
            "type":"Services"
        }
    ],
    "sg:phone":"+1 520 325 9452",
    "sg:postcode":"85712",
    "sg:province":"AZ",
    "sg:tags":[
        "cashing",
        "check"
    ],
    "wof:name":"Ace Cash Express",
    "wof:placetype":"venue"
},
  "geometry": {"coordinates":[-110.908719,32.236247],"type":"Point"}
}