{
  "type": "Feature",
  "properties": {
    "iso:country":"US",
    "sg:address":"5119 E Andora Dr",
    "sg:city":"Scottsdale",
    "sg:classifiers":[
        {
            "category":"Shopping",
            "subcategory":"Computers & Home Electronics",
            "type":"Retail Goods"
        }
    ],
    "sg:phone":"+1 602 923 2585",
    "sg:postcode":"85254",
    "sg:province":"AZ",
    "sg:tags":[
        "software"
    ],
    "wof:name":"Terra Firma Consulting Inc",
    "wof:placetype":"venue"
},
  "geometry": {"coordinates":[-111.96983,33.607274],"type":"Point"}
}