{
  "type": "Feature",
  "properties": {
    "addr:full":"9295 E Thunderbird Rd Scottsdale AZ 85060",
    "addr:housenumber":"9295",
    "addr:postcode":"85060",
    "addr:street":"E Thunderbird Rd",
    "iso:country":"US",
    "sg:address":"9295 E Thunderbird Rd",
    "sg:city":"Scottsdale",
    "sg:classifiers":[
        {
            "category":"Health Services",
            "subcategory":"Doctor",
            "type":"Services"
        }
    ],
    "sg:phone":"+1 480 767 6918",
    "sg:postcode":"85060",
    "sg:province":"AZ",
    "sg:tags":[
        "dentist"
    ],
    "sg:website":"www.drrenukakumar.com",
    "wof:name":"Renuka Kumar DDS",
    "wof:placetype":"venue"
},
  "geometry": {"coordinates":[-111.88021500000001,33.611494],"type":"Point"}
}