{
  "type": "Feature",
  "properties": {
    "iso:country":"US",
    "sg:address":"411 Moonshine Dr",
    "sg:city":"Lake Havasu City",
    "sg:classifiers":[
        {
            "category":"Cinema",
            "subcategory":"Movie Rental",
            "type":"Entertainment"
        }
    ],
    "sg:phone":"+1 928 855 6703",
    "sg:postcode":"86406",
    "sg:province":"AZ",
    "sg:tags":[
        "video",
        "game",
        "leasing"
    ],
    "wof:name":"Arizona Tilt",
    "wof:placetype":"venue"
},
  "geometry": {"coordinates":[-114.272515,34.492284],"type":"Point"}
}