{
  "type": "Feature",
  "properties": {
    "addr:full":"6969 N Wade Rd Tucson AZ 85743",
    "addr:housenumber":"6969",
    "addr:postcode":"85743",
    "addr:street":"N Wade Rd",
    "iso:country":"US",
    "sg:address":"6969 N Wade Rd",
    "sg:city":"Tucson",
    "sg:classifiers":[
        {
            "category":"Organizations",
            "subcategory":"Religious Organization",
            "type":"Services"
        }
    ],
    "sg:phone":"+1 520 572 3777",
    "sg:postcode":"85743",
    "sg:province":"AZ",
    "wof:name":"Az Diamond Zen Ctr",
    "wof:placetype":"venue"
},
  "geometry": {"coordinates":[-111.114227,32.337559],"type":"Point"}
}