{
  "type": "Feature",
  "properties": {
    "iso:country":"US",
    "sg:address":"5126 N 7th St",
    "sg:city":"Phoenix",
    "sg:classifiers":[
        {
            "category":"Retail",
            "subcategory":"Auto Repair",
            "type":"Services"
        }
    ],
    "sg:phone":"+1 877 676 9426",
    "sg:postcode":"85014",
    "sg:province":"AZ",
    "sg:tags":[
        "brake"
    ],
    "sg:website":"http://www.justbrakes.com",
    "wof:name":"Just Brakes",
    "wof:placetype":"venue"
},
  "geometry": {"coordinates":[-112.06501,33.51153],"type":"Point"}
}