{
  "type": "Feature",
  "properties": {
    "iso:country":"US",
    "sg:address":"4002 E Grant Rd",
    "sg:city":"Tucson",
    "sg:classifiers":[
        {
            "category":"Health Services",
            "subcategory":"Clinic",
            "type":"Services"
        }
    ],
    "sg:phone":"+1 520 795 3108",
    "sg:postcode":"85712",
    "sg:province":"AZ",
    "sg:tags":[
        "home"
    ],
    "sg:website":"www.ucpsa.org",
    "wof:name":"United Cerebral Palsy",
    "wof:placetype":"venue"
},
  "geometry": {"coordinates":[-110.909408,32.250541],"type":"Point"}
}