{
  "type": "Feature",
  "properties": {
    "iso:country":"US",
    "sg:address":"3260 N Hayden Rd",
    "sg:city":"Scottsdale",
    "sg:classifiers":[
        {
            "category":"Manufacturing",
            "subcategory":"Apparel",
            "type":"Manufacturing & Wholesale Goods"
        }
    ],
    "sg:phone":"+1 480 368 2750",
    "sg:postcode":"85251",
    "sg:province":"AZ",
    "sg:tags":[
        "emblem"
    ],
    "wof:name":"O C Tanner Recognition Co",
    "wof:placetype":"venue"
},
  "geometry": {"coordinates":[-111.908978,33.486611],"type":"Point"}
}