{
  "type": "Feature",
  "properties": {
    "iso:country":"US",
    "sg:address":"10130 N Inverrary Pl",
    "sg:city":"Oro Valley",
    "sg:classifiers":[
        {
            "category":"Shopping",
            "subcategory":"Discount & Variety Stores",
            "type":"Retail Goods"
        }
    ],
    "sg:phone":"+1 520 219 0481",
    "sg:postcode":"85737",
    "sg:province":"AZ",
    "sg:tags":[
        "merchandise",
        "general"
    ],
    "wof:name":"Indian Store Consolidated Inc",
    "wof:placetype":"venue"
},
  "geometry": {"coordinates":[-110.987415,32.391156],"type":"Point"}
}