{
  "type": "Feature",
  "properties": {
    "iso:country":"US",
    "sg:address":"2415 W Huntington Dr",
    "sg:city":"Tempe",
    "sg:classifiers":[
        {
            "category":"Shopping",
            "subcategory":"Stationery & Office Supplies",
            "type":"Retail Goods"
        },
        {
            "category":"Retail",
            "subcategory":"Repair Shop",
            "type":"Services"
        }
    ],
    "sg:phone":"+1 623 399 4345",
    "sg:postcode":"85282",
    "sg:province":"AZ",
    "sg:tags":[
        "machine",
        "copy"
    ],
    "wof:name":"Imaging Technology Solutions",
    "wof:placetype":"venue"
},
  "geometry": {"coordinates":[-111.974158,33.394178],"type":"Point"}
}