{
  "type": "Feature",
  "properties": {
    "addr:full":"3107 W Cactus Blossom Dr Benson AZ 85602",
    "addr:housenumber":"3107",
    "addr:postcode":"85602",
    "addr:street":"W Cactus Blossom Dr",
    "iso:country":"US",
    "sg:address":"3107 W Cactus Blossom Dr",
    "sg:city":"Benson",
    "sg:classifiers":[
        {
            "category":"Manufacturing",
            "subcategory":"Printing",
            "type":"Manufacturing & Wholesale Goods"
        }
    ],
    "sg:phone":"+1 520 586 4245",
    "sg:postcode":"85602",
    "sg:province":"AZ",
    "sg:tags":[
        "commercial"
    ],
    "wof:name":"Lk Enterprises",
    "wof:placetype":"venue"
},
  "geometry": {"coordinates":[-110.426182,31.978046],"type":"Point"}
}