{
  "type": "Feature",
  "properties": {
    "addr:full":"8102 W Maryland Ave Glendale AZ 85303",
    "addr:housenumber":"8102",
    "addr:postcode":"85303",
    "addr:street":"W Maryland Ave",
    "iso:country":"US",
    "sg:address":"8102 W Maryland Ave",
    "sg:city":"Glendale",
    "sg:classifiers":[
        {
            "category":"Building & Trades",
            "subcategory":"Construction",
            "type":"Services"
        }
    ],
    "sg:phone":"+1 623 934 0702",
    "sg:postcode":"85303",
    "sg:province":"AZ",
    "sg:tags":[
        "handyman"
    ],
    "wof:name":"Liz's Interior & Exterior Cln",
    "wof:placetype":"venue"
},
  "geometry": {"coordinates":[-112.23615100000001,33.530597],"type":"Point"}
}