{
  "type": "Feature",
  "properties": {
    "addr:full":"11229 E Hedgehog Pl Scottsdale AZ 85262",
    "addr:housenumber":"11229",
    "addr:postcode":"85262",
    "addr:street":"E Hedgehog Pl",
    "iso:country":"US",
    "sg:address":"11229 E Hedgehog Pl",
    "sg:city":"Scottsdale",
    "sg:classifiers":[
        {
            "category":"Wholesale",
            "subcategory":"Non-durable Goods",
            "type":"Manufacturing & Wholesale Goods"
        }
    ],
    "sg:phone":"+1 602 740 0700",
    "sg:postcode":"85262",
    "sg:province":"AZ",
    "wof:name":"American Sun States Trading Co",
    "wof:placetype":"venue"
},
  "geometry": {"coordinates":[-111.84100100000001,33.736514],"type":"Point"}
}