{
  "type": "Feature",
  "properties": {
    "iso:country":"US",
    "sg:address":"3198 N Flowing Wells Rd",
    "sg:city":"Tucson",
    "sg:classifiers":[
        {
            "category":"Professional",
            "type":"Services"
        }
    ],
    "sg:phone":"+1 520 292 9186",
    "sg:postcode":"85705",
    "sg:province":"AZ",
    "sg:tags":[
        "establishment"
    ],
    "wof:name":"LA Roca Comunidad Christiana",
    "wof:placetype":"venue"
},
  "geometry": {"coordinates":[-110.99502,32.264064],"type":"Point"}
}