{
  "type": "Feature",
  "properties": {
    "iso:country":"US",
    "sg:address":"3131 N 70th St",
    "sg:city":"Scottsdale",
    "sg:phone":"+1 602 790 8303",
    "sg:postcode":"85251",
    "sg:province":"AZ",
    "sg:tags":[
        "communications",
        "telegraph"
    ],
    "wof:name":"Ymd",
    "wof:placetype":"venue"
},
  "geometry": {"coordinates":[-111.930364,33.484397],"type":"Point"}
}