{
  "type": "Feature",
  "properties": {
    "iso:country":"US",
    "sg:address":"555 W Middle Verde Rd",
    "sg:city":"Camp Verde",
    "sg:classifiers":[
        {
            "category":"Travel",
            "subcategory":"Hotels & Motels",
            "type":"Entertainment"
        }
    ],
    "sg:phone":"+1 928 567 9709",
    "sg:postcode":"86322",
    "sg:province":"AZ",
    "sg:tags":[
        "operation",
        "eating",
        "drinking"
    ],
    "wof:name":"Cliff Castle Casino",
    "wof:placetype":"venue"
},
  "geometry": {"coordinates":[-111.861812,34.611316],"type":"Point"}
}