{
  "type": "Feature",
  "properties": {
    "iso:country":"US",
    "sg:address":"2316 N Chrysler Dr",
    "sg:city":"Tucson",
    "sg:classifiers":[
        {
            "category":"Shopping",
            "subcategory":"Bicycles & Sporting Goods",
            "type":"Retail Goods"
        }
    ],
    "sg:phone":"+1 520 320 7762",
    "sg:postcode":"85716",
    "sg:province":"AZ",
    "wof:name":"Multisports Training Co LLC",
    "wof:placetype":"venue"
},
  "geometry": {"coordinates":[-110.915064,32.248881],"type":"Point"}
}