{
  "type": "Feature",
  "properties": {
    "addr:full":"1010 N 339th Ave Tonopah AZ 85354",
    "addr:housenumber":"1010",
    "addr:postcode":"85354",
    "addr:street":"N 339Th Ave",
    "iso:country":"US",
    "sg:address":"1010 N 339th Ave",
    "sg:city":"Tonopah",
    "sg:classifiers":[
        {
            "category":"Autos & Motor Vehicles",
            "subcategory":"Fuel & Gas Station",
            "type":"Retail Goods"
        }
    ],
    "sg:phone":"+1 623 386 6443",
    "sg:postcode":"85354",
    "sg:province":"AZ",
    "sg:tags":[
        "repair",
        "station",
        "eating",
        "gasoline",
        "general"
    ],
    "wof:name":"Griffin Rip Truck Travel Ctr",
    "wof:placetype":"venue"
},
  "geometry": {"coordinates":[-112.781431,33.457472],"type":"Point"}
}