{
  "type": "Feature",
  "properties": {
    "iso:country":"US",
    "sg:address":"4802 N 7th Ave",
    "sg:city":"Phoenix",
    "sg:classifiers":[
        {
            "category":"Building & Trades",
            "subcategory":"Construction",
            "type":"Services"
        }
    ],
    "sg:phone":"+1 602 279 2989",
    "sg:postcode":"85013",
    "sg:province":"AZ",
    "sg:tags":[
        "tile",
        "dealer"
    ],
    "wof:name":"D & D Tile Svc LTD",
    "wof:placetype":"venue"
},
  "geometry": {"coordinates":[-112.082559,33.508332],"type":"Point"}
}