{
  "type": "Feature",
  "properties": {
    "addr:full":"257 W Broadway Rd Mesa AZ 85210",
    "addr:housenumber":"257",
    "addr:postcode":"85210",
    "addr:street":"W Broadway Rd",
    "iso:country":"US",
    "sg:address":"257 W Broadway Rd",
    "sg:city":"Mesa",
    "sg:classifiers":[
        {
            "category":"Building & Trades",
            "subcategory":"Construction",
            "type":"Services"
        }
    ],
    "sg:phone":"+1 480 833 4538",
    "sg:postcode":"85210",
    "sg:province":"AZ",
    "sg:tags":[
        "fire",
        "restoration",
        "damage",
        "contractor"
    ],
    "sg:website":"www.eastvalleydisaster.com",
    "wof:name":"East Valley Disaster Services",
    "wof:placetype":"venue"
},
  "geometry": {"coordinates":[-111.838679,33.407814],"type":"Point"}
}