{
  "type": "Feature",
  "properties": {
    "iso:country":"US",
    "sg:address":"13203 N 103rd Ave",
    "sg:city":"Sun City",
    "sg:classifiers":[
        {
            "category":"Professional",
            "type":"Services"
        }
    ],
    "sg:phone":"+1 623 583 6834",
    "sg:postcode":"85351",
    "sg:province":"AZ",
    "wof:name":"Aubeta Networks",
    "wof:placetype":"venue"
},
  "geometry": {"coordinates":[-112.281155,33.604641],"type":"Point"}
}