{
  "type": "Feature",
  "properties": {
    "iso:country":"US",
    "sg:address":"4930 E Main St",
    "sg:city":"Mesa",
    "sg:classifiers":[
        {
            "category":"Personal",
            "subcategory":"Beauty Salon",
            "type":"Services"
        }
    ],
    "sg:phone":"+1 480 832 5826",
    "sg:postcode":"85205",
    "sg:province":"AZ",
    "wof:name":"Kay's Village Hairdressers",
    "wof:placetype":"venue"
},
  "geometry": {"coordinates":[-111.724403,33.415621],"type":"Point"}
}