{
  "type": "Feature",
  "properties": {
    "iso:country":"US",
    "sg:address":"3128 E Villa Rita Dr",
    "sg:city":"Phoenix",
    "sg:classifiers":[
        {
            "category":"Building & Trades",
            "subcategory":"Plumbing",
            "type":"Services"
        }
    ],
    "sg:phone":"+1 602 971 1740",
    "sg:postcode":"85032",
    "sg:province":"AZ",
    "sg:tags":[
        "contractor"
    ],
    "wof:name":"J P Neely AC & Heat",
    "wof:placetype":"venue"
},
  "geometry": {"coordinates":[-112.015987,33.651215],"type":"Point"}
}