{
  "type": "Feature",
  "properties": {
    "addr:full":"20278 N 51st Dr Glendale AZ 85308",
    "addr:housenumber":"20278",
    "addr:postcode":"85308",
    "addr:street":"N 51St Dr",
    "iso:country":"US",
    "sg:address":"20278 N 51st Dr",
    "sg:city":"Glendale",
    "sg:classifiers":[
        {
            "category":"Social Services",
            "type":"Services"
        }
    ],
    "sg:phone":"+1 623 572 4127",
    "sg:postcode":"85308",
    "sg:province":"AZ",
    "sg:tags":[
        "information",
        "center",
        "diabetes"
    ],
    "wof:name":"Donohue & Assoc Consulting",
    "wof:placetype":"venue"
},
  "geometry": {"coordinates":[-112.170075,33.669989],"type":"Point"}
}