{
  "type": "Feature",
  "properties": {
    "iso:country":"US",
    "sg:address":"705 N 1st St",
    "sg:city":"Phoenix",
    "sg:classifiers":[
        {
            "category":"Restaurant",
            "type":"Food & Drink"
        }
    ],
    "sg:menulink":"http://www.allmenus.com/az/phoenix/283052-sens/menu/",
    "sg:phone":"+1 602 340 9777",
    "sg:postcode":"85004",
    "sg:province":"AZ",
    "sg:tags":[
        "japanese",
        "asian"
    ],
    "wof:name":"Sens",
    "wof:placetype":"venue"
},
  "geometry": {"coordinates":[-112.07239800000001,33.455685],"type":"Point"}
}