{
  "type": "Feature",
  "properties": {
    "iso:country":"US",
    "sg:address":"42 W Boxelder Pl",
    "sg:city":"Chandler",
    "sg:classifiers":[
        {
            "category":"Shopping",
            "type":"Retail Goods"
        }
    ],
    "sg:phone":"+1 480 222 3704",
    "sg:postcode":"85225",
    "sg:province":"AZ",
    "sg:tags":[
        "art",
        "gallery",
        "dealer"
    ],
    "wof:name":"Boxelder Art",
    "wof:placetype":"venue"
},
  "geometry": {"coordinates":[-111.84358899999999,33.355868],"type":"Point"}
}