{
  "type": "Feature",
  "properties": {
    "iso:country":"US",
    "sg:address":"11654 W Emmer Dr",
    "sg:city":"Marana",
    "sg:classifiers":[
        {
            "category":"Real Estate",
            "subcategory":"Real Estate Services",
            "type":"Services"
        },
        {
            "category":"Real Estate",
            "subcategory":"Real Estate Agent",
            "type":"Services"
        }
    ],
    "sg:phone":"+1 520 889 8395",
    "sg:postcode":"85653",
    "sg:province":"AZ",
    "sg:tags":[
        "buyer",
        "broker"
    ],
    "wof:name":"Thomas Dianetta Real Estate Inc",
    "wof:placetype":"venue"
},
  "geometry": {"coordinates":[-111.214601,32.43786],"type":"Point"}
}