{
  "type": "Feature",
  "properties": {
    "iso:country":"US",
    "sg:address":"5519 W Turquoise Ave",
    "sg:city":"Glendale",
    "sg:classifiers":[
        {
            "category":"Recreation",
            "type":"Entertainment"
        }
    ],
    "sg:phone":"+1 623 934 5529",
    "sg:postcode":"85302",
    "sg:province":"AZ",
    "sg:tags":[
        "merchandise"
    ],
    "wof:name":"Framing Works",
    "wof:placetype":"venue"
},
  "geometry": {"coordinates":[-112.179012,33.575398],"type":"Point"}
}