{
  "type": "Feature",
  "properties": {
    "iso:country":"US",
    "sg:address":"2136 Senita Dr",
    "sg:city":"Lake Havasu City",
    "sg:classifiers":[
        {
            "category":"Real Estate",
            "subcategory":"Architect",
            "type":"Services"
        }
    ],
    "sg:phone":"+1 928 855 8484",
    "sg:postcode":"86403",
    "sg:province":"AZ",
    "wof:name":"Maximum Planning",
    "wof:placetype":"venue"
},
  "geometry": {"coordinates":[-114.326081,34.483378],"type":"Point"}
}