{
  "type": "Feature",
  "properties": {
    "iso:country":"US",
    "sg:address":"34125 N Boulders Pkwy",
    "sg:city":"Scottsdale",
    "sg:classifiers":[
        {
            "category":"Cinema",
            "subcategory":"Movie Rental",
            "type":"Entertainment"
        }
    ],
    "sg:phone":"+1 480 720 7214",
    "sg:postcode":"85266",
    "sg:province":"AZ",
    "sg:tags":[
        "motion",
        "picture",
        "distributor",
        "film",
        "exchange"
    ],
    "wof:name":"T H E Productions",
    "wof:placetype":"venue"
},
  "geometry": {"coordinates":[-111.923887,33.795189],"type":"Point"}
}