{
  "type": "Feature",
  "properties": {
    "addr:full":"710 W Constitution Dr Gilbert AZ 85233",
    "addr:housenumber":"710",
    "addr:postcode":"85233",
    "addr:street":"W Constitution Dr",
    "iso:country":"US",
    "sg:address":"710 W Constitution Dr",
    "sg:city":"Gilbert",
    "sg:classifiers":[
        {
            "category":"Professional",
            "type":"Services"
        }
    ],
    "sg:phone":"+1 480 821 2050",
    "sg:postcode":"85233",
    "sg:province":"AZ",
    "wof:name":"Buell Works",
    "wof:placetype":"venue"
},
  "geometry": {"coordinates":[-111.80542,33.322387],"type":"Point"}
}