{
  "type": "Feature",
  "properties": {
    "iso:country":"US",
    "sg:address":"3939 E Frye Rd",
    "sg:city":"Phoenix",
    "sg:classifiers":[
        {
            "category":"Professional",
            "subcategory":"Business Services",
            "type":"Services"
        }
    ],
    "sg:phone":"+1 480 219 7663",
    "sg:postcode":"85048",
    "sg:province":"AZ",
    "sg:tags":[
        "inspection"
    ],
    "wof:name":"First Priority Inspections",
    "wof:placetype":"venue"
},
  "geometry": {"coordinates":[-111.99818,33.298052],"type":"Point"}
}