{
  "type": "Feature",
  "properties": {
    "addr:full":"1403 N 61st Pl Mesa AZ 85205",
    "addr:housenumber":"1403",
    "addr:postcode":"85205",
    "addr:street":"N 61St Pl",
    "iso:country":"US",
    "sg:address":"1403 N 61st Pl",
    "sg:city":"Mesa",
    "sg:classifiers":[
        {
            "category":"Building & Trades",
            "subcategory":"Construction",
            "type":"Services"
        }
    ],
    "sg:phone":"+1 480 219 5233",
    "sg:postcode":"85205",
    "sg:province":"AZ",
    "sg:tags":[
        "painter"
    ],
    "wof:name":"Andy Richards Painting Inc",
    "wof:placetype":"venue"
},
  "geometry": {"coordinates":[-111.69785,33.441035],"type":"Point"}
}