{
  "type": "Feature",
  "properties": {
    "iso:country":"US",
    "sg:address":"5577 N Oracle Rd",
    "sg:city":"Tucson",
    "sg:classifiers":[
        {
            "category":"Health Services",
            "subcategory":"Doctor",
            "type":"Services"
        }
    ],
    "sg:phone":"+1 520 293 9100",
    "sg:postcode":"85704",
    "sg:province":"AZ",
    "sg:tags":[
        "physician",
        "surgeon"
    ],
    "wof:name":"Saguaro Electrology",
    "wof:placetype":"venue"
},
  "geometry": {"coordinates":[-110.97865899999999,32.307322],"type":"Point"}
}