{
  "type": "Feature",
  "properties": {
    "iso:country":"US",
    "sg:address":"2600 N Cam Cascabel",
    "sg:city":"Tucson",
    "sg:classifiers":[
        {
            "category":"Restaurant",
            "type":"Food & Drink"
        }
    ],
    "sg:phone":"+1 520 797 2484",
    "sg:postcode":"85749",
    "sg:province":"AZ",
    "wof:name":"Hacienda Tanque Verde",
    "wof:placetype":"venue"
},
  "geometry": {"coordinates":[-110.695762,32.252315],"type":"Point"}
}