{
  "type": "Feature",
  "properties": {
    "addr:full":"2033 E Southern Ave Mesa AZ 85204",
    "addr:housenumber":"2033",
    "addr:postcode":"85204",
    "addr:street":"E Southern Ave",
    "iso:country":"US",
    "sg:address":"2033 E Southern Ave",
    "sg:city":"Mesa",
    "sg:classifiers":[
        {
            "category":"Restaurant",
            "type":"Food & Drink"
        }
    ],
    "sg:menulink":"http://www.allmenus.com/az/phoenix/166587-burger-king/menu/",
    "sg:phone":"+1 480 926 2246",
    "sg:postcode":"85204",
    "sg:province":"AZ",
    "sg:tags":[
        "burger",
        "american"
    ],
    "wof:name":"Burger King",
    "wof:placetype":"venue"
},
  "geometry": {"coordinates":[-111.78721,33.39317],"type":"Point"}
}