{
  "type": "Feature",
  "properties": {
    "iso:country":"US",
    "sg:address":"10205 N Eight Iron Rd",
    "sg:city":"Tucson",
    "sg:classifiers":[
        {
            "category":"Building & Trades",
            "subcategory":"Construction",
            "type":"Services"
        }
    ],
    "sg:phone":"+1 520 878 8101",
    "sg:postcode":"85737",
    "sg:province":"AZ",
    "sg:tags":[
        "house"
    ],
    "wof:name":"Asset Builders Ltd",
    "wof:placetype":"venue"
},
  "geometry": {"coordinates":[-110.993246,32.391527],"type":"Point"}
}