{
  "type": "Feature",
  "properties": {
    "iso:country":"US",
    "sg:address":"1124 E Hampton St",
    "sg:city":"Tucson",
    "sg:classifiers":[
        {
            "category":"Wholesale",
            "subcategory":"Machinery & Supplies",
            "type":"Manufacturing & Wholesale Goods"
        }
    ],
    "sg:phone":"+1 520 740 1644",
    "sg:postcode":"85719",
    "sg:province":"AZ",
    "sg:tags":[
        "sprinkler"
    ],
    "wof:name":"Adams Fire Protection",
    "wof:placetype":"venue"
},
  "geometry": {"coordinates":[-110.954221,32.247719],"type":"Point"}
}