{
  "type": "Feature",
  "properties": {
    "iso:country":"US",
    "sg:address":"320 N 48th St",
    "sg:city":"Phoenix",
    "sg:classifiers":[
        {
            "category":"Wholesale",
            "subcategory":"Auto Parts",
            "type":"Manufacturing & Wholesale Goods"
        }
    ],
    "sg:phone":"+1 602 306 2954",
    "sg:postcode":"85008",
    "sg:province":"AZ",
    "sg:tags":[
        "automobile",
        "supply"
    ],
    "wof:name":"Transmission Parts Service",
    "wof:placetype":"venue"
},
  "geometry": {"coordinates":[-111.978447,33.451591],"type":"Point"}
}