{
  "type": "Feature",
  "properties": {
    "iso:country":"US",
    "sg:address":"7018 E Main St",
    "sg:city":"Scottsdale",
    "sg:classifiers":[
        {
            "category":"Bars & Pubs",
            "type":"Food & Drink"
        }
    ],
    "sg:phone":"+1 480 946 0363",
    "sg:postcode":"85251",
    "sg:province":"AZ",
    "sg:tags":[
        "club",
        "night"
    ],
    "sg:website":"www.mabelmurphys.com",
    "wof:name":"Mabel Murphys",
    "wof:placetype":"venue"
},
  "geometry": {"coordinates":[-111.928616,33.493187],"type":"Point"}
}