{
  "type": "Feature",
  "properties": {
    "iso:country":"US",
    "sg:address":"4818 E Peak View Rd",
    "sg:city":"Cave Creek",
    "sg:classifiers":[
        {
            "category":"Wholesale",
            "subcategory":"Groceries",
            "type":"Manufacturing & Wholesale Goods"
        }
    ],
    "sg:phone":"+1 480 502 7500",
    "sg:postcode":"85331",
    "sg:province":"AZ",
    "sg:tags":[
        "food",
        "broker"
    ],
    "wof:name":"Biltmore Trading",
    "wof:placetype":"venue"
},
  "geometry": {"coordinates":[-111.976871,33.74884],"type":"Point"}
}