{
  "type": "Feature",
  "properties": {
    "addr:full":"9720 E Cactus Rd Scottsdale AZ 85260",
    "addr:housenumber":"9720",
    "addr:postcode":"85260",
    "addr:street":"E Cactus Rd",
    "iso:country":"US",
    "sg:address":"9720 E Cactus Rd",
    "sg:city":"Scottsdale",
    "sg:classifiers":[
        {
            "category":"Farming",
            "subcategory":"Livestock Farm",
            "type":"Manufacturing & Wholesale Goods"
        },
        {
            "category":"Recreation",
            "type":"Entertainment"
        }
    ],
    "sg:phone":"+1 480 391 8663",
    "sg:postcode":"85260",
    "sg:province":"AZ",
    "sg:tags":[
        "equine",
        "animal",
        "stable"
    ],
    "wof:name":"Saguaro Creek Farm LLC",
    "wof:placetype":"venue"
},
  "geometry": {"coordinates":[-111.871797,33.597143],"type":"Point"}
}