{
  "type": "Feature",
  "properties": {
    "iso:country":"US",
    "sg:address":"8625 N 7th Ave",
    "sg:city":"Phoenix",
    "sg:classifiers":[
        {
            "category":"Professional",
            "subcategory":"Management & Consulting",
            "type":"Services"
        }
    ],
    "sg:phone":"+1 602 944 6358",
    "sg:postcode":"85021",
    "sg:province":"AZ",
    "sg:tags":[
        "food",
        "consultant",
        "beverage",
        "facility"
    ],
    "sg:website":"http://www.hamilton-web.com",
    "wof:name":"Hamilton Associates",
    "wof:placetype":"venue"
},
  "geometry": {"coordinates":[-112.08255,33.562777],"type":"Point"}
}