{
  "type": "Feature",
  "properties": {
    "iso:country":"US",
    "sg:address":"9839 W Bell Rd",
    "sg:city":"Sun City",
    "sg:classifiers":[
        {
            "category":"Recreation",
            "type":"Entertainment"
        }
    ],
    "sg:phone":"+1 623 977 9642",
    "sg:postcode":"85351",
    "sg:province":"AZ",
    "sg:tags":[
        "instruction",
        "yoga"
    ],
    "wof:name":"Blissful Yoga",
    "wof:placetype":"venue"
},
  "geometry": {"coordinates":[-112.272897,33.638046],"type":"Point"}
}