{
  "type": "Feature",
  "properties": {
    "iso:country":"US",
    "sg:address":"5033 N 19th Ave",
    "sg:city":"Phoenix",
    "sg:classifiers":[
        {
            "category":"Organizations",
            "subcategory":"Professional Association",
            "type":"Services"
        }
    ],
    "sg:phone":"+1 602 589 7310",
    "sg:postcode":"85015",
    "sg:province":"AZ",
    "sg:website":"www.dlea.org",
    "wof:name":"Deputies Law Enforcement Assn",
    "wof:placetype":"venue"
},
  "geometry": {"coordinates":[-112.09975799999999,33.512779],"type":"Point"}
}