{
  "type": "Feature",
  "properties": {
    "iso:country":"US",
    "sg:address":"7107 W Edgemont Ave",
    "sg:city":"Phoenix",
    "sg:classifiers":[
        {
            "category":"Building & Trades",
            "subcategory":"Construction",
            "type":"Services"
        }
    ],
    "sg:phone":"+1 623 849 8582",
    "sg:postcode":"85035",
    "sg:province":"AZ",
    "sg:tags":[
        "concrete",
        "contractor"
    ],
    "wof:name":"A New Surface Inc",
    "wof:placetype":"venue"
},
  "geometry": {"coordinates":[-112.212581,33.479657],"type":"Point"}
}