{
  "type": "Feature",
  "properties": {
    "iso:country":"US",
    "sg:address":"8021 N 43rd Ave",
    "sg:city":"Phoenix",
    "sg:classifiers":[
        {
            "category":"Food & Beverages",
            "subcategory":"Specialty",
            "type":"Retail Goods"
        }
    ],
    "sg:phone":"+1 623 934 3055",
    "sg:postcode":"85051",
    "sg:province":"AZ",
    "sg:tags":[
        "grocery",
        "general"
    ],
    "wof:name":"Portscare Shipping and Trdg Co",
    "wof:placetype":"venue"
},
  "geometry": {"coordinates":[-112.151508,33.554645],"type":"Point"}
}