{
  "type": "Feature",
  "properties": {
    "iso:country":"US",
    "sg:address":"1602 N 3rd Ave",
    "sg:city":"Phoenix",
    "sg:classifiers":[
        {
            "category":"Shopping",
            "subcategory":"Used Merchandise",
            "type":"Retail Goods"
        }
    ],
    "sg:phone":"+1 602 258 1111",
    "sg:postcode":"85003",
    "sg:province":"AZ",
    "sg:tags":[
        "pawnbroker"
    ],
    "wof:name":"Central Pawn Brokers Inc",
    "wof:placetype":"venue"
},
  "geometry": {"coordinates":[-112.07831,33.466729],"type":"Point"}
}