{
  "type": "Feature",
  "properties": {
    "addr:full":"2800 N el Paso Flagstaff Rd Flagstaff AZ 86004",
    "addr:housenumber":"2800",
    "addr:postcode":"86004",
    "addr:street":"N El Paso Flagstaff Rd",
    "iso:country":"US",
    "sg:address":"2800 N el Paso Flagstaff Rd",
    "sg:city":"Flagstaff",
    "sg:classifiers":[
        {
            "category":"Government",
            "subcategory":"Office",
            "type":"Public Place"
        }
    ],
    "sg:phone":"+1 928 526 2520",
    "sg:postcode":"86004",
    "sg:province":"AZ",
    "sg:tags":[
        "village"
    ],
    "wof:name":"Wildcat Hill Wastewater Plant",
    "wof:placetype":"venue"
},
  "geometry": {"coordinates":[-111.560194,35.223048],"type":"Point"}
}