{
  "type": "Feature",
  "properties": {
    "iso:country":"US",
    "sg:address":"12825 E 34th Pl",
    "sg:city":"Yuma",
    "sg:classifiers":[
        {
            "category":"Wholesale",
            "subcategory":"Machinery & Supplies",
            "type":"Manufacturing & Wholesale Goods"
        }
    ],
    "sg:phone":"+1 928 342 3055",
    "sg:postcode":"85367",
    "sg:province":"AZ",
    "sg:tags":[
        "equipment",
        "irrigation",
        "system"
    ],
    "wof:name":"Foothills Irrigations",
    "wof:placetype":"venue"
},
  "geometry": {"coordinates":[-114.411681,32.665588],"type":"Point"}
}