{
  "type": "Feature",
  "properties": {
    "iso:country":"US",
    "sg:address":"3431 Big Chief Dr",
    "sg:city":"Lake Havasu City",
    "sg:classifiers":[
        {
            "category":"Freight",
            "type":"Transportation"
        }
    ],
    "sg:phone":"+1 928 453 6771",
    "sg:postcode":"86406",
    "sg:province":"AZ",
    "sg:tags":[
        "operator",
        "local",
        "trucking"
    ],
    "wof:name":"Olivers Distributing",
    "wof:placetype":"venue"
},
  "geometry": {"coordinates":[-114.274558,34.464141],"type":"Point"}
}