{
  "type": "Feature",
  "properties": {
    "iso:country":"US",
    "sg:address":"310 W Watkins St",
    "sg:city":"Phoenix",
    "sg:classifiers":[
        {
            "category":"Retail",
            "subcategory":"Auto Repair",
            "type":"Services"
        }
    ],
    "sg:phone":"+1 602 253 4007",
    "sg:postcode":"85003",
    "sg:province":"AZ",
    "sg:tags":[
        "trailer"
    ],
    "wof:name":"B & A Trailer Specialists",
    "wof:placetype":"venue"
},
  "geometry": {"coordinates":[-112.077251,33.425956],"type":"Point"}
}