{
  "type": "Feature",
  "properties": {
    "iso:country":"US",
    "sg:address":"1811 S Alma School Rd Ste 260",
    "sg:city":"Mesa",
    "sg:classifiers":[
        {
            "category":"Professional",
            "subcategory":"Accounting & Tax Preparation",
            "type":"Services"
        },
        {
            "category":"Banks & Credit Unions",
            "subcategory":"Atm",
            "type":"Services"
        }
    ],
    "sg:phone":"+1 480 745 1505",
    "sg:postcode":"85210",
    "sg:province":"AZ",
    "sg:tags":[
        "accountant",
        "bankruptcy"
    ],
    "sg:website":"www.MyPhoenixBankruptcyCenter.com",
    "wof:name":"Pew Law Center, PLLC",
    "wof:placetype":"venue"
},
  "geometry": {"coordinates":[-111.857761,33.382194],"type":"Point"}
}