{
  "type": "Feature",
  "properties": {
    "addr:full":"7032 E Cochise Rd Scottsdale AZ 85253",
    "addr:housenumber":"7032",
    "addr:postcode":"85253",
    "addr:street":"E Cochise Rd",
    "iso:country":"US",
    "sg:address":"7032 E Cochise Rd",
    "sg:city":"Scottsdale",
    "sg:classifiers":[
        {
            "category":"Health Services",
            "subcategory":"Doctor",
            "type":"Services"
        }
    ],
    "sg:phone":"+1 480 443 8440",
    "sg:postcode":"85253",
    "sg:province":"AZ",
    "sg:tags":[
        "dentist"
    ],
    "wof:name":"Periodontal Specialists",
    "wof:placetype":"venue"
},
  "geometry": {"coordinates":[-111.93035399999999,33.58033],"type":"Point"}
}