{
  "type": "Feature",
  "properties": {
    "addr:full":"5535 N 67th Avenue Glendale AZ 85301",
    "addr:housenumber":"5535",
    "addr:postcode":"85301",
    "addr:street":"N 67Th Avenue",
    "iso:country":"US",
    "sg:address":"5535 N 67th Avenue",
    "sg:city":"Glendale",
    "sg:classifiers":[
        {
            "category":"Social Services",
            "subcategory":"Child Care",
            "type":"Services"
        }
    ],
    "sg:phone":"+1 623 847 4863",
    "sg:postcode":"85301",
    "sg:province":"AZ",
    "sg:tags":[
        "day"
    ],
    "wof:name":"Menendick Head Start",
    "wof:placetype":"venue"
},
  "geometry": {"coordinates":[-112.203227,33.517412],"type":"Point"}
}