{
  "type": "Feature",
  "properties": {
    "iso:country":"US",
    "sg:address":"3413 US Hwy 191",
    "sg:city":"Safford",
    "sg:classifiers":[
        {
            "category":"Real Estate",
            "subcategory":"Developer",
            "type":"Services"
        }
    ],
    "sg:phone":"+1 928 428 1993",
    "sg:postcode":"85546",
    "sg:province":"AZ",
    "sg:tags":[
        "mobile",
        "home"
    ],
    "wof:name":"Graham Shadows Mobile Home Pk",
    "wof:placetype":"venue"
},
  "geometry": {"coordinates":[-109.657883,32.816521],"type":"Point"}
}