{
  "type": "Feature",
  "properties": {
    "iso:country":"US",
    "sg:address":"10789 N 90th St",
    "sg:city":"Scottsdale",
    "sg:classifiers":[
        {
            "category":"Social Services",
            "type":"Services"
        }
    ],
    "sg:phone":"+1 480 391 9902",
    "sg:postcode":"85260",
    "sg:province":"AZ",
    "sg:tags":[
        "counselor",
        "marriage",
        "family"
    ],
    "wof:name":"Claire Bellefeuille",
    "wof:placetype":"venue"
},
  "geometry": {"coordinates":[-111.886006,33.583549],"type":"Point"}
}