{
  "type": "Feature",
  "properties": {
    "iso:country":"US",
    "sg:address":"1765 E Jacinto Cir",
    "sg:city":"Mesa",
    "sg:classifiers":[
        {
            "category":"Shopping",
            "subcategory":"Clothing, Apparel, & Fashions",
            "type":"Retail Goods"
        }
    ],
    "sg:phone":"+1 480 632 6043",
    "sg:postcode":"85204",
    "sg:province":"AZ",
    "wof:name":"Dye Masters",
    "wof:placetype":"venue"
},
  "geometry": {"coordinates":[-111.793605,33.379453],"type":"Point"}
}