{
  "type": "Feature",
  "properties": {
    "iso:country":"US",
    "sg:address":"4815 E Main St",
    "sg:city":"Mesa",
    "sg:classifiers":[
        {
            "category":"Shopping",
            "subcategory":"Gifts & Souvenirs",
            "type":"Retail Goods"
        }
    ],
    "sg:phone":"+1 480 654 0815",
    "sg:postcode":"85205",
    "sg:province":"AZ",
    "sg:tags":[
        "collectible"
    ],
    "wof:name":"Route 66 & Diecast Car Store",
    "wof:placetype":"venue"
},
  "geometry": {"coordinates":[-111.72617700000001,33.415463],"type":"Point"}
}