{
  "type": "Feature",
  "properties": {
    "addr:full":"6630 W Camelback Rd Glendale AZ 85301",
    "addr:housenumber":"6630",
    "addr:postcode":"85301",
    "addr:street":"W Camelback Rd",
    "iso:country":"US",
    "sg:address":"6630 W Camelback Rd",
    "sg:city":"Glendale",
    "sg:classifiers":[
        {
            "category":"Food & Beverages",
            "subcategory":"Groceries & Convenience Stores",
            "type":"Retail Goods"
        }
    ],
    "sg:phone":"+1 623 848 1088",
    "sg:postcode":"85301",
    "sg:province":"AZ",
    "sg:tags":[
        "product"
    ],
    "wof:name":"Food N Fuel",
    "wof:placetype":"venue"
},
  "geometry": {"coordinates":[-112.20263199999999,33.509432],"type":"Point"}
}