{
  "type": "Feature",
  "properties": {
    "addr:full":"630 N Montezuma St Prescott AZ 86301",
    "addr:housenumber":"630",
    "addr:postcode":"86301",
    "addr:street":"N Montezuma St",
    "iso:country":"US",
    "sg:address":"630 N Montezuma St",
    "sg:city":"Prescott",
    "sg:classifiers":[
        {
            "category":"Retail",
            "subcategory":"Auto Repair",
            "type":"Services"
        }
    ],
    "sg:phone":"+1 928 771 0595",
    "sg:postcode":"86301",
    "sg:province":"AZ",
    "sg:tags":[
        "automobile",
        "lubrication"
    ],
    "wof:name":"Grease Monkey",
    "wof:placetype":"venue"
},
  "geometry": {"coordinates":[-112.469598,34.551557],"type":"Point"}
}