{
  "type": "Feature",
  "properties": {
    "iso:country":"US",
    "sg:address":"250 N 3rd Ave",
    "sg:city":"Holbrook",
    "sg:classifiers":[
        {
            "category":"Home & Garden",
            "subcategory":"Building Materials",
            "type":"Retail Goods"
        }
    ],
    "sg:phone":"+1 928 524 3176",
    "sg:postcode":"86025",
    "sg:province":"AZ",
    "sg:tags":[
        "equipment",
        "electric",
        "supply"
    ],
    "wof:name":"Service Electric & Supply",
    "wof:placetype":"venue"
},
  "geometry": {"coordinates":[-110.162894,34.903257],"type":"Point"}
}