{
  "type": "Feature",
  "properties": {
    "iso:country":"US",
    "sg:address":"350 E Bell Rd",
    "sg:city":"Phoenix",
    "sg:classifiers":[
        {
            "category":"Insurance",
            "subcategory":"Insurance Agent",
            "type":"Services"
        }
    ],
    "sg:phone":"+1 602 788 6494",
    "sg:postcode":"85022",
    "sg:province":"AZ",
    "wof:name":"American Family Insurance",
    "wof:placetype":"venue"
},
  "geometry": {"coordinates":[-112.06939199999999,33.640354],"type":"Point"}
}