{
  "type": "Feature",
  "properties": {
    "iso:country":"US",
    "sg:address":"206 US Hwy 66",
    "sg:city":"Williams",
    "sg:classifiers":[
        {
            "category":"Shopping",
            "subcategory":"Musical Instruments",
            "type":"Retail Goods"
        }
    ],
    "sg:phone":"+1 928 635 9271",
    "sg:postcode":"86046",
    "sg:province":"AZ",
    "wof:name":"Gateway Music",
    "wof:placetype":"venue"
},
  "geometry": {"coordinates":[-112.185099,35.251496],"type":"Point"}
}