{
  "type": "Feature",
  "properties": {
    "iso:country":"US",
    "sg:address":"12449 N 36th Dr",
    "sg:city":"Phoenix",
    "sg:classifiers":[
        {
            "category":"Professional",
            "subcategory":"Business Services",
            "type":"Services"
        }
    ],
    "sg:phone":"+1 602 978 2185",
    "sg:postcode":"85029",
    "sg:province":"AZ",
    "sg:tags":[
        "painter",
        "sign"
    ],
    "wof:name":"Accu Screen Specialties",
    "wof:placetype":"venue"
},
  "geometry": {"coordinates":[-112.13597,33.59876],"type":"Point"}
}