{
  "type": "Feature",
  "properties": {
    "iso:country":"US",
    "sg:address":"2251 W 24th St",
    "sg:city":"Yuma",
    "sg:classifiers":[
        {
            "category":"Freight",
            "type":"Transportation"
        }
    ],
    "sg:phone":"+1 928 726 1550",
    "sg:postcode":"85364",
    "sg:province":"AZ",
    "sg:tags":[
        "general"
    ],
    "wof:name":"Security First Self Storage",
    "wof:placetype":"venue"
},
  "geometry": {"coordinates":[-114.647544,32.68388],"type":"Point"}
}