{
  "type": "Feature",
  "properties": {
    "iso:country":"US",
    "sg:address":"405 W University Dr Ste 101",
    "sg:city":"Tempe",
    "sg:classifiers":[
        {
            "category":"Fast Food",
            "type":"Food & Drink"
        },
        {
            "category":"Personal",
            "type":"Services"
        },
        {
            "category":"Restaurant",
            "type":"Food & Drink"
        }
    ],
    "sg:phone":"+1 480 894 8424",
    "sg:postcode":"85281",
    "sg:province":"AZ",
    "sg:tags":[
        "delivery",
        "take",
        "pizza"
    ],
    "sg:website":"http://www.tessiospizza.com",
    "wof:name":"Tessio's Pizza",
    "wof:placetype":"venue"
},
  "geometry": {"coordinates":[-111.944298,33.42189],"type":"Point"}
}