{
  "type": "Feature",
  "properties": {
    "iso:country":"US",
    "sg:address":"2531 S 4th Ave",
    "sg:city":"Yuma",
    "sg:classifiers":[
        {
            "category":"Autos & Motor Vehicles",
            "subcategory":"Auto Supplies",
            "type":"Retail Goods"
        }
    ],
    "sg:phone":"+1 928 344 2722",
    "sg:postcode":"85364",
    "sg:province":"AZ",
    "wof:name":"Autozone 2761",
    "wof:placetype":"venue"
},
  "geometry": {"coordinates":[-114.624547,32.682077],"type":"Point"}
}