{
  "type": "Feature",
  "properties": {
    "iso:country":"US",
    "sg:address":"3285 E Hemisphere Loop",
    "sg:city":"Tucson",
    "sg:classifiers":[
        {
            "category":"Government",
            "subcategory":"Police Station",
            "type":"Public Place"
        }
    ],
    "sg:phone":"+1 520 573 5500",
    "sg:postcode":"85706",
    "sg:province":"AZ",
    "sg:tags":[
        "federal"
    ],
    "wof:name":"US Drug Enforcement Admin",
    "wof:placetype":"venue"
},
  "geometry": {"coordinates":[-110.921988,32.134451],"type":"Point"}
}