{
  "type": "Feature",
  "properties": {
    "iso:country":"US",
    "sg:address":"3450 E Sunrise Dr",
    "sg:city":"Tucson",
    "sg:classifiers":[
        {
            "category":"Manufacturing",
            "subcategory":"Aerospace",
            "type":"Manufacturing & Wholesale Goods"
        }
    ],
    "sg:phone":"+1 520 615 1257",
    "sg:postcode":"85718",
    "sg:province":"AZ",
    "sg:tags":[
        "system",
        "space"
    ],
    "wof:name":"General Dynmics C4 Systems Inc",
    "wof:placetype":"venue"
},
  "geometry": {"coordinates":[-110.919149,32.32046],"type":"Point"}
}