{
  "type": "Feature",
  "properties": {
    "iso:country":"US",
    "sg:address":"3272 Calanda St",
    "sg:city":"Laughlin",
    "sg:classifiers":[
        {
            "category":"Professional",
            "type":"Services"
        }
    ],
    "sg:phone":"+1 702 298 7504",
    "sg:postcode":"89029",
    "sg:province":"NV",
    "sg:tags":[
        "establishment"
    ],
    "wof:name":"Del Sol Monte Homeowners Assoc",
    "wof:placetype":"venue"
},
  "geometry": {"coordinates":[-114.618745,35.135766],"type":"Point"}
}