{
  "type": "Feature",
  "properties": {
    "addr:full":"1980 W Wetmore Rd Tucson AZ 85705",
    "addr:housenumber":"1980",
    "addr:postcode":"85705",
    "addr:street":"W Wetmore Rd",
    "iso:country":"US",
    "sg:address":"1980 W Wetmore Rd",
    "sg:city":"Tucson",
    "sg:classifiers":[
        {
            "category":"Retail",
            "subcategory":"Auto Repair",
            "type":"Services"
        }
    ],
    "sg:phone":"+1 520 481 6576",
    "sg:postcode":"85705",
    "sg:province":"AZ",
    "sg:tags":[
        "wrecker"
    ],
    "wof:name":"D & D Enterprise Three",
    "wof:placetype":"venue"
},
  "geometry": {"coordinates":[-111.009703,32.287111],"type":"Point"}
}