{
  "type": "Feature",
  "properties": {
    "addr:full":"1104 S Milton Rd Flagstaff AZ 86001",
    "addr:housenumber":"1104",
    "addr:postcode":"86001",
    "addr:street":"S Milton Rd",
    "iso:country":"US",
    "sg:address":"1104 S Milton Rd",
    "sg:city":"Flagstaff",
    "sg:classifiers":[
        {
            "category":"Ice Cream",
            "type":"Food & Drink"
        }
    ],
    "sg:menulink":"http://www.allmenus.com/az/coconino/242967-baskin-robbins/menu/",
    "sg:phone":"+1 928 779 1012",
    "sg:postcode":"86001",
    "sg:province":"AZ",
    "sg:tags":[
        "american"
    ],
    "wof:name":"Baskin-Robbins",
    "wof:placetype":"venue"
},
  "geometry": {"coordinates":[-111.661421,35.185434],"type":"Point"}
}