{
  "type": "Feature",
  "properties": {
    "addr:full":"6859 E Rembrandt Ave # 120 Mesa AZ 85212",
    "addr:housenumber":"6859",
    "addr:postcode":"85212",
    "addr:street":"E Rembrandt Ave # 120",
    "iso:country":"US",
    "sg:address":"6859 E Rembrandt Ave # 120",
    "sg:city":"Mesa",
    "sg:classifiers":[
        {
            "category":"Professional",
            "subcategory":"Engineering",
            "type":"Services"
        }
    ],
    "sg:phone":"+1 480 988 7224",
    "sg:postcode":"85212",
    "sg:province":"AZ",
    "sg:tags":[
        "aeronautical",
        "engineer"
    ],
    "wof:name":"Volaeris Aviation Inc",
    "wof:placetype":"venue"
},
  "geometry": {"coordinates":[-111.591976,33.34029],"type":"Point"}
}