{
  "type": "Feature",
  "properties": {
    "addr:full":"3108 W Ravina Ln Anthem AZ 85086",
    "addr:housenumber":"3108",
    "addr:postcode":"85086",
    "addr:street":"W Ravina Ln",
    "iso:country":"US",
    "sg:address":"3108 W Ravina Ln",
    "sg:city":"Anthem",
    "sg:classifiers":[
        {
            "category":"Insurance",
            "subcategory":"Insurance Agent",
            "type":"Services"
        }
    ],
    "sg:phone":"+1 623 551 9620",
    "sg:postcode":"85086",
    "sg:province":"AZ",
    "wof:name":"Morgan & Morgan Insurance",
    "wof:placetype":"venue"
},
  "geometry": {"coordinates":[-112.127673,33.867757],"type":"Point"}
}