{
  "type": "Feature",
  "properties": {
    "iso:country":"US",
    "sg:address":"5544 E Thomas Rd",
    "sg:city":"Phoenix",
    "sg:classifiers":[
        {
            "category":"Shopping",
            "subcategory":"Pharmacy",
            "type":"Retail Goods"
        }
    ],
    "sg:phone":"+1 602 840 5920",
    "sg:postcode":"85018",
    "sg:province":"AZ",
    "wof:name":"Rays United Drug",
    "wof:placetype":"venue"
},
  "geometry": {"coordinates":[-111.963846,33.480111],"type":"Point"}
}