{
  "type": "Feature",
  "properties": {
    "iso:country":"US",
    "sg:address":"410 S Madison Dr",
    "sg:city":"Tempe",
    "sg:classifiers":[
        {
            "category":"Manufacturing",
            "subcategory":"Paper Products",
            "type":"Manufacturing & Wholesale Goods"
        },
        {
            "category":"Building & Trades",
            "subcategory":"Construction",
            "type":"Services"
        }
    ],
    "sg:phone":"+1 480 731 9899",
    "sg:postcode":"85281",
    "sg:province":"AZ",
    "sg:tags":[
        "acoustical",
        "decorated",
        "material",
        "wallboard",
        "mfg"
    ],
    "sg:website":"www.brejtfus.com",
    "wof:name":"Brejtfus Enterprises Inc",
    "wof:placetype":"venue"
},
  "geometry": {"coordinates":[-111.973425,33.425178],"type":"Point"}
}