{
  "type": "Feature",
  "properties": {
    "addr:full":"2414 E Inverness Ave Mesa AZ 85204",
    "addr:housenumber":"2414",
    "addr:postcode":"85204",
    "addr:street":"E Inverness Ave",
    "iso:country":"US",
    "sg:address":"2414 E Inverness Ave",
    "sg:city":"Mesa",
    "sg:classifiers":[
        {
            "category":"Professional",
            "type":"Services"
        }
    ],
    "sg:phone":"+1 480 539 1824",
    "sg:postcode":"85204",
    "sg:province":"AZ",
    "wof:name":"Area Films",
    "wof:placetype":"venue"
},
  "geometry": {"coordinates":[-111.77622100000001,33.382504],"type":"Point"}
}