{
  "type": "Feature",
  "properties": {
    "addr:full":"3420 E Shea Blvd Phoenix AZ 85028",
    "addr:housenumber":"3420",
    "addr:postcode":"85028",
    "addr:street":"E Shea Blvd",
    "iso:country":"US",
    "sg:address":"3420 E Shea Blvd",
    "sg:city":"Phoenix",
    "sg:classifiers":[
        {
            "category":"Shopping",
            "type":"Retail Goods"
        }
    ],
    "sg:phone":"+1 602 787 0100",
    "sg:postcode":"85028",
    "sg:province":"AZ",
    "sg:tags":[
        "cosmetic",
        "perfume"
    ],
    "wof:name":"Mac Cosmetics",
    "wof:placetype":"venue"
},
  "geometry": {"coordinates":[-112.005938,33.582659],"type":"Point"}
}