{
  "type": "Feature",
  "properties": {
    "addr:full":"1635 W University Dr # 130 Tempe AZ 85281",
    "addr:housenumber":"1635",
    "addr:postcode":"85281",
    "addr:street":"W University Dr # 130",
    "iso:country":"US",
    "sg:address":"1635 W University Dr # 130",
    "sg:city":"Tempe",
    "sg:classifiers":[
        {
            "category":"Professional",
            "subcategory":"Advertising",
            "type":"Services"
        }
    ],
    "sg:phone":"+1 480 946 5543",
    "sg:postcode":"85281",
    "sg:province":"AZ",
    "sg:tags":[
        "advertising-promotional",
        "product",
        "specialty"
    ],
    "sg:website":"http://www.diggslogo.com",
    "wof:name":"Diggs' Logo Products Inc",
    "wof:placetype":"venue"
},
  "geometry": {"coordinates":[-111.965233,33.42194],"type":"Point"}
}