{
  "type": "Feature",
  "properties": {
    "iso:country":"US",
    "sg:address":"4225 E University Dr # 16",
    "sg:city":"Mesa",
    "sg:classifiers":[
        {
            "category":"Professional",
            "subcategory":"Computer Services",
            "type":"Services"
        }
    ],
    "sg:phone":"+1 928 425 3700",
    "sg:postcode":"85205",
    "sg:province":"AZ",
    "sg:tags":[
        "technical",
        "assistance",
        "support"
    ],
    "wof:name":"911 Creative Sftwr Solutions",
    "wof:placetype":"venue"
},
  "geometry": {"coordinates":[-111.740051,33.422771],"type":"Point"}
}