{
  "type": "Feature",
  "properties": {
    "iso:country":"US",
    "sg:address":"2641 W Bountiful Ln",
    "sg:city":"Tucson",
    "sg:classifiers":[
        {
            "category":"Organizations",
            "subcategory":"Religious Organization",
            "type":"Services"
        }
    ],
    "sg:phone":"+1 520 797 9741",
    "sg:postcode":"85742",
    "sg:province":"AZ",
    "sg:tags":[
        "church"
    ],
    "wof:name":"Church - Jesus Christ - Lds",
    "wof:placetype":"venue"
},
  "geometry": {"coordinates":[-111.02510700000001,32.388934],"type":"Point"}
}