{
  "type": "Feature",
  "properties": {
    "iso:country":"US",
    "sg:address":"7801 E Wrightstown Rd",
    "sg:city":"Tucson",
    "sg:classifiers":[
        {
            "category":"Building & Trades",
            "subcategory":"Landscaping Services",
            "type":"Services"
        }
    ],
    "sg:phone":"+1 520 886 4632",
    "sg:postcode":"85715",
    "sg:province":"AZ",
    "wof:name":"Ocotillo Blue Inc",
    "wof:placetype":"venue"
},
  "geometry": {"coordinates":[-110.823753,32.250754],"type":"Point"}
}