{
  "type": "Feature",
  "properties": {
    "addr:full":"23740 W Dunlap Rd Buckeye AZ 85326",
    "addr:housenumber":"23740",
    "addr:postcode":"85326",
    "addr:street":"W Dunlap Rd",
    "iso:country":"US",
    "sg:address":"23740 W Dunlap Rd",
    "sg:city":"Buckeye",
    "sg:classifiers":[
        {
            "category":"Building & Trades",
            "subcategory":"Construction",
            "type":"Services"
        }
    ],
    "sg:phone":"+1 623 386 6363",
    "sg:postcode":"85326",
    "sg:province":"AZ",
    "sg:tags":[
        "excavation",
        "contractor"
    ],
    "wof:name":"P & L Enterprises",
    "wof:placetype":"venue"
},
  "geometry": {"coordinates":[-112.602131,33.414347],"type":"Point"}
}