{
  "type": "Feature",
  "properties": {
    "addr:full":"428 S Gilbert Rd Ste 115 Gilbert AZ 85296",
    "addr:housenumber":"428",
    "addr:postcode":"85296",
    "addr:street":"S Gilbert Rd Ste 115",
    "iso:country":"US",
    "sg:address":"428 S Gilbert Rd Ste 115",
    "sg:city":"Gilbert",
    "sg:classifiers":[
        {
            "category":"Professional",
            "subcategory":"Accounting & Tax Preparation",
            "type":"Services"
        }
    ],
    "sg:phone":"+1 480 507 2961",
    "sg:postcode":"85296",
    "sg:province":"AZ",
    "sg:tags":[
        "billing"
    ],
    "wof:name":"Preferred Billing Services",
    "wof:placetype":"venue"
},
  "geometry": {"coordinates":[-111.789727,33.341594],"type":"Point"}
}