{
  "type": "Feature",
  "properties": {
    "iso:country":"US",
    "sg:address":"55407 N Vulture Mine Rd",
    "sg:city":"Wickenburg",
    "sg:classifiers":[
        {
            "category":"Shopping",
            "subcategory":"Computers & Home Electronics",
            "type":"Retail Goods"
        }
    ],
    "sg:phone":"+1 928 684 5494",
    "sg:postcode":"85390",
    "sg:province":"AZ",
    "sg:tags":[
        "equipment",
        "electronic",
        "supply"
    ],
    "wof:name":"Arizona Electronic Homes Inc",
    "wof:placetype":"venue"
},
  "geometry": {"coordinates":[-112.771862,33.987981],"type":"Point"}
}