{
  "type": "Feature",
  "properties": {
    "addr:full":"371 E Greenway Rd Phoenix AZ 85042",
    "addr:housenumber":"371",
    "addr:postcode":"85042",
    "addr:street":"E Greenway Rd",
    "iso:country":"US",
    "sg:address":"371 E Greenway Rd",
    "sg:city":"Phoenix",
    "sg:classifiers":[
        {
            "category":"Building & Trades",
            "subcategory":"Construction",
            "type":"Services"
        }
    ],
    "sg:phone":"+1 602 485 7718",
    "sg:postcode":"85042",
    "sg:province":"AZ",
    "sg:tags":[
        "contractor"
    ],
    "wof:name":"Ramirez Roofing",
    "wof:placetype":"venue"
},
  "geometry": {"coordinates":[-112.069838,33.384013],"type":"Point"}
}