{
  "type": "Feature",
  "properties": {
    "iso:country":"US",
    "sg:address":"2030 W Baseline Rd",
    "sg:city":"Phoenix",
    "sg:classifiers":[
        {
            "category":"Real Estate",
            "subcategory":"Real Estate Services",
            "type":"Services"
        },
        {
            "category":"Real Estate",
            "subcategory":"Real Estate Agent",
            "type":"Services"
        }
    ],
    "sg:phone":"+1 602 232 2810",
    "sg:postcode":"85041",
    "sg:province":"AZ",
    "sg:tags":[
        "buyer",
        "broker"
    ],
    "wof:name":"Cortes Real Estate, Inc.",
    "wof:placetype":"venue"
},
  "geometry": {"coordinates":[-112.10253400000001,33.377762],"type":"Point"}
}