{
  "type": "Feature",
  "properties": {
    "iso:country":"US",
    "sg:address":"2370 Santa Monica Cv",
    "sg:city":"Kingman",
    "sg:classifiers":[
        {
            "category":"Building & Trades",
            "subcategory":"Electrical",
            "type":"Services"
        }
    ],
    "sg:phone":"+1 928 377 3057",
    "sg:postcode":"86409",
    "sg:province":"AZ",
    "sg:tags":[
        "electrician"
    ],
    "wof:name":"Matthew Bell",
    "wof:placetype":"venue"
},
  "geometry": {"coordinates":[-114.02258999999999,35.232957],"type":"Point"}
}