{
  "type": "Feature",
  "properties": {
    "iso:country":"US",
    "sg:address":"5157 N Shannon Rd",
    "sg:city":"Tucson",
    "sg:classifiers":[
        {
            "category":"Retail",
            "subcategory":"Repair Shop",
            "type":"Services"
        }
    ],
    "sg:phone":"+1 520 293 2726",
    "sg:postcode":"85705",
    "sg:province":"AZ",
    "sg:tags":[
        "clocks",
        "parts"
    ],
    "wof:name":"Howard's Clock Shop",
    "wof:placetype":"venue"
},
  "geometry": {"coordinates":[-111.02913,32.298634],"type":"Point"}
}