{
  "type": "Feature",
  "properties": {
    "iso:country":"US",
    "sg:address":"1950 W Indian School Rd",
    "sg:city":"Phoenix",
    "sg:classifiers":[
        {
            "category":"Restaurant",
            "type":"Food & Drink"
        }
    ],
    "sg:menulink":"http://www.allmenus.com/az/phoenix/128984-subway/menu/",
    "sg:phone":"+1 602 650 1700",
    "sg:postcode":"85015",
    "sg:province":"AZ",
    "sg:tags":[
        "american",
        "sandwich"
    ],
    "wof:name":"Subway",
    "wof:placetype":"venue"
},
  "geometry": {"coordinates":[-112.100657,33.496102],"type":"Point"}
}