{
  "type": "Feature",
  "properties": {
    "iso:country":"US",
    "sg:address":"8 E Cottonwood St",
    "sg:city":"Cottonwood",
    "sg:classifiers":[
        {
            "category":"Health Services",
            "subcategory":"Hospital",
            "type":"Services"
        }
    ],
    "sg:phone":"+1 928 634 2236",
    "sg:postcode":"86326",
    "sg:province":"AZ",
    "sg:tags":[
        "mental"
    ],
    "sg:website":"www.verdevalleyguidanceclinic.com",
    "wof:name":"Verde Valley Guidance Clinic",
    "wof:placetype":"venue"
},
  "geometry": {"coordinates":[-112.027813,34.728728],"type":"Point"}
}