{
  "type": "Feature",
  "properties": {
    "iso:country":"US",
    "sg:address":"5245 S Kyrene Rd",
    "sg:city":"Tempe",
    "sg:classifiers":[
        {
            "category":"Retail",
            "subcategory":"Repair Shop",
            "type":"Services"
        },
        {
            "category":"Manufacturing",
            "subcategory":"Motor Vehicles & Parts",
            "type":"Manufacturing & Wholesale Goods"
        }
    ],
    "sg:phone":"+1 480 730 9444",
    "sg:postcode":"85283",
    "sg:province":"AZ",
    "sg:tags":[
        "scooter",
        "motorcycle",
        "mfg"
    ],
    "wof:name":"American Rat Racing Inc",
    "wof:placetype":"venue"
},
  "geometry": {"coordinates":[-111.945902,33.377068],"type":"Point"}
}