{
  "type": "Feature",
  "properties": {
    "addr:full":"5066 W Olive Ave Glendale AZ 85302",
    "addr:housenumber":"5066",
    "addr:postcode":"85302",
    "addr:street":"W Olive Ave",
    "iso:country":"US",
    "sg:address":"5066 W Olive Ave",
    "sg:city":"Glendale",
    "sg:classifiers":[
        {
            "category":"Restaurant",
            "type":"Food & Drink"
        }
    ],
    "sg:menulink":"http://www.allmenus.com/az/phoenix/152197-honeybaked-ham/menu/",
    "sg:phone":"+1 623 245 0000",
    "sg:postcode":"85302",
    "sg:province":"AZ",
    "sg:tags":[
        "american"
    ],
    "wof:name":"The HoneyBaked Ham Company",
    "wof:placetype":"venue"
},
  "geometry": {"coordinates":[-112.168021,33.567475],"type":"Point"}
}