{
  "type": "Feature",
  "properties": {
    "iso:country":"US",
    "sg:address":"4630 E Frye Rd",
    "sg:city":"Phoenix",
    "sg:classifiers":[
        {
            "category":"Education",
            "subcategory":"School",
            "type":"Public Place"
        }
    ],
    "sg:phone":"+1 480 783 3400",
    "sg:postcode":"85048",
    "sg:province":"AZ",
    "sg:website":"www.kyrene.org",
    "wof:name":"Kyrene Del Milenio Elementary",
    "wof:placetype":"venue"
},
  "geometry": {"coordinates":[-111.982488,33.298073],"type":"Point"}
}