{
  "type": "Feature",
  "properties": {
    "iso:country":"US",
    "sg:address":"1300 S Litchfield Rd Ste 16",
    "sg:city":"Goodyear",
    "sg:classifiers":[
        {
            "category":"Manufacturing",
            "subcategory":"Buildings",
            "type":"Manufacturing & Wholesale Goods"
        },
        {
            "category":"Structure",
            "subcategory":"Warehouse",
            "type":"Public Place"
        },
        {
            "category":"Building & Trades",
            "subcategory":"Construction",
            "type":"Services"
        }
    ],
    "sg:phone":"+1 602 330 1699",
    "sg:postcode":"85338",
    "sg:province":"AZ",
    "sg:tags":[
        "home",
        "builder",
        "warehouses-merchandise",
        "warehouses-public-commercial",
        "contractor"
    ],
    "wof:name":"Design Builders West",
    "wof:placetype":"venue"
},
  "geometry": {"coordinates":[-112.358282,33.433333],"type":"Point"}
}