{
  "type": "Feature",
  "properties": {
    "addr:full":"5055 W Ray Rd Suite 21,21 Chandler AZ 85226",
    "addr:housenumber":"5055",
    "addr:postcode":"85226",
    "addr:street":"W Ray Rd Suite 21,21",
    "iso:country":"US",
    "sg:address":"5055 W Ray Rd Suite 21,21",
    "sg:city":"Chandler",
    "sg:classifiers":[
        {
            "category":"Health Services",
            "subcategory":"Clinic",
            "type":"Services"
        },
        {
            "category":"Health Services",
            "subcategory":"Health Practitioner",
            "type":"Services"
        },
        {
            "category":"Health Services",
            "subcategory":"Chiropractor",
            "type":"Services"
        }
    ],
    "sg:phone":"+1 480 717 4758",
    "sg:postcode":"85226",
    "sg:province":"AZ",
    "sg:tags":[
        "information",
        "referral",
        "chiropractic",
        "sport",
        "therapist",
        "therapy",
        "treatment",
        "medicine",
        "injury",
        "physical"
    ],
    "sg:website":"http://www.yext.com/p/superpages/cottingham-chiropractic-chandler-arizona.html",
    "wof:name":"Cottingham Chiropractic",
    "wof:placetype":"venue"
},
  "geometry": {"coordinates":[-111.929378,33.31992],"type":"Point"}
}