{
  "type": "Feature",
  "properties": {
    "iso:country":"US",
    "sg:address":"9928 W Bell Rd",
    "sg:city":"Sun City",
    "sg:classifiers":[
        {
            "category":"Banks & Credit Unions",
            "subcategory":"Bank",
            "type":"Services"
        }
    ],
    "sg:phone":"+1 623 876 5946",
    "sg:postcode":"85351",
    "sg:province":"AZ",
    "sg:tags":[
        "state",
        "commercial"
    ],
    "wof:name":"Wells Fargo",
    "wof:placetype":"venue"
},
  "geometry": {"coordinates":[-112.27763899999999,33.638234],"type":"Point"}
}