{
  "type": "Feature",
  "properties": {
    "iso:country":"US",
    "sg:address":"1305 N Frances St",
    "sg:city":"Tempe",
    "sg:classifiers":[
        {
            "category":"Building & Trades",
            "subcategory":"Construction",
            "type":"Services"
        }
    ],
    "sg:phone":"+1 480 731 9516",
    "sg:postcode":"85281",
    "sg:province":"AZ",
    "sg:tags":[
        "floor",
        "laying",
        "contractor"
    ],
    "wof:name":"Auggie Flooring",
    "wof:placetype":"venue"
},
  "geometry": {"coordinates":[-111.92314,33.44265],"type":"Point"}
}