{
  "type": "Feature",
  "properties": {
    "iso:country":"US",
    "sg:address":"449 N 96th Pl",
    "sg:city":"Mesa",
    "sg:classifiers":[
        {
            "category":"Manufacturing",
            "subcategory":"Printing",
            "type":"Manufacturing & Wholesale Goods"
        }
    ],
    "sg:phone":"+1 480 610 1910",
    "sg:postcode":"85207",
    "sg:province":"AZ",
    "sg:tags":[
        "screen"
    ],
    "wof:name":"Gecko Graphics",
    "wof:placetype":"venue"
},
  "geometry": {"coordinates":[-111.62280800000001,33.423361],"type":"Point"}
}