{
  "type": "Feature",
  "properties": {
    "iso:country":"US",
    "sg:address":"3917 E Pima St",
    "sg:city":"Tucson",
    "sg:classifiers":[
        {
            "category":"Health Services",
            "subcategory":"Chiropractor",
            "type":"Services"
        }
    ],
    "sg:phone":"+1 520 318 9841",
    "sg:postcode":"85712",
    "sg:province":"AZ",
    "wof:name":"Allen Chiropractic Ctr",
    "wof:placetype":"venue"
},
  "geometry": {"coordinates":[-110.907883,32.243532],"type":"Point"}
}