{
  "type": "Feature",
  "properties": {
    "iso:country":"US",
    "sg:address":"2618 W 1st St Ste 18",
    "sg:city":"Tempe",
    "sg:classifiers":[
        {
            "category":"Building & Trades",
            "subcategory":"Construction",
            "type":"Services"
        }
    ],
    "sg:phone":"+1 480 829 6900",
    "sg:postcode":"85281",
    "sg:province":"AZ",
    "sg:tags":[
        "asbestos",
        "detection",
        "removal",
        "contractor"
    ],
    "sg:website":"http://horizoncontracting.net",
    "wof:name":"Horizon Contracting",
    "wof:placetype":"venue"
},
  "geometry": {"coordinates":[-111.969566,33.424564],"type":"Point"}
}