{
  "type": "Feature",
  "properties": {
    "iso:country":"US",
    "sg:address":"185 N Apache Trl",
    "sg:city":"Apache Junction",
    "sg:classifiers":[
        {
            "category":"Real Estate",
            "subcategory":"Real Estate Agent",
            "type":"Services"
        }
    ],
    "sg:phone":"+1 480 982 7720",
    "sg:postcode":"85220",
    "sg:province":"AZ",
    "wof:name":"Arizona 1 Group Home Life Real",
    "wof:placetype":"venue"
},
  "geometry": {"coordinates":[-111.549042,33.415915],"type":"Point"}
}