{
  "type": "Feature",
  "properties": {
    "iso:country":"US",
    "sg:address":"5465 N Cumberland Dr",
    "sg:city":"Tucson",
    "sg:classifiers":[
        {
            "category":"Recreation",
            "type":"Entertainment"
        }
    ],
    "sg:phone":"+1 520 887 4156",
    "sg:postcode":"85704",
    "sg:province":"AZ",
    "sg:tags":[
        "camps-recreational"
    ],
    "wof:name":"Tom E Camp Jr",
    "wof:placetype":"venue"
},
  "geometry": {"coordinates":[-111.002001,32.306425],"type":"Point"}
}