{
  "type": "Feature",
  "properties": {
    "iso:country":"US",
    "sg:address":"9332 N 95th Way",
    "sg:city":"Scottsdale",
    "sg:classifiers":[
        {
            "category":"Real Estate",
            "subcategory":"Real Estate Agent",
            "type":"Services"
        }
    ],
    "sg:phone":"+1 480 391 1845",
    "sg:postcode":"85258",
    "sg:province":"AZ",
    "wof:name":"Advisory Equus Realty",
    "wof:placetype":"venue"
},
  "geometry": {"coordinates":[-111.875169,33.569412],"type":"Point"}
}