{
  "type": "Feature",
  "properties": {
    "iso:country":"US",
    "sg:address":"7677 N 16th St",
    "sg:city":"Phoenix",
    "sg:classifiers":[
        {
            "category":"Restaurant",
            "type":"Food & Drink"
        },
        {
            "category":"Retail",
            "subcategory":"Event Space",
            "type":"Services"
        }
    ],
    "sg:phone":"+1 877 753 7302",
    "sg:postcode":"85020",
    "sg:province":"AZ",
    "sg:tags":[
        "banquet",
        "hall",
        "reception",
        "facility"
    ],
    "wof:name":"Pointe Hilton Squaw Peak Resort",
    "wof:placetype":"venue"
},
  "geometry": {"coordinates":[-112.047793,33.548331],"type":"Point"}
}