{
  "type": "Feature",
  "properties": {
    "addr:full":"1450 S 27th Ave Phoenix AZ 85009",
    "addr:housenumber":"1450",
    "addr:postcode":"85009",
    "addr:street":"S 27Th Ave",
    "iso:country":"US",
    "sg:address":"1450 S 27th Ave",
    "sg:city":"Phoenix",
    "sg:classifiers":[
        {
            "category":"Organizations",
            "subcategory":"Labor Organization",
            "type":"Services"
        }
    ],
    "sg:phone":"+1 602 352 0401",
    "sg:postcode":"85009",
    "sg:province":"AZ",
    "wof:name":"Phoenix Mailers",
    "wof:placetype":"venue"
},
  "geometry": {"coordinates":[-112.117318,33.434958],"type":"Point"}
}