{
  "type": "Feature",
  "properties": {
    "addr:full":"686 N Western Ave Nogales AZ 85621",
    "addr:housenumber":"686",
    "addr:postcode":"85621",
    "addr:street":"N Western Ave",
    "iso:country":"US",
    "sg:address":"686 N Western Ave",
    "sg:city":"Nogales",
    "sg:classifiers":[
        {
            "category":"Social Services",
            "subcategory":"Child Care",
            "type":"Services"
        }
    ],
    "sg:phone":"+1 520 287 3662",
    "sg:postcode":"85621",
    "sg:province":"AZ",
    "wof:name":"Western Head Start",
    "wof:placetype":"venue"
},
  "geometry": {"coordinates":[-110.946212,31.345511],"type":"Point"}
}