{
  "type": "Feature",
  "properties": {
    "iso:country":"US",
    "sg:address":"3888 Mark Twain Dr",
    "sg:city":"Pinetop",
    "sg:classifiers":[
        {
            "category":"Shopping",
            "subcategory":"Hobbies, Toys, & Games",
            "type":"Retail Goods"
        }
    ],
    "sg:phone":"+1 928 369 4207",
    "sg:postcode":"85935",
    "sg:province":"AZ",
    "wof:name":"Roses Everlasting",
    "wof:placetype":"venue"
},
  "geometry": {"coordinates":[-109.893555,34.105016],"type":"Point"}
}