{
  "type": "Feature",
  "properties": {
    "addr:full":"1761 E McNair Dr Tempe AZ 85283",
    "addr:housenumber":"1761",
    "addr:postcode":"85283",
    "addr:street":"E Mcnair Dr",
    "iso:country":"US",
    "sg:address":"1761 E McNair Dr",
    "sg:city":"Tempe",
    "sg:classifiers":[
        {
            "category":"Professional",
            "subcategory":"Lawyer & Legal Services",
            "type":"Services"
        }
    ],
    "sg:phone":"+1 480 345 3323",
    "sg:postcode":"85283",
    "sg:province":"AZ",
    "wof:name":"Huang Joy Atty",
    "wof:placetype":"venue"
},
  "geometry": {"coordinates":[-111.912003,33.351601],"type":"Point"}
}