{
  "type": "Feature",
  "properties": {
    "iso:country":"US",
    "sg:address":"4970 S Alma School Rd",
    "sg:city":"Chandler",
    "sg:classifiers":[
        {
            "category":"Ice Cream",
            "type":"Food & Drink"
        }
    ],
    "sg:phone":"+1 480 802 2731",
    "sg:postcode":"85248",
    "sg:province":"AZ",
    "sg:tags":[
        "frozen",
        "yogurt"
    ],
    "wof:name":"Baskin Robbins",
    "wof:placetype":"venue"
},
  "geometry": {"coordinates":[-111.859905,33.233662],"type":"Point"}
}