{
  "type": "Feature",
  "properties": {
    "addr:full":"2802 E Meadowbrook Ave Phoenix AZ 85016",
    "addr:housenumber":"2802",
    "addr:postcode":"85016",
    "addr:street":"E Meadowbrook Ave",
    "iso:country":"US",
    "sg:address":"2802 E Meadowbrook Ave",
    "sg:city":"Phoenix",
    "sg:classifiers":[
        {
            "category":"Social Services",
            "subcategory":"Child Care",
            "type":"Services"
        }
    ],
    "sg:phone":"+1 602 381 8037",
    "sg:postcode":"85016",
    "sg:province":"AZ",
    "sg:tags":[
        "nursery",
        "day"
    ],
    "wof:name":"Villa Montessori Elem School",
    "wof:placetype":"venue"
},
  "geometry": {"coordinates":[-112.02136900000001,33.504157],"type":"Point"}
}