{
  "type": "Feature",
  "properties": {
    "iso:country":"US",
    "sg:address":"1345 E Hubbell St",
    "sg:city":"Phoenix",
    "sg:classifiers":[
        {
            "category":"Professional",
            "subcategory":"Art Services",
            "type":"Services"
        }
    ],
    "sg:phone":"+1 602 349 6866",
    "sg:postcode":"85006",
    "sg:province":"AZ",
    "sg:tags":[
        "designer",
        "display",
        "producer"
    ],
    "sg:website":"http://www.orb-design.com",
    "wof:name":"Orb Analysis For Design",
    "wof:placetype":"venue"
},
  "geometry": {"coordinates":[-112.053226,33.470322],"type":"Point"}
}