{
  "type": "Feature",
  "properties": {
    "addr:full":"496 W 2nd St Tucson AZ 85705",
    "addr:housenumber":"496",
    "addr:postcode":"85705",
    "addr:street":"W 2Nd St",
    "iso:country":"US",
    "sg:address":"496 W 2nd St",
    "sg:city":"Tucson",
    "sg:classifiers":[
        {
            "category":"Building & Trades",
            "subcategory":"Construction",
            "type":"Services"
        }
    ],
    "sg:phone":"+1 520 628 7742",
    "sg:postcode":"85705",
    "sg:province":"AZ",
    "sg:tags":[
        "contractor"
    ],
    "wof:name":"Arizona Metal Craft",
    "wof:placetype":"venue"
},
  "geometry": {"coordinates":[-110.977987,32.232962],"type":"Point"}
}