{
  "type": "Feature",
  "properties": {
    "iso:country":"US",
    "sg:address":"2836 N 27th Ave",
    "sg:city":"Phoenix",
    "sg:classifiers":[
        {
            "category":"Food & Beverages",
            "subcategory":"Groceries & Convenience Stores",
            "type":"Retail Goods"
        }
    ],
    "sg:phone":"+1 602 233 3355",
    "sg:postcode":"85009",
    "sg:province":"AZ",
    "sg:website":"http://www.quiktrip.com",
    "wof:name":"Quiktrip",
    "wof:placetype":"venue"
},
  "geometry": {"coordinates":[-112.117069,33.479378],"type":"Point"}
}