{
  "type": "Feature",
  "properties": {
    "addr:full":"4432 N 19th Ave Phoenix AZ 85015",
    "addr:housenumber":"4432",
    "addr:postcode":"85015",
    "addr:street":"N 19Th Ave",
    "iso:country":"US",
    "sg:address":"4432 N 19th Ave",
    "sg:city":"Phoenix",
    "sg:classifiers":[
        {
            "category":"Restaurant",
            "type":"Food & Drink"
        }
    ],
    "sg:phone":"+1 602 241 0527",
    "sg:postcode":"85015",
    "sg:province":"AZ",
    "wof:name":"Lavecchia Pizzeria",
    "wof:placetype":"venue"
},
  "geometry": {"coordinates":[-112.09996599999999,33.50214],"type":"Point"}
}