{
  "type": "Feature",
  "properties": {
    "addr:full":"7252 E Melrose St Mesa AZ 85207",
    "addr:housenumber":"7252",
    "addr:postcode":"85207",
    "addr:street":"E Melrose St",
    "iso:country":"US",
    "sg:address":"7252 E Melrose St",
    "sg:city":"Mesa",
    "sg:classifiers":[
        {
            "category":"Shopping",
            "subcategory":"Clothing, Apparel, & Fashions",
            "type":"Retail Goods"
        }
    ],
    "sg:phone":"+1 480 358 1360",
    "sg:postcode":"85207",
    "sg:province":"AZ",
    "sg:tags":[
        "dancing",
        "supply"
    ],
    "sg:website":"www.balletcostume.com",
    "wof:name":"BALLETCOSTUME.COM",
    "wof:placetype":"venue"
},
  "geometry": {"coordinates":[-111.67408,33.462048],"type":"Point"}
}