{
  "type": "Feature",
  "properties": {
    "iso:country":"US",
    "sg:address":"385 N Broad St",
    "sg:city":"Globe",
    "sg:classifiers":[
        {
            "category":"Professional",
            "subcategory":"Accounting & Tax Preparation",
            "type":"Services"
        }
    ],
    "sg:phone":"+1 928 425 2146",
    "sg:postcode":"85502",
    "sg:province":"AZ",
    "sg:tags":[
        "return",
        "filing"
    ],
    "wof:name":"Jackson Hewitt Tax Svc",
    "wof:placetype":"venue"
},
  "geometry": {"coordinates":[-110.78904799999999,33.399662],"type":"Point"}
}