{
  "type": "Feature",
  "properties": {
    "iso:country":"US",
    "sg:address":"7316 E Vernon Ave",
    "sg:city":"Scottsdale",
    "sg:classifiers":[
        {
            "category":"Shopping",
            "subcategory":"Bicycles & Sporting Goods",
            "type":"Retail Goods"
        }
    ],
    "sg:phone":"+1 480 946 9509",
    "sg:postcode":"85257",
    "sg:province":"AZ",
    "wof:name":"Disc Golf Unlimited",
    "wof:placetype":"venue"
},
  "geometry": {"coordinates":[-111.92340900000001,33.473877],"type":"Point"}
}