{
  "type": "Feature",
  "properties": {
    "iso:country":"US",
    "sg:address":"4800 S Alma School Rd",
    "sg:city":"Chandler",
    "sg:classifiers":[
        {
            "category":"Professional",
            "type":"Services"
        }
    ],
    "sg:phone":"+1 480 895 8155",
    "sg:postcode":"85248",
    "sg:province":"AZ",
    "wof:name":"Albert Schwartz",
    "wof:placetype":"venue"
},
  "geometry": {"coordinates":[-111.862351,33.237787],"type":"Point"}
}