{
  "type": "Feature",
  "properties": {
    "addr:full":"2180 N Wilmot Rd Tucson AZ 85712",
    "addr:housenumber":"2180",
    "addr:postcode":"85712",
    "addr:street":"N Wilmot Rd",
    "iso:country":"US",
    "sg:address":"2180 N Wilmot Rd",
    "sg:city":"Tucson",
    "sg:classifiers":[
        {
            "category":"Building & Trades",
            "subcategory":"Construction",
            "type":"Services"
        }
    ],
    "sg:phone":"+1 520 884 9821",
    "sg:postcode":"85712",
    "sg:province":"AZ",
    "sg:tags":[
        "general",
        "contractor"
    ],
    "sg:website":"www.lloydconstruction.com",
    "wof:name":"Lloyd Construction Co Inc",
    "wof:placetype":"venue"
},
  "geometry": {"coordinates":[-110.857855,32.249687],"type":"Point"}
}