{
  "type": "Feature",
  "properties": {
    "addr:full":"4195 S Contractors Way Tucson AZ 85714",
    "addr:housenumber":"4195",
    "addr:postcode":"85714",
    "addr:street":"S Contractors Way",
    "iso:country":"US",
    "sg:address":"4195 S Contractors Way",
    "sg:city":"Tucson",
    "sg:classifiers":[
        {
            "category":"Retail",
            "subcategory":"Auto Repair",
            "type":"Services"
        }
    ],
    "sg:phone":"+1 520 750 8008",
    "sg:postcode":"85714",
    "sg:province":"AZ",
    "sg:tags":[
        "body",
        "automobile",
        "painting"
    ],
    "wof:name":"All Auto Body & Frame Repair",
    "wof:placetype":"venue"
},
  "geometry": {"coordinates":[-110.908141,32.175257],"type":"Point"}
}