{
  "type": "Feature",
  "properties": {
    "iso:country":"US",
    "sg:address":"1308 E Commodore Pl",
    "sg:city":"Tempe",
    "sg:classifiers":[
        {
            "category":"Home & Garden",
            "subcategory":"Home Furnishings",
            "type":"Retail Goods"
        },
        {
            "category":"Professional",
            "subcategory":"Business Services",
            "type":"Services"
        },
        {
            "category":"Real Estate",
            "subcategory":"Architect",
            "type":"Services"
        }
    ],
    "sg:phone":"+1 480 839 8131",
    "sg:postcode":"85283",
    "sg:province":"AZ",
    "sg:tags":[
        "designer",
        "residential",
        "drafting",
        "planning",
        "design"
    ],
    "sg:website":"www.daltondesigns.com",
    "wof:name":"Dalton Designs Inc",
    "wof:placetype":"venue"
},
  "geometry": {"coordinates":[-111.917999,33.374901],"type":"Point"}
}