{
  "type": "Feature",
  "properties": {
    "addr:full":"2345 W Glendale Ave Phoenix AZ 85021",
    "addr:housenumber":"2345",
    "addr:postcode":"85021",
    "addr:street":"W Glendale Ave",
    "iso:country":"US",
    "sg:address":"2345 W Glendale Ave",
    "sg:city":"Phoenix",
    "sg:classifiers":[
        {
            "category":"Health Services",
            "subcategory":"Clinic",
            "type":"Services"
        }
    ],
    "sg:phone":"+1 602 279 0008",
    "sg:postcode":"85021",
    "sg:province":"AZ",
    "sg:tags":[
        "aids",
        "testing",
        "information"
    ],
    "sg:website":"www.shantiaz.org",
    "wof:name":"Phoenix Shanti Group Inc",
    "wof:placetype":"venue"
},
  "geometry": {"coordinates":[-112.110696,33.538548],"type":"Point"}
}