{
  "type": "Feature",
  "properties": {
    "iso:country":"US",
    "sg:address":"6941 E Meseto Ave",
    "sg:city":"Mesa",
    "sg:classifiers":[
        {
            "category":"Wholesale",
            "subcategory":"Machinery & Supplies",
            "type":"Manufacturing & Wholesale Goods"
        }
    ],
    "sg:phone":"+1 480 774 0038",
    "sg:postcode":"85209",
    "sg:province":"AZ",
    "sg:tags":[
        "car"
    ],
    "wof:name":"Tech Products",
    "wof:placetype":"venue"
},
  "geometry": {"coordinates":[-111.685046,33.371203],"type":"Point"}
}