{
  "type": "Feature",
  "properties": {
    "addr:full":"4244 W Brown St Phoenix AZ 85051",
    "addr:housenumber":"4244",
    "addr:postcode":"85051",
    "addr:street":"W Brown St",
    "iso:country":"US",
    "sg:address":"4244 W Brown St",
    "sg:city":"Phoenix",
    "sg:classifiers":[
        {
            "category":"Social Services",
            "type":"Services"
        }
    ],
    "sg:phone":"+1 623 939 8272",
    "sg:postcode":"85051",
    "sg:province":"AZ",
    "sg:tags":[
        "counselor",
        "marriage",
        "family"
    ],
    "wof:name":"Family Support Resources",
    "wof:placetype":"venue"
},
  "geometry": {"coordinates":[-112.15110199999999,33.577152],"type":"Point"}
}