{
  "type": "Feature",
  "properties": {
    "iso:country":"US",
    "sg:address":"5150 N 16th St",
    "sg:city":"Phoenix",
    "sg:classifiers":[
        {
            "category":"Banks & Credit Unions",
            "subcategory":"Bank",
            "type":"Services"
        }
    ],
    "sg:phone":"+1 602 285 1111",
    "sg:postcode":"85016",
    "sg:province":"AZ",
    "sg:tags":[
        "loan",
        "real estate"
    ],
    "wof:name":"Major Mortgage LTD",
    "wof:placetype":"venue"
},
  "geometry": {"coordinates":[-112.047595,33.511928],"type":"Point"}
}