{
  "type": "Feature",
  "properties": {
    "iso:country":"US",
    "sg:address":"3816 E Astro St",
    "sg:city":"Hereford",
    "sg:classifiers":[
        {
            "category":"Organizations",
            "subcategory":"Professional Association",
            "type":"Services"
        }
    ],
    "sg:phone":"+1 520 803 1078",
    "sg:postcode":"85615",
    "sg:province":"AZ",
    "wof:name":"Huachuca Art Assn Gallery",
    "wof:placetype":"venue"
},
  "geometry": {"coordinates":[-110.259772,31.456296],"type":"Point"}
}