{
  "type": "Feature",
  "properties": {
    "iso:country":"US",
    "sg:address":"1095 E Indian School Rd",
    "sg:city":"Phoenix",
    "sg:classifiers":[
        {
            "category":"Home & Garden",
            "subcategory":"Home Furnishings",
            "type":"Retail Goods"
        }
    ],
    "sg:phone":"+1 602 242 5667",
    "sg:postcode":"85014",
    "sg:province":"AZ",
    "sg:tags":[
        "housewares"
    ],
    "wof:name":"Royal Prestige Az",
    "wof:placetype":"venue"
},
  "geometry": {"coordinates":[-112.059424,33.49466],"type":"Point"}
}