{
  "type": "Feature",
  "properties": {
    "iso:country":"US",
    "sg:address":"8392 W Thunderbird Rd",
    "sg:city":"Peoria",
    "sg:classifiers":[
        {
            "category":"Health Services",
            "subcategory":"Dentist",
            "type":"Services"
        }
    ],
    "sg:phone":"+1 877 699 3732",
    "sg:postcode":"85381",
    "sg:province":"AZ",
    "sg:tags":[
        "dentists-pediatric",
        "dentistry"
    ],
    "sg:website":"http://www-westerndental-com.netsolads.com/?_nsag=34847",
    "wof:name":"Western Dental Centers",
    "wof:placetype":"venue"
},
  "geometry": {"coordinates":[-112.239671,33.60993],"type":"Point"}
}