{
  "type": "Feature",
  "properties": {
    "iso:country":"US",
    "sg:address":"4500 S Lakeshore Drive",
    "sg:city":"Tempe",
    "sg:classifiers":[
        {
            "category":"Building & Trades",
            "subcategory":"Construction",
            "type":"Services"
        }
    ],
    "sg:phone":"+1 480 838 0369",
    "sg:postcode":"85282",
    "sg:province":"AZ",
    "sg:tags":[
        "contractor"
    ],
    "sg:website":"www.curtisbuilders.com",
    "wof:name":"Curtis Builders",
    "wof:placetype":"venue"
},
  "geometry": {"coordinates":[-111.92637,33.382073],"type":"Point"}
}