{
  "type": "Feature",
  "properties": {
    "addr:full":"9393 N 90th St Scottsdale AZ 85258",
    "addr:housenumber":"9393",
    "addr:postcode":"85258",
    "addr:street":"N 90Th St",
    "iso:country":"US",
    "sg:address":"9393 N 90th St",
    "sg:city":"Scottsdale",
    "sg:classifiers":[
        {
            "category":"Shopping",
            "type":"Retail Goods"
        }
    ],
    "sg:phone":"+1 480 227 6822",
    "sg:postcode":"85258",
    "sg:province":"AZ",
    "sg:tags":[
        "item",
        "boutique"
    ],
    "wof:name":"Get Dressed",
    "wof:placetype":"venue"
},
  "geometry": {"coordinates":[-111.88700300000001,33.571149],"type":"Point"}
}