{
  "type": "Feature",
  "properties": {
    "addr:full":"140 N Litchfield Rd Goodyear AZ 85338",
    "addr:housenumber":"140",
    "addr:postcode":"85338",
    "addr:street":"N Litchfield Rd",
    "iso:country":"US",
    "sg:address":"140 N Litchfield Rd",
    "sg:city":"Goodyear",
    "sg:classifiers":[
        {
            "category":"Social Services",
            "type":"Services"
        }
    ],
    "sg:phone":"+1 623 932 5111",
    "sg:postcode":"85338",
    "sg:province":"AZ",
    "sg:tags":[
        "information",
        "planning",
        "center",
        "family"
    ],
    "sg:website":"www.plannedparenthood.org",
    "wof:name":"Planned Parenthood",
    "wof:placetype":"venue"
},
  "geometry": {"coordinates":[-112.35833100000001,33.435593],"type":"Point"}
}