{
  "type": "Feature",
  "properties": {
    "iso:country":"US",
    "sg:address":"11459 N 28th Dr",
    "sg:city":"Phoenix",
    "sg:classifiers":[
        {
            "category":"Real Estate",
            "subcategory":"Real Estate Operator",
            "type":"Services"
        }
    ],
    "sg:phone":"+1 602 993 2390",
    "sg:postcode":"85029",
    "sg:province":"AZ",
    "sg:tags":[
        "building",
        "apartment"
    ],
    "wof:name":"Portofino At The Lake",
    "wof:placetype":"venue"
},
  "geometry": {"coordinates":[-112.119955,33.589729],"type":"Point"}
}