{
  "type": "Feature",
  "properties": {
    "iso:country":"US",
    "sg:address":"10614 N 43rd Ave",
    "sg:city":"Glendale",
    "sg:phone":"+1 602 439 2337",
    "sg:postcode":"85304",
    "sg:province":"AZ",
    "sg:website":"http://www.dennys.com",
    "wof:name":"Denny's",
    "wof:placetype":"venue"
},
  "geometry": {"coordinates":[-112.151539,33.582096],"type":"Point"}
}