{
  "type": "Feature",
  "properties": {
    "addr:full":"7020 E Monte Vista Rd Scottsdale AZ 85257",
    "addr:housenumber":"7020",
    "addr:postcode":"85257",
    "addr:street":"E Monte Vista Rd",
    "iso:country":"US",
    "sg:address":"7020 E Monte Vista Rd",
    "sg:city":"Scottsdale",
    "sg:classifiers":[
        {
            "category":"Building & Trades",
            "subcategory":"Construction",
            "type":"Services"
        }
    ],
    "sg:phone":"+1 480 970 0465",
    "sg:postcode":"85257",
    "sg:province":"AZ",
    "sg:tags":[
        "house"
    ],
    "wof:name":"T Squared Inc",
    "wof:placetype":"venue"
},
  "geometry": {"coordinates":[-111.929282,33.471606],"type":"Point"}
}