{
  "type": "Feature",
  "properties": {
    "addr:full":"9229 N 4th St Phoenix AZ 85020",
    "addr:housenumber":"9229",
    "addr:postcode":"85020",
    "addr:street":"N 4Th St",
    "iso:country":"US",
    "sg:address":"9229 N 4th St",
    "sg:city":"Phoenix",
    "sg:classifiers":[
        {
            "category":"Health Services",
            "subcategory":"Doctor",
            "type":"Services"
        },
        {
            "category":"Social Services",
            "subcategory":"Job Training",
            "type":"Services"
        },
        {
            "category":"Social Services",
            "subcategory":"Retirement Home",
            "type":"Services"
        }
    ],
    "sg:phone":"+1 602 870 6060",
    "sg:postcode":"85020",
    "sg:province":"AZ",
    "sg:tags":[
        "living",
        "nursing",
        "homes-skilled",
        "physician",
        "assisted",
        "facility",
        "surgeon"
    ],
    "sg:website":"http://www.desertmissionanglican.org",
    "wof:name":"Desert Mission Food Bank",
    "wof:placetype":"venue"
},
  "geometry": {"coordinates":[-112.068439,33.57014],"type":"Point"}
}