{
  "type": "Feature",
  "properties": {
    "iso:country":"US",
    "sg:address":"2475 N Elliott Rd",
    "sg:city":"Ajo",
    "sg:classifiers":[
        {
            "category":"Professional",
            "type":"Services"
        }
    ],
    "sg:phone":"+1 520 387 7661",
    "sg:postcode":"85321",
    "sg:province":"AZ",
    "wof:name":"Don Ebann",
    "wof:placetype":"venue"
},
  "geometry": {"coordinates":[-112.875917,32.401913],"type":"Point"}
}