{
  "type": "Feature",
  "properties": {
    "iso:country":"US",
    "sg:address":"628 W Bentrup St",
    "sg:city":"Chandler",
    "sg:classifiers":[
        {
            "category":"Building & Trades",
            "subcategory":"Construction",
            "type":"Services"
        }
    ],
    "sg:phone":"+1 480 831 2112",
    "sg:postcode":"85225",
    "sg:province":"AZ",
    "sg:tags":[
        "contractor"
    ],
    "wof:name":"RBC Contracting",
    "wof:placetype":"venue"
},
  "geometry": {"coordinates":[-111.853678,33.350616],"type":"Point"}
}