{
  "type": "Feature",
  "properties": {
    "addr:full":"12856 W Orange Dr Litchfield Park AZ 85340",
    "addr:housenumber":"12856",
    "addr:postcode":"85340",
    "addr:street":"W Orange Dr",
    "iso:country":"US",
    "sg:address":"12856 W Orange Dr",
    "sg:city":"Litchfield Park",
    "sg:classifiers":[
        {
            "category":"Wholesale",
            "subcategory":"Durable Goods & Equipment",
            "type":"Manufacturing & Wholesale Goods"
        }
    ],
    "sg:phone":"+1 623 535 7989",
    "sg:postcode":"85340",
    "sg:province":"AZ",
    "sg:tags":[
        "instrument",
        "scientific",
        "apparatus"
    ],
    "wof:name":"Envioronmentally Scientific",
    "wof:placetype":"venue"
},
  "geometry": {"coordinates":[-112.33586,33.510617],"type":"Point"}
}