{
  "type": "Feature",
  "properties": {
    "iso:country":"US",
    "sg:address":"5812 W Marconi Ave",
    "sg:city":"Glendale",
    "sg:classifiers":[
        {
            "category":"Building & Trades",
            "subcategory":"Plumbing",
            "type":"Services"
        }
    ],
    "sg:phone":"+1 602 547 2334",
    "sg:postcode":"85306",
    "sg:province":"AZ",
    "sg:tags":[
        "air",
        "heating",
        "conditioning",
        "contractor"
    ],
    "wof:name":"Rivards Cooling & Heating Inc",
    "wof:placetype":"venue"
},
  "geometry": {"coordinates":[-112.183439,33.629923],"type":"Point"}
}