{
  "type": "Feature",
  "properties": {
    "iso:country":"US",
    "sg:address":"12405 N 98th St",
    "sg:city":"Scottsdale",
    "sg:classifiers":[
        {
            "category":"Wholesale",
            "subcategory":"Auto Parts",
            "type":"Manufacturing & Wholesale Goods"
        }
    ],
    "sg:phone":"+1 480 391 2888",
    "sg:postcode":"85260",
    "sg:province":"AZ",
    "sg:tags":[
        "automobile",
        "rebuilt"
    ],
    "wof:name":"Arizona Automotive Recyclers",
    "wof:placetype":"venue"
},
  "geometry": {"coordinates":[-111.869579,33.597164],"type":"Point"}
}