{
  "type": "Feature",
  "properties": {
    "iso:country":"US",
    "sg:address":"2487 S Gilbert Rd PMB 106",
    "sg:city":"Gilbert",
    "sg:classifiers":[
        {
            "category":"Building & Trades",
            "subcategory":"Construction",
            "type":"Services"
        }
    ],
    "sg:phone":"+1 480 262 5300",
    "sg:postcode":"85295",
    "sg:province":"AZ",
    "sg:tags":[
        "altering",
        "remodeling",
        "contractor"
    ],
    "wof:name":"Advantage Contractors Services",
    "wof:placetype":"venue"
},
  "geometry": {"coordinates":[-111.789649,33.304071],"type":"Point"}
}