{
  "type": "Feature",
  "properties": {
    "addr:full":"3437 N 7th Ave Phoenix AZ 85013",
    "addr:housenumber":"3437",
    "addr:postcode":"85013",
    "addr:street":"N 7Th Ave",
    "iso:country":"US",
    "sg:address":"3437 N 7th Ave",
    "sg:city":"Phoenix",
    "sg:classifiers":[
        {
            "category":"Restaurant",
            "type":"Food & Drink"
        }
    ],
    "sg:phone":"+1 602 264 8517",
    "sg:postcode":"85013",
    "sg:province":"AZ",
    "sg:tags":[
        "mexican"
    ],
    "wof:name":"Eribertos Mexican Food",
    "wof:placetype":"venue"
},
  "geometry": {"coordinates":[-112.083229,33.488721],"type":"Point"}
}