{
  "type": "Feature",
  "properties": {
    "iso:country":"US",
    "sg:address":"3731 W Vista Ave",
    "sg:city":"Phoenix",
    "sg:classifiers":[
        {
            "category":"Building & Trades",
            "subcategory":"Plumbing",
            "type":"Services"
        }
    ],
    "sg:phone":"+1 602 272 6591",
    "sg:postcode":"85051",
    "sg:province":"AZ",
    "sg:tags":[
        "conditioning",
        "air",
        "system",
        "contractor"
    ],
    "wof:name":"General Air Conditioning Inc",
    "wof:placetype":"venue"
},
  "geometry": {"coordinates":[-112.139342,33.54696],"type":"Point"}
}