{
  "type": "Feature",
  "properties": {
    "iso:country":"US",
    "sg:address":"4801 E Washington St # 100",
    "sg:city":"Phoenix",
    "sg:classifiers":[
        {
            "category":"Banks & Credit Unions",
            "subcategory":"Financial Services",
            "type":"Services"
        },
        {
            "category":"Real Estate",
            "subcategory":"Real Estate Services",
            "type":"Services"
        },
        {
            "category":"Insurance",
            "subcategory":"Hazard Insurance",
            "type":"Services"
        },
        {
            "category":"Insurance",
            "subcategory":"Title Insurance",
            "type":"Services"
        },
        {
            "category":"Real Estate",
            "subcategory":"Real Estate Agent",
            "type":"Services"
        }
    ],
    "sg:phone":"+1 602 685 7000",
    "sg:postcode":"85034",
    "sg:province":"AZ",
    "sg:tags":[
        "mortgage",
        "escrow"
    ],
    "sg:website":"http://www.firstamedu.com",
    "wof:name":"First American Title Ins Co",
    "wof:placetype":"venue"
},
  "geometry": {"coordinates":[-111.978447,33.447311],"type":"Point"}
}