{
  "type": "Feature",
  "properties": {
    "addr:full":"5227 W Waltann Ln Glendale AZ 85306",
    "addr:housenumber":"5227",
    "addr:postcode":"85306",
    "addr:street":"W Waltann Ln",
    "iso:country":"US",
    "sg:address":"5227 W Waltann Ln",
    "sg:city":"Glendale",
    "sg:classifiers":[
        {
            "category":"Building & Trades",
            "subcategory":"Construction",
            "type":"Services"
        }
    ],
    "sg:phone":"+1 602 702 7298",
    "sg:postcode":"85306",
    "sg:province":"AZ",
    "sg:tags":[
        "post"
    ],
    "wof:name":"Postal Specialists",
    "wof:placetype":"venue"
},
  "geometry": {"coordinates":[-112.170305,33.626882],"type":"Point"}
}