{
  "type": "Feature",
  "properties": {
    "iso:country":"US",
    "sg:address":"2141 W Deer Valley Rd",
    "sg:city":"Phoenix",
    "sg:classifiers":[
        {
            "category":"Restaurant",
            "type":"Food & Drink"
        }
    ],
    "sg:menulink":"http://www.allmenus.com/az/phoenix/180253-jack-in-the-box/menu/",
    "sg:phone":"+1 623 582 0894",
    "sg:postcode":"85027",
    "sg:province":"AZ",
    "sg:tags":[
        "burger",
        "american"
    ],
    "wof:name":"Jack in the Box",
    "wof:placetype":"venue"
},
  "geometry": {"coordinates":[-112.106182,33.683219],"type":"Point"}
}