{
  "type": "Feature",
  "properties": {
    "iso:country":"US",
    "sg:address":"302 W Mcdowell Rd",
    "sg:city":"Phoenix",
    "sg:classifiers":[
        {
            "category":"Personal",
            "subcategory":"Barber",
            "type":"Services"
        }
    ],
    "sg:phone":"+1 602 484 0250",
    "sg:postcode":"85003",
    "sg:province":"AZ",
    "wof:name":"Tony's Barber Shop",
    "wof:placetype":"venue"
},
  "geometry": {"coordinates":[-112.078274,33.465771],"type":"Point"}
}