{
  "type": "Feature",
  "properties": {
    "iso:country":"US",
    "sg:address":"101 N 1st Ave Ste 2200",
    "sg:city":"Phoenix",
    "sg:classifiers":[
        {
            "category":"Professional",
            "subcategory":"Computer Services",
            "type":"Services"
        },
        {
            "category":"Internet Cafe",
            "subcategory":"None",
            "type":"Food & Drink"
        }
    ],
    "sg:phone":"+1 602 412 2000",
    "sg:postcode":"85003",
    "sg:province":"AZ",
    "sg:tags":[
        "product",
        "online"
    ],
    "sg:website":"http://www.acs-inc.com",
    "wof:name":"Prepass",
    "wof:placetype":"venue"
},
  "geometry": {"coordinates":[-112.075157,33.449299],"type":"Point"}
}