{
  "type": "Feature",
  "properties": {
    "iso:country":"US",
    "sg:address":"541 E Juanita Ave Ste 8",
    "sg:city":"Mesa",
    "sg:classifiers":[
        {
            "category":"Arts & Performance",
            "subcategory":"Art Gallery",
            "type":"Entertainment"
        },
        {
            "category":"Manufacturing",
            "subcategory":"Wood Products",
            "type":"Manufacturing & Wholesale Goods"
        },
        {
            "category":"Professional",
            "subcategory":"Art Services",
            "type":"Services"
        }
    ],
    "sg:phone":"+1 480 813 6817",
    "sg:postcode":"85204",
    "sg:province":"AZ",
    "sg:tags":[
        "picture",
        "frames-wholesale",
        "consultant",
        "frame",
        "galleries",
        "manufacturer"
    ],
    "sg:website":"www.frameofmindaz.com",
    "wof:name":"Frame of Mind",
    "wof:placetype":"venue"
},
  "geometry": {"coordinates":[-111.819918,33.381432],"type":"Point"}
}