{
  "type": "Feature",
  "properties": {
    "addr:full":"5420 S Tanglewood Dr Sun Lakes AZ 85248",
    "addr:housenumber":"5420",
    "addr:postcode":"85248",
    "addr:street":"S Tanglewood Dr",
    "iso:country":"US",
    "sg:address":"5420 S Tanglewood Dr",
    "sg:city":"Sun Lakes",
    "sg:classifiers":[
        {
            "category":"Professional",
            "subcategory":"Art Services",
            "type":"Services"
        },
        {
            "category":"Building & Trades",
            "subcategory":"Construction",
            "type":"Services"
        }
    ],
    "sg:phone":"+1 480 895 3228",
    "sg:postcode":"85248",
    "sg:province":"AZ",
    "sg:tags":[
        "interior",
        "designer",
        "design",
        "decorator"
    ],
    "wof:name":"Pillars of Design",
    "wof:placetype":"venue"
},
  "geometry": {"coordinates":[-111.845001,33.228199],"type":"Point"}
}