{
  "type": "Feature",
  "properties": {
    "iso:country":"US",
    "sg:address":"2916 N 35th Ave",
    "sg:city":"Phoenix",
    "sg:classifiers":[
        {
            "category":"Wholesale",
            "subcategory":"Groceries",
            "type":"Manufacturing & Wholesale Goods"
        }
    ],
    "sg:phone":"+1 602 455 6380",
    "sg:postcode":"85017",
    "sg:province":"AZ",
    "sg:tags":[
        "food",
        "product",
        "health"
    ],
    "sg:website":"www.aloeverajuice.com",
    "wof:name":"Aerobic Life Industries",
    "wof:placetype":"venue"
},
  "geometry": {"coordinates":[-112.134426,33.482138],"type":"Point"}
}