{
  "type": "Feature",
  "properties": {
    "iso:country":"US",
    "sg:address":"10244 E Placita Pinole",
    "sg:city":"Tucson",
    "sg:classifiers":[
        {
            "category":"Home & Garden",
            "subcategory":"Home Furnishings",
            "type":"Retail Goods"
        }
    ],
    "sg:phone":"+1 520 445 5055",
    "sg:postcode":"85730",
    "sg:province":"AZ",
    "sg:tags":[
        "draperies",
        "curtain",
        "window",
        "treatment"
    ],
    "wof:name":"Blinds More",
    "wof:placetype":"venue"
},
  "geometry": {"coordinates":[-110.77348000000001,32.164395],"type":"Point"}
}