{
  "type": "Feature",
  "properties": {
    "iso:country":"US",
    "sg:address":"2720 W Camelback Rd",
    "sg:city":"Phoenix",
    "sg:classifiers":[
        {
            "category":"Restaurant",
            "type":"Food & Drink"
        }
    ],
    "sg:phone":"+1 602 973 1888",
    "sg:postcode":"85017",
    "sg:province":"AZ",
    "wof:name":"David Kwan's Chinese Buffett",
    "wof:placetype":"venue"
},
  "geometry": {"coordinates":[-112.119112,33.509528],"type":"Point"}
}