{
  "type": "Feature",
  "properties": {
    "addr:full":"1631 E Hedrick Dr Tucson AZ 85719",
    "addr:housenumber":"1631",
    "addr:postcode":"85719",
    "addr:street":"E Hedrick Dr",
    "iso:country":"US",
    "sg:address":"1631 E Hedrick Dr",
    "sg:city":"Tucson",
    "sg:classifiers":[
        {
            "category":"Building & Trades",
            "subcategory":"Landscaping Services",
            "type":"Services"
        }
    ],
    "sg:phone":"+1 520 326 7209",
    "sg:postcode":"85719",
    "sg:province":"AZ",
    "sg:tags":[
        "lawn",
        "maintenance",
        "grounds"
    ],
    "wof:name":"Sonoran Scapes Landscaping Inc",
    "wof:placetype":"venue"
},
  "geometry": {"coordinates":[-110.944181,32.263055],"type":"Point"}
}