{
  "type": "Feature",
  "properties": {
    "addr:full":"3920 E Keresan St Phoenix AZ 85044",
    "addr:housenumber":"3920",
    "addr:postcode":"85044",
    "addr:street":"E Keresan St",
    "iso:country":"US",
    "sg:address":"3920 E Keresan St",
    "sg:city":"Phoenix",
    "sg:classifiers":[
        {
            "category":"Banks & Credit Unions",
            "subcategory":"Financial Services",
            "type":"Services"
        }
    ],
    "sg:phone":"+1 480 759 0326",
    "sg:postcode":"85044",
    "sg:province":"AZ",
    "sg:tags":[
        "trust",
        "management"
    ],
    "wof:name":"McVicker Family Trust",
    "wof:placetype":"venue"
},
  "geometry": {"coordinates":[-111.998502,33.330468],"type":"Point"}
}