{
  "type": "Feature",
  "properties": {
    "iso:country":"US",
    "sg:address":"15525 N 83rd Way",
    "sg:city":"Scottsdale",
    "sg:classifiers":[
        {
            "category":"Shopping",
            "subcategory":"Computers & Home Electronics",
            "type":"Retail Goods"
        }
    ],
    "sg:phone":"+1 480 515 0154",
    "sg:postcode":"85260",
    "sg:province":"AZ",
    "sg:tags":[
        "audio"
    ],
    "wof:name":"Biff Monday",
    "wof:placetype":"venue"
},
  "geometry": {"coordinates":[-111.901605,33.627958],"type":"Point"}
}