{
  "type": "Feature",
  "properties": {
    "addr:full":"4310 E Cotton Center Blvd Phoenix AZ 85040",
    "addr:housenumber":"4310",
    "addr:postcode":"85040",
    "addr:street":"E Cotton Center Blvd",
    "iso:country":"US",
    "sg:address":"4310 E Cotton Center Blvd",
    "sg:city":"Phoenix",
    "sg:classifiers":[
        {
            "category":"Utilities",
            "subcategory":"Telephone",
            "type":"Services"
        }
    ],
    "sg:phone":"+1 520 792 0933",
    "sg:postcode":"85040",
    "sg:province":"AZ",
    "sg:tags":[
        "systems-wholesale",
        "manufacturer",
        "system",
        "equipment"
    ],
    "sg:website":"http://www.inter-tel.com",
    "wof:name":"Inter-Tel (Delaware), Incorporated",
    "wof:placetype":"venue"
},
  "geometry": {"coordinates":[-111.988559,33.4021],"type":"Point"}
}