{
  "type": "Feature",
  "properties": {
    "iso:country":"US",
    "sg:address":"50 Co Rd 1120",
    "sg:city":"Greer",
    "sg:classifiers":[
        {
            "category":"Autos & Motor Vehicles",
            "subcategory":"Recreational Vehicle Sales",
            "type":"Retail Goods"
        }
    ],
    "sg:phone":"+1 928 735 7524",
    "sg:postcode":"85927",
    "sg:province":"AZ",
    "sg:tags":[
        "travel",
        "trailer"
    ],
    "wof:name":"Mountain Aire Rv Park",
    "wof:placetype":"venue"
},
  "geometry": {"coordinates":[-109.461569,34.002014],"type":"Point"}
}