{
  "type": "Feature",
  "properties": {
    "addr:full":"595 S Galleria Way Chandler AZ 85226",
    "addr:housenumber":"595",
    "addr:postcode":"85226",
    "addr:street":"S Galleria Way",
    "iso:country":"US",
    "sg:address":"595 S Galleria Way",
    "sg:city":"Chandler",
    "sg:classifiers":[
        {
            "category":"Utilities",
            "subcategory":"Mobile Phone",
            "type":"Services"
        },
        {
            "category":"Shopping",
            "subcategory":"Mobile Phones",
            "type":"Retail Goods"
        },
        {
            "category":"Utilities",
            "subcategory":"Telephone",
            "type":"Services"
        },
        {
            "category":"Professional",
            "subcategory":"Computer Services",
            "type":"Services"
        }
    ],
    "sg:phone":"+1 480 375 2094",
    "sg:postcode":"85226",
    "sg:province":"AZ",
    "sg:tags":[
        "telecommunication",
        "supply",
        "communication",
        "system",
        "wireless",
        "equipment",
        "cellular"
    ],
    "sg:website":"http://clickserve.dartsearch.net/link/click?lid=43000000308049899",
    "wof:name":"T-Mobile",
    "wof:placetype":"venue"
},
  "geometry": {"coordinates":[-111.89904799999999,33.294709],"type":"Point"}
}