{
  "type": "Feature",
  "properties": {
    "iso:country":"US",
    "sg:address":"106 E Safford St",
    "sg:city":"Tombstone",
    "sg:classifiers":[
        {
            "category":"Real Estate",
            "subcategory":"Real Estate Agent",
            "type":"Services"
        }
    ],
    "sg:phone":"+1 520 457 3440",
    "sg:postcode":"85638",
    "sg:province":"AZ",
    "wof:name":"Long Realty Tombstone",
    "wof:placetype":"venue"
},
  "geometry": {"coordinates":[-110.069406,31.715867],"type":"Point"}
}