{
  "type": "Feature",
  "properties": {
    "iso:country":"US",
    "sg:address":"14500 N Northsight Blvd",
    "sg:city":"Scottsdale",
    "sg:classifiers":[
        {
            "category":"Social Services",
            "type":"Services"
        },
        {
            "category":"Professional",
            "subcategory":"Employment Agencies",
            "type":"Services"
        }
    ],
    "sg:phone":"+1 480 483 5328",
    "sg:postcode":"85260",
    "sg:province":"AZ",
    "sg:tags":[
        "workers'",
        "placement",
        "volunteer"
    ],
    "wof:name":"Hearts To Hands Foundation",
    "wof:placetype":"venue"
},
  "geometry": {"coordinates":[-111.89785000000001,33.616501],"type":"Point"}
}