{
  "type": "Feature",
  "properties": {
    "addr:full":"4221 E Madison St Phoenix AZ 85034",
    "addr:housenumber":"4221",
    "addr:postcode":"85034",
    "addr:street":"E Madison St",
    "iso:country":"US",
    "sg:address":"4221 E Madison St",
    "sg:city":"Phoenix",
    "sg:classifiers":[
        {
            "category":"Retail",
            "subcategory":"Auto Repair",
            "type":"Services"
        }
    ],
    "sg:phone":"+1 602 244 1418",
    "sg:postcode":"85034",
    "sg:province":"AZ",
    "sg:tags":[
        "automobile",
        "top",
        "upholstery"
    ],
    "wof:name":"C & G Auto Upholstery",
    "wof:placetype":"venue"
},
  "geometry": {"coordinates":[-111.990011,33.446192],"type":"Point"}
}