{
  "type": "Feature",
  "properties": {
    "addr:full":"6330 N Campbell Ave Tucson AZ 85718",
    "addr:housenumber":"6330",
    "addr:postcode":"85718",
    "addr:street":"N Campbell Ave",
    "iso:country":"US",
    "sg:address":"6330 N Campbell Ave",
    "sg:city":"Tucson",
    "sg:classifiers":[
        {
            "category":"Sports & Exercise",
            "subcategory":"Gym",
            "type":"Entertainment"
        }
    ],
    "sg:phone":"+1 520 232 0390",
    "sg:postcode":"85718",
    "sg:province":"AZ",
    "sg:tags":[
        "club",
        "health",
        "studio",
        "gymnasium"
    ],
    "wof:name":"Curves",
    "wof:placetype":"venue"
},
  "geometry": {"coordinates":[-110.929664,32.321357],"type":"Point"}
}