{
  "type": "Feature",
  "properties": {
    "iso:country":"US",
    "sg:address":"2600 E Southern Ave",
    "sg:city":"Tempe",
    "sg:classifiers":[
        {
            "category":"Health Services",
            "subcategory":"Doctor",
            "type":"Services"
        }
    ],
    "sg:phone":"+1 480 345 0964",
    "sg:postcode":"85282",
    "sg:province":"AZ",
    "sg:tags":[
        "physician",
        "pediatrics-otorhinolaryngology",
        "surgeons",
        "otorhinolaryngology",
        "nose",
        "throat",
        "surgeon",
        "ear"
    ],
    "wof:name":"Cactus Ear Nose and Throat Associates",
    "wof:placetype":"venue"
},
  "geometry": {"coordinates":[-111.88327,33.393009],"type":"Point"}
}