{
  "type": "Feature",
  "properties": {
    "iso:country":"US",
    "sg:address":"4545 E Broadway Blvd",
    "sg:city":"Tucson",
    "sg:classifiers":[
        {
            "category":"Home & Garden",
            "subcategory":"Home Furnishings",
            "type":"Retail Goods"
        }
    ],
    "sg:phone":"+1 520 322 4303",
    "sg:postcode":"85711",
    "sg:province":"AZ",
    "sg:tags":[
        "lighting",
        "fixture"
    ],
    "sg:website":"www.sunlighting.net",
    "wof:name":"Sun Lighting Co",
    "wof:placetype":"venue"
},
  "geometry": {"coordinates":[-110.895342,32.22159],"type":"Point"}
}