{
  "type": "Feature",
  "properties": {
    "addr:full":"4709 E Bermuda St Tucson AZ 85712",
    "addr:housenumber":"4709",
    "addr:postcode":"85712",
    "addr:street":"E Bermuda St",
    "iso:country":"US",
    "sg:address":"4709 E Bermuda St",
    "sg:city":"Tucson",
    "sg:classifiers":[
        {
            "category":"Professional",
            "subcategory":"Art Services",
            "type":"Services"
        }
    ],
    "sg:phone":"+1 520 881 6209",
    "sg:postcode":"85712",
    "sg:province":"AZ",
    "sg:tags":[
        "photographer"
    ],
    "wof:name":"Patrick Grimes Photography",
    "wof:placetype":"venue"
},
  "geometry": {"coordinates":[-110.891867,32.25614],"type":"Point"}
}