{
  "type": "Feature",
  "properties": {
    "addr:full":"4501 N 22nd St Ste 110 Phoenix AZ 85016",
    "addr:housenumber":"4501",
    "addr:postcode":"85016",
    "addr:street":"N 22Nd St Ste 110",
    "iso:country":"US",
    "sg:address":"4501 N 22nd St Ste 110",
    "sg:city":"Phoenix",
    "sg:classifiers":[
        {
            "category":"Real Estate",
            "subcategory":"Real Estate Services",
            "type":"Services"
        }
    ],
    "sg:phone":"+1 602 515 3836",
    "sg:postcode":"85016",
    "sg:province":"AZ",
    "sg:tags":[
        "management",
        "condominium"
    ],
    "wof:name":"Casa De Sierra Vista Condominium Association",
    "wof:placetype":"venue"
},
  "geometry": {"coordinates":[-112.034561,33.502041],"type":"Point"}
}