{
  "type": "Feature",
  "properties": {
    "iso:country":"US",
    "sg:address":"11101 E Bella Vista Dr",
    "sg:city":"Scottsdale",
    "sg:classifiers":[
        {
            "category":"Building & Trades",
            "subcategory":"Construction",
            "type":"Services"
        }
    ],
    "sg:phone":"+1 480 451 4300",
    "sg:postcode":"85259",
    "sg:province":"AZ",
    "sg:tags":[
        "new",
        "remodel",
        "home"
    ],
    "wof:name":"West Construction & Dev Co",
    "wof:placetype":"venue"
},
  "geometry": {"coordinates":[-111.839679,33.568605],"type":"Point"}
}