{
  "type": "Feature",
  "properties": {
    "iso:country":"US",
    "sg:address":"4015 N 40th Pl",
    "sg:city":"Phoenix",
    "sg:classifiers":[
        {
            "category":"Shopping",
            "subcategory":"Pharmacy",
            "type":"Retail Goods"
        }
    ],
    "sg:phone":"+1 602 955 9007",
    "sg:postcode":"85018",
    "sg:province":"AZ",
    "sg:tags":[
        "product",
        "health"
    ],
    "wof:name":"Snore Formula Inc",
    "wof:placetype":"venue"
},
  "geometry": {"coordinates":[-111.99381200000001,33.494879],"type":"Point"}
}