{
  "type": "Feature",
  "properties": {
    "iso:country":"US",
    "sg:address":"1808 W Bell Rd",
    "sg:city":"Phoenix",
    "sg:classifiers":[
        {
            "category":"Home & Garden",
            "subcategory":"Furniture",
            "type":"Retail Goods"
        }
    ],
    "sg:phone":"+1 602 789 9747",
    "sg:postcode":"85023",
    "sg:province":"AZ",
    "sg:tags":[
        "futon"
    ],
    "sg:website":"www.futonsaz.com",
    "wof:name":"Futon Factory Outlet Inc",
    "wof:placetype":"venue"
},
  "geometry": {"coordinates":[-112.09771000000001,33.640225],"type":"Point"}
}