{
  "type": "Feature",
  "properties": {
    "iso:country":"US",
    "sg:address":"310 N Dysart Rd",
    "sg:city":"Avondale",
    "sg:classifiers":[
        {
            "category":"Building & Trades",
            "subcategory":"Locksmith",
            "type":"Services"
        }
    ],
    "sg:phone":"+1 623 505 2072",
    "sg:postcode":"85323",
    "sg:province":"AZ",
    "sg:tags":[
        "key"
    ],
    "wof:name":"24 Hr A - 1 Locksmith",
    "wof:placetype":"venue"
},
  "geometry": {"coordinates":[-112.341201,33.438265],"type":"Point"}
}