{
  "type": "Feature",
  "properties": {
    "addr:full":"5801 S Mcclintock Dr Tempe AZ 85283",
    "addr:housenumber":"5801",
    "addr:postcode":"85283",
    "addr:street":"S Mcclintock Dr",
    "iso:country":"US",
    "sg:address":"5801 S Mcclintock Dr",
    "sg:city":"Tempe",
    "sg:classifiers":[
        {
            "category":"Professional",
            "subcategory":"Accounting & Tax Preparation",
            "type":"Services"
        }
    ],
    "sg:phone":"+1 480 505 5715",
    "sg:postcode":"85283",
    "sg:province":"AZ",
    "sg:tags":[
        "bookkeeping",
        "billing"
    ],
    "sg:website":"http://www.securemedical.com",
    "wof:name":"Secure Medical, Inc",
    "wof:placetype":"venue"
},
  "geometry": {"coordinates":[-111.911278,33.371239],"type":"Point"}
}