{
  "type": "Feature",
  "properties": {
    "addr:full":"1955 N Horne Apt 106 Mesa AZ 85203",
    "addr:housenumber":"1955;106",
    "addr:postcode":"85203",
    "addr:street":"N Horne Apt",
    "iso:country":"US",
    "sg:address":"1955 N Horne Apt 106",
    "sg:city":"Mesa",
    "sg:classifiers":[
        {
            "category":"Wholesale",
            "subcategory":"Plants",
            "type":"Manufacturing & Wholesale Goods"
        },
        {
            "category":"Shopping",
            "subcategory":"Crafts & Fabrics",
            "type":"Retail Goods"
        }
    ],
    "sg:phone":"+1 480 964 1890",
    "sg:postcode":"85203",
    "sg:province":"AZ",
    "sg:tags":[
        "florists'",
        "supply",
        "florist",
        "supplies-wholesale",
        "plants-wholesale",
        "manufacturer"
    ],
    "wof:name":"Cooper's Wholesale Nursery",
    "wof:placetype":"venue"
},
  "geometry": {"coordinates":[-111.813654,33.450798],"type":"Point"}
}