{
  "type": "Feature",
  "properties": {
    "iso:country":"US",
    "sg:address":"16500 N Stallion Pl",
    "sg:city":"Tucson",
    "sg:classifiers":[
        {
            "category":"Farming",
            "subcategory":"Farm & Veterinary Services",
            "type":"Manufacturing & Wholesale Goods"
        }
    ],
    "sg:phone":"+1 520 825 0192",
    "sg:postcode":"85739",
    "sg:province":"AZ",
    "sg:tags":[
        "crop"
    ],
    "wof:name":"Desert Weed Control",
    "wof:placetype":"venue"
},
  "geometry": {"coordinates":[-110.898357,32.507196],"type":"Point"}
}