{
  "type": "Feature",
  "properties": {
    "iso:country":"US",
    "sg:address":"11446 Oak Run Ln",
    "sg:city":"Cornville",
    "sg:classifiers":[
        {
            "category":"Building & Trades",
            "subcategory":"Construction",
            "type":"Services"
        }
    ],
    "sg:phone":"+1 928 649 3883",
    "sg:postcode":"86325",
    "sg:province":"AZ",
    "sg:tags":[
        "concrete",
        "contractor"
    ],
    "wof:name":"Foxworthy Concrete",
    "wof:placetype":"venue"
},
  "geometry": {"coordinates":[-111.903116,34.72026],"type":"Point"}
}