{
  "type": "Feature",
  "properties": {
    "iso:country":"US",
    "sg:address":"1438 W Broadway Rd",
    "sg:city":"Tempe",
    "sg:classifiers":[
        {
            "category":"Shopping",
            "subcategory":"Computers & Home Electronics",
            "type":"Retail Goods"
        }
    ],
    "sg:phone":"+1 480 921 9211",
    "sg:postcode":"85282",
    "sg:province":"AZ",
    "sg:tags":[
        "system"
    ],
    "wof:name":"Cad Solutions",
    "wof:placetype":"venue"
},
  "geometry": {"coordinates":[-111.963653,33.407523],"type":"Point"}
}