{
  "type": "Feature",
  "properties": {
    "iso:country":"US",
    "sg:address":"2040 N 69th Pl",
    "sg:city":"Scottsdale",
    "sg:classifiers":[
        {
            "category":"Travel",
            "subcategory":"Travel Agent",
            "type":"Entertainment"
        }
    ],
    "sg:phone":"+1 602 540 7850",
    "sg:postcode":"85257",
    "sg:province":"AZ",
    "sg:tags":[
        "consultant",
        "transportation"
    ],
    "wof:name":"Cadre",
    "wof:placetype":"venue"
},
  "geometry": {"coordinates":[-111.931698,33.470353],"type":"Point"}
}