{
  "type": "Feature",
  "properties": {
    "addr:full":"703 E Ash St Ste 1 Globe AZ 85501",
    "addr:housenumber":"703",
    "addr:postcode":"az 85501",
    "addr:street":"E Ash St Ste 1",
    "iso:country":"US",
    "sg:address":"703 E Ash St Ste 1",
    "sg:city":"Globe",
    "sg:classifiers":[
        {
            "category":"Personal",
            "subcategory":"Beauty Salon",
            "type":"Services"
        }
    ],
    "sg:phone":"+1 928 425 3670",
    "sg:postcode":"85501",
    "sg:province":"AZ",
    "wof:name":"Cynthia's Skin And Hair Salon",
    "wof:placetype":"venue"
},
  "geometry": {"coordinates":[-110.77919300000001,33.393768],"type":"Point"}
}