{
  "type": "Feature",
  "properties": {
    "iso:country":"US",
    "sg:address":"703 E Ash St Ste 1",
    "sg:city":"Globe",
    "sg:classifiers":[
        {
            "category":"Personal",
            "subcategory":"Beauty Salon",
            "type":"Services"
        }
    ],
    "sg:phone":"+1 928 425 3670",
    "sg:postcode":"85501",
    "sg:province":"AZ",
    "wof:name":"Cynthia's Skin And Hair Salon",
    "wof:placetype":"venue"
},
  "geometry": {"coordinates":[-110.779193,33.393768],"type":"Point"}
}