{
  "type": "Feature",
  "properties": {
    "addr:full":"3010 N 2nd St Ste 301 Phoenix AZ 85012",
    "addr:housenumber":"3010",
    "addr:postcode":"85012",
    "addr:street":"N 2Nd St Ste 301",
    "iso:country":"US",
    "sg:address":"3010 N 2nd St Ste 301",
    "sg:city":"Phoenix",
    "sg:classifiers":[
        {
            "category":"Organizations",
            "subcategory":"Community Association",
            "type":"Services"
        }
    ],
    "sg:phone":"+1 602 664 5902",
    "sg:postcode":"85012",
    "sg:province":"AZ",
    "sg:tags":[
        "club"
    ],
    "wof:name":"Federal Womens Program",
    "wof:placetype":"venue"
},
  "geometry": {"coordinates":[-112.07088899999999,33.482226],"type":"Point"}
}