{
  "type": "Feature",
  "properties": {
    "iso:country":"US",
    "sg:address":"3260 E Universal Way",
    "sg:city":"Tucson",
    "sg:classifiers":[
        {
            "category":"Manufacturing",
            "subcategory":"Tools & Machinery",
            "type":"Manufacturing & Wholesale Goods"
        }
    ],
    "sg:phone":"+1 520 434 4400",
    "sg:postcode":"85706",
    "sg:province":"AZ",
    "sg:tags":[
        "measuring",
        "search",
        "controlling",
        "mfg"
    ],
    "sg:website":"www.uasc.com",
    "wof:name":"Universal Avonics Systems Corp",
    "wof:placetype":"venue"
},
  "geometry": {"coordinates":[-110.923306,32.132492],"type":"Point"}
}