{
  "type": "Feature",
  "properties": {
    "iso:country":"US",
    "sg:address":"15545 N 77th St",
    "sg:city":"Scottsdale",
    "sg:classifiers":[
        {
            "category":"Wholesale",
            "subcategory":"Durable Goods & Equipment",
            "type":"Manufacturing & Wholesale Goods"
        }
    ],
    "sg:phone":"+1 480 998 0141",
    "sg:postcode":"85260",
    "sg:province":"AZ",
    "sg:tags":[
        "representative",
        "manufacturer"
    ],
    "sg:website":"www.adcoservice.com",
    "wof:name":"Adco Services",
    "wof:placetype":"venue"
},
  "geometry": {"coordinates":[-111.914463,33.627933],"type":"Point"}
}