{
  "type": "Feature",
  "properties": {
    "iso:country":"US",
    "sg:address":"32 Main St",
    "sg:city":"Bisbee",
    "sg:classifiers":[
        {
            "category":"Shopping",
            "type":"Retail Goods"
        }
    ],
    "sg:phone":"+1 520 432 5824",
    "sg:postcode":"85603",
    "sg:province":"AZ",
    "sg:tags":[
        "merchandise"
    ],
    "wof:name":"Tang Gallery",
    "wof:placetype":"venue"
},
  "geometry": {"coordinates":[-109.916447,31.441583],"type":"Point"}
}