{
  "type": "Feature",
  "properties": {
    "iso:country":"US",
    "sg:address":"250 S Springs Dr",
    "sg:city":"Chandler",
    "sg:classifiers":[
        {
            "category":"Retail",
            "subcategory":"Car Wash",
            "type":"Services"
        }
    ],
    "sg:phone":"+1 480 558 9400",
    "sg:postcode":"85225",
    "sg:province":"AZ",
    "sg:tags":[
        "polishing",
        "washing"
    ],
    "wof:name":"Auto Bright Car Wash",
    "wof:placetype":"venue"
},
  "geometry": {"coordinates":[-111.823643,33.300013],"type":"Point"}
}