{
  "type": "Feature",
  "properties": {
    "iso:country":"US",
    "sg:address":"2601 Stockton Hill Rd",
    "sg:city":"Kingman",
    "sg:classifiers":[
        {
            "category":"Retail",
            "subcategory":"Laundry & Dry Cleaning",
            "type":"Services"
        }
    ],
    "sg:phone":"+1 928 753 1106",
    "sg:postcode":"86401",
    "sg:province":"AZ",
    "sg:tags":[
        "cleaners"
    ],
    "wof:name":"Andy's Cleaners",
    "wof:placetype":"venue"
},
  "geometry": {"coordinates":[-114.034818,35.210369],"type":"Point"}
}