{
  "type": "Feature",
  "properties": {
    "addr:full":"545 E Mcdowell Rd Phoenix AZ 85004",
    "addr:housenumber":"545",
    "addr:postcode":"85004",
    "addr:street":"E Mcdowell Rd",
    "iso:country":"US",
    "sg:address":"545 E Mcdowell Rd",
    "sg:city":"Phoenix",
    "sg:classifiers":[
        {
            "category":"Fast Food",
            "type":"Food & Drink"
        },
        {
            "category":"Restaurant",
            "type":"Food & Drink"
        }
    ],
    "sg:phone":"+1 602 262 2388",
    "sg:postcode":"85004",
    "sg:province":"AZ",
    "sg:tags":[
        "hamburger",
        "hot",
        "dog",
        "american",
        "take",
        "chicken"
    ],
    "sg:website":"http://www.mcdonalds.com",
    "wof:name":"McDonald's",
    "wof:placetype":"venue"
},
  "geometry": {"coordinates":[-112.065731,33.46571],"type":"Point"}
}