{
  "type": "Feature",
  "properties": {
    "iso:country":"US",
    "sg:address":"3917 S Central Ave",
    "sg:city":"Phoenix",
    "sg:classifiers":[
        {
            "category":"Real Estate",
            "subcategory":"Real Estate Services",
            "type":"Services"
        }
    ],
    "sg:phone":"+1 602 268 8328",
    "sg:postcode":"85040",
    "sg:province":"AZ",
    "sg:tags":[
        "company",
        "title"
    ],
    "wof:name":"Arizona Auto Title Loan Co",
    "wof:placetype":"venue"
},
  "geometry": {"coordinates":[-112.073303,33.410865],"type":"Point"}
}