{
  "type": "Feature",
  "properties": {
    "addr:full":"214 E Wigwam Blvd Litchfield Park AZ 85340",
    "addr:housenumber":"214",
    "addr:postcode":"85340",
    "addr:street":"E Wigwam Blvd",
    "iso:country":"US",
    "sg:address":"214 E Wigwam Blvd",
    "sg:city":"Litchfield Park",
    "sg:classifiers":[
        {
            "category":"Government",
            "subcategory":"Office",
            "type":"Public Place"
        }
    ],
    "sg:phone":"+1 623 935 1066",
    "sg:postcode":"85340",
    "sg:province":"AZ",
    "sg:tags":[
        "executive"
    ],
    "wof:name":"Permits & Building Insptn Svcs",
    "wof:placetype":"venue"
},
  "geometry": {"coordinates":[-112.35637199999999,33.493462],"type":"Point"}
}