{
  "type": "Feature",
  "properties": {
    "addr:full":"316 S 52nd St Tempe AZ 85281",
    "addr:housenumber":"316",
    "addr:postcode":"85281",
    "addr:street":"S 52Nd St",
    "iso:country":"US",
    "sg:address":"316 S 52nd St",
    "sg:city":"Tempe",
    "sg:classifiers":[
        {
            "category":"Wholesale",
            "subcategory":"Electrical",
            "type":"Manufacturing & Wholesale Goods"
        }
    ],
    "sg:phone":"+1 480 894 0950",
    "sg:postcode":"85281",
    "sg:province":"AZ",
    "sg:tags":[
        "telecommunication"
    ],
    "wof:name":"DIVERSIFIED Telecommunications",
    "wof:placetype":"venue"
},
  "geometry": {"coordinates":[-111.969707,33.426622],"type":"Point"}
}