{
  "type": "Feature",
  "properties": {
    "iso:country":"US",
    "sg:address":"8108 E Krail St",
    "sg:city":"Scottsdale",
    "sg:classifiers":[
        {
            "category":"Coffee & Tea",
            "type":"Food & Drink"
        }
    ],
    "sg:phone":"+1 480 784 4773",
    "sg:postcode":"85250",
    "sg:province":"AZ",
    "sg:tags":[
        "break",
        "supply"
    ],
    "wof:name":"Java Joint Inc",
    "wof:placetype":"venue"
},
  "geometry": {"coordinates":[-111.905852,33.53466],"type":"Point"}
}