{
  "type": "Feature",
  "properties": {
    "iso:country":"US",
    "sg:address":"12995 N Oracle Rd",
    "sg:city":"Tucson",
    "sg:classifiers":[
        {
            "category":"Shopping",
            "subcategory":"Jewelry",
            "type":"Retail Goods"
        }
    ],
    "sg:phone":"+1 520 818 1769",
    "sg:postcode":"85739",
    "sg:province":"AZ",
    "wof:name":"Artist Made Jewelry",
    "wof:placetype":"venue"
},
  "geometry": {"coordinates":[-110.933908,32.446476],"type":"Point"}
}