{
  "type": "Feature",
  "properties": {
    "iso:country":"US",
    "sg:address":"13954 W Waddell Rd",
    "sg:city":"Surprise",
    "sg:classifiers":[
        {
            "category":"Real Estate",
            "subcategory":"Surveying",
            "type":"Services"
        }
    ],
    "sg:phone":"+1 623 703 0399",
    "sg:postcode":"85379",
    "sg:province":"AZ",
    "sg:tags":[
        "surveyor"
    ],
    "wof:name":"Dms Survey LLC",
    "wof:placetype":"venue"
},
  "geometry": {"coordinates":[-112.362347,33.609281],"type":"Point"}
}