{
  "type": "Feature",
  "properties": {
    "iso:country":"US",
    "sg:address":"2020 6th Ave",
    "sg:city":"Flagstaff",
    "sg:classifiers":[
        {
            "category":"Retail",
            "subcategory":"Auto Repair",
            "type":"Services"
        }
    ],
    "sg:phone":"+1 928 774 8051",
    "sg:postcode":"86004",
    "sg:province":"AZ",
    "sg:tags":[
        "repairing",
        "automobile"
    ],
    "sg:website":"www.lifetimeautomotive.com",
    "wof:name":"Lifetime Automotive",
    "wof:placetype":"venue"
},
  "geometry": {"coordinates":[-111.61876700000001,35.210778],"type":"Point"}
}