{
  "type": "Feature",
  "properties": {
    "iso:country":"US",
    "sg:address":"1129 N Winstel Blvd",
    "sg:city":"Tucson",
    "sg:classifiers":[
        {
            "category":"Professional",
            "subcategory":"Engineering",
            "type":"Services"
        }
    ],
    "sg:phone":"+1 520 881 1234",
    "sg:postcode":"85716",
    "sg:province":"AZ",
    "sg:tags":[
        "consulting",
        "petroleum",
        "engineer"
    ],
    "sg:website":"http://www.pattisonevanoff.com",
    "wof:name":"Pattison Evanoff Engnrng",
    "wof:placetype":"venue"
},
  "geometry": {"coordinates":[-110.911838,32.236765],"type":"Point"}
}