{
  "type": "Feature",
  "properties": {
    "iso:country":"US",
    "sg:address":"3801 N Oracle Rd",
    "sg:city":"Tucson",
    "sg:classifiers":[
        {
            "category":"Shopping",
            "subcategory":"Bicycles & Sporting Goods",
            "type":"Retail Goods"
        }
    ],
    "sg:phone":"+1 520 887 7770",
    "sg:postcode":"85705",
    "sg:province":"AZ",
    "sg:tags":[
        "shop"
    ],
    "wof:name":"Bicycles West",
    "wof:placetype":"venue"
},
  "geometry": {"coordinates":[-110.97822600000001,32.275291],"type":"Point"}
}