{
  "type": "Feature",
  "properties": {
    "iso:country":"US",
    "sg:address":"937 N Miller Dr",
    "sg:city":"Tucson",
    "sg:classifiers":[
        {
            "category":"Real Estate",
            "subcategory":"Real Estate Agent",
            "type":"Services"
        }
    ],
    "sg:phone":"+1 520 293 7533",
    "sg:postcode":"85710",
    "sg:province":"AZ",
    "wof:name":"Roger Grant Real Estate",
    "wof:placetype":"venue"
},
  "geometry": {"coordinates":[-110.804997,32.233293],"type":"Point"}
}