{
  "type": "Feature",
  "properties": {
    "iso:country":"US",
    "sg:address":"4645 S Lakeshore Dr Suite 6",
    "sg:city":"Tempe",
    "sg:classifiers":[
        {
            "category":"Professional",
            "subcategory":"Lawyer & Legal Services",
            "type":"Services"
        }
    ],
    "sg:phone":"+1 602 265 9665",
    "sg:postcode":"85282",
    "sg:province":"AZ",
    "sg:tags":[
        "attorney",
        "business",
        "practice",
        "labor",
        "law",
        "employment"
    ],
    "sg:website":"http://www.davidlarkinlaw.com",
    "wof:name":"David C. Larkin",
    "wof:placetype":"venue"
},
  "geometry": {"coordinates":[-111.923532,33.381246],"type":"Point"}
}