{
  "type": "Feature",
  "properties": {
    "addr:full":"2380 N Oakmont Dr Flagstaff AZ 86004",
    "addr:housenumber":"2380",
    "addr:postcode":"86004",
    "addr:street":"N Oakmont Dr",
    "iso:country":"US",
    "sg:address":"2380 N Oakmont Dr",
    "sg:city":"Flagstaff",
    "sg:classifiers":[
        {
            "category":"Insurance",
            "subcategory":"Insurance Agent",
            "type":"Services"
        }
    ],
    "sg:phone":"+1 928 526 2911",
    "sg:postcode":"86004",
    "sg:province":"AZ",
    "sg:tags":[
        "planning",
        "financial"
    ],
    "wof:name":"Massmutual",
    "wof:placetype":"venue"
},
  "geometry": {"coordinates":[-111.58017,35.201646],"type":"Point"}
}