{
  "type": "Feature",
  "properties": {
    "addr:full":"501 E Alameda Dr Tempe AZ 85282",
    "addr:housenumber":"501",
    "addr:postcode":"85282",
    "addr:street":"E Alameda Dr",
    "iso:country":"US",
    "sg:address":"501 E Alameda Dr",
    "sg:city":"Tempe",
    "sg:classifiers":[
        {
            "category":"Farming",
            "subcategory":"Orchard",
            "type":"Manufacturing & Wholesale Goods"
        }
    ],
    "sg:phone":"+1 480 921 9205",
    "sg:postcode":"85282",
    "sg:province":"AZ",
    "wof:name":"5k Orchards",
    "wof:placetype":"venue"
},
  "geometry": {"coordinates":[-111.930588,33.400211],"type":"Point"}
}