{
  "type": "Feature",
  "properties": {
    "iso:country":"US",
    "sg:address":"5150 State Hwy 90",
    "sg:city":"Sierra Vista",
    "sg:classifiers":[
        {
            "category":"Travel",
            "subcategory":"Hotels & Motels",
            "type":"Entertainment"
        }
    ],
    "sg:phone":"+1 520 458 7820",
    "sg:postcode":"85635",
    "sg:province":"AZ",
    "wof:name":"Blue Horizon Apartments",
    "wof:placetype":"venue"
},
  "geometry": {"coordinates":[-110.282042,31.556824],"type":"Point"}
}