{
  "type": "Feature",
  "properties": {
    "iso:country":"US",
    "sg:address":"5110 N 32nd St",
    "sg:city":"Phoenix",
    "sg:classifiers":[
        {
            "category":"Real Estate",
            "subcategory":"Real Estate Operator",
            "type":"Services"
        }
    ],
    "sg:phone":"+1 602 957 3400",
    "sg:postcode":"85018",
    "sg:province":"AZ",
    "sg:tags":[
        "apartment"
    ],
    "wof:name":"Del Prado Apartments",
    "wof:placetype":"venue"
},
  "geometry": {"coordinates":[-112.01307,33.512847],"type":"Point"}
}