{
  "type": "Feature",
  "properties": {
    "iso:country":"US",
    "sg:address":"12601 N 59th Pl Ste 100",
    "sg:city":"Scottsdale",
    "sg:classifiers":[
        {
            "category":"Professional",
            "subcategory":"Lawyer & Legal Services",
            "type":"Services"
        }
    ],
    "sg:phone":"+1 602 795 5515",
    "sg:postcode":"85254",
    "sg:province":"AZ",
    "sg:tags":[
        "convention",
        "reporters-court"
    ],
    "wof:name":"Mcnutt Reporting Service, Inc",
    "wof:placetype":"venue"
},
  "geometry": {"coordinates":[-111.952881,33.60059],"type":"Point"}
}