{
  "type": "Feature",
  "properties": {
    "iso:country":"US",
    "sg:address":"15576 N Pima Rd",
    "sg:city":"Scottsdale",
    "sg:classifiers":[
        {
            "category":"Restaurant",
            "type":"Food & Drink"
        }
    ],
    "sg:menulink":"http://www.allmenus.com/az/phoenix/4590-fasta-pasta/menu/",
    "sg:phone":"+1 480 905 0510",
    "sg:postcode":"85260",
    "sg:province":"AZ",
    "sg:tags":[
        "italian"
    ],
    "wof:name":"Fasta Pasta",
    "wof:placetype":"venue"
},
  "geometry": {"coordinates":[-111.891023,33.627457],"type":"Point"}
}