{
  "type": "Feature",
  "properties": {
    "addr:full":"415 Cid Ct Rio Rico AZ 85648",
    "addr:housenumber":"415",
    "addr:postcode":"85648",
    "addr:street":"Cid Ct",
    "iso:country":"US",
    "sg:address":"415 Cid Ct",
    "sg:city":"Rio Rico",
    "sg:phone":"+1 520 281 8285",
    "sg:postcode":"85648",
    "sg:province":"AZ",
    "sg:tags":[
        "food",
        "equipment",
        "mfr",
        "warming"
    ],
    "wof:name":"La Tortilla Loca LLC",
    "wof:placetype":"venue"
},
  "geometry": {"coordinates":[-110.974391,31.480135],"type":"Point"}
}