{
  "type": "Feature",
  "properties": {
    "iso:country":"US",
    "sg:address":"1949 E Brown Rd Ste B6",
    "sg:city":"Mesa",
    "sg:classifiers":[
        {
            "category":"Social Services",
            "subcategory":"Child Care",
            "type":"Services"
        },
        {
            "category":"Education",
            "subcategory":"Preschool",
            "type":"Public Place"
        }
    ],
    "sg:phone":"+1 480 464 0110",
    "sg:postcode":"85203",
    "sg:province":"AZ",
    "sg:tags":[
        "kindergarten",
        "nursery",
        "day"
    ],
    "wof:name":"Cambridge Preschool Academy",
    "wof:placetype":"venue"
},
  "geometry": {"coordinates":[-111.788927,33.437183],"type":"Point"}
}