{
  "type": "Feature",
  "properties": {
    "iso:country":"US",
    "sg:address":"1111 N 7th St",
    "sg:city":"Phoenix",
    "sg:classifiers":[
        {
            "category":"Travel",
            "subcategory":"Hotels & Motels",
            "type":"Entertainment"
        },
        {
            "category":"Restaurant",
            "type":"Food & Drink"
        },
        {
            "category":"Personal",
            "subcategory":"Day Spa",
            "type":"Services"
        },
        {
            "category":"Travel",
            "subcategory":"Resort",
            "type":"Entertainment"
        },
        {
            "category":"Sports & Exercise",
            "subcategory":"Golf",
            "type":"Entertainment"
        }
    ],
    "sg:phone":"+1 602 866 6350",
    "sg:postcode":"85006",
    "sg:province":"AZ",
    "sg:tags":[
        "course",
        "fine",
        "dining"
    ],
    "sg:website":"http://tapatiocliffshilton.com/dining/different-pointe-of-view/index.cfm",
    "wof:name":"Pointe Hilton Tapatio Cliffs Resort- Different Point of View",
    "wof:placetype":"venue"
},
  "geometry": {"coordinates":[-112.065189,33.460079],"type":"Point"}
}