{
  "type": "Feature",
  "properties": {
    "addr:full":"1116 S Crismon Rd Ste 103 Mesa AZ 85208",
    "addr:housenumber":"1116",
    "addr:postcode":"85208",
    "addr:street":"S Crismon Rd Ste 103",
    "iso:country":"US",
    "sg:address":"1116 S Crismon Rd Ste 103",
    "sg:city":"Mesa",
    "sg:classifiers":[
        {
            "category":"Professional",
            "subcategory":"Management & Consulting",
            "type":"Services"
        },
        {
            "category":"Education",
            "subcategory":"Special Training",
            "type":"Public Place"
        },
        {
            "category":"Education",
            "subcategory":"Library",
            "type":"Public Place"
        }
    ],
    "sg:phone":"+1 480 373 6284",
    "sg:postcode":"85208",
    "sg:province":"AZ",
    "sg:tags":[
        "educational",
        "consultant",
        "instruction",
        "system",
        "improvement",
        "preparation",
        "equipment",
        "adult",
        "test",
        "reading",
        "tutoring"
    ],
    "sg:website":"http://www.sylvanlearningcenter.com",
    "wof:name":"Sylvan Learning Center",
    "wof:placetype":"venue"
},
  "geometry": {"coordinates":[-111.615405,33.394708],"type":"Point"}
}