{
  "type": "Feature",
  "properties": {
    "addr:full":"1137 N Scotts Crest Rd Thatcher AZ 85552",
    "addr:housenumber":"1137",
    "addr:postcode":"85552",
    "addr:street":"N Scotts Crest Rd",
    "iso:country":"US",
    "sg:address":"1137 N Scotts Crest Rd",
    "sg:city":"Thatcher",
    "sg:classifiers":[
        {
            "category":"Building & Trades",
            "subcategory":"Construction",
            "type":"Services"
        }
    ],
    "sg:phone":"+1 928 428 6376",
    "sg:postcode":"85552",
    "sg:province":"AZ",
    "sg:tags":[
        "handyman"
    ],
    "wof:name":"Snyders Repair",
    "wof:placetype":"venue"
},
  "geometry": {"coordinates":[-109.78633600000001,32.849493],"type":"Point"}
}