{
  "type": "Feature",
  "properties": {
    "iso:country":"US",
    "sg:address":"1761 E Warner Road Suite 16",
    "sg:city":"Tempe",
    "sg:classifiers":[
        {
            "category":"Building & Trades",
            "subcategory":"Locksmith",
            "type":"Services"
        }
    ],
    "sg:phone":"+1 480 785 9999",
    "sg:postcode":"85284",
    "sg:province":"AZ",
    "sg:tags":[
        "key"
    ],
    "wof:name":"Copperstate Locksmith Company",
    "wof:placetype":"venue"
},
  "geometry": {"coordinates":[-111.91154400000001,33.334612],"type":"Point"}
}