{
  "type": "Feature",
  "properties": {
    "iso:country":"US",
    "sg:address":"3746 W Surrey Ave",
    "sg:city":"Phoenix",
    "sg:classifiers":[
        {
            "category":"Building & Trades",
            "subcategory":"Construction",
            "type":"Services"
        }
    ],
    "sg:phone":"+1 602 993 9647",
    "sg:postcode":"85029",
    "sg:province":"AZ",
    "sg:tags":[
        "paving",
        "contractor"
    ],
    "wof:name":"ASI Arizona Surfaces Inc",
    "wof:placetype":"venue"
},
  "geometry": {"coordinates":[-112.140231,33.605267],"type":"Point"}
}