{
  "type": "Feature",
  "properties": {
    "addr:full":"6029 W Earll Dr Phoenix AZ 85033",
    "addr:housenumber":"6029",
    "addr:postcode":"85033",
    "addr:street":"W Earll Dr",
    "iso:country":"US",
    "sg:address":"6029 W Earll Dr",
    "sg:city":"Phoenix",
    "sg:classifiers":[
        {
            "category":"Building & Trades",
            "subcategory":"Construction",
            "type":"Services"
        }
    ],
    "sg:phone":"+1 623 247 9759",
    "sg:postcode":"85033",
    "sg:province":"AZ",
    "sg:tags":[
        "contractor"
    ],
    "wof:name":"Glass Tile Designs",
    "wof:placetype":"venue"
},
  "geometry": {"coordinates":[-112.187772,33.48435],"type":"Point"}
}