{
  "type": "Feature",
  "properties": {
    "iso:country":"US",
    "sg:address":"17031 N 11th Ave",
    "sg:city":"Phoenix",
    "sg:classifiers":[
        {
            "category":"Freight",
            "type":"Transportation"
        }
    ],
    "sg:phone":"+1 602 820 1540",
    "sg:postcode":"85023",
    "sg:province":"AZ",
    "sg:tags":[
        "operator",
        "local",
        "trucking"
    ],
    "wof:name":"RMC Trucking Inc",
    "wof:placetype":"venue"
},
  "geometry": {"coordinates":[-112.087929,33.641928],"type":"Point"}
}