{
  "type": "Feature",
  "properties": {
    "addr:full":"933 N Main Ave Tucson AZ 85705",
    "addr:housenumber":"933",
    "addr:postcode":"85705",
    "addr:street":"N Main Ave",
    "iso:country":"US",
    "sg:address":"933 N Main Ave",
    "sg:city":"Tucson",
    "sg:classifiers":[
        {
            "category":"Shopping",
            "subcategory":"Gifts & Souvenirs",
            "type":"Retail Goods"
        }
    ],
    "sg:phone":"+1 520 882 8886",
    "sg:postcode":"85705",
    "sg:province":"AZ",
    "sg:tags":[
        "merchandise"
    ],
    "wof:name":"V Rock Shop",
    "wof:placetype":"venue"
},
  "geometry": {"coordinates":[-110.978014,32.235658],"type":"Point"}
}