{
  "type": "Feature",
  "properties": {
    "iso:country":"US",
    "sg:address":"2455 E Broadway Rd",
    "sg:city":"Mesa",
    "sg:classifiers":[
        {
            "category":"Professional",
            "subcategory":"Management & Consulting",
            "type":"Services"
        }
    ],
    "sg:phone":"+1 480 615 0681",
    "sg:postcode":"85204",
    "sg:province":"AZ",
    "sg:tags":[
        "medical",
        "administration",
        "business"
    ],
    "wof:name":"All Medical Billing",
    "wof:placetype":"venue"
},
  "geometry": {"coordinates":[-111.776444,33.408069],"type":"Point"}
}