{
  "type": "Feature",
  "properties": {
    "iso:country":"US",
    "sg:address":"20508 E Conestoga Dr",
    "sg:city":"Mayer",
    "sg:classifiers":[
        {
            "category":"Utilities",
            "subcategory":"Telephone",
            "type":"Services"
        }
    ],
    "sg:phone":"+1 928 632 8347",
    "sg:postcode":"86333",
    "sg:province":"AZ",
    "sg:tags":[
        "communications"
    ],
    "wof:name":"Gary R Halverson",
    "wof:placetype":"venue"
},
  "geometry": {"coordinates":[-112.101488,34.314753],"type":"Point"}
}