{
  "type": "Feature",
  "properties": {
    "iso:country":"US",
    "sg:address":"4820 W Brown St",
    "sg:city":"Glendale",
    "sg:classifiers":[
        {
            "category":"Professional",
            "type":"Services"
        }
    ],
    "sg:phone":"+1 623 939 7076",
    "sg:postcode":"85302",
    "sg:province":"AZ",
    "wof:name":"Norman Jim & Co Inc",
    "wof:placetype":"venue"
},
  "geometry": {"coordinates":[-112.16405399999999,33.578397],"type":"Point"}
}