{
  "type": "Feature",
  "properties": {
    "iso:country":"US",
    "sg:address":"10320 W McDowell Road",
    "sg:city":"Avondale",
    "sg:classifiers":[
        {
            "category":"Insurance",
            "subcategory":"Hazard Insurance",
            "type":"Services"
        }
    ],
    "sg:phone":"+1 623 882 8049",
    "sg:postcode":"85323",
    "sg:province":"AZ",
    "wof:name":"American Family Insurance-Freddie Ram",
    "wof:placetype":"venue"
},
  "geometry": {"coordinates":[-112.282899,33.464625],"type":"Point"}
}