{
  "type": "Feature",
  "properties": {
    "iso:country":"US",
    "sg:address":"222 N Central Ave Ste 1110",
    "sg:city":"Phoenix",
    "sg:classifiers":[
        {
            "category":"Government",
            "subcategory":"Office",
            "type":"Public Place"
        }
    ],
    "sg:phone":"+1 602 506 8541",
    "sg:postcode":"85004",
    "sg:province":"AZ",
    "sg:tags":[
        "parish",
        "government-county"
    ],
    "sg:website":"http://www.phxses.com",
    "wof:name":"Maricopa County Government Justice of The Peace",
    "wof:placetype":"venue"
},
  "geometry": {"coordinates":[-112.073827,33.450591],"type":"Point"}
}