{
  "type": "Feature",
  "properties": {
    "addr:full":"13127 W Glendale Ave Luke Afb AZ 85307",
    "addr:housenumber":"13127",
    "addr:postcode":"85307",
    "addr:street":"W Glendale Ave",
    "iso:country":"US",
    "sg:address":"13127 W Glendale Ave",
    "sg:city":"Luke Afb",
    "sg:classifiers":[
        {
            "category":"Autos & Motor Vehicles",
            "subcategory":"Auto Supplies",
            "type":"Retail Goods"
        }
    ],
    "sg:phone":"+1 623 536 9974",
    "sg:postcode":"85307",
    "sg:province":"AZ",
    "sg:tags":[
        "tire"
    ],
    "wof:name":"Coyote Tire & Automotive",
    "wof:placetype":"venue"
},
  "geometry": {"coordinates":[-112.342445,33.536653],"type":"Point"}
}