{
  "type": "Feature",
  "properties": {
    "addr:full":"2500 N Rosemont Blvd Tucson AZ 85712",
    "addr:housenumber":"2500",
    "addr:postcode":"85712",
    "addr:street":"N Rosemont Blvd",
    "iso:country":"US",
    "sg:address":"2500 N Rosemont Blvd",
    "sg:city":"Tucson",
    "sg:classifiers":[
        {
            "category":"Health Services",
            "subcategory":"Nursing And Care Facility",
            "type":"Services"
        }
    ],
    "sg:phone":"+1 520 320 6554",
    "sg:postcode":"85712",
    "sg:province":"AZ",
    "sg:tags":[
        "home",
        "retirement",
        "community"
    ],
    "wof:name":"Forwin At Tucson",
    "wof:placetype":"venue"
},
  "geometry": {"coordinates":[-110.883932,32.251622],"type":"Point"}
}