{
  "type": "Feature",
  "properties": {
    "iso:country":"US",
    "sg:address":"1600 S 52nd St",
    "sg:city":"Tempe",
    "sg:classifiers":[
        {
            "category":"Professional",
            "type":"Services"
        }
    ],
    "sg:phone":"+1 480 829 9617",
    "sg:postcode":"85281",
    "sg:province":"AZ",
    "wof:name":"Janet Moore",
    "wof:placetype":"venue"
},
  "geometry": {"coordinates":[-111.969528,33.409501],"type":"Point"}
}