{
  "type": "Feature",
  "properties": {
    "iso:country":"US",
    "sg:address":"3646 E Ray Rd",
    "sg:city":"Phoenix",
    "sg:classifiers":[
        {
            "category":"Health Services",
            "subcategory":"Clinic",
            "type":"Services"
        }
    ],
    "sg:phone":"+1 480 899 4280",
    "sg:postcode":"85044",
    "sg:province":"AZ",
    "sg:tags":[
        "information",
        "alcoholism",
        "treatment"
    ],
    "wof:name":"Therapy Network",
    "wof:placetype":"venue"
},
  "geometry": {"coordinates":[-112.00367199999999,33.315979],"type":"Point"}
}