{
  "type": "Feature",
  "properties": {
    "addr:full":"6835 S Willow Dr Tempe AZ 85283",
    "addr:housenumber":"6835",
    "addr:postcode":"85283",
    "addr:street":"S Willow Dr",
    "iso:country":"US",
    "sg:address":"6835 S Willow Dr",
    "sg:city":"Tempe",
    "sg:classifiers":[
        {
            "category":"Professional",
            "subcategory":"Computer Services",
            "type":"Services"
        }
    ],
    "sg:phone":"+1 480 343 5847",
    "sg:postcode":"85283",
    "sg:province":"AZ",
    "sg:tags":[
        "related"
    ],
    "wof:name":"Latino Tech",
    "wof:placetype":"venue"
},
  "geometry": {"coordinates":[-111.914841,33.358248],"type":"Point"}
}