{
  "type": "Feature",
  "properties": {
    "iso:country":"US",
    "sg:address":"10320 N 84th Ave",
    "sg:city":"Peoria",
    "sg:classifiers":[
        {
            "category":"Organizations",
            "subcategory":"Religious Organization",
            "type":"Services"
        }
    ],
    "sg:phone":"+1 623 486 8665",
    "sg:postcode":"85345",
    "sg:province":"AZ",
    "sg:tags":[
        "church"
    ],
    "wof:name":"St Haralambos Greek Orthodox",
    "wof:placetype":"venue"
},
  "geometry": {"coordinates":[-112.239891,33.579208],"type":"Point"}
}