{
  "type": "Feature",
  "properties": {
    "iso:country":"US",
    "sg:address":"237 S Date Ste A",
    "sg:city":"Mesa",
    "sg:classifiers":[
        {
            "category":"Building & Trades",
            "subcategory":"Landscaping Services",
            "type":"Services"
        }
    ],
    "sg:phone":"+1 480 898 9005",
    "sg:postcode":"85210",
    "sg:province":"AZ",
    "sg:tags":[
        "environmental",
        "remediation",
        "services-site"
    ],
    "wof:name":"Hr & E",
    "wof:placetype":"venue"
},
  "geometry": {"coordinates":[-111.844181,33.410853],"type":"Point"}
}