{
  "type": "Feature",
  "properties": {
    "iso:country":"US",
    "sg:address":"4602 W Elwood St",
    "sg:city":"Phoenix",
    "sg:classifiers":[
        {
            "category":"Building & Trades",
            "subcategory":"Construction",
            "type":"Services"
        }
    ],
    "sg:phone":"+1 602 346 1700",
    "sg:postcode":"85043",
    "sg:province":"AZ",
    "sg:tags":[
        "roofing",
        "industrial",
        "contractors-commercial",
        "contractor"
    ],
    "wof:name":"Eagle Roofing Products Southwest",
    "wof:placetype":"venue"
},
  "geometry": {"coordinates":[-112.151903,33.415329],"type":"Point"}
}