{
  "type": "Feature",
  "properties": {
    "iso:country":"US",
    "sg:address":"7317 W Williams St",
    "sg:city":"Phoenix",
    "sg:classifiers":[
        {
            "category":"Utilities",
            "subcategory":"Electric",
            "type":"Services"
        },
        {
            "category":"Building & Trades",
            "subcategory":"Electrical",
            "type":"Services"
        }
    ],
    "sg:phone":"+1 480 202 2804",
    "sg:postcode":"85043",
    "sg:province":"AZ",
    "sg:tags":[
        "electrician"
    ],
    "sg:website":"http://www.srvelectric.com",
    "wof:name":"SRV Electric",
    "wof:placetype":"venue"
},
  "geometry": {"coordinates":[-112.217867,33.420887],"type":"Point"}
}