{
  "type": "Feature",
  "properties": {
    "iso:country":"US",
    "sg:address":"325 S Davis",
    "sg:city":"Mesa",
    "sg:classifiers":[
        {
            "category":"Professional",
            "type":"Services"
        }
    ],
    "sg:phone":"+1 480 964 6382",
    "sg:postcode":"85210",
    "sg:province":"AZ",
    "sg:tags":[
        "stamping",
        "metal"
    ],
    "wof:name":"Auer Precision Stamping Co",
    "wof:placetype":"venue"
},
  "geometry": {"coordinates":[-111.85431699999999,33.409181],"type":"Point"}
}