{
  "type": "Feature",
  "properties": {
    "iso:country":"US",
    "sg:address":"12025 N Saguaro Blvd",
    "sg:city":"Fountain Hills",
    "sg:classifiers":[
        {
            "category":"Home & Garden",
            "subcategory":"Garden Supply",
            "type":"Retail Goods"
        }
    ],
    "sg:phone":"+1 480 837 8131",
    "sg:postcode":"85268",
    "sg:province":"AZ",
    "wof:name":"Verde Valley Nursery",
    "wof:placetype":"venue"
},
  "geometry": {"coordinates":[-111.715101,33.595059],"type":"Point"}
}