{
  "type": "Feature",
  "properties": {
    "iso:country":"US",
    "sg:address":"6210 E Thomas Rd Ste 301",
    "sg:city":"Scottsdale",
    "sg:classifiers":[
        {
            "category":"Home & Garden",
            "subcategory":"Home Furnishings",
            "type":"Retail Goods"
        },
        {
            "category":"Professional",
            "subcategory":"Business Services",
            "type":"Services"
        },
        {
            "category":"Real Estate",
            "subcategory":"Architect",
            "type":"Services"
        }
    ],
    "sg:phone":"+1 480 921 0629",
    "sg:postcode":"85251",
    "sg:province":"AZ",
    "sg:tags":[
        "designer",
        "residential",
        "drafting",
        "planning",
        "design"
    ],
    "wof:name":"Fine Line Designs",
    "wof:placetype":"venue"
},
  "geometry": {"coordinates":[-111.948648,33.480163],"type":"Point"}
}