{
  "type": "Feature",
  "properties": {
    "iso:country":"US",
    "sg:address":"710 E Lodge Dr",
    "sg:city":"Tempe",
    "sg:classifiers":[
        {
            "category":"Wholesale",
            "subcategory":"Books, Periodicals, & Newspapers",
            "type":"Manufacturing & Wholesale Goods"
        }
    ],
    "sg:phone":"+1 480 752 8937",
    "sg:postcode":"85283",
    "sg:province":"AZ",
    "sg:tags":[
        "publisher",
        "book"
    ],
    "wof:name":"Hayden's Ferry Music Publishing",
    "wof:placetype":"venue"
},
  "geometry": {"coordinates":[-111.92925,33.359357],"type":"Point"}
}