{
  "type": "Feature",
  "properties": {
    "iso:country":"US",
    "sg:address":"2141 E Camelback Rd",
    "sg:city":"Phoenix",
    "sg:classifiers":[
        {
            "category":"Health Services",
            "subcategory":"Doctor",
            "type":"Services"
        }
    ],
    "sg:phone":"+1 602 354 0039",
    "sg:postcode":"85016",
    "sg:province":"AZ",
    "sg:tags":[
        "medical",
        "imaging"
    ],
    "wof:name":"Biltmore MRI",
    "wof:placetype":"venue"
},
  "geometry": {"coordinates":[-112.035256,33.509215],"type":"Point"}
}