{
  "type": "Feature",
  "properties": {
    "addr:full":"307 N Central Ave Avondale AZ 85323",
    "addr:housenumber":"307",
    "addr:postcode":"85323",
    "addr:street":"N Central Ave",
    "iso:country":"US",
    "sg:address":"307 N Central Ave",
    "sg:city":"Avondale",
    "sg:classifiers":[
        {
            "category":"Professional",
            "subcategory":"Accounting & Tax Preparation",
            "type":"Services"
        }
    ],
    "sg:phone":"+1 623 882 8855",
    "sg:postcode":"85323",
    "sg:province":"AZ",
    "sg:tags":[
        "return",
        "filing"
    ],
    "wof:name":"Dinerito Express",
    "wof:placetype":"venue"
},
  "geometry": {"coordinates":[-112.349604,33.438889],"type":"Point"}
}