{
  "type": "Feature",
  "properties": {
    "iso:country":"US",
    "sg:address":"1395 N 19th Ave",
    "sg:city":"Phoenix",
    "sg:classifiers":[
        {
            "category":"Retail",
            "subcategory":"Auto Repair",
            "type":"Services"
        }
    ],
    "sg:phone":"+1 602 256 0838",
    "sg:postcode":"85009",
    "sg:province":"AZ",
    "sg:tags":[
        "injection",
        "part",
        "engines-diesel-fuel"
    ],
    "wof:name":"Engine Warehouse Inc",
    "wof:placetype":"venue"
},
  "geometry": {"coordinates":[-112.099991,33.463932],"type":"Point"}
}