{
  "type": "Feature",
  "properties": {
    "iso:country":"US",
    "sg:address":"5141 N 40th St",
    "sg:city":"Phoenix",
    "sg:classifiers":[
        {
            "category":"Real Estate",
            "subcategory":"Real Estate Agent",
            "type":"Services"
        }
    ],
    "sg:phone":"+1 602 468 3900",
    "sg:postcode":"85018",
    "sg:province":"AZ",
    "wof:name":"Fountainhead Assoc",
    "wof:placetype":"venue"
},
  "geometry": {"coordinates":[-111.995212,33.511695],"type":"Point"}
}