{
  "type": "Feature",
  "properties": {
    "iso:country":"US",
    "sg:address":"6016 N 185th Ave",
    "sg:city":"Waddell",
    "sg:classifiers":[
        {
            "category":"Wholesale",
            "subcategory":"Electrical",
            "type":"Manufacturing & Wholesale Goods"
        }
    ],
    "sg:phone":"+1 623 853 9822",
    "sg:postcode":"85355",
    "sg:province":"AZ",
    "sg:tags":[
        "equipment",
        "distribute"
    ],
    "wof:name":"Powerserver",
    "wof:placetype":"venue"
},
  "geometry": {"coordinates":[-112.457087,33.525184],"type":"Point"}
}