{
  "type": "Feature",
  "properties": {
    "addr:full":"2521 Village Dr Cottonwood AZ 86326",
    "addr:housenumber":"2521",
    "addr:postcode":"86326",
    "addr:street":"Village Dr",
    "iso:country":"US",
    "sg:address":"2521 Village Dr",
    "sg:city":"Cottonwood",
    "sg:classifiers":[
        {
            "category":"Manufacturing",
            "subcategory":"Printing",
            "type":"Manufacturing & Wholesale Goods"
        }
    ],
    "sg:phone":"+1 928 646 5734",
    "sg:postcode":"86326",
    "sg:province":"AZ",
    "sg:tags":[
        "screen"
    ],
    "wof:name":"Rokzoo Screen Printers",
    "wof:placetype":"venue"
},
  "geometry": {"coordinates":[-111.982776,34.693259],"type":"Point"}
}