{
  "type": "Feature",
  "properties": {
    "iso:country":"US",
    "sg:address":"756 S Tohono Ridge Pl",
    "sg:city":"Tucson",
    "sg:classifiers":[
        {
            "category":"Professional",
            "type":"Services"
        },
        {
            "category":"Professional",
            "subcategory":"Management & Consulting",
            "type":"Services"
        }
    ],
    "sg:phone":"+1 520 620 3500",
    "sg:postcode":"85745",
    "sg:province":"AZ",
    "sg:tags":[
        "consultant",
        "business"
    ],
    "wof:name":"Bright Enterprises Inc",
    "wof:placetype":"venue"
},
  "geometry": {"coordinates":[-111.047878,32.211149],"type":"Point"}
}