{
  "type": "Feature",
  "properties": {
    "iso:country":"US",
    "sg:address":"1532 E Peregrine Trl",
    "sg:city":"Casa Grande",
    "sg:classifiers":[
        {
            "category":"Insurance",
            "subcategory":"Insurance Agent",
            "type":"Services"
        }
    ],
    "sg:phone":"+1 520 423 2191",
    "sg:postcode":"85222",
    "sg:province":"AZ",
    "wof:name":"Woodruff Insurance",
    "wof:placetype":"venue"
},
  "geometry": {"coordinates":[-111.721298,32.885732],"type":"Point"}
}