{
  "type": "Feature",
  "properties": {
    "iso:country":"US",
    "sg:address":"120 S Houghton Rd",
    "sg:city":"Tucson",
    "sg:classifiers":[
        {
            "category":"Personal",
            "subcategory":"Beauty Salon",
            "type":"Services"
        }
    ],
    "sg:phone":"+1 520 751 7454",
    "sg:postcode":"85748",
    "sg:province":"AZ",
    "wof:name":"Cost Cutters Family Hair Care",
    "wof:placetype":"venue"
},
  "geometry": {"coordinates":[-110.772774,32.220076],"type":"Point"}
}