{
  "type": "Feature",
  "properties": {
    "iso:country":"US",
    "sg:address":"3205 N Delaware St",
    "sg:city":"Chandler",
    "sg:classifiers":[
        {
            "category":"Manufacturing",
            "subcategory":"Tools & Machinery",
            "type":"Manufacturing & Wholesale Goods"
        }
    ],
    "sg:phone":"+1 480 892 0950",
    "sg:postcode":"85225",
    "sg:province":"AZ",
    "sg:tags":[
        "machine",
        "shop"
    ],
    "wof:name":"GEC Engineering",
    "wof:placetype":"venue"
},
  "geometry": {"coordinates":[-111.836292,33.355057],"type":"Point"}
}