{
  "type": "Feature",
  "properties": {
    "addr:full":"2330 W Main St Mesa AZ 85201",
    "addr:housenumber":"2330",
    "addr:postcode":"85201",
    "addr:street":"W Main St",
    "iso:country":"US",
    "sg:address":"2330 W Main St",
    "sg:city":"Mesa",
    "sg:classifiers":[
        {
            "category":"Retail",
            "subcategory":"Auto Repair",
            "type":"Services"
        }
    ],
    "sg:phone":"+1 480 921 9700",
    "sg:postcode":"85201",
    "sg:province":"AZ",
    "sg:tags":[
        "repairing",
        "automobile"
    ],
    "sg:website":"http://www.germanautotec.com",
    "wof:name":"German Autotec",
    "wof:placetype":"venue"
},
  "geometry": {"coordinates":[-111.88208,33.414902],"type":"Point"}
}