{
  "type": "Feature",
  "properties": {
    "addr:full":"1955 W Grant Rd Tucson AZ 85745",
    "addr:housenumber":"1955",
    "addr:postcode":"85745",
    "addr:street":"W Grant Rd",
    "iso:country":"US",
    "sg:address":"1955 W Grant Rd",
    "sg:city":"Tucson",
    "sg:classifiers":[
        {
            "category":"Banks & Credit Unions",
            "subcategory":"Bank",
            "type":"Services"
        }
    ],
    "sg:phone":"+1 520 207 3680",
    "sg:postcode":"85745",
    "sg:province":"AZ",
    "sg:tags":[
        "loan",
        "real estate"
    ],
    "wof:name":"First Finance",
    "wof:placetype":"venue"
},
  "geometry": {"coordinates":[-111.00702699999999,32.250516],"type":"Point"}
}