{
  "type": "Feature",
  "properties": {
    "iso:country":"US",
    "sg:address":"116 N Lindsay Rd",
    "sg:city":"Mesa",
    "sg:classifiers":[
        {
            "category":"Food & Beverages",
            "subcategory":"Bakery",
            "type":"Retail Goods"
        }
    ],
    "sg:phone":"+1 480 834 0133",
    "sg:postcode":"85213",
    "sg:province":"AZ",
    "sg:tags":[
        "doughnut"
    ],
    "wof:name":"19th Donut Hole",
    "wof:placetype":"venue"
},
  "geometry": {"coordinates":[-111.771133,33.4166],"type":"Point"}
}