{
  "type": "Feature",
  "properties": {
    "iso:country":"US",
    "sg:address":"429 E Broadway Rd",
    "sg:city":"Mesa",
    "sg:classifiers":[
        {
            "category":"Retail",
            "subcategory":"Auto Repair",
            "type":"Services"
        }
    ],
    "sg:phone":"+1 480 964 6555",
    "sg:postcode":"85204",
    "sg:province":"AZ",
    "sg:tags":[
        "repairing",
        "automobile"
    ],
    "wof:name":"Gonz'o Plus Auto Repair Ctr",
    "wof:placetype":"venue"
},
  "geometry": {"coordinates":[-111.822801,33.407694],"type":"Point"}
}