{
  "type": "Feature",
  "properties": {
    "addr:full":"8351 N Cracker Barrel Rd Tucson AZ 85743",
    "addr:housenumber":"8351",
    "addr:postcode":"85743",
    "addr:street":"N Cracker Barrel Rd",
    "iso:country":"US",
    "sg:address":"8351 N Cracker Barrel Rd",
    "sg:city":"Tucson",
    "sg:classifiers":[
        {
            "category":"Travel",
            "subcategory":"Hotels & Motels",
            "type":"Entertainment"
        }
    ],
    "sg:phone":"+1 520 572 0300",
    "sg:postcode":"85743",
    "sg:province":"AZ",
    "wof:name":"Super 8 Motel",
    "wof:placetype":"venue"
},
  "geometry": {"coordinates":[-111.09201,32.358471],"type":"Point"}
}