{
  "type": "Feature",
  "properties": {
    "iso:country":"US",
    "sg:address":"7 Plaza Rd",
    "sg:city":"Tubac",
    "sg:classifiers":[
        {
            "category":"Retail",
            "subcategory":"Portrait Studio",
            "type":"Services"
        },
        {
            "category":"Professional",
            "subcategory":"Art Services",
            "type":"Services"
        }
    ],
    "sg:phone":"+1 520 398 2369",
    "sg:postcode":"85646",
    "sg:province":"AZ",
    "sg:tags":[
        "rental",
        "photographers-portrait",
        "photographic",
        "darkroom"
    ],
    "sg:website":"http://www.tubacrugs.com",
    "wof:name":"Wilson, Walter Portrait Studio",
    "wof:placetype":"venue"
},
  "geometry": {"coordinates":[-111.048111,31.61314],"type":"Point"}
}