{
  "type": "Feature",
  "properties": {
    "addr:full":"9716 E Riggs Rd Sun Lakes AZ 85248",
    "addr:housenumber":"9716",
    "addr:postcode":"85248",
    "addr:street":"E Riggs Rd",
    "iso:country":"US",
    "sg:address":"9716 E Riggs Rd",
    "sg:city":"Sun Lakes",
    "sg:classifiers":[
        {
            "category":"Retail",
            "subcategory":"Auto Repair",
            "type":"Services"
        }
    ],
    "sg:phone":"+1 480 895 0881",
    "sg:postcode":"85248",
    "sg:province":"AZ",
    "sg:tags":[
        "repairing",
        "automobile"
    ],
    "wof:name":"Sun Devil Auto",
    "wof:placetype":"venue"
},
  "geometry": {"coordinates":[-111.87303300000001,33.218218],"type":"Point"}
}