{
  "type": "Feature",
  "properties": {
    "iso:country":"US",
    "sg:address":"924 E 8th St",
    "sg:city":"Mesa",
    "sg:classifiers":[
        {
            "category":"Retail",
            "subcategory":"Repair Shop",
            "type":"Services"
        }
    ],
    "sg:phone":"+1 480 898 9229",
    "sg:postcode":"85203",
    "sg:province":"AZ",
    "wof:name":"Garcia S Lawnmower Main",
    "wof:placetype":"venue"
},
  "geometry": {"coordinates":[-111.81210900000001,33.429626],"type":"Point"}
}