{
  "type": "Feature",
  "properties": {
    "iso:country":"US",
    "sg:address":"13635 E Wethersfield Rd",
    "sg:city":"Scottsdale",
    "sg:classifiers":[
        {
            "category":"Wholesale",
            "subcategory":"Chemicals & Plastics",
            "type":"Manufacturing & Wholesale Goods"
        }
    ],
    "sg:phone":"+1 480 314 0930",
    "sg:postcode":"85259",
    "sg:province":"AZ",
    "wof:name":"Seventeen Plus L L C",
    "wof:placetype":"venue"
},
  "geometry": {"coordinates":[-111.785698,33.5975],"type":"Point"}
}