{
  "type": "Feature",
  "properties": {
    "iso:country":"US",
    "sg:address":"2570 E Cherrywood Pl",
    "sg:city":"Chandler",
    "sg:classifiers":[
        {
            "category":"Building & Trades",
            "subcategory":"Construction",
            "type":"Services"
        }
    ],
    "sg:phone":"+1 480 857 3551",
    "sg:postcode":"85249",
    "sg:province":"AZ",
    "sg:tags":[
        "home",
        "builder"
    ],
    "sg:website":"www.ocotilloconstruction.com",
    "wof:name":"Ocotillo Construction Co",
    "wof:placetype":"venue"
},
  "geometry": {"coordinates":[-111.796835,33.232824],"type":"Point"}
}