{
  "type": "Feature",
  "properties": {
    "iso:country":"US",
    "sg:address":"1781 E State Route 69",
    "sg:city":"Prescott",
    "sg:classifiers":[
        {
            "category":"Restaurant",
            "type":"Food & Drink"
        }
    ],
    "sg:menulink":"http://www.allmenus.com/az/prescott/128969-subway/menu/",
    "sg:phone":"+1 928 771 0066",
    "sg:postcode":"86301",
    "sg:province":"AZ",
    "sg:tags":[
        "american",
        "sandwich"
    ],
    "wof:name":"Subway",
    "wof:placetype":"venue"
},
  "geometry": {"coordinates":[-112.426463,34.552694],"type":"Point"}
}