{
  "type": "Feature",
  "properties": {
    "addr:full":"2015 N Dobson Rd Ste 14 Chandler AZ 85224",
    "addr:housenumber":"2015;14",
    "addr:postcode":"85224",
    "addr:street":"N Dobson Rd Ste",
    "iso:country":"US",
    "sg:address":"2015 N Dobson Rd Ste 14",
    "sg:city":"Chandler",
    "sg:classifiers":[
        {
            "category":"Health Services",
            "subcategory":"Health Practitioner",
            "type":"Services"
        }
    ],
    "sg:phone":"+1 480 857 8911",
    "sg:postcode":"85224",
    "sg:province":"AZ",
    "sg:tags":[
        "acupuncture"
    ],
    "wof:name":"Lee & Lee Acupuncture",
    "wof:placetype":"venue"
},
  "geometry": {"coordinates":[-111.87599899999999,33.3353],"type":"Point"}
}