{
  "type": "Feature",
  "properties": {
    "addr:full":"7407 W Robin Ln Glendale AZ 85310",
    "addr:housenumber":"7407",
    "addr:postcode":"85310",
    "addr:street":"W Robin Ln",
    "iso:country":"US",
    "sg:address":"7407 W Robin Ln",
    "sg:city":"Glendale",
    "sg:classifiers":[
        {
            "category":"Professional",
            "type":"Services"
        }
    ],
    "sg:phone":"+1 623 561 7831",
    "sg:postcode":"85310",
    "sg:province":"AZ",
    "wof:name":"Advanced Semicdtr Tech LLC",
    "wof:placetype":"venue"
},
  "geometry": {"coordinates":[-112.21964199999999,33.686526],"type":"Point"}
}