{
  "type": "Feature",
  "properties": {
    "iso:country":"US",
    "sg:address":"7407 W Robin Ln",
    "sg:city":"Glendale",
    "sg:classifiers":[
        {
            "category":"Professional",
            "type":"Services"
        }
    ],
    "sg:phone":"+1 623 561 7831",
    "sg:postcode":"85310",
    "sg:province":"AZ",
    "wof:name":"Advanced Semicdtr Tech LLC",
    "wof:placetype":"venue"
},
  "geometry": {"coordinates":[-112.219642,33.686526],"type":"Point"}
}