{
  "type": "Feature",
  "properties": {
    "iso:country":"US",
    "sg:address":"121 E Birch Ave",
    "sg:city":"Flagstaff",
    "sg:classifiers":[
        {
            "category":"Professional",
            "subcategory":"Lawyer & Legal Services",
            "type":"Services"
        }
    ],
    "sg:phone":"+1 928 774 4321",
    "sg:postcode":"86001",
    "sg:province":"AZ",
    "sg:tags":[
        "attorney"
    ],
    "wof:name":"Gary E Robbins",
    "wof:placetype":"venue"
},
  "geometry": {"coordinates":[-111.64703,35.198908],"type":"Point"}
}