{
  "type": "Feature",
  "properties": {
    "addr:full":"627 E Seattle Slew Ln Gilbert AZ 85296",
    "addr:housenumber":"627",
    "addr:postcode":"85296",
    "addr:street":"E Seattle Slew Ln",
    "iso:country":"US",
    "sg:address":"627 E Seattle Slew Ln",
    "sg:city":"Gilbert",
    "sg:classifiers":[
        {
            "category":"Professional",
            "subcategory":"Management & Consulting",
            "type":"Services"
        }
    ],
    "sg:phone":"+1 480 813 8087",
    "sg:postcode":"85296",
    "sg:province":"AZ",
    "sg:tags":[
        "training",
        "sales"
    ],
    "wof:name":"PROCESS Corp",
    "wof:placetype":"venue"
},
  "geometry": {"coordinates":[-111.77632,33.3451],"type":"Point"}
}