{
  "type": "Feature",
  "properties": {
    "iso:country":"US",
    "sg:address":"28401 N 55th St",
    "sg:city":"Cave Creek",
    "sg:classifiers":[
        {
            "category":"Education",
            "subcategory":"Special Training",
            "type":"Public Place"
        }
    ],
    "sg:phone":"+1 480 502 5357",
    "sg:postcode":"85331",
    "sg:province":"AZ",
    "sg:tags":[
        "self",
        "motivational",
        "improvement"
    ],
    "wof:name":"Jillian Ministries",
    "wof:placetype":"venue"
},
  "geometry": {"coordinates":[-111.962856,33.74247],"type":"Point"}
}