{
  "type": "Feature",
  "properties": {
    "addr:full":"2602 N 31st Ave Phoenix AZ 85009",
    "addr:housenumber":"2602",
    "addr:postcode":"85009",
    "addr:street":"N 31St Ave",
    "iso:country":"US",
    "sg:address":"2602 N 31st Ave",
    "sg:city":"Phoenix",
    "sg:classifiers":[
        {
            "category":"Autos & Motor Vehicles",
            "subcategory":"Automobile Sales",
            "type":"Retail Goods"
        },
        {
            "category":"Autos & Motor Vehicles",
            "subcategory":"Auto Supplies",
            "type":"Retail Goods"
        },
        {
            "category":"Sports & Exercise",
            "subcategory":"Race Track",
            "type":"Entertainment"
        }
    ],
    "sg:phone":"+1 602 278 0450",
    "sg:postcode":"85009",
    "sg:province":"AZ",
    "sg:tags":[
        "car",
        "equipment",
        "performance",
        "new",
        "racing"
    ],
    "wof:name":"Ellis Racing Enterprise",
    "wof:placetype":"venue"
},
  "geometry": {"coordinates":[-112.125731,33.476882],"type":"Point"}
}