{
  "type": "Feature",
  "properties": {
    "iso:country":"US",
    "sg:address":"4209 N 19th St",
    "sg:city":"Phoenix",
    "sg:classifiers":[
        {
            "category":"Shopping",
            "subcategory":"Jewelry",
            "type":"Retail Goods"
        },
        {
            "category":"Manufacturing",
            "subcategory":"Jewelry",
            "type":"Manufacturing & Wholesale Goods"
        }
    ],
    "sg:phone":"+1 602 277 3929",
    "sg:postcode":"85016",
    "sg:province":"AZ",
    "sg:tags":[
        "stone",
        "jewelers-wholesale",
        "precious",
        "semi-precious",
        "manufacturer"
    ],
    "wof:name":"Fancy This",
    "wof:placetype":"venue"
},
  "geometry": {"coordinates":[-112.041098,33.496593],"type":"Point"}
}