{
  "type": "Feature",
  "properties": {
    "addr:full":"6062 E Speedway Blvd Tucson AZ 85712",
    "addr:housenumber":"6062",
    "addr:postcode":"85712",
    "addr:street":"E Speedway Blvd",
    "iso:country":"US",
    "sg:address":"6062 E Speedway Blvd",
    "sg:city":"Tucson",
    "sg:classifiers":[
        {
            "category":"Home & Garden",
            "subcategory":"Building Materials",
            "type":"Retail Goods"
        }
    ],
    "sg:phone":"+1 520 745 0300",
    "sg:postcode":"85712",
    "sg:province":"AZ",
    "sg:tags":[
        "plumbing",
        "fixture",
        "supply"
    ],
    "wof:name":"Naughton's",
    "wof:placetype":"venue"
},
  "geometry": {"coordinates":[-110.863568,32.236062],"type":"Point"}
}