{
  "type": "Feature",
  "properties": {
    "iso:country":"US",
    "sg:address":"20623 E Excelsior Ave",
    "sg:city":"Queen Creek",
    "sg:classifiers":[
        {
            "category":"Retail",
            "subcategory":"Animal Services",
            "type":"Services"
        }
    ],
    "sg:phone":"+1 480 855 5688",
    "sg:postcode":"85242",
    "sg:province":"AZ",
    "wof:name":"Aquatic Environments",
    "wof:placetype":"venue"
},
  "geometry": {"coordinates":[-111.637508,33.214585],"type":"Point"}
}