{
  "type": "Feature",
  "properties": {
    "iso:country":"US",
    "sg:address":"8220 N Hayden Rd",
    "sg:city":"Scottsdale",
    "sg:classifiers":[
        {
            "category":"Personal",
            "subcategory":"Beauty Salon",
            "type":"Services"
        }
    ],
    "sg:phone":"+1 480 443 8886",
    "sg:postcode":"85258",
    "sg:province":"AZ",
    "sg:tags":[
        "manicuring"
    ],
    "wof:name":"Hair Et Al Beauty Salon",
    "wof:placetype":"venue"
},
  "geometry": {"coordinates":[-111.898627,33.556686],"type":"Point"}
}