{
  "type": "Feature",
  "properties": {
    "iso:country":"US",
    "sg:address":"20625 W Narramore Rd",
    "sg:city":"Buckeye",
    "sg:classifiers":[
        {
            "category":"Personal",
            "subcategory":"Beauty Salon",
            "type":"Services"
        }
    ],
    "sg:phone":"+1 623 386 1698",
    "sg:postcode":"85326",
    "sg:province":"AZ",
    "sg:tags":[
        "hair",
        "stylist"
    ],
    "wof:name":"Mattie Sedig",
    "wof:placetype":"venue"
},
  "geometry": {"coordinates":[-112.493875,33.333943],"type":"Point"}
}