{
  "type": "Feature",
  "properties": {
    "iso:country":"US",
    "sg:address":"533 E Terrace Ave",
    "sg:city":"Gilbert",
    "sg:classifiers":[
        {
            "category":"Real Estate",
            "subcategory":"Real Estate Agent",
            "type":"Services"
        }
    ],
    "sg:phone":"+1 480 892 4940",
    "sg:postcode":"85234",
    "sg:province":"AZ",
    "wof:name":"Choice One Properties",
    "wof:placetype":"venue"
},
  "geometry": {"coordinates":[-111.779732,33.377693],"type":"Point"}
}