{
  "type": "Feature",
  "properties": {
    "iso:country":"US",
    "sg:address":"1360 W Frontage Rd",
    "sg:city":"Rio Rico",
    "sg:classifiers":[
        {
            "category":"Government",
            "subcategory":"Fire Station",
            "type":"Public Place"
        }
    ],
    "sg:phone":"+1 520 761 1066",
    "sg:postcode":"85648",
    "sg:province":"AZ",
    "sg:tags":[
        "department",
        "protection"
    ],
    "wof:name":"Tubac Peck Canyon Fire Station",
    "wof:placetype":"venue"
},
  "geometry": {"coordinates":[-111.007115,31.485794],"type":"Point"}
}