{
  "type": "Feature",
  "properties": {
    "iso:country":"US",
    "sg:address":"1100 E Apache Blvd",
    "sg:city":"Tempe",
    "sg:classifiers":[
        {
            "category":"Education",
            "subcategory":"Special Training",
            "type":"Public Place"
        }
    ],
    "sg:phone":"+1 480 994 9244",
    "sg:postcode":"85281",
    "sg:province":"AZ",
    "sg:tags":[
        "school",
        "massage"
    ],
    "wof:name":"Southwest Institute Of Healing",
    "wof:placetype":"venue"
},
  "geometry": {"coordinates":[-111.922453,33.414852],"type":"Point"}
}