{
  "type": "Feature",
  "properties": {
    "iso:country":"US",
    "sg:address":"511 E Canterbury Dr",
    "sg:city":"Phoenix",
    "sg:classifiers":[
        {
            "category":"Professional",
            "type":"Services"
        }
    ],
    "sg:phone":"+1 602 548 8029",
    "sg:postcode":"85022",
    "sg:province":"AZ",
    "wof:name":"New West Companies LLC",
    "wof:placetype":"venue"
},
  "geometry": {"coordinates":[-112.067543,33.615512],"type":"Point"}
}