{
  "type": "Feature",
  "properties": {
    "iso:country":"US",
    "sg:address":"3917 E Illini St",
    "sg:city":"Phoenix",
    "sg:classifiers":[
        {
            "category":"Autos & Motor Vehicles",
            "subcategory":"Auto Supplies",
            "type":"Retail Goods"
        },
        {
            "category":"Retail",
            "subcategory":"Auto Repair",
            "type":"Services"
        },
        {
            "category":"Autos & Motor Vehicles",
            "subcategory":"Recreational Vehicle Sales",
            "type":"Retail Goods"
        },
        {
            "category":"Wholesale",
            "subcategory":"Auto Parts",
            "type":"Manufacturing & Wholesale Goods"
        }
    ],
    "sg:phone":"+1 602 437 1476",
    "sg:postcode":"85040",
    "sg:province":"AZ",
    "sg:tags":[
        "engines-rebuild",
        "four",
        "rebuilding",
        "camper",
        "exchange",
        "vehicles-supplies",
        "drive",
        "engine",
        "equipment",
        "wheel",
        "truck"
    ],
    "sg:website":"http://www.alanhall.com",
    "wof:name":"Gear Shop",
    "wof:placetype":"venue"
},
  "geometry": {"coordinates":[-111.997289,33.411813],"type":"Point"}
}