{
  "type": "Feature",
  "properties": {
    "iso:country":"US",
    "sg:address":"1700 E Fort Lowell Rd",
    "sg:city":"Tucson",
    "sg:classifiers":[
        {
            "category":"Professional",
            "subcategory":"Secretarial Services",
            "type":"Services"
        }
    ],
    "sg:phone":"+1 520 326 3371",
    "sg:postcode":"85719",
    "sg:province":"AZ",
    "sg:tags":[
        "convention",
        "court",
        "reporter"
    ],
    "wof:name":"Hunt-Kelly Reporting",
    "wof:placetype":"venue"
},
  "geometry": {"coordinates":[-110.943786,32.264846],"type":"Point"}
}