{
  "type": "Feature",
  "properties": {
    "addr:full":"8880 E Paraiso Dr Scottsdale AZ 85255",
    "addr:housenumber":"8880",
    "addr:postcode":"85255",
    "addr:street":"E Paraiso Dr",
    "iso:country":"US",
    "sg:address":"8880 E Paraiso Dr",
    "sg:city":"Scottsdale",
    "sg:classifiers":[
        {
            "category":"Restaurant",
            "type":"Food & Drink"
        }
    ],
    "sg:phone":"+1 480 419 9529",
    "sg:postcode":"85255",
    "sg:province":"AZ",
    "sg:tags":[
        "eating"
    ],
    "wof:name":"Case Enterprises LLC",
    "wof:placetype":"venue"
},
  "geometry": {"coordinates":[-111.88876999999999,33.693509],"type":"Point"}
}