{
  "type": "Feature",
  "properties": {
    "addr:full":"8777 E Via de Ventura Scottsdale AZ 85258",
    "addr:housenumber":"8777",
    "addr:postcode":"85258",
    "addr:street":"E Via De Ventura",
    "iso:country":"US",
    "sg:address":"8777 E Via de Ventura",
    "sg:city":"Scottsdale",
    "sg:classifiers":[
        {
            "category":"Building & Trades",
            "subcategory":"Electrical",
            "type":"Services"
        }
    ],
    "sg:phone":"+1 480 443 1805",
    "sg:postcode":"85258",
    "sg:province":"AZ",
    "sg:tags":[
        "home",
        "design",
        "system",
        "install"
    ],
    "wof:name":"Csi Automation & Design",
    "wof:placetype":"venue"
},
  "geometry": {"coordinates":[-111.89318,33.553081],"type":"Point"}
}