{
  "type": "Feature",
  "properties": {
    "iso:country":"US",
    "sg:address":"2986 W Hwy 89A",
    "sg:city":"Sedona",
    "sg:classifiers":[
        {
            "category":"Restaurant",
            "type":"Food & Drink"
        }
    ],
    "sg:phone":"+1 928 282 0599",
    "sg:postcode":"86336",
    "sg:province":"AZ",
    "sg:website":"www.thaispices.com",
    "wof:name":"Thai Spices Natural",
    "wof:placetype":"venue"
},
  "geometry": {"coordinates":[-111.811325,34.862195],"type":"Point"}
}