{
  "type": "Feature",
  "properties": {
    "iso:country":"US",
    "sg:address":"6107 N 51st Ave",
    "sg:city":"Glendale",
    "sg:classifiers":[
        {
            "category":"Retail",
            "subcategory":"Auto Repair",
            "type":"Services"
        }
    ],
    "sg:phone":"+1 623 937 2267",
    "sg:postcode":"85301",
    "sg:province":"AZ",
    "sg:tags":[
        "body",
        "automobile",
        "painting"
    ],
    "wof:name":"Angelitos Bodyshop",
    "wof:placetype":"venue"
},
  "geometry": {"coordinates":[-112.168581,33.525806],"type":"Point"}
}