{
  "type": "Feature",
  "properties": {
    "iso:country":"US",
    "sg:address":"115 S Allen",
    "sg:city":"Mesa",
    "sg:classifiers":[
        {
            "category":"Professional",
            "subcategory":"Business Services",
            "type":"Services"
        }
    ],
    "sg:phone":"+1 602 740 7905",
    "sg:postcode":"85204",
    "sg:province":"AZ",
    "sg:tags":[
        "notary",
        "public"
    ],
    "wof:name":"Az Signings",
    "wof:placetype":"venue"
},
  "geometry": {"coordinates":[-111.804039,33.412898],"type":"Point"}
}