{
  "type": "Feature",
  "properties": {
    "iso:country":"US",
    "sg:address":"507 W Thomas Rd",
    "sg:city":"Phoenix",
    "sg:classifiers":[
        {
            "category":"Restaurant",
            "type":"Food & Drink"
        }
    ],
    "sg:phone":"+1 602 269 8181",
    "sg:postcode":"85013",
    "sg:province":"AZ",
    "wof:name":"Cousins Subs",
    "wof:placetype":"venue"
},
  "geometry": {"coordinates":[-112.081745,33.48027],"type":"Point"}
}