{
  "type": "Feature",
  "properties": {
    "addr:full":"23 E Fine Ave Flagstaff AZ 86001",
    "addr:housenumber":"23",
    "addr:postcode":"86001",
    "addr:street":"Fine Ave",
    "iso:country":"US",
    "sg:address":"23 E Fine Ave",
    "sg:city":"Flagstaff",
    "sg:classifiers":[
        {
            "category":"Real Estate",
            "subcategory":"Real Estate Agent",
            "type":"Services"
        }
    ],
    "sg:phone":"+1 928 779 2197",
    "sg:postcode":"86001",
    "sg:province":"AZ",
    "wof:name":"Keepsake Ponderosa Homes LLC",
    "wof:placetype":"venue"
},
  "geometry": {"coordinates":[-111.646383,35.202935],"type":"Point"}
}