{
  "type": "Feature",
  "properties": {
    "iso:country":"US",
    "sg:address":"10601 N 56th St",
    "sg:city":"Scottsdale",
    "sg:classifiers":[
        {
            "category":"Restaurant",
            "type":"Food & Drink"
        }
    ],
    "sg:menulink":"http://www.allmenus.com/az/phoenix/4974-longitude-10601/menu/",
    "sg:phone":"+1 480 443 2119",
    "sg:postcode":"85254",
    "sg:province":"AZ",
    "sg:tags":[
        "american"
    ],
    "wof:name":"Longitude 10601",
    "wof:placetype":"venue"
},
  "geometry": {"coordinates":[-111.960543,33.58272],"type":"Point"}
}