{
  "type": "Feature",
  "properties": {
    "iso:country":"US",
    "sg:address":"8260 E Raintree Dr",
    "sg:city":"Scottsdale",
    "sg:classifiers":[
        {
            "category":"Professional",
            "subcategory":"Accounting & Tax Preparation",
            "type":"Services"
        }
    ],
    "sg:phone":"+1 480 948 1528",
    "sg:postcode":"85260",
    "sg:province":"AZ",
    "sg:tags":[
        "accountant"
    ],
    "wof:name":"Stephen F Ward PC",
    "wof:placetype":"venue"
},
  "geometry": {"coordinates":[-111.9033,33.619065],"type":"Point"}
}