{
  "type": "Feature",
  "properties": {
    "iso:country":"US",
    "sg:address":"5555 Buckboard Trl",
    "sg:city":"Flagstaff",
    "sg:classifiers":[
        {
            "category":"Building & Trades",
            "subcategory":"Construction",
            "type":"Services"
        }
    ],
    "sg:phone":"+1 928 526 0564",
    "sg:postcode":"86004",
    "sg:province":"AZ",
    "sg:tags":[
        "house"
    ],
    "wof:name":"Buckboard Builders",
    "wof:placetype":"venue"
},
  "geometry": {"coordinates":[-111.55045200000001,35.308482],"type":"Point"}
}