{
  "type": "Feature",
  "properties": {
    "iso:country":"US",
    "sg:address":"20804 N 20th Ave",
    "sg:city":"Phoenix",
    "sg:classifiers":[
        {
            "category":"Manufacturing",
            "subcategory":"Rubber & Plastics",
            "type":"Manufacturing & Wholesale Goods"
        }
    ],
    "sg:phone":"+1 623 869 0600",
    "sg:postcode":"85027",
    "sg:province":"AZ",
    "sg:tags":[
        "industrial",
        "mfg",
        "supply",
        "devices",
        "gasket",
        "sealing"
    ],
    "sg:website":"www.cgstech.com",
    "wof:name":"Cgs Technologies Inc",
    "wof:placetype":"venue"
},
  "geometry": {"coordinates":[-112.102425,33.674977],"type":"Point"}
}