{
  "type": "Feature",
  "properties": {
    "iso:country":"US",
    "sg:address":"6914 N Cam Martin",
    "sg:city":"Tucson",
    "sg:classifiers":[
        {
            "category":"Retail",
            "subcategory":"Laundry & Dry Cleaning",
            "type":"Services"
        }
    ],
    "sg:phone":"+1 520 293 9291",
    "sg:postcode":"85741",
    "sg:province":"AZ",
    "sg:tags":[
        "cleaners",
        "rug",
        "carpet"
    ],
    "sg:website":"www.rainbowintl.com",
    "wof:name":"Rainbow International Carpet",
    "wof:placetype":"venue"
},
  "geometry": {"coordinates":[-111.057438,32.337521],"type":"Point"}
}