{
  "type": "Feature",
  "properties": {
    "iso:country":"US",
    "sg:address":"698 W Hillside Ave",
    "sg:city":"Prescott",
    "sg:classifiers":[
        {
            "category":"Retail",
            "subcategory":"Auto Repair",
            "type":"Services"
        }
    ],
    "sg:phone":"+1 928 445 2103",
    "sg:postcode":"86301",
    "sg:province":"AZ",
    "sg:tags":[
        "repairing",
        "automobile"
    ],
    "wof:name":"Jim's Alignment & Brake Svc",
    "wof:placetype":"venue"
},
  "geometry": {"coordinates":[-112.477099,34.553174],"type":"Point"}
}