{
  "type": "Feature",
  "properties": {
    "iso:country":"US",
    "sg:address":"2234 W Jacinto Cir",
    "sg:city":"Mesa",
    "sg:classifiers":[
        {
            "category":"Real Estate",
            "subcategory":"Real Estate Agent",
            "type":"Services"
        }
    ],
    "sg:phone":"+1 602 248 9842",
    "sg:postcode":"85202",
    "sg:province":"AZ",
    "sg:tags":[
        "appraiser"
    ],
    "wof:name":"Desert City Appraisal LLC",
    "wof:placetype":"venue"
},
  "geometry": {"coordinates":[-111.880716,33.379169],"type":"Point"}
}