{
  "type": "Feature",
  "properties": {
    "iso:country":"US",
    "sg:address":"4638 E Shea Blvd",
    "sg:city":"Phoenix",
    "sg:classifiers":[
        {
            "category":"Professional",
            "subcategory":"Advertising",
            "type":"Services"
        },
        {
            "category":"Wholesale",
            "subcategory":"Non-durable Goods",
            "type":"Manufacturing & Wholesale Goods"
        }
    ],
    "sg:phone":"+1 602 996 0006",
    "sg:postcode":"85028",
    "sg:province":"AZ",
    "wof:name":"Commotion Promotions Ltd",
    "wof:placetype":"venue"
},
  "geometry": {"coordinates":[-111.978582,33.582777],"type":"Point"}
}