{
  "type": "Feature",
  "properties": {
    "addr:full":"34522 N Scottsdale Rd Phoenix AZ 85054",
    "addr:housenumber":"34522",
    "addr:postcode":"85054",
    "addr:street":"N Scottsdale Rd",
    "iso:country":"US",
    "sg:address":"34522 N Scottsdale Rd",
    "sg:city":"Phoenix",
    "sg:classifiers":[
        {
            "category":"Building & Trades",
            "subcategory":"Cleaning & Sanitation",
            "type":"Services"
        },
        {
            "category":"Retail",
            "subcategory":"Laundry & Dry Cleaning",
            "type":"Services"
        }
    ],
    "sg:phone":"+1 602 997 4888",
    "sg:postcode":"85054",
    "sg:province":"AZ",
    "sg:tags":[
        "cleaner",
        "floor",
        "rug",
        "contractor",
        "waxing",
        "cleaning-industrial",
        "polishing",
        "janitorial",
        "carpet"
    ],
    "sg:website":"http://www.aprecisionjanitorial.com",
    "wof:name":"A Precision Janitorial",
    "wof:placetype":"venue"
},
  "geometry": {"coordinates":[-111.925377,33.655169],"type":"Point"}
}