{
  "type": "Feature",
  "properties": {
    "iso:country":"US",
    "sg:address":"3201 N 16th St",
    "sg:city":"Phoenix",
    "sg:classifiers":[
        {
            "category":"Social Services",
            "subcategory":"Job Training",
            "type":"Services"
        }
    ],
    "sg:phone":"+1 602 241 1006",
    "sg:postcode":"85016",
    "sg:province":"AZ",
    "sg:tags":[
        "rehabilitation"
    ],
    "wof:name":"Camelback Rehab Assoc",
    "wof:placetype":"venue"
},
  "geometry": {"coordinates":[-112.047651,33.484494],"type":"Point"}
}