{
  "type": "Feature",
  "properties": {
    "addr:full":"2001 E Huntington Dr Flagstaff AZ 86004",
    "addr:housenumber":"2001",
    "addr:postcode":"86004",
    "addr:street":"E Huntington Dr",
    "iso:country":"US",
    "sg:address":"2001 E Huntington Dr",
    "sg:city":"Flagstaff",
    "sg:classifiers":[
        {
            "category":"Wholesale",
            "subcategory":"Construction Materials",
            "type":"Manufacturing & Wholesale Goods"
        }
    ],
    "sg:phone":"+1 928 556 0583",
    "sg:postcode":"86004",
    "sg:province":"AZ",
    "sg:tags":[
        "tile"
    ],
    "wof:name":"Dal-Tile",
    "wof:placetype":"venue"
},
  "geometry": {"coordinates":[-111.627014,35.193918],"type":"Point"}
}