{
  "type": "Feature",
  "properties": {
    "iso:country":"US",
    "sg:address":"10420 N 57th St",
    "sg:city":"Paradise Valley",
    "sg:classifiers":[
        {
            "category":"Real Estate",
            "subcategory":"Real Estate Agent",
            "type":"Services"
        }
    ],
    "sg:phone":"+1 480 991 5985",
    "sg:postcode":"85253",
    "sg:province":"AZ",
    "wof:name":"Re/Max",
    "wof:placetype":"venue"
},
  "geometry": {"coordinates":[-111.958479,33.579898],"type":"Point"}
}