{
  "type": "Feature",
  "properties": {
    "iso:country":"US",
    "sg:address":"11901 E State Rte 69",
    "sg:city":"Dewey",
    "sg:classifiers":[
        {
            "category":"Restaurant",
            "type":"Food & Drink"
        }
    ],
    "sg:phone":"+1 928 772 1124",
    "sg:postcode":"86327",
    "sg:province":"AZ",
    "wof:name":"Screamin Mimi Road House",
    "wof:placetype":"venue"
},
  "geometry": {"coordinates":[-112.256784,34.559204],"type":"Point"}
}