{
  "type": "Feature",
  "properties": {
    "iso:country":"US",
    "sg:address":"7975 N Hayden Rd",
    "sg:city":"Scottsdale",
    "sg:classifiers":[
        {
            "category":"Insurance",
            "subcategory":"Hazard Insurance",
            "type":"Services"
        }
    ],
    "sg:phone":"+1 480 922 0363",
    "sg:postcode":"85250",
    "sg:province":"AZ",
    "sg:tags":[
        "profit",
        "sharing",
        "pension",
        "plan"
    ],
    "sg:website":"www.scottsdalepension.com",
    "wof:name":"Scottsdale Pension Systems Inc",
    "wof:placetype":"venue"
},
  "geometry": {"coordinates":[-111.898848,33.552638],"type":"Point"}
}