{
  "type": "Feature",
  "properties": {
    "iso:country":"US",
    "sg:address":"7064 E 5th Ave",
    "sg:city":"Scottsdale",
    "sg:classifiers":[
        {
            "category":"Manufacturing",
            "subcategory":"Rubber & Plastics",
            "type":"Manufacturing & Wholesale Goods"
        }
    ],
    "sg:phone":"+1 480 946 0007",
    "sg:postcode":"85251",
    "sg:province":"AZ",
    "sg:tags":[
        "stamp",
        "products-manufacturers"
    ],
    "wof:name":"Frenzy Stamper",
    "wof:placetype":"venue"
},
  "geometry": {"coordinates":[-111.929151,33.49799],"type":"Point"}
}