{
  "type": "Feature",
  "properties": {
    "iso:country":"US",
    "sg:address":"1150 N College Ave",
    "sg:city":"Thatcher",
    "sg:classifiers":[
        {
            "category":"Government",
            "subcategory":"Fire Station",
            "type":"Public Place"
        }
    ],
    "sg:phone":"+1 928 428 1200",
    "sg:postcode":"85552",
    "sg:province":"AZ",
    "sg:tags":[
        "department"
    ],
    "wof:name":"Thatcher City Fire Dept",
    "wof:placetype":"venue"
},
  "geometry": {"coordinates":[-109.76108,32.849986],"type":"Point"}
}