{
  "type": "Feature",
  "properties": {
    "iso:country":"US",
    "sg:address":"1724 N Winstel Blvd",
    "sg:city":"Tucson",
    "sg:classifiers":[
        {
            "category":"Insurance",
            "subcategory":"Insurance Agent",
            "type":"Services"
        }
    ],
    "sg:phone":"+1 520 327 6539",
    "sg:postcode":"85716",
    "sg:province":"AZ",
    "wof:name":"Prater & Sons Insurance",
    "wof:placetype":"venue"
},
  "geometry": {"coordinates":[-110.911788,32.246815],"type":"Point"}
}