{
  "type": "Feature",
  "properties": {
    "iso:country":"US",
    "sg:address":"1420 Corona Rd",
    "sg:city":"Fort Mohave",
    "sg:classifiers":[
        {
            "category":"Recreation",
            "subcategory":"Marina",
            "type":"Entertainment"
        }
    ],
    "sg:phone":"+1 928 788 8352",
    "sg:postcode":"86426",
    "sg:province":"AZ",
    "sg:tags":[
        "storage",
        "boat"
    ],
    "wof:name":"Anderson's Boat & Rv STORAGE",
    "wof:placetype":"venue"
},
  "geometry": {"coordinates":[-114.600418,35.010893],"type":"Point"}
}