{
  "type": "Feature",
  "properties": {
    "addr:full":"1433 N Tech Blvd Gilbert AZ 85233",
    "addr:housenumber":"1433",
    "addr:postcode":"85233",
    "addr:street":"N Tech Blvd",
    "iso:country":"US",
    "sg:address":"1433 N Tech Blvd",
    "sg:city":"Gilbert",
    "sg:classifiers":[
        {
            "category":"Manufacturing",
            "subcategory":"Electronics",
            "type":"Manufacturing & Wholesale Goods"
        }
    ],
    "sg:phone":"+1 480 507 8333",
    "sg:postcode":"85233",
    "sg:province":"AZ",
    "sg:tags":[
        "machinery",
        "manufacturer"
    ],
    "wof:name":"Avalon Manufacturing Co",
    "wof:placetype":"venue"
},
  "geometry": {"coordinates":[-111.834414,33.376051],"type":"Point"}
}