{
  "type": "Feature",
  "properties": {
    "iso:country":"US",
    "sg:address":"7425 E Broadway Blvd",
    "sg:city":"Tucson",
    "sg:classifiers":[
        {
            "category":"Retail",
            "subcategory":"Laundry & Dry Cleaning",
            "type":"Services"
        }
    ],
    "sg:phone":"+1 520 751 1214",
    "sg:postcode":"85710",
    "sg:province":"AZ",
    "sg:tags":[
        "cleaners"
    ],
    "sg:website":"www.sparklecleaners.com",
    "wof:name":"Sparkle Cleaners",
    "wof:placetype":"venue"
},
  "geometry": {"coordinates":[-110.832892,32.221062],"type":"Point"}
}