{
  "type": "Feature",
  "properties": {
    "iso:country":"US",
    "sg:address":"552 E Bromley St",
    "sg:city":"Tucson",
    "sg:classifiers":[
        {
            "category":"Real Estate",
            "subcategory":"Real Estate Operator",
            "type":"Services"
        }
    ],
    "sg:phone":"+1 520 292 6374",
    "sg:postcode":"85704",
    "sg:province":"AZ",
    "sg:tags":[
        "management"
    ],
    "wof:name":"Mike Teufel Investments",
    "wof:placetype":"venue"
},
  "geometry": {"coordinates":[-110.964777,32.292919],"type":"Point"}
}