{
  "type": "Feature",
  "properties": {
    "iso:country":"US",
    "sg:address":"3900 E Camelback Rd",
    "sg:city":"Phoenix",
    "sg:classifiers":[
        {
            "category":"Banks & Credit Unions",
            "subcategory":"Bank",
            "type":"Services"
        }
    ],
    "sg:phone":"+1 602 955 7830",
    "sg:postcode":"85018",
    "sg:province":"AZ",
    "sg:tags":[
        "mortgage"
    ],
    "wof:name":"Grdn Mortgage Documents Inc",
    "wof:placetype":"venue"
},
  "geometry": {"coordinates":[-111.995519,33.509936],"type":"Point"}
}