{
  "type": "Feature",
  "properties": {
    "iso:country":"US",
    "sg:address":"8640 E Main St",
    "sg:city":"Mesa",
    "sg:classifiers":[
        {
            "category":"Home & Garden",
            "subcategory":"Building Materials",
            "type":"Retail Goods"
        }
    ],
    "sg:phone":"+1 480 986 5505",
    "sg:postcode":"85207",
    "sg:province":"AZ",
    "sg:tags":[
        "glass",
        "window",
        "plate"
    ],
    "wof:name":"Apache Glass",
    "wof:placetype":"venue"
},
  "geometry": {"coordinates":[-111.645406,33.415224],"type":"Point"}
}