{
  "type": "Feature",
  "properties": {
    "addr:full":"2647 W Baseline Rd Mesa AZ 85202",
    "addr:housenumber":"2647",
    "addr:postcode":"85202",
    "addr:street":"W Baseline Rd",
    "iso:country":"US",
    "sg:address":"2647 W Baseline Rd",
    "sg:city":"Mesa",
    "sg:classifiers":[
        {
            "category":"Shopping",
            "subcategory":"Crafts & Fabrics",
            "type":"Retail Goods"
        }
    ],
    "sg:phone":"+1 480 839 0154",
    "sg:postcode":"85202",
    "sg:province":"AZ",
    "sg:tags":[
        "shop",
        "sewing"
    ],
    "wof:name":"Sally's Fabrics",
    "wof:placetype":"venue"
},
  "geometry": {"coordinates":[-111.891345,33.378396],"type":"Point"}
}