{
  "type": "Feature",
  "properties": {
    "iso:country":"US",
    "sg:address":"717 W Ray Road",
    "sg:city":"Gilbert",
    "sg:classifiers":[
        {
            "category":"Shopping",
            "subcategory":"Pharmacy",
            "type":"Retail Goods"
        }
    ],
    "sg:phone":"+1 480 899 6840",
    "sg:postcode":"85233",
    "sg:province":"AZ",
    "sg:tags":[
        "drugstore"
    ],
    "wof:name":"Osco Drug",
    "wof:placetype":"venue"
},
  "geometry": {"coordinates":[-111.805283,33.320722],"type":"Point"}
}