{
  "type": "Feature",
  "properties": {
    "addr:full":"4626 E Thunderbird Rd Phoenix AZ 85032",
    "addr:housenumber":"4626",
    "addr:postcode":"85032",
    "addr:street":"E Thunderbird Rd",
    "iso:country":"US",
    "sg:address":"4626 E Thunderbird Rd",
    "sg:city":"Phoenix",
    "sg:classifiers":[
        {
            "category":"Wholesale",
            "subcategory":"Home Furnishings",
            "type":"Manufacturing & Wholesale Goods"
        }
    ],
    "sg:phone":"+1 602 953 1338",
    "sg:postcode":"85032",
    "sg:province":"AZ",
    "wof:name":"Tolivers Carpet One",
    "wof:placetype":"venue"
},
  "geometry": {"coordinates":[-111.97819699999999,33.611636],"type":"Point"}
}