{
  "type": "Feature",
  "properties": {
    "iso:country":"US",
    "sg:address":"144 S Mesa Dr",
    "sg:city":"Mesa",
    "sg:classifiers":[
        {
            "category":"Professional",
            "subcategory":"Accounting & Tax Preparation",
            "type":"Services"
        }
    ],
    "sg:phone":"+1 480 649 9550",
    "sg:postcode":"85210",
    "sg:province":"AZ",
    "sg:tags":[
        "accountant"
    ],
    "wof:name":"Theresa Carmichael CPA",
    "wof:placetype":"venue"
},
  "geometry": {"coordinates":[-111.823039,33.411754],"type":"Point"}
}