{
  "type": "Feature",
  "properties": {
    "iso:country":"US",
    "sg:address":"450 W Prince Rd",
    "sg:city":"Tucson",
    "sg:classifiers":[
        {
            "category":"Retail",
            "subcategory":"Auto Repair",
            "type":"Services"
        }
    ],
    "sg:phone":"+1 520 293 7044",
    "sg:postcode":"85705",
    "sg:province":"AZ",
    "sg:tags":[
        "transmission"
    ],
    "wof:name":"Performance Drivetrain",
    "wof:placetype":"venue"
},
  "geometry": {"coordinates":[-110.985865,32.272106],"type":"Point"}
}