{
  "type": "Feature",
  "properties": {
    "addr:full":"2032 E Baseline Rd Mesa AZ 85204",
    "addr:housenumber":"2032",
    "addr:postcode":"85204",
    "addr:street":"E Baseline Rd",
    "iso:country":"US",
    "sg:address":"2032 E Baseline Rd",
    "sg:city":"Mesa",
    "sg:classifiers":[
        {
            "category":"Restaurant",
            "type":"Food & Drink"
        }
    ],
    "sg:menulink":"http://www.allmenus.com/az/phoenix/2444-applebees/menu/",
    "sg:phone":"+1 480 545 4299",
    "sg:postcode":"85204",
    "sg:province":"AZ",
    "sg:tags":[
        "burger",
        "american",
        "sandwich",
        "soup"
    ],
    "wof:name":"Applebee's",
    "wof:placetype":"venue"
},
  "geometry": {"coordinates":[-111.78765,33.378963],"type":"Point"}
}