{
  "type": "Feature",
  "properties": {
    "addr:full":"2225 E 16th St Yuma AZ 85365",
    "addr:housenumber":"2225",
    "addr:postcode":"85365",
    "addr:street":"E 16Th St",
    "iso:country":"US",
    "sg:address":"2225 E 16th St",
    "sg:city":"Yuma",
    "sg:classifiers":[
        {
            "category":"Home & Garden",
            "subcategory":"Home Furnishings",
            "type":"Retail Goods"
        },
        {
            "category":"Home & Garden",
            "subcategory":"Building Materials",
            "type":"Retail Goods"
        },
        {
            "category":"Manufacturing",
            "subcategory":"Glass & Minerals",
            "type":"Manufacturing & Wholesale Goods"
        },
        {
            "category":"Retail",
            "subcategory":"Auto Repair",
            "type":"Services"
        }
    ],
    "sg:phone":"+1 928 782 4632",
    "sg:postcode":"85365",
    "sg:province":"AZ",
    "sg:tags":[
        "plate",
        "glass-auto",
        "windshield",
        "window",
        "mirror"
    ],
    "wof:name":"John's Glass Service",
    "wof:placetype":"venue"
},
  "geometry": {"coordinates":[-114.57052299999999,32.698834],"type":"Point"}
}