{
  "type": "Feature",
  "properties": {
    "iso:country":"US",
    "sg:address":"1956 W Cheryl Dr",
    "sg:city":"Phoenix",
    "sg:classifiers":[
        {
            "category":"Building & Trades",
            "subcategory":"Construction",
            "type":"Services"
        }
    ],
    "sg:phone":"+1 602 944 0300",
    "sg:postcode":"85021",
    "sg:province":"AZ",
    "sg:tags":[
        "roofing",
        "contractor"
    ],
    "wof:name":"Centimark Corp",
    "wof:placetype":"venue"
},
  "geometry": {"coordinates":[-112.100803,33.578452],"type":"Point"}
}