{
  "type": "Feature",
  "properties": {
    "addr:full":"6300 E Main St Mesa AZ 85205",
    "addr:housenumber":"6300",
    "addr:postcode":"85205",
    "addr:street":"E Main St",
    "iso:country":"US",
    "sg:address":"6300 E Main St",
    "sg:city":"Mesa",
    "sg:classifiers":[
        {
            "category":"Government",
            "subcategory":"Police Station",
            "type":"Public Place"
        }
    ],
    "sg:phone":"+1 480 924 4683",
    "sg:postcode":"85205",
    "sg:province":"AZ",
    "sg:tags":[
        "protection"
    ],
    "wof:name":"Police Dept",
    "wof:placetype":"venue"
},
  "geometry": {"coordinates":[-111.694273,33.415645],"type":"Point"}
}