{
  "type": "Feature",
  "properties": {
    "iso:country":"US",
    "sg:address":"14545 W Grand Ave Ste 103",
    "sg:city":"Surprise",
    "sg:classifiers":[
        {
            "category":"Personal",
            "subcategory":"Nail Salon",
            "type":"Services"
        }
    ],
    "sg:phone":"+1 623 544 2487",
    "sg:postcode":"85374",
    "sg:province":"AZ",
    "wof:name":"Bien Nails",
    "wof:placetype":"venue"
},
  "geometry": {"coordinates":[-112.373865,33.656925],"type":"Point"}
}