{
  "type": "Feature",
  "properties": {
    "addr:full":"2017 W Indianola Ave Phoenix AZ 85015",
    "addr:housenumber":"2017",
    "addr:postcode":"85015",
    "addr:street":"W Indianola Ave",
    "iso:country":"US",
    "sg:address":"2017 W Indianola Ave",
    "sg:city":"Phoenix",
    "sg:classifiers":[
        {
            "category":"Building & Trades",
            "subcategory":"Construction",
            "type":"Services"
        }
    ],
    "sg:phone":"+1 602 248 8272",
    "sg:postcode":"85015",
    "sg:province":"AZ",
    "sg:tags":[
        "residential",
        "remodeling",
        "general"
    ],
    "wof:name":"A&T Construction",
    "wof:placetype":"venue"
},
  "geometry": {"coordinates":[-112.101506,33.492309],"type":"Point"}
}