{
  "type": "Feature",
  "properties": {
    "iso:country":"US",
    "sg:address":"4346 E Magnolia St",
    "sg:city":"Phoenix",
    "sg:classifiers":[
        {
            "category":"Wholesale",
            "subcategory":"Machinery & Supplies",
            "type":"Manufacturing & Wholesale Goods"
        }
    ],
    "sg:phone":"+1 602 437 3110",
    "sg:postcode":"85034",
    "sg:province":"AZ",
    "sg:tags":[
        "industrial",
        "equipment",
        "used",
        "machinery-new",
        "supplies-wholesale"
    ],
    "wof:name":"Bexon Equipment",
    "wof:placetype":"venue"
},
  "geometry": {"coordinates":[-111.987963,33.422776],"type":"Point"}
}