{
  "type": "Feature",
  "properties": {
    "iso:country":"US",
    "sg:address":"24817 N 49th Ave",
    "sg:city":"Glendale",
    "sg:classifiers":[
        {
            "category":"Building & Trades",
            "subcategory":"Construction",
            "type":"Services"
        }
    ],
    "sg:phone":"+1 623 434 1391",
    "sg:postcode":"85310",
    "sg:province":"AZ",
    "sg:tags":[
        "residential",
        "nonresidential"
    ],
    "wof:name":"Art of Special Construction",
    "wof:placetype":"venue"
},
  "geometry": {"coordinates":[-112.16534799999999,33.712463],"type":"Point"}
}