{
  "type": "Feature",
  "properties": {
    "addr:full":"2033 E Warner Rd Tempe AZ 85284",
    "addr:housenumber":"2033",
    "addr:postcode":"85284",
    "addr:street":"E Warner Rd",
    "iso:country":"US",
    "sg:address":"2033 E Warner Rd",
    "sg:city":"Tempe",
    "sg:classifiers":[
        {
            "category":"Insurance",
            "subcategory":"Insurance Agent",
            "type":"Services"
        }
    ],
    "sg:phone":"+1 480 831 8668",
    "sg:postcode":"85284",
    "sg:province":"AZ",
    "wof:name":"Richard Utter Agency Inc",
    "wof:placetype":"venue"
},
  "geometry": {"coordinates":[-111.900705,33.334667],"type":"Point"}
}