{
  "type": "Feature",
  "properties": {
    "iso:country":"US",
    "sg:address":"841 E Jefferson St",
    "sg:city":"Phoenix",
    "sg:classifiers":[
        {
            "category":"Professional",
            "subcategory":"Detective & Security Services",
            "type":"Services"
        }
    ],
    "sg:phone":"+1 480 270 8738",
    "sg:postcode":"85034",
    "sg:province":"AZ",
    "sg:tags":[
        "guard",
        "patrol"
    ],
    "sg:website":"http://www.localhomealarmsystems.com",
    "wof:name":"Local Home Alarm Systems",
    "wof:placetype":"venue"
},
  "geometry": {"coordinates":[-112.062782,33.447109],"type":"Point"}
}