{
  "type": "Feature",
  "properties": {
    "iso:country":"US",
    "sg:address":"9332 N 95th Way Ste 208",
    "sg:city":"Scottsdale",
    "sg:classifiers":[
        {
            "category":"Health Services",
            "subcategory":"Clinic",
            "type":"Services"
        },
        {
            "category":"Health Services",
            "subcategory":"Health Practitioner",
            "type":"Services"
        }
    ],
    "sg:phone":"+1 480 614 5878",
    "sg:postcode":"85258",
    "sg:province":"AZ",
    "sg:tags":[
        "therapist",
        "therapy",
        "physical"
    ],
    "wof:name":"Metro Physical Therapy",
    "wof:placetype":"venue"
},
  "geometry": {"coordinates":[-111.875092,33.56902],"type":"Point"}
}