{
  "type": "Feature",
  "properties": {
    "iso:country":"US",
    "sg:address":"1831 W Cloud Rd",
    "sg:city":"Phoenix",
    "sg:classifiers":[
        {
            "category":"Real Estate",
            "subcategory":"Real Estate Services",
            "type":"Services"
        },
        {
            "category":"Banks & Credit Unions",
            "subcategory":"Financial Services",
            "type":"Services"
        }
    ],
    "sg:phone":"+1 623 332 5900",
    "sg:postcode":"85086",
    "sg:province":"AZ",
    "sg:tags":[
        "loan",
        "processing"
    ],
    "wof:name":"Est Of Pacific Coast Mortg",
    "wof:placetype":"venue"
},
  "geometry": {"coordinates":[-112.097666,33.813246],"type":"Point"}
}