{
  "type": "Feature",
  "properties": {
    "addr:full":"3756 E 22nd St Tucson AZ 85713",
    "addr:housenumber":"3756",
    "addr:postcode":"85713",
    "addr:street":"E 22Nd St",
    "iso:country":"US",
    "sg:address":"3756 E 22nd St",
    "sg:city":"Tucson",
    "sg:classifiers":[
        {
            "category":"Shopping",
            "type":"Retail Goods"
        }
    ],
    "sg:phone":"+1 520 327 1998",
    "sg:postcode":"85713",
    "sg:province":"AZ",
    "sg:tags":[
        "merchandise"
    ],
    "wof:name":"Rrr Safety Products",
    "wof:placetype":"venue"
},
  "geometry": {"coordinates":[-110.912273,32.206921],"type":"Point"}
}