{
  "type": "Feature",
  "properties": {
    "iso:country":"US",
    "sg:address":"4818 E Broadway Blvd",
    "sg:city":"Tucson",
    "sg:classifiers":[
        {
            "category":"Communications",
            "type":"Services"
        }
    ],
    "sg:phone":"+1 520 203 7842",
    "sg:postcode":"85711",
    "sg:province":"AZ",
    "sg:tags":[
        "communication"
    ],
    "wof:name":"Prefuel Media",
    "wof:placetype":"venue"
},
  "geometry": {"coordinates":[-110.89198500000001,32.221432],"type":"Point"}
}