{
  "type": "Feature",
  "properties": {
    "iso:country":"US",
    "sg:address":"15824 W Acapulco Ln",
    "sg:city":"Surprise",
    "sg:classifiers":[
        {
            "category":"Professional",
            "subcategory":"Computer Services",
            "type":"Services"
        }
    ],
    "sg:phone":"+1 623 544 1204",
    "sg:postcode":"85379",
    "sg:province":"AZ",
    "sg:tags":[
        "consultant",
        "designer"
    ],
    "wof:name":"Farley Development & Cnsltng",
    "wof:placetype":"venue"
},
  "geometry": {"coordinates":[-112.399997,33.622583],"type":"Point"}
}