{
  "type": "Feature",
  "properties": {
    "iso:country":"US",
    "sg:address":"1546 E Prescott Ct",
    "sg:city":"Chandler",
    "sg:classifiers":[
        {
            "category":"Personal",
            "subcategory":"Tanning Parlor",
            "type":"Services"
        }
    ],
    "sg:phone":"+1 480 423 1031",
    "sg:postcode":"85249",
    "sg:province":"AZ",
    "sg:tags":[
        "salon"
    ],
    "wof:name":"Club Tan",
    "wof:placetype":"venue"
},
  "geometry": {"coordinates":[-111.814041,33.241967],"type":"Point"}
}