{
  "type": "Feature",
  "properties": {
    "iso:country":"US",
    "sg:address":"5055 West Ray Road",
    "sg:city":"Chandler",
    "sg:classifiers":[
        {
            "category":"Restaurant",
            "type":"Food & Drink"
        }
    ],
    "sg:postcode":"85226",
    "sg:province":"AZ",
    "sg:tags":[
        "chinese"
    ],
    "sg:website":"ikitchen.webs.com/",
    "wof:name":"iKitchen",
    "wof:placetype":"venue"
},
  "geometry": {"coordinates":[-111.929312,33.319375],"type":"Point"}
}