{
  "type": "Feature",
  "properties": {
    "addr:full":"34225 N 27th Dr Ste 100 Phoenix AZ 85085",
    "addr:housenumber":"34225",
    "addr:postcode":"85085",
    "addr:street":"N 27Th Dr Ste 100",
    "iso:country":"US",
    "sg:address":"34225 N 27th Dr Ste 100",
    "sg:city":"Phoenix",
    "sg:classifiers":[
        {
            "category":"Insurance",
            "subcategory":"Insurance Agent",
            "type":"Services"
        },
        {
            "category":"Insurance",
            "subcategory":"Hazard Insurance",
            "type":"Services"
        },
        {
            "category":"Insurance",
            "subcategory":"Health Insurance",
            "type":"Services"
        }
    ],
    "sg:phone":"+1 623 201 2977",
    "sg:postcode":"85085",
    "sg:province":"AZ",
    "sg:tags":[
        "business",
        "auto",
        "commercial",
        "benefit",
        "employee"
    ],
    "sg:website":"http://www.farmersagent.com/jwallace3",
    "wof:name":"Farmers And Wallace Insurance Agency",
    "wof:placetype":"venue"
},
  "geometry": {"coordinates":[-112.117767,33.796225],"type":"Point"}
}