{
  "type": "Feature",
  "properties": {
    "iso:country":"US",
    "sg:address":"3019 E Marilyn Rd",
    "sg:city":"Phoenix",
    "sg:classifiers":[
        {
            "category":"Sports & Exercise",
            "subcategory":"Race Track",
            "type":"Entertainment"
        }
    ],
    "sg:phone":"+1 602 996 4015",
    "sg:postcode":"85032",
    "sg:province":"AZ",
    "wof:name":"Ram Jet Racing Online",
    "wof:placetype":"venue"
},
  "geometry": {"coordinates":[-112.016549,33.621023],"type":"Point"}
}