{
  "type": "Feature",
  "properties": {
    "iso:country":"US",
    "sg:address":"5041 W Northern Ave Ste A",
    "sg:city":"Glendale",
    "sg:classifiers":[
        {
            "category":"Shopping",
            "subcategory":"Clothing, Apparel, & Fashions",
            "type":"Retail Goods"
        },
        {
            "category":"Retail",
            "subcategory":"Laundry & Dry Cleaning",
            "type":"Services"
        }
    ],
    "sg:phone":"+1 623 931 3512",
    "sg:postcode":"85301",
    "sg:province":"AZ",
    "sg:tags":[
        "supply",
        "work",
        "uniform",
        "clothes"
    ],
    "wof:name":"Jeenie Aprons Manufacturing",
    "wof:placetype":"venue"
},
  "geometry": {"coordinates":[-112.167862,33.553082],"type":"Point"}
}