{
  "type": "Feature",
  "properties": {
    "addr:full":"440 S Williams Blvd Tucson AZ 85711",
    "addr:housenumber":"440",
    "addr:postcode":"85711",
    "addr:street":"S Williams Blvd",
    "iso:country":"US",
    "sg:address":"440 S Williams Blvd",
    "sg:city":"Tucson",
    "sg:classifiers":[
        {
            "category":"Insurance",
            "subcategory":"Insurance Agent",
            "type":"Services"
        }
    ],
    "sg:phone":"+1 520 790 1791",
    "sg:postcode":"85711",
    "sg:province":"AZ",
    "wof:name":"Bankers Life & Casualty Co",
    "wof:placetype":"venue"
},
  "geometry": {"coordinates":[-110.87801,32.216272],"type":"Point"}
}