{
  "type": "Feature",
  "properties": {
    "iso:country":"US",
    "sg:address":"8591 W Washington St",
    "sg:city":"Tolleson",
    "sg:classifiers":[
        {
            "category":"Home & Garden",
            "subcategory":"Home Furnishings",
            "type":"Retail Goods"
        }
    ],
    "sg:phone":"+1 623 478 7283",
    "sg:postcode":"85353",
    "sg:province":"AZ",
    "sg:tags":[
        "set",
        "bed",
        "bedroom"
    ],
    "wof:name":"International Bedding Of Az",
    "wof:placetype":"venue"
},
  "geometry": {"coordinates":[-112.2441,33.446923],"type":"Point"}
}