{
  "type": "Feature",
  "properties": {
    "iso:country":"US",
    "sg:address":"5 S 84th Ave",
    "sg:city":"Tolleson",
    "sg:classifiers":[
        {
            "category":"Freight",
            "type":"Transportation"
        }
    ],
    "sg:phone":"+1 623 936 3777",
    "sg:postcode":"85353",
    "sg:province":"AZ",
    "sg:tags":[
        "trucking"
    ],
    "wof:name":"Tab Transportation",
    "wof:placetype":"venue"
},
  "geometry": {"coordinates":[-112.241232,33.4454],"type":"Point"}
}