{
  "type": "Feature",
  "properties": {
    "iso:country":"US",
    "sg:address":"1728 W Glendale Ave",
    "sg:city":"Phoenix",
    "sg:classifiers":[
        {
            "category":"Health Services",
            "subcategory":"Doctor",
            "type":"Services"
        }
    ],
    "sg:phone":"+1 602 995 1253",
    "sg:postcode":"85021",
    "sg:province":"AZ",
    "sg:tags":[
        "dentist"
    ],
    "wof:name":"Michael R Macchione DDS",
    "wof:placetype":"venue"
},
  "geometry": {"coordinates":[-112.095618,33.538647],"type":"Point"}
}