{
  "type": "Feature",
  "properties": {
    "addr:full":"12204 N 51st Ave Glendale AZ 85304",
    "addr:housenumber":"12204",
    "addr:postcode":"85304",
    "addr:street":"N 51St Ave",
    "iso:country":"US",
    "sg:address":"12204 N 51st Ave",
    "sg:city":"Glendale",
    "sg:classifiers":[
        {
            "category":"Home & Garden",
            "subcategory":"Garden Supply",
            "type":"Retail Goods"
        },
        {
            "category":"Shopping",
            "subcategory":"Gifts & Souvenirs",
            "type":"Retail Goods"
        },
        {
            "category":"Shopping",
            "subcategory":"Crafts & Fabrics",
            "type":"Retail Goods"
        },
        {
            "category":"Shopping",
            "subcategory":"Florist",
            "type":"Retail Goods"
        }
    ],
    "sg:phone":"+1 602 283 2837",
    "sg:postcode":"85304",
    "sg:province":"AZ",
    "sg:tags":[
        "plant",
        "etc-retail",
        "dried",
        "basket",
        "trees-silk",
        "flowers"
    ],
    "sg:website":"http://www.floweramaaz.com",
    "wof:name":"Flowerama of Glendale",
    "wof:placetype":"venue"
},
  "geometry": {"coordinates":[-112.16865900000001,33.596534],"type":"Point"}
}