{
  "type": "Feature",
  "properties": {
    "addr:full":"12434 N Tatum Blvd Phoenix AZ 85032",
    "addr:housenumber":"12434",
    "addr:postcode":"85032",
    "addr:street":"N Tatum Blvd",
    "iso:country":"US",
    "sg:address":"12434 N Tatum Blvd",
    "sg:city":"Phoenix",
    "sg:classifiers":[
        {
            "category":"Banks & Credit Unions",
            "subcategory":"Bank",
            "type":"Services"
        }
    ],
    "sg:phone":"+1 602 285 3610",
    "sg:postcode":"85032",
    "sg:province":"AZ",
    "sg:tags":[
        "commercial",
        "saving"
    ],
    "sg:website":"http://www.compassbank.com",
    "wof:name":"Compass Bank",
    "wof:placetype":"venue"
},
  "geometry": {"coordinates":[-111.97999900000001,33.599827],"type":"Point"}
}