{
  "type": "Feature",
  "properties": {
    "iso:country":"US",
    "sg:address":"4914 E Duane Ln",
    "sg:city":"Cave Creek",
    "sg:classifiers":[
        {
            "category":"Building & Trades",
            "subcategory":"Construction",
            "type":"Services"
        }
    ],
    "sg:phone":"+1 480 659 9049",
    "sg:postcode":"85331",
    "sg:province":"AZ",
    "sg:tags":[
        "contractor"
    ],
    "wof:name":"Perfection Auto Glass By",
    "wof:placetype":"venue"
},
  "geometry": {"coordinates":[-111.974772,33.753581],"type":"Point"}
}