{
  "type": "Feature",
  "properties": {
    "iso:country":"US",
    "sg:address":"1113 N Beeline Hwy",
    "sg:city":"Payson",
    "sg:classifiers":[
        {
            "category":"Professional",
            "type":"Services"
        }
    ],
    "sg:phone":"+1 928 474 2350",
    "sg:postcode":"85541",
    "sg:province":"AZ",
    "wof:name":"Tops Jeans & You",
    "wof:placetype":"venue"
},
  "geometry": {"coordinates":[-111.322408,34.255228],"type":"Point"}
}