{
  "type": "Feature",
  "properties": {
    "iso:country":"US",
    "sg:address":"22517 N Ellison Rd",
    "sg:city":"Maricopa",
    "sg:classifiers":[
        {
            "category":"Wholesale",
            "subcategory":"Machinery & Supplies",
            "type":"Manufacturing & Wholesale Goods"
        }
    ],
    "sg:phone":"+1 520 431 2580",
    "sg:postcode":"85239",
    "sg:province":"AZ",
    "sg:tags":[
        "equipment",
        "industrial",
        "export",
        "wood"
    ],
    "wof:name":"Equipment & Material R&R",
    "wof:placetype":"venue"
},
  "geometry": {"coordinates":[-112.150627,33.080372],"type":"Point"}
}