{
  "type": "Feature",
  "properties": {
    "iso:country":"US",
    "sg:address":"5812 N 12th Pl",
    "sg:city":"Phoenix",
    "sg:classifiers":[
        {
            "category":"Professional",
            "subcategory":"Management & Consulting",
            "type":"Services"
        }
    ],
    "sg:phone":"+1 602 264 2671",
    "sg:postcode":"85014",
    "sg:province":"AZ",
    "sg:tags":[
        "consultant",
        "business"
    ],
    "wof:name":"Horizon Management & Finance",
    "wof:placetype":"venue"
},
  "geometry": {"coordinates":[-112.054659,33.521686],"type":"Point"}
}