{
  "type": "Feature",
  "properties": {
    "addr:full":"786 N Arizona Ave Chandler AZ 85225",
    "addr:housenumber":"786",
    "addr:postcode":"85225",
    "addr:street":"N Arizona Ave",
    "iso:country":"US",
    "sg:address":"786 N Arizona Ave",
    "sg:city":"Chandler",
    "sg:classifiers":[
        {
            "category":"Professional",
            "subcategory":"Business Services",
            "type":"Services"
        }
    ],
    "sg:phone":"+1 480 722 2897",
    "sg:postcode":"85225",
    "sg:province":"AZ",
    "sg:tags":[
        "recording",
        "studio"
    ],
    "wof:name":"Around The Way Studios",
    "wof:placetype":"venue"
},
  "geometry": {"coordinates":[-111.841622,33.316545],"type":"Point"}
}