{
  "type": "Feature",
  "properties": {
    "iso:country":"US",
    "sg:address":"13910 N Frank Lloyd Wright Blvd",
    "sg:city":"Scottsdale",
    "sg:classifiers":[
        {
            "category":"Banks & Credit Unions",
            "subcategory":"Financial Services",
            "type":"Services"
        }
    ],
    "sg:phone":"+1 480 502 5844",
    "sg:postcode":"85260",
    "sg:province":"AZ",
    "sg:tags":[
        "trust",
        "management"
    ],
    "wof:name":"Charity Management System",
    "wof:placetype":"venue"
},
  "geometry": {"coordinates":[-111.871103,33.616708],"type":"Point"}
}