{
  "type": "Feature",
  "properties": {
    "iso:country":"US",
    "sg:address":"4515 S McClintock Dr",
    "sg:city":"Tempe",
    "sg:classifiers":[
        {
            "category":"Professional",
            "subcategory":"Management & Consulting",
            "type":"Services"
        }
    ],
    "sg:phone":"+1 480 831 7700",
    "sg:postcode":"85282",
    "sg:province":"AZ",
    "sg:tags":[
        "employee",
        "consultant",
        "benefit"
    ],
    "wof:name":"Benefits By Design",
    "wof:placetype":"venue"
},
  "geometry": {"coordinates":[-111.909114,33.384638],"type":"Point"}
}