{
  "type": "Feature",
  "properties": {
    "addr:full":"961 W Ray Rd Chandler AZ 85225",
    "addr:housenumber":"961",
    "addr:postcode":"85225",
    "addr:street":"W Ray Rd",
    "iso:country":"US",
    "sg:address":"961 W Ray Rd",
    "sg:city":"Chandler",
    "sg:classifiers":[
        {
            "category":"Food & Beverages",
            "subcategory":"Specialty",
            "type":"Retail Goods"
        }
    ],
    "sg:phone":"+1 480 899 9480",
    "sg:postcode":"85225",
    "sg:province":"AZ",
    "sg:tags":[
        "health",
        "market"
    ],
    "wof:name":"Yerberia San Francisco",
    "wof:placetype":"venue"
},
  "geometry": {"coordinates":[-111.858002,33.320599],"type":"Point"}
}