{
  "type": "Feature",
  "properties": {
    "iso:country":"US",
    "sg:address":"3301 E Lee St",
    "sg:city":"Tucson",
    "sg:classifiers":[
        {
            "category":"Professional",
            "subcategory":"Art Services",
            "type":"Services"
        }
    ],
    "sg:phone":"+1 520 299 6823",
    "sg:postcode":"85716",
    "sg:province":"AZ",
    "sg:tags":[
        "graphic",
        "designer"
    ],
    "wof:name":"Aire Design Co",
    "wof:placetype":"venue"
},
  "geometry": {"coordinates":[-110.92038700000001,32.241548],"type":"Point"}
}