{
  "type": "Feature",
  "properties": {
    "iso:country":"US",
    "sg:address":"20206 N 27th Ave",
    "sg:city":"Phoenix",
    "sg:classifiers":[
        {
            "category":"Restaurant",
            "type":"Food & Drink"
        }
    ],
    "sg:phone":"+1 623 869 9027",
    "sg:postcode":"85027",
    "sg:province":"AZ",
    "sg:tags":[
        "eating",
        "ice",
        "cream"
    ],
    "wof:name":"Togos & Baskin-Robbins",
    "wof:placetype":"venue"
},
  "geometry": {"coordinates":[-112.11732,33.668932],"type":"Point"}
}