{
  "type": "Feature",
  "properties": {
    "iso:country":"US",
    "sg:address":"2246 E Toledo Pl",
    "sg:city":"Chandler",
    "sg:classifiers":[
        {
            "category":"Banks & Credit Unions",
            "subcategory":"Bank",
            "type":"Services"
        }
    ],
    "sg:phone":"+1 480 812 1818",
    "sg:postcode":"85225",
    "sg:province":"AZ",
    "sg:tags":[
        "mortgage",
        "loan",
        "broker",
        "real estate"
    ],
    "wof:name":"Lenders Home Mortage",
    "wof:placetype":"venue"
},
  "geometry": {"coordinates":[-111.802002,33.307701],"type":"Point"}
}