{
  "type": "Feature",
  "properties": {
    "addr:full":"4923 E Hillery Dr Scottsdale AZ 85254",
    "addr:housenumber":"4923",
    "addr:postcode":"85254",
    "addr:street":"E Hillery Dr",
    "iso:country":"US",
    "sg:address":"4923 E Hillery Dr",
    "sg:city":"Scottsdale",
    "sg:classifiers":[
        {
            "category":"Building & Trades",
            "subcategory":"Electrical",
            "type":"Services"
        }
    ],
    "sg:phone":"+1 602 996 6878",
    "sg:postcode":"85254",
    "sg:province":"AZ",
    "sg:tags":[
        "electrical",
        "contractor"
    ],
    "wof:name":"Upland Electric Inc",
    "wof:placetype":"venue"
},
  "geometry": {"coordinates":[-111.974936,33.621566],"type":"Point"}
}