{
  "type": "Feature",
  "properties": {
    "iso:country":"US",
    "sg:address":"1545 S 14th Ave",
    "sg:city":"Yuma",
    "sg:classifiers":[
        {
            "category":"Real Estate",
            "subcategory":"Real Estate Operator",
            "type":"Services"
        }
    ],
    "sg:phone":"+1 928 343 0807",
    "sg:postcode":"85364",
    "sg:province":"AZ",
    "sg:tags":[
        "building",
        "apartment"
    ],
    "wof:name":"Desert Rose",
    "wof:placetype":"venue"
},
  "geometry": {"coordinates":[-114.63750899999999,32.699932],"type":"Point"}
}