{
  "type": "Feature",
  "properties": {
    "addr:full":"1300 S Litchfield Rd # 8 Goodyear AZ 85338",
    "addr:housenumber":"1300",
    "addr:postcode":"85338",
    "addr:street":"S Litchfield Rd # 8",
    "iso:country":"US",
    "sg:address":"1300 S Litchfield Rd # 8",
    "sg:city":"Goodyear",
    "sg:classifiers":[
        {
            "category":"Professional",
            "subcategory":"Business Services",
            "type":"Services"
        }
    ],
    "sg:phone":"+1 623 695 3914",
    "sg:postcode":"85338",
    "sg:province":"AZ",
    "sg:tags":[
        "labeling"
    ],
    "wof:name":"Southbay Packaging",
    "wof:placetype":"venue"
},
  "geometry": {"coordinates":[-112.358282,33.433333],"type":"Point"}
}