{
  "type": "Feature",
  "properties": {
    "addr:full":"3842 E Forge Ave Mesa AZ 85206",
    "addr:housenumber":"3842",
    "addr:postcode":"85206",
    "addr:street":"E Forge Ave",
    "iso:country":"US",
    "sg:address":"3842 E Forge Ave",
    "sg:city":"Mesa",
    "sg:classifiers":[
        {
            "category":"Health Services",
            "subcategory":"Doctor",
            "type":"Services"
        },
        {
            "category":"Health Services",
            "subcategory":"Hospital",
            "type":"Services"
        }
    ],
    "sg:phone":"+1 480 203 5111",
    "sg:postcode":"85206",
    "sg:province":"AZ",
    "sg:tags":[
        "consultant",
        "medical",
        "practice",
        "nursing",
        "home"
    ],
    "wof:name":"Rmm Endovascular Consulting",
    "wof:placetype":"venue"
},
  "geometry": {"coordinates":[-111.748295,33.396024],"type":"Point"}
}