{
  "type": "Feature",
  "properties": {
    "iso:country":"US",
    "sg:address":"3820 E Briarwood Ter",
    "sg:city":"Phoenix",
    "sg:classifiers":[
        {
            "category":"Professional",
            "subcategory":"Credit Reporting & Collection",
            "type":"Services"
        }
    ],
    "sg:phone":"+1 480 706 9517",
    "sg:postcode":"85048",
    "sg:province":"AZ",
    "sg:tags":[
        "agency"
    ],
    "wof:name":"Capital Collections & Loan Svc",
    "wof:placetype":"venue"
},
  "geometry": {"coordinates":[-112.001643,33.297422],"type":"Point"}
}