{
  "type": "Feature",
  "properties": {
    "iso:country":"US",
    "sg:address":"1502 E Grovers Ave",
    "sg:city":"Phoenix",
    "sg:classifiers":[
        {
            "category":"Professional",
            "subcategory":"Business Services",
            "type":"Services"
        }
    ],
    "sg:phone":"+1 602 992 2805",
    "sg:postcode":"85022",
    "sg:province":"AZ",
    "sg:tags":[
        "mfg",
        "vestment",
        "church"
    ],
    "sg:website":"www.aheavenlystitch.com",
    "wof:name":"A Heavenly Stitch",
    "wof:placetype":"venue"
},
  "geometry": {"coordinates":[-112.049942,33.647713],"type":"Point"}
}