{
  "type": "Feature",
  "properties": {
    "iso:country":"US",
    "sg:address":"8767 E Via de Ventura",
    "sg:city":"Scottsdale",
    "sg:classifiers":[
        {
            "category":"Banks & Credit Unions",
            "subcategory":"Investment Brokerage",
            "type":"Services"
        }
    ],
    "sg:phone":"+1 480 777 9870",
    "sg:postcode":"85258",
    "sg:province":"AZ",
    "sg:tags":[
        "advisory",
        "financial"
    ],
    "sg:website":"www.faml.net",
    "wof:name":"Foothills Asset Management LTD",
    "wof:placetype":"venue"
},
  "geometry": {"coordinates":[-111.89495100000001,33.553627],"type":"Point"}
}