{
  "type": "Feature",
  "properties": {
    "addr:full":"920 W Silver Hills St Tucson AZ 85737",
    "addr:housenumber":"920",
    "addr:postcode":"85737",
    "addr:street":"W Silver;St",
    "iso:country":"US",
    "sg:address":"920 W Silver Hills St",
    "sg:city":"Tucson",
    "sg:classifiers":[
        {
            "category":"Professional",
            "type":"Services"
        }
    ],
    "sg:phone":"+1 520 229 3229",
    "sg:postcode":"85737",
    "sg:province":"AZ",
    "sg:tags":[
        "establishment"
    ],
    "wof:name":"Pl8scan Inc",
    "wof:placetype":"venue"
},
  "geometry": {"coordinates":[-110.985353,32.421437],"type":"Point"}
}