{
  "type": "Feature",
  "properties": {
    "iso:country":"US",
    "sg:address":"6439 E Catalina Ct",
    "sg:city":"Tucson",
    "sg:classifiers":[
        {
            "category":"Professional",
            "type":"Services"
        }
    ],
    "sg:phone":"+1 520 747 2889",
    "sg:postcode":"85708",
    "sg:province":"AZ",
    "wof:name":"Rolland Roth",
    "wof:placetype":"venue"
},
  "geometry": {"coordinates":[-110.866431,32.188934],"type":"Point"}
}