{
  "type": "Feature",
  "properties": {
    "iso:country":"US",
    "sg:address":"239 N 2nd St W",
    "sg:city":"Snowflake",
    "sg:classifiers":[
        {
            "category":"Freight",
            "type":"Transportation"
        }
    ],
    "sg:phone":"+1 928 536 7242",
    "sg:postcode":"85937",
    "sg:province":"AZ",
    "sg:tags":[
        "operator",
        "local",
        "trucking"
    ],
    "wof:name":"Larson Waste",
    "wof:placetype":"venue"
},
  "geometry": {"coordinates":[-110.08223,34.506008],"type":"Point"}
}