{
  "type": "Feature",
  "properties": {
    "iso:country":"US",
    "sg:address":"819 Westin Pass",
    "sg:city":"Prescott",
    "sg:classifiers":[
        {
            "category":"Shopping",
            "subcategory":"Jewelry",
            "type":"Retail Goods"
        }
    ],
    "sg:phone":"+1 928 771 9856",
    "sg:postcode":"86301",
    "sg:province":"AZ",
    "wof:name":"Granite Mountain Bead Creation",
    "wof:placetype":"venue"
},
  "geometry": {"coordinates":[-112.456756,34.593744],"type":"Point"}
}