{
  "type": "Feature",
  "properties": {
    "iso:country":"US",
    "sg:address":"817 N Oregon St",
    "sg:city":"Chandler",
    "sg:classifiers":[
        {
            "category":"Manufacturing",
            "subcategory":"Glass & Minerals",
            "type":"Manufacturing & Wholesale Goods"
        }
    ],
    "sg:phone":"+1 480 430 7101",
    "sg:postcode":"85225",
    "sg:province":"AZ",
    "sg:tags":[
        "concrete",
        "product",
        "mfg"
    ],
    "sg:website":"www.coyotesimulatedstone.com",
    "wof:name":"Coyote Stone & Springs",
    "wof:placetype":"venue"
},
  "geometry": {"coordinates":[-111.84334699999999,33.317879],"type":"Point"}
}