{
  "type": "Feature",
  "properties": {
    "addr:full":"6420 E Waltann Ln Scottsdale AZ 85254",
    "addr:housenumber":"6420",
    "addr:postcode":"85254",
    "addr:street":"E Waltann Ln",
    "iso:country":"US",
    "sg:address":"6420 E Waltann Ln",
    "sg:city":"Scottsdale",
    "sg:classifiers":[
        {
            "category":"Personal",
            "subcategory":"Beauty Salon",
            "type":"Services"
        }
    ],
    "sg:phone":"+1 480 657 0700",
    "sg:postcode":"85254",
    "sg:province":"AZ",
    "sg:tags":[
        "treatment",
        "skin"
    ],
    "wof:name":"Aachen Inc",
    "wof:placetype":"venue"
},
  "geometry": {"coordinates":[-111.94160100000001,33.628462],"type":"Point"}
}