{
  "type": "Feature",
  "properties": {
    "addr:full":"1774 E Winchester Pl Chandler AZ 85286",
    "addr:housenumber":"1774",
    "addr:postcode":"85286",
    "addr:street":"E Winchester Pl",
    "iso:country":"US",
    "sg:address":"1774 E Winchester Pl",
    "sg:city":"Chandler",
    "sg:classifiers":[
        {
            "category":"Building & Trades",
            "subcategory":"Landscaping Services",
            "type":"Services"
        }
    ],
    "sg:phone":"+1 480 287 6008",
    "sg:postcode":"85286",
    "sg:province":"AZ",
    "sg:tags":[
        "architect",
        "landscape"
    ],
    "sg:website":"www.aridoasislandscapes.com",
    "wof:name":"Arid Oasis Landscapes",
    "wof:placetype":"venue"
},
  "geometry": {"coordinates":[-111.81107900000001,33.290081],"type":"Point"}
}