{
  "type": "Feature",
  "properties": {
    "addr:full":"1249 S 27th St Phoenix AZ 85034",
    "addr:housenumber":"1249",
    "addr:postcode":"85034",
    "addr:street":"S 27Th St",
    "iso:country":"US",
    "sg:address":"1249 S 27th St",
    "sg:city":"Phoenix",
    "sg:classifiers":[
        {
            "category":"Professional",
            "subcategory":"Detective & Security Services",
            "type":"Services"
        }
    ],
    "sg:phone":"+1 602 220 0893",
    "sg:postcode":"85034",
    "sg:province":"AZ",
    "sg:tags":[
        "information",
        "bureau"
    ],
    "wof:name":"Quantam Aviation Services",
    "wof:placetype":"venue"
},
  "geometry": {"coordinates":[-112.022964,33.434817],"type":"Point"}
}