{
  "type": "Feature",
  "properties": {
    "iso:country":"US",
    "sg:address":"1955 W Baseline Rd",
    "sg:city":"Mesa",
    "sg:classifiers":[
        {
            "category":"Shopping",
            "subcategory":"Mobile Phones",
            "type":"Retail Goods"
        }
    ],
    "sg:phone":"+1 480 820 2466",
    "sg:postcode":"85202",
    "sg:province":"AZ",
    "wof:name":"Coast To Coast Cellular",
    "wof:placetype":"venue"
},
  "geometry": {"coordinates":[-111.87666400000001,33.378358],"type":"Point"}
}