{
  "type": "Feature",
  "properties": {
    "addr:full":"1040 E Indian School Rd Phoenix AZ 85014",
    "addr:housenumber":"1040",
    "addr:postcode":"85014",
    "addr:street":"E Indian School Rd",
    "iso:country":"US",
    "sg:address":"1040 E Indian School Rd",
    "sg:city":"Phoenix",
    "sg:classifiers":[
        {
            "category":"Banks & Credit Unions",
            "subcategory":"Investment Brokerage",
            "type":"Services"
        }
    ],
    "sg:phone":"+1 602 318 9020",
    "sg:postcode":"85014",
    "sg:province":"AZ",
    "sg:tags":[
        "advisory"
    ],
    "wof:name":"Brocor Investments",
    "wof:placetype":"venue"
},
  "geometry": {"coordinates":[-112.059023,33.494701],"type":"Point"}
}