{
  "type": "Feature",
  "properties": {
    "iso:country":"US",
    "sg:address":"3629 W White Mountain Blvd",
    "sg:city":"Lakeside",
    "sg:classifiers":[
        {
            "category":"Autos & Motor Vehicles",
            "subcategory":"Recreational Vehicle Sales",
            "type":"Retail Goods"
        }
    ],
    "sg:phone":"+1 928 368 4927",
    "sg:postcode":"85929",
    "sg:province":"AZ",
    "sg:tags":[
        "campground",
        "park"
    ],
    "wof:name":"Rim Country Rv Park",
    "wof:placetype":"venue"
},
  "geometry": {"coordinates":[-109.993448,34.166123],"type":"Point"}
}