{
  "type": "Feature",
  "properties": {
    "addr:full":"2836 N 25th Pl Phoenix AZ 85008",
    "addr:housenumber":"2836",
    "addr:postcode":"85008",
    "addr:street":"N 25Th Pl",
    "iso:country":"US",
    "sg:address":"2836 N 25th Pl",
    "sg:city":"Phoenix",
    "sg:classifiers":[
        {
            "category":"Freight",
            "type":"Transportation"
        }
    ],
    "sg:phone":"+1 602 468 6371",
    "sg:postcode":"85008",
    "sg:province":"AZ",
    "wof:name":"Charles & Sons Transportation",
    "wof:placetype":"venue"
},
  "geometry": {"coordinates":[-112.02701399999999,33.480215],"type":"Point"}
}