{
  "type": "Feature",
  "properties": {
    "iso:country":"US",
    "sg:address":"7902 N 67th Ave",
    "sg:city":"Glendale",
    "sg:classifiers":[
        {
            "category":"Autos & Motor Vehicles",
            "subcategory":"Motorcycle Sales",
            "type":"Retail Goods"
        }
    ],
    "sg:phone":"+1 623 463 3488",
    "sg:postcode":"85301",
    "sg:province":"AZ",
    "wof:name":"Palo Verde Motorcross (llc)",
    "wof:placetype":"venue"
},
  "geometry": {"coordinates":[-112.203041,33.551104],"type":"Point"}
}