{
  "type": "Feature",
  "properties": {
    "iso:country":"US",
    "sg:address":"4501 W Hayward Ave",
    "sg:city":"Glendale",
    "sg:classifiers":[
        {
            "category":"Professional",
            "subcategory":"Advertising",
            "type":"Services"
        }
    ],
    "sg:phone":"+1 623 930 0032",
    "sg:postcode":"85301",
    "sg:province":"AZ",
    "sg:tags":[
        "promotion",
        "sale"
    ],
    "wof:name":"Computree Promotions",
    "wof:placetype":"venue"
},
  "geometry": {"coordinates":[-112.15585299999999,33.5509],"type":"Point"}
}