{
  "type": "Feature",
  "properties": {
    "iso:country":"US",
    "sg:address":"13051 N Tortolita Rd",
    "sg:city":"Marana",
    "sg:classifiers":[
        {
            "category":"Real Estate",
            "subcategory":"Real Estate Services",
            "type":"Services"
        },
        {
            "category":"Real Estate",
            "subcategory":"Real Estate Agent",
            "type":"Services"
        }
    ],
    "sg:phone":"+1 520 270 4277",
    "sg:postcode":"85658",
    "sg:province":"AZ",
    "sg:tags":[
        "buyer",
        "broker"
    ],
    "wof:name":"Sandberg Realty",
    "wof:placetype":"venue"
},
  "geometry": {"coordinates":[-111.080463,32.442633],"type":"Point"}
}