{
  "type": "Feature",
  "properties": {
    "addr:full":"5715 S Kenwood Ln Tempe AZ 85283",
    "addr:housenumber":"5715",
    "addr:postcode":"85283",
    "addr:street":"S Kenwood Ln",
    "iso:country":"US",
    "sg:address":"5715 S Kenwood Ln",
    "sg:city":"Tempe",
    "sg:classifiers":[
        {
            "category":"Arts & Performance",
            "subcategory":"Theater",
            "type":"Entertainment"
        }
    ],
    "sg:phone":"+1 480 456 5755",
    "sg:postcode":"85283",
    "sg:province":"AZ",
    "sg:tags":[
        "live",
        "music"
    ],
    "wof:name":"Disc Jockeys All About Muzic",
    "wof:placetype":"venue"
},
  "geometry": {"coordinates":[-111.90310700000001,33.37133],"type":"Point"}
}