{
  "type": "Feature",
  "properties": {
    "iso:country":"US",
    "sg:address":"8900 N Central Ave",
    "sg:city":"Phoenix",
    "sg:classifiers":[
        {
            "category":"Professional",
            "subcategory":"Lawyer & Legal Services",
            "type":"Services"
        }
    ],
    "sg:phone":"+1 602 997 4500",
    "sg:postcode":"85020",
    "sg:province":"AZ",
    "sg:tags":[
        "planning",
        "estate"
    ],
    "wof:name":"Empire Estate Planning",
    "wof:placetype":"venue"
},
  "geometry": {"coordinates":[-112.073964,33.56639],"type":"Point"}
}