{
  "type": "Feature",
  "properties": {
    "addr:full":"430 N Vineyard Mesa AZ 85201",
    "addr:housenumber":"430",
    "addr:postcode":"85201",
    "addr:street":"N Vineyard",
    "iso:country":"US",
    "sg:address":"430 N Vineyard",
    "sg:city":"Mesa",
    "sg:classifiers":[
        {
            "category":"Professional",
            "subcategory":"Lawyer & Legal Services",
            "type":"Services"
        }
    ],
    "sg:phone":"+1 480 833 8533",
    "sg:postcode":"85201",
    "sg:province":"AZ",
    "sg:tags":[
        "convention",
        "reporters-court"
    ],
    "wof:name":"Judy K Murphy",
    "wof:placetype":"venue"
},
  "geometry": {"coordinates":[-111.84183,33.423178],"type":"Point"}
}