{
  "type": "Feature",
  "properties": {
    "addr:full":"5540 W Glendale Ave Glendale AZ 85301",
    "addr:housenumber":"5540",
    "addr:postcode":"85301",
    "addr:street":"W Glendale Ave",
    "iso:country":"US",
    "sg:address":"5540 W Glendale Ave",
    "sg:city":"Glendale",
    "sg:classifiers":[
        {
            "category":"Health Services",
            "subcategory":"Health Practitioner",
            "type":"Services"
        }
    ],
    "sg:phone":"+1 623 939 4982",
    "sg:postcode":"85301",
    "sg:province":"AZ",
    "sg:tags":[
        "nurse",
        "registry"
    ],
    "wof:name":"Healthchoice Nurses Agency",
    "wof:placetype":"venue"
},
  "geometry": {"coordinates":[-112.17980300000001,33.538619],"type":"Point"}
}