{
  "type": "Feature",
  "properties": {
    "iso:country":"US",
    "sg:address":"16523 W Northern Ave",
    "sg:city":"Litchfield Park",
    "sg:classifiers":[
        {
            "category":"Restaurant",
            "type":"Food & Drink"
        }
    ],
    "sg:phone":"+1 623 935 1567",
    "sg:postcode":"85340",
    "sg:province":"AZ",
    "wof:name":"Frazier Enterprises",
    "wof:placetype":"venue"
},
  "geometry": {"coordinates":[-112.412685,33.551631],"type":"Point"}
}