{
  "type": "Feature",
  "properties": {
    "iso:country":"US",
    "sg:address":"10899 W Citrus Grove Way",
    "sg:city":"Avondale",
    "sg:classifiers":[
        {
            "category":"Building & Trades",
            "subcategory":"Locksmith",
            "type":"Services"
        }
    ],
    "sg:phone":"+1 623 518 1890",
    "sg:postcode":"85392",
    "sg:province":"AZ",
    "sg:tags":[
        "key"
    ],
    "wof:name":"A Locksmith 0 0 24 Hour",
    "wof:placetype":"venue"
},
  "geometry": {"coordinates":[-112.293451,33.481707],"type":"Point"}
}