{
  "type": "Feature",
  "properties": {
    "addr:full":"6245 E Bell Rd Scottsdale AZ 85254",
    "addr:housenumber":"6245",
    "addr:postcode":"85254",
    "addr:street":"E Bell Rd",
    "iso:country":"US",
    "sg:address":"6245 E Bell Rd",
    "sg:city":"Scottsdale",
    "sg:classifiers":[
        {
            "category":"Banks & Credit Unions",
            "subcategory":"Bank",
            "type":"Services"
        }
    ],
    "sg:phone":"+1 480 367 1212",
    "sg:postcode":"85254",
    "sg:province":"AZ",
    "sg:tags":[
        "mortgage",
        "loan",
        "broker",
        "real estate"
    ],
    "wof:name":"Money Mart Mortgage",
    "wof:placetype":"venue"
},
  "geometry": {"coordinates":[-111.944999,33.640363],"type":"Point"}
}