{
  "type": "Feature",
  "properties": {
    "addr:full":"3500 W River Rd Tucson AZ 85741",
    "addr:housenumber":"3500",
    "addr:postcode":"85741",
    "addr:street":"W River Rd",
    "iso:country":"US",
    "sg:address":"3500 W River Rd",
    "sg:city":"Tucson",
    "sg:classifiers":[
        {
            "category":"Government",
            "subcategory":"Office",
            "type":"Public Place"
        }
    ],
    "sg:phone":"+1 520 877 6000",
    "sg:postcode":"85741",
    "sg:province":"AZ",
    "wof:name":"Pima County Natural Resource",
    "wof:placetype":"venue"
},
  "geometry": {"coordinates":[-111.041648,32.316294],"type":"Point"}
}