{
  "type": "Feature",
  "properties": {
    "iso:country":"US",
    "sg:address":"5602 E Vernon Ave",
    "sg:city":"Scottsdale",
    "sg:classifiers":[
        {
            "category":"Wholesale",
            "subcategory":"Furniture",
            "type":"Manufacturing & Wholesale Goods"
        }
    ],
    "sg:phone":"+1 480 423 0738",
    "sg:postcode":"85257",
    "sg:province":"AZ",
    "wof:name":"White & Assoc",
    "wof:placetype":"venue"
},
  "geometry": {"coordinates":[-111.959313,33.473973],"type":"Point"}
}