{
  "type": "Feature",
  "properties": {
    "iso:country":"US",
    "sg:address":"10913 E Minnesota Ave",
    "sg:city":"Chandler",
    "sg:classifiers":[
        {
            "category":"Shopping",
            "subcategory":"Beauty & Cosmetics",
            "type":"Retail Goods"
        }
    ],
    "sg:phone":"+1 480 895 8998",
    "sg:postcode":"85248",
    "sg:province":"AZ",
    "sg:tags":[
        "merchandise"
    ],
    "wof:name":"Darlene Johnson",
    "wof:placetype":"venue"
},
  "geometry": {"coordinates":[-111.84579600000001,33.218208],"type":"Point"}
}