{
  "type": "Feature",
  "properties": {
    "iso:country":"US",
    "sg:address":"7680 W Mary Jane Ln",
    "sg:city":"Peoria",
    "sg:classifiers":[
        {
            "category":"Professional",
            "subcategory":"Printing & Photocopies",
            "type":"Services"
        }
    ],
    "sg:phone":"+1 623 487 9640",
    "sg:postcode":"85382",
    "sg:province":"AZ",
    "sg:tags":[
        "lithographer"
    ],
    "wof:name":"Jewell Printing Machinery",
    "wof:placetype":"venue"
},
  "geometry": {"coordinates":[-112.223908,33.626761],"type":"Point"}
}