{
  "type": "Feature",
  "properties": {
    "iso:country":"US",
    "sg:address":"10820 N 43rd Dr",
    "sg:city":"Glendale",
    "sg:classifiers":[
        {
            "category":"Personal",
            "subcategory":"Beauty Salon",
            "type":"Services"
        }
    ],
    "sg:phone":"+1 623 937 2749",
    "sg:postcode":"85304",
    "sg:province":"AZ",
    "sg:tags":[
        "school"
    ],
    "sg:website":"www.artisticbeautycolleges.com",
    "wof:name":"Artistic Beauty Colleges",
    "wof:placetype":"venue"
},
  "geometry": {"coordinates":[-112.152159,33.584894],"type":"Point"}
}