{
  "type": "Feature",
  "properties": {
    "iso:country":"US",
    "sg:address":"1745 W Linden St",
    "sg:city":"Phoenix",
    "sg:classifiers":[
        {
            "category":"Shopping",
            "subcategory":"Florist",
            "type":"Retail Goods"
        }
    ],
    "sg:phone":"+1 602 462 9700",
    "sg:postcode":"85007",
    "sg:province":"AZ",
    "wof:name":"Phoenix Sliding Disc Valve Co",
    "wof:placetype":"venue"
},
  "geometry": {"coordinates":[-112.096616,33.459513],"type":"Point"}
}