{
  "type": "Feature",
  "properties": {
    "addr:full":"896 W Tyson St Chandler AZ 85225",
    "addr:housenumber":"896",
    "addr:postcode":"85225",
    "addr:street":"W Tyson St",
    "iso:country":"US",
    "sg:address":"896 W Tyson St",
    "sg:city":"Chandler",
    "sg:classifiers":[
        {
            "category":"Real Estate",
            "subcategory":"Real Estate Agent",
            "type":"Services"
        }
    ],
    "sg:phone":"+1 480 857 9160",
    "sg:postcode":"85225",
    "sg:province":"AZ",
    "sg:tags":[
        "management"
    ],
    "wof:name":"Arimex Realty",
    "wof:placetype":"venue"
},
  "geometry": {"coordinates":[-111.855514,33.31074],"type":"Point"}
}