{
  "type": "Feature",
  "properties": {
    "iso:country":"US",
    "sg:address":"380 E Fort Lowell Rd",
    "sg:city":"Tucson",
    "sg:classifiers":[
        {
            "category":"Social Services",
            "type":"Services"
        }
    ],
    "sg:phone":"+1 520 548 2213",
    "sg:postcode":"85705",
    "sg:province":"AZ",
    "sg:tags":[
        "counselor",
        "marriage",
        "family"
    ],
    "wof:name":"R Gallegos Counseling Svc",
    "wof:placetype":"venue"
},
  "geometry": {"coordinates":[-110.96596,32.264704],"type":"Point"}
}