{
  "type": "Feature",
  "properties": {
    "iso:country":"US",
    "sg:address":"21293 N Sally Dr",
    "sg:city":"Maricopa",
    "sg:classifiers":[
        {
            "category":"Building & Trades",
            "subcategory":"Construction",
            "type":"Services"
        }
    ],
    "sg:phone":"+1 520 568 5095",
    "sg:postcode":"85138",
    "sg:province":"AZ",
    "sg:tags":[
        "system",
        "contractor",
        "air conditioning"
    ],
    "wof:name":"Extreme Conditioning",
    "wof:placetype":"venue"
},
  "geometry": {"coordinates":[-112.031662,33.073382],"type":"Point"}
}