{
  "type": "Feature",
  "properties": {
    "iso:country":"US",
    "sg:address":"3553 Maricopa Ave",
    "sg:city":"Lake Havasu City",
    "sg:classifiers":[
        {
            "category":"Building & Trades",
            "subcategory":"Construction",
            "type":"Services"
        }
    ],
    "sg:phone":"+1 928 453 1244",
    "sg:postcode":"86406",
    "sg:province":"AZ",
    "sg:tags":[
        "plastering",
        "coping",
        "contractor",
        "tiling",
        "pool",
        "swimming"
    ],
    "wof:name":"Bill Blasters",
    "wof:placetype":"venue"
},
  "geometry": {"coordinates":[-114.267307,34.454558],"type":"Point"}
}