{
  "type": "Feature",
  "properties": {
    "iso:country":"US",
    "sg:address":"2735 E Main St Ste 9",
    "sg:city":"Mesa",
    "sg:classifiers":[
        {
            "category":"Personal",
            "type":"Services"
        },
        {
            "category":"Professional",
            "subcategory":"Art Services",
            "type":"Services"
        }
    ],
    "sg:phone":"+1 480 250 6956",
    "sg:postcode":"85213",
    "sg:province":"AZ",
    "sg:tags":[
        "photography",
        "videography",
        "wedding"
    ],
    "wof:name":"All Pro Jl Hammette Photograph",
    "wof:placetype":"venue"
},
  "geometry": {"coordinates":[-111.77290600000001,33.41539],"type":"Point"}
}