{
  "type": "Feature",
  "properties": {
    "addr:full":"1438 N Scottsdale Rd Tempe AZ 85281",
    "addr:housenumber":"1438",
    "addr:postcode":"85281",
    "addr:street":"N Scottsdale Rd",
    "iso:country":"US",
    "sg:address":"1438 N Scottsdale Rd",
    "sg:city":"Tempe",
    "sg:classifiers":[
        {
            "category":"Insurance",
            "subcategory":"Insurance Agent",
            "type":"Services"
        }
    ],
    "sg:phone":"+1 480 668 9100",
    "sg:postcode":"85281",
    "sg:province":"AZ",
    "wof:name":"Auto Insurance America",
    "wof:placetype":"venue"
},
  "geometry": {"coordinates":[-111.92651600000001,33.446142],"type":"Point"}
}