{
  "type": "Feature",
  "properties": {
    "addr:full":"4250 E Camelback Rd Phoenix AZ 85018",
    "addr:housenumber":"4250",
    "addr:postcode":"85018",
    "addr:street":"E Camelback Rd",
    "iso:country":"US",
    "sg:address":"4250 E Camelback Rd",
    "sg:city":"Phoenix",
    "sg:classifiers":[
        {
            "category":"Real Estate",
            "subcategory":"Real Estate Agent",
            "type":"Services"
        }
    ],
    "sg:phone":"+1 602 667 0237",
    "sg:postcode":"85018",
    "sg:province":"AZ",
    "sg:tags":[
        "management"
    ],
    "wof:name":"AIMCO",
    "wof:placetype":"venue"
},
  "geometry": {"coordinates":[-111.991168,33.50977],"type":"Point"}
}