{
  "type": "Feature",
  "properties": {
    "addr:full":"4212 N 16th St Phoenix AZ 85016",
    "addr:housenumber":"4212",
    "addr:postcode":"85016",
    "addr:street":"N 16Th St",
    "iso:country":"US",
    "sg:address":"4212 N 16th St",
    "sg:city":"Phoenix",
    "sg:classifiers":[
        {
            "category":"Manufacturing",
            "subcategory":"Chemicals & Compounds",
            "type":"Manufacturing & Wholesale Goods"
        }
    ],
    "sg:phone":"+1 602 263 1506",
    "sg:postcode":"85016",
    "sg:province":"AZ",
    "sg:tags":[
        "tech",
        "pharmacy"
    ],
    "wof:name":"Victoria Curley",
    "wof:placetype":"venue"
},
  "geometry": {"coordinates":[-112.047681,33.496264],"type":"Point"}
}