{
  "type": "Feature",
  "properties": {
    "iso:country":"US",
    "sg:address":"1885 E Skyline Dr",
    "sg:city":"Tucson",
    "sg:classifiers":[
        {
            "category":"Shopping",
            "subcategory":"Clothing, Apparel, & Fashions",
            "type":"Retail Goods"
        }
    ],
    "sg:phone":"+1 520 398 0400",
    "sg:postcode":"85718",
    "sg:province":"AZ",
    "sg:tags":[
        "item",
        "boutique"
    ],
    "wof:name":"Cowboy's Sweetheart",
    "wof:placetype":"venue"
},
  "geometry": {"coordinates":[-110.929153,32.322721],"type":"Point"}
}