{
  "type": "Feature",
  "properties": {
    "iso:country":"US",
    "sg:address":"947 S 48th St",
    "sg:city":"Tempe",
    "sg:classifiers":[
        {
            "category":"Real Estate",
            "subcategory":"Real Estate Agent",
            "type":"Services"
        }
    ],
    "sg:phone":"+1 480 759 5273",
    "sg:postcode":"85281",
    "sg:province":"AZ",
    "sg:tags":[
        "car",
        "agency",
        "rental"
    ],
    "wof:name":"Lase Rent",
    "wof:placetype":"venue"
},
  "geometry": {"coordinates":[-111.976985,33.42127],"type":"Point"}
}