{
  "type": "Feature",
  "properties": {
    "addr:full":"7016 N Cathedral Rock Pl Tucson AZ 85718",
    "addr:housenumber":"7016",
    "addr:postcode":"85718",
    "addr:street":"N Cathedral Rock Pl",
    "iso:country":"US",
    "sg:address":"7016 N Cathedral Rock Pl",
    "sg:city":"Tucson",
    "sg:classifiers":[
        {
            "category":"Banks & Credit Unions",
            "subcategory":"Financial Services",
            "type":"Services"
        }
    ],
    "sg:phone":"+1 520 888 2088",
    "sg:postcode":"85718",
    "sg:province":"AZ",
    "sg:tags":[
        "investor"
    ],
    "wof:name":"Kenlee Investment Corporation",
    "wof:placetype":"venue"
},
  "geometry": {"coordinates":[-110.920806,32.335972],"type":"Point"}
}