{
  "type": "Feature",
  "properties": {
    "iso:country":"US",
    "sg:address":"9225 E Tanque Verde Rd",
    "sg:city":"Tucson",
    "sg:classifiers":[
        {
            "category":"Professional",
            "type":"Services"
        }
    ],
    "sg:phone":"+1 520 886 1236",
    "sg:postcode":"85749",
    "sg:province":"AZ",
    "wof:name":"Jon J WI",
    "wof:placetype":"venue"
},
  "geometry": {"coordinates":[-110.795284,32.256832],"type":"Point"}
}