{
  "type": "Feature",
  "properties": {
    "iso:country":"US",
    "sg:address":"301 E Virginia Ave Fl 2",
    "sg:city":"Phoenix",
    "sg:classifiers":[
        {
            "category":"Professional",
            "subcategory":"Employment Agencies",
            "type":"Services"
        },
        {
            "category":"Professional",
            "subcategory":"Credit Reporting & Collection",
            "type":"Services"
        }
    ],
    "sg:phone":"+1 602 744 3700",
    "sg:postcode":"85004",
    "sg:province":"AZ",
    "sg:tags":[
        "screening"
    ],
    "sg:website":"http://www.merchantsinfo.com",
    "wof:name":"Merchants Information Solutions, Inc.",
    "wof:placetype":"venue"
},
  "geometry": {"coordinates":[-112.069427,33.47662],"type":"Point"}
}