{
  "type": "Feature",
  "properties": {
    "iso:country":"US",
    "sg:address":"1350 W Harwell Rd",
    "sg:city":"Gilbert",
    "sg:classifiers":[
        {
            "category":"Building & Trades",
            "subcategory":"Construction",
            "type":"Services"
        }
    ],
    "sg:phone":"+1 480 844 1990",
    "sg:postcode":"85233",
    "sg:province":"AZ",
    "sg:tags":[
        "painter"
    ],
    "sg:website":"www.optcoaz.com",
    "wof:name":"OPT Co",
    "wof:placetype":"venue"
},
  "geometry": {"coordinates":[-111.819813,33.377422],"type":"Point"}
}