{
  "type": "Feature",
  "properties": {
    "addr:full":"3309 E Rock Wren Rd Phoenix AZ 85044",
    "addr:housenumber":"3309",
    "addr:postcode":"85044",
    "addr:street":"E Rock Wren Rd",
    "iso:country":"US",
    "sg:address":"3309 E Rock Wren Rd",
    "sg:city":"Phoenix",
    "sg:classifiers":[
        {
            "category":"Banks & Credit Unions",
            "subcategory":"Financial Services",
            "type":"Services"
        }
    ],
    "sg:phone":"+1 480 759 5171",
    "sg:postcode":"85044",
    "sg:province":"AZ",
    "sg:tags":[
        "investor"
    ],
    "wof:name":"RC Rogers Investments LLC",
    "wof:placetype":"venue"
},
  "geometry": {"coordinates":[-112.011999,33.312767],"type":"Point"}
}