{
  "type": "Feature",
  "properties": {
    "addr:full":"303 E 2nd St Winslow AZ 86047",
    "addr:housenumber":"303",
    "addr:postcode":"86047",
    "addr:street":"E 2Nd St",
    "iso:country":"US",
    "sg:address":"303 E 2nd St",
    "sg:city":"Winslow",
    "sg:classifiers":[
        {
            "category":"Cinema",
            "subcategory":"Movie Theater",
            "type":"Entertainment"
        }
    ],
    "sg:phone":"+1 928 289 4100",
    "sg:postcode":"86047",
    "sg:province":"AZ",
    "wof:name":"Winslow Theatre",
    "wof:placetype":"venue"
},
  "geometry": {"coordinates":[-110.69594600000001,35.022413],"type":"Point"}
}