{
  "type": "Feature",
  "properties": {
    "iso:country":"US",
    "sg:address":"2229 S Orange",
    "sg:city":"Mesa",
    "sg:classifiers":[
        {
            "category":"Professional",
            "subcategory":"Computer Services",
            "type":"Services"
        },
        {
            "category":"Wholesale",
            "subcategory":"Computers",
            "type":"Manufacturing & Wholesale Goods"
        }
    ],
    "sg:phone":"+1 480 612 7443",
    "sg:postcode":"85210",
    "sg:province":"AZ",
    "sg:tags":[
        "equipment",
        "cd-rom",
        "software"
    ],
    "wof:name":"Mgp Computers",
    "wof:placetype":"venue"
},
  "geometry": {"coordinates":[-111.845909,33.374171],"type":"Point"}
}