{
  "type": "Feature",
  "properties": {
    "iso:country":"US",
    "sg:address":"1870 S 4th Ave",
    "sg:city":"Yuma",
    "sg:classifiers":[
        {
            "category":"Professional",
            "type":"Services"
        }
    ],
    "sg:phone":"+1 928 343 0309",
    "sg:postcode":"85364",
    "sg:province":"AZ",
    "wof:name":"D Bennett",
    "wof:placetype":"venue"
},
  "geometry": {"coordinates":[-114.624715,32.693902],"type":"Point"}
}