{
  "type": "Feature",
  "properties": {
    "addr:full":"1850 E 8th St Mesa AZ 85203",
    "addr:housenumber":"1850",
    "addr:postcode":"85203",
    "addr:street":"E 8Th St",
    "iso:country":"US",
    "sg:address":"1850 E 8th St",
    "sg:city":"Mesa",
    "sg:classifiers":[
        {
            "category":"Building & Trades",
            "subcategory":"Construction",
            "type":"Services"
        }
    ],
    "sg:phone":"+1 480 833 2753",
    "sg:postcode":"85203",
    "sg:province":"AZ",
    "sg:tags":[
        "house",
        "contractor",
        "concrete"
    ],
    "wof:name":"On Site Construction Inc",
    "wof:placetype":"venue"
},
  "geometry": {"coordinates":[-111.78868900000001,33.429999],"type":"Point"}
}