{
  "type": "Feature",
  "properties": {
    "iso:country":"US",
    "sg:address":"3415 W Glendale Ave",
    "sg:city":"Phoenix",
    "sg:classifiers":[
        {
            "category":"Health Services",
            "subcategory":"Chiropractor",
            "type":"Services"
        }
    ],
    "sg:phone":"+1 602 973 1630",
    "sg:postcode":"85051",
    "sg:province":"AZ",
    "wof:name":"Mathew Bailey DC",
    "wof:placetype":"venue"
},
  "geometry": {"coordinates":[-112.134018,33.538439],"type":"Point"}
}