{
  "type": "Feature",
  "properties": {
    "iso:country":"US",
    "sg:address":"20235 N Cave Creek Rd Ste 115",
    "sg:city":"Phoenix",
    "sg:phone":"+1 602 404 6449",
    "sg:postcode":"85024",
    "sg:province":"AZ",
    "sg:website":"http://coffeebean.com/",
    "wof:name":"The Coffee Bean & Tea Leaf",
    "wof:placetype":"venue"
},
  "geometry": {"coordinates":[-112.03095999999999,33.670746],"type":"Point"}
}