{
  "type": "Feature",
  "properties": {
    "addr:full":"5606 E Mckellips Rd Mesa AZ 85215",
    "addr:housenumber":"5606",
    "addr:postcode":"85215",
    "addr:street":"E Mckellips Rd",
    "iso:country":"US",
    "sg:address":"5606 E Mckellips Rd",
    "sg:city":"Mesa",
    "sg:classifiers":[
        {
            "category":"Cafe",
            "type":"Food & Drink"
        }
    ],
    "sg:menulink":"http://www.allmenus.com/az/phoenix/2452-the-iowa-cafe/menu/",
    "sg:phone":"+1 480 985 2022",
    "sg:postcode":"85215",
    "sg:province":"AZ",
    "sg:tags":[
        "american"
    ],
    "wof:name":"The Iowa Cafe",
    "wof:placetype":"venue"
},
  "geometry": {"coordinates":[-111.71010200000001,33.451819],"type":"Point"}
}