{
  "type": "Feature",
  "properties": {
    "iso:country":"US",
    "sg:address":"115 W University Dr",
    "sg:city":"Tempe",
    "sg:classifiers":[
        {
            "category":"Personal",
            "type":"Services"
        }
    ],
    "sg:phone":"+1 480 894 2602",
    "sg:postcode":"85281",
    "sg:province":"AZ",
    "sg:tags":[
        "palmist"
    ],
    "wof:name":"Mrs Rita's Palm Reading",
    "wof:placetype":"venue"
},
  "geometry": {"coordinates":[-111.94225,33.421868],"type":"Point"}
}