{
  "type": "Feature",
  "properties": {
    "addr:full":"7780 S Autoplex Loop Tempe AZ 85284",
    "addr:housenumber":"7780",
    "addr:postcode":"85284",
    "addr:street":"S Autoplex Loop",
    "iso:country":"US",
    "sg:address":"7780 S Autoplex Loop",
    "sg:city":"Tempe",
    "sg:classifiers":[
        {
            "category":"Autos & Motor Vehicles",
            "subcategory":"Automobile Sales",
            "type":"Retail Goods"
        }
    ],
    "sg:phone":"+1 877 311 6825",
    "sg:postcode":"85284",
    "sg:province":"AZ",
    "sg:tags":[
        "new",
        "used",
        "car"
    ],
    "sg:website":"http://www.coulter-tempe.com",
    "wof:name":"Coulter Motor Company",
    "wof:placetype":"venue"
},
  "geometry": {"coordinates":[-111.96836399999999,33.347134],"type":"Point"}
}