{
  "type": "Feature",
  "properties": {
    "iso:country":"US",
    "sg:address":"1176 W Apache Ln",
    "sg:city":"Lakeside",
    "sg:classifiers":[
        {
            "category":"Insurance",
            "subcategory":"Insurance Agent",
            "type":"Services"
        }
    ],
    "sg:phone":"+1 928 367 0915",
    "sg:postcode":"85929",
    "sg:province":"AZ",
    "wof:name":"Farmers Insurance",
    "wof:placetype":"venue"
},
  "geometry": {"coordinates":[-109.962372,34.14107],"type":"Point"}
}