{
  "type": "Feature",
  "properties": {
    "iso:country":"US",
    "sg:address":"420 S Perry Ln",
    "sg:city":"Tempe",
    "sg:classifiers":[
        {
            "category":"Wholesale",
            "subcategory":"Meat",
            "type":"Manufacturing & Wholesale Goods"
        }
    ],
    "sg:phone":"+1 480 731 4977",
    "sg:postcode":"85281",
    "sg:province":"AZ",
    "sg:tags":[
        "mfg",
        "product",
        "prod",
        "prepared"
    ],
    "sg:website":"www.datri.com",
    "wof:name":"D'Atri Gourmet Foods",
    "wof:placetype":"venue"
},
  "geometry": {"coordinates":[-111.904803,33.426722],"type":"Point"}
}