{
  "type": "Feature",
  "properties": {
    "iso:country":"US",
    "sg:address":"3219 N Flowing Wells Rd",
    "sg:city":"Tucson",
    "sg:classifiers":[
        {
            "category":"Professional",
            "subcategory":"Accounting & Tax Preparation",
            "type":"Services"
        }
    ],
    "sg:phone":"+1 520 293 1968",
    "sg:postcode":"85705",
    "sg:province":"AZ",
    "sg:tags":[
        "accountant"
    ],
    "wof:name":"James O Benson Jr CPA",
    "wof:placetype":"venue"
},
  "geometry": {"coordinates":[-110.995119,32.265431],"type":"Point"}
}