{
  "type": "Feature",
  "properties": {
    "iso:country":"US",
    "sg:address":"991 N US Hwy 89",
    "sg:city":"Chino Valley",
    "sg:classifiers":[
        {
            "category":"Banks & Credit Unions",
            "subcategory":"Bank",
            "type":"Services"
        }
    ],
    "sg:phone":"+1 928 583 0601",
    "sg:postcode":"86323",
    "sg:province":"AZ",
    "sg:tags":[
        "national"
    ],
    "wof:name":"National Bank of Arizona",
    "wof:placetype":"venue"
},
  "geometry": {"coordinates":[-112.45414100000001,34.731165],"type":"Point"}
}