{
  "type": "Feature",
  "properties": {
    "addr:full":"4506 E Barbarita Ct Gilbert AZ 85234",
    "addr:housenumber":"4506",
    "addr:postcode":"85234",
    "addr:street":"E Barbarita Ct",
    "iso:country":"US",
    "sg:address":"4506 E Barbarita Ct",
    "sg:city":"Gilbert",
    "sg:classifiers":[
        {
            "category":"Manufacturing",
            "subcategory":"Chemicals & Compounds",
            "type":"Manufacturing & Wholesale Goods"
        },
        {
            "category":"Wholesale",
            "subcategory":"Medical Equipment & Supplies",
            "type":"Manufacturing & Wholesale Goods"
        }
    ],
    "sg:phone":"+1 480 503 4872",
    "sg:postcode":"85234",
    "sg:province":"AZ",
    "sg:tags":[
        "pharmaceutical",
        "product",
        "products-wholesale",
        "manufacturer"
    ],
    "sg:website":"http://www.gene.com",
    "wof:name":"Genentech Inc",
    "wof:placetype":"venue"
},
  "geometry": {"coordinates":[-111.693787,33.363503],"type":"Point"}
}