{
  "type": "Feature",
  "properties": {
    "addr:full":"4122 N 17th St Phoenix AZ 85016",
    "addr:housenumber":"4122",
    "addr:postcode":"85016",
    "addr:street":"N 17Th St",
    "iso:country":"US",
    "sg:address":"4122 N 17th St",
    "sg:city":"Phoenix",
    "sg:classifiers":[
        {
            "category":"Real Estate",
            "subcategory":"Real Estate Services",
            "type":"Services"
        },
        {
            "category":"Structure",
            "subcategory":"Office Building",
            "type":"Public Place"
        },
        {
            "category":"Real Estate",
            "subcategory":"Real Estate Agent",
            "type":"Services"
        }
    ],
    "sg:phone":"+1 602 265 4663",
    "sg:postcode":"85016",
    "sg:province":"AZ",
    "sg:tags":[
        "management",
        "park"
    ],
    "wof:name":"Rnh Properties",
    "wof:placetype":"venue"
},
  "geometry": {"coordinates":[-112.04543700000001,33.495161],"type":"Point"}
}