{
  "type": "Feature",
  "properties": {
    "addr:full":"909 E Kaler Dr Phoenix AZ 85020",
    "addr:housenumber":"909",
    "addr:postcode":"85020",
    "addr:street":"E Kaler Dr",
    "iso:country":"US",
    "sg:address":"909 E Kaler Dr",
    "sg:city":"Phoenix",
    "sg:classifiers":[
        {
            "category":"Real Estate",
            "subcategory":"Real Estate Agent",
            "type":"Services"
        }
    ],
    "sg:phone":"+1 602 279 9955",
    "sg:postcode":"85020",
    "sg:province":"AZ",
    "sg:tags":[
        "consultant"
    ],
    "wof:name":"G K Realty",
    "wof:placetype":"venue"
},
  "geometry": {"coordinates":[-112.061526,33.547758],"type":"Point"}
}