{
  "type": "Feature",
  "properties": {
    "iso:country":"US",
    "sg:address":"275 S River Run Rd",
    "sg:city":"Flagstaff",
    "sg:classifiers":[
        {
            "category":"Wholesale",
            "subcategory":"Home Furnishings",
            "type":"Manufacturing & Wholesale Goods"
        },
        {
            "category":"Wholesale",
            "subcategory":"Metals & Minerals",
            "type":"Manufacturing & Wholesale Goods"
        }
    ],
    "sg:phone":"+1 928 527 4390",
    "sg:postcode":"86001",
    "sg:province":"AZ",
    "sg:tags":[
        "blanket"
    ],
    "wof:name":"Babbitt's Wholesale",
    "wof:placetype":"venue"
},
  "geometry": {"coordinates":[-111.637477,35.190206],"type":"Point"}
}