{
  "type": "Feature",
  "properties": {
    "addr:full":"28808 N 49th Pl Cave Creek AZ 85331",
    "addr:housenumber":"28808",
    "addr:postcode":"85331",
    "addr:street":"N 49Th Pl",
    "iso:country":"US",
    "sg:address":"28808 N 49th Pl",
    "sg:city":"Cave Creek",
    "sg:classifiers":[
        {
            "category":"Shopping",
            "subcategory":"Computers & Home Electronics",
            "type":"Retail Goods"
        }
    ],
    "sg:phone":"+1 480 563 1754",
    "sg:postcode":"85331",
    "sg:province":"AZ",
    "sg:tags":[
        "software"
    ],
    "wof:name":"Process Improvement Inttvs",
    "wof:placetype":"venue"
},
  "geometry": {"coordinates":[-111.97547900000001,33.742622],"type":"Point"}
}