{
  "type": "Feature",
  "properties": {
    "addr:full":"1051 S 81st Pl Mesa AZ 85208",
    "addr:housenumber":"1051",
    "addr:postcode":"85208",
    "addr:street":"S 81St Pl",
    "iso:country":"US",
    "sg:address":"1051 S 81st Pl",
    "sg:city":"Mesa",
    "sg:classifiers":[
        {
            "category":"Banks & Credit Unions",
            "subcategory":"Financial Services",
            "type":"Services"
        }
    ],
    "sg:phone":"+1 480 984 5625",
    "sg:postcode":"85208",
    "sg:province":"AZ",
    "sg:tags":[
        "investor"
    ],
    "wof:name":"Lennon Group LLC",
    "wof:placetype":"venue"
},
  "geometry": {"coordinates":[-111.655722,33.394876],"type":"Point"}
}