{
  "type": "Feature",
  "properties": {
    "iso:country":"US",
    "sg:address":"5210 N 19th Ave",
    "sg:city":"Phoenix",
    "sg:classifiers":[
        {
            "category":"Autos & Motor Vehicles",
            "subcategory":"Auto Supplies",
            "type":"Retail Goods"
        },
        {
            "category":"Shopping",
            "subcategory":"Computers & Home Electronics",
            "type":"Retail Goods"
        }
    ],
    "sg:phone":"+1 602 433 0777",
    "sg:postcode":"85015",
    "sg:province":"AZ",
    "sg:tags":[
        "stereo",
        "theater",
        "automobile",
        "system",
        "radio",
        "consumer"
    ],
    "wof:name":"Discount Electronic Center",
    "wof:placetype":"venue"
},
  "geometry": {"coordinates":[-112.099943,33.513641],"type":"Point"}
}