{
  "type": "Feature",
  "properties": {
    "iso:country":"US",
    "sg:address":"4700 N Central Ave",
    "sg:city":"Phoenix",
    "sg:classifiers":[
        {
            "category":"Personal",
            "subcategory":"Beauty Salon",
            "type":"Services"
        }
    ],
    "sg:phone":"+1 602 279 4247",
    "sg:postcode":"85012",
    "sg:province":"AZ",
    "wof:name":"Salon Matthew Stephens",
    "wof:placetype":"venue"
},
  "geometry": {"coordinates":[-112.073832,33.505456],"type":"Point"}
}