{
  "type": "Feature",
  "properties": {
    "iso:country":"US",
    "sg:address":"2401 N 32nd St",
    "sg:city":"Phoenix",
    "sg:classifiers":[
        {
            "category":"Utilities",
            "subcategory":"Mobile Phone",
            "type":"Services"
        }
    ],
    "sg:phone":"+1 602 957 2113",
    "sg:postcode":"85008",
    "sg:province":"AZ",
    "sg:tags":[
        "telephone",
        "cellular"
    ],
    "wof:name":"Happy Cellular",
    "wof:placetype":"venue"
},
  "geometry": {"coordinates":[-112.01290299999999,33.474959],"type":"Point"}
}