{
  "type": "Feature",
  "properties": {
    "addr:full":"8096 N 85th Way Ste 105 Scottsdale AZ 85258",
    "addr:housenumber":"8096",
    "addr:postcode":"85258",
    "addr:street":"N 85Th Way Ste 105",
    "iso:country":"US",
    "sg:address":"8096 N 85th Way Ste 105",
    "sg:city":"Scottsdale",
    "sg:classifiers":[
        {
            "category":"Manufacturing",
            "subcategory":"Electronics",
            "type":"Manufacturing & Wholesale Goods"
        },
        {
            "category":"Shopping",
            "subcategory":"Computers & Home Electronics",
            "type":"Retail Goods"
        }
    ],
    "sg:phone":"+1 480 607 7370",
    "sg:postcode":"85258",
    "sg:province":"AZ",
    "sg:tags":[
        "supplies-wholesale",
        "manufacturer",
        "electronic",
        "consumer",
        "equipment"
    ],
    "sg:website":"http://www.dapdesign.com",
    "wof:name":"Riley Solutions Inc",
    "wof:placetype":"venue"
},
  "geometry": {"coordinates":[-111.896114,33.554491],"type":"Point"}
}