{
  "type": "Feature",
  "properties": {
    "iso:country":"US",
    "sg:address":"4444 E Tennessee St",
    "sg:city":"Tucson",
    "sg:classifiers":[
        {
            "category":"Manufacturing",
            "subcategory":"Motor Vehicles & Parts",
            "type":"Manufacturing & Wholesale Goods"
        }
    ],
    "sg:phone":"+1 520 748 7075",
    "sg:postcode":"85714",
    "sg:province":"AZ",
    "sg:tags":[
        "body",
        "mfg",
        "truck",
        "custom"
    ],
    "wof:name":"Southern Truck Equipment Inc",
    "wof:placetype":"venue"
},
  "geometry": {"coordinates":[-110.898167,32.166029],"type":"Point"}
}