{
  "type": "Feature",
  "properties": {
    "addr:full":"2462 N Pantano Rd Tucson AZ 85715",
    "addr:housenumber":"2462",
    "addr:postcode":"85715",
    "addr:street":"N Pantano Rd",
    "iso:country":"US",
    "sg:address":"2462 N Pantano Rd",
    "sg:city":"Tucson",
    "sg:classifiers":[
        {
            "category":"Professional",
            "type":"Services"
        }
    ],
    "sg:phone":"+1 520 546 1527",
    "sg:postcode":"85715",
    "sg:province":"AZ",
    "sg:tags":[
        "establishment"
    ],
    "wof:name":"FSI",
    "wof:placetype":"venue"
},
  "geometry": {"coordinates":[-110.82355200000001,32.25191],"type":"Point"}
}