{
  "type": "Feature",
  "properties": {
    "iso:country":"US",
    "sg:address":"330 N Huachuca Blvd",
    "sg:city":"Huachuca City",
    "sg:classifiers":[
        {
            "category":"Food & Beverages",
            "subcategory":"Groceries & Convenience Stores",
            "type":"Retail Goods"
        }
    ],
    "sg:phone":"+1 520 456 1310",
    "sg:postcode":"85616",
    "sg:province":"AZ",
    "sg:tags":[
        "station",
        "gasoline"
    ],
    "wof:name":"Circle K",
    "wof:placetype":"venue"
},
  "geometry": {"coordinates":[-110.33561400000001,31.62649],"type":"Point"}
}