{
  "type": "Feature",
  "properties": {
    "iso:country":"US",
    "sg:address":"125 S 56th St",
    "sg:city":"Mesa",
    "sg:classifiers":[
        {
            "category":"Real Estate",
            "subcategory":"Architect",
            "type":"Services"
        }
    ],
    "sg:phone":"+1 480 830 7992",
    "sg:postcode":"85206",
    "sg:province":"AZ",
    "wof:name":"Artec Designs",
    "wof:placetype":"venue"
},
  "geometry": {"coordinates":[-111.710418,33.411607],"type":"Point"}
}