{
  "type": "Feature",
  "properties": {
    "iso:country":"US",
    "sg:address":"7822 N 12th St",
    "sg:city":"Phoenix",
    "sg:classifiers":[
        {
            "category":"Restaurant",
            "type":"Food & Drink"
        }
    ],
    "sg:phone":"+1 602 216 9600",
    "sg:postcode":"85020",
    "sg:province":"AZ",
    "sg:tags":[
        "buffet",
        "chinese"
    ],
    "wof:name":"Happy Buffett",
    "wof:placetype":"venue"
},
  "geometry": {"coordinates":[-112.056581,33.551352],"type":"Point"}
}