{
  "type": "Feature",
  "properties": {
    "iso:country":"US",
    "sg:address":"1125 W Elliot Rd",
    "sg:city":"Tempe",
    "sg:classifiers":[
        {
            "category":"Restaurant",
            "type":"Food & Drink"
        }
    ],
    "sg:phone":"+1 480 753 1811",
    "sg:postcode":"85284",
    "sg:province":"AZ",
    "sg:tags":[
        "style",
        "family"
    ],
    "wof:name":"City Chen Phoenix Corp",
    "wof:placetype":"venue"
},
  "geometry": {"coordinates":[-111.955376,33.349072],"type":"Point"}
}