{
  "type": "Feature",
  "properties": {
    "iso:country":"US",
    "sg:address":"3161 Hwy 95",
    "sg:city":"Bullhead City",
    "sg:classifiers":[
        {
            "category":"Home & Garden",
            "subcategory":"Garden Supply",
            "type":"Retail Goods"
        }
    ],
    "sg:phone":"+1 928 758 7755",
    "sg:postcode":"86442",
    "sg:province":"AZ",
    "wof:name":"Yard Bird",
    "wof:placetype":"venue"
},
  "geometry": {"coordinates":[-114.589979,35.071168],"type":"Point"}
}