{
  "type": "Feature",
  "properties": {
    "iso:country":"US",
    "sg:address":"4040 E Magnolia St",
    "sg:city":"Phoenix",
    "sg:classifiers":[
        {
            "category":"Building & Trades",
            "subcategory":"Construction",
            "type":"Services"
        }
    ],
    "sg:phone":"+1 602 454 2949",
    "sg:postcode":"85034",
    "sg:province":"AZ",
    "sg:tags":[
        "engineering"
    ],
    "wof:name":"S J Louis Construction Inc",
    "wof:placetype":"venue"
},
  "geometry": {"coordinates":[-111.993384,33.422882],"type":"Point"}
}