{
  "type": "Feature",
  "properties": {
    "iso:country":"US",
    "sg:address":"5055 S 12th Ave",
    "sg:city":"Tucson",
    "sg:classifiers":[
        {
            "category":"Shopping",
            "subcategory":"Clothing, Apparel, & Fashions",
            "type":"Retail Goods"
        }
    ],
    "sg:phone":"+1 520 889 1047",
    "sg:postcode":"85706",
    "sg:province":"AZ",
    "sg:tags":[
        "shop",
        "bridal"
    ],
    "wof:name":"Divina Bridal & Flowers",
    "wof:placetype":"venue"
},
  "geometry": {"coordinates":[-110.977426,32.161553],"type":"Point"}
}