{
  "type": "Feature",
  "properties": {
    "iso:country":"US",
    "sg:address":"81 W Vera Ln",
    "sg:city":"Tempe",
    "sg:classifiers":[
        {
            "category":"Professional",
            "subcategory":"Management & Consulting",
            "type":"Services"
        }
    ],
    "sg:phone":"+1 480 961 3643",
    "sg:postcode":"85284",
    "sg:province":"AZ",
    "sg:tags":[
        "consultant",
        "automation"
    ],
    "wof:name":"Home Applied Automation Inc",
    "wof:placetype":"venue"
},
  "geometry": {"coordinates":[-111.939066,33.325699],"type":"Point"}
}