{
  "type": "Feature",
  "properties": {
    "iso:country":"US",
    "sg:address":"39506 N. Daisy Mountain Dr. Suite 122-433",
    "sg:city":"Phoenix",
    "sg:classifiers":[
        {
            "category":"Professional",
            "subcategory":"Advertising",
            "type":"Services"
        }
    ],
    "sg:phone":"+1 623 551 3742",
    "sg:postcode":"85086",
    "sg:province":"AZ",
    "sg:tags":[
        "seo",
        "sem",
        "smm",
        "smo",
        "link-building",
        "ppc"
    ],
    "sg:website":"http://www.searchrank.com",
    "wof:name":"SearchRank",
    "wof:placetype":"venue"
},
  "geometry": {"coordinates":[-112.114119,33.856514],"type":"Point"}
}