{
  "type": "Feature",
  "properties": {
    "iso:country":"US",
    "sg:address":"15620 E Chandler Heights Rd",
    "sg:city":"Gilbert",
    "sg:phone":"+1 480 242 6456",
    "sg:postcode":"85298",
    "sg:province":"AZ",
    "wof:name":"Sanchez Fencing",
    "wof:placetype":"venue"
},
  "geometry": {"coordinates":[-111.745973,33.233935],"type":"Point"}
}