{
  "type": "Feature",
  "properties": {
    "addr:full":"1325 W Pso del Compadre Sahuarita AZ 85629",
    "addr:housenumber":"1325",
    "addr:postcode":"85629",
    "addr:street":"W Pso Del Compadre",
    "iso:country":"US",
    "sg:address":"1325 W Pso del Compadre",
    "sg:city":"Sahuarita",
    "sg:classifiers":[
        {
            "category":"Professional",
            "type":"Services"
        }
    ],
    "sg:phone":"+1 520 393 1942",
    "sg:postcode":"85629",
    "sg:province":"AZ",
    "wof:name":"Pima Unlimited LLC",
    "wof:placetype":"venue"
},
  "geometry": {"coordinates":[-110.993633,31.922399],"type":"Point"}
}