{
  "type": "Feature",
  "properties": {
    "iso:country":"US",
    "sg:address":"1201 E Northern Ave",
    "sg:city":"Phoenix",
    "sg:classifiers":[
        {
            "category":"Autos & Motor Vehicles",
            "subcategory":"Fuel & Gas Station",
            "type":"Retail Goods"
        },
        {
            "category":"Food & Beverages",
            "subcategory":"Groceries & Convenience Stores",
            "type":"Retail Goods"
        }
    ],
    "sg:phone":"+1 602 943 4630",
    "sg:postcode":"85020",
    "sg:province":"AZ",
    "sg:website":"http://www.arco.com/",
    "wof:name":"ARCO Station",
    "wof:placetype":"venue"
},
  "geometry": {"coordinates":[-112.05661000000001,33.553051],"type":"Point"}
}