{
  "type": "Feature",
  "properties": {
    "iso:country":"US",
    "sg:address":"3275 W Ina Rd",
    "sg:city":"Tucson",
    "sg:classifiers":[
        {
            "category":"Home & Garden",
            "subcategory":"Mobile Homes",
            "type":"Retail Goods"
        }
    ],
    "sg:phone":"+1 520 977 6804",
    "sg:postcode":"85741",
    "sg:province":"AZ",
    "sg:tags":[
        "dealer"
    ],
    "wof:name":"William M Naponelli",
    "wof:placetype":"venue"
},
  "geometry": {"coordinates":[-111.034265,32.337342],"type":"Point"}
}