{
  "type": "Feature",
  "properties": {
    "addr:full":"8849 N 7th St Phoenix AZ 85020",
    "addr:housenumber":"8849",
    "addr:postcode":"85020",
    "addr:street":"N 7Th St",
    "iso:country":"US",
    "sg:address":"8849 N 7th St",
    "sg:city":"Phoenix",
    "sg:classifiers":[
        {
            "category":"Restaurant",
            "type":"Food & Drink"
        }
    ],
    "sg:menulink":"http://www.allmenus.com/az/phoenix/190617-mcdonalds/menu/",
    "sg:postcode":"85020",
    "sg:province":"AZ",
    "sg:tags":[
        "burger",
        "american"
    ],
    "wof:name":"McDonald's",
    "wof:placetype":"venue"
},
  "geometry": {"coordinates":[-112.064682,33.565695],"type":"Point"}
}