{
  "type": "Feature",
  "properties": {
    "iso:country":"US",
    "sg:address":"420 N Pinal Dr",
    "sg:city":"Apache Junction",
    "sg:classifiers":[
        {
            "category":"Restaurant",
            "type":"Food & Drink"
        }
    ],
    "sg:phone":"+1 480 983 8273",
    "sg:postcode":"85220",
    "sg:province":"AZ",
    "sg:tags":[
        "eating"
    ],
    "wof:name":"Pleasure Time Grill",
    "wof:placetype":"venue"
},
  "geometry": {"coordinates":[-111.577448,33.419219],"type":"Point"}
}