{
  "type": "Feature",
  "properties": {
    "addr:full":"17226 N 47th St Phoenix AZ 85032",
    "addr:housenumber":"17226",
    "addr:postcode":"85032",
    "addr:street":"N 47Th St",
    "iso:country":"US",
    "sg:address":"17226 N 47th St",
    "sg:city":"Phoenix",
    "sg:classifiers":[
        {
            "category":"Social Services",
            "subcategory":"Child Care",
            "type":"Services"
        }
    ],
    "sg:phone":"+1 602 388 3728",
    "sg:postcode":"85032",
    "sg:province":"AZ",
    "sg:tags":[
        "nursery",
        "day"
    ],
    "wof:name":"Ultimate Start",
    "wof:placetype":"venue"
},
  "geometry": {"coordinates":[-111.97998,33.64335],"type":"Point"}
}