{
  "type": "Feature",
  "properties": {
    "iso:country":"US",
    "sg:address":"4535 E Oregon Ave",
    "sg:city":"Phoenix",
    "sg:classifiers":[
        {
            "category":"Professional",
            "type":"Services"
        }
    ],
    "sg:phone":"+1 602 840 6119",
    "sg:postcode":"85018",
    "sg:province":"AZ",
    "wof:name":"Nadler Co An Arizona General P",
    "wof:placetype":"venue"
},
  "geometry": {"coordinates":[-111.98185700000001,33.514102],"type":"Point"}
}