{
  "type": "Feature",
  "properties": {
    "iso:country":"US",
    "sg:address":"3120 N Red Mountain",
    "sg:city":"Mesa",
    "sg:classifiers":[
        {
            "category":"Education",
            "subcategory":"School",
            "type":"Public Place"
        }
    ],
    "sg:phone":"+1 480 807 7898",
    "sg:postcode":"85207",
    "sg:province":"AZ",
    "wof:name":"Mesa Public Schools Las Sendas",
    "wof:placetype":"venue"
},
  "geometry": {"coordinates":[-111.675014,33.470612],"type":"Point"}
}