{
  "type": "Feature",
  "properties": {
    "addr:full":"153 S Mesa Dr Mesa AZ 85210",
    "addr:housenumber":"153",
    "addr:postcode":"85210",
    "addr:street":"S Mesa Dr",
    "iso:country":"US",
    "sg:address":"153 S Mesa Dr",
    "sg:city":"Mesa",
    "sg:classifiers":[
        {
            "category":"Professional",
            "subcategory":"Computer Services",
            "type":"Services"
        }
    ],
    "sg:phone":"+1 480 833 2755",
    "sg:postcode":"85210",
    "sg:province":"AZ",
    "sg:tags":[
        "related"
    ],
    "wof:name":"Ryan Jones PC",
    "wof:placetype":"venue"
},
  "geometry": {"coordinates":[-111.822891,33.410728],"type":"Point"}
}