{
  "type": "Feature",
  "properties": {
    "iso:country":"US",
    "sg:address":"1955 W Grant Rd",
    "sg:city":"Tucson",
    "sg:classifiers":[
        {
            "category":"Food & Beverages",
            "subcategory":"Specialty",
            "type":"Retail Goods"
        }
    ],
    "sg:phone":"+1 520 623 0053",
    "sg:postcode":"85745",
    "sg:province":"AZ",
    "sg:tags":[
        "health",
        "diet"
    ],
    "wof:name":"Shaklee Distributor",
    "wof:placetype":"venue"
},
  "geometry": {"coordinates":[-111.00702699999999,32.250516],"type":"Point"}
}