{
  "type": "Feature",
  "properties": {
    "iso:country":"US",
    "sg:address":"3121 E Kleindale Rd",
    "sg:city":"Tucson",
    "sg:classifiers":[
        {
            "category":"Real Estate",
            "subcategory":"Surveying",
            "type":"Services"
        }
    ],
    "sg:phone":"+1 520 881 2155",
    "sg:postcode":"85716",
    "sg:province":"AZ",
    "sg:tags":[
        "surveyor"
    ],
    "sg:website":"www.arrowlandsurvey.com",
    "wof:name":"Arrow Land Survey Inc",
    "wof:placetype":"venue"
},
  "geometry": {"coordinates":[-110.926533,32.268767],"type":"Point"}
}