{
  "type": "Feature",
  "properties": {
    "addr:full":"2880 E Grant Rd Tucson AZ 85716",
    "addr:housenumber":"2880",
    "addr:postcode":"85716",
    "addr:street":"E Grant Rd",
    "iso:country":"US",
    "sg:address":"2880 E Grant Rd",
    "sg:city":"Tucson",
    "sg:classifiers":[
        {
            "category":"Shopping",
            "subcategory":"Used Merchandise",
            "type":"Retail Goods"
        }
    ],
    "sg:phone":"+1 520 319 1122",
    "sg:postcode":"85716",
    "sg:province":"AZ",
    "sg:tags":[
        "pawnbroker"
    ],
    "wof:name":"Loan Prairie",
    "wof:placetype":"venue"
},
  "geometry": {"coordinates":[-110.93083300000001,32.250283],"type":"Point"}
}