{
  "type": "Feature",
  "properties": {
    "iso:country":"US",
    "sg:address":"10193 E Happy Valley Rd",
    "sg:city":"Scottsdale",
    "sg:classifiers":[
        {
            "category":"Professional",
            "type":"Services"
        }
    ],
    "sg:phone":"+1 480 585 4323",
    "sg:postcode":"85255",
    "sg:province":"AZ",
    "wof:name":"D B Dahlin",
    "wof:placetype":"venue"
},
  "geometry": {"coordinates":[-111.862295,33.712646],"type":"Point"}
}