{
  "type": "Feature",
  "properties": {
    "addr:full":"2104 N 23rd Ave Phoenix AZ 85009",
    "addr:housenumber":"2104",
    "addr:postcode":"85009",
    "addr:street":"N 23Rd Ave",
    "iso:country":"US",
    "sg:address":"2104 N 23rd Ave",
    "sg:city":"Phoenix",
    "sg:classifiers":[
        {
            "category":"Home & Garden",
            "subcategory":"Home Furnishings",
            "type":"Retail Goods"
        }
    ],
    "sg:phone":"+1 602 262 5483",
    "sg:postcode":"85009",
    "sg:province":"AZ",
    "sg:tags":[
        "lighting",
        "fixture"
    ],
    "wof:name":"Andrew's Stage Lighting & Snd",
    "wof:placetype":"venue"
},
  "geometry": {"coordinates":[-112.109641,33.473218],"type":"Point"}
}