{
  "type": "Feature",
  "properties": {
    "addr:full":"740 E Mingus Ave Cottonwood AZ 86326",
    "addr:housenumber":"740",
    "addr:postcode":"86326",
    "addr:street":"E Mingus Ave",
    "iso:country":"US",
    "sg:address":"740 E Mingus Ave",
    "sg:city":"Cottonwood",
    "sg:classifiers":[
        {
            "category":"Shopping",
            "type":"Retail Goods"
        }
    ],
    "sg:phone":"+1 928 649 7420",
    "sg:postcode":"86326",
    "sg:province":"AZ",
    "sg:tags":[
        "merchandise"
    ],
    "wof:name":"J Reed & Sons",
    "wof:placetype":"venue"
},
  "geometry": {"coordinates":[-112.020658,34.739615],"type":"Point"}
}