{
  "type": "Feature",
  "properties": {
    "iso:country":"US",
    "sg:address":"181 State Hwy 179",
    "sg:city":"Sedona",
    "sg:classifiers":[
        {
            "category":"Shopping",
            "subcategory":"Used Merchandise",
            "type":"Retail Goods"
        }
    ],
    "sg:phone":"+1 928 282 4343",
    "sg:postcode":"86336",
    "sg:province":"AZ",
    "sg:tags":[
        "antique"
    ],
    "wof:name":"Delightful Muddle-Antiques",
    "wof:placetype":"venue"
},
  "geometry": {"coordinates":[-111.763593,34.863157],"type":"Point"}
}