{
  "type": "Feature",
  "properties": {
    "iso:country":"US",
    "sg:address":"6553 E Russell St",
    "sg:city":"Mesa",
    "sg:classifiers":[
        {
            "category":"Retail",
            "subcategory":"Laundry & Dry Cleaning",
            "type":"Services"
        },
        {
            "category":"Retail",
            "subcategory":"Repair Shop",
            "type":"Services"
        },
        {
            "category":"Building & Trades",
            "subcategory":"Construction",
            "type":"Services"
        },
        {
            "category":"Building & Trades",
            "subcategory":"Cleaning & Sanitation",
            "type":"Services"
        }
    ],
    "sg:phone":"+1 480 832 5629",
    "sg:postcode":"85215",
    "sg:province":"AZ",
    "sg:tags":[
        "cleaner",
        "upholstery",
        "house",
        "rug",
        "specialty",
        "window",
        "heating",
        "curtain",
        "contractor",
        "drapery",
        "carpet"
    ],
    "wof:name":"Marsol Carpet Care Services",
    "wof:placetype":"venue"
},
  "geometry": {"coordinates":[-111.68765500000001,33.475965],"type":"Point"}
}