{
  "type": "Feature",
  "properties": {
    "addr:full":"637 E Main St Mesa AZ 85203",
    "addr:housenumber":"637",
    "addr:postcode":"85203",
    "addr:street":"E Main St",
    "iso:country":"US",
    "sg:address":"637 E Main St",
    "sg:city":"Mesa",
    "sg:classifiers":[
        {
            "category":"Health Services",
            "subcategory":"Chiropractor",
            "type":"Services"
        }
    ],
    "sg:phone":"+1 602 628 0839",
    "sg:postcode":"85203",
    "sg:province":"AZ",
    "wof:name":"Quest For Health Chiro Life",
    "wof:placetype":"venue"
},
  "geometry": {"coordinates":[-111.817198,33.415023],"type":"Point"}
}