{
  "type": "Feature",
  "properties": {
    "iso:country":"US",
    "sg:address":"6 E Palo Verde St Ste 12/13",
    "sg:city":"Gilbert",
    "sg:classifiers":[
        {
            "category":"Sports & Exercise",
            "subcategory":"Gym",
            "type":"Entertainment"
        }
    ],
    "sg:phone":"+1 480 507 9642",
    "sg:postcode":"85296",
    "sg:province":"AZ",
    "sg:tags":[
        "yoga"
    ],
    "sg:website":"www.gilbertyoga.com",
    "wof:name":"Gilbert Yoga",
    "wof:placetype":"venue"
},
  "geometry": {"coordinates":[-111.788957,33.348024],"type":"Point"}
}