{
  "type": "Feature",
  "properties": {
    "addr:full":"4390 N 1st Ave Tucson AZ 85719",
    "addr:housenumber":"4390",
    "addr:postcode":"85719",
    "addr:street":"N 1St Ave",
    "iso:country":"US",
    "sg:address":"4390 N 1st Ave",
    "sg:city":"Tucson",
    "sg:classifiers":[
        {
            "category":"Food & Beverages",
            "subcategory":"Groceries & Convenience Stores",
            "type":"Retail Goods"
        }
    ],
    "sg:phone":"+1 520 292 2196",
    "sg:postcode":"85719",
    "sg:province":"AZ",
    "wof:name":"Chevron",
    "wof:placetype":"venue"
},
  "geometry": {"coordinates":[-110.961018,32.28574],"type":"Point"}
}