{
  "type": "Feature",
  "properties": {
    "addr:full":"10520 S Samuel Rd Hereford AZ 85615",
    "addr:housenumber":"10520",
    "addr:postcode":"85615",
    "addr:street":"S Samuel Rd",
    "iso:country":"US",
    "sg:address":"10520 S Samuel Rd",
    "sg:city":"Hereford",
    "sg:phone":"+1 520 366 0506",
    "sg:postcode":"85615",
    "sg:province":"AZ",
    "wof:name":"Palominas Acupuncture And Oriental Medicine",
    "wof:placetype":"venue"
},
  "geometry": {"coordinates":[-110.164686,31.375351],"type":"Point"}
}