{
  "type": "Feature",
  "properties": {
    "iso:country":"US",
    "sg:address":"3877 N 7th St Ste 101",
    "sg:city":"Phoenix",
    "sg:classifiers":[
        {
            "category":"Government",
            "subcategory":"Office",
            "type":"Public Place"
        }
    ],
    "sg:phone":"+1 602 938 4425",
    "sg:postcode":"85014",
    "sg:province":"AZ",
    "sg:tags":[
        "government-united",
        "state"
    ],
    "sg:website":"http://www.arizonahighways.com",
    "wof:name":"Arizona Dept Of Transportation",
    "wof:placetype":"venue"
},
  "geometry": {"coordinates":[-112.065048,33.492547],"type":"Point"}
}