{
  "type": "Feature",
  "properties": {
    "iso:country":"US",
    "sg:address":"1157 N Gilbert Road",
    "sg:city":"Gilbert",
    "sg:classifiers":[
        {
            "category":"Food & Beverages",
            "subcategory":"Groceries & Convenience Stores",
            "type":"Retail Goods"
        }
    ],
    "sg:phone":"+1 480 926 4068",
    "sg:postcode":"85234",
    "sg:province":"AZ",
    "wof:name":"7-Eleven Food Stores",
    "wof:placetype":"venue"
},
  "geometry": {"coordinates":[-111.79005100000001,33.371339],"type":"Point"}
}