{
  "type": "Feature",
  "properties": {
    "addr:full":"1522 E Victory St Ste 1 Phoenix AZ 85040",
    "addr:housenumber":"1522",
    "addr:postcode":"85040",
    "addr:street":"E Victory St Ste 1",
    "iso:country":"US",
    "sg:address":"1522 E Victory St Ste 1",
    "sg:city":"Phoenix",
    "sg:classifiers":[
        {
            "category":"Manufacturing",
            "subcategory":"Metals",
            "type":"Manufacturing & Wholesale Goods"
        },
        {
            "category":"Professional",
            "subcategory":"Art Services",
            "type":"Services"
        },
        {
            "category":"Building & Trades",
            "subcategory":"Construction",
            "type":"Services"
        }
    ],
    "sg:phone":"+1 602 276 8101",
    "sg:postcode":"85040",
    "sg:province":"AZ",
    "sg:tags":[
        "ornamental",
        "work",
        "iron",
        "welder"
    ],
    "sg:website":"http://www.eaglewingsironcraft.com",
    "wof:name":"Eaglewings Iron Craft",
    "wof:placetype":"venue"
},
  "geometry": {"coordinates":[-112.04791400000001,33.415958],"type":"Point"}
}