{
  "type": "Feature",
  "properties": {
    "iso:country":"US",
    "sg:address":"252 W 32nd St",
    "sg:city":"Yuma",
    "sg:classifiers":[
        {
            "category":"Food & Beverages",
            "subcategory":"Groceries & Convenience Stores",
            "type":"Retail Goods"
        }
    ],
    "sg:phone":"+1 928 726 9500",
    "sg:postcode":"85364",
    "sg:province":"AZ",
    "sg:tags":[
        "supermarket",
        "chain"
    ],
    "wof:name":"Albertsons 951",
    "wof:placetype":"venue"
},
  "geometry": {"coordinates":[-114.623103,32.669436],"type":"Point"}
}