{
  "type": "Feature",
  "properties": {
    "addr:full":"1322 US Hwy 66 Flagstaff AZ 86001",
    "addr:housenumber":"1322",
    "addr:postcode":"86001",
    "addr:street":"Us Hwy 66",
    "iso:country":"US",
    "sg:address":"1322 US Hwy 66",
    "sg:city":"Flagstaff",
    "sg:classifiers":[
        {
            "category":"Autos & Motor Vehicles",
            "subcategory":"Fuel & Gas Station",
            "type":"Retail Goods"
        }
    ],
    "sg:phone":"+1 928 774 7844",
    "sg:postcode":"86001",
    "sg:province":"AZ",
    "sg:tags":[
        "station",
        "gasoline"
    ],
    "wof:name":"Carter 76 Mart",
    "wof:placetype":"venue"
},
  "geometry": {"coordinates":[-111.669498,35.188079],"type":"Point"}
}