{
  "type": "Feature",
  "properties": {
    "iso:country":"US",
    "sg:address":"2590 US Hwy 66",
    "sg:city":"Williams",
    "sg:phone":"+1 928 635 4543",
    "sg:postcode":"86046",
    "sg:province":"AZ",
    "sg:tags":[
        "oil",
        "gasoline"
    ],
    "wof:name":"M & M Oil Co",
    "wof:placetype":"venue"
},
  "geometry": {"coordinates":[-112.214555,35.245267],"type":"Point"}
}