{
  "type": "Feature",
  "properties": {
    "iso:country":"US",
    "sg:address":"4201 N 24th St",
    "sg:city":"Phoenix",
    "sg:classifiers":[
        {
            "category":"Banks & Credit Unions",
            "subcategory":"Bank",
            "type":"Services"
        }
    ],
    "sg:phone":"+1 602 468 9307",
    "sg:postcode":"85016",
    "sg:province":"AZ",
    "sg:tags":[
        "mortgage"
    ],
    "wof:name":"Robert C Wilson Company",
    "wof:placetype":"venue"
},
  "geometry": {"coordinates":[-112.03012,33.495007],"type":"Point"}
}