{
  "type": "Feature",
  "properties": {
    "iso:country":"US",
    "sg:address":"12871 E Becker Ln",
    "sg:city":"Scottsdale",
    "sg:classifiers":[
        {
            "category":"Home & Garden",
            "subcategory":"Household Appliances",
            "type":"Retail Goods"
        },
        {
            "category":"Retail",
            "subcategory":"Laundry & Dry Cleaning",
            "type":"Services"
        },
        {
            "category":"Building & Trades",
            "subcategory":"Cleaning & Sanitation",
            "type":"Services"
        }
    ],
    "sg:phone":"+1 480 614 5273",
    "sg:postcode":"85259",
    "sg:province":"AZ",
    "sg:tags":[
        "cleaner",
        "upholstery",
        "duct",
        "house",
        "rug",
        "air",
        "ventilation",
        "cleaning-industrial",
        "vacuum",
        "curtain",
        "drapery",
        "carpet"
    ],
    "sg:website":"http://www.servicemasterclean.com/reslf/smclean_leadform.asp?url=http://www.servicemasterclean.com/reslf/smclean_leadform.asp&partnerName=YellowPages.com&adName=yptl&HGProp=SMClean",
    "wof:name":"ServiceMaster Clean",
    "wof:placetype":"venue"
},
  "geometry": {"coordinates":[-111.80292,33.583049],"type":"Point"}
}