{
  "type": "Feature",
  "properties": {
    "addr:full":"15721 E Yucca Dr Fountain Hills AZ 85268",
    "addr:housenumber":"15721",
    "addr:postcode":"85268",
    "addr:street":"E Yucca Dr",
    "iso:country":"US",
    "sg:address":"15721 E Yucca Dr",
    "sg:city":"Fountain Hills",
    "sg:classifiers":[
        {
            "category":"Freight",
            "type":"Transportation"
        }
    ],
    "sg:phone":"+1 480 836 8613",
    "sg:postcode":"85268",
    "sg:province":"AZ",
    "sg:tags":[
        "operator",
        "trucking"
    ],
    "wof:name":"Alex Inc",
    "wof:placetype":"venue"
},
  "geometry": {"coordinates":[-111.740559,33.618458],"type":"Point"}
}