{
  "type": "Feature",
  "properties": {
    "addr:full":"5650 E 22nd St Tucson AZ 85711",
    "addr:housenumber":"5650",
    "addr:postcode":"85711",
    "addr:street":"E 22Nd St",
    "iso:country":"US",
    "sg:address":"5650 E 22nd St",
    "sg:city":"Tucson",
    "sg:classifiers":[
        {
            "category":"Health Services",
            "subcategory":"Doctor",
            "type":"Services"
        }
    ],
    "sg:phone":"+1 520 747 8494",
    "sg:postcode":"85711",
    "sg:province":"AZ",
    "sg:tags":[
        "physician",
        "surgeon"
    ],
    "wof:name":"Southwest Gecko",
    "wof:placetype":"venue"
},
  "geometry": {"coordinates":[-110.871796,32.206837],"type":"Point"}
}