{
  "type": "Feature",
  "properties": {
    "addr:full":"10570 S Nogales Hwy Tucson AZ 85706",
    "addr:housenumber":"10570",
    "addr:postcode":"85706",
    "addr:street":"S Nogales Hwy",
    "iso:country":"US",
    "sg:address":"10570 S Nogales Hwy",
    "sg:city":"Tucson",
    "sg:classifiers":[
        {
            "category":"Building & Trades",
            "subcategory":"Construction",
            "type":"Services"
        }
    ],
    "sg:phone":"+1 520 746 0176",
    "sg:postcode":"85706",
    "sg:province":"AZ",
    "sg:tags":[
        "dry wall",
        "contractor"
    ],
    "wof:name":"Antonick Drywall Co",
    "wof:placetype":"venue"
},
  "geometry": {"coordinates":[-110.954988,32.058549],"type":"Point"}
}