{
  "type": "Feature",
  "properties": {
    "addr:full":"16815 N 29th St Phoenix AZ 85032",
    "addr:housenumber":"16815",
    "addr:postcode":"85032",
    "addr:street":"N 29Th St",
    "iso:country":"US",
    "sg:address":"16815 N 29th St",
    "sg:city":"Phoenix",
    "sg:classifiers":[
        {
            "category":"Real Estate",
            "subcategory":"Real Estate Operator",
            "type":"Services"
        }
    ],
    "sg:phone":"+1 602 404 1100",
    "sg:postcode":"85032",
    "sg:province":"AZ",
    "sg:tags":[
        "building",
        "apartment"
    ],
    "wof:name":"Harbor Ridge Apartments",
    "wof:placetype":"venue"
},
  "geometry": {"coordinates":[-112.019927,33.640477],"type":"Point"}
}