{
  "type": "Feature",
  "properties": {
    "iso:country":"US",
    "sg:address":"950 N Saint Elena St",
    "sg:city":"Gilbert",
    "sg:classifiers":[
        {
            "category":"Building & Trades",
            "subcategory":"Construction",
            "type":"Services"
        }
    ],
    "sg:phone":"+1 480 497 8257",
    "sg:postcode":"85234",
    "sg:province":"AZ",
    "sg:tags":[
        "painter"
    ],
    "wof:name":"Kantarze Painting Service",
    "wof:placetype":"venue"
},
  "geometry": {"coordinates":[-111.76799800000001,33.368198],"type":"Point"}
}