{
  "type": "Feature",
  "properties": {
    "addr:full":"6710 N 47th Ave Suite 3 Glendale AZ 85301",
    "addr:housenumber":"6710",
    "addr:postcode":"85301",
    "addr:street":"N 47Th Ave Suite 3",
    "iso:country":"US",
    "sg:address":"6710 N 47th Ave Suite 3",
    "sg:city":"Glendale",
    "sg:classifiers":[
        {
            "category":"Insurance",
            "subcategory":"Insurance Agent",
            "type":"Services"
        },
        {
            "category":"Insurance",
            "subcategory":"Hazard Insurance",
            "type":"Services"
        }
    ],
    "sg:phone":"+1 623 842 4221",
    "sg:postcode":"85301",
    "sg:province":"AZ",
    "sg:tags":[
        "auto",
        "recreational",
        "motorcycle",
        "vehicle",
        "marine",
        "boat"
    ],
    "wof:name":"AABAR INSURANCE SERVICES",
    "wof:placetype":"venue"
},
  "geometry": {"coordinates":[-112.160025,33.534564],"type":"Point"}
}