{
  "type": "Feature",
  "properties": {
    "iso:country":"US",
    "sg:address":"8700 E Main St",
    "sg:city":"Mesa",
    "sg:classifiers":[
        {
            "category":"Manufacturing",
            "subcategory":"Lumber",
            "type":"Manufacturing & Wholesale Goods"
        }
    ],
    "sg:phone":"+1 480 380 9424",
    "sg:postcode":"85207",
    "sg:province":"AZ",
    "sg:tags":[
        "mill"
    ],
    "wof:name":"Shields",
    "wof:placetype":"venue"
},
  "geometry": {"coordinates":[-111.64224900000001,33.415216],"type":"Point"}
}