{
  "type": "Feature",
  "properties": {
    "iso:country":"US",
    "sg:address":"1030 N 32nd St",
    "sg:city":"Phoenix",
    "sg:classifiers":[
        {
            "category":"Education",
            "subcategory":"Library",
            "type":"Public Place"
        },
        {
            "category":"Government",
            "subcategory":"Office",
            "type":"Public Place"
        }
    ],
    "sg:phone":"+1 602 255 5578",
    "sg:postcode":"85008",
    "sg:province":"AZ",
    "wof:name":"Library-Blind & Physically",
    "wof:placetype":"venue"
},
  "geometry": {"coordinates":[-112.01284,33.459469],"type":"Point"}
}