{
  "type": "Feature",
  "properties": {
    "addr:full":"310 E Southern Ave Ste 5 Mesa AZ 85210",
    "addr:housenumber":"310",
    "addr:postcode":"85210",
    "addr:street":"E Southern Ave Ste 5",
    "iso:country":"US",
    "sg:address":"310 E Southern Ave Ste 5",
    "sg:city":"Mesa",
    "sg:classifiers":[
        {
            "category":"Autos & Motor Vehicles",
            "subcategory":"Auto Supplies",
            "type":"Retail Goods"
        },
        {
            "category":"Manufacturing",
            "subcategory":"Motor Vehicles & Parts",
            "type":"Manufacturing & Wholesale Goods"
        }
    ],
    "sg:phone":"+1 480 898 1957",
    "sg:postcode":"85210",
    "sg:province":"AZ",
    "sg:tags":[
        "driveshaft",
        "automobile",
        "accessory",
        "parts",
        "supplies-used",
        "accessories-wholesale",
        "rebuilt",
        "manufacturer"
    ],
    "sg:website":"http://www.mesadriveshaft.com",
    "wof:name":"Mesa Driveshaft Svc",
    "wof:placetype":"venue"
},
  "geometry": {"coordinates":[-111.824922,33.39333],"type":"Point"}
}