{
  "type": "Feature",
  "properties": {
    "iso:country":"US",
    "sg:address":"3031 E Andy Devine Ave",
    "sg:city":"Kingman",
    "sg:classifiers":[
        {
            "category":"Travel",
            "subcategory":"Hotels & Motels",
            "type":"Entertainment"
        }
    ],
    "sg:phone":"+1 928 718 4343",
    "sg:postcode":"86401",
    "sg:province":"AZ",
    "wof:name":"Holiday Inn Express",
    "wof:placetype":"venue"
},
  "geometry": {"coordinates":[-114.010681,35.217332],"type":"Point"}
}