{
  "type": "Feature",
  "properties": {
    "iso:country":"US",
    "sg:address":"1350 S White Mountain Rd",
    "sg:city":"Show Low",
    "sg:classifiers":[
        {
            "category":"Professional",
            "subcategory":"Computer Services",
            "type":"Services"
        }
    ],
    "sg:phone":"+1 928 367 4638",
    "sg:postcode":"85901",
    "sg:province":"AZ",
    "sg:tags":[
        "internet"
    ],
    "wof:name":"Onewave Internet Solutions",
    "wof:placetype":"venue"
},
  "geometry": {"coordinates":[-110.026578,34.23761],"type":"Point"}
}