{
  "type": "Feature",
  "properties": {
    "iso:country":"US",
    "sg:address":"4502 W Indian School Rd",
    "sg:city":"Phoenix",
    "sg:classifiers":[
        {
            "category":"Sports & Exercise",
            "subcategory":"Gym",
            "type":"Entertainment"
        }
    ],
    "sg:phone":"+1 623 245 2511",
    "sg:postcode":"85031",
    "sg:province":"AZ",
    "sg:tags":[
        "club",
        "health",
        "studio",
        "gymnasium"
    ],
    "wof:name":"Arizona Fitness Health Clubs",
    "wof:placetype":"venue"
},
  "geometry": {"coordinates":[-112.157973,33.495034],"type":"Point"}
}