{
  "type": "Feature",
  "properties": {
    "iso:country":"US",
    "sg:address":"64 N Rayburn Pl",
    "sg:city":"Tucson",
    "sg:classifiers":[
        {
            "category":"Building & Trades",
            "subcategory":"Landscaping Services",
            "type":"Services"
        }
    ],
    "sg:phone":"+1 520 591 3150",
    "sg:postcode":"85710",
    "sg:province":"AZ",
    "sg:tags":[
        "tree"
    ],
    "wof:name":"The Bodhi Tree",
    "wof:placetype":"venue"
},
  "geometry": {"coordinates":[-110.80309099999999,32.221274],"type":"Point"}
}