{
  "type": "Feature",
  "properties": {
    "iso:country":"US",
    "sg:address":"707 E Fort Lowell Rd",
    "sg:city":"Tucson",
    "sg:classifiers":[
        {
            "category":"Shopping",
            "subcategory":"Discount & Variety Stores",
            "type":"Retail Goods"
        }
    ],
    "sg:phone":"+1 520 408 4934",
    "sg:postcode":"85719",
    "sg:province":"AZ",
    "wof:name":"Family Dollar Stores",
    "wof:placetype":"venue"
},
  "geometry": {"coordinates":[-110.956772,32.26486],"type":"Point"}
}