{
  "type": "Feature",
  "properties": {
    "addr:full":"12821 S Tuthill Rd Buckeye AZ 85326",
    "addr:housenumber":"12821",
    "addr:postcode":"85326",
    "addr:street":"S Tuthill Rd",
    "iso:country":"US",
    "sg:address":"12821 S Tuthill Rd",
    "sg:city":"Buckeye",
    "sg:classifiers":[
        {
            "category":"Food & Beverages",
            "subcategory":"Groceries & Convenience Stores",
            "type":"Retail Goods"
        }
    ],
    "sg:phone":"+1 623 393 8460",
    "sg:postcode":"85326",
    "sg:province":"AZ",
    "wof:name":"James H Teeter Jean Vida",
    "wof:placetype":"venue"
},
  "geometry": {"coordinates":[-112.487055,33.326568],"type":"Point"}
}