{
  "type": "Feature",
  "properties": {
    "iso:country":"US",
    "sg:address":"16511 S Country Club Rd",
    "sg:city":"Sahuarita",
    "sg:classifiers":[
        {
            "category":"Wholesale",
            "subcategory":"Farm Supplies",
            "type":"Manufacturing & Wholesale Goods"
        }
    ],
    "sg:phone":"+1 520 625 1275",
    "sg:postcode":"85629",
    "sg:province":"AZ",
    "sg:tags":[
        "feed"
    ],
    "wof:name":"S & D Feed Store",
    "wof:placetype":"venue"
},
  "geometry": {"coordinates":[-110.929514,31.950263],"type":"Point"}
}