{
  "type": "Feature",
  "properties": {
    "iso:country":"US",
    "sg:address":"7349 N Via Paseo del Sur",
    "sg:city":"Scottsdale",
    "sg:classifiers":[
        {
            "category":"Building & Trades",
            "subcategory":"Construction",
            "type":"Services"
        }
    ],
    "sg:phone":"+1 480 200 8350",
    "sg:postcode":"85258",
    "sg:province":"AZ",
    "sg:tags":[
        "general",
        "contractor"
    ],
    "wof:name":"Maxim Construction Group Inc",
    "wof:placetype":"venue"
},
  "geometry": {"coordinates":[-111.90507,33.714112],"type":"Point"}
}