{
  "type": "Feature",
  "properties": {
    "iso:country":"US",
    "sg:address":"5454 E Pima St",
    "sg:city":"Tucson",
    "sg:classifiers":[
        {
            "category":"Shopping",
            "subcategory":"Used Merchandise",
            "type":"Retail Goods"
        }
    ],
    "sg:phone":"+1 520 795 5210",
    "sg:postcode":"85712",
    "sg:province":"AZ",
    "wof:name":"Toms Furniture & Collectibles",
    "wof:placetype":"venue"
},
  "geometry": {"coordinates":[-110.876602,32.243369],"type":"Point"}
}