{
  "type": "Feature",
  "properties": {
    "iso:country":"US",
    "sg:address":"1040 Whipple St",
    "sg:city":"Prescott",
    "sg:classifiers":[
        {
            "category":"Real Estate",
            "subcategory":"Real Estate Agent",
            "type":"Services"
        }
    ],
    "sg:phone":"+1 928 541 1116",
    "sg:postcode":"86305",
    "sg:province":"AZ",
    "sg:tags":[
        "management"
    ],
    "wof:name":"Foundation Property Management",
    "wof:placetype":"venue"
},
  "geometry": {"coordinates":[-112.48379,34.556797],"type":"Point"}
}