{
  "type": "Feature",
  "properties": {
    "addr:full":"1440 N Torino Ave Tucson AZ 85712",
    "addr:housenumber":"1440",
    "addr:postcode":"85712",
    "addr:street":"N Torino Ave",
    "iso:country":"US",
    "sg:address":"1440 N Torino Ave",
    "sg:city":"Tucson",
    "sg:classifiers":[
        {
            "category":"Social Services",
            "subcategory":"Child Care",
            "type":"Services"
        }
    ],
    "sg:phone":"+1 520 290 8400",
    "sg:postcode":"85712",
    "sg:province":"AZ",
    "wof:name":"Guardian Nannies LLC",
    "wof:placetype":"venue"
},
  "geometry": {"coordinates":[-110.88942400000001,32.240273],"type":"Point"}
}