{
  "type": "Feature",
  "properties": {
    "iso:country":"US",
    "sg:address":"2305 W Ruthrauff Rd",
    "sg:city":"Tucson",
    "sg:classifiers":[
        {
            "category":"Education",
            "subcategory":"Library",
            "type":"Public Place"
        }
    ],
    "sg:phone":"+1 520 207 8515",
    "sg:postcode":"85705",
    "sg:province":"AZ",
    "sg:tags":[
        "research"
    ],
    "wof:name":"Peck Law Report Filing Service",
    "wof:placetype":"venue"
},
  "geometry": {"coordinates":[-111.016327,32.294331],"type":"Point"}
}