{
  "type": "Feature",
  "properties": {
    "addr:full":"602 N Wilmot Rd Tucson AZ 85711",
    "addr:housenumber":"602",
    "addr:postcode":"85711",
    "addr:street":"N Wilmot Rd",
    "iso:country":"US",
    "sg:address":"602 N Wilmot Rd",
    "sg:city":"Tucson",
    "sg:classifiers":[
        {
            "category":"Organizations",
            "subcategory":"Religious Organization",
            "type":"Services"
        }
    ],
    "sg:phone":"+1 520 886 7292",
    "sg:postcode":"85711",
    "sg:province":"AZ",
    "sg:tags":[
        "church"
    ],
    "wof:name":"St Michael & All Angels",
    "wof:placetype":"venue"
},
  "geometry": {"coordinates":[-110.857899,32.228828],"type":"Point"}
}