{
  "type": "Feature",
  "properties": {
    "addr:full":"444 N 44th St Phoenix AZ 85008",
    "addr:housenumber":"444",
    "addr:postcode":"85008",
    "addr:street":"N 44Th St",
    "iso:country":"US",
    "sg:address":"444 N 44th St",
    "sg:city":"Phoenix",
    "sg:classifiers":[
        {
            "category":"Wholesale",
            "subcategory":"Motor Vehicles",
            "type":"Manufacturing & Wholesale Goods"
        }
    ],
    "sg:phone":"+1 602 760 3650",
    "sg:postcode":"85008",
    "sg:province":"AZ",
    "wof:name":"Autonation USA SW District",
    "wof:placetype":"venue"
},
  "geometry": {"coordinates":[-111.98721999999999,33.454275],"type":"Point"}
}