{
  "type": "Feature",
  "properties": {
    "iso:country":"US",
    "sg:address":"373 E Coronado Rd Unit 8",
    "sg:city":"Phoenix",
    "sg:classifiers":[
        {
            "category":"Wholesale",
            "subcategory":"Machinery & Supplies",
            "type":"Manufacturing & Wholesale Goods"
        }
    ],
    "sg:phone":"+1 602 258 4511",
    "sg:postcode":"85004",
    "sg:province":"AZ",
    "sg:tags":[
        "equipment",
        "industrial"
    ],
    "wof:name":"Wayne Beck Consulting",
    "wof:placetype":"venue"
},
  "geometry": {"coordinates":[-112.068367,33.467519],"type":"Point"}
}