{
  "type": "Feature",
  "properties": {
    "iso:country":"US",
    "sg:address":"578 Miller Valley Rd",
    "sg:city":"Prescott",
    "sg:classifiers":[
        {
            "category":"Building & Trades",
            "subcategory":"Construction",
            "type":"Services"
        },
        {
            "category":"Retail",
            "subcategory":"Auto Repair",
            "type":"Services"
        }
    ],
    "sg:phone":"+1 928 445 2468",
    "sg:postcode":"86301",
    "sg:province":"AZ",
    "sg:tags":[
        "repairing",
        "residential",
        "general",
        "automobile"
    ],
    "wof:name":"Central Arizona Auto Techs",
    "wof:placetype":"venue"
},
  "geometry": {"coordinates":[-112.478907,34.550264],"type":"Point"}
}