{
  "type": "Feature",
  "properties": {
    "iso:country":"US",
    "sg:address":"9035 E Eagle Pl",
    "sg:city":"Tucson",
    "sg:classifiers":[
        {
            "category":"Real Estate",
            "subcategory":"Real Estate Agent",
            "type":"Services"
        }
    ],
    "sg:phone":"+1 520 760 1719",
    "sg:postcode":"85749",
    "sg:province":"AZ",
    "wof:name":"King Biscuit Entertainers Inc",
    "wof:placetype":"venue"
},
  "geometry": {"coordinates":[-110.799255,32.273945],"type":"Point"}
}