{
  "type": "Feature",
  "properties": {
    "iso:country":"US",
    "sg:address":"7420 E Pinnacle Peak Rd",
    "sg:city":"Scottsdale",
    "sg:classifiers":[
        {
            "category":"Professional",
            "subcategory":"Lawyer & Legal Services",
            "type":"Services"
        }
    ],
    "sg:phone":"+1 480 585 1900",
    "sg:postcode":"85255",
    "sg:province":"AZ",
    "sg:tags":[
        "attorney"
    ],
    "wof:name":"David Kurtz Law Offices",
    "wof:placetype":"venue"
},
  "geometry": {"coordinates":[-111.920202,33.698767],"type":"Point"}
}