{
  "type": "Feature",
  "properties": {
    "addr:full":"2569 E Fort Lowell Rd Tucson AZ 85716",
    "addr:housenumber":"2569",
    "addr:postcode":"85716",
    "addr:street":"E Fort Lowell Rd",
    "iso:country":"US",
    "sg:address":"2569 E Fort Lowell Rd",
    "sg:city":"Tucson",
    "sg:classifiers":[
        {
            "category":"Building & Trades",
            "subcategory":"Pest Control",
            "type":"Services"
        }
    ],
    "sg:phone":"+1 520 834 8406",
    "sg:postcode":"85716",
    "sg:province":"AZ",
    "sg:website":"http://www.arizona-territorial.com",
    "wof:name":"Arizona Territorial Termite & Pest Control",
    "wof:placetype":"venue"
},
  "geometry": {"coordinates":[-110.93362500000001,32.264935],"type":"Point"}
}