{
  "type": "Feature",
  "properties": {
    "addr:full":"1102 E University Dr Mesa AZ 85203",
    "addr:housenumber":"1102",
    "addr:postcode":"85203",
    "addr:street":"E University Dr",
    "iso:country":"US",
    "sg:address":"1102 E University Dr",
    "sg:city":"Mesa",
    "sg:classifiers":[
        {
            "category":"Personal",
            "subcategory":"Beauty Salon",
            "type":"Services"
        }
    ],
    "sg:phone":"+1 480 890 8736",
    "sg:postcode":"85203",
    "sg:province":"AZ",
    "wof:name":"John Brown Stylist",
    "wof:placetype":"venue"
},
  "geometry": {"coordinates":[-111.805318,33.42249],"type":"Point"}
}