{
  "type": "Feature",
  "properties": {
    "iso:country":"US",
    "sg:address":"1480 S Watson Rd",
    "sg:city":"Buckeye",
    "sg:classifiers":[
        {
            "category":"Professional",
            "subcategory":"Accounting & Tax Preparation",
            "type":"Services"
        },
        {
            "category":"Banks & Credit Unions",
            "subcategory":"Financial Services",
            "type":"Services"
        }
    ],
    "sg:phone":"+1 623 327 0121",
    "sg:postcode":"85326",
    "sg:province":"AZ",
    "sg:tags":[
        "return",
        "preparation-business",
        "taxes-consultants",
        "loan",
        "reporting",
        "representative",
        "alternative",
        "bookkeeping"
    ],
    "sg:website":"http://www.hrblock.com",
    "wof:name":"H&R Block",
    "wof:placetype":"venue"
},
  "geometry": {"coordinates":[-112.55638999999999,33.432547],"type":"Point"}
}