{
  "type": "Feature",
  "properties": {
    "iso:country":"US",
    "sg:address":"4041 N Central Ave",
    "sg:city":"Phoenix",
    "sg:classifiers":[
        {
            "category":"Parking",
            "type":"Transportation"
        }
    ],
    "sg:phone":"+1 602 241 1067",
    "sg:postcode":"85012",
    "sg:province":"AZ",
    "sg:tags":[
        "garage",
        "lot"
    ],
    "sg:website":"http://www.standardparking.com",
    "wof:name":"Standard Parking",
    "wof:placetype":"venue"
},
  "geometry": {"coordinates":[-112.07370400000001,33.493473],"type":"Point"}
}