{
  "type": "Feature",
  "properties": {
    "iso:country":"US",
    "sg:address":"9202 E Main St",
    "sg:city":"Mesa",
    "sg:classifiers":[
        {
            "category":"Autos & Motor Vehicles",
            "subcategory":"Fuel & Gas Station",
            "type":"Retail Goods"
        }
    ],
    "sg:phone":"+1 480 986 6782",
    "sg:postcode":"85207",
    "sg:province":"AZ",
    "sg:tags":[
        "oil"
    ],
    "wof:name":"Shell",
    "wof:placetype":"venue"
},
  "geometry": {"coordinates":[-111.63019199999999,33.415196],"type":"Point"}
}