{
  "type": "Feature",
  "properties": {
    "iso:country":"US",
    "sg:address":"1032 S Hopi Ave",
    "sg:city":"Parker",
    "sg:classifiers":[
        {
            "category":"Government",
            "subcategory":"Office",
            "type":"Public Place"
        }
    ],
    "sg:phone":"+1 928 669 8389",
    "sg:postcode":"85344",
    "sg:province":"AZ",
    "sg:tags":[
        "state",
        "resource"
    ],
    "wof:name":"Vocational Rehabilitation Dept",
    "wof:placetype":"venue"
},
  "geometry": {"coordinates":[-114.28752,34.150622],"type":"Point"}
}