{
  "type": "Feature",
  "properties": {
    "addr:full":"17336 W Cheryl Dr Waddell AZ 85355",
    "addr:housenumber":"17336",
    "addr:postcode":"85355",
    "addr:street":"W Cheryl Dr",
    "iso:country":"US",
    "sg:address":"17336 W Cheryl Dr",
    "sg:city":"Waddell",
    "sg:classifiers":[
        {
            "category":"Professional",
            "subcategory":"Printing & Photocopies",
            "type":"Services"
        }
    ],
    "sg:phone":"+1 623 935 2498",
    "sg:postcode":"85355",
    "sg:province":"AZ",
    "sg:tags":[
        "lithographer"
    ],
    "wof:name":"Printing Technology",
    "wof:placetype":"venue"
},
  "geometry": {"coordinates":[-112.43304999999999,33.577017],"type":"Point"}
}