{
  "type": "Feature",
  "properties": {
    "iso:country":"US",
    "sg:address":"12322 W Desert Mirage Cir",
    "sg:city":"El Mirage",
    "sg:classifiers":[
        {
            "category":"Professional",
            "type":"Services"
        }
    ],
    "sg:phone":"+1 623 933 6060",
    "sg:postcode":"85335",
    "sg:province":"AZ",
    "wof:name":"Qt PI Designs",
    "wof:placetype":"venue"
},
  "geometry": {"coordinates":[-112.326858,33.58534],"type":"Point"}
}