{
  "type": "Feature",
  "properties": {
    "iso:country":"US",
    "sg:address":"6131 N 16th St",
    "sg:city":"Phoenix",
    "sg:classifiers":[
        {
            "category":"Professional",
            "subcategory":"Advertising",
            "type":"Services"
        }
    ],
    "sg:phone":"+1 602 285 0685",
    "sg:postcode":"85016",
    "sg:province":"AZ",
    "sg:tags":[
        "distribution"
    ],
    "wof:name":"Herbalife Distributor",
    "wof:placetype":"venue"
},
  "geometry": {"coordinates":[-112.047411,33.526718],"type":"Point"}
}