{
  "type": "Feature",
  "properties": {
    "iso:country":"US",
    "sg:address":"107 W Fort Lowell Rd",
    "sg:city":"Tucson",
    "sg:classifiers":[
        {
            "category":"Home & Garden",
            "subcategory":"Garden Supply",
            "type":"Retail Goods"
        }
    ],
    "sg:phone":"+1 520 622 1105",
    "sg:postcode":"85705",
    "sg:province":"AZ",
    "sg:tags":[
        "lawn",
        "mower"
    ],
    "wof:name":"H & H Small Equipment Svc",
    "wof:placetype":"venue"
},
  "geometry": {"coordinates":[-110.973153,32.264661],"type":"Point"}
}