{
  "type": "Feature",
  "properties": {
    "addr:full":"28 W Juniper Ave Gilbert AZ 85233",
    "addr:housenumber":"28",
    "addr:postcode":"85233",
    "addr:street":"W Juniper Ave",
    "iso:country":"US",
    "sg:address":"28 W Juniper Ave",
    "sg:city":"Gilbert",
    "sg:classifiers":[
        {
            "category":"Professional",
            "subcategory":"Management & Consulting",
            "type":"Services"
        }
    ],
    "sg:phone":"+1 480 663 7769",
    "sg:postcode":"85233",
    "sg:province":"AZ",
    "sg:tags":[
        "marketing",
        "program"
    ],
    "wof:name":"Marketing Success Intl LLC",
    "wof:placetype":"venue"
},
  "geometry": {"coordinates":[-111.790008,33.359684],"type":"Point"}
}