{
  "type": "Feature",
  "properties": {
    "addr:full":"445 N Stapley Dr Mesa AZ 85203",
    "addr:housenumber":"445",
    "addr:postcode":"85203",
    "addr:street":"N Stapley Dr",
    "iso:country":"US",
    "sg:address":"445 N Stapley Dr",
    "sg:city":"Mesa",
    "sg:classifiers":[
        {
            "category":"Shopping",
            "subcategory":"Pharmacy",
            "type":"Retail Goods"
        }
    ],
    "sg:phone":"+1 480 733 1855",
    "sg:postcode":"85203",
    "sg:province":"AZ",
    "sg:website":"www.albertsons.com",
    "wof:name":"Osco Drug",
    "wof:placetype":"venue"
},
  "geometry": {"coordinates":[-111.80520799999999,33.422752],"type":"Point"}
}