{
  "type": "Feature",
  "properties": {
    "addr:full":"406 E Carleton St Prescott AZ 86303",
    "addr:housenumber":"406",
    "addr:postcode":"86303",
    "addr:street":"E Carleton St",
    "iso:country":"US",
    "sg:address":"406 E Carleton St",
    "sg:city":"Prescott",
    "sg:classifiers":[
        {
            "category":"Wholesale",
            "subcategory":"Non-durable Goods",
            "type":"Manufacturing & Wholesale Goods"
        }
    ],
    "sg:phone":"+1 928 717 2684",
    "sg:postcode":"86303",
    "sg:province":"AZ",
    "sg:tags":[
        "shop",
        "gift"
    ],
    "wof:name":"Kencuts",
    "wof:placetype":"venue"
},
  "geometry": {"coordinates":[-112.46451399999999,34.537962],"type":"Point"}
}