{
  "type": "Feature",
  "properties": {
    "addr:full":"5831 W Morelos St Chandler AZ 85226",
    "addr:housenumber":"5831",
    "addr:postcode":"85226",
    "addr:street":"W Morelos St",
    "iso:country":"US",
    "sg:address":"5831 W Morelos St",
    "sg:city":"Chandler",
    "sg:classifiers":[
        {
            "category":"Building & Trades",
            "subcategory":"Plumbing",
            "type":"Services"
        }
    ],
    "sg:phone":"+1 480 961 3620",
    "sg:postcode":"85226",
    "sg:province":"AZ",
    "sg:tags":[
        "contractor"
    ],
    "wof:name":"Schiller Heating & Cooling",
    "wof:placetype":"venue"
},
  "geometry": {"coordinates":[-111.942881,33.29552],"type":"Point"}
}