{
  "type": "Feature",
  "properties": {
    "iso:country":"US",
    "sg:address":"3650 E Andy Devine Ave",
    "sg:city":"Kingman",
    "sg:classifiers":[
        {
            "category":"Building & Trades",
            "subcategory":"Construction",
            "type":"Services"
        }
    ],
    "sg:phone":"+1 928 681 6060",
    "sg:postcode":"86401",
    "sg:province":"AZ",
    "sg:tags":[
        "road",
        "contractor"
    ],
    "wof:name":"Highway Maintenance",
    "wof:placetype":"venue"
},
  "geometry": {"coordinates":[-113.99747499999999,35.230626],"type":"Point"}
}