{
  "type": "Feature",
  "properties": {
    "iso:country":"US",
    "sg:address":"3927 E Indian School Rd",
    "sg:city":"Phoenix",
    "sg:classifiers":[
        {
            "category":"Manufacturing",
            "subcategory":"Toys & Sporting Goods",
            "type":"Manufacturing & Wholesale Goods"
        }
    ],
    "sg:phone":"+1 602 956 8648",
    "sg:postcode":"85018",
    "sg:province":"AZ",
    "sg:tags":[
        "manufacture",
        "retail",
        "stuffed",
        "animal",
        "doll"
    ],
    "sg:website":"www.dolls-bears.com",
    "wof:name":"Dolls Bears & Surprises",
    "wof:placetype":"venue"
},
  "geometry": {"coordinates":[-111.995953,33.495053],"type":"Point"}
}