{
  "type": "Feature",
  "properties": {
    "addr:full":"4907 W Glendale Ave Glendale AZ 85301",
    "addr:housenumber":"4907",
    "addr:postcode":"85301",
    "addr:street":"W Glendale Ave",
    "iso:country":"US",
    "sg:address":"4907 W Glendale Ave",
    "sg:city":"Glendale",
    "sg:classifiers":[
        {
            "category":"Real Estate",
            "subcategory":"Real Estate Agent",
            "type":"Services"
        }
    ],
    "sg:phone":"+1 623 939 7586",
    "sg:postcode":"85301",
    "sg:province":"AZ",
    "wof:name":"Ryan Real Estate",
    "wof:placetype":"venue"
},
  "geometry": {"coordinates":[-112.166357,33.538372],"type":"Point"}
}