{
  "type": "Feature",
  "properties": {
    "addr:full":"1901 E Southern Ave Mesa AZ 85204",
    "addr:housenumber":"1901",
    "addr:postcode":"85204",
    "addr:street":"E Southern Ave",
    "iso:country":"US",
    "sg:address":"1901 E Southern Ave",
    "sg:city":"Mesa",
    "sg:classifiers":[
        {
            "category":"Retail",
            "subcategory":"Veterinary Services",
            "type":"Services"
        }
    ],
    "sg:phone":"+1 480 892 7958",
    "sg:postcode":"85204",
    "sg:province":"AZ",
    "sg:tags":[
        "veterinarian"
    ],
    "wof:name":"Animal Medical Clinic",
    "wof:placetype":"venue"
},
  "geometry": {"coordinates":[-111.791748,33.39344],"type":"Point"}
}