{
  "type": "Feature",
  "properties": {
    "addr:full":"4111 E Valley Auto Dr Ste 104 Mesa AZ 85208",
    "addr:housenumber":"4111",
    "addr:postcode":"85208",
    "addr:street":"E Valley Auto Dr Ste 104",
    "iso:country":"US",
    "sg:address":"4111 E Valley Auto Dr Ste 104",
    "sg:city":"Mesa",
    "sg:classifiers":[
        {
            "category":"Health Services",
            "subcategory":"Clinic",
            "type":"Services"
        }
    ],
    "sg:phone":"+1 480 478 4221",
    "sg:postcode":"85208",
    "sg:province":"AZ",
    "sg:tags":[
        "counseling",
        "mental"
    ],
    "sg:website":"aztraumatherapy.com",
    "wof:name":"Psychological Health & Wellness",
    "wof:placetype":"venue"
},
  "geometry": {"coordinates":[-111.743488,33.380758],"type":"Point"}
}