{
  "type": "Feature",
  "properties": {
    "iso:country":"US",
    "sg:address":"1948 Viola Pl",
    "sg:city":"Sierra Vista",
    "sg:classifiers":[
        {
            "category":"Organizations",
            "subcategory":"Religious Organization",
            "type":"Services"
        }
    ],
    "sg:phone":"+1 520 452 8393",
    "sg:postcode":"85635",
    "sg:province":"AZ",
    "sg:tags":[
        "mill",
        "knit",
        "outerwear"
    ],
    "wof:name":"Uc-Unity Consciousness",
    "wof:placetype":"venue"
},
  "geometry": {"coordinates":[-110.28049799999999,31.55924],"type":"Point"}
}