{
  "type": "Feature",
  "properties": {
    "iso:country":"US",
    "sg:address":"8248 W Deer Valley Rd",
    "sg:city":"Peoria",
    "sg:classifiers":[
        {
            "category":"Personal",
            "subcategory":"Beauty Salon",
            "type":"Services"
        }
    ],
    "sg:phone":"+1 623 376 2500",
    "sg:postcode":"85382",
    "sg:province":"AZ",
    "wof:name":"Pure Elements",
    "wof:placetype":"venue"
},
  "geometry": {"coordinates":[-112.236183,33.681655],"type":"Point"}
}