{
  "type": "Feature",
  "properties": {
    "addr:full":"873 Howards Rd Camp Verde AZ 86322",
    "addr:housenumber":"873",
    "addr:postcode":"86322",
    "addr:street":"Howards Rd",
    "iso:country":"US",
    "sg:address":"873 Howards Rd",
    "sg:city":"Camp Verde",
    "sg:classifiers":[
        {
            "category":"Shopping",
            "subcategory":"Used Merchandise",
            "type":"Retail Goods"
        }
    ],
    "sg:phone":"+1 928 567 2306",
    "sg:postcode":"86322",
    "sg:province":"AZ",
    "sg:tags":[
        "carpet",
        "dealer",
        "rug"
    ],
    "wof:name":"Economy Carpet",
    "wof:placetype":"venue"
},
  "geometry": {"coordinates":[-111.847809,34.548063],"type":"Point"}
}