{
  "type": "Feature",
  "properties": {
    "iso:country":"US",
    "sg:address":"5005 W Myrtle Ave",
    "sg:city":"Glendale",
    "sg:classifiers":[
        {
            "category":"Freight",
            "type":"Transportation"
        }
    ],
    "sg:phone":"+1 623 934 7355",
    "sg:postcode":"85301",
    "sg:province":"AZ",
    "sg:tags":[
        "local",
        "trucking"
    ],
    "sg:website":"http://www.familyspirit.com",
    "wof:name":"Family Spirit, Inc",
    "wof:placetype":"venue"
},
  "geometry": {"coordinates":[-112.168443,33.542111],"type":"Point"}
}