{
  "type": "Feature",
  "properties": {
    "iso:country":"US",
    "sg:address":"801 W Rex Allen Dr",
    "sg:city":"Willcox",
    "sg:classifiers":[
        {
            "category":"Health Services",
            "subcategory":"Doctor",
            "type":"Services"
        },
        {
            "category":"Health Services",
            "subcategory":"Clinic",
            "type":"Services"
        }
    ],
    "sg:phone":"+1 520 766 5000",
    "sg:postcode":"85643",
    "sg:province":"AZ",
    "sg:tags":[
        "physician",
        "pediatrics",
        "family",
        "practice",
        "surgeons",
        "medicine",
        "surgeon"
    ],
    "sg:website":"http://www.WalkerFamilyMedicine.com",
    "wof:name":"Walker Family Medicine",
    "wof:placetype":"venue"
},
  "geometry": {"coordinates":[-109.837214,32.264279],"type":"Point"}
}