{
  "type": "Feature",
  "properties": {
    "addr:full":"1805 W Fairway Ln Payson AZ 85541",
    "addr:housenumber":"1805",
    "addr:postcode":"85541",
    "addr:street":"W Fairway Ln",
    "iso:country":"US",
    "sg:address":"1805 W Fairway Ln",
    "sg:city":"Payson",
    "sg:classifiers":[
        {
            "category":"Structure",
            "subcategory":"Office Building",
            "type":"Public Place"
        }
    ],
    "sg:phone":"+1 928 474 2216",
    "sg:postcode":"85541",
    "sg:province":"AZ",
    "sg:tags":[
        "park"
    ],
    "wof:name":"B J Q Properties",
    "wof:placetype":"venue"
},
  "geometry": {"coordinates":[-111.356641,34.235313],"type":"Point"}
}