{
  "type": "Feature",
  "properties": {
    "addr:full":"1729 E Florence Blvd Casa Grande AZ 85222",
    "addr:housenumber":"1729",
    "addr:postcode":"85222",
    "addr:street":"E Florence Blvd",
    "iso:country":"US",
    "sg:address":"1729 E Florence Blvd",
    "sg:city":"Casa Grande",
    "sg:classifiers":[
        {
            "category":"Restaurant",
            "type":"Food & Drink"
        }
    ],
    "sg:menulink":"http://www.allmenus.com/az/casa-grande/200727-long-john-silvers/menu/",
    "sg:phone":"+1 520 876 4872",
    "sg:postcode":"85222",
    "sg:province":"AZ",
    "sg:tags":[
        "seafood",
        "american"
    ],
    "wof:name":"Long John Silver's",
    "wof:placetype":"venue"
},
  "geometry": {"coordinates":[-111.712523,32.879619],"type":"Point"}
}