{
  "type": "Feature",
  "properties": {
    "iso:country":"US",
    "sg:address":"150 S Cam Seco",
    "sg:city":"Tucson",
    "sg:classifiers":[
        {
            "category":"Wholesale",
            "subcategory":"Machinery & Supplies",
            "type":"Manufacturing & Wholesale Goods"
        },
        {
            "category":"Professional",
            "type":"Services"
        }
    ],
    "sg:phone":"+1 520 298 1742",
    "sg:postcode":"85710",
    "sg:province":"AZ",
    "sg:tags":[
        "contractor"
    ],
    "wof:name":"Finish Line Tools & Acces",
    "wof:placetype":"venue"
},
  "geometry": {"coordinates":[-110.806885,32.2204],"type":"Point"}
}