{
  "type": "Feature",
  "properties": {
    "iso:country":"US",
    "sg:address":"1502 S Alvernon Way",
    "sg:city":"Tucson",
    "sg:classifiers":[
        {
            "category":"Autos & Motor Vehicles",
            "subcategory":"Auto Supplies",
            "type":"Retail Goods"
        }
    ],
    "sg:phone":"+1 520 325 2656",
    "sg:postcode":"85711",
    "sg:province":"AZ",
    "sg:tags":[
        "repair",
        "brake",
        "tire"
    ],
    "sg:website":"http://www.bigotires.com",
    "wof:name":"Big O Tires",
    "wof:placetype":"venue"
},
  "geometry": {"coordinates":[-110.909667,32.203828],"type":"Point"}
}