{
  "type": "Feature",
  "properties": {
    "addr:full":"7510 E Main St Mesa AZ 85207",
    "addr:housenumber":"7510",
    "addr:postcode":"85207",
    "addr:street":"E Main St",
    "iso:country":"US",
    "sg:address":"7510 E Main St",
    "sg:city":"Mesa",
    "sg:classifiers":[
        {
            "category":"Restaurant",
            "type":"Food & Drink"
        }
    ],
    "sg:phone":"+1 480 981 7037",
    "sg:postcode":"85207",
    "sg:province":"AZ",
    "sg:tags":[
        "eating"
    ],
    "wof:name":"Wendys",
    "wof:placetype":"venue"
},
  "geometry": {"coordinates":[-111.669431,33.415261],"type":"Point"}
}