{
  "type": "Feature",
  "properties": {
    "iso:country":"US",
    "sg:address":"18401 N 32nd St",
    "sg:city":"Phoenix",
    "sg:classifiers":[
        {
            "category":"Shopping",
            "subcategory":"Books",
            "type":"Retail Goods"
        }
    ],
    "sg:phone":"+1 602 493 2657",
    "sg:postcode":"85032",
    "sg:province":"AZ",
    "sg:tags":[
        "textbook"
    ],
    "wof:name":"Paradise Valley Bookstore",
    "wof:placetype":"venue"
},
  "geometry": {"coordinates":[-112.013515,33.653484],"type":"Point"}
}