{
  "type": "Feature",
  "properties": {
    "iso:country":"US",
    "sg:address":"425 W Nebraska St",
    "sg:city":"Tucson",
    "sg:classifiers":[
        {
            "category":"Manufacturing",
            "subcategory":"Toys & Sporting Goods",
            "type":"Manufacturing & Wholesale Goods"
        }
    ],
    "sg:phone":"+1 520 746 3635",
    "sg:postcode":"85706",
    "sg:province":"AZ",
    "sg:tags":[
        "mfg"
    ],
    "wof:name":"Arizona Youth Softball Inc",
    "wof:placetype":"venue"
},
  "geometry": {"coordinates":[-110.975879,32.155876],"type":"Point"}
}