{
  "type": "Feature",
  "properties": {
    "iso:country":"US",
    "sg:address":"2706 E University Dr",
    "sg:city":"Mesa",
    "sg:classifiers":[
        {
            "category":"Food & Beverages",
            "subcategory":"Specialty",
            "type":"Retail Goods"
        }
    ],
    "sg:phone":"+1 480 733 3738",
    "sg:postcode":"85213",
    "sg:province":"AZ",
    "sg:tags":[
        "health",
        "diet"
    ],
    "wof:name":"GNC",
    "wof:placetype":"venue"
},
  "geometry": {"coordinates":[-111.771424,33.422765],"type":"Point"}
}