{
  "type": "Feature",
  "properties": {
    "iso:country":"US",
    "sg:address":"2240 N Silverbell Rd",
    "sg:city":"Tucson",
    "sg:classifiers":[
        {
            "category":"Retail",
            "subcategory":"Auto Rental",
            "type":"Services"
        }
    ],
    "sg:phone":"+1 520 623 4443",
    "sg:postcode":"85745",
    "sg:province":"AZ",
    "sg:tags":[
        "renting",
        "truck",
        "leasing"
    ],
    "wof:name":"U-Haul Co",
    "wof:placetype":"venue"
},
  "geometry": {"coordinates":[-111.012044,32.248165],"type":"Point"}
}