{
  "type": "Feature",
  "properties": {
    "iso:country":"US",
    "sg:address":"5050 Bison Ave",
    "sg:city":"Fort Mohave",
    "sg:classifiers":[
        {
            "category":"Building & Trades",
            "subcategory":"Equipment Rental",
            "type":"Services"
        }
    ],
    "sg:phone":"+1 928 768 3176",
    "sg:postcode":"86426",
    "sg:province":"AZ",
    "wof:name":"Sun Valley Air Port",
    "wof:placetype":"venue"
},
  "geometry": {"coordinates":[-114.566982,35.010121],"type":"Point"}
}