{
  "type": "Feature",
  "properties": {
    "iso:country":"US",
    "sg:address":"674 E Manor Dr",
    "sg:city":"Chandler",
    "sg:classifiers":[
        {
            "category":"Shopping",
            "type":"Retail Goods"
        }
    ],
    "sg:phone":"+1 480 786 3324",
    "sg:postcode":"85225",
    "sg:province":"AZ",
    "sg:tags":[
        "merchandise"
    ],
    "wof:name":"Jettie & Bevs Pet Care",
    "wof:placetype":"venue"
},
  "geometry": {"coordinates":[-111.830202,33.328523],"type":"Point"}
}