{
  "type": "Feature",
  "properties": {
    "iso:country":"US",
    "sg:address":"4692 Knudsen Ln",
    "sg:city":"Snowflake",
    "sg:classifiers":[
        {
            "category":"Building & Trades",
            "subcategory":"Construction",
            "type":"Services"
        }
    ],
    "sg:phone":"+1 928 536 2957",
    "sg:postcode":"85937",
    "sg:province":"AZ",
    "sg:tags":[
        "house",
        "contractor"
    ],
    "wof:name":"Mike Skowronski Custom Bldg",
    "wof:placetype":"venue"
},
  "geometry": {"coordinates":[-109.946388,34.547387],"type":"Point"}
}