{
  "type": "Feature",
  "properties": {
    "iso:country":"US",
    "sg:address":"1741 W Rose Garden Ln",
    "sg:city":"Phoenix",
    "sg:classifiers":[
        {
            "category":"Manufacturing",
            "subcategory":"Metals",
            "type":"Manufacturing & Wholesale Goods"
        }
    ],
    "sg:phone":"+1 602 867 6991",
    "sg:postcode":"85027",
    "sg:province":"AZ",
    "sg:tags":[
        "fabrication"
    ],
    "wof:name":"Strictly Custom Metals Llc",
    "wof:placetype":"venue"
},
  "geometry": {"coordinates":[-112.09609500000001,33.67641],"type":"Point"}
}