{
  "type": "Feature",
  "properties": {
    "addr:full":"29209 N 56th St Cave Creek AZ 85331",
    "addr:housenumber":"29209",
    "addr:postcode":"85331",
    "addr:street":"N 56Th St",
    "iso:country":"US",
    "sg:address":"29209 N 56th St",
    "sg:city":"Cave Creek",
    "sg:classifiers":[
        {
            "category":"Social Services",
            "subcategory":"Child Care",
            "type":"Services"
        }
    ],
    "sg:phone":"+1 480 563 2929",
    "sg:postcode":"85331",
    "sg:province":"AZ",
    "sg:tags":[
        "elementary",
        "kindergarten",
        "school",
        "academic"
    ],
    "sg:website":"www.cavecreekmontessori.com",
    "wof:name":"Cave Creek Montessori",
    "wof:placetype":"venue"
},
  "geometry": {"coordinates":[-111.960999,33.750599],"type":"Point"}
}