{
  "type": "Feature",
  "properties": {
    "iso:country":"US",
    "sg:address":"13601 N 19th Ave",
    "sg:city":"Phoenix",
    "sg:classifiers":[
        {
            "category":"Personal",
            "subcategory":"Beauty Salon",
            "type":"Services"
        }
    ],
    "sg:phone":"+1 602 993 7428",
    "sg:postcode":"85029",
    "sg:province":"AZ",
    "wof:name":"Studio 19 Hair & Nails Salon",
    "wof:placetype":"venue"
},
  "geometry": {"coordinates":[-112.09956,33.610347],"type":"Point"}
}