{
  "type": "Feature",
  "properties": {
    "addr:full":"12921 W Via Camille El Mirage AZ 85335",
    "addr:housenumber":"12921",
    "addr:postcode":"85335",
    "addr:street":"W Via Camille",
    "iso:country":"US",
    "sg:address":"12921 W Via Camille",
    "sg:city":"El Mirage",
    "sg:classifiers":[
        {
            "category":"Wholesale",
            "subcategory":"Sporting Goods",
            "type":"Manufacturing & Wholesale Goods"
        }
    ],
    "sg:phone":"+1 623 583 0563",
    "sg:postcode":"85335",
    "sg:province":"AZ",
    "sg:tags":[
        "equipment",
        "fish",
        "farming",
        "supply"
    ],
    "wof:name":"Artemia International",
    "wof:placetype":"venue"
},
  "geometry": {"coordinates":[-112.336386,33.612543],"type":"Point"}
}