{
  "type": "Feature",
  "properties": {
    "iso:country":"US",
    "sg:address":"2001 N 4th St",
    "sg:city":"Flagstaff",
    "sg:classifiers":[
        {
            "category":"Health Services",
            "subcategory":"Health Practitioner",
            "type":"Services"
        }
    ],
    "sg:phone":"+1 928 774 4420",
    "sg:postcode":"86004",
    "sg:province":"AZ",
    "sg:tags":[
        "therapist",
        "physical"
    ],
    "wof:name":"John J Mauz",
    "wof:placetype":"venue"
},
  "geometry": {"coordinates":[-111.613427,35.208205],"type":"Point"}
}