{
  "type": "Feature",
  "properties": {
    "addr:full":"9531 E 5th St Tucson AZ 85748",
    "addr:housenumber":"9531",
    "addr:postcode":"85748",
    "addr:street":"E 5Th St",
    "iso:country":"US",
    "sg:address":"9531 E 5th St",
    "sg:city":"Tucson",
    "sg:classifiers":[
        {
            "category":"Professional",
            "type":"Services"
        }
    ],
    "sg:phone":"+1 520 546 3106",
    "sg:postcode":"85748",
    "sg:province":"AZ",
    "sg:tags":[
        "establishment"
    ],
    "wof:name":"A Rise Inc",
    "wof:placetype":"venue"
},
  "geometry": {"coordinates":[-110.788151,32.22822],"type":"Point"}
}