{
  "type": "Feature",
  "properties": {
    "iso:country":"US",
    "sg:address":"4840 E Virginia Ave Suite #7",
    "sg:city":"Phoenix",
    "sg:classifiers":[
        {
            "category":"Personal",
            "type":"Services"
        }
    ],
    "sg:phone":"+1 602 459 1400",
    "sg:postcode":"85008",
    "sg:province":"AZ",
    "sg:tags":[
        "mover"
    ],
    "wof:name":"ONE WORLD MOVING INC.",
    "wof:placetype":"venue"
},
  "geometry": {"coordinates":[-111.976862,33.476452],"type":"Point"}
}