{
  "type": "Feature",
  "properties": {
    "iso:country":"US",
    "sg:address":"9164 N Ingrid Pl",
    "sg:city":"Tucson",
    "sg:classifiers":[
        {
            "category":"Retail",
            "subcategory":"Repair Shop",
            "type":"Services"
        },
        {
            "category":"Food & Beverages",
            "subcategory":"Groceries & Convenience Stores",
            "type":"Retail Goods"
        }
    ],
    "sg:phone":"+1 520 744 0574",
    "sg:postcode":"85743",
    "sg:province":"AZ",
    "sg:tags":[
        "major",
        "refinishing",
        "appliance",
        "refrigerant",
        "small",
        "freezers-repair",
        "refrigerator",
        "recovery"
    ],
    "wof:name":"All Brnads Appliance Service",
    "wof:placetype":"venue"
},
  "geometry": {"coordinates":[-111.121927,32.372902],"type":"Point"}
}