{
  "type": "Feature",
  "properties": {
    "addr:full":"2745 W Camelback Rd Phoenix AZ 85017",
    "addr:housenumber":"2745",
    "addr:postcode":"85017",
    "addr:street":"W Camelback Rd",
    "iso:country":"US",
    "sg:address":"2745 W Camelback Rd",
    "sg:city":"Phoenix",
    "sg:classifiers":[
        {
            "category":"Professional",
            "subcategory":"Business Services",
            "type":"Services"
        }
    ],
    "sg:phone":"+1 602 604 8300",
    "sg:postcode":"85017",
    "sg:province":"AZ",
    "sg:tags":[
        "water",
        "treatment"
    ],
    "wof:name":"E-Z Life Home Products",
    "wof:placetype":"venue"
},
  "geometry": {"coordinates":[-112.118588,33.50938],"type":"Point"}
}