{
  "type": "Feature",
  "properties": {
    "addr:full":"4635 S 33rd St Phoenix AZ 85040",
    "addr:housenumber":"4635",
    "addr:postcode":"85040",
    "addr:street":"S 33Rd St",
    "iso:country":"US",
    "sg:address":"4635 S 33rd St",
    "sg:city":"Phoenix",
    "sg:classifiers":[
        {
            "category":"Building & Trades",
            "subcategory":"Cleaning & Sanitation",
            "type":"Services"
        }
    ],
    "sg:phone":"+1 602 275 6373",
    "sg:postcode":"85040",
    "sg:province":"AZ",
    "sg:tags":[
        "janitor"
    ],
    "sg:website":"www.caretakersinc.com",
    "wof:name":"Care-Takers Building Mntnc",
    "wof:placetype":"venue"
},
  "geometry": {"coordinates":[-112.01067,33.404662],"type":"Point"}
}