{
  "type": "Feature",
  "properties": {
    "iso:country":"US",
    "sg:address":"4709 N Cam Escuela",
    "sg:city":"Tucson",
    "sg:classifiers":[
        {
            "category":"Building & Trades",
            "subcategory":"Construction",
            "type":"Services"
        }
    ],
    "sg:phone":"+1 520 299 2969",
    "sg:postcode":"85718",
    "sg:province":"AZ",
    "sg:tags":[
        "general",
        "contractor"
    ],
    "wof:name":"Chandler Design & Construction",
    "wof:placetype":"venue"
},
  "geometry": {"coordinates":[-110.938113,32.291671],"type":"Point"}
}