{
  "type": "Feature",
  "properties": {
    "iso:country":"US",
    "sg:address":"1901 N 9th Ave",
    "sg:city":"Tucson",
    "sg:classifiers":[
        {
            "category":"Retail",
            "subcategory":"Auto Repair",
            "type":"Services"
        }
    ],
    "sg:phone":"+1 520 623 7511",
    "sg:postcode":"85705",
    "sg:province":"AZ",
    "sg:tags":[
        "body",
        "automobile",
        "painting"
    ],
    "wof:name":"Gilbert Automotive",
    "wof:placetype":"venue"
},
  "geometry": {"coordinates":[-110.973417,32.245959],"type":"Point"}
}