{
  "type": "Feature",
  "properties": {
    "iso:country":"US",
    "sg:address":"9449 N 99th Ave",
    "sg:city":"Peoria",
    "sg:classifiers":[
        {
            "category":"Social Services",
            "type":"Services"
        }
    ],
    "sg:phone":"+1 623 977 6020",
    "sg:postcode":"85345",
    "sg:province":"AZ",
    "sg:tags":[
        "organization",
        "welfare"
    ],
    "sg:website":"www.rfbd.org",
    "wof:name":"Recording For The Blind",
    "wof:placetype":"venue"
},
  "geometry": {"coordinates":[-112.27460499999999,33.57032],"type":"Point"}
}