{
  "type": "Feature",
  "properties": {
    "addr:full":"3873 Lighthouse Dr Lake Havasu City AZ 86406",
    "addr:housenumber":"3873",
    "addr:postcode":"86406",
    "addr:street":"Lighthouse Dr",
    "iso:country":"US",
    "sg:address":"3873 Lighthouse Dr",
    "sg:city":"Lake Havasu City",
    "sg:classifiers":[
        {
            "category":"Building & Trades",
            "subcategory":"Construction",
            "type":"Services"
        }
    ],
    "sg:phone":"+1 928 855 0412",
    "sg:postcode":"86406",
    "sg:province":"AZ",
    "sg:tags":[
        "house"
    ],
    "wof:name":"Scott Allen & Co",
    "wof:placetype":"venue"
},
  "geometry": {"coordinates":[-114.27163,34.488983],"type":"Point"}
}