{
  "type": "Feature",
  "properties": {
    "iso:country":"US",
    "sg:address":"506 Westwood Dr",
    "sg:city":"Prescott",
    "sg:classifiers":[
        {
            "category":"Shopping",
            "type":"Retail Goods"
        }
    ],
    "sg:phone":"+1 928 776 8211",
    "sg:postcode":"86303",
    "sg:province":"AZ",
    "sg:tags":[
        "merchandise"
    ],
    "wof:name":"Adams James Hermon Jr",
    "wof:placetype":"venue"
},
  "geometry": {"coordinates":[-112.486094,34.534445],"type":"Point"}
}