{
  "type": "Feature",
  "properties": {
    "iso:country":"US",
    "sg:address":"19207 N 7th Dr",
    "sg:city":"Phoenix",
    "sg:classifiers":[
        {
            "category":"Transit Center",
            "subcategory":"Freight",
            "type":"Transportation"
        },
        {
            "category":"Freight",
            "type":"Transportation"
        }
    ],
    "sg:phone":"+1 623 869 8168",
    "sg:postcode":"85027",
    "sg:province":"AZ",
    "sg:tags":[
        "trucking-motor",
        "trucking"
    ],
    "wof:name":"Capa Express",
    "wof:placetype":"venue"
},
  "geometry": {"coordinates":[-112.083422,33.66024],"type":"Point"}
}