{
  "type": "Feature",
  "properties": {
    "iso:country":"US",
    "sg:address":"10839 E Apache Trl",
    "sg:city":"Apache Junction",
    "sg:classifiers":[
        {
            "category":"Shopping",
            "subcategory":"Gifts & Souvenirs",
            "type":"Retail Goods"
        }
    ],
    "sg:phone":"+1 480 984 1707",
    "sg:postcode":"85220",
    "sg:province":"AZ",
    "wof:name":"Discount Card Outl of Suthwest",
    "wof:placetype":"venue"
},
  "geometry": {"coordinates":[-111.595234,33.415173],"type":"Point"}
}