{
  "type": "Feature",
  "properties": {
    "iso:country":"US",
    "sg:address":"5030 E Broadway Blvd",
    "sg:city":"Tucson",
    "sg:classifiers":[
        {
            "category":"Wholesale",
            "subcategory":"Non-durable Goods",
            "type":"Manufacturing & Wholesale Goods"
        }
    ],
    "sg:phone":"+1 520 795 0060",
    "sg:postcode":"85711",
    "sg:province":"AZ",
    "sg:tags":[
        "merchandise"
    ],
    "wof:name":"Reptile Specialists",
    "wof:placetype":"venue"
},
  "geometry": {"coordinates":[-110.885751,32.221567],"type":"Point"}
}