{
  "type": "Feature",
  "properties": {
    "iso:country":"US",
    "sg:address":"9020 W Thomas Road",
    "sg:city":"Phoenix",
    "sg:classifiers":[
        {
            "category":"Food & Beverages",
            "subcategory":"Groceries & Convenience Stores",
            "type":"Retail Goods"
        }
    ],
    "sg:phone":"+1 623 872 6200",
    "sg:postcode":"85037",
    "sg:province":"AZ",
    "wof:name":"Food City",
    "wof:placetype":"venue"
},
  "geometry": {"coordinates":[-112.25332,33.479696],"type":"Point"}
}