{
  "type": "Feature",
  "properties": {
    "iso:country":"US",
    "sg:address":"2540 N. 33rd Avenue",
    "sg:city":"Phoenix",
    "sg:classifiers":[
        {
            "category":"Professional",
            "subcategory":"Advertising",
            "type":"Services"
        },
        {
            "category":"Commercial Area",
            "type":"Public Place"
        },
        {
            "category":"Manufacturing",
            "subcategory":"Signs",
            "type":"Manufacturing & Wholesale Goods"
        },
        {
            "category":"Manufacturing",
            "subcategory":"Building Materials",
            "type":"Manufacturing & Wholesale Goods"
        }
    ],
    "sg:phone":"+1 602 331 1185",
    "sg:postcode":"85009",
    "sg:province":"AZ",
    "sg:tags":[
        "product",
        "fixture",
        "front",
        "advertising-promotional",
        "store"
    ],
    "sg:website":"http://jbsign.com",
    "wof:name":"JB Signs LLC",
    "wof:placetype":"venue"
},
  "geometry": {"coordinates":[-112.13005,33.47593],"type":"Point"}
}