{
  "type": "Feature",
  "properties": {
    "iso:country":"US",
    "sg:address":"234 E Hillside Ave",
    "sg:city":"Prescott",
    "sg:classifiers":[
        {
            "category":"Building & Trades",
            "subcategory":"Plumbing",
            "type":"Services"
        }
    ],
    "sg:phone":"+1 928 445 2351",
    "sg:postcode":"86301",
    "sg:province":"AZ",
    "sg:tags":[
        "cleaner",
        "repairer",
        "sewer",
        "contractor"
    ],
    "sg:website":"http://www.brewerplumbinginc.com",
    "wof:name":"Brewer Plumbing Inc",
    "wof:placetype":"venue"
},
  "geometry": {"coordinates":[-112.466899,34.553037],"type":"Point"}
}