{
  "type": "Feature",
  "properties": {
    "addr:full":"5250 E Pima St Tucson AZ 85712",
    "addr:housenumber":"5250",
    "addr:postcode":"85712",
    "addr:street":"E Pima St",
    "iso:country":"US",
    "sg:address":"5250 E Pima St",
    "sg:city":"Tucson",
    "sg:classifiers":[
        {
            "category":"Professional",
            "subcategory":"Business Services",
            "type":"Services"
        }
    ],
    "sg:phone":"+1 520 296 2230",
    "sg:postcode":"85712",
    "sg:province":"AZ",
    "sg:tags":[
        "broker"
    ],
    "wof:name":"R W WEBB Consulting",
    "wof:placetype":"venue"
},
  "geometry": {"coordinates":[-110.880212,32.243351],"type":"Point"}
}