{
  "type": "Feature",
  "properties": {
    "iso:country":"US",
    "sg:address":"8205 E Posada Ave",
    "sg:city":"Mesa",
    "sg:classifiers":[
        {
            "category":"Professional",
            "subcategory":"Management & Consulting",
            "type":"Services"
        }
    ],
    "sg:phone":"+1 480 429 4532",
    "sg:postcode":"85212",
    "sg:province":"AZ",
    "sg:tags":[
        "consultant",
        "business"
    ],
    "wof:name":"Definitive Data Solutions LLC",
    "wof:placetype":"venue"
},
  "geometry": {"coordinates":[-111.65808800000001,33.359509],"type":"Point"}
}