{
  "type": "Feature",
  "properties": {
    "addr:full":"3161 N Windsong Dr Prescott Valley AZ 86314",
    "addr:housenumber":"3161",
    "addr:postcode":"86314",
    "addr:street":"N Windsong Dr",
    "iso:country":"US",
    "sg:address":"3161 N Windsong Dr",
    "sg:city":"Prescott Valley",
    "sg:classifiers":[
        {
            "category":"Health Services",
            "subcategory":"Hospital",
            "type":"Services"
        }
    ],
    "sg:phone":"+1 928 759 9978",
    "sg:postcode":"86314",
    "sg:province":"AZ",
    "sg:tags":[
        "mental"
    ],
    "wof:name":"Mingus Center",
    "wof:placetype":"venue"
},
  "geometry": {"coordinates":[-112.326843,34.587855],"type":"Point"}
}