{
  "type": "Feature",
  "properties": {
    "iso:country":"US",
    "sg:address":"6200 W Dobbins Rd",
    "sg:city":"Laveen",
    "sg:classifiers":[
        {
            "category":"Wholesale",
            "subcategory":"Durable Goods & Equipment",
            "type":"Manufacturing & Wholesale Goods"
        }
    ],
    "sg:phone":"+1 602 237 3301",
    "sg:postcode":"85339",
    "sg:province":"AZ",
    "sg:tags":[
        "sawdust",
        "shaving"
    ],
    "wof:name":"R & D Sales Co",
    "wof:placetype":"venue"
},
  "geometry": {"coordinates":[-112.193679,33.362777],"type":"Point"}
}