{
  "type": "Feature",
  "properties": {
    "addr:full":"77 W Forest Ave Flagstaff AZ 86001",
    "addr:housenumber":"77",
    "addr:postcode":"86001",
    "addr:street":"W Forest Ave",
    "iso:country":"US",
    "sg:address":"77 W Forest Ave",
    "sg:city":"Flagstaff",
    "sg:classifiers":[
        {
            "category":"Health Services",
            "subcategory":"Health Practitioner",
            "type":"Services"
        }
    ],
    "sg:phone":"+1 928 214 2747",
    "sg:postcode":"86001",
    "sg:province":"AZ",
    "sg:tags":[
        "therapist",
        "physical"
    ],
    "wof:name":"Flagstaff Physical Therapy",
    "wof:placetype":"venue"
},
  "geometry": {"coordinates":[-111.642527,35.210671],"type":"Point"}
}