{
  "type": "Feature",
  "properties": {
    "iso:country":"US",
    "sg:address":"3038 E Irwin Avenue",
    "sg:city":"Mesa",
    "sg:classifiers":[
        {
            "category":"Real Estate",
            "subcategory":"Architect",
            "type":"Services"
        }
    ],
    "sg:phone":"+1 480 892 2247",
    "sg:postcode":"85204",
    "sg:province":"AZ",
    "wof:name":"Bain Kevin Randolph Architect",
    "wof:placetype":"venue"
},
  "geometry": {"coordinates":[-111.766088,33.384132],"type":"Point"}
}