{
  "type": "Feature",
  "properties": {
    "addr:full":"1620 E Tierra Buena Ln Phoenix AZ 85022",
    "addr:housenumber":"1620",
    "addr:postcode":"85022",
    "addr:street":"E Tierra Buena Ln",
    "iso:country":"US",
    "sg:address":"1620 E Tierra Buena Ln",
    "sg:city":"Phoenix",
    "sg:classifiers":[
        {
            "category":"Manufacturing",
            "subcategory":"Building Materials",
            "type":"Manufacturing & Wholesale Goods"
        },
        {
            "category":"Home & Garden",
            "subcategory":"Carpets & Floor Coverings",
            "type":"Retail Goods"
        }
    ],
    "sg:phone":"+1 602 909 8841",
    "sg:postcode":"85022",
    "sg:province":"AZ",
    "sg:tags":[
        "materials-wholesale",
        "manufacturer"
    ],
    "wof:name":"Royal Desert Floor Covering",
    "wof:placetype":"venue"
},
  "geometry": {"coordinates":[-112.047141,33.630773],"type":"Point"}
}