{
  "type": "Feature",
  "properties": {
    "iso:country":"US",
    "sg:address":"2209 W Coolidge St",
    "sg:city":"Phoenix",
    "sg:classifiers":[
        {
            "category":"Shopping",
            "subcategory":"Clothing, Apparel, & Fashions",
            "type":"Retail Goods"
        }
    ],
    "sg:phone":"+1 602 242 5125",
    "sg:postcode":"85015",
    "sg:province":"AZ",
    "wof:name":"Placencia Enterprise",
    "wof:placetype":"venue"
},
  "geometry": {"coordinates":[-112.10825199999999,33.50491],"type":"Point"}
}