{
  "type": "Feature",
  "properties": {
    "iso:country":"US",
    "sg:address":"333 W Fort Lowell Rd",
    "sg:city":"Tucson",
    "sg:classifiers":[
        {
            "category":"Utilities",
            "subcategory":"Telephone",
            "type":"Services"
        }
    ],
    "sg:phone":"+1 520 792 1644",
    "sg:postcode":"85705",
    "sg:province":"AZ",
    "sg:tags":[
        "communications"
    ],
    "wof:name":"C C I Communications Inc",
    "wof:placetype":"venue"
},
  "geometry": {"coordinates":[-110.977525,32.264626],"type":"Point"}
}