{
  "type": "Feature",
  "properties": {
    "iso:country":"US",
    "sg:address":"941 N Orchard",
    "sg:city":"Mesa",
    "sg:classifiers":[
        {
            "category":"Professional",
            "subcategory":"Accounting & Tax Preparation",
            "type":"Services"
        }
    ],
    "sg:phone":"+1 480 833 9663",
    "sg:postcode":"85213",
    "sg:province":"AZ",
    "sg:tags":[
        "return",
        "filing"
    ],
    "wof:name":"Padgett Business Svc Of Mesa",
    "wof:placetype":"venue"
},
  "geometry": {"coordinates":[-111.754167,33.432935],"type":"Point"}
}