{
  "type": "Feature",
  "properties": {
    "iso:country":"US",
    "sg:address":"2929 N Central Ave",
    "sg:city":"Phoenix",
    "sg:classifiers":[
        {
            "category":"Retail",
            "subcategory":"Photofinishing",
            "type":"Services"
        }
    ],
    "sg:phone":"+1 602 263 4725",
    "sg:postcode":"85012",
    "sg:province":"AZ",
    "sg:tags":[
        "photo",
        "finishing"
    ],
    "wof:name":"Shipp Shape Television & Film",
    "wof:placetype":"venue"
},
  "geometry": {"coordinates":[-112.07369799999999,33.481923],"type":"Point"}
}