{
  "type": "Feature",
  "properties": {
    "addr:full":"3041 E Mckellips Rd Mesa AZ 85213",
    "addr:housenumber":"3041",
    "addr:postcode":"85213",
    "addr:street":"E Mckellips Rd",
    "iso:country":"US",
    "sg:address":"3041 E Mckellips Rd",
    "sg:city":"Mesa",
    "sg:classifiers":[
        {
            "category":"Restaurant",
            "type":"Food & Drink"
        }
    ],
    "sg:menulink":"http://www.allmenus.com/az/phoenix/235313-taco-time/menu/",
    "sg:phone":"+1 480 218 1621",
    "sg:postcode":"85213",
    "sg:province":"AZ",
    "sg:tags":[
        "american",
        "mexican",
        "tex-mex"
    ],
    "wof:name":"Taco Time",
    "wof:placetype":"venue"
},
  "geometry": {"coordinates":[-111.765765,33.451828],"type":"Point"}
}