{
  "type": "Feature",
  "properties": {
    "addr:full":"424 S Gilbert Rd Mesa AZ 85204",
    "addr:housenumber":"424",
    "addr:postcode":"85204",
    "addr:street":"S Gilbert Rd",
    "iso:country":"US",
    "sg:address":"424 S Gilbert Rd",
    "sg:city":"Mesa",
    "sg:classifiers":[
        {
            "category":"Home & Garden",
            "subcategory":"Building Materials",
            "type":"Retail Goods"
        }
    ],
    "sg:phone":"+1 480 461 8050",
    "sg:postcode":"85204",
    "sg:province":"AZ",
    "sg:tags":[
        "glass",
        "window",
        "plate"
    ],
    "wof:name":"Harmon Auto Glass",
    "wof:placetype":"venue"
},
  "geometry": {"coordinates":[-111.78837900000001,33.406368],"type":"Point"}
}