{
  "type": "Feature",
  "properties": {
    "iso:country":"US",
    "sg:address":"238 S Main St",
    "sg:city":"Camp Verde",
    "sg:classifiers":[
        {
            "category":"Restaurant",
            "type":"Food & Drink"
        }
    ],
    "sg:phone":"+1 928 567 9702",
    "sg:postcode":"86322",
    "sg:province":"AZ",
    "sg:tags":[
        "eating"
    ],
    "wof:name":"Dash In",
    "wof:placetype":"venue"
},
  "geometry": {"coordinates":[-111.855275,34.565463],"type":"Point"}
}