{
  "type": "Feature",
  "properties": {
    "addr:full":"4206 N 32nd St Ste 1 Phoenix AZ 85018",
    "addr:housenumber":"4206",
    "addr:postcode":"85018",
    "addr:street":"N 32Nd St Ste 1",
    "iso:country":"US",
    "sg:address":"4206 N 32nd St Ste 1",
    "sg:city":"Phoenix",
    "sg:classifiers":[
        {
            "category":"Professional",
            "subcategory":"Testing Lab",
            "type":"Services"
        },
        {
            "category":"Health Services",
            "subcategory":"Medical Lab",
            "type":"Services"
        }
    ],
    "sg:phone":"+1 602 381 8027",
    "sg:postcode":"85018",
    "sg:province":"AZ",
    "sg:tags":[
        "laboratory",
        "dental"
    ],
    "wof:name":"Integrident Dental Laboratory",
    "wof:placetype":"venue"
},
  "geometry": {"coordinates":[-112.01298,33.496983],"type":"Point"}
}