{
  "type": "Feature",
  "properties": {
    "iso:country":"US",
    "sg:address":"8205 Winchester Dr",
    "sg:city":"Flagstaff",
    "sg:classifiers":[
        {
            "category":"Professional",
            "subcategory":"Lawyer & Legal Services",
            "type":"Services"
        }
    ],
    "sg:phone":"+1 928 526 6018",
    "sg:postcode":"86004",
    "sg:province":"AZ",
    "sg:tags":[
        "real estate"
    ],
    "wof:name":"Anjoy Inc",
    "wof:placetype":"venue"
},
  "geometry": {"coordinates":[-111.547647,35.259333],"type":"Point"}
}