{
  "type": "Feature",
  "properties": {
    "addr:full":"2202 W Lone Cactus Dr Phoenix AZ 85027",
    "addr:housenumber":"2202",
    "addr:postcode":"85027",
    "addr:street":"W Lone Cactus Dr",
    "iso:country":"US",
    "sg:address":"2202 W Lone Cactus Dr",
    "sg:city":"Phoenix",
    "sg:classifiers":[
        {
            "category":"Wholesale",
            "subcategory":"Stationery",
            "type":"Manufacturing & Wholesale Goods"
        }
    ],
    "sg:phone":"+1 623 587 4875",
    "sg:postcode":"85027",
    "sg:province":"AZ",
    "sg:tags":[
        "business",
        "form",
        "system"
    ],
    "wof:name":"Metropolitan Business Forms",
    "wof:placetype":"venue"
},
  "geometry": {"coordinates":[-112.10650699999999,33.680225],"type":"Point"}
}