{
  "type": "Feature",
  "properties": {
    "addr:full":"4322 W Bell Rd Glendale AZ 85308",
    "addr:housenumber":"4322",
    "addr:postcode":"85308",
    "addr:street":"W Bell Rd",
    "iso:country":"US",
    "sg:address":"4322 W Bell Rd",
    "sg:city":"Glendale",
    "sg:classifiers":[
        {
            "category":"Home & Garden",
            "subcategory":"Furniture",
            "type":"Retail Goods"
        }
    ],
    "sg:phone":"+1 602 863 1178",
    "sg:postcode":"85308",
    "sg:province":"AZ",
    "wof:name":"Furniture Discount Center",
    "wof:placetype":"venue"
},
  "geometry": {"coordinates":[-112.155001,33.639336],"type":"Point"}
}