{
  "type": "Feature",
  "properties": {
    "iso:country":"US",
    "sg:address":"2549 E 8th St",
    "sg:city":"Tucson",
    "sg:classifiers":[
        {
            "category":"Social Services",
            "type":"Services"
        }
    ],
    "sg:phone":"+1 520 881 0046",
    "sg:postcode":"85716",
    "sg:province":"AZ",
    "sg:tags":[
        "counselor",
        "marriage",
        "family"
    ],
    "wof:name":"Holly Mc Carter",
    "wof:placetype":"venue"
},
  "geometry": {"coordinates":[-110.934479,32.225367],"type":"Point"}
}