{
  "type": "Feature",
  "properties": {
    "iso:country":"US",
    "sg:address":"3561 Maricopa Ave",
    "sg:city":"Lake Havasu City",
    "sg:classifiers":[
        {
            "category":"Retail",
            "subcategory":"Repair Shop",
            "type":"Services"
        }
    ],
    "sg:phone":"+1 928 505 3200",
    "sg:postcode":"86406",
    "sg:province":"AZ",
    "sg:tags":[
        "scooter",
        "motorcycle",
        "motor"
    ],
    "wof:name":"B & M Cycle",
    "wof:placetype":"venue"
},
  "geometry": {"coordinates":[-114.267027,34.454385],"type":"Point"}
}