{
  "type": "Feature",
  "properties": {
    "iso:country":"US",
    "sg:address":"2600 Silver Creek Rd",
    "sg:city":"Bullhead City",
    "sg:classifiers":[
        {
            "category":"Health Services",
            "subcategory":"Doctor",
            "type":"Services"
        }
    ],
    "sg:phone":"+1 928 763 5565",
    "sg:postcode":"86442",
    "sg:province":"AZ",
    "sg:tags":[
        "dentist"
    ],
    "wof:name":"Family Dentistry",
    "wof:placetype":"venue"
},
  "geometry": {"coordinates":[-114.562961,35.111429],"type":"Point"}
}