{
  "type": "Feature",
  "properties": {
    "iso:country":"US",
    "sg:address":"2515 E Thomas Rd Ste 16",
    "sg:city":"Phoenix",
    "sg:classifiers":[
        {
            "category":"Wholesale",
            "subcategory":"Medical Equipment & Supplies",
            "type":"Manufacturing & Wholesale Goods"
        }
    ],
    "sg:phone":"+1 602 738 2255",
    "sg:postcode":"85016",
    "sg:province":"AZ",
    "sg:tags":[
        "polishing",
        "buffing"
    ],
    "wof:name":"Off The Cuff Mobile Dry Clg",
    "wof:placetype":"venue"
},
  "geometry": {"coordinates":[-112.027337,33.480344],"type":"Point"}
}