{
  "type": "Feature",
  "properties": {
    "iso:country":"US",
    "sg:address":"91 S Main St Ste E",
    "sg:city":"Snowflake",
    "sg:classifiers":[
        {
            "category":"Professional",
            "subcategory":"Lawyer & Legal Services",
            "type":"Services"
        }
    ],
    "sg:phone":"+1 928 536 7607",
    "sg:postcode":"85937",
    "sg:province":"AZ",
    "sg:tags":[
        "attorney",
        "practice"
    ],
    "wof:name":"Roser Law Office P",
    "wof:placetype":"venue"
},
  "geometry": {"coordinates":[-110.091235,34.463809],"type":"Point"}
}