{
  "type": "Feature",
  "properties": {
    "addr:full":"3850 N Hayden Rd Scottsdale AZ 85251",
    "addr:housenumber":"3850",
    "addr:postcode":"85251",
    "addr:street":"N Hayden Rd",
    "iso:country":"US",
    "sg:address":"3850 N Hayden Rd",
    "sg:city":"Scottsdale",
    "sg:classifiers":[
        {
            "category":"Professional",
            "subcategory":"Advertising",
            "type":"Services"
        }
    ],
    "sg:phone":"+1 480 664 1710",
    "sg:postcode":"85251",
    "sg:province":"AZ",
    "sg:tags":[
        "counselor"
    ],
    "wof:name":"Origin Web & Marketing Sols",
    "wof:placetype":"venue"
},
  "geometry": {"coordinates":[-111.908962,33.492028],"type":"Point"}
}