{
  "type": "Feature",
  "properties": {
    "iso:country":"US",
    "sg:address":"600 N 40th St",
    "sg:city":"Phoenix",
    "sg:classifiers":[
        {
            "category":"Government",
            "subcategory":"Office",
            "type":"Public Place"
        }
    ],
    "sg:phone":"+1 602 207 7000",
    "sg:postcode":"85008",
    "sg:province":"AZ",
    "wof:name":"Phoenix Vehicle Emissions Info",
    "wof:placetype":"venue"
},
  "geometry": {"coordinates":[-111.995262,33.454891],"type":"Point"}
}