{
  "type": "Feature",
  "properties": {
    "iso:country":"US",
    "sg:address":"17823 W Stella Ln",
    "sg:city":"Waddell",
    "sg:classifiers":[
        {
            "category":"Building & Trades",
            "subcategory":"Construction",
            "type":"Services"
        }
    ],
    "sg:phone":"+1 623 536 2232",
    "sg:postcode":"85355",
    "sg:province":"AZ",
    "sg:tags":[
        "house",
        "general",
        "contractor"
    ],
    "wof:name":"R Mb Construction Inc",
    "wof:placetype":"venue"
},
  "geometry": {"coordinates":[-112.443274,33.528938],"type":"Point"}
}