{
  "type": "Feature",
  "properties": {
    "addr:full":"2714 E Birchwood Ave Mesa AZ 85204",
    "addr:housenumber":"2714",
    "addr:postcode":"85204",
    "addr:street":"E Birchwood Ave",
    "iso:country":"US",
    "sg:address":"2714 E Birchwood Ave",
    "sg:city":"Mesa",
    "sg:classifiers":[
        {
            "category":"Retail",
            "subcategory":"Laundry & Dry Cleaning",
            "type":"Services"
        }
    ],
    "sg:phone":"+1 602 769 8640",
    "sg:postcode":"85204",
    "sg:province":"AZ",
    "sg:tags":[
        "repairing",
        "rug",
        "carpet"
    ],
    "wof:name":"B-Floor Tec Installations",
    "wof:placetype":"venue"
},
  "geometry": {"coordinates":[-111.771817,33.410716],"type":"Point"}
}