{
  "type": "Feature",
  "properties": {
    "addr:full":"1178 S Litchfield Rd Goodyear AZ 85338",
    "addr:housenumber":"1178",
    "addr:postcode":"85338",
    "addr:street":"S Litchfield Rd",
    "iso:country":"US",
    "sg:address":"1178 S Litchfield Rd",
    "sg:city":"Goodyear",
    "sg:classifiers":[
        {
            "category":"Restaurant",
            "type":"Food & Drink"
        }
    ],
    "sg:menulink":"http://www.allmenus.com/az/phoenix/174034-wendys/menu/",
    "sg:phone":"+1 623 935 5532",
    "sg:postcode":"85338",
    "sg:province":"AZ",
    "sg:tags":[
        "burger",
        "american",
        "soup"
    ],
    "wof:name":"Wendy's",
    "wof:placetype":"venue"
},
  "geometry": {"coordinates":[-112.358149,33.429237],"type":"Point"}
}