{
  "type": "Feature",
  "properties": {
    "iso:country":"US",
    "sg:address":"18300 W Bell Rd",
    "sg:city":"Surprise",
    "sg:classifiers":[
        {
            "category":"Organizations",
            "subcategory":"Community Association",
            "type":"Services"
        }
    ],
    "sg:phone":"+1 623 975 0815",
    "sg:postcode":"85374",
    "sg:province":"AZ",
    "sg:tags":[
        "fraternal"
    ],
    "wof:name":"Bpoe Surprise Elks 2833",
    "wof:placetype":"venue"
},
  "geometry": {"coordinates":[-112.44487700000001,33.638961],"type":"Point"}
}