{
  "type": "Feature",
  "properties": {
    "iso:country":"US",
    "sg:address":"110 S 54th St",
    "sg:city":"Chandler",
    "sg:classifiers":[
        {
            "category":"Wholesale",
            "subcategory":"Machinery & Supplies",
            "type":"Manufacturing & Wholesale Goods"
        }
    ],
    "sg:phone":"+1 480 496 9200",
    "sg:postcode":"85226",
    "sg:province":"AZ",
    "sg:tags":[
        "equipment",
        "weed",
        "pest",
        "spraying"
    ],
    "wof:name":"Quality Equipment",
    "wof:placetype":"venue"
},
  "geometry": {"coordinates":[-111.967681,33.301092],"type":"Point"}
}