{
  "type": "Feature",
  "properties": {
    "iso:country":"US",
    "sg:address":"15341 N 86th Ave",
    "sg:city":"Peoria",
    "sg:classifiers":[
        {
            "category":"Building & Trades",
            "subcategory":"Pest Control",
            "type":"Services"
        }
    ],
    "sg:phone":"+1 602 290 1371",
    "sg:postcode":"85381",
    "sg:province":"AZ",
    "sg:tags":[
        "mothproofing"
    ],
    "wof:name":"Joe R Cons",
    "wof:placetype":"venue"
},
  "geometry": {"coordinates":[-112.2449,33.623665],"type":"Point"}
}