{
  "type": "Feature",
  "properties": {
    "iso:country":"US",
    "sg:address":"5245 S Kyrene Rd",
    "sg:city":"Tempe",
    "sg:classifiers":[
        {
            "category":"Professional",
            "subcategory":"Management & Consulting",
            "type":"Services"
        }
    ],
    "sg:phone":"+1 480 831 5930",
    "sg:postcode":"85283",
    "sg:province":"AZ",
    "sg:tags":[
        "party",
        "planning"
    ],
    "wof:name":"A-Able Entertainment Equipment",
    "wof:placetype":"venue"
},
  "geometry": {"coordinates":[-111.945902,33.377068],"type":"Point"}
}