{
  "type": "Feature",
  "properties": {
    "iso:country":"US",
    "sg:address":"14360 N Frank Lloyd Wright Blvd",
    "sg:city":"Scottsdale",
    "sg:classifiers":[
        {
            "category":"Professional",
            "type":"Services"
        }
    ],
    "sg:phone":"+1 480 477 6980",
    "sg:postcode":"85260",
    "sg:province":"AZ",
    "sg:tags":[
        "establishment"
    ],
    "wof:name":"Bass Trading",
    "wof:placetype":"venue"
},
  "geometry": {"coordinates":[-111.87125,33.616886],"type":"Point"}
}