{
  "type": "Feature",
  "properties": {
    "addr:full":"6210 N 79th Ln Glendale AZ 85303",
    "addr:housenumber":"6210",
    "addr:postcode":"85303",
    "addr:street":"N 79Th Ln",
    "iso:country":"US",
    "sg:address":"6210 N 79th Ln",
    "sg:city":"Glendale",
    "sg:classifiers":[
        {
            "category":"Freight",
            "type":"Transportation"
        }
    ],
    "sg:phone":"+1 623 842 2347",
    "sg:postcode":"85303",
    "sg:province":"AZ",
    "sg:tags":[
        "operator",
        "local",
        "trucking"
    ],
    "wof:name":"Sartirana Trucking LLC",
    "wof:placetype":"venue"
},
  "geometry": {"coordinates":[-112.228033,33.525061],"type":"Point"}
}