{
  "type": "Feature",
  "properties": {
    "addr:full":"4700 S Overland Dr Tucson AZ 85714",
    "addr:housenumber":"4700",
    "addr:postcode":"85714",
    "addr:street":"S Overland Dr",
    "iso:country":"US",
    "sg:address":"4700 S Overland Dr",
    "sg:city":"Tucson",
    "sg:classifiers":[
        {
            "category":"Manufacturing",
            "subcategory":"Tools & Machinery",
            "type":"Manufacturing & Wholesale Goods"
        }
    ],
    "sg:phone":"+1 520 882 7794",
    "sg:postcode":"85714",
    "sg:province":"AZ",
    "sg:tags":[
        "physician",
        "surgeon"
    ],
    "wof:name":"MRI Mfg & Research Inc",
    "wof:placetype":"venue"
},
  "geometry": {"coordinates":[-110.911447,32.166793],"type":"Point"}
}