{
  "type": "Feature",
  "properties": {
    "iso:country":"US",
    "sg:address":"7720 E Gelding Dr",
    "sg:city":"Scottsdale",
    "sg:classifiers":[
        {
            "category":"Freight",
            "type":"Transportation"
        }
    ],
    "sg:phone":"+1 480 889 3089",
    "sg:postcode":"85260",
    "sg:province":"AZ",
    "wof:name":"Pinnacle Executive Trnsprtn",
    "wof:placetype":"venue"
},
  "geometry": {"coordinates":[-111.912668,33.615308],"type":"Point"}
}