{
  "type": "Feature",
  "properties": {
    "iso:country":"US",
    "sg:address":"8801 N Central Ave",
    "sg:city":"Phoenix",
    "sg:classifiers":[
        {
            "category":"Home & Garden",
            "subcategory":"Home Furnishings",
            "type":"Retail Goods"
        }
    ],
    "sg:phone":"+1 602 997 6890",
    "sg:postcode":"85020",
    "sg:province":"AZ",
    "sg:tags":[
        "house",
        "decor"
    ],
    "wof:name":"Mirage Collection",
    "wof:placetype":"venue"
},
  "geometry": {"coordinates":[-112.073868,33.564091],"type":"Point"}
}