{
  "type": "Feature",
  "properties": {
    "addr:full":"2205 W Melinda Ln Phoenix AZ 85027",
    "addr:housenumber":"2205",
    "addr:postcode":"85027",
    "addr:street":"W Melinda Ln",
    "iso:country":"US",
    "sg:address":"2205 W Melinda Ln",
    "sg:city":"Phoenix",
    "sg:classifiers":[
        {
            "category":"Home & Garden",
            "subcategory":"Home Furnishings",
            "type":"Retail Goods"
        }
    ],
    "sg:phone":"+1 623 780 1900",
    "sg:postcode":"85027",
    "sg:province":"AZ",
    "sg:tags":[
        "venetian",
        "blind"
    ],
    "wof:name":"Blind Ideas & Interiors",
    "wof:placetype":"venue"
},
  "geometry": {"coordinates":[-112.107004,33.681875],"type":"Point"}
}