{
  "type": "Feature",
  "properties": {
    "iso:country":"US",
    "sg:address":"2709 W Van Buren St",
    "sg:city":"Phoenix",
    "sg:classifiers":[
        {
            "category":"Food & Beverages",
            "subcategory":"Groceries & Convenience Stores",
            "type":"Retail Goods"
        }
    ],
    "sg:phone":"+1 602 272 0652",
    "sg:postcode":"85009",
    "sg:province":"AZ",
    "wof:name":"Food City",
    "wof:placetype":"venue"
},
  "geometry": {"coordinates":[-112.11863,33.451046],"type":"Point"}
}