{
  "type": "Feature",
  "properties": {
    "iso:country":"US",
    "sg:address":"1200 E Southern Ave",
    "sg:city":"Tempe",
    "sg:classifiers":[
        {
            "category":"Organizations",
            "subcategory":"Religious Organization",
            "type":"Services"
        }
    ],
    "sg:phone":"+1 480 894 2201",
    "sg:postcode":"85282",
    "sg:province":"AZ",
    "wof:name":"Grace Community Church",
    "wof:placetype":"venue"
},
  "geometry": {"coordinates":[-111.92003099999999,33.392977],"type":"Point"}
}