{
  "type": "Feature",
  "properties": {
    "iso:country":"US",
    "sg:address":"1015 W Prince Rd",
    "sg:city":"Tucson",
    "sg:classifiers":[
        {
            "category":"Professional",
            "subcategory":"Lawyer & Legal Services",
            "type":"Services"
        }
    ],
    "sg:phone":"+1 520 293 8690",
    "sg:postcode":"85705",
    "sg:province":"AZ",
    "sg:tags":[
        "attorney"
    ],
    "wof:name":"George W Reiblich Attorney Law",
    "wof:placetype":"venue"
},
  "geometry": {"coordinates":[-110.989635,32.271994],"type":"Point"}
}