{
  "type": "Feature",
  "properties": {
    "addr:full":"242 E Mountain Sunset Pl Oro Valley AZ 85704",
    "addr:housenumber":"242",
    "addr:postcode":"85704",
    "addr:street":"E Mountain Sunset Pl",
    "iso:country":"US",
    "sg:address":"242 E Mountain Sunset Pl",
    "sg:city":"Oro Valley",
    "sg:classifiers":[
        {
            "category":"Shopping",
            "subcategory":"Hobbies, Toys, & Games",
            "type":"Retail Goods"
        }
    ],
    "sg:phone":"+1 520 744 2436",
    "sg:postcode":"85704",
    "sg:province":"AZ",
    "sg:tags":[
        "shop",
        "rock"
    ],
    "sg:website":"www.rockyourworld.com",
    "wof:name":"Rock Your World",
    "wof:placetype":"venue"
},
  "geometry": {"coordinates":[-110.968563,32.36176],"type":"Point"}
}