{
  "type": "Feature",
  "properties": {
    "addr:full":"17300 N Sun Village Pkwy Surprise AZ 85374",
    "addr:housenumber":"17300",
    "addr:postcode":"85374",
    "addr:street":"N Sun Village Pkwy",
    "iso:country":"US",
    "sg:address":"17300 N Sun Village Pkwy",
    "sg:city":"Surprise",
    "sg:classifiers":[
        {
            "category":"Restaurant",
            "type":"Food & Drink"
        }
    ],
    "sg:phone":"+1 623 584 5931",
    "sg:postcode":"85374",
    "sg:province":"AZ",
    "wof:name":"Faylene's",
    "wof:placetype":"venue"
},
  "geometry": {"coordinates":[-112.368574,33.641038],"type":"Point"}
}