{
  "type": "Feature",
  "properties": {
    "addr:full":"701 N 95th Ave Tolleson AZ 85353",
    "addr:housenumber":"701",
    "addr:postcode":"85353",
    "addr:street":"N 95Th Ave",
    "iso:country":"US",
    "sg:address":"701 N 95th Ave",
    "sg:city":"Tolleson",
    "sg:classifiers":[
        {
            "category":"Organizations",
            "subcategory":"Religious Organization",
            "type":"Services"
        }
    ],
    "sg:phone":"+1 623 936 3042",
    "sg:postcode":"85353",
    "sg:province":"AZ",
    "sg:tags":[
        "church"
    ],
    "wof:name":"Church Of Jesus Christ Of Lds",
    "wof:placetype":"venue"
},
  "geometry": {"coordinates":[-112.263865,33.455619],"type":"Point"}
}