{
  "type": "Feature",
  "properties": {
    "addr:full":"321 E Rimrock Dr Phoenix AZ 85024",
    "addr:housenumber":"321",
    "addr:postcode":"85024",
    "addr:street":"E Rimrock Dr",
    "iso:country":"US",
    "sg:address":"321 E Rimrock Dr",
    "sg:city":"Phoenix",
    "sg:classifiers":[
        {
            "category":"Education",
            "subcategory":"Vocational School",
            "type":"Public Place"
        }
    ],
    "sg:phone":"+1 602 451 4402",
    "sg:postcode":"85024",
    "sg:province":"AZ",
    "sg:tags":[
        "technical",
        "industrial",
        "business",
        "trade"
    ],
    "wof:name":"Options Training And Development Services",
    "wof:placetype":"venue"
},
  "geometry": {"coordinates":[-112.069624,33.662653],"type":"Point"}
}