{
  "type": "Feature",
  "properties": {
    "iso:country":"US",
    "sg:address":"1 N Macdonald Ste 204",
    "sg:city":"Mesa",
    "sg:classifiers":[
        {
            "category":"Banks & Credit Unions",
            "subcategory":"Financial Services",
            "type":"Services"
        }
    ],
    "sg:phone":"+1 480 355 2430",
    "sg:postcode":"85201",
    "sg:province":"AZ",
    "sg:tags":[
        "mortgage"
    ],
    "wof:name":"Blue Brick Financial",
    "wof:placetype":"venue"
},
  "geometry": {"coordinates":[-111.834068,33.415138],"type":"Point"}
}