{
  "type": "Feature",
  "properties": {
    "addr:full":"4525 N 12th St Phoenix AZ 85014",
    "addr:housenumber":"4525",
    "addr:postcode":"85014",
    "addr:street":"N 12Th St",
    "iso:country":"US",
    "sg:address":"4525 N 12th St",
    "sg:city":"Phoenix",
    "sg:classifiers":[
        {
            "category":"Professional",
            "subcategory":"Employment Agencies",
            "type":"Services"
        }
    ],
    "sg:phone":"+1 602 248 9313",
    "sg:postcode":"85014",
    "sg:province":"AZ",
    "sg:tags":[
        "opportunity"
    ],
    "wof:name":"Temporary Team Employment Svc",
    "wof:placetype":"venue"
},
  "geometry": {"coordinates":[-112.056208,33.503756],"type":"Point"}
}