{
  "type": "Feature",
  "properties": {
    "iso:country":"US",
    "sg:address":"9794 W Peoria Ave",
    "sg:city":"Peoria",
    "sg:classifiers":[
        {
            "category":"Professional",
            "subcategory":"Accounting & Tax Preparation",
            "type":"Services"
        }
    ],
    "sg:phone":"+1 623 933 2829",
    "sg:postcode":"85345",
    "sg:province":"AZ",
    "sg:tags":[
        "return",
        "filing"
    ],
    "wof:name":"Metz Tax Svc",
    "wof:placetype":"venue"
},
  "geometry": {"coordinates":[-112.266921,33.580567],"type":"Point"}
}