{
  "type": "Feature",
  "properties": {
    "iso:country":"US",
    "sg:address":"9053 E Baseline Rd",
    "sg:city":"Mesa",
    "sg:classifiers":[
        {
            "category":"Restaurant",
            "type":"Food & Drink"
        }
    ],
    "sg:phone":"+1 480 986 2228",
    "sg:postcode":"85209",
    "sg:province":"AZ",
    "sg:tags":[
        "grill",
        "bar"
    ],
    "wof:name":"Uncle Bears Ellsworth LLC",
    "wof:placetype":"venue"
},
  "geometry": {"coordinates":[-111.64487,33.379168],"type":"Point"}
}