{
  "type": "Feature",
  "properties": {
    "iso:country":"US",
    "sg:address":"415 S Higley Rd",
    "sg:city":"Mesa",
    "sg:classifiers":[
        {
            "category":"Shopping",
            "subcategory":"Pharmacy",
            "type":"Retail Goods"
        }
    ],
    "sg:phone":"+1 480 981 0249",
    "sg:postcode":"85206",
    "sg:province":"AZ",
    "wof:name":"Osco Drug",
    "wof:placetype":"venue"
},
  "geometry": {"coordinates":[-111.719082,33.408135],"type":"Point"}
}