{
  "type": "Feature",
  "properties": {
    "addr:full":"4560 N 19th Ave Phoenix AZ 85015",
    "addr:housenumber":"4560",
    "addr:postcode":"85015",
    "addr:street":"N 19Th Ave",
    "iso:country":"US",
    "sg:address":"4560 N 19th Ave",
    "sg:city":"Phoenix",
    "sg:classifiers":[
        {
            "category":"Banks & Credit Unions",
            "subcategory":"Bank",
            "type":"Services"
        }
    ],
    "sg:phone":"+1 602 249 7300",
    "sg:postcode":"85015",
    "sg:province":"AZ",
    "sg:tags":[
        "loan",
        "real estate"
    ],
    "wof:name":"Mortgage Pro USA",
    "wof:placetype":"venue"
},
  "geometry": {"coordinates":[-112.099964,33.503007],"type":"Point"}
}