{
  "type": "Feature",
  "properties": {
    "addr:full":"4601 E Marconi Ave Phoenix AZ 85032",
    "addr:housenumber":"4601",
    "addr:postcode":"85032",
    "addr:street":"E Marconi Ave",
    "iso:country":"US",
    "sg:address":"4601 E Marconi Ave",
    "sg:city":"Phoenix",
    "sg:classifiers":[
        {
            "category":"Shopping",
            "subcategory":"Pets & Pet Supplies",
            "type":"Retail Goods"
        }
    ],
    "sg:phone":"+1 602 909 5845",
    "sg:postcode":"85032",
    "sg:province":"AZ",
    "sg:tags":[
        "furnishing",
        "dog",
        "store",
        "cat"
    ],
    "wof:name":"Please Save My Pets",
    "wof:placetype":"venue"
},
  "geometry": {"coordinates":[-111.982162,33.631008],"type":"Point"}
}