{
  "type": "Feature",
  "properties": {
    "iso:country":"US",
    "sg:address":"5767 E Roundup St",
    "sg:city":"Apache Junction",
    "sg:classifiers":[
        {
            "category":"Manufacturing",
            "subcategory":"Apparel",
            "type":"Manufacturing & Wholesale Goods"
        }
    ],
    "sg:phone":"+1 480 983 4309",
    "sg:postcode":"85219",
    "sg:province":"AZ",
    "sg:tags":[
        "mfg"
    ],
    "wof:name":"Fur By US",
    "wof:placetype":"venue"
},
  "geometry": {"coordinates":[-111.48378,33.425892],"type":"Point"}
}