{
  "type": "Feature",
  "properties": {
    "iso:country":"US",
    "sg:address":"517 N Mondel Dr",
    "sg:city":"Gilbert",
    "sg:classifiers":[
        {
            "category":"Building & Trades",
            "subcategory":"Construction",
            "type":"Services"
        }
    ],
    "sg:phone":"+1 480 545 1738",
    "sg:postcode":"85233",
    "sg:province":"AZ",
    "sg:tags":[
        "general",
        "contractor"
    ],
    "wof:name":"Osness Contracting Inc",
    "wof:placetype":"venue"
},
  "geometry": {"coordinates":[-111.818534,33.360868],"type":"Point"}
}