{
  "type": "Feature",
  "properties": {
    "iso:country":"US",
    "sg:address":"736 S Pla Amena",
    "sg:city":"Green Valley",
    "sg:classifiers":[
        {
            "category":"Communications",
            "subcategory":"Radio Station",
            "type":"Services"
        }
    ],
    "sg:phone":"+1 520 625 0083",
    "sg:postcode":"85614",
    "sg:province":"AZ",
    "sg:tags":[
        "company",
        "broadcasting"
    ],
    "wof:name":"KGO Radio Inc",
    "wof:placetype":"venue"
},
  "geometry": {"coordinates":[-111.00632299999999,31.85944],"type":"Point"}
}