{
  "type": "Feature",
  "properties": {
    "iso:country":"US",
    "sg:address":"7701 W Minnezona Ave",
    "sg:city":"Phoenix",
    "sg:classifiers":[
        {
            "category":"Building & Trades",
            "subcategory":"Locksmith",
            "type":"Services"
        }
    ],
    "sg:phone":"+1 602 635 6742",
    "sg:postcode":"85033",
    "sg:province":"AZ",
    "sg:tags":[
        "key"
    ],
    "wof:name":"Locksmith Available",
    "wof:placetype":"venue"
},
  "geometry": {"coordinates":[-112.22571600000001,33.501933],"type":"Point"}
}