{
  "type": "Feature",
  "properties": {
    "iso:country":"US",
    "sg:address":"3641 W Vista Ave",
    "sg:city":"Phoenix",
    "sg:classifiers":[
        {
            "category":"Professional",
            "type":"Services"
        }
    ],
    "sg:phone":"+1 602 841 1232",
    "sg:postcode":"85051",
    "sg:province":"AZ",
    "wof:name":"Scan Deogrphics",
    "wof:placetype":"venue"
},
  "geometry": {"coordinates":[-112.137479,33.546535],"type":"Point"}
}