{
  "type": "Feature",
  "properties": {
    "iso:country":"US",
    "sg:address":"21027 N Cave Creek Rd",
    "sg:city":"Phoenix",
    "sg:classifiers":[
        {
            "category":"Retail",
            "subcategory":"Laundry & Dry Cleaning",
            "type":"Services"
        }
    ],
    "sg:phone":"+1 602 867 4501",
    "sg:postcode":"85024",
    "sg:province":"AZ",
    "sg:tags":[
        "cleaners"
    ],
    "wof:name":"Cambridge 1.75 Cleaners",
    "wof:placetype":"venue"
},
  "geometry": {"coordinates":[-112.030998,33.678408],"type":"Point"}
}