{
  "type": "Feature",
  "properties": {
    "iso:country":"US",
    "sg:address":"1941 E Brown Rd",
    "sg:city":"Mesa",
    "sg:classifiers":[
        {
            "category":"Home & Garden",
            "subcategory":"Hardware",
            "type":"Retail Goods"
        }
    ],
    "sg:phone":"+1 480 890 1900",
    "sg:postcode":"85203",
    "sg:province":"AZ",
    "wof:name":"Ace Hardware",
    "wof:placetype":"venue"
},
  "geometry": {"coordinates":[-111.790492,33.43708],"type":"Point"}
}