{
  "type": "Feature",
  "properties": {
    "iso:country":"US",
    "sg:address":"12125 E Cloud Rd",
    "sg:city":"Chandler",
    "sg:classifiers":[
        {
            "category":"Professional",
            "type":"Services"
        }
    ],
    "sg:phone":"+1 480 895 1862",
    "sg:postcode":"85249",
    "sg:province":"AZ",
    "wof:name":"Arizona Rocky Road",
    "wof:placetype":"venue"
},
  "geometry": {"coordinates":[-111.822247,33.225932],"type":"Point"}
}