{
  "type": "Feature",
  "properties": {
    "iso:country":"US",
    "sg:address":"2014 Plaza Dr",
    "sg:city":"Bullhead City",
    "sg:classifiers":[
        {
            "category":"Shopping",
            "type":"Retail Goods"
        }
    ],
    "sg:phone":"+1 928 758 9801",
    "sg:postcode":"86442",
    "sg:province":"AZ",
    "wof:name":"Sun Enterprises",
    "wof:placetype":"venue"
},
  "geometry": {"coordinates":[-114.62569,35.100315],"type":"Point"}
}