{
  "type": "Feature",
  "properties": {
    "iso:country":"US",
    "sg:address":"11300 E Highway 181",
    "sg:city":"Willcox",
    "sg:classifiers":[
        {
            "category":"Restaurant",
            "type":"Food & Drink"
        }
    ],
    "sg:phone":"+1 520 824 3472",
    "sg:postcode":"85643",
    "sg:province":"AZ",
    "wof:name":"Natural Beef Network",
    "wof:placetype":"venue"
},
  "geometry": {"coordinates":[-109.408439,32.006734],"type":"Point"}
}