{
  "type": "Feature",
  "properties": {
    "iso:country":"US",
    "sg:address":"1217 W Hatcher Rd",
    "sg:city":"Phoenix",
    "sg:classifiers":[
        {
            "category":"Autos & Motor Vehicles",
            "subcategory":"Motorcycle Sales",
            "type":"Retail Goods"
        }
    ],
    "sg:phone":"+1 602 870 4050",
    "sg:postcode":"85021",
    "sg:province":"AZ",
    "sg:tags":[
        "scooter"
    ],
    "wof:name":"Ballistic Pipe WERX LLC",
    "wof:placetype":"venue"
},
  "geometry": {"coordinates":[-112.090034,33.571162],"type":"Point"}
}