{
  "type": "Feature",
  "properties": {
    "iso:country":"US",
    "sg:address":"1196 N Arizona Ave",
    "sg:city":"Chandler",
    "sg:classifiers":[
        {
            "category":"Retail",
            "subcategory":"Car Wash",
            "type":"Services"
        }
    ],
    "sg:phone":"+1 480 855 5124",
    "sg:postcode":"85225",
    "sg:province":"AZ",
    "sg:tags":[
        "polishing",
        "washing"
    ],
    "wof:name":"Arizona Avenue Car Wash",
    "wof:placetype":"venue"
},
  "geometry": {"coordinates":[-111.841696,33.32277],"type":"Point"}
}