{
  "type": "Feature",
  "properties": {
    "addr:full":"261 N White Mountain Rd Show Low AZ 85901",
    "addr:housenumber":"261",
    "addr:postcode":"85901",
    "addr:street":"N White Mountain Rd",
    "iso:country":"US",
    "sg:address":"261 N White Mountain Rd",
    "sg:city":"Show Low",
    "sg:classifiers":[
        {
            "category":"Retail",
            "subcategory":"Car Wash",
            "type":"Services"
        }
    ],
    "sg:phone":"+1 928 532 7080",
    "sg:postcode":"85901",
    "sg:province":"AZ",
    "sg:tags":[
        "polishing",
        "washing"
    ],
    "wof:name":"Splash & Dash Car Wash & Exp",
    "wof:placetype":"venue"
},
  "geometry": {"coordinates":[-110.028549,34.251884],"type":"Point"}
}