{
  "type": "Feature",
  "properties": {
    "addr:full":"3837 State Hwy 92 Sierra Vista AZ 85650",
    "addr:housenumber":"3837",
    "addr:postcode":"85650",
    "addr:street":"State Hwy 92",
    "iso:country":"US",
    "sg:address":"3837 State Hwy 92",
    "sg:city":"Sierra Vista",
    "sg:classifiers":[
        {
            "category":"Recreation",
            "type":"Entertainment"
        }
    ],
    "sg:phone":"+1 520 378 2255",
    "sg:postcode":"85650",
    "sg:province":"AZ",
    "sg:tags":[
        "parlor",
        "billiard"
    ],
    "wof:name":"Rack-Um Pool Emporium",
    "wof:placetype":"venue"
},
  "geometry": {"coordinates":[-110.25730900000001,31.499598],"type":"Point"}
}