{
  "type": "Feature",
  "properties": {
    "iso:country":"US",
    "sg:address":"4602 N Pso del Barranco",
    "sg:city":"Tucson",
    "sg:classifiers":[
        {
            "category":"Professional",
            "subcategory":"Computer Services",
            "type":"Services"
        }
    ],
    "sg:phone":"+1 520 743 8171",
    "sg:postcode":"85745",
    "sg:province":"AZ",
    "wof:name":"Dynavar Networking",
    "wof:placetype":"venue"
},
  "geometry": {"coordinates":[-111.08309,32.289111],"type":"Point"}
}