{
  "type": "Feature",
  "properties": {
    "addr:full":"1641 S Stapley Dr Mesa AZ 85204",
    "addr:housenumber":"1641",
    "addr:postcode":"85204",
    "addr:street":"S Stapley Dr",
    "iso:country":"US",
    "sg:address":"1641 S Stapley Dr",
    "sg:city":"Mesa",
    "sg:classifiers":[
        {
            "category":"Restaurant",
            "type":"Food & Drink"
        }
    ],
    "sg:phone":"+1 480 545 6123",
    "sg:postcode":"85204",
    "sg:province":"AZ",
    "wof:name":"Charley's Grilled Subs",
    "wof:placetype":"venue"
},
  "geometry": {"coordinates":[-111.80546699999999,33.385713],"type":"Point"}
}