{
  "type": "Feature",
  "properties": {
    "iso:country":"US",
    "sg:address":"1641 S Stapley Dr",
    "sg:city":"Mesa",
    "sg:classifiers":[
        {
            "category":"Restaurant",
            "type":"Food & Drink"
        }
    ],
    "sg:phone":"+1 480 545 6123",
    "sg:postcode":"85204",
    "sg:province":"AZ",
    "wof:name":"Charley's Grilled Subs",
    "wof:placetype":"venue"
},
  "geometry": {"coordinates":[-111.805467,33.385713],"type":"Point"}
}