{
  "type": "Feature",
  "properties": {
    "iso:country":"US",
    "sg:address":"1761 E McNair Drive",
    "sg:city":"Tempe",
    "sg:classifiers":[
        {
            "category":"Professional",
            "subcategory":"Lawyer & Legal Services",
            "type":"Services"
        }
    ],
    "sg:phone":"+1 480 413 1300",
    "sg:postcode":"85283",
    "sg:province":"AZ",
    "wof:name":"Lawson Slade Attorney At Law",
    "wof:placetype":"venue"
},
  "geometry": {"coordinates":[-111.908806,33.350647],"type":"Point"}
}