{
  "type": "Feature",
  "properties": {
    "iso:country":"US",
    "sg:address":"742 N Country Club Rd",
    "sg:city":"Tucson",
    "sg:classifiers":[
        {
            "category":"Government",
            "subcategory":"Office",
            "type":"Public Place"
        }
    ],
    "sg:phone":"+1 520 319 5610",
    "sg:postcode":"85716",
    "sg:province":"AZ",
    "sg:tags":[
        "state",
        "program"
    ],
    "sg:website":"www.dot.state.az.us",
    "wof:name":"Transportation Department",
    "wof:placetype":"venue"
},
  "geometry": {"coordinates":[-110.926628,32.230047],"type":"Point"}
}