{
  "type": "Feature",
  "properties": {
    "iso:country":"US",
    "sg:address":"2403 N Pebble Creek Pkwy",
    "sg:city":"Goodyear",
    "sg:classifiers":[
        {
            "category":"Personal",
            "subcategory":"Nail Salon",
            "type":"Services"
        }
    ],
    "sg:phone":"+1 623 535 1095",
    "sg:postcode":"85338",
    "sg:province":"AZ",
    "wof:name":"Pretty Nails & Spa by BN",
    "wof:placetype":"venue"
},
  "geometry": {"coordinates":[-112.392592,33.47903],"type":"Point"}
}