{
  "type": "Feature",
  "properties": {
    "iso:country":"US",
    "sg:address":"1118 E Baseline Rd",
    "sg:city":"Tempe",
    "sg:classifiers":[
        {
            "category":"Restaurant",
            "type":"Food & Drink"
        }
    ],
    "sg:menulink":"http://www.allmenus.com/az/phoenix/110851-quiznos-sub/menu/",
    "sg:phone":"+1 480 345 2040",
    "sg:postcode":"85283",
    "sg:province":"AZ",
    "sg:tags":[
        "wrap",
        "american",
        "sandwich"
    ],
    "wof:name":"Quiznos Sub",
    "wof:placetype":"venue"
},
  "geometry": {"coordinates":[-111.92223300000001,33.378314],"type":"Point"}
}