{
  "type": "Feature",
  "properties": {
    "iso:country":"US",
    "sg:address":"1004 W Congress St",
    "sg:city":"Tucson",
    "sg:classifiers":[
        {
            "category":"Personal",
            "subcategory":"Beauty Salon",
            "type":"Services"
        }
    ],
    "sg:phone":"+1 520 294 2871",
    "sg:postcode":"85745",
    "sg:province":"AZ",
    "wof:name":"Nortorious Salon",
    "wof:placetype":"venue"
},
  "geometry": {"coordinates":[-110.989697,32.219865],"type":"Point"}
}