{
  "type": "Feature",
  "properties": {
    "addr:full":"1004 W Congress St Tucson AZ 85745",
    "addr:housenumber":"1004",
    "addr:postcode":"85745",
    "addr:street":"W Congress St",
    "iso:country":"US",
    "sg:address":"1004 W Congress St",
    "sg:city":"Tucson",
    "sg:classifiers":[
        {
            "category":"Personal",
            "subcategory":"Beauty Salon",
            "type":"Services"
        }
    ],
    "sg:phone":"+1 520 294 2871",
    "sg:postcode":"85745",
    "sg:province":"AZ",
    "wof:name":"Nortorious Salon",
    "wof:placetype":"venue"
},
  "geometry": {"coordinates":[-110.98969700000001,32.219865],"type":"Point"}
}