{
  "type": "Feature",
  "properties": {
    "iso:country":"US",
    "sg:address":"15422 N 99th Ave",
    "sg:city":"Sun City",
    "sg:classifiers":[
        {
            "category":"Autos & Motor Vehicles",
            "subcategory":"Automobile Sales",
            "type":"Retail Goods"
        }
    ],
    "sg:phone":"+1 623 933 3888",
    "sg:postcode":"85351",
    "sg:province":"AZ",
    "sg:tags":[
        "car",
        "golf"
    ],
    "wof:name":"Jacar Corp",
    "wof:placetype":"venue"
},
  "geometry": {"coordinates":[-112.269959,33.624479],"type":"Point"}
}