{
  "type": "Feature",
  "properties": {
    "addr:full":"517 W 17th St Tempe AZ 85281",
    "addr:housenumber":"517",
    "addr:postcode":"85281",
    "addr:street":"W 17Th St",
    "iso:country":"US",
    "sg:address":"517 W 17th St",
    "sg:city":"Tempe",
    "sg:classifiers":[
        {
            "category":"Wholesale",
            "subcategory":"Electrical",
            "type":"Manufacturing & Wholesale Goods"
        }
    ],
    "sg:phone":"+1 480 966 5098",
    "sg:postcode":"85281",
    "sg:province":"AZ",
    "sg:tags":[
        "equipment",
        "lighting",
        "system"
    ],
    "sg:website":"www.platinumlighting.com",
    "wof:name":"Platinum Lighting Inc",
    "wof:placetype":"venue"
},
  "geometry": {"coordinates":[-111.945699,33.410945],"type":"Point"}
}