{
  "type": "Feature",
  "properties": {
    "addr:full":"1656 W Tierra Buena Ln Phoenix AZ 85023",
    "addr:housenumber":"1656",
    "addr:postcode":"85023",
    "addr:street":"W Tierra Buena Ln",
    "iso:country":"US",
    "sg:address":"1656 W Tierra Buena Ln",
    "sg:city":"Phoenix",
    "sg:classifiers":[
        {
            "category":"Real Estate",
            "subcategory":"Real Estate Operator",
            "type":"Services"
        }
    ],
    "sg:phone":"+1 602 942 4500",
    "sg:postcode":"85023",
    "sg:province":"AZ",
    "sg:tags":[
        "mfg",
        "mobile",
        "tr",
        "site",
        "home",
        "trailer"
    ],
    "wof:name":"Turf Paradise Travel Trlr Pk",
    "wof:placetype":"venue"
},
  "geometry": {"coordinates":[-112.094972,33.629345],"type":"Point"}
}