{
  "type": "Feature",
  "properties": {
    "iso:country":"US",
    "sg:address":"7512 N la Cholla Blvd",
    "sg:city":"Tucson",
    "sg:classifiers":[
        {
            "category":"Insurance",
            "subcategory":"Hazard Insurance",
            "type":"Services"
        },
        {
            "category":"Insurance",
            "subcategory":"Insurance Agent",
            "type":"Services"
        },
        {
            "category":"Insurance",
            "subcategory":"Life Insurance",
            "type":"Services"
        },
        {
            "category":"Insurance",
            "subcategory":"Title Insurance",
            "type":"Services"
        }
    ],
    "sg:phone":"+1 520 744 5858",
    "sg:postcode":"85741",
    "sg:province":"AZ",
    "sg:tags":[
        "property",
        "casualty",
        "homeowner"
    ],
    "sg:website":"http://www.amfam.com/agentlocator/GHARRIS1?sourceid=yp9",
    "wof:name":"American Family Insurance- Grant Harris",
    "wof:placetype":"venue"
},
  "geometry": {"coordinates":[-111.012679,32.342992],"type":"Point"}
}