{
  "type": "Feature",
  "properties": {
    "iso:country":"US",
    "sg:address":"16436 N 38th St",
    "sg:city":"Phoenix",
    "sg:classifiers":[
        {
            "category":"Building & Trades",
            "subcategory":"Construction",
            "type":"Services"
        }
    ],
    "sg:phone":"+1 602 788 8220",
    "sg:postcode":"85032",
    "sg:province":"AZ",
    "sg:tags":[
        "pipe",
        "line",
        "contractor"
    ],
    "wof:name":"Performance Underground LLC",
    "wof:placetype":"venue"
},
  "geometry": {"coordinates":[-112.000531,33.63602],"type":"Point"}
}