{
  "type": "Feature",
  "properties": {
    "iso:country":"US",
    "sg:address":"2202 Stockton Hill Rd",
    "sg:city":"Kingman",
    "sg:classifiers":[
        {
            "category":"Professional",
            "subcategory":"Engineering",
            "type":"Services"
        }
    ],
    "sg:phone":"+1 928 753 2627",
    "sg:postcode":"86401",
    "sg:province":"AZ",
    "sg:tags":[
        "engineer"
    ],
    "wof:name":"Mohave Engineering Assoc Inc",
    "wof:placetype":"venue"
},
  "geometry": {"coordinates":[-114.03443900000001,35.207521],"type":"Point"}
}