{
  "type": "Feature",
  "properties": {
    "iso:country":"US",
    "sg:address":"3614 E Southern Ave #105",
    "sg:city":"Mesa",
    "sg:classifiers":[
        {
            "category":"Personal",
            "subcategory":"Massage",
            "type":"Services"
        },
        {
            "category":"Health Services",
            "subcategory":"Clinic",
            "type":"Services"
        },
        {
            "category":"Health Services",
            "subcategory":"Health Practitioner",
            "type":"Services"
        },
        {
            "category":"Health Services",
            "subcategory":"Chiropractor",
            "type":"Services"
        }
    ],
    "sg:phone":"+1 480 779 3317",
    "sg:postcode":"85206",
    "sg:province":"AZ",
    "sg:tags":[
        "information",
        "sport",
        "chiropractic",
        "acupuncture",
        "nutritionist",
        "therapist",
        "therapy",
        "treatment",
        "medicine",
        "injury",
        "alternative",
        "referral",
        "physical"
    ],
    "sg:website":"http://www.yext.com/p/superpages/healthsource-of-central-mesa-mesa-arizona.html",
    "wof:name":"HealthSource of Central Mesa",
    "wof:placetype":"venue"
},
  "geometry": {"coordinates":[-111.753494,33.393712],"type":"Point"}
}