{
  "type": "Feature",
  "properties": {
    "iso:country":"US",
    "sg:address":"8909 W Quail Trl",
    "sg:city":"Queen Creek",
    "sg:classifiers":[
        {
            "category":"Building & Trades",
            "subcategory":"Plumbing",
            "type":"Services"
        }
    ],
    "sg:phone":"+1 480 987 3631",
    "sg:postcode":"85242",
    "sg:province":"AZ",
    "sg:tags":[
        "contractor"
    ],
    "wof:name":"Eba Plumbing LLC",
    "wof:placetype":"venue"
},
  "geometry": {"coordinates":[-111.660079,33.195482],"type":"Point"}
}