{
  "type": "Feature",
  "properties": {
    "iso:country":"US",
    "sg:address":"351 E Patagonia Hwy",
    "sg:city":"Nogales",
    "sg:classifiers":[
        {
            "category":"Wholesale",
            "subcategory":"Stationery",
            "type":"Manufacturing & Wholesale Goods"
        }
    ],
    "sg:phone":"+1 520 287 2542",
    "sg:postcode":"85621",
    "sg:province":"AZ",
    "sg:tags":[
        "supply"
    ],
    "wof:name":"Nogales Industrial Distrs",
    "wof:placetype":"venue"
},
  "geometry": {"coordinates":[-110.922062,31.352228],"type":"Point"}
}