{
  "type": "Feature",
  "properties": {
    "iso:country":"US",
    "sg:address":"1102 S 5th Ave",
    "sg:city":"Yuma",
    "sg:classifiers":[
        {
            "category":"Building & Trades",
            "subcategory":"Plumbing",
            "type":"Services"
        }
    ],
    "sg:phone":"+1 928 782 2990",
    "sg:postcode":"85364",
    "sg:province":"AZ",
    "sg:tags":[
        "contractor"
    ],
    "wof:name":"D C Plumbing",
    "wof:placetype":"venue"
},
  "geometry": {"coordinates":[-114.625923,32.706847],"type":"Point"}
}