{
  "type": "Feature",
  "properties": {
    "iso:country":"US",
    "sg:address":"1638 S Research Loop",
    "sg:city":"Tucson",
    "sg:classifiers":[
        {
            "category":"Wholesale",
            "subcategory":"Medical Equipment & Supplies",
            "type":"Manufacturing & Wholesale Goods"
        },
        {
            "category":"Manufacturing",
            "subcategory":"Tools & Machinery",
            "type":"Manufacturing & Wholesale Goods"
        }
    ],
    "sg:phone":"+1 520 733 9302",
    "sg:postcode":"85710",
    "sg:province":"AZ",
    "sg:tags":[
        "professional",
        "optical",
        "mfg"
    ],
    "sg:website":"www.compositemirrors.com",
    "wof:name":"Composite Mirror Applications",
    "wof:placetype":"venue"
},
  "geometry": {"coordinates":[-110.823752,32.201913],"type":"Point"}
}