{
  "type": "Feature",
  "properties": {
    "addr:full":"346 S Cll de Madrid Tucson AZ 85711",
    "addr:housenumber":"346",
    "addr:postcode":"85711",
    "addr:street":"S Cll De Madrid",
    "iso:country":"US",
    "sg:address":"346 S Cll de Madrid",
    "sg:city":"Tucson",
    "sg:classifiers":[
        {
            "category":"Professional",
            "subcategory":"Management & Consulting",
            "type":"Services"
        }
    ],
    "sg:phone":"+1 520 881 1053",
    "sg:postcode":"85711",
    "sg:province":"AZ",
    "sg:tags":[
        "marketing",
        "consultant"
    ],
    "wof:name":"RAR Productions",
    "wof:placetype":"venue"
},
  "geometry": {"coordinates":[-110.904045,32.216869],"type":"Point"}
}