{
  "type": "Feature",
  "properties": {
    "addr:full":"802 W Madison St Kingman AZ 86401",
    "addr:housenumber":"802",
    "addr:postcode":"86401",
    "addr:street":"W Madison St",
    "iso:country":"US",
    "sg:address":"802 W Madison St",
    "sg:city":"Kingman",
    "sg:classifiers":[
        {
            "category":"Professional",
            "type":"Services"
        }
    ],
    "sg:phone":"+1 928 753 7901",
    "sg:postcode":"86401",
    "sg:province":"AZ",
    "wof:name":"Michael Richards",
    "wof:placetype":"venue"
},
  "geometry": {"coordinates":[-114.04452499999999,35.184557],"type":"Point"}
}