{
  "type": "Feature",
  "properties": {
    "iso:country":"US",
    "sg:address":"6602 E Corrine Dr",
    "sg:city":"Scottsdale",
    "sg:classifiers":[
        {
            "category":"Building & Trades",
            "subcategory":"Construction",
            "type":"Services"
        }
    ],
    "sg:phone":"+1 480 905 3103",
    "sg:postcode":"85254",
    "sg:province":"AZ",
    "sg:tags":[
        "house"
    ],
    "wof:name":"Kals Remodeling",
    "wof:placetype":"venue"
},
  "geometry": {"coordinates":[-111.93599,33.601759],"type":"Point"}
}