{
  "type": "Feature",
  "properties": {
    "iso:country":"US",
    "sg:address":"440 N Alvernon Way # 105",
    "sg:city":"Tucson",
    "sg:classifiers":[
        {
            "category":"Shopping",
            "subcategory":"Optical Goods",
            "type":"Retail Goods"
        },
        {
            "category":"Health Services",
            "subcategory":"Optometrist",
            "type":"Services"
        },
        {
            "category":"Shopping",
            "subcategory":"Optician",
            "type":"Retail Goods"
        }
    ],
    "sg:phone":"+1 520 327 6211",
    "sg:postcode":"85711",
    "sg:province":"AZ",
    "sg:tags":[
        "lens",
        "repair",
        "contact"
    ],
    "sg:website":"http://www.alvernonoptical.com",
    "wof:name":"Alvernon Optical, Inc",
    "wof:placetype":"venue"
},
  "geometry": {"coordinates":[-110.909509,32.227394],"type":"Point"}
}