{
  "type": "Feature",
  "properties": {
    "addr:full":"4828 N 74th St Scottsdale AZ 85251",
    "addr:housenumber":"4828",
    "addr:postcode":"85251",
    "addr:street":"N 74Th St",
    "iso:country":"US",
    "sg:address":"4828 N 74th St",
    "sg:city":"Scottsdale",
    "sg:classifiers":[
        {
            "category":"Real Estate",
            "subcategory":"Real Estate Operator",
            "type":"Services"
        }
    ],
    "sg:phone":"+1 480 874 3357",
    "sg:postcode":"85251",
    "sg:province":"AZ",
    "sg:tags":[
        "building",
        "nonresidential"
    ],
    "wof:name":"Trevelayn Properties LLC",
    "wof:placetype":"venue"
},
  "geometry": {"coordinates":[-111.92225999999999,33.507864],"type":"Point"}
}