{
  "type": "Feature",
  "properties": {
    "iso:country":"US",
    "sg:address":"7850 N Silverbell Rd",
    "sg:city":"Tucson",
    "sg:classifiers":[
        {
            "category":"Wholesale",
            "subcategory":"Office Equipment",
            "type":"Manufacturing & Wholesale Goods"
        }
    ],
    "sg:phone":"+1 520 579 5993",
    "sg:postcode":"85743",
    "sg:province":"AZ",
    "sg:tags":[
        "machine",
        "duplicating",
        "copying"
    ],
    "wof:name":"Janco Copier & Svc",
    "wof:placetype":"venue"
},
  "geometry": {"coordinates":[-111.099945,32.34861],"type":"Point"}
}