{
  "type": "Feature",
  "properties": {
    "addr:full":"1696 N Higley Rd Gilbert AZ 85234",
    "addr:housenumber":"1696",
    "addr:postcode":"85234",
    "addr:street":"N Higley Rd",
    "iso:country":"US",
    "sg:address":"1696 N Higley Rd",
    "sg:city":"Gilbert",
    "sg:classifiers":[
        {
            "category":"Fast Food",
            "type":"Food & Drink"
        },
        {
            "category":"Restaurant",
            "type":"Food & Drink"
        },
        {
            "category":"Ice Cream",
            "type":"Food & Drink"
        }
    ],
    "sg:phone":"+1 480 924 6550",
    "sg:postcode":"85234",
    "sg:province":"AZ",
    "sg:tags":[
        "frozen",
        "dessert",
        "american",
        "take"
    ],
    "wof:name":"Dq Grill & Chill",
    "wof:placetype":"venue"
},
  "geometry": {"coordinates":[-111.722229,33.380831],"type":"Point"}
}