{
  "type": "Feature",
  "properties": {
    "iso:country":"US",
    "sg:address":"4002 W Indian School Rd",
    "sg:city":"Phoenix",
    "sg:classifiers":[
        {
            "category":"Professional",
            "type":"Services"
        },
        {
            "category":"Retail",
            "subcategory":"Storage",
            "type":"Services"
        },
        {
            "category":"Manufacturing",
            "subcategory":"Paper Products",
            "type":"Manufacturing & Wholesale Goods"
        }
    ],
    "sg:phone":"+1 602 272 0146",
    "sg:postcode":"85019",
    "sg:province":"AZ",
    "sg:tags":[
        "fiber",
        "self",
        "commercial",
        "packaging",
        "boxes-corrugated",
        "materials-wholesale",
        "household",
        "manufacturer"
    ],
    "sg:website":"http://www.a-aaakey.com",
    "wof:name":"A-Aaa Key Mini Storage",
    "wof:placetype":"venue"
},
  "geometry": {"coordinates":[-112.145173,33.494968],"type":"Point"}
}