{
  "type": "Feature",
  "properties": {
    "iso:country":"US",
    "sg:address":"8055 E Thomas Rd",
    "sg:city":"Scottsdale",
    "sg:classifiers":[
        {
            "category":"Real Estate",
            "subcategory":"Real Estate Agent",
            "type":"Services"
        }
    ],
    "sg:phone":"+1 480 947 3139",
    "sg:postcode":"85251",
    "sg:province":"AZ",
    "sg:tags":[
        "investment"
    ],
    "wof:name":"LA Moon Investments LLC",
    "wof:placetype":"venue"
},
  "geometry": {"coordinates":[-111.907704,33.48031],"type":"Point"}
}