{
  "type": "Feature",
  "properties": {
    "iso:country":"US",
    "sg:address":"12840 N 89th Pl",
    "sg:city":"Scottsdale",
    "sg:classifiers":[
        {
            "category":"Health Services",
            "subcategory":"Health Practitioner",
            "type":"Services"
        }
    ],
    "sg:phone":"+1 480 860 1269",
    "sg:postcode":"85260",
    "sg:province":"AZ",
    "sg:tags":[
        "home",
        "nurse",
        "registry"
    ],
    "wof:name":"B&R Nursing Inc",
    "wof:placetype":"venue"
},
  "geometry": {"coordinates":[-111.887573,33.602631],"type":"Point"}
}