{
  "type": "Feature",
  "properties": {
    "iso:country":"US",
    "sg:address":"3334 W Maryland Ave",
    "sg:city":"Phoenix",
    "sg:classifiers":[
        {
            "category":"Transit Center",
            "subcategory":"Freight",
            "type":"Transportation"
        }
    ],
    "sg:phone":"+1 602 332 0320",
    "sg:postcode":"85017",
    "sg:province":"AZ",
    "sg:tags":[
        "container",
        "broker"
    ],
    "wof:name":"Saray Trans",
    "wof:placetype":"venue"
},
  "geometry": {"coordinates":[-112.130674,33.531234],"type":"Point"}
}