{
  "type": "Feature",
  "properties": {
    "iso:country":"US",
    "sg:address":"5812 N 10th Ave",
    "sg:city":"Phoenix",
    "sg:classifiers":[
        {
            "category":"Retail",
            "subcategory":"Repair Shop",
            "type":"Services"
        },
        {
            "category":"Professional",
            "subcategory":"Detective & Security Services",
            "type":"Services"
        }
    ],
    "sg:phone":"+1 602 481 3718",
    "sg:postcode":"85013",
    "sg:province":"AZ",
    "sg:tags":[
        "skip",
        "tracing",
        "bail",
        "bond"
    ],
    "wof:name":"Ameri-Bail Bond",
    "wof:placetype":"venue"
},
  "geometry": {"coordinates":[-112.085551,33.521905],"type":"Point"}
}