{
  "type": "Feature",
  "properties": {
    "iso:country":"US",
    "sg:address":"1319 W Indian School Rd",
    "sg:city":"Phoenix",
    "sg:classifiers":[
        {
            "category":"Wholesale",
            "subcategory":"Non-durable Goods",
            "type":"Manufacturing & Wholesale Goods"
        }
    ],
    "sg:phone":"+1 602 241 1444",
    "sg:postcode":"85013",
    "sg:province":"AZ",
    "wof:name":"Healthy Future Wholesale",
    "wof:placetype":"venue"
},
  "geometry": {"coordinates":[-112.09114700000001,33.494894],"type":"Point"}
}