{
  "type": "Feature",
  "properties": {
    "iso:country":"US",
    "sg:address":"1550 W Van Buren St",
    "sg:city":"Phoenix",
    "sg:classifiers":[
        {
            "category":"Shopping",
            "subcategory":"Department Store",
            "type":"Retail Goods"
        },
        {
            "category":"Shopping",
            "subcategory":"Gifts & Souvenirs",
            "type":"Retail Goods"
        },
        {
            "category":"Shopping",
            "subcategory":"Discount & Variety Stores",
            "type":"Retail Goods"
        }
    ],
    "sg:phone":"+1 602 257 2285",
    "sg:postcode":"85007",
    "sg:province":"AZ",
    "sg:tags":[
        "shop"
    ],
    "wof:name":"Arizona Dollar Store",
    "wof:placetype":"venue"
},
  "geometry": {"coordinates":[-112.092934,33.451351],"type":"Point"}
}