{
  "type": "Feature",
  "properties": {
    "addr:full":"2935 S Dobson Rd Mesa AZ 85202",
    "addr:housenumber":"2935",
    "addr:postcode":"85202",
    "addr:street":"S Dobson Rd",
    "iso:country":"US",
    "sg:address":"2935 S Dobson Rd",
    "sg:city":"Mesa",
    "sg:classifiers":[
        {
            "category":"Restaurant",
            "type":"Food & Drink"
        }
    ],
    "sg:phone":"+1 480 491 7811",
    "sg:postcode":"85202",
    "sg:province":"AZ",
    "sg:tags":[
        "eating",
        "fast"
    ],
    "sg:website":"www.sonicdrivein.com",
    "wof:name":"Sonic Drive-In",
    "wof:placetype":"venue"
},
  "geometry": {"coordinates":[-111.87656200000001,33.361649],"type":"Point"}
}