{
  "type": "Feature",
  "properties": {
    "iso:country":"US",
    "sg:address":"7500 N Dreamy Draw Dr",
    "sg:city":"Phoenix",
    "sg:classifiers":[
        {
            "category":"Building & Trades",
            "subcategory":"Construction",
            "type":"Services"
        }
    ],
    "sg:phone":"+1 602 957 3936",
    "sg:postcode":"85020",
    "sg:province":"AZ",
    "sg:tags":[
        "consultant"
    ],
    "wof:name":"Oridian Construction Services",
    "wof:placetype":"venue"
},
  "geometry": {"coordinates":[-112.042503,33.546499],"type":"Point"}
}