{
  "type": "Feature",
  "properties": {
    "iso:country":"US",
    "sg:address":"98 E Fort Lowell Rd",
    "sg:city":"Tucson",
    "sg:classifiers":[
        {
            "category":"Building & Trades",
            "subcategory":"Construction",
            "type":"Services"
        }
    ],
    "sg:phone":"+1 520 623 5815",
    "sg:postcode":"85705",
    "sg:province":"AZ",
    "sg:tags":[
        "home",
        "general",
        "commercial",
        "contractor"
    ],
    "wof:name":"Wilford Construction Company",
    "wof:placetype":"venue"
},
  "geometry": {"coordinates":[-110.970843,32.264673],"type":"Point"}
}