{
  "type": "Feature",
  "properties": {
    "iso:country":"US",
    "sg:address":"4701 S Pla Dos Pajaritos",
    "sg:city":"Tucson",
    "sg:classifiers":[
        {
            "category":"Professional",
            "type":"Services"
        }
    ],
    "sg:phone":"+1 520 298 8829",
    "sg:postcode":"85730",
    "sg:province":"AZ",
    "sg:tags":[
        "establishment"
    ],
    "wof:name":"Scout Nationwide",
    "wof:placetype":"venue"
},
  "geometry": {"coordinates":[-110.750361,32.165642],"type":"Point"}
}