{
  "type": "Feature",
  "properties": {
    "iso:country":"US",
    "sg:address":"8219 W Leyva Ln",
    "sg:city":"Peoria",
    "sg:classifiers":[
        {
            "category":"Building & Trades",
            "subcategory":"Construction",
            "type":"Services"
        }
    ],
    "sg:phone":"+1 623 773 3460",
    "sg:postcode":"85345",
    "sg:province":"AZ",
    "sg:tags":[
        "plastering",
        "contractor"
    ],
    "wof:name":"New Sonoran Pool Plastering",
    "wof:placetype":"venue"
},
  "geometry": {"coordinates":[-112.236405,33.591291],"type":"Point"}
}