{
  "type": "Feature",
  "properties": {
    "addr:full":"6765 W Ina Rd Tucson AZ 85743",
    "addr:housenumber":"6765",
    "addr:postcode":"85743",
    "addr:street":"W Ina Rd",
    "iso:country":"US",
    "sg:address":"6765 W Ina Rd",
    "sg:city":"Tucson",
    "sg:phone":"+1 520 744 4424",
    "sg:postcode":"85743",
    "sg:province":"AZ",
    "sg:tags":[
        "partition"
    ],
    "sg:website":"www.modularhardware.com",
    "wof:name":"Modular Hardware",
    "wof:placetype":"venue"
},
  "geometry": {"coordinates":[-111.10636,32.337494],"type":"Point"}
}