{
  "type": "Feature",
  "properties": {
    "addr:full":"10661 N Oracle Rd Tucson AZ 85737",
    "addr:housenumber":"10661",
    "addr:postcode":"85737",
    "addr:street":"N Oracle Rd",
    "iso:country":"US",
    "sg:address":"10661 N Oracle Rd",
    "sg:city":"Tucson",
    "sg:classifiers":[
        {
            "category":"Food & Beverages",
            "subcategory":"Groceries & Convenience Stores",
            "type":"Retail Goods"
        }
    ],
    "sg:phone":"+1 520 742 6663",
    "sg:postcode":"85737",
    "sg:province":"AZ",
    "sg:tags":[
        "grocer"
    ],
    "sg:website":"www.frysfoodanddrug.com",
    "wof:name":"Fry's Food Store",
    "wof:placetype":"venue"
},
  "geometry": {"coordinates":[-110.958624,32.396986],"type":"Point"}
}