{
  "type": "Feature",
  "properties": {
    "addr:full":"4120 N Bitter Well Dr Prescott Valley AZ 86314",
    "addr:housenumber":"4120",
    "addr:postcode":"86314",
    "addr:street":"N Bitter Well Dr",
    "iso:country":"US",
    "sg:address":"4120 N Bitter Well Dr",
    "sg:city":"Prescott Valley",
    "sg:classifiers":[
        {
            "category":"Retail",
            "subcategory":"Repair Shop",
            "type":"Services"
        }
    ],
    "sg:phone":"+1 928 772 7626",
    "sg:postcode":"86314",
    "sg:province":"AZ",
    "sg:tags":[
        "hardwood",
        "mill"
    ],
    "wof:name":"RMS Custom Gunsmithing",
    "wof:placetype":"venue"
},
  "geometry": {"coordinates":[-112.307406,34.602125],"type":"Point"}
}