{
  "type": "Feature",
  "properties": {
    "addr:full":"2239 E Kleindale Rd Tucson AZ 85719",
    "addr:housenumber":"2239",
    "addr:postcode":"85719",
    "addr:street":"E Kleindale Rd",
    "iso:country":"US",
    "sg:address":"2239 E Kleindale Rd",
    "sg:city":"Tucson",
    "sg:classifiers":[
        {
            "category":"Wholesale",
            "subcategory":"Chemicals & Plastics",
            "type":"Manufacturing & Wholesale Goods"
        }
    ],
    "sg:phone":"+1 520 881 0169",
    "sg:postcode":"85719",
    "sg:province":"AZ",
    "sg:tags":[
        "carbon",
        "product"
    ],
    "wof:name":"Stoner & Stoner",
    "wof:placetype":"venue"
},
  "geometry": {"coordinates":[-110.938137,32.268656],"type":"Point"}
}