{
  "type": "Feature",
  "properties": {
    "iso:country":"US",
    "sg:address":"15615 N 65th St",
    "sg:city":"Scottsdale",
    "sg:classifiers":[
        {
            "category":"Banks & Credit Unions",
            "subcategory":"Bank",
            "type":"Services"
        }
    ],
    "sg:phone":"+1 480 699 2005",
    "sg:postcode":"85254",
    "sg:province":"AZ",
    "sg:tags":[
        "personal",
        "institution"
    ],
    "wof:name":"Key Equipment Finance",
    "wof:placetype":"venue"
},
  "geometry": {"coordinates":[-111.941273,33.628268],"type":"Point"}
}