{
  "type": "Feature",
  "properties": {
    "iso:country":"US",
    "sg:address":"4350 N 19th Ave",
    "sg:city":"Phoenix",
    "sg:classifiers":[
        {
            "category":"Food & Beverages",
            "subcategory":"Specialty",
            "type":"Retail Goods"
        },
        {
            "category":"Health Services",
            "subcategory":"Health Practitioner",
            "type":"Services"
        }
    ],
    "sg:phone":"+1 602 274 2592",
    "sg:postcode":"85015",
    "sg:province":"AZ",
    "sg:tags":[
        "acupuncture"
    ],
    "wof:name":"Arizona Acupuncture & Chinese",
    "wof:placetype":"venue"
},
  "geometry": {"coordinates":[-112.09997,33.500344],"type":"Point"}
}