{
  "type": "Feature",
  "properties": {
    "addr:full":"8405 E Vista Dr del Parque Scottsdale AZ 85250",
    "addr:housenumber":"8405",
    "addr:postcode":"85250",
    "addr:street":"E Vista Dr Del Parque",
    "iso:country":"US",
    "sg:address":"8405 E Vista Dr del Parque",
    "sg:city":"Scottsdale",
    "sg:classifiers":[
        {
            "category":"Sports & Exercise",
            "subcategory":"Gym",
            "type":"Entertainment"
        }
    ],
    "sg:phone":"+1 480 315 9601",
    "sg:postcode":"85250",
    "sg:province":"AZ",
    "sg:tags":[
        "instruction",
        "yoga"
    ],
    "wof:name":"Yoga Experiences",
    "wof:placetype":"venue"
},
  "geometry": {"coordinates":[-111.900121,33.513008],"type":"Point"}
}