{
  "type": "Feature",
  "properties": {
    "iso:country":"US",
    "sg:address":"20 S 48th Ave",
    "sg:city":"Phoenix",
    "sg:classifiers":[
        {
            "category":"Home & Garden",
            "subcategory":"Furniture",
            "type":"Retail Goods"
        },
        {
            "category":"Manufacturing",
            "subcategory":"Tools & Machinery",
            "type":"Manufacturing & Wholesale Goods"
        }
    ],
    "sg:phone":"+1 602 278 4704",
    "sg:postcode":"85043",
    "sg:province":"AZ",
    "sg:tags":[
        "company",
        "milling",
        "cabinet"
    ],
    "sg:website":"www.gcfrp.com",
    "wof:name":"Gaston Contracting",
    "wof:placetype":"venue"
},
  "geometry": {"coordinates":[-112.16296699999999,33.446923],"type":"Point"}
}