{
  "type": "Feature",
  "properties": {
    "addr:full":"1845 W Orange Grove Rd # 137 Tucson AZ 85704",
    "addr:housenumber":"1845",
    "addr:postcode":"85704",
    "addr:street":"W Orange Grove Rd # 137",
    "iso:country":"US",
    "sg:address":"1845 W Orange Grove Rd # 137",
    "sg:city":"Tucson",
    "sg:classifiers":[
        {
            "category":"Health Services",
            "subcategory":"Doctor",
            "type":"Services"
        }
    ],
    "sg:phone":"+1 520 544 0906",
    "sg:postcode":"85704",
    "sg:province":"AZ",
    "sg:tags":[
        "gynecology",
        "physician",
        "surgeon",
        "surgeons",
        "obstetrics"
    ],
    "wof:name":"Avalon Obstetrics & Gynecolgy",
    "wof:placetype":"venue"
},
  "geometry": {"coordinates":[-111.00615500000001,32.323151],"type":"Point"}
}