{
  "type": "Feature",
  "properties": {
    "iso:country":"US",
    "sg:address":"14362 N Frank Lloyd Wright Blvd",
    "sg:city":"Scottsdale",
    "sg:classifiers":[
        {
            "category":"Professional",
            "subcategory":"Lawyer & Legal Services",
            "type":"Services"
        }
    ],
    "sg:phone":"+1 480 477 6467",
    "sg:postcode":"85260",
    "sg:province":"AZ",
    "sg:tags":[
        "attorney",
        "practice"
    ],
    "wof:name":"Watkin Law Office",
    "wof:placetype":"venue"
},
  "geometry": {"coordinates":[-111.889416,33.629799],"type":"Point"}
}