{
  "type": "Feature",
  "properties": {
    "iso:country":"US",
    "sg:address":"1422 E Thornton Ave",
    "sg:city":"Gilbert",
    "sg:classifiers":[
        {
            "category":"Banks & Credit Unions",
            "subcategory":"Investment Brokerage",
            "type":"Services"
        }
    ],
    "sg:phone":"+1 480 295 1266",
    "sg:postcode":"85297",
    "sg:province":"AZ",
    "sg:tags":[
        "advisory"
    ],
    "wof:name":"Jkn Investments Inc",
    "wof:placetype":"venue"
},
  "geometry": {"coordinates":[-111.759415,33.263907],"type":"Point"}
}