{
  "type": "Feature",
  "properties": {
    "addr:full":"870 Riverview Dr Bullhead City AZ 86442",
    "addr:housenumber":"870",
    "addr:postcode":"86442",
    "addr:street":"Riverview Dr",
    "iso:country":"US",
    "sg:address":"870 Riverview Dr",
    "sg:city":"Bullhead City",
    "sg:classifiers":[
        {
            "category":"Building & Trades",
            "subcategory":"Construction",
            "type":"Services"
        }
    ],
    "sg:phone":"+1 928 763 6100",
    "sg:postcode":"86442",
    "sg:province":"AZ",
    "sg:tags":[
        "contractor"
    ],
    "wof:name":"Barnard Construction",
    "wof:placetype":"venue"
},
  "geometry": {"coordinates":[-114.618208,35.093358],"type":"Point"}
}