{
  "type": "Feature",
  "properties": {
    "iso:country":"US",
    "sg:address":"3051 S White Mountain Rd",
    "sg:city":"Show Low",
    "sg:classifiers":[
        {
            "category":"Shopping",
            "type":"Retail Goods"
        },
        {
            "category":"Shopping",
            "subcategory":"Books",
            "type":"Retail Goods"
        }
    ],
    "sg:phone":"+1 928 537 2166",
    "sg:postcode":"85901",
    "sg:province":"AZ",
    "sg:tags":[
        "religious"
    ],
    "wof:name":"Book Barn",
    "wof:placetype":"venue"
},
  "geometry": {"coordinates":[-110.029326,34.223626],"type":"Point"}
}