{
  "type": "Feature",
  "properties": {
    "iso:country":"US",
    "sg:address":"1935 Carpenter Ln",
    "sg:city":"Cottonwood",
    "sg:classifiers":[
        {
            "category":"Building & Trades",
            "subcategory":"Construction",
            "type":"Services"
        }
    ],
    "sg:phone":"+1 928 634 2125",
    "sg:postcode":"86326",
    "sg:province":"AZ",
    "sg:tags":[
        "floor",
        "laying",
        "contractor"
    ],
    "wof:name":"Designed Flooring Creations",
    "wof:placetype":"venue"
},
  "geometry": {"coordinates":[-112.00756199999999,34.705073],"type":"Point"}
}