{
  "type": "Feature",
  "properties": {
    "iso:country":"US",
    "sg:address":"7702 W Flower St",
    "sg:city":"Phoenix",
    "sg:classifiers":[
        {
            "category":"Real Estate",
            "subcategory":"Real Estate Services",
            "type":"Services"
        },
        {
            "category":"Building & Trades",
            "subcategory":"Cleaning & Sanitation",
            "type":"Services"
        }
    ],
    "sg:phone":"+1 623 849 2882",
    "sg:postcode":"85033",
    "sg:province":"AZ",
    "sg:tags":[
        "maintenance",
        "cleaners-interior"
    ],
    "wof:name":"Keith S Quality Maintenence",
    "wof:placetype":"venue"
},
  "geometry": {"coordinates":[-112.224176,33.485],"type":"Point"}
}