{
  "type": "Feature",
  "properties": {
    "addr:full":"99 Easy St Carefree AZ 85377",
    "addr:housenumber":"99",
    "addr:postcode":"az 85377",
    "addr:street":"Easy St",
    "iso:country":"US",
    "sg:address":"99 Easy St",
    "sg:city":"Carefree",
    "sg:classifiers":[
        {
            "category":"Restaurant",
            "type":"Food & Drink"
        }
    ],
    "sg:phone":"+1 480 575 0021",
    "sg:postcode":"85377",
    "sg:province":"AZ",
    "sg:website":"www.saguarogrille.com",
    "wof:name":"Saguaro Grille",
    "wof:placetype":"venue"
},
  "geometry": {"coordinates":[-111.923557,33.825088],"type":"Point"}
}