{
  "type": "Feature",
  "properties": {
    "iso:country":"US",
    "sg:address":"16402 N 31st St Unit 134",
    "sg:city":"Phoenix",
    "sg:classifiers":[
        {
            "category":"Food & Beverages",
            "subcategory":"Specialty",
            "type":"Retail Goods"
        }
    ],
    "sg:phone":"+1 602 249 9402",
    "sg:postcode":"85032",
    "sg:province":"AZ",
    "sg:tags":[
        "sauce",
        "condiment"
    ],
    "wof:name":"4 Brothers Bbq Sauce & More",
    "wof:placetype":"venue"
},
  "geometry": {"coordinates":[-112.01561700000001,33.635338],"type":"Point"}
}