{
  "type": "Feature",
  "properties": {
    "iso:country":"US",
    "sg:address":"1207 E Loyola Dr",
    "sg:city":"Tempe",
    "sg:classifiers":[
        {
            "category":"Professional",
            "subcategory":"Business Services",
            "type":"Services"
        }
    ],
    "sg:phone":"+1 480 897 8895",
    "sg:postcode":"85282",
    "sg:province":"AZ",
    "sg:tags":[
        "consultant",
        "coach"
    ],
    "wof:name":"K2 Consulting",
    "wof:placetype":"venue"
},
  "geometry": {"coordinates":[-111.919939,33.39613],"type":"Point"}
}