{
  "type": "Feature",
  "properties": {
    "addr:full":"21257 N Black Canyon Hwy Phoenix AZ 85027",
    "addr:housenumber":"21257",
    "addr:postcode":"85027",
    "addr:street":"N Black Canyon Hwy",
    "iso:country":"US",
    "sg:address":"21257 N Black Canyon Hwy",
    "sg:city":"Phoenix",
    "sg:classifiers":[
        {
            "category":"Building & Trades",
            "subcategory":"Construction",
            "type":"Services"
        }
    ],
    "sg:phone":"+1 623 582 5104",
    "sg:postcode":"85027",
    "sg:province":"AZ",
    "sg:tags":[
        "concrete",
        "lathe",
        "stucco",
        "contractor"
    ],
    "wof:name":"DVC Construction Company",
    "wof:placetype":"venue"
},
  "geometry": {"coordinates":[-112.11216899999999,33.678604],"type":"Point"}
}