{
  "type": "Feature",
  "properties": {
    "addr:full":"722 W Taylor St Apt 14 Phoenix AZ 85007",
    "addr:housenumber":"722;14",
    "addr:postcode":"85007",
    "addr:street":"W Taylor St Apt",
    "iso:country":"US",
    "sg:address":"722 W Taylor St Apt 14",
    "sg:city":"Phoenix",
    "sg:classifiers":[
        {
            "category":"Real Estate",
            "subcategory":"Real Estate Operator",
            "type":"Services"
        }
    ],
    "sg:phone":"+1 602 258 0661",
    "sg:postcode":"85007",
    "sg:province":"AZ",
    "sg:tags":[
        "apartment"
    ],
    "wof:name":"Fillmore Courtyard Apts",
    "wof:placetype":"venue"
},
  "geometry": {"coordinates":[-112.083054,33.45422],"type":"Point"}
}