{
  "type": "Feature",
  "properties": {
    "iso:country":"US",
    "sg:address":"405 W Congress St",
    "sg:city":"Tucson",
    "sg:classifiers":[
        {
            "category":"Government",
            "subcategory":"Office",
            "type":"Public Place"
        }
    ],
    "sg:phone":"+1 520 205 4600",
    "sg:postcode":"85701",
    "sg:province":"AZ",
    "wof:name":"Honorable Nancy F Fiora",
    "wof:placetype":"venue"
},
  "geometry": {"coordinates":[-110.978478,32.221003],"type":"Point"}
}