{
  "type": "Feature",
  "properties": {
    "iso:country":"US",
    "sg:address":"17034 S 54th St",
    "sg:city":"Chandler",
    "sg:classifiers":[
        {
            "category":"Manufacturing",
            "subcategory":"Toys & Sporting Goods",
            "type":"Manufacturing & Wholesale Goods"
        },
        {
            "category":"Utilities",
            "subcategory":"Natural Gas",
            "type":"Services"
        },
        {
            "category":"Organizations",
            "subcategory":"Religious Organization",
            "type":"Services"
        }
    ],
    "sg:phone":"+1 480 948 0090",
    "sg:postcode":"85226",
    "sg:province":"AZ",
    "sg:tags":[
        "fireworks-wholesale",
        "firework",
        "fireworks-public",
        "display",
        "manufacturer"
    ],
    "sg:website":"http://www.fireworksaz.com",
    "wof:name":"Fireworks Products",
    "wof:placetype":"venue"
},
  "geometry": {"coordinates":[-111.967713,33.291287],"type":"Point"}
}