{
  "type": "Feature",
  "properties": {
    "addr:full":"400 N 5th St Phoenix AZ 85004",
    "addr:housenumber":"400",
    "addr:postcode":"85004",
    "addr:street":"N 5Th St",
    "iso:country":"US",
    "sg:address":"400 N 5th St",
    "sg:city":"Phoenix",
    "sg:classifiers":[
        {
            "category":"Professional",
            "subcategory":"Detective & Security Services",
            "type":"Services"
        }
    ],
    "sg:phone":"+1 602 250 4581",
    "sg:postcode":"85004",
    "sg:province":"AZ",
    "sg:tags":[
        "information",
        "bureau"
    ],
    "wof:name":"Global Technical Services, Inc.",
    "wof:placetype":"venue"
},
  "geometry": {"coordinates":[-112.06745100000001,33.45145],"type":"Point"}
}