{
  "type": "Feature",
  "properties": {
    "iso:country":"US",
    "sg:address":"1520 S Melpomene Way",
    "sg:city":"Tucson",
    "sg:classifiers":[
        {
            "category":"Organizations",
            "subcategory":"Non-profit Organization",
            "type":"Services"
        }
    ],
    "sg:phone":"+1 520 979 9966",
    "sg:postcode":"85748",
    "sg:province":"AZ",
    "wof:name":"Team Tucson",
    "wof:placetype":"venue"
},
  "geometry": {"coordinates":[-110.755664,32.206313],"type":"Point"}
}