{
  "type": "Feature",
  "properties": {
    "addr:full":"324 W Goldfinch Way Chandler AZ 85286",
    "addr:housenumber":"324",
    "addr:postcode":"85286",
    "addr:street":"W Goldfinch Way",
    "iso:country":"US",
    "sg:address":"324 W Goldfinch Way",
    "sg:city":"Chandler",
    "sg:classifiers":[
        {
            "category":"Professional",
            "type":"Services"
        }
    ],
    "sg:phone":"+1 480 248 7890",
    "sg:postcode":"85286",
    "sg:province":"AZ",
    "sg:tags":[
        "relocation"
    ],
    "sg:website":"http://www.nationalsuites.com",
    "wof:name":"National Corporate Suites, Inc.",
    "wof:placetype":"venue"
},
  "geometry": {"coordinates":[-111.846743,33.26637],"type":"Point"}
}