{
  "type": "Feature",
  "properties": {
    "iso:country":"US",
    "sg:address":"7547 N 31st Dr",
    "sg:city":"Phoenix",
    "sg:classifiers":[
        {
            "category":"Manufacturing",
            "subcategory":"Printing",
            "type":"Manufacturing & Wholesale Goods"
        }
    ],
    "sg:phone":"+1 602 432 9519",
    "sg:postcode":"85051",
    "sg:province":"AZ",
    "sg:tags":[
        "book"
    ],
    "wof:name":"Music Voice",
    "wof:placetype":"venue"
},
  "geometry": {"coordinates":[-112.126786,33.547243],"type":"Point"}
}