{
  "type": "Feature",
  "properties": {
    "addr:full":"19205 N 83rd Ave Peoria AZ 85382",
    "addr:housenumber":"19205",
    "addr:postcode":"85382",
    "addr:street":"N 83Rd Ave",
    "iso:country":"US",
    "sg:address":"19205 N 83rd Ave",
    "sg:city":"Peoria",
    "sg:classifiers":[
        {
            "category":"Shopping",
            "type":"Retail Goods"
        }
    ],
    "sg:phone":"+1 623 376 7555",
    "sg:postcode":"85382",
    "sg:province":"AZ",
    "sg:tags":[
        "spa",
        "hot",
        "tub"
    ],
    "wof:name":"Spa Man Spas",
    "wof:placetype":"venue"
},
  "geometry": {"coordinates":[-112.237657,33.654046],"type":"Point"}
}