{
  "type": "Feature",
  "properties": {
    "addr:full":"3871 N Commerce Dr Tucson AZ 85705",
    "addr:housenumber":"3871",
    "addr:postcode":"85705",
    "addr:street":"N Commerce Dr",
    "iso:country":"US",
    "sg:address":"3871 N Commerce Dr",
    "sg:city":"Tucson",
    "sg:classifiers":[
        {
            "category":"Communications",
            "subcategory":"Radio Station",
            "type":"Services"
        }
    ],
    "sg:phone":"+1 520 622 6711",
    "sg:postcode":"85705",
    "sg:province":"AZ",
    "wof:name":"Ktkt Radio",
    "wof:placetype":"venue"
},
  "geometry": {"coordinates":[-111.017291,32.278127],"type":"Point"}
}