{
  "type": "Feature",
  "properties": {
    "addr:full":"162 W Boxelder Pl Suite 3 Chandler AZ 85225",
    "addr:housenumber":"162",
    "addr:postcode":"85225",
    "addr:street":"W Boxelder Pl Suite 3",
    "iso:country":"US",
    "sg:address":"162 W Boxelder Pl Suite 3",
    "sg:city":"Chandler",
    "sg:classifiers":[
        {
            "category":"Building & Trades",
            "subcategory":"Pest Control",
            "type":"Services"
        }
    ],
    "sg:phone":"+1 480 558 8555",
    "sg:postcode":"85225",
    "sg:province":"AZ",
    "sg:website":"http://www.preventivepestcontrol.com",
    "wof:name":"Preventive Pest Control",
    "wof:placetype":"venue"
},
  "geometry": {"coordinates":[-111.844002,33.355674],"type":"Point"}
}