{
  "type": "Feature",
  "properties": {
    "iso:country":"US",
    "sg:address":"1256 W Chandler Blvd",
    "sg:city":"Chandler",
    "sg:classifiers":[
        {
            "category":"Professional",
            "subcategory":"Business Services",
            "type":"Services"
        }
    ],
    "sg:phone":"+1 480 855 0807",
    "sg:postcode":"85224",
    "sg:province":"AZ",
    "sg:tags":[
        "appraiser"
    ],
    "sg:website":"www.pvappraisals.net",
    "wof:name":"P V Appraisals",
    "wof:placetype":"venue"
},
  "geometry": {"coordinates":[-111.86479300000001,33.306111],"type":"Point"}
}