{
  "type": "Feature",
  "properties": {
    "iso:country":"US",
    "sg:address":"15231 N 87th St Ste 115A",
    "sg:city":"Scottsdale",
    "sg:classifiers":[
        {
            "category":"Manufacturing",
            "subcategory":"Rubber & Plastics",
            "type":"Manufacturing & Wholesale Goods"
        },
        {
            "category":"Shopping",
            "type":"Retail Goods"
        }
    ],
    "sg:phone":"+1 480 922 1600",
    "sg:postcode":"85260",
    "sg:province":"AZ",
    "sg:tags":[
        "equipment",
        "clothing",
        "safety",
        "clothing-wholesale",
        "manufacturer"
    ],
    "wof:name":"Meaz Trading Company",
    "wof:placetype":"venue"
},
  "geometry": {"coordinates":[-111.892095,33.625441],"type":"Point"}
}