{
  "type": "Feature",
  "properties": {
    "addr:full":"1100 N Estrella Pkwy Goodyear AZ 85338",
    "addr:housenumber":"1100",
    "addr:postcode":"85338",
    "addr:street":"N Estrella Pkwy",
    "iso:country":"US",
    "sg:address":"1100 N Estrella Pkwy",
    "sg:city":"Goodyear",
    "sg:classifiers":[
        {
            "category":"Banks & Credit Unions",
            "subcategory":"Bank",
            "type":"Services"
        }
    ],
    "sg:phone":"+1 623 433 7000",
    "sg:postcode":"85338",
    "sg:province":"AZ",
    "wof:name":"Desert Schools Federal Cu",
    "wof:placetype":"venue"
},
  "geometry": {"coordinates":[-112.39255900000001,33.458194],"type":"Point"}
}