{
  "type": "Feature",
  "properties": {
    "iso:country":"US",
    "sg:address":"1314 W 11th St",
    "sg:city":"Parker",
    "sg:classifiers":[
        {
            "category":"Government",
            "subcategory":"Police Station",
            "type":"Public Place"
        },
        {
            "category":"Government",
            "subcategory":"Office",
            "type":"Public Place"
        }
    ],
    "sg:phone":"+1 928 669 9265",
    "sg:postcode":"85344",
    "sg:province":"AZ",
    "sg:tags":[
        "enforcement",
        "agencies-government",
        "village",
        "department",
        "township",
        "law",
        "government-city"
    ],
    "sg:website":"http://www.ci.parker.az.us",
    "wof:name":"Town Of Parker",
    "wof:placetype":"venue"
},
  "geometry": {"coordinates":[-114.293651,34.147209],"type":"Point"}
}