{
  "type": "Feature",
  "properties": {
    "addr:full":"3410 E University Dr Phoenix AZ 85034",
    "addr:housenumber":"3410",
    "addr:postcode":"85034",
    "addr:street":"E University Dr",
    "iso:country":"US",
    "sg:address":"3410 E University Dr",
    "sg:city":"Phoenix",
    "sg:classifiers":[
        {
            "category":"Building & Trades",
            "subcategory":"Construction",
            "type":"Services"
        }
    ],
    "sg:phone":"+1 602 437 2012",
    "sg:postcode":"85034",
    "sg:province":"AZ",
    "sg:tags":[
        "general",
        "contractor"
    ],
    "wof:name":"Madison Square Development",
    "wof:placetype":"venue"
},
  "geometry": {"coordinates":[-112.008503,33.415782],"type":"Point"}
}