{
  "type": "Feature",
  "properties": {
    "iso:country":"US",
    "sg:address":"326 N Main St Ste A",
    "sg:city":"Snowflake",
    "sg:classifiers":[
        {
            "category":"Health Services",
            "subcategory":"Clinic",
            "type":"Services"
        },
        {
            "category":"Health Services",
            "subcategory":"Health Practitioner",
            "type":"Services"
        }
    ],
    "sg:phone":"+1 928 536 3309",
    "sg:postcode":"85937",
    "sg:province":"AZ",
    "sg:tags":[
        "occupational",
        "therapist",
        "therapy",
        "physical"
    ],
    "wof:name":"Snowflake Healing Center",
    "wof:placetype":"venue"
},
  "geometry": {"coordinates":[-110.090937,34.468941],"type":"Point"}
}