{
  "type": "Feature",
  "properties": {
    "addr:full":"80 W State Ave Phoenix AZ 85021",
    "addr:housenumber":"80",
    "addr:postcode":"85021",
    "addr:street":"W State Ave",
    "iso:country":"US",
    "sg:address":"80 W State Ave",
    "sg:city":"Phoenix",
    "sg:classifiers":[
        {
            "category":"Professional",
            "subcategory":"Management & Consulting",
            "type":"Services"
        }
    ],
    "sg:phone":"+1 602 906 1905",
    "sg:postcode":"85021",
    "sg:province":"AZ",
    "sg:tags":[
        "consultant",
        "business"
    ],
    "wof:name":"O'Malley Group",
    "wof:placetype":"venue"
},
  "geometry": {"coordinates":[-112.076959,33.544304],"type":"Point"}
}