{
  "type": "Feature",
  "properties": {
    "addr:full":"13 N San Francisco St Flagstaff AZ 86001",
    "addr:housenumber":"13",
    "addr:postcode":"86001",
    "addr:street":"N San Francisco St",
    "iso:country":"US",
    "sg:address":"13 N San Francisco St",
    "sg:city":"Flagstaff",
    "sg:classifiers":[
        {
            "category":"Professional",
            "subcategory":"Accounting & Tax Preparation",
            "type":"Services"
        }
    ],
    "sg:phone":"+1 928 773 1465",
    "sg:postcode":"86001",
    "sg:province":"AZ",
    "sg:tags":[
        "accountant"
    ],
    "wof:name":"Don Borzilleri CPA",
    "wof:placetype":"venue"
},
  "geometry": {"coordinates":[-111.64773099999999,35.198035],"type":"Point"}
}