{
  "type": "Feature",
  "properties": {
    "iso:country":"US",
    "sg:address":"4801 E Towner St",
    "sg:city":"Tucson",
    "sg:classifiers":[
        {
            "category":"Building & Trades",
            "subcategory":"Plumbing",
            "type":"Services"
        }
    ],
    "sg:phone":"+1 520 326 8019",
    "sg:postcode":"85712",
    "sg:province":"AZ",
    "sg:tags":[
        "plumbing",
        "contractor"
    ],
    "wof:name":"Mountain States Plumbing",
    "wof:placetype":"venue"
},
  "geometry": {"coordinates":[-110.890296,32.255415],"type":"Point"}
}