{
  "type": "Feature",
  "properties": {
    "iso:country":"US",
    "sg:address":"24820 N 16th Ave",
    "sg:city":"Phoenix",
    "sg:classifiers":[
        {
            "category":"Professional",
            "subcategory":"Advertising",
            "type":"Services"
        }
    ],
    "sg:phone":"+1 623 869 9656",
    "sg:postcode":"85085",
    "sg:province":"AZ",
    "sg:tags":[
        "mailing",
        "list"
    ],
    "wof:name":"Global Lists Inc",
    "wof:placetype":"venue"
},
  "geometry": {"coordinates":[-112.093559,33.710825],"type":"Point"}
}