{
  "type": "Feature",
  "properties": {
    "iso:country":"US",
    "sg:address":"7434 S Rooks Rd",
    "sg:city":"Buckeye",
    "sg:classifiers":[
        {
            "category":"Professional",
            "subcategory":"Computer Services",
            "type":"Services"
        }
    ],
    "sg:phone":"+1 623 386 4310",
    "sg:postcode":"85326",
    "sg:province":"AZ",
    "wof:name":"AZ Kustom Computers",
    "wof:placetype":"venue"
},
  "geometry": {"coordinates":[-112.607931,33.379407],"type":"Point"}
}