{
  "type": "Feature",
  "properties": {
    "iso:country":"US",
    "sg:address":"2730 S Val Vista Dr",
    "sg:city":"Gilbert",
    "sg:classifiers":[
        {
            "category":"Personal",
            "subcategory":"Massage",
            "type":"Services"
        },
        {
            "category":"Health Services",
            "subcategory":"Clinic",
            "type":"Services"
        },
        {
            "category":"Health Services",
            "subcategory":"Health Practitioner",
            "type":"Services"
        },
        {
            "category":"Health Services",
            "subcategory":"Chiropractor",
            "type":"Services"
        }
    ],
    "sg:phone":"+1 480 320 4894",
    "sg:postcode":"85295",
    "sg:province":"AZ",
    "sg:tags":[
        "chiropractic",
        "acupuncture",
        "therapist",
        "therapy",
        "medicine",
        "alternative",
        "physical"
    ],
    "sg:website":"http://www.yext.com/p/superpages/all-star-health-gilbert-arizona.html",
    "wof:name":"All Star Health- Gilbert",
    "wof:placetype":"venue"
},
  "geometry": {"coordinates":[-111.755659,33.300639],"type":"Point"}
}