{
  "type": "Feature",
  "properties": {
    "addr:full":"1202 N 54th Ave Ste 103 Phoenix AZ 85043",
    "addr:housenumber":"1202",
    "addr:postcode":"85043",
    "addr:street":"N 54Th Ave Ste 103",
    "iso:country":"US",
    "sg:address":"1202 N 54th Ave Ste 103",
    "sg:city":"Phoenix",
    "sg:phone":"+1 602 353 0970",
    "sg:postcode":"85043",
    "sg:province":"AZ",
    "wof:name":"Maverick Petroleum Svc Inc",
    "wof:placetype":"venue"
},
  "geometry": {"coordinates":[-112.175048,33.460529],"type":"Point"}
}