{
  "type": "Feature",
  "properties": {
    "addr:full":"1333 E 10th St Tucson AZ 85719",
    "addr:housenumber":"1333",
    "addr:postcode":"85719",
    "addr:street":"E 10Th St",
    "iso:country":"US",
    "sg:address":"1333 E 10th St",
    "sg:city":"Tucson",
    "sg:classifiers":[
        {
            "category":"Education",
            "subcategory":"School",
            "type":"Public Place"
        }
    ],
    "sg:phone":"+1 520 882 8826",
    "sg:postcode":"85719",
    "sg:province":"AZ",
    "wof:name":"Ha-San Preparatory & Ldrshp",
    "wof:placetype":"venue"
},
  "geometry": {"coordinates":[-110.95140000000001,32.222617],"type":"Point"}
}