{
  "type": "Feature",
  "properties": {
    "addr:full":"7415 E Random Ridge Dr Tucson AZ 85710",
    "addr:housenumber":"7415",
    "addr:postcode":"85710",
    "addr:street":"E Random Ridge Dr",
    "iso:country":"US",
    "sg:address":"7415 E Random Ridge Dr",
    "sg:city":"Tucson",
    "sg:classifiers":[
        {
            "category":"Place Of Worship",
            "type":"Public Place"
        }
    ],
    "sg:phone":"+1 520 886 5968",
    "sg:postcode":"85710",
    "sg:province":"AZ",
    "sg:tags":[
        "church"
    ],
    "wof:name":"Iglesia De Cristo De Tucson",
    "wof:placetype":"venue"
},
  "geometry": {"coordinates":[-110.834294,32.19705],"type":"Point"}
}