{
  "type": "Feature",
  "properties": {
    "iso:country":"US",
    "sg:address":"450 W Cll Concordia",
    "sg:city":"Oro Valley",
    "sg:classifiers":[
        {
            "category":"Building & Trades",
            "subcategory":"Construction",
            "type":"Services"
        }
    ],
    "sg:phone":"+1 520 742 2474",
    "sg:postcode":"85704",
    "sg:province":"AZ",
    "sg:tags":[
        "masonry",
        "contractor"
    ],
    "wof:name":"D Tellez Masonry",
    "wof:placetype":"venue"
},
  "geometry": {"coordinates":[-110.976863,32.373684],"type":"Point"}
}