{
  "type": "Feature",
  "properties": {
    "iso:country":"US",
    "sg:address":"6867 N Oracle Rd",
    "sg:city":"Tucson",
    "sg:classifiers":[
        {
            "category":"Professional",
            "type":"Services"
        }
    ],
    "sg:phone":"+1 520 219 1856",
    "sg:postcode":"85704",
    "sg:province":"AZ",
    "sg:tags":[
        "establishment"
    ],
    "wof:name":"Capri Inc",
    "wof:placetype":"venue"
},
  "geometry": {"coordinates":[-110.976939,32.331186],"type":"Point"}
}