{
  "type": "Feature",
  "properties": {
    "addr:full":"4012 E Main St Mesa AZ 85205",
    "addr:housenumber":"4012",
    "addr:postcode":"85205",
    "addr:street":"E Main St",
    "iso:country":"US",
    "sg:address":"4012 E Main St",
    "sg:city":"Mesa",
    "sg:classifiers":[
        {
            "category":"Home & Garden",
            "subcategory":"Furniture",
            "type":"Retail Goods"
        }
    ],
    "sg:phone":"+1 480 641 0256",
    "sg:postcode":"85205",
    "sg:province":"AZ",
    "wof:name":"At Ease Furniture",
    "wof:placetype":"venue"
},
  "geometry": {"coordinates":[-111.743921,33.41555],"type":"Point"}
}