{
  "type": "Feature",
  "properties": {
    "addr:full":"7463 E Monte Ave Mesa AZ 85209",
    "addr:housenumber":"7463",
    "addr:postcode":"85209",
    "addr:street":"E Monte Ave",
    "iso:country":"US",
    "sg:address":"7463 E Monte Ave",
    "sg:city":"Mesa",
    "sg:classifiers":[
        {
            "category":"Utilities",
            "type":"Services"
        }
    ],
    "sg:phone":"+1 480 963 7027",
    "sg:postcode":"85209",
    "sg:province":"AZ",
    "sg:tags":[
        "sanitary"
    ],
    "wof:name":"Jr Sweeping Service",
    "wof:placetype":"venue"
},
  "geometry": {"coordinates":[-111.672595,33.370187],"type":"Point"}
}