{
  "type": "Feature",
  "properties": {
    "iso:country":"US",
    "sg:address":"700 N US Hwy 89",
    "sg:city":"Chino Valley",
    "sg:classifiers":[
        {
            "category":"Organizations",
            "subcategory":"Religious Organization",
            "type":"Services"
        }
    ],
    "sg:phone":"+1 928 636 9533",
    "sg:postcode":"86323",
    "sg:province":"AZ",
    "sg:tags":[
        "church"
    ],
    "wof:name":"Saving Grace Lutheran Church",
    "wof:placetype":"venue"
},
  "geometry": {"coordinates":[-112.454314,34.735363],"type":"Point"}
}