{
  "type": "Feature",
  "properties": {
    "iso:country":"US",
    "sg:address":"444 W Sheldon St",
    "sg:city":"Prescott",
    "sg:classifiers":[
        {
            "category":"Manufacturing",
            "subcategory":"Printing",
            "type":"Manufacturing & Wholesale Goods"
        }
    ],
    "sg:phone":"+1 928 445 3534",
    "sg:postcode":"86301",
    "sg:province":"AZ",
    "sg:tags":[
        "commercial",
        "typesetting"
    ],
    "wof:name":"Fornara's Printing & Graphics",
    "wof:placetype":"venue"
},
  "geometry": {"coordinates":[-112.473947,34.545528],"type":"Point"}
}