{
  "type": "Feature",
  "properties": {
    "addr:full":"230 W Baseline Rd Tempe AZ 85283",
    "addr:housenumber":"230",
    "addr:postcode":"85283",
    "addr:street":"W Baseline Rd",
    "iso:country":"US",
    "sg:address":"230 W Baseline Rd",
    "sg:city":"Tempe",
    "sg:classifiers":[
        {
            "category":"Professional",
            "subcategory":"Engineering",
            "type":"Services"
        }
    ],
    "sg:phone":"+1 480 755 1042",
    "sg:postcode":"85283",
    "sg:province":"AZ",
    "sg:tags":[
        "consulting",
        "engineer"
    ],
    "wof:name":"Tres Rios Consulting Engineers, Inc.",
    "wof:placetype":"venue"
},
  "geometry": {"coordinates":[-111.94292299999999,33.378211],"type":"Point"}
}