{
  "type": "Feature",
  "properties": {
    "iso:country":"US",
    "sg:address":"629 N Judd Ave",
    "sg:city":"Chandler",
    "sg:classifiers":[
        {
            "category":"Banks & Credit Unions",
            "subcategory":"Bank",
            "type":"Services"
        }
    ],
    "sg:phone":"+1 480 785 7933",
    "sg:postcode":"85226",
    "sg:province":"AZ",
    "sg:tags":[
        "loan",
        "real estate"
    ],
    "wof:name":"CTX Intl",
    "wof:placetype":"venue"
},
  "geometry": {"coordinates":[-111.951187,33.3136],"type":"Point"}
}