{
  "type": "Feature",
  "properties": {
    "iso:country":"US",
    "sg:address":"3411 N 12th St",
    "sg:city":"Phoenix",
    "sg:classifiers":[
        {
            "category":"Retail",
            "subcategory":"Animal Services",
            "type":"Services"
        }
    ],
    "sg:phone":"+1 623 780 3803",
    "sg:postcode":"85014",
    "sg:province":"AZ",
    "wof:name":"Special Arabian Training Ctr",
    "wof:placetype":"venue"
},
  "geometry": {"coordinates":[-112.056264,33.489168],"type":"Point"}
}