{
  "type": "Feature",
  "properties": {
    "iso:country":"US",
    "sg:address":"1711 W 17th St",
    "sg:city":"Tempe",
    "sg:classifiers":[
        {
            "category":"Manufacturing",
            "subcategory":"Printing",
            "type":"Manufacturing & Wholesale Goods"
        }
    ],
    "sg:phone":"+1 480 940 9310",
    "sg:postcode":"85281",
    "sg:province":"AZ",
    "sg:tags":[
        "commercial"
    ],
    "wof:name":"Good Impressions Printing Inc",
    "wof:placetype":"venue"
},
  "geometry": {"coordinates":[-111.96311799999999,33.409696],"type":"Point"}
}