{
  "type": "Feature",
  "properties": {
    "iso:country":"US",
    "sg:address":"365 E White Mountain Blvd",
    "sg:city":"Pinetop",
    "sg:classifiers":[
        {
            "category":"Restaurant",
            "type":"Food & Drink"
        }
    ],
    "sg:menulink":"http://www.allmenus.com/az/snowflake/166699-burger-king/menu/",
    "sg:phone":"+1 928 367 2565",
    "sg:postcode":"85935",
    "sg:province":"AZ",
    "sg:tags":[
        "burger",
        "american"
    ],
    "wof:name":"Burger King",
    "wof:placetype":"venue"
},
  "geometry": {"coordinates":[-109.950833,34.13674],"type":"Point"}
}