{
  "type": "Feature",
  "properties": {
    "iso:country":"US",
    "sg:address":"519 W Lone Cactus Dr",
    "sg:city":"Phoenix",
    "sg:classifiers":[
        {
            "category":"Manufacturing",
            "subcategory":"Electronics",
            "type":"Manufacturing & Wholesale Goods"
        }
    ],
    "sg:phone":"+1 623 435 6555",
    "sg:postcode":"85027",
    "sg:province":"AZ",
    "sg:tags":[
        "equipment",
        "mfg",
        "electronic",
        "supply"
    ],
    "wof:name":"Beckelec",
    "wof:placetype":"venue"
},
  "geometry": {"coordinates":[-112.080558,33.680753],"type":"Point"}
}