{
  "type": "Feature",
  "properties": {
    "iso:country":"US",
    "sg:address":"801 N Beeline Hwy",
    "sg:city":"Payson",
    "sg:classifiers":[
        {
            "category":"Travel",
            "subcategory":"Hotels & Motels",
            "type":"Entertainment"
        }
    ],
    "sg:phone":"+1 877 574 2464",
    "sg:postcode":"85541",
    "sg:province":"AZ",
    "sg:tags":[
        "lodging"
    ],
    "sg:website":"http://book.bestwestern.com/bestwestern/priceAvail.do?propertyCode=03140&cm_mmc=IYP-_-YP-_-property-_-3140",
    "wof:name":"Best Western Payson Inn",
    "wof:placetype":"venue"
},
  "geometry": {"coordinates":[-111.322586,34.250061],"type":"Point"}
}