{
  "type": "Feature",
  "properties": {
    "addr:full":"2950 N 32nd St Phoenix AZ 85018",
    "addr:housenumber":"2950",
    "addr:postcode":"85018",
    "addr:street":"N 32Nd St",
    "iso:country":"US",
    "sg:address":"2950 N 32nd St",
    "sg:city":"Phoenix",
    "sg:classifiers":[
        {
            "category":"Banks & Credit Unions",
            "subcategory":"Bank",
            "type":"Services"
        }
    ],
    "sg:phone":"+1 602 381 1100",
    "sg:postcode":"85018",
    "sg:province":"AZ",
    "sg:tags":[
        "cashing",
        "check"
    ],
    "wof:name":"Checkmate",
    "wof:placetype":"venue"
},
  "geometry": {"coordinates":[-112.012987,33.481398],"type":"Point"}
}