{
  "type": "Feature",
  "properties": {
    "iso:country":"US",
    "sg:address":"7575 E Princess Dr",
    "sg:city":"Scottsdale",
    "sg:classifiers":[
        {
            "category":"Building & Trades",
            "subcategory":"Equipment Rental",
            "type":"Services"
        },
        {
            "category":"Shopping",
            "subcategory":"Computers & Home Electronics",
            "type":"Retail Goods"
        }
    ],
    "sg:phone":"+1 480 797 8336",
    "sg:postcode":"85255",
    "sg:province":"AZ",
    "sg:tags":[
        "stereo",
        "leasing",
        "video",
        "audio",
        "equipment-renting",
        "audio-visual"
    ],
    "sg:website":"http://www.americanav.com",
    "wof:name":"American Audio Visual Center Inc",
    "wof:placetype":"venue"
},
  "geometry": {"coordinates":[-111.916917,33.645937],"type":"Point"}
}