{
  "type": "Feature",
  "properties": {
    "addr:full":"14905 N 134th Ln Surprise AZ 85379",
    "addr:housenumber":"14905",
    "addr:postcode":"85379",
    "addr:street":"N 134Th Ln",
    "iso:country":"US",
    "sg:address":"14905 N 134th Ln",
    "sg:city":"Surprise",
    "sg:classifiers":[
        {
            "category":"Transit Center",
            "subcategory":"Freight",
            "type":"Transportation"
        },
        {
            "category":"Freight",
            "type":"Transportation"
        }
    ],
    "sg:phone":"+1 623 544 4012",
    "sg:postcode":"85379",
    "sg:province":"AZ",
    "sg:tags":[
        "local",
        "trucking-motor",
        "trucking"
    ],
    "wof:name":"Walmart Trucking",
    "wof:placetype":"venue"
},
  "geometry": {"coordinates":[-112.35004000000001,33.619158],"type":"Point"}
}