{
  "type": "Feature",
  "properties": {
    "addr:full":"188 N Nevada Way Gilbert AZ 85233",
    "addr:housenumber":"188",
    "addr:postcode":"85233",
    "addr:street":"N Nevada Way",
    "iso:country":"US",
    "sg:address":"188 N Nevada Way",
    "sg:city":"Gilbert",
    "sg:classifiers":[
        {
            "category":"Professional",
            "subcategory":"Management & Consulting",
            "type":"Services"
        }
    ],
    "sg:phone":"+1 480 545 1713",
    "sg:postcode":"85233",
    "sg:province":"AZ",
    "sg:tags":[
        "sales"
    ],
    "wof:name":"Tri Plus Sales Inc",
    "wof:placetype":"venue"
},
  "geometry": {"coordinates":[-111.81529399999999,33.351616],"type":"Point"}
}