{
  "type": "Feature",
  "properties": {
    "addr:full":"3510 E Baseline Rd Ste 103 Mesa AZ 85204",
    "addr:housenumber":"3510",
    "addr:postcode":"85204",
    "addr:street":"E Baseline Rd Ste 103",
    "iso:country":"US",
    "sg:address":"3510 E Baseline Rd Ste 103",
    "sg:city":"Mesa",
    "sg:classifiers":[
        {
            "category":"Personal",
            "subcategory":"Beauty Salon",
            "type":"Services"
        }
    ],
    "sg:phone":"+1 480 545 6727",
    "sg:postcode":"85204",
    "sg:province":"AZ",
    "sg:tags":[
        "hair"
    ],
    "wof:name":"Lollilocks Kids Hair Salon",
    "wof:placetype":"venue"
},
  "geometry": {"coordinates":[-111.75538299999999,33.37963],"type":"Point"}
}