{
  "type": "Feature",
  "properties": {
    "iso:country":"US",
    "sg:address":"7611 W Thomas Rd",
    "sg:city":"Phoenix",
    "sg:classifiers":[
        {
            "category":"Shopping",
            "subcategory":"Jewelry",
            "type":"Retail Goods"
        }
    ],
    "sg:phone":"+1 623 873 3537",
    "sg:postcode":"85033",
    "sg:province":"AZ",
    "sg:tags":[
        "jeweler"
    ],
    "wof:name":"Rogers Jewelers",
    "wof:placetype":"venue"
},
  "geometry": {"coordinates":[-112.221258,33.480106],"type":"Point"}
}