{
  "type": "Feature",
  "properties": {
    "addr:full":"3142 W Hartford Dr Phoenix AZ 85053",
    "addr:housenumber":"3142",
    "addr:postcode":"85053",
    "addr:street":"W Hartford Dr",
    "iso:country":"US",
    "sg:address":"3142 W Hartford Dr",
    "sg:city":"Phoenix",
    "sg:classifiers":[
        {
            "category":"Education",
            "subcategory":"Dance Studio",
            "type":"Public Place"
        }
    ],
    "sg:phone":"+1 602 577 3262",
    "sg:postcode":"85053",
    "sg:province":"AZ",
    "sg:tags":[
        "instruction",
        "dancing"
    ],
    "wof:name":"Maggee's Dance Studio",
    "wof:placetype":"venue"
},
  "geometry": {"coordinates":[-112.127876,33.643084],"type":"Point"}
}