{
  "type": "Feature",
  "properties": {
    "addr:full":"1505 N Tamarisk Dr Chandler AZ 85224",
    "addr:housenumber":"1505",
    "addr:postcode":"85224",
    "addr:street":"N Tamarisk Dr",
    "iso:country":"US",
    "sg:address":"1505 N Tamarisk Dr",
    "sg:city":"Chandler",
    "sg:classifiers":[
        {
            "category":"Wholesale",
            "subcategory":"Non-durable Goods",
            "type":"Manufacturing & Wholesale Goods"
        }
    ],
    "sg:phone":"+1 480 899 5892",
    "sg:postcode":"85224",
    "sg:province":"AZ",
    "wof:name":"On Core Promotions",
    "wof:placetype":"venue"
},
  "geometry": {"coordinates":[-111.881687,33.32865],"type":"Point"}
}