{
  "type": "Feature",
  "properties": {
    "iso:country":"US",
    "sg:address":"7227 W Turquoise Ave",
    "sg:city":"Peoria",
    "sg:classifiers":[
        {
            "category":"Manufacturing",
            "subcategory":"Metals",
            "type":"Manufacturing & Wholesale Goods"
        }
    ],
    "sg:phone":"+1 602 299 9522",
    "sg:postcode":"85345",
    "sg:province":"AZ",
    "sg:tags":[
        "cutlery",
        "mfg"
    ],
    "wof:name":"Dragons Den",
    "wof:placetype":"venue"
},
  "geometry": {"coordinates":[-112.213427,33.574954],"type":"Point"}
}