{
  "type": "Feature",
  "properties": {
    "iso:country":"US",
    "sg:address":"3633 W Camelback Rd",
    "sg:city":"Phoenix",
    "sg:classifiers":[
        {
            "category":"Personal",
            "subcategory":"Beauty Salon",
            "type":"Services"
        }
    ],
    "sg:phone":"+1 602 995 7114",
    "sg:postcode":"85019",
    "sg:province":"AZ",
    "wof:name":"Dalias",
    "wof:placetype":"venue"
},
  "geometry": {"coordinates":[-112.137941,33.509362],"type":"Point"}
}