{
  "type": "Feature",
  "properties": {
    "iso:country":"US",
    "sg:address":"83 S Mountain View Rd",
    "sg:city":"Apache Junction",
    "sg:classifiers":[
        {
            "category":"Insurance",
            "subcategory":"Insurance Agent",
            "type":"Services"
        }
    ],
    "sg:phone":"+1 480 671 6734",
    "sg:postcode":"85219",
    "sg:province":"AZ",
    "sg:tags":[
        "engine",
        "adjuster",
        "appraisal",
        "for",
        "jet"
    ],
    "wof:name":"Borescope In Video",
    "wof:placetype":"venue"
},
  "geometry": {"coordinates":[-111.49406500000001,33.414319],"type":"Point"}
}