{
  "type": "Feature",
  "properties": {
    "iso:country":"US",
    "sg:address":"6021 N 57th Dr",
    "sg:city":"Glendale",
    "sg:classifiers":[
        {
            "category":"Manufacturing",
            "subcategory":"Printing",
            "type":"Manufacturing & Wholesale Goods"
        }
    ],
    "sg:phone":"+1 623 931 3414",
    "sg:postcode":"85301",
    "sg:province":"AZ",
    "sg:tags":[
        "commercial"
    ],
    "wof:name":"Three Four Printing",
    "wof:placetype":"venue"
},
  "geometry": {"coordinates":[-112.183032,33.524344],"type":"Point"}
}