{
  "type": "Feature",
  "properties": {
    "iso:country":"US",
    "sg:address":"9981 W Camelback Rd",
    "sg:city":"Phoenix",
    "sg:classifiers":[
        {
            "category":"Professional",
            "subcategory":"Management & Consulting",
            "type":"Services"
        }
    ],
    "sg:phone":"+1 623 872 0714",
    "sg:postcode":"85037",
    "sg:province":"AZ",
    "wof:name":"Americal Management Co Inc",
    "wof:placetype":"venue"
},
  "geometry": {"coordinates":[-112.275503,33.508258],"type":"Point"}
}