{
  "type": "Feature",
  "properties": {
    "iso:country":"US",
    "sg:address":"3548 Corte de la Perla",
    "sg:city":"Green Valley",
    "sg:classifiers":[
        {
            "category":"Professional",
            "type":"Services"
        }
    ],
    "sg:phone":"+1 520 648 6072",
    "sg:postcode":"85614",
    "sg:province":"AZ",
    "wof:name":"Spring Meadow Lodge",
    "wof:placetype":"venue"
},
  "geometry": {"coordinates":[-111.015492,31.817063],"type":"Point"}
}