{
  "type": "Feature",
  "properties": {
    "iso:country":"US",
    "sg:address":"7962 N Oracle Rd",
    "sg:city":"Tucson",
    "sg:classifiers":[
        {
            "category":"Retail",
            "subcategory":"Laundry & Dry Cleaning",
            "type":"Services"
        }
    ],
    "sg:phone":"+1 520 498 5310",
    "sg:postcode":"85704",
    "sg:province":"AZ",
    "sg:tags":[
        "cleaners"
    ],
    "wof:name":"Seville Cleaners",
    "wof:placetype":"venue"
},
  "geometry": {"coordinates":[-110.976051,32.345769],"type":"Point"}
}