{
  "type": "Feature",
  "properties": {
    "iso:country":"US",
    "sg:address":"3728 E Glenrosa Ave",
    "sg:city":"Phoenix",
    "sg:classifiers":[
        {
            "category":"Real Estate",
            "subcategory":"Real Estate Operator",
            "type":"Services"
        }
    ],
    "sg:phone":"+1 602 381 0844",
    "sg:postcode":"85018",
    "sg:province":"AZ",
    "sg:tags":[
        "building",
        "nonresidential"
    ],
    "wof:name":"Morgan Properties",
    "wof:placetype":"venue"
},
  "geometry": {"coordinates":[-112.00032299999999,33.498442],"type":"Point"}
}