{
  "type": "Feature",
  "properties": {
    "iso:country":"US",
    "sg:address":"2930 W Camelback Rd",
    "sg:city":"Phoenix",
    "sg:classifiers":[
        {
            "category":"Shopping",
            "subcategory":"Gifts & Souvenirs",
            "type":"Retail Goods"
        }
    ],
    "sg:phone":"+1 602 841 1185",
    "sg:postcode":"85017",
    "sg:province":"AZ",
    "wof:name":"Promise Gift Baskets",
    "wof:placetype":"venue"
},
  "geometry": {"coordinates":[-112.12504,33.509514],"type":"Point"}
}