{
  "type": "Feature",
  "properties": {
    "iso:country":"US",
    "sg:address":"4844 E 22nd St",
    "sg:city":"Tucson",
    "sg:classifiers":[
        {
            "category":"Restaurant",
            "type":"Food & Drink"
        }
    ],
    "sg:phone":"+1 520 519 0355",
    "sg:postcode":"85711",
    "sg:province":"AZ",
    "sg:tags":[
        "bar"
    ],
    "wof:name":"Speakeasy The",
    "wof:placetype":"venue"
},
  "geometry": {"coordinates":[-110.884466,32.206843],"type":"Point"}
}