{
  "type": "Feature",
  "properties": {
    "iso:country":"US",
    "sg:address":"1695 W Sahuaro Dr",
    "sg:city":"Tucson",
    "sg:classifiers":[
        {
            "category":"Building & Trades",
            "subcategory":"Landscaping Services",
            "type":"Services"
        }
    ],
    "sg:phone":"+1 520 882 6322",
    "sg:postcode":"85745",
    "sg:province":"AZ",
    "sg:tags":[
        "landscape",
        "contractor"
    ],
    "wof:name":"Desert Glen Inc",
    "wof:placetype":"venue"
},
  "geometry": {"coordinates":[-111.002153,32.249024],"type":"Point"}
}