{
  "type": "Feature",
  "properties": {
    "addr:full":"1695 W Sahuaro Dr Tucson AZ 85745",
    "addr:housenumber":"1695",
    "addr:postcode":"85745",
    "addr:street":"W Sahuaro Dr",
    "iso:country":"US",
    "sg:address":"1695 W Sahuaro Dr",
    "sg:city":"Tucson",
    "sg:classifiers":[
        {
            "category":"Building & Trades",
            "subcategory":"Landscaping Services",
            "type":"Services"
        }
    ],
    "sg:phone":"+1 520 882 6322",
    "sg:postcode":"85745",
    "sg:province":"AZ",
    "sg:tags":[
        "landscape",
        "contractor"
    ],
    "wof:name":"Desert Glen Inc",
    "wof:placetype":"venue"
},
  "geometry": {"coordinates":[-111.00215300000001,32.249024],"type":"Point"}
}