{
  "type": "Feature",
  "properties": {
    "iso:country":"US",
    "sg:address":"1423 S Country Club Dr",
    "sg:city":"Mesa",
    "sg:classifiers":[
        {
            "category":"Banks & Credit Unions",
            "subcategory":"Bank",
            "type":"Services"
        }
    ],
    "sg:phone":"+1 480 834 5565",
    "sg:postcode":"85210",
    "sg:province":"AZ",
    "sg:tags":[
        "depository",
        "banking"
    ],
    "wof:name":"Money Mart 2251",
    "wof:placetype":"venue"
},
  "geometry": {"coordinates":[-111.840017,33.387824],"type":"Point"}
}