{
  "type": "Feature",
  "properties": {
    "addr:full":"11529 E Quade Ave Mesa AZ 85212",
    "addr:housenumber":"11529",
    "addr:postcode":"85212",
    "addr:street":"E Quade Ave",
    "iso:country":"US",
    "sg:address":"11529 E Quade Ave",
    "sg:city":"Mesa",
    "sg:classifiers":[
        {
            "category":"Restaurant",
            "type":"Food & Drink"
        }
    ],
    "sg:phone":"+1 480 986 0281",
    "sg:postcode":"85212",
    "sg:province":"AZ",
    "wof:name":"Jack In The Box",
    "wof:placetype":"venue"
},
  "geometry": {"coordinates":[-111.585793,33.347577],"type":"Point"}
}