{
  "type": "Feature",
  "properties": {
    "iso:country":"US",
    "sg:address":"26009 N 7th Ave",
    "sg:city":"Phoenix",
    "sg:classifiers":[
        {
            "category":"Shopping",
            "subcategory":"Bicycles & Sporting Goods",
            "type":"Retail Goods"
        }
    ],
    "sg:phone":"+1 623 581 2986",
    "sg:postcode":"85085",
    "sg:province":"AZ",
    "sg:tags":[
        "equipment",
        "golf",
        "supply"
    ],
    "wof:name":"Condor Golf",
    "wof:placetype":"venue"
},
  "geometry": {"coordinates":[-112.082831,33.720386],"type":"Point"}
}