{
  "type": "Feature",
  "properties": {
    "addr:full":"655 N Center St Mesa AZ 85201",
    "addr:housenumber":"655",
    "addr:postcode":"85201",
    "addr:street":"N Center St",
    "iso:country":"US",
    "sg:address":"655 N Center St",
    "sg:city":"Mesa",
    "sg:classifiers":[
        {
            "category":"Building & Trades",
            "subcategory":"Landscaping Services",
            "type":"Services"
        }
    ],
    "sg:phone":"+1 602 565 7225",
    "sg:postcode":"85201",
    "sg:province":"AZ",
    "sg:tags":[
        "tree"
    ],
    "wof:name":"Mark Heywood Tree Transplanter",
    "wof:placetype":"venue"
},
  "geometry": {"coordinates":[-111.831266,33.427818],"type":"Point"}
}