{
  "type": "Feature",
  "properties": {
    "addr:full":"4645 E Cotton Center Blvd Phoenix AZ 85040",
    "addr:housenumber":"4645",
    "addr:postcode":"85040",
    "addr:street":"E Cotton Center Blvd",
    "iso:country":"US",
    "sg:address":"4645 E Cotton Center Blvd",
    "sg:city":"Phoenix",
    "sg:classifiers":[
        {
            "category":"Home & Garden",
            "subcategory":"Furniture",
            "type":"Retail Goods"
        }
    ],
    "sg:phone":"+1 602 470 1500",
    "sg:postcode":"85040",
    "sg:province":"AZ",
    "wof:name":"Southwest Business Furnishing",
    "wof:placetype":"venue"
},
  "geometry": {"coordinates":[-111.978442,33.403548],"type":"Point"}
}