{
  "type": "Feature",
  "properties": {
    "iso:country":"US",
    "sg:address":"1830 S Central Ave",
    "sg:city":"Phoenix",
    "sg:classifiers":[
        {
            "category":"Professional",
            "type":"Services"
        },
        {
            "category":"Personal",
            "type":"Services"
        },
        {
            "category":"Restaurant",
            "type":"Food & Drink"
        }
    ],
    "sg:phone":"+1 602 388 1870",
    "sg:postcode":"85004",
    "sg:province":"AZ",
    "sg:tags":[
        "mexican",
        "planning",
        "caterer",
        "party",
        "event"
    ],
    "sg:website":"http://www.comedorguadalajara.com",
    "wof:name":"Comedor Guadalajara",
    "wof:placetype":"venue"
},
  "geometry": {"coordinates":[-112.073753,33.429562],"type":"Point"}
}