{
  "type": "Feature",
  "properties": {
    "iso:country":"US",
    "sg:address":"7333 W Thomas Rd",
    "sg:city":"Phoenix",
    "sg:classifiers":[
        {
            "category":"Shopping",
            "subcategory":"Optical Goods",
            "type":"Retail Goods"
        }
    ],
    "sg:phone":"+1 623 247 0777",
    "sg:postcode":"85033",
    "sg:province":"AZ",
    "wof:name":"Americas Best Cntcts Eyglasses",
    "wof:placetype":"venue"
},
  "geometry": {"coordinates":[-112.218334,33.480144],"type":"Point"}
}