{
  "type": "Feature",
  "properties": {
    "addr:full":"13959 W Bell Rd Surprise AZ 85374",
    "addr:housenumber":"13959",
    "addr:postcode":"85374",
    "addr:street":"W Bell Rd",
    "iso:country":"US",
    "sg:address":"13959 W Bell Rd",
    "sg:city":"Surprise",
    "sg:classifiers":[
        {
            "category":"Restaurant",
            "type":"Food & Drink"
        },
        {
            "category":"Bakery",
            "type":"Food & Drink"
        }
    ],
    "sg:phone":"+1 623 512 4684",
    "sg:postcode":"85374",
    "sg:province":"AZ",
    "sg:website":"http://www.paradisebakery.com",
    "wof:name":"Paradise Bakery & Cafe",
    "wof:placetype":"venue"
},
  "geometry": {"coordinates":[-112.36118999999999,33.638569],"type":"Point"}
}