{
  "type": "Feature",
  "properties": {
    "iso:country":"US",
    "sg:address":"6330 E Main St",
    "sg:city":"Mesa",
    "sg:classifiers":[
        {
            "category":"Professional",
            "subcategory":"Advertising",
            "type":"Services"
        }
    ],
    "sg:phone":"+1 480 396 4065",
    "sg:postcode":"85205",
    "sg:province":"AZ",
    "sg:website":"www.circseller.com",
    "wof:name":"Circseller",
    "wof:placetype":"venue"
},
  "geometry": {"coordinates":[-111.69493199999999,33.415722],"type":"Point"}
}