{
  "type": "Feature",
  "properties": {
    "iso:country":"US",
    "sg:address":"37203 N 16th St",
    "sg:city":"Phoenix",
    "sg:classifiers":[
        {
            "category":"Wholesale",
            "subcategory":"Construction Materials",
            "type":"Manufacturing & Wholesale Goods"
        }
    ],
    "sg:phone":"+1 623 465 0500",
    "sg:postcode":"85086",
    "sg:province":"AZ",
    "sg:tags":[
        "rock"
    ],
    "wof:name":"New Rock Enterprises",
    "wof:placetype":"venue"
},
  "geometry": {"coordinates":[-112.047834,33.825342],"type":"Point"}
}