{
  "type": "Feature",
  "properties": {
    "iso:country":"US",
    "sg:address":"2164 McCulloch Blvd N",
    "sg:city":"Lake Havasu City",
    "sg:classifiers":[
        {
            "category":"Insurance",
            "subcategory":"Insurance Agent",
            "type":"Services"
        }
    ],
    "sg:phone":"+1 928 855 1109",
    "sg:postcode":"86403",
    "sg:province":"AZ",
    "wof:name":"American Family Insurance",
    "wof:placetype":"venue"
},
  "geometry": {"coordinates":[-114.32331000000001,34.4751],"type":"Point"}
}