{
  "type": "Feature",
  "properties": {
    "iso:country":"US",
    "sg:address":"717 W Union Hills Dr",
    "sg:city":"Phoenix",
    "sg:classifiers":[
        {
            "category":"Wholesale",
            "subcategory":"Construction Materials",
            "type":"Manufacturing & Wholesale Goods"
        }
    ],
    "sg:phone":"+1 602 863 0007",
    "sg:postcode":"85027",
    "sg:province":"AZ",
    "sg:tags":[
        "granite"
    ],
    "wof:name":"Bockelman Trucking LLC",
    "wof:placetype":"venue"
},
  "geometry": {"coordinates":[-112.086217,33.654554],"type":"Point"}
}