{
  "type": "Feature",
  "properties": {
    "addr:full":"6872 E Sunrise Dr Tucson AZ 85750",
    "addr:housenumber":"6872",
    "addr:postcode":"85750",
    "addr:street":"E Sunrise Dr",
    "iso:country":"US",
    "sg:address":"6872 E Sunrise Dr",
    "sg:city":"Tucson",
    "sg:classifiers":[
        {
            "category":"Insurance",
            "subcategory":"Insurance Agent",
            "type":"Services"
        },
        {
            "category":"Insurance",
            "subcategory":"Hazard Insurance",
            "type":"Services"
        },
        {
            "category":"Insurance",
            "subcategory":"Title Insurance",
            "type":"Services"
        },
        {
            "category":"Insurance",
            "subcategory":"Life Insurance",
            "type":"Services"
        }
    ],
    "sg:phone":"+1 520 299 3445",
    "sg:postcode":"85750",
    "sg:province":"AZ",
    "sg:tags":[
        "business",
        "auto",
        "commercial",
        "homeowner",
        "motorcycle",
        "renter"
    ],
    "wof:name":"Allstate Insurance Company - Jose Durazo",
    "wof:placetype":"venue"
},
  "geometry": {"coordinates":[-110.846895,32.308848],"type":"Point"}
}