{
  "type": "Feature",
  "properties": {
    "addr:full":"2828 N Country Club Rd Tucson AZ 85716",
    "addr:housenumber":"2828",
    "addr:postcode":"85716",
    "addr:street":"N Country Club Rd",
    "iso:country":"US",
    "sg:address":"2828 N Country Club Rd",
    "sg:city":"Tucson",
    "sg:classifiers":[
        {
            "category":"Professional",
            "subcategory":"Management & Consulting",
            "type":"Services"
        }
    ],
    "sg:phone":"+1 520 326 2288",
    "sg:postcode":"85716",
    "sg:province":"AZ",
    "sg:tags":[
        "food",
        "facility"
    ],
    "wof:name":"Culinary Design Group LLC",
    "wof:placetype":"venue"
},
  "geometry": {"coordinates":[-110.926734,32.25895],"type":"Point"}
}