{
  "type": "Feature",
  "properties": {
    "iso:country":"US",
    "sg:address":"22076 Balboa Dr",
    "sg:city":"Maricopa",
    "sg:classifiers":[
        {
            "category":"Building & Trades",
            "subcategory":"Construction",
            "type":"Services"
        }
    ],
    "sg:phone":"+1 520 568 1470",
    "sg:postcode":"85239",
    "sg:province":"AZ",
    "sg:tags":[
        "house"
    ],
    "wof:name":"Hacienda Builders Enclave",
    "wof:placetype":"venue"
},
  "geometry": {"coordinates":[-112.033274,33.08037],"type":"Point"}
}