{
  "type": "Feature",
  "properties": {
    "iso:country":"US",
    "sg:address":"4535 E Elwood St",
    "sg:city":"Phoenix",
    "sg:classifiers":[
        {
            "category":"Shopping",
            "type":"Retail Goods"
        }
    ],
    "sg:phone":"+1 480 517 9782",
    "sg:postcode":"85040",
    "sg:province":"AZ",
    "sg:tags":[
        "merchandise"
    ],
    "wof:name":"Paddock Pools",
    "wof:placetype":"venue"
},
  "geometry": {"coordinates":[-111.983086,33.413018],"type":"Point"}
}