{
  "type": "Feature",
  "properties": {
    "iso:country":"US",
    "sg:address":"1426 E Citation Ln",
    "sg:city":"Tempe",
    "sg:classifiers":[
        {
            "category":"Shopping",
            "type":"Retail Goods"
        }
    ],
    "sg:phone":"+1 480 330 4773",
    "sg:postcode":"85284",
    "sg:province":"AZ",
    "sg:tags":[
        "plant",
        "flower",
        "tree",
        "artificial"
    ],
    "wof:name":"Bloom On",
    "wof:placetype":"venue"
},
  "geometry": {"coordinates":[-111.915249,33.342874],"type":"Point"}
}