{
  "type": "Feature",
  "properties": {
    "addr:full":"3809 N Oracle Rd Tucson AZ 85705",
    "addr:housenumber":"3809",
    "addr:postcode":"85705",
    "addr:street":"N Oracle Rd",
    "iso:country":"US",
    "sg:address":"3809 N Oracle Rd",
    "sg:city":"Tucson",
    "sg:classifiers":[
        {
            "category":"Shopping",
            "type":"Retail Goods"
        }
    ],
    "sg:phone":"+1 520 888 3082",
    "sg:postcode":"85705",
    "sg:province":"AZ",
    "sg:tags":[
        "product",
        "pest"
    ],
    "wof:name":"Do-It-Yourself Pest Control",
    "wof:placetype":"venue"
},
  "geometry": {"coordinates":[-110.978154,32.275188],"type":"Point"}
}