{
  "type": "Feature",
  "properties": {
    "iso:country":"US",
    "sg:address":"1809 S 4th Ave",
    "sg:city":"Tucson",
    "sg:classifiers":[
        {
            "category":"Wholesale",
            "subcategory":"Auto Parts",
            "type":"Manufacturing & Wholesale Goods"
        }
    ],
    "sg:phone":"+1 520 792 4389",
    "sg:postcode":"85713",
    "sg:province":"AZ",
    "sg:tags":[
        "dealers-used",
        "automobile",
        "rebuilt",
        "cars-wholesale"
    ],
    "wof:name":"Southwest Chevy",
    "wof:placetype":"venue"
},
  "geometry": {"coordinates":[-110.965388,32.200233],"type":"Point"}
}