{
  "type": "Feature",
  "properties": {
    "iso:country":"US",
    "sg:address":"4109 E Lariat Ln",
    "sg:city":"Phoenix",
    "sg:classifiers":[
        {
            "category":"Personal",
            "type":"Services"
        }
    ],
    "sg:phone":"+1 480 948 1123",
    "sg:postcode":"85050",
    "sg:province":"AZ",
    "sg:tags":[
        "counseling"
    ],
    "wof:name":"Stacey Bruen",
    "wof:placetype":"venue"
},
  "geometry": {"coordinates":[-111.994412,33.722321],"type":"Point"}
}