{
  "type": "Feature",
  "properties": {
    "addr:full":"215 S Industrial Dr Tempe AZ 85281",
    "addr:housenumber":"215",
    "addr:postcode":"85281",
    "addr:street":"S Industrial Dr",
    "iso:country":"US",
    "sg:address":"215 S Industrial Dr",
    "sg:city":"Tempe",
    "sg:classifiers":[
        {
            "category":"Retail",
            "subcategory":"Auto Repair",
            "type":"Services"
        }
    ],
    "sg:phone":"+1 480 967 0544",
    "sg:postcode":"85281",
    "sg:province":"AZ",
    "sg:tags":[
        "van",
        "conversion",
        "truck",
        "accessory"
    ],
    "sg:website":"www.designerseatworks.com",
    "wof:name":"Designer Seat Works",
    "wof:placetype":"venue"
},
  "geometry": {"coordinates":[-111.906127,33.428487],"type":"Point"}
}