{
  "type": "Feature",
  "properties": {
    "iso:country":"US",
    "sg:address":"21 N Frontier St",
    "sg:city":"Wickenburg",
    "sg:classifiers":[
        {
            "category":"Museum",
            "type":"Entertainment"
        }
    ],
    "sg:phone":"+1 928 684 2272",
    "sg:postcode":"85390",
    "sg:province":"AZ",
    "sg:website":"www.westernmuseum.org",
    "wof:name":"Desert Caballeros Western Msm",
    "wof:placetype":"venue"
},
  "geometry": {"coordinates":[-112.731675,33.968622],"type":"Point"}
}