{
  "type": "Feature",
  "properties": {
    "addr:city":"Wickenburg",
    "addr:full":"21 North Frontier Street Wickenburg, Az 85390",
    "addr:house_number":"21",
    "addr:housenumber":"21",
    "addr:phone":"+1 602-684-2272",
    "addr:postcode":"85390",
    "addr:road":"North Frontier Street",
    "addr:state":"AZ",
    "addr:street":"N Frontier St",
    "iso:country":"US",
    "sg:address":"21 N Frontier St",
    "sg:city":"Wickenburg",
    "sg:classifiers":[
        {
            "category":"Museum",
            "type":"Entertainment"
        }
    ],
    "sg:phone":"+1 928 684 2272",
    "sg:postcode":"85390",
    "sg:province":"AZ",
    "sg:website":"www.westernmuseum.org",
    "wof:name":"Desert Caballeros Western Museum",
    "wof:placetype":"venue"
},
  "geometry": {"coordinates":[-112.73092,33.96856],"type":"Point"}
}