{
  "type": "Feature",
  "properties": {
    "iso:country":"US",
    "sg:address":"355 S Euclid Ave",
    "sg:city":"Tucson",
    "sg:classifiers":[
        {
            "category":"Wholesale",
            "subcategory":"Machinery & Supplies",
            "type":"Manufacturing & Wholesale Goods"
        }
    ],
    "sg:phone":"+1 520 629 9699",
    "sg:postcode":"85719",
    "sg:province":"AZ",
    "sg:tags":[
        "equipment",
        "establishment"
    ],
    "wof:name":"Waxie Sanitary Supply",
    "wof:placetype":"venue"
},
  "geometry": {"coordinates":[-110.95921800000001,32.218986],"type":"Point"}
}