{
  "type": "Feature",
  "properties": {
    "iso:country":"US",
    "sg:address":"2601 N Park Dr",
    "sg:city":"Winslow",
    "sg:classifiers":[
        {
            "category":"Real Estate",
            "subcategory":"Developer",
            "type":"Services"
        }
    ],
    "sg:phone":"+1 928 289 2856",
    "sg:postcode":"86047",
    "sg:province":"AZ",
    "sg:tags":[
        "mobile",
        "home"
    ],
    "wof:name":"North Park Village Homes",
    "wof:placetype":"venue"
},
  "geometry": {"coordinates":[-110.698005,35.042922],"type":"Point"}
}