{
  "type": "Feature",
  "properties": {
    "iso:country":"US",
    "sg:address":"1023 S Arizona Blvd",
    "sg:city":"Coolidge",
    "sg:classifiers":[
        {
            "category":"Autos & Motor Vehicles",
            "subcategory":"Auto Supplies",
            "type":"Retail Goods"
        }
    ],
    "sg:phone":"+1 520 723 4986",
    "sg:postcode":"85228",
    "sg:province":"AZ",
    "wof:name":"Jcs Tires",
    "wof:placetype":"venue"
},
  "geometry": {"coordinates":[-111.524078,32.968389],"type":"Point"}
}