{
  "type": "Feature",
  "properties": {
    "addr:full":"15634 E Sundown Dr Fountain Hills AZ 85268",
    "addr:housenumber":"15634",
    "addr:postcode":"85268",
    "addr:street":"E Sundown Dr",
    "iso:country":"US",
    "sg:address":"15634 E Sundown Dr",
    "sg:city":"Fountain Hills",
    "sg:classifiers":[
        {
            "category":"Professional",
            "type":"Services"
        }
    ],
    "sg:phone":"+1 480 836 2101",
    "sg:postcode":"85268",
    "sg:province":"AZ",
    "wof:name":"Raymond & Suzanne M Muzzarelli",
    "wof:placetype":"venue"
},
  "geometry": {"coordinates":[-111.74279,33.61851],"type":"Point"}
}