{
  "type": "Feature",
  "properties": {
    "addr:full":"35200 N 54th St Cave Creek AZ 85331",
    "addr:housenumber":"35200",
    "addr:postcode":"85331",
    "addr:street":"N 54Th St",
    "iso:country":"US",
    "sg:address":"35200 N 54th St",
    "sg:city":"Cave Creek",
    "sg:classifiers":[
        {
            "category":"Recreation",
            "type":"Entertainment"
        }
    ],
    "sg:phone":"+1 480 488 7978",
    "sg:postcode":"85331",
    "sg:province":"AZ",
    "sg:tags":[
        "stable"
    ],
    "wof:name":"Beaver Creek Equestrian",
    "wof:placetype":"venue"
},
  "geometry": {"coordinates":[-111.96522299999999,33.800923],"type":"Point"}
}