{
  "type": "Feature",
  "properties": {
    "iso:country":"US",
    "sg:address":"2929 N 75th Ave",
    "sg:city":"Phoenix",
    "sg:classifiers":[
        {
            "category":"Retail",
            "subcategory":"Photofinishing",
            "type":"Services"
        }
    ],
    "sg:phone":"+1 623 245 8116",
    "sg:postcode":"85033",
    "sg:province":"AZ",
    "sg:tags":[
        "photo",
        "finishing"
    ],
    "wof:name":"Foto Magic",
    "wof:placetype":"venue"
},
  "geometry": {"coordinates":[-112.220533,33.481559],"type":"Point"}
}