{
  "type": "Feature",
  "properties": {
    "addr:full":"7517 S McClintock Dr Ste 104 Tempe AZ 85283",
    "addr:housenumber":"7517",
    "addr:postcode":"85283",
    "addr:street":"S Mcclintock Dr Ste 104",
    "iso:country":"US",
    "sg:address":"7517 S McClintock Dr Ste 104",
    "sg:city":"Tempe",
    "sg:classifiers":[
        {
            "category":"Health Services",
            "subcategory":"Chiropractor",
            "type":"Services"
        }
    ],
    "sg:phone":"+1 480 831 6050",
    "sg:postcode":"85283",
    "sg:province":"AZ",
    "wof:name":"Carson Chiropractic Clinic",
    "wof:placetype":"venue"
},
  "geometry": {"coordinates":[-111.909845,33.350894],"type":"Point"}
}