{
  "type": "Feature",
  "properties": {
    "iso:country":"US",
    "sg:address":"3235 E Indian School Rd",
    "sg:city":"Phoenix",
    "sg:classifiers":[
        {
            "category":"Manufacturing",
            "subcategory":"Printing",
            "type":"Manufacturing & Wholesale Goods"
        }
    ],
    "sg:phone":"+1 602 381 6335",
    "sg:postcode":"85018",
    "sg:province":"AZ",
    "sg:tags":[
        "scanning",
        "supply",
        "lithographic",
        "services-commercial",
        "equipment",
        "commercial",
        "plotting"
    ],
    "wof:name":"Copy Works & Printing",
    "wof:placetype":"venue"
},
  "geometry": {"coordinates":[-112.012061,33.49519],"type":"Point"}
}