{
  "type": "Feature",
  "properties": {
    "addr:full":"2094 State Hwy 90 Huachuca City AZ 85616",
    "addr:housenumber":"2094",
    "addr:postcode":"85616",
    "addr:street":"State Hwy 90",
    "iso:country":"US",
    "sg:address":"2094 State Hwy 90",
    "sg:city":"Huachuca City",
    "sg:classifiers":[
        {
            "category":"Autos & Motor Vehicles",
            "subcategory":"Automobile Sales",
            "type":"Retail Goods"
        }
    ],
    "sg:phone":"+1 520 456 9400",
    "sg:postcode":"85616",
    "sg:province":"AZ",
    "sg:tags":[
        "car",
        "used",
        "dealer"
    ],
    "wof:name":"B & D Auto Sales Inc",
    "wof:placetype":"venue"
},
  "geometry": {"coordinates":[-110.35038400000001,31.685067],"type":"Point"}
}