{
  "type": "Feature",
  "properties": {
    "iso:country":"US",
    "sg:address":"88 S. San Marcos Place",
    "sg:city":"Chandler",
    "sg:classifiers":[
        {
            "category":"Professional",
            "subcategory":"Management & Consulting",
            "type":"Services"
        }
    ],
    "sg:phone":"+1 602 220 1437",
    "sg:postcode":"85225",
    "sg:province":"AZ",
    "sg:website":"http://www.levementum.com",
    "wof:name":"Levementum",
    "wof:placetype":"venue"
},
  "geometry": {"coordinates":[-111.842134,33.30327],"type":"Point"}
}