{
  "type": "Feature",
  "properties": {
    "iso:country":"US",
    "sg:address":"1334 E Chandler Blvd",
    "sg:city":"Phoenix",
    "sg:classifiers":[
        {
            "category":"Professional",
            "subcategory":"Advertising",
            "type":"Services"
        }
    ],
    "sg:phone":"+1 480 460 2108",
    "sg:postcode":"85048",
    "sg:province":"AZ",
    "sg:tags":[
        "mailing",
        "shipping"
    ],
    "wof:name":"Mailboxes & More",
    "wof:placetype":"venue"
},
  "geometry": {"coordinates":[-112.053817,33.305569],"type":"Point"}
}