{
  "type": "Feature",
  "properties": {
    "iso:country":"US",
    "sg:address":"1006 E Warner Rd Ste 104",
    "sg:city":"Tempe",
    "sg:classifiers":[
        {
            "category":"Sports & Exercise",
            "subcategory":"Bicycle Rental",
            "type":"Entertainment"
        },
        {
            "category":"Shopping",
            "subcategory":"Shoes",
            "type":"Retail Goods"
        }
    ],
    "sg:phone":"+1 480 522 2475",
    "sg:postcode":"85284",
    "sg:province":"AZ",
    "sg:tags":[
        "wear",
        "store"
    ],
    "sg:website":"www.solesportsrunning.com",
    "wof:name":"Sole Sports Running Zone",
    "wof:placetype":"venue"
},
  "geometry": {"coordinates":[-111.927409,33.33543],"type":"Point"}
}