{
  "type": "Feature",
  "properties": {
    "addr:full":"3639 N 29th St Phoenix AZ 85016",
    "addr:housenumber":"3639",
    "addr:postcode":"85016",
    "addr:street":"N 29Th St",
    "iso:country":"US",
    "sg:address":"3639 N 29th St",
    "sg:city":"Phoenix",
    "sg:classifiers":[
        {
            "category":"Professional",
            "subcategory":"Management & Consulting",
            "type":"Services"
        }
    ],
    "sg:phone":"+1 602 956 9240",
    "sg:postcode":"85016",
    "sg:province":"AZ",
    "sg:tags":[
        "consultant",
        "educational"
    ],
    "wof:name":"American Educational Systems Inc An Ar",
    "wof:placetype":"venue"
},
  "geometry": {"coordinates":[-112.01924,33.491043],"type":"Point"}
}