{
  "type": "Feature",
  "properties": {
    "iso:country":"US",
    "sg:address":"1329 N 90th Pl",
    "sg:city":"Mesa",
    "sg:classifiers":[
        {
            "category":"Shopping",
            "subcategory":"Clothing, Apparel, & Fashions",
            "type":"Retail Goods"
        }
    ],
    "sg:phone":"+1 480 984 0726",
    "sg:postcode":"85207",
    "sg:province":"AZ",
    "wof:name":"Lady Fan Inc",
    "wof:placetype":"venue"
},
  "geometry": {"coordinates":[-111.635165,33.436584],"type":"Point"}
}