{
  "type": "Feature",
  "properties": {
    "addr:full":"4343 E Camelback Rd Phoenix AZ 85018",
    "addr:housenumber":"4343",
    "addr:postcode":"85018",
    "addr:street":"E Camelback Rd",
    "iso:country":"US",
    "sg:address":"4343 E Camelback Rd",
    "sg:city":"Phoenix",
    "sg:classifiers":[
        {
            "category":"Organizations",
            "subcategory":"Professional Association",
            "type":"Services"
        }
    ],
    "sg:phone":"+1 602 808 9548",
    "sg:postcode":"85018",
    "sg:province":"AZ",
    "wof:name":"Juvenile Diabetes Foundation",
    "wof:placetype":"venue"
},
  "geometry": {"coordinates":[-111.987858,33.509483],"type":"Point"}
}