{
  "type": "Feature",
  "properties": {
    "iso:country":"US",
    "sg:address":"4250 N Drinkwater Blvd # 165",
    "sg:city":"Scottsdale",
    "sg:classifiers":[
        {
            "category":"Health Services",
            "subcategory":"Nursing And Care Facility",
            "type":"Services"
        },
        {
            "category":"Health Services",
            "subcategory":"Health Practitioner",
            "type":"Services"
        }
    ],
    "sg:phone":"+1 480 444 7777",
    "sg:postcode":"85251",
    "sg:province":"AZ",
    "sg:tags":[
        "home",
        "eldercare-home"
    ],
    "wof:name":"Affinity Home Health, Inc",
    "wof:placetype":"venue"
},
  "geometry": {"coordinates":[-111.921982,33.497189],"type":"Point"}
}