{
  "type": "Feature",
  "properties": {
    "addr:full":"1716 W Ajo Way Tucson AZ 85713",
    "addr:housenumber":"1716",
    "addr:postcode":"85713",
    "addr:street":"W Ajo Way",
    "iso:country":"US",
    "sg:address":"1716 W Ajo Way",
    "sg:city":"Tucson",
    "sg:classifiers":[
        {
            "category":"Personal",
            "subcategory":"Beauty Salon",
            "type":"Services"
        }
    ],
    "sg:phone":"+1 520 889 0040",
    "sg:postcode":"85713",
    "sg:province":"AZ",
    "sg:website":"www.greatclips.com",
    "wof:name":"Great Clips",
    "wof:placetype":"venue"
},
  "geometry": {"coordinates":[-110.999061,32.177945],"type":"Point"}
}