{
  "type": "Feature",
  "properties": {
    "iso:country":"US",
    "sg:address":"7338 E Maritime Dr",
    "sg:city":"Tucson",
    "sg:classifiers":[
        {
            "category":"Autos & Motor Vehicles",
            "subcategory":"Automobile Sales",
            "type":"Retail Goods"
        }
    ],
    "sg:phone":"+1 520 664 0854",
    "sg:postcode":"85706",
    "sg:province":"AZ",
    "sg:tags":[
        "used"
    ],
    "wof:name":"Fremont Rent-All",
    "wof:placetype":"venue"
},
  "geometry": {"coordinates":[-110.833423,32.093725],"type":"Point"}
}