{
  "type": "Feature",
  "properties": {
    "iso:country":"US",
    "sg:address":"508 N Whiting",
    "sg:city":"Mesa",
    "sg:classifiers":[
        {
            "category":"Real Estate",
            "subcategory":"Real Estate Agent",
            "type":"Services"
        }
    ],
    "sg:phone":"+1 480 835 0275",
    "sg:postcode":"85213",
    "sg:province":"AZ",
    "sg:tags":[
        "appraiser"
    ],
    "wof:name":"Erwin Standing Appraisal",
    "wof:placetype":"venue"
},
  "geometry": {"coordinates":[-111.777003,33.42431],"type":"Point"}
}