{
  "type": "Feature",
  "properties": {
    "iso:country":"US",
    "sg:address":"6102 W Maui Ln",
    "sg:city":"Glendale",
    "sg:classifiers":[
        {
            "category":"Professional",
            "type":"Services"
        }
    ],
    "sg:phone":"+1 602 439 4494",
    "sg:postcode":"85306",
    "sg:province":"AZ",
    "wof:name":"Classic Baseball International",
    "wof:placetype":"venue"
},
  "geometry": {"coordinates":[-112.191133,33.62115],"type":"Point"}
}