{
  "type": "Feature",
  "properties": {
    "iso:country":"US",
    "sg:address":"208 E Prince Rd",
    "sg:city":"Tucson",
    "sg:classifiers":[
        {
            "category":"Travel",
            "subcategory":"Hotels & Motels",
            "type":"Entertainment"
        }
    ],
    "sg:phone":"+1 520 887 6959",
    "sg:postcode":"85705",
    "sg:province":"AZ",
    "wof:name":"Parker Suites Hotel",
    "wof:placetype":"venue"
},
  "geometry": {"coordinates":[-110.970454,32.271916],"type":"Point"}
}