{
  "type": "Feature",
  "properties": {
    "addr:full":"15471 W Bell Rd Surprise AZ 85374",
    "addr:housenumber":"15471",
    "addr:postcode":"85374",
    "addr:street":"W Bell Rd",
    "iso:country":"US",
    "sg:address":"15471 W Bell Rd",
    "sg:city":"Surprise",
    "sg:classifiers":[
        {
            "category":"Restaurant",
            "type":"Food & Drink"
        }
    ],
    "sg:menulink":"http://www.allmenus.com/az/phoenix/231448-sonic/menu/",
    "sg:phone":"+1 623 584 5756",
    "sg:postcode":"85374",
    "sg:province":"AZ",
    "sg:tags":[
        "burger",
        "american"
    ],
    "wof:name":"Sonic",
    "wof:placetype":"venue"
},
  "geometry": {"coordinates":[-112.393371,33.63865],"type":"Point"}
}