{
  "type": "Feature",
  "properties": {
    "iso:country":"US",
    "sg:address":"400 N 5th St",
    "sg:city":"Phoenix",
    "sg:classifiers":[
        {
            "category":"Education",
            "subcategory":"Library",
            "type":"Public Place"
        }
    ],
    "sg:phone":"+1 602 250 2844",
    "sg:postcode":"85004",
    "sg:province":"AZ",
    "sg:tags":[
        "special",
        "interest"
    ],
    "wof:name":"Corporate Library",
    "wof:placetype":"venue"
},
  "geometry": {"coordinates":[-112.067481,33.453452],"type":"Point"}
}