{
  "type": "Feature",
  "properties": {
    "iso:country":"US",
    "sg:address":"139 E Southern Ave",
    "sg:city":"Tempe",
    "sg:classifiers":[
        {
            "category":"Social Services",
            "subcategory":"Child Care",
            "type":"Services"
        }
    ],
    "sg:phone":"+1 480 966 1151",
    "sg:postcode":"85282",
    "sg:province":"AZ",
    "sg:website":"www.lilmunchkinpreschool.com",
    "wof:name":"Li'l Munchkin",
    "wof:placetype":"venue"
},
  "geometry": {"coordinates":[-111.936711,33.392824],"type":"Point"}
}