{
  "type": "Feature",
  "properties": {
    "addr:full":"4144 E Indian School Rd Phoenix AZ 85018",
    "addr:housenumber":"4144",
    "addr:postcode":"85018",
    "addr:street":"E Indian School Rd",
    "iso:country":"US",
    "sg:address":"4144 E Indian School Rd",
    "sg:city":"Phoenix",
    "sg:classifiers":[
        {
            "category":"Restaurant",
            "type":"Food & Drink"
        }
    ],
    "sg:phone":"+1 602 956 0178",
    "sg:postcode":"85018",
    "sg:province":"AZ",
    "sg:website":"http://www.teepeemexicanfood.com",
    "wof:name":"Tee Pee Mexican Food",
    "wof:placetype":"venue"
},
  "geometry": {"coordinates":[-111.992065,33.494995],"type":"Point"}
}