{
  "type": "Feature",
  "properties": {
    "iso:country":"US",
    "sg:address":"16435 S Shoshone Trl",
    "sg:city":"Benson",
    "sg:classifiers":[
        {
            "category":"Shopping",
            "subcategory":"Gifts & Souvenirs",
            "type":"Retail Goods"
        }
    ],
    "sg:phone":"+1 520 360 5276",
    "sg:postcode":"85602",
    "sg:province":"AZ",
    "sg:tags":[
        "basket",
        "parcel"
    ],
    "wof:name":"Klassey Kreations",
    "wof:placetype":"venue"
},
  "geometry": {"coordinates":[-110.474434,31.956326],"type":"Point"}
}