{
  "type": "Feature",
  "properties": {
    "addr:full":"4631 W Orangewood Ave Glendale AZ 85301",
    "addr:housenumber":"4631",
    "addr:postcode":"85301",
    "addr:street":"W Orangewood Ave",
    "iso:country":"US",
    "sg:address":"4631 W Orangewood Ave",
    "sg:city":"Glendale",
    "sg:classifiers":[
        {
            "category":"Professional",
            "type":"Services"
        }
    ],
    "sg:phone":"+1 623 939 9294",
    "sg:postcode":"85301",
    "sg:province":"AZ",
    "wof:name":"Dennis M Williams",
    "wof:placetype":"venue"
},
  "geometry": {"coordinates":[-112.160118,33.545729],"type":"Point"}
}