{
  "type": "Feature",
  "properties": {
    "addr:full":"6025 N 27th Ave Ste 20 Phoenix AZ 85017",
    "addr:housenumber":"6025",
    "addr:postcode":"85017",
    "addr:street":"N 27Th Ave Ste 20",
    "iso:country":"US",
    "sg:address":"6025 N 27th Ave Ste 20",
    "sg:city":"Phoenix",
    "sg:classifiers":[
        {
            "category":"Retail",
            "subcategory":"Laundry & Dry Cleaning",
            "type":"Services"
        }
    ],
    "sg:phone":"+1 602 433 9655",
    "sg:postcode":"85017",
    "sg:province":"AZ",
    "sg:tags":[
        "commercial",
        "operated",
        "dryer",
        "laundries-self",
        "washer",
        "coin"
    ],
    "wof:name":"Super Kleen Laundry & Dry Clean",
    "wof:placetype":"venue"
},
  "geometry": {"coordinates":[-112.116913,33.524452],"type":"Point"}
}