{
  "type": "Feature",
  "properties": {
    "addr:full":"275 W Warner Rd Chandler AZ 85225",
    "addr:housenumber":"275",
    "addr:postcode":"85225",
    "addr:street":"W Warner Rd",
    "iso:country":"US",
    "sg:address":"275 W Warner Rd",
    "sg:city":"Chandler",
    "sg:classifiers":[
        {
            "category":"Personal",
            "subcategory":"Beauty Salon",
            "type":"Services"
        }
    ],
    "sg:phone":"+1 480 786 4843",
    "sg:postcode":"85225",
    "sg:province":"AZ",
    "sg:tags":[
        "manicuring"
    ],
    "wof:name":"MCM Nail Co",
    "wof:placetype":"venue"
},
  "geometry": {"coordinates":[-111.84629099999999,33.335042],"type":"Point"}
}