{
  "type": "Feature",
  "properties": {
    "iso:country":"US",
    "sg:address":"2390 E Camelback Rd",
    "sg:city":"Phoenix",
    "sg:classifiers":[
        {
            "category":"Real Estate",
            "subcategory":"Real Estate Services",
            "type":"Services"
        }
    ],
    "sg:phone":"+1 602 224 8500",
    "sg:postcode":"85016",
    "sg:province":"AZ",
    "sg:tags":[
        "company",
        "title"
    ],
    "sg:website":"www.fidelitymaricopa.com",
    "wof:name":"Fidelity National Title",
    "wof:placetype":"venue"
},
  "geometry": {"coordinates":[-112.032961,33.509362],"type":"Point"}
}