{
  "type": "Feature",
  "properties": {
    "iso:country":"US",
    "sg:address":"505 E 16th St",
    "sg:city":"Yuma",
    "sg:classifiers":[
        {
            "category":"Professional",
            "type":"Services"
        }
    ],
    "sg:phone":"+1 928 329 6222",
    "sg:postcode":"85365",
    "sg:province":"AZ",
    "wof:name":"Johnny Carinos",
    "wof:placetype":"venue"
},
  "geometry": {"coordinates":[-114.611931,32.698457],"type":"Point"}
}