{
  "type": "Feature",
  "properties": {
    "iso:country":"US",
    "sg:address":"3029 N Alma School Rd Ste 114",
    "sg:city":"Chandler",
    "sg:classifiers":[
        {
            "category":"Recreation",
            "subcategory":"Arcade",
            "type":"Entertainment"
        },
        {
            "category":"Bars & Pubs",
            "subcategory":"Sports Bar",
            "type":"Food & Drink"
        }
    ],
    "sg:phone":"+1 480 659 3280",
    "sg:postcode":"85225",
    "sg:province":"AZ",
    "sg:tags":[
        "hall",
        "pool"
    ],
    "wof:name":"Hollywood Billiards",
    "wof:placetype":"venue"
},
  "geometry": {"coordinates":[-111.858064,33.350965],"type":"Point"}
}