{
  "type": "Feature",
  "properties": {
    "iso:country":"US",
    "sg:address":"7511 E McDonald Dr",
    "sg:city":"Scottsdale",
    "sg:classifiers":[
        {
            "category":"Professional",
            "subcategory":"Business Services",
            "type":"Services"
        }
    ],
    "sg:phone":"+1 480 315 3737",
    "sg:postcode":"85250",
    "sg:province":"AZ",
    "sg:tags":[
        "interior",
        "consultant",
        "design",
        "decorator"
    ],
    "wof:name":"Exclaim Design",
    "wof:placetype":"venue"
},
  "geometry": {"coordinates":[-111.919986,33.523994],"type":"Point"}
}