{
  "type": "Feature",
  "properties": {
    "iso:country":"US",
    "sg:address":"633 E Ray Rd Ste 108",
    "sg:city":"Gilbert",
    "sg:classifiers":[
        {
            "category":"Real Estate",
            "subcategory":"Real Estate Services",
            "type":"Services"
        },
        {
            "category":"Real Estate",
            "subcategory":"Real Estate Agent",
            "type":"Services"
        }
    ],
    "sg:phone":"+1 480 699 0888",
    "sg:postcode":"85296",
    "sg:province":"AZ",
    "sg:tags":[
        "buyer",
        "broker"
    ],
    "wof:name":"Orange Realty",
    "wof:placetype":"venue"
},
  "geometry": {"coordinates":[-111.777022,33.321075],"type":"Point"}
}