{
  "type": "Feature",
  "properties": {
    "addr:full":"3232 Medicine Bow Dr Lake Havasu City AZ 86406",
    "addr:housenumber":"3232",
    "addr:postcode":"86406",
    "addr:street":"Medicine Bow Dr",
    "iso:country":"US",
    "sg:address":"3232 Medicine Bow Dr",
    "sg:city":"Lake Havasu City",
    "sg:classifiers":[
        {
            "category":"Retail",
            "subcategory":"Laundry & Dry Cleaning",
            "type":"Services"
        }
    ],
    "sg:phone":"+1 928 453 2717",
    "sg:postcode":"86406",
    "sg:province":"AZ",
    "sg:tags":[
        "cleaners",
        "rug",
        "carpet"
    ],
    "wof:name":"Service Master Co",
    "wof:placetype":"venue"
},
  "geometry": {"coordinates":[-114.282917,34.465607],"type":"Point"}
}