{
  "type": "Feature",
  "properties": {
    "addr:full":"15220 N Cave Creek Rd Phoenix AZ 85032",
    "addr:housenumber":"15220",
    "addr:postcode":"85032",
    "addr:street":"N Cave Creek Rd",
    "iso:country":"US",
    "sg:address":"15220 N Cave Creek Rd",
    "sg:city":"Phoenix",
    "sg:classifiers":[
        {
            "category":"Bars & Pubs",
            "type":"Food & Drink"
        }
    ],
    "sg:phone":"+1 602 992 0966",
    "sg:postcode":"85032",
    "sg:province":"AZ",
    "sg:tags":[
        "lounge",
        "cocktail"
    ],
    "wof:name":"No Name Lounge",
    "wof:placetype":"venue"
},
  "geometry": {"coordinates":[-112.030772,33.624025],"type":"Point"}
}