{
  "type": "Feature",
  "properties": {
    "iso:country":"US",
    "sg:address":"200 N Dysart Rd",
    "sg:city":"Avondale",
    "sg:classifiers":[
        {
            "category":"Education",
            "subcategory":"School",
            "type":"Public Place"
        }
    ],
    "sg:phone":"+1 623 932 9902",
    "sg:postcode":"85323",
    "sg:province":"AZ",
    "sg:tags":[
        "high",
        "middle",
        "elementary"
    ],
    "sg:website":"www.bradleyacademyofexcellence.com",
    "wof:name":"Bradley Academy of Excellence",
    "wof:placetype":"venue"
},
  "geometry": {"coordinates":[-112.341383,33.437208],"type":"Point"}
}