{
  "type": "Feature",
  "properties": {
    "iso:country":"US",
    "sg:address":"2150 W University Dr",
    "sg:city":"Tempe",
    "sg:classifiers":[
        {
            "category":"Manufacturing",
            "subcategory":"Glass & Minerals",
            "type":"Manufacturing & Wholesale Goods"
        },
        {
            "category":"Retail",
            "subcategory":"Auto Repair",
            "type":"Services"
        }
    ],
    "sg:phone":"+1 480 967 6167",
    "sg:postcode":"85281",
    "sg:province":"AZ",
    "sg:tags":[
        "plate",
        "doors-glass",
        "shape",
        "glass-auto",
        "window",
        "circle",
        "windshield",
        "special",
        "replacement"
    ],
    "sg:website":"http://www.speedyglass.com",
    "wof:name":"Speedy Glass",
    "wof:placetype":"venue"
},
  "geometry": {"coordinates":[-111.97125,33.421933],"type":"Point"}
}