{
  "type": "Feature",
  "properties": {
    "iso:country":"US",
    "sg:address":"66 Fairbanks Rd",
    "sg:city":"Morenci",
    "sg:classifiers":[
        {
            "category":"Mining & Drilling",
            "type":"Manufacturing & Wholesale Goods"
        }
    ],
    "sg:phone":"+1 928 865 2229",
    "sg:postcode":"85540",
    "sg:province":"AZ",
    "wof:name":"Morenci Water & Electric Company",
    "wof:placetype":"venue"
},
  "geometry": {"coordinates":[-109.32374900000001,33.048614],"type":"Point"}
}