{
  "type": "Feature",
  "properties": {
    "addr:full":"3355 W Chandler Blvd Chandler AZ 85226",
    "addr:housenumber":"3355",
    "addr:postcode":"85226",
    "addr:street":"W Chandler Blvd",
    "iso:country":"US",
    "sg:address":"3355 W Chandler Blvd",
    "sg:city":"Chandler",
    "sg:classifiers":[
        {
            "category":"Shopping",
            "subcategory":"Jewelry",
            "type":"Retail Goods"
        }
    ],
    "sg:phone":"+1 480 857 0256",
    "sg:postcode":"85226",
    "sg:province":"AZ",
    "sg:tags":[
        "jeweler"
    ],
    "wof:name":"Gotta Have It Jewelry & Acces",
    "wof:placetype":"venue"
},
  "geometry": {"coordinates":[-111.900268,33.305599],"type":"Point"}
}