{
  "type": "Feature",
  "properties": {
    "iso:country":"US",
    "sg:address":"1085 Chaparral Dr",
    "sg:city":"Bullhead City",
    "sg:classifiers":[
        {
            "category":"Health Services",
            "subcategory":"Clinic",
            "type":"Services"
        }
    ],
    "sg:phone":"+1 928 763 5016",
    "sg:postcode":"86442",
    "sg:province":"AZ",
    "wof:name":"Aston William H Life & Health",
    "wof:placetype":"venue"
},
  "geometry": {"coordinates":[-114.612098,35.086134],"type":"Point"}
}