{
  "type": "Feature",
  "properties": {
    "iso:country":"US",
    "sg:address":"5946 N Black Canyon Hwy",
    "sg:city":"Phoenix",
    "sg:classifiers":[
        {
            "category":"Personal",
            "subcategory":"Beauty Salon",
            "type":"Services"
        }
    ],
    "sg:phone":"+1 602 242 1295",
    "sg:postcode":"85017",
    "sg:province":"AZ",
    "sg:tags":[
        "cosmetologist"
    ],
    "wof:name":"Terry's Beauty Salon",
    "wof:placetype":"venue"
},
  "geometry": {"coordinates":[-112.112728,33.523295],"type":"Point"}
}