{
  "type": "Feature",
  "properties": {
    "iso:country":"US",
    "sg:address":"313 S Beeline Hwy",
    "sg:city":"Payson",
    "sg:classifiers":[
        {
            "category":"Health Services",
            "subcategory":"Doctor",
            "type":"Services"
        },
        {
            "category":"Health Services",
            "subcategory":"Clinic",
            "type":"Services"
        },
        {
            "category":"Community Center",
            "type":"Public Place"
        }
    ],
    "sg:phone":"+1 928 472 7107",
    "sg:postcode":"85541",
    "sg:province":"AZ",
    "sg:tags":[
        "dermatology",
        "physician",
        "medical",
        "surgeons",
        "surgeon"
    ],
    "wof:name":"Payson Dermatology",
    "wof:placetype":"venue"
},
  "geometry": {"coordinates":[-111.323066,34.238276],"type":"Point"}
}