{
  "type": "Feature",
  "properties": {
    "iso:country":"US",
    "sg:address":"402 Maurice Ave",
    "sg:city":"Fredonia",
    "sg:classifiers":[
        {
            "category":"Wholesale",
            "subcategory":"Machinery & Supplies",
            "type":"Manufacturing & Wholesale Goods"
        }
    ],
    "sg:phone":"+1 928 643 7908",
    "sg:postcode":"86022",
    "sg:province":"AZ",
    "sg:tags":[
        "janitor"
    ],
    "wof:name":"Dadson Products",
    "wof:placetype":"venue"
},
  "geometry": {"coordinates":[-112.520533,36.943225],"type":"Point"}
}