{
  "type": "Feature",
  "properties": {
    "iso:country":"US",
    "sg:address":"3221 N 16th St",
    "sg:city":"Phoenix",
    "sg:classifiers":[
        {
            "category":"Professional",
            "type":"Services"
        }
    ],
    "sg:phone":"+1 602 494 9610",
    "sg:postcode":"85016",
    "sg:province":"AZ",
    "sg:tags":[
        "establishment"
    ],
    "wof:name":"Hester Heitel & Assoc Heitel",
    "wof:placetype":"venue"
},
  "geometry": {"coordinates":[-112.04757600000001,33.48428],"type":"Point"}
}