{
  "type": "Feature",
  "properties": {
    "addr:full":"2838 N Yucca St Chandler AZ 85224",
    "addr:housenumber":"2838",
    "addr:postcode":"85224",
    "addr:street":"N Yucca St",
    "iso:country":"US",
    "sg:address":"2838 N Yucca St",
    "sg:city":"Chandler",
    "sg:classifiers":[
        {
            "category":"Building & Trades",
            "subcategory":"Electrical",
            "type":"Services"
        }
    ],
    "sg:phone":"+1 480 821 2624",
    "sg:postcode":"85224",
    "sg:province":"AZ",
    "sg:tags":[
        "electrician",
        "contractor"
    ],
    "wof:name":"Ker Electric Inc",
    "wof:placetype":"venue"
},
  "geometry": {"coordinates":[-111.875,33.348099],"type":"Point"}
}