{
  "type": "Feature",
  "properties": {
    "addr:full":"8027 S Avenida del Yaqui Guadalupe AZ 85283",
    "addr:housenumber":"8027",
    "addr:postcode":"85283",
    "addr:street":"S Avenida Del Yaqui",
    "iso:country":"US",
    "sg:address":"8027 S Avenida del Yaqui",
    "sg:city":"Guadalupe",
    "sg:classifiers":[
        {
            "category":"Transit Center",
            "subcategory":"Freight",
            "type":"Transportation"
        },
        {
            "category":"Freight",
            "type":"Transportation"
        }
    ],
    "sg:phone":"+1 480 839 2781",
    "sg:postcode":"85283",
    "sg:province":"AZ",
    "sg:tags":[
        "local",
        "trucking-motor",
        "trucking"
    ],
    "wof:name":"R Hernandez Trucking Co",
    "wof:placetype":"venue"
},
  "geometry": {"coordinates":[-111.96317500000001,33.373694],"type":"Point"}
}