{
  "type": "Feature",
  "properties": {
    "iso:country":"US",
    "sg:address":"16323 E Carmel Dr",
    "sg:city":"Fountain Hills",
    "sg:classifiers":[
        {
            "category":"Building & Trades",
            "subcategory":"Plumbing",
            "type":"Services"
        }
    ],
    "sg:phone":"+1 480 837 8860",
    "sg:postcode":"85268",
    "sg:province":"AZ",
    "sg:tags":[
        "plumbing",
        "contractor"
    ],
    "wof:name":"Fountain Hills Plumbing Co",
    "wof:placetype":"venue"
},
  "geometry": {"coordinates":[-111.729653,33.622772],"type":"Point"}
}