{
  "type": "Feature",
  "properties": {
    "iso:country":"US",
    "sg:address":"3230 E Union Hills Dr",
    "sg:city":"Phoenix",
    "sg:classifiers":[
        {
            "category":"Restaurant",
            "type":"Food & Drink"
        }
    ],
    "sg:menulink":"http://www.allmenus.com/az/phoenix/77730-papa-murphys/menu/",
    "sg:phone":"+1 602 867 7272",
    "sg:postcode":"85050",
    "sg:province":"AZ",
    "sg:tags":[
        "american",
        "pizza"
    ],
    "wof:name":"Papa Murphy's",
    "wof:placetype":"venue"
},
  "geometry": {"coordinates":[-112.012653,33.655269],"type":"Point"}
}