{
  "type": "Feature",
  "properties": {
    "iso:country":"US",
    "sg:address":"2432 W Peoria Ave",
    "sg:city":"Phoenix",
    "sg:classifiers":[
        {
            "category":"Building & Trades",
            "subcategory":"Electrical",
            "type":"Services"
        }
    ],
    "sg:phone":"+1 602 674 3072",
    "sg:postcode":"85029",
    "sg:province":"AZ",
    "sg:tags":[
        "electrician"
    ],
    "sg:website":"http://www.greaterphoenixelectric.com",
    "wof:name":"Greater Phoenix Electric Incorporated",
    "wof:placetype":"venue"
},
  "geometry": {"coordinates":[-112.111184,33.581989],"type":"Point"}
}