{
  "type": "Feature",
  "properties": {
    "iso:country":"US",
    "sg:address":"3105 E Fry Blvd",
    "sg:city":"Sierra Vista",
    "sg:classifiers":[
        {
            "category":"Government",
            "subcategory":"Office",
            "type":"Public Place"
        }
    ],
    "sg:phone":"+1 520 459 4377",
    "sg:postcode":"85635",
    "sg:province":"AZ",
    "sg:tags":[
        "village"
    ],
    "wof:name":"Sierra Vista Youth Ctr Bldg",
    "wof:placetype":"venue"
},
  "geometry": {"coordinates":[-110.266959,31.554706],"type":"Point"}
}