{
  "type": "Feature",
  "properties": {
    "iso:country":"US",
    "sg:address":"18002 Mustang Way",
    "sg:city":"Scottsdale",
    "sg:classifiers":[
        {
            "category":"Farming",
            "subcategory":"Livestock Farm",
            "type":"Manufacturing & Wholesale Goods"
        }
    ],
    "sg:phone":"+1 480 837 2585",
    "sg:postcode":"85264",
    "sg:province":"AZ",
    "sg:tags":[
        "ranch"
    ],
    "wof:name":"Fort Mc Dowell Tribal Farms",
    "wof:placetype":"venue"
},
  "geometry": {"coordinates":[-111.668974,33.686193],"type":"Point"}
}