{
  "type": "Feature",
  "properties": {
    "addr:full":"1404 W Weston Trl Flagstaff AZ 86001",
    "addr:housenumber":"1404",
    "addr:postcode":"86001",
    "addr:street":"W Weston Trl",
    "iso:country":"US",
    "sg:address":"1404 W Weston Trl",
    "sg:city":"Flagstaff",
    "sg:classifiers":[
        {
            "category":"Building & Trades",
            "subcategory":"Construction",
            "type":"Services"
        }
    ],
    "sg:phone":"+1 928 221 6162",
    "sg:postcode":"86001",
    "sg:province":"AZ",
    "sg:tags":[
        "system",
        "contractor",
        "air conditioning"
    ],
    "wof:name":"Flagstaff Hawk Air Conditioning Heating",
    "wof:placetype":"venue"
},
  "geometry": {"coordinates":[-111.673507,35.157324],"type":"Point"}
}