{
  "type": "Feature",
  "properties": {
    "iso:country":"US",
    "sg:address":"11811 N Tami Pl",
    "sg:city":"Tucson",
    "sg:classifiers":[
        {
            "category":"Shopping",
            "type":"Retail Goods"
        }
    ],
    "sg:phone":"+1 520 297 2282",
    "sg:postcode":"85737",
    "sg:province":"AZ",
    "sg:tags":[
        "merchandise"
    ],
    "wof:name":"Arizona PHD Pet Academy",
    "wof:placetype":"venue"
},
  "geometry": {"coordinates":[-110.966864,32.421038],"type":"Point"}
}