{
  "type": "Feature",
  "properties": {
    "iso:country":"US",
    "sg:address":"7414 W Aurora Dr",
    "sg:city":"Glendale",
    "sg:classifiers":[
        {
            "category":"Building & Trades",
            "subcategory":"Construction",
            "type":"Services"
        }
    ],
    "sg:phone":"+1 623 266 0068",
    "sg:postcode":"85308",
    "sg:province":"AZ",
    "sg:tags":[
        "contractor"
    ],
    "wof:name":"Horizon Caulking LLC",
    "wof:placetype":"venue"
},
  "geometry": {"coordinates":[-112.217697,33.678321],"type":"Point"}
}