{
  "type": "Feature",
  "properties": {
    "iso:country":"US",
    "sg:address":"2296 N Pinal Ave",
    "sg:city":"Casa Grande",
    "sg:classifiers":[
        {
            "category":"Professional",
            "subcategory":"Management & Consulting",
            "type":"Services"
        }
    ],
    "sg:phone":"+1 520 421 1223",
    "sg:postcode":"85222",
    "sg:province":"AZ",
    "sg:tags":[
        "heavy"
    ],
    "wof:name":"Pro-Turf International Inc",
    "wof:placetype":"venue"
},
  "geometry": {"coordinates":[-111.756969,32.917674],"type":"Point"}
}