{
  "type": "Feature",
  "properties": {
    "iso:country":"US",
    "sg:address":"14749 E Pecos Rd",
    "sg:city":"Gilbert",
    "sg:classifiers":[
        {
            "category":"Recreation",
            "type":"Entertainment"
        }
    ],
    "sg:phone":"+1 480 786 0703",
    "sg:postcode":"85295",
    "sg:province":"AZ",
    "sg:tags":[
        "instruction",
        "swimming"
    ],
    "wof:name":"Summer Splash",
    "wof:placetype":"venue"
},
  "geometry": {"coordinates":[-111.706126,33.292532],"type":"Point"}
}