{
  "type": "Feature",
  "properties": {
    "addr:full":"4749 E Southern Ave Mesa AZ 85206",
    "addr:housenumber":"4749",
    "addr:postcode":"85206",
    "addr:street":"E Southern Ave",
    "iso:country":"US",
    "sg:address":"4749 E Southern Ave",
    "sg:city":"Mesa",
    "sg:classifiers":[
        {
            "category":"Restaurant",
            "type":"Food & Drink"
        }
    ],
    "sg:phone":"+1 602 438 0578",
    "sg:postcode":"85206",
    "sg:province":"AZ",
    "sg:website":"http://www.jackinthebox.com",
    "wof:name":"Jack in the Box",
    "wof:placetype":"venue"
},
  "geometry": {"coordinates":[-111.72894100000001,33.393815],"type":"Point"}
}