{
  "type": "Feature",
  "properties": {
    "iso:country":"US",
    "sg:address":"428 E Thunderbird Rd",
    "sg:city":"Phoenix",
    "sg:classifiers":[
        {
            "category":"Professional",
            "subcategory":"Business Services",
            "type":"Services"
        }
    ],
    "sg:phone":"+1 602 828 9936",
    "sg:postcode":"85022",
    "sg:province":"AZ",
    "sg:tags":[
        "plant",
        "design",
        "maintenance"
    ],
    "wof:name":"A Plantz Life",
    "wof:placetype":"venue"
},
  "geometry": {"coordinates":[-112.06618,33.607703],"type":"Point"}
}