{
  "type": "Feature",
  "properties": {
    "iso:country":"US",
    "sg:address":"615 W Sterling Pl",
    "sg:city":"Chandler",
    "sg:classifiers":[
        {
            "category":"Building & Trades",
            "subcategory":"Electrical",
            "type":"Services"
        }
    ],
    "sg:phone":"+1 480 820 7502",
    "sg:postcode":"85225",
    "sg:province":"AZ",
    "sg:tags":[
        "electric",
        "contractor"
    ],
    "wof:name":"Gazy",
    "wof:placetype":"venue"
},
  "geometry": {"coordinates":[-111.852069,33.356116],"type":"Point"}
}