{
  "type": "Feature",
  "properties": {
    "addr:full":"4596 N Robert Rd Prescott Valley AZ 86314",
    "addr:housenumber":"4596",
    "addr:postcode":"86314",
    "addr:street":"N Robert Rd",
    "iso:country":"US",
    "sg:address":"4596 N Robert Rd",
    "sg:city":"Prescott Valley",
    "sg:classifiers":[
        {
            "category":"Restaurant",
            "type":"Food & Drink"
        }
    ],
    "sg:phone":"+1 928 775 3288",
    "sg:postcode":"86314",
    "sg:province":"AZ",
    "wof:name":"Spirit Gas Station",
    "wof:placetype":"venue"
},
  "geometry": {"coordinates":[-112.32078199999999,34.609113],"type":"Point"}
}