{
  "type": "Feature",
  "properties": {
    "iso:country":"US",
    "sg:address":"1850 N Central Ave # 930",
    "sg:city":"Phoenix",
    "sg:classifiers":[
        {
            "category":"Professional",
            "subcategory":"Lawyer & Legal Services",
            "type":"Services"
        }
    ],
    "sg:phone":"+1 602 808 7770",
    "sg:postcode":"85004",
    "sg:province":"AZ",
    "sg:tags":[
        "attorney",
        "law",
        "business",
        "bankruptcy"
    ],
    "wof:name":"Mason Bankruptcy Trustee",
    "wof:placetype":"venue"
},
  "geometry": {"coordinates":[-112.073921,33.468552],"type":"Point"}
}