{
  "type": "Feature",
  "properties": {
    "iso:country":"US",
    "sg:address":"3652 S 16th Ave",
    "sg:city":"Tucson",
    "sg:classifiers":[
        {
            "category":"Professional",
            "subcategory":"Business Services",
            "type":"Services"
        },
        {
            "category":"Government",
            "subcategory":"Post Office",
            "type":"Public Place"
        }
    ],
    "sg:phone":"+1 800 275 8777",
    "sg:postcode":"85713",
    "sg:province":"AZ",
    "sg:tags":[
        "mail",
        "shipping"
    ],
    "sg:website":"http://www.usps.com",
    "wof:name":"USPS - United States Post Office - CPU Wendys Hallmark",
    "wof:placetype":"venue"
},
  "geometry": {"coordinates":[-110.981306,32.178778],"type":"Point"}
}