{
  "type": "Feature",
  "properties": {
    "iso:country":"US",
    "sg:address":"923 N Swan Rd",
    "sg:city":"Tucson",
    "sg:classifiers":[
        {
            "category":"Professional",
            "subcategory":"Business Services",
            "type":"Services"
        }
    ],
    "sg:phone":"+1 520 326 5264",
    "sg:postcode":"85711",
    "sg:province":"AZ",
    "sg:tags":[
        "shop",
        "sign"
    ],
    "wof:name":"Budget Signs & Graphics",
    "wof:placetype":"venue"
},
  "geometry": {"coordinates":[-110.892652,32.234937],"type":"Point"}
}