{
  "type": "Feature",
  "properties": {
    "iso:country":"US",
    "sg:address":"5440 S 43rd Ave",
    "sg:city":"Phoenix",
    "sg:classifiers":[
        {
            "category":"Building & Trades",
            "subcategory":"Plumbing",
            "type":"Services"
        },
        {
            "category":"Home & Garden",
            "subcategory":"Building Materials",
            "type":"Retail Goods"
        },
        {
            "category":"Building & Trades",
            "subcategory":"Construction",
            "type":"Services"
        }
    ],
    "sg:phone":"+1 602 273 7473",
    "sg:postcode":"85041",
    "sg:province":"AZ",
    "sg:tags":[
        "heater",
        "plumber",
        "system",
        "contractor",
        "water",
        "air conditioning"
    ],
    "wof:name":"Stevens Plumbing Inc Heating",
    "wof:placetype":"venue"
},
  "geometry": {"coordinates":[-112.150879,33.397121],"type":"Point"}
}