{
  "type": "Feature",
  "properties": {
    "iso:country":"US",
    "sg:address":"140 S Ash Ave",
    "sg:city":"Tempe",
    "sg:classifiers":[
        {
            "category":"Local Transit",
            "type":"Transportation"
        }
    ],
    "sg:phone":"+1 480 759 4330",
    "sg:postcode":"85281",
    "sg:province":"AZ",
    "sg:tags":[
        "airport",
        "limousine"
    ],
    "wof:name":"Hallmark Limousine Ltd",
    "wof:placetype":"venue"
},
  "geometry": {"coordinates":[-111.94259099999999,33.428992],"type":"Point"}
}