{
  "type": "Feature",
  "properties": {
    "iso:country":"US",
    "sg:address":"12950 W Alegre Dr",
    "sg:city":"Litchfield Park",
    "sg:classifiers":[
        {
            "category":"Restaurant",
            "type":"Food & Drink"
        }
    ],
    "sg:phone":"+1 623 935 5334",
    "sg:postcode":"85340",
    "sg:province":"AZ",
    "sg:tags":[
        "caterer"
    ],
    "wof:name":"Elegant Memories",
    "wof:placetype":"venue"
},
  "geometry": {"coordinates":[-112.338684,33.50054],"type":"Point"}
}