{
  "type": "Feature",
  "properties": {
    "addr:full":"3126 W Thomas Rd Phoenix AZ 85017",
    "addr:housenumber":"3126",
    "addr:postcode":"85017",
    "addr:street":"W Thomas Rd",
    "iso:country":"US",
    "sg:address":"3126 W Thomas Rd",
    "sg:city":"Phoenix",
    "sg:classifiers":[
        {
            "category":"Manufacturing",
            "subcategory":"Furniture",
            "type":"Manufacturing & Wholesale Goods"
        }
    ],
    "sg:phone":"+1 602 233 0885",
    "sg:postcode":"85017",
    "sg:province":"AZ",
    "sg:tags":[
        "household",
        "wood",
        "mfg"
    ],
    "wof:name":"J JS Furniture",
    "wof:placetype":"venue"
},
  "geometry": {"coordinates":[-112.126946,33.480512],"type":"Point"}
}