{
  "type": "Feature",
  "properties": {
    "iso:country":"US",
    "sg:address":"7655 W Whitton Ave",
    "sg:city":"Phoenix",
    "sg:classifiers":[
        {
            "category":"Shopping",
            "subcategory":"Hobbies, Toys, & Games",
            "type":"Retail Goods"
        }
    ],
    "sg:phone":"+1 623 849 6022",
    "sg:postcode":"85033",
    "sg:province":"AZ",
    "sg:tags":[
        "gun",
        "gunsmith"
    ],
    "wof:name":"Studio Infinity",
    "wof:placetype":"venue"
},
  "geometry": {"coordinates":[-112.224626,33.490119],"type":"Point"}
}