{
  "type": "Feature",
  "properties": {
    "iso:country":"US",
    "sg:address":"2501 W Happy Valley Rd",
    "sg:city":"Phoenix",
    "sg:classifiers":[
        {
            "category":"Utilities",
            "subcategory":"Mobile Phone",
            "type":"Services"
        },
        {
            "category":"Shopping",
            "subcategory":"Mobile Phones",
            "type":"Retail Goods"
        }
    ],
    "sg:phone":"+1 623 434 4719",
    "sg:postcode":"85085",
    "sg:province":"AZ",
    "sg:tags":[
        "supply",
        "communication",
        "telephone",
        "wireless",
        "equipment",
        "cellular"
    ],
    "wof:name":"Verizon Wireless",
    "wof:placetype":"venue"
},
  "geometry": {"coordinates":[-112.11174,33.712799],"type":"Point"}
}