{
  "type": "Feature",
  "properties": {
    "iso:country":"US",
    "sg:address":"7917 N 68th Ave",
    "sg:city":"Glendale",
    "sg:classifiers":[
        {
            "category":"Bars & Pubs",
            "type":"Food & Drink"
        }
    ],
    "sg:phone":"+1 623 937 7465",
    "sg:postcode":"85303",
    "sg:province":"AZ",
    "sg:tags":[
        "club",
        "night"
    ],
    "wof:name":"Pink Caberet",
    "wof:placetype":"venue"
},
  "geometry": {"coordinates":[-112.204347,33.551749],"type":"Point"}
}