{
  "type": "Feature",
  "properties": {
    "iso:country":"US",
    "sg:address":"282 E Harrison St",
    "sg:city":"Gilbert",
    "sg:classifiers":[
        {
            "category":"Professional",
            "subcategory":"Management & Consulting",
            "type":"Services"
        }
    ],
    "sg:phone":"+1 480 726 9633",
    "sg:postcode":"85295",
    "sg:province":"AZ",
    "sg:tags":[
        "consultant"
    ],
    "sg:website":"http://www.macfab.com",
    "wof:name":"Macfab",
    "wof:placetype":"venue"
},
  "geometry": {"coordinates":[-111.784149,33.315566],"type":"Point"}
}