{
  "type": "Feature",
  "properties": {
    "addr:full":"24210 S Oakwood Boulevard Sun Lakes AZ 85248",
    "addr:housenumber":"24210",
    "addr:postcode":"85248",
    "addr:street":"S Oakwood Boulevard",
    "iso:country":"US",
    "sg:address":"24210 S Oakwood Boulevard",
    "sg:city":"Sun Lakes",
    "sg:classifiers":[
        {
            "category":"Sports & Exercise",
            "subcategory":"Gym",
            "type":"Entertainment"
        }
    ],
    "sg:phone":"+1 480 895 2476",
    "sg:postcode":"85248",
    "sg:province":"AZ",
    "wof:name":"Oakwood Health Center",
    "wof:placetype":"venue"
},
  "geometry": {"coordinates":[-111.854951,33.227927],"type":"Point"}
}