{
  "type": "Feature",
  "properties": {
    "iso:country":"US",
    "sg:address":"2706 E Chambers St",
    "sg:city":"Phoenix",
    "sg:classifiers":[
        {
            "category":"Wholesale",
            "subcategory":"Machinery & Supplies",
            "type":"Manufacturing & Wholesale Goods"
        }
    ],
    "sg:phone":"+1 602 305 8273",
    "sg:postcode":"85040",
    "sg:province":"AZ",
    "sg:tags":[
        "tape",
        "tapes-industrial"
    ],
    "sg:website":"www.brontapesofarizona.com",
    "wof:name":"Bron Tapes Of Arizona",
    "wof:placetype":"venue"
},
  "geometry": {"coordinates":[-112.022823,33.397642],"type":"Point"}
}