{
  "type": "Feature",
  "properties": {
    "iso:country":"US",
    "sg:address":"143 W Vaughn Ave",
    "sg:city":"Gilbert",
    "sg:classifiers":[
        {
            "category":"Retail",
            "subcategory":"Animal Services",
            "type":"Services"
        },
        {
            "category":"Organizations",
            "subcategory":"Membership Organization",
            "type":"Services"
        }
    ],
    "sg:phone":"+1 480 497 8296",
    "sg:postcode":"85233",
    "sg:province":"AZ",
    "sg:tags":[
        "pet",
        "shelter",
        "store"
    ],
    "sg:website":"www.azfriends.org",
    "wof:name":"Friends For Life",
    "wof:placetype":"venue"
},
  "geometry": {"coordinates":[-111.79299899999999,33.3559],"type":"Point"}
}