{
  "type": "Feature",
  "properties": {
    "iso:country":"US",
    "sg:address":"252 E Cherry St Ste A",
    "sg:city":"Cottonwood",
    "sg:classifiers":[
        {
            "category":"Home & Garden",
            "subcategory":"Furniture",
            "type":"Retail Goods"
        }
    ],
    "sg:phone":"+1 928 649 8305",
    "sg:postcode":"86326",
    "sg:province":"AZ",
    "sg:tags":[
        "store"
    ],
    "wof:name":"Home Furnishings Direct",
    "wof:placetype":"venue"
},
  "geometry": {"coordinates":[-112.025544,34.732939],"type":"Point"}
}