{
  "type": "Feature",
  "properties": {
    "addr:full":"6131 E Southern Ave Mesa AZ 85206",
    "addr:housenumber":"6131",
    "addr:postcode":"85206",
    "addr:street":"E Southern Ave",
    "iso:country":"US",
    "sg:address":"6131 E Southern Ave",
    "sg:city":"Mesa",
    "sg:classifiers":[
        {
            "category":"Restaurant",
            "type":"Food & Drink"
        }
    ],
    "sg:menulink":"http://www.allmenus.com/az/phoenix/190551-mcdonalds/menu/",
    "sg:postcode":"85206",
    "sg:province":"AZ",
    "sg:tags":[
        "burger",
        "american"
    ],
    "wof:name":"McDonald's",
    "wof:placetype":"venue"
},
  "geometry": {"coordinates":[-111.698916,33.393827],"type":"Point"}
}