{
  "type": "Feature",
  "properties": {
    "iso:country":"US",
    "sg:address":"7840 Candi Ln",
    "sg:city":"Flagstaff",
    "sg:classifiers":[
        {
            "category":"Building & Trades",
            "subcategory":"Landscaping Services",
            "type":"Services"
        }
    ],
    "sg:phone":"+1 928 714 1232",
    "sg:postcode":"86004",
    "sg:province":"AZ",
    "sg:tags":[
        "tree"
    ],
    "wof:name":"Gauns Tree Service",
    "wof:placetype":"venue"
},
  "geometry": {"coordinates":[-111.551115,35.250178],"type":"Point"}
}