{
  "type": "Feature",
  "properties": {
    "iso:country":"US",
    "sg:address":"300 S 55th Ave",
    "sg:city":"Phoenix",
    "sg:classifiers":[
        {
            "category":"Structure",
            "subcategory":"Warehouse",
            "type":"Public Place"
        },
        {
            "category":"Retail",
            "subcategory":"Storage",
            "type":"Services"
        }
    ],
    "sg:phone":"+1 602 477 8013",
    "sg:postcode":"85043",
    "sg:province":"AZ",
    "sg:tags":[
        "self",
        "warehouses-public-commercial"
    ],
    "sg:website":"http://www.theloanauthority.com",
    "wof:name":"Home Depot, The",
    "wof:placetype":"venue"
},
  "geometry": {"coordinates":[-112.177757,33.443871],"type":"Point"}
}