{
  "type": "Feature",
  "properties": {
    "iso:country":"US",
    "sg:address":"3500 N Campbell Ave",
    "sg:city":"Tucson",
    "sg:classifiers":[
        {
            "category":"Government",
            "subcategory":"Office",
            "type":"Public Place"
        }
    ],
    "sg:phone":"+1 520 670 5054",
    "sg:postcode":"85719",
    "sg:province":"AZ",
    "sg:tags":[
        "security",
        "administration",
        "social"
    ],
    "wof:name":"Social Security Administration",
    "wof:placetype":"venue"
},
  "geometry": {"coordinates":[-110.943788,32.272208],"type":"Point"}
}