{
  "type": "Feature",
  "properties": {
    "addr:full":"1445 W Southern Ave Mesa AZ 85210",
    "addr:housenumber":"1445",
    "addr:postcode":"85210",
    "addr:street":"W Southern Ave",
    "iso:country":"US",
    "sg:address":"1445 W Southern Ave",
    "sg:city":"Mesa",
    "sg:classifiers":[
        {
            "category":"Shopping",
            "subcategory":"Jewelry",
            "type":"Retail Goods"
        }
    ],
    "sg:phone":"+1 480 649 6122",
    "sg:postcode":"85210",
    "sg:province":"AZ",
    "sg:website":"arizonadiamondcenter.com",
    "wof:name":"Arizona Diamond Center",
    "wof:placetype":"venue"
},
  "geometry": {"coordinates":[-111.86058,33.3892],"type":"Point"}
}