{
  "type": "Feature",
  "properties": {
    "addr:full":"2541 N 76th Pl Mesa AZ 85207",
    "addr:housenumber":"2541",
    "addr:postcode":"85207",
    "addr:street":"N 76Th Pl",
    "iso:country":"US",
    "sg:address":"2541 N 76th Pl",
    "sg:city":"Mesa",
    "sg:classifiers":[
        {
            "category":"Building & Trades",
            "subcategory":"Construction",
            "type":"Services"
        }
    ],
    "sg:phone":"+1 480 357 6825",
    "sg:postcode":"85207",
    "sg:province":"AZ",
    "sg:tags":[
        "contractor"
    ],
    "wof:name":"Christy Custom Masonry Inc",
    "wof:placetype":"venue"
},
  "geometry": {"coordinates":[-111.666031,33.462122],"type":"Point"}
}