{
  "type": "Feature",
  "properties": {
    "addr:full":"3614 E Orange Dr Phoenix AZ 85018",
    "addr:housenumber":"3614",
    "addr:postcode":"85018",
    "addr:street":"E Orange Dr",
    "iso:country":"US",
    "sg:address":"3614 E Orange Dr",
    "sg:city":"Phoenix",
    "sg:classifiers":[
        {
            "category":"Farming",
            "subcategory":"Farm",
            "type":"Manufacturing & Wholesale Goods"
        }
    ],
    "sg:phone":"+1 602 956 7959",
    "sg:postcode":"85018",
    "sg:province":"AZ",
    "wof:name":"The Ranch Mine",
    "wof:placetype":"venue"
},
  "geometry": {"coordinates":[-112.003455,33.513103],"type":"Point"}
}