{
  "type": "Feature",
  "properties": {
    "iso:country":"US",
    "sg:address":"2385 N Pima Dr",
    "sg:city":"Lake Havasu City",
    "sg:classifiers":[
        {
            "category":"Social Services",
            "subcategory":"Child Care",
            "type":"Services"
        }
    ],
    "sg:phone":"+1 928 680 6212",
    "sg:postcode":"86403",
    "sg:province":"AZ",
    "sg:tags":[
        "kindergarten",
        "academic",
        "school"
    ],
    "wof:name":"Head START-Wacog",
    "wof:placetype":"venue"
},
  "geometry": {"coordinates":[-114.322428,34.486346],"type":"Point"}
}