{
  "type": "Feature",
  "properties": {
    "addr:full":"836 E 7th St Tucson AZ 85719",
    "addr:housenumber":"836",
    "addr:postcode":"85719",
    "addr:street":"E 7Th St",
    "iso:country":"US",
    "sg:address":"836 E 7th St",
    "sg:city":"Tucson",
    "sg:classifiers":[
        {
            "category":"Building & Trades",
            "subcategory":"Construction",
            "type":"Services"
        }
    ],
    "sg:phone":"+1 520 882 0191",
    "sg:postcode":"85719",
    "sg:province":"AZ",
    "sg:tags":[
        "house"
    ],
    "wof:name":"Territon Builders Inc",
    "wof:placetype":"venue"
},
  "geometry": {"coordinates":[-110.95843499999999,32.226381],"type":"Point"}
}