{
  "type": "Feature",
  "properties": {
    "iso:country":"US",
    "sg:address":"4334 W Highland Ave",
    "sg:city":"Phoenix",
    "sg:classifiers":[
        {
            "category":"Wholesale",
            "subcategory":"Groceries",
            "type":"Manufacturing & Wholesale Goods"
        }
    ],
    "sg:phone":"+1 623 848 7228",
    "sg:postcode":"85031",
    "sg:province":"AZ",
    "wof:name":"United Food Service",
    "wof:placetype":"venue"
},
  "geometry": {"coordinates":[-112.153645,33.505306],"type":"Point"}
}