{
  "type": "Feature",
  "properties": {
    "iso:country":"US",
    "sg:address":"1740 W Montebello Ave",
    "sg:city":"Phoenix",
    "sg:classifiers":[
        {
            "category":"Food & Beverages",
            "subcategory":"Candy",
            "type":"Retail Goods"
        }
    ],
    "sg:phone":"+1 602 347 0420",
    "sg:postcode":"85015",
    "sg:province":"AZ",
    "wof:name":"Candymania",
    "wof:placetype":"venue"
},
  "geometry": {"coordinates":[-112.099234,33.519976],"type":"Point"}
}