{
  "type": "Feature",
  "properties": {
    "iso:country":"US",
    "sg:address":"1801 N Sulphur Springs St",
    "sg:city":"Douglas",
    "sg:classifiers":[
        {
            "category":"Building & Trades",
            "subcategory":"Construction",
            "type":"Services"
        }
    ],
    "sg:phone":"+1 520 805 0195",
    "sg:postcode":"85607",
    "sg:province":"AZ",
    "sg:tags":[
        "excavation",
        "contractor"
    ],
    "wof:name":"A & B Diversified",
    "wof:placetype":"venue"
},
  "geometry": {"coordinates":[-109.553966,31.353534],"type":"Point"}
}