{
  "type": "Feature",
  "properties": {
    "iso:country":"US",
    "sg:address":"3515 W Gleeson Rd",
    "sg:city":"Elfrida",
    "sg:phone":"+1 520 824 3336",
    "sg:postcode":"85610",
    "sg:province":"AZ",
    "sg:tags":[
        "irrigation"
    ],
    "wof:name":"Southeastern Ariz Irrigation",
    "wof:placetype":"venue"
},
  "geometry": {"coordinates":[-109.637249,31.700142],"type":"Point"}
}