{
  "type": "Feature",
  "properties": {
    "addr:full":"3300 W Camelback Rd Phoenix AZ 85017",
    "addr:housenumber":"3300",
    "addr:postcode":"85017",
    "addr:street":"W Camelback Rd",
    "iso:country":"US",
    "sg:address":"3300 W Camelback Rd",
    "sg:city":"Phoenix",
    "sg:classifiers":[
        {
            "category":"Shopping",
            "subcategory":"Books",
            "type":"Retail Goods"
        }
    ],
    "sg:phone":"+1 602 589 2838",
    "sg:postcode":"85017",
    "sg:province":"AZ",
    "sg:tags":[
        "dealer"
    ],
    "wof:name":"Follett Campus Bookstore",
    "wof:placetype":"venue"
},
  "geometry": {"coordinates":[-112.131597,33.509437],"type":"Point"}
}