{
  "type": "Feature",
  "properties": {
    "iso:country":"US",
    "sg:address":"2040 S Alma School Road Suite 1",
    "sg:city":"Chandler",
    "sg:classifiers":[
        {
            "category":"Shopping",
            "subcategory":"Florist",
            "type":"Retail Goods"
        }
    ],
    "sg:phone":"+1 480 899 4980",
    "sg:postcode":"85248",
    "sg:province":"AZ",
    "wof:name":"Kabloom",
    "wof:placetype":"venue"
},
  "geometry": {"coordinates":[-111.858781,33.275355],"type":"Point"}
}