{
  "type": "Feature",
  "properties": {
    "iso:country":"US",
    "sg:address":"2305 E Mcdowell Rd",
    "sg:city":"Phoenix",
    "sg:classifiers":[
        {
            "category":"Social Services",
            "subcategory":"Child Care",
            "type":"Services"
        },
        {
            "category":"Education",
            "subcategory":"Preschool",
            "type":"Public Place"
        }
    ],
    "sg:phone":"+1 602 275 9387",
    "sg:postcode":"85006",
    "sg:province":"AZ",
    "sg:tags":[
        "kindergarten",
        "nursery",
        "day"
    ],
    "wof:name":"Miss Muffet Childcare Center",
    "wof:placetype":"venue"
},
  "geometry": {"coordinates":[-112.032056,33.465778],"type":"Point"}
}