{
  "type": "Feature",
  "properties": {
    "iso:country":"US",
    "sg:address":"4349 E Tennessee St",
    "sg:city":"Tucson",
    "sg:classifiers":[
        {
            "category":"Building & Trades",
            "subcategory":"Construction",
            "type":"Services"
        }
    ],
    "sg:phone":"+1 520 722 0014",
    "sg:postcode":"85714",
    "sg:province":"AZ",
    "sg:tags":[
        "general",
        "contractor"
    ],
    "wof:name":"Starnes & Oswalt Construction",
    "wof:placetype":"venue"
},
  "geometry": {"coordinates":[-110.89664,32.166147],"type":"Point"}
}