{
  "type": "Feature",
  "properties": {
    "addr:full":"796 S 4th Ave Yuma AZ 85364",
    "addr:housenumber":"796",
    "addr:postcode":"85364",
    "addr:street":"S 4Th Ave",
    "iso:country":"US",
    "sg:address":"796 S 4th Ave",
    "sg:city":"Yuma",
    "sg:classifiers":[
        {
            "category":"Autos & Motor Vehicles",
            "subcategory":"Fuel & Gas Station",
            "type":"Retail Goods"
        }
    ],
    "sg:phone":"+1 928 783 8506",
    "sg:postcode":"85364",
    "sg:province":"AZ",
    "sg:tags":[
        "station",
        "gasoline"
    ],
    "wof:name":"McNeece Mart",
    "wof:placetype":"venue"
},
  "geometry": {"coordinates":[-114.624658,32.713515],"type":"Point"}
}