{
  "type": "Feature",
  "properties": {
    "iso:country":"US",
    "sg:address":"1989 W Ray Rd",
    "sg:city":"Chandler",
    "sg:classifiers":[
        {
            "category":"Autos & Motor Vehicles",
            "subcategory":"Fuel & Gas Station",
            "type":"Retail Goods"
        }
    ],
    "sg:phone":"+1 480 510 4633",
    "sg:postcode":"85224",
    "sg:province":"AZ",
    "sg:tags":[
        "station",
        "gasoline"
    ],
    "wof:name":"Am/PM Mini Market",
    "wof:placetype":"venue"
},
  "geometry": {"coordinates":[-111.874112,33.320513],"type":"Point"}
}