{
  "type": "Feature",
  "properties": {
    "iso:country":"US",
    "sg:address":"2239 Sonoita Dr",
    "sg:city":"Sierra Vista",
    "sg:classifiers":[
        {
            "category":"Health Services",
            "subcategory":"Medical Lab",
            "type":"Services"
        }
    ],
    "sg:phone":"+1 520 458 2489",
    "sg:postcode":"85635",
    "sg:province":"AZ",
    "sg:tags":[
        "laboratory"
    ],
    "wof:name":"Jakes Dental Laboratory",
    "wof:placetype":"venue"
},
  "geometry": {"coordinates":[-110.275334,31.561954],"type":"Point"}
}