{
  "type": "Feature",
  "properties": {
    "addr:full":"3844 N 32nd St Phoenix AZ 85018",
    "addr:housenumber":"3844",
    "addr:postcode":"85018",
    "addr:street":"N 32Nd St",
    "iso:country":"US",
    "sg:address":"3844 N 32nd St",
    "sg:city":"Phoenix",
    "sg:classifiers":[
        {
            "category":"Professional",
            "type":"Services"
        }
    ],
    "sg:phone":"+1 602 912 9113",
    "sg:postcode":"85018",
    "sg:province":"AZ",
    "wof:name":"Lor E Phillips LLC",
    "wof:placetype":"venue"
},
  "geometry": {"coordinates":[-112.013042,33.492574],"type":"Point"}
}