{
  "type": "Feature",
  "properties": {
    "addr:full":"7212 E Main St Ste A Scottsdale AZ 85251",
    "addr:housenumber":"7212",
    "addr:postcode":"85251",
    "addr:street":"E Main St Ste A",
    "iso:country":"US",
    "sg:address":"7212 E Main St Ste A",
    "sg:city":"Scottsdale",
    "sg:classifiers":[
        {
            "category":"Shopping",
            "subcategory":"Jewelry",
            "type":"Retail Goods"
        },
        {
            "category":"Manufacturing",
            "subcategory":"Jewelry",
            "type":"Manufacturing & Wholesale Goods"
        }
    ],
    "sg:phone":"+1 480 423 0567",
    "sg:postcode":"85251",
    "sg:province":"AZ",
    "sg:tags":[
        "manufacturer",
        "designer",
        "watch",
        "jewelers-wholesale",
        "jeweler"
    ],
    "wof:name":"A Z Gallery",
    "wof:placetype":"venue"
},
  "geometry": {"coordinates":[-111.925922,33.493118],"type":"Point"}
}