{
  "type": "Feature",
  "properties": {
    "addr:full":"211 W Vaughn St Tempe AZ 85283",
    "addr:housenumber":"211",
    "addr:postcode":"85283",
    "addr:street":"W Vaughn St",
    "iso:country":"US",
    "sg:address":"211 W Vaughn St",
    "sg:city":"Tempe",
    "sg:classifiers":[
        {
            "category":"Building & Trades",
            "subcategory":"Electrical",
            "type":"Services"
        },
        {
            "category":"Utilities",
            "subcategory":"Cable",
            "type":"Services"
        }
    ],
    "sg:phone":"+1 480 730 1900",
    "sg:postcode":"85283",
    "sg:province":"AZ",
    "sg:tags":[
        "product",
        "wire",
        "products-wholesale",
        "manufacturer"
    ],
    "sg:website":"http://www.firstelectronicsaz.com",
    "wof:name":"First Electronics, Inc.",
    "wof:placetype":"venue"
},
  "geometry": {"coordinates":[-111.94148,33.361127],"type":"Point"}
}