{
  "type": "Feature",
  "properties": {
    "iso:country":"US",
    "sg:address":"4551 E Acoma Dr",
    "sg:city":"Phoenix",
    "sg:classifiers":[
        {
            "category":"Building & Trades",
            "subcategory":"Plumbing",
            "type":"Services"
        }
    ],
    "sg:phone":"+1 602 493 5866",
    "sg:postcode":"85032",
    "sg:province":"AZ",
    "sg:tags":[
        "plumber",
        "contractor"
    ],
    "wof:name":"Schest Plumbing Inc",
    "wof:placetype":"venue"
},
  "geometry": {"coordinates":[-111.983147,33.618877],"type":"Point"}
}