{
  "type": "Feature",
  "properties": {
    "addr:full":"525 E Orange St Tempe AZ 85287",
    "addr:housenumber":"525",
    "addr:postcode":"85287",
    "addr:street":"E Orange St",
    "iso:country":"US",
    "sg:address":"525 E Orange St",
    "sg:city":"Tempe",
    "sg:classifiers":[
        {
            "category":"Utilities",
            "subcategory":"Mobile Phone",
            "type":"Services"
        },
        {
            "category":"Coffee & Tea",
            "type":"Food & Drink"
        }
    ],
    "sg:phone":"+1 480 727 0830",
    "sg:postcode":"85287",
    "sg:province":"AZ",
    "sg:tags":[
        "shop",
        "wi-fi",
        "espresso",
        "hotspot",
        "restaurant"
    ],
    "sg:website":"http://www.starbuckscoffee.com",
    "wof:name":"Starbucks Coffee",
    "wof:placetype":"venue"
},
  "geometry": {"coordinates":[-111.93136199999999,33.418381],"type":"Point"}
}