{
  "type": "Feature",
  "properties": {
    "iso:country":"US",
    "sg:address":"2445 W 12th St",
    "sg:city":"Tempe",
    "sg:classifiers":[
        {
            "category":"Professional",
            "subcategory":"Computer Services",
            "type":"Services"
        }
    ],
    "sg:phone":"+1 480 377 8450",
    "sg:postcode":"85281",
    "sg:province":"AZ",
    "sg:tags":[
        "repair"
    ],
    "wof:name":"Genesis Technologies",
    "wof:placetype":"venue"
},
  "geometry": {"coordinates":[-111.97372300000001,33.415991],"type":"Point"}
}