{
  "type": "Feature",
  "properties": {
    "iso:country":"US",
    "sg:address":"4965 Iron Springs Rd",
    "sg:city":"Prescott",
    "sg:classifiers":[
        {
            "category":"Professional",
            "subcategory":"Business Services",
            "type":"Services"
        }
    ],
    "sg:phone":"+1 602 579 7463",
    "sg:postcode":"86305",
    "sg:province":"AZ",
    "sg:tags":[
        "interior",
        "consultant",
        "design",
        "decorator"
    ],
    "wof:name":"Pam Conner Interior Designs",
    "wof:placetype":"venue"
},
  "geometry": {"coordinates":[-112.515402,34.575326],"type":"Point"}
}