{
  "type": "Feature",
  "properties": {
    "addr:full":"841 E 47th St Tucson AZ 85713",
    "addr:housenumber":"841",
    "addr:postcode":"85713",
    "addr:street":"E 47Th St",
    "iso:country":"US",
    "sg:address":"841 E 47th St",
    "sg:city":"Tucson",
    "sg:classifiers":[
        {
            "category":"Wholesale",
            "subcategory":"Machinery & Supplies",
            "type":"Manufacturing & Wholesale Goods"
        },
        {
            "category":"Wholesale",
            "subcategory":"Hardware",
            "type":"Manufacturing & Wholesale Goods"
        }
    ],
    "sg:phone":"+1 520 622 6200",
    "sg:postcode":"85713",
    "sg:province":"AZ",
    "sg:tags":[
        "fastener",
        "industrial"
    ],
    "sg:website":"www.qsn.com",
    "wof:name":"Quality Screw & Nut Company",
    "wof:placetype":"venue"
},
  "geometry": {"coordinates":[-110.957733,32.180199],"type":"Point"}
}