{
  "type": "Feature",
  "properties": {
    "iso:country":"US",
    "sg:address":"7835 E McClain Dr",
    "sg:city":"Scottsdale",
    "sg:classifiers":[
        {
            "category":"Shopping",
            "subcategory":"Computers & Home Electronics",
            "type":"Retail Goods"
        }
    ],
    "sg:phone":"+1 480 998 3400",
    "sg:postcode":"85260",
    "sg:province":"AZ",
    "wof:name":"Sensory Science Corporation",
    "wof:placetype":"venue"
},
  "geometry": {"coordinates":[-111.912378,33.628348],"type":"Point"}
}