{
  "type": "Feature",
  "properties": {
    "addr:full":"530 N Estrella Pkwy Goodyear AZ 85338",
    "addr:housenumber":"530",
    "addr:postcode":"85338",
    "addr:street":"N Estrella Pkwy",
    "iso:country":"US",
    "sg:address":"530 N Estrella Pkwy",
    "sg:city":"Goodyear",
    "sg:classifiers":[
        {
            "category":"Health Services",
            "subcategory":"Dentist",
            "type":"Services"
        }
    ],
    "sg:phone":"+1 623 925 8300",
    "sg:postcode":"85338",
    "sg:province":"AZ",
    "sg:website":"www.christensenortho.com",
    "wof:name":"Christensen Troy L DDS Ms DDS Ms",
    "wof:placetype":"venue"
},
  "geometry": {"coordinates":[-112.392714,33.457978],"type":"Point"}
}