{
  "type": "Feature",
  "properties": {
    "iso:country":"US",
    "sg:address":"821 W Thatcher Blvd",
    "sg:city":"Safford",
    "sg:classifiers":[
        {
            "category":"Retail",
            "subcategory":"Auto Repair",
            "type":"Services"
        }
    ],
    "sg:phone":"+1 928 428 3593",
    "sg:postcode":"85546",
    "sg:province":"AZ",
    "sg:tags":[
        "repairing",
        "automobile"
    ],
    "wof:name":"J L's Car Care",
    "wof:placetype":"venue"
},
  "geometry": {"coordinates":[-109.716435,32.834538],"type":"Point"}
}