{
  "type": "Feature",
  "properties": {
    "iso:country":"US",
    "sg:address":"10808 W Hayward Ave",
    "sg:city":"Glendale",
    "sg:classifiers":[
        {
            "category":"Banks & Credit Unions",
            "subcategory":"Investment Brokerage",
            "type":"Services"
        }
    ],
    "sg:phone":"+1 623 872 8235",
    "sg:postcode":"85307",
    "sg:province":"AZ",
    "sg:tags":[
        "broker",
        "commodity"
    ],
    "wof:name":"Cactus Auction Service",
    "wof:placetype":"venue"
},
  "geometry": {"coordinates":[-112.291545,33.548628],"type":"Point"}
}