{
  "type": "Feature",
  "properties": {
    "iso:country":"US",
    "sg:address":"13308 W Colter St",
    "sg:city":"Litchfield Park",
    "sg:classifiers":[
        {
            "category":"Banks & Credit Unions",
            "subcategory":"Bank",
            "type":"Services"
        }
    ],
    "sg:phone":"+1 623 433 9691",
    "sg:postcode":"85340",
    "sg:province":"AZ",
    "sg:tags":[
        "loan",
        "real estate"
    ],
    "wof:name":"American Mortgage Mktng Inc",
    "wof:placetype":"venue"
},
  "geometry": {"coordinates":[-112.345219,33.512086],"type":"Point"}
}