{
  "type": "Feature",
  "properties": {
    "iso:country":"US",
    "sg:address":"5416 E Baseline Rd",
    "sg:city":"Mesa",
    "sg:classifiers":[
        {
            "category":"Insurance",
            "subcategory":"Insurance Agent",
            "type":"Services"
        }
    ],
    "sg:phone":"+1 480 325 6474",
    "sg:postcode":"85206",
    "sg:province":"AZ",
    "wof:name":"Karen Stafford",
    "wof:placetype":"venue"
},
  "geometry": {"coordinates":[-111.718426,33.379361],"type":"Point"}
}