{
  "type": "Feature",
  "properties": {
    "iso:country":"US",
    "sg:address":"18038 N 6th Dr",
    "sg:city":"Phoenix",
    "sg:classifiers":[
        {
            "category":"Manufacturing",
            "subcategory":"Buildings",
            "type":"Manufacturing & Wholesale Goods"
        },
        {
            "category":"Building & Trades",
            "subcategory":"Construction",
            "type":"Services"
        }
    ],
    "sg:phone":"+1 602 885 1426",
    "sg:postcode":"85023",
    "sg:province":"AZ",
    "sg:tags":[
        "industrial",
        "builder",
        "specialty",
        "heating",
        "contractors-commercial",
        "home",
        "contractor"
    ],
    "wof:name":"Homeplace Contracting",
    "wof:placetype":"venue"
},
  "geometry": {"coordinates":[-112.08217399999999,33.649558],"type":"Point"}
}