{
  "type": "Feature",
  "properties": {
    "iso:country":"US",
    "sg:address":"1100 E Ajo Way",
    "sg:city":"Tucson",
    "sg:classifiers":[
        {
            "category":"Building & Trades",
            "subcategory":"Construction",
            "type":"Services"
        }
    ],
    "sg:phone":"+1 520 806 1400",
    "sg:postcode":"85713",
    "sg:province":"AZ",
    "wof:name":"Alcoa Wireless Services Inc",
    "wof:placetype":"venue"
},
  "geometry": {"coordinates":[-110.952451,32.177901],"type":"Point"}
}