{
  "type": "Feature",
  "properties": {
    "addr:full":"23 W Prince Rd Tucson AZ 85705",
    "addr:housenumber":"23",
    "addr:postcode":"85705",
    "addr:street":"W Prince Rd",
    "iso:country":"US",
    "sg:address":"23 W Prince Rd",
    "sg:city":"Tucson",
    "sg:classifiers":[
        {
            "category":"Ice Cream",
            "type":"Food & Drink"
        }
    ],
    "sg:menulink":"http://www.allmenus.com/az/tucson/164820-dairy-queen/menu/",
    "sg:phone":"+1 520 888 0560",
    "sg:postcode":"85705",
    "sg:province":"AZ",
    "sg:tags":[
        "burger",
        "american"
    ],
    "wof:name":"Dairy Queen",
    "wof:placetype":"venue"
},
  "geometry": {"coordinates":[-110.972317,32.271967],"type":"Point"}
}