{
  "type": "Feature",
  "properties": {
    "iso:country":"US",
    "sg:address":"3837 E la Salle St",
    "sg:city":"Phoenix",
    "sg:classifiers":[
        {
            "category":"Wholesale",
            "subcategory":"Office Equipment",
            "type":"Manufacturing & Wholesale Goods"
        }
    ],
    "sg:phone":"+1 602 426 1662",
    "sg:postcode":"85040",
    "sg:province":"AZ",
    "sg:tags":[
        "equipment-wholesale",
        "manufacturer",
        "furniture"
    ],
    "sg:website":"http://www.aadsofficesolutions.com",
    "wof:name":"Aads Office Solutions Int'l",
    "wof:placetype":"venue"
},
  "geometry": {"coordinates":[-111.997985,33.396867],"type":"Point"}
}