{
  "type": "Feature",
  "properties": {
    "addr:full":"1856 E 6th St Tempe AZ 85281",
    "addr:housenumber":"1856",
    "addr:postcode":"85281",
    "addr:street":"E 6Th St",
    "iso:country":"US",
    "sg:address":"1856 E 6th St",
    "sg:city":"Tempe",
    "sg:classifiers":[
        {
            "category":"Food & Beverages",
            "subcategory":"Specialty",
            "type":"Retail Goods"
        }
    ],
    "sg:phone":"+1 480 894 1255",
    "sg:postcode":"85281",
    "sg:province":"AZ",
    "sg:tags":[
        "manufacturing",
        "health",
        "supplement",
        "nutritional",
        "diet"
    ],
    "sg:website":"www.sarken.com",
    "wof:name":"Sarken Nutrition Corp",
    "wof:placetype":"venue"
},
  "geometry": {"coordinates":[-111.905961,33.425037],"type":"Point"}
}