{
  "type": "Feature",
  "properties": {
    "addr:full":"4132 W Firethorn St Tucson AZ 85741",
    "addr:housenumber":"4132",
    "addr:postcode":"85741",
    "addr:street":"W Firethorn St",
    "iso:country":"US",
    "sg:address":"4132 W Firethorn St",
    "sg:city":"Tucson",
    "sg:classifiers":[
        {
            "category":"Building & Trades",
            "subcategory":"Pest Control",
            "type":"Services"
        }
    ],
    "sg:phone":"+1 520 572 1342",
    "sg:postcode":"85741",
    "sg:province":"AZ",
    "wof:name":"Insect Eradication Specialists",
    "wof:placetype":"venue"
},
  "geometry": {"coordinates":[-111.055452,32.3543],"type":"Point"}
}