{
  "type": "Feature",
  "properties": {
    "addr:full":"4440 E Elwood St Phoenix AZ 85040",
    "addr:housenumber":"4440",
    "addr:postcode":"85040",
    "addr:street":"E Elwood St",
    "iso:country":"US",
    "sg:address":"4440 E Elwood St",
    "sg:city":"Phoenix",
    "sg:classifiers":[
        {
            "category":"Personal",
            "type":"Services"
        },
        {
            "category":"Retail",
            "subcategory":"Storage",
            "type":"Services"
        }
    ],
    "sg:phone":"+1 602 903 6776",
    "sg:postcode":"85040",
    "sg:province":"AZ",
    "sg:tags":[
        "household",
        "full",
        "commercial",
        "mover"
    ],
    "wof:name":"McCollister's Transportation Group - Agent for Mayflower",
    "wof:placetype":"venue"
},
  "geometry": {"coordinates":[-111.98707,33.414998],"type":"Point"}
}