{
  "type": "Feature",
  "properties": {
    "iso:country":"US",
    "sg:address":"330 E Southern Ave",
    "sg:city":"Mesa",
    "sg:classifiers":[
        {
            "category":"Retail",
            "subcategory":"Repair Shop",
            "type":"Services"
        },
        {
            "category":"Autos & Motor Vehicles",
            "subcategory":"Motorcycle Sales",
            "type":"Retail Goods"
        }
    ],
    "sg:phone":"+1 480 898 0559",
    "sg:postcode":"85210",
    "sg:province":"AZ",
    "sg:tags":[
        "scooter"
    ],
    "wof:name":"Cycle Moto",
    "wof:placetype":"venue"
},
  "geometry": {"coordinates":[-111.822935,33.393338],"type":"Point"}
}