{
  "type": "Feature",
  "properties": {
    "iso:country":"US",
    "sg:address":"1216 S Kofa Ave",
    "sg:city":"Parker",
    "sg:classifiers":[
        {
            "category":"Personal",
            "subcategory":"Beauty Salon",
            "type":"Services"
        }
    ],
    "sg:phone":"+1 928 669 2477",
    "sg:postcode":"85344",
    "sg:province":"AZ",
    "wof:name":"Terri's Studio Styles",
    "wof:placetype":"venue"
},
  "geometry": {"coordinates":[-114.290314,34.147203],"type":"Point"}
}