{
  "type": "Feature",
  "properties": {
    "addr:full":"217 1st St E Snowflake AZ 85937",
    "addr:housenumber":"217",
    "addr:postcode":"85937",
    "addr:street":"1St St E",
    "iso:country":"US",
    "sg:address":"217 1st St E",
    "sg:city":"Snowflake",
    "sg:classifiers":[
        {
            "category":"Farming",
            "subcategory":"Livestock Farm",
            "type":"Manufacturing & Wholesale Goods"
        }
    ],
    "sg:phone":"+1 928 536 4477",
    "sg:postcode":"85937",
    "sg:province":"AZ",
    "sg:tags":[
        "beef",
        "feedlot",
        "cattle"
    ],
    "wof:name":"Snowflake Cattle Company",
    "wof:placetype":"venue"
},
  "geometry": {"coordinates":[-110.07745199999999,34.506245],"type":"Point"}
}