{
  "type": "Feature",
  "properties": {
    "addr:full":"6970 N 95th Ave Glendale AZ 85305",
    "addr:housenumber":"6970",
    "addr:postcode":"85305",
    "addr:street":"N 95Th Ave",
    "iso:country":"US",
    "sg:address":"6970 N 95th Ave",
    "sg:city":"Glendale",
    "sg:classifiers":[
        {
            "category":"Restaurant",
            "type":"Food & Drink"
        }
    ],
    "sg:phone":"+1 623 772 1110",
    "sg:postcode":"85305",
    "sg:province":"AZ",
    "wof:name":"Camarones Mexican Grill",
    "wof:placetype":"venue"
},
  "geometry": {"coordinates":[-112.26388799999999,33.53669],"type":"Point"}
}