{
  "type": "Feature",
  "properties": {
    "addr:full":"5350 E Marriott Dr Phoenix AZ 85054",
    "addr:housenumber":"5350",
    "addr:postcode":"85054",
    "addr:street":"E Marriott Dr",
    "iso:country":"US",
    "sg:address":"5350 E Marriott Dr",
    "sg:city":"Phoenix",
    "sg:classifiers":[
        {
            "category":"Restaurant",
            "type":"Food & Drink"
        }
    ],
    "sg:menulink":"http://www.allmenus.com/az/phoenix/4035-ristorante-tuscany-at-jw-marriott-resort/menu/",
    "sg:phone":"+1 800 835 6206",
    "sg:postcode":"85054",
    "sg:province":"AZ",
    "sg:tags":[
        "italian"
    ],
    "wof:name":"Ristorante Tuscany at JW Marriott Resort",
    "wof:placetype":"venue"
},
  "geometry": {"coordinates":[-111.967681,33.683066],"type":"Point"}
}