{
  "type": "Feature",
  "properties": {
    "iso:country":"US",
    "sg:address":"26 W Lone Cactus Dr",
    "sg:city":"Phoenix",
    "sg:classifiers":[
        {
            "category":"Manufacturing",
            "subcategory":"Tools & Machinery",
            "type":"Manufacturing & Wholesale Goods"
        }
    ],
    "sg:phone":"+1 480 607 1010",
    "sg:postcode":"85027",
    "sg:province":"AZ",
    "sg:tags":[
        "computer",
        "storage",
        "devices"
    ],
    "wof:name":"Sanone",
    "wof:placetype":"venue"
},
  "geometry": {"coordinates":[-112.074392,33.680936],"type":"Point"}
}