{
  "type": "Feature",
  "properties": {
    "iso:country":"US",
    "sg:address":"1854 S Val Vista Drive",
    "sg:city":"Mesa",
    "sg:classifiers":[
        {
            "category":"Home & Garden",
            "subcategory":"Furniture",
            "type":"Retail Goods"
        }
    ],
    "sg:phone":"+1 480 813 1640",
    "sg:postcode":"85204",
    "sg:province":"AZ",
    "sg:tags":[
        "store"
    ],
    "sg:website":"www.kirklands.com",
    "wof:name":"Kirkland's",
    "wof:placetype":"venue"
},
  "geometry": {"coordinates":[-111.754048,33.381514],"type":"Point"}
}