{
  "type": "Feature",
  "properties": {
    "iso:country":"US",
    "sg:address":"3443 N Central Ave",
    "sg:city":"Phoenix",
    "sg:classifiers":[
        {
            "category":"Professional",
            "subcategory":"Computer Services",
            "type":"Services"
        }
    ],
    "sg:phone":"+1 480 998 7237",
    "sg:postcode":"85012",
    "sg:province":"AZ",
    "sg:tags":[
        "internet"
    ],
    "wof:name":"Deru Internet",
    "wof:placetype":"venue"
},
  "geometry": {"coordinates":[-112.07371,33.488219],"type":"Point"}
}