{
  "type": "Feature",
  "properties": {
    "addr:full":"2345 E Thomas Rd Ste 100 Phoenix AZ 85016",
    "addr:housenumber":"2345",
    "addr:postcode":"85016",
    "addr:street":"E Thomas Rd Ste 100",
    "iso:country":"US",
    "sg:address":"2345 E Thomas Rd Ste 100",
    "sg:city":"Phoenix",
    "sg:classifiers":[
        {
            "category":"Professional",
            "subcategory":"Detective & Security Services",
            "type":"Services"
        }
    ],
    "sg:phone":"+1 602 508 9102",
    "sg:postcode":"85016",
    "sg:province":"AZ",
    "sg:tags":[
        "guard",
        "patrol"
    ],
    "sg:website":"http://www.proguardinc.com",
    "wof:name":"Proguard Technologies",
    "wof:placetype":"venue"
},
  "geometry": {"coordinates":[-112.03117399999999,33.48032],"type":"Point"}
}