{
  "type": "Feature",
  "properties": {
    "iso:country":"US",
    "sg:address":"1615 W Curry Dr",
    "sg:city":"Chandler",
    "sg:classifiers":[
        {
            "category":"Shopping",
            "subcategory":"Clothing, Apparel, & Fashions",
            "type":"Retail Goods"
        }
    ],
    "sg:phone":"+1 480 730 1532",
    "sg:postcode":"85224",
    "sg:province":"AZ",
    "wof:name":"Legendary Ladies",
    "wof:placetype":"venue"
},
  "geometry": {"coordinates":[-111.871329,33.352798],"type":"Point"}
}