{
  "type": "Feature",
  "properties": {
    "addr:full":"723 E Acoma Dr Phoenix AZ 85022",
    "addr:housenumber":"723",
    "addr:postcode":"85022",
    "addr:street":"E Acoma Dr",
    "iso:country":"US",
    "sg:address":"723 E Acoma Dr",
    "sg:city":"Phoenix",
    "sg:classifiers":[
        {
            "category":"Home & Garden",
            "subcategory":"Building Materials",
            "type":"Retail Goods"
        }
    ],
    "sg:phone":"+1 602 548 1992",
    "sg:postcode":"85022",
    "sg:province":"AZ",
    "sg:tags":[
        "window",
        "door",
        "screen"
    ],
    "wof:name":"Shadowcraft Custom Sun Screen",
    "wof:placetype":"venue"
},
  "geometry": {"coordinates":[-112.06474300000001,33.6185],"type":"Point"}
}