{
  "type": "Feature",
  "properties": {
    "iso:country":"US",
    "sg:address":"3225 W Baseline Rd",
    "sg:city":"Laveen",
    "sg:classifiers":[
        {
            "category":"Building & Trades",
            "subcategory":"Construction",
            "type":"Services"
        }
    ],
    "sg:phone":"+1 602 237 9393",
    "sg:postcode":"85339",
    "sg:province":"AZ",
    "sg:tags":[
        "general",
        "contractor"
    ],
    "wof:name":"Chavita Inc",
    "wof:placetype":"venue"
},
  "geometry": {"coordinates":[-112.125087,33.377691],"type":"Point"}
}