{
  "type": "Feature",
  "properties": {
    "addr:full":"501 S Evergreen St Chandler AZ 85225",
    "addr:housenumber":"501",
    "addr:postcode":"85225",
    "addr:street":"S Evergreen St",
    "iso:country":"US",
    "sg:address":"501 S Evergreen St",
    "sg:city":"Chandler",
    "sg:classifiers":[
        {
            "category":"Professional",
            "type":"Services"
        }
    ],
    "sg:phone":"+1 480 786 5798",
    "sg:postcode":"85225",
    "sg:province":"AZ",
    "wof:name":"United Daughters of Confe",
    "wof:placetype":"venue"
},
  "geometry": {"coordinates":[-111.85334,33.294793],"type":"Point"}
}