{
  "type": "Feature",
  "properties": {
    "iso:country":"US",
    "sg:address":"13742 W Bell Rd",
    "sg:city":"Surprise",
    "sg:classifiers":[
        {
            "category":"Autos & Motor Vehicles",
            "subcategory":"Auto Supplies",
            "type":"Retail Goods"
        }
    ],
    "sg:phone":"+1 623 544 2811",
    "sg:postcode":"85374",
    "sg:province":"AZ",
    "wof:name":"Reinalt-Thomas Corporation",
    "wof:placetype":"venue"
},
  "geometry": {"coordinates":[-112.358539,33.638796],"type":"Point"}
}