{
  "type": "Feature",
  "properties": {
    "iso:country":"US",
    "sg:address":"712 N Bridlegate Dr.",
    "sg:city":"Gilbert",
    "sg:classifiers":[
        {
            "category":"Building & Trades",
            "subcategory":"Cleaning & Sanitation",
            "type":"Services"
        }
    ],
    "sg:phone":"+1 480 220 0368",
    "sg:postcode":"85234",
    "sg:province":"AZ",
    "sg:tags":[
        "cleaning-industrial"
    ],
    "sg:website":"http://pinnacleofficecleaning.com",
    "wof:name":"Pinnacle Office Cleaning",
    "wof:placetype":"venue"
},
  "geometry": {"coordinates":[-111.708479,33.363352],"type":"Point"}
}