{
  "type": "Feature",
  "properties": {
    "addr:full":"536 W Utah St Tucson AZ 85706",
    "addr:housenumber":"536",
    "addr:postcode":"85706",
    "addr:street":"W Utah St",
    "iso:country":"US",
    "sg:address":"536 W Utah St",
    "sg:city":"Tucson",
    "sg:classifiers":[
        {
            "category":"Real Estate",
            "subcategory":"Real Estate Services",
            "type":"Services"
        }
    ],
    "sg:phone":"+1 520 294 2828",
    "sg:postcode":"85706",
    "sg:province":"AZ",
    "sg:tags":[
        "company",
        "title"
    ],
    "wof:name":"K & K Insurance",
    "wof:placetype":"venue"
},
  "geometry": {"coordinates":[-110.97713,32.157852],"type":"Point"}
}