{
  "type": "Feature",
  "properties": {
    "iso:country":"US",
    "sg:address":"3251 S Dodge Blvd",
    "sg:city":"Tucson",
    "sg:classifiers":[
        {
            "category":"Manufacturing",
            "subcategory":"Metals",
            "type":"Manufacturing & Wholesale Goods"
        }
    ],
    "sg:phone":"+1 520 790 4114",
    "sg:postcode":"85713",
    "sg:province":"AZ",
    "sg:tags":[
        "ornamental",
        "work"
    ],
    "wof:name":"Exquisite Creations & Strctrl",
    "wof:placetype":"venue"
},
  "geometry": {"coordinates":[-110.913506,32.186587],"type":"Point"}
}