{
  "type": "Feature",
  "properties": {
    "iso:country":"US",
    "sg:address":"2600 N Central Ave",
    "sg:city":"Phoenix",
    "sg:classifiers":[
        {
            "category":"Professional",
            "subcategory":"Lawyer & Legal Services",
            "type":"Services"
        }
    ],
    "sg:phone":"+1 602 606 4660",
    "sg:postcode":"85004",
    "sg:province":"AZ",
    "sg:tags":[
        "information",
        "attorney",
        "referral",
        "plan"
    ],
    "wof:name":"Carter Rodrick Pc",
    "wof:placetype":"venue"
},
  "geometry": {"coordinates":[-112.073891,33.476631],"type":"Point"}
}