{
  "type": "Feature",
  "properties": {
    "iso:country":"US",
    "sg:address":"6147 E Grant Rd",
    "sg:city":"Tucson",
    "sg:classifiers":[
        {
            "category":"Health Services",
            "subcategory":"Health Practitioner",
            "type":"Services"
        }
    ],
    "sg:phone":"+1 520 444 2559",
    "sg:postcode":"85712",
    "sg:province":"AZ",
    "sg:tags":[
        "psychologist"
    ],
    "wof:name":"Neuro Psychology",
    "wof:placetype":"venue"
},
  "geometry": {"coordinates":[-110.858208,32.250722],"type":"Point"}
}