{
  "type": "Feature",
  "properties": {
    "iso:country":"US",
    "sg:address":"332 E Camelback Rd",
    "sg:city":"Phoenix",
    "sg:classifiers":[
        {
            "category":"Shopping",
            "subcategory":"Used Merchandise",
            "type":"Retail Goods"
        }
    ],
    "sg:phone":"+1 602 248 0008",
    "sg:postcode":"85012",
    "sg:province":"AZ",
    "sg:tags":[
        "antique"
    ],
    "wof:name":"Antiques On Camelback",
    "wof:placetype":"venue"
},
  "geometry": {"coordinates":[-112.067407,33.509321],"type":"Point"}
}