{
  "type": "Feature",
  "properties": {
    "iso:country":"US",
    "sg:address":"5082 S Price Rd",
    "sg:city":"Tempe",
    "sg:classifiers":[
        {
            "category":"Food & Beverages",
            "subcategory":"Specialty",
            "type":"Retail Goods"
        }
    ],
    "sg:phone":"+1 480 730 1322",
    "sg:postcode":"85282",
    "sg:province":"AZ",
    "sg:tags":[
        "water",
        "bulk",
        "company"
    ],
    "wof:name":"Baseline Water & Ice Super Str",
    "wof:placetype":"venue"
},
  "geometry": {"coordinates":[-111.892638,33.381918],"type":"Point"}
}