{
  "type": "Feature",
  "properties": {
    "iso:country":"US",
    "sg:address":"6961 E 42nd St",
    "sg:city":"Tucson",
    "sg:classifiers":[
        {
            "category":"Building & Trades",
            "subcategory":"Construction",
            "type":"Services"
        }
    ],
    "sg:phone":"+1 520 571 8034",
    "sg:postcode":"85730",
    "sg:province":"AZ",
    "sg:tags":[
        "contractor"
    ],
    "wof:name":"Rock Roofing",
    "wof:placetype":"venue"
},
  "geometry": {"coordinates":[-110.842893,32.186286],"type":"Point"}
}