{
  "type": "Feature",
  "properties": {
    "addr:full":"5201 N 27th Ave Phoenix AZ 85017",
    "addr:housenumber":"5201",
    "addr:postcode":"85017",
    "addr:street":"N 27Th Ave",
    "iso:country":"US",
    "sg:address":"5201 N 27th Ave",
    "sg:city":"Phoenix",
    "sg:classifiers":[
        {
            "category":"Organizations",
            "subcategory":"Religious Organization",
            "type":"Services"
        }
    ],
    "sg:phone":"+1 602 242 8644",
    "sg:postcode":"85017",
    "sg:province":"AZ",
    "sg:tags":[
        "church"
    ],
    "sg:website":"www.loveinternational.org",
    "wof:name":"Love International Ministries",
    "wof:placetype":"venue"
},
  "geometry": {"coordinates":[-112.116894,33.512607],"type":"Point"}
}