{
  "type": "Feature",
  "properties": {
    "iso:country":"US",
    "sg:address":"700 N Arizona Ave",
    "sg:city":"Chandler",
    "sg:classifiers":[
        {
            "category":"Freight",
            "type":"Transportation"
        }
    ],
    "sg:phone":"+1 480 963 4693",
    "sg:postcode":"85225",
    "sg:province":"AZ",
    "sg:tags":[
        "broker",
        "trucking"
    ],
    "wof:name":"J M Buck Newman",
    "wof:placetype":"venue"
},
  "geometry": {"coordinates":[-111.841543,33.316356],"type":"Point"}
}