{
  "type": "Feature",
  "properties": {
    "iso:country":"US",
    "sg:address":"4335 E Sunnybrook Ln",
    "sg:city":"Tucson",
    "sg:classifiers":[
        {
            "category":"Utilities",
            "subcategory":"Telephone",
            "type":"Services"
        }
    ],
    "sg:phone":"+1 520 954 7786",
    "sg:postcode":"85712",
    "sg:province":"AZ",
    "sg:tags":[
        "communications"
    ],
    "wof:name":"Tele Plus Services",
    "wof:placetype":"venue"
},
  "geometry": {"coordinates":[-110.900239,32.269606],"type":"Point"}
}