{
  "type": "Feature",
  "properties": {
    "iso:country":"US",
    "sg:address":"161 E Deuce of Clubs",
    "sg:city":"Show Low",
    "sg:classifiers":[
        {
            "category":"Autos & Motor Vehicles",
            "subcategory":"Auto Supplies",
            "type":"Retail Goods"
        }
    ],
    "sg:phone":"+1 928 537 4533",
    "sg:postcode":"85901",
    "sg:province":"AZ",
    "wof:name":"Checker Auto Parts 585",
    "wof:placetype":"venue"
},
  "geometry": {"coordinates":[-110.04103000000001,34.251101],"type":"Point"}
}