{
  "type": "Feature",
  "properties": {
    "iso:country":"US",
    "sg:address":"1672 E Guadalupe Rd",
    "sg:city":"Gilbert",
    "sg:classifiers":[
        {
            "category":"Insurance",
            "subcategory":"Hazard Insurance",
            "type":"Services"
        },
        {
            "category":"Insurance",
            "subcategory":"Insurance Agent",
            "type":"Services"
        },
        {
            "category":"Insurance",
            "subcategory":"Life Insurance",
            "type":"Services"
        },
        {
            "category":"Insurance",
            "subcategory":"Title Insurance",
            "type":"Services"
        }
    ],
    "sg:phone":"+1 480 753 9711",
    "sg:postcode":"85234",
    "sg:province":"AZ",
    "sg:tags":[
        "property",
        "casualty",
        "homeowner"
    ],
    "sg:website":"http://www.amfam.com/agentlocator/MBUSTOS?sourceid=yp9",
    "wof:name":"American Family Insurance- Mark Bustos",
    "wof:placetype":"venue"
},
  "geometry": {"coordinates":[-111.754457,33.364726],"type":"Point"}
}