{
  "type": "Feature",
  "properties": {
    "iso:country":"US",
    "sg:address":"10401 W Thunderbird Blvd",
    "sg:city":"Sun City",
    "sg:classifiers":[
        {
            "category":"Health Services",
            "subcategory":"Hospital",
            "type":"Services"
        }
    ],
    "sg:phone":"+1 623 977 7211",
    "sg:postcode":"85351",
    "sg:province":"AZ",
    "sg:website":"www.sunhealth.org",
    "wof:name":"Boswell Memorial Hospital",
    "wof:placetype":"venue"
},
  "geometry": {"coordinates":[-112.28424,33.604832],"type":"Point"}
}