{
  "type": "Feature",
  "properties": {
    "iso:country":"US",
    "sg:address":"8030 N el Mirage Rd",
    "sg:city":"El Mirage",
    "sg:classifiers":[
        {
            "category":"Retail",
            "subcategory":"Auto Repair",
            "type":"Services"
        }
    ],
    "sg:phone":"+1 623 935 6678",
    "sg:postcode":"85335",
    "sg:province":"AZ",
    "sg:tags":[
        "body",
        "automobile",
        "painting"
    ],
    "sg:website":"www.premiercoachworks.com",
    "wof:name":"Premier Coach Works",
    "wof:placetype":"venue"
},
  "geometry": {"coordinates":[-112.324369,33.551179],"type":"Point"}
}