{
  "type": "Feature",
  "properties": {
    "iso:country":"US",
    "sg:address":"5402 E Main St",
    "sg:city":"Mesa",
    "sg:classifiers":[
        {
            "category":"Travel",
            "subcategory":"Hotels & Motels",
            "type":"Entertainment"
        }
    ],
    "sg:phone":"+1 480 985 9966",
    "sg:postcode":"85205",
    "sg:province":"AZ",
    "wof:name":"Centebar Motel",
    "wof:placetype":"venue"
},
  "geometry": {"coordinates":[-111.71445,33.415646],"type":"Point"}
}