{
  "type": "Feature",
  "properties": {
    "addr:full":"440 N Arizona Ave Chandler AZ 85225",
    "addr:housenumber":"440",
    "addr:postcode":"85225",
    "addr:street":"N Arizona Ave",
    "iso:country":"US",
    "sg:address":"440 N Arizona Ave",
    "sg:city":"Chandler",
    "sg:classifiers":[
        {
            "category":"Retail",
            "subcategory":"Auto Repair",
            "type":"Services"
        }
    ],
    "sg:phone":"+1 480 855 6995",
    "sg:postcode":"85225",
    "sg:province":"AZ",
    "sg:tags":[
        "repairing",
        "automobile"
    ],
    "wof:name":"T & J's Automotive",
    "wof:placetype":"venue"
},
  "geometry": {"coordinates":[-111.84155,33.311491],"type":"Point"}
}