{
  "type": "Feature",
  "properties": {
    "addr:full":"6801 S Tucson Blvd Tucson AZ 85706",
    "addr:housenumber":"6801",
    "addr:postcode":"85706",
    "addr:street":"S Tucson Blvd",
    "iso:country":"US",
    "sg:address":"6801 S Tucson Blvd",
    "sg:city":"Tucson",
    "sg:classifiers":[
        {
            "category":"Restaurant",
            "type":"Food & Drink"
        }
    ],
    "sg:phone":"+1 520 889 4461",
    "sg:postcode":"85706",
    "sg:province":"AZ",
    "wof:name":"Morgan's Food & Spirits",
    "wof:placetype":"venue"
},
  "geometry": {"coordinates":[-110.934612,32.126827],"type":"Point"}
}