{
  "type": "Feature",
  "properties": {
    "iso:country":"US",
    "sg:address":"3307 W Christy Dr",
    "sg:city":"Phoenix",
    "sg:classifiers":[
        {
            "category":"Health Services",
            "subcategory":"Medical Lab",
            "type":"Services"
        }
    ],
    "sg:phone":"+1 602 938 5839",
    "sg:postcode":"85029",
    "sg:province":"AZ",
    "sg:tags":[
        "laboratory",
        "testing"
    ],
    "sg:website":"http://www.pickettdentalab.com",
    "wof:name":"Pickett Dental Laboratory",
    "wof:placetype":"venue"
},
  "geometry": {"coordinates":[-112.130225,33.584676],"type":"Point"}
}