{
  "type": "Feature",
  "properties": {
    "addr:full":"1170 N Estrella Pkwy Goodyear AZ 85338",
    "addr:housenumber":"1170",
    "addr:postcode":"85338",
    "addr:street":"N Estrella Pkwy",
    "iso:country":"US",
    "sg:address":"1170 N Estrella Pkwy",
    "sg:city":"Goodyear",
    "sg:classifiers":[
        {
            "category":"Shopping",
            "subcategory":"Mobile Phones",
            "type":"Retail Goods"
        }
    ],
    "sg:phone":"+1 623 925 8880",
    "sg:postcode":"85338",
    "sg:province":"AZ",
    "sg:website":"www.gowireless.net",
    "wof:name":"Go Wireless",
    "wof:placetype":"venue"
},
  "geometry": {"coordinates":[-112.392714,33.459755],"type":"Point"}
}