{
  "type": "Feature",
  "properties": {
    "iso:country":"US",
    "sg:address":"7823 E Broadway Blvd",
    "sg:city":"Tucson",
    "sg:classifiers":[
        {
            "category":"Manufacturing",
            "subcategory":"Food",
            "type":"Manufacturing & Wholesale Goods"
        }
    ],
    "sg:phone":"+1 520 298 5966",
    "sg:postcode":"85710",
    "sg:province":"AZ",
    "sg:tags":[
        "canned",
        "eating",
        "specialty",
        "mfg"
    ],
    "wof:name":"LA Mesa Tortillas",
    "wof:placetype":"venue"
},
  "geometry": {"coordinates":[-110.825177,32.221047],"type":"Point"}
}