{
  "type": "Feature",
  "properties": {
    "iso:country":"US",
    "sg:address":"25461 W Riverside St",
    "sg:city":"Buckeye",
    "sg:classifiers":[
        {
            "category":"Professional",
            "subcategory":"Art Services",
            "type":"Services"
        }
    ],
    "sg:phone":"+1 623 327 9045",
    "sg:postcode":"85326",
    "sg:province":"AZ",
    "sg:tags":[
        "designer",
        "display",
        "producer"
    ],
    "wof:name":"All Star Sprinkler & Design Co.",
    "wof:placetype":"venue"
},
  "geometry": {"coordinates":[-112.597662,33.409538],"type":"Point"}
}