{
  "type": "Feature",
  "properties": {
    "iso:country":"US",
    "sg:address":"6767 N Glen Harbor Blvd",
    "sg:city":"Glendale",
    "sg:classifiers":[
        {
            "category":"Government",
            "subcategory":"Office",
            "type":"Public Place"
        }
    ],
    "sg:phone":"+1 623 872 9588",
    "sg:postcode":"85307",
    "sg:province":"AZ",
    "sg:tags":[
        "control",
        "tower",
        "traffic",
        "air"
    ],
    "wof:name":"Airport Traffic Control Tower",
    "wof:placetype":"venue"
},
  "geometry": {"coordinates":[-112.301957,33.522252],"type":"Point"}
}