{
  "type": "Feature",
  "properties": {
    "addr:full":"6620 S Memorial Pl Tucson AZ 85706",
    "addr:housenumber":"6620",
    "addr:postcode":"85706",
    "addr:street":"S Memorial Pl",
    "iso:country":"US",
    "sg:address":"6620 S Memorial Pl",
    "sg:city":"Tucson",
    "sg:classifiers":[
        {
            "category":"Freight",
            "type":"Transportation"
        }
    ],
    "sg:phone":"+1 520 574 9438",
    "sg:postcode":"85706",
    "sg:province":"AZ",
    "sg:tags":[
        "warehouse",
        "self",
        "storage"
    ],
    "wof:name":"Avent",
    "wof:placetype":"venue"
},
  "geometry": {"coordinates":[-110.853279,32.131313],"type":"Point"}
}