{
  "type": "Feature",
  "properties": {
    "addr:full":"1585 N Santa Rita Ave Tucson AZ 85719",
    "addr:housenumber":"1585",
    "addr:postcode":"85719",
    "addr:street":"N Santa Rita Ave",
    "iso:country":"US",
    "sg:address":"1585 N Santa Rita Ave",
    "sg:city":"Tucson",
    "sg:classifiers":[
        {
            "category":"Real Estate",
            "subcategory":"Real Estate Operator",
            "type":"Services"
        }
    ],
    "sg:phone":"+1 520 623 8058",
    "sg:postcode":"85719",
    "sg:province":"AZ",
    "sg:tags":[
        "building",
        "apartment"
    ],
    "wof:name":"Meadow West Apartments Inc",
    "wof:placetype":"venue"
},
  "geometry": {"coordinates":[-110.95388699999999,32.240742],"type":"Point"}
}