{
  "type": "Feature",
  "properties": {
    "addr:full":"715 E Sierra Vista Dr Phoenix AZ 85014",
    "addr:housenumber":"715",
    "addr:postcode":"85014",
    "addr:street":"E Sierra Vista Dr",
    "iso:country":"US",
    "sg:address":"715 E Sierra Vista Dr",
    "sg:city":"Phoenix",
    "sg:classifiers":[
        {
            "category":"Professional",
            "type":"Services"
        }
    ],
    "sg:phone":"+1 602 274 8547",
    "sg:postcode":"85014",
    "sg:province":"AZ",
    "wof:name":"Rd Beller LLC",
    "wof:placetype":"venue"
},
  "geometry": {"coordinates":[-112.060812,33.531899],"type":"Point"}
}