{
  "type": "Feature",
  "properties": {
    "addr:full":"1068 N Saguaro St Chandler AZ 85224",
    "addr:housenumber":"1068",
    "addr:postcode":"85224",
    "addr:street":"N Saguaro St",
    "iso:country":"US",
    "sg:address":"1068 N Saguaro St",
    "sg:city":"Chandler",
    "sg:classifiers":[
        {
            "category":"Personal",
            "type":"Services"
        },
        {
            "category":"Professional",
            "subcategory":"Art Services",
            "type":"Services"
        }
    ],
    "sg:phone":"+1 480 459 2727",
    "sg:postcode":"85224",
    "sg:province":"AZ",
    "sg:tags":[
        "photography",
        "videography",
        "photographers-portrait",
        "wedding"
    ],
    "wof:name":"Photography by Bill Nash",
    "wof:placetype":"venue"
},
  "geometry": {"coordinates":[-111.869893,33.321154],"type":"Point"}
}