{
  "type": "Feature",
  "properties": {
    "iso:country":"US",
    "sg:address":"4530 E Shea Blvd",
    "sg:city":"Phoenix",
    "sg:classifiers":[
        {
            "category":"Real Estate",
            "subcategory":"Real Estate Agent",
            "type":"Services"
        }
    ],
    "sg:phone":"+1 480 998 9900",
    "sg:postcode":"85028",
    "sg:province":"AZ",
    "wof:name":"Realty Xtra",
    "wof:placetype":"venue"
},
  "geometry": {"coordinates":[-111.984234,33.582732],"type":"Point"}
}