{
  "type": "Feature",
  "properties": {
    "addr:full":"3351 E Hemisphere Loop Tucson AZ 85706",
    "addr:housenumber":"3351",
    "addr:postcode":"85706",
    "addr:street":"E Hemisphere Loop",
    "iso:country":"US",
    "sg:address":"3351 E Hemisphere Loop",
    "sg:city":"Tucson",
    "sg:classifiers":[
        {
            "category":"Professional",
            "type":"Services"
        }
    ],
    "sg:phone":"+1 520 799 8000",
    "sg:postcode":"85706",
    "sg:province":"AZ",
    "sg:tags":[
        "establishment"
    ],
    "wof:name":"TDI Intl",
    "wof:placetype":"venue"
},
  "geometry": {"coordinates":[-110.91973400000001,32.139121],"type":"Point"}
}