{
  "type": "Feature",
  "properties": {
    "iso:country":"US",
    "sg:address":"9144 N Cave Creek Rd",
    "sg:city":"Phoenix",
    "sg:classifiers":[
        {
            "category":"Autos & Motor Vehicles",
            "subcategory":"Automobile Sales",
            "type":"Retail Goods"
        }
    ],
    "sg:phone":"+1 602 751 6909",
    "sg:postcode":"85020",
    "sg:province":"AZ",
    "sg:tags":[
        "car",
        "used"
    ],
    "wof:name":"Your Way Auto Sales",
    "wof:placetype":"venue"
},
  "geometry": {"coordinates":[-112.06323999999999,33.569389],"type":"Point"}
}