{
  "type": "Feature",
  "properties": {
    "iso:country":"US",
    "sg:address":"928 S 41st St",
    "sg:city":"Mesa",
    "sg:classifiers":[
        {
            "category":"Real Estate",
            "subcategory":"Developer",
            "type":"Services"
        }
    ],
    "sg:phone":"+1 480 964 3358",
    "sg:postcode":"85206",
    "sg:province":"AZ",
    "wof:name":"Canyon State Development",
    "wof:placetype":"venue"
},
  "geometry": {"coordinates":[-111.74323200000001,33.398714],"type":"Point"}
}