{
  "type": "Feature",
  "properties": {
    "addr:full":"5237 State Hwy 92 Sierra Vista AZ 85650",
    "addr:housenumber":"5237",
    "addr:postcode":"85650",
    "addr:street":"State Hwy 92",
    "iso:country":"US",
    "sg:address":"5237 State Hwy 92",
    "sg:city":"Sierra Vista",
    "sg:classifiers":[
        {
            "category":"Shopping",
            "type":"Retail Goods"
        },
        {
            "category":"Shopping",
            "subcategory":"Musical Instruments",
            "type":"Retail Goods"
        }
    ],
    "sg:phone":"+1 520 803 7722",
    "sg:postcode":"85650",
    "sg:province":"AZ",
    "sg:tags":[
        "merchandise"
    ],
    "wof:name":"Periwinkle's Music Emporium",
    "wof:placetype":"venue"
},
  "geometry": {"coordinates":[-110.257336,31.473878],"type":"Point"}
}