{
  "type": "Feature",
  "properties": {
    "iso:country":"US",
    "sg:address":"2901 S 4th Ave",
    "sg:city":"Tucson",
    "sg:classifiers":[
        {
            "category":"Home & Garden",
            "subcategory":"Building Materials",
            "type":"Retail Goods"
        }
    ],
    "sg:phone":"+1 520 622 6430",
    "sg:postcode":"85713",
    "sg:province":"AZ",
    "sg:tags":[
        "windows"
    ],
    "wof:name":"Window Depot Tucson 2",
    "wof:placetype":"venue"
},
  "geometry": {"coordinates":[-110.965202,32.189711],"type":"Point"}
}