{
  "type": "Feature",
  "properties": {
    "addr:full":"2901 S 4th Ave Tucson AZ 85713",
    "addr:housenumber":"2901",
    "addr:postcode":"85713",
    "addr:street":"S 4Th Ave",
    "iso:country":"US",
    "sg:address":"2901 S 4th Ave",
    "sg:city":"Tucson",
    "sg:classifiers":[
        {
            "category":"Home & Garden",
            "subcategory":"Building Materials",
            "type":"Retail Goods"
        }
    ],
    "sg:phone":"+1 520 622 6430",
    "sg:postcode":"85713",
    "sg:province":"AZ",
    "sg:tags":[
        "windows"
    ],
    "wof:name":"Window Depot Tucson 2",
    "wof:placetype":"venue"
},
  "geometry": {"coordinates":[-110.96520200000001,32.189711],"type":"Point"}
}