{
  "type": "Feature",
  "properties": {
    "iso:country":"US",
    "sg:address":"4362 W Thunderbird Rd",
    "sg:city":"Glendale",
    "sg:classifiers":[
        {
            "category":"Restaurant",
            "type":"Food & Drink"
        }
    ],
    "sg:phone":"+1 602 978 5959",
    "sg:postcode":"85306",
    "sg:province":"AZ",
    "sg:tags":[
        "shop",
        "retail",
        "ice",
        "cream"
    ],
    "sg:website":"www.baskinrobbins.com",
    "wof:name":"Baskin-Robbins",
    "wof:placetype":"venue"
},
  "geometry": {"coordinates":[-112.153825,33.610805],"type":"Point"}
}