{
  "type": "Feature",
  "properties": {
    "iso:country":"US",
    "sg:address":"704 S Haskell Ave",
    "sg:city":"Willcox",
    "sg:classifiers":[
        {
            "category":"Travel",
            "subcategory":"Hotels & Motels",
            "type":"Entertainment"
        }
    ],
    "sg:phone":"+1 520 384 3577",
    "sg:postcode":"85643",
    "sg:province":"AZ",
    "wof:name":"Desert Inn Of Willcox",
    "wof:placetype":"venue"
},
  "geometry": {"coordinates":[-109.83756099999999,32.244712],"type":"Point"}
}