{
  "type": "Feature",
  "properties": {
    "addr:full":"3040 N Campbell Ave Tucson AZ 85719",
    "addr:housenumber":"3040",
    "addr:postcode":"85719",
    "addr:street":"N Campbell Ave",
    "iso:country":"US",
    "sg:address":"3040 N Campbell Ave",
    "sg:city":"Tucson",
    "sg:classifiers":[
        {
            "category":"Shopping",
            "subcategory":"Used Merchandise",
            "type":"Retail Goods"
        }
    ],
    "sg:phone":"+1 520 881 4950",
    "sg:postcode":"85719",
    "sg:province":"AZ",
    "sg:tags":[
        "clothing"
    ],
    "sg:website":"www.shopselltrade.com",
    "wof:name":"Twice As Nice Family Fashion",
    "wof:placetype":"venue"
},
  "geometry": {"coordinates":[-110.94373,32.26224],"type":"Point"}
}