{
  "type": "Feature",
  "properties": {
    "iso:country":"US",
    "sg:address":"3122 W Melvin St",
    "sg:city":"Phoenix",
    "sg:classifiers":[
        {
            "category":"Restaurant",
            "type":"Food & Drink"
        }
    ],
    "sg:phone":"+1 602 278 6783",
    "sg:postcode":"85009",
    "sg:province":"AZ",
    "sg:tags":[
        "mexican"
    ],
    "wof:name":"Frankie Garcia Jr",
    "wof:placetype":"venue"
},
  "geometry": {"coordinates":[-112.12649500000001,33.452244],"type":"Point"}
}