{
  "type": "Feature",
  "properties": {
    "iso:country":"US",
    "sg:address":"5757 N Oracle Rd",
    "sg:city":"Tucson",
    "sg:classifiers":[
        {
            "category":"Home & Garden",
            "subcategory":"Home Furnishings",
            "type":"Retail Goods"
        }
    ],
    "sg:phone":"+1 520 888 8867",
    "sg:postcode":"85704",
    "sg:province":"AZ",
    "sg:tags":[
        "wholesale",
        "stove",
        "wood",
        "burning"
    ],
    "wof:name":"Earth Energy Hearth and Patio",
    "wof:placetype":"venue"
},
  "geometry": {"coordinates":[-110.97858100000001,32.311348],"type":"Point"}
}