{
  "type": "Feature",
  "properties": {
    "addr:full":"650 E Park Ave Chandler AZ 85225",
    "addr:housenumber":"650",
    "addr:postcode":"85225",
    "addr:street":"E Park Ave",
    "iso:country":"US",
    "sg:address":"650 E Park Ave",
    "sg:city":"Chandler",
    "sg:classifiers":[
        {
            "category":"Building & Trades",
            "subcategory":"Plumbing",
            "type":"Services"
        }
    ],
    "sg:phone":"+1 480 659 3511",
    "sg:postcode":"85225",
    "sg:province":"AZ",
    "sg:tags":[
        "contractor"
    ],
    "wof:name":"Direct H2o Plumbing and Inc",
    "wof:placetype":"venue"
},
  "geometry": {"coordinates":[-111.831395,33.322326],"type":"Point"}
}