{
  "type": "Feature",
  "properties": {
    "iso:country":"US",
    "sg:address":"9202 N 2nd St",
    "sg:city":"Phoenix",
    "sg:classifiers":[
        {
            "category":"Health Services",
            "subcategory":"Hospital",
            "type":"Services"
        }
    ],
    "sg:phone":"+1 602 870 6300",
    "sg:postcode":"85020",
    "sg:province":"AZ",
    "sg:website":"www.jcl.com",
    "wof:name":"Cowden Center",
    "wof:placetype":"venue"
},
  "geometry": {"coordinates":[-112.071752,33.57046],"type":"Point"}
}