{
  "type": "Feature",
  "properties": {
    "addr:full":"14040 N Cave Creek Rd Phoenix AZ 85022",
    "addr:housenumber":"14040",
    "addr:postcode":"85022",
    "addr:street":"N Cave Creek Rd",
    "iso:country":"US",
    "sg:address":"14040 N Cave Creek Rd",
    "sg:city":"Phoenix",
    "sg:classifiers":[
        {
            "category":"Manufacturing",
            "subcategory":"Printing",
            "type":"Manufacturing & Wholesale Goods"
        }
    ],
    "sg:phone":"+1 602 867 4700",
    "sg:postcode":"85022",
    "sg:province":"AZ",
    "sg:tags":[
        "publisher"
    ],
    "wof:name":"North American Publishers Svc",
    "wof:placetype":"venue"
},
  "geometry": {"coordinates":[-112.034532,33.615375],"type":"Point"}
}