{
  "type": "Feature",
  "properties": {
    "iso:country":"US",
    "sg:address":"7701 E Gray Rd",
    "sg:city":"Scottsdale",
    "sg:classifiers":[
        {
            "category":"Freight",
            "type":"Transportation"
        }
    ],
    "sg:phone":"+1 480 948 8448",
    "sg:postcode":"85260",
    "sg:province":"AZ",
    "sg:tags":[
        "forwarder",
        "broker"
    ],
    "wof:name":"E Besler and Co",
    "wof:placetype":"venue"
},
  "geometry": {"coordinates":[-111.911973,33.612378],"type":"Point"}
}