{
  "type": "Feature",
  "properties": {
    "addr:full":"933 E University Dr Tempe AZ 85281",
    "addr:housenumber":"933",
    "addr:postcode":"85281",
    "addr:street":"E University Dr",
    "iso:country":"US",
    "sg:address":"933 E University Dr",
    "sg:city":"Tempe",
    "sg:classifiers":[
        {
            "category":"Shopping",
            "subcategory":"Department Store",
            "type":"Retail Goods"
        }
    ],
    "sg:phone":"+1 480 968 4135",
    "sg:postcode":"85281",
    "sg:province":"AZ",
    "wof:name":"Tempe Towne Assoc Maintenace",
    "wof:placetype":"venue"
},
  "geometry": {"coordinates":[-111.92371900000001,33.421962],"type":"Point"}
}