{
  "type": "Feature",
  "properties": {
    "iso:country":"US",
    "sg:address":"4855 E Warner Rd",
    "sg:city":"Phoenix",
    "sg:classifiers":[
        {
            "category":"Manufacturing",
            "subcategory":"Food",
            "type":"Manufacturing & Wholesale Goods"
        },
        {
            "category":"Restaurant",
            "type":"Food & Drink"
        },
        {
            "category":"Ice Cream",
            "type":"Food & Drink"
        }
    ],
    "sg:phone":"+1 480 785 1141",
    "sg:postcode":"85044",
    "sg:province":"AZ",
    "sg:tags":[
        "frozen",
        "desserts-manufacturers",
        "distributor",
        "dessert"
    ],
    "wof:name":"Golden Spoon Frozen Yogurt",
    "wof:placetype":"venue"
},
  "geometry": {"coordinates":[-111.98001600000001,33.330894],"type":"Point"}
}