{
  "type": "Feature",
  "properties": {
    "iso:country":"US",
    "sg:address":"1949 E Broadway Rd",
    "sg:city":"Tempe",
    "sg:classifiers":[
        {
            "category":"Professional",
            "subcategory":"Detective & Security Services",
            "type":"Services"
        }
    ],
    "sg:phone":"+1 480 967 4444",
    "sg:postcode":"85282",
    "sg:province":"AZ",
    "sg:tags":[
        "investigator"
    ],
    "wof:name":"Bio Technics Investigations",
    "wof:placetype":"venue"
},
  "geometry": {"coordinates":[-111.904192,33.4075],"type":"Point"}
}