{
  "type": "Feature",
  "properties": {
    "addr:full":"270 E Congress St Tucson AZ 85701",
    "addr:housenumber":"270",
    "addr:postcode":"85701",
    "addr:street":"E Congress St",
    "iso:country":"US",
    "sg:address":"270 E Congress St",
    "sg:city":"Tucson",
    "sg:classifiers":[
        {
            "category":"Retail",
            "subcategory":"Repair Shop",
            "type":"Services"
        }
    ],
    "sg:phone":"+1 520 791 9195",
    "sg:postcode":"85701",
    "sg:province":"AZ",
    "sg:tags":[
        "merchandise"
    ],
    "wof:name":"Sid Zaro Custom Framing",
    "wof:placetype":"venue"
},
  "geometry": {"coordinates":[-110.967309,32.221979],"type":"Point"}
}