{
  "type": "Feature",
  "properties": {
    "iso:country":"US",
    "sg:address":"10210 N 23rd Ave",
    "sg:city":"Phoenix",
    "sg:classifiers":[
        {
            "category":"Government",
            "subcategory":"Office",
            "type":"Public Place"
        }
    ],
    "sg:phone":"+1 602 470 4646",
    "sg:postcode":"85021",
    "sg:province":"AZ",
    "wof:name":"Arizona Vehicle Inspection",
    "wof:placetype":"venue"
},
  "geometry": {"coordinates":[-112.108215,33.58001],"type":"Point"}
}