{
  "type": "Feature",
  "properties": {
    "iso:country":"US",
    "sg:address":"4322 E Branded Rd",
    "sg:city":"Gilbert",
    "sg:classifiers":[
        {
            "category":"Professional",
            "subcategory":"Business Services",
            "type":"Services"
        }
    ],
    "sg:phone":"+1 480 279 2359",
    "sg:postcode":"85297",
    "sg:province":"AZ",
    "sg:tags":[
        "interior",
        "consultant",
        "design",
        "decorator"
    ],
    "wof:name":"Interior Ideas By Kristine",
    "wof:placetype":"venue"
},
  "geometry": {"coordinates":[-111.697036,33.266675],"type":"Point"}
}