{
  "type": "Feature",
  "properties": {
    "iso:country":"US",
    "sg:address":"7018 W Brown St",
    "sg:city":"Peoria",
    "sg:classifiers":[
        {
            "category":"Professional",
            "subcategory":"Engineering",
            "type":"Services"
        },
        {
            "category":"Building & Trades",
            "subcategory":"Construction",
            "type":"Services"
        }
    ],
    "sg:phone":"+1 623 334 1570",
    "sg:postcode":"85345",
    "sg:province":"AZ",
    "sg:tags":[
        "system",
        "contractor",
        "equipment",
        "ventilating",
        "air conditioning"
    ],
    "wof:name":"Ultraire Inc",
    "wof:placetype":"venue"
},
  "geometry": {"coordinates":[-112.209814,33.577218],"type":"Point"}
}