{
  "type": "Feature",
  "properties": {
    "iso:country":"US",
    "sg:address":"1746 E Madison St",
    "sg:city":"Phoenix",
    "sg:classifiers":[
        {
            "category":"Professional",
            "subcategory":"Employment Agencies",
            "type":"Services"
        }
    ],
    "sg:phone":"+1 602 252 3577",
    "sg:postcode":"85034",
    "sg:province":"AZ",
    "sg:tags":[
        "help",
        "contractor"
    ],
    "wof:name":"Aztex Temporaries",
    "wof:placetype":"venue"
},
  "geometry": {"coordinates":[-112.04423800000001,33.446252],"type":"Point"}
}