{
  "type": "Feature",
  "properties": {
    "iso:country":"US",
    "sg:address":"1125 W Baseline Rd",
    "sg:city":"Mesa",
    "sg:classifiers":[
        {
            "category":"Personal",
            "type":"Services"
        }
    ],
    "sg:phone":"+1 480 897 0833",
    "sg:postcode":"85210",
    "sg:province":"AZ",
    "sg:tags":[
        "therapist",
        "massage"
    ],
    "wof:name":"Gail's Therapeutic Massage",
    "wof:placetype":"venue"
},
  "geometry": {"coordinates":[-111.854292,33.378832],"type":"Point"}
}