{
  "type": "Feature",
  "properties": {
    "iso:country":"US",
    "sg:address":"119 W Central Ave",
    "sg:city":"Coolidge",
    "sg:classifiers":[
        {
            "category":"Government",
            "subcategory":"Office",
            "type":"Public Place"
        }
    ],
    "sg:phone":"+1 520 723 4174",
    "sg:postcode":"85228",
    "sg:province":"AZ",
    "sg:tags":[
        "administrative",
        "program",
        "health"
    ],
    "wof:name":"Pinal County Health Dept",
    "wof:placetype":"venue"
},
  "geometry": {"coordinates":[-111.51764,32.977582],"type":"Point"}
}