{
  "type": "Feature",
  "properties": {
    "iso:country":"US",
    "sg:address":"6508 W Northview Ave",
    "sg:city":"Glendale",
    "sg:classifiers":[
        {
            "category":"Manufacturing",
            "subcategory":"Buildings",
            "type":"Manufacturing & Wholesale Goods"
        },
        {
            "category":"Building & Trades",
            "subcategory":"Plumbing",
            "type":"Services"
        },
        {
            "category":"Building & Trades",
            "subcategory":"Construction",
            "type":"Services"
        }
    ],
    "sg:phone":"+1 623 435 2808",
    "sg:postcode":"85301",
    "sg:province":"AZ",
    "sg:tags":[
        "industrial",
        "builder",
        "contractor",
        "pipe",
        "contractors-commercial",
        "home",
        "line"
    ],
    "wof:name":"Tierra Contracting Inc",
    "wof:placetype":"venue"
},
  "geometry": {"coordinates":[-112.19949099999999,33.543207],"type":"Point"}
}