{
  "type": "Feature",
  "properties": {
    "iso:country":"US",
    "sg:address":"7914 E Thunderhawk Rd",
    "sg:city":"Scottsdale",
    "sg:classifiers":[
        {
            "category":"Insurance",
            "subcategory":"Insurance Agent",
            "type":"Services"
        }
    ],
    "sg:phone":"+1 480 502 9552",
    "sg:postcode":"85255",
    "sg:province":"AZ",
    "wof:name":"Matroni Insurance",
    "wof:placetype":"venue"
},
  "geometry": {"coordinates":[-111.910731,33.676285],"type":"Point"}
}