{
  "type": "Feature",
  "properties": {
    "iso:country":"US",
    "sg:address":"113 E State Highway 260",
    "sg:city":"Payson",
    "sg:classifiers":[
        {
            "category":"Restaurant",
            "type":"Food & Drink"
        }
    ],
    "sg:phone":"+1 928 472 7250",
    "sg:postcode":"85541",
    "sg:province":"AZ",
    "sg:tags":[
        "pizza"
    ],
    "wof:name":"Pizza Hut Of The Globe",
    "wof:placetype":"venue"
},
  "geometry": {"coordinates":[-111.322148,34.240551],"type":"Point"}
}