{
  "type": "Feature",
  "properties": {
    "addr:full":"2660 W Quail Ave Phoenix AZ 85027",
    "addr:housenumber":"2660",
    "addr:postcode":"85027",
    "addr:street":"W Quail Ave",
    "iso:country":"US",
    "sg:address":"2660 W Quail Ave",
    "sg:city":"Phoenix",
    "sg:classifiers":[
        {
            "category":"Manufacturing",
            "subcategory":"Tools & Machinery",
            "type":"Manufacturing & Wholesale Goods"
        }
    ],
    "sg:phone":"+1 623 869 6749",
    "sg:postcode":"85027",
    "sg:province":"AZ",
    "sg:tags":[
        "machine",
        "automobile",
        "shop"
    ],
    "wof:name":"Jet Products",
    "wof:placetype":"venue"
},
  "geometry": {"coordinates":[-112.116123,33.67841],"type":"Point"}
}