{
  "type": "Feature",
  "properties": {
    "iso:country":"US",
    "sg:address":"215 Air Terminal Dr",
    "sg:city":"Sedona",
    "sg:classifiers":[
        {
            "category":"Retail",
            "subcategory":"Auto Rental",
            "type":"Services"
        }
    ],
    "sg:phone":"+1 928 282 6004",
    "sg:postcode":"86336",
    "sg:province":"AZ",
    "sg:tags":[
        "renting",
        "automobile"
    ],
    "wof:name":"Avis Rent A Car",
    "wof:placetype":"venue"
},
  "geometry": {"coordinates":[-111.78996100000001,34.851011],"type":"Point"}
}