{
  "type": "Feature",
  "properties": {
    "addr:full":"405 W Congress St Tucson AZ 85701",
    "addr:housenumber":"405",
    "addr:postcode":"85701",
    "addr:street":"W Congress St",
    "iso:country":"US",
    "sg:address":"405 W Congress St",
    "sg:city":"Tucson",
    "sg:classifiers":[
        {
            "category":"Government",
            "subcategory":"Court House",
            "type":"Public Place"
        }
    ],
    "sg:phone":"+1 520 205 4200",
    "sg:postcode":"85701",
    "sg:province":"AZ",
    "sg:tags":[
        "federal"
    ],
    "wof:name":"US District Court Clerk",
    "wof:placetype":"venue"
},
  "geometry": {"coordinates":[-110.978478,32.221003],"type":"Point"}
}