{
  "type": "Feature",
  "properties": {
    "iso:country":"US",
    "sg:address":"3612 W Dunlap Ave Ste K",
    "sg:city":"Phoenix",
    "sg:classifiers":[
        {
            "category":"Professional",
            "type":"Services"
        }
    ],
    "sg:phone":"+1 602 230 1144",
    "sg:postcode":"85051",
    "sg:province":"AZ",
    "sg:tags":[
        "processing",
        "data"
    ],
    "wof:name":"Phoenix 3612",
    "wof:placetype":"venue"
},
  "geometry": {"coordinates":[-112.137597,33.567542],"type":"Point"}
}