{
  "type": "Feature",
  "properties": {
    "iso:country":"US",
    "sg:address":"5618 E Broadway Blvd",
    "sg:city":"Tucson",
    "sg:classifiers":[
        {
            "category":"Retail",
            "subcategory":"Repair Shop",
            "type":"Services"
        }
    ],
    "sg:phone":"+1 520 747 9947",
    "sg:postcode":"85711",
    "sg:province":"AZ",
    "sg:tags":[
        "jewelry"
    ],
    "sg:website":"www.bertlayneclocks.com",
    "wof:name":"Bert Layne Jewelers & Clocks",
    "wof:placetype":"venue"
},
  "geometry": {"coordinates":[-110.872735,32.221531],"type":"Point"}
}