{
  "type": "Feature",
  "properties": {
    "iso:country":"US",
    "sg:address":"202 W Main St",
    "sg:city":"Mesa",
    "sg:classifiers":[
        {
            "category":"Shopping",
            "subcategory":"Clothing, Apparel, & Fashions",
            "type":"Retail Goods"
        }
    ],
    "sg:phone":"+1 480 827 1868",
    "sg:postcode":"85201",
    "sg:province":"AZ",
    "sg:tags":[
        "leather"
    ],
    "wof:name":"Joeta's Leather Outlet",
    "wof:placetype":"venue"
},
  "geometry": {"coordinates":[-111.839181,33.415196],"type":"Point"}
}