{
  "type": "Feature",
  "properties": {
    "addr:full":"1440 N 40th St Mesa AZ 85205",
    "addr:housenumber":"1440",
    "addr:postcode":"85205",
    "addr:street":"N 40Th St",
    "iso:country":"US",
    "sg:address":"1440 N 40th St",
    "sg:city":"Mesa",
    "sg:classifiers":[
        {
            "category":"Manufacturing",
            "subcategory":"Printing",
            "type":"Manufacturing & Wholesale Goods"
        }
    ],
    "sg:phone":"+1 480 396 4339",
    "sg:postcode":"85205",
    "sg:province":"AZ",
    "sg:tags":[
        "mfg"
    ],
    "wof:name":"Scrapbook Kits",
    "wof:placetype":"venue"
},
  "geometry": {"coordinates":[-111.744879,33.441828],"type":"Point"}
}