{
  "type": "Feature",
  "properties": {
    "iso:country":"US",
    "sg:address":"3104 E Camelback Rd",
    "sg:city":"Phoenix",
    "sg:classifiers":[
        {
            "category":"Building & Trades",
            "subcategory":"Pest Control",
            "type":"Services"
        }
    ],
    "sg:phone":"+1 602 331 0800",
    "sg:postcode":"85016",
    "sg:province":"AZ",
    "sg:website":"http://abeepestpro.com",
    "wof:name":"A Bee & Pest Pro",
    "wof:placetype":"venue"
},
  "geometry": {"coordinates":[-112.015902,33.509993],"type":"Point"}
}