{
  "type": "Feature",
  "properties": {
    "iso:country":"US",
    "sg:address":"3845 S Country Club Rd",
    "sg:city":"Tucson",
    "sg:classifiers":[
        {
            "category":"Food & Beverages",
            "subcategory":"Groceries & Convenience Stores",
            "type":"Retail Goods"
        }
    ],
    "sg:phone":"+1 520 746 3600",
    "sg:postcode":"85714",
    "sg:province":"AZ",
    "wof:name":"Circle K",
    "wof:placetype":"venue"
},
  "geometry": {"coordinates":[-110.92629599999999,32.177352],"type":"Point"}
}