{
  "type": "Feature",
  "properties": {
    "iso:country":"US",
    "sg:address":"701 N 44th St",
    "sg:city":"Phoenix",
    "sg:classifiers":[
        {
            "category":"Retail",
            "subcategory":"Laundry & Dry Cleaning",
            "type":"Services"
        }
    ],
    "sg:phone":"+1 602 220 5292",
    "sg:postcode":"85008",
    "sg:province":"AZ",
    "sg:tags":[
        "equipment",
        "supply"
    ],
    "wof:name":"Western Equipment Company",
    "wof:placetype":"venue"
},
  "geometry": {"coordinates":[-111.987083,33.4557],"type":"Point"}
}