{
  "type": "Feature",
  "properties": {
    "addr:full":"2222 W Grant St Phoenix AZ 85009",
    "addr:housenumber":"2222",
    "addr:postcode":"85009",
    "addr:street":"W Grant St",
    "iso:country":"US",
    "sg:address":"2222 W Grant St",
    "sg:city":"Phoenix",
    "sg:classifiers":[
        {
            "category":"Building & Trades",
            "subcategory":"Plumbing",
            "type":"Services"
        }
    ],
    "sg:phone":"+1 602 705 7626",
    "sg:postcode":"85009",
    "sg:province":"AZ",
    "sg:tags":[
        "plumber",
        "contractor"
    ],
    "wof:name":"Roto-Rooter Plumbing & Drain",
    "wof:placetype":"venue"
},
  "geometry": {"coordinates":[-112.106791,33.441319],"type":"Point"}
}