{
  "type": "Feature",
  "properties": {
    "iso:country":"US",
    "sg:address":"650 N Scottsdale Rd",
    "sg:city":"Tempe",
    "sg:classifiers":[
        {
            "category":"Restaurant",
            "type":"Food & Drink"
        }
    ],
    "sg:menulink":"http://www.allmenus.com/az/phoenix/9299-dennys/menu/",
    "sg:phone":"+1 480 858 9276",
    "sg:postcode":"85281",
    "sg:province":"AZ",
    "sg:tags":[
        "american",
        "diner"
    ],
    "wof:name":"Denny's",
    "wof:placetype":"venue"
},
  "geometry": {"coordinates":[-111.926334,33.435082],"type":"Point"}
}