{
  "type": "Feature",
  "properties": {
    "iso:country":"US",
    "sg:address":"6366 N Cam Los Machis",
    "sg:city":"Tucson",
    "sg:classifiers":[
        {
            "category":"Professional",
            "subcategory":"Engineering",
            "type":"Services"
        }
    ],
    "sg:phone":"+1 520 577 2153",
    "sg:postcode":"85718",
    "sg:province":"AZ",
    "sg:tags":[
        "engineer"
    ],
    "wof:name":"James S Caid Engineers",
    "wof:placetype":"venue"
},
  "geometry": {"coordinates":[-110.89609799999999,32.320925],"type":"Point"}
}