{
  "type": "Feature",
  "properties": {
    "iso:country":"US",
    "sg:address":"6616 S 28th St",
    "sg:city":"Phoenix",
    "sg:classifiers":[
        {
            "category":"Retail",
            "subcategory":"Repair Shop",
            "type":"Services"
        }
    ],
    "sg:phone":"+1 602 276 5550",
    "sg:postcode":"85042",
    "sg:province":"AZ",
    "sg:tags":[
        "lighting",
        "fixture"
    ],
    "wof:name":"Double DD Electric Co",
    "wof:placetype":"venue"
},
  "geometry": {"coordinates":[-112.021351,33.3906],"type":"Point"}
}