{
  "type": "Feature",
  "properties": {
    "iso:country":"US",
    "sg:address":"10505 N 69th St",
    "sg:city":"Scottsdale",
    "sg:classifiers":[
        {
            "category":"Health Services",
            "subcategory":"Health Practitioner",
            "type":"Services"
        }
    ],
    "sg:phone":"+1 480 922 6912",
    "sg:postcode":"85253",
    "sg:province":"AZ",
    "sg:tags":[
        "psychologist"
    ],
    "wof:name":"Franklin M Berry",
    "wof:placetype":"venue"
},
  "geometry": {"coordinates":[-111.93244199999999,33.581189],"type":"Point"}
}