{
  "type": "Feature",
  "properties": {
    "iso:country":"US",
    "sg:address":"1811 S Alma School Rd Ste 232",
    "sg:city":"Mesa",
    "sg:classifiers":[
        {
            "category":"Professional",
            "subcategory":"Accounting & Tax Preparation",
            "type":"Services"
        }
    ],
    "sg:phone":"+1 480 461 1001",
    "sg:postcode":"85210",
    "sg:province":"AZ",
    "sg:tags":[
        "accountant"
    ],
    "sg:website":"www.satzcpa.com",
    "wof:name":"Craig Satz CPA P C",
    "wof:placetype":"venue"
},
  "geometry": {"coordinates":[-111.857894,33.382072],"type":"Point"}
}