{
  "type": "Feature",
  "properties": {
    "iso:country":"US",
    "sg:address":"124 W Beale St",
    "sg:city":"Kingman",
    "sg:classifiers":[
        {
            "category":"Retail",
            "subcategory":"Auto Repair",
            "type":"Services"
        }
    ],
    "sg:phone":"+1 928 753 3121",
    "sg:postcode":"86401",
    "sg:province":"AZ",
    "sg:tags":[
        "transmission"
    ],
    "wof:name":"Automatic Transmission Rbldrs",
    "wof:placetype":"venue"
},
  "geometry": {"coordinates":[-114.059762,35.190139],"type":"Point"}
}