{
  "type": "Feature",
  "properties": {
    "iso:country":"US",
    "sg:address":"1601 S 7th St",
    "sg:city":"Phoenix",
    "sg:classifiers":[
        {
            "category":"Wholesale",
            "subcategory":"Machinery & Supplies",
            "type":"Manufacturing & Wholesale Goods"
        }
    ],
    "sg:phone":"+1 602 252 2892",
    "sg:postcode":"85034",
    "sg:province":"AZ",
    "sg:tags":[
        "heavy",
        "equipment",
        "parts"
    ],
    "wof:name":"Klemmer",
    "wof:placetype":"venue"
},
  "geometry": {"coordinates":[-112.06512499999999,33.432252],"type":"Point"}
}