{
  "type": "Feature",
  "properties": {
    "iso:country":"US",
    "sg:address":"1911 W Fairway Ln",
    "sg:city":"Payson",
    "sg:classifiers":[
        {
            "category":"Building & Trades",
            "subcategory":"Plumbing",
            "type":"Services"
        }
    ],
    "sg:phone":"+1 928 472 9171",
    "sg:postcode":"85541",
    "sg:province":"AZ",
    "sg:tags":[
        "contractor"
    ],
    "wof:name":"Pride Plumbing",
    "wof:placetype":"venue"
},
  "geometry": {"coordinates":[-111.358517,34.23531],"type":"Point"}
}