{
  "type": "Feature",
  "properties": {
    "iso:country":"US",
    "sg:address":"2081 N Arizona Avenue 132",
    "sg:city":"Chandler",
    "sg:classifiers":[
        {
            "category":"Restaurant",
            "type":"Food & Drink"
        }
    ],
    "sg:phone":"+1 480 722 7577",
    "sg:postcode":"85225",
    "sg:province":"AZ",
    "sg:tags":[
        "caribbean"
    ],
    "wof:name":"Hot Pot Caribbean Cuisine",
    "wof:placetype":"venue"
},
  "geometry": {"coordinates":[-111.841712,33.337994],"type":"Point"}
}