{
  "type": "Feature",
  "properties": {
    "iso:country":"US",
    "sg:address":"2550 S Prudence Rd",
    "sg:city":"Tucson",
    "sg:classifiers":[
        {
            "category":"Building & Trades",
            "subcategory":"Construction",
            "type":"Services"
        }
    ],
    "sg:phone":"+1 520 721 1837",
    "sg:postcode":"85710",
    "sg:province":"AZ",
    "sg:tags":[
        "house"
    ],
    "wof:name":"Genesee Company LLC",
    "wof:placetype":"venue"
},
  "geometry": {"coordinates":[-110.832439,32.192185],"type":"Point"}
}