{
  "type": "Feature",
  "properties": {
    "addr:full":"3443 E Mcdowell Rd Mesa AZ 85213",
    "addr:housenumber":"3443",
    "addr:postcode":"85213",
    "addr:street":"E Mcdowell Rd",
    "iso:country":"US",
    "sg:address":"3443 E Mcdowell Rd",
    "sg:city":"Mesa",
    "sg:classifiers":[
        {
            "category":"Wholesale",
            "subcategory":"Motor Vehicles",
            "type":"Manufacturing & Wholesale Goods"
        }
    ],
    "sg:phone":"+1 480 797 5475",
    "sg:postcode":"85213",
    "sg:province":"AZ",
    "sg:tags":[
        "recreational",
        "campers-wholesale",
        "manufacturer"
    ],
    "wof:name":"Clausen & Clausen",
    "wof:placetype":"venue"
},
  "geometry": {"coordinates":[-111.755495,33.466389],"type":"Point"}
}