{
  "type": "Feature",
  "properties": {
    "addr:full":"15905 N Greenway Hayden Loop Scottsdale AZ 85260",
    "addr:housenumber":"15905",
    "addr:postcode":"85260",
    "addr:street":"N Greenway Hayden Loop",
    "iso:country":"US",
    "sg:address":"15905 N Greenway Hayden Loop",
    "sg:city":"Scottsdale",
    "sg:classifiers":[
        {
            "category":"Building & Trades",
            "subcategory":"Construction",
            "type":"Services"
        }
    ],
    "sg:phone":"+1 480 609 0319",
    "sg:postcode":"85260",
    "sg:province":"AZ",
    "sg:tags":[
        "general",
        "contractor"
    ],
    "wof:name":"Outdoor Settings",
    "wof:placetype":"venue"
},
  "geometry": {"coordinates":[-111.910917,33.630579],"type":"Point"}
}