{
  "type": "Feature",
  "properties": {
    "addr:full":"2928 W Colter St Phoenix AZ 85017",
    "addr:housenumber":"2928",
    "addr:postcode":"85017",
    "addr:street":"W Colter St",
    "iso:country":"US",
    "sg:address":"2928 W Colter St",
    "sg:city":"Phoenix",
    "sg:classifiers":[
        {
            "category":"Retail",
            "subcategory":"Auto Repair",
            "type":"Services"
        }
    ],
    "sg:phone":"+1 602 307 5514",
    "sg:postcode":"85017",
    "sg:province":"AZ",
    "sg:tags":[
        "body",
        "automobile",
        "painting"
    ],
    "wof:name":"Arthurs Auto Body & Frame",
    "wof:placetype":"venue"
},
  "geometry": {"coordinates":[-112.123993,33.513261],"type":"Point"}
}