{
  "type": "Feature",
  "properties": {
    "iso:country":"US",
    "sg:address":"4206 E Pearce Rd",
    "sg:city":"Phoenix",
    "sg:classifiers":[
        {
            "category":"Manufacturing",
            "subcategory":"Chemicals & Compounds",
            "type":"Manufacturing & Wholesale Goods"
        }
    ],
    "sg:phone":"+1 480 705 6745",
    "sg:postcode":"85044",
    "sg:province":"AZ",
    "sg:tags":[
        "carwash",
        "mfg"
    ],
    "wof:name":"Manarin Detailing Co",
    "wof:placetype":"venue"
},
  "geometry": {"coordinates":[-111.99468400000001,33.354788],"type":"Point"}
}