{
  "type": "Feature",
  "properties": {
    "iso:country":"US",
    "sg:address":"16140 N Arrowhead Fountains Ctr Dr 105",
    "sg:city":"Peoria",
    "sg:classifiers":[
        {
            "category":"Health Services",
            "subcategory":"Health Practitioner",
            "type":"Services"
        }
    ],
    "sg:phone":"+1 623 572 6776",
    "sg:postcode":"85382",
    "sg:province":"AZ",
    "sg:tags":[
        "therapist",
        "physical"
    ],
    "wof:name":"Physiotherapy Associates Inc",
    "wof:placetype":"venue"
},
  "geometry": {"coordinates":[-112.236407,33.634346],"type":"Point"}
}