{
  "type": "Feature",
  "properties": {
    "iso:country":"US",
    "sg:address":"101 Riviera Dr",
    "sg:city":"Lake Havasu City",
    "sg:classifiers":[
        {
            "category":"Health Services",
            "subcategory":"Doctor",
            "type":"Services"
        }
    ],
    "sg:phone":"+1 928 855 5061",
    "sg:postcode":"86403",
    "sg:province":"AZ",
    "sg:tags":[
        "dentist"
    ],
    "wof:name":"Hamstra & Mead",
    "wof:placetype":"venue"
},
  "geometry": {"coordinates":[-114.334944,34.480231],"type":"Point"}
}