{
  "type": "Feature",
  "properties": {
    "iso:country":"US",
    "sg:address":"6914 E Upper Trail Cir",
    "sg:city":"Mesa",
    "sg:classifiers":[
        {
            "category":"Shopping",
            "subcategory":"Clothing, Apparel, & Fashions",
            "type":"Retail Goods"
        }
    ],
    "sg:phone":"+1 480 654 6220",
    "sg:postcode":"85207",
    "sg:province":"AZ",
    "wof:name":"National Cstumers Associon UNC",
    "wof:placetype":"venue"
},
  "geometry": {"coordinates":[-111.68095099999999,33.489768],"type":"Point"}
}