{
  "type": "Feature",
  "properties": {
    "iso:country":"US",
    "sg:address":"240 N Broad St",
    "sg:city":"Globe",
    "sg:classifiers":[
        {
            "category":"Shopping",
            "subcategory":"Gifts & Souvenirs",
            "type":"Retail Goods"
        }
    ],
    "sg:phone":"+1 928 425 0902",
    "sg:postcode":"85501",
    "sg:province":"AZ",
    "sg:tags":[
        "shop"
    ],
    "wof:name":"Rusty Buffalo Traders",
    "wof:placetype":"venue"
},
  "geometry": {"coordinates":[-110.787973,33.397377],"type":"Point"}
}