{
  "type": "Feature",
  "properties": {
    "iso:country":"US",
    "sg:address":"1080 E Pecos Rd",
    "sg:city":"Chandler",
    "sg:classifiers":[
        {
            "category":"Home & Garden",
            "subcategory":"Carpets & Floor Coverings",
            "type":"Retail Goods"
        }
    ],
    "sg:phone":"+1 480 233 6368",
    "sg:postcode":"85225",
    "sg:province":"AZ",
    "sg:tags":[
        "material"
    ],
    "wof:name":"Hacienda Mexican Floors",
    "wof:placetype":"venue"
},
  "geometry": {"coordinates":[-111.823331,33.29182],"type":"Point"}
}