{
  "type": "Feature",
  "properties": {
    "iso:country":"US",
    "sg:address":"903 N Swan Rd",
    "sg:city":"Tucson",
    "sg:classifiers":[
        {
            "category":"Shopping",
            "subcategory":"Gifts & Souvenirs",
            "type":"Retail Goods"
        }
    ],
    "sg:phone":"+1 520 327 1945",
    "sg:postcode":"85711",
    "sg:province":"AZ",
    "sg:tags":[
        "party",
        "rent",
        "supply"
    ],
    "wof:name":"Party Carousel",
    "wof:placetype":"venue"
},
  "geometry": {"coordinates":[-110.89261,32.232781],"type":"Point"}
}