{
  "type": "Feature",
  "properties": {
    "iso:country":"US",
    "sg:address":"30 Scott Dr",
    "sg:city":"Lake Havasu City",
    "sg:classifiers":[
        {
            "category":"Real Estate",
            "subcategory":"Real Estate Agent",
            "type":"Services"
        }
    ],
    "sg:phone":"+1 928 855 0400",
    "sg:postcode":"86403",
    "sg:province":"AZ",
    "wof:name":"Arizona Coast Properties",
    "wof:placetype":"venue"
},
  "geometry": {"coordinates":[-114.33053,34.475632],"type":"Point"}
}