{
  "type": "Feature",
  "properties": {
    "iso:country":"US",
    "sg:address":"6033 W Bell Rd",
    "sg:city":"Glendale",
    "sg:classifiers":[
        {
            "category":"Professional",
            "subcategory":"Lawyer & Legal Services",
            "type":"Services"
        }
    ],
    "sg:phone":"+1 602 234 2000",
    "sg:postcode":"85308",
    "sg:province":"AZ",
    "sg:tags":[
        "attorney"
    ],
    "wof:name":"Henry G Hester",
    "wof:placetype":"venue"
},
  "geometry": {"coordinates":[-112.188387,33.638616],"type":"Point"}
}