{
  "type": "Feature",
  "properties": {
    "iso:country":"US",
    "sg:address":"2924 N 68th St",
    "sg:city":"Scottsdale",
    "sg:classifiers":[
        {
            "category":"Professional",
            "subcategory":"Management & Consulting",
            "type":"Services"
        }
    ],
    "sg:phone":"+1 480 994 8120",
    "sg:postcode":"85251",
    "sg:province":"AZ",
    "sg:tags":[
        "consultants-referral",
        "international",
        "consultant"
    ],
    "wof:name":"Condor International Ltd.",
    "wof:placetype":"venue"
},
  "geometry": {"coordinates":[-111.93476099999999,33.480716],"type":"Point"}
}