{
  "type": "Feature",
  "properties": {
    "iso:country":"US",
    "sg:address":"4225 W Glendale Ave",
    "sg:city":"Phoenix",
    "sg:classifiers":[
        {
            "category":"Organizations",
            "subcategory":"Religious Organization",
            "type":"Services"
        }
    ],
    "sg:phone":"+1 602 434 5774",
    "sg:postcode":"85051",
    "sg:province":"AZ",
    "sg:tags":[
        "church"
    ],
    "wof:name":"Phoenix Free Presbyterian Chr",
    "wof:placetype":"venue"
},
  "geometry": {"coordinates":[-112.151179,33.538377],"type":"Point"}
}