{
  "type": "Feature",
  "properties": {
    "addr:full":"6006 N 83rd Ave Glendale AZ 85303",
    "addr:housenumber":"6006",
    "addr:postcode":"85303",
    "addr:street":"N 83Rd Ave",
    "iso:country":"US",
    "sg:address":"6006 N 83rd Ave",
    "sg:city":"Glendale",
    "sg:classifiers":[
        {
            "category":"Real Estate",
            "subcategory":"Real Estate Agent",
            "type":"Services"
        }
    ],
    "sg:phone":"+1 623 247 2500",
    "sg:postcode":"85303",
    "sg:province":"AZ",
    "sg:tags":[
        "development",
        "residential",
        "land",
        "broker"
    ],
    "wof:name":"Traw & Associates Inc",
    "wof:placetype":"venue"
},
  "geometry": {"coordinates":[-112.23773199999999,33.52347],"type":"Point"}
}