{
  "type": "Feature",
  "properties": {
    "iso:country":"US",
    "sg:address":"4925 E Desert Cove Ave",
    "sg:city":"Scottsdale",
    "sg:classifiers":[
        {
            "category":"Banks & Credit Unions",
            "subcategory":"Investment Brokerage",
            "type":"Services"
        }
    ],
    "sg:phone":"+1 480 607 9998",
    "sg:postcode":"85254",
    "sg:province":"AZ",
    "sg:tags":[
        "consultant"
    ],
    "wof:name":"Krene Group LLC",
    "wof:placetype":"venue"
},
  "geometry": {"coordinates":[-111.976283,33.586239],"type":"Point"}
}