{
  "type": "Feature",
  "properties": {
    "iso:country":"US",
    "sg:address":"3351 N 87th Ave",
    "sg:city":"Phoenix",
    "sg:classifiers":[
        {
            "category":"Building & Trades",
            "subcategory":"Locksmith",
            "type":"Services"
        }
    ],
    "sg:phone":"+1 623 734 1896",
    "sg:postcode":"85037",
    "sg:province":"AZ",
    "sg:tags":[
        "key"
    ],
    "wof:name":"A 24 Hour A Locksmith",
    "wof:placetype":"venue"
},
  "geometry": {"coordinates":[-112.246297,33.486779],"type":"Point"}
}