{
  "type": "Feature",
  "properties": {
    "addr:full":"1785 S Railroad Springs Blvd Flagstaff AZ 86001",
    "addr:housenumber":"1785",
    "addr:postcode":"86001",
    "addr:street":"S Railroad Springs Blvd",
    "iso:country":"US",
    "sg:address":"1785 S Railroad Springs Blvd",
    "sg:city":"Flagstaff",
    "sg:classifiers":[
        {
            "category":"Food & Beverages",
            "subcategory":"Groceries & Convenience Stores",
            "type":"Retail Goods"
        }
    ],
    "sg:phone":"+1 928 773 9500",
    "sg:postcode":"86001",
    "sg:province":"AZ",
    "wof:name":"Whistle Stop Fueling Station",
    "wof:placetype":"venue"
},
  "geometry": {"coordinates":[-111.68072100000001,35.187864],"type":"Point"}
}