{
  "type": "Feature",
  "properties": {
    "addr:full":"3116 S Mill Ave Tempe AZ 85282",
    "addr:housenumber":"3116",
    "addr:postcode":"85282",
    "addr:street":"S Mill Ave",
    "iso:country":"US",
    "sg:address":"3116 S Mill Ave",
    "sg:city":"Tempe",
    "sg:classifiers":[
        {
            "category":"Personal",
            "type":"Services"
        }
    ],
    "sg:phone":"+1 480 233 0753",
    "sg:postcode":"85282",
    "sg:province":"AZ",
    "sg:tags":[
        "car",
        "loading",
        "unloading"
    ],
    "wof:name":"Desert Choice Movers",
    "wof:placetype":"venue"
},
  "geometry": {"coordinates":[-111.939627,33.395274],"type":"Point"}
}