{
  "type": "Feature",
  "properties": {
    "addr:full":"6021 S 45th St Phoenix AZ 85042",
    "addr:housenumber":"6021",
    "addr:postcode":"85042",
    "addr:street":"S 45Th St",
    "iso:country":"US",
    "sg:address":"6021 S 45th St",
    "sg:city":"Phoenix",
    "sg:classifiers":[
        {
            "category":"Professional",
            "subcategory":"Computer Services",
            "type":"Services"
        },
        {
            "category":"Internet Cafe",
            "subcategory":"None",
            "type":"Food & Drink"
        }
    ],
    "sg:phone":"+1 602 438 2778",
    "sg:postcode":"85042",
    "sg:province":"AZ",
    "sg:tags":[
        "consultant",
        "product",
        "designer",
        "system",
        "software"
    ],
    "wof:name":"Computer Management And Software Design",
    "wof:placetype":"venue"
},
  "geometry": {"coordinates":[-111.985035,33.39253],"type":"Point"}
}