{
  "type": "Feature",
  "properties": {
    "iso:country":"US",
    "sg:address":"708 E 32nd St",
    "sg:city":"Yuma",
    "sg:classifiers":[
        {
            "category":"Insurance",
            "subcategory":"Insurance Agent",
            "type":"Services"
        }
    ],
    "sg:phone":"+1 602 341 1150",
    "sg:postcode":"85365",
    "sg:province":"AZ",
    "wof:name":"Martin C Armijo Insurance",
    "wof:placetype":"venue"
},
  "geometry": {"coordinates":[-114.613104,32.669509],"type":"Point"}
}