{
  "type": "Feature",
  "properties": {
    "addr:full":"4715 N Stage Way Ln Prescott Valley AZ 86314",
    "addr:housenumber":"4715",
    "addr:postcode":"86314",
    "addr:street":"N Stage Way Ln",
    "iso:country":"US",
    "sg:address":"4715 N Stage Way Ln",
    "sg:city":"Prescott Valley",
    "sg:classifiers":[
        {
            "category":"Social Services",
            "type":"Services"
        }
    ],
    "sg:phone":"+1 928 775 0019",
    "sg:postcode":"86314",
    "sg:province":"AZ",
    "sg:tags":[
        "counselor",
        "marriage",
        "family"
    ],
    "wof:name":"Bradshaw Mountain Counseling",
    "wof:placetype":"venue"
},
  "geometry": {"coordinates":[-112.341188,34.608386],"type":"Point"}
}