{
  "type": "Feature",
  "properties": {
    "iso:country":"US",
    "sg:address":"3210 S 80th Ave",
    "sg:city":"Phoenix",
    "sg:classifiers":[
        {
            "category":"Building & Trades",
            "subcategory":"Locksmith",
            "type":"Services"
        }
    ],
    "sg:phone":"+1 602 635 6883",
    "sg:postcode":"85043",
    "sg:province":"AZ",
    "sg:tags":[
        "key"
    ],
    "wof:name":"Locksmith Emergency",
    "wof:placetype":"venue"
},
  "geometry": {"coordinates":[-112.231714,33.419037],"type":"Point"}
}