{
  "type": "Feature",
  "properties": {
    "iso:country":"US",
    "sg:address":"356 W Cam de Mesa",
    "sg:city":"Huachuca City",
    "sg:classifiers":[
        {
            "category":"Building & Trades",
            "subcategory":"Construction",
            "type":"Services"
        }
    ],
    "sg:phone":"+1 520 456 2020",
    "sg:postcode":"85616",
    "sg:province":"AZ",
    "sg:tags":[
        "house",
        "general",
        "contractor"
    ],
    "wof:name":"Derosa Construction Co",
    "wof:placetype":"venue"
},
  "geometry": {"coordinates":[-110.358992,31.708615],"type":"Point"}
}