{
  "type": "Feature",
  "properties": {
    "addr:full":"7530 W Peoria Ave Ste F Peoria AZ 85345",
    "addr:housenumber":"7530",
    "addr:postcode":"85345",
    "addr:street":"W Peoria Ave Ste F",
    "iso:country":"US",
    "sg:address":"7530 W Peoria Ave Ste F",
    "sg:city":"Peoria",
    "sg:classifiers":[
        {
            "category":"Bars & Pubs",
            "type":"Food & Drink"
        },
        {
            "category":"Bars & Pubs",
            "subcategory":"Lounge",
            "type":"Food & Drink"
        }
    ],
    "sg:phone":"+1 623 878 4154",
    "sg:postcode":"85345",
    "sg:province":"AZ",
    "sg:tags":[
        "cocktail"
    ],
    "wof:name":"Neighbors",
    "wof:placetype":"venue"
},
  "geometry": {"coordinates":[-112.221345,33.581388],"type":"Point"}
}