{
  "type": "Feature",
  "properties": {
    "addr:full":"2031 E Taxidea Way Phoenix AZ 85048",
    "addr:housenumber":"2031",
    "addr:postcode":"85048",
    "addr:street":"E Taxidea Way",
    "iso:country":"US",
    "sg:address":"2031 E Taxidea Way",
    "sg:city":"Phoenix",
    "sg:classifiers":[
        {
            "category":"Building & Trades",
            "subcategory":"Construction",
            "type":"Services"
        }
    ],
    "sg:phone":"+1 602 739 1000",
    "sg:postcode":"85048",
    "sg:province":"AZ",
    "sg:tags":[
        "nonresidential"
    ],
    "wof:name":"D V Witcher Enterprises",
    "wof:placetype":"venue"
},
  "geometry": {"coordinates":[-112.038585,33.312766],"type":"Point"}
}