{
  "type": "Feature",
  "properties": {
    "addr:full":"1814 E Granada Rd Phoenix AZ 85006",
    "addr:housenumber":"1814",
    "addr:postcode":"85006",
    "addr:street":"E Granada Rd",
    "iso:country":"US",
    "sg:address":"1814 E Granada Rd",
    "sg:city":"Phoenix",
    "sg:classifiers":[
        {
            "category":"Professional",
            "type":"Services"
        }
    ],
    "sg:phone":"+1 602 538 7904",
    "sg:postcode":"85006",
    "sg:province":"AZ",
    "wof:name":"Micor Energy LLC",
    "wof:placetype":"venue"
},
  "geometry": {"coordinates":[-112.04127800000001,33.46855],"type":"Point"}
}