{
  "type": "Feature",
  "properties": {
    "iso:country":"US",
    "sg:address":"1537 E Dava Drive",
    "sg:city":"Tempe",
    "sg:classifiers":[
        {
            "category":"Shopping",
            "subcategory":"Antiques",
            "type":"Retail Goods"
        },
        {
            "category":"Building & Trades",
            "subcategory":"Construction",
            "type":"Services"
        }
    ],
    "sg:phone":"+1 480 491 1506",
    "sg:postcode":"85283",
    "sg:province":"AZ",
    "sg:tags":[
        "contractor"
    ],
    "wof:name":"Geppetto's Wood Shop",
    "wof:placetype":"venue"
},
  "geometry": {"coordinates":[-111.915139,33.354464],"type":"Point"}
}