{
  "type": "Feature",
  "properties": {
    "iso:country":"US",
    "sg:address":"7119 E Shea Blvd",
    "sg:city":"Scottsdale",
    "sg:classifiers":[
        {
            "category":"Food & Beverages",
            "subcategory":"Specialty",
            "type":"Retail Goods"
        }
    ],
    "sg:phone":"+1 480 443 0053",
    "sg:postcode":"85254",
    "sg:province":"AZ",
    "sg:tags":[
        "health",
        "diet"
    ],
    "sg:website":"www.arizonahealthfoods.com",
    "wof:name":"Granola's",
    "wof:placetype":"venue"
},
  "geometry": {"coordinates":[-111.926897,33.582098],"type":"Point"}
}