{
  "type": "Feature",
  "properties": {
    "addr:full":"4515 S Mcclintock Dr # 201 Tempe AZ 85282",
    "addr:housenumber":"4515",
    "addr:postcode":"85282",
    "addr:street":"S Mcclintock Dr # 201",
    "iso:country":"US",
    "sg:address":"4515 S Mcclintock Dr # 201",
    "sg:city":"Tempe",
    "sg:classifiers":[
        {
            "category":"Insurance",
            "subcategory":"Hazard Insurance",
            "type":"Services"
        },
        {
            "category":"Banks & Credit Unions",
            "subcategory":"Financial Services",
            "type":"Services"
        }
    ],
    "sg:phone":"+1 480 632 0905",
    "sg:postcode":"85282",
    "sg:province":"AZ",
    "sg:tags":[
        "consultant",
        "planning",
        "commercial",
        "business"
    ],
    "sg:website":"http://www.primerica.com",
    "wof:name":"Primerica Financial Svc",
    "wof:placetype":"venue"
},
  "geometry": {"coordinates":[-111.90920699999999,33.383858],"type":"Point"}
}