{
  "type": "Feature",
  "properties": {
    "iso:country":"US",
    "sg:address":"27826 N 193rd Ave",
    "sg:city":"Wittmann",
    "sg:classifiers":[
        {
            "category":"Utilities",
            "subcategory":"Telephone",
            "type":"Services"
        }
    ],
    "sg:phone":"+1 623 388 2895",
    "sg:postcode":"85361",
    "sg:province":"AZ",
    "sg:tags":[
        "telecommunication"
    ],
    "wof:name":"MCI",
    "wof:placetype":"venue"
},
  "geometry": {"coordinates":[-112.477473,33.735615],"type":"Point"}
}