{
  "type": "Feature",
  "properties": {
    "iso:country":"US",
    "sg:address":"2835 N Central Ave",
    "sg:city":"Phoenix",
    "sg:classifiers":[
        {
            "category":"Insurance",
            "subcategory":"Insurance Agent",
            "type":"Services"
        }
    ],
    "sg:phone":"+1 602 285 9444",
    "sg:postcode":"85004",
    "sg:province":"AZ",
    "wof:name":"American Family Insurance",
    "wof:placetype":"venue"
},
  "geometry": {"coordinates":[-112.073699,33.479987],"type":"Point"}
}