{
  "type": "Feature",
  "properties": {
    "iso:country":"US",
    "sg:address":"8400 S Kyrene Rd",
    "sg:city":"Tempe",
    "sg:classifiers":[
        {
            "category":"Professional",
            "subcategory":"Lawyer & Legal Services",
            "type":"Services"
        }
    ],
    "sg:phone":"+1 623 229 3843",
    "sg:postcode":"85284",
    "sg:province":"AZ",
    "sg:tags":[
        "attorney",
        "criminal",
        "family",
        "clinic",
        "plan",
        "law"
    ],
    "sg:website":"http://www.aubuchonlaw.com",
    "wof:name":"Aubuchon Law Office",
    "wof:placetype":"venue"
},
  "geometry": {"coordinates":[-111.945686,33.338982],"type":"Point"}
}