{
  "type": "Feature",
  "properties": {
    "iso:country":"US",
    "sg:address":"1820 West Northern Avenue, Suite 100",
    "sg:city":"Phoenix",
    "sg:classifiers":[
        {
            "category":"Banks & Credit Unions",
            "subcategory":"Financial Services",
            "type":"Services"
        },
        {
            "category":"Insurance",
            "subcategory":"Insurance Agent",
            "type":"Services"
        },
        {
            "category":"Insurance",
            "subcategory":"Title Insurance",
            "type":"Services"
        },
        {
            "category":"Insurance",
            "subcategory":"Health Insurance",
            "type":"Services"
        },
        {
            "category":"Insurance",
            "subcategory":"Life Insurance",
            "type":"Services"
        },
        {
            "category":"Insurance",
            "subcategory":"Hazard Insurance",
            "type":"Services"
        }
    ],
    "sg:phone":"+1 602 997 7300",
    "sg:postcode":"85021",
    "sg:province":"AZ",
    "sg:tags":[
        "retirement",
        "annuity",
        "homeowner",
        "plan",
        "renter",
        "auto"
    ],
    "sg:website":"http://www.wesstahler.com",
    "wof:name":"State Farm Insurance - Wes Stahler",
    "wof:placetype":"venue"
},
  "geometry": {"coordinates":[-112.098378,33.553097],"type":"Point"}
}