{
  "type": "Feature",
  "properties": {
    "iso:country":"US",
    "sg:address":"18465 N Chila Vista Dr",
    "sg:city":"Surprise",
    "sg:classifiers":[
        {
            "category":"Professional",
            "type":"Services"
        }
    ],
    "sg:phone":"+1 623 214 3632",
    "sg:postcode":"85374",
    "sg:province":"AZ",
    "wof:name":"Mountain & Desert Specialties",
    "wof:placetype":"venue"
},
  "geometry": {"coordinates":[-112.438851,33.652454],"type":"Point"}
}