{
  "type": "Feature",
  "properties": {
    "addr:full":"120 E Sheldon St Prescott AZ 86301",
    "addr:housenumber":"120",
    "addr:postcode":"86301",
    "addr:street":"E Sheldon St",
    "iso:country":"US",
    "sg:address":"120 E Sheldon St",
    "sg:city":"Prescott",
    "sg:classifiers":[
        {
            "category":"Personal",
            "subcategory":"Beauty Salon",
            "type":"Services"
        }
    ],
    "sg:phone":"+1 928 443 9802",
    "sg:postcode":"86301",
    "sg:province":"AZ",
    "sg:tags":[
        "manicuring"
    ],
    "wof:name":"V & B Nails",
    "wof:placetype":"venue"
},
  "geometry": {"coordinates":[-112.467448,34.54549],"type":"Point"}
}