{
  "type": "Feature",
  "properties": {
    "iso:country":"US",
    "sg:address":"336 W Rancho Dr",
    "sg:city":"Phoenix",
    "sg:classifiers":[
        {
            "category":"Professional",
            "subcategory":"Management & Consulting",
            "type":"Services"
        }
    ],
    "sg:phone":"+1 602 266 0100",
    "sg:postcode":"85013",
    "sg:province":"AZ",
    "sg:tags":[
        "consultant",
        "political"
    ],
    "wof:name":"Fifty Plus One Inc",
    "wof:placetype":"venue"
},
  "geometry": {"coordinates":[-112.079864,33.522052],"type":"Point"}
}