{
  "type": "Feature",
  "properties": {
    "iso:country":"US",
    "sg:address":"2352 W Main St",
    "sg:city":"Mesa",
    "sg:classifiers":[
        {
            "category":"Autos & Motor Vehicles",
            "subcategory":"Automobile Sales",
            "type":"Retail Goods"
        },
        {
            "category":"Wholesale",
            "subcategory":"Scrap",
            "type":"Manufacturing & Wholesale Goods"
        }
    ],
    "sg:phone":"+1 888 332 9533",
    "sg:postcode":"85201",
    "sg:province":"AZ",
    "sg:tags":[
        "junk",
        "salvage"
    ],
    "wof:name":"Donate Car ? 24 Hour Pickup Response",
    "wof:placetype":"venue"
},
  "geometry": {"coordinates":[-111.882364,33.414902],"type":"Point"}
}