{
  "type": "Feature",
  "properties": {
    "addr:full":"1010 E McDowell Rd Phoenix AZ 85006",
    "addr:housenumber":"1010",
    "addr:postcode":"85006",
    "addr:street":"E Mcdowell Rd",
    "iso:country":"US",
    "sg:address":"1010 E McDowell Rd",
    "sg:city":"Phoenix",
    "sg:classifiers":[
        {
            "category":"Health Services",
            "subcategory":"Clinic",
            "type":"Services"
        }
    ],
    "sg:phone":"+1 602 252 0077",
    "sg:postcode":"85006",
    "sg:province":"AZ",
    "sg:tags":[
        "examination",
        "insurance"
    ],
    "wof:name":"Examination Management Svc",
    "wof:placetype":"venue"
},
  "geometry": {"coordinates":[-112.060114,33.465788],"type":"Point"}
}