{
  "type": "Feature",
  "properties": {
    "addr:full":"1902 E Baseline Rd Mesa AZ 85204",
    "addr:housenumber":"1902",
    "addr:postcode":"85204",
    "addr:street":"E Baseline Rd",
    "iso:country":"US",
    "sg:address":"1902 E Baseline Rd",
    "sg:city":"Mesa",
    "sg:classifiers":[
        {
            "category":"Restaurant",
            "type":"Food & Drink"
        }
    ],
    "sg:phone":"+1 480 926 7499",
    "sg:postcode":"85204",
    "sg:province":"AZ",
    "sg:tags":[
        "pizza"
    ],
    "wof:name":"Amazing Jake's Food & Fun",
    "wof:placetype":"venue"
},
  "geometry": {"coordinates":[-111.790531,33.379079],"type":"Point"}
}