{
  "type": "Feature",
  "properties": {
    "iso:country":"US",
    "sg:address":"6940 E Broadway Blvd",
    "sg:city":"Tucson",
    "sg:classifiers":[
        {
            "category":"Restaurant",
            "type":"Food & Drink"
        }
    ],
    "sg:phone":"+1 520 731 2138",
    "sg:postcode":"85710",
    "sg:province":"AZ",
    "sg:tags":[
        "eating"
    ],
    "wof:name":"Maxim Super Buffet",
    "wof:placetype":"venue"
},
  "geometry": {"coordinates":[-110.841841,32.22096],"type":"Point"}
}