{
  "type": "Feature",
  "properties": {
    "iso:country":"US",
    "sg:address":"6522 N 16th St",
    "sg:city":"Phoenix",
    "sg:classifiers":[
        {
            "category":"Personal",
            "subcategory":"Beauty Salon",
            "type":"Services"
        }
    ],
    "sg:phone":"+1 602 870 4838",
    "sg:postcode":"85016",
    "sg:province":"AZ",
    "wof:name":"Beauty Gallery & Assoc",
    "wof:placetype":"venue"
},
  "geometry": {"coordinates":[-112.04757,33.532672],"type":"Point"}
}