{
  "type": "Feature",
  "properties": {
    "iso:country":"US",
    "sg:address":"39541 N 107th Way",
    "sg:city":"Scottsdale",
    "sg:classifiers":[
        {
            "category":"Building & Trades",
            "subcategory":"Construction",
            "type":"Services"
        }
    ],
    "sg:phone":"+1 480 488 3711",
    "sg:postcode":"85262",
    "sg:province":"AZ",
    "sg:tags":[
        "house"
    ],
    "wof:name":"Ocotillo East Ltd Partner",
    "wof:placetype":"venue"
},
  "geometry": {"coordinates":[-111.847895,33.855346],"type":"Point"}
}