{
  "type": "Feature",
  "properties": {
    "iso:country":"US",
    "sg:address":"214 N 47th Ave",
    "sg:city":"Phoenix",
    "sg:classifiers":[
        {
            "category":"Building & Trades",
            "subcategory":"Equipment Rental",
            "type":"Services"
        }
    ],
    "sg:phone":"+1 602 484 0408",
    "sg:postcode":"85043",
    "sg:province":"AZ",
    "sg:tags":[
        "packaging",
        "materials-wholesale",
        "manufacturer",
        "moving",
        "supply"
    ],
    "wof:name":"New Haven Moving Equipment",
    "wof:placetype":"venue"
},
  "geometry": {"coordinates":[-112.16039499999999,33.450336],"type":"Point"}
}