{
  "type": "Feature",
  "properties": {
    "addr:full":"946 S Stapley Dr Mesa AZ 85204",
    "addr:housenumber":"946",
    "addr:postcode":"85204",
    "addr:street":"S Stapley Dr",
    "iso:country":"US",
    "sg:address":"946 S Stapley Dr",
    "sg:city":"Mesa",
    "sg:classifiers":[
        {
            "category":"Professional",
            "subcategory":"Business Services",
            "type":"Services"
        }
    ],
    "sg:phone":"+1 480 752 0007",
    "sg:postcode":"85204",
    "sg:province":"AZ",
    "sg:tags":[
        "appraiser"
    ],
    "wof:name":"Desertwide Real Estate Apprsrs",
    "wof:placetype":"venue"
},
  "geometry": {"coordinates":[-111.80549000000001,33.397622],"type":"Point"}
}