{
  "type": "Feature",
  "properties": {
    "iso:country":"US",
    "sg:address":"1243 S 7th St",
    "sg:city":"Phoenix",
    "sg:classifiers":[
        {
            "category":"Autos & Motor Vehicles",
            "subcategory":"Automobile Sales",
            "type":"Retail Goods"
        }
    ],
    "sg:phone":"+1 602 340 8824",
    "sg:postcode":"85034",
    "sg:province":"AZ",
    "sg:tags":[
        "used"
    ],
    "wof:name":"Sunset Bus",
    "wof:placetype":"venue"
},
  "geometry": {"coordinates":[-112.06505199999999,33.436573],"type":"Point"}
}