{
  "type": "Feature",
  "properties": {
    "addr:full":"2005 N 17th Ave Phoenix AZ 85007",
    "addr:housenumber":"2005",
    "addr:postcode":"85007",
    "addr:street":"N 17Th Ave",
    "iso:country":"US",
    "sg:address":"2005 N 17th Ave",
    "sg:city":"Phoenix",
    "sg:classifiers":[
        {
            "category":"Shopping",
            "subcategory":"Bicycles & Sporting Goods",
            "type":"Retail Goods"
        }
    ],
    "sg:phone":"+1 602 257 1199",
    "sg:postcode":"85007",
    "sg:province":"AZ",
    "sg:tags":[
        "equipment",
        "archery",
        "supply"
    ],
    "wof:name":"Talbo Archery",
    "wof:placetype":"venue"
},
  "geometry": {"coordinates":[-112.094881,33.473144],"type":"Point"}
}