{
  "type": "Feature",
  "properties": {
    "iso:country":"US",
    "sg:address":"16801 N 94th St Apt 2034",
    "sg:city":"Scottsdale",
    "sg:classifiers":[
        {
            "category":"Shopping Center",
            "type":"Public Place"
        }
    ],
    "sg:phone":"+1 480 502 6975",
    "sg:postcode":"85260",
    "sg:province":"AZ",
    "sg:tags":[
        "mall"
    ],
    "wof:name":"Dianna Mall",
    "wof:placetype":"venue"
},
  "geometry": {"coordinates":[-111.878433,33.638672],"type":"Point"}
}