{
  "type": "Feature",
  "properties": {
    "iso:country":"US",
    "sg:address":"1790 S White Mountain Rd",
    "sg:city":"Show Low",
    "sg:classifiers":[
        {
            "category":"Autos & Motor Vehicles",
            "subcategory":"Fuel & Gas Station",
            "type":"Retail Goods"
        }
    ],
    "sg:phone":"+1 928 537 3452",
    "sg:postcode":"85901",
    "sg:province":"AZ",
    "sg:tags":[
        "mart",
        "convenience",
        "station",
        "gasoline"
    ],
    "wof:name":"Shell",
    "wof:placetype":"venue"
},
  "geometry": {"coordinates":[-110.026702,34.233004],"type":"Point"}
}