{
  "type": "Feature",
  "properties": {
    "iso:country":"US",
    "sg:address":"5802 E Main St",
    "sg:city":"Mesa",
    "sg:classifiers":[
        {
            "category":"Professional",
            "type":"Services"
        }
    ],
    "sg:phone":"+1 480 832 7467",
    "sg:postcode":"85205",
    "sg:province":"AZ",
    "sg:tags":[
        "establishment"
    ],
    "wof:name":"East Valley Custom Inc",
    "wof:placetype":"venue"
},
  "geometry": {"coordinates":[-111.705222,33.415679],"type":"Point"}
}