{
  "type": "Feature",
  "properties": {
    "iso:country":"US",
    "sg:address":"4633 E Van Buren St",
    "sg:city":"Phoenix",
    "sg:classifiers":[
        {
            "category":"Building & Trades",
            "subcategory":"Plumbing",
            "type":"Services"
        }
    ],
    "sg:phone":"+1 602 244 2990",
    "sg:postcode":"85008",
    "sg:province":"AZ",
    "sg:tags":[
        "conditioning",
        "air",
        "system",
        "contractor"
    ],
    "wof:name":"Albers Air Conditioning Corp",
    "wof:placetype":"venue"
},
  "geometry": {"coordinates":[-111.98125,33.451063],"type":"Point"}
}