{
  "type": "Feature",
  "properties": {
    "iso:country":"US",
    "sg:address":"2151 E Broadway Rd",
    "sg:city":"Tempe",
    "sg:classifiers":[
        {
            "category":"Professional",
            "subcategory":"Lawyer & Legal Services",
            "type":"Services"
        }
    ],
    "sg:phone":"+1 480 921 1311",
    "sg:postcode":"85282",
    "sg:province":"AZ",
    "sg:tags":[
        "attorney"
    ],
    "wof:name":"Lynn M Harris PC",
    "wof:placetype":"venue"
},
  "geometry": {"coordinates":[-111.895121,33.407421],"type":"Point"}
}