{
  "type": "Feature",
  "properties": {
    "iso:country":"US",
    "sg:address":"14001 N 7th St",
    "sg:city":"Phoenix",
    "sg:classifiers":[
        {
            "category":"Banks & Credit Unions",
            "subcategory":"Bank",
            "type":"Services"
        }
    ],
    "sg:phone":"+1 602 889 0632",
    "sg:postcode":"85022",
    "sg:province":"AZ",
    "sg:tags":[
        "loan",
        "real estate"
    ],
    "wof:name":"Copperstate",
    "wof:placetype":"venue"
},
  "geometry": {"coordinates":[-112.065433,33.613611],"type":"Point"}
}