{
  "type": "Feature",
  "properties": {
    "iso:country":"US",
    "sg:address":"10 E Ellis Dr",
    "sg:city":"Tempe",
    "sg:classifiers":[
        {
            "category":"Shopping",
            "type":"Retail Goods"
        }
    ],
    "sg:phone":"+1 480 703 4475",
    "sg:postcode":"85282",
    "sg:province":"AZ",
    "sg:tags":[
        "merchandise"
    ],
    "wof:name":"Simply Floral By MSA",
    "wof:placetype":"venue"
},
  "geometry": {"coordinates":[-111.93528499999999,33.380546],"type":"Point"}
}