{
  "type": "Feature",
  "properties": {
    "addr:full":"4556 E Sycamore Ct Gilbert AZ 85298",
    "addr:housenumber":"4556",
    "addr:postcode":"85298",
    "addr:street":"E Sycamore Ct",
    "iso:country":"US",
    "sg:address":"4556 E Sycamore Ct",
    "sg:city":"Gilbert",
    "sg:classifiers":[
        {
            "category":"Banks & Credit Unions",
            "subcategory":"Financial Services",
            "type":"Services"
        }
    ],
    "sg:phone":"+1 480 279 0602",
    "sg:postcode":"85298",
    "sg:province":"AZ",
    "sg:tags":[
        "trust",
        "management"
    ],
    "wof:name":"Melot Roy E & Ramona V Trust",
    "wof:placetype":"venue"
},
  "geometry": {"coordinates":[-111.691874,33.260588],"type":"Point"}
}