{
  "type": "Feature",
  "properties": {
    "addr:full":"3302 W Thomas Rd Phoenix AZ 85017",
    "addr:housenumber":"3302",
    "addr:postcode":"85017",
    "addr:street":"W Thomas Rd",
    "iso:country":"US",
    "sg:address":"3302 W Thomas Rd",
    "sg:city":"Phoenix",
    "sg:classifiers":[
        {
            "category":"Personal",
            "subcategory":"Barber",
            "type":"Services"
        }
    ],
    "sg:phone":"+1 602 269 3503",
    "sg:postcode":"85017",
    "sg:province":"AZ",
    "wof:name":"Frank's Barber Shop",
    "wof:placetype":"venue"
},
  "geometry": {"coordinates":[-112.132615,33.480558],"type":"Point"}
}