{
  "type": "Feature",
  "properties": {
    "iso:country":"US",
    "sg:address":"1 W Campbell Ave",
    "sg:city":"Phoenix",
    "sg:classifiers":[
        {
            "category":"Manufacturing",
            "subcategory":"Tools & Machinery",
            "type":"Manufacturing & Wholesale Goods"
        }
    ],
    "sg:phone":"+1 602 999 7961",
    "sg:postcode":"85013",
    "sg:province":"AZ",
    "sg:tags":[
        "photographic",
        "mfg"
    ],
    "wof:name":"Maelstrom Films",
    "wof:placetype":"venue"
},
  "geometry": {"coordinates":[-112.074912,33.502046],"type":"Point"}
}