{
  "type": "Feature",
  "properties": {
    "addr:full":"898 W Tifffany Pl Chino Valley AZ 86323",
    "addr:housenumber":"898",
    "addr:postcode":"86323",
    "addr:street":"W Tifffany Pl",
    "iso:country":"US",
    "sg:address":"898 W Tifffany Pl",
    "sg:city":"Chino Valley",
    "sg:classifiers":[
        {
            "category":"Professional",
            "type":"Services"
        }
    ],
    "sg:phone":"+1 928 636 6408",
    "sg:postcode":"86323",
    "sg:province":"AZ",
    "wof:name":"To Z A Boiler",
    "wof:placetype":"venue"
},
  "geometry": {"coordinates":[-112.460534,34.77768],"type":"Point"}
}