{
  "type": "Feature",
  "properties": {
    "iso:country":"US",
    "sg:address":"6315 W Michigan St",
    "sg:city":"Tucson",
    "sg:classifiers":[
        {
            "category":"Retail",
            "subcategory":"Auto Repair",
            "type":"Services"
        }
    ],
    "sg:phone":"+1 520 908 2301",
    "sg:postcode":"85735",
    "sg:province":"AZ",
    "sg:tags":[
        "wrecker"
    ],
    "wof:name":"Mac's 24 Hr Towing & Storage",
    "wof:placetype":"venue"
},
  "geometry": {"coordinates":[-111.098477,32.17],"type":"Point"}
}