{
  "type": "Feature",
  "properties": {
    "iso:country":"US",
    "sg:address":"13041 N 35th Ave",
    "sg:city":"Phoenix",
    "sg:classifiers":[
        {
            "category":"Organizations",
            "subcategory":"Religious Organization",
            "type":"Services"
        }
    ],
    "sg:phone":"+1 602 548 0933",
    "sg:postcode":"85029",
    "sg:province":"AZ",
    "sg:tags":[
        "church"
    ],
    "wof:name":"Assembly Of God",
    "wof:placetype":"venue"
},
  "geometry": {"coordinates":[-112.133811,33.604395],"type":"Point"}
}