{
  "type": "Feature",
  "properties": {
    "iso:country":"US",
    "sg:address":"4330 W Glendale Ave",
    "sg:city":"Glendale",
    "sg:classifiers":[
        {
            "category":"Food & Beverages",
            "subcategory":"Liquor & Beverages",
            "type":"Retail Goods"
        }
    ],
    "sg:phone":"+1 623 435 9247",
    "sg:postcode":"85301",
    "sg:province":"AZ",
    "wof:name":"Farmer's Quality Liquor Stores",
    "wof:placetype":"venue"
},
  "geometry": {"coordinates":[-112.155303,33.538522],"type":"Point"}
}