{
  "type": "Feature",
  "properties": {
    "addr:full":"12046 N 32nd St Phoenix AZ 85028",
    "addr:housenumber":"12046",
    "addr:postcode":"85028",
    "addr:street":"N 32Nd St",
    "iso:country":"US",
    "sg:address":"12046 N 32nd St",
    "sg:city":"Phoenix",
    "sg:classifiers":[
        {
            "category":"Home & Garden",
            "subcategory":"Furniture",
            "type":"Retail Goods"
        }
    ],
    "sg:phone":"+1 602 971 6660",
    "sg:postcode":"85028",
    "sg:province":"AZ",
    "sg:tags":[
        "lawn",
        "furnishing"
    ],
    "wof:name":"Paddock Pool & Patio",
    "wof:placetype":"venue"
},
  "geometry": {"coordinates":[-112.01321799999999,33.594069],"type":"Point"}
}