{
  "type": "Feature",
  "properties": {
    "addr:full":"5209 N 16th Dr Phoenix AZ 85015",
    "addr:housenumber":"5209",
    "addr:postcode":"85015",
    "addr:street":"N 16Th Dr",
    "iso:country":"US",
    "sg:address":"5209 N 16th Dr",
    "sg:city":"Phoenix",
    "sg:classifiers":[
        {
            "category":"Real Estate",
            "subcategory":"Real Estate Agent",
            "type":"Services"
        }
    ],
    "sg:phone":"+1 602 944 5638",
    "sg:postcode":"85015",
    "sg:province":"AZ",
    "wof:name":"Colter Lofts",
    "wof:placetype":"venue"
},
  "geometry": {"coordinates":[-112.093166,33.513353],"type":"Point"}
}