{
  "type": "Feature",
  "properties": {
    "iso:country":"US",
    "sg:address":"709 S California Ave",
    "sg:city":"Parker",
    "sg:classifiers":[
        {
            "category":"Communications",
            "subcategory":"Radio Station",
            "type":"Services"
        }
    ],
    "sg:phone":"+1 928 669 9625",
    "sg:postcode":"85344",
    "sg:province":"AZ",
    "sg:tags":[
        "broadcast"
    ],
    "wof:name":"Terion Inc",
    "wof:placetype":"venue"
},
  "geometry": {"coordinates":[-114.290887,34.153239],"type":"Point"}
}