{
  "type": "Feature",
  "properties": {
    "iso:country":"US",
    "sg:address":"4449 N 12th St",
    "sg:city":"Phoenix",
    "sg:classifiers":[
        {
            "category":"Banks & Credit Unions",
            "subcategory":"Bank",
            "type":"Services"
        }
    ],
    "sg:phone":"+1 602 277 5807",
    "sg:postcode":"85014",
    "sg:province":"AZ",
    "sg:tags":[
        "cashing",
        "check"
    ],
    "wof:name":"Global Cash Market",
    "wof:placetype":"venue"
},
  "geometry": {"coordinates":[-112.05622,33.500973],"type":"Point"}
}