{
  "type": "Feature",
  "properties": {
    "iso:country":"US",
    "sg:address":"21432 S 140th St",
    "sg:city":"Chandler",
    "sg:classifiers":[
        {
            "category":"Retail",
            "subcategory":"Repair Shop",
            "type":"Services"
        }
    ],
    "sg:phone":"+1 480 821 8694",
    "sg:postcode":"85286",
    "sg:province":"AZ",
    "sg:tags":[
        "merchandise"
    ],
    "wof:name":"Scope Doctor",
    "wof:placetype":"venue"
},
  "geometry": {"coordinates":[-111.78144,33.252404],"type":"Point"}
}