{
  "type": "Feature",
  "properties": {
    "iso:country":"US",
    "sg:address":"7140 N 63rd Dr",
    "sg:city":"Glendale",
    "sg:phone":"+1 623 930 7342",
    "sg:postcode":"85301",
    "sg:province":"AZ",
    "wof:name":"Jim Consultants",
    "wof:placetype":"venue"
},
  "geometry": {"coordinates":[-112.196823,33.541329],"type":"Point"}
}