{
  "type": "Feature",
  "properties": {
    "addr:full":"7140 N 63rd Dr Glendale AZ 85301",
    "addr:housenumber":"7140",
    "addr:postcode":"85301",
    "addr:street":"N 63Rd Dr",
    "iso:country":"US",
    "sg:address":"7140 N 63rd Dr",
    "sg:city":"Glendale",
    "sg:phone":"+1 623 930 7342",
    "sg:postcode":"85301",
    "sg:province":"AZ",
    "wof:name":"Jim Consultants",
    "wof:placetype":"venue"
},
  "geometry": {"coordinates":[-112.19682299999999,33.541329],"type":"Point"}
}