{
  "type": "Feature",
  "properties": {
    "iso:country":"US",
    "sg:address":"801 S Mill Ave",
    "sg:city":"Tempe",
    "sg:classifiers":[
        {
            "category":"Restaurant",
            "type":"Food & Drink"
        }
    ],
    "sg:menulink":"http://www.allmenus.com/az/phoenix/109858-chilis/menu/",
    "sg:phone":"+1 480 731 9482",
    "sg:postcode":"85281",
    "sg:province":"AZ",
    "sg:tags":[
        "burger",
        "american",
        "sandwich",
        "tex-mex",
        "soup"
    ],
    "wof:name":"Chili's",
    "wof:placetype":"venue"
},
  "geometry": {"coordinates":[-111.939932,33.421934],"type":"Point"}
}