{
  "type": "Feature",
  "properties": {
    "addr:full":"1161 N el Dorado Pl Tucson AZ 85715",
    "addr:housenumber":"1161",
    "addr:postcode":"85715",
    "addr:street":"N El Dorado Pl",
    "iso:country":"US",
    "sg:address":"1161 N el Dorado Pl",
    "sg:city":"Tucson",
    "sg:classifiers":[
        {
            "category":"Insurance",
            "subcategory":"Insurance Agent",
            "type":"Services"
        }
    ],
    "sg:phone":"+1 520 721 4076",
    "sg:postcode":"85715",
    "sg:province":"AZ",
    "wof:name":"Independent Order of Foresters",
    "wof:placetype":"venue"
},
  "geometry": {"coordinates":[-110.855636,32.236502],"type":"Point"}
}