{
  "type": "Feature",
  "properties": {
    "addr:full":"901 N California Ave Coolidge AZ 85228",
    "addr:housenumber":"901",
    "addr:postcode":"85228",
    "addr:street":"N California Ave",
    "iso:country":"US",
    "sg:address":"901 N California Ave",
    "sg:city":"Coolidge",
    "sg:classifiers":[
        {
            "category":"Real Estate",
            "subcategory":"Real Estate Operator",
            "type":"Services"
        }
    ],
    "sg:phone":"+1 520 723 3300",
    "sg:postcode":"85228",
    "sg:province":"AZ",
    "sg:tags":[
        "building",
        "apartment"
    ],
    "wof:name":"Canyon Crek/Coronado APT Homes",
    "wof:placetype":"venue"
},
  "geometry": {"coordinates":[-111.514084,32.986773],"type":"Point"}
}