{
  "type": "Feature",
  "properties": {
    "iso:country":"US",
    "sg:address":"1948 E Minorka St",
    "sg:city":"Tucson",
    "sg:classifiers":[
        {
            "category":"Taxi",
            "type":"Transportation"
        }
    ],
    "sg:phone":"+1 520 349 4390",
    "sg:postcode":"85706",
    "sg:province":"AZ",
    "sg:tags":[
        "taxicab"
    ],
    "wof:name":"Gerald H Nadeau",
    "wof:placetype":"venue"
},
  "geometry": {"coordinates":[-110.941853,32.152077],"type":"Point"}
}