{
  "type": "Feature",
  "properties": {
    "iso:country":"US",
    "sg:address":"6823 N 13th Pl",
    "sg:city":"Phoenix",
    "sg:classifiers":[
        {
            "category":"Real Estate",
            "subcategory":"Architect",
            "type":"Services"
        }
    ],
    "sg:phone":"+1 602 212 0333",
    "sg:postcode":"85014",
    "sg:province":"AZ",
    "wof:name":"Conk Architecture",
    "wof:placetype":"venue"
},
  "geometry": {"coordinates":[-112.052385,33.536002],"type":"Point"}
}