{
  "type": "Feature",
  "properties": {
    "iso:country":"US",
    "sg:address":"24 W Ingram St",
    "sg:city":"Mesa",
    "sg:classifiers":[
        {
            "category":"Building & Trades",
            "subcategory":"Electrical",
            "type":"Services"
        }
    ],
    "sg:phone":"+1 602 291 3189",
    "sg:postcode":"85201",
    "sg:province":"AZ",
    "sg:tags":[
        "electric",
        "contractor"
    ],
    "wof:name":"Straight Edge Electric",
    "wof:placetype":"venue"
},
  "geometry": {"coordinates":[-111.831151,33.446491],"type":"Point"}
}