{
  "type": "Feature",
  "properties": {
    "iso:country":"US",
    "sg:address":"4018 E Cholla Canyon Dr",
    "sg:city":"Phoenix",
    "sg:classifiers":[
        {
            "category":"Manufacturing",
            "subcategory":"Signs",
            "type":"Manufacturing & Wholesale Goods"
        }
    ],
    "sg:phone":"+1 480 759 8109",
    "sg:postcode":"85044",
    "sg:province":"AZ",
    "sg:tags":[
        "advertising",
        "specialty"
    ],
    "wof:name":"C R Spirit Connection",
    "wof:placetype":"venue"
},
  "geometry": {"coordinates":[-111.998031,33.310528],"type":"Point"}
}