{
  "type": "Feature",
  "properties": {
    "iso:country":"US",
    "sg:address":"1011 Commerce Dr",
    "sg:city":"Prescott",
    "sg:classifiers":[
        {
            "category":"Retail",
            "subcategory":"Repair Shop",
            "type":"Services"
        }
    ],
    "sg:phone":"+1 928 445 4365",
    "sg:postcode":"86305",
    "sg:province":"AZ",
    "sg:tags":[
        "upholsterer"
    ],
    "wof:name":"Timkens Upholstery & Slip Cvrs",
    "wof:placetype":"venue"
},
  "geometry": {"coordinates":[-112.457158,34.604157],"type":"Point"}
}