{
  "type": "Feature",
  "properties": {
    "addr:full":"7014 E Camelback Rd Scottsdale AZ 85251",
    "addr:housenumber":"7014",
    "addr:postcode":"85251",
    "addr:street":"E Camelback Rd",
    "iso:country":"US",
    "sg:address":"7014 E Camelback Rd",
    "sg:city":"Scottsdale",
    "sg:classifiers":[
        {
            "category":"Restaurant",
            "type":"Food & Drink"
        }
    ],
    "sg:phone":"+1 480 994 4112",
    "sg:postcode":"85251",
    "sg:province":"AZ",
    "sg:website":"www.tacodelmar.com",
    "wof:name":"Taco Del Mar LA Fashion Sq",
    "wof:placetype":"venue"
},
  "geometry": {"coordinates":[-111.92887500000001,33.502163],"type":"Point"}
}