{
  "type": "Feature",
  "properties": {
    "iso:country":"US",
    "sg:address":"61 S Macdonald",
    "sg:city":"Mesa",
    "sg:classifiers":[
        {
            "category":"Manufacturing",
            "subcategory":"Printing",
            "type":"Manufacturing & Wholesale Goods"
        }
    ],
    "sg:phone":"+1 480 844 8044",
    "sg:postcode":"85210",
    "sg:province":"AZ",
    "sg:tags":[
        "equipment",
        "scanning",
        "commercial",
        "plotting",
        "supply"
    ],
    "wof:name":"Mesa Art & Printing",
    "wof:placetype":"venue"
},
  "geometry": {"coordinates":[-111.834068,33.413743],"type":"Point"}
}