{
  "type": "Feature",
  "properties": {
    "addr:full":"7755 E Evans Rd Scottsdale AZ 85260",
    "addr:housenumber":"7755",
    "addr:postcode":"85260",
    "addr:street":"E Evans Rd",
    "iso:country":"US",
    "sg:address":"7755 E Evans Rd",
    "sg:city":"Scottsdale",
    "sg:classifiers":[
        {
            "category":"Structure",
            "subcategory":"Office Building",
            "type":"Public Place"
        }
    ],
    "sg:phone":"+1 480 951 0911",
    "sg:postcode":"85260",
    "sg:province":"AZ",
    "sg:tags":[
        "park"
    ],
    "wof:name":"Fair Weather Properties",
    "wof:placetype":"venue"
},
  "geometry": {"coordinates":[-111.915494,33.616512],"type":"Point"}
}