{
  "type": "Feature",
  "properties": {
    "addr:full":"1919 Meadow St Lakeside AZ 85929",
    "addr:housenumber":"1919",
    "addr:postcode":"85929",
    "addr:street":"Meadow St",
    "iso:country":"US",
    "sg:address":"1919 Meadow St",
    "sg:city":"Lakeside",
    "sg:classifiers":[
        {
            "category":"Shopping",
            "subcategory":"Computers & Home Electronics",
            "type":"Retail Goods"
        }
    ],
    "sg:phone":"+1 928 367 5224",
    "sg:postcode":"85929",
    "sg:province":"AZ",
    "wof:name":"American Video International",
    "wof:placetype":"venue"
},
  "geometry": {"coordinates":[-109.97552399999999,34.146865],"type":"Point"}
}