{
  "type": "Feature",
  "properties": {
    "iso:country":"US",
    "sg:address":"2828 N Stone Ave",
    "sg:city":"Tucson",
    "sg:classifiers":[
        {
            "category":"Health Services",
            "subcategory":"Doctor",
            "type":"Services"
        }
    ],
    "sg:phone":"+1 520 622 4580",
    "sg:postcode":"85705",
    "sg:province":"AZ",
    "sg:tags":[
        "physician",
        "surgeon"
    ],
    "wof:name":"Cornerstone Health & Family",
    "wof:placetype":"venue"
},
  "geometry": {"coordinates":[-110.97192,32.258899],"type":"Point"}
}