{
  "type": "Feature",
  "properties": {
    "addr:full":"12912 Santa Fe Dr Surprise AZ 85374",
    "addr:housenumber":"12912",
    "addr:postcode":"85374",
    "addr:street":"Santa Fe Dr",
    "iso:country":"US",
    "sg:address":"12912 Santa Fe Dr",
    "sg:city":"Surprise",
    "sg:classifiers":[
        {
            "category":"Wholesale",
            "subcategory":"Machinery & Supplies",
            "type":"Manufacturing & Wholesale Goods"
        }
    ],
    "sg:phone":"+1 623 583 6307",
    "sg:postcode":"85374",
    "sg:province":"AZ",
    "sg:tags":[
        "equipment",
        "irrigation"
    ],
    "wof:name":"Grand Sprinkler Inc",
    "wof:placetype":"venue"
},
  "geometry": {"coordinates":[-112.340056,33.631676],"type":"Point"}
}