{
  "type": "Feature",
  "properties": {
    "addr:full":"621 S 48th St Ste 110 Tempe AZ 85281",
    "addr:housenumber":"621",
    "addr:postcode":"85281",
    "addr:street":"S 48Th St Ste 110",
    "iso:country":"US",
    "sg:address":"621 S 48th St Ste 110",
    "sg:city":"Tempe",
    "sg:classifiers":[
        {
            "category":"Professional",
            "subcategory":"Computer Services",
            "type":"Services"
        }
    ],
    "sg:phone":"+1 602 595 4740",
    "sg:postcode":"85281",
    "sg:province":"AZ",
    "sg:tags":[
        "design",
        "network",
        "system"
    ],
    "sg:website":"http://www.graphicsgraphics.com",
    "wof:name":"Graphics Website Design & Development",
    "wof:placetype":"venue"
},
  "geometry": {"coordinates":[-111.976311,33.42236],"type":"Point"}
}