{
  "type": "Feature",
  "properties": {
    "iso:country":"US",
    "sg:address":"7 S Naco Hwy",
    "sg:city":"Bisbee",
    "sg:classifiers":[
        {
            "category":"Shopping",
            "type":"Retail Goods"
        }
    ],
    "sg:phone":"+1 520 432 4424",
    "sg:postcode":"85603",
    "sg:province":"AZ",
    "sg:tags":[
        "art",
        "gallery",
        "dealer"
    ],
    "wof:name":"Bellassai Gallery At Lyric Plz",
    "wof:placetype":"venue"
},
  "geometry": {"coordinates":[-109.91902899999999,31.400467],"type":"Point"}
}