{
  "type": "Feature",
  "properties": {
    "addr:full":"1225 N 36th St #1117 Phoenix AZ 85008",
    "addr:housenumber":"1225",
    "addr:postcode":"85008",
    "addr:street":"N 36Th St # 1117",
    "iso:country":"US",
    "sg:address":"1225 N 36th St #1117",
    "sg:city":"Phoenix",
    "sg:classifiers":[
        {
            "category":"Communications",
            "subcategory":"Film & Video Production",
            "type":"Services"
        },
        {
            "category":"Professional",
            "subcategory":"Art Services",
            "type":"Services"
        }
    ],
    "sg:phone":"+1 602 795 8980",
    "sg:postcode":"85008",
    "sg:province":"AZ",
    "sg:tags":[
        "videography",
        "photography",
        "services-commercial",
        "creative",
        "tape",
        "editing",
        "audio-visual"
    ],
    "wof:name":"LegalVid",
    "wof:placetype":"venue"
},
  "geometry": {"coordinates":[-112.004181,33.461631],"type":"Point"}
}