{
  "type": "Feature",
  "properties": {
    "addr:full":"4138 N Longview Ave Phoenix AZ 85014",
    "addr:housenumber":"4138",
    "addr:postcode":"85014",
    "addr:street":"N Longview Ave",
    "iso:country":"US",
    "sg:address":"4138 N Longview Ave",
    "sg:city":"Phoenix",
    "sg:classifiers":[
        {
            "category":"Banks & Credit Unions",
            "subcategory":"Investment Brokerage",
            "type":"Services"
        }
    ],
    "sg:phone":"+1 602 277 5442",
    "sg:postcode":"85014",
    "sg:province":"AZ",
    "wof:name":"Crispin Investments LLC",
    "wof:placetype":"venue"
},
  "geometry": {"coordinates":[-112.054345,33.496008],"type":"Point"}
}