{
  "type": "Feature",
  "properties": {
    "iso:country":"US",
    "sg:address":"1060 N Campbell Ave",
    "sg:city":"Tucson",
    "sg:classifiers":[
        {
            "category":"Health Services",
            "subcategory":"Optometrist",
            "type":"Services"
        }
    ],
    "sg:phone":"+1 520 325 8700",
    "sg:postcode":"85719",
    "sg:province":"AZ",
    "wof:name":"Arizona Vision Specialists",
    "wof:placetype":"venue"
},
  "geometry": {"coordinates":[-110.943871,32.235946],"type":"Point"}
}