{
  "type": "Feature",
  "properties": {
    "iso:country":"US",
    "sg:address":"9249 W Union Hills Dr",
    "sg:city":"Peoria",
    "sg:classifiers":[
        {
            "category":"Restaurant",
            "type":"Food & Drink"
        }
    ],
    "sg:menulink":"http://www.allmenus.com/az/deer-valley/4909-streets-of-new-york/menu/",
    "sg:phone":"+1 623 875 6600",
    "sg:postcode":"85382",
    "sg:province":"AZ",
    "sg:tags":[
        "american",
        "pizza"
    ],
    "wof:name":"Streets of New York",
    "wof:placetype":"venue"
},
  "geometry": {"coordinates":[-112.25791099999999,33.652747],"type":"Point"}
}