{
  "type": "Feature",
  "properties": {
    "addr:full":"2187 McCulloch Blvd N Lake Havasu City AZ 86403",
    "addr:housenumber":"2187",
    "addr:postcode":"86403",
    "addr:street":"Mcculloch Blvd N",
    "iso:country":"US",
    "sg:address":"2187 McCulloch Blvd N",
    "sg:city":"Lake Havasu City",
    "sg:classifiers":[
        {
            "category":"Restaurant",
            "type":"Food & Drink"
        }
    ],
    "sg:phone":"+1 928 855 4405",
    "sg:postcode":"86403",
    "sg:province":"AZ",
    "wof:name":"Pepper Mill Cafe",
    "wof:placetype":"venue"
},
  "geometry": {"coordinates":[-114.32486299999999,34.474909],"type":"Point"}
}