{
  "type": "Feature",
  "properties": {
    "iso:country":"US",
    "sg:address":"1662 W Silverberry Pl",
    "sg:city":"Tucson",
    "sg:classifiers":[
        {
            "category":"Professional",
            "type":"Services"
        }
    ],
    "sg:phone":"+1 520 548 4345",
    "sg:postcode":"85737",
    "sg:province":"AZ",
    "wof:name":"Alan & Roxie Bancroft Inc",
    "wof:placetype":"venue"
},
  "geometry": {"coordinates":[-111.00229,32.416608],"type":"Point"}
}