{
  "type": "Feature",
  "properties": {
    "iso:country":"US",
    "sg:address":"232 W Grant Rd",
    "sg:city":"Tucson",
    "sg:classifiers":[
        {
            "category":"Wholesale",
            "subcategory":"Stationery",
            "type":"Manufacturing & Wholesale Goods"
        }
    ],
    "sg:phone":"+1 520 623 6066",
    "sg:postcode":"85705",
    "sg:province":"AZ",
    "sg:tags":[
        "product",
        "paper"
    ],
    "sg:website":"www.kellypaper.com",
    "wof:name":"Kelly Paper",
    "wof:placetype":"venue"
},
  "geometry": {"coordinates":[-110.974074,32.250299],"type":"Point"}
}