{
  "type": "Feature",
  "properties": {
    "addr:full":"8726 W Olive Ave Peoria AZ 85345",
    "addr:housenumber":"8726",
    "addr:postcode":"85345",
    "addr:street":"W Olive Ave",
    "iso:country":"US",
    "sg:address":"8726 W Olive Ave",
    "sg:city":"Peoria",
    "sg:classifiers":[
        {
            "category":"Place Of Worship",
            "subcategory":"Church",
            "type":"Public Place"
        },
        {
            "category":"Place Of Worship",
            "type":"Public Place"
        }
    ],
    "sg:phone":"+1 623 979 7511",
    "sg:postcode":"85345",
    "sg:province":"AZ",
    "sg:tags":[
        "lutheran",
        "america",
        "churches-lutheran",
        "churches-lutheran-evangelical"
    ],
    "wof:name":"Celebration Lutheran Church",
    "wof:placetype":"venue"
},
  "geometry": {"coordinates":[-112.24696400000001,33.566391],"type":"Point"}
}