{
  "type": "Feature",
  "properties": {
    "iso:country":"US",
    "sg:address":"2410 W Broadway Rd",
    "sg:city":"Phoenix",
    "sg:classifiers":[
        {
            "category":"Utilities",
            "subcategory":"Sewage",
            "type":"Services"
        }
    ],
    "sg:phone":"+1 602 268 4111",
    "sg:postcode":"85041",
    "sg:province":"AZ",
    "sg:tags":[
        "sewerage"
    ],
    "wof:name":"American Public Service Co",
    "wof:placetype":"venue"
},
  "geometry": {"coordinates":[-112.110155,33.406812],"type":"Point"}
}