{
  "type": "Feature",
  "properties": {
    "iso:country":"US",
    "sg:address":"141 N Date",
    "sg:city":"Mesa",
    "sg:classifiers":[
        {
            "category":"Building & Trades",
            "subcategory":"Plumbing",
            "type":"Services"
        }
    ],
    "sg:phone":"+1 480 964 4488",
    "sg:postcode":"85201",
    "sg:province":"AZ",
    "sg:tags":[
        "plumbing",
        "contractor"
    ],
    "wof:name":"George White Plumbing Co",
    "wof:placetype":"venue"
},
  "geometry": {"coordinates":[-111.844069,33.417933],"type":"Point"}
}