{
  "type": "Feature",
  "properties": {
    "iso:country":"US",
    "sg:address":"1990 W Camelback Rd",
    "sg:city":"Phoenix",
    "sg:classifiers":[
        {
            "category":"Insurance",
            "subcategory":"Insurance Agent",
            "type":"Services"
        }
    ],
    "sg:phone":"+1 602 246 8000",
    "sg:postcode":"85015",
    "sg:province":"AZ",
    "sg:tags":[
        "adjuster"
    ],
    "wof:name":"Accident Claim Adjusters LLC",
    "wof:placetype":"venue"
},
  "geometry": {"coordinates":[-112.100472,33.509697],"type":"Point"}
}