{
  "type": "Feature",
  "properties": {
    "iso:country":"US",
    "sg:address":"3730 E Morrow Dr",
    "sg:city":"Phoenix",
    "sg:classifiers":[
        {
            "category":"Wholesale",
            "subcategory":"Machinery & Supplies",
            "type":"Manufacturing & Wholesale Goods"
        }
    ],
    "sg:phone":"+1 602 460 4922",
    "sg:postcode":"85050",
    "sg:province":"AZ",
    "sg:tags":[
        "pallet",
        "distribution",
        "plastic"
    ],
    "wof:name":"Globe Trading Company LLC",
    "wof:placetype":"venue"
},
  "geometry": {"coordinates":[-112.000716,33.658541],"type":"Point"}
}