{
  "type": "Feature",
  "properties": {
    "iso:country":"US",
    "sg:address":"4014 W Van Buren St Ste 1",
    "sg:city":"Phoenix",
    "sg:classifiers":[
        {
            "category":"Manufacturing",
            "subcategory":"Motor Vehicles & Parts",
            "type":"Manufacturing & Wholesale Goods"
        },
        {
            "category":"Retail",
            "subcategory":"Auto Repair",
            "type":"Services"
        }
    ],
    "sg:phone":"+1 602 269 5043",
    "sg:postcode":"85009",
    "sg:province":"AZ",
    "sg:tags":[
        "engines-diesel",
        "injection",
        "engines-diesel-fuel"
    ],
    "wof:name":"Diesel Performance Center",
    "wof:placetype":"venue"
},
  "geometry": {"coordinates":[-112.146367,33.45137],"type":"Point"}
}