{
  "type": "Feature",
  "properties": {
    "iso:country":"US",
    "sg:address":"106 Fuller St",
    "sg:city":"Fort Huachuca",
    "sg:classifiers":[
        {
            "category":"Shopping",
            "subcategory":"Catalog Store",
            "type":"Retail Goods"
        }
    ],
    "sg:phone":"+1 520 439 0460",
    "sg:postcode":"85613",
    "sg:province":"AZ",
    "sg:tags":[
        "mail",
        "house"
    ],
    "wof:name":"Flat Earth Comix",
    "wof:placetype":"venue"
},
  "geometry": {"coordinates":[-110.336135,31.55569],"type":"Point"}
}