{
  "type": "Feature",
  "properties": {
    "iso:country":"US",
    "sg:address":"287 S Haskell Ave",
    "sg:city":"Willcox",
    "sg:classifiers":[
        {
            "category":"Autos & Motor Vehicles",
            "subcategory":"Auto Supplies",
            "type":"Retail Goods"
        }
    ],
    "sg:phone":"+1 520 384 2208",
    "sg:postcode":"85643",
    "sg:province":"AZ",
    "sg:tags":[
        "automobile",
        "parts"
    ],
    "wof:name":"Carquest Auto Parts",
    "wof:placetype":"venue"
},
  "geometry": {"coordinates":[-109.83350900000001,32.251067],"type":"Point"}
}