{
  "type": "Feature",
  "properties": {
    "iso:country":"US",
    "sg:address":"3219 N Hayden Rd",
    "sg:city":"Scottsdale",
    "sg:classifiers":[
        {
            "category":"Bars & Pubs",
            "type":"Food & Drink"
        }
    ],
    "sg:phone":"+1 480 941 8340",
    "sg:postcode":"85251",
    "sg:province":"AZ",
    "sg:tags":[
        "lounge",
        "cocktail"
    ],
    "wof:name":"Roadrunner Lounge",
    "wof:placetype":"venue"
},
  "geometry": {"coordinates":[-111.908826,33.487121],"type":"Point"}
}