{
  "type": "Feature",
  "properties": {
    "iso:country":"US",
    "sg:address":"1035 Cam Diestro",
    "sg:city":"Tucson",
    "sg:classifiers":[
        {
            "category":"Professional",
            "subcategory":"Management & Consulting",
            "type":"Services"
        }
    ],
    "sg:phone":"+1 520 575 9292",
    "sg:postcode":"85704",
    "sg:province":"AZ",
    "sg:tags":[
        "consultant",
        "business"
    ],
    "wof:name":"William H Gardner Inc",
    "wof:placetype":"venue"
},
  "geometry": {"coordinates":[-110.956402,32.391171],"type":"Point"}
}