{
  "type": "Feature",
  "properties": {
    "iso:country":"US",
    "sg:address":"2754 E Luann Pl",
    "sg:city":"Chandler",
    "sg:classifiers":[
        {
            "category":"Wholesale",
            "subcategory":"Durable Goods & Equipment",
            "type":"Manufacturing & Wholesale Goods"
        }
    ],
    "sg:phone":"+1 480 664 7497",
    "sg:postcode":"85225",
    "sg:province":"AZ",
    "sg:tags":[
        "importer"
    ],
    "wof:name":"K M Imports",
    "wof:placetype":"venue"
},
  "geometry": {"coordinates":[-111.793813,33.309852],"type":"Point"}
}