{
  "type": "Feature",
  "properties": {
    "addr:full":"10429 N 99th St Scottsdale AZ 85258",
    "addr:housenumber":"10429",
    "addr:postcode":"85258",
    "addr:street":"N 99Th St",
    "iso:country":"US",
    "sg:address":"10429 N 99th St",
    "sg:city":"Scottsdale",
    "sg:classifiers":[
        {
            "category":"Professional",
            "type":"Services"
        }
    ],
    "sg:phone":"+1 480 614 5529",
    "sg:postcode":"85258",
    "sg:province":"AZ",
    "wof:name":"Gallo Flp Inc",
    "wof:placetype":"venue"
},
  "geometry": {"coordinates":[-111.868897,33.580937],"type":"Point"}
}