{
  "type": "Feature",
  "properties": {
    "addr:full":"4955 E McKellips Rd Mesa AZ 85215",
    "addr:housenumber":"4955",
    "addr:postcode":"85215",
    "addr:street":"E Mckellips Rd",
    "iso:country":"US",
    "sg:address":"4955 E McKellips Rd",
    "sg:city":"Mesa",
    "sg:classifiers":[
        {
            "category":"Wholesale",
            "subcategory":"Groceries",
            "type":"Manufacturing & Wholesale Goods"
        }
    ],
    "sg:phone":"+1 480 962 5017",
    "sg:postcode":"85215",
    "sg:province":"AZ",
    "sg:tags":[
        "nut",
        "fruit",
        "dried",
        "candy"
    ],
    "sg:website":"www.lehivalley.com",
    "wof:name":"Lehi Valley Wholesale",
    "wof:placetype":"venue"
},
  "geometry": {"coordinates":[-111.726161,33.451769],"type":"Point"}
}