{
  "type": "Feature",
  "properties": {
    "iso:country":"US",
    "sg:address":"3031 N 31st Ave",
    "sg:city":"Phoenix",
    "sg:classifiers":[
        {
            "category":"Wholesale",
            "subcategory":"Apparel",
            "type":"Manufacturing & Wholesale Goods"
        },
        {
            "category":"Wholesale",
            "subcategory":"Durable Goods & Equipment",
            "type":"Manufacturing & Wholesale Goods"
        }
    ],
    "sg:phone":"+1 602 233 9363",
    "sg:postcode":"85017",
    "sg:province":"AZ",
    "sg:tags":[
        "rep",
        "infant",
        "wear"
    ],
    "wof:name":"Impressionable Designs L L C",
    "wof:placetype":"venue"
},
  "geometry": {"coordinates":[-112.12559899999999,33.486363],"type":"Point"}
}