{
  "type": "Feature",
  "properties": {
    "addr:full":"1242 N Central Ave Phoenix AZ 85004",
    "addr:housenumber":"1242",
    "addr:postcode":"85004",
    "addr:street":"N Central Ave",
    "iso:country":"US",
    "sg:address":"1242 N Central Ave",
    "sg:city":"Phoenix",
    "sg:classifiers":[
        {
            "category":"Organizations",
            "subcategory":"Non-profit Organization",
            "type":"Services"
        }
    ],
    "sg:phone":"+1 602 257 0335",
    "sg:postcode":"85004",
    "sg:province":"AZ",
    "sg:website":"www.azbookfestival.org",
    "wof:name":"Arizona Humanities Council",
    "wof:placetype":"venue"
},
  "geometry": {"coordinates":[-112.073909,33.460927],"type":"Point"}
}