{
  "type": "Feature",
  "properties": {
    "iso:country":"US",
    "sg:address":"718 E Mountain Sage Dr",
    "sg:city":"Phoenix",
    "sg:classifiers":[
        {
            "category":"Manufacturing",
            "subcategory":"Tools & Machinery",
            "type":"Manufacturing & Wholesale Goods"
        }
    ],
    "sg:phone":"+1 480 460 0664",
    "sg:postcode":"85048",
    "sg:province":"AZ",
    "sg:tags":[
        "mfg",
        "table",
        "set",
        "chiropractic"
    ],
    "wof:name":"Custom Chiropractic Eqp Corp",
    "wof:placetype":"venue"
},
  "geometry": {"coordinates":[-112.066126,33.316738],"type":"Point"}
}