{
  "type": "Feature",
  "properties": {
    "addr:full":"8133 W Mulberry Dr Phoenix AZ 85033",
    "addr:housenumber":"8133",
    "addr:postcode":"85033",
    "addr:street":"W Mulberry Dr",
    "iso:country":"US",
    "sg:address":"8133 W Mulberry Dr",
    "sg:city":"Phoenix",
    "sg:classifiers":[
        {
            "category":"Manufacturing",
            "subcategory":"Glass & Minerals",
            "type":"Manufacturing & Wholesale Goods"
        },
        {
            "category":"Retail",
            "subcategory":"Auto Repair",
            "type":"Services"
        }
    ],
    "sg:phone":"+1 623 606 8969",
    "sg:postcode":"85033",
    "sg:province":"AZ",
    "sg:tags":[
        "plate",
        "window",
        "windshield",
        "glass-auto"
    ],
    "sg:website":"http://ezlocal.com/AZ/Phoenix/Auto-Repair-Shop/5289",
    "wof:name":"Pristine Autoglass",
    "wof:placetype":"venue"
},
  "geometry": {"coordinates":[-112.234105,33.48595],"type":"Point"}
}