{
  "type": "Feature",
  "properties": {
    "iso:country":"US",
    "sg:address":"1920 S Stapley Dr",
    "sg:city":"Mesa",
    "sg:classifiers":[
        {
            "category":"Manufacturing",
            "subcategory":"Printing",
            "type":"Manufacturing & Wholesale Goods"
        }
    ],
    "sg:phone":"+1 480 813 4331",
    "sg:postcode":"85204",
    "sg:province":"AZ",
    "sg:tags":[
        "printer"
    ],
    "wof:name":"Fed Ex Kinko's Ofc & Print Ctr",
    "wof:placetype":"venue"
},
  "geometry": {"coordinates":[-111.807338,33.379014],"type":"Point"}
}