{
  "type": "Feature",
  "properties": {
    "iso:country":"US",
    "sg:address":"1002 N Colcord Rd",
    "sg:city":"Payson",
    "sg:classifiers":[
        {
            "category":"Real Estate",
            "subcategory":"Real Estate Agent",
            "type":"Services"
        }
    ],
    "sg:phone":"+1 928 472 7789",
    "sg:postcode":"85541",
    "sg:province":"AZ",
    "sg:tags":[
        "appraiser"
    ],
    "wof:name":"Meehan Real Estate Appraisals",
    "wof:placetype":"venue"
},
  "geometry": {"coordinates":[-111.325449,34.25396],"type":"Point"}
}