{
  "type": "Feature",
  "properties": {
    "iso:country":"US",
    "sg:address":"4433 N 16th St",
    "sg:city":"Phoenix",
    "sg:classifiers":[
        {
            "category":"Autos & Motor Vehicles",
            "subcategory":"Automobile Sales",
            "type":"Retail Goods"
        }
    ],
    "sg:phone":"+1 602 280 1276",
    "sg:postcode":"85016",
    "sg:province":"AZ",
    "wof:name":"Pepe Motorsports",
    "wof:placetype":"venue"
},
  "geometry": {"coordinates":[-112.04749,33.50185],"type":"Point"}
}