{
  "type": "Feature",
  "properties": {
    "iso:country":"US",
    "sg:address":"114 W Adams St",
    "sg:city":"Phoenix",
    "sg:classifiers":[
        {
            "category":"Parking",
            "type":"Transportation"
        },
        {
            "category":"Parking",
            "subcategory":"Garage",
            "type":"Transportation"
        }
    ],
    "sg:phone":"+1 602 256 9664",
    "sg:postcode":"85003",
    "sg:province":"AZ",
    "sg:tags":[
        "attendant",
        "lot"
    ],
    "wof:name":"Central Parking System",
    "wof:placetype":"venue"
},
  "geometry": {"coordinates":[-112.075339,33.449299],"type":"Point"}
}