{
  "type": "Feature",
  "properties": {
    "iso:country":"US",
    "sg:address":"350 W Thomas Rd Ste 3",
    "sg:city":"Phoenix",
    "sg:classifiers":[
        {
            "category":"Health Services",
            "subcategory":"Hospital",
            "type":"Services"
        },
        {
            "category":"Social Services",
            "subcategory":"Job Training",
            "type":"Services"
        },
        {
            "category":"Health Services",
            "subcategory":"Clinic",
            "type":"Services"
        }
    ],
    "sg:phone":"+1 602 406 6800",
    "sg:postcode":"85013",
    "sg:province":"AZ",
    "sg:tags":[
        "medical",
        "nursing",
        "homes-skilled",
        "facility"
    ],
    "sg:website":"http://www.selectmedicalcorp.com",
    "wof:name":"Select Specialty Hospital",
    "wof:placetype":"venue"
},
  "geometry": {"coordinates":[-112.07933,33.480311],"type":"Point"}
}