{
  "type": "Feature",
  "properties": {
    "addr:full":"6925 E 5th Ave Scottsdale AZ 85251",
    "addr:housenumber":"6925",
    "addr:postcode":"85251",
    "addr:street":"E 5Th Ave",
    "iso:country":"US",
    "sg:address":"6925 E 5th Ave",
    "sg:city":"Scottsdale",
    "sg:classifiers":[
        {
            "category":"Professional",
            "subcategory":"Lawyer & Legal Services",
            "type":"Services"
        }
    ],
    "sg:phone":"+1 480 945 6789",
    "sg:postcode":"85251",
    "sg:province":"AZ",
    "sg:tags":[
        "attorney"
    ],
    "wof:name":"Richard Simonson",
    "wof:placetype":"venue"
},
  "geometry": {"coordinates":[-111.933393,33.494835],"type":"Point"}
}