{
  "type": "Feature",
  "properties": {
    "iso:country":"US",
    "sg:address":"4554 E Paradise Village Pkwy N",
    "sg:city":"Phoenix",
    "sg:classifiers":[
        {
            "category":"Professional",
            "type":"Services"
        }
    ],
    "sg:phone":"+1 480 502 3939",
    "sg:postcode":"85032",
    "sg:province":"AZ",
    "sg:tags":[
        "establishment"
    ],
    "wof:name":"Astro's House",
    "wof:placetype":"venue"
},
  "geometry": {"coordinates":[-111.983272,33.605084],"type":"Point"}
}