{
  "type": "Feature",
  "properties": {
    "iso:country":"US",
    "sg:address":"8367 E Pecos Dr",
    "sg:city":"Prescott Valley",
    "sg:classifiers":[
        {
            "category":"Autos & Motor Vehicles",
            "subcategory":"Auto Supplies",
            "type":"Retail Goods"
        }
    ],
    "sg:phone":"+1 928 772 8770",
    "sg:postcode":"86314",
    "sg:province":"AZ",
    "sg:tags":[
        "equipment",
        "racing",
        "car",
        "automobile"
    ],
    "wof:name":"Reapers Racing",
    "wof:placetype":"venue"
},
  "geometry": {"coordinates":[-112.319291,34.62688],"type":"Point"}
}