{
  "type": "Feature",
  "properties": {
    "iso:country":"US",
    "sg:address":"707 E Mingus Ave Suite 503",
    "sg:city":"Cottonwood",
    "sg:classifiers":[
        {
            "category":"Professional",
            "subcategory":"Lawyer & Legal Services",
            "type":"Services"
        }
    ],
    "sg:phone":"+1 928 634 2620",
    "sg:postcode":"86326",
    "sg:province":"AZ",
    "sg:tags":[
        "attorney",
        "criminal",
        "estate",
        "family",
        "accident",
        "personal",
        "wills",
        "practice",
        "damage",
        "planning",
        "trust",
        "injury",
        "property",
        "law",
        "bankruptcy"
    ],
    "wof:name":"Morse, David P. Attorney",
    "wof:placetype":"venue"
},
  "geometry": {"coordinates":[-112.02068300000001,34.73954],"type":"Point"}
}