{
  "type": "Feature",
  "properties": {
    "iso:country":"US",
    "sg:address":"1854 Viola Pl",
    "sg:city":"Sierra Vista",
    "sg:classifiers":[
        {
            "category":"Building & Trades",
            "subcategory":"Construction",
            "type":"Services"
        }
    ],
    "sg:phone":"+1 520 452 1400",
    "sg:postcode":"85635",
    "sg:province":"AZ",
    "sg:tags":[
        "light",
        "custom",
        "kitchen",
        "remolding",
        "bath"
    ],
    "wof:name":"Premier Kitchen & Bath",
    "wof:placetype":"venue"
},
  "geometry": {"coordinates":[-110.278964,31.559814],"type":"Point"}
}