{
  "type": "Feature",
  "properties": {
    "addr:full":"7975 N Hayden Rd Scottsdale AZ 85250",
    "addr:housenumber":"7975",
    "addr:postcode":"85250",
    "addr:street":"N Hayden Rd",
    "iso:country":"US",
    "sg:address":"7975 N Hayden Rd",
    "sg:city":"Scottsdale",
    "sg:classifiers":[
        {
            "category":"Utilities",
            "subcategory":"Mobile Phone",
            "type":"Services"
        }
    ],
    "sg:phone":"+1 480 783 5590",
    "sg:postcode":"85250",
    "sg:province":"AZ",
    "sg:tags":[
        "dispatching",
        "air",
        "provides",
        "for",
        "time"
    ],
    "wof:name":"Verizon",
    "wof:placetype":"venue"
},
  "geometry": {"coordinates":[-111.898848,33.552638],"type":"Point"}
}