{
  "type": "Feature",
  "properties": {
    "iso:country":"US",
    "sg:address":"311 W Goodwin St",
    "sg:city":"Prescott",
    "sg:classifiers":[
        {
            "category":"Health Services",
            "subcategory":"Clinic",
            "type":"Services"
        }
    ],
    "sg:phone":"+1 928 771 8590",
    "sg:postcode":"86303",
    "sg:province":"AZ",
    "sg:tags":[
        "wellness",
        "program"
    ],
    "wof:name":"Network Wellness Ctr-Prescott",
    "wof:placetype":"venue"
},
  "geometry": {"coordinates":[-112.472251,34.539921],"type":"Point"}
}