{
  "type": "Feature",
  "properties": {
    "iso:country":"US",
    "sg:address":"6132 E 22nd St",
    "sg:city":"Tucson",
    "sg:classifiers":[
        {
            "category":"Insurance",
            "subcategory":"Insurance Agent",
            "type":"Services"
        }
    ],
    "sg:phone":"+1 520 232 9610",
    "sg:postcode":"85711",
    "sg:province":"AZ",
    "wof:name":"Beverly A Villa",
    "wof:placetype":"venue"
},
  "geometry": {"coordinates":[-110.861074,32.206904],"type":"Point"}
}