{
  "type": "Feature",
  "properties": {
    "iso:country":"US",
    "sg:address":"931 S Gilbert Rd",
    "sg:city":"Mesa",
    "sg:classifiers":[
        {
            "category":"Health Services",
            "subcategory":"Health Practitioner",
            "type":"Services"
        }
    ],
    "sg:phone":"+1 480 892 0479",
    "sg:postcode":"85204",
    "sg:province":"AZ",
    "sg:tags":[
        "therapist",
        "physical"
    ],
    "wof:name":"Next Level Physical Therapy",
    "wof:placetype":"venue"
},
  "geometry": {"coordinates":[-111.788225,33.394089],"type":"Point"}
}