{
  "type": "Feature",
  "properties": {
    "iso:country":"US",
    "sg:address":"10426 N Cave Creek Rd",
    "sg:city":"Phoenix",
    "sg:classifiers":[
        {
            "category":"Professional",
            "subcategory":"Accounting & Tax Preparation",
            "type":"Services"
        }
    ],
    "sg:phone":"+1 602 997 2559",
    "sg:postcode":"85020",
    "sg:province":"AZ",
    "sg:tags":[
        "accountant"
    ],
    "wof:name":"Cecilia G Francis CPA",
    "wof:placetype":"venue"
},
  "geometry": {"coordinates":[-112.051872,33.582193],"type":"Point"}
}