{
  "type": "Feature",
  "properties": {
    "iso:country":"US",
    "sg:address":"717 N Stapley Dr",
    "sg:city":"Mesa",
    "sg:classifiers":[
        {
            "category":"Organizations",
            "subcategory":"Religious Organization",
            "type":"Services"
        }
    ],
    "sg:phone":"+1 480 833 7500",
    "sg:postcode":"85203",
    "sg:province":"AZ",
    "sg:tags":[
        "church"
    ],
    "sg:website":"www.churchredeemeraz.org",
    "wof:name":"Church Of The Redeemer",
    "wof:placetype":"venue"
},
  "geometry": {"coordinates":[-111.805204,33.428578],"type":"Point"}
}