{
  "type": "Feature",
  "properties": {
    "iso:country":"US",
    "sg:address":"1202 E Maryland Ave",
    "sg:city":"Phoenix",
    "sg:classifiers":[
        {
            "category":"Building & Trades",
            "subcategory":"Pest Control",
            "type":"Services"
        }
    ],
    "sg:phone":"+1 602 265 2199",
    "sg:postcode":"85014",
    "sg:province":"AZ",
    "sg:tags":[
        "industrial",
        "services-commercial",
        "bee",
        "removal"
    ],
    "sg:website":"http://www.azbeeremoval.com",
    "wof:name":"The Beekeeper Total Bee Control Inc",
    "wof:placetype":"venue"
},
  "geometry": {"coordinates":[-112.056177,33.530989],"type":"Point"}
}