{
  "type": "Feature",
  "properties": {
    "addr:full":"3538 E Indian School Rd Phoenix AZ 85018",
    "addr:housenumber":"3538",
    "addr:postcode":"85018",
    "addr:street":"E Indian School Rd",
    "iso:country":"US",
    "sg:address":"3538 E Indian School Rd",
    "sg:city":"Phoenix",
    "sg:classifiers":[
        {
            "category":"Restaurant",
            "type":"Food & Drink"
        }
    ],
    "sg:phone":"+1 602 553 9200",
    "sg:postcode":"85018",
    "sg:province":"AZ",
    "sg:tags":[
        "eating"
    ],
    "wof:name":"Paul's Little Philly",
    "wof:placetype":"venue"
},
  "geometry": {"coordinates":[-112.00523800000001,33.495261],"type":"Point"}
}