{
  "type": "Feature",
  "properties": {
    "iso:country":"US",
    "sg:address":"3402 W Osborn Rd",
    "sg:city":"Phoenix",
    "sg:classifiers":[
        {
            "category":"Shopping",
            "subcategory":"Computers & Home Electronics",
            "type":"Retail Goods"
        },
        {
            "category":"Wholesale",
            "subcategory":"Computers",
            "type":"Manufacturing & Wholesale Goods"
        }
    ],
    "sg:phone":"+1 602 371 8555",
    "sg:postcode":"85017",
    "sg:province":"AZ",
    "sg:tags":[
        "equipment",
        "printer",
        "supply"
    ],
    "sg:website":"http://www.zytrex.net",
    "wof:name":"Zytrex",
    "wof:placetype":"venue"
},
  "geometry": {"coordinates":[-112.132455,33.487656],"type":"Point"}
}