{
  "type": "Feature",
  "properties": {
    "addr:full":"1379 E Stoney Canyon Cir Tucson AZ 85737",
    "addr:housenumber":"1379",
    "addr:postcode":"85737",
    "addr:street":"E Stoney Canyon Cir",
    "iso:country":"US",
    "sg:address":"1379 E Stoney Canyon Cir",
    "sg:city":"Tucson",
    "sg:classifiers":[
        {
            "category":"Professional",
            "type":"Services"
        }
    ],
    "sg:phone":"+1 520 544 9485",
    "sg:postcode":"85737",
    "sg:province":"AZ",
    "wof:name":"Arizona Assc of FMLy&cnsmr SCI",
    "wof:placetype":"venue"
},
  "geometry": {"coordinates":[-110.952392,32.396129],"type":"Point"}
}