{
  "type": "Feature",
  "properties": {
    "addr:full":"1048 N 44th St Ste 200 Phoenix AZ 85008",
    "addr:housenumber":"1048",
    "addr:postcode":"85008",
    "addr:street":"N 44Th St Ste 200",
    "iso:country":"US",
    "sg:address":"1048 N 44th St Ste 200",
    "sg:city":"Phoenix",
    "sg:classifiers":[
        {
            "category":"Professional",
            "subcategory":"Art Services",
            "type":"Services"
        },
        {
            "category":"Professional",
            "subcategory":"Business Services",
            "type":"Services"
        },
        {
            "category":"Real Estate",
            "subcategory":"Architect",
            "type":"Services"
        }
    ],
    "sg:phone":"+1 602 952 8585",
    "sg:postcode":"85008",
    "sg:province":"AZ",
    "sg:tags":[
        "architects'",
        "development",
        "product",
        "designer",
        "designers-industrial",
        "marketing",
        "specification",
        "commercial",
        "builders'",
        "construction",
        "design",
        "architectural",
        "interior",
        "decorator"
    ],
    "wof:name":"Pinnacle Design, Inc.",
    "wof:placetype":"venue"
},
  "geometry": {"coordinates":[-111.987213,33.460213],"type":"Point"}
}