{
  "type": "Feature",
  "properties": {
    "iso:country":"US",
    "sg:address":"4655 W Mcdowell Rd Ste 110",
    "sg:city":"Phoenix",
    "sg:classifiers":[
        {
            "category":"Wholesale",
            "subcategory":"Groceries",
            "type":"Manufacturing & Wholesale Goods"
        }
    ],
    "sg:phone":"+1 602 246 8595",
    "sg:postcode":"85035",
    "sg:province":"AZ",
    "sg:tags":[
        "food",
        "products-wholesale"
    ],
    "wof:name":"Food Sales West Inc",
    "wof:placetype":"venue"
},
  "geometry": {"coordinates":[-112.15920800000001,33.465972],"type":"Point"}
}