{
  "type": "Feature",
  "properties": {
    "addr:full":"1042 Willow Creek Rd Prescott AZ 86301",
    "addr:housenumber":"1042",
    "addr:postcode":"86301",
    "addr:street":"Willow Creek Rd",
    "iso:country":"US",
    "sg:address":"1042 Willow Creek Rd",
    "sg:city":"Prescott",
    "sg:classifiers":[
        {
            "category":"Restaurant",
            "type":"Food & Drink"
        }
    ],
    "sg:phone":"+1 928 778 5276",
    "sg:postcode":"86301",
    "sg:province":"AZ",
    "sg:tags":[
        "eating"
    ],
    "wof:name":"Beijing Chinese Restaurant",
    "wof:placetype":"venue"
},
  "geometry": {"coordinates":[-112.482303,34.562548],"type":"Point"}
}