{
  "type": "Feature",
  "properties": {
    "addr:full":"185 E Oak St Globe AZ 85501",
    "addr:housenumber":"185",
    "addr:postcode":"85501",
    "addr:street":"E Oak St",
    "iso:country":"US",
    "sg:address":"185 E Oak St",
    "sg:city":"Globe",
    "sg:classifiers":[
        {
            "category":"Place Of Worship",
            "subcategory":"Church",
            "type":"Public Place"
        },
        {
            "category":"Place Of Worship",
            "type":"Public Place"
        },
        {
            "category":"Organizations",
            "subcategory":"Religious Organization",
            "type":"Services"
        }
    ],
    "sg:phone":"+1 928 425 5160",
    "sg:postcode":"85501",
    "sg:province":"AZ",
    "sg:tags":[
        "churches-episcopal-anglican",
        "churches-episcopal"
    ],
    "sg:website":"http://www.azdiocese.org",
    "wof:name":"St Johns Episcopal",
    "wof:placetype":"venue"
},
  "geometry": {"coordinates":[-110.786119,33.396333],"type":"Point"}
}