{
  "type": "Feature",
  "properties": {
    "iso:country":"US",
    "sg:address":"610 W Main St",
    "sg:city":"Safford",
    "sg:classifiers":[
        {
            "category":"Insurance",
            "subcategory":"Insurance Agent",
            "type":"Services"
        },
        {
            "category":"Insurance",
            "subcategory":"Hazard Insurance",
            "type":"Services"
        },
        {
            "category":"Insurance",
            "subcategory":"Title Insurance",
            "type":"Services"
        },
        {
            "category":"Insurance",
            "subcategory":"Life Insurance",
            "type":"Services"
        }
    ],
    "sg:phone":"+1 928 428 1570",
    "sg:postcode":"85546",
    "sg:province":"AZ",
    "sg:tags":[
        "auto",
        "commercial",
        "business",
        "homeowner"
    ],
    "sg:website":"http://www.farmersagent.com/mwilson2/",
    "wof:name":"Michelle Wilson - Farmers Insurance",
    "wof:placetype":"venue"
},
  "geometry": {"coordinates":[-109.713858,32.833292],"type":"Point"}
}