{
  "type": "Feature",
  "properties": {
    "addr:full":"4801 E Indian School Rd Phoenix AZ 85018",
    "addr:housenumber":"4801",
    "addr:postcode":"85018",
    "addr:street":"E Indian School Rd",
    "iso:country":"US",
    "sg:address":"4801 E Indian School Rd",
    "sg:city":"Phoenix",
    "sg:classifiers":[
        {
            "category":"Personal",
            "subcategory":"Beauty Salon",
            "type":"Services"
        }
    ],
    "sg:phone":"+1 602 954 4018",
    "sg:postcode":"85018",
    "sg:province":"AZ",
    "sg:tags":[
        "treatment",
        "skin"
    ],
    "wof:name":"Brandon Alexander Salon & Spa",
    "wof:placetype":"venue"
},
  "geometry": {"coordinates":[-111.97640699999999,33.494602],"type":"Point"}
}