{
  "type": "Feature",
  "properties": {
    "iso:country":"US",
    "sg:address":"3121 N Swan Rd",
    "sg:city":"Tucson",
    "sg:classifiers":[
        {
            "category":"Real Estate",
            "subcategory":"Real Estate Agent",
            "type":"Services"
        }
    ],
    "sg:phone":"+1 520 529 2592",
    "sg:postcode":"85712",
    "sg:province":"AZ",
    "wof:name":"Hacienda Properties",
    "wof:placetype":"venue"
},
  "geometry": {"coordinates":[-110.892551,32.270017],"type":"Point"}
}