{
  "type": "Feature",
  "properties": {
    "addr:full":"13915 E Ray Rd Gilbert AZ 85296",
    "addr:housenumber":"13915",
    "addr:postcode":"85296",
    "addr:street":"E Ray Rd",
    "iso:country":"US",
    "sg:address":"13915 E Ray Rd",
    "sg:city":"Gilbert",
    "sg:classifiers":[
        {
            "category":"Building & Trades",
            "subcategory":"Landscaping Services",
            "type":"Services"
        }
    ],
    "sg:phone":"+1 480 821 5718",
    "sg:postcode":"85296",
    "sg:province":"AZ",
    "wof:name":"Silver Star Landscaping Inc",
    "wof:placetype":"venue"
},
  "geometry": {"coordinates":[-111.78378499999999,33.321003],"type":"Point"}
}