{
  "type": "Feature",
  "properties": {
    "iso:country":"US",
    "sg:address":"11740 W Grier Rd",
    "sg:city":"Marana",
    "sg:classifiers":[
        {
            "category":"Social Services",
            "subcategory":"Child Care",
            "type":"Services"
        }
    ],
    "sg:phone":"+1 520 682 3170",
    "sg:postcode":"85653",
    "sg:province":"AZ",
    "sg:tags":[
        "kindergarten",
        "academic",
        "school"
    ],
    "wof:name":"Community Christian Preschool",
    "wof:placetype":"venue"
},
  "geometry": {"coordinates":[-111.21514999999999,32.453391],"type":"Point"}
}