{
  "type": "Feature",
  "properties": {
    "iso:country":"US",
    "sg:address":"1902 S Craycroft Rd",
    "sg:city":"Tucson",
    "sg:classifiers":[
        {
            "category":"Organizations",
            "subcategory":"Religious Organization",
            "type":"Services"
        }
    ],
    "sg:phone":"+1 520 439 4143",
    "sg:postcode":"85711",
    "sg:province":"AZ",
    "sg:tags":[
        "church"
    ],
    "wof:name":"Word Of Mouf",
    "wof:placetype":"venue"
},
  "geometry": {"coordinates":[-110.875174,32.19882],"type":"Point"}
}