{
  "type": "Feature",
  "properties": {
    "iso:country":"US",
    "sg:address":"1100 F Ave",
    "sg:city":"Douglas",
    "sg:classifiers":[
        {
            "category":"Shopping",
            "subcategory":"Used Merchandise",
            "type":"Retail Goods"
        }
    ],
    "sg:phone":"+1 520 364 6554",
    "sg:postcode":"85607",
    "sg:province":"AZ",
    "wof:name":"Thomas Used Appliance Center",
    "wof:placetype":"venue"
},
  "geometry": {"coordinates":[-109.552942,31.346534],"type":"Point"}
}