{
  "type": "Feature",
  "properties": {
    "iso:country":"US",
    "sg:address":"550 E Bell Rd",
    "sg:city":"Phoenix",
    "sg:classifiers":[
        {
            "category":"Coffee & Tea",
            "type":"Food & Drink"
        }
    ],
    "sg:menulink":"http://www.allmenus.com/az/phoenix/108354-starbucks-coffee/menu/",
    "sg:phone":"+1 602 863 4194",
    "sg:postcode":"85022",
    "sg:province":"AZ",
    "sg:tags":[
        "american"
    ],
    "wof:name":"Starbucks Coffee",
    "wof:placetype":"venue"
},
  "geometry": {"coordinates":[-112.066992,33.64133],"type":"Point"}
}