{
  "type": "Feature",
  "properties": {
    "iso:country":"US",
    "sg:address":"2316 E Desert Cove Ave",
    "sg:city":"Phoenix",
    "sg:classifiers":[
        {
            "category":"Real Estate",
            "subcategory":"Real Estate Operator",
            "type":"Services"
        }
    ],
    "sg:phone":"+1 602 992 9457",
    "sg:postcode":"85028",
    "sg:province":"AZ",
    "sg:tags":[
        "building",
        "nonresidential"
    ],
    "wof:name":"EZ Street Partnership",
    "wof:placetype":"venue"
},
  "geometry": {"coordinates":[-112.03294699999999,33.586747],"type":"Point"}
}