{
  "type": "Feature",
  "properties": {
    "addr:full":"11435 N Cave Creek Rd Ste 204 Phoenix AZ 85020",
    "addr:housenumber":"11435",
    "addr:postcode":"85020",
    "addr:street":"N Cave Creek Rd Ste 204",
    "iso:country":"US",
    "sg:address":"11435 N Cave Creek Rd Ste 204",
    "sg:city":"Phoenix",
    "sg:classifiers":[
        {
            "category":"Professional",
            "subcategory":"Business Services",
            "type":"Services"
        }
    ],
    "sg:phone":"+1 602 997 1088",
    "sg:postcode":"85020",
    "sg:province":"AZ",
    "sg:tags":[
        "consultant",
        "coach",
        "management"
    ],
    "wof:name":"Williams Investments",
    "wof:placetype":"venue"
},
  "geometry": {"coordinates":[-112.045177,33.590038],"type":"Point"}
}