{
  "type": "Feature",
  "properties": {
    "iso:country":"US",
    "sg:address":"2060 E Baseline Rd",
    "sg:city":"Mesa",
    "sg:classifiers":[
        {
            "category":"Shopping",
            "subcategory":"Crafts & Fabrics",
            "type":"Retail Goods"
        }
    ],
    "sg:phone":"+1 480 503 2415",
    "sg:postcode":"85204",
    "sg:province":"AZ",
    "sg:tags":[
        "art"
    ],
    "sg:website":"www.michaels.com",
    "wof:name":"Michaels Arts & Crafts",
    "wof:placetype":"venue"
},
  "geometry": {"coordinates":[-111.787193,33.380806],"type":"Point"}
}