{
  "type": "Feature",
  "properties": {
    "iso:country":"US",
    "sg:address":"2831 W Mcdowell Rd",
    "sg:city":"Phoenix",
    "sg:classifiers":[
        {
            "category":"Home & Garden",
            "subcategory":"Hardware",
            "type":"Retail Goods"
        },
        {
            "category":"Manufacturing",
            "subcategory":"Building Materials",
            "type":"Manufacturing & Wholesale Goods"
        }
    ],
    "sg:phone":"+1 602 271 9234",
    "sg:postcode":"85009",
    "sg:province":"AZ",
    "sg:tags":[
        "doors-wholesale",
        "accessory",
        "doors",
        "frames",
        "store",
        "manufacturer"
    ],
    "wof:name":"Arizona Door Closers",
    "wof:placetype":"venue"
},
  "geometry": {"coordinates":[-112.119964,33.46595],"type":"Point"}
}