{
  "type": "Feature",
  "properties": {
    "iso:country":"US",
    "sg:address":"8220 N Hayden Rd",
    "sg:city":"Scottsdale",
    "sg:classifiers":[
        {
            "category":"Restaurant",
            "type":"Food & Drink"
        }
    ],
    "sg:menulink":"http://www.allmenus.com/az/phoenix/4587-el-paso-bbq-company/menu/",
    "sg:phone":"+1 480 998 2626",
    "sg:postcode":"85258",
    "sg:province":"AZ",
    "sg:tags":[
        "american"
    ],
    "wof:name":"El Paso BBQ Company",
    "wof:placetype":"venue"
},
  "geometry": {"coordinates":[-111.898685,33.556106],"type":"Point"}
}