{
  "type": "Feature",
  "properties": {
    "addr:full":"3414 W Bell Rd Phoenix AZ 85053",
    "addr:housenumber":"3414",
    "addr:postcode":"85053",
    "addr:street":"W Bell Rd",
    "iso:country":"US",
    "sg:address":"3414 W Bell Rd",
    "sg:city":"Phoenix",
    "sg:classifiers":[
        {
            "category":"Health Services",
            "subcategory":"Chiropractor",
            "type":"Services"
        }
    ],
    "sg:phone":"+1 602 942 6055",
    "sg:postcode":"85053",
    "sg:province":"AZ",
    "wof:name":"Az Chiropractic Ctr",
    "wof:placetype":"venue"
},
  "geometry": {"coordinates":[-112.131837,33.639715],"type":"Point"}
}