{
  "type": "Feature",
  "properties": {
    "addr:full":"390 Meadview Blvd Meadview AZ 86444",
    "addr:housenumber":"390",
    "addr:postcode":"86444",
    "addr:street":"Meadview Blvd",
    "iso:country":"US",
    "sg:address":"390 Meadview Blvd",
    "sg:city":"Meadview",
    "sg:classifiers":[
        {
            "category":"Restaurant",
            "type":"Food & Drink"
        }
    ],
    "sg:phone":"+1 928 564 2885",
    "sg:postcode":"86444",
    "sg:province":"AZ",
    "wof:name":"Crow's Nest Restaurant",
    "wof:placetype":"venue"
},
  "geometry": {"coordinates":[-114.07615,36.001652],"type":"Point"}
}