{
  "type": "Feature",
  "properties": {
    "addr:full":"1800 E Fort Lowell Rd Tucson AZ 85719",
    "addr:housenumber":"1800",
    "addr:postcode":"85719",
    "addr:street":"E Fort Lowell Rd",
    "iso:country":"US",
    "sg:address":"1800 E Fort Lowell Rd",
    "sg:city":"Tucson",
    "sg:classifiers":[
        {
            "category":"Restaurant",
            "type":"Food & Drink"
        }
    ],
    "sg:phone":"+1 520 624 0172",
    "sg:postcode":"85719",
    "sg:province":"AZ",
    "sg:website":"www.mysterymansion.com",
    "wof:name":"A Mystery Dinner Theater",
    "wof:placetype":"venue"
},
  "geometry": {"coordinates":[-110.944762,32.264755],"type":"Point"}
}