{
  "type": "Feature",
  "properties": {
    "iso:country":"US",
    "sg:address":"4722 E Ray Rd",
    "sg:city":"Phoenix",
    "sg:classifiers":[
        {
            "category":"Personal",
            "subcategory":"Beauty Salon",
            "type":"Services"
        }
    ],
    "sg:phone":"+1 480 705 9366",
    "sg:postcode":"85044",
    "sg:province":"AZ",
    "wof:name":"Beauty Express",
    "wof:placetype":"venue"
},
  "geometry": {"coordinates":[-111.982392,33.319904],"type":"Point"}
}