{
  "type": "Feature",
  "properties": {
    "addr:full":"2326 E Electra Ln Phoenix AZ 85024",
    "addr:housenumber":"2326",
    "addr:postcode":"85024",
    "addr:street":"E Electra Ln",
    "iso:country":"US",
    "sg:address":"2326 E Electra Ln",
    "sg:city":"Phoenix",
    "sg:classifiers":[
        {
            "category":"Building & Trades",
            "subcategory":"Landscaping Services",
            "type":"Services"
        }
    ],
    "sg:phone":"+1 480 513 1886",
    "sg:postcode":"85024",
    "sg:province":"AZ",
    "wof:name":"Life First Landscape Maint",
    "wof:placetype":"venue"
},
  "geometry": {"coordinates":[-112.033365,33.700571],"type":"Point"}
}