{
  "type": "Feature",
  "properties": {
    "addr:full":"1395 S Arizona Ave Chandler AZ 85286",
    "addr:housenumber":"1395",
    "addr:postcode":"85286",
    "addr:street":"S Arizona Ave",
    "iso:country":"US",
    "sg:address":"1395 S Arizona Ave",
    "sg:city":"Chandler",
    "sg:classifiers":[
        {
            "category":"Building & Trades",
            "subcategory":"Locksmith",
            "type":"Services"
        }
    ],
    "sg:phone":"+1 602 732 7797",
    "sg:postcode":"85286",
    "sg:province":"AZ",
    "sg:tags":[
        "key"
    ],
    "wof:name":"Fast Locksmith Service",
    "wof:placetype":"venue"
},
  "geometry": {"coordinates":[-111.841166,33.285254],"type":"Point"}
}