{
  "type": "Feature",
  "properties": {
    "addr:full":"1205 W Baseline Rd Mesa AZ 85202",
    "addr:housenumber":"1205",
    "addr:postcode":"85202",
    "addr:street":"W Baseline Rd",
    "iso:country":"US",
    "sg:address":"1205 W Baseline Rd",
    "sg:city":"Mesa",
    "sg:classifiers":[
        {
            "category":"Autos & Motor Vehicles",
            "subcategory":"Fuel & Gas Station",
            "type":"Retail Goods"
        },
        {
            "category":"Manufacturing",
            "subcategory":"Food",
            "type":"Manufacturing & Wholesale Goods"
        },
        {
            "category":"Food & Beverages",
            "subcategory":"Groceries & Convenience Stores",
            "type":"Retail Goods"
        }
    ],
    "sg:phone":"+1 480 839 0205",
    "sg:postcode":"85202",
    "sg:province":"AZ",
    "sg:tags":[
        "product"
    ],
    "wof:name":"4 Sons Food Stores",
    "wof:placetype":"venue"
},
  "geometry": {"coordinates":[-111.861,33.378502],"type":"Point"}
}