{
  "type": "Feature",
  "properties": {
    "addr:full":"7817 E Sheridan St Scottsdale AZ 85257",
    "addr:housenumber":"7817",
    "addr:postcode":"85257",
    "addr:street":"E Sheridan St",
    "iso:country":"US",
    "sg:address":"7817 E Sheridan St",
    "sg:city":"Scottsdale",
    "sg:classifiers":[
        {
            "category":"Professional",
            "subcategory":"Art Services",
            "type":"Services"
        }
    ],
    "sg:phone":"+1 480 946 1499",
    "sg:postcode":"85257",
    "sg:province":"AZ",
    "sg:tags":[
        "photographer"
    ],
    "sg:website":"www.christinejohnsonphotography.com",
    "wof:name":"Christine Johnson Photography",
    "wof:placetype":"venue"
},
  "geometry": {"coordinates":[-111.911506,33.474805],"type":"Point"}
}