{
  "type": "Feature",
  "properties": {
    "addr:full":"12419 N Tatum Blvd Phoenix AZ 85032",
    "addr:housenumber":"12419",
    "addr:postcode":"85032",
    "addr:street":"N Tatum Blvd",
    "iso:country":"US",
    "sg:address":"12419 N Tatum Blvd",
    "sg:city":"Phoenix",
    "sg:classifiers":[
        {
            "category":"Shopping",
            "subcategory":"Bicycles & Sporting Goods",
            "type":"Retail Goods"
        },
        {
            "category":"Home & Garden",
            "subcategory":"Furniture",
            "type":"Retail Goods"
        },
        {
            "category":"Personal",
            "subcategory":"Sauna",
            "type":"Services"
        },
        {
            "category":"Personal",
            "subcategory":"Day Spa",
            "type":"Services"
        }
    ],
    "sg:phone":"+1 602 996 8100",
    "sg:postcode":"85032",
    "sg:province":"AZ",
    "sg:tags":[
        "outdoor",
        "supply",
        "equipment",
        "hot",
        "patio",
        "tub",
        "pool",
        "swimming"
    ],
    "sg:website":"http://www.todayspatio.com",
    "wof:name":"Today's Pool & Patio",
    "wof:placetype":"venue"
},
  "geometry": {"coordinates":[-111.979607,33.600208],"type":"Point"}
}