{
  "type": "Feature",
  "properties": {
    "iso:country":"US",
    "sg:address":"1423 S Country Club Dr Ste 2",
    "sg:city":"Mesa",
    "sg:classifiers":[
        {
            "category":"Shopping",
            "subcategory":"Beauty & Cosmetics",
            "type":"Retail Goods"
        }
    ],
    "sg:phone":"+1 480 655 4808",
    "sg:postcode":"85210",
    "sg:province":"AZ",
    "sg:tags":[
        "supply"
    ],
    "wof:name":"United Beauty Supply",
    "wof:placetype":"venue"
},
  "geometry": {"coordinates":[-111.839896,33.388538],"type":"Point"}
}