{
  "type": "Feature",
  "properties": {
    "addr:full":"7154 W Eugie Ave Peoria AZ 85381",
    "addr:housenumber":"7154",
    "addr:postcode":"85381",
    "addr:street":"W Eugie Ave",
    "iso:country":"US",
    "sg:address":"7154 W Eugie Ave",
    "sg:city":"Peoria",
    "sg:classifiers":[
        {
            "category":"Building & Trades",
            "subcategory":"Construction",
            "type":"Services"
        }
    ],
    "sg:phone":"+1 623 776 9910",
    "sg:postcode":"85381",
    "sg:province":"AZ",
    "sg:tags":[
        "coping",
        "plastering",
        "tiling",
        "pool",
        "swimming"
    ],
    "wof:name":"Arizona Pool Svc",
    "wof:placetype":"venue"
},
  "geometry": {"coordinates":[-112.214431,33.608162],"type":"Point"}
}