{
  "type": "Feature",
  "properties": {
    "addr:full":"20235 N Cave Creek Rd Phoenix AZ 85024",
    "addr:housenumber":"20235",
    "addr:postcode":"85024",
    "addr:street":"N Cave Creek Rd",
    "iso:country":"US",
    "sg:address":"20235 N Cave Creek Rd",
    "sg:city":"Phoenix",
    "sg:classifiers":[
        {
            "category":"Building & Trades",
            "subcategory":"Construction",
            "type":"Services"
        }
    ],
    "sg:phone":"+1 480 734 3382",
    "sg:postcode":"85024",
    "sg:province":"AZ",
    "sg:tags":[
        "road",
        "contractor"
    ],
    "wof:name":"Kalosa Builders",
    "wof:placetype":"venue"
},
  "geometry": {"coordinates":[-112.03095999999999,33.670746],"type":"Point"}
}