{
  "type": "Feature",
  "properties": {
    "iso:country":"US",
    "sg:address":"3434 W Anthem Way Suite 112.",
    "sg:city":"Anthem",
    "sg:classifiers":[
        {
            "category":"Real Estate",
            "subcategory":"Real Estate Agent",
            "type":"Services"
        }
    ],
    "sg:phone":"+1 623 243 1143",
    "sg:postcode":"85086",
    "sg:province":"AZ",
    "sg:website":"http://www.daisymountainrealestate.com",
    "wof:name":"Coldwell Banker Daisy Mountain Real Estate",
    "wof:placetype":"venue"
},
  "geometry": {"coordinates":[-112.133306,33.862439],"type":"Point"}
}