{
  "type": "Feature",
  "properties": {
    "iso:country":"US",
    "sg:address":"1942 E Carver Rd",
    "sg:city":"Tempe",
    "sg:classifiers":[
        {
            "category":"Building & Trades",
            "subcategory":"Construction",
            "type":"Services"
        }
    ],
    "sg:phone":"+1 480 839 2423",
    "sg:postcode":"85284",
    "sg:province":"AZ",
    "sg:tags":[
        "carpenter"
    ],
    "wof:name":"A Carpenter",
    "wof:placetype":"venue"
},
  "geometry": {"coordinates":[-111.905666,33.34161],"type":"Point"}
}