{
  "type": "Feature",
  "properties": {
    "iso:country":"US",
    "sg:address":"6221 E Sunny Dr",
    "sg:city":"Tucson",
    "sg:classifiers":[
        {
            "category":"Shopping",
            "subcategory":"Clothing, Apparel, & Fashions",
            "type":"Retail Goods"
        }
    ],
    "sg:phone":"+1 520 885 4222",
    "sg:postcode":"85712",
    "sg:province":"AZ",
    "wof:name":"Network Big & Tall Shop Ltd",
    "wof:placetype":"venue"
},
  "geometry": {"coordinates":[-110.858298,32.247147],"type":"Point"}
}