{
  "type": "Feature",
  "properties": {
    "iso:country":"US",
    "sg:address":"7143 N 7th St",
    "sg:city":"Phoenix",
    "sg:classifiers":[
        {
            "category":"Health Services",
            "subcategory":"Chiropractor",
            "type":"Services"
        }
    ],
    "sg:phone":"+1 602 997 2273",
    "sg:postcode":"85020",
    "sg:province":"AZ",
    "wof:name":"Chiropractic Care Ctr",
    "wof:placetype":"venue"
},
  "geometry": {"coordinates":[-112.065013,33.541028],"type":"Point"}
}