{
  "type": "Feature",
  "properties": {
    "addr:full":"1975 W Frontier St Apache Junction AZ 85220",
    "addr:housenumber":"1975",
    "addr:postcode":"85220",
    "addr:street":"W Frontier St",
    "iso:country":"US",
    "sg:address":"1975 W Frontier St",
    "sg:city":"Apache Junction",
    "sg:classifiers":[
        {
            "category":"Travel",
            "subcategory":"Travel Agent",
            "type":"Entertainment"
        }
    ],
    "sg:phone":"+1 480 288 9528",
    "sg:postcode":"85220",
    "sg:province":"AZ",
    "sg:tags":[
        "agency"
    ],
    "wof:name":"Southwest Travel Inc",
    "wof:placetype":"venue"
},
  "geometry": {"coordinates":[-111.567401,33.456367],"type":"Point"}
}