{
  "type": "Feature",
  "properties": {
    "addr:full":"3101 W Thomas Rd Phoenix AZ 85017",
    "addr:housenumber":"3101",
    "addr:postcode":"85017",
    "addr:street":"W Thomas Rd",
    "iso:country":"US",
    "sg:address":"3101 W Thomas Rd",
    "sg:city":"Phoenix",
    "sg:classifiers":[
        {
            "category":"Manufacturing",
            "subcategory":"Tools & Machinery",
            "type":"Manufacturing & Wholesale Goods"
        }
    ],
    "sg:phone":"+1 602 272 4223",
    "sg:postcode":"85017",
    "sg:province":"AZ",
    "sg:tags":[
        "machine",
        "shop"
    ],
    "wof:name":"Rae Tech",
    "wof:placetype":"venue"
},
  "geometry": {"coordinates":[-112.127538,33.480438],"type":"Point"}
}