{
  "type": "Feature",
  "properties": {
    "iso:country":"US",
    "sg:address":"3954 E Speedway Blvd",
    "sg:city":"Tucson",
    "sg:classifiers":[
        {
            "category":"Shopping",
            "type":"Retail Goods"
        }
    ],
    "sg:phone":"+1 520 784 0564",
    "sg:postcode":"85712",
    "sg:province":"AZ",
    "sg:tags":[
        "spa",
        "hot",
        "tub"
    ],
    "wof:name":"Spa World By The Water Spclsts",
    "wof:placetype":"venue"
},
  "geometry": {"coordinates":[-110.908722,32.236097],"type":"Point"}
}