{
  "type": "Feature",
  "properties": {
    "iso:country":"US",
    "sg:address":"2012 E Catamaran Dr",
    "sg:city":"Gilbert",
    "sg:classifiers":[
        {
            "category":"Real Estate",
            "subcategory":"Real Estate Agent",
            "type":"Services"
        }
    ],
    "sg:phone":"+1 480 926 6680",
    "sg:postcode":"85234",
    "sg:province":"AZ",
    "wof:name":"New Century Realty Inc",
    "wof:placetype":"venue"
},
  "geometry": {"coordinates":[-111.744978,33.37603],"type":"Point"}
}