{
  "type": "Feature",
  "properties": {
    "addr:full":"1731 S Greenfield Rd Mesa AZ 85206",
    "addr:housenumber":"1731",
    "addr:postcode":"85206",
    "addr:street":"S Greenfield Rd",
    "iso:country":"US",
    "sg:address":"1731 S Greenfield Rd",
    "sg:city":"Mesa",
    "sg:classifiers":[
        {
            "category":"Personal",
            "type":"Services"
        },
        {
            "category":"Arena",
            "subcategory":"Sports Club",
            "type":"Entertainment"
        }
    ],
    "sg:phone":"+1 480 635 9600",
    "sg:postcode":"85206",
    "sg:province":"AZ",
    "sg:tags":[
        "trainer",
        "consultant",
        "physical",
        "health",
        "fitness"
    ],
    "sg:website":"http://www.lafitness.com/",
    "wof:name":"La Fitness",
    "wof:placetype":"venue"
},
  "geometry": {"coordinates":[-111.738889,33.382415],"type":"Point"}
}