{
  "type": "Feature",
  "properties": {
    "iso:country":"US",
    "sg:address":"300 E Commonwealth Ave",
    "sg:city":"Chandler",
    "sg:classifiers":[
        {
            "category":"Real Estate",
            "subcategory":"Real Estate Operator",
            "type":"Services"
        }
    ],
    "sg:phone":"+1 480 917 7230",
    "sg:postcode":"85225",
    "sg:province":"AZ",
    "sg:tags":[
        "apartment"
    ],
    "wof:name":"Chandler Gardens Apartments",
    "wof:placetype":"venue"
},
  "geometry": {"coordinates":[-111.836998,33.303398],"type":"Point"}
}