{
  "type": "Feature",
  "properties": {
    "addr:full":"1720 S 27th Ave Phoenix AZ 85009",
    "addr:housenumber":"1720",
    "addr:postcode":"85009",
    "addr:street":"S 27Th Ave",
    "iso:country":"US",
    "sg:address":"1720 S 27th Ave",
    "sg:city":"Phoenix",
    "sg:classifiers":[
        {
            "category":"Building & Trades",
            "subcategory":"Construction",
            "type":"Services"
        }
    ],
    "sg:phone":"+1 602 484 0700",
    "sg:postcode":"85009",
    "sg:province":"AZ",
    "sg:tags":[
        "general",
        "contractor"
    ],
    "wof:name":"Stonecreek Contracting",
    "wof:placetype":"venue"
},
  "geometry": {"coordinates":[-112.11729200000001,33.43065],"type":"Point"}
}