{
  "type": "Feature",
  "properties": {
    "iso:country":"US",
    "sg:address":"1791 W Ajo Way",
    "sg:city":"Tucson",
    "sg:classifiers":[
        {
            "category":"Shopping",
            "type":"Retail Goods"
        }
    ],
    "sg:phone":"+1 520 741 0235",
    "sg:postcode":"85713",
    "sg:province":"AZ",
    "sg:tags":[
        "merchandise"
    ],
    "wof:name":"Old Fashioned Barber Shop",
    "wof:placetype":"venue"
},
  "geometry": {"coordinates":[-111.002412,32.177801],"type":"Point"}
}