{
  "type": "Feature",
  "properties": {
    "iso:country":"US",
    "sg:address":"1509 N Arizona Ave",
    "sg:city":"Chandler",
    "sg:classifiers":[
        {
            "category":"Food & Beverages",
            "subcategory":"Candy",
            "type":"Retail Goods"
        }
    ],
    "sg:phone":"+1 480 899 6150",
    "sg:postcode":"85225",
    "sg:province":"AZ",
    "wof:name":"Deannas Fudge",
    "wof:placetype":"venue"
},
  "geometry": {"coordinates":[-111.84161,33.33036],"type":"Point"}
}