{
  "type": "Feature",
  "properties": {
    "addr:full":"12888 E Appaloosa Pl Scottsdale AZ 85259",
    "addr:housenumber":"12888",
    "addr:postcode":"85259",
    "addr:street":"E Appaloosa Pl",
    "iso:country":"US",
    "sg:address":"12888 E Appaloosa Pl",
    "sg:city":"Scottsdale",
    "sg:classifiers":[
        {
            "category":"Restaurant",
            "type":"Food & Drink"
        }
    ],
    "sg:phone":"+1 480 767 1100",
    "sg:postcode":"85259",
    "sg:province":"AZ",
    "sg:tags":[
        "eating"
    ],
    "wof:name":"Market The",
    "wof:placetype":"venue"
},
  "geometry": {"coordinates":[-111.804855,33.57455],"type":"Point"}
}