{
  "type": "Feature",
  "properties": {
    "iso:country":"US",
    "sg:address":"1352 E Powell Way",
    "sg:city":"Chandler",
    "sg:classifiers":[
        {
            "category":"Shopping",
            "subcategory":"Discount & Variety Stores",
            "type":"Retail Goods"
        }
    ],
    "sg:phone":"+1 480 857 1590",
    "sg:postcode":"85249",
    "sg:province":"AZ",
    "sg:tags":[
        "merchandise",
        "general"
    ],
    "wof:name":"Delicate Designs",
    "wof:placetype":"venue"
},
  "geometry": {"coordinates":[-111.816465,33.235886],"type":"Point"}
}