{
  "type": "Feature",
  "properties": {
    "iso:country":"US",
    "sg:address":"13786 E Via Valderrama",
    "sg:city":"Vail",
    "sg:classifiers":[
        {
            "category":"Real Estate",
            "subcategory":"Real Estate Agent",
            "type":"Services"
        }
    ],
    "sg:phone":"+1 520 886 6577",
    "sg:postcode":"85641",
    "sg:province":"AZ",
    "wof:name":"Kaufman & Kaufman",
    "wof:placetype":"venue"
},
  "geometry": {"coordinates":[-110.70021,32.053414],"type":"Point"}
}