{
  "type": "Feature",
  "properties": {
    "addr:full":"6312 E Mescal St Scottsdale AZ 85254",
    "addr:housenumber":"6312",
    "addr:postcode":"85254",
    "addr:street":"E Mescal St",
    "iso:country":"US",
    "sg:address":"6312 E Mescal St",
    "sg:city":"Scottsdale",
    "sg:classifiers":[
        {
            "category":"Health Services",
            "subcategory":"Hospital",
            "type":"Services"
        }
    ],
    "sg:phone":"+1 480 368 7448",
    "sg:postcode":"85254",
    "sg:province":"AZ",
    "sg:tags":[
        "nurse",
        "registry"
    ],
    "wof:name":"P V Nurses Touch",
    "wof:placetype":"venue"
},
  "geometry": {"coordinates":[-111.945211,33.586768],"type":"Point"}
}