{
  "type": "Feature",
  "properties": {
    "addr:full":"3330 E Thomas Rd Phoenix AZ 85018",
    "addr:housenumber":"3330",
    "addr:postcode":"85018",
    "addr:street":"E Thomas Rd",
    "iso:country":"US",
    "sg:address":"3330 E Thomas Rd",
    "sg:city":"Phoenix",
    "sg:classifiers":[
        {
            "category":"Restaurant",
            "type":"Food & Drink"
        }
    ],
    "sg:menulink":"http://www.allmenus.com/az/phoenix/231429-sonic/menu/",
    "sg:phone":"+1 602 224 0830",
    "sg:postcode":"85018",
    "sg:province":"AZ",
    "sg:tags":[
        "burger",
        "american"
    ],
    "wof:name":"Sonic",
    "wof:placetype":"venue"
},
  "geometry": {"coordinates":[-112.00939099999999,33.480479],"type":"Point"}
}