{
  "type": "Feature",
  "properties": {
    "addr:full":"5837 S College Ave Tempe AZ 85283",
    "addr:housenumber":"5837",
    "addr:postcode":"85283",
    "addr:street":"S College Ave",
    "iso:country":"US",
    "sg:address":"5837 S College Ave",
    "sg:city":"Tempe",
    "sg:classifiers":[
        {
            "category":"Social Services",
            "type":"Services"
        }
    ],
    "sg:phone":"+1 480 752 1832",
    "sg:postcode":"85283",
    "sg:province":"AZ",
    "sg:tags":[
        "organization",
        "welfare"
    ],
    "wof:name":"Compassionate Friends",
    "wof:placetype":"venue"
},
  "geometry": {"coordinates":[-111.932973,33.368534],"type":"Point"}
}