{
  "type": "Feature",
  "properties": {
    "iso:country":"US",
    "sg:address":"2980 Corral Cir",
    "sg:city":"Lake Havasu City",
    "sg:classifiers":[
        {
            "category":"Building & Trades",
            "subcategory":"Construction",
            "type":"Services"
        }
    ],
    "sg:phone":"+1 928 855 6827",
    "sg:postcode":"86404",
    "sg:province":"AZ",
    "sg:tags":[
        "roofing",
        "contractor"
    ],
    "wof:name":"Meyer's Roof Coatings & Roof",
    "wof:placetype":"venue"
},
  "geometry": {"coordinates":[-114.321641,34.527839],"type":"Point"}
}