{
  "type": "Feature",
  "properties": {
    "addr:full":"1206 N Stadem Dr Tempe AZ 85281",
    "addr:housenumber":"1206",
    "addr:postcode":"85281",
    "addr:street":"N Stadem Dr",
    "iso:country":"US",
    "sg:address":"1206 N Stadem Dr",
    "sg:city":"Tempe",
    "sg:classifiers":[
        {
            "category":"Home & Garden",
            "subcategory":"Home Furnishings",
            "type":"Retail Goods"
        },
        {
            "category":"Professional",
            "subcategory":"Art Services",
            "type":"Services"
        }
    ],
    "sg:phone":"+1 480 626 6850",
    "sg:postcode":"85281",
    "sg:province":"AZ",
    "sg:tags":[
        "draperies",
        "designer",
        "window",
        "treatment",
        "interior",
        "curtain",
        "decorator"
    ],
    "wof:name":"Progressive Commercial Interiors",
    "wof:placetype":"venue"
},
  "geometry": {"coordinates":[-111.913719,33.442261],"type":"Point"}
}