{
  "type": "Feature",
  "properties": {
    "iso:country":"US",
    "sg:address":"6748 E Mckellips Rd",
    "sg:city":"Mesa",
    "sg:classifiers":[
        {
            "category":"Restaurant",
            "type":"Food & Drink"
        }
    ],
    "sg:menulink":"http://www.allmenus.com/az/phoenix/190552-mcdonalds/menu/",
    "sg:postcode":"85215",
    "sg:province":"AZ",
    "sg:tags":[
        "burger",
        "american"
    ],
    "wof:name":"McDonald's",
    "wof:placetype":"venue"
},
  "geometry": {"coordinates":[-111.685322,33.451864],"type":"Point"}
}