{
  "type": "Feature",
  "properties": {
    "iso:country":"US",
    "sg:address":"1231 N Rhinestone Dr",
    "sg:city":"Prescott",
    "sg:classifiers":[
        {
            "category":"Building & Trades",
            "subcategory":"Construction",
            "type":"Services"
        }
    ],
    "sg:phone":"+1 928 443 5600",
    "sg:postcode":"86301",
    "sg:province":"AZ",
    "sg:tags":[
        "general",
        "contractor"
    ],
    "wof:name":"Cavanaugh Construction",
    "wof:placetype":"venue"
},
  "geometry": {"coordinates":[-112.379565,34.560957],"type":"Point"}
}