{
  "type": "Feature",
  "properties": {
    "iso:country":"US",
    "sg:address":"2050 N Alma School Road Suite 7",
    "sg:city":"Chandler",
    "sg:classifiers":[
        {
            "category":"Cinema",
            "subcategory":"Movie Rental",
            "type":"Entertainment"
        }
    ],
    "sg:phone":"+1 480 345 0102",
    "sg:postcode":"85224",
    "sg:province":"AZ",
    "sg:tags":[
        "game",
        "video"
    ],
    "wof:name":"Video Paradise",
    "wof:placetype":"venue"
},
  "geometry": {"coordinates":[-111.859066,33.335838],"type":"Point"}
}