{
  "type": "Feature",
  "properties": {
    "addr:full":"1526 Idylwild Dr Prescott AZ 86305",
    "addr:housenumber":"1526",
    "addr:postcode":"86305",
    "addr:street":"Idylwild Dr",
    "iso:country":"US",
    "sg:address":"1526 Idylwild Dr",
    "sg:city":"Prescott",
    "sg:classifiers":[
        {
            "category":"Health Services",
            "subcategory":"Health Practitioner",
            "type":"Services"
        }
    ],
    "sg:phone":"+1 928 442 1234",
    "sg:postcode":"86305",
    "sg:province":"AZ",
    "sg:tags":[
        "therapist",
        "physical"
    ],
    "wof:name":"Garcia Physical Therapy",
    "wof:placetype":"venue"
},
  "geometry": {"coordinates":[-112.493126,34.543776],"type":"Point"}
}