{
  "type": "Feature",
  "properties": {
    "iso:country":"US",
    "sg:address":"25 S 48th Ave",
    "sg:city":"Phoenix",
    "sg:classifiers":[
        {
            "category":"Wholesale",
            "subcategory":"Electrical",
            "type":"Manufacturing & Wholesale Goods"
        }
    ],
    "sg:phone":"+1 602 272 4080",
    "sg:postcode":"85043",
    "sg:province":"AZ",
    "sg:tags":[
        "lighting",
        "fixture"
    ],
    "wof:name":"Aztec Lighting",
    "wof:placetype":"venue"
},
  "geometry": {"coordinates":[-112.162818,33.446979],"type":"Point"}
}