{
  "type": "Feature",
  "properties": {
    "addr:full":"2610 N 3rd St Ste A Phoenix AZ 85004",
    "addr:housenumber":"2610",
    "addr:postcode":"85004",
    "addr:street":"N 3Rd St Ste A",
    "iso:country":"US",
    "sg:address":"2610 N 3rd St Ste A",
    "sg:city":"Phoenix",
    "sg:classifiers":[
        {
            "category":"Health Services",
            "subcategory":"Doctor",
            "type":"Services"
        }
    ],
    "sg:phone":"+1 602 277 2228",
    "sg:postcode":"85004",
    "sg:province":"AZ",
    "sg:tags":[
        "physician",
        "surgeon",
        "neurology",
        "surgeons"
    ],
    "sg:website":"http://www.mdsdocs.com",
    "wof:name":"John E Samantha M D , P",
    "wof:placetype":"venue"
},
  "geometry": {"coordinates":[-112.069427,33.476759],"type":"Point"}
}