{
  "type": "Feature",
  "properties": {
    "addr:full":"16913 E Enterprise Dr Fountain Hills AZ 85268",
    "addr:housenumber":"16913 e",
    "addr:postcode":"85268",
    "addr:street":"Enterprise Dr",
    "iso:country":"US",
    "sg:address":"16913 E Enterprise Dr",
    "sg:city":"Fountain Hills",
    "sg:classifiers":[
        {
            "category":"Personal",
            "type":"Services"
        }
    ],
    "sg:phone":"+1 480 816 3900",
    "sg:postcode":"85268",
    "sg:province":"AZ",
    "sg:tags":[
        "therapist",
        "massage"
    ],
    "wof:name":"Center For Perfect Health",
    "wof:placetype":"venue"
},
  "geometry": {"coordinates":[-111.712288,33.595392],"type":"Point"}
}