{
  "type": "Feature",
  "properties": {
    "iso:country":"US",
    "sg:address":"6508 N 10th Pl",
    "sg:city":"Phoenix",
    "sg:classifiers":[
        {
            "category":"Professional",
            "subcategory":"Lawyer & Legal Services",
            "type":"Services"
        }
    ],
    "sg:phone":"+1 602 255 0330",
    "sg:postcode":"85014",
    "sg:province":"AZ",
    "sg:tags":[
        "attorney"
    ],
    "wof:name":"Allen B Bickart Law Office",
    "wof:placetype":"venue"
},
  "geometry": {"coordinates":[-112.05933,33.531496],"type":"Point"}
}