{
  "type": "Feature",
  "properties": {
    "iso:country":"US",
    "sg:address":"11555 E Speedway Blvd",
    "sg:city":"Tucson",
    "sg:classifiers":[
        {
            "category":"Wholesale",
            "subcategory":"Computers",
            "type":"Manufacturing & Wholesale Goods"
        }
    ],
    "sg:phone":"+1 520 886 6677",
    "sg:postcode":"85748",
    "sg:province":"AZ",
    "sg:tags":[
        "development",
        "software"
    ],
    "wof:name":"Nevar Development Inc",
    "wof:placetype":"venue"
},
  "geometry": {"coordinates":[-110.745165,32.235534],"type":"Point"}
}