{
  "type": "Feature",
  "properties": {
    "addr:full":"3103 E Fairmount St Tucson AZ 85716",
    "addr:housenumber":"3103",
    "addr:postcode":"85716",
    "addr:street":"E Fairmount St",
    "iso:country":"US",
    "sg:address":"3103 E Fairmount St",
    "sg:city":"Tucson",
    "sg:classifiers":[
        {
            "category":"Shopping",
            "subcategory":"Music",
            "type":"Retail Goods"
        }
    ],
    "sg:phone":"+1 520 319 0317",
    "sg:postcode":"85716",
    "sg:province":"AZ",
    "wof:name":"Record Ian W Cevallos Wen",
    "wof:placetype":"venue"
},
  "geometry": {"coordinates":[-110.924679,32.239786],"type":"Point"}
}