{
  "type": "Feature",
  "properties": {
    "iso:country":"US",
    "sg:address":"1536 E Maryland Ave",
    "sg:city":"Phoenix",
    "sg:phone":"+1 480 650 8883",
    "sg:postcode":"85014",
    "sg:province":"AZ",
    "wof:name":"Kimberly Kino, LPC / At Home Counseling Services",
    "wof:placetype":"venue"
},
  "geometry": {"coordinates":[-112.049107,33.530972],"type":"Point"}
}