{
  "type": "Feature",
  "properties": {
    "iso:country":"US",
    "sg:address":"4235 E Nisbet Rd",
    "sg:city":"Phoenix",
    "sg:classifiers":[
        {
            "category":"Shopping",
            "subcategory":"Pharmacy",
            "type":"Retail Goods"
        }
    ],
    "sg:phone":"+1 602 971 3811",
    "sg:postcode":"85032",
    "sg:province":"AZ",
    "wof:name":"Medicare Health Benefits Inc",
    "wof:placetype":"venue"
},
  "geometry": {"coordinates":[-111.99100900000001,33.622617],"type":"Point"}
}