{
  "type": "Feature",
  "properties": {
    "iso:country":"US",
    "sg:address":"9501 E Ashford Dr",
    "sg:city":"Tucson",
    "sg:classifiers":[
        {
            "category":"Professional",
            "subcategory":"Business Services",
            "type":"Services"
        }
    ],
    "sg:phone":"+1 520 324 0300",
    "sg:postcode":"85747",
    "sg:province":"AZ",
    "sg:tags":[
        "interior",
        "consultant",
        "design",
        "decorator"
    ],
    "wof:name":"Belle Provence",
    "wof:placetype":"venue"
},
  "geometry": {"coordinates":[-110.789233,32.107435],"type":"Point"}
}