{
  "type": "Feature",
  "properties": {
    "iso:country":"US",
    "sg:address":"325 W Glenrosa Ave",
    "sg:city":"Phoenix",
    "sg:classifiers":[
        {
            "category":"Professional",
            "type":"Services"
        }
    ],
    "sg:phone":"+1 602 234 3283",
    "sg:postcode":"85013",
    "sg:province":"AZ",
    "wof:name":"Lynns Nanny",
    "wof:placetype":"venue"
},
  "geometry": {"coordinates":[-112.079066,33.498362],"type":"Point"}
}