{
  "type": "Feature",
  "properties": {
    "addr:full":"1914 S Mesa Dr Mesa AZ 85210",
    "addr:housenumber":"1914",
    "addr:postcode":"85210",
    "addr:street":"S Mesa Dr",
    "iso:country":"US",
    "sg:address":"1914 S Mesa Dr",
    "sg:city":"Mesa",
    "sg:classifiers":[
        {
            "category":"Retail",
            "subcategory":"Car Wash",
            "type":"Services"
        }
    ],
    "sg:phone":"+1 480 633 0617",
    "sg:postcode":"85210",
    "sg:province":"AZ",
    "sg:tags":[
        "polishing",
        "washing"
    ],
    "wof:name":"Ralphie's Car Wash",
    "wof:placetype":"venue"
},
  "geometry": {"coordinates":[-111.82486900000001,33.380136],"type":"Point"}
}