{
  "type": "Feature",
  "properties": {
    "iso:country":"US",
    "sg:address":"4402 W Glendale Ave",
    "sg:city":"Glendale",
    "sg:classifiers":[
        {
            "category":"Restaurant",
            "type":"Food & Drink"
        }
    ],
    "sg:menulink":"http://www.allmenus.com/az/phoenix/204940-taco-bell/menu/",
    "sg:postcode":"85301",
    "sg:province":"AZ",
    "sg:tags":[
        "mexican"
    ],
    "wof:name":"Taco Bell",
    "wof:placetype":"venue"
},
  "geometry": {"coordinates":[-112.15376500000001,33.538778],"type":"Point"}
}