{
  "type": "Feature",
  "properties": {
    "addr:full":"20818 N 19th Ave Phoenix AZ 85027",
    "addr:housenumber":"20818",
    "addr:postcode":"85027",
    "addr:street":"N 19Th Ave",
    "iso:country":"US",
    "sg:address":"20818 N 19th Ave",
    "sg:city":"Phoenix",
    "sg:classifiers":[
        {
            "category":"Restaurant",
            "type":"Food & Drink"
        }
    ],
    "sg:phone":"+1 623 580 0591",
    "sg:postcode":"85027",
    "sg:province":"AZ",
    "sg:tags":[
        "eating"
    ],
    "wof:name":"Q Bar & Grill",
    "wof:placetype":"venue"
},
  "geometry": {"coordinates":[-112.099867,33.676344],"type":"Point"}
}