{
  "type": "Feature",
  "properties": {
    "iso:country":"US",
    "sg:address":"901 S Central Ave",
    "sg:city":"Show Low",
    "sg:classifiers":[
        {
            "category":"Real Estate",
            "subcategory":"Developer",
            "type":"Services"
        }
    ],
    "sg:phone":"+1 928 537 7298",
    "sg:postcode":"85901",
    "sg:province":"AZ",
    "sg:tags":[
        "cemetery"
    ],
    "wof:name":"Mass Development of Arizona",
    "wof:placetype":"venue"
},
  "geometry": {"coordinates":[-110.040054,34.238583],"type":"Point"}
}