{
  "type": "Feature",
  "properties": {
    "iso:country":"US",
    "sg:address":"320 N Power Rd",
    "sg:city":"Mesa",
    "sg:classifiers":[
        {
            "category":"Personal",
            "subcategory":"Beauty Salon",
            "type":"Services"
        }
    ],
    "sg:phone":"+1 480 981 0016",
    "sg:postcode":"85205",
    "sg:province":"AZ",
    "wof:name":"Angel's Scissor Talk",
    "wof:placetype":"venue"
},
  "geometry": {"coordinates":[-111.684558,33.422594],"type":"Point"}
}