{
  "type": "Feature",
  "properties": {
    "iso:country":"US",
    "sg:address":"9746 E Monterey Ave",
    "sg:city":"Mesa",
    "sg:classifiers":[
        {
            "category":"Building & Trades",
            "subcategory":"Construction",
            "type":"Services"
        }
    ],
    "sg:phone":"+1 480 615 2173",
    "sg:postcode":"85209",
    "sg:province":"AZ",
    "sg:tags":[
        "fire",
        "restoration",
        "damage"
    ],
    "wof:name":"AWER Svc",
    "wof:placetype":"venue"
},
  "geometry": {"coordinates":[-111.622125,33.369124],"type":"Point"}
}