{
  "type": "Feature",
  "properties": {
    "iso:country":"US",
    "sg:address":"7611 W Thomas Rd",
    "sg:city":"Phoenix",
    "sg:classifiers":[
        {
            "category":"Shopping",
            "subcategory":"Clothing, Apparel, & Fashions",
            "type":"Retail Goods"
        }
    ],
    "sg:phone":"+1 623 845 0355",
    "sg:postcode":"85033",
    "sg:province":"AZ",
    "sg:tags":[
        "children's",
        "clothing"
    ],
    "sg:website":"www.childrensplace.com",
    "wof:name":"Children's Place the",
    "wof:placetype":"venue"
},
  "geometry": {"coordinates":[-112.223,33.4799],"type":"Point"}
}