{
  "type": "Feature",
  "properties": {
    "iso:country":"US",
    "sg:address":"2625 W Holly St",
    "sg:city":"Phoenix",
    "sg:classifiers":[
        {
            "category":"Building & Trades",
            "subcategory":"Electrical",
            "type":"Services"
        }
    ],
    "sg:phone":"+1 602 272 3090",
    "sg:postcode":"85009",
    "sg:province":"AZ",
    "sg:tags":[
        "electric",
        "contractor"
    ],
    "wof:name":"Interstate Electric Co",
    "wof:placetype":"venue"
},
  "geometry": {"coordinates":[-112.11516,33.470392],"type":"Point"}
}