{
  "type": "Feature",
  "properties": {
    "iso:country":"US",
    "sg:address":"725 W Ash St",
    "sg:city":"Globe",
    "sg:classifiers":[
        {
            "category":"Professional",
            "subcategory":"Advertising",
            "type":"Services"
        },
        {
            "category":"Manufacturing",
            "subcategory":"Signs",
            "type":"Manufacturing & Wholesale Goods"
        }
    ],
    "sg:phone":"+1 928 425 7734",
    "sg:postcode":"85501",
    "sg:province":"AZ",
    "sg:tags":[
        "specialty"
    ],
    "wof:name":"Corona Signs",
    "wof:placetype":"venue"
},
  "geometry": {"coordinates":[-110.778969,33.393845],"type":"Point"}
}