{
  "type": "Feature",
  "properties": {
    "iso:country":"US",
    "sg:address":"850 E Monroe Ave",
    "sg:city":"Buckeye",
    "sg:classifiers":[
        {
            "category":"Travel",
            "subcategory":"Campground",
            "type":"Entertainment"
        }
    ],
    "sg:phone":"+1 623 386 4819",
    "sg:postcode":"85326",
    "sg:province":"AZ",
    "sg:tags":[
        "recreational",
        "parks",
        "vehicle"
    ],
    "wof:name":"Parkside Travel Trailer Park",
    "wof:placetype":"venue"
},
  "geometry": {"coordinates":[-112.57901,33.370575],"type":"Point"}
}