{
  "type": "Feature",
  "properties": {
    "iso:country":"US",
    "sg:address":"2289 W Village Dr",
    "sg:city":"Phoenix",
    "sg:classifiers":[
        {
            "category":"Building & Trades",
            "subcategory":"Plumbing",
            "type":"Services"
        }
    ],
    "sg:phone":"+1 602 588 9296",
    "sg:postcode":"85023",
    "sg:province":"AZ",
    "sg:tags":[
        "conditioning",
        "air",
        "system",
        "contractor"
    ],
    "wof:name":"Costello Heating & Air Cond",
    "wof:placetype":"venue"
},
  "geometry": {"coordinates":[-112.105592,33.646185],"type":"Point"}
}