{
  "type": "Feature",
  "properties": {
    "iso:country":"US",
    "sg:address":"1687 W Grant Rd",
    "sg:city":"Tucson",
    "sg:classifiers":[
        {
            "category":"Building & Trades",
            "subcategory":"Construction",
            "type":"Services"
        }
    ],
    "sg:phone":"+1 520 884 1081",
    "sg:postcode":"85745",
    "sg:province":"AZ",
    "sg:tags":[
        "residential",
        "general",
        "nonresidential",
        "contractor"
    ],
    "wof:name":"Echo Construction Inc",
    "wof:placetype":"venue"
},
  "geometry": {"coordinates":[-111.000819,32.250471],"type":"Point"}
}