{
  "type": "Feature",
  "properties": {
    "iso:country":"US",
    "sg:address":"9705 E Mountain View Rd",
    "sg:city":"Scottsdale",
    "sg:classifiers":[
        {
            "category":"Shopping",
            "subcategory":"Hobbies, Toys, & Games",
            "type":"Retail Goods"
        }
    ],
    "sg:phone":"+1 480 657 9316",
    "sg:postcode":"85258",
    "sg:province":"AZ",
    "sg:tags":[
        "toy",
        "store",
        "supply"
    ],
    "wof:name":"Trend Times Toys",
    "wof:placetype":"venue"
},
  "geometry": {"coordinates":[-111.871727,33.57555],"type":"Point"}
}