{
  "type": "Feature",
  "properties": {
    "iso:country":"US",
    "sg:address":"1341 S River Dr",
    "sg:city":"Tempe",
    "sg:classifiers":[
        {
            "category":"Shopping",
            "subcategory":"Bicycles & Sporting Goods",
            "type":"Retail Goods"
        }
    ],
    "sg:phone":"+1 480 894 6397",
    "sg:postcode":"85281",
    "sg:province":"AZ",
    "wof:name":"Unique Gun Smithing",
    "wof:placetype":"venue"
},
  "geometry": {"coordinates":[-111.896129,33.413705],"type":"Point"}
}