{
  "type": "Feature",
  "properties": {
    "iso:country":"US",
    "sg:address":"8151 E Main St",
    "sg:city":"Mesa",
    "sg:classifiers":[
        {
            "category":"Shopping",
            "subcategory":"Used Merchandise",
            "type":"Retail Goods"
        },
        {
            "category":"Shopping",
            "subcategory":"Jewelry",
            "type":"Retail Goods"
        }
    ],
    "sg:phone":"+1 480 964 6666",
    "sg:postcode":"85207",
    "sg:province":"AZ",
    "sg:tags":[
        "pawnbroker",
        "jeweler"
    ],
    "wof:name":"Pawns Plus",
    "wof:placetype":"venue"
},
  "geometry": {"coordinates":[-111.655419,33.415094],"type":"Point"}
}