{
  "type": "Feature",
  "properties": {
    "iso:country":"US",
    "sg:address":"1617 E Bethany Home Rd",
    "sg:city":"Phoenix",
    "sg:classifiers":[
        {
            "category":"Retail",
            "subcategory":"Veterinary Services",
            "type":"Services"
        }
    ],
    "sg:phone":"+1 602 265 4101",
    "sg:postcode":"85016",
    "sg:province":"AZ",
    "sg:tags":[
        "veterinarian"
    ],
    "wof:name":"Dreamy Draw Cat Hospital",
    "wof:placetype":"venue"
},
  "geometry": {"coordinates":[-112.04656199999999,33.523762],"type":"Point"}
}