{
  "type": "Feature",
  "properties": {
    "iso:country":"US",
    "sg:address":"7349 Martin Dr",
    "sg:city":"Mohave Valley",
    "sg:classifiers":[
        {
            "category":"Professional",
            "subcategory":"Business Services",
            "type":"Services"
        }
    ],
    "sg:phone":"+1 928 768 1145",
    "sg:postcode":"86440",
    "sg:province":"AZ",
    "sg:tags":[
        "notary"
    ],
    "wof:name":"Notary Dar",
    "wof:placetype":"venue"
},
  "geometry": {"coordinates":[-114.578005,34.946018],"type":"Point"}
}