{
  "type": "Feature",
  "properties": {
    "addr:full":"517 W Monte Way Phoenix AZ 85041",
    "addr:housenumber":"517",
    "addr:postcode":"85041",
    "addr:street":"W Monte Way",
    "iso:country":"US",
    "sg:address":"517 W Monte Way",
    "sg:city":"Phoenix",
    "sg:classifiers":[
        {
            "category":"Building & Trades",
            "subcategory":"Landscaping Services",
            "type":"Services"
        }
    ],
    "sg:phone":"+1 602 268 6323",
    "sg:postcode":"85041",
    "sg:province":"AZ",
    "wof:name":"Jorges Lawn & Maintenance",
    "wof:placetype":"venue"
},
  "geometry": {"coordinates":[-112.082088,33.360381],"type":"Point"}
}