{
  "type": "Feature",
  "properties": {
    "addr:full":"3501 E Lockett Rd Flagstaff AZ 86004",
    "addr:housenumber":"3501",
    "addr:postcode":"86004",
    "addr:street":"E Lockett Rd",
    "iso:country":"US",
    "sg:address":"3501 E Lockett Rd",
    "sg:city":"Flagstaff",
    "sg:classifiers":[
        {
            "category":"Travel",
            "subcategory":"Hotels & Motels",
            "type":"Entertainment"
        }
    ],
    "sg:phone":"+1 928 526 1885",
    "sg:postcode":"86004",
    "sg:province":"AZ",
    "wof:name":"Hampton Inn",
    "wof:placetype":"venue"
},
  "geometry": {"coordinates":[-111.597814,35.2185],"type":"Point"}
}