{
  "type": "Feature",
  "properties": {
    "iso:country":"US",
    "sg:address":"1051 W University Dr",
    "sg:city":"Tempe",
    "sg:classifiers":[
        {
            "category":"Utilities",
            "subcategory":"Telephone",
            "type":"Services"
        },
        {
            "category":"Communications",
            "type":"Services"
        }
    ],
    "sg:phone":"+1 480 894 3346",
    "sg:postcode":"85281",
    "sg:province":"AZ",
    "sg:tags":[
        "equipment-servicing",
        "systems-repair",
        "answering",
        "system",
        "equipment"
    ],
    "wof:name":"Tonal Center",
    "wof:placetype":"venue"
},
  "geometry": {"coordinates":[-111.953267,33.421907],"type":"Point"}
}