{
  "type": "Feature",
  "properties": {
    "iso:country":"US",
    "sg:address":"2240 N Floyd Dr",
    "sg:city":"Mesa",
    "sg:classifiers":[
        {
            "category":"Professional",
            "type":"Services"
        }
    ],
    "sg:phone":"+1 480 981 2946",
    "sg:postcode":"85215",
    "sg:province":"AZ",
    "wof:name":"Waldo A Ballhorn",
    "wof:placetype":"venue"
},
  "geometry": {"coordinates":[-111.71511,33.456594],"type":"Point"}
}