{
  "type": "Feature",
  "properties": {
    "addr:full":"2560 E 16th St Yuma AZ 85365",
    "addr:housenumber":"2560",
    "addr:postcode":"85365",
    "addr:street":"E 16Th St",
    "iso:country":"US",
    "sg:address":"2560 E 16th St",
    "sg:city":"Yuma",
    "sg:classifiers":[
        {
            "category":"Building & Trades",
            "subcategory":"Construction",
            "type":"Services"
        }
    ],
    "sg:phone":"+1 928 783 6387",
    "sg:postcode":"85365",
    "sg:province":"AZ",
    "sg:tags":[
        "plastering",
        "coating",
        "contractor",
        "exterior",
        "drywall",
        "stucco"
    ],
    "sg:website":"http://www.kenyonweb.com",
    "wof:name":"Kenyon Plastering Inc",
    "wof:placetype":"venue"
},
  "geometry": {"coordinates":[-114.559119,32.698938],"type":"Point"}
}