{
  "type": "Feature",
  "properties": {
    "iso:country":"US",
    "sg:address":"3710 N Larrea Ln",
    "sg:city":"Tucson",
    "sg:classifiers":[
        {
            "category":"Restaurant",
            "type":"Food & Drink"
        }
    ],
    "sg:phone":"+1 520 886 7365",
    "sg:postcode":"85750",
    "sg:province":"AZ",
    "sg:tags":[
        "eating"
    ],
    "wof:name":"Simply Delicious",
    "wof:placetype":"venue"
},
  "geometry": {"coordinates":[-110.815111,32.274879],"type":"Point"}
}