{
  "type": "Feature",
  "properties": {
    "iso:country":"US",
    "sg:address":"2044 E Mitchell Dr",
    "sg:city":"Phoenix",
    "sg:classifiers":[
        {
            "category":"Professional",
            "subcategory":"Engineering",
            "type":"Services"
        }
    ],
    "sg:phone":"+1 602 272 1424",
    "sg:postcode":"85016",
    "sg:province":"AZ",
    "sg:tags":[
        "refrigeration",
        "engineer"
    ],
    "wof:name":"Miluca Refrigeration",
    "wof:placetype":"venue"
},
  "geometry": {"coordinates":[-112.038839,33.488415],"type":"Point"}
}