{
  "type": "Feature",
  "properties": {
    "addr:full":"12636 N 2nd St Phoenix AZ 85022",
    "addr:housenumber":"12636",
    "addr:postcode":"85022",
    "addr:street":"N 2Nd St",
    "iso:country":"US",
    "sg:address":"12636 N 2nd St",
    "sg:city":"Phoenix",
    "sg:classifiers":[
        {
            "category":"Building & Trades",
            "subcategory":"Construction",
            "type":"Services"
        }
    ],
    "sg:phone":"+1 602 997 2204",
    "sg:postcode":"85022",
    "sg:province":"AZ",
    "sg:tags":[
        "concrete",
        "staining",
        "contractor"
    ],
    "wof:name":"Caseys Custom Concrete Inc",
    "wof:placetype":"venue"
},
  "geometry": {"coordinates":[-112.072085,33.601953],"type":"Point"}
}