{
  "type": "Feature",
  "properties": {
    "addr:full":"6190 Bradley Dr Mohave Valley AZ 86440",
    "addr:housenumber":"6190",
    "addr:postcode":"86440",
    "addr:street":"Bradley Dr",
    "iso:country":"US",
    "sg:address":"6190 Bradley Dr",
    "sg:city":"Mohave Valley",
    "sg:classifiers":[
        {
            "category":"Shopping",
            "subcategory":"Clothing, Apparel, & Fashions",
            "type":"Retail Goods"
        }
    ],
    "sg:phone":"+1 928 768 3625",
    "sg:postcode":"86440",
    "sg:province":"AZ",
    "wof:name":"Creations By Hayseeds",
    "wof:placetype":"venue"
},
  "geometry": {"coordinates":[-114.54075899999999,34.977602],"type":"Point"}
}