{
  "type": "Feature",
  "properties": {
    "iso:country":"US",
    "sg:address":"2234 E Yale St",
    "sg:city":"Phoenix",
    "sg:classifiers":[
        {
            "category":"Organizations",
            "subcategory":"Religious Organization",
            "type":"Services"
        }
    ],
    "sg:phone":"+1 928 244 1254",
    "sg:postcode":"85006",
    "sg:province":"AZ",
    "sg:tags":[
        "church"
    ],
    "wof:name":"Phoenix Tenrikyo Fellowship",
    "wof:placetype":"venue"
},
  "geometry": {"coordinates":[-112.03302,33.475826],"type":"Point"}
}