{
  "type": "Feature",
  "properties": {
    "addr:full":"1900 N 2nd Ave Ajo AZ 85321",
    "addr:housenumber":"1900",
    "addr:postcode":"85321",
    "addr:street":"N 2Nd Ave",
    "iso:country":"US",
    "sg:address":"1900 N 2nd Ave",
    "sg:city":"Ajo",
    "sg:classifiers":[
        {
            "category":"Organizations",
            "subcategory":"Religious Organization",
            "type":"Services"
        }
    ],
    "sg:phone":"+1 520 387 3537",
    "sg:postcode":"85321",
    "sg:province":"AZ",
    "sg:tags":[
        "church"
    ],
    "wof:name":"Full Gospel Fellowship",
    "wof:placetype":"venue"
},
  "geometry": {"coordinates":[-112.872152,32.389623],"type":"Point"}
}