{
  "type": "Feature",
  "properties": {
    "iso:country":"US",
    "sg:address":"607 N Circle Dr",
    "sg:city":"Benson",
    "sg:classifiers":[
        {
            "category":"Building & Trades",
            "subcategory":"Construction",
            "type":"Services"
        }
    ],
    "sg:phone":"+1 520 586 3338",
    "sg:postcode":"85602",
    "sg:province":"AZ",
    "sg:tags":[
        "painter"
    ],
    "wof:name":"Colony Painting",
    "wof:placetype":"venue"
},
  "geometry": {"coordinates":[-110.294344,31.974725],"type":"Point"}
}