{
  "type": "Feature",
  "properties": {
    "iso:country":"US",
    "sg:address":"5665 E Speedway Blvd",
    "sg:city":"Tucson",
    "sg:classifiers":[
        {
            "category":"Shopping",
            "subcategory":"Clothing, Apparel, & Fashions",
            "type":"Retail Goods"
        }
    ],
    "sg:phone":"+1 520 795 2400",
    "sg:postcode":"85712",
    "sg:province":"AZ",
    "sg:tags":[
        "wear",
        "furniture"
    ],
    "wof:name":"Aldrich Baby News Inc",
    "wof:placetype":"venue"
},
  "geometry": {"coordinates":[-110.872221,32.236254],"type":"Point"}
}