{
  "type": "Feature",
  "properties": {
    "iso:country":"US",
    "sg:address":"2415 E Camelback Rd # 700",
    "sg:city":"Phoenix",
    "sg:classifiers":[
        {
            "category":"Professional",
            "subcategory":"Accounting & Tax Preparation",
            "type":"Services"
        }
    ],
    "sg:phone":"+1 602 508 6056",
    "sg:postcode":"85016",
    "sg:province":"AZ",
    "sg:tags":[
        "public",
        "accountants-certified"
    ],
    "wof:name":"Rivers & Moorhead Plcc",
    "wof:placetype":"venue"
},
  "geometry": {"coordinates":[-112.029034,33.509245],"type":"Point"}
}