{
  "type": "Feature",
  "properties": {
    "addr:full":"3308 E Madison St Phoenix AZ 85034",
    "addr:housenumber":"3308",
    "addr:postcode":"85034",
    "addr:street":"E Madison St",
    "iso:country":"US",
    "sg:address":"3308 E Madison St",
    "sg:city":"Phoenix",
    "sg:classifiers":[
        {
            "category":"Building & Trades",
            "subcategory":"Construction",
            "type":"Services"
        },
        {
            "category":"Building & Trades",
            "subcategory":"Plumbing",
            "type":"Services"
        }
    ],
    "sg:phone":"+1 602 244 8994",
    "sg:postcode":"85034",
    "sg:province":"AZ",
    "sg:tags":[
        "sheet",
        "work",
        "metal",
        "contractor"
    ],
    "sg:website":"www.ramirezmechanical.com",
    "wof:name":"Ramirez Mechanical Systems Inc",
    "wof:placetype":"venue"
},
  "geometry": {"coordinates":[-112.007586,33.446227],"type":"Point"}
}