{
  "type": "Feature",
  "properties": {
    "addr:full":"409 E Baffert Dr Nogales AZ 85621",
    "addr:housenumber":"409",
    "addr:postcode":"85621",
    "addr:street":"E Baffert Dr",
    "iso:country":"US",
    "sg:address":"409 E Baffert Dr",
    "sg:city":"Nogales",
    "sg:classifiers":[
        {
            "category":"Food & Beverages",
            "subcategory":"Groceries & Convenience Stores",
            "type":"Retail Goods"
        }
    ],
    "sg:phone":"+1 520 281 5775",
    "sg:postcode":"85621",
    "sg:province":"AZ",
    "sg:tags":[
        "grocer",
        "super",
        "supermarket"
    ],
    "wof:name":"Nogales Market 2",
    "wof:placetype":"venue"
},
  "geometry": {"coordinates":[-110.924165,31.372024],"type":"Point"}
}