{
  "type": "Feature",
  "properties": {
    "iso:country":"US",
    "sg:address":"2120 E Rose Garden Ln",
    "sg:city":"Phoenix",
    "sg:classifiers":[
        {
            "category":"Retail",
            "subcategory":"Auto Repair",
            "type":"Services"
        }
    ],
    "sg:phone":"+1 602 380 7005",
    "sg:postcode":"85024",
    "sg:province":"AZ",
    "sg:tags":[
        "repairing",
        "automobile"
    ],
    "wof:name":"Atchinson Automotive Inc",
    "wof:placetype":"venue"
},
  "geometry": {"coordinates":[-112.036762,33.676879],"type":"Point"}
}