{
  "type": "Feature",
  "properties": {
    "iso:country":"US",
    "sg:address":"4205 E Chaparosa Way",
    "sg:city":"Cave Creek",
    "sg:classifiers":[
        {
            "category":"Shopping",
            "subcategory":"Catalog Store",
            "type":"Retail Goods"
        }
    ],
    "sg:phone":"+1 480 473 9859",
    "sg:postcode":"85331",
    "sg:province":"AZ",
    "sg:tags":[
        "mail",
        "house"
    ],
    "wof:name":"W Meyers Enterprises",
    "wof:placetype":"venue"
},
  "geometry": {"coordinates":[-111.99226,33.768528],"type":"Point"}
}