{
  "type": "Feature",
  "properties": {
    "addr:full":"23630 N 89th Ave Peoria AZ 85383",
    "addr:housenumber":"23630",
    "addr:postcode":"85383",
    "addr:street":"N 89Th Ave",
    "iso:country":"US",
    "sg:address":"23630 N 89th Ave",
    "sg:city":"Peoria",
    "sg:classifiers":[
        {
            "category":"Building & Trades",
            "subcategory":"Construction",
            "type":"Services"
        }
    ],
    "sg:phone":"+1 623 566 4622",
    "sg:postcode":"85383",
    "sg:province":"AZ",
    "sg:tags":[
        "contractor"
    ],
    "wof:name":"Russ Lemons Roofing",
    "wof:placetype":"venue"
},
  "geometry": {"coordinates":[-112.250829,33.698372],"type":"Point"}
}