{
  "type": "Feature",
  "properties": {
    "addr:full":"2231 E Camelback Rd Phoenix AZ 85016",
    "addr:housenumber":"2231",
    "addr:postcode":"85016",
    "addr:street":"E Camelback Rd",
    "iso:country":"US",
    "sg:address":"2231 E Camelback Rd",
    "sg:city":"Phoenix",
    "sg:classifiers":[
        {
            "category":"Travel",
            "subcategory":"Hotels & Motels",
            "type":"Entertainment"
        }
    ],
    "sg:phone":"+1 602 952 7119",
    "sg:postcode":"85016",
    "sg:province":"AZ",
    "wof:name":"Starwood Hotels & Resorts",
    "wof:placetype":"venue"
},
  "geometry": {"coordinates":[-112.033883,33.509214],"type":"Point"}
}