{
  "type": "Feature",
  "properties": {
    "addr:full":"4944 E Cascalote Dr Cave Creek AZ 85331",
    "addr:housenumber":"4944",
    "addr:postcode":"85331",
    "addr:street":"E Cascalote Dr",
    "iso:country":"US",
    "sg:address":"4944 E Cascalote Dr",
    "sg:city":"Cave Creek",
    "sg:classifiers":[
        {
            "category":"Professional",
            "subcategory":"Business Services",
            "type":"Services"
        }
    ],
    "sg:phone":"+1 480 502 8718",
    "sg:postcode":"85331",
    "sg:province":"AZ",
    "sg:tags":[
        "interior",
        "consultant",
        "design",
        "decorator"
    ],
    "wof:name":"Cynthia Brown & Assoc",
    "wof:placetype":"venue"
},
  "geometry": {"coordinates":[-111.97220900000001,33.7603],"type":"Point"}
}