{
  "type": "Feature",
  "properties": {
    "iso:country":"US",
    "sg:address":"1121 S Gilbert Rd Ste 104",
    "sg:city":"Mesa",
    "sg:classifiers":[
        {
            "category":"Health Services",
            "subcategory":"Dentist",
            "type":"Services"
        }
    ],
    "sg:phone":"+1 480 926 7363",
    "sg:postcode":"85204",
    "sg:province":"AZ",
    "sg:tags":[
        "dentists-pediatric",
        "dentistry"
    ],
    "wof:name":"Family Care Dentistry",
    "wof:placetype":"venue"
},
  "geometry": {"coordinates":[-111.788252,33.393689],"type":"Point"}
}