{
  "type": "Feature",
  "properties": {
    "addr:full":"7720 E Redfield Rd Scottsdale AZ 85260",
    "addr:housenumber":"7720",
    "addr:postcode":"85260",
    "addr:street":"E Redfield Rd",
    "iso:country":"US",
    "sg:address":"7720 E Redfield Rd",
    "sg:city":"Scottsdale",
    "sg:classifiers":[
        {
            "category":"Wholesale",
            "subcategory":"Durable Goods & Equipment",
            "type":"Manufacturing & Wholesale Goods"
        }
    ],
    "sg:phone":"+1 480 948 4448",
    "sg:postcode":"85260",
    "sg:province":"AZ",
    "sg:tags":[
        "instrument",
        "scientific",
        "apparatus"
    ],
    "sg:website":"www.sperscientific.com",
    "wof:name":"Sper Scientific Ltd",
    "wof:placetype":"venue"
},
  "geometry": {"coordinates":[-111.91219,33.614013],"type":"Point"}
}