{
  "type": "Feature",
  "properties": {
    "addr:full":"549 E Plaza Cir Litchfield Park AZ 85340",
    "addr:housenumber":"549",
    "addr:postcode":"85340",
    "addr:street":"E Plaza Cir",
    "iso:country":"US",
    "sg:address":"549 E Plaza Cir",
    "sg:city":"Litchfield Park",
    "sg:classifiers":[
        {
            "category":"Building & Trades",
            "subcategory":"Locksmith",
            "type":"Services"
        }
    ],
    "sg:phone":"+1 866 251 6462",
    "sg:postcode":"85340",
    "sg:province":"AZ",
    "sg:tags":[
        "key"
    ],
    "wof:name":"Anytime Anywhere Emergency Locksmith",
    "wof:placetype":"venue"
},
  "geometry": {"coordinates":[-112.35088500000001,33.486408],"type":"Point"}
}