{
  "type": "Feature",
  "properties": {
    "iso:country":"US",
    "sg:address":"1737 W Missouri Ave",
    "sg:city":"Phoenix",
    "sg:classifiers":[
        {
            "category":"Real Estate",
            "subcategory":"Real Estate Operator",
            "type":"Services"
        }
    ],
    "sg:phone":"+1 602 433 7660",
    "sg:postcode":"85015",
    "sg:province":"AZ",
    "sg:tags":[
        "building",
        "apartment"
    ],
    "wof:name":"Siena Village Apartments",
    "wof:placetype":"venue"
},
  "geometry": {"coordinates":[-112.09649,33.516819],"type":"Point"}
}