{
  "type": "Feature",
  "properties": {
    "iso:country":"US",
    "sg:address":"960 W University Dr",
    "sg:city":"Tempe",
    "sg:classifiers":[
        {
            "category":"Personal",
            "subcategory":"Beauty Salon",
            "type":"Services"
        }
    ],
    "sg:phone":"+1 480 557 9149",
    "sg:postcode":"85281",
    "sg:province":"AZ",
    "wof:name":"Spice It Up",
    "wof:placetype":"venue"
},
  "geometry": {"coordinates":[-111.951334,33.421994],"type":"Point"}
}