{
  "type": "Feature",
  "properties": {
    "iso:country":"US",
    "sg:address":"3808 E Camelback Rd",
    "sg:city":"Phoenix",
    "sg:classifiers":[
        {
            "category":"Professional",
            "subcategory":"Detective & Security Services",
            "type":"Services"
        }
    ],
    "sg:phone":"+1 602 955 2204",
    "sg:postcode":"85018",
    "sg:province":"AZ",
    "sg:tags":[
        "investigator"
    ],
    "wof:name":"EPI Insurance Svc Inc",
    "wof:placetype":"venue"
},
  "geometry": {"coordinates":[-111.997392,33.509944],"type":"Point"}
}