{
  "type": "Feature",
  "properties": {
    "iso:country":"US",
    "sg:address":"15025 N 8th Ave",
    "sg:city":"Phoenix",
    "sg:classifiers":[
        {
            "category":"Communications",
            "subcategory":"Film & Video Production",
            "type":"Services"
        }
    ],
    "sg:phone":"+1 602 942 9441",
    "sg:postcode":"85023",
    "sg:province":"AZ",
    "sg:tags":[
        "tv",
        "radio",
        "services-commercial",
        "companies-film"
    ],
    "wof:name":"Wakeford Productions",
    "wof:placetype":"venue"
},
  "geometry": {"coordinates":[-112.084222,33.622975],"type":"Point"}
}