{
  "type": "Feature",
  "properties": {
    "iso:country":"US",
    "sg:address":"10828 N 55th Dr",
    "sg:city":"Glendale",
    "sg:classifiers":[
        {
            "category":"Building & Trades",
            "subcategory":"Pest Control",
            "type":"Services"
        }
    ],
    "sg:phone":"+1 623 486 7661",
    "sg:postcode":"85304",
    "sg:province":"AZ",
    "wof:name":"Professional Exterminators",
    "wof:placetype":"venue"
},
  "geometry": {"coordinates":[-112.178129,33.584485],"type":"Point"}
}