{
  "type": "Feature",
  "properties": {
    "addr:full":"27817 N 160th St Scottsdale AZ 85262",
    "addr:housenumber":"27817",
    "addr:postcode":"85262",
    "addr:street":"N 160Th St",
    "iso:country":"US",
    "sg:address":"27817 N 160th St",
    "sg:city":"Scottsdale",
    "sg:classifiers":[
        {
            "category":"Insurance",
            "subcategory":"Insurance Agent",
            "type":"Services"
        }
    ],
    "sg:phone":"+1 480 471 1411",
    "sg:postcode":"85262",
    "sg:province":"AZ",
    "wof:name":"Structured Fincl Assoc Phoenix",
    "wof:placetype":"venue"
},
  "geometry": {"coordinates":[-111.734819,33.737361],"type":"Point"}
}