{
  "type": "Feature",
  "properties": {
    "iso:country":"US",
    "sg:address":"7245 S Harl Ave",
    "sg:city":"Tempe",
    "sg:classifiers":[
        {
            "category":"Retail",
            "subcategory":"Auto Repair",
            "type":"Services"
        }
    ],
    "sg:phone":"+1 480 730 5191",
    "sg:postcode":"85283",
    "sg:province":"AZ",
    "sg:tags":[
        "body",
        "automobile",
        "painting"
    ],
    "sg:website":"www.greulichs.com",
    "wof:name":"Greulich's Autobody",
    "wof:placetype":"venue"
},
  "geometry": {"coordinates":[-111.966413,33.353372],"type":"Point"}
}