{
  "type": "Feature",
  "properties": {
    "addr:full":"2107 W Broadway Rd Phoenix AZ 85041",
    "addr:housenumber":"2107",
    "addr:postcode":"85041",
    "addr:street":"W Broadway Rd",
    "iso:country":"US",
    "sg:address":"2107 W Broadway Rd",
    "sg:city":"Phoenix",
    "sg:classifiers":[
        {
            "category":"Real Estate",
            "subcategory":"Real Estate Operator",
            "type":"Services"
        }
    ],
    "sg:phone":"+1 480 898 8986",
    "sg:postcode":"85041",
    "sg:province":"AZ",
    "sg:tags":[
        "apartment"
    ],
    "wof:name":"Broadway Village Apartment",
    "wof:placetype":"venue"
},
  "geometry": {"coordinates":[-112.103075,33.406729],"type":"Point"}
}