{
  "type": "Feature",
  "properties": {
    "addr:full":"6140 N Bailey Ave Prescott AZ 86305",
    "addr:housenumber":"6140",
    "addr:postcode":"86305",
    "addr:street":"N Bailey Ave",
    "iso:country":"US",
    "sg:address":"6140 N Bailey Ave",
    "sg:city":"Prescott",
    "sg:classifiers":[
        {
            "category":"Building & Trades",
            "subcategory":"Construction",
            "type":"Services"
        }
    ],
    "sg:phone":"+1 928 771 8754",
    "sg:postcode":"86305",
    "sg:province":"AZ",
    "sg:tags":[
        "house"
    ],
    "wof:name":"Clyde Detweiler Construction",
    "wof:placetype":"venue"
},
  "geometry": {"coordinates":[-112.48396,34.630876],"type":"Point"}
}