{
  "type": "Feature",
  "properties": {
    "addr:full":"81 E Deuce of Clubs Show Low AZ 85901",
    "addr:housenumber":"81",
    "addr:postcode":"85901",
    "addr:street":"E Deuce Of Clubs",
    "iso:country":"US",
    "sg:address":"81 E Deuce of Clubs",
    "sg:city":"Show Low",
    "sg:classifiers":[
        {
            "category":"Organizations",
            "subcategory":"Professional Association",
            "type":"Services"
        }
    ],
    "sg:phone":"+1 928 537 2326",
    "sg:postcode":"85901",
    "sg:province":"AZ",
    "sg:tags":[
        "chambers",
        "commerce"
    ],
    "wof:name":"Show Low Chamber Of Commerce",
    "wof:placetype":"venue"
},
  "geometry": {"coordinates":[-110.040245,34.251567],"type":"Point"}
}