{
  "type": "Feature",
  "properties": {
    "iso:country":"US",
    "sg:address":"2602 W Lone Cactus Dr 1",
    "sg:city":"Phoenix",
    "sg:classifiers":[
        {
            "category":"Building & Trades",
            "subcategory":"Construction",
            "type":"Services"
        }
    ],
    "sg:phone":"+1 623 780 1771",
    "sg:postcode":"85027",
    "sg:province":"AZ",
    "sg:tags":[
        "excavation",
        "contractor"
    ],
    "wof:name":"Dirt Pro Contracting, Inc.",
    "wof:placetype":"venue"
},
  "geometry": {"coordinates":[-112.11413,33.679829],"type":"Point"}
}