{
  "type": "Feature",
  "properties": {
    "addr:full":"4181 E Glenn Rd Sierra Vista AZ 85650",
    "addr:housenumber":"4181",
    "addr:postcode":"85650",
    "addr:street":"E Glenn Rd",
    "iso:country":"US",
    "sg:address":"4181 E Glenn Rd",
    "sg:city":"Sierra Vista",
    "sg:classifiers":[
        {
            "category":"Shopping",
            "type":"Retail Goods"
        }
    ],
    "sg:phone":"+1 520 378 6666",
    "sg:postcode":"85650",
    "sg:province":"AZ",
    "sg:tags":[
        "pet",
        "food",
        "supply"
    ],
    "wof:name":"Coronado Veterinary Clinic",
    "wof:placetype":"venue"
},
  "geometry": {"coordinates":[-110.255571,31.49642],"type":"Point"}
}