{
  "type": "Feature",
  "properties": {
    "iso:country":"US",
    "sg:address":"1282 N Bedford Dr",
    "sg:city":"Chandler",
    "sg:classifiers":[
        {
            "category":"Real Estate",
            "subcategory":"Real Estate Agent",
            "type":"Services"
        }
    ],
    "sg:phone":"+1 480 963 7330",
    "sg:postcode":"85225",
    "sg:province":"AZ",
    "wof:name":"H J N Enterprises Inc",
    "wof:placetype":"venue"
},
  "geometry": {"coordinates":[-111.821059,33.326408],"type":"Point"}
}