{
  "type": "Feature",
  "properties": {
    "addr:full":"4732 N Oracle Rd Tucson AZ 85705",
    "addr:housenumber":"4732",
    "addr:postcode":"85705",
    "addr:street":"N Oracle Rd",
    "iso:country":"US",
    "sg:address":"4732 N Oracle Rd",
    "sg:city":"Tucson",
    "sg:classifiers":[
        {
            "category":"Health Services",
            "subcategory":"Health Practitioner",
            "type":"Services"
        }
    ],
    "sg:phone":"+1 520 887 0985",
    "sg:postcode":"85705",
    "sg:province":"AZ",
    "sg:tags":[
        "psychologist"
    ],
    "wof:name":"PBSI-Behavioral Health",
    "wof:placetype":"venue"
},
  "geometry": {"coordinates":[-110.978199,32.29328],"type":"Point"}
}