{
  "type": "Feature",
  "properties": {
    "iso:country":"US",
    "sg:address":"10835 E Covina St",
    "sg:city":"Mesa",
    "sg:classifiers":[
        {
            "category":"Manufacturing",
            "subcategory":"Jewelry",
            "type":"Manufacturing & Wholesale Goods"
        }
    ],
    "sg:phone":"+1 480 354 3066",
    "sg:postcode":"85207",
    "sg:province":"AZ",
    "wof:name":"Designs By Paula",
    "wof:placetype":"venue"
},
  "geometry": {"coordinates":[-111.59688800000001,33.424352],"type":"Point"}
}