{
  "type": "Feature",
  "properties": {
    "iso:country":"US",
    "sg:address":"3111 E 2nd St",
    "sg:city":"Tucson",
    "sg:classifiers":[
        {
            "category":"Building & Trades",
            "subcategory":"Construction",
            "type":"Services"
        },
        {
            "category":"Real Estate",
            "subcategory":"Real Estate Operator",
            "type":"Services"
        }
    ],
    "sg:phone":"+1 520 882 0885",
    "sg:postcode":"85716",
    "sg:province":"AZ",
    "sg:tags":[
        "carpentry",
        "parks",
        "contractor"
    ],
    "wof:name":"Johnson-Manley Lumber Company",
    "wof:placetype":"venue"
},
  "geometry": {"coordinates":[-110.925334,32.23431],"type":"Point"}
}