{
  "type": "Feature",
  "properties": {
    "iso:country":"US",
    "sg:address":"7848 E Redfield Rd",
    "sg:city":"Scottsdale",
    "sg:classifiers":[
        {
            "category":"Home & Garden",
            "subcategory":"Furniture",
            "type":"Retail Goods"
        }
    ],
    "sg:phone":"+1 480 951 8737",
    "sg:postcode":"85260",
    "sg:province":"AZ",
    "wof:name":"Containers International",
    "wof:placetype":"venue"
},
  "geometry": {"coordinates":[-111.915097,33.614028],"type":"Point"}
}