{
  "type": "Feature",
  "properties": {
    "iso:country":"US",
    "sg:address":"8550 N Mulberry Pl",
    "sg:city":"Tucson",
    "sg:classifiers":[
        {
            "category":"Building & Trades",
            "subcategory":"Landscaping Services",
            "type":"Services"
        }
    ],
    "sg:phone":"+1 520 544 0622",
    "sg:postcode":"85704",
    "sg:province":"AZ",
    "sg:tags":[
        "landscape"
    ],
    "wof:name":"Rose Landscape Inc",
    "wof:placetype":"venue"
},
  "geometry": {"coordinates":[-110.99420000000001,32.360956],"type":"Point"}
}