{
  "type": "Feature",
  "properties": {
    "addr:full":"21024 N 74th Pl Scottsdale AZ 85255",
    "addr:housenumber":"21024",
    "addr:postcode":"85255",
    "addr:street":"N 74Th Pl",
    "iso:country":"US",
    "sg:address":"21024 N 74th Pl",
    "sg:city":"Scottsdale",
    "sg:classifiers":[
        {
            "category":"Professional",
            "subcategory":"Lawyer & Legal Services",
            "type":"Services"
        }
    ],
    "sg:phone":"+1 480 585 3738",
    "sg:postcode":"85255",
    "sg:province":"AZ",
    "sg:tags":[
        "attorney"
    ],
    "wof:name":"Gregory A Gienko",
    "wof:placetype":"venue"
},
  "geometry": {"coordinates":[-111.920784,33.677282],"type":"Point"}
}