{
  "type": "Feature",
  "properties": {
    "iso:country":"US",
    "sg:address":"7515 E Edison St",
    "sg:city":"Tucson",
    "sg:classifiers":[
        {
            "category":"Shopping",
            "subcategory":"Gifts & Souvenirs",
            "type":"Retail Goods"
        }
    ],
    "sg:phone":"+1 520 886 1697",
    "sg:postcode":"85715",
    "sg:province":"AZ",
    "wof:name":"K S Wickey",
    "wof:placetype":"venue"
},
  "geometry": {"coordinates":[-110.830526,32.248564],"type":"Point"}
}