{
  "type": "Feature",
  "properties": {
    "addr:full":"7515 E Edison St Tucson AZ 85715",
    "addr:housenumber":"7515",
    "addr:postcode":"85715",
    "addr:street":"E Edison St",
    "iso:country":"US",
    "sg:address":"7515 E Edison St",
    "sg:city":"Tucson",
    "sg:classifiers":[
        {
            "category":"Shopping",
            "subcategory":"Gifts & Souvenirs",
            "type":"Retail Goods"
        }
    ],
    "sg:phone":"+1 520 886 1697",
    "sg:postcode":"85715",
    "sg:province":"AZ",
    "wof:name":"K S Wickey",
    "wof:placetype":"venue"
},
  "geometry": {"coordinates":[-110.83052600000001,32.248564],"type":"Point"}
}