{
  "type": "Feature",
  "properties": {
    "iso:country":"US",
    "sg:address":"8144 N 29th Ave",
    "sg:city":"Phoenix",
    "sg:classifiers":[
        {
            "category":"Shopping",
            "type":"Retail Goods"
        }
    ],
    "sg:phone":"+1 602 973 1700",
    "sg:postcode":"85051",
    "sg:province":"AZ",
    "sg:tags":[
        "cosmetic",
        "perfume"
    ],
    "wof:name":"Jafra USA Ce",
    "wof:placetype":"venue"
},
  "geometry": {"coordinates":[-112.121349,33.556517],"type":"Point"}
}