{
  "type": "Feature",
  "properties": {
    "iso:country":"US",
    "sg:address":"2929 N 75th Avenue",
    "sg:city":"Phoenix",
    "sg:classifiers":[
        {
            "category":"Retail",
            "subcategory":"Laundry & Dry Cleaning",
            "type":"Services"
        }
    ],
    "sg:phone":"+1 623 849 1209",
    "sg:postcode":"85033",
    "sg:province":"AZ",
    "wof:name":"Supermat",
    "wof:placetype":"venue"
},
  "geometry": {"coordinates":[-112.193242,33.483768],"type":"Point"}
}