{
  "type": "Feature",
  "properties": {
    "iso:country":"US",
    "sg:address":"2420 N Huachuca Dr",
    "sg:city":"Tucson",
    "sg:classifiers":[
        {
            "category":"Professional",
            "subcategory":"Management & Consulting",
            "type":"Services"
        }
    ],
    "sg:phone":"+1 520 623 3090",
    "sg:postcode":"85745",
    "sg:province":"AZ",
    "sg:tags":[
        "consultant",
        "mining"
    ],
    "wof:name":"Sage Associates",
    "wof:placetype":"venue"
},
  "geometry": {"coordinates":[-111.002185,32.253852],"type":"Point"}
}