{
  "type": "Feature",
  "properties": {
    "iso:country":"US",
    "sg:address":"1303 E Palomino Dr",
    "sg:city":"Tempe",
    "sg:classifiers":[
        {
            "category":"Professional",
            "type":"Services"
        }
    ],
    "sg:phone":"+1 480 752 2323",
    "sg:postcode":"85284",
    "sg:province":"AZ",
    "wof:name":"Alternatives In Espanol",
    "wof:placetype":"venue"
},
  "geometry": {"coordinates":[-111.91912600000001,33.337666],"type":"Point"}
}