{
  "type": "Feature",
  "properties": {
    "addr:full":"10503 W Thunderbird Blvd Sun City AZ 85351",
    "addr:housenumber":"10503",
    "addr:postcode":"85351",
    "addr:street":"W Thunderbird Blvd",
    "iso:country":"US",
    "sg:address":"10503 W Thunderbird Blvd",
    "sg:city":"Sun City",
    "sg:classifiers":[
        {
            "category":"Health Services",
            "subcategory":"Doctor",
            "type":"Services"
        }
    ],
    "sg:phone":"+1 623 876 2300",
    "sg:postcode":"85351",
    "sg:province":"AZ",
    "sg:tags":[
        "physician",
        "surgeon"
    ],
    "wof:name":"Northwest Valley Health Assoc",
    "wof:placetype":"venue"
},
  "geometry": {"coordinates":[-112.28652599999999,33.604966],"type":"Point"}
}