{
  "type": "Feature",
  "properties": {
    "addr:full":"3131 E Camelback Rd Phoenix AZ 85016",
    "addr:housenumber":"3131",
    "addr:postcode":"85016",
    "addr:street":"E Camelback Rd",
    "iso:country":"US",
    "sg:address":"3131 E Camelback Rd",
    "sg:city":"Phoenix",
    "sg:classifiers":[
        {
            "category":"Professional",
            "subcategory":"Business Services",
            "type":"Services"
        }
    ],
    "sg:phone":"+1 602 606 5700",
    "sg:postcode":"85016",
    "sg:province":"AZ",
    "sg:tags":[
        "paging",
        "answering"
    ],
    "sg:website":"www.hq.com",
    "wof:name":"HQ Global Workplaces",
    "wof:placetype":"venue"
},
  "geometry": {"coordinates":[-112.013769,33.509892],"type":"Point"}
}