{
  "type": "Feature",
  "properties": {
    "addr:full":"5969 W Bell Rd Glendale AZ 85308",
    "addr:housenumber":"5969",
    "addr:postcode":"85308",
    "addr:street":"W Bell Rd",
    "iso:country":"US",
    "sg:address":"5969 W Bell Rd",
    "sg:city":"Glendale",
    "sg:classifiers":[
        {
            "category":"Education",
            "subcategory":"Dance Studio",
            "type":"Public Place"
        }
    ],
    "sg:phone":"+1 602 547 0547",
    "sg:postcode":"85308",
    "sg:province":"AZ",
    "sg:tags":[
        "instruction",
        "dancing"
    ],
    "wof:name":"Spisak Dance Academy",
    "wof:placetype":"venue"
},
  "geometry": {"coordinates":[-112.189566,33.638596],"type":"Point"}
}