{
  "type": "Feature",
  "properties": {
    "addr:full":"1445 S Power Rd Mesa AZ 85206",
    "addr:housenumber":"1445",
    "addr:postcode":"85206",
    "addr:street":"S Power Rd",
    "iso:country":"US",
    "sg:address":"1445 S Power Rd",
    "sg:city":"Mesa",
    "sg:classifiers":[
        {
            "category":"Shopping",
            "subcategory":"Department Store",
            "type":"Retail Goods"
        }
    ],
    "sg:phone":"+1 480 985 8448",
    "sg:postcode":"85206",
    "sg:province":"AZ",
    "sg:tags":[
        "laboratory",
        "eating",
        "re"
    ],
    "wof:name":"Kmart",
    "wof:placetype":"venue"
},
  "geometry": {"coordinates":[-111.684714,33.388415],"type":"Point"}
}