{
  "type": "Feature",
  "properties": {
    "addr:full":"4635 W Mcdowell Rd Ste 110 Phoenix AZ 85035",
    "addr:housenumber":"4635",
    "addr:postcode":"85035",
    "addr:street":"W Mcdowell Rd Ste 110",
    "iso:country":"US",
    "sg:address":"4635 W Mcdowell Rd Ste 110",
    "sg:city":"Phoenix",
    "sg:classifiers":[
        {
            "category":"Shopping",
            "subcategory":"Books",
            "type":"Retail Goods"
        }
    ],
    "sg:phone":"+1 602 484 0894",
    "sg:postcode":"85035",
    "sg:province":"AZ",
    "sg:tags":[
        "store"
    ],
    "wof:name":"Distributech",
    "wof:placetype":"venue"
},
  "geometry": {"coordinates":[-112.15882499999999,33.465974],"type":"Point"}
}