{
  "type": "Feature",
  "properties": {
    "addr:full":"465 W Gila Bend Hwy Casa Grande AZ 85222",
    "addr:housenumber":"465",
    "addr:postcode":"85222",
    "addr:street":"W Gila Bend Hwy",
    "iso:country":"US",
    "sg:address":"465 W Gila Bend Hwy",
    "sg:city":"Casa Grande",
    "sg:classifiers":[
        {
            "category":"Shopping",
            "subcategory":"Gifts & Souvenirs",
            "type":"Retail Goods"
        }
    ],
    "sg:phone":"+1 520 426 9222",
    "sg:postcode":"85222",
    "sg:province":"AZ",
    "wof:name":"The Ark",
    "wof:placetype":"venue"
},
  "geometry": {"coordinates":[-111.766677,32.879394],"type":"Point"}
}