{
  "type": "Feature",
  "properties": {
    "iso:country":"US",
    "sg:address":"7904 E Chaparral Rd",
    "sg:city":"Scottsdale",
    "sg:classifiers":[
        {
            "category":"Transit Center",
            "subcategory":"Freight",
            "type":"Transportation"
        }
    ],
    "sg:phone":"+1 602 416 1295",
    "sg:postcode":"85250",
    "sg:province":"AZ",
    "sg:tags":[
        "container",
        "broker"
    ],
    "wof:name":"Montgomery Freight Solutions",
    "wof:placetype":"venue"
},
  "geometry": {"coordinates":[-111.910867,33.509402],"type":"Point"}
}