{
  "type": "Feature",
  "properties": {
    "addr:full":"5120 W Bethany Home Rd Glendale AZ 85301",
    "addr:housenumber":"5120",
    "addr:postcode":"85301",
    "addr:street":"W Bethany Home Rd",
    "iso:country":"US",
    "sg:address":"5120 W Bethany Home Rd",
    "sg:city":"Glendale",
    "sg:classifiers":[
        {
            "category":"Building & Trades",
            "subcategory":"Construction",
            "type":"Services"
        }
    ],
    "sg:phone":"+1 623 463 0638",
    "sg:postcode":"85301",
    "sg:province":"AZ",
    "sg:tags":[
        "contractor"
    ],
    "wof:name":"Superior Pool Plastering Inc",
    "wof:placetype":"venue"
},
  "geometry": {"coordinates":[-112.169635,33.524046],"type":"Point"}
}