{
  "type": "Feature",
  "properties": {
    "iso:country":"US",
    "sg:address":"4955 W Joyce Cir",
    "sg:city":"Glendale",
    "sg:classifiers":[
        {
            "category":"Building & Trades",
            "subcategory":"Electrical",
            "type":"Services"
        }
    ],
    "sg:phone":"+1 602 938 9773",
    "sg:postcode":"85308",
    "sg:province":"AZ",
    "sg:tags":[
        "industrial",
        "electrician",
        "contractors-commercial",
        "electric"
    ],
    "wof:name":"Shane Electric Inc",
    "wof:placetype":"venue"
},
  "geometry": {"coordinates":[-112.166425,33.640512],"type":"Point"}
}