{
  "type": "Feature",
  "properties": {
    "iso:country":"US",
    "sg:address":"8525 E Pinnacle Peak Rd",
    "sg:city":"Scottsdale",
    "sg:classifiers":[
        {
            "category":"Banks & Credit Unions",
            "subcategory":"Investment Brokerage",
            "type":"Services"
        }
    ],
    "sg:phone":"+1 888 200 1588",
    "sg:postcode":"85255",
    "sg:province":"AZ",
    "sg:tags":[
        "security"
    ],
    "wof:name":"UBS Financial Services Inc",
    "wof:placetype":"venue"
},
  "geometry": {"coordinates":[-111.894507,33.698603],"type":"Point"}
}