{
  "type": "Feature",
  "properties": {
    "addr:full":"1120 S Gilbert Rd Ste 102 Gilbert AZ 85296",
    "addr:housenumber":"1120",
    "addr:postcode":"85296",
    "addr:street":"S Gilbert Rd Ste 102",
    "iso:country":"US",
    "sg:address":"1120 S Gilbert Rd Ste 102",
    "sg:city":"Gilbert",
    "sg:classifiers":[
        {
            "category":"Real Estate",
            "subcategory":"Developer",
            "type":"Services"
        }
    ],
    "sg:phone":"+1 480 890 0555",
    "sg:postcode":"85296",
    "sg:province":"AZ",
    "sg:website":"http://www.danapark.com",
    "wof:name":"Dana Park",
    "wof:placetype":"venue"
},
  "geometry": {"coordinates":[-111.78990899999999,33.328076],"type":"Point"}
}