{
  "type": "Feature",
  "properties": {
    "addr:full":"141 E Kaler Dr Phoenix AZ 85020",
    "addr:housenumber":"141",
    "addr:postcode":"85020",
    "addr:street":"E Kaler Dr",
    "iso:country":"US",
    "sg:address":"141 E Kaler Dr",
    "sg:city":"Phoenix",
    "sg:classifiers":[
        {
            "category":"Insurance",
            "subcategory":"Insurance Agent",
            "type":"Services"
        }
    ],
    "sg:phone":"+1 602 870 3203",
    "sg:postcode":"85020",
    "sg:province":"AZ",
    "wof:name":"Republic Mortgage Insurance Co",
    "wof:placetype":"venue"
},
  "geometry": {"coordinates":[-112.070168,33.5477],"type":"Point"}
}