{
  "type": "Feature",
  "properties": {
    "iso:country":"US",
    "sg:address":"4957 W Onyx Ave",
    "sg:city":"Glendale",
    "sg:classifiers":[
        {
            "category":"Manufacturing",
            "subcategory":"Food",
            "type":"Manufacturing & Wholesale Goods"
        }
    ],
    "sg:phone":"+1 623 931 4687",
    "sg:postcode":"85302",
    "sg:province":"AZ",
    "sg:tags":[
        "drink",
        "soft",
        "mfg"
    ],
    "wof:name":"Sun West Bottlers L L C",
    "wof:placetype":"venue"
},
  "geometry": {"coordinates":[-112.165514,33.576876],"type":"Point"}
}