{
  "type": "Feature",
  "properties": {
    "addr:full":"10 W Southern Ave Mesa AZ 85210",
    "addr:housenumber":"10",
    "addr:postcode":"85210",
    "addr:street":"W Southern Ave",
    "iso:country":"US",
    "sg:address":"10 W Southern Ave",
    "sg:city":"Mesa",
    "sg:classifiers":[
        {
            "category":"Autos & Motor Vehicles",
            "subcategory":"Auto Supplies",
            "type":"Retail Goods"
        }
    ],
    "sg:phone":"+1 480 834 1847",
    "sg:postcode":"85210",
    "sg:province":"AZ",
    "sg:tags":[
        "tire"
    ],
    "wof:name":"Kenny Speeds Tire",
    "wof:placetype":"venue"
},
  "geometry": {"coordinates":[-111.83199399999999,33.393406],"type":"Point"}
}