{
  "type": "Feature",
  "properties": {
    "iso:country":"US",
    "sg:address":"4216 N 7th Ave",
    "sg:city":"Phoenix",
    "sg:classifiers":[
        {
            "category":"Professional",
            "subcategory":"Art Services",
            "type":"Services"
        }
    ],
    "sg:phone":"+1 602 466 2736",
    "sg:postcode":"85013",
    "sg:province":"AZ",
    "sg:tags":[
        "commercial",
        "artist"
    ],
    "wof:name":"Lucky Number Fifteen Paper",
    "wof:placetype":"venue"
},
  "geometry": {"coordinates":[-112.083513,33.497214],"type":"Point"}
}