{
  "type": "Feature",
  "properties": {
    "addr:full":"7440 W Cactus Rd Peoria AZ 85381",
    "addr:housenumber":"7440",
    "addr:postcode":"85381",
    "addr:street":"W Cactus Rd",
    "iso:country":"US",
    "sg:address":"7440 W Cactus Rd",
    "sg:city":"Peoria",
    "sg:classifiers":[
        {
            "category":"Real Estate",
            "subcategory":"Real Estate Agent",
            "type":"Services"
        }
    ],
    "sg:phone":"+1 623 337 5702",
    "sg:postcode":"85381",
    "sg:province":"AZ",
    "wof:name":"Acosta New Horizon Realty",
    "wof:placetype":"venue"
},
  "geometry": {"coordinates":[-112.21825200000001,33.595977],"type":"Point"}
}