{
  "type": "Feature",
  "properties": {
    "addr:full":"3438 W 1st St Thatcher AZ 85552",
    "addr:housenumber":"3438",
    "addr:postcode":"85552",
    "addr:street":"W 1St St",
    "iso:country":"US",
    "sg:address":"3438 W 1st St",
    "sg:city":"Thatcher",
    "sg:classifiers":[
        {
            "category":"Travel",
            "subcategory":"Hotels & Motels",
            "type":"Entertainment"
        }
    ],
    "sg:phone":"+1 928 428 6481",
    "sg:postcode":"85552",
    "sg:province":"AZ",
    "sg:tags":[
        "ranch",
        "guest"
    ],
    "wof:name":"Black Rock Ranch Wilderness",
    "wof:placetype":"venue"
},
  "geometry": {"coordinates":[-109.757527,32.853109],"type":"Point"}
}