{
  "type": "Feature",
  "properties": {
    "iso:country":"US",
    "sg:address":"20830 N 39th Way",
    "sg:city":"Phoenix",
    "sg:classifiers":[
        {
            "category":"Retail",
            "subcategory":"Repair Shop",
            "type":"Services"
        }
    ],
    "sg:phone":"+1 623 581 0202",
    "sg:postcode":"85050",
    "sg:province":"AZ",
    "sg:tags":[
        "refinish",
        "furniture"
    ],
    "wof:name":"American Furniture Repair",
    "wof:placetype":"venue"
},
  "geometry": {"coordinates":[-111.99691,33.676249],"type":"Point"}
}