{
  "type": "Feature",
  "properties": {
    "iso:country":"US",
    "sg:address":"7539 W Peoria Ave",
    "sg:city":"Peoria",
    "sg:classifiers":[
        {
            "category":"Personal",
            "subcategory":"Beauty Salon",
            "type":"Services"
        }
    ],
    "sg:phone":"+1 623 878 6415",
    "sg:postcode":"85345",
    "sg:province":"AZ",
    "sg:tags":[
        "manicuring"
    ],
    "wof:name":"Phancy Nails",
    "wof:placetype":"venue"
},
  "geometry": {"coordinates":[-112.22290700000001,33.581256],"type":"Point"}
}