{
  "type": "Feature",
  "properties": {
    "iso:country":"US",
    "sg:address":"1671 Cabana Dr",
    "sg:city":"Lake Havasu City",
    "sg:classifiers":[
        {
            "category":"Wholesale",
            "subcategory":"Furniture",
            "type":"Manufacturing & Wholesale Goods"
        }
    ],
    "sg:phone":"+1 928 855 7714",
    "sg:postcode":"86404",
    "sg:province":"AZ",
    "wof:name":"Wicker & Trees",
    "wof:placetype":"venue"
},
  "geometry": {"coordinates":[-114.359837,34.51952],"type":"Point"}
}