{
  "type": "Feature",
  "properties": {
    "addr:full":"19306 N Comet Trl Maricopa AZ 85138",
    "addr:housenumber":"19306",
    "addr:postcode":"85138",
    "addr:street":"N Comet Trl",
    "iso:country":"US",
    "sg:address":"19306 N Comet Trl",
    "sg:city":"Maricopa",
    "sg:classifiers":[
        {
            "category":"Professional",
            "subcategory":"Lawyer & Legal Services",
            "type":"Services"
        }
    ],
    "sg:phone":"+1 520 568 7666",
    "sg:postcode":"85138",
    "sg:province":"AZ",
    "sg:tags":[
        "attorney"
    ],
    "wof:name":"Robert G Meyers",
    "wof:placetype":"venue"
},
  "geometry": {"coordinates":[-112.028103,33.054227],"type":"Point"}
}