{
  "type": "Feature",
  "properties": {
    "addr:full":"719 E Bethany Home Rd Phoenix AZ 85014",
    "addr:housenumber":"719",
    "addr:postcode":"85014",
    "addr:street":"E Bethany Home Rd",
    "iso:country":"US",
    "sg:address":"719 E Bethany Home Rd",
    "sg:city":"Phoenix",
    "sg:classifiers":[
        {
            "category":"Retail",
            "subcategory":"Car Wash",
            "type":"Services"
        }
    ],
    "sg:phone":"+1 602 264 0425",
    "sg:postcode":"85014",
    "sg:province":"AZ",
    "sg:tags":[
        "polishing",
        "washing"
    ],
    "wof:name":"Rainmaker Carwash",
    "wof:placetype":"venue"
},
  "geometry": {"coordinates":[-112.06360599999999,33.523662],"type":"Point"}
}