{
  "type": "Feature",
  "properties": {
    "addr:full":"7171 E Cave Creek Rd Cave Creek AZ 85331",
    "addr:housenumber":"7171",
    "addr:postcode":"85331",
    "addr:street":"E Cave Creek Rd",
    "iso:country":"US",
    "sg:address":"7171 E Cave Creek Rd",
    "sg:city":"Cave Creek",
    "sg:classifiers":[
        {
            "category":"Banks & Credit Unions",
            "subcategory":"Investment Brokerage",
            "type":"Services"
        }
    ],
    "sg:phone":"+1 480 595 4792",
    "sg:postcode":"85331",
    "sg:province":"AZ",
    "sg:tags":[
        "stock",
        "bond"
    ],
    "wof:name":"I C Financial",
    "wof:placetype":"venue"
},
  "geometry": {"coordinates":[-111.926818,33.828238],"type":"Point"}
}