{
  "type": "Feature",
  "properties": {
    "iso:country":"US",
    "sg:address":"1038 W Southern Ave",
    "sg:city":"Mesa",
    "sg:classifiers":[
        {
            "category":"Restaurant",
            "type":"Food & Drink"
        }
    ],
    "sg:phone":"+1 480 969 7550",
    "sg:postcode":"85210",
    "sg:province":"AZ",
    "sg:tags":[
        "eating"
    ],
    "wof:name":"Pizzabella",
    "wof:placetype":"venue"
},
  "geometry": {"coordinates":[-111.856467,33.39319],"type":"Point"}
}