{
  "type": "Feature",
  "properties": {
    "addr:full":"1218 E Greenway Dr Tempe AZ 85282",
    "addr:housenumber":"1218",
    "addr:postcode":"85282",
    "addr:street":"E Greenway Dr",
    "iso:country":"US",
    "sg:address":"1218 E Greenway Dr",
    "sg:city":"Tempe",
    "sg:classifiers":[
        {
            "category":"Building & Trades",
            "subcategory":"Plumbing",
            "type":"Services"
        }
    ],
    "sg:phone":"+1 480 755 7959",
    "sg:postcode":"85282",
    "sg:province":"AZ",
    "sg:tags":[
        "contractor"
    ],
    "wof:name":"Shamrock Heating & Cooling",
    "wof:placetype":"venue"
},
  "geometry": {"coordinates":[-111.918443,33.384908],"type":"Point"}
}