{
  "type": "Feature",
  "properties": {
    "addr:full":"921 Stockton Hill Ave Kingman AZ 86401",
    "addr:housenumber":"921",
    "addr:postcode":"86401",
    "addr:street":"Stockton Hill Ave",
    "iso:country":"US",
    "sg:address":"921 Stockton Hill Ave",
    "sg:city":"Kingman",
    "sg:classifiers":[
        {
            "category":"Shopping",
            "subcategory":"Bicycles & Sporting Goods",
            "type":"Retail Goods"
        }
    ],
    "sg:phone":"+1 928 753 1792",
    "sg:postcode":"86401",
    "sg:province":"AZ",
    "sg:tags":[
        "gun",
        "gunsmith"
    ],
    "wof:name":"Jim Cornwall",
    "wof:placetype":"venue"
},
  "geometry": {"coordinates":[-114.060435,35.197435],"type":"Point"}
}