{
  "type": "Feature",
  "properties": {
    "iso:country":"US",
    "sg:address":"1185 E Brenda Dr",
    "sg:city":"Casa Grande",
    "sg:classifiers":[
        {
            "category":"Building & Trades",
            "subcategory":"Plumbing",
            "type":"Services"
        }
    ],
    "sg:phone":"+1 520 316 9120",
    "sg:postcode":"85222",
    "sg:province":"AZ",
    "sg:tags":[
        "contractor"
    ],
    "wof:name":"Mankel Mechanical LLC",
    "wof:placetype":"venue"
},
  "geometry": {"coordinates":[-111.739668,32.889048],"type":"Point"}
}