{
  "type": "Feature",
  "properties": {
    "iso:country":"US",
    "sg:address":"1326 N 21st Ave",
    "sg:city":"Phoenix",
    "sg:classifiers":[
        {
            "category":"Wholesale",
            "subcategory":"Hardware",
            "type":"Manufacturing & Wholesale Goods"
        }
    ],
    "sg:phone":"+1 602 257 0278",
    "sg:postcode":"85009",
    "sg:province":"AZ",
    "sg:tags":[
        "system",
        "mfg",
        "heating",
        "air",
        "conditioning",
        "representative"
    ],
    "wof:name":"Breecher Sales Inc",
    "wof:placetype":"venue"
},
  "geometry": {"coordinates":[-112.104389,33.463797],"type":"Point"}
}