{
  "type": "Feature",
  "properties": {
    "iso:country":"US",
    "sg:address":"118 S Southgate Dr Ste 2",
    "sg:city":"Chandler",
    "sg:classifiers":[
        {
            "category":"Shopping Center",
            "type":"Public Place"
        }
    ],
    "sg:phone":"+1 480 767 7747",
    "sg:postcode":"85226",
    "sg:province":"AZ",
    "sg:tags":[
        "mall"
    ],
    "wof:name":"Deck The Mall",
    "wof:placetype":"venue"
},
  "geometry": {"coordinates":[-111.96899999999999,33.301717],"type":"Point"}
}