{
  "type": "Feature",
  "properties": {
    "iso:country":"US",
    "sg:address":"319 E Waltann Ln",
    "sg:city":"Phoenix",
    "sg:classifiers":[
        {
            "category":"Organizations",
            "subcategory":"Religious Organization",
            "type":"Services"
        }
    ],
    "sg:phone":"+1 602 942 1450",
    "sg:postcode":"85022",
    "sg:province":"AZ",
    "sg:tags":[
        "clergy"
    ],
    "wof:name":"Doss, Eddie Ralph Sr",
    "wof:placetype":"venue"
},
  "geometry": {"coordinates":[-112.069434,33.627581],"type":"Point"}
}