{
  "type": "Feature",
  "properties": {
    "iso:country":"US",
    "sg:address":"6454 E Rochelle St",
    "sg:city":"Mesa",
    "sg:classifiers":[
        {
            "category":"Real Estate",
            "subcategory":"Real Estate Operator",
            "type":"Services"
        }
    ],
    "sg:phone":"+1 480 654 2651",
    "sg:postcode":"85215",
    "sg:province":"AZ",
    "sg:tags":[
        "property",
        "lessor"
    ],
    "wof:name":"Lois B Honeycutt",
    "wof:placetype":"venue"
},
  "geometry": {"coordinates":[-111.689696,33.480336],"type":"Point"}
}