{
  "type": "Feature",
  "properties": {
    "iso:country":"US",
    "sg:address":"1734 E Amber Ln",
    "sg:city":"Gilbert",
    "sg:classifiers":[
        {
            "category":"Building & Trades",
            "subcategory":"Plumbing",
            "type":"Services"
        }
    ],
    "sg:phone":"+1 480 986 9577",
    "sg:postcode":"85296",
    "sg:province":"AZ",
    "sg:tags":[
        "conditioning",
        "air",
        "system",
        "contractor"
    ],
    "wof:name":"AA Xtreme Air Conditioning",
    "wof:placetype":"venue"
},
  "geometry": {"coordinates":[-111.75461,33.34487],"type":"Point"}
}