{
  "type": "Feature",
  "properties": {
    "iso:country":"US",
    "sg:address":"2300 S Huffer Ln",
    "sg:city":"Flagstaff",
    "sg:classifiers":[
        {
            "category":"Government",
            "subcategory":"Court House",
            "type":"Public Place"
        }
    ],
    "sg:phone":"+1 928 779 6772",
    "sg:postcode":"86001",
    "sg:province":"AZ",
    "sg:tags":[
        "juvenile",
        "system"
    ],
    "wof:name":"Juvenile Court",
    "wof:placetype":"venue"
},
  "geometry": {"coordinates":[-111.656368,35.175387],"type":"Point"}
}