{
  "type": "Feature",
  "properties": {
    "iso:country":"US",
    "sg:address":"7645 N la Cholla Blvd",
    "sg:city":"Tucson",
    "sg:classifiers":[
        {
            "category":"Banks & Credit Unions",
            "subcategory":"Bank",
            "type":"Services"
        },
        {
            "category":"Banks & Credit Unions",
            "subcategory":"Financial Services",
            "type":"Services"
        }
    ],
    "sg:phone":"+1 520 514 4110",
    "sg:postcode":"85741",
    "sg:province":"AZ",
    "sg:tags":[
        "saving",
        "loan",
        "commercial"
    ],
    "sg:website":"http://www.compassbank.com",
    "wof:name":"Compass Bank",
    "wof:placetype":"venue"
},
  "geometry": {"coordinates":[-111.012772,32.344932],"type":"Point"}
}