{
  "type": "Feature",
  "properties": {
    "iso:country":"US",
    "sg:address":"8 Co Rd 1120",
    "sg:city":"Greer",
    "sg:classifiers":[
        {
            "category":"Travel",
            "subcategory":"Hotels & Motels",
            "type":"Entertainment"
        }
    ],
    "sg:phone":"+1 928 735 7441",
    "sg:postcode":"85927",
    "sg:province":"AZ",
    "sg:tags":[
        "breakfast",
        "accommodation",
        "bed"
    ],
    "wof:name":"Red Setter Inn",
    "wof:placetype":"venue"
},
  "geometry": {"coordinates":[-109.461404,34.002336],"type":"Point"}
}