{
  "type": "Feature",
  "properties": {
    "iso:country":"US",
    "sg:address":"1661 Cal Edison",
    "sg:city":"Laughlin",
    "sg:classifiers":[
        {
            "category":"Professional",
            "type":"Services"
        }
    ],
    "sg:phone":"+1 702 298 2241",
    "sg:postcode":"89028",
    "sg:province":"NV",
    "sg:tags":[
        "establishment"
    ],
    "wof:name":"ETT Inc",
    "wof:placetype":"venue"
},
  "geometry": {"coordinates":[-114.617222,35.135196],"type":"Point"}
}