{
  "type": "Feature",
  "properties": {
    "iso:country":"US",
    "sg:address":"904 Oak Ter",
    "sg:city":"Prescott",
    "sg:classifiers":[
        {
            "category":"Wholesale",
            "subcategory":"Vending Machines",
            "type":"Manufacturing & Wholesale Goods"
        }
    ],
    "sg:phone":"+1 928 776 7988",
    "sg:postcode":"86301",
    "sg:province":"AZ",
    "sg:tags":[
        "operator"
    ],
    "wof:name":"Candy Man Dans Vending",
    "wof:placetype":"venue"
},
  "geometry": {"coordinates":[-112.470316,34.558225],"type":"Point"}
}