{
  "type": "Feature",
  "properties": {
    "addr:full":"7301 N 58th Ave Glendale AZ 85301",
    "addr:housenumber":"7301",
    "addr:postcode":"85301",
    "addr:street":"N 58Th Ave",
    "iso:country":"US",
    "sg:address":"7301 N 58th Ave",
    "sg:city":"Glendale",
    "sg:classifiers":[
        {
            "category":"Education",
            "subcategory":"School",
            "type":"Public Place"
        }
    ],
    "sg:phone":"+1 623 842 8175",
    "sg:postcode":"85301",
    "sg:province":"AZ",
    "sg:tags":[
        "educational",
        "program"
    ],
    "wof:name":"Gary Tang Adult Education Ctr",
    "wof:placetype":"venue"
},
  "geometry": {"coordinates":[-112.183689,33.544956],"type":"Point"}
}