{
  "type": "Feature",
  "properties": {
    "iso:country":"US",
    "sg:address":"4401 US Hwy 89",
    "sg:city":"Flagstaff",
    "sg:classifiers":[
        {
            "category":"Wholesale",
            "subcategory":"Durable Goods & Equipment",
            "type":"Manufacturing & Wholesale Goods"
        }
    ],
    "sg:phone":"+1 928 526 1780",
    "sg:postcode":"86004",
    "sg:province":"AZ",
    "wof:name":"Good As New",
    "wof:placetype":"venue"
},
  "geometry": {"coordinates":[-111.583634,35.224107],"type":"Point"}
}