{
  "type": "Feature",
  "properties": {
    "addr:full":"3207 E Menadota Dr Phoenix AZ 85050",
    "addr:housenumber":"3207",
    "addr:postcode":"85050",
    "addr:street":"E Menadota Dr",
    "iso:country":"US",
    "sg:address":"3207 E Menadota Dr",
    "sg:city":"Phoenix",
    "sg:classifiers":[
        {
            "category":"Professional",
            "subcategory":"Computer Services",
            "type":"Services"
        }
    ],
    "sg:phone":"+1 480 951 3592",
    "sg:postcode":"85050",
    "sg:province":"AZ",
    "sg:tags":[
        "designer",
        "network",
        "consultant",
        "system",
        "design"
    ],
    "wof:name":"Gha Technologies, Inc.",
    "wof:placetype":"venue"
},
  "geometry": {"coordinates":[-112.013204,33.669197],"type":"Point"}
}