{
  "type": "Feature",
  "properties": {
    "iso:country":"US",
    "sg:address":"2108 S 6th Ave",
    "sg:city":"Tucson",
    "sg:classifiers":[
        {
            "category":"Bars & Pubs",
            "type":"Food & Drink"
        }
    ],
    "sg:phone":"+1 520 622 9180",
    "sg:postcode":"85713",
    "sg:province":"AZ",
    "sg:tags":[
        "drinking"
    ],
    "wof:name":"Wagon Wheel Inc",
    "wof:placetype":"venue"
},
  "geometry": {"coordinates":[-110.96848300000001,32.196631],"type":"Point"}
}