{
  "type": "Feature",
  "properties": {
    "addr:full":"15020 S Tuthill Rd Buckeye AZ 85326",
    "addr:housenumber":"15020",
    "addr:postcode":"85326",
    "addr:street":"S Tuthill Rd",
    "iso:country":"US",
    "sg:address":"15020 S Tuthill Rd",
    "sg:city":"Buckeye",
    "sg:classifiers":[
        {
            "category":"Wholesale",
            "subcategory":"Auto Parts",
            "type":"Manufacturing & Wholesale Goods"
        }
    ],
    "sg:phone":"+1 602 276 6563",
    "sg:postcode":"85326",
    "sg:province":"AZ",
    "sg:tags":[
        "automobile",
        "rebuilt"
    ],
    "wof:name":"Bert & Son Truck Works",
    "wof:placetype":"venue"
},
  "geometry": {"coordinates":[-112.487193,33.308847],"type":"Point"}
}