{
  "type": "Feature",
  "properties": {
    "iso:country":"US",
    "sg:address":"3713 S 7th Ave",
    "sg:city":"Tucson",
    "sg:classifiers":[
        {
            "category":"Social Services",
            "subcategory":"Child Care",
            "type":"Services"
        }
    ],
    "sg:phone":"+1 520 884 8908",
    "sg:postcode":"85713",
    "sg:province":"AZ",
    "sg:tags":[
        "kindergarten",
        "academic",
        "school"
    ],
    "wof:name":"Mis Hijitos Preschool Ctr",
    "wof:placetype":"venue"
},
  "geometry": {"coordinates":[-110.96953600000001,32.179853],"type":"Point"}
}