{
  "type": "Feature",
  "properties": {
    "addr:full":"2167 W Apache Trl Apache Junction AZ 85220",
    "addr:housenumber":"2167",
    "addr:postcode":"85220",
    "addr:street":"W Apache Trl",
    "iso:country":"US",
    "sg:address":"2167 W Apache Trl",
    "sg:city":"Apache Junction",
    "sg:classifiers":[
        {
            "category":"Restaurant",
            "type":"Food & Drink"
        }
    ],
    "sg:menulink":"http://www.allmenus.com/az/north-pinal/151508-aw-restaurant/menu/",
    "sg:phone":"+1 480 671 3089",
    "sg:postcode":"85220",
    "sg:province":"AZ",
    "sg:tags":[
        "burger",
        "american",
        "dog",
        "pub",
        "hot"
    ],
    "wof:name":"A&W Restaurant",
    "wof:placetype":"venue"
},
  "geometry": {"coordinates":[-111.569821,33.41505],"type":"Point"}
}