{
  "type": "Feature",
  "properties": {
    "iso:country":"US",
    "sg:address":"8225 E Rockgate Rd",
    "sg:city":"Tucson",
    "sg:classifiers":[
        {
            "category":"Shopping",
            "subcategory":"Gifts & Souvenirs",
            "type":"Retail Goods"
        }
    ],
    "sg:phone":"+1 520 749 5523",
    "sg:postcode":"85750",
    "sg:province":"AZ",
    "sg:tags":[
        "basket",
        "southwestern"
    ],
    "wof:name":"Gifts To Go",
    "wof:placetype":"venue"
},
  "geometry": {"coordinates":[-110.818012,32.297084],"type":"Point"}
}