{
  "type": "Feature",
  "properties": {
    "addr:full":"3939 S Avenue A 3 E 3 E Ste 108 Yuma AZ 85365",
    "addr:housenumber":"3939;3 e 3 e ste 108",
    "addr:postcode":"85365",
    "addr:street":"S Avenue A",
    "iso:country":"US",
    "sg:address":"3939 S Avenue A 3 E 3 E Ste 108",
    "sg:city":"Yuma",
    "sg:classifiers":[
        {
            "category":"Fast Food",
            "type":"Food & Drink"
        },
        {
            "category":"Restaurant",
            "type":"Food & Drink"
        }
    ],
    "sg:phone":"+1 928 341 4759",
    "sg:postcode":"85365",
    "sg:province":"AZ",
    "sg:tags":[
        "take"
    ],
    "wof:name":"Onestop Burger Shop",
    "wof:placetype":"venue"
},
  "geometry": {"coordinates":[-114.63285999999999,32.656013],"type":"Point"}
}