{
  "type": "Feature",
  "properties": {
    "iso:country":"US",
    "sg:address":"905 W McDowell Rd",
    "sg:city":"Phoenix",
    "sg:classifiers":[
        {
            "category":"Professional",
            "subcategory":"Art Services",
            "type":"Services"
        }
    ],
    "sg:phone":"+1 602 253 2343",
    "sg:postcode":"85007",
    "sg:province":"AZ",
    "sg:tags":[
        "graphic"
    ],
    "wof:name":"Bob Oliva Creative Svc",
    "wof:placetype":"venue"
},
  "geometry": {"coordinates":[-112.086961,33.465749],"type":"Point"}
}