{
  "type": "Feature",
  "properties": {
    "iso:country":"US",
    "sg:address":"2114 W Grant Rd",
    "sg:city":"Tucson",
    "sg:classifiers":[
        {
            "category":"Professional",
            "subcategory":"Management & Consulting",
            "type":"Services"
        }
    ],
    "sg:phone":"+1 520 326 7468",
    "sg:postcode":"85745",
    "sg:province":"AZ",
    "sg:tags":[
        "marketing",
        "consultant"
    ],
    "wof:name":"Ideamagic Marketing Promotions",
    "wof:placetype":"venue"
},
  "geometry": {"coordinates":[-111.013206,32.25076],"type":"Point"}
}