{
  "type": "Feature",
  "properties": {
    "addr:full":"3030 Forest Hills Dr Flagstaff AZ 86001",
    "addr:housenumber":"3030",
    "addr:postcode":"86001",
    "addr:street":"Forest Hills Dr",
    "iso:country":"US",
    "sg:address":"3030 Forest Hills Dr",
    "sg:city":"Flagstaff",
    "sg:classifiers":[
        {
            "category":"Professional",
            "type":"Services"
        }
    ],
    "sg:phone":"+1 928 774 5656",
    "sg:postcode":"86001",
    "sg:province":"AZ",
    "wof:name":"Mutemouse",
    "wof:placetype":"venue"
},
  "geometry": {"coordinates":[-111.681669,35.24579],"type":"Point"}
}