{
  "type": "Feature",
  "properties": {
    "iso:country":"US",
    "sg:address":"1228 W Cheyenne Dr",
    "sg:city":"Chandler",
    "sg:classifiers":[
        {
            "category":"Building & Trades",
            "subcategory":"Construction",
            "type":"Services"
        }
    ],
    "sg:phone":"+1 602 908 4600",
    "sg:postcode":"85224",
    "sg:province":"AZ",
    "sg:tags":[
        "management"
    ],
    "wof:name":"Compass Telecommunication Services",
    "wof:placetype":"venue"
},
  "geometry": {"coordinates":[-111.864061,33.347466],"type":"Point"}
}