{
  "type": "Feature",
  "properties": {
    "iso:country":"US",
    "sg:address":"12230 W Monroe St",
    "sg:city":"Avondale",
    "sg:classifiers":[
        {
            "category":"Professional",
            "type":"Services"
        }
    ],
    "sg:phone":"+1 623 935 0913",
    "sg:postcode":"85323",
    "sg:province":"AZ",
    "wof:name":"Big Bad Party Planning",
    "wof:placetype":"venue"
},
  "geometry": {"coordinates":[-112.32219600000001,33.446216],"type":"Point"}
}