{
  "type": "Feature",
  "properties": {
    "iso:country":"US",
    "sg:address":"1968 E Villa St",
    "sg:city":"Phoenix",
    "sg:classifiers":[
        {
            "category":"Community Center",
            "subcategory":"Senior",
            "type":"Public Place"
        },
        {
            "category":"Social Services",
            "subcategory":"Adult Care",
            "type":"Services"
        }
    ],
    "sg:phone":"+1 602 254 1810",
    "sg:postcode":"85006",
    "sg:province":"AZ",
    "sg:tags":[
        "counseling",
        "citizen"
    ],
    "wof:name":"Seniors Resource Guide",
    "wof:placetype":"venue"
},
  "geometry": {"coordinates":[-112.039456,33.456341],"type":"Point"}
}