{
  "type": "Feature",
  "properties": {
    "iso:country":"US",
    "sg:address":"9284 W Northern Ave",
    "sg:city":"Glendale",
    "sg:classifiers":[
        {
            "category":"Home & Garden",
            "subcategory":"Furniture",
            "type":"Retail Goods"
        }
    ],
    "sg:phone":"+1 623 772 5433",
    "sg:postcode":"85305",
    "sg:province":"AZ",
    "sg:tags":[
        "bed"
    ],
    "wof:name":"Sleep America",
    "wof:placetype":"venue"
},
  "geometry": {"coordinates":[-112.261926,33.551511],"type":"Point"}
}