{
  "type": "Feature",
  "properties": {
    "iso:country":"US",
    "sg:address":"671 State Hwy 179",
    "sg:city":"Sedona",
    "sg:classifiers":[
        {
            "category":"Real Estate",
            "subcategory":"Real Estate Agent",
            "type":"Services"
        }
    ],
    "sg:phone":"+1 928 282 7080",
    "sg:postcode":"86336",
    "sg:province":"AZ",
    "wof:name":"K D Venture Properties",
    "wof:placetype":"venue"
},
  "geometry": {"coordinates":[-111.762242,34.859995],"type":"Point"}
}