{
  "type": "Feature",
  "properties": {
    "addr:full":"8737 W Bell Rd Peoria AZ 85382",
    "addr:housenumber":"8737",
    "addr:postcode":"85382",
    "addr:street":"W Bell Rd",
    "iso:country":"US",
    "sg:address":"8737 W Bell Rd",
    "sg:city":"Peoria",
    "sg:classifiers":[
        {
            "category":"Autos & Motor Vehicles",
            "subcategory":"Automobile Sales",
            "type":"Retail Goods"
        }
    ],
    "sg:phone":"+1 623 933 5000",
    "sg:postcode":"85382",
    "sg:province":"AZ",
    "sg:tags":[
        "car",
        "dealer"
    ],
    "sg:website":"www.libertybuick.com",
    "wof:name":"Liberty Buick Inc",
    "wof:placetype":"venue"
},
  "geometry": {"coordinates":[-112.247874,33.638057],"type":"Point"}
}