{
  "type": "Feature",
  "properties": {
    "iso:country":"US",
    "sg:address":"2424 S Mill Ave",
    "sg:city":"Tempe",
    "sg:classifiers":[
        {
            "category":"Place Of Worship",
            "subcategory":"Church",
            "type":"Public Place"
        },
        {
            "category":"Place Of Worship",
            "type":"Public Place"
        }
    ],
    "sg:phone":"+1 480 968 7847",
    "sg:postcode":"85282",
    "sg:province":"AZ",
    "sg:tags":[
        "testament",
        "christ-new",
        "christ",
        "churches-church"
    ],
    "wof:name":"Tempe Church Of Christ",
    "wof:placetype":"venue"
},
  "geometry": {"coordinates":[-111.939751,33.403389],"type":"Point"}
}