{
  "type": "Feature",
  "properties": {
    "iso:country":"US",
    "sg:address":"1404 W Ridgeview Dr",
    "sg:city":"Yuma",
    "sg:classifiers":[
        {
            "category":"Building & Trades",
            "subcategory":"Construction",
            "type":"Services"
        }
    ],
    "sg:phone":"+1 928 726 5256",
    "sg:postcode":"85364",
    "sg:province":"AZ",
    "sg:tags":[
        "contractor"
    ],
    "wof:name":"Cabinet Source",
    "wof:placetype":"venue"
},
  "geometry": {"coordinates":[-114.638987,32.691862],"type":"Point"}
}