{
  "type": "Feature",
  "properties": {
    "addr:full":"14884 E Pine Valley Rd Scottsdale AZ 85260",
    "addr:housenumber":"14884",
    "addr:postcode":"85260",
    "addr:street":"E Pine Valley Rd",
    "iso:country":"US",
    "sg:address":"14884 E Pine Valley Rd",
    "sg:city":"Scottsdale",
    "sg:classifiers":[
        {
            "category":"Cafe",
            "type":"Food & Drink"
        },
        {
            "category":"Bakery",
            "type":"Food & Drink"
        }
    ],
    "sg:menulink":"http://www.allmenus.com/az/phoenix/39037-paradise-bakery--cafe/menu/",
    "sg:phone":"+1 480 290 7770",
    "sg:postcode":"85260",
    "sg:province":"AZ",
    "sg:tags":[
        "american",
        "pastry"
    ],
    "wof:name":"Paradise Bakery & Cafe",
    "wof:placetype":"venue"
},
  "geometry": {"coordinates":[-111.904163,33.620689],"type":"Point"}
}