{
  "type": "Feature",
  "properties": {
    "iso:country":"US",
    "sg:address":"2487 W Cactus Wren St",
    "sg:city":"Apache Junction",
    "sg:classifiers":[
        {
            "category":"Building & Trades",
            "subcategory":"Construction",
            "type":"Services"
        }
    ],
    "sg:phone":"+1 480 982 8387",
    "sg:postcode":"85220",
    "sg:province":"AZ",
    "sg:tags":[
        "house"
    ],
    "wof:name":"Sbjmd Construction Inc",
    "wof:placetype":"venue"
},
  "geometry": {"coordinates":[-111.572718,33.417789],"type":"Point"}
}