{
  "type": "Feature",
  "properties": {
    "iso:country":"US",
    "sg:address":"3395 W Chandler Blvd",
    "sg:city":"Chandler",
    "sg:classifiers":[
        {
            "category":"Restaurant",
            "type":"Food & Drink"
        }
    ],
    "sg:menulink":"http://www.allmenus.com/az/chandler/4934-pasta-pomodoro/menu/",
    "sg:phone":"+1 480 855 3736",
    "sg:postcode":"85226",
    "sg:province":"AZ",
    "sg:tags":[
        "italian"
    ],
    "wof:name":"Pasta Pomodoro",
    "wof:placetype":"venue"
},
  "geometry": {"coordinates":[-111.89956100000001,33.305433],"type":"Point"}
}