{
  "type": "Feature",
  "properties": {
    "addr:full":"1847 W Broadway Rd Phoenix AZ 85041",
    "addr:housenumber":"1847",
    "addr:postcode":"85041",
    "addr:street":"W Broadway Rd",
    "iso:country":"US",
    "sg:address":"1847 W Broadway Rd",
    "sg:city":"Phoenix",
    "sg:classifiers":[
        {
            "category":"Autos & Motor Vehicles",
            "subcategory":"Automobile Sales",
            "type":"Retail Goods"
        },
        {
            "category":"Retail",
            "subcategory":"Auto Rental",
            "type":"Services"
        }
    ],
    "sg:phone":"+1 602 276 2931",
    "sg:postcode":"85041",
    "sg:province":"AZ",
    "sg:tags":[
        "car",
        "leasing"
    ],
    "wof:name":"Auto Action",
    "wof:placetype":"venue"
},
  "geometry": {"coordinates":[-112.09815999999999,33.406731],"type":"Point"}
}