{
  "type": "Feature",
  "properties": {
    "iso:country":"US",
    "sg:address":"1266 W Tulsa St",
    "sg:city":"Chandler",
    "sg:classifiers":[
        {
            "category":"Retail",
            "subcategory":"Laundry & Dry Cleaning",
            "type":"Services"
        }
    ],
    "sg:phone":"+1 602 618 5045",
    "sg:postcode":"85224",
    "sg:province":"AZ",
    "sg:tags":[
        "cleaners",
        "rug",
        "carpet"
    ],
    "wof:name":"Magic Touch Floor Care",
    "wof:placetype":"venue"
},
  "geometry": {"coordinates":[-111.864867,33.312625],"type":"Point"}
}