{
  "type": "Feature",
  "properties": {
    "iso:country":"US",
    "sg:address":"3151 N 34th Dr",
    "sg:city":"Phoenix",
    "sg:classifiers":[
        {
            "category":"Manufacturing",
            "subcategory":"Tools & Machinery",
            "type":"Manufacturing & Wholesale Goods"
        }
    ],
    "sg:phone":"+1 602 269 5951",
    "sg:postcode":"85017",
    "sg:province":"AZ",
    "sg:tags":[
        "ink"
    ],
    "wof:name":"Mix & Match Corp",
    "wof:placetype":"venue"
},
  "geometry": {"coordinates":[-112.132311,33.485333],"type":"Point"}
}