{
  "type": "Feature",
  "properties": {
    "addr:full":"1560 E Thornton Show Low AZ 85901",
    "addr:housenumber":"1560",
    "addr:postcode":"85901",
    "addr:street":"E",
    "iso:country":"US",
    "sg:address":"1560 E Thornton",
    "sg:city":"Show Low",
    "sg:classifiers":[
        {
            "category":"Utilities",
            "subcategory":"Electric",
            "type":"Services"
        }
    ],
    "sg:phone":"+1 928 537 2802",
    "sg:postcode":"85901",
    "sg:province":"AZ",
    "wof:name":"Arizona Public Service Company",
    "wof:placetype":"venue"
},
  "geometry": {"coordinates":[-110.025876,34.264267],"type":"Point"}
}