{
  "type": "Feature",
  "properties": {
    "iso:country":"US",
    "sg:address":"710 E Mohave St",
    "sg:city":"Phoenix",
    "sg:classifiers":[
        {
            "category":"Restaurant",
            "type":"Food & Drink"
        }
    ],
    "sg:phone":"+1 602 256 0134",
    "sg:postcode":"85034",
    "sg:province":"AZ",
    "sg:tags":[
        "drinking",
        "eating"
    ],
    "wof:name":"Los Arcos Restaurant & Bar",
    "wof:placetype":"venue"
},
  "geometry": {"coordinates":[-112.060945,33.431417],"type":"Point"}
}