{
  "type": "Feature",
  "properties": {
    "addr:full":"9909 E Kleindale Rd Tucson AZ 85749",
    "addr:housenumber":"9909",
    "addr:postcode":"85749",
    "addr:street":"E Kleindale Rd",
    "iso:country":"US",
    "sg:address":"9909 E Kleindale Rd",
    "sg:city":"Tucson",
    "sg:classifiers":[
        {
            "category":"Building & Trades",
            "subcategory":"Landscaping Services",
            "type":"Services"
        }
    ],
    "sg:phone":"+1 520 749 5403",
    "sg:postcode":"85749",
    "sg:province":"AZ",
    "sg:tags":[
        "landscape",
        "contractor"
    ],
    "wof:name":"Copper Cactus Landscape Co",
    "wof:placetype":"venue"
},
  "geometry": {"coordinates":[-110.774451,32.269132],"type":"Point"}
}