{
  "type": "Feature",
  "properties": {
    "iso:country":"US",
    "sg:address":"21 N Velero Ct",
    "sg:city":"Chandler",
    "sg:classifiers":[
        {
            "category":"Retail",
            "subcategory":"Repair Shop",
            "type":"Services"
        }
    ],
    "sg:phone":"+1 480 917 0829",
    "sg:postcode":"85225",
    "sg:province":"AZ",
    "sg:tags":[
        "equipment",
        "electronic",
        "supply"
    ],
    "wof:name":"Kismet Electronics",
    "wof:placetype":"venue"
},
  "geometry": {"coordinates":[-111.814036,33.303945],"type":"Point"}
}