{
  "type": "Feature",
  "properties": {
    "addr:full":"405 W Franklin St Tucson AZ 85701",
    "addr:housenumber":"405",
    "addr:postcode":"85701",
    "addr:street":"W Franklin St",
    "iso:country":"US",
    "sg:address":"405 W Franklin St",
    "sg:city":"Tucson",
    "sg:classifiers":[
        {
            "category":"Professional",
            "subcategory":"Lawyer & Legal Services",
            "type":"Services"
        }
    ],
    "sg:phone":"+1 520 624 9334",
    "sg:postcode":"85701",
    "sg:province":"AZ",
    "sg:tags":[
        "attorney"
    ],
    "wof:name":"Sandy Forbes",
    "wof:placetype":"venue"
},
  "geometry": {"coordinates":[-110.97831600000001,32.225174],"type":"Point"}
}