{
  "type": "Feature",
  "properties": {
    "iso:country":"US",
    "sg:address":"1066 W Pleasant Ave",
    "sg:city":"Chino Valley",
    "sg:classifiers":[
        {
            "category":"Freight",
            "type":"Transportation"
        }
    ],
    "sg:phone":"+1 928 636 8610",
    "sg:postcode":"86323",
    "sg:province":"AZ",
    "sg:tags":[
        "operator",
        "local",
        "trucking"
    ],
    "wof:name":"Flyers By Laura",
    "wof:placetype":"venue"
},
  "geometry": {"coordinates":[-112.468452,34.74013],"type":"Point"}
}