{
  "type": "Feature",
  "properties": {
    "iso:country":"US",
    "sg:address":"4715 N 47th Ave",
    "sg:city":"Glendale",
    "sg:classifiers":[
        {
            "category":"Shopping",
            "subcategory":"Pets & Pet Supplies",
            "type":"Retail Goods"
        },
        {
            "category":"Retail",
            "subcategory":"Animal Services",
            "type":"Services"
        }
    ],
    "sg:phone":"+1 623 939 5093",
    "sg:postcode":"85301",
    "sg:province":"AZ",
    "sg:tags":[
        "grooming",
        "dog",
        "cat"
    ],
    "wof:name":"Shear Ecstasy All Breed Grooming",
    "wof:placetype":"venue"
},
  "geometry": {"coordinates":[-112.160027,33.532349],"type":"Point"}
}