{
  "type": "Feature",
  "properties": {
    "addr:full":"3434 W Greenway Rd Suite 15 Phoenix AZ 85053",
    "addr:housenumber":"3434;15",
    "addr:postcode":"85053",
    "addr:street":"W Greenway Rd Suite",
    "iso:country":"US",
    "sg:address":"3434 W Greenway Rd Suite 15",
    "sg:city":"Phoenix",
    "sg:classifiers":[
        {
            "category":"Banks & Credit Unions",
            "subcategory":"Financial Services",
            "type":"Services"
        }
    ],
    "sg:phone":"+1 866 344 7969",
    "sg:postcode":"85053",
    "sg:province":"AZ",
    "sg:tags":[
        "payday",
        "loan"
    ],
    "sg:website":"http://www.813CASH.com",
    "wof:name":"Lighthouse Financial Services of AZ Inc.",
    "wof:placetype":"venue"
},
  "geometry": {"coordinates":[-112.13224,33.625278],"type":"Point"}
}