{
  "type": "Feature",
  "properties": {
    "addr:full":"1315 S Gilbert Rd Mesa AZ 85204",
    "addr:housenumber":"1315",
    "addr:postcode":"85204",
    "addr:street":"S Gilbert Rd",
    "iso:country":"US",
    "sg:address":"1315 S Gilbert Rd",
    "sg:city":"Mesa",
    "sg:classifiers":[
        {
            "category":"Shopping",
            "subcategory":"Tobacco",
            "type":"Retail Goods"
        }
    ],
    "sg:phone":"+1 480 668 1161",
    "sg:postcode":"85204",
    "sg:province":"AZ",
    "sg:tags":[
        "shop"
    ],
    "wof:name":"Cannibal's Pipes & More",
    "wof:placetype":"venue"
},
  "geometry": {"coordinates":[-111.788224,33.391182],"type":"Point"}
}