{
  "type": "Feature",
  "properties": {
    "iso:country":"US",
    "sg:address":"10455 E Morning Star Dr",
    "sg:city":"Scottsdale",
    "sg:classifiers":[
        {
            "category":"Professional",
            "type":"Services"
        }
    ],
    "sg:phone":"+1 480 515 2000",
    "sg:postcode":"85255",
    "sg:province":"AZ",
    "sg:tags":[
        "establishment"
    ],
    "wof:name":"Kaplan Search Inc",
    "wof:placetype":"venue"
},
  "geometry": {"coordinates":[-111.856374,33.631672],"type":"Point"}
}