{
  "type": "Feature",
  "properties": {
    "iso:country":"US",
    "sg:address":"635 N Craycroft Rd",
    "sg:city":"Tucson",
    "sg:classifiers":[
        {
            "category":"Building & Trades",
            "subcategory":"Construction",
            "type":"Services"
        }
    ],
    "sg:phone":"+1 520 325 3313",
    "sg:postcode":"85711",
    "sg:province":"AZ",
    "sg:tags":[
        "contractor"
    ],
    "wof:name":"Miller Companies",
    "wof:placetype":"venue"
},
  "geometry": {"coordinates":[-110.87553200000001,32.229146],"type":"Point"}
}