{
  "type": "Feature",
  "properties": {
    "addr:full":"6747 E Paradise Ln Scottsdale AZ 85254",
    "addr:housenumber":"6747",
    "addr:postcode":"85254",
    "addr:street":"E Paradise Ln",
    "iso:country":"US",
    "sg:address":"6747 E Paradise Ln",
    "sg:city":"Scottsdale",
    "sg:classifiers":[
        {
            "category":"Building & Trades",
            "subcategory":"Construction",
            "type":"Services"
        }
    ],
    "sg:phone":"+1 480 998 0961",
    "sg:postcode":"85254",
    "sg:province":"AZ",
    "sg:tags":[
        "house"
    ],
    "wof:name":"Sonoran Valley Cnstr LLC",
    "wof:placetype":"venue"
},
  "geometry": {"coordinates":[-111.935957,33.633045],"type":"Point"}
}