{
  "type": "Feature",
  "properties": {
    "addr:full":"107 State Hwy 260 Payson AZ 85541",
    "addr:housenumber":"107",
    "addr:postcode":"85541",
    "addr:street":"State Hwy 260",
    "iso:country":"US",
    "sg:address":"107 State Hwy 260",
    "sg:city":"Payson",
    "sg:classifiers":[
        {
            "category":"Restaurant",
            "type":"Food & Drink"
        }
    ],
    "sg:phone":"+1 928 474 3698",
    "sg:postcode":"85541",
    "sg:province":"AZ",
    "sg:website":"www.mcdonalds.com",
    "wof:name":"Mc Donald's",
    "wof:placetype":"venue"
},
  "geometry": {"coordinates":[-111.3229,34.241838],"type":"Point"}
}