{
  "type": "Feature",
  "properties": {
    "iso:country":"US",
    "sg:address":"3418 E Mercer Ln",
    "sg:city":"Phoenix",
    "sg:classifiers":[
        {
            "category":"Professional",
            "type":"Services"
        }
    ],
    "sg:phone":"+1 602 795 1551",
    "sg:postcode":"85028",
    "sg:province":"AZ",
    "sg:tags":[
        "establishment"
    ],
    "wof:name":"Hippopotamus Wake Enhancing",
    "wof:placetype":"venue"
},
  "geometry": {"coordinates":[-112.005666,33.584402],"type":"Point"}
}