{
  "type": "Feature",
  "properties": {
    "iso:country":"US",
    "sg:address":"18411 N Cave Creek Rd",
    "sg:city":"Phoenix",
    "sg:classifiers":[
        {
            "category":"Coffee & Tea",
            "type":"Food & Drink"
        }
    ],
    "sg:menulink":"http://www.allmenus.com/az/phoenix/108338-starbucks-coffee/menu/",
    "sg:phone":"+1 602 494 7388",
    "sg:postcode":"85032",
    "sg:province":"AZ",
    "sg:tags":[
        "american"
    ],
    "wof:name":"Starbucks Coffee",
    "wof:placetype":"venue"
},
  "geometry": {"coordinates":[-112.02976700000001,33.653889],"type":"Point"}
}