{
  "type": "Feature",
  "properties": {
    "iso:country":"US",
    "sg:address":"3903 S Butte Ave",
    "sg:city":"Tempe",
    "sg:classifiers":[
        {
            "category":"Building & Trades",
            "subcategory":"Locksmith",
            "type":"Services"
        }
    ],
    "sg:phone":"+1 602 635 6852",
    "sg:postcode":"85282",
    "sg:province":"AZ",
    "sg:tags":[
        "key"
    ],
    "wof:name":"Locksmith Anytime Anywhere Emergency",
    "wof:placetype":"venue"
},
  "geometry": {"coordinates":[-111.910526,33.387427],"type":"Point"}
}