{
  "type": "Feature",
  "properties": {
    "iso:country":"US",
    "sg:address":"3616 W Thomas Rd",
    "sg:city":"Phoenix",
    "sg:classifiers":[
        {
            "category":"Wholesale",
            "subcategory":"Construction Materials",
            "type":"Manufacturing & Wholesale Goods"
        }
    ],
    "sg:phone":"+1 888 778 5994",
    "sg:postcode":"85019",
    "sg:province":"AZ",
    "sg:tags":[
        "coatings-protective"
    ],
    "wof:name":"Vitracoat America, Inc.",
    "wof:placetype":"venue"
},
  "geometry": {"coordinates":[-112.136796,33.480457],"type":"Point"}
}