{
  "type": "Feature",
  "properties": {
    "addr:full":"419 E Juanita Ave Mesa AZ 85204",
    "addr:housenumber":"419",
    "addr:postcode":"85204",
    "addr:street":"E Juanita Ave",
    "iso:country":"US",
    "sg:address":"419 E Juanita Ave",
    "sg:city":"Mesa",
    "sg:classifiers":[
        {
            "category":"Shopping",
            "subcategory":"Books",
            "type":"Retail Goods"
        }
    ],
    "sg:phone":"+1 480 632 0440",
    "sg:postcode":"85204",
    "sg:province":"AZ",
    "sg:tags":[
        "bookstore"
    ],
    "sg:website":"www.aplusbookfairs.com",
    "wof:name":"A Plus Book Fairs",
    "wof:placetype":"venue"
},
  "geometry": {"coordinates":[-111.823044,33.382071],"type":"Point"}
}