{
  "type": "Feature",
  "properties": {
    "addr:full":"4939 W Ray Rd Chandler AZ 85226",
    "addr:housenumber":"4939",
    "addr:postcode":"85226",
    "addr:street":"W Ray Rd",
    "iso:country":"US",
    "sg:address":"4939 W Ray Rd",
    "sg:city":"Chandler",
    "sg:classifiers":[
        {
            "category":"Restaurant",
            "type":"Food & Drink"
        }
    ],
    "sg:menulink":"http://www.allmenus.com/az/chandler/129044-subway/menu/",
    "sg:phone":"+1 480 940 7085",
    "sg:postcode":"85226",
    "sg:province":"AZ",
    "sg:tags":[
        "american",
        "sandwich"
    ],
    "wof:name":"Subway",
    "wof:placetype":"venue"
},
  "geometry": {"coordinates":[-111.925957,33.318446],"type":"Point"}
}