{
  "type": "Feature",
  "properties": {
    "iso:country":"US",
    "sg:address":"10815 W McDowell Rd",
    "sg:city":"Avondale",
    "sg:classifiers":[
        {
            "category":"Professional",
            "subcategory":"Research",
            "type":"Services"
        }
    ],
    "sg:phone":"+1 623 907 8505",
    "sg:postcode":"85323",
    "sg:province":"AZ",
    "sg:tags":[
        "laboratory"
    ],
    "wof:name":"Labcorp",
    "wof:placetype":"venue"
},
  "geometry": {"coordinates":[-112.292271,33.464359],"type":"Point"}
}