{
  "type": "Feature",
  "properties": {
    "iso:country":"US",
    "sg:address":"630 W Catalina Dr",
    "sg:city":"Yuma",
    "sg:classifiers":[
        {
            "category":"Shopping",
            "subcategory":"Musical Instruments",
            "type":"Retail Goods"
        }
    ],
    "sg:phone":"+1 928 314 0105",
    "sg:postcode":"85364",
    "sg:province":"AZ",
    "wof:name":"Noahs Music Store",
    "wof:placetype":"venue"
},
  "geometry": {"coordinates":[-114.625957,32.672959],"type":"Point"}
}