{
  "type": "Feature",
  "properties": {
    "iso:country":"US",
    "sg:address":"150 W 1st St",
    "sg:city":"Nogales",
    "sg:classifiers":[
        {
            "category":"Communications",
            "subcategory":"Radio Station",
            "type":"Services"
        }
    ],
    "sg:phone":"+1 520 287 5206",
    "sg:postcode":"85621",
    "sg:province":"AZ",
    "sg:tags":[
        "company",
        "broadcasting"
    ],
    "wof:name":"KNOG",
    "wof:placetype":"venue"
},
  "geometry": {"coordinates":[-110.929235,31.352216],"type":"Point"}
}