{
  "type": "Feature",
  "properties": {
    "addr:full":"150 S State Rte 69 Dewey AZ 86327",
    "addr:housenumber":"150",
    "addr:postcode":"86327",
    "addr:street":"S State Rte 69",
    "iso:country":"US",
    "sg:address":"150 S State Rte 69",
    "sg:city":"Dewey",
    "sg:classifiers":[
        {
            "category":"Building & Trades",
            "subcategory":"Construction",
            "type":"Services"
        }
    ],
    "sg:phone":"+1 928 632 0106",
    "sg:postcode":"86327",
    "sg:province":"AZ",
    "sg:tags":[
        "tile",
        "dealer"
    ],
    "wof:name":"Mister Tile",
    "wof:placetype":"venue"
},
  "geometry": {"coordinates":[-112.247669,34.541901],"type":"Point"}
}