{
  "type": "Feature",
  "properties": {
    "iso:country":"US",
    "sg:address":"1430 S Arizona Ave",
    "sg:city":"Chandler",
    "sg:classifiers":[
        {
            "category":"Shopping",
            "subcategory":"Department Store",
            "type":"Retail Goods"
        }
    ],
    "sg:phone":"+1 480 782 5865",
    "sg:postcode":"85286",
    "sg:province":"AZ",
    "wof:name":"Kohl's Department Store",
    "wof:placetype":"venue"
},
  "geometry": {"coordinates":[-111.84151900000001,33.283983],"type":"Point"}
}