{
  "type": "Feature",
  "properties": {
    "iso:country":"US",
    "sg:address":"7245 E Jenan Dr",
    "sg:city":"Scottsdale",
    "sg:classifiers":[
        {
            "category":"Retail",
            "subcategory":"Repair Shop",
            "type":"Services"
        },
        {
            "category":"Building & Trades",
            "subcategory":"Plumbing",
            "type":"Services"
        }
    ],
    "sg:phone":"+1 480 991 5256",
    "sg:postcode":"85260",
    "sg:province":"AZ",
    "sg:tags":[
        "equipment",
        "air",
        "conditioning",
        "contractor"
    ],
    "wof:name":"M & K Air Conditioning and Htg",
    "wof:placetype":"venue"
},
  "geometry": {"coordinates":[-111.922302,33.592957],"type":"Point"}
}