{
  "type": "Feature",
  "properties": {
    "iso:country":"US",
    "sg:address":"721 E Dunlap Ave",
    "sg:city":"Phoenix",
    "sg:classifiers":[
        {
            "category":"Bars & Pubs",
            "type":"Food & Drink"
        }
    ],
    "sg:phone":"+1 602 861 1034",
    "sg:postcode":"85020",
    "sg:province":"AZ",
    "sg:tags":[
        "drinking",
        "eating"
    ],
    "wof:name":"Big Daddy's Sports Lounge",
    "wof:placetype":"venue"
},
  "geometry": {"coordinates":[-112.063046,33.567688],"type":"Point"}
}