{
  "type": "Feature",
  "properties": {
    "addr:full":"2217 W Windsor Ave Phoenix AZ 85009",
    "addr:housenumber":"2217",
    "addr:postcode":"85009",
    "addr:street":"W Windsor Ave",
    "iso:country":"US",
    "sg:address":"2217 W Windsor Ave",
    "sg:city":"Phoenix",
    "sg:classifiers":[
        {
            "category":"Building & Trades",
            "subcategory":"Construction",
            "type":"Services"
        }
    ],
    "sg:phone":"+1 602 271 4642",
    "sg:postcode":"85009",
    "sg:province":"AZ",
    "sg:tags":[
        "mfg",
        "kitchen",
        "cabinet",
        "wood",
        "contractor",
        "carpentry"
    ],
    "wof:name":"Bradford Millwork Inc",
    "wof:placetype":"venue"
},
  "geometry": {"coordinates":[-112.107292,33.478666],"type":"Point"}
}