{
  "type": "Feature",
  "properties": {
    "addr:full":"522 W Muriel Dr Phoenix AZ 85023",
    "addr:housenumber":"522",
    "addr:postcode":"85023",
    "addr:street":"W Muriel Dr",
    "iso:country":"US",
    "sg:address":"522 W Muriel Dr",
    "sg:city":"Phoenix",
    "sg:classifiers":[
        {
            "category":"Building & Trades",
            "subcategory":"Construction",
            "type":"Services"
        }
    ],
    "sg:phone":"+1 602 795 8352",
    "sg:postcode":"85023",
    "sg:province":"AZ",
    "sg:tags":[
        "hanging",
        "contractor"
    ],
    "wof:name":"Super K Painting",
    "wof:placetype":"venue"
},
  "geometry": {"coordinates":[-112.081324,33.646012],"type":"Point"}
}