{
  "type": "Feature",
  "properties": {
    "iso:country":"US",
    "sg:address":"3432 W Lupine Ave",
    "sg:city":"Phoenix",
    "sg:classifiers":[
        {
            "category":"Professional",
            "subcategory":"Employment Agencies",
            "type":"Services"
        }
    ],
    "sg:phone":"+1 602 795 8693",
    "sg:postcode":"85029",
    "sg:province":"AZ",
    "sg:tags":[
        "contractor"
    ],
    "wof:name":"Alex Kelly Attorney Services",
    "wof:placetype":"venue"
},
  "geometry": {"coordinates":[-112.132558,33.590544],"type":"Point"}
}