{
  "type": "Feature",
  "properties": {
    "addr:full":"4030 E Thunderbird Rd B Phoenix AZ 85032",
    "addr:housenumber":"4030",
    "addr:postcode":"85032",
    "addr:street":"E Thunderbird Rd B",
    "iso:country":"US",
    "sg:address":"4030 E Thunderbird Rd B",
    "sg:city":"Phoenix",
    "sg:classifiers":[
        {
            "category":"Personal",
            "subcategory":"Beauty Salon",
            "type":"Services"
        }
    ],
    "sg:phone":"+1 602 485 1515",
    "sg:postcode":"85032",
    "sg:province":"AZ",
    "sg:tags":[
        "hair",
        "stylist"
    ],
    "wof:name":"Park's Hair Haven",
    "wof:placetype":"venue"
},
  "geometry": {"coordinates":[-111.994522,33.611839],"type":"Point"}
}