{
  "type": "Feature",
  "properties": {
    "iso:country":"US",
    "sg:address":"116 N Roosevelt Ave",
    "sg:city":"Chandler",
    "sg:classifiers":[
        {
            "category":"Wholesale",
            "subcategory":"Hardware",
            "type":"Manufacturing & Wholesale Goods"
        },
        {
            "category":"Home & Garden",
            "subcategory":"Building Materials",
            "type":"Retail Goods"
        }
    ],
    "sg:phone":"+1 480 940 8141",
    "sg:postcode":"85226",
    "sg:province":"AZ",
    "sg:tags":[
        "tool"
    ],
    "wof:name":"Discount Builders Supply Inc",
    "wof:placetype":"venue"
},
  "geometry": {"coordinates":[-111.951125,33.304026],"type":"Point"}
}