{
  "type": "Feature",
  "properties": {
    "iso:country":"US",
    "sg:address":"10215 N 28th Dr",
    "sg:city":"Phoenix",
    "sg:classifiers":[
        {
            "category":"Banks & Credit Unions",
            "subcategory":"Bank",
            "type":"Services"
        }
    ],
    "sg:phone":"+1 602 870 0459",
    "sg:postcode":"85051",
    "sg:province":"AZ",
    "sg:tags":[
        "loan",
        "financing",
        "real estate"
    ],
    "wof:name":"Household Finance",
    "wof:placetype":"venue"
},
  "geometry": {"coordinates":[-112.121883,33.580898],"type":"Point"}
}