{
  "type": "Feature",
  "properties": {
    "iso:country":"US",
    "sg:address":"2331 W Aloe Vera Dr",
    "sg:city":"Phoenix",
    "sg:classifiers":[
        {
            "category":"Manufacturing",
            "subcategory":"Tools & Machinery",
            "type":"Manufacturing & Wholesale Goods"
        }
    ],
    "sg:phone":"+1 623 518 2757",
    "sg:postcode":"85085",
    "sg:province":"AZ",
    "sg:tags":[
        "springs-wholesale",
        "manufacturer"
    ],
    "wof:name":"Canyon Springs",
    "wof:placetype":"venue"
},
  "geometry": {"coordinates":[-112.11014,33.78048],"type":"Point"}
}