{
  "type": "Feature",
  "properties": {
    "iso:country":"US",
    "sg:address":"6933 W Corrine Dr",
    "sg:city":"Peoria",
    "sg:classifiers":[
        {
            "category":"Personal",
            "type":"Services"
        },
        {
            "category":"Retail",
            "subcategory":"Event Space",
            "type":"Services"
        }
    ],
    "sg:phone":"+1 623 486 1626",
    "sg:postcode":"85381",
    "sg:province":"AZ",
    "sg:tags":[
        "facility",
        "hall",
        "planning",
        "reception",
        "party",
        "banquet"
    ],
    "wof:name":"Discount Wedding Invitation",
    "wof:placetype":"venue"
},
  "geometry": {"coordinates":[-112.207372,33.600424],"type":"Point"}
}