{
  "type": "Feature",
  "properties": {
    "iso:country":"US",
    "sg:address":"1646 N Arrowhead Dr",
    "sg:city":"Chandler",
    "sg:classifiers":[
        {
            "category":"Manufacturing",
            "subcategory":"Printing",
            "type":"Manufacturing & Wholesale Goods"
        }
    ],
    "sg:phone":"+1 602 989 7280",
    "sg:postcode":"85224",
    "sg:province":"AZ",
    "sg:tags":[
        "lithographic",
        "commercial"
    ],
    "wof:name":"T&T Printing",
    "wof:placetype":"venue"
},
  "geometry": {"coordinates":[-111.86723600000001,33.331365],"type":"Point"}
}