{
  "type": "Feature",
  "properties": {
    "iso:country":"US",
    "sg:address":"4515 S McClintock Dr",
    "sg:city":"Tempe",
    "sg:classifiers":[
        {
            "category":"Professional",
            "type":"Services"
        }
    ],
    "sg:phone":"+1 480 820 2923",
    "sg:postcode":"85282",
    "sg:province":"AZ",
    "wof:name":"Laura Nelson",
    "wof:placetype":"venue"
},
  "geometry": {"coordinates":[-111.909114,33.384638],"type":"Point"}
}