{
  "type": "Feature",
  "properties": {
    "iso:country":"US",
    "sg:address":"4735 E Camp Lowell Dr",
    "sg:city":"Tucson",
    "sg:classifiers":[
        {
            "category":"Real Estate",
            "subcategory":"Real Estate Agent",
            "type":"Services"
        }
    ],
    "sg:phone":"+1 520 327 3350",
    "sg:postcode":"85712",
    "sg:province":"AZ",
    "sg:tags":[
        "management"
    ],
    "wof:name":"Silver Home Rentals",
    "wof:placetype":"venue"
},
  "geometry": {"coordinates":[-110.891238,32.265336],"type":"Point"}
}