{
  "type": "Feature",
  "properties": {
    "iso:country":"US",
    "sg:address":"7315 W Buckeye Rd",
    "sg:city":"Phoenix",
    "sg:classifiers":[
        {
            "category":"Shopping",
            "type":"Retail Goods"
        }
    ],
    "sg:phone":"+1 623 936 5549",
    "sg:postcode":"85043",
    "sg:province":"AZ",
    "sg:tags":[
        "feed",
        "store"
    ],
    "wof:name":"Stockman Feeds",
    "wof:placetype":"venue"
},
  "geometry": {"coordinates":[-112.216881,33.437092],"type":"Point"}
}