{
  "type": "Feature",
  "properties": {
    "iso:country":"US",
    "sg:address":"8759 N 77th Dr",
    "sg:city":"Peoria",
    "sg:classifiers":[
        {
            "category":"Wholesale",
            "subcategory":"Hardware",
            "type":"Manufacturing & Wholesale Goods"
        }
    ],
    "sg:phone":"+1 623 979 3690",
    "sg:postcode":"85345",
    "sg:province":"AZ",
    "sg:tags":[
        "nut",
        "bolt"
    ],
    "wof:name":"Breslin Performance Products",
    "wof:placetype":"venue"
},
  "geometry": {"coordinates":[-112.225425,33.562881],"type":"Point"}
}