{
  "type": "Feature",
  "properties": {
    "addr:full":"1 Perkins Dr Prescott AZ 86301",
    "addr:housenumber":"1",
    "addr:postcode":"86301",
    "addr:street":"Perkins Dr",
    "iso:country":"US",
    "sg:address":"1 Perkins Dr",
    "sg:city":"Prescott",
    "sg:classifiers":[
        {
            "category":"Sports & Exercise",
            "subcategory":"Golf",
            "type":"Entertainment"
        }
    ],
    "sg:phone":"+1 928 776 7888",
    "sg:postcode":"86301",
    "sg:province":"AZ",
    "sg:tags":[
        "course"
    ],
    "sg:website":"www.antelopehillsgolf.com",
    "wof:name":"Antelope Hills Golf Course",
    "wof:placetype":"venue"
},
  "geometry": {"coordinates":[-112.429813,34.640193],"type":"Point"}
}