{
  "type": "Feature",
  "properties": {
    "iso:country":"US",
    "sg:address":"4146 W Camelback Rd",
    "sg:city":"Phoenix",
    "sg:classifiers":[
        {
            "category":"Manufacturing",
            "subcategory":"Tools & Machinery",
            "type":"Manufacturing & Wholesale Goods"
        },
        {
            "category":"Shopping",
            "subcategory":"Computers & Home Electronics",
            "type":"Retail Goods"
        }
    ],
    "sg:phone":"+1 602 347 8788",
    "sg:postcode":"85019",
    "sg:province":"AZ",
    "sg:tags":[
        "stereo",
        "electric",
        "high",
        "equipment",
        "stereophonic",
        "video",
        "equipment-dealers",
        "fidelity",
        "audio",
        "supplies-wholesale",
        "manufacturer"
    ],
    "wof:name":"Waels Sound Image",
    "wof:placetype":"venue"
},
  "geometry": {"coordinates":[-112.14799,33.509446],"type":"Point"}
}