{
  "type": "Feature",
  "properties": {
    "iso:country":"US",
    "sg:address":"1819 S Dobson Rd",
    "sg:city":"Mesa",
    "sg:classifiers":[
        {
            "category":"Real Estate",
            "subcategory":"Real Estate Agent",
            "type":"Services"
        }
    ],
    "sg:phone":"+1 480 491 3600",
    "sg:postcode":"85202",
    "sg:province":"AZ",
    "sg:tags":[
        "management"
    ],
    "wof:name":"Action Property Management",
    "wof:placetype":"venue"
},
  "geometry": {"coordinates":[-111.876289,33.381542],"type":"Point"}
}