{
  "type": "Feature",
  "properties": {
    "iso:country":"US",
    "sg:address":"1745 E River Rd",
    "sg:city":"Tucson",
    "sg:classifiers":[
        {
            "category":"Professional",
            "subcategory":"Management & Consulting",
            "type":"Services"
        }
    ],
    "sg:phone":"+1 520 325 9977",
    "sg:postcode":"85718",
    "sg:province":"AZ",
    "sg:tags":[
        "environmental",
        "planning"
    ],
    "wof:name":"Recon Consultants Inc",
    "wof:placetype":"venue"
},
  "geometry": {"coordinates":[-110.944909,32.287367],"type":"Point"}
}