{
  "type": "Feature",
  "properties": {
    "addr:full":"201 E Mcnair Dr Tempe AZ 85283",
    "addr:housenumber":"201",
    "addr:postcode":"85283",
    "addr:street":"E Mcnair Dr",
    "iso:country":"US",
    "sg:address":"201 E Mcnair Dr",
    "sg:city":"Tempe",
    "sg:classifiers":[
        {
            "category":"Manufacturing",
            "subcategory":"Building Materials",
            "type":"Manufacturing & Wholesale Goods"
        }
    ],
    "sg:phone":"+1 480 831 0024",
    "sg:postcode":"85283",
    "sg:province":"AZ",
    "sg:tags":[
        "materials-wholesale",
        "manufacturer"
    ],
    "wof:name":"Building Solutions",
    "wof:placetype":"venue"
},
  "geometry": {"coordinates":[-111.93634,33.35043],"type":"Point"}
}