{
  "type": "Feature",
  "properties": {
    "iso:country":"US",
    "sg:address":"44166 W Roth Rd",
    "sg:city":"Maricopa",
    "sg:classifiers":[
        {
            "category":"Wholesale",
            "subcategory":"Scrap",
            "type":"Manufacturing & Wholesale Goods"
        }
    ],
    "sg:phone":"+1 480 200 3331",
    "sg:postcode":"85138",
    "sg:province":"AZ",
    "sg:tags":[
        "junk"
    ],
    "wof:name":"American Junk",
    "wof:placetype":"venue"
},
  "geometry": {"coordinates":[-112.042355,33.067139],"type":"Point"}
}