{
  "type": "Feature",
  "properties": {
    "iso:country":"US",
    "sg:address":"7401 N la Cholla Blvd",
    "sg:city":"Tucson",
    "sg:classifiers":[
        {
            "category":"Fast Food",
            "type":"Food & Drink"
        }
    ],
    "sg:phone":"+1 520 531 8219",
    "sg:postcode":"85741",
    "sg:province":"AZ",
    "sg:tags":[
        "restaurant"
    ],
    "sg:website":"http://www.arbys.com",
    "wof:name":"Arby's",
    "wof:placetype":"venue"
},
  "geometry": {"coordinates":[-111.012852,32.341553],"type":"Point"}
}