{
  "type": "Feature",
  "properties": {
    "iso:country":"US",
    "sg:address":"2240 McCulloch Blvd N",
    "sg:city":"Lake Havasu City",
    "sg:classifiers":[
        {
            "category":"Professional",
            "subcategory":"Lawyer & Legal Services",
            "type":"Services"
        }
    ],
    "sg:phone":"+1 928 854 6673",
    "sg:postcode":"86403",
    "sg:province":"AZ",
    "sg:tags":[
        "attorney"
    ],
    "wof:name":"Dana R Stoker Law Office",
    "wof:placetype":"venue"
},
  "geometry": {"coordinates":[-114.322118,34.475747],"type":"Point"}
}