{
  "type": "Feature",
  "properties": {
    "iso:country":"US",
    "sg:address":"6628 S 5th Pl",
    "sg:city":"Phoenix",
    "sg:classifiers":[
        {
            "category":"Professional",
            "subcategory":"Accounting & Tax Preparation",
            "type":"Services"
        }
    ],
    "sg:phone":"+1 623 535 7299",
    "sg:postcode":"85042",
    "sg:province":"AZ",
    "sg:tags":[
        "bookkeeping",
        "general"
    ],
    "wof:name":"Avalon Accounting Svc",
    "wof:placetype":"venue"
},
  "geometry": {"coordinates":[-112.06708,33.385541],"type":"Point"}
}