{
  "type": "Feature",
  "properties": {
    "addr:full":"3800 W Chandler Blvd Chandler AZ 85226",
    "addr:housenumber":"3800",
    "addr:postcode":"85226",
    "addr:street":"W Chandler Blvd",
    "iso:country":"US",
    "sg:address":"3800 W Chandler Blvd",
    "sg:city":"Chandler",
    "sg:classifiers":[
        {
            "category":"Communications",
            "type":"Services"
        }
    ],
    "sg:phone":"+1 480 812 9422",
    "sg:postcode":"85226",
    "sg:province":"AZ",
    "sg:tags":[
        "communication"
    ],
    "wof:name":"Konnect Communications",
    "wof:placetype":"venue"
},
  "geometry": {"coordinates":[-111.909289,33.305456],"type":"Point"}
}