{
  "type": "Feature",
  "properties": {
    "iso:country":"US",
    "sg:address":"1183 N Recker Rd",
    "sg:city":"Gilbert",
    "sg:classifiers":[
        {
            "category":"Social Services",
            "subcategory":"Child Care",
            "type":"Services"
        },
        {
            "category":"Education",
            "subcategory":"Preschool",
            "type":"Public Place"
        }
    ],
    "sg:phone":"+1 480 807 6528",
    "sg:postcode":"85234",
    "sg:province":"AZ",
    "sg:tags":[
        "kindergarten",
        "nursery",
        "day"
    ],
    "sg:website":"http://www.advantagelearningcenters.com",
    "wof:name":"Advantage Learning Centers",
    "wof:placetype":"venue"
},
  "geometry": {"coordinates":[-111.704857,33.369824],"type":"Point"}
}