{
  "type": "Feature",
  "properties": {
    "iso:country":"US",
    "sg:address":"2525 E Camelback Rd",
    "sg:city":"Phoenix",
    "sg:classifiers":[
        {
            "category":"Real Estate",
            "subcategory":"Real Estate Agent",
            "type":"Services"
        }
    ],
    "sg:phone":"+1 602 955 1122",
    "sg:postcode":"85016",
    "sg:province":"AZ",
    "wof:name":"Hendricks & Partners",
    "wof:placetype":"venue"
},
  "geometry": {"coordinates":[-112.02871500000001,33.509286],"type":"Point"}
}