{
  "type": "Feature",
  "properties": {
    "iso:country":"US",
    "sg:address":"11430 N 91st Dr",
    "sg:city":"Peoria",
    "sg:classifiers":[
        {
            "category":"Wholesale",
            "subcategory":"Drugs",
            "type":"Manufacturing & Wholesale Goods"
        }
    ],
    "sg:phone":"+1 623 594 4241",
    "sg:postcode":"85345",
    "sg:province":"AZ",
    "wof:name":"Herbalife International Inc",
    "wof:placetype":"venue"
},
  "geometry": {"coordinates":[-112.25584000000001,33.588723],"type":"Point"}
}