{
  "type": "Feature",
  "properties": {
    "iso:country":"US",
    "sg:address":"8716 E Sheridan St",
    "sg:city":"Scottsdale",
    "sg:classifiers":[
        {
            "category":"Travel",
            "subcategory":"Travel Agent",
            "type":"Entertainment"
        }
    ],
    "sg:phone":"+1 480 949 0199",
    "sg:postcode":"85257",
    "sg:province":"AZ",
    "sg:tags":[
        "operator",
        "tour"
    ],
    "wof:name":"Pro Leisure Tour Sportswear",
    "wof:placetype":"venue"
},
  "geometry": {"coordinates":[-111.89373,33.474628],"type":"Point"}
}