{
  "type": "Feature",
  "properties": {
    "iso:country":"US",
    "sg:address":"737 W Magnolia St",
    "sg:city":"Phoenix",
    "sg:classifiers":[
        {
            "category":"Retail",
            "subcategory":"Auto Repair",
            "type":"Services"
        }
    ],
    "sg:phone":"+1 602 712 1251",
    "sg:postcode":"85007",
    "sg:province":"AZ",
    "sg:tags":[
        "body",
        "automobile",
        "painting",
        "repairing"
    ],
    "wof:name":"Alaniz Auto Body",
    "wof:placetype":"venue"
},
  "geometry": {"coordinates":[-112.08295099999999,33.424333],"type":"Point"}
}