{
  "type": "Feature",
  "properties": {
    "iso:country":"US",
    "sg:address":"2257 E Broadway Blvd",
    "sg:city":"Tucson",
    "sg:classifiers":[
        {
            "category":"Shopping",
            "subcategory":"Clothing, Apparel, & Fashions",
            "type":"Retail Goods"
        }
    ],
    "sg:phone":"+1 520 294 9199",
    "sg:postcode":"85719",
    "sg:province":"AZ",
    "wof:name":"Lauras Novelties",
    "wof:placetype":"venue"
},
  "geometry": {"coordinates":[-110.937358,32.221546],"type":"Point"}
}