{
  "type": "Feature",
  "properties": {
    "addr:full":"19636 N 19th Pl Phoenix AZ 85024",
    "addr:housenumber":"19636",
    "addr:postcode":"85024",
    "addr:street":"N 19Th Pl",
    "iso:country":"US",
    "sg:address":"19636 N 19th Pl",
    "sg:city":"Phoenix",
    "sg:classifiers":[
        {
            "category":"Home & Garden",
            "subcategory":"Home Furnishings",
            "type":"Retail Goods"
        }
    ],
    "sg:phone":"+1 602 697 6284",
    "sg:postcode":"85024",
    "sg:province":"AZ",
    "sg:tags":[
        "mirror"
    ],
    "wof:name":"Mirrors & More, Inc.",
    "wof:placetype":"venue"
},
  "geometry": {"coordinates":[-112.040257,33.665442],"type":"Point"}
}