{
  "type": "Feature",
  "properties": {
    "addr:full":"423 W Cherry Ave Flagstaff AZ 86001",
    "addr:housenumber":"423",
    "addr:postcode":"86001",
    "addr:street":"W Cherry Ave",
    "iso:country":"US",
    "sg:address":"423 W Cherry Ave",
    "sg:city":"Flagstaff",
    "sg:classifiers":[
        {
            "category":"Travel",
            "subcategory":"Hotels & Motels",
            "type":"Entertainment"
        }
    ],
    "sg:phone":"+1 928 774 3249",
    "sg:postcode":"86001",
    "sg:province":"AZ",
    "sg:tags":[
        "breakfast",
        "accommodation",
        "bed"
    ],
    "wof:name":"Dierker House Bed & Breakfast",
    "wof:placetype":"venue"
},
  "geometry": {"coordinates":[-111.653155,35.201896],"type":"Point"}
}