{
  "type": "Feature",
  "properties": {
    "addr:full":"1346 E Harmony Cir Mesa AZ 85204",
    "addr:housenumber":"1346",
    "addr:postcode":"85204",
    "addr:street":"E Harmony Cir",
    "iso:country":"US",
    "sg:address":"1346 E Harmony Cir",
    "sg:city":"Mesa",
    "sg:classifiers":[
        {
            "category":"Health Services",
            "subcategory":"Chiropractor",
            "type":"Services"
        }
    ],
    "sg:phone":"+1 480 926 7372",
    "sg:postcode":"85204",
    "sg:province":"AZ",
    "wof:name":"Russell Lisonbee",
    "wof:placetype":"venue"
},
  "geometry": {"coordinates":[-111.80256900000001,33.389736],"type":"Point"}
}