{
  "type": "Feature",
  "properties": {
    "iso:country":"US",
    "sg:address":"4951 E Grant Rd",
    "sg:city":"Tucson",
    "sg:classifiers":[
        {
            "category":"Freight",
            "type":"Transportation"
        }
    ],
    "sg:phone":"+1 520 881 5445",
    "sg:postcode":"85712",
    "sg:province":"AZ",
    "sg:tags":[
        "shipping",
        "agent"
    ],
    "sg:website":"www.postnet.com",
    "wof:name":"Postnet",
    "wof:placetype":"venue"
},
  "geometry": {"coordinates":[-110.886939,32.250726],"type":"Point"}
}