{
  "type": "Feature",
  "properties": {
    "iso:country":"US",
    "sg:address":"1522 W Todd Dr",
    "sg:city":"Tempe",
    "sg:classifiers":[
        {
            "category":"Building & Trades",
            "subcategory":"Electrical",
            "type":"Services"
        }
    ],
    "sg:phone":"+1 480 413 9278",
    "sg:postcode":"85283",
    "sg:province":"AZ",
    "sg:tags":[
        "electric",
        "contractor"
    ],
    "wof:name":"Ketring Electric",
    "wof:placetype":"venue"
},
  "geometry": {"coordinates":[-111.966123,33.352815],"type":"Point"}
}