{
  "type": "Feature",
  "properties": {
    "addr:full":"11627 E Onyx Ave Scottsdale AZ 85259",
    "addr:housenumber":"11627",
    "addr:postcode":"85259",
    "addr:street":"E Onyx Ave",
    "iso:country":"US",
    "sg:address":"11627 E Onyx Ave",
    "sg:city":"Scottsdale",
    "sg:classifiers":[
        {
            "category":"Building & Trades",
            "subcategory":"Construction",
            "type":"Services"
        }
    ],
    "sg:phone":"+1 480 860 2328",
    "sg:postcode":"85259",
    "sg:province":"AZ",
    "sg:tags":[
        "painting",
        "contractor"
    ],
    "wof:name":"Lynn Stanley",
    "wof:placetype":"venue"
},
  "geometry": {"coordinates":[-111.82893,33.578164],"type":"Point"}
}