{
  "type": "Feature",
  "properties": {
    "addr:full":"9970 W Monterosa Ave Phoenix AZ 85037",
    "addr:housenumber":"9970",
    "addr:postcode":"85037",
    "addr:street":"W Monterosa Ave",
    "iso:country":"US",
    "sg:address":"9970 W Monterosa Ave",
    "sg:city":"Phoenix",
    "sg:classifiers":[
        {
            "category":"Professional",
            "subcategory":"Engineering",
            "type":"Services"
        }
    ],
    "sg:phone":"+1 623 872 8267",
    "sg:postcode":"85037",
    "sg:province":"AZ",
    "sg:tags":[
        "engineer"
    ],
    "wof:name":"Cortes Engineering Inc",
    "wof:placetype":"venue"
},
  "geometry": {"coordinates":[-112.276257,33.496027],"type":"Point"}
}