{
  "type": "Feature",
  "properties": {
    "iso:country":"US",
    "sg:address":"3034 E Indigo Bay Ct",
    "sg:city":"Gilbert",
    "sg:classifiers":[
        {
            "category":"Building & Trades",
            "subcategory":"Construction",
            "type":"Services"
        }
    ],
    "sg:phone":"+1 480 854 3124",
    "sg:postcode":"85234",
    "sg:province":"AZ",
    "sg:tags":[
        "contractor"
    ],
    "wof:name":"Valley Erectors",
    "wof:placetype":"venue"
},
  "geometry": {"coordinates":[-111.72563700000001,33.372656],"type":"Point"}
}