{
  "type": "Feature",
  "properties": {
    "addr:full":"14443 N 73rd St Scottsdale AZ 85260",
    "addr:housenumber":"14443",
    "addr:postcode":"85260",
    "addr:street":"N 73Rd St",
    "iso:country":"US",
    "sg:address":"14443 N 73rd St",
    "sg:city":"Scottsdale",
    "sg:classifiers":[
        {
            "category":"Transit Center",
            "subcategory":"Freight",
            "type":"Transportation"
        },
        {
            "category":"Professional",
            "subcategory":"Advertising",
            "type":"Services"
        }
    ],
    "sg:phone":"+1 602 749 9499",
    "sg:postcode":"85260",
    "sg:province":"AZ",
    "sg:tags":[
        "outdoor"
    ],
    "wof:name":"Ao Media, Southwest, Inc.",
    "wof:placetype":"venue"
},
  "geometry": {"coordinates":[-111.92447300000001,33.614897],"type":"Point"}
}