{
  "type": "Feature",
  "properties": {
    "iso:country":"US",
    "sg:address":"3839 W Whitten St",
    "sg:city":"Chandler",
    "sg:classifiers":[
        {
            "category":"Manufacturing",
            "subcategory":"Printing",
            "type":"Manufacturing & Wholesale Goods"
        }
    ],
    "sg:phone":"+1 602 225 7199",
    "sg:postcode":"85226",
    "sg:province":"AZ",
    "sg:tags":[
        "lithographic",
        "commercial"
    ],
    "wof:name":"Wallace Offset Service",
    "wof:placetype":"venue"
},
  "geometry": {"coordinates":[-111.909737,33.29623],"type":"Point"}
}