{
  "type": "Feature",
  "properties": {
    "iso:country":"US",
    "sg:address":"3035 S Ellsworth Rd",
    "sg:city":"Mesa",
    "sg:classifiers":[
        {
            "category":"Building & Trades",
            "subcategory":"Construction",
            "type":"Services"
        }
    ],
    "sg:phone":"+1 480 354 8233",
    "sg:postcode":"85212",
    "sg:province":"AZ",
    "sg:tags":[
        "general",
        "contractor"
    ],
    "wof:name":"Kroll Construction",
    "wof:placetype":"venue"
},
  "geometry": {"coordinates":[-111.635762,33.360165],"type":"Point"}
}