{
  "type": "Feature",
  "properties": {
    "iso:country":"US",
    "sg:address":"1235 S Gilbert Rd",
    "sg:city":"Mesa",
    "sg:phone":"+1 480 926 3308",
    "sg:postcode":"85204",
    "sg:province":"AZ",
    "sg:tags":[
        "fuel",
        "diesel"
    ],
    "wof:name":"Jamie Diesel",
    "wof:placetype":"venue"
},
  "geometry": {"coordinates":[-111.78823800000001,33.391217],"type":"Point"}
}