{
  "type": "Feature",
  "properties": {
    "iso:country":"US",
    "sg:address":"2260 N Rosemont Blvd",
    "sg:city":"Tucson",
    "sg:classifiers":[
        {
            "category":"Health Services",
            "subcategory":"Health Practitioner",
            "type":"Services"
        }
    ],
    "sg:phone":"+1 520 327 5959",
    "sg:postcode":"85712",
    "sg:province":"AZ",
    "sg:tags":[
        "therapist",
        "physical"
    ],
    "wof:name":"William J Adelman",
    "wof:placetype":"venue"
},
  "geometry": {"coordinates":[-110.883967,32.249792],"type":"Point"}
}