{
  "type": "Feature",
  "properties": {
    "iso:country":"US",
    "sg:address":"1120 S Country Club Dr Ste 104",
    "sg:city":"Mesa",
    "sg:phone":"+1 480 833 1166",
    "sg:postcode":"85210",
    "sg:province":"AZ",
    "wof:name":"Sports Exchange",
    "wof:placetype":"venue"
},
  "geometry": {"coordinates":[-111.840073,33.394744],"type":"Point"}
}