{
  "type": "Feature",
  "properties": {
    "addr:full":"4026 E Broadway Rd Phoenix AZ 85040",
    "addr:housenumber":"4026",
    "addr:postcode":"85040",
    "addr:street":"E Broadway Rd",
    "iso:country":"US",
    "sg:address":"4026 E Broadway Rd",
    "sg:city":"Phoenix",
    "sg:classifiers":[
        {
            "category":"Communications",
            "subcategory":"Radio Station",
            "type":"Services"
        }
    ],
    "sg:phone":"+1 602 759 1922",
    "sg:postcode":"85040",
    "sg:province":"AZ",
    "sg:tags":[
        "broadcast"
    ],
    "wof:name":"930 Enterprizes",
    "wof:placetype":"venue"
},
  "geometry": {"coordinates":[-111.99471,33.40728],"type":"Point"}
}