{
  "type": "Feature",
  "properties": {
    "addr:full":"640 S River Dr Tempe AZ 85281",
    "addr:housenumber":"640",
    "addr:postcode":"85281",
    "addr:street":"S River Dr",
    "iso:country":"US",
    "sg:address":"640 S River Dr",
    "sg:city":"Tempe",
    "sg:phone":"+1 480 446 7788",
    "sg:postcode":"85281",
    "sg:province":"AZ",
    "sg:website":"http://www.alaskanqualityservices.com",
    "wof:name":"Alaskan Quality Svc",
    "wof:placetype":"venue"
},
  "geometry": {"coordinates":[-111.895554,33.423754],"type":"Point"}
}