{
  "type": "Feature",
  "properties": {
    "iso:country":"US",
    "sg:address":"8160 E Butherus Dr #5",
    "sg:city":"Scottsdale",
    "sg:classifiers":[
        {
            "category":"Insurance",
            "subcategory":"Life Insurance",
            "type":"Services"
        },
        {
            "category":"Banks & Credit Unions",
            "subcategory":"Financial Services",
            "type":"Services"
        }
    ],
    "sg:phone":"+1 480 556 9931",
    "sg:postcode":"85260",
    "sg:province":"AZ",
    "sg:tags":[
        "consultant",
        "planning"
    ],
    "sg:website":"http://www.spivakfinancial.com",
    "wof:name":"Spivak Financial Group, An Office of Centaurus Financial, Inc.",
    "wof:placetype":"venue"
},
  "geometry": {"coordinates":[-111.90535300000001,33.620459],"type":"Point"}
}