{
  "type": "Feature",
  "properties": {
    "addr:full":"4827 E Indian School Rd Phoenix AZ 85018",
    "addr:housenumber":"4827",
    "addr:postcode":"85018",
    "addr:street":"E Indian School Rd",
    "iso:country":"US",
    "sg:address":"4827 E Indian School Rd",
    "sg:city":"Phoenix",
    "sg:classifiers":[
        {
            "category":"Retail",
            "subcategory":"Auto Repair",
            "type":"Services"
        }
    ],
    "sg:phone":"+1 602 840 3640",
    "sg:postcode":"85018",
    "sg:province":"AZ",
    "sg:tags":[
        "repairing",
        "automobile"
    ],
    "sg:website":"http://clickserve.dartsearch.net/link/click?lid=43000000313869003&ds_s_kwgid=58000000006820725&ds_e_matchtype={MatchType}&ds_e_kwdid={OrderItemId}&ds_e_adid={AdId}&ds_url_v=2",
    "wof:name":"Spitfire Automotive",
    "wof:placetype":"venue"
},
  "geometry": {"coordinates":[-111.977599,33.494602],"type":"Point"}
}