{
  "type": "Feature",
  "properties": {
    "iso:country":"US",
    "sg:address":"2500 N 44th St",
    "sg:city":"Phoenix",
    "sg:classifiers":[
        {
            "category":"Autos & Motor Vehicles",
            "subcategory":"Auto Supplies",
            "type":"Retail Goods"
        }
    ],
    "sg:phone":"+1 602 957 2200",
    "sg:postcode":"85008",
    "sg:province":"AZ",
    "wof:name":"Centenial Leasing and Sales",
    "wof:placetype":"venue"
},
  "geometry": {"coordinates":[-111.987032,33.476003],"type":"Point"}
}