{
  "type": "Feature",
  "properties": {
    "iso:country":"US",
    "sg:address":"8141 W Camelback Road",
    "sg:city":"Phoenix",
    "sg:classifiers":[
        {
            "category":"Health Services",
            "subcategory":"Dentist",
            "type":"Services"
        }
    ],
    "sg:phone":"+1 623 848 9100",
    "sg:postcode":"85033",
    "sg:province":"AZ",
    "wof:name":"Coyote Ridge Family Dentistry",
    "wof:placetype":"venue"
},
  "geometry": {"coordinates":[-112.235316,33.508804],"type":"Point"}
}