{
  "type": "Feature",
  "properties": {
    "iso:country":"US",
    "sg:address":"8518 N 7th St",
    "sg:city":"Phoenix",
    "sg:classifiers":[
        {
            "category":"Manufacturing",
            "subcategory":"Tobacco Products",
            "type":"Manufacturing & Wholesale Goods"
        },
        {
            "category":"Shopping",
            "subcategory":"Tobacco",
            "type":"Retail Goods"
        }
    ],
    "sg:phone":"+1 602 997 2324",
    "sg:postcode":"85020",
    "sg:province":"AZ",
    "sg:tags":[
        "cigar",
        "tobacco-wholesale",
        "cigarette",
        "smoke",
        "stack",
        "manufacturer"
    ],
    "wof:name":"M J Smoke Shop",
    "wof:placetype":"venue"
},
  "geometry": {"coordinates":[-112.06529,33.560636],"type":"Point"}
}