{
  "type": "Feature",
  "properties": {
    "addr:full":"12011 W Thunderbird Rd El Mirage AZ 85335",
    "addr:housenumber":"12011",
    "addr:postcode":"85335",
    "addr:street":"W Thunderbird Rd",
    "iso:country":"US",
    "sg:address":"12011 W Thunderbird Rd",
    "sg:city":"El Mirage",
    "sg:classifiers":[
        {
            "category":"Shopping",
            "subcategory":"Discount & Variety Stores",
            "type":"Retail Goods"
        }
    ],
    "sg:phone":"+1 623 583 8339",
    "sg:postcode":"85335",
    "sg:province":"AZ",
    "wof:name":"99 Cents Discount Store",
    "wof:placetype":"venue"
},
  "geometry": {"coordinates":[-112.318512,33.608855],"type":"Point"}
}