{
  "type": "Feature",
  "properties": {
    "iso:country":"US",
    "sg:address":"4141 N 32nd St Ste 100",
    "sg:city":"Phoenix",
    "sg:classifiers":[
        {
            "category":"Health Services",
            "subcategory":"Dentist",
            "type":"Services"
        }
    ],
    "sg:phone":"+1 602 667 3600",
    "sg:postcode":"85018",
    "sg:province":"AZ",
    "sg:tags":[
        "dentists-endodontists"
    ],
    "sg:website":"http://www.valleyendodontic.com",
    "wof:name":"North Valley Endodontics",
    "wof:placetype":"venue"
},
  "geometry": {"coordinates":[-112.012979,33.496772],"type":"Point"}
}