{
  "type": "Feature",
  "properties": {
    "iso:country":"US",
    "sg:address":"1776 E Ash St",
    "sg:city":"Globe",
    "sg:classifiers":[
        {
            "category":"Professional",
            "type":"Services"
        }
    ],
    "sg:phone":"+1 928 425 3017",
    "sg:postcode":"85501",
    "sg:province":"AZ",
    "sg:tags":[
        "environmental",
        "analysis"
    ],
    "wof:name":"Wheeler & Assoc Arizona Ranch",
    "wof:placetype":"venue"
},
  "geometry": {"coordinates":[-110.762937,33.390213],"type":"Point"}
}