{
  "type": "Feature",
  "properties": {
    "addr:full":"7049 E Mcdowell Rd Scottsdale AZ 85257",
    "addr:housenumber":"7049",
    "addr:postcode":"85257",
    "addr:street":"E Mcdowell Rd",
    "iso:country":"US",
    "sg:address":"7049 E Mcdowell Rd",
    "sg:city":"Scottsdale",
    "sg:classifiers":[
        {
            "category":"Restaurant",
            "type":"Food & Drink"
        }
    ],
    "sg:menulink":"http://www.allmenus.com/az/phoenix/4685-shararazad-mediterranean-grill/menu/",
    "sg:phone":"+1 480 785 0865",
    "sg:postcode":"85257",
    "sg:province":"AZ",
    "sg:tags":[
        "mediterranean"
    ],
    "wof:name":"Shararazad Mediterranean Grill",
    "wof:placetype":"venue"
},
  "geometry": {"coordinates":[-111.929344,33.465538],"type":"Point"}
}