{
  "type": "Feature",
  "properties": {
    "addr:full":"455 S 75th Ave Phoenix AZ 85043",
    "addr:housenumber":"455",
    "addr:postcode":"85043",
    "addr:street":"S 75Th Ave",
    "iso:country":"US",
    "sg:address":"455 S 75th Ave",
    "sg:city":"Phoenix",
    "sg:classifiers":[
        {
            "category":"Wholesale",
            "subcategory":"Non-durable Goods",
            "type":"Manufacturing & Wholesale Goods"
        }
    ],
    "sg:phone":"+1 623 907 2299",
    "sg:postcode":"85043",
    "sg:province":"AZ",
    "sg:tags":[
        "merchandise-wholesale"
    ],
    "wof:name":"Psf Distribution",
    "wof:placetype":"venue"
},
  "geometry": {"coordinates":[-112.22111099999999,33.443097],"type":"Point"}
}