{
  "type": "Feature",
  "properties": {
    "iso:country":"US",
    "sg:address":"2555 N Coyote Dr",
    "sg:city":"Tucson",
    "sg:classifiers":[
        {
            "category":"Wholesale",
            "subcategory":"Groceries",
            "type":"Manufacturing & Wholesale Goods"
        }
    ],
    "sg:phone":"+1 520 623 5282",
    "sg:postcode":"85745",
    "sg:province":"AZ",
    "sg:tags":[
        "coffee"
    ],
    "wof:name":"Cafe La Finca",
    "wof:placetype":"venue"
},
  "geometry": {"coordinates":[-111.005033,32.251388],"type":"Point"}
}