{
  "type": "Feature",
  "properties": {
    "addr:full":"102 W Gurley St Prescott AZ 86301",
    "addr:housenumber":"102",
    "addr:postcode":"86301",
    "addr:street":"W Gurley St",
    "iso:country":"US",
    "sg:address":"102 W Gurley St",
    "sg:city":"Prescott",
    "sg:classifiers":[
        {
            "category":"Banks & Credit Unions",
            "subcategory":"Bank",
            "type":"Services"
        }
    ],
    "sg:phone":"+1 928 771 8100",
    "sg:postcode":"86301",
    "sg:province":"AZ",
    "sg:website":"www.nbarizona.com",
    "wof:name":"National Bank",
    "wof:placetype":"venue"
},
  "geometry": {"coordinates":[-112.468734,34.54196],"type":"Point"}
}