{
  "type": "Feature",
  "properties": {
    "iso:country":"US",
    "sg:address":"205 W Riverside Dr",
    "sg:city":"Parker",
    "sg:classifiers":[
        {
            "category":"Fast Food",
            "type":"Food & Drink"
        },
        {
            "category":"Restaurant",
            "type":"Food & Drink"
        }
    ],
    "sg:phone":"+1 928 669 2842",
    "sg:postcode":"85344",
    "sg:province":"AZ",
    "sg:tags":[
        "shop",
        "hamburger",
        "dog",
        "hot",
        "fountain",
        "soda",
        "american"
    ],
    "sg:website":"http://www.awrestaurants.com",
    "wof:name":"A & W Restaurants",
    "wof:placetype":"venue"
},
  "geometry": {"coordinates":[-114.280325,34.154126],"type":"Point"}
}