{
  "type": "Feature",
  "properties": {
    "addr:full":"5310 W Glendale Ave Glendale AZ 85301",
    "addr:housenumber":"5310",
    "addr:postcode":"85301",
    "addr:street":"W Glendale Ave",
    "iso:country":"US",
    "sg:address":"5310 W Glendale Ave",
    "sg:city":"Glendale",
    "sg:classifiers":[
        {
            "category":"Manufacturing",
            "subcategory":"Printing",
            "type":"Manufacturing & Wholesale Goods"
        }
    ],
    "sg:phone":"+1 623 939 0092",
    "sg:postcode":"85301",
    "sg:province":"AZ",
    "sg:tags":[
        "printer",
        "commercial",
        "offset"
    ],
    "wof:name":"Air Rapid Printing Co Inc",
    "wof:placetype":"venue"
},
  "geometry": {"coordinates":[-112.17475,33.538588],"type":"Point"}
}