{
  "type": "Feature",
  "properties": {
    "iso:country":"US",
    "sg:address":"2244 W Bell Rd",
    "sg:city":"Phoenix",
    "sg:classifiers":[
        {
            "category":"Bars & Pubs",
            "type":"Food & Drink"
        }
    ],
    "sg:phone":"+1 602 863 3725",
    "sg:postcode":"85023",
    "sg:province":"AZ",
    "sg:tags":[
        "drinking"
    ],
    "wof:name":"Shenanigans Bar & Grill",
    "wof:placetype":"venue"
},
  "geometry": {"coordinates":[-112.106786,33.640115],"type":"Point"}
}