{
  "type": "Feature",
  "properties": {
    "iso:country":"US",
    "sg:address":"5710 E 22nd St",
    "sg:city":"Tucson",
    "sg:classifiers":[
        {
            "category":"Retail",
            "subcategory":"Auto Repair",
            "type":"Services"
        }
    ],
    "sg:phone":"+1 520 745 1075",
    "sg:postcode":"85711",
    "sg:province":"AZ",
    "sg:tags":[
        "automobile",
        "lubrication"
    ],
    "wof:name":"Jiffy Lube",
    "wof:placetype":"venue"
},
  "geometry": {"coordinates":[-110.867304,32.20687],"type":"Point"}
}