{
  "type": "Feature",
  "properties": {
    "iso:country":"US",
    "sg:address":"11 Bisbee Rd",
    "sg:city":"Bisbee",
    "sg:classifiers":[
        {
            "category":"Utilities",
            "subcategory":"Telephone",
            "type":"Services"
        }
    ],
    "sg:phone":"+1 520 432 2240",
    "sg:postcode":"85603",
    "sg:province":"AZ",
    "sg:tags":[
        "telecommunication"
    ],
    "wof:name":"Qwest Solutions Ctr",
    "wof:placetype":"venue"
},
  "geometry": {"coordinates":[-109.891678,31.42752],"type":"Point"}
}