{
  "type": "Feature",
  "properties": {
    "iso:country":"US",
    "sg:address":"4717 N 7th Ave",
    "sg:city":"Phoenix",
    "sg:classifiers":[
        {
            "category":"Autos & Motor Vehicles",
            "subcategory":"Automobile Sales",
            "type":"Retail Goods"
        },
        {
            "category":"Building & Trades",
            "subcategory":"Equipment Rental",
            "type":"Services"
        }
    ],
    "sg:phone":"+1 602 274 1200",
    "sg:postcode":"85013",
    "sg:province":"AZ",
    "sg:tags":[
        "trucks-industrial",
        "yard",
        "store",
        "contractors'"
    ],
    "wof:name":"Rainbow Rentals",
    "wof:placetype":"venue"
},
  "geometry": {"coordinates":[-112.082469,33.506316],"type":"Point"}
}