{
  "type": "Feature",
  "properties": {
    "iso:country":"US",
    "sg:address":"1329 E Apache St",
    "sg:city":"Cottonwood",
    "sg:classifiers":[
        {
            "category":"Organizations",
            "subcategory":"Religious Organization",
            "type":"Services"
        }
    ],
    "sg:phone":"+1 928 634 5809",
    "sg:postcode":"86326",
    "sg:province":"AZ",
    "sg:tags":[
        "church"
    ],
    "wof:name":"Evangel Worship Ctr",
    "wof:placetype":"venue"
},
  "geometry": {"coordinates":[-112.012863,34.740322],"type":"Point"}
}