{
  "type": "Feature",
  "properties": {
    "addr:full":"1300 W University Ave Flagstaff AZ 86001",
    "addr:housenumber":"1300",
    "addr:postcode":"86001",
    "addr:street":"W University Ave",
    "iso:country":"US",
    "sg:address":"1300 W University Ave",
    "sg:city":"Flagstaff",
    "sg:classifiers":[
        {
            "category":"Banks & Credit Unions",
            "subcategory":"Bank",
            "type":"Services"
        }
    ],
    "sg:phone":"+1 928 226 8266",
    "sg:postcode":"86001",
    "sg:province":"AZ",
    "sg:tags":[
        "loan",
        "real estate"
    ],
    "wof:name":"RBC Mortgage Co",
    "wof:placetype":"venue"
},
  "geometry": {"coordinates":[-111.67086500000001,35.184177],"type":"Point"}
}