{
  "type": "Feature",
  "properties": {
    "iso:country":"US",
    "sg:address":"1300 W University Ave",
    "sg:city":"Flagstaff",
    "sg:classifiers":[
        {
            "category":"Banks & Credit Unions",
            "subcategory":"Bank",
            "type":"Services"
        }
    ],
    "sg:phone":"+1 928 226 8266",
    "sg:postcode":"86001",
    "sg:province":"AZ",
    "sg:tags":[
        "loan",
        "real estate"
    ],
    "wof:name":"RBC Mortgage Co",
    "wof:placetype":"venue"
},
  "geometry": {"coordinates":[-111.670865,35.184177],"type":"Point"}
}