{
  "type": "Feature",
  "properties": {
    "iso:country":"US",
    "sg:address":"4821 N 20th St",
    "sg:city":"Phoenix",
    "sg:classifiers":[
        {
            "category":"Sports & Exercise",
            "subcategory":"Gym",
            "type":"Entertainment"
        }
    ],
    "sg:phone":"+1 602 241 9800",
    "sg:postcode":"85016",
    "sg:province":"AZ",
    "sg:tags":[
        "club",
        "health",
        "studio",
        "gymnasium"
    ],
    "wof:name":"L A Fitness Sports Club",
    "wof:placetype":"venue"
},
  "geometry": {"coordinates":[-112.03877799999999,33.507804],"type":"Point"}
}