{
  "type": "Feature",
  "properties": {
    "iso:country":"US",
    "sg:address":"3846 E Lupine Ave",
    "sg:city":"Phoenix",
    "sg:classifiers":[
        {
            "category":"Building & Trades",
            "subcategory":"Construction",
            "type":"Services"
        }
    ],
    "sg:phone":"+1 602 996 1201",
    "sg:postcode":"85028",
    "sg:province":"AZ",
    "sg:tags":[
        "contractor"
    ],
    "wof:name":"Jk Drywall",
    "wof:placetype":"venue"
},
  "geometry": {"coordinates":[-111.997674,33.591067],"type":"Point"}
}