{
  "type": "Feature",
  "properties": {
    "addr:full":"604 E Balboa Dr Tempe AZ 85282",
    "addr:housenumber":"604",
    "addr:postcode":"85282",
    "addr:street":"E Balboa Dr",
    "iso:country":"US",
    "sg:address":"604 E Balboa Dr",
    "sg:city":"Tempe",
    "sg:classifiers":[
        {
            "category":"Professional",
            "subcategory":"Research",
            "type":"Services"
        },
        {
            "category":"Education",
            "subcategory":"Library",
            "type":"Public Place"
        }
    ],
    "sg:phone":"+1 480 966 2724",
    "sg:postcode":"85282",
    "sg:province":"AZ",
    "wof:name":"Collaborative Research Institute",
    "wof:placetype":"venue"
},
  "geometry": {"coordinates":[-111.93045600000001,33.397788],"type":"Point"}
}