{
  "type": "Feature",
  "properties": {
    "iso:country":"US",
    "sg:address":"130 W Hampton Ave",
    "sg:city":"Mesa",
    "sg:classifiers":[
        {
            "category":"Retail",
            "subcategory":"Repair Shop",
            "type":"Services"
        }
    ],
    "sg:phone":"+1 480 641 8582",
    "sg:postcode":"85210",
    "sg:province":"AZ",
    "sg:tags":[
        "equipment",
        "printing"
    ],
    "wof:name":"First Call Svc",
    "wof:placetype":"venue"
},
  "geometry": {"coordinates":[-111.834988,33.387927],"type":"Point"}
}