{
  "type": "Feature",
  "properties": {
    "addr:full":"8450 E Plaza Ave Scottsdale AZ 85250",
    "addr:housenumber":"8450",
    "addr:postcode":"85250",
    "addr:street":"E Plaza Ave",
    "iso:country":"US",
    "sg:address":"8450 E Plaza Ave",
    "sg:city":"Scottsdale",
    "sg:classifiers":[
        {
            "category":"Professional",
            "subcategory":"Management & Consulting",
            "type":"Services"
        }
    ],
    "sg:phone":"+1 480 994 8069",
    "sg:postcode":"85250",
    "sg:province":"AZ",
    "sg:tags":[
        "training",
        "sales"
    ],
    "wof:name":"Sales Training Institute",
    "wof:placetype":"venue"
},
  "geometry": {"coordinates":[-111.89910500000001,33.514544],"type":"Point"}
}