{
  "type": "Feature",
  "properties": {
    "iso:country":"US",
    "sg:address":"8800 N Gainey Center Dr",
    "sg:city":"Scottsdale",
    "sg:classifiers":[
        {
            "category":"Travel",
            "subcategory":"Travel Agent",
            "type":"Entertainment"
        }
    ],
    "sg:phone":"+1 480 905 8550",
    "sg:postcode":"85258",
    "sg:province":"AZ",
    "sg:tags":[
        "agency"
    ],
    "wof:name":"Architect of Travel",
    "wof:placetype":"venue"
},
  "geometry": {"coordinates":[-111.917249,33.564873],"type":"Point"}
}