{
  "type": "Feature",
  "properties": {
    "iso:country":"US",
    "sg:address":"4750 E Grant Rd",
    "sg:city":"Tucson",
    "sg:classifiers":[
        {
            "category":"Retail",
            "subcategory":"Veterinary Services",
            "type":"Services"
        }
    ],
    "sg:phone":"+1 520 321 0277",
    "sg:postcode":"85712",
    "sg:province":"AZ",
    "sg:tags":[
        "veterinarian"
    ],
    "wof:name":"Four Paws Veterinairy Clinic",
    "wof:placetype":"venue"
},
  "geometry": {"coordinates":[-110.891527,32.250574],"type":"Point"}
}