{
  "type": "Feature",
  "properties": {
    "iso:country":"US",
    "sg:address":"7131 E Tanque Verde Rd",
    "sg:city":"Tucson",
    "sg:classifiers":[
        {
            "category":"Shopping",
            "subcategory":"Bicycles & Sporting Goods",
            "type":"Retail Goods"
        }
    ],
    "sg:phone":"+1 520 721 9176",
    "sg:postcode":"85715",
    "sg:province":"AZ",
    "sg:tags":[
        "equipment",
        "golf",
        "supply"
    ],
    "wof:name":"Pro Golf Discount",
    "wof:placetype":"venue"
},
  "geometry": {"coordinates":[-110.838967,32.250845],"type":"Point"}
}