{
  "type": "Feature",
  "properties": {
    "iso:country":"US",
    "sg:address":"9040 S Rita Rd",
    "sg:city":"Tucson",
    "sg:classifiers":[
        {
            "category":"Professional",
            "type":"Services"
        }
    ],
    "sg:phone":"+1 520 382 2460",
    "sg:postcode":"85747",
    "sg:province":"AZ",
    "wof:name":"LSI Logic Storage Systems",
    "wof:placetype":"venue"
},
  "geometry": {"coordinates":[-110.80430699999999,32.089769],"type":"Point"}
}