{
  "type": "Feature",
  "properties": {
    "addr:full":"4970 S Alma School Road Chandler AZ 85248",
    "addr:housenumber":"4970",
    "addr:postcode":"85248",
    "addr:street":"S Alma School Road",
    "iso:country":"US",
    "sg:address":"4970 S Alma School Road",
    "sg:city":"Chandler",
    "sg:classifiers":[
        {
            "category":"Shopping",
            "subcategory":"Pharmacy",
            "type":"Retail Goods"
        }
    ],
    "sg:phone":"+1 480 883 0260",
    "sg:postcode":"85248",
    "sg:province":"AZ",
    "sg:tags":[
        "drugstore"
    ],
    "wof:name":"Pharmacy At Safeway",
    "wof:placetype":"venue"
},
  "geometry": {"coordinates":[-111.85900599999999,33.234475],"type":"Point"}
}