{
  "type": "Feature",
  "properties": {
    "addr:full":"4646 E Van Buren St Ste Phoenix AZ 85008",
    "addr:housenumber":"4646",
    "addr:postcode":"85008",
    "addr:street":"E Van Buren St Ste",
    "iso:country":"US",
    "sg:address":"4646 E Van Buren St Ste",
    "sg:city":"Phoenix",
    "sg:classifiers":[
        {
            "category":"Wholesale",
            "subcategory":"Construction Materials",
            "type":"Manufacturing & Wholesale Goods"
        },
        {
            "category":"Home & Garden",
            "subcategory":"Building Materials",
            "type":"Retail Goods"
        },
        {
            "category":"Building & Trades",
            "subcategory":"Construction",
            "type":"Services"
        },
        {
            "category":"Manufacturing",
            "subcategory":"Building Materials",
            "type":"Manufacturing & Wholesale Goods"
        }
    ],
    "sg:phone":"+1 602 416 2600",
    "sg:postcode":"85008",
    "sg:province":"AZ",
    "sg:tags":[
        "concrete-stamped",
        "cement",
        "concrete",
        "shape",
        "decorative",
        "mixed",
        "concrete-ready",
        "block"
    ],
    "wof:name":"Cemex Corp.",
    "wof:placetype":"venue"
},
  "geometry": {"coordinates":[-111.985474,33.451172],"type":"Point"}
}