{
  "type": "Feature",
  "properties": {
    "iso:country":"US",
    "sg:address":"2540 S Quail Run",
    "sg:city":"Cottonwood",
    "sg:classifiers":[
        {
            "category":"Autos & Motor Vehicles",
            "subcategory":"Fuel & Gas Station",
            "type":"Retail Goods"
        }
    ],
    "sg:phone":"+1 928 646 5161",
    "sg:postcode":"86326",
    "sg:province":"AZ",
    "sg:tags":[
        "station",
        "gasoline"
    ],
    "wof:name":"Village Gasery",
    "wof:placetype":"venue"
},
  "geometry": {"coordinates":[-112.024759,34.693317],"type":"Point"}
}