{
  "type": "Feature",
  "properties": {
    "addr:full":"3344 N Oracle Rd Tucson AZ 85705",
    "addr:housenumber":"3344",
    "addr:postcode":"85705",
    "addr:street":"N Oracle Rd",
    "iso:country":"US",
    "sg:address":"3344 N Oracle Rd",
    "sg:city":"Tucson",
    "sg:classifiers":[
        {
            "category":"Restaurant",
            "type":"Food & Drink"
        }
    ],
    "sg:menulink":"http://www.allmenus.com/az/tucson/198775-kfc---kentucky-fried-chicken/menu/",
    "sg:phone":"+1 520 888 6590",
    "sg:postcode":"85705",
    "sg:province":"AZ",
    "sg:tags":[
        "american",
        "chicken"
    ],
    "wof:name":"KFC - Kentucky Fried Chicken",
    "wof:placetype":"venue"
},
  "geometry": {"coordinates":[-110.977541,32.267366],"type":"Point"}
}