{
  "type": "Feature",
  "properties": {
    "iso:country":"US",
    "sg:address":"1346 S Rose Cir",
    "sg:city":"Mesa",
    "sg:classifiers":[
        {
            "category":"Building & Trades",
            "subcategory":"Landscaping Services",
            "type":"Services"
        }
    ],
    "sg:phone":"+1 480 620 5761",
    "sg:postcode":"85204",
    "sg:province":"AZ",
    "sg:tags":[
        "lawn",
        "maintenance",
        "grounds"
    ],
    "wof:name":"Lawn Keeper",
    "wof:placetype":"venue"
},
  "geometry": {"coordinates":[-111.782999,33.390974],"type":"Point"}
}