{
  "type": "Feature",
  "properties": {
    "addr:full":"3290 W Morgan Rd Tucson AZ 85745",
    "addr:housenumber":"3290",
    "addr:postcode":"85745",
    "addr:street":"W Morgan Rd",
    "iso:country":"US",
    "sg:address":"3290 W Morgan Rd",
    "sg:city":"Tucson",
    "sg:classifiers":[
        {
            "category":"Banks & Credit Unions",
            "subcategory":"Financial Services",
            "type":"Services"
        }
    ],
    "sg:phone":"+1 520 743 7128",
    "sg:postcode":"85745",
    "sg:province":"AZ",
    "sg:tags":[
        "company",
        "holding"
    ],
    "wof:name":"Cimarron Holdings LLC",
    "wof:placetype":"venue"
},
  "geometry": {"coordinates":[-111.037342,32.261696],"type":"Point"}
}