{
  "type": "Feature",
  "properties": {
    "addr:full":"2434 E Paradise Ln Phoenix AZ 85032",
    "addr:housenumber":"2434",
    "addr:postcode":"85032",
    "addr:street":"E Paradise Ln",
    "iso:country":"US",
    "sg:address":"2434 E Paradise Ln",
    "sg:city":"Phoenix",
    "sg:classifiers":[
        {
            "category":"Real Estate",
            "subcategory":"Real Estate Operator",
            "type":"Services"
        }
    ],
    "sg:phone":"+1 602 571 4291",
    "sg:postcode":"85032",
    "sg:province":"AZ",
    "sg:tags":[
        "apartment"
    ],
    "wof:name":"Paradise Apartments",
    "wof:placetype":"venue"
},
  "geometry": {"coordinates":[-112.029234,33.633272],"type":"Point"}
}