{
  "type": "Feature",
  "properties": {
    "iso:country":"US",
    "sg:address":"1850 W Drake Dr",
    "sg:city":"Tempe",
    "sg:classifiers":[
        {
            "category":"Shopping",
            "subcategory":"Bicycles & Sporting Goods",
            "type":"Retail Goods"
        },
        {
            "category":"Wholesale",
            "subcategory":"Sporting Goods",
            "type":"Manufacturing & Wholesale Goods"
        }
    ],
    "sg:phone":"+1 602 431 1057",
    "sg:postcode":"85283",
    "sg:province":"AZ",
    "sg:tags":[
        "golf",
        "supply",
        "equipment",
        "supplies-wholesale",
        "manufacturer"
    ],
    "wof:name":"Sedona Golf Products",
    "wof:placetype":"venue"
},
  "geometry": {"coordinates":[-111.968302,33.355092],"type":"Point"}
}