{
  "type": "Feature",
  "properties": {
    "iso:country":"US",
    "sg:address":"95 Arch Dr",
    "sg:city":"Sedona",
    "sg:classifiers":[
        {
            "category":"Professional",
            "subcategory":"Business Services",
            "type":"Services"
        }
    ],
    "sg:phone":"+1 928 284 9444",
    "sg:postcode":"86351",
    "sg:province":"AZ",
    "sg:tags":[
        "appraiser"
    ],
    "wof:name":"Bell Rock Vehicle Appraisal",
    "wof:placetype":"venue"
},
  "geometry": {"coordinates":[-111.767413,34.786714],"type":"Point"}
}