{
  "type": "Feature",
  "properties": {
    "iso:country":"US",
    "sg:address":"7009 E Acoma Dr",
    "sg:city":"Scottsdale",
    "sg:classifiers":[
        {
            "category":"Personal",
            "subcategory":"Beauty Salon",
            "type":"Services"
        }
    ],
    "sg:phone":"+1 480 860 1333",
    "sg:postcode":"85254",
    "sg:province":"AZ",
    "sg:tags":[
        "treatment",
        "skin"
    ],
    "wof:name":"Sunskincare By Annette",
    "wof:placetype":"venue"
},
  "geometry": {"coordinates":[-111.92988200000001,33.618525],"type":"Point"}
}