{
  "type": "Feature",
  "properties": {
    "addr:full":"330 S Gilbert Rd Mesa AZ 85204",
    "addr:housenumber":"330",
    "addr:postcode":"85204",
    "addr:street":"S Gilbert Rd",
    "iso:country":"US",
    "sg:address":"330 S Gilbert Rd",
    "sg:city":"Mesa",
    "sg:classifiers":[
        {
            "category":"Travel",
            "subcategory":"Hotels & Motels",
            "type":"Entertainment"
        }
    ],
    "sg:phone":"+1 480 898 0464",
    "sg:postcode":"85204",
    "sg:province":"AZ",
    "wof:name":"Chinese Panda Inn Buffet",
    "wof:placetype":"venue"
},
  "geometry": {"coordinates":[-111.788376,33.408783],"type":"Point"}
}