{
  "type": "Feature",
  "properties": {
    "iso:country":"US",
    "sg:address":"2101 E Kathleen Rd",
    "sg:city":"Phoenix",
    "sg:classifiers":[
        {
            "category":"Building & Trades",
            "subcategory":"Construction",
            "type":"Services"
        },
        {
            "category":"Manufacturing",
            "subcategory":"Building Materials",
            "type":"Manufacturing & Wholesale Goods"
        }
    ],
    "sg:phone":"+1 602 296 7354",
    "sg:postcode":"85022",
    "sg:province":"AZ",
    "sg:tags":[
        "roofing",
        "industrial",
        "sheet",
        "work",
        "metal",
        "contractor",
        "siding",
        "contractors-commercial"
    ],
    "wof:name":"Aladdin Roofing",
    "wof:placetype":"venue"
},
  "geometry": {"coordinates":[-112.03812,33.63023],"type":"Point"}
}