{
  "type": "Feature",
  "properties": {
    "iso:country":"US",
    "sg:address":"40505 N Kearny Way",
    "sg:city":"Phoenix",
    "sg:classifiers":[
        {
            "category":"Professional",
            "subcategory":"Business Services",
            "type":"Services"
        }
    ],
    "sg:phone":"+1 623 551 2344",
    "sg:postcode":"85086",
    "sg:province":"AZ",
    "sg:tags":[
        "embroidery"
    ],
    "wof:name":"Custom Image Printwear",
    "wof:placetype":"venue"
},
  "geometry": {"coordinates":[-112.105522,33.85334],"type":"Point"}
}