{
  "type": "Feature",
  "properties": {
    "addr:full":"2501 Happy Valley Phoenix AZ 85027",
    "addr:housenumber":"2501",
    "addr:postcode":"85027",
    "addr:street":"Happy Valley",
    "iso:country":"US",
    "sg:address":"2501 Happy Valley",
    "sg:city":"Phoenix",
    "sg:classifiers":[
        {
            "category":"Restaurant",
            "type":"Food & Drink"
        }
    ],
    "sg:menulink":"http://www.allmenus.com/az/deer-valley/121829-keva-juice/menu/",
    "sg:phone":"+1 623 580 0062",
    "sg:postcode":"85027",
    "sg:province":"AZ",
    "sg:tags":[
        "smoothy",
        "juice",
        "american"
    ],
    "wof:name":"Keva Juice",
    "wof:placetype":"venue"
},
  "geometry": {"coordinates":[-112.111808,33.7121],"type":"Point"}
}