{
  "type": "Feature",
  "properties": {
    "iso:country":"US",
    "sg:address":"1750 W Culver St",
    "sg:city":"Phoenix",
    "sg:classifiers":[
        {
            "category":"Utilities",
            "subcategory":"Recycling",
            "type":"Services"
        },
        {
            "category":"Shopping",
            "subcategory":"Discount & Variety Stores",
            "type":"Retail Goods"
        }
    ],
    "sg:phone":"+1 602 253 2336",
    "sg:postcode":"85007",
    "sg:province":"AZ",
    "sg:tags":[
        "salvage",
        "surplus",
        "merchandise"
    ],
    "sg:website":"http://www.recyclingmadeez.com",
    "wof:name":"EZ Recycling",
    "wof:placetype":"venue"
},
  "geometry": {"coordinates":[-112.096953,33.463146],"type":"Point"}
}