{
  "type": "Feature",
  "properties": {
    "iso:country":"US",
    "sg:address":"650 W Linda Vista Blvd",
    "sg:city":"Tucson",
    "sg:classifiers":[
        {
            "category":"Education",
            "subcategory":"School",
            "type":"Public Place"
        }
    ],
    "sg:phone":"+1 520 896 3100",
    "sg:postcode":"85704",
    "sg:province":"AZ",
    "wof:name":"Sierra Oaks Community School",
    "wof:placetype":"venue"
},
  "geometry": {"coordinates":[-110.98201899999999,32.380931],"type":"Point"}
}