{
  "type": "Feature",
  "properties": {
    "iso:country":"US",
    "sg:address":"43 S San Francisco St",
    "sg:city":"Flagstaff",
    "sg:classifiers":[
        {
            "category":"Social Services",
            "type":"Services"
        }
    ],
    "sg:phone":"+1 928 774 9125",
    "sg:postcode":"86001",
    "sg:province":"AZ",
    "sg:tags":[
        "organization",
        "welfare"
    ],
    "wof:name":"Catholic Charities",
    "wof:placetype":"venue"
},
  "geometry": {"coordinates":[-111.648062,35.197168],"type":"Point"}
}