{
  "type": "Feature",
  "properties": {
    "iso:country":"US",
    "sg:address":"2512 E Greenway Rd",
    "sg:city":"Phoenix",
    "sg:classifiers":[
        {
            "category":"Retail",
            "subcategory":"Auto Repair",
            "type":"Services"
        }
    ],
    "sg:phone":"+1 602 992 6909",
    "sg:postcode":"85032",
    "sg:province":"AZ",
    "sg:tags":[
        "repairing",
        "automobile"
    ],
    "wof:name":"Bill's Automotive",
    "wof:placetype":"venue"
},
  "geometry": {"coordinates":[-112.027404,33.626384],"type":"Point"}
}