{
  "type": "Feature",
  "properties": {
    "iso:country":"US",
    "sg:address":"26600 S la Canoa Dr",
    "sg:city":"Amado",
    "sg:classifiers":[
        {
            "category":"Real Estate",
            "subcategory":"Real Estate Services",
            "type":"Services"
        },
        {
            "category":"Real Estate",
            "subcategory":"Real Estate Agent",
            "type":"Services"
        }
    ],
    "sg:phone":"+1 520 398 9187",
    "sg:postcode":"85645",
    "sg:province":"AZ",
    "sg:tags":[
        "buyer",
        "broker"
    ],
    "wof:name":"Goretcki Realty",
    "wof:placetype":"venue"
},
  "geometry": {"coordinates":[-111.002164,31.76984],"type":"Point"}
}