{
  "type": "Feature",
  "properties": {
    "addr:full":"801 W Wickenburg Way Wickenburg AZ 85390",
    "addr:housenumber":"801",
    "addr:postcode":"85390",
    "addr:street":"W Wickenburg Way",
    "iso:country":"US",
    "sg:address":"801 W Wickenburg Way",
    "sg:city":"Wickenburg",
    "sg:classifiers":[
        {
            "category":"Communications",
            "subcategory":"Radio Station",
            "type":"Services"
        }
    ],
    "sg:phone":"+1 602 254 6644",
    "sg:postcode":"85390",
    "sg:province":"AZ",
    "sg:tags":[
        "company",
        "broadcasting"
    ],
    "wof:name":"KSWG",
    "wof:placetype":"venue"
},
  "geometry": {"coordinates":[-112.745631,33.965832],"type":"Point"}
}