{
  "type": "Feature",
  "properties": {
    "iso:country":"US",
    "sg:address":"1977 E Vinedo Ln",
    "sg:city":"Tempe",
    "sg:classifiers":[
        {
            "category":"Banks & Credit Unions",
            "subcategory":"Investment Brokerage",
            "type":"Services"
        }
    ],
    "sg:phone":"+1 480 345 0588",
    "sg:postcode":"85284",
    "sg:province":"AZ",
    "sg:tags":[
        "advisory"
    ],
    "wof:name":"Alliant Capital",
    "wof:placetype":"venue"
},
  "geometry": {"coordinates":[-111.905119,33.347072],"type":"Point"}
}