{
  "type": "Feature",
  "properties": {
    "iso:country":"US",
    "sg:address":"2912 N Tucson Blvd",
    "sg:city":"Tucson",
    "sg:classifiers":[
        {
            "category":"Professional",
            "subcategory":"Lawyer & Legal Services",
            "type":"Services"
        }
    ],
    "sg:phone":"+1 520 881 2300",
    "sg:postcode":"85716",
    "sg:province":"AZ",
    "sg:tags":[
        "attorney",
        "law",
        "plan",
        "business",
        "bankruptcy"
    ],
    "wof:name":"Blankenship, Albert Jr Law Office Of",
    "wof:placetype":"venue"
},
  "geometry": {"coordinates":[-110.93527,32.259645],"type":"Point"}
}