{
  "type": "Feature",
  "properties": {
    "iso:country":"US",
    "sg:address":"829 S Rural Rd",
    "sg:city":"Tempe",
    "sg:classifiers":[
        {
            "category":"Restaurant",
            "type":"Food & Drink"
        }
    ],
    "sg:phone":"+1 480 517 1188",
    "sg:postcode":"85281",
    "sg:province":"AZ",
    "wof:name":"Devil House",
    "wof:placetype":"venue"
},
  "geometry": {"coordinates":[-111.92623,33.42198],"type":"Point"}
}