{
  "type": "Feature",
  "properties": {
    "addr:full":"515 S 48th St Ste 108 Tempe AZ 85281",
    "addr:housenumber":"515",
    "addr:postcode":"85281",
    "addr:street":"S 48Th St Ste 108",
    "iso:country":"US",
    "sg:address":"515 S 48th St Ste 108",
    "sg:city":"Tempe",
    "sg:classifiers":[
        {
            "category":"Conference Center",
            "type":"Public Place"
        }
    ],
    "sg:phone":"+1 480 894 0200",
    "sg:postcode":"85281",
    "sg:province":"AZ",
    "sg:tags":[
        "device",
        "backflow",
        "prevention"
    ],
    "sg:website":"http://www.msiaz.net",
    "wof:name":"Metering Services Inc",
    "wof:placetype":"venue"
},
  "geometry": {"coordinates":[-111.976358,33.422421],"type":"Point"}
}