{
  "type": "Feature",
  "properties": {
    "iso:country":"US",
    "sg:address":"2427 E Cairo Dr",
    "sg:city":"Tempe",
    "sg:classifiers":[
        {
            "category":"Personal",
            "type":"Services"
        }
    ],
    "sg:phone":"+1 718 491 1241",
    "sg:postcode":"85282",
    "sg:province":"AZ",
    "sg:tags":[
        "assistant"
    ],
    "wof:name":"Artfag",
    "wof:placetype":"venue"
},
  "geometry": {"coordinates":[-111.888296,33.399032],"type":"Point"}
}