{
  "type": "Feature",
  "properties": {
    "iso:country":"US",
    "sg:address":"13441 N 37th Dr",
    "sg:city":"Phoenix",
    "sg:classifiers":[
        {
            "category":"Building & Trades",
            "subcategory":"Construction",
            "type":"Services"
        }
    ],
    "sg:phone":"+1 602 843 1719",
    "sg:postcode":"85029",
    "sg:province":"AZ",
    "sg:tags":[
        "painting",
        "contractor"
    ],
    "wof:name":"First Rate Custom Coating Inc",
    "wof:placetype":"venue"
},
  "geometry": {"coordinates":[-112.139018,33.608872],"type":"Point"}
}