{
  "type": "Feature",
  "properties": {
    "iso:country":"US",
    "sg:address":"714 E Van Buren St",
    "sg:city":"Phoenix",
    "sg:classifiers":[
        {
            "category":"Professional",
            "subcategory":"Research",
            "type":"Services"
        }
    ],
    "sg:phone":"+1 602 470 2129",
    "sg:postcode":"85006",
    "sg:province":"AZ",
    "sg:tags":[
        "development",
        "laboratory"
    ],
    "sg:website":"www.ribomed.com",
    "wof:name":"Ribomed Biotechnologies Inc",
    "wof:placetype":"venue"
},
  "geometry": {"coordinates":[-112.064379,33.451429],"type":"Point"}
}