{
  "type": "Feature",
  "properties": {
    "iso:country":"US",
    "sg:address":"2832 N Power Rd",
    "sg:city":"Mesa",
    "sg:classifiers":[
        {
            "category":"Coffee & Tea",
            "type":"Food & Drink"
        }
    ],
    "sg:menulink":"http://www.allmenus.com/az/phoenix/108299-starbucks-coffee/menu/",
    "sg:phone":"+1 480 830 2876",
    "sg:postcode":"85215",
    "sg:province":"AZ",
    "sg:tags":[
        "american"
    ],
    "wof:name":"Starbucks Coffee",
    "wof:placetype":"venue"
},
  "geometry": {"coordinates":[-111.68404,33.467217],"type":"Point"}
}