{
  "type": "Feature",
  "properties": {
    "iso:country":"US",
    "sg:address":"15820 N 11th St",
    "sg:city":"Phoenix",
    "sg:classifiers":[
        {
            "category":"Real Estate",
            "subcategory":"Real Estate Agent",
            "type":"Services"
        }
    ],
    "sg:phone":"+1 602 363 8248",
    "sg:postcode":"85022",
    "sg:province":"AZ",
    "wof:name":"Az Homes",
    "wof:placetype":"venue"
},
  "geometry": {"coordinates":[-112.058447,33.629339],"type":"Point"}
}