{
  "type": "Feature",
  "properties": {
    "iso:country":"US",
    "sg:address":"2617 Player Ave",
    "sg:city":"Sierra Vista",
    "sg:classifiers":[
        {
            "category":"Manufacturing",
            "subcategory":"Textiles",
            "type":"Manufacturing & Wholesale Goods"
        }
    ],
    "sg:phone":"+1 520 378 1853",
    "sg:postcode":"85650",
    "sg:province":"AZ",
    "sg:tags":[
        "plant",
        "silk",
        "finishing",
        "fiber"
    ],
    "wof:name":"Team Concepts",
    "wof:placetype":"venue"
},
  "geometry": {"coordinates":[-110.25831599999999,31.52087],"type":"Point"}
}