{
  "type": "Feature",
  "properties": {
    "addr:full":"220 W Cll de Las Tiendas Green Valley AZ 85614",
    "addr:housenumber":"220",
    "addr:postcode":"85614",
    "addr:street":"W Cll De Las Tiendas",
    "iso:country":"US",
    "sg:address":"220 W Cll de Las Tiendas",
    "sg:city":"Green Valley",
    "sg:classifiers":[
        {
            "category":"Professional",
            "subcategory":"Business Services",
            "type":"Services"
        }
    ],
    "sg:phone":"+1 520 762 0764",
    "sg:postcode":"85614",
    "sg:province":"AZ",
    "sg:tags":[
        "embroidery"
    ],
    "wof:name":"Stitch N Vaders",
    "wof:placetype":"venue"
},
  "geometry": {"coordinates":[-110.994056,31.899133],"type":"Point"}
}