{
  "type": "Feature",
  "properties": {
    "iso:country":"US",
    "sg:address":"18206 N 19th Ave",
    "sg:city":"Phoenix",
    "sg:classifiers":[
        {
            "category":"Real Estate",
            "subcategory":"Real Estate Agent",
            "type":"Services"
        }
    ],
    "sg:phone":"+1 602 200 9939",
    "sg:postcode":"85023",
    "sg:province":"AZ",
    "wof:name":"Net Growth Realty",
    "wof:placetype":"venue"
},
  "geometry": {"coordinates":[-112.099799,33.651435],"type":"Point"}
}