{
  "type": "Feature",
  "properties": {
    "iso:country":"US",
    "sg:address":"107 E Aero Dr",
    "sg:city":"Payson",
    "sg:classifiers":[
        {
            "category":"Health Services",
            "subcategory":"Hospital",
            "type":"Services"
        }
    ],
    "sg:phone":"+1 928 474 2668",
    "sg:postcode":"85541",
    "sg:province":"AZ",
    "sg:tags":[
        "mental"
    ],
    "wof:name":"Southwest Behavioral Health",
    "wof:placetype":"venue"
},
  "geometry": {"coordinates":[-111.32758,34.228399],"type":"Point"}
}