{
  "type": "Feature",
  "properties": {
    "iso:country":"US",
    "sg:address":"10430 N 19th Ave",
    "sg:city":"Phoenix",
    "sg:classifiers":[
        {
            "category":"Food & Beverages",
            "subcategory":"Meat & Fish",
            "type":"Retail Goods"
        }
    ],
    "sg:phone":"+1 602 943 7277",
    "sg:postcode":"85021",
    "sg:province":"AZ",
    "sg:tags":[
        "seafood"
    ],
    "wof:name":"Song Song Oriental Seafood Mkt",
    "wof:placetype":"venue"
},
  "geometry": {"coordinates":[-112.099704,33.581978],"type":"Point"}
}