{
  "type": "Feature",
  "properties": {
    "addr:full":"8100 E Camelback Rd Scottsdale AZ 85251",
    "addr:housenumber":"8100",
    "addr:postcode":"85251",
    "addr:street":"E Camelback Rd",
    "iso:country":"US",
    "sg:address":"8100 E Camelback Rd",
    "sg:city":"Scottsdale",
    "sg:classifiers":[
        {
            "category":"Restaurant",
            "type":"Food & Drink"
        }
    ],
    "sg:phone":"+1 480 990 7639",
    "sg:postcode":"85251",
    "sg:province":"AZ",
    "sg:tags":[
        "style",
        "american",
        "french",
        "family"
    ],
    "sg:website":"http://www.dinewithsci.com/Home_Page.html",
    "wof:name":"L'Ecole",
    "wof:placetype":"venue"
},
  "geometry": {"coordinates":[-111.907127,33.502121],"type":"Point"}
}