{
  "type": "Feature",
  "properties": {
    "iso:country":"US",
    "sg:address":"923 E Gurley St",
    "sg:city":"Prescott",
    "sg:classifiers":[
        {
            "category":"Banks & Credit Unions",
            "subcategory":"Bank",
            "type":"Services"
        }
    ],
    "sg:phone":"+1 928 778 2497",
    "sg:postcode":"86301",
    "sg:province":"AZ",
    "sg:tags":[
        "state",
        "commercial"
    ],
    "wof:name":"Compass Bank",
    "wof:placetype":"venue"
},
  "geometry": {"coordinates":[-112.457545,34.542078],"type":"Point"}
}