{
  "type": "Feature",
  "properties": {
    "iso:country":"US",
    "sg:address":"177 N Arroyo Blvd",
    "sg:city":"Nogales",
    "sg:classifiers":[
        {
            "category":"Shopping",
            "subcategory":"Clothing, Apparel, & Fashions",
            "type":"Retail Goods"
        }
    ],
    "sg:phone":"+1 520 287 9647",
    "sg:postcode":"85621",
    "sg:province":"AZ",
    "wof:name":"Fashion Corner",
    "wof:placetype":"venue"
},
  "geometry": {"coordinates":[-110.940842,31.335804],"type":"Point"}
}