{
  "type": "Feature",
  "properties": {
    "addr:full":"2950 East Germann Rd Chandler AZ 85249",
    "addr:housenumber":"2950",
    "addr:postcode":"85249",
    "addr:street":"East Germann Rd",
    "iso:country":"US",
    "sg:address":"2950 East Germann Rd",
    "sg:city":"Chandler",
    "sg:classifiers":[
        {
            "category":"Restaurant",
            "type":"Food & Drink"
        }
    ],
    "sg:phone":"+1 480 857 6500",
    "sg:postcode":"85249",
    "sg:province":"AZ",
    "sg:tags":[
        "steakhouse"
    ],
    "sg:website":"www.longhornsteakhouse.com",
    "wof:name":"LongHorn Steakhouse",
    "wof:placetype":"venue"
},
  "geometry": {"coordinates":[-111.790556,33.277426],"type":"Point"}
}