{
  "type": "Feature",
  "properties": {
    "iso:country":"US",
    "sg:address":"7241 W Rose Garden Ln",
    "sg:city":"Glendale",
    "sg:classifiers":[
        {
            "category":"Education",
            "subcategory":"School",
            "type":"Public Place"
        }
    ],
    "sg:phone":"+1 602 376 4800",
    "sg:postcode":"85308",
    "sg:province":"AZ",
    "wof:name":"Schools Public Sierra Verde",
    "wof:placetype":"venue"
},
  "geometry": {"coordinates":[-112.213235,33.674732],"type":"Point"}
}