{
  "type": "Feature",
  "properties": {
    "addr:full":"3100 N Stone Ave Tucson AZ 85705",
    "addr:housenumber":"3100",
    "addr:postcode":"85705",
    "addr:street":"N Stone Ave",
    "iso:country":"US",
    "sg:address":"3100 N Stone Ave",
    "sg:city":"Tucson",
    "sg:classifiers":[
        {
            "category":"Home & Garden",
            "subcategory":"Household Appliances",
            "type":"Retail Goods"
        }
    ],
    "sg:phone":"+1 520 292 2707",
    "sg:postcode":"85705",
    "sg:province":"AZ",
    "sg:tags":[
        "cleaners",
        "vacuum"
    ],
    "wof:name":"Arizona Kirby Co",
    "wof:placetype":"venue"
},
  "geometry": {"coordinates":[-110.972043,32.264742],"type":"Point"}
}