{
  "type": "Feature",
  "properties": {
    "iso:country":"US",
    "sg:address":"14960 W Indian School Rd",
    "sg:city":"Goodyear",
    "sg:classifiers":[
        {
            "category":"Building & Trades",
            "subcategory":"Locksmith",
            "type":"Services"
        }
    ],
    "sg:phone":"+1 866 242 3592",
    "sg:postcode":"85395",
    "sg:province":"AZ",
    "sg:tags":[
        "key"
    ],
    "wof:name":"A 1 Emergency Locksmith",
    "wof:placetype":"venue"
},
  "geometry": {"coordinates":[-112.380725,33.492429],"type":"Point"}
}