{
  "type": "Feature",
  "properties": {
    "iso:country":"US",
    "sg:address":"7422 W Topeka Dr",
    "sg:city":"Glendale",
    "sg:classifiers":[
        {
            "category":"Professional",
            "type":"Services"
        }
    ],
    "sg:phone":"+1 623 594 2532",
    "sg:postcode":"85308",
    "sg:province":"AZ",
    "wof:name":"Zeplin 2000 Inc",
    "wof:placetype":"venue"
},
  "geometry": {"coordinates":[-112.218594,33.657871],"type":"Point"}
}