{
  "type": "Feature",
  "properties": {
    "iso:country":"US",
    "sg:address":"2525 E Camelback Rd",
    "sg:city":"Phoenix",
    "sg:classifiers":[
        {
            "category":"Real Estate",
            "subcategory":"Real Estate Services",
            "type":"Services"
        }
    ],
    "sg:phone":"+1 602 840 2540",
    "sg:postcode":"85016",
    "sg:province":"AZ",
    "sg:tags":[
        "company",
        "title"
    ],
    "wof:name":"Guaranty Title Agency-Arizona",
    "wof:placetype":"venue"
},
  "geometry": {"coordinates":[-112.028715,33.509286],"type":"Point"}
}