{
  "type": "Feature",
  "properties": {
    "iso:country":"US",
    "sg:address":"2111 E Butler St",
    "sg:city":"Chandler",
    "sg:classifiers":[
        {
            "category":"Building & Trades",
            "subcategory":"Locksmith",
            "type":"Services"
        }
    ],
    "sg:phone":"+1 480 718 2162",
    "sg:postcode":"85225",
    "sg:province":"AZ",
    "sg:tags":[
        "key"
    ],
    "wof:name":"24 Hr Emerg A Locksmith",
    "wof:placetype":"venue"
},
  "geometry": {"coordinates":[-111.804196,33.301596],"type":"Point"}
}