{
  "type": "Feature",
  "properties": {
    "iso:country":"US",
    "sg:address":"3516 E Fairbrook Cir",
    "sg:city":"Mesa",
    "sg:classifiers":[
        {
            "category":"Building & Trades",
            "subcategory":"Construction",
            "type":"Services"
        }
    ],
    "sg:phone":"+1 480 924 6265",
    "sg:postcode":"85213",
    "sg:province":"AZ",
    "sg:tags":[
        "house"
    ],
    "wof:name":"Breinholt Concrete & Dev",
    "wof:placetype":"venue"
},
  "geometry": {"coordinates":[-111.754722,33.436502],"type":"Point"}
}