{
  "type": "Feature",
  "properties": {
    "iso:country":"US",
    "sg:address":"8207 N 59th Ave",
    "sg:city":"Glendale",
    "sg:classifiers":[
        {
            "category":"Freight",
            "type":"Transportation"
        }
    ],
    "sg:phone":"+1 623 772 8121",
    "sg:postcode":"85302",
    "sg:province":"AZ",
    "wof:name":"Logistix LLC",
    "wof:placetype":"venue"
},
  "geometry": {"coordinates":[-112.186121,33.556591],"type":"Point"}
}