{
  "type": "Feature",
  "properties": {
    "iso:country":"US",
    "sg:address":"7316 E Thomas Rd",
    "sg:city":"Scottsdale",
    "sg:classifiers":[
        {
            "category":"Retail",
            "subcategory":"Veterinary Services",
            "type":"Services"
        }
    ],
    "sg:phone":"+1 480 946 2223",
    "sg:postcode":"85251",
    "sg:province":"AZ",
    "sg:tags":[
        "veterinarian"
    ],
    "sg:website":"www.diamondbackdrugs.com",
    "wof:name":"Diamondback Drugs",
    "wof:placetype":"venue"
},
  "geometry": {"coordinates":[-111.921933,33.480439],"type":"Point"}
}