{
  "type": "Feature",
  "properties": {
    "iso:country":"US",
    "sg:address":"10768 W Grand Ave",
    "sg:city":"Sun City",
    "sg:classifiers":[
        {
            "category":"Home & Garden",
            "subcategory":"Carpets & Floor Coverings",
            "type":"Retail Goods"
        },
        {
            "category":"Building & Trades",
            "subcategory":"Construction",
            "type":"Services"
        }
    ],
    "sg:phone":"+1 623 583 9542",
    "sg:postcode":"85351",
    "sg:province":"AZ",
    "sg:tags":[
        "tile",
        "dealer"
    ],
    "wof:name":"L & S Tile & Carpet",
    "wof:placetype":"venue"
},
  "geometry": {"coordinates":[-112.291024,33.603088],"type":"Point"}
}