{
  "type": "Feature",
  "properties": {
    "iso:country":"US",
    "sg:address":"3224 Medicine Bow Dr",
    "sg:city":"Lake Havasu City",
    "sg:classifiers":[
        {
            "category":"Building & Trades",
            "subcategory":"Landscaping Services",
            "type":"Services"
        }
    ],
    "sg:phone":"+1 928 855 9410",
    "sg:postcode":"86406",
    "sg:province":"AZ",
    "sg:tags":[
        "landscape"
    ],
    "wof:name":"Reynolds Landscape Design",
    "wof:placetype":"venue"
},
  "geometry": {"coordinates":[-114.283254,34.466123],"type":"Point"}
}