{
  "type": "Feature",
  "properties": {
    "addr:full":"2020 N Central Ave Phoenix AZ 85004",
    "addr:housenumber":"2020",
    "addr:postcode":"85004",
    "addr:street":"N Central Ave",
    "iso:country":"US",
    "sg:address":"2020 N Central Ave",
    "sg:city":"Phoenix",
    "sg:classifiers":[
        {
            "category":"Food & Beverages",
            "subcategory":"Specialty",
            "type":"Retail Goods"
        }
    ],
    "sg:phone":"+1 602 257 8260",
    "sg:postcode":"85004",
    "sg:province":"AZ",
    "wof:name":"Picadeli Square",
    "wof:placetype":"venue"
},
  "geometry": {"coordinates":[-112.073849,33.470368],"type":"Point"}
}