{
  "type": "Feature",
  "properties": {
    "iso:country":"US",
    "sg:address":"1645 W Valencia Rd",
    "sg:city":"Tucson",
    "sg:classifiers":[
        {
            "category":"Building & Trades",
            "subcategory":"Plumbing",
            "type":"Services"
        }
    ],
    "sg:phone":"+1 520 260 8204",
    "sg:postcode":"85746",
    "sg:province":"AZ",
    "sg:tags":[
        "plumbing",
        "contractor"
    ],
    "wof:name":"AAA Antythinggas",
    "wof:placetype":"venue"
},
  "geometry": {"coordinates":[-111.00193,32.133733],"type":"Point"}
}