{
  "type": "Feature",
  "properties": {
    "iso:country":"US",
    "sg:address":"3220 E Jerome Ave",
    "sg:city":"Mesa",
    "sg:classifiers":[
        {
            "category":"Shopping",
            "subcategory":"Beauty & Cosmetics",
            "type":"Retail Goods"
        }
    ],
    "sg:phone":"+1 480 632 0520",
    "sg:postcode":"85204",
    "sg:province":"AZ",
    "sg:tags":[
        "merchandise"
    ],
    "wof:name":"Dennis & Kristine Gilbert",
    "wof:placetype":"venue"
},
  "geometry": {"coordinates":[-111.76179,33.381417],"type":"Point"}
}