{
  "type": "Feature",
  "properties": {
    "addr:full":"3105 E Main St Mesa AZ 85213",
    "addr:housenumber":"3105",
    "addr:postcode":"85213",
    "addr:street":"E Main St",
    "iso:country":"US",
    "sg:address":"3105 E Main St",
    "sg:city":"Mesa",
    "sg:classifiers":[
        {
            "category":"Retail",
            "subcategory":"Auto Repair",
            "type":"Services"
        }
    ],
    "sg:phone":"+1 480 924 1711",
    "sg:postcode":"85213",
    "sg:province":"AZ",
    "sg:tags":[
        "brake"
    ],
    "wof:name":"Alignment & Brakes Of Mesa",
    "wof:placetype":"venue"
},
  "geometry": {"coordinates":[-111.761882,33.415417],"type":"Point"}
}