{
  "type": "Feature",
  "properties": {
    "addr:full":"6989 N Hayden Rd Scottsdale AZ 85250",
    "addr:housenumber":"6989",
    "addr:postcode":"85250",
    "addr:street":"N Hayden Rd",
    "iso:country":"US",
    "sg:address":"6989 N Hayden Rd",
    "sg:city":"Scottsdale",
    "sg:classifiers":[
        {
            "category":"Restaurant",
            "type":"Food & Drink"
        }
    ],
    "sg:phone":"+1 480 922 5230",
    "sg:postcode":"85250",
    "sg:province":"AZ",
    "wof:name":"News Cafe At Gateview Park",
    "wof:placetype":"venue"
},
  "geometry": {"coordinates":[-111.908546,33.537868],"type":"Point"}
}