{
  "type": "Feature",
  "properties": {
    "addr:full":"255 N Country Club Dr Mesa AZ 85201",
    "addr:housenumber":"255",
    "addr:postcode":"85201",
    "addr:street":"N Country Club Dr",
    "iso:country":"US",
    "sg:address":"255 N Country Club Dr",
    "sg:city":"Mesa",
    "sg:classifiers":[
        {
            "category":"Retail",
            "subcategory":"Auto Rental",
            "type":"Services"
        }
    ],
    "sg:phone":"+1 480 844 2292",
    "sg:postcode":"85201",
    "sg:province":"AZ",
    "sg:tags":[
        "renting",
        "automobile"
    ],
    "wof:name":"Almost New Car Rental",
    "wof:placetype":"venue"
},
  "geometry": {"coordinates":[-111.83987999999999,33.419019],"type":"Point"}
}