{
  "type": "Feature",
  "properties": {
    "iso:country":"US",
    "sg:address":"1232 E Southern Ave",
    "sg:city":"Mesa",
    "sg:classifiers":[
        {
            "category":"Insurance",
            "subcategory":"Insurance Agent",
            "type":"Services"
        }
    ],
    "sg:phone":"+1 480 610 1101",
    "sg:postcode":"85204",
    "sg:province":"AZ",
    "wof:name":"Farmers Insurance Group",
    "wof:placetype":"venue"
},
  "geometry": {"coordinates":[-111.802801,33.393478],"type":"Point"}
}