{
  "type": "Feature",
  "properties": {
    "iso:country":"US",
    "sg:address":"6245 E Bell Rd",
    "sg:city":"Scottsdale",
    "sg:classifiers":[
        {
            "category":"Personal",
            "subcategory":"Beauty Salon",
            "type":"Services"
        },
        {
            "category":"Personal",
            "subcategory":"Nail Salon",
            "type":"Services"
        }
    ],
    "sg:phone":"+1 480 348 9433",
    "sg:postcode":"85254",
    "sg:province":"AZ",
    "wof:name":"China Nail Salon",
    "wof:placetype":"venue"
},
  "geometry": {"coordinates":[-111.945348,33.640379],"type":"Point"}
}