{
  "type": "Feature",
  "properties": {
    "iso:country":"US",
    "sg:address":"8512 N 59th Pl",
    "sg:city":"Paradise Valley",
    "sg:classifiers":[
        {
            "category":"Real Estate",
            "subcategory":"Real Estate Operator",
            "type":"Services"
        }
    ],
    "sg:phone":"+1 480 596 9048",
    "sg:postcode":"85253",
    "sg:province":"AZ",
    "sg:tags":[
        "building",
        "apartment"
    ],
    "wof:name":"G E Belle Villas L L C",
    "wof:placetype":"venue"
},
  "geometry": {"coordinates":[-111.952645,33.561971],"type":"Point"}
}