{
  "type": "Feature",
  "properties": {
    "addr:full":"7333 W Cameron Dr Peoria AZ 85345",
    "addr:housenumber":"7333",
    "addr:postcode":"85345",
    "addr:street":"W Cameron Dr",
    "iso:country":"US",
    "sg:address":"7333 W Cameron Dr",
    "sg:city":"Peoria",
    "sg:classifiers":[
        {
            "category":"Sports & Exercise",
            "subcategory":"Skate Park",
            "type":"Entertainment"
        }
    ],
    "sg:phone":"+1 623 979 3781",
    "sg:postcode":"85345",
    "sg:province":"AZ",
    "sg:tags":[
        "magician"
    ],
    "wof:name":"The Pool Magician",
    "wof:placetype":"venue"
},
  "geometry": {"coordinates":[-112.21689499999999,33.589566],"type":"Point"}
}