{
  "type": "Feature",
  "properties": {
    "iso:country":"US",
    "sg:address":"8906 E Old Spanish Trl",
    "sg:city":"Tucson",
    "sg:classifiers":[
        {
            "category":"Building & Trades",
            "subcategory":"Electrical",
            "type":"Services"
        }
    ],
    "sg:phone":"+1 520 886 6913",
    "sg:postcode":"85710",
    "sg:province":"AZ",
    "sg:tags":[
        "electrical",
        "contractor"
    ],
    "wof:name":"Knight Electric Inc A Corp",
    "wof:placetype":"venue"
},
  "geometry": {"coordinates":[-110.800994,32.211376],"type":"Point"}
}