{
  "type": "Feature",
  "properties": {
    "iso:country":"US",
    "sg:address":"1501 E Washington St",
    "sg:city":"Phoenix",
    "sg:classifiers":[
        {
            "category":"Health Services",
            "subcategory":"Doctor",
            "type":"Services"
        },
        {
            "category":"Health Services",
            "subcategory":"Clinic",
            "type":"Services"
        },
        {
            "category":"Health Services",
            "subcategory":"Health Practitioner",
            "type":"Services"
        }
    ],
    "sg:phone":"+1 602 253 6553",
    "sg:postcode":"85034",
    "sg:province":"AZ",
    "sg:tags":[
        "physician",
        "medical",
        "surgeons",
        "drug",
        "abuse",
        "medicine",
        "addiction",
        "surgeon"
    ],
    "wof:name":"Center For Behavioral Health",
    "wof:placetype":"venue"
},
  "geometry": {"coordinates":[-112.049889,33.448219],"type":"Point"}
}