{
  "type": "Feature",
  "properties": {
    "iso:country":"US",
    "sg:address":"1985 Hwy 95",
    "sg:city":"Bullhead City",
    "sg:classifiers":[
        {
            "category":"Shopping",
            "subcategory":"Music",
            "type":"Retail Goods"
        }
    ],
    "sg:phone":"+1 928 763 0025",
    "sg:postcode":"86442",
    "sg:province":"AZ",
    "wof:name":"Hastings Books 9874",
    "wof:placetype":"venue"
},
  "geometry": {"coordinates":[-114.598212,35.116318],"type":"Point"}
}