{
  "type": "Feature",
  "properties": {
    "addr:full":"8200 N 75th Ave Peoria AZ 85345",
    "addr:housenumber":"8200",
    "addr:postcode":"85345",
    "addr:street":"N 75Th Ave",
    "iso:country":"US",
    "sg:address":"8200 N 75th Ave",
    "sg:city":"Peoria",
    "sg:classifiers":[
        {
            "category":"Building & Trades",
            "subcategory":"Construction",
            "type":"Services"
        }
    ],
    "sg:phone":"+1 623 979 4885",
    "sg:postcode":"85345",
    "sg:province":"AZ",
    "sg:tags":[
        "roofing",
        "contractor"
    ],
    "wof:name":"Specialty Roofing Inc",
    "wof:placetype":"venue"
},
  "geometry": {"coordinates":[-112.220489,33.558385],"type":"Point"}
}