{
  "type": "Feature",
  "properties": {
    "iso:country":"US",
    "sg:address":"22047 N 23rd Ave Ste A",
    "sg:city":"Phoenix",
    "sg:classifiers":[
        {
            "category":"Manufacturing",
            "subcategory":"Tools & Machinery",
            "type":"Manufacturing & Wholesale Goods"
        },
        {
            "category":"Industrial Area",
            "type":"Public Place"
        }
    ],
    "sg:phone":"+1 623 582 1655",
    "sg:postcode":"85027",
    "sg:province":"AZ",
    "sg:tags":[
        "repair",
        "equipment-repairing",
        "machinery-rebuild"
    ],
    "wof:name":"Small Engine World",
    "wof:placetype":"venue"
},
  "geometry": {"coordinates":[-112.108681,33.686676],"type":"Point"}
}