{
  "type": "Feature",
  "properties": {
    "iso:country":"US",
    "sg:address":"3802 N 53rd Ave",
    "sg:city":"Phoenix",
    "sg:classifiers":[
        {
            "category":"Banks & Credit Unions",
            "subcategory":"Bank",
            "type":"Services"
        }
    ],
    "sg:phone":"+1 602 233 3400",
    "sg:postcode":"85031",
    "sg:province":"AZ",
    "sg:tags":[
        "mortgage"
    ],
    "wof:name":"Venture Financial Services",
    "wof:placetype":"venue"
},
  "geometry": {"coordinates":[-112.173379,33.494999],"type":"Point"}
}