{
  "type": "Feature",
  "properties": {
    "iso:country":"US",
    "sg:address":"3208 E Milber St",
    "sg:city":"Tucson",
    "sg:classifiers":[
        {
            "category":"Sports & Exercise",
            "subcategory":"Race Track",
            "type":"Entertainment"
        }
    ],
    "sg:phone":"+1 520 748 7223",
    "sg:postcode":"85714",
    "sg:province":"AZ",
    "sg:tags":[
        "equipment",
        "supply"
    ],
    "wof:name":"I Got Race Parts",
    "wof:placetype":"venue"
},
  "geometry": {"coordinates":[-110.924224,32.172596],"type":"Point"}
}