{
  "type": "Feature",
  "properties": {
    "iso:country":"US",
    "sg:address":"5151 N 16th St Ste 132",
    "sg:city":"Phoenix",
    "sg:classifiers":[
        {
            "category":"Professional",
            "subcategory":"Engineering",
            "type":"Services"
        }
    ],
    "sg:phone":"+1 602 279 8092",
    "sg:postcode":"85016",
    "sg:province":"AZ",
    "sg:tags":[
        "electronic",
        "electrical",
        "engineer"
    ],
    "wof:name":"Woo, Tony Engineering",
    "wof:placetype":"venue"
},
  "geometry": {"coordinates":[-112.047531,33.511955],"type":"Point"}
}