{
  "type": "Feature",
  "properties": {
    "iso:country":"US",
    "sg:address":"2151 N Palo Verde Blvd",
    "sg:city":"Tucson",
    "sg:classifiers":[
        {
            "category":"Organizations",
            "subcategory":"Religious Organization",
            "type":"Services"
        }
    ],
    "sg:phone":"+1 520 327 6233",
    "sg:postcode":"85716",
    "sg:province":"AZ",
    "sg:tags":[
        "church"
    ],
    "sg:website":"www.paloverdebaptist.org",
    "wof:name":"Palo Verde Baptist Church",
    "wof:placetype":"venue"
},
  "geometry": {"coordinates":[-110.918353,32.247453],"type":"Point"}
}