{
  "type": "Feature",
  "properties": {
    "iso:country":"US",
    "sg:address":"5301 E Pershing Ave",
    "sg:city":"Scottsdale",
    "sg:classifiers":[
        {
            "category":"Wholesale",
            "subcategory":"Construction Materials",
            "type":"Manufacturing & Wholesale Goods"
        },
        {
            "category":"Home & Garden",
            "subcategory":"Furniture",
            "type":"Retail Goods"
        }
    ],
    "sg:phone":"+1 480 949 5665",
    "sg:postcode":"85254",
    "sg:province":"AZ",
    "sg:tags":[
        "sales",
        "cabinetry",
        "cabinet",
        "equipment",
        "design",
        "kitchen"
    ],
    "wof:name":"Showcase Kitchens & Baths",
    "wof:placetype":"venue"
},
  "geometry": {"coordinates":[-111.966717,33.606077],"type":"Point"}
}