{
  "type": "Feature",
  "properties": {
    "iso:country":"US",
    "sg:address":"1830 W Colter St",
    "sg:city":"Phoenix",
    "sg:classifiers":[
        {
            "category":"Shopping",
            "type":"Retail Goods"
        }
    ],
    "sg:phone":"+1 602 864 5560",
    "sg:postcode":"85015",
    "sg:province":"AZ",
    "sg:tags":[
        "limb",
        "merchandise",
        "artificial"
    ],
    "sg:website":"www.ariseprosthetics.com",
    "wof:name":"Arise Prosthetics LLC",
    "wof:placetype":"venue"
},
  "geometry": {"coordinates":[-112.099275,33.513313],"type":"Point"}
}