{
  "type": "Feature",
  "properties": {
    "iso:country":"US",
    "sg:address":"946 W Southern Ave",
    "sg:city":"Mesa",
    "sg:classifiers":[
        {
            "category":"Manufacturing",
            "subcategory":"Tools & Machinery",
            "type":"Manufacturing & Wholesale Goods"
        },
        {
            "category":"Home & Garden",
            "subcategory":"Garden Supply",
            "type":"Retail Goods"
        },
        {
            "category":"Wholesale",
            "subcategory":"Painting Supplies",
            "type":"Manufacturing & Wholesale Goods"
        },
        {
            "category":"Home & Garden",
            "subcategory":"Building Materials",
            "type":"Retail Goods"
        },
        {
            "category":"Manufacturing",
            "subcategory":"Paper Products",
            "type":"Manufacturing & Wholesale Goods"
        }
    ],
    "sg:phone":"+1 480 833 2976",
    "sg:postcode":"85210",
    "sg:province":"AZ",
    "sg:tags":[
        "spraying",
        "wallpaper",
        "paint-wholesale",
        "equipment",
        "wallcoverings",
        "bamboo",
        "paint",
        "manufacturer"
    ],
    "sg:website":"http://www.frazeepaint.com",
    "wof:name":"Frazee Paint & Wallcovering",
    "wof:placetype":"venue"
},
  "geometry": {"coordinates":[-111.851721,33.393232],"type":"Point"}
}