{
  "type": "Feature",
  "properties": {
    "iso:country":"US",
    "sg:address":"146 E 6th St",
    "sg:city":"Benson",
    "sg:classifiers":[
        {
            "category":"Personal",
            "subcategory":"Beauty Salon",
            "type":"Services"
        }
    ],
    "sg:phone":"+1 520 720 4503",
    "sg:postcode":"85602",
    "sg:province":"AZ",
    "wof:name":"Michelle's Hair Corral",
    "wof:placetype":"venue"
},
  "geometry": {"coordinates":[-110.297301,31.966248],"type":"Point"}
}