{
  "type": "Feature",
  "properties": {
    "addr:full":"1594 Co Rd 3140 Vernon AZ 85940",
    "addr:housenumber":"1594",
    "addr:postcode":"3140;85940",
    "addr:street":"Co Rd",
    "iso:country":"US",
    "sg:address":"1594 Co Rd 3140",
    "sg:city":"Vernon",
    "sg:classifiers":[
        {
            "category":"Home & Garden",
            "subcategory":"Home Furnishings",
            "type":"Retail Goods"
        }
    ],
    "sg:phone":"+1 928 537 4786",
    "sg:postcode":"85940",
    "sg:province":"AZ",
    "sg:tags":[
        "pottery"
    ],
    "wof:name":"Mineral Spring Studios",
    "wof:placetype":"venue"
},
  "geometry": {"coordinates":[-109.692291,34.256362],"type":"Point"}
}