{
  "type": "Feature",
  "properties": {
    "iso:country":"US",
    "sg:address":"5105 E Burns St",
    "sg:city":"Tucson",
    "sg:classifiers":[
        {
            "category":"Social Services",
            "subcategory":"Adult Care",
            "type":"Services"
        }
    ],
    "sg:phone":"+1 520 750 1824",
    "sg:postcode":"85711",
    "sg:province":"AZ",
    "sg:tags":[
        "home",
        "residential"
    ],
    "wof:name":"Our Place Adult Care Home",
    "wof:placetype":"venue"
},
  "geometry": {"coordinates":[-110.882587,32.224642],"type":"Point"}
}