{
  "type": "Feature",
  "properties": {
    "iso:country":"US",
    "sg:address":"11550 W Northern Ave",
    "sg:city":"Glendale",
    "sg:classifiers":[
        {
            "category":"Wholesale",
            "subcategory":"Construction Materials",
            "type":"Manufacturing & Wholesale Goods"
        },
        {
            "category":"Home & Garden",
            "subcategory":"Garden Supply",
            "type":"Retail Goods"
        }
    ],
    "sg:phone":"+1 623 977 4800",
    "sg:postcode":"85307",
    "sg:province":"AZ",
    "sg:tags":[
        "landscaping",
        "equipment"
    ],
    "wof:name":"Pioneer Landscaping Materials",
    "wof:placetype":"venue"
},
  "geometry": {"coordinates":[-112.307087,33.550897],"type":"Point"}
}