{
  "type": "Feature",
  "properties": {
    "iso:country":"US",
    "sg:address":"8520 E Oak St",
    "sg:city":"Scottsdale",
    "sg:classifiers":[
        {
            "category":"Professional",
            "type":"Services"
        }
    ],
    "sg:phone":"+1 480 429 3566",
    "sg:postcode":"85257",
    "sg:province":"AZ",
    "wof:name":"Lenores Paper Chase",
    "wof:placetype":"venue"
},
  "geometry": {"coordinates":[-111.897698,33.473167],"type":"Point"}
}