{
  "type": "Feature",
  "properties": {
    "iso:country":"US",
    "sg:address":"37 N McQueen Rd",
    "sg:city":"Gilbert",
    "sg:classifiers":[
        {
            "category":"Food & Beverages",
            "subcategory":"Groceries & Convenience Stores",
            "type":"Retail Goods"
        }
    ],
    "sg:phone":"+1 480 503 2188",
    "sg:postcode":"85233",
    "sg:province":"AZ",
    "wof:name":"Am/PM Mini Market",
    "wof:placetype":"venue"
},
  "geometry": {"coordinates":[-111.824309,33.352899],"type":"Point"}
}