{
  "type": "Feature",
  "properties": {
    "addr:full":"7821 W Cheryl Dr Peoria AZ 85345",
    "addr:housenumber":"7821",
    "addr:postcode":"85345",
    "addr:street":"W Cheryl Dr",
    "iso:country":"US",
    "sg:address":"7821 W Cheryl Dr",
    "sg:city":"Peoria",
    "sg:classifiers":[
        {
            "category":"Organizations",
            "subcategory":"Community Association",
            "type":"Services"
        }
    ],
    "sg:phone":"+1 623 878 6223",
    "sg:postcode":"85345",
    "sg:province":"AZ",
    "sg:tags":[
        "club"
    ],
    "wof:name":"Wadleigh Bear L",
    "wof:placetype":"venue"
},
  "geometry": {"coordinates":[-112.227231,33.577603],"type":"Point"}
}