{
  "type": "Feature",
  "properties": {
    "iso:country":"US",
    "sg:address":"10180 N Hayden Rd",
    "sg:city":"Scottsdale",
    "sg:classifiers":[
        {
            "category":"Organizations",
            "subcategory":"Religious Organization",
            "type":"Services"
        }
    ],
    "sg:phone":"+1 480 998 0769",
    "sg:postcode":"85258",
    "sg:province":"AZ",
    "sg:tags":[
        "church"
    ],
    "wof:name":"Christian Science Second Chr",
    "wof:placetype":"venue"
},
  "geometry": {"coordinates":[-111.90733,33.577299],"type":"Point"}
}