{
  "type": "Feature",
  "properties": {
    "addr:full":"12031 E Colony Dr Fountain Hills AZ 85268",
    "addr:housenumber":"12031",
    "addr:postcode":"85268",
    "addr:street":"E Colony Dr",
    "iso:country":"US",
    "sg:address":"12031 E Colony Dr",
    "sg:city":"Fountain Hills",
    "sg:classifiers":[
        {
            "category":"Wholesale",
            "subcategory":"Hardware",
            "type":"Manufacturing & Wholesale Goods"
        }
    ],
    "sg:phone":"+1 602 242 9325",
    "sg:postcode":"85268",
    "sg:province":"AZ",
    "sg:tags":[
        "equipment",
        "energy",
        "solar"
    ],
    "wof:name":"Sun Glow Systems",
    "wof:placetype":"venue"
},
  "geometry": {"coordinates":[-111.711721,33.596191],"type":"Point"}
}