{
  "type": "Feature",
  "properties": {
    "iso:country":"US",
    "sg:address":"8585 E Frank Lloyd Wright Blvd",
    "sg:city":"Scottsdale",
    "sg:classifiers":[
        {
            "category":"Autos & Motor Vehicles",
            "subcategory":"Automobile Sales",
            "type":"Retail Goods"
        }
    ],
    "sg:phone":"+1 480 367 2942",
    "sg:postcode":"85260",
    "sg:province":"AZ",
    "sg:tags":[
        "new",
        "truck",
        "car"
    ],
    "wof:name":"Van Chevrolet",
    "wof:placetype":"venue"
},
  "geometry": {"coordinates":[-111.893692,33.630341],"type":"Point"}
}