{
  "type": "Feature",
  "properties": {
    "iso:country":"US",
    "sg:address":"2470 W 8th St",
    "sg:city":"Yuma",
    "sg:classifiers":[
        {
            "category":"Home & Garden",
            "subcategory":"Furniture",
            "type":"Retail Goods"
        }
    ],
    "sg:phone":"+1 928 373 9278",
    "sg:postcode":"85364",
    "sg:province":"AZ",
    "wof:name":"Willys Furniture",
    "wof:placetype":"venue"
},
  "geometry": {"coordinates":[-114.64967900000001,32.713129],"type":"Point"}
}