{
  "type": "Feature",
  "properties": {
    "iso:country":"US",
    "sg:address":"606 S Plumer Ave",
    "sg:city":"Tucson",
    "sg:classifiers":[
        {
            "category":"Organizations",
            "subcategory":"Labor Organization",
            "type":"Services"
        }
    ],
    "sg:phone":"+1 520 882 0896",
    "sg:postcode":"85719",
    "sg:province":"AZ",
    "wof:name":"Arizona Federation-Teacher",
    "wof:placetype":"venue"
},
  "geometry": {"coordinates":[-110.939493,32.213315],"type":"Point"}
}