{
  "type": "Feature",
  "properties": {
    "iso:country":"US",
    "sg:address":"4001 E Baseline Rd",
    "sg:city":"Gilbert",
    "sg:classifiers":[
        {
            "category":"Health Services",
            "subcategory":"Doctor",
            "type":"Services"
        }
    ],
    "sg:phone":"+1 480 626 6600",
    "sg:postcode":"85234",
    "sg:province":"AZ",
    "sg:tags":[
        "physician",
        "surgeon"
    ],
    "wof:name":"Sam Reed Shimamoto MD",
    "wof:placetype":"venue"
},
  "geometry": {"coordinates":[-111.745438,33.379107],"type":"Point"}
}