{
  "type": "Feature",
  "properties": {
    "iso:country":"US",
    "sg:address":"6991 E Camelback Rd",
    "sg:city":"Scottsdale",
    "sg:classifiers":[
        {
            "category":"Professional",
            "type":"Services"
        }
    ],
    "sg:phone":"+1 480 429 0555",
    "sg:postcode":"85251",
    "sg:province":"AZ",
    "sg:tags":[
        "establishment"
    ],
    "wof:name":"21st Century Diversified",
    "wof:placetype":"venue"
},
  "geometry": {"coordinates":[-111.932208,33.502095],"type":"Point"}
}