{
  "type": "Feature",
  "properties": {
    "iso:country":"US",
    "sg:address":"2931 E Andy Devine Ave",
    "sg:city":"Kingman",
    "sg:classifiers":[
        {
            "category":"Autos & Motor Vehicles",
            "subcategory":"Fuel & Gas Station",
            "type":"Retail Goods"
        }
    ],
    "sg:phone":"+1 928 753 2313",
    "sg:postcode":"86401",
    "sg:province":"AZ",
    "sg:tags":[
        "gasoline"
    ],
    "wof:name":"Shell Hallum Stores",
    "wof:placetype":"venue"
},
  "geometry": {"coordinates":[-114.01588700000001,35.211776],"type":"Point"}
}