{
  "type": "Feature",
  "properties": {
    "addr:full":"2544 W 16th St Yuma AZ 85364",
    "addr:housenumber":"2544",
    "addr:postcode":"85364",
    "addr:street":"W 16Th St",
    "iso:country":"US",
    "sg:address":"2544 W 16th St",
    "sg:city":"Yuma",
    "sg:classifiers":[
        {
            "category":"Restaurant",
            "type":"Food & Drink"
        }
    ],
    "sg:menulink":"http://www.allmenus.com/az/yuma/75025-round-table-pizza/menu/",
    "sg:phone":"+1 928 783 5895",
    "sg:postcode":"85364",
    "sg:province":"AZ",
    "sg:tags":[
        "american",
        "pizza"
    ],
    "wof:name":"Round Table Pizza",
    "wof:placetype":"venue"
},
  "geometry": {"coordinates":[-114.65260600000001,32.698499],"type":"Point"}
}