{
  "type": "Feature",
  "properties": {
    "iso:country":"US",
    "sg:address":"14650 N Sun City Blvd",
    "sg:city":"Tucson",
    "sg:classifiers":[
        {
            "category":"Sports & Exercise",
            "subcategory":"Sports Center",
            "type":"Entertainment"
        }
    ],
    "sg:phone":"+1 520 825 0495",
    "sg:postcode":"85737",
    "sg:province":"AZ",
    "sg:tags":[
        "amateur",
        "team"
    ],
    "wof:name":"Desert Oasis Recreation Center",
    "wof:placetype":"venue"
},
  "geometry": {"coordinates":[-110.95500199999999,32.4711],"type":"Point"}
}