{
  "type": "Feature",
  "properties": {
    "iso:country":"US",
    "sg:address":"550 N Grand Ave",
    "sg:city":"Nogales",
    "sg:classifiers":[
        {
            "category":"Restaurant",
            "type":"Food & Drink"
        }
    ],
    "sg:phone":"+1 520 287 4730",
    "sg:postcode":"85621",
    "sg:province":"AZ",
    "wof:name":"Los Tacos Inc",
    "wof:placetype":"venue"
},
  "geometry": {"coordinates":[-110.937341,31.340645],"type":"Point"}
}