{
  "type": "Feature",
  "properties": {
    "iso:country":"US",
    "sg:address":"1783 S 45th Dr",
    "sg:city":"Yuma",
    "sg:classifiers":[
        {
            "category":"Freight",
            "type":"Transportation"
        }
    ],
    "sg:phone":"+1 928 783 3523",
    "sg:postcode":"85364",
    "sg:province":"AZ",
    "sg:tags":[
        "operator",
        "local",
        "trucking"
    ],
    "wof:name":"J&J Trucking Inc",
    "wof:placetype":"venue"
},
  "geometry": {"coordinates":[-114.67658299999999,32.695035],"type":"Point"}
}