{
  "type": "Feature",
  "properties": {
    "iso:country":"US",
    "sg:address":"20805 N 19th Ave",
    "sg:city":"Phoenix",
    "sg:classifiers":[
        {
            "category":"Home & Garden",
            "subcategory":"Home Furnishings",
            "type":"Retail Goods"
        }
    ],
    "sg:phone":"+1 623 581 9105",
    "sg:postcode":"85027",
    "sg:province":"AZ",
    "sg:tags":[
        "pottery"
    ],
    "wof:name":"Premier Pottery & Copper",
    "wof:placetype":"venue"
},
  "geometry": {"coordinates":[-112.099717,33.676455],"type":"Point"}
}