{
  "type": "Feature",
  "properties": {
    "addr:full":"2615 S Industrial Park Ave Tempe AZ 85282",
    "addr:housenumber":"2615",
    "addr:postcode":"85282",
    "addr:street":"S Industrial Park Ave",
    "iso:country":"US",
    "sg:address":"2615 S Industrial Park Ave",
    "sg:city":"Tempe",
    "sg:classifiers":[
        {
            "category":"Utilities",
            "subcategory":"Cable",
            "type":"Services"
        }
    ],
    "sg:phone":"+1 623 328 4053",
    "sg:postcode":"85282",
    "sg:province":"AZ",
    "sg:tags":[
        "television"
    ],
    "wof:name":"Cox Communications",
    "wof:placetype":"venue"
},
  "geometry": {"coordinates":[-111.955161,33.402993],"type":"Point"}
}