{
  "type": "Feature",
  "properties": {
    "iso:country":"US",
    "sg:address":"2337 W Northern Ave",
    "sg:city":"Phoenix",
    "sg:classifiers":[
        {
            "category":"Health Services",
            "subcategory":"Doctor",
            "type":"Services"
        },
        {
            "category":"Health Services",
            "subcategory":"Health Practitioner",
            "type":"Services"
        }
    ],
    "sg:phone":"+1 602 995 8848",
    "sg:postcode":"85021",
    "sg:province":"AZ",
    "sg:tags":[
        "physician",
        "ophthalmology",
        "surgeons",
        "surgeon"
    ],
    "wof:name":"Eye Clinic, The",
    "wof:placetype":"venue"
},
  "geometry": {"coordinates":[-112.110023,33.553108],"type":"Point"}
}