{
  "type": "Feature",
  "properties": {
    "iso:country":"US",
    "sg:address":"9705 N el Mirage Rd",
    "sg:city":"El Mirage",
    "sg:classifiers":[
        {
            "category":"Freight",
            "type":"Transportation"
        }
    ],
    "sg:phone":"+1 623 877 5652",
    "sg:postcode":"85335",
    "sg:province":"AZ",
    "sg:tags":[
        "trucking"
    ],
    "wof:name":"Root CE Trucking",
    "wof:placetype":"venue"
},
  "geometry": {"coordinates":[-112.32445199999999,33.56563],"type":"Point"}
}