{
  "type": "Feature",
  "properties": {
    "iso:country":"US",
    "sg:address":"1090 E Baseline Rd",
    "sg:city":"Phoenix",
    "sg:classifiers":[
        {
            "category":"Sports & Exercise",
            "subcategory":"Gym",
            "type":"Entertainment"
        }
    ],
    "sg:phone":"+1 602 505 6388",
    "sg:postcode":"85042",
    "sg:province":"AZ",
    "sg:tags":[
        "gymnasium"
    ],
    "wof:name":"Pure Fitness",
    "wof:placetype":"venue"
},
  "geometry": {"coordinates":[-112.057371,33.377724],"type":"Point"}
}