{
  "type": "Feature",
  "properties": {
    "addr:full":"1901 W Cactus Rd Phoenix AZ 85029",
    "addr:housenumber":"1901",
    "addr:postcode":"85029",
    "addr:street":"W Cactus Rd",
    "iso:country":"US",
    "sg:address":"1901 W Cactus Rd",
    "sg:city":"Phoenix",
    "sg:classifiers":[
        {
            "category":"Food & Beverages",
            "subcategory":"Groceries & Convenience Stores",
            "type":"Retail Goods"
        }
    ],
    "sg:phone":"+1 602 997 1127",
    "sg:postcode":"85029",
    "sg:province":"AZ",
    "sg:website":"http://www.circlek.com",
    "wof:name":"Circle K",
    "wof:placetype":"venue"
},
  "geometry": {"coordinates":[-112.099609,33.596539],"type":"Point"}
}