{
  "type": "Feature",
  "properties": {
    "iso:country":"US",
    "sg:address":"3121 N Swan Rd",
    "sg:city":"Tucson",
    "sg:classifiers":[
        {
            "category":"Real Estate",
            "subcategory":"Real Estate Agent",
            "type":"Services"
        },
        {
            "category":"Real Estate",
            "subcategory":"Real Estate Operator",
            "type":"Services"
        }
    ],
    "sg:phone":"+1 520 325 1599",
    "sg:postcode":"85712",
    "sg:province":"AZ",
    "sg:tags":[
        "apartment"
    ],
    "wof:name":"Cimerron Place",
    "wof:placetype":"venue"
},
  "geometry": {"coordinates":[-110.892551,32.270017],"type":"Point"}
}