{
  "type": "Feature",
  "properties": {
    "iso:country":"US",
    "sg:address":"2336 W Holly St",
    "sg:city":"Phoenix",
    "sg:classifiers":[
        {
            "category":"Retail",
            "subcategory":"Auto Repair",
            "type":"Services"
        }
    ],
    "sg:phone":"+1 602 271 0582",
    "sg:postcode":"85009",
    "sg:province":"AZ",
    "sg:tags":[
        "recreational",
        "vehicle"
    ],
    "wof:name":"Razr ATV & Cycle",
    "wof:placetype":"venue"
},
  "geometry": {"coordinates":[-112.111169,33.470887],"type":"Point"}
}