{
  "type": "Feature",
  "properties": {
    "iso:country":"US",
    "sg:address":"480 W Deuce of Clubs",
    "sg:city":"Show Low",
    "sg:classifiers":[
        {
            "category":"Bars & Pubs",
            "type":"Food & Drink"
        }
    ],
    "sg:phone":"+1 928 537 7460",
    "sg:postcode":"85901",
    "sg:province":"AZ",
    "sg:tags":[
        "lounge",
        "drinking",
        "cocktail"
    ],
    "wof:name":"One Eyed Jacks Sports Lounge",
    "wof:placetype":"venue"
},
  "geometry": {"coordinates":[-110.047454,34.247807],"type":"Point"}
}