{
  "type": "Feature",
  "properties": {
    "iso:country":"US",
    "sg:address":"529 E Camelback Rd",
    "sg:city":"Phoenix",
    "sg:classifiers":[
        {
            "category":"Autos & Motor Vehicles",
            "subcategory":"Auto Supplies",
            "type":"Retail Goods"
        }
    ],
    "sg:phone":"+1 602 241 8600",
    "sg:postcode":"85012",
    "sg:province":"AZ",
    "sg:tags":[
        "wheel",
        "cover"
    ],
    "wof:name":"Az Wheels & Sound",
    "wof:placetype":"venue"
},
  "geometry": {"coordinates":[-112.065141,33.50916],"type":"Point"}
}