{
  "type": "Feature",
  "properties": {
    "iso:country":"US",
    "sg:address":"2693 N Industrial Way",
    "sg:city":"Prescott Valley",
    "sg:classifiers":[
        {
            "category":"Building & Trades",
            "subcategory":"Construction",
            "type":"Services"
        }
    ],
    "sg:phone":"+1 928 759 9741",
    "sg:postcode":"86314",
    "sg:province":"AZ",
    "sg:tags":[
        "resurfacing",
        "laying",
        "refinishing",
        "floor"
    ],
    "wof:name":"Desoto",
    "wof:placetype":"venue"
},
  "geometry": {"coordinates":[-112.298402,34.582129],"type":"Point"}
}