{
  "type": "Feature",
  "properties": {
    "iso:country":"US",
    "sg:address":"104 E Route 66",
    "sg:city":"Flagstaff",
    "sg:classifiers":[
        {
            "category":"Personal",
            "subcategory":"Tattoo Parlor",
            "type":"Services"
        },
        {
            "category":"Personal",
            "subcategory":"Piercing",
            "type":"Services"
        }
    ],
    "sg:phone":"+1 928 213 5493",
    "sg:postcode":"86001",
    "sg:province":"AZ",
    "sg:tags":[
        "body"
    ],
    "sg:website":"http://www.tatfutattoo.net",
    "wof:name":"Tat-Fu Tattoo",
    "wof:placetype":"venue"
},
  "geometry": {"coordinates":[-111.647997,35.197115],"type":"Point"}
}