{
  "type": "Feature",
  "properties": {
    "iso:country":"US",
    "sg:address":"777 E Thomas Rd Suite 100",
    "sg:city":"Phoenix",
    "sg:classifiers":[
        {
            "category":"Professional",
            "subcategory":"Lawyer & Legal Services",
            "type":"Services"
        }
    ],
    "sg:phone":"+1 480 422 2014",
    "sg:postcode":"85014",
    "sg:province":"AZ",
    "sg:tags":[
        "divorce",
        "attorney",
        "custody",
        "child"
    ],
    "sg:website":"http://phoenix.citysearch.com/profile/external/41167067/phoenix_az/law_office_of_scott_david_stewart.html?publisher=yellowpages&reference_id=15&placement=ypwebsitemip",
    "wof:name":"Law Office Of Scott David Stewart",
    "wof:placetype":"venue"
},
  "geometry": {"coordinates":[-112.064296,33.480221],"type":"Point"}
}