{
  "type": "Feature",
  "properties": {
    "addr:full":"10 S Gilbert Rd Gilbert AZ 85296",
    "addr:housenumber":"10",
    "addr:postcode":"85296",
    "addr:street":"S Gilbert Rd",
    "iso:country":"US",
    "sg:address":"10 S Gilbert Rd",
    "sg:city":"Gilbert",
    "sg:classifiers":[
        {
            "category":"Museum",
            "type":"Entertainment"
        }
    ],
    "sg:phone":"+1 480 926 1577",
    "sg:postcode":"85296",
    "sg:province":"AZ",
    "wof:name":"Gilbert Historical Society",
    "wof:placetype":"venue"
},
  "geometry": {"coordinates":[-111.78965599999999,33.348304],"type":"Point"}
}