{
  "type": "Feature",
  "properties": {
    "iso:country":"US",
    "sg:address":"7435 E Stetson Dr",
    "sg:city":"Scottsdale",
    "sg:classifiers":[
        {
            "category":"Professional",
            "subcategory":"Accounting & Tax Preparation",
            "type":"Services"
        }
    ],
    "sg:phone":"+1 480 722 1477",
    "sg:postcode":"85251",
    "sg:province":"AZ",
    "sg:tags":[
        "accountant"
    ],
    "wof:name":"Russel A Knight CPA Pllc",
    "wof:placetype":"venue"
},
  "geometry": {"coordinates":[-111.920454,33.499484],"type":"Point"}
}