{
  "type": "Feature",
  "properties": {
    "iso:country":"US",
    "sg:address":"525 E Harrison Drive Apt 216",
    "sg:city":"Avondale",
    "sg:classifiers":[
        {
            "category":"Real Estate",
            "subcategory":"Real Estate Operator",
            "type":"Services"
        }
    ],
    "sg:phone":"+1 623 882 0538",
    "sg:postcode":"85323",
    "sg:province":"AZ",
    "sg:tags":[
        "apartment"
    ],
    "wof:name":"Rose Terrace Apartments",
    "wof:placetype":"venue"
},
  "geometry": {"coordinates":[-112.343551,33.428044],"type":"Point"}
}