{
  "type": "Feature",
  "properties": {
    "iso:country":"US",
    "sg:address":"6860 N Oracle Rd",
    "sg:city":"Tucson",
    "sg:classifiers":[
        {
            "category":"Real Estate",
            "subcategory":"Real Estate Services",
            "type":"Services"
        }
    ],
    "sg:phone":"+1 520 742 7801",
    "sg:postcode":"85704",
    "sg:province":"AZ",
    "sg:tags":[
        "company",
        "title"
    ],
    "wof:name":"Fidelity National Title",
    "wof:placetype":"venue"
},
  "geometry": {"coordinates":[-110.976822,32.331371],"type":"Point"}
}