{
  "type": "Feature",
  "properties": {
    "addr:full":"2424 E Grant Rd Tucson AZ 85719",
    "addr:housenumber":"2424",
    "addr:postcode":"85719",
    "addr:street":"E Grant Rd",
    "iso:country":"US",
    "sg:address":"2424 E Grant Rd",
    "sg:city":"Tucson",
    "sg:classifiers":[
        {
            "category":"Home & Garden",
            "subcategory":"Carpets & Floor Coverings",
            "type":"Retail Goods"
        }
    ],
    "sg:phone":"+1 520 795 4222",
    "sg:postcode":"85719",
    "sg:province":"AZ",
    "wof:name":"Tucson Commercial Carpet Inc",
    "wof:placetype":"venue"
},
  "geometry": {"coordinates":[-110.936654,32.250279],"type":"Point"}
}