{
  "type": "Feature",
  "properties": {
    "iso:country":"US",
    "sg:address":"3508 W Baseline Rd",
    "sg:city":"Laveen",
    "sg:classifiers":[
        {
            "category":"Food & Beverages",
            "subcategory":"Groceries & Convenience Stores",
            "type":"Retail Goods"
        }
    ],
    "sg:phone":"+1 602 237 2728",
    "sg:postcode":"85339",
    "sg:province":"AZ",
    "wof:name":"Circle K",
    "wof:placetype":"venue"
},
  "geometry": {"coordinates":[-112.134556,33.377752],"type":"Point"}
}