{
  "type": "Feature",
  "properties": {
    "iso:country":"US",
    "sg:address":"6090 N Oracle Rd",
    "sg:city":"Tucson",
    "sg:classifiers":[
        {
            "category":"Restaurant",
            "type":"Food & Drink"
        }
    ],
    "sg:phone":"+1 520 575 1767",
    "sg:postcode":"85704",
    "sg:province":"AZ",
    "sg:website":"www.putneystucson.com",
    "wof:name":"Putney's Sports Saloon",
    "wof:placetype":"venue"
},
  "geometry": {"coordinates":[-110.976488,32.31578],"type":"Point"}
}