{
  "type": "Feature",
  "properties": {
    "iso:country":"US",
    "sg:address":"201 W Hermosa Dr",
    "sg:city":"Tempe",
    "sg:classifiers":[
        {
            "category":"Building & Trades",
            "subcategory":"Plumbing",
            "type":"Services"
        }
    ],
    "sg:phone":"+1 480 921 4158",
    "sg:postcode":"85282",
    "sg:province":"AZ",
    "sg:tags":[
        "contractor"
    ],
    "wof:name":"Apex Plumbing",
    "wof:placetype":"venue"
},
  "geometry": {"coordinates":[-111.941774,33.388208],"type":"Point"}
}