{
  "type": "Feature",
  "properties": {
    "iso:country":"US",
    "sg:address":"1347 N Alma School Rd Ste 150",
    "sg:city":"Chandler",
    "sg:classifiers":[
        {
            "category":"Utilities",
            "subcategory":"Telephone",
            "type":"Services"
        }
    ],
    "sg:phone":"+1 631 586 5100",
    "sg:postcode":"85224",
    "sg:province":"AZ",
    "sg:tags":[
        "systems-wholesale",
        "equipment",
        "system",
        "manufacturer"
    ],
    "sg:website":"http://www.oss-sat.com",
    "wof:name":"O'gara Satellite Systems, Inc.",
    "wof:placetype":"venue"
},
  "geometry": {"coordinates":[-111.859123,33.326402],"type":"Point"}
}