{
  "type": "Feature",
  "properties": {
    "iso:country":"US",
    "sg:address":"149 W Main St",
    "sg:city":"Mesa",
    "sg:classifiers":[
        {
            "category":"Manufacturing",
            "subcategory":"Printing",
            "type":"Manufacturing & Wholesale Goods"
        }
    ],
    "sg:phone":"+1 480 833 6900",
    "sg:postcode":"85201",
    "sg:province":"AZ",
    "sg:tags":[
        "screen"
    ],
    "sg:website":"www.shirtail.com",
    "wof:name":"Shirtail Screen & Embroidery",
    "wof:placetype":"venue"
},
  "geometry": {"coordinates":[-111.835614,33.415037],"type":"Point"}
}