{
  "type": "Feature",
  "properties": {
    "addr:full":"385 E Alamo Dr Chandler AZ 85225",
    "addr:housenumber":"385",
    "addr:postcode":"85225",
    "addr:street":"E Alamo Dr",
    "iso:country":"US",
    "sg:address":"385 E Alamo Dr",
    "sg:city":"Chandler",
    "sg:classifiers":[
        {
            "category":"Manufacturing",
            "subcategory":"Electronics",
            "type":"Manufacturing & Wholesale Goods"
        }
    ],
    "sg:phone":"+1 480 497 4511",
    "sg:postcode":"85225",
    "sg:province":"AZ",
    "sg:tags":[
        "semiconductor",
        "devices"
    ],
    "wof:name":"Cactus Custom Analog Design",
    "wof:placetype":"venue"
},
  "geometry": {"coordinates":[-111.83665499999999,33.348442],"type":"Point"}
}