{
  "type": "Feature",
  "properties": {
    "addr:full":"6631 W Peoria Ave Glendale AZ 85302",
    "addr:housenumber":"6631",
    "addr:postcode":"85302",
    "addr:street":"W Peoria Ave",
    "iso:country":"US",
    "sg:address":"6631 W Peoria Ave",
    "sg:city":"Glendale",
    "sg:classifiers":[
        {
            "category":"Shopping",
            "subcategory":"Discount & Variety Stores",
            "type":"Retail Goods"
        }
    ],
    "sg:phone":"+1 623 334 4903",
    "sg:postcode":"85302",
    "sg:province":"AZ",
    "sg:website":"www.familydollar.com",
    "wof:name":"Family Dollar Stores",
    "wof:placetype":"venue"
},
  "geometry": {"coordinates":[-112.2022,33.581647],"type":"Point"}
}