{
  "type": "Feature",
  "properties": {
    "iso:country":"US",
    "sg:address":"4202 E Cactus Rd",
    "sg:city":"Phoenix",
    "sg:classifiers":[
        {
            "category":"Professional",
            "subcategory":"Computer Services",
            "type":"Services"
        }
    ],
    "sg:phone":"+1 602 285 2399",
    "sg:postcode":"85032",
    "sg:province":"AZ",
    "sg:tags":[
        "information",
        "technology"
    ],
    "wof:name":"Major On Line Stores LLC",
    "wof:placetype":"venue"
},
  "geometry": {"coordinates":[-111.991579,33.597991],"type":"Point"}
}