{
  "type": "Feature",
  "properties": {
    "iso:country":"US",
    "sg:address":"4004 E Big Game Pl",
    "sg:city":"Tucson",
    "sg:classifiers":[
        {
            "category":"Retail",
            "subcategory":"Car Wash",
            "type":"Services"
        }
    ],
    "sg:phone":"+1 520 351 2157",
    "sg:postcode":"85706",
    "sg:province":"AZ",
    "wof:name":"Blessed Detailing",
    "wof:placetype":"venue"
},
  "geometry": {"coordinates":[-110.90754099999999,32.14023],"type":"Point"}
}