{
  "type": "Feature",
  "properties": {
    "addr:full":"9750 E Celeste Dr Tucson AZ 85730",
    "addr:housenumber":"9750",
    "addr:postcode":"85730",
    "addr:street":"E Celeste Dr",
    "iso:country":"US",
    "sg:address":"9750 E Celeste Dr",
    "sg:city":"Tucson",
    "sg:classifiers":[
        {
            "category":"Travel",
            "subcategory":"Travel Agent",
            "type":"Entertainment"
        }
    ],
    "sg:phone":"+1 520 722 5280",
    "sg:postcode":"85730",
    "sg:province":"AZ",
    "sg:tags":[
        "agency"
    ],
    "wof:name":"Great Connections Travel",
    "wof:placetype":"venue"
},
  "geometry": {"coordinates":[-110.78439,32.181202],"type":"Point"}
}