{
  "type": "Feature",
  "properties": {
    "iso:country":"US",
    "sg:address":"6604 N 77th Dr",
    "sg:city":"Glendale",
    "sg:classifiers":[
        {
            "category":"Professional",
            "subcategory":"Lawyer & Legal Services",
            "type":"Services"
        }
    ],
    "sg:phone":"+1 623 930 1054",
    "sg:postcode":"85303",
    "sg:province":"AZ",
    "sg:tags":[
        "attorney"
    ],
    "wof:name":"Bruner, Alvoid Jack Mr.",
    "wof:placetype":"venue"
},
  "geometry": {"coordinates":[-112.225517,33.531304],"type":"Point"}
}