{
  "type": "Feature",
  "properties": {
    "iso:country":"US",
    "sg:address":"2850 E Cannon Dr",
    "sg:city":"Phoenix",
    "sg:classifiers":[
        {
            "category":"Social Services",
            "subcategory":"Adult Care",
            "type":"Services"
        }
    ],
    "sg:phone":"+1 602 788 9013",
    "sg:postcode":"85028",
    "sg:province":"AZ",
    "sg:tags":[
        "home",
        "residential"
    ],
    "wof:name":"C & M Adult Care",
    "wof:placetype":"venue"
},
  "geometry": {"coordinates":[-112.018342,33.581973],"type":"Point"}
}