{
  "type": "Feature",
  "properties": {
    "addr:full":"704 E Baseline Rd Buckeye AZ 85326",
    "addr:housenumber":"704",
    "addr:postcode":"85326",
    "addr:street":"E Baseline Rd",
    "iso:country":"US",
    "sg:address":"704 E Baseline Rd",
    "sg:city":"Buckeye",
    "sg:classifiers":[
        {
            "category":"Manufacturing",
            "subcategory":"Textiles",
            "type":"Manufacturing & Wholesale Goods"
        }
    ],
    "sg:phone":"+1 623 386 2680",
    "sg:postcode":"85326",
    "sg:province":"AZ",
    "sg:tags":[
        "broker",
        "cotton"
    ],
    "wof:name":"Tilley Farms Inc",
    "wof:placetype":"venue"
},
  "geometry": {"coordinates":[-112.577499,33.379318],"type":"Point"}
}