{
  "type": "Feature",
  "properties": {
    "iso:country":"US",
    "sg:address":"6520 E 2nd St",
    "sg:city":"Prescott Valley",
    "sg:classifiers":[
        {
            "category":"Wholesale",
            "subcategory":"Painting Supplies",
            "type":"Manufacturing & Wholesale Goods"
        }
    ],
    "sg:phone":"+1 928 759 9372",
    "sg:postcode":"86314",
    "sg:province":"AZ",
    "sg:tags":[
        "paint"
    ],
    "wof:name":"Kelly-Moore Paints",
    "wof:placetype":"venue"
},
  "geometry": {"coordinates":[-112.350082,34.580243],"type":"Point"}
}