{
  "type": "Feature",
  "properties": {
    "iso:country":"US",
    "sg:address":"11681 E Parkview Ln",
    "sg:city":"Scottsdale",
    "sg:classifiers":[
        {
            "category":"Professional",
            "subcategory":"Accounting & Tax Preparation",
            "type":"Services"
        }
    ],
    "sg:phone":"+1 480 609 7201",
    "sg:postcode":"85255",
    "sg:province":"AZ",
    "sg:tags":[
        "billing"
    ],
    "wof:name":"Medical Billing Office",
    "wof:placetype":"venue"
},
  "geometry": {"coordinates":[-111.82850999999999,33.70591],"type":"Point"}
}