{
  "type": "Feature",
  "properties": {
    "iso:country":"US",
    "sg:address":"135 State Hwy 92",
    "sg:city":"Sierra Vista",
    "sg:classifiers":[
        {
            "category":"Shopping",
            "subcategory":"Bicycles & Sporting Goods",
            "type":"Retail Goods"
        }
    ],
    "sg:phone":"+1 520 459 1801",
    "sg:postcode":"85650",
    "sg:province":"AZ",
    "sg:website":"www.big5sportinggoods.com",
    "wof:name":"Big 5 Sporting Goods",
    "wof:placetype":"venue"
},
  "geometry": {"coordinates":[-110.25724700000001,31.553464],"type":"Point"}
}