{
  "type": "Feature",
  "properties": {
    "iso:country":"US",
    "sg:address":"23015 N 15th Ave, Ste 107",
    "sg:city":"Phoenix",
    "sg:phone":"+1 602 548 2399",
    "sg:postcode":"85023",
    "sg:province":"AZ",
    "sg:website":"http://www.yourorc.com",
    "wof:name":"Official Restoration Company",
    "wof:placetype":"venue"
},
  "geometry": {"coordinates":[-112.091774,33.694892],"type":"Point"}
}