{
  "type": "Feature",
  "properties": {
    "iso:country":"US",
    "sg:address":"4625 E Gold Poppy Way",
    "sg:city":"Phoenix",
    "sg:classifiers":[
        {
            "category":"Utilities",
            "subcategory":"Electric",
            "type":"Services"
        }
    ],
    "sg:phone":"+1 480 940 3449",
    "sg:postcode":"85044",
    "sg:province":"AZ",
    "sg:tags":[
        "equipment",
        "supplies-repair",
        "electronic",
        "equipment-repair"
    ],
    "wof:name":"Solutions In Motion Inc",
    "wof:placetype":"venue"
},
  "geometry": {"coordinates":[-111.98458599999999,33.317462],"type":"Point"}
}