{
  "type": "Feature",
  "properties": {
    "iso:country":"US",
    "sg:address":"7202 W Wescott Dr",
    "sg:city":"Glendale",
    "sg:classifiers":[
        {
            "category":"Home & Garden",
            "subcategory":"Garden Supply",
            "type":"Retail Goods"
        }
    ],
    "sg:phone":"+1 602 594 7060",
    "sg:postcode":"85308",
    "sg:province":"AZ",
    "sg:tags":[
        "equipment",
        "lawn",
        "supplies-wholesale",
        "manufacturer"
    ],
    "wof:name":"S & L Products",
    "wof:placetype":"venue"
},
  "geometry": {"coordinates":[-112.21476699999999,33.65659],"type":"Point"}
}