{
  "type": "Feature",
  "properties": {
    "addr:full":"1617 E Jefferson St Phoenix AZ 85034",
    "addr:housenumber":"1617",
    "addr:postcode":"85034",
    "addr:street":"E Jefferson St",
    "iso:country":"US",
    "sg:address":"1617 E Jefferson St",
    "sg:city":"Phoenix",
    "sg:classifiers":[
        {
            "category":"Taxi",
            "type":"Transportation"
        }
    ],
    "sg:phone":"+1 602 468 3618",
    "sg:postcode":"85034",
    "sg:province":"AZ",
    "sg:tags":[
        "taxicab"
    ],
    "wof:name":"Sunrise Cab Inc",
    "wof:placetype":"venue"
},
  "geometry": {"coordinates":[-112.04694600000001,33.447182],"type":"Point"}
}