{
  "type": "Feature",
  "properties": {
    "addr:full":"116 N Lindsay Rd Mesa AZ 85213",
    "addr:housenumber":"116",
    "addr:postcode":"85213",
    "addr:street":"N Lindsay Rd",
    "iso:country":"US",
    "sg:address":"116 N Lindsay Rd",
    "sg:city":"Mesa",
    "sg:classifiers":[
        {
            "category":"Personal",
            "subcategory":"Beauty Salon",
            "type":"Services"
        }
    ],
    "sg:phone":"+1 602 644 0120",
    "sg:postcode":"85213",
    "sg:province":"AZ",
    "wof:name":"Hair Concepts By D & D",
    "wof:placetype":"venue"
},
  "geometry": {"coordinates":[-111.77113300000001,33.4166],"type":"Point"}
}