{
  "type": "Feature",
  "properties": {
    "iso:country":"US",
    "sg:address":"3660 N Oracle Rd",
    "sg:city":"Tucson",
    "sg:classifiers":[
        {
            "category":"Retail",
            "subcategory":"Auto Repair",
            "type":"Services"
        }
    ],
    "sg:phone":"+1 520 408 1650",
    "sg:postcode":"85705",
    "sg:province":"AZ",
    "sg:tags":[
        "repairing",
        "automobile"
    ],
    "wof:name":"Edmund's Automotive",
    "wof:placetype":"venue"
},
  "geometry": {"coordinates":[-110.97804499999999,32.272661],"type":"Point"}
}