{
  "type": "Feature",
  "properties": {
    "addr:full":"609 Miller Valley Rd Prescott AZ 86301",
    "addr:housenumber":"609",
    "addr:postcode":"86301",
    "addr:street":"Miller Valley Rd",
    "iso:country":"US",
    "sg:address":"609 Miller Valley Rd",
    "sg:city":"Prescott",
    "sg:classifiers":[
        {
            "category":"Autos & Motor Vehicles",
            "subcategory":"Auto Supplies",
            "type":"Retail Goods"
        }
    ],
    "sg:phone":"+1 928 442 0111",
    "sg:postcode":"86301",
    "sg:province":"AZ",
    "wof:name":"Batteries Batteries Batteries",
    "wof:placetype":"venue"
},
  "geometry": {"coordinates":[-112.479641,34.551839],"type":"Point"}
}