{
  "type": "Feature",
  "properties": {
    "iso:country":"US",
    "sg:address":"17214 N 15th Dr",
    "sg:city":"Phoenix",
    "sg:classifiers":[
        {
            "category":"Utilities",
            "subcategory":"Fuel Oil & Lpg",
            "type":"Services"
        }
    ],
    "sg:phone":"+1 602 388 2090",
    "sg:postcode":"85023",
    "sg:province":"AZ",
    "sg:tags":[
        "bulk",
        "petroleum-bottled",
        "gas-liquefied"
    ],
    "wof:name":"Desert Flame Gas Works",
    "wof:placetype":"venue"
},
  "geometry": {"coordinates":[-112.092339,33.641638],"type":"Point"}
}