{
  "type": "Feature",
  "properties": {
    "iso:country":"US",
    "sg:address":"1035 E Guadalupe Road",
    "sg:city":"Tempe",
    "sg:classifiers":[
        {
            "category":"Organizations",
            "subcategory":"Religious Organization",
            "type":"Services"
        }
    ],
    "sg:phone":"+1 480 968 6085",
    "sg:postcode":"85283",
    "sg:province":"AZ",
    "wof:name":"University Bible Church",
    "wof:placetype":"venue"
},
  "geometry": {"coordinates":[-111.92501,33.363875],"type":"Point"}
}