{
  "type": "Feature",
  "properties": {
    "addr:full":"21101 N John Wayne Pkwy Maricopa AZ 85239",
    "addr:housenumber":"21101",
    "addr:postcode":"85239",
    "addr:street":"N John Wayne Pkwy",
    "iso:country":"US",
    "sg:address":"21101 N John Wayne Pkwy",
    "sg:city":"Maricopa",
    "sg:classifiers":[
        {
            "category":"Restaurant",
            "type":"Food & Drink"
        }
    ],
    "sg:menulink":"http://www.allmenus.com/az/maricopa-stanfield/104837-taco-del-mar/menu/",
    "sg:phone":"+1 520 568 0884",
    "sg:postcode":"85239",
    "sg:province":"AZ",
    "sg:tags":[
        "mexican"
    ],
    "wof:name":"Taco Del Mar",
    "wof:placetype":"venue"
},
  "geometry": {"coordinates":[-112.04492399999999,33.070834],"type":"Point"}
}