{
  "type": "Feature",
  "properties": {
    "iso:country":"US",
    "sg:address":"1840 E River Rd",
    "sg:city":"Tucson",
    "sg:classifiers":[
        {
            "category":"Professional",
            "subcategory":"Business Services",
            "type":"Services"
        }
    ],
    "sg:phone":"+1 520 408 2373",
    "sg:postcode":"85718",
    "sg:province":"AZ",
    "sg:tags":[
        "inventory"
    ],
    "sg:website":"www.rgisinv.com",
    "wof:name":"RGIS Inventory Specialists",
    "wof:placetype":"venue"
},
  "geometry": {"coordinates":[-110.94171,32.28693],"type":"Point"}
}