{
  "type": "Feature",
  "properties": {
    "addr:full":"19 Sowles Ave Bisbee AZ 85603",
    "addr:housenumber":"19",
    "addr:postcode":"85603",
    "addr:street":"Sowles Ave",
    "iso:country":"US",
    "sg:address":"19 Sowles Ave",
    "sg:city":"Bisbee",
    "sg:classifiers":[
        {
            "category":"Organizations",
            "subcategory":"Religious Organization",
            "type":"Services"
        }
    ],
    "sg:phone":"+1 520 432 7006",
    "sg:postcode":"85603",
    "sg:province":"AZ",
    "sg:tags":[
        "church"
    ],
    "wof:name":"St John's Episcopal Church",
    "wof:placetype":"venue"
},
  "geometry": {"coordinates":[-109.91604700000001,31.442297],"type":"Point"}
}