{
  "type": "Feature",
  "properties": {
    "iso:country":"US",
    "sg:address":"10505 N 69th St",
    "sg:city":"Scottsdale",
    "sg:classifiers":[
        {
            "category":"Real Estate",
            "subcategory":"Surveying",
            "type":"Services"
        }
    ],
    "sg:phone":"+1 480 905 1126",
    "sg:postcode":"85253",
    "sg:province":"AZ",
    "sg:tags":[
        "surveyor"
    ],
    "wof:name":"Professional Land Surveys-Az",
    "wof:placetype":"venue"
},
  "geometry": {"coordinates":[-111.93244199999999,33.581189],"type":"Point"}
}