{
  "type": "Feature",
  "properties": {
    "addr:full":"423 S Stapley Dr Mesa AZ 85204",
    "addr:housenumber":"423",
    "addr:postcode":"85204",
    "addr:street":"S Stapley Dr",
    "iso:country":"US",
    "sg:address":"423 S Stapley Dr",
    "sg:city":"Mesa",
    "sg:classifiers":[
        {
            "category":"Retail",
            "subcategory":"Car Wash",
            "type":"Services"
        }
    ],
    "sg:phone":"+1 480 833 5061",
    "sg:postcode":"85204",
    "sg:province":"AZ",
    "sg:tags":[
        "polishing",
        "washing"
    ],
    "wof:name":"Buggy Bath Car Wash",
    "wof:placetype":"venue"
},
  "geometry": {"coordinates":[-111.805255,33.407689],"type":"Point"}
}