{
  "type": "Feature",
  "properties": {
    "iso:country":"US",
    "sg:address":"4130 E Van Buren St # 250",
    "sg:city":"Phoenix",
    "sg:classifiers":[
        {
            "category":"Professional",
            "subcategory":"Computer Services",
            "type":"Services"
        }
    ],
    "sg:phone":"+1 602 265 5242",
    "sg:postcode":"85008",
    "sg:province":"AZ",
    "sg:tags":[
        "repair",
        "technical",
        "assistance",
        "equipment-service",
        "support"
    ],
    "wof:name":"Adon Network, Inc.",
    "wof:placetype":"venue"
},
  "geometry": {"coordinates":[-111.991804,33.45121],"type":"Point"}
}