{
  "type": "Feature",
  "properties": {
    "addr:full":"300 S 12th St Phoenix AZ 85034",
    "addr:housenumber":"300",
    "addr:postcode":"85034",
    "addr:street":"S 12Th St",
    "iso:country":"US",
    "sg:address":"300 S 12th St",
    "sg:city":"Phoenix",
    "sg:classifiers":[
        {
            "category":"Building & Trades",
            "subcategory":"Construction",
            "type":"Services"
        }
    ],
    "sg:phone":"+1 602 443 9902",
    "sg:postcode":"85034",
    "sg:province":"AZ",
    "sg:tags":[
        "management"
    ],
    "wof:name":"4 Wall Builders",
    "wof:placetype":"venue"
},
  "geometry": {"coordinates":[-112.056427,33.445461],"type":"Point"}
}