{
  "type": "Feature",
  "properties": {
    "iso:country":"US",
    "sg:address":"7430 E Butherus Dr",
    "sg:city":"Scottsdale",
    "sg:classifiers":[
        {
            "category":"Real Estate",
            "subcategory":"Real Estate Agent",
            "type":"Services"
        }
    ],
    "sg:phone":"+1 480 905 5900",
    "sg:postcode":"85260",
    "sg:province":"AZ",
    "sg:tags":[
        "inspection"
    ],
    "sg:website":"www.newcomersaz.com",
    "wof:name":"Newcomer's Inspection Svc",
    "wof:placetype":"venue"
},
  "geometry": {"coordinates":[-111.918515,33.622663],"type":"Point"}
}