{
  "type": "Feature",
  "properties": {
    "addr:full":"602 S Alandale Ave Tucson AZ 85710",
    "addr:housenumber":"602",
    "addr:postcode":"85710",
    "addr:street":"S Alandale Ave",
    "iso:country":"US",
    "sg:address":"602 S Alandale Ave",
    "sg:city":"Tucson",
    "sg:classifiers":[
        {
            "category":"Retail",
            "subcategory":"Auto Repair",
            "type":"Services"
        }
    ],
    "sg:phone":"+1 520 792 0703",
    "sg:postcode":"85710",
    "sg:province":"AZ",
    "sg:tags":[
        "truck"
    ],
    "wof:name":"Diesel Chaser",
    "wof:placetype":"venue"
},
  "geometry": {"coordinates":[-110.82149200000001,32.21292],"type":"Point"}
}