{
  "type": "Feature",
  "properties": {
    "iso:country":"US",
    "sg:address":"7775 S Ave 19 E",
    "sg:city":"Wellton",
    "sg:classifiers":[
        {
            "category":"Farming",
            "subcategory":"Farm",
            "type":"Manufacturing & Wholesale Goods"
        }
    ],
    "sg:phone":"+1 928 785 4096",
    "sg:postcode":"85356",
    "sg:province":"AZ",
    "sg:tags":[
        "crop",
        "general"
    ],
    "wof:name":"Pratt Farms Inc",
    "wof:placetype":"venue"
},
  "geometry": {"coordinates":[-114.313197,32.710936],"type":"Point"}
}