{
  "type": "Feature",
  "properties": {
    "addr:full":"450 Jordan Rd Sedona AZ 86336",
    "addr:housenumber":"450",
    "addr:postcode":"86336",
    "addr:street":"Jordan Rd",
    "iso:country":"US",
    "sg:address":"450 Jordan Rd",
    "sg:city":"Sedona",
    "sg:classifiers":[
        {
            "category":"Professional",
            "subcategory":"Computer Services",
            "type":"Services"
        }
    ],
    "sg:phone":"+1 928 204 5553",
    "sg:postcode":"86336",
    "sg:province":"AZ",
    "sg:tags":[
        "website",
        "design"
    ],
    "wof:name":"Sun Graphic",
    "wof:placetype":"venue"
},
  "geometry": {"coordinates":[-111.761026,34.873403],"type":"Point"}
}