{
  "type": "Feature",
  "properties": {
    "addr:full":"8805 W Palm Ln Phoenix AZ 85037",
    "addr:housenumber":"8805",
    "addr:postcode":"85037",
    "addr:street":"W Palm Ln",
    "iso:country":"US",
    "sg:address":"8805 W Palm Ln",
    "sg:city":"Phoenix",
    "sg:classifiers":[
        {
            "category":"Professional",
            "subcategory":"Accounting & Tax Preparation",
            "type":"Services"
        }
    ],
    "sg:phone":"+1 623 907 3990",
    "sg:postcode":"85037",
    "sg:province":"AZ",
    "sg:tags":[
        "return",
        "filing"
    ],
    "wof:name":"Accounting & Adm Svc",
    "wof:placetype":"venue"
},
  "geometry": {"coordinates":[-112.249308,33.468823],"type":"Point"}
}