{
  "type": "Feature",
  "properties": {
    "addr:full":"4101 E Illinois St Tucson AZ 85714",
    "addr:housenumber":"4101",
    "addr:postcode":"85714",
    "addr:street":"E Illinois St",
    "iso:country":"US",
    "sg:address":"4101 E Illinois St",
    "sg:city":"Tucson",
    "sg:classifiers":[
        {
            "category":"Building & Trades",
            "subcategory":"Construction",
            "type":"Services"
        }
    ],
    "sg:phone":"+1 520 748 7007",
    "sg:postcode":"85714",
    "sg:province":"AZ",
    "sg:tags":[
        "nonresidential",
        "contractor"
    ],
    "wof:name":"Cooley Corporation",
    "wof:placetype":"venue"
},
  "geometry": {"coordinates":[-110.90191900000001,32.169182],"type":"Point"}
}