{
  "type": "Feature",
  "properties": {
    "addr:full":"7252 S Central Ave Phoenix AZ 85042",
    "addr:housenumber":"7252",
    "addr:postcode":"85042",
    "addr:street":"S Central Ave",
    "iso:country":"US",
    "sg:address":"7252 S Central Ave",
    "sg:city":"Phoenix",
    "sg:classifiers":[
        {
            "category":"Professional",
            "type":"Services"
        }
    ],
    "sg:phone":"+1 602 232 2061",
    "sg:postcode":"85042",
    "sg:province":"AZ",
    "sg:tags":[
        "establishment"
    ],
    "wof:name":"Goad International",
    "wof:placetype":"venue"
},
  "geometry": {"coordinates":[-112.073261,33.379174],"type":"Point"}
}