{
  "type": "Feature",
  "properties": {
    "iso:country":"US",
    "sg:address":"455 N Ferro Ave",
    "sg:city":"Tucson",
    "sg:classifiers":[
        {
            "category":"Professional",
            "subcategory":"Art Services",
            "type":"Services"
        }
    ],
    "sg:phone":"+1 520 882 2033",
    "sg:postcode":"85705",
    "sg:province":"AZ",
    "sg:tags":[
        "photographer"
    ],
    "wof:name":"Fotosmith",
    "wof:placetype":"venue"
},
  "geometry": {"coordinates":[-110.96950099999999,32.227124],"type":"Point"}
}