{
  "type": "Feature",
  "properties": {
    "addr:full":"161 E Deuce of Clubs Show Low AZ 85901",
    "addr:housenumber":"161",
    "addr:postcode":"85901",
    "addr:street":"E Deuce Of Clubs",
    "iso:country":"US",
    "sg:address":"161 E Deuce of Clubs",
    "sg:city":"Show Low",
    "sg:classifiers":[
        {
            "category":"Shopping",
            "subcategory":"Discount & Variety Stores",
            "type":"Retail Goods"
        }
    ],
    "sg:phone":"+1 928 537 2981",
    "sg:postcode":"85901",
    "sg:province":"AZ",
    "wof:name":"Family Dollar Stores",
    "wof:placetype":"venue"
},
  "geometry": {"coordinates":[-110.04103000000001,34.251101],"type":"Point"}
}