{
  "type": "Feature",
  "properties": {
    "addr:full":"11011 E Delta Ave Mesa AZ 85208",
    "addr:housenumber":"11011",
    "addr:postcode":"85208",
    "addr:street":"E Delta Ave",
    "iso:country":"US",
    "sg:address":"11011 E Delta Ave",
    "sg:city":"Mesa",
    "sg:classifiers":[
        {
            "category":"Building & Trades",
            "subcategory":"Construction",
            "type":"Services"
        }
    ],
    "sg:phone":"+1 480 986 5531",
    "sg:postcode":"85208",
    "sg:province":"AZ",
    "sg:tags":[
        "contractor"
    ],
    "wof:name":"JNF Contracting",
    "wof:placetype":"venue"
},
  "geometry": {"coordinates":[-111.592326,33.400976],"type":"Point"}
}