{
  "type": "Feature",
  "properties": {
    "iso:country":"US",
    "sg:address":"9001 S Eisenhower Rd",
    "sg:city":"Tucson",
    "sg:classifiers":[
        {
            "category":"Freight",
            "type":"Transportation"
        }
    ],
    "sg:phone":"+1 520 294 2384",
    "sg:postcode":"85706",
    "sg:province":"AZ",
    "wof:name":"Titan Transport",
    "wof:placetype":"venue"
},
  "geometry": {"coordinates":[-110.957407,32.086324],"type":"Point"}
}