{
  "type": "Feature",
  "properties": {
    "iso:country":"US",
    "sg:address":"7101 E Jackrabbit Rd",
    "sg:city":"Paradise Valley",
    "sg:classifiers":[
        {
            "category":"Health Services",
            "subcategory":"Clinic",
            "type":"Services"
        }
    ],
    "sg:phone":"+1 480 994 4080",
    "sg:postcode":"85253",
    "sg:province":"AZ",
    "sg:tags":[
        "surgical",
        "center"
    ],
    "wof:name":"Paradise Valley Cosmetic Ctr",
    "wof:placetype":"venue"
},
  "geometry": {"coordinates":[-111.926403,33.516771],"type":"Point"}
}