{
  "type": "Feature",
  "properties": {
    "iso:country":"US",
    "sg:address":"3721 E Thomas Rd",
    "sg:city":"Phoenix",
    "sg:classifiers":[
        {
            "category":"Banks & Credit Unions",
            "subcategory":"Bank",
            "type":"Services"
        }
    ],
    "sg:phone":"+1 602 797 0211",
    "sg:postcode":"85018",
    "sg:province":"AZ",
    "wof:name":"First National Bank Of Arizona",
    "wof:placetype":"venue"
},
  "geometry": {"coordinates":[-112.000132,33.480367],"type":"Point"}
}