{
  "type": "Feature",
  "properties": {
    "addr:full":"6025 N 7th St Phoenix AZ 85014",
    "addr:housenumber":"6025",
    "addr:postcode":"85014",
    "addr:street":"N 7Th St",
    "iso:country":"US",
    "sg:address":"6025 N 7th St",
    "sg:city":"Phoenix",
    "sg:classifiers":[
        {
            "category":"Shopping",
            "subcategory":"Beauty & Cosmetics",
            "type":"Retail Goods"
        },
        {
            "category":"Personal",
            "subcategory":"Barber",
            "type":"Services"
        }
    ],
    "sg:phone":"+1 602 200 0789",
    "sg:postcode":"85014",
    "sg:province":"AZ",
    "sg:tags":[
        "equipment",
        "salons-equipment",
        "supply"
    ],
    "wof:name":"West Coast Beauty Supply",
    "wof:placetype":"venue"
},
  "geometry": {"coordinates":[-112.065003,33.523961],"type":"Point"}
}