{
  "type": "Feature",
  "properties": {
    "iso:country":"US",
    "sg:address":"3425 W Thunderbird Rd",
    "sg:city":"Phoenix",
    "sg:classifiers":[
        {
            "category":"Shopping",
            "subcategory":"Clothing, Apparel, & Fashions",
            "type":"Retail Goods"
        }
    ],
    "sg:phone":"+1 602 863 6443",
    "sg:postcode":"85053",
    "sg:province":"AZ",
    "wof:name":"Ys Fashion",
    "wof:placetype":"venue"
},
  "geometry": {"coordinates":[-112.133185,33.610741],"type":"Point"}
}