{
  "type": "Feature",
  "properties": {
    "addr:full":"8989 N Pima Rd Scottsdale AZ 85258",
    "addr:housenumber":"8989",
    "addr:postcode":"85258",
    "addr:street":"N Pima Rd",
    "iso:country":"US",
    "sg:address":"8989 N Pima Rd",
    "sg:city":"Scottsdale",
    "sg:classifiers":[
        {
            "category":"Building & Trades",
            "subcategory":"Construction",
            "type":"Services"
        }
    ],
    "sg:phone":"+1 602 956 2054",
    "sg:postcode":"85258",
    "sg:province":"AZ",
    "sg:tags":[
        "masonry",
        "contractor"
    ],
    "wof:name":"Rock & Stone",
    "wof:placetype":"venue"
},
  "geometry": {"coordinates":[-111.891341,33.563791],"type":"Point"}
}