{
  "type": "Feature",
  "properties": {
    "iso:country":"US",
    "sg:address":"1241 E Broadway Rd",
    "sg:city":"Mesa",
    "sg:classifiers":[
        {
            "category":"Personal",
            "type":"Services"
        }
    ],
    "sg:phone":"+1 602 644 0353",
    "sg:postcode":"85204",
    "sg:province":"AZ",
    "sg:tags":[
        "therapist",
        "massage"
    ],
    "wof:name":"Exclusive Massage",
    "wof:placetype":"venue"
},
  "geometry": {"coordinates":[-111.803634,33.407862],"type":"Point"}
}