{
  "type": "Feature",
  "properties": {
    "iso:country":"US",
    "sg:address":"7039 W Firebird Dr",
    "sg:city":"Glendale",
    "sg:classifiers":[
        {
            "category":"Shopping",
            "subcategory":"Discount & Variety Stores",
            "type":"Retail Goods"
        }
    ],
    "sg:phone":"+1 623 572 0214",
    "sg:postcode":"85308",
    "sg:province":"AZ",
    "sg:tags":[
        "merchandise",
        "general"
    ],
    "wof:name":"Specialty & Technical Products",
    "wof:placetype":"venue"
},
  "geometry": {"coordinates":[-112.21271299999999,33.676761],"type":"Point"}
}