{
  "type": "Feature",
  "properties": {
    "addr:full":"10448 W Coggins Dr Sun City AZ 85351",
    "addr:housenumber":"10448",
    "addr:postcode":"85351",
    "addr:street":"W Coggins Dr",
    "iso:country":"US",
    "sg:address":"10448 W Coggins Dr",
    "sg:city":"Sun City",
    "sg:classifiers":[
        {
            "category":"Health Services",
            "subcategory":"Clinic",
            "type":"Services"
        }
    ],
    "sg:phone":"+1 623 974 7500",
    "sg:postcode":"85351",
    "sg:province":"AZ",
    "sg:tags":[
        "home"
    ],
    "wof:name":"Sun Health",
    "wof:placetype":"venue"
},
  "geometry": {"coordinates":[-112.282556,33.598631],"type":"Point"}
}