{
  "type": "Feature",
  "properties": {
    "addr:full":"865 S Cooper Rd Gilbert AZ 85233",
    "addr:housenumber":"865",
    "addr:postcode":"85233",
    "addr:street":"S Cooper Rd",
    "iso:country":"US",
    "sg:address":"865 S Cooper Rd",
    "sg:city":"Gilbert",
    "sg:classifiers":[
        {
            "category":"Restaurant",
            "type":"Food & Drink"
        }
    ],
    "sg:menulink":"http://www.allmenus.com/az/chandler/198785-kfc---kentucky-fried-chicken/menu/",
    "sg:phone":"+1 480 782 8285",
    "sg:postcode":"85233",
    "sg:province":"AZ",
    "sg:tags":[
        "american",
        "chicken"
    ],
    "wof:name":"KFC - Kentucky Fried Chicken",
    "wof:placetype":"venue"
},
  "geometry": {"coordinates":[-111.806301,33.334121],"type":"Point"}
}