{
  "type": "Feature",
  "properties": {
    "iso:country":"US",
    "sg:address":"14 Old Douglas Rd",
    "sg:city":"Bisbee",
    "sg:classifiers":[
        {
            "category":"Building & Trades",
            "subcategory":"Construction",
            "type":"Services"
        }
    ],
    "sg:phone":"+1 520 432 2743",
    "sg:postcode":"85603",
    "sg:province":"AZ",
    "sg:tags":[
        "residential",
        "nonresidential"
    ],
    "wof:name":"Gruey Construction",
    "wof:placetype":"venue"
},
  "geometry": {"coordinates":[-109.887854,31.42868],"type":"Point"}
}