{
  "type": "Feature",
  "properties": {
    "iso:country":"US",
    "sg:address":"505 Riata Valley Rd",
    "sg:city":"Kingman",
    "sg:classifiers":[
        {
            "category":"Professional",
            "subcategory":"Accounting & Tax Preparation",
            "type":"Services"
        }
    ],
    "sg:phone":"+1 928 757 5400",
    "sg:postcode":"86409",
    "sg:province":"AZ",
    "sg:tags":[
        "accountant"
    ],
    "wof:name":"Accounting Services Unlimited",
    "wof:placetype":"venue"
},
  "geometry": {"coordinates":[-114.050597,35.230597],"type":"Point"}
}