{
  "type": "Feature",
  "properties": {
    "addr:full":"3826 W Libby St Glendale AZ 85308",
    "addr:housenumber":"3826",
    "addr:postcode":"85308",
    "addr:street":"W Libby St",
    "iso:country":"US",
    "sg:address":"3826 W Libby St",
    "sg:city":"Glendale",
    "sg:classifiers":[
        {
            "category":"Home & Garden",
            "subcategory":"Carpets & Floor Coverings",
            "type":"Retail Goods"
        }
    ],
    "sg:phone":"+1 602 677 9096",
    "sg:postcode":"85308",
    "sg:province":"AZ",
    "sg:tags":[
        "material"
    ],
    "wof:name":"Long Lasting Floors, Inc.",
    "wof:placetype":"venue"
},
  "geometry": {"coordinates":[-112.142212,33.648071],"type":"Point"}
}