{
  "type": "Feature",
  "properties": {
    "iso:country":"US",
    "sg:address":"2929 N 44th St",
    "sg:city":"Phoenix",
    "sg:phone":"+1 602 441 0003",
    "sg:postcode":"85018",
    "sg:province":"AZ",
    "sg:tags":[
        "oil"
    ],
    "wof:name":"Musket Corp",
    "wof:placetype":"venue"
},
  "geometry": {"coordinates":[-111.986915,33.481529],"type":"Point"}
}