{
  "type": "Feature",
  "properties": {
    "addr:full":"6708 W Deer Valley Rd Glendale AZ 85310",
    "addr:housenumber":"6708",
    "addr:postcode":"85310",
    "addr:street":"W Deer Valley Rd",
    "iso:country":"US",
    "sg:address":"6708 W Deer Valley Rd",
    "sg:city":"Glendale",
    "sg:classifiers":[
        {
            "category":"Restaurant",
            "type":"Food & Drink"
        }
    ],
    "sg:menulink":"http://www.allmenus.com/az/deer-valley/204945-taco-bell/menu/",
    "sg:postcode":"85310",
    "sg:province":"AZ",
    "sg:tags":[
        "mexican"
    ],
    "wof:name":"Taco Bell",
    "wof:placetype":"venue"
},
  "geometry": {"coordinates":[-112.203619,33.682278],"type":"Point"}
}