{
  "type": "Feature",
  "properties": {
    "iso:country":"US",
    "sg:address":"28307 N 156th Way",
    "sg:city":"Scottsdale",
    "sg:classifiers":[
        {
            "category":"Shopping",
            "subcategory":"Pets & Pet Supplies",
            "type":"Retail Goods"
        },
        {
            "category":"Retail",
            "subcategory":"Veterinary Services",
            "type":"Services"
        }
    ],
    "sg:phone":"+1 480 941 8040",
    "sg:postcode":"85262",
    "sg:province":"AZ",
    "sg:tags":[
        "specialty"
    ],
    "sg:website":"http://www.almosthome.net",
    "wof:name":"Canine Behavior Consultants",
    "wof:placetype":"venue"
},
  "geometry": {"coordinates":[-111.741677,33.742921],"type":"Point"}
}