{
  "type": "Feature",
  "properties": {
    "addr:full":"1310 Iron Springs Rd Prescott AZ 86305",
    "addr:housenumber":"1310",
    "addr:postcode":"86305",
    "addr:street":"Iron Springs Rd",
    "iso:country":"US",
    "sg:address":"1310 Iron Springs Rd",
    "sg:city":"Prescott",
    "sg:classifiers":[
        {
            "category":"Mining & Drilling",
            "type":"Manufacturing & Wholesale Goods"
        }
    ],
    "sg:phone":"+1 928 443 0297",
    "sg:postcode":"86305",
    "sg:province":"AZ",
    "sg:tags":[
        "oil",
        "gas",
        "producer"
    ],
    "wof:name":"Bennett Oil Co",
    "wof:placetype":"venue"
},
  "geometry": {"coordinates":[-112.48708000000001,34.562176],"type":"Point"}
}