{
  "type": "Feature",
  "properties": {
    "iso:country":"US",
    "sg:address":"1310 Iron Springs Rd",
    "sg:city":"Prescott",
    "sg:classifiers":[
        {
            "category":"Mining & Drilling",
            "type":"Manufacturing & Wholesale Goods"
        }
    ],
    "sg:phone":"+1 928 443 0297",
    "sg:postcode":"86305",
    "sg:province":"AZ",
    "sg:tags":[
        "oil",
        "gas",
        "producer"
    ],
    "wof:name":"Bennett Oil Co",
    "wof:placetype":"venue"
},
  "geometry": {"coordinates":[-112.48708,34.562176],"type":"Point"}
}