{
  "type": "Feature",
  "properties": {
    "iso:country":"US",
    "sg:address":"2470 W Tom Watson Dr",
    "sg:city":"Tucson",
    "sg:classifiers":[
        {
            "category":"Recreation",
            "type":"Entertainment"
        }
    ],
    "sg:phone":"+1 520 219 9060",
    "sg:postcode":"85742",
    "sg:province":"AZ",
    "sg:tags":[
        "pool",
        "swimming"
    ],
    "wof:name":"Swim Girl",
    "wof:placetype":"venue"
},
  "geometry": {"coordinates":[-111.021748,32.365454],"type":"Point"}
}