{
  "type": "Feature",
  "properties": {
    "iso:country":"US",
    "sg:address":"7596 E Palo Verde St",
    "sg:city":"Prescott Valley",
    "sg:classifiers":[
        {
            "category":"Personal",
            "subcategory":"Beauty Salon",
            "type":"Services"
        }
    ],
    "sg:phone":"+1 928 775 0502",
    "sg:postcode":"86314",
    "sg:province":"AZ",
    "wof:name":"Hair By Michelle",
    "wof:placetype":"venue"
},
  "geometry": {"coordinates":[-112.331948,34.63558],"type":"Point"}
}