{
  "type": "Feature",
  "properties": {
    "iso:country":"US",
    "sg:address":"16238 N Oracle Rd",
    "sg:city":"Tucson",
    "sg:classifiers":[
        {
            "category":"Restaurant",
            "type":"Food & Drink"
        }
    ],
    "sg:phone":"+1 520 825 3040",
    "sg:postcode":"85739",
    "sg:province":"AZ",
    "sg:tags":[
        "mexican"
    ],
    "wof:name":"Mi Tierra Restaurant",
    "wof:placetype":"venue"
},
  "geometry": {"coordinates":[-110.92600299999999,32.5009],"type":"Point"}
}