{
  "type": "Feature",
  "properties": {
    "iso:country":"US",
    "sg:address":"424 W Nebraska St",
    "sg:city":"Tucson",
    "sg:classifiers":[
        {
            "category":"Organizations",
            "subcategory":"Religious Organization",
            "type":"Services"
        }
    ],
    "sg:phone":"+1 520 294 6465",
    "sg:postcode":"85706",
    "sg:province":"AZ",
    "sg:tags":[
        "church"
    ],
    "wof:name":"Templo Nuevos Horizontes",
    "wof:placetype":"venue"
},
  "geometry": {"coordinates":[-110.97588,32.156026],"type":"Point"}
}