{
  "type": "Feature",
  "properties": {
    "iso:country":"US",
    "sg:address":"2925 N 38th St",
    "sg:city":"Phoenix",
    "sg:classifiers":[
        {
            "category":"Real Estate",
            "subcategory":"Real Estate Operator",
            "type":"Services"
        }
    ],
    "sg:phone":"+1 602 840 0878",
    "sg:postcode":"85018",
    "sg:province":"AZ",
    "sg:tags":[
        "apartment"
    ],
    "wof:name":"Sterling Apartments",
    "wof:placetype":"venue"
},
  "geometry": {"coordinates":[-111.999847,33.480994],"type":"Point"}
}