{
  "type": "Feature",
  "properties": {
    "iso:country":"US",
    "sg:address":"52227 US Hwy 60",
    "sg:city":"Aguila",
    "sg:classifiers":[
        {
            "category":"Travel",
            "subcategory":"Campground",
            "type":"Entertainment"
        }
    ],
    "sg:phone":"+1 928 685 2412",
    "sg:postcode":"85320",
    "sg:province":"AZ",
    "sg:tags":[
        "recreational",
        "parks",
        "vehicle"
    ],
    "wof:name":"Fairhaven RV Park",
    "wof:placetype":"venue"
},
  "geometry": {"coordinates":[-113.235995,33.924523],"type":"Point"}
}