{
  "type": "Feature",
  "properties": {
    "iso:country":"US",
    "sg:address":"625 S McClintock Dr",
    "sg:city":"Tempe",
    "sg:classifiers":[
        {
            "category":"Building & Trades",
            "subcategory":"Construction",
            "type":"Services"
        }
    ],
    "sg:phone":"+1 480 831 7932",
    "sg:postcode":"85281",
    "sg:province":"AZ",
    "sg:tags":[
        "coping",
        "plastering",
        "tiling",
        "pool",
        "swimming"
    ],
    "wof:name":"Coral Pools Inc",
    "wof:placetype":"venue"
},
  "geometry": {"coordinates":[-111.908977,33.423776],"type":"Point"}
}