{
  "type": "Feature",
  "properties": {
    "addr:full":"7131 W Ray Rd Chandler AZ 85226",
    "addr:housenumber":"7131",
    "addr:postcode":"85226",
    "addr:street":"W Ray Rd",
    "iso:country":"US",
    "sg:address":"7131 W Ray Rd",
    "sg:city":"Chandler",
    "sg:classifiers":[
        {
            "category":"Bars & Pubs",
            "type":"Food & Drink"
        }
    ],
    "sg:menulink":"http://www.allmenus.com/az/chandler/267779-56-east-bar--kitchen/menu/",
    "sg:phone":"+1 480 705 5602",
    "sg:postcode":"85226",
    "sg:province":"AZ",
    "sg:tags":[
        "american"
    ],
    "wof:name":"56 East Bar & Kitchen",
    "wof:placetype":"venue"
},
  "geometry": {"coordinates":[-111.965783,33.318515],"type":"Point"}
}