{
  "type": "Feature",
  "properties": {
    "iso:country":"US",
    "sg:address":"5735 W Campo Bello Dr",
    "sg:city":"Glendale",
    "sg:classifiers":[
        {
            "category":"Utilities",
            "subcategory":"Telephone",
            "type":"Services"
        }
    ],
    "sg:phone":"+1 602 688 9543",
    "sg:postcode":"85308",
    "sg:province":"AZ",
    "sg:tags":[
        "telecommunication"
    ],
    "wof:name":"Excel Communications",
    "wof:placetype":"venue"
},
  "geometry": {"coordinates":[-112.183101,33.644311],"type":"Point"}
}