{
  "type": "Feature",
  "properties": {
    "addr:full":"4050 E Columbia St Tucson AZ 85714",
    "addr:housenumber":"4050",
    "addr:postcode":"85714",
    "addr:street":"E;St",
    "iso:country":"US",
    "sg:address":"4050 E Columbia St",
    "sg:city":"Tucson",
    "sg:classifiers":[
        {
            "category":"Wholesale",
            "subcategory":"Electrical",
            "type":"Manufacturing & Wholesale Goods"
        }
    ],
    "sg:phone":"+1 520 293 7777",
    "sg:postcode":"85714",
    "sg:province":"AZ",
    "sg:tags":[
        "signal",
        "traffic",
        "sign"
    ],
    "sg:website":"www.nesrentals.com",
    "wof:name":"NES Traffic Safety",
    "wof:placetype":"venue"
},
  "geometry": {"coordinates":[-110.906113,32.173395],"type":"Point"}
}