{
  "type": "Feature",
  "properties": {
    "iso:country":"US",
    "sg:address":"6937 E Princeton Dr",
    "sg:city":"Tucson",
    "sg:classifiers":[
        {
            "category":"Professional",
            "type":"Services"
        }
    ],
    "sg:phone":"+1 520 571 9577",
    "sg:postcode":"85710",
    "sg:province":"AZ",
    "wof:name":"Rincon Valley Securit",
    "wof:placetype":"venue"
},
  "geometry": {"coordinates":[-110.845181,32.210491],"type":"Point"}
}