{
  "type": "Feature",
  "properties": {
    "iso:country":"US",
    "sg:address":"2265 Swanson Ave",
    "sg:city":"Lake Havasu City",
    "sg:classifiers":[
        {
            "category":"Professional",
            "subcategory":"Computer Services",
            "type":"Services"
        }
    ],
    "sg:phone":"+1 928 855 7040",
    "sg:postcode":"86403",
    "sg:province":"AZ",
    "sg:website":"www.dmcdesigns.com",
    "wof:name":"Data Masters",
    "wof:placetype":"venue"
},
  "geometry": {"coordinates":[-114.3219,34.47396],"type":"Point"}
}