{
  "type": "Feature",
  "properties": {
    "iso:country":"US",
    "sg:address":"1500 N Page Springs Rd",
    "sg:city":"Cornville",
    "sg:classifiers":[
        {
            "category":"Professional",
            "type":"Services"
        }
    ],
    "sg:phone":"+1 928 639 3004",
    "sg:postcode":"86325",
    "sg:province":"AZ",
    "sg:tags":[
        "establishment"
    ],
    "wof:name":"Page Springs Sellers",
    "wof:placetype":"venue"
},
  "geometry": {"coordinates":[-111.887517,34.75593],"type":"Point"}
}