{
  "type": "Feature",
  "properties": {
    "addr:full":"115 E Watkins St Phoenix AZ 85004",
    "addr:housenumber":"115",
    "addr:postcode":"85004",
    "addr:street":"E Watkins St",
    "iso:country":"US",
    "sg:address":"115 E Watkins St",
    "sg:city":"Phoenix",
    "sg:classifiers":[
        {
            "category":"Building & Trades",
            "subcategory":"Construction",
            "type":"Services"
        },
        {
            "category":"Home & Garden",
            "subcategory":"Furniture",
            "type":"Retail Goods"
        }
    ],
    "sg:phone":"+1 602 257 0100",
    "sg:postcode":"85004",
    "sg:province":"AZ",
    "sg:tags":[
        "cabinet",
        "wood",
        "kitchen",
        "mfg"
    ],
    "wof:name":"Builders Choice Cabinetry LLC",
    "wof:placetype":"venue"
},
  "geometry": {"coordinates":[-112.071449,33.425765],"type":"Point"}
}