{
  "type": "Feature",
  "properties": {
    "iso:country":"US",
    "sg:address":"4322 E Upper Ridge Way",
    "sg:city":"Paradise Valley",
    "sg:classifiers":[
        {
            "category":"Professional",
            "type":"Services"
        }
    ],
    "sg:phone":"+1 480 367 7948",
    "sg:postcode":"85253",
    "sg:province":"AZ",
    "wof:name":"Faramarz Boorboor",
    "wof:placetype":"venue"
},
  "geometry": {"coordinates":[-111.98753000000001,33.538663],"type":"Point"}
}