{
  "type": "Feature",
  "properties": {
    "iso:country":"US",
    "sg:address":"365 S Main St",
    "sg:city":"Camp Verde",
    "sg:classifiers":[
        {
            "category":"Real Estate",
            "subcategory":"Real Estate Agent",
            "type":"Services"
        }
    ],
    "sg:phone":"+1 928 554 0400",
    "sg:postcode":"86322",
    "sg:province":"AZ",
    "wof:name":"Windermere Real Estate",
    "wof:placetype":"venue"
},
  "geometry": {"coordinates":[-111.85455399999999,34.564315],"type":"Point"}
}