{
  "type": "Feature",
  "properties": {
    "addr:full":"4604 E Cactus Rd Phoenix AZ 85032",
    "addr:housenumber":"4604",
    "addr:postcode":"85032",
    "addr:street":"E Cactus Rd",
    "iso:country":"US",
    "sg:address":"4604 E Cactus Rd",
    "sg:city":"Phoenix",
    "sg:classifiers":[
        {
            "category":"Wholesale",
            "subcategory":"Medical Equipment & Supplies",
            "type":"Manufacturing & Wholesale Goods"
        }
    ],
    "sg:phone":"+1 602 953 1422",
    "sg:postcode":"85032",
    "sg:province":"AZ",
    "sg:tags":[
        "device",
        "assistive",
        "aid",
        "hearing"
    ],
    "wof:name":"Miracle Ear Store",
    "wof:placetype":"venue"
},
  "geometry": {"coordinates":[-111.981911,33.599255],"type":"Point"}
}