{
  "type": "Feature",
  "properties": {
    "iso:country":"US",
    "sg:address":"5250 N Gerhart Rd",
    "sg:city":"Tucson",
    "sg:classifiers":[
        {
            "category":"Shopping",
            "subcategory":"Computers & Home Electronics",
            "type":"Retail Goods"
        }
    ],
    "sg:phone":"+1 520 622 3850",
    "sg:postcode":"85745",
    "sg:province":"AZ",
    "wof:name":"Primetime Mini Dish",
    "wof:placetype":"venue"
},
  "geometry": {"coordinates":[-111.088334,32.303377],"type":"Point"}
}