{
  "type": "Feature",
  "properties": {
    "iso:country":"US",
    "sg:address":"40 W Baseline Rd Ste 201",
    "sg:city":"Mesa",
    "sg:classifiers":[
        {
            "category":"Manufacturing",
            "subcategory":"Chemicals & Compounds",
            "type":"Manufacturing & Wholesale Goods"
        }
    ],
    "sg:phone":"+1 480 827 1366",
    "sg:postcode":"85210",
    "sg:province":"AZ",
    "sg:tags":[
        "chemicals-wholesale",
        "manufacturer"
    ],
    "wof:name":"Marks Paper and Chemical Company",
    "wof:placetype":"venue"
},
  "geometry": {"coordinates":[-111.832572,33.37886],"type":"Point"}
}