{
  "type": "Feature",
  "properties": {
    "iso:country":"US",
    "sg:address":"557 E. Juanita Ave",
    "sg:city":"Mesa",
    "sg:classifiers":[
        {
            "category":"Autos & Motor Vehicles",
            "subcategory":"Automobile Sales",
            "type":"Retail Goods"
        },
        {
            "category":"Professional",
            "type":"Services"
        },
        {
            "category":"Retail",
            "subcategory":"Auto Repair",
            "type":"Services"
        }
    ],
    "sg:phone":"+1 480 789 3367",
    "sg:postcode":"85204",
    "sg:province":"AZ",
    "sg:tags":[
        "automotive"
    ],
    "sg:website":"www.tuninggruppe.com",
    "wof:name":"Tuning Gr?ppe",
    "wof:placetype":"venue"
},
  "geometry": {"coordinates":[-111.819098,33.381059],"type":"Point"}
}