{
  "type": "Feature",
  "properties": {
    "iso:country":"US",
    "sg:address":"5925 W Olive Ave",
    "sg:city":"Glendale",
    "sg:classifiers":[
        {
            "category":"Professional",
            "type":"Services"
        }
    ],
    "sg:phone":"+1 623 937 0823",
    "sg:postcode":"85302",
    "sg:province":"AZ",
    "wof:name":"Shri Krishna Ent",
    "wof:placetype":"venue"
},
  "geometry": {"coordinates":[-112.188422,33.567409],"type":"Point"}
}