{
  "type": "Feature",
  "properties": {
    "iso:country":"US",
    "sg:address":"21075 Tara Springs Rd",
    "sg:city":"Black Canyon City",
    "sg:classifiers":[
        {
            "category":"Manufacturing",
            "subcategory":"Metals",
            "type":"Manufacturing & Wholesale Goods"
        }
    ],
    "sg:phone":"+1 623 979 7952",
    "sg:postcode":"85324",
    "sg:province":"AZ",
    "sg:tags":[
        "plate",
        "tank",
        "mfg"
    ],
    "wof:name":"Lee Tanks",
    "wof:placetype":"venue"
},
  "geometry": {"coordinates":[-112.10736199999999,34.086566],"type":"Point"}
}