{
  "type": "Feature",
  "properties": {
    "iso:country":"US",
    "sg:address":"540 N 2nd Ave",
    "sg:city":"Ajo",
    "sg:classifiers":[
        {
            "category":"Restaurant",
            "type":"Food & Drink"
        }
    ],
    "sg:phone":"+1 520 387 8861",
    "sg:postcode":"85321",
    "sg:province":"AZ",
    "wof:name":"Billy's Place",
    "wof:placetype":"venue"
},
  "geometry": {"coordinates":[-112.871893,32.374823],"type":"Point"}
}