{
  "type": "Feature",
  "properties": {
    "iso:country":"US",
    "sg:address":"175 Main St",
    "sg:city":"Fredonia",
    "sg:classifiers":[
        {
            "category":"Travel",
            "subcategory":"Hotels & Motels",
            "type":"Entertainment"
        }
    ],
    "sg:phone":"+1 928 643 7646",
    "sg:postcode":"86022",
    "sg:province":"AZ",
    "wof:name":"Grand Canyon Motel",
    "wof:placetype":"venue"
},
  "geometry": {"coordinates":[-112.75442,36.903085],"type":"Point"}
}