{
  "type": "Feature",
  "properties": {
    "iso:country":"US",
    "sg:address":"2102 W Encanto Blvd",
    "sg:city":"Phoenix",
    "sg:classifiers":[
        {
            "category":"Government",
            "subcategory":"Police Station",
            "type":"Public Place"
        },
        {
            "category":"Government",
            "subcategory":"Office",
            "type":"Public Place"
        }
    ],
    "sg:phone":"+1 602 223 2000",
    "sg:postcode":"85009",
    "sg:province":"AZ",
    "sg:tags":[
        "department",
        "government-state"
    ],
    "sg:website":"http://www.rmin.riss.net",
    "wof:name":"Highway Patrol",
    "wof:placetype":"venue"
},
  "geometry": {"coordinates":[-112.10437899999999,33.473221],"type":"Point"}
}