{
  "type": "Feature",
  "properties": {
    "addr:full":"2120 W Adobe Dr Phoenix AZ 85027",
    "addr:housenumber":"2120",
    "addr:postcode":"85027",
    "addr:street":"W Adobe Dr",
    "iso:country":"US",
    "sg:address":"2120 W Adobe Dr",
    "sg:city":"Phoenix",
    "sg:classifiers":[
        {
            "category":"Utilities",
            "subcategory":"Refuse",
            "type":"Services"
        },
        {
            "category":"Utilities",
            "type":"Services"
        }
    ],
    "sg:phone":"+1 623 869 6799",
    "sg:postcode":"85027",
    "sg:province":"AZ",
    "sg:tags":[
        "collection",
        "garbage"
    ],
    "wof:name":"Waste Management Inc",
    "wof:placetype":"venue"
},
  "geometry": {"coordinates":[-112.104736,33.687408],"type":"Point"}
}