{
  "type": "Feature",
  "properties": {
    "iso:country":"US",
    "sg:address":"4399 E Pima St",
    "sg:city":"Tucson",
    "sg:classifiers":[
        {
            "category":"Real Estate",
            "subcategory":"Real Estate Operator",
            "type":"Services"
        }
    ],
    "sg:phone":"+1 520 326 1133",
    "sg:postcode":"85712",
    "sg:province":"AZ",
    "sg:tags":[
        "apartment"
    ],
    "wof:name":"Berkeley Court LLC",
    "wof:placetype":"venue"
},
  "geometry": {"coordinates":[-110.900179,32.243421],"type":"Point"}
}