{
  "type": "Feature",
  "properties": {
    "iso:country":"US",
    "sg:address":"2701 N 16th St",
    "sg:city":"Phoenix",
    "sg:classifiers":[
        {
            "category":"Restaurant",
            "type":"Food & Drink"
        }
    ],
    "sg:phone":"+1 602 324 0701",
    "sg:postcode":"85006",
    "sg:province":"AZ",
    "sg:tags":[
        "eating"
    ],
    "wof:name":"State Rest Assn Northern",
    "wof:placetype":"venue"
},
  "geometry": {"coordinates":[-112.047643,33.478392],"type":"Point"}
}