{
  "type": "Feature",
  "properties": {
    "addr:full":"5009 S Priest Dr Tempe AZ 85282",
    "addr:housenumber":"5009",
    "addr:postcode":"85282",
    "addr:street":"S Priest Dr",
    "iso:country":"US",
    "sg:address":"5009 S Priest Dr",
    "sg:city":"Tempe",
    "sg:classifiers":[
        {
            "category":"Autos & Motor Vehicles",
            "subcategory":"Automobile Sales",
            "type":"Retail Goods"
        }
    ],
    "sg:phone":"+1 480 775 4520",
    "sg:postcode":"85282",
    "sg:province":"AZ",
    "sg:tags":[
        "car",
        "dealer"
    ],
    "wof:name":"ABC Nissan",
    "wof:placetype":"venue"
},
  "geometry": {"coordinates":[-111.96239,33.379644],"type":"Point"}
}