{
  "type": "Feature",
  "properties": {
    "iso:country":"US",
    "sg:address":"8844 N Sandy Ridge Pl",
    "sg:city":"Tucson",
    "sg:classifiers":[
        {
            "category":"Building & Trades",
            "subcategory":"Construction",
            "type":"Services"
        }
    ],
    "sg:phone":"+1 520 290 3766",
    "sg:postcode":"85742",
    "sg:province":"AZ",
    "sg:tags":[
        "wallcoverings-installation",
        "wallpaper",
        "painting",
        "contractor"
    ],
    "wof:name":"Avalon Custom Painting",
    "wof:placetype":"venue"
},
  "geometry": {"coordinates":[-111.024,32.366695],"type":"Point"}
}