{
  "type": "Feature",
  "properties": {
    "addr:full":"1116 S Dobson Rd Mesa AZ 85202",
    "addr:housenumber":"1116",
    "addr:postcode":"85202",
    "addr:street":"S Dobson Rd",
    "iso:country":"US",
    "sg:address":"1116 S Dobson Rd",
    "sg:city":"Mesa",
    "sg:classifiers":[
        {
            "category":"Wholesale",
            "subcategory":"Electrical",
            "type":"Manufacturing & Wholesale Goods"
        }
    ],
    "sg:phone":"+1 480 833 6002",
    "sg:postcode":"85202",
    "sg:province":"AZ",
    "sg:tags":[
        "communication",
        "electronic",
        "telephone"
    ],
    "wof:name":"Budget Marketing",
    "wof:placetype":"venue"
},
  "geometry": {"coordinates":[-111.87468,33.394434],"type":"Point"}
}