{
  "type": "Feature",
  "properties": {
    "iso:country":"US",
    "sg:address":"1072 N Swan Rd",
    "sg:city":"Tucson",
    "sg:classifiers":[
        {
            "category":"Professional",
            "type":"Services"
        }
    ],
    "sg:phone":"+1 520 326 8137",
    "sg:postcode":"85711",
    "sg:province":"AZ",
    "wof:name":"Simp L Care",
    "wof:placetype":"venue"
},
  "geometry": {"coordinates":[-110.89252399999999,32.236124],"type":"Point"}
}