{
  "type": "Feature",
  "properties": {
    "addr:full":"3416 Saddleback Dr Lake Havasu City AZ 86406",
    "addr:housenumber":"3416",
    "addr:postcode":"86406",
    "addr:street":"Saddleback Dr",
    "iso:country":"US",
    "sg:address":"3416 Saddleback Dr",
    "sg:city":"Lake Havasu City",
    "sg:classifiers":[
        {
            "category":"Professional",
            "subcategory":"Accounting & Tax Preparation",
            "type":"Services"
        }
    ],
    "sg:phone":"+1 928 854 3610",
    "sg:postcode":"86406",
    "sg:province":"AZ",
    "sg:tags":[
        "bookkeeping",
        "general"
    ],
    "wof:name":"Quail Bookkeeping Svc Inc",
    "wof:placetype":"venue"
},
  "geometry": {"coordinates":[-114.284504,34.486965],"type":"Point"}
}