{
  "type": "Feature",
  "properties": {
    "addr:full":"2530 E Villa Maria Dr Phoenix AZ 85032",
    "addr:housenumber":"2530",
    "addr:postcode":"85032",
    "addr:street":"E Villa Maria Dr",
    "iso:country":"US",
    "sg:address":"2530 E Villa Maria Dr",
    "sg:city":"Phoenix",
    "sg:classifiers":[
        {
            "category":"Home & Garden",
            "subcategory":"Garden Supply",
            "type":"Retail Goods"
        }
    ],
    "sg:phone":"+1 602 717 5730",
    "sg:postcode":"85032",
    "sg:province":"AZ",
    "sg:tags":[
        "mulch"
    ],
    "wof:name":"Bargain Barks",
    "wof:placetype":"venue"
},
  "geometry": {"coordinates":[-112.02770200000001,33.652191],"type":"Point"}
}