{
  "type": "Feature",
  "properties": {
    "addr:full":"4809 E Thistle Landing Dr #110 Phoenix AZ 85044",
    "addr:housenumber":"4809",
    "addr:postcode":"85044",
    "addr:street":"E Thistle Landing Dr # 110",
    "iso:country":"US",
    "sg:address":"4809 E Thistle Landing Dr #110",
    "sg:city":"Phoenix",
    "sg:classifiers":[
        {
            "category":"Health Services",
            "subcategory":"Doctor",
            "type":"Services"
        },
        {
            "category":"Social Services",
            "subcategory":"Job Training",
            "type":"Services"
        },
        {
            "category":"Social Services",
            "subcategory":"Retirement Home",
            "type":"Services"
        }
    ],
    "sg:phone":"+1 480 281 0781",
    "sg:postcode":"85044",
    "sg:province":"AZ",
    "sg:tags":[
        "living",
        "nursing",
        "homes-skilled",
        "facility",
        "assisted",
        "physician",
        "surgeon"
    ],
    "wof:name":"Healthways",
    "wof:placetype":"venue"
},
  "geometry": {"coordinates":[-111.980335,33.312561],"type":"Point"}
}