{
  "type": "Feature",
  "properties": {
    "iso:country":"US",
    "sg:address":"1430 E Missouri Ave",
    "sg:city":"Phoenix",
    "sg:classifiers":[
        {
            "category":"Professional",
            "subcategory":"Advertising",
            "type":"Services"
        }
    ],
    "sg:phone":"+1 602 532 2700",
    "sg:postcode":"85014",
    "sg:province":"AZ",
    "sg:tags":[
        "mailing",
        "list"
    ],
    "wof:name":"Supplemental Health Care",
    "wof:placetype":"venue"
},
  "geometry": {"coordinates":[-112.050026,33.516552],"type":"Point"}
}