{
  "type": "Feature",
  "properties": {
    "addr:full":"515 E Carefree Hwy Phoenix AZ 85085",
    "addr:housenumber":"515",
    "addr:postcode":"85085",
    "addr:street":"E Carefree Hwy",
    "iso:country":"US",
    "sg:address":"515 E Carefree Hwy",
    "sg:city":"Phoenix",
    "sg:classifiers":[
        {
            "category":"Professional",
            "subcategory":"Accounting & Tax Preparation",
            "type":"Services"
        },
        {
            "category":"Social Services",
            "subcategory":"Job Training",
            "type":"Services"
        }
    ],
    "sg:phone":"+1 623 561 2828",
    "sg:postcode":"85085",
    "sg:province":"AZ",
    "sg:tags":[
        "public",
        "accountants-certified",
        "incorporating"
    ],
    "sg:website":"http://phoenix.citysearch.com/profile/external/608540280/phoenix_az/creative_accounting.html?publisher=yellowpages&reference_id=1&placement=ypwebsitemip",
    "wof:name":"Creative Accounting",
    "wof:placetype":"venue"
},
  "geometry": {"coordinates":[-112.06735999999999,33.799019],"type":"Point"}
}