{
  "type": "Feature",
  "properties": {
    "iso:country":"US",
    "sg:address":"155 W Hampton Ave",
    "sg:city":"Mesa",
    "sg:classifiers":[
        {
            "category":"Recreation",
            "subcategory":"Amusement Park",
            "type":"Entertainment"
        },
        {
            "category":"Sports & Exercise",
            "subcategory":"Golf",
            "type":"Entertainment"
        }
    ],
    "sg:phone":"+1 480 834 8319",
    "sg:postcode":"85210",
    "sg:province":"AZ",
    "sg:tags":[
        "mini"
    ],
    "sg:website":"www.golfland.com",
    "wof:name":"Golfland Sunsplash",
    "wof:placetype":"venue"
},
  "geometry": {"coordinates":[-111.835874,33.387898],"type":"Point"}
}