{
  "type": "Feature",
  "properties": {
    "iso:country":"US",
    "sg:address":"18170 S Cam de Paez",
    "sg:city":"Green Valley",
    "sg:classifiers":[
        {
            "category":"Building & Trades",
            "subcategory":"Electrical",
            "type":"Services"
        }
    ],
    "sg:phone":"+1 520 661 7309",
    "sg:postcode":"85614",
    "sg:province":"AZ",
    "sg:tags":[
        "electrical",
        "contractor"
    ],
    "wof:name":"Oceanside Electric",
    "wof:placetype":"venue"
},
  "geometry": {"coordinates":[-110.975978,31.918508],"type":"Point"}
}