{
  "type": "Feature",
  "properties": {
    "addr:full":"11 Sundial Cir Carefree AZ 85377",
    "addr:housenumber":"11",
    "addr:postcode":"az 85377",
    "addr:street":"Sundial Cir",
    "iso:country":"US",
    "sg:address":"11 Sundial Cir",
    "sg:city":"Carefree",
    "sg:classifiers":[
        {
            "category":"Professional",
            "subcategory":"Employment Agencies",
            "type":"Services"
        }
    ],
    "sg:phone":"+1 480 575 5506",
    "sg:postcode":"85377",
    "sg:province":"AZ",
    "sg:website":"www.newmedsearch.com",
    "wof:name":"Newmed Search Solutions Inc",
    "wof:placetype":"venue"
},
  "geometry": {"coordinates":[-111.920238,33.823717],"type":"Point"}
}