{
  "type": "Feature",
  "properties": {
    "addr:full":"5 Commercial St St Johns AZ 85936",
    "addr:housenumber":"5",
    "addr:postcode":"85936",
    "addr:street":"Commercial St",
    "iso:country":"US",
    "sg:address":"5 Commercial St",
    "sg:city":"St Johns",
    "sg:classifiers":[
        {
            "category":"Banks & Credit Unions",
            "subcategory":"Investment Brokerage",
            "type":"Services"
        }
    ],
    "sg:phone":"+1 928 337 4544",
    "sg:postcode":"85936",
    "sg:province":"AZ",
    "wof:name":"Whiting Bros Invstmnt Co St",
    "wof:placetype":"venue"
},
  "geometry": {"coordinates":[-109.364401,34.506562],"type":"Point"}
}