{
  "type": "Feature",
  "properties": {
    "addr:full":"8912 E Pinnacle Peak Rd Scottsdale AZ 85255",
    "addr:housenumber":"8912",
    "addr:postcode":"85255",
    "addr:street":"E Pinnacle Peak Rd",
    "iso:country":"US",
    "sg:address":"8912 E Pinnacle Peak Rd",
    "sg:city":"Scottsdale",
    "sg:classifiers":[
        {
            "category":"Manufacturing",
            "subcategory":"Tools & Machinery",
            "type":"Manufacturing & Wholesale Goods"
        }
    ],
    "sg:phone":"+1 480 473 7773",
    "sg:postcode":"85255",
    "sg:province":"AZ",
    "sg:tags":[
        "water",
        "purification"
    ],
    "wof:name":"Aquaco",
    "wof:placetype":"venue"
},
  "geometry": {"coordinates":[-111.88935499999999,33.698696],"type":"Point"}
}