{
  "type": "Feature",
  "properties": {
    "iso:country":"US",
    "sg:address":"6650 N 47th Ave",
    "sg:city":"Glendale",
    "sg:classifiers":[
        {
            "category":"Building & Trades",
            "subcategory":"Plumbing",
            "type":"Services"
        }
    ],
    "sg:phone":"+1 623 939 2665",
    "sg:postcode":"85301",
    "sg:province":"AZ",
    "sg:tags":[
        "conditioning",
        "air",
        "system",
        "contractor"
    ],
    "wof:name":"Cool Man Air Conditioning",
    "wof:placetype":"venue"
},
  "geometry": {"coordinates":[-112.16010900000001,33.533046],"type":"Point"}
}