{
  "type": "Feature",
  "properties": {
    "iso:country":"US",
    "sg:address":"4236 Old US Hwy 80",
    "sg:city":"Yuma",
    "sg:classifiers":[
        {
            "category":"Retail",
            "subcategory":"Auto Repair",
            "type":"Services"
        }
    ],
    "sg:phone":"+1 928 726 3601",
    "sg:postcode":"85365",
    "sg:province":"AZ",
    "sg:tags":[
        "general"
    ],
    "wof:name":"Rv Master",
    "wof:placetype":"venue"
},
  "geometry": {"coordinates":[-114.560347,32.669912],"type":"Point"}
}