{
  "type": "Feature",
  "properties": {
    "addr:full":"4236 Old US Hwy 80 Yuma AZ 85365",
    "addr:housenumber":"4236",
    "addr:postcode":"85365",
    "addr:street":"Old Us Hwy 80",
    "iso:country":"US",
    "sg:address":"4236 Old US Hwy 80",
    "sg:city":"Yuma",
    "sg:classifiers":[
        {
            "category":"Retail",
            "subcategory":"Auto Repair",
            "type":"Services"
        }
    ],
    "sg:phone":"+1 928 726 3601",
    "sg:postcode":"85365",
    "sg:province":"AZ",
    "sg:tags":[
        "general"
    ],
    "wof:name":"Rv Master",
    "wof:placetype":"venue"
},
  "geometry": {"coordinates":[-114.56034699999999,32.669912],"type":"Point"}
}