{
  "type": "Feature",
  "properties": {
    "iso:country":"US",
    "sg:address":"3724 W Acapulco Ln",
    "sg:city":"Phoenix",
    "sg:classifiers":[
        {
            "category":"Shopping",
            "subcategory":"Gifts & Souvenirs",
            "type":"Retail Goods"
        }
    ],
    "sg:phone":"+1 602 973 8878",
    "sg:postcode":"85053",
    "sg:province":"AZ",
    "sg:tags":[
        "collectible"
    ],
    "wof:name":"Bears Around Us",
    "wof:placetype":"venue"
},
  "geometry": {"coordinates":[-112.139304,33.623642],"type":"Point"}
}