{
  "type": "Feature",
  "properties": {
    "iso:country":"US",
    "sg:address":"2800 E Chambers St # 600",
    "sg:city":"Phoenix",
    "sg:classifiers":[
        {
            "category":"Manufacturing",
            "subcategory":"Food",
            "type":"Manufacturing & Wholesale Goods"
        },
        {
            "category":"Health Services",
            "subcategory":"Health Practitioner",
            "type":"Services"
        },
        {
            "category":"Food & Beverages",
            "subcategory":"Specialty",
            "type":"Retail Goods"
        }
    ],
    "sg:phone":"+1 602 323 0477",
    "sg:postcode":"85040",
    "sg:province":"AZ",
    "sg:tags":[
        "product",
        "products-wholesale",
        "vitamin",
        "diet",
        "supplement",
        "nutritionist",
        "manufacturer"
    ],
    "wof:name":"Nutritional Beverages",
    "wof:placetype":"venue"
},
  "geometry": {"coordinates":[-112.0215,33.397591],"type":"Point"}
}