{
  "type": "Feature",
  "properties": {
    "iso:country":"US",
    "sg:address":"1334 S Country Club Dr",
    "sg:city":"Mesa",
    "sg:classifiers":[
        {
            "category":"Banks & Credit Unions",
            "subcategory":"Bank",
            "type":"Services"
        }
    ],
    "sg:phone":"+1 480 964 0133",
    "sg:postcode":"85210",
    "sg:province":"AZ",
    "sg:tags":[
        "cashing",
        "check"
    ],
    "wof:name":"Advance America",
    "wof:placetype":"venue"
},
  "geometry": {"coordinates":[-111.840138,33.392443],"type":"Point"}
}