{
  "type": "Feature",
  "properties": {
    "iso:country":"US",
    "sg:address":"8750 E Speedway Blvd",
    "sg:city":"Tucson",
    "sg:classifiers":[
        {
            "category":"Real Estate",
            "subcategory":"Real Estate Agent",
            "type":"Services"
        }
    ],
    "sg:phone":"+1 520 885 0125",
    "sg:postcode":"85710",
    "sg:province":"AZ",
    "wof:name":"Colonial Properties Trust",
    "wof:placetype":"venue"
},
  "geometry": {"coordinates":[-110.805087,32.235384],"type":"Point"}
}