{
  "type": "Feature",
  "properties": {
    "iso:country":"US",
    "sg:address":"7400 E Golf Links Rd",
    "sg:city":"Tucson",
    "sg:classifiers":[
        {
            "category":"Professional",
            "type":"Services"
        }
    ],
    "sg:phone":"+1 520 750 0140",
    "sg:postcode":"85730",
    "sg:province":"AZ",
    "wof:name":"Dixondezignz",
    "wof:placetype":"venue"
},
  "geometry": {"coordinates":[-110.836546,32.191947],"type":"Point"}
}