{
  "type": "Feature",
  "properties": {
    "addr:full":"410 E Florence Blvd Casa Grande AZ 85222",
    "addr:housenumber":"410",
    "addr:postcode":"85222",
    "addr:street":"E Florence Blvd",
    "iso:country":"US",
    "sg:address":"410 E Florence Blvd",
    "sg:city":"Casa Grande",
    "sg:classifiers":[
        {
            "category":"Utilities",
            "subcategory":"Electric",
            "type":"Services"
        }
    ],
    "sg:phone":"+1 520 876 4982",
    "sg:postcode":"85222",
    "sg:province":"AZ",
    "wof:name":"Santa Cruz Wtr & Pwr Dst Assn",
    "wof:placetype":"venue"
},
  "geometry": {"coordinates":[-111.74957000000001,32.879595],"type":"Point"}
}