{
  "type": "Feature",
  "properties": {
    "iso:country":"US",
    "sg:address":"924 E Gurley St",
    "sg:city":"Prescott",
    "sg:classifiers":[
        {
            "category":"Food & Beverages",
            "subcategory":"Groceries & Convenience Stores",
            "type":"Retail Goods"
        }
    ],
    "sg:phone":"+1 928 445 2410",
    "sg:postcode":"86301",
    "sg:province":"AZ",
    "sg:tags":[
        "grocer"
    ],
    "wof:name":"Mikes Mini Market",
    "wof:placetype":"venue"
},
  "geometry": {"coordinates":[-112.457625,34.54212],"type":"Point"}
}