{
  "type": "Feature",
  "properties": {
    "iso:country":"US",
    "sg:address":"3076 E. Chandler Heights Rd Suite #104",
    "sg:city":"Chandler",
    "sg:classifiers":[
        {
            "category":"Restaurant",
            "type":"Food & Drink"
        }
    ],
    "sg:phone":"+1 480 507 3885",
    "sg:postcode":"85249",
    "sg:province":"AZ",
    "sg:tags":[
        "chinese"
    ],
    "wof:name":"Hong Kong Kitchen II",
    "wof:placetype":"venue"
},
  "geometry": {"coordinates":[-111.830018,33.233247],"type":"Point"}
}