{
  "type": "Feature",
  "properties": {
    "iso:country":"US",
    "sg:address":"30005 W Yuma Rd",
    "sg:city":"Buckeye",
    "sg:classifiers":[
        {
            "category":"Farming",
            "subcategory":"Dairy Farm",
            "type":"Manufacturing & Wholesale Goods"
        }
    ],
    "sg:phone":"+1 623 386 5989",
    "sg:postcode":"85326",
    "sg:province":"AZ",
    "wof:name":"Arizona Machinery Co",
    "wof:placetype":"venue"
},
  "geometry": {"coordinates":[-112.697563,33.43509],"type":"Point"}
}