{
  "type": "Feature",
  "properties": {
    "addr:full":"721 W Geneva Dr Tempe AZ 85282",
    "addr:housenumber":"721",
    "addr:postcode":"85282",
    "addr:street":"W Geneva Dr",
    "iso:country":"US",
    "sg:address":"721 W Geneva Dr",
    "sg:city":"Tempe",
    "sg:classifiers":[
        {
            "category":"Building & Trades",
            "subcategory":"Construction",
            "type":"Services"
        }
    ],
    "sg:phone":"+1 480 892 0811",
    "sg:postcode":"85282",
    "sg:province":"AZ",
    "sg:tags":[
        "carpentry",
        "contractor"
    ],
    "wof:name":"B C W Inc",
    "wof:placetype":"venue"
},
  "geometry": {"coordinates":[-111.95173,33.394841],"type":"Point"}
}