{
  "type": "Feature",
  "properties": {
    "addr:full":"2640 E Rose Garden Ln Phoenix AZ 85050",
    "addr:housenumber":"2640",
    "addr:postcode":"85050",
    "addr:street":"E Rose Garden Ln",
    "iso:country":"US",
    "sg:address":"2640 E Rose Garden Ln",
    "sg:city":"Phoenix",
    "sg:classifiers":[
        {
            "category":"Wholesale",
            "subcategory":"Hardware",
            "type":"Manufacturing & Wholesale Goods"
        },
        {
            "category":"Home & Garden",
            "subcategory":"Garden Supply",
            "type":"Retail Goods"
        },
        {
            "category":"Retail",
            "subcategory":"Repair Shop",
            "type":"Services"
        }
    ],
    "sg:phone":"+1 602 923 4120",
    "sg:postcode":"85050",
    "sg:province":"AZ",
    "sg:tags":[
        "renting",
        "lawn",
        "outdoor",
        "power",
        "landscaping",
        "equipment-sales",
        "equipment",
        "saw"
    ],
    "sg:website":"http://www.stihlusa.com/",
    "wof:name":"A & G Turf Equipment",
    "wof:placetype":"venue"
},
  "geometry": {"coordinates":[-112.025785,33.676873],"type":"Point"}
}