{
  "type": "Feature",
  "properties": {
    "addr:full":"210 N 5th Ave Phoenix AZ 85003",
    "addr:housenumber":"210",
    "addr:postcode":"85003",
    "addr:street":"N 5Th Ave",
    "iso:country":"US",
    "sg:address":"210 N 5th Ave",
    "sg:city":"Phoenix",
    "sg:classifiers":[
        {
            "category":"Shopping",
            "type":"Retail Goods"
        }
    ],
    "sg:phone":"+1 520 385 4621",
    "sg:postcode":"85003",
    "sg:province":"AZ",
    "sg:tags":[
        "plastic"
    ],
    "wof:name":"Republic Plastics",
    "wof:placetype":"venue"
},
  "geometry": {"coordinates":[-112.08026599999999,33.451318],"type":"Point"}
}