{
  "type": "Feature",
  "properties": {
    "addr:full":"175 E Terminal Produce Dr Nogales AZ 85621",
    "addr:housenumber":"175",
    "addr:postcode":"85621",
    "addr:street":"E;Dr",
    "iso:country":"US",
    "sg:address":"175 E Terminal Produce Dr",
    "sg:city":"Nogales",
    "sg:classifiers":[
        {
            "category":"Retail",
            "subcategory":"Auto Repair",
            "type":"Services"
        }
    ],
    "sg:phone":"+1 520 377 9054",
    "sg:postcode":"85621",
    "sg:province":"AZ",
    "sg:tags":[
        "repairing",
        "automobile"
    ],
    "wof:name":"MATS",
    "wof:placetype":"venue"
},
  "geometry": {"coordinates":[-110.92791200000001,31.371043],"type":"Point"}
}