{
  "type": "Feature",
  "properties": {
    "iso:country":"US",
    "sg:address":"1366 E Thomas Rd",
    "sg:city":"Phoenix",
    "sg:classifiers":[
        {
            "category":"Social Services",
            "type":"Services"
        }
    ],
    "sg:phone":"+1 602 264 8878",
    "sg:postcode":"85014",
    "sg:province":"AZ",
    "sg:tags":[
        "organization",
        "welfare"
    ],
    "wof:name":"Retired Senior Volunteer Prgrm",
    "wof:placetype":"venue"
},
  "geometry": {"coordinates":[-112.051306,33.48029],"type":"Point"}
}