{
  "type": "Feature",
  "properties": {
    "addr:full":"449 S Country Club Dr Mesa AZ 85210",
    "addr:housenumber":"449",
    "addr:postcode":"85210",
    "addr:street":"S Country Club Dr",
    "iso:country":"US",
    "sg:address":"449 S Country Club Dr",
    "sg:city":"Mesa",
    "sg:classifiers":[
        {
            "category":"Professional",
            "type":"Services"
        }
    ],
    "sg:phone":"+1 480 962 0740",
    "sg:postcode":"85210",
    "sg:province":"AZ",
    "wof:name":"Payson Aviation Inc",
    "wof:placetype":"venue"
},
  "geometry": {"coordinates":[-111.84003800000001,33.406324],"type":"Point"}
}