{
  "type": "Feature",
  "properties": {
    "iso:country":"US",
    "sg:address":"820 W Warner Rd",
    "sg:city":"Chandler",
    "sg:classifiers":[
        {
            "category":"Manufacturing",
            "subcategory":"Tools & Machinery",
            "type":"Manufacturing & Wholesale Goods"
        }
    ],
    "sg:phone":"+1 480 497 8400",
    "sg:postcode":"85225",
    "sg:province":"AZ",
    "sg:tags":[
        "generation",
        "r",
        "d",
        "power"
    ],
    "wof:name":"Cube Technology  Inc",
    "wof:placetype":"venue"
},
  "geometry": {"coordinates":[-111.857893,33.335167],"type":"Point"}
}