{
  "type": "Feature",
  "properties": {
    "iso:country":"US",
    "sg:address":"1118 W Saint Marys Rd",
    "sg:city":"Tucson",
    "sg:classifiers":[
        {
            "category":"Restaurant",
            "type":"Food & Drink"
        }
    ],
    "sg:phone":"+1 520 624 3916",
    "sg:postcode":"85745",
    "sg:province":"AZ",
    "wof:name":"Laaerabula",
    "wof:placetype":"venue"
},
  "geometry": {"coordinates":[-110.991747,32.229509],"type":"Point"}
}