{
  "type": "Feature",
  "properties": {
    "addr:full":"4010 Grand Ave Phoenix AZ 85019",
    "addr:housenumber":"4010",
    "addr:postcode":"85019",
    "addr:street":"Grand Ave",
    "iso:country":"US",
    "sg:address":"4010 Grand Ave",
    "sg:city":"Phoenix",
    "sg:classifiers":[
        {
            "category":"Shopping",
            "subcategory":"Computers & Home Electronics",
            "type":"Retail Goods"
        }
    ],
    "sg:phone":"+1 602 242 0427",
    "sg:postcode":"85019",
    "sg:province":"AZ",
    "sg:tags":[
        "audio"
    ],
    "wof:name":"Mobile Acoustics",
    "wof:placetype":"venue"
},
  "geometry": {"coordinates":[-112.145073,33.503879],"type":"Point"}
}