{
  "type": "Feature",
  "properties": {
    "iso:country":"US",
    "sg:address":"105 N Links Dr",
    "sg:city":"Avondale",
    "sg:classifiers":[
        {
            "category":"Real Estate",
            "subcategory":"Real Estate Operator",
            "type":"Services"
        }
    ],
    "sg:phone":"+1 623 925 9506",
    "sg:postcode":"85323",
    "sg:province":"AZ",
    "sg:tags":[
        "apartment"
    ],
    "wof:name":"Club At Coldwater Springs the",
    "wof:placetype":"venue"
},
  "geometry": {"coordinates":[-112.31335,33.448483],"type":"Point"}
}