{
  "type": "Feature",
  "properties": {
    "addr:full":"10858 N 32nd St Phoenix AZ 85028",
    "addr:housenumber":"10858",
    "addr:postcode":"85028",
    "addr:street":"N 32Nd St",
    "iso:country":"US",
    "sg:address":"10858 N 32nd St",
    "sg:city":"Phoenix",
    "sg:classifiers":[
        {
            "category":"Building & Trades",
            "subcategory":"Construction",
            "type":"Services"
        }
    ],
    "sg:phone":"+1 602 787 9353",
    "sg:postcode":"85028",
    "sg:province":"AZ",
    "sg:tags":[
        "new",
        "builder",
        "home"
    ],
    "wof:name":"Cambridge Homes LLC",
    "wof:placetype":"venue"
},
  "geometry": {"coordinates":[-112.013183,33.582971],"type":"Point"}
}