{
  "type": "Feature",
  "properties": {
    "iso:country":"US",
    "sg:address":"519 N Leroux St",
    "sg:city":"Flagstaff",
    "sg:classifiers":[
        {
            "category":"Organizations",
            "subcategory":"Non-profit Organization",
            "type":"Services"
        }
    ],
    "sg:phone":"+1 928 556 0033",
    "sg:postcode":"86001",
    "sg:province":"AZ",
    "wof:name":"Arise Inc",
    "wof:placetype":"venue"
},
  "geometry": {"coordinates":[-111.646691,35.202939],"type":"Point"}
}