{
  "type": "Feature",
  "properties": {
    "iso:country":"US",
    "sg:address":"930 E University Dr",
    "sg:city":"Tempe",
    "sg:classifiers":[
        {
            "category":"Bars & Pubs",
            "type":"Food & Drink"
        }
    ],
    "sg:phone":"+1 480 921 9877",
    "sg:postcode":"85281",
    "sg:province":"AZ",
    "sg:tags":[
        "club",
        "comedy"
    ],
    "sg:website":"www.tempeimprov.com",
    "wof:name":"Tempe Improv",
    "wof:placetype":"venue"
},
  "geometry": {"coordinates":[-111.923687,33.422112],"type":"Point"}
}