{
  "type": "Feature",
  "properties": {
    "iso:country":"US",
    "sg:address":"4924 W Oraibi Dr",
    "sg:city":"Glendale",
    "sg:classifiers":[
        {
            "category":"Building & Trades",
            "subcategory":"Plumbing",
            "type":"Services"
        }
    ],
    "sg:phone":"+1 602 253 2600",
    "sg:postcode":"85308",
    "sg:province":"AZ",
    "sg:tags":[
        "plumbing",
        "contractor"
    ],
    "wof:name":"Moon Valley Plumbing & Rooter",
    "wof:placetype":"venue"
},
  "geometry": {"coordinates":[-112.166231,33.664384],"type":"Point"}
}