{
  "type": "Feature",
  "properties": {
    "iso:country":"US",
    "sg:address":"1030 N Stadem Dr",
    "sg:city":"Tempe",
    "sg:classifiers":[
        {
            "category":"Wholesale",
            "subcategory":"Medical Equipment & Supplies",
            "type":"Manufacturing & Wholesale Goods"
        },
        {
            "category":"Communications",
            "subcategory":"Film & Video Production",
            "type":"Services"
        }
    ],
    "sg:phone":"+1 480 966 1591",
    "sg:postcode":"85281",
    "sg:province":"AZ",
    "sg:tags":[
        "machine",
        "service-sound",
        "recording",
        "electrical",
        "discharge",
        "studio"
    ],
    "sg:website":"http://www.redmountainstudios.com",
    "wof:name":"Red Mountain Studios",
    "wof:placetype":"venue"
},
  "geometry": {"coordinates":[-111.913739,33.440647],"type":"Point"}
}