{
  "type": "Feature",
  "properties": {
    "iso:country":"US",
    "sg:address":"2932 E Broadway Blvd",
    "sg:city":"Tucson",
    "sg:classifiers":[
        {
            "category":"Shopping",
            "subcategory":"Clothing, Apparel, & Fashions",
            "type":"Retail Goods"
        }
    ],
    "sg:phone":"+1 520 320 5699",
    "sg:postcode":"85716",
    "sg:province":"AZ",
    "wof:name":"Picante Designs",
    "wof:placetype":"venue"
},
  "geometry": {"coordinates":[-110.928214,32.221446],"type":"Point"}
}