{
  "type": "Feature",
  "properties": {
    "addr:full":"900 W Chandler Blvd Ste B3 Chandler AZ 85225",
    "addr:housenumber":"900",
    "addr:postcode":"85225",
    "addr:street":"W Chandler Blvd Ste B3",
    "iso:country":"US",
    "sg:address":"900 W Chandler Blvd Ste B3",
    "sg:city":"Chandler",
    "sg:classifiers":[
        {
            "category":"Health Services",
            "subcategory":"Dentist",
            "type":"Services"
        }
    ],
    "sg:phone":"+1 480 821 1047",
    "sg:postcode":"85225",
    "sg:province":"AZ",
    "wof:name":"Brett Sperbeck, DDS",
    "wof:placetype":"venue"
},
  "geometry": {"coordinates":[-111.85711999999999,33.306502],"type":"Point"}
}