{
  "type": "Feature",
  "properties": {
    "iso:country":"US",
    "sg:address":"10401 W Coggins Dr",
    "sg:city":"Sun City",
    "sg:classifiers":[
        {
            "category":"Organizations",
            "subcategory":"Professional Association",
            "type":"Services"
        }
    ],
    "sg:phone":"+1 623 974 4718",
    "sg:postcode":"85351",
    "sg:province":"AZ",
    "wof:name":"Sun City Home Owners Assn Inc",
    "wof:placetype":"venue"
},
  "geometry": {"coordinates":[-112.28338,33.598984],"type":"Point"}
}