{
  "type": "Feature",
  "properties": {
    "addr:full":"1201 N Alvernon Way Tucson AZ 85712",
    "addr:housenumber":"1201",
    "addr:postcode":"85712",
    "addr:street":"N Alvernon Way",
    "iso:country":"US",
    "sg:address":"1201 N Alvernon Way",
    "sg:city":"Tucson",
    "sg:classifiers":[
        {
            "category":"Real Estate",
            "subcategory":"Real Estate Operator",
            "type":"Services"
        }
    ],
    "sg:phone":"+1 520 326 3039",
    "sg:postcode":"85712",
    "sg:province":"AZ",
    "sg:tags":[
        "apartment"
    ],
    "wof:name":"Desert Cove Apartments",
    "wof:placetype":"venue"
},
  "geometry": {"coordinates":[-110.909728,32.238898],"type":"Point"}
}