{
  "type": "Feature",
  "properties": {
    "addr:full":"1167 W Samalayuca Dr Tucson AZ 85704",
    "addr:housenumber":"1167",
    "addr:postcode":"85704",
    "addr:street":"W Samalayuca Dr",
    "iso:country":"US",
    "sg:address":"1167 W Samalayuca Dr",
    "sg:city":"Tucson",
    "sg:classifiers":[
        {
            "category":"Professional",
            "subcategory":"Management & Consulting",
            "type":"Services"
        }
    ],
    "sg:phone":"+1 520 797 4392",
    "sg:postcode":"85704",
    "sg:province":"AZ",
    "sg:tags":[
        "consultant",
        "energy",
        "conservation"
    ],
    "wof:name":"Schlegel & Assoc",
    "wof:placetype":"venue"
},
  "geometry": {"coordinates":[-110.99026499999999,32.349239],"type":"Point"}
}