{
  "type": "Feature",
  "properties": {
    "addr:full":"1070 Hwy 95 Bullhead City AZ 86429",
    "addr:housenumber":"1070",
    "addr:postcode":"86429",
    "addr:street":"Hwy 95",
    "iso:country":"US",
    "sg:address":"1070 Hwy 95",
    "sg:city":"Bullhead City",
    "sg:classifiers":[
        {
            "category":"Restaurant",
            "type":"Food & Drink"
        }
    ],
    "sg:phone":"+1 928 754 1244",
    "sg:postcode":"86429",
    "sg:province":"AZ",
    "sg:tags":[
        "eating"
    ],
    "wof:name":"Ranch Steakhouse & Barbecue",
    "wof:placetype":"venue"
},
  "geometry": {"coordinates":[-114.568111,35.14912],"type":"Point"}
}