{
  "type": "Feature",
  "properties": {
    "addr:full":"1159 S Marie Ct Gilbert AZ 85296",
    "addr:housenumber":"1159",
    "addr:postcode":"85296",
    "addr:street":"S Marie Ct",
    "iso:country":"US",
    "sg:address":"1159 S Marie Ct",
    "sg:city":"Gilbert",
    "sg:classifiers":[
        {
            "category":"Wholesale",
            "subcategory":"Machinery & Supplies",
            "type":"Manufacturing & Wholesale Goods"
        }
    ],
    "sg:phone":"+1 480 892 0798",
    "sg:postcode":"85296",
    "sg:province":"AZ",
    "sg:tags":[
        "salon",
        "beauty"
    ],
    "wof:name":"Maly's Education Arizona",
    "wof:placetype":"venue"
},
  "geometry": {"coordinates":[-111.730979,33.329467],"type":"Point"}
}