{
  "type": "Feature",
  "properties": {
    "iso:country":"US",
    "sg:address":"6022 N 57th Ave",
    "sg:city":"Glendale",
    "sg:classifiers":[
        {
            "category":"Wholesale",
            "subcategory":"Metals & Minerals",
            "type":"Manufacturing & Wholesale Goods"
        }
    ],
    "sg:phone":"+1 623 847 9585",
    "sg:postcode":"85301",
    "sg:province":"AZ",
    "sg:tags":[
        "center"
    ],
    "wof:name":"Gates By Ray Inc",
    "wof:placetype":"venue"
},
  "geometry": {"coordinates":[-112.181946,33.524369],"type":"Point"}
}