{
  "type": "Feature",
  "properties": {
    "iso:country":"US",
    "sg:address":"2899 Maricopa Ave",
    "sg:city":"Lake Havasu City",
    "sg:classifiers":[
        {
            "category":"Building & Trades",
            "subcategory":"Electrical",
            "type":"Services"
        }
    ],
    "sg:phone":"+1 928 855 0389",
    "sg:postcode":"86406",
    "sg:province":"AZ",
    "sg:tags":[
        "electrical",
        "contractor"
    ],
    "sg:website":"www.mcatlin.com",
    "wof:name":"Mc Atlin Electrical Corp",
    "wof:placetype":"venue"
},
  "geometry": {"coordinates":[-114.29038,34.456248],"type":"Point"}
}