{
  "type": "Feature",
  "properties": {
    "iso:country":"US",
    "sg:address":"1201 E Cooley St",
    "sg:city":"Show Low",
    "sg:classifiers":[
        {
            "category":"Professional",
            "type":"Services"
        }
    ],
    "sg:phone":"+1 928 537 3211",
    "sg:postcode":"85901",
    "sg:province":"AZ",
    "wof:name":"Body of Paradise LLC",
    "wof:placetype":"venue"
},
  "geometry": {"coordinates":[-110.029324,34.253027],"type":"Point"}
}