{
  "type": "Feature",
  "properties": {
    "iso:country":"US",
    "sg:address":"8655 E Via de Ventura de Ventura Ste G233",
    "sg:city":"Scottsdale",
    "sg:classifiers":[
        {
            "category":"Social Services",
            "type":"Services"
        },
        {
            "category":"Personal",
            "type":"Services"
        }
    ],
    "sg:phone":"+1 480 991 8904",
    "sg:postcode":"85258",
    "sg:province":"AZ",
    "sg:tags":[
        "family",
        "counselors-licensed",
        "individual",
        "marriage",
        "child",
        "professional",
        "counselor"
    ],
    "wof:name":"Bergman Marjorie H & Counseling Affiliates",
    "wof:placetype":"venue"
},
  "geometry": {"coordinates":[-111.895499,33.553745],"type":"Point"}
}