{
  "type": "Feature",
  "properties": {
    "addr:full":"4237 S 2nd Ave Tucson AZ 85714",
    "addr:housenumber":"4237",
    "addr:postcode":"85714",
    "addr:street":"S 2Nd Ave",
    "iso:country":"US",
    "sg:address":"4237 S 2nd Ave",
    "sg:city":"Tucson",
    "sg:classifiers":[
        {
            "category":"Manufacturing",
            "subcategory":"Tools & Machinery",
            "type":"Manufacturing & Wholesale Goods"
        }
    ],
    "sg:phone":"+1 520 741 0116",
    "sg:postcode":"85714",
    "sg:province":"AZ",
    "sg:tags":[
        "pattern",
        "foundry",
        "mfg"
    ],
    "wof:name":"Tucson Pattern Inc",
    "wof:placetype":"venue"
},
  "geometry": {"coordinates":[-110.96275300000001,32.173523],"type":"Point"}
}