{
  "type": "Feature",
  "properties": {
    "iso:country":"US",
    "sg:address":"4355 N Sanders Rd",
    "sg:city":"Tucson",
    "sg:classifiers":[
        {
            "category":"Building & Trades",
            "subcategory":"Construction",
            "type":"Services"
        }
    ],
    "sg:phone":"+1 520 682 8129",
    "sg:postcode":"85743",
    "sg:province":"AZ",
    "sg:tags":[
        "designer",
        "dealer",
        "pool",
        "swimming"
    ],
    "wof:name":"Bonnema Pools",
    "wof:placetype":"venue"
},
  "geometry": {"coordinates":[-111.235421,32.28779],"type":"Point"}
}