{
  "type": "Feature",
  "properties": {
    "iso:country":"US",
    "sg:address":"10135 N Citrus Rd",
    "sg:city":"Waddell",
    "sg:classifiers":[
        {
            "category":"Retail",
            "subcategory":"Animal Services",
            "type":"Services"
        }
    ],
    "sg:phone":"+1 623 935 4678",
    "sg:postcode":"85355",
    "sg:province":"AZ",
    "wof:name":"Liberty Kennels",
    "wof:placetype":"venue"
},
  "geometry": {"coordinates":[-112.44416,33.576932],"type":"Point"}
}