{
  "type": "Feature",
  "properties": {
    "iso:country":"US",
    "sg:address":"10751 S Cam Loma Alta",
    "sg:city":"Vail",
    "sg:classifiers":[
        {
            "category":"Shopping",
            "subcategory":"Computers & Home Electronics",
            "type":"Retail Goods"
        }
    ],
    "sg:phone":"+1 520 647 7199",
    "sg:postcode":"85641",
    "sg:province":"AZ",
    "sg:tags":[
        "parts",
        "supply"
    ],
    "wof:name":"Tucson Toner Systems Intl",
    "wof:placetype":"venue"
},
  "geometry": {"coordinates":[-110.689143,32.063207],"type":"Point"}
}