{
  "type": "Feature",
  "properties": {
    "addr:full":"5080 N 40th St Suite 245 Phoenix AZ 85018",
    "addr:housenumber":"5080",
    "addr:postcode":"85018",
    "addr:street":"N 40Th St Suite 245",
    "iso:country":"US",
    "sg:address":"5080 N 40th St Suite 245",
    "sg:city":"Phoenix",
    "sg:classifiers":[
        {
            "category":"Professional",
            "subcategory":"Management & Consulting",
            "type":"Services"
        }
    ],
    "sg:phone":"+1 602 840 0400",
    "sg:postcode":"85018",
    "sg:province":"AZ",
    "sg:tags":[
        "business-planning",
        "internet-strategy",
        "online-marketing",
        "digital-media",
        "business-incubation",
        "venture-management"
    ],
    "sg:website":"http://www.tallwave.com/",
    "wof:name":"Tallwave",
    "wof:placetype":"venue"
},
  "geometry": {"coordinates":[-111.995349,33.513312],"type":"Point"}
}