{
  "type": "Feature",
  "properties": {
    "addr:full":"10841 S 48th St Phoenix AZ 85044",
    "addr:housenumber":"10841",
    "addr:postcode":"85044",
    "addr:street":"S 48Th St",
    "iso:country":"US",
    "sg:address":"10841 S 48th St",
    "sg:city":"Phoenix",
    "sg:classifiers":[
        {
            "category":"Social Services",
            "subcategory":"Child Care",
            "type":"Services"
        }
    ],
    "sg:phone":"+1 480 598 5600",
    "sg:postcode":"85044",
    "sg:province":"AZ",
    "sg:tags":[
        "kindergarten",
        "preschool"
    ],
    "sg:website":"http://www.gracegardenchristianpreschool.com",
    "wof:name":"Grace Garden Christian Preschool",
    "wof:placetype":"venue"
},
  "geometry": {"coordinates":[-111.9804,33.347884],"type":"Point"}
}