{
  "type": "Feature",
  "properties": {
    "addr:full":"1817 W Baseline Rd Mesa AZ 85202",
    "addr:housenumber":"1817",
    "addr:postcode":"85202",
    "addr:street":"W Baseline Rd",
    "iso:country":"US",
    "sg:address":"1817 W Baseline Rd",
    "sg:city":"Mesa",
    "sg:classifiers":[
        {
            "category":"Food & Beverages",
            "subcategory":"Groceries & Convenience Stores",
            "type":"Retail Goods"
        }
    ],
    "sg:phone":"+1 480 491 2045",
    "sg:postcode":"85202",
    "sg:province":"AZ",
    "sg:website":"www.circlek.com",
    "wof:name":"Circle K Stores Inc",
    "wof:placetype":"venue"
},
  "geometry": {"coordinates":[-111.87358999999999,33.378391],"type":"Point"}
}