{
  "type": "Feature",
  "properties": {
    "iso:country":"US",
    "sg:address":"4550 E Cactus Rd Ste 176",
    "sg:city":"Phoenix",
    "sg:classifiers":[
        {
            "category":"Food & Beverages",
            "subcategory":"Supermarket",
            "type":"Retail Goods"
        }
    ],
    "sg:phone":"+1 602 996 6808",
    "sg:postcode":"85032",
    "sg:province":"AZ",
    "sg:tags":[
        "super",
        "store"
    ],
    "sg:website":"http://www.littmanjewelers.com",
    "wof:name":"Fred Meyer Jewelers 00598",
    "wof:placetype":"venue"
},
  "geometry": {"coordinates":[-111.983978,33.599819],"type":"Point"}
}