{
  "type": "Feature",
  "properties": {
    "iso:country":"US",
    "sg:address":"7531 E Pima St",
    "sg:city":"Tucson",
    "sg:classifiers":[
        {
            "category":"Professional",
            "subcategory":"Engineering",
            "type":"Services"
        }
    ],
    "sg:phone":"+1 520 312 7439",
    "sg:postcode":"85715",
    "sg:province":"AZ",
    "sg:tags":[
        "consulting",
        "engineer"
    ],
    "wof:name":"Cdk Engineering",
    "wof:placetype":"venue"
},
  "geometry": {"coordinates":[-110.83152699999999,32.24287],"type":"Point"}
}