{
  "type": "Feature",
  "properties": {
    "iso:country":"US",
    "sg:address":"2 W Alameda Dr",
    "sg:city":"Tempe",
    "sg:classifiers":[
        {
            "category":"Real Estate",
            "subcategory":"Architect",
            "type":"Services"
        }
    ],
    "sg:phone":"+1 480 968 3023",
    "sg:postcode":"85282",
    "sg:province":"AZ",
    "wof:name":"Abell & Assoc Architects",
    "wof:placetype":"venue"
},
  "geometry": {"coordinates":[-111.94076,33.400093],"type":"Point"}
}