{
  "type": "Feature",
  "properties": {
    "iso:country":"US",
    "sg:address":"2000 Airport Rd",
    "sg:city":"Williams",
    "sg:classifiers":[
        {
            "category":"Retail",
            "subcategory":"Repair Shop",
            "type":"Services"
        }
    ],
    "sg:phone":"+1 928 635 9571",
    "sg:postcode":"86046",
    "sg:province":"AZ",
    "sg:tags":[
        "taxidermist"
    ],
    "wof:name":"Mountain View Taxidermy",
    "wof:placetype":"venue"
},
  "geometry": {"coordinates":[-112.186974,35.275933],"type":"Point"}
}