{
  "type": "Feature",
  "properties": {
    "iso:country":"US",
    "sg:address":"2757 E Main St",
    "sg:city":"Mesa",
    "sg:classifiers":[
        {
            "category":"Restaurant",
            "type":"Food & Drink"
        }
    ],
    "sg:phone":"+1 480 833 8602",
    "sg:postcode":"85213",
    "sg:province":"AZ",
    "sg:tags":[
        "chicken",
        "fast"
    ],
    "sg:website":"www.kfc.com",
    "wof:name":"KFC",
    "wof:placetype":"venue"
},
  "geometry": {"coordinates":[-111.77290600000001,33.415369],"type":"Point"}
}