{
  "type": "Feature",
  "properties": {
    "iso:country":"US",
    "sg:address":"2809 E Thomas Rd",
    "sg:city":"Phoenix",
    "sg:classifiers":[
        {
            "category":"Shopping",
            "subcategory":"Computers & Home Electronics",
            "type":"Retail Goods"
        }
    ],
    "sg:phone":"+1 602 957 3397",
    "sg:postcode":"85016",
    "sg:province":"AZ",
    "sg:tags":[
        "stereo",
        "auto",
        "high",
        "stereophonic",
        "install",
        "equipment-dealers",
        "fidelity"
    ],
    "sg:website":"http://www.sunvalleystereo.com",
    "wof:name":"Sun Valley Stereo",
    "wof:placetype":"venue"
},
  "geometry": {"coordinates":[-112.02132,33.480404],"type":"Point"}
}