{
  "type": "Feature",
  "properties": {
    "iso:country":"US",
    "sg:address":"4240 E Runaway Bay Dr",
    "sg:city":"Chandler",
    "sg:classifiers":[
        {
            "category":"Home & Garden",
            "subcategory":"Garden Supply",
            "type":"Retail Goods"
        }
    ],
    "sg:phone":"+1 480 883 1691",
    "sg:postcode":"85249",
    "sg:province":"AZ",
    "sg:tags":[
        "sprinkler"
    ],
    "wof:name":"Extreme Landscape Contractors",
    "wof:placetype":"venue"
},
  "geometry": {"coordinates":[-111.76787400000001,33.213795],"type":"Point"}
}