{
  "type": "Feature",
  "properties": {
    "iso:country":"US",
    "sg:address":"5111 E Windrose Dr",
    "sg:city":"Scottsdale",
    "sg:classifiers":[
        {
            "category":"Building & Trades",
            "subcategory":"Construction",
            "type":"Services"
        }
    ],
    "sg:phone":"+1 602 579 1833",
    "sg:postcode":"85254",
    "sg:province":"AZ",
    "sg:tags":[
        "carpentry",
        "contractor"
    ],
    "wof:name":"Custom Concepts Cabinetry",
    "wof:placetype":"venue"
},
  "geometry": {"coordinates":[-111.97206,33.602678],"type":"Point"}
}