{
  "type": "Feature",
  "properties": {
    "iso:country":"US",
    "sg:address":"5509 W John Cabot Rd",
    "sg:city":"Glendale",
    "sg:classifiers":[
        {
            "category":"Building & Trades",
            "subcategory":"Construction",
            "type":"Services"
        }
    ],
    "sg:phone":"+1 602 439 9553",
    "sg:postcode":"85308",
    "sg:province":"AZ",
    "sg:tags":[
        "hanging",
        "contractor"
    ],
    "wof:name":"Harmon Painting",
    "wof:placetype":"venue"
},
  "geometry": {"coordinates":[-112.17865,33.649932],"type":"Point"}
}