{
  "type": "Feature",
  "properties": {
    "addr:full":"3755 N Elliott Rd Ajo AZ 85321",
    "addr:housenumber":"3755",
    "addr:postcode":"85321",
    "addr:street":"N Elliott Rd",
    "iso:country":"US",
    "sg:address":"3755 N Elliott Rd",
    "sg:city":"Ajo",
    "sg:classifiers":[
        {
            "category":"Retail",
            "subcategory":"Auto Repair",
            "type":"Services"
        }
    ],
    "sg:phone":"+1 520 387 7890",
    "sg:postcode":"85321",
    "sg:province":"AZ",
    "sg:tags":[
        "automotive",
        "used",
        "general"
    ],
    "wof:name":"Ajo Auto Wrecking & Towing",
    "wof:placetype":"venue"
},
  "geometry": {"coordinates":[-112.875896,32.425169],"type":"Point"}
}