{
  "type": "Feature",
  "properties": {
    "iso:country":"US",
    "sg:address":"2024 E University Dr",
    "sg:city":"Mesa",
    "sg:classifiers":[
        {
            "category":"Organizations",
            "subcategory":"Religious Organization",
            "type":"Services"
        }
    ],
    "sg:phone":"+1 480 964 8747",
    "sg:postcode":"85213",
    "sg:province":"AZ",
    "sg:tags":[
        "church"
    ],
    "sg:website":"www.graceumcmesa.org",
    "wof:name":"Grace United Methodist Church",
    "wof:placetype":"venue"
},
  "geometry": {"coordinates":[-111.78655999999999,33.422724],"type":"Point"}
}