{
  "type": "Feature",
  "properties": {
    "iso:country":"US",
    "sg:address":"1910 E Winter Dr",
    "sg:city":"Phoenix",
    "sg:classifiers":[
        {
            "category":"Communications",
            "subcategory":"Film & Video Production",
            "type":"Services"
        }
    ],
    "sg:phone":"+1 602 395 0504",
    "sg:postcode":"85020",
    "sg:province":"AZ",
    "sg:tags":[
        "taping"
    ],
    "wof:name":"Legacy Art's Video Inc",
    "wof:placetype":"venue"
},
  "geometry": {"coordinates":[-112.04012299999999,33.552134],"type":"Point"}
}