{
  "type": "Feature",
  "properties": {
    "addr:full":"10355 N la Canada Dr Ste 197 Tucson AZ 85737",
    "addr:housenumber":"10355",
    "addr:postcode":"85737",
    "addr:street":"N La Canada Dr Ste 197",
    "iso:country":"US",
    "sg:address":"10355 N la Canada Dr Ste 197",
    "sg:city":"Tucson",
    "sg:classifiers":[
        {
            "category":"Insurance",
            "subcategory":"Insurance Agent",
            "type":"Services"
        },
        {
            "category":"Insurance",
            "subcategory":"Hazard Insurance",
            "type":"Services"
        },
        {
            "category":"Insurance",
            "subcategory":"Title Insurance",
            "type":"Services"
        }
    ],
    "sg:phone":"+1 520 885 3083",
    "sg:postcode":"85737",
    "sg:province":"AZ",
    "sg:tags":[
        "auto",
        "renter",
        "homeowner"
    ],
    "sg:website":"http://www.fbfs.com/content/insurance/farm-bureau-members-choice/default.aspx?utm_source=dcdirectory&utm_medium=dcpdonline&utm_content=home-rent&utm_campaign=YP",
    "wof:name":"Farm Bureau Financial Services",
    "wof:placetype":"venue"
},
  "geometry": {"coordinates":[-110.99583699999999,32.394141],"type":"Point"}
}