{
  "type": "Feature",
  "properties": {
    "iso:country":"US",
    "sg:address":"1514 E Van Buren St",
    "sg:city":"Phoenix",
    "sg:classifiers":[
        {
            "category":"Shopping",
            "subcategory":"Department Store",
            "type":"Retail Goods"
        }
    ],
    "sg:phone":"+1 602 462 5503",
    "sg:postcode":"85006",
    "sg:province":"AZ",
    "wof:name":"Dollar Days Store 4",
    "wof:placetype":"venue"
},
  "geometry": {"coordinates":[-112.04785099999999,33.451499],"type":"Point"}
}