{
  "type": "Feature",
  "properties": {
    "addr:full":"9328 E Barbara Jean Pl Tucson AZ 85710",
    "addr:housenumber":"9328",
    "addr:postcode":"85710",
    "addr:street":"E Barbara Jean Pl",
    "iso:country":"US",
    "sg:address":"9328 E Barbara Jean Pl",
    "sg:city":"Tucson",
    "sg:classifiers":[
        {
            "category":"Building & Trades",
            "subcategory":"Electrical",
            "type":"Services"
        }
    ],
    "sg:phone":"+1 520 722 6826",
    "sg:postcode":"85710",
    "sg:province":"AZ",
    "sg:tags":[
        "electrical",
        "contractor"
    ],
    "wof:name":"Aura Electric Co",
    "wof:placetype":"venue"
},
  "geometry": {"coordinates":[-110.792678,32.19575],"type":"Point"}
}