{
  "type": "Feature",
  "properties": {
    "iso:country":"US",
    "sg:address":"2128 Colorado Blvd",
    "sg:city":"Bullhead City",
    "sg:classifiers":[
        {
            "category":"Food & Beverages",
            "subcategory":"Groceries & Convenience Stores",
            "type":"Retail Goods"
        }
    ],
    "sg:phone":"+1 928 704 0145",
    "sg:postcode":"86442",
    "sg:province":"AZ",
    "sg:tags":[
        "eating"
    ],
    "wof:name":"Sub Shack",
    "wof:placetype":"venue"
},
  "geometry": {"coordinates":[-114.636513,35.096658],"type":"Point"}
}