{
  "type": "Feature",
  "properties": {
    "iso:country":"US",
    "sg:address":"16000 N 77th Ave",
    "sg:city":"Peoria",
    "sg:classifiers":[
        {
            "category":"Building & Trades",
            "subcategory":"Landscaping Services",
            "type":"Services"
        }
    ],
    "sg:phone":"+1 623 979 7484",
    "sg:postcode":"85382",
    "sg:province":"AZ",
    "wof:name":"Arizona Professional Lawn Care",
    "wof:placetype":"venue"
},
  "geometry": {"coordinates":[-112.22422299999999,33.631385],"type":"Point"}
}