{
  "type": "Feature",
  "properties": {
    "iso:country":"US",
    "sg:address":"9414 E San Salvador Dr",
    "sg:city":"Scottsdale",
    "sg:classifiers":[
        {
            "category":"Shopping",
            "type":"Retail Goods"
        }
    ],
    "sg:phone":"+1 480 661 8940",
    "sg:postcode":"85258",
    "sg:province":"AZ",
    "sg:tags":[
        "merchandise"
    ],
    "wof:name":"Hayward Industries Inc",
    "wof:placetype":"venue"
},
  "geometry": {"coordinates":[-111.877607,33.570627],"type":"Point"}
}