{
  "type": "Feature",
  "properties": {
    "addr:full":"1201 N Oxbow Dr Dewey AZ 86327",
    "addr:housenumber":"1201",
    "addr:postcode":"86327",
    "addr:street":"N Oxbow Dr",
    "iso:country":"US",
    "sg:address":"1201 N Oxbow Dr",
    "sg:city":"Dewey",
    "sg:classifiers":[
        {
            "category":"Building & Trades",
            "subcategory":"Equipment Rental",
            "type":"Services"
        }
    ],
    "sg:phone":"+1 928 772 1149",
    "sg:postcode":"86327",
    "sg:province":"AZ",
    "sg:tags":[
        "audio",
        "leasing"
    ],
    "wof:name":"Huntington Equipment Leasing",
    "wof:placetype":"venue"
},
  "geometry": {"coordinates":[-112.280804,34.561462],"type":"Point"}
}