{
  "type": "Feature",
  "properties": {
    "addr:full":"2810 S 24th St Phoenix AZ 85034",
    "addr:housenumber":"2810",
    "addr:postcode":"85034",
    "addr:street":"S 24Th St",
    "iso:country":"US",
    "sg:address":"2810 S 24th St",
    "sg:city":"Phoenix",
    "sg:classifiers":[
        {
            "category":"Freight",
            "type":"Transportation"
        }
    ],
    "sg:phone":"+1 602 267 0294",
    "sg:postcode":"85034",
    "sg:province":"AZ",
    "sg:tags":[
        "delivery"
    ],
    "wof:name":"Complete Sky Cap Svc Inc",
    "wof:placetype":"venue"
},
  "geometry": {"coordinates":[-112.030439,33.421725],"type":"Point"}
}