{
  "type": "Feature",
  "properties": {
    "iso:country":"US",
    "sg:address":"4122 W Paradise Ln",
    "sg:city":"Phoenix",
    "sg:classifiers":[
        {
            "category":"Building & Trades",
            "subcategory":"Construction",
            "type":"Services"
        }
    ],
    "sg:phone":"+1 602 439 3147",
    "sg:postcode":"85053",
    "sg:province":"AZ",
    "sg:tags":[
        "house"
    ],
    "wof:name":"Emchs",
    "wof:placetype":"venue"
},
  "geometry": {"coordinates":[-112.15104,33.632329],"type":"Point"}
}