{
  "type": "Feature",
  "properties": {
    "addr:full":"331 W Pastime Rd Tucson AZ 85705",
    "addr:housenumber":"331",
    "addr:postcode":"85705",
    "addr:street":"W Pastime Rd",
    "iso:country":"US",
    "sg:address":"331 W Pastime Rd",
    "sg:city":"Tucson",
    "sg:classifiers":[
        {
            "category":"Real Estate",
            "subcategory":"Real Estate Operator",
            "type":"Services"
        }
    ],
    "sg:phone":"+1 520 888 8587",
    "sg:postcode":"85705",
    "sg:province":"AZ",
    "sg:tags":[
        "building",
        "apartment"
    ],
    "wof:name":"Villa Siena",
    "wof:placetype":"venue"
},
  "geometry": {"coordinates":[-110.977553,32.275501],"type":"Point"}
}