{
  "type": "Feature",
  "properties": {
    "iso:country":"US",
    "sg:address":"1700 E Union Hills Dr",
    "sg:city":"Phoenix",
    "sg:classifiers":[
        {
            "category":"Education",
            "subcategory":"School",
            "type":"Public Place"
        }
    ],
    "sg:phone":"+1 623 780 4200",
    "sg:postcode":"85024",
    "sg:province":"AZ",
    "wof:name":"North Canyon High School",
    "wof:placetype":"venue"
},
  "geometry": {"coordinates":[-112.044405,33.655037],"type":"Point"}
}