{
  "type": "Feature",
  "properties": {
    "iso:country":"US",
    "sg:address":"9215 State Hwy 92",
    "sg:city":"Hereford",
    "sg:classifiers":[
        {
            "category":"Food & Beverages",
            "subcategory":"Groceries & Convenience Stores",
            "type":"Retail Goods"
        }
    ],
    "sg:phone":"+1 520 366 5877",
    "sg:postcode":"85615",
    "sg:province":"AZ",
    "wof:name":"Palominas Country Store",
    "wof:placetype":"venue"
},
  "geometry": {"coordinates":[-110.152058,31.37984],"type":"Point"}
}