{
  "type": "Feature",
  "properties": {
    "addr:full":"3525 W Ocotillo Rd Phoenix AZ 85019",
    "addr:housenumber":"3525",
    "addr:postcode":"85019",
    "addr:street":"W Ocotillo Rd",
    "iso:country":"US",
    "sg:address":"3525 W Ocotillo Rd",
    "sg:city":"Phoenix",
    "sg:classifiers":[
        {
            "category":"Building & Trades",
            "subcategory":"Landscaping Services",
            "type":"Services"
        }
    ],
    "sg:phone":"+1 602 973 9096",
    "sg:postcode":"85019",
    "sg:province":"AZ",
    "sg:tags":[
        "landscape",
        "contractor"
    ],
    "wof:name":"Monarch Landscape & Design Inc",
    "wof:placetype":"venue"
},
  "geometry": {"coordinates":[-112.138229,33.534745],"type":"Point"}
}