{
  "type": "Feature",
  "properties": {
    "addr:full":"1722 E Tamar Rd Phoenix AZ 85086",
    "addr:housenumber":"1722",
    "addr:postcode":"85086",
    "addr:street":"E Tamar Rd",
    "iso:country":"US",
    "sg:address":"1722 E Tamar Rd",
    "sg:city":"Phoenix",
    "sg:classifiers":[
        {
            "category":"Social Services",
            "subcategory":"Adult Care",
            "type":"Services"
        }
    ],
    "sg:phone":"+1 623 465 2998",
    "sg:postcode":"85086",
    "sg:province":"AZ",
    "sg:tags":[
        "home",
        "residential"
    ],
    "wof:name":"Highland Hills By Sheppard",
    "wof:placetype":"venue"
},
  "geometry": {"coordinates":[-112.04718200000001,33.831853],"type":"Point"}
}