{
  "type": "Feature",
  "properties": {
    "iso:country":"US",
    "sg:address":"6271 E Calle Silvosa",
    "sg:city":"Tucson",
    "sg:classifiers":[
        {
            "category":"Manufacturing",
            "subcategory":"Chemicals & Compounds",
            "type":"Manufacturing & Wholesale Goods"
        }
    ],
    "sg:phone":"+1 520 750 8118",
    "sg:postcode":"85711",
    "sg:province":"AZ",
    "sg:tags":[
        "chemicals-wholesale",
        "manufacturer"
    ],
    "wof:name":"Bite Size Bakery",
    "wof:placetype":"venue"
},
  "geometry": {"coordinates":[-110.858785,32.194824],"type":"Point"}
}