{
  "type": "Feature",
  "properties": {
    "iso:country":"US",
    "sg:address":"15440 N 7th St",
    "sg:city":"Phoenix",
    "sg:classifiers":[
        {
            "category":"Sports & Exercise",
            "subcategory":"Gym",
            "type":"Entertainment"
        }
    ],
    "sg:phone":"+1 602 843 7872",
    "sg:postcode":"85022",
    "sg:province":"AZ",
    "sg:tags":[
        "instruction",
        "yoga"
    ],
    "sg:website":"http://www.yogapura.com",
    "wof:name":"Yoga Pura",
    "wof:placetype":"venue"
},
  "geometry": {"coordinates":[-112.065483,33.626906],"type":"Point"}
}