{
  "type": "Feature",
  "properties": {
    "iso:country":"US",
    "sg:address":"1738 W Montebello Ave",
    "sg:city":"Phoenix",
    "sg:classifiers":[
        {
            "category":"Shopping",
            "subcategory":"Jewelry",
            "type":"Retail Goods"
        }
    ],
    "sg:phone":"+1 602 249 0257",
    "sg:postcode":"85015",
    "sg:province":"AZ",
    "wof:name":"Vitas Jewellers",
    "wof:placetype":"venue"
},
  "geometry": {"coordinates":[-112.099272,33.519976],"type":"Point"}
}