{
  "type": "Feature",
  "properties": {
    "iso:country":"US",
    "sg:address":"9239 E Wrightstown Rd",
    "sg:city":"Tucson",
    "sg:classifiers":[
        {
            "category":"Education",
            "subcategory":"School",
            "type":"Public Place"
        }
    ],
    "sg:phone":"+1 520 296 0883",
    "sg:postcode":"85715",
    "sg:province":"AZ",
    "sg:website":"www.tcdcharterschool.com",
    "wof:name":"Camp Adventure",
    "wof:placetype":"venue"
},
  "geometry": {"coordinates":[-110.797405,32.242755],"type":"Point"}
}