{
  "type": "Feature",
  "properties": {
    "iso:country":"US",
    "sg:address":"6025 N 16th St",
    "sg:city":"Phoenix",
    "sg:classifiers":[
        {
            "category":"Food & Beverages",
            "subcategory":"Groceries & Convenience Stores",
            "type":"Retail Goods"
        }
    ],
    "sg:phone":"+1 602 265 4315",
    "sg:postcode":"85016",
    "sg:province":"AZ",
    "wof:name":"Convenience Station One",
    "wof:placetype":"venue"
},
  "geometry": {"coordinates":[-112.047402,33.525058],"type":"Point"}
}