{
  "type": "Feature",
  "properties": {
    "iso:country":"US",
    "sg:address":"2005 W Mesquite St",
    "sg:city":"Chandler",
    "sg:classifiers":[
        {
            "category":"Real Estate",
            "subcategory":"Real Estate Agent",
            "type":"Services"
        }
    ],
    "sg:phone":"+1 480 786 3874",
    "sg:postcode":"85224",
    "sg:province":"AZ",
    "sg:website":"http://www.goldbahr.com",
    "wof:name":"Steven & Julie Bahr",
    "wof:placetype":"venue"
},
  "geometry": {"coordinates":[-111.876527,33.342304],"type":"Point"}
}