{
  "type": "Feature",
  "properties": {
    "iso:country":"US",
    "sg:address":"840 W University Dr",
    "sg:city":"Mesa",
    "sg:classifiers":[
        {
            "category":"Professional",
            "subcategory":"Lawyer & Legal Services",
            "type":"Services"
        }
    ],
    "sg:phone":"+1 602 644 1144",
    "sg:postcode":"85201",
    "sg:province":"AZ",
    "sg:tags":[
        "attorney"
    ],
    "wof:name":"Robert J Watson PC",
    "wof:placetype":"venue"
},
  "geometry": {"coordinates":[-111.84923,33.422339],"type":"Point"}
}