{
  "type": "Feature",
  "properties": {
    "iso:country":"US",
    "sg:address":"820 W Warner Rd",
    "sg:city":"Chandler",
    "sg:classifiers":[
        {
            "category":"Real Estate",
            "subcategory":"Real Estate Agent",
            "type":"Services"
        }
    ],
    "sg:phone":"+1 480 831 9222",
    "sg:postcode":"85225",
    "sg:province":"AZ",
    "sg:website":"www.hearthsiderealty.net",
    "wof:name":"Hearthside Realty LTD",
    "wof:placetype":"venue"
},
  "geometry": {"coordinates":[-111.857893,33.335167],"type":"Point"}
}