{
  "type": "Feature",
  "properties": {
    "iso:country":"US",
    "sg:address":"7260 E Lincoln Dr",
    "sg:city":"Scottsdale",
    "sg:classifiers":[
        {
            "category":"Real Estate",
            "subcategory":"Real Estate Operator",
            "type":"Services"
        }
    ],
    "sg:phone":"+1 480 991 4843",
    "sg:postcode":"85250",
    "sg:province":"AZ",
    "sg:tags":[
        "condominium"
    ],
    "wof:name":"Casabella Residential Comm",
    "wof:placetype":"venue"
},
  "geometry": {"coordinates":[-111.923649,33.531489],"type":"Point"}
}