{
  "type": "Feature",
  "properties": {
    "iso:country":"US",
    "sg:address":"6738 W Kerry Ln",
    "sg:city":"Glendale",
    "sg:classifiers":[
        {
            "category":"Health Services",
            "subcategory":"Doctor",
            "type":"Services"
        }
    ],
    "sg:phone":"+1 623 974 4888",
    "sg:postcode":"85308",
    "sg:province":"AZ",
    "sg:tags":[
        "dentist"
    ],
    "wof:name":"Calvin C Chen DDS",
    "wof:placetype":"venue"
},
  "geometry": {"coordinates":[-112.203997,33.658632],"type":"Point"}
}