{
  "type": "Feature",
  "properties": {
    "iso:country":"US",
    "sg:address":"3232 E Corona Ave",
    "sg:city":"Phoenix",
    "sg:classifiers":[
        {
            "category":"Professional",
            "subcategory":"Advertising",
            "type":"Services"
        }
    ],
    "sg:phone":"+1 602 305 7500",
    "sg:postcode":"85040",
    "sg:province":"AZ",
    "wof:name":"OVERHEADRACKS.COM",
    "wof:placetype":"venue"
},
  "geometry": {"coordinates":[-112.011234,33.40557],"type":"Point"}
}