{
  "type": "Feature",
  "properties": {
    "addr:full":"5802 N 37th Dr Phoenix AZ 85019",
    "addr:housenumber":"5802",
    "addr:postcode":"85019",
    "addr:street":"N 37Th Dr",
    "iso:country":"US",
    "sg:address":"5802 N 37th Dr",
    "sg:city":"Phoenix",
    "sg:classifiers":[
        {
            "category":"Freight",
            "type":"Transportation"
        }
    ],
    "sg:phone":"+1 602 269 8300",
    "sg:postcode":"85019",
    "sg:province":"AZ",
    "sg:tags":[
        "operator",
        "local",
        "trucking"
    ],
    "wof:name":"Discount Moving",
    "wof:placetype":"venue"
},
  "geometry": {"coordinates":[-112.139499,33.521507],"type":"Point"}
}