{
  "type": "Feature",
  "properties": {
    "iso:country":"US",
    "sg:address":"1720 Kaibab Loop",
    "sg:city":"Prescott",
    "sg:classifiers":[
        {
            "category":"Building & Trades",
            "subcategory":"Landscaping Services",
            "type":"Services"
        }
    ],
    "sg:phone":"+1 928 708 0863",
    "sg:postcode":"86303",
    "sg:province":"AZ",
    "sg:tags":[
        "landscape",
        "contractor"
    ],
    "wof:name":"Jeff's Landscaping & Yard Svc",
    "wof:placetype":"venue"
},
  "geometry": {"coordinates":[-112.467045,34.516418],"type":"Point"}
}