{
  "type": "Feature",
  "properties": {
    "addr:full":"1922 N 66th Pl Mesa AZ 85205",
    "addr:housenumber":"1922",
    "addr:postcode":"85205",
    "addr:street":"N 66Th Pl",
    "iso:country":"US",
    "sg:address":"1922 N 66th Pl",
    "sg:city":"Mesa",
    "sg:classifiers":[
        {
            "category":"Building & Trades",
            "subcategory":"Construction",
            "type":"Services"
        }
    ],
    "sg:phone":"+1 480 854 0607",
    "sg:postcode":"85205",
    "sg:province":"AZ",
    "sg:tags":[
        "concrete",
        "contractor"
    ],
    "wof:name":"Tidwell Concrete Inc",
    "wof:placetype":"venue"
},
  "geometry": {"coordinates":[-111.688079,33.450703],"type":"Point"}
}