{
  "type": "Feature",
  "properties": {
    "iso:country":"US",
    "sg:address":"2701 W Grovers Ave",
    "sg:city":"Phoenix",
    "sg:classifiers":[
        {
            "category":"Real Estate",
            "subcategory":"Developer",
            "type":"Services"
        }
    ],
    "sg:phone":"+1 602 463 7146",
    "sg:postcode":"85053",
    "sg:province":"AZ",
    "sg:tags":[
        "investing"
    ],
    "wof:name":"Wild West Development Inc",
    "wof:placetype":"venue"
},
  "geometry": {"coordinates":[-112.11711099999999,33.647369],"type":"Point"}
}