{
  "type": "Feature",
  "properties": {
    "iso:country":"US",
    "sg:address":"816 S 4th Ave",
    "sg:city":"Yuma",
    "sg:classifiers":[
        {
            "category":"Manufacturing",
            "subcategory":"Tools & Machinery",
            "type":"Manufacturing & Wholesale Goods"
        }
    ],
    "sg:phone":"+1 928 782 0081",
    "sg:postcode":"85364",
    "sg:province":"AZ",
    "sg:tags":[
        "machine",
        "shop",
        "industrial"
    ],
    "wof:name":"Franks Pumps & Machine Works",
    "wof:placetype":"venue"
},
  "geometry": {"coordinates":[-114.624746,32.7115],"type":"Point"}
}