{
  "type": "Feature",
  "properties": {
    "iso:country":"US",
    "sg:address":"7229 E Manana Grande Pl",
    "sg:city":"Tucson",
    "sg:classifiers":[
        {
            "category":"Organizations",
            "subcategory":"Religious Organization",
            "type":"Services"
        }
    ],
    "sg:phone":"+1 520 323 5075",
    "sg:postcode":"85710",
    "sg:province":"AZ",
    "sg:tags":[
        "church"
    ],
    "wof:name":"Word In Season Christian Ctr",
    "wof:placetype":"venue"
},
  "geometry": {"coordinates":[-110.837394,32.202715],"type":"Point"}
}