{
  "type": "Feature",
  "properties": {
    "iso:country":"US",
    "sg:address":"505 W Ray Rd",
    "sg:city":"Chandler",
    "sg:classifiers":[
        {
            "category":"Health Services",
            "subcategory":"Optometrist",
            "type":"Services"
        }
    ],
    "sg:phone":"+1 480 821 2020",
    "sg:postcode":"85225",
    "sg:province":"AZ",
    "wof:name":"Kirk T Reed OD",
    "wof:placetype":"venue"
},
  "geometry": {"coordinates":[-111.850374,33.320642],"type":"Point"}
}