{
  "type": "Feature",
  "properties": {
    "iso:country":"US",
    "sg:address":"2314 W Sierra St",
    "sg:city":"Phoenix",
    "sg:classifiers":[
        {
            "category":"Manufacturing",
            "subcategory":"Textiles",
            "type":"Manufacturing & Wholesale Goods"
        }
    ],
    "sg:phone":"+1 602 576 2453",
    "sg:postcode":"85029",
    "sg:province":"AZ",
    "sg:tags":[
        "sewing",
        "contractor"
    ],
    "wof:name":"Virginia L Pirilahaynes",
    "wof:placetype":"venue"
},
  "geometry": {"coordinates":[-112.108126,33.591384],"type":"Point"}
}