{
  "type": "Feature",
  "properties": {
    "addr:full":"11541 W Bell Rd Surprise AZ 85374",
    "addr:housenumber":"11541",
    "addr:postcode":"85374",
    "addr:street":"W Bell Rd",
    "iso:country":"US",
    "sg:address":"11541 W Bell Rd",
    "sg:city":"Surprise",
    "sg:classifiers":[
        {
            "category":"Autos & Motor Vehicles",
            "subcategory":"Auto Supplies",
            "type":"Retail Goods"
        }
    ],
    "sg:phone":"+1 623 974 6676",
    "sg:postcode":"85374",
    "sg:province":"AZ",
    "sg:tags":[
        "tire"
    ],
    "wof:name":"Firestone Tire & Svc Ctr",
    "wof:placetype":"venue"
},
  "geometry": {"coordinates":[-112.309082,33.638677],"type":"Point"}
}