{
  "type": "Feature",
  "properties": {
    "addr:full":"500 W Southern Ave Mesa AZ 85210",
    "addr:housenumber":"500",
    "addr:postcode":"85210",
    "addr:street":"W Southern Ave",
    "iso:country":"US",
    "sg:address":"500 W Southern Ave",
    "sg:city":"Mesa",
    "sg:classifiers":[
        {
            "category":"Shopping",
            "subcategory":"Used Merchandise",
            "type":"Retail Goods"
        }
    ],
    "sg:phone":"+1 480 889 3511",
    "sg:postcode":"85210",
    "sg:province":"AZ",
    "sg:tags":[
        "pawnbroker"
    ],
    "wof:name":"E-Z Cash Superpawn",
    "wof:placetype":"venue"
},
  "geometry": {"coordinates":[-111.840765,33.393408],"type":"Point"}
}