{
  "type": "Feature",
  "properties": {
    "iso:country":"US",
    "sg:address":"1150 E 30th St",
    "sg:city":"Tucson",
    "sg:classifiers":[
        {
            "category":"Manufacturing",
            "subcategory":"Chemicals & Compounds",
            "type":"Manufacturing & Wholesale Goods"
        }
    ],
    "sg:phone":"+1 520 623 0041",
    "sg:postcode":"85713",
    "sg:province":"AZ",
    "sg:tags":[
        "chemicals-wholesale",
        "manufacturer"
    ],
    "wof:name":"L A Chemical",
    "wof:placetype":"venue"
},
  "geometry": {"coordinates":[-110.953775,32.198604],"type":"Point"}
}