{
  "type": "Feature",
  "properties": {
    "iso:country":"US",
    "sg:address":"7813 E Buena Tera Way",
    "sg:city":"Scottsdale",
    "sg:classifiers":[
        {
            "category":"Professional",
            "type":"Services"
        }
    ],
    "sg:phone":"+1 480 986 8760",
    "sg:postcode":"85250",
    "sg:province":"AZ",
    "sg:tags":[
        "art",
        "restoring"
    ],
    "wof:name":"Copley Fine Art & Restoration",
    "wof:placetype":"venue"
},
  "geometry": {"coordinates":[-111.912775,33.518004],"type":"Point"}
}