{
  "type": "Feature",
  "properties": {
    "iso:country":"US",
    "sg:address":"2188 E Glacier Pl",
    "sg:city":"Chandler",
    "sg:classifiers":[
        {
            "category":"Professional",
            "subcategory":"Management & Consulting",
            "type":"Services"
        }
    ],
    "sg:phone":"+1 480 704 3810",
    "sg:postcode":"85249",
    "sg:province":"AZ",
    "sg:tags":[
        "consultant",
        "business"
    ],
    "wof:name":"Replenishment Technology Group",
    "wof:placetype":"venue"
},
  "geometry": {"coordinates":[-111.805749,33.245083],"type":"Point"}
}