{
  "type": "Feature",
  "properties": {
    "addr:full":"813 S 1st Ave Yuma AZ 85364",
    "addr:housenumber":"813",
    "addr:postcode":"85364",
    "addr:street":"S 1St Ave",
    "iso:country":"US",
    "sg:address":"813 S 1st Ave",
    "sg:city":"Yuma",
    "sg:classifiers":[
        {
            "category":"Transit Center",
            "subcategory":"Freight",
            "type":"Transportation"
        },
        {
            "category":"Freight",
            "type":"Transportation"
        }
    ],
    "sg:phone":"+1 928 819 7020",
    "sg:postcode":"85364",
    "sg:province":"AZ",
    "sg:tags":[
        "local",
        "trucking-motor",
        "trucking"
    ],
    "wof:name":"Rendon Trucking",
    "wof:placetype":"venue"
},
  "geometry": {"coordinates":[-114.62087099999999,32.712862],"type":"Point"}
}