{
  "type": "Feature",
  "properties": {
    "addr:full":"2710 N Steves Blvd Ste 26 Flagstaff AZ 86004",
    "addr:housenumber":"2710",
    "addr:postcode":"86004",
    "addr:street":"N Steves Blvd Ste 26",
    "iso:country":"US",
    "sg:address":"2710 N Steves Blvd Ste 26",
    "sg:city":"Flagstaff",
    "sg:classifiers":[
        {
            "category":"Insurance",
            "subcategory":"Hazard Insurance",
            "type":"Services"
        }
    ],
    "sg:phone":"+1 928 526 5204",
    "sg:postcode":"86004",
    "sg:province":"AZ",
    "sg:tags":[
        "commercial",
        "business"
    ],
    "sg:website":"http://www.farmers.com",
    "wof:name":"Farmers Insurance",
    "wof:placetype":"venue"
},
  "geometry": {"coordinates":[-111.606393,35.212395],"type":"Point"}
}