{
  "type": "Feature",
  "properties": {
    "addr:full":"19711 N Tolby Creek Ct Surprise AZ 85387",
    "addr:housenumber":"19711",
    "addr:postcode":"85387",
    "addr:street":"N Tolby Creek Ct",
    "iso:country":"US",
    "sg:address":"19711 N Tolby Creek Ct",
    "sg:city":"Surprise",
    "sg:classifiers":[
        {
            "category":"Wholesale",
            "subcategory":"Toys & Hobbies",
            "type":"Manufacturing & Wholesale Goods"
        }
    ],
    "sg:phone":"+1 623 546 4981",
    "sg:postcode":"85387",
    "sg:province":"AZ",
    "wof:name":"Netdragonscom",
    "wof:placetype":"venue"
},
  "geometry": {"coordinates":[-112.428888,33.663107],"type":"Point"}
}