{
  "type": "Feature",
  "properties": {
    "addr:full":"6740 E State Rte 69 Prescott Valley AZ 86314",
    "addr:housenumber":"6740",
    "addr:postcode":"86314",
    "addr:street":"E State Rte 69",
    "iso:country":"US",
    "sg:address":"6740 E State Rte 69",
    "sg:city":"Prescott Valley",
    "sg:classifiers":[
        {
            "category":"Autos & Motor Vehicles",
            "subcategory":"Automobile Sales",
            "type":"Retail Goods"
        }
    ],
    "sg:phone":"+1 928 772 7792",
    "sg:postcode":"86314",
    "sg:province":"AZ",
    "sg:tags":[
        "car",
        "dealer"
    ],
    "wof:name":"Tim's Used Cars",
    "wof:placetype":"venue"
},
  "geometry": {"coordinates":[-112.346666,34.582392],"type":"Point"}
}