{
  "type": "Feature",
  "properties": {
    "iso:country":"US",
    "sg:address":"2228 E 6th St",
    "sg:city":"Tucson",
    "sg:classifiers":[
        {
            "category":"Professional",
            "subcategory":"Computer Services",
            "type":"Services"
        }
    ],
    "sg:phone":"+1 520 304 8300",
    "sg:postcode":"85719",
    "sg:province":"AZ",
    "sg:tags":[
        "repair"
    ],
    "wof:name":"Computer Guru",
    "wof:placetype":"venue"
},
  "geometry": {"coordinates":[-110.938458,32.227801],"type":"Point"}
}