{
  "type": "Feature",
  "properties": {
    "iso:country":"US",
    "sg:address":"3030 W San Juan Ter",
    "sg:city":"Tucson",
    "sg:classifiers":[
        {
            "category":"Building & Trades",
            "subcategory":"Landscaping Services",
            "type":"Services"
        }
    ],
    "sg:phone":"+1 520 622 6938",
    "sg:postcode":"85713",
    "sg:province":"AZ",
    "wof:name":"Barba Juan & Assoc",
    "wof:placetype":"venue"
},
  "geometry": {"coordinates":[-111.030872,32.200385],"type":"Point"}
}