{
  "type": "Feature",
  "properties": {
    "addr:full":"4635 N 7th St Phoenix AZ 85014",
    "addr:housenumber":"4635",
    "addr:postcode":"85014",
    "addr:street":"N 7Th St",
    "iso:country":"US",
    "sg:address":"4635 N 7th St",
    "sg:city":"Phoenix",
    "sg:classifiers":[
        {
            "category":"Autos & Motor Vehicles",
            "subcategory":"Automobile Sales",
            "type":"Retail Goods"
        }
    ],
    "sg:phone":"+1 602 264 3626",
    "sg:postcode":"85014",
    "sg:province":"AZ",
    "sg:tags":[
        "car",
        "dealer"
    ],
    "wof:name":"ABC Nissan Pdi Center",
    "wof:placetype":"venue"
},
  "geometry": {"coordinates":[-112.064949,33.50467],"type":"Point"}
}