{
  "type": "Feature",
  "properties": {
    "iso:country":"US",
    "sg:address":"5095 W Camelback Rd",
    "sg:city":"Phoenix",
    "sg:classifiers":[
        {
            "category":"Autos & Motor Vehicles",
            "subcategory":"Automobile Sales",
            "type":"Retail Goods"
        }
    ],
    "sg:phone":"+1 602 331 3333",
    "sg:postcode":"85031",
    "sg:province":"AZ",
    "sg:tags":[
        "car",
        "used"
    ],
    "sg:website":"http://libertyusedautosales.com",
    "wof:name":"Liberty Auto Sales",
    "wof:placetype":"venue"
},
  "geometry": {"coordinates":[-112.168391,33.509472],"type":"Point"}
}