{
  "type": "Feature",
  "properties": {
    "iso:country":"US",
    "sg:address":"8660 E Valley Rd",
    "sg:city":"Prescott Valley",
    "sg:classifiers":[
        {
            "category":"Manufacturing",
            "subcategory":"Printing",
            "type":"Manufacturing & Wholesale Goods"
        }
    ],
    "sg:phone":"+1 928 772 5045",
    "sg:postcode":"86314",
    "sg:province":"AZ",
    "sg:tags":[
        "commercial"
    ],
    "wof:name":"Bob Moons Specialty Print",
    "wof:placetype":"venue"
},
  "geometry": {"coordinates":[-112.313706,34.585715],"type":"Point"}
}