{
  "type": "Feature",
  "properties": {
    "iso:country":"US",
    "sg:address":"960 E 17th St",
    "sg:city":"Tucson",
    "sg:classifiers":[
        {
            "category":"Shopping",
            "subcategory":"Gifts & Souvenirs",
            "type":"Retail Goods"
        }
    ],
    "sg:phone":"+1 520 624 1415",
    "sg:postcode":"85719",
    "sg:province":"AZ",
    "sg:tags":[
        "party",
        "favors",
        "supply"
    ],
    "sg:website":"http://www.tucsonpartyrentals.com",
    "wof:name":"Tucson Party Rentals",
    "wof:placetype":"venue"
},
  "geometry": {"coordinates":[-110.95549,32.213408],"type":"Point"}
}