{
  "type": "Feature",
  "properties": {
    "iso:country":"US",
    "sg:address":"718 W Gurley St",
    "sg:city":"Prescott",
    "sg:classifiers":[
        {
            "category":"Retail",
            "subcategory":"Animal Services",
            "type":"Services"
        }
    ],
    "sg:phone":"+1 928 445 7244",
    "sg:postcode":"86305",
    "sg:province":"AZ",
    "sg:tags":[
        "pet",
        "grooming",
        "washing"
    ],
    "wof:name":"Yvonne's Pet Grooming",
    "wof:placetype":"venue"
},
  "geometry": {"coordinates":[-112.480063,34.542702],"type":"Point"}
}