{
  "type": "Feature",
  "properties": {
    "addr:full":"4823 W Marconi Ave Glendale AZ 85306",
    "addr:housenumber":"4823",
    "addr:postcode":"85306",
    "addr:street":"W Marconi Ave",
    "iso:country":"US",
    "sg:address":"4823 W Marconi Ave",
    "sg:city":"Glendale",
    "sg:classifiers":[
        {
            "category":"Professional",
            "subcategory":"Art Services",
            "type":"Services"
        }
    ],
    "sg:phone":"+1 602 978 5995",
    "sg:postcode":"85306",
    "sg:province":"AZ",
    "sg:tags":[
        "graphic",
        "agency",
        "commercial",
        "designer",
        "design",
        "advertising"
    ],
    "wof:name":"Tr&A Signs & Engraving",
    "wof:placetype":"venue"
},
  "geometry": {"coordinates":[-112.163189,33.62999],"type":"Point"}
}