{
  "type": "Feature",
  "properties": {
    "iso:country":"US",
    "sg:address":"2901 W Dunlap Ave",
    "sg:city":"Phoenix",
    "sg:classifiers":[
        {
            "category":"Health Services",
            "subcategory":"Health Practitioner",
            "type":"Services"
        }
    ],
    "sg:phone":"+1 602 995 6188",
    "sg:postcode":"85051",
    "sg:province":"AZ",
    "sg:tags":[
        "acupuncture"
    ],
    "wof:name":"Acu-Acupuncture",
    "wof:placetype":"venue"
},
  "geometry": {"coordinates":[-112.124642,33.567583],"type":"Point"}
}