{
  "type": "Feature",
  "properties": {
    "iso:country":"US",
    "sg:address":"5620 N 7th St",
    "sg:city":"Phoenix",
    "sg:classifiers":[
        {
            "category":"Professional",
            "type":"Services"
        }
    ],
    "sg:phone":"+1 602 231 0499",
    "sg:postcode":"85014",
    "sg:province":"AZ",
    "wof:name":"A Aaaabsolute Escort Inc",
    "wof:placetype":"venue"
},
  "geometry": {"coordinates":[-112.065074,33.519868],"type":"Point"}
}