{
  "type": "Feature",
  "properties": {
    "iso:country":"US",
    "sg:address":"9318 N 95th Way",
    "sg:city":"Scottsdale",
    "sg:classifiers":[
        {
            "category":"Professional",
            "subcategory":"Computer Services",
            "type":"Services"
        }
    ],
    "sg:phone":"+1 480 445 0110",
    "sg:postcode":"85258",
    "sg:province":"AZ",
    "sg:tags":[
        "website",
        "design"
    ],
    "sg:website":"www.labcreek.net",
    "wof:name":"Labcreek Technical Solutions",
    "wof:placetype":"venue"
},
  "geometry": {"coordinates":[-111.87517,33.569144],"type":"Point"}
}