{
  "type": "Feature",
  "properties": {
    "iso:country":"US",
    "sg:address":"3031 E Cholla St",
    "sg:city":"Phoenix",
    "sg:classifiers":[
        {
            "category":"Professional",
            "subcategory":"Business Services",
            "type":"Services"
        }
    ],
    "sg:phone":"+1 602 885 2821",
    "sg:postcode":"85028",
    "sg:province":"AZ",
    "sg:tags":[
        "pool",
        "swimming"
    ],
    "wof:name":"Peacock Pool Svc",
    "wof:placetype":"venue"
},
  "geometry": {"coordinates":[-112.015205,33.589374],"type":"Point"}
}