{
  "type": "Feature",
  "properties": {
    "iso:country":"US",
    "sg:address":"3333 E Camelback Rd",
    "sg:city":"Phoenix",
    "sg:classifiers":[
        {
            "category":"Real Estate",
            "subcategory":"Real Estate Agent",
            "type":"Services"
        }
    ],
    "sg:phone":"+1 602 954 6641",
    "sg:postcode":"85018",
    "sg:province":"AZ",
    "sg:tags":[
        "investment"
    ],
    "wof:name":"David C Russ Investments",
    "wof:placetype":"venue"
},
  "geometry": {"coordinates":[-112.010963,33.50989],"type":"Point"}
}