{
  "type": "Feature",
  "properties": {
    "iso:country":"US",
    "sg:address":"1686 E Fry Blvd",
    "sg:city":"Sierra Vista",
    "sg:classifiers":[
        {
            "category":"Restaurant",
            "type":"Food & Drink"
        }
    ],
    "sg:phone":"+1 520 459 7008",
    "sg:postcode":"85635",
    "sg:province":"AZ",
    "wof:name":"Chicos Tortillas",
    "wof:placetype":"venue"
},
  "geometry": {"coordinates":[-110.2804,31.554562],"type":"Point"}
}