{
  "type": "Feature",
  "properties": {
    "iso:country":"US",
    "sg:address":"4662 E Greenway St",
    "sg:city":"Mesa",
    "sg:classifiers":[
        {
            "category":"Building & Trades",
            "subcategory":"Construction",
            "type":"Services"
        }
    ],
    "sg:phone":"+1 602 696 2595",
    "sg:postcode":"85205",
    "sg:province":"AZ",
    "sg:tags":[
        "handyman"
    ],
    "wof:name":"Lapo Remodeling & Handyman Svc",
    "wof:placetype":"venue"
},
  "geometry": {"coordinates":[-111.730273,33.43793],"type":"Point"}
}