{
  "type": "Feature",
  "properties": {
    "iso:country":"US",
    "sg:address":"2214 W Laurel Ln",
    "sg:city":"Phoenix",
    "sg:classifiers":[
        {
            "category":"Home & Garden",
            "subcategory":"Building Materials",
            "type":"Retail Goods"
        }
    ],
    "sg:phone":"+1 602 943 4346",
    "sg:postcode":"85029",
    "sg:province":"AZ",
    "wof:name":"Colonial Glass Inc",
    "wof:placetype":"venue"
},
  "geometry": {"coordinates":[-112.105686,33.59469],"type":"Point"}
}