{
  "type": "Feature",
  "properties": {
    "iso:country":"US",
    "sg:address":"9201 N 29th Ave",
    "sg:city":"Phoenix",
    "sg:classifiers":[
        {
            "category":"Shopping",
            "subcategory":"Clothing, Apparel, & Fashions",
            "type":"Retail Goods"
        }
    ],
    "sg:phone":"+1 602 674 5377",
    "sg:postcode":"85051",
    "sg:province":"AZ",
    "wof:name":"Catherines Plus Sizes",
    "wof:placetype":"venue"
},
  "geometry": {"coordinates":[-112.120676,33.570026],"type":"Point"}
}