{
  "type": "Feature",
  "properties": {
    "iso:country":"US",
    "sg:address":"2808 E Indian School Rd",
    "sg:city":"Phoenix",
    "sg:classifiers":[
        {
            "category":"Restaurant",
            "type":"Food & Drink"
        }
    ],
    "sg:menulink":"http://www.allmenus.com/az/phoenix/4233-vine-tavern--eatery/menu/",
    "sg:phone":"+1 602 957 9806",
    "sg:postcode":"85016",
    "sg:province":"AZ",
    "sg:tags":[
        "american"
    ],
    "wof:name":"Vine Tavern & Eatery",
    "wof:placetype":"venue"
},
  "geometry": {"coordinates":[-112.021322,33.495027],"type":"Point"}
}