{
  "type": "Feature",
  "properties": {
    "iso:country":"US",
    "sg:address":"10049 E Dynamite Blvd Ste 110",
    "sg:city":"Scottsdale",
    "sg:classifiers":[
        {
            "category":"Health Services",
            "subcategory":"Dentist",
            "type":"Services"
        }
    ],
    "sg:phone":"+1 480 513 6864",
    "sg:postcode":"85262",
    "sg:province":"AZ",
    "wof:name":"Graber Gregory E DDS Pllc",
    "wof:placetype":"venue"
},
  "geometry": {"coordinates":[-111.863775,33.742851],"type":"Point"}
}