{
  "type": "Feature",
  "properties": {
    "addr:full":"2707 W Willow Breeze Rd Chino Valley AZ 86323",
    "addr:housenumber":"2707",
    "addr:postcode":"86323",
    "addr:street":"W Willow Breeze Rd",
    "iso:country":"US",
    "sg:address":"2707 W Willow Breeze Rd",
    "sg:city":"Chino Valley",
    "sg:classifiers":[
        {
            "category":"Freight",
            "type":"Transportation"
        }
    ],
    "sg:phone":"+1 928 636 2958",
    "sg:postcode":"86323",
    "sg:province":"AZ",
    "sg:tags":[
        "operator",
        "local",
        "trucking"
    ],
    "wof:name":"Say Dump Truck Service",
    "wof:placetype":"venue"
},
  "geometry": {"coordinates":[-112.494827,34.734402],"type":"Point"}
}