{
  "type": "Feature",
  "properties": {
    "iso:country":"US",
    "sg:address":"4520 N 19th Ave",
    "sg:city":"Phoenix",
    "sg:classifiers":[
        {
            "category":"Manufacturing",
            "subcategory":"Printing",
            "type":"Manufacturing & Wholesale Goods"
        }
    ],
    "sg:phone":"+1 602 242 2308",
    "sg:postcode":"85015",
    "sg:province":"AZ",
    "sg:tags":[
        "printer"
    ],
    "wof:name":"Sav-On Printing Ctr Inc",
    "wof:placetype":"venue"
},
  "geometry": {"coordinates":[-112.099962,33.503755],"type":"Point"}
}