{
  "type": "Feature",
  "properties": {
    "iso:country":"US",
    "sg:address":"7020 E Hermosa Vista Dr",
    "sg:city":"Mesa",
    "sg:classifiers":[
        {
            "category":"Real Estate",
            "subcategory":"Real Estate Operator",
            "type":"Services"
        }
    ],
    "sg:phone":"+1 480 396 3239",
    "sg:postcode":"85207",
    "sg:province":"AZ",
    "sg:tags":[
        "building",
        "nonresidential"
    ],
    "wof:name":"Ecms Properties LLC",
    "wof:placetype":"venue"
},
  "geometry": {"coordinates":[-111.678147,33.458844],"type":"Point"}
}