{
  "type": "Feature",
  "properties": {
    "iso:country":"US",
    "sg:address":"6810 E Broadway Blvd",
    "sg:city":"Tucson",
    "sg:classifiers":[
        {
            "category":"Real Estate",
            "subcategory":"Real Estate Agent",
            "type":"Services"
        }
    ],
    "sg:phone":"+1 520 546 9601",
    "sg:postcode":"85710",
    "sg:province":"AZ",
    "sg:tags":[
        "investment"
    ],
    "wof:name":"New Horizon Properties",
    "wof:placetype":"venue"
},
  "geometry": {"coordinates":[-110.846595,32.220951],"type":"Point"}
}