{
  "type": "Feature",
  "properties": {
    "iso:country":"US",
    "sg:address":"6917 E Avalon Dr",
    "sg:city":"Scottsdale",
    "sg:classifiers":[
        {
            "category":"Manufacturing",
            "subcategory":"Buildings",
            "type":"Manufacturing & Wholesale Goods"
        },
        {
            "category":"Building & Trades",
            "subcategory":"Construction",
            "type":"Services"
        },
        {
            "category":"Manufacturing",
            "subcategory":"Building Materials",
            "type":"Manufacturing & Wholesale Goods"
        }
    ],
    "sg:phone":"+1 480 970 0309",
    "sg:postcode":"85251",
    "sg:province":"AZ",
    "sg:tags":[
        "doors-wholesale",
        "builder",
        "accessory",
        "doors",
        "frames",
        "home",
        "contractor",
        "manufacturer"
    ],
    "wof:name":"R Doors",
    "wof:placetype":"venue"
},
  "geometry": {"coordinates":[-111.932802,33.483187],"type":"Point"}
}