{
  "type": "Feature",
  "properties": {
    "iso:country":"US",
    "sg:address":"9160 E Cam del Santo",
    "sg:city":"Scottsdale",
    "sg:classifiers":[
        {
            "category":"Local Transit",
            "type":"Transportation"
        }
    ],
    "sg:phone":"+1 480 661 8977",
    "sg:postcode":"85260",
    "sg:province":"AZ",
    "wof:name":"Grand Metro Transit",
    "wof:placetype":"venue"
},
  "geometry": {"coordinates":[-111.88362100000001,33.607253],"type":"Point"}
}