{
  "type": "Feature",
  "properties": {
    "addr:full":"7225 N Oracle Rd Tucson AZ 85704",
    "addr:housenumber":"7225",
    "addr:postcode":"85704",
    "addr:street":"N Oracle Rd",
    "iso:country":"US",
    "sg:address":"7225 N Oracle Rd",
    "sg:city":"Tucson",
    "sg:classifiers":[
        {
            "category":"Building & Trades",
            "subcategory":"Construction",
            "type":"Services"
        }
    ],
    "sg:phone":"+1 520 498 1128",
    "sg:postcode":"85704",
    "sg:province":"AZ",
    "sg:tags":[
        "general",
        "contractor"
    ],
    "wof:name":"Keith A Winnie Design & Build",
    "wof:placetype":"venue"
},
  "geometry": {"coordinates":[-110.97739,32.339879],"type":"Point"}
}