{
  "type": "Feature",
  "properties": {
    "iso:country":"US",
    "sg:address":"695 E Grant Rd",
    "sg:city":"Tucson",
    "sg:classifiers":[
        {
            "category":"Restaurant",
            "type":"Food & Drink"
        }
    ],
    "sg:phone":"+1 520 882 8710",
    "sg:postcode":"85705",
    "sg:province":"AZ",
    "wof:name":"Apple Farm Bakery Restaurant",
    "wof:placetype":"venue"
},
  "geometry": {"coordinates":[-110.96172799999999,32.250463],"type":"Point"}
}