{
  "type": "Feature",
  "properties": {
    "addr:full":"3379 Jadito Trl Flagstaff AZ 86001",
    "addr:housenumber":"3379",
    "addr:postcode":"86001",
    "addr:street":"Jadito Trl",
    "iso:country":"US",
    "sg:address":"3379 Jadito Trl",
    "sg:city":"Flagstaff",
    "sg:classifiers":[
        {
            "category":"Building & Trades",
            "subcategory":"Construction",
            "type":"Services"
        }
    ],
    "sg:phone":"+1 928 525 9529",
    "sg:postcode":"86001",
    "sg:province":"AZ",
    "sg:tags":[
        "wallcoverings-installation",
        "wallpaper",
        "painting",
        "contractor"
    ],
    "wof:name":"Rea Dominic Painting Inc",
    "wof:placetype":"venue"
},
  "geometry": {"coordinates":[-111.70264400000001,35.091936],"type":"Point"}
}