{
  "type": "Feature",
  "properties": {
    "iso:country":"US",
    "sg:address":"7720 E Redfield Rd Ste 5",
    "sg:city":"Scottsdale",
    "sg:classifiers":[
        {
            "category":"Manufacturing",
            "subcategory":"Metals",
            "type":"Manufacturing & Wholesale Goods"
        }
    ],
    "sg:phone":"+1 480 998 8570",
    "sg:postcode":"85260",
    "sg:province":"AZ",
    "sg:tags":[
        "metal-wholesale",
        "specialty",
        "manufacturer"
    ],
    "wof:name":"Alloy Arts",
    "wof:placetype":"venue"
},
  "geometry": {"coordinates":[-111.914364,33.61394],"type":"Point"}
}