{
  "type": "Feature",
  "properties": {
    "iso:country":"US",
    "sg:address":"7740 E Redfield Rd Ste 106",
    "sg:city":"Scottsdale",
    "sg:classifiers":[
        {
            "category":"Manufacturing",
            "subcategory":"Buildings",
            "type":"Manufacturing & Wholesale Goods"
        },
        {
            "category":"Building & Trades",
            "subcategory":"Construction",
            "type":"Services"
        }
    ],
    "sg:phone":"+1 480 994 8767",
    "sg:postcode":"85260",
    "sg:province":"AZ",
    "sg:tags":[
        "altering",
        "consultant",
        "builder",
        "contractor",
        "home",
        "remodeling"
    ],
    "wof:name":"Azcal Construction",
    "wof:placetype":"venue"
},
  "geometry": {"coordinates":[-111.91386799999999,33.613938],"type":"Point"}
}