{
  "type": "Feature",
  "properties": {
    "addr:full":"1180 N Naples Dr Chandler AZ 85226",
    "addr:housenumber":"1180",
    "addr:postcode":"85226",
    "addr:street":"N Naples Dr",
    "iso:country":"US",
    "sg:address":"1180 N Naples Dr",
    "sg:city":"Chandler",
    "sg:classifiers":[
        {
            "category":"Home & Garden",
            "subcategory":"Building Materials",
            "type":"Retail Goods"
        }
    ],
    "sg:phone":"+1 480 461 8662",
    "sg:postcode":"85226",
    "sg:province":"AZ",
    "sg:tags":[
        "paint"
    ],
    "wof:name":"AAA Valley Wide Custom Paint",
    "wof:placetype":"venue"
},
  "geometry": {"coordinates":[-111.899738,33.323255],"type":"Point"}
}