{
  "type": "Feature",
  "properties": {
    "addr:full":"4603 E Speedway Blvd Tucson AZ 85712",
    "addr:housenumber":"4603",
    "addr:postcode":"85712",
    "addr:street":"E Speedway Blvd",
    "iso:country":"US",
    "sg:address":"4603 E Speedway Blvd",
    "sg:city":"Tucson",
    "sg:classifiers":[
        {
            "category":"Bars & Pubs",
            "type":"Food & Drink"
        }
    ],
    "sg:phone":"+1 520 325 3555",
    "sg:postcode":"85712",
    "sg:province":"AZ",
    "sg:tags":[
        "drinking"
    ],
    "wof:name":"Terry & Zekes Friendly Tavern",
    "wof:placetype":"venue"
},
  "geometry": {"coordinates":[-110.892639,32.236283],"type":"Point"}
}