{
  "type": "Feature",
  "properties": {
    "iso:country":"US",
    "sg:address":"2121 W Pima St",
    "sg:city":"Phoenix",
    "sg:classifiers":[
        {
            "category":"Manufacturing",
            "subcategory":"Signs",
            "type":"Manufacturing & Wholesale Goods"
        }
    ],
    "sg:phone":"+1 866 247 1061",
    "sg:postcode":"85009",
    "sg:province":"AZ",
    "sg:website":"http://www.kenssignservice.com",
    "wof:name":"Ken's Sign Service",
    "wof:placetype":"venue"
},
  "geometry": {"coordinates":[-112.104766,33.433093],"type":"Point"}
}