{
  "type": "Feature",
  "properties": {
    "addr:full":"15502 W Agua Linda Ln Surprise AZ 85374",
    "addr:housenumber":"15502",
    "addr:postcode":"85374",
    "addr:street":"W Agua Linda Ln",
    "iso:country":"US",
    "sg:address":"15502 W Agua Linda Ln",
    "sg:city":"Surprise",
    "sg:classifiers":[
        {
            "category":"Structure",
            "subcategory":"Office Building",
            "type":"Public Place"
        }
    ],
    "sg:phone":"+1 623 544 1058",
    "sg:postcode":"85374",
    "sg:province":"AZ",
    "sg:tags":[
        "park"
    ],
    "wof:name":"B Bar B Mt Properties",
    "wof:placetype":"venue"
},
  "geometry": {"coordinates":[-112.393518,33.652439],"type":"Point"}
}