{
  "type": "Feature",
  "properties": {
    "iso:country":"US",
    "sg:address":"8 Will Rogers Ln",
    "sg:city":"Tubac",
    "sg:classifiers":[
        {
            "category":"Home & Garden",
            "subcategory":"Home Furnishings",
            "type":"Retail Goods"
        }
    ],
    "sg:phone":"+1 520 398 9666",
    "sg:postcode":"85646",
    "sg:province":"AZ",
    "wof:name":"Tubac Village Emporium",
    "wof:placetype":"venue"
},
  "geometry": {"coordinates":[-111.050104,31.612622],"type":"Point"}
}