{
  "type": "Feature",
  "properties": {
    "iso:country":"US",
    "sg:address":"5221 W Montebello Ave",
    "sg:city":"Glendale",
    "sg:classifiers":[
        {
            "category":"Manufacturing",
            "subcategory":"Electronics",
            "type":"Manufacturing & Wholesale Goods"
        }
    ],
    "sg:phone":"+1 623 842 2176",
    "sg:postcode":"85301",
    "sg:province":"AZ",
    "sg:tags":[
        "semiconductor",
        "die",
        "mold",
        "tooling",
        "mfg"
    ],
    "wof:name":"Arizona Semi-Technologies",
    "wof:placetype":"venue"
},
  "geometry": {"coordinates":[-112.172657,33.520272],"type":"Point"}
}