{
  "type": "Feature",
  "properties": {
    "iso:country":"US",
    "sg:address":"345 W Vernon Ave",
    "sg:city":"Phoenix",
    "sg:classifiers":[
        {
            "category":"Real Estate",
            "subcategory":"Real Estate Agent",
            "type":"Services"
        }
    ],
    "sg:phone":"+1 602 625 4718",
    "sg:postcode":"85003",
    "sg:province":"AZ",
    "wof:name":"Amy & Frank Johnson",
    "wof:placetype":"venue"
},
  "geometry": {"coordinates":[-112.079608,33.473949],"type":"Point"}
}