{
  "type": "Feature",
  "properties": {
    "iso:country":"US",
    "sg:address":"4765 W Marlette Ave",
    "sg:city":"Glendale",
    "sg:classifiers":[
        {
            "category":"Utilities",
            "subcategory":"Telephone",
            "type":"Services"
        }
    ],
    "sg:phone":"+1 623 934 2933",
    "sg:postcode":"85301",
    "sg:province":"AZ",
    "sg:tags":[
        "communications"
    ],
    "wof:name":"Campzona Co",
    "wof:placetype":"venue"
},
  "geometry": {"coordinates":[-112.160898,33.529312],"type":"Point"}
}