{
  "type": "Feature",
  "properties": {
    "addr:full":"2700 S Woodlands Village Blvd Ste 640 Flagstaff AZ 86001",
    "addr:housenumber":"2700",
    "addr:postcode":"86001",
    "addr:street":"S Woodlands Village Blvd Ste 640",
    "iso:country":"US",
    "sg:address":"2700 S Woodlands Village Blvd Ste 640",
    "sg:city":"Flagstaff",
    "sg:classifiers":[
        {
            "category":"Professional",
            "type":"Services"
        },
        {
            "category":"Restaurant",
            "type":"Food & Drink"
        }
    ],
    "sg:phone":"+1 928 556 0019",
    "sg:postcode":"86001",
    "sg:province":"AZ",
    "sg:tags":[
        "indian",
        "caterer"
    ],
    "wof:name":"Delhi Palace",
    "wof:placetype":"venue"
},
  "geometry": {"coordinates":[-111.66788,35.176153],"type":"Point"}
}