{
  "type": "Feature",
  "properties": {
    "addr:full":"2901 S 6th Ave Tucson AZ 85713",
    "addr:housenumber":"2901",
    "addr:postcode":"85713",
    "addr:street":"S 6Th Ave",
    "iso:country":"US",
    "sg:address":"2901 S 6th Ave",
    "sg:city":"Tucson",
    "sg:classifiers":[
        {
            "category":"Manufacturing",
            "subcategory":"Building Materials",
            "type":"Manufacturing & Wholesale Goods"
        }
    ],
    "sg:phone":"+1 520 624 2347",
    "sg:postcode":"85713",
    "sg:province":"AZ",
    "sg:tags":[
        "mfg"
    ],
    "wof:name":"City Doors",
    "wof:placetype":"venue"
},
  "geometry": {"coordinates":[-110.968351,32.188743],"type":"Point"}
}