{
  "type": "Feature",
  "properties": {
    "iso:country":"US",
    "sg:address":"1505 E Broadway Rd",
    "sg:city":"Phoenix",
    "sg:classifiers":[
        {
            "category":"Real Estate",
            "subcategory":"Real Estate Operator",
            "type":"Services"
        }
    ],
    "sg:phone":"+1 602 276 6590",
    "sg:postcode":"85040",
    "sg:province":"AZ",
    "sg:tags":[
        "property",
        "lessor"
    ],
    "wof:name":"Juan & Beverly Ortiz",
    "wof:placetype":"venue"
},
  "geometry": {"coordinates":[-112.047207,33.40671],"type":"Point"}
}