{
  "type": "Feature",
  "properties": {
    "addr:full":"1804 W Elliot Rd Tempe AZ 85284",
    "addr:housenumber":"1804",
    "addr:postcode":"85284",
    "addr:street":"W Elliot Rd",
    "iso:country":"US",
    "sg:address":"1804 W Elliot Rd",
    "sg:city":"Tempe",
    "sg:classifiers":[
        {
            "category":"Health Services",
            "subcategory":"Doctor",
            "type":"Services"
        }
    ],
    "sg:phone":"+1 480 456 0444",
    "sg:postcode":"85284",
    "sg:province":"AZ",
    "sg:tags":[
        "physician",
        "surgeon"
    ],
    "wof:name":"Advanced Urgent Care",
    "wof:placetype":"venue"
},
  "geometry": {"coordinates":[-111.969875,33.349163],"type":"Point"}
}