{
  "type": "Feature",
  "properties": {
    "iso:country":"US",
    "sg:address":"1416 W 18th Pl",
    "sg:city":"Yuma",
    "sg:classifiers":[
        {
            "category":"Building & Trades",
            "subcategory":"Landscaping Services",
            "type":"Services"
        }
    ],
    "sg:phone":"+1 928 783 5517",
    "sg:postcode":"85364",
    "sg:province":"AZ",
    "wof:name":"Adolfos Tree Service",
    "wof:placetype":"venue"
},
  "geometry": {"coordinates":[-114.638807,32.693729],"type":"Point"}
}