{
  "type": "Feature",
  "properties": {
    "iso:country":"US",
    "sg:address":"3102 S 44th St",
    "sg:city":"Phoenix",
    "sg:classifiers":[
        {
            "category":"Building & Trades",
            "subcategory":"Construction",
            "type":"Services"
        }
    ],
    "sg:phone":"+1 602 258 3890",
    "sg:postcode":"85040",
    "sg:province":"AZ",
    "sg:tags":[
        "rack"
    ],
    "wof:name":"Desert Rack Company",
    "wof:placetype":"venue"
},
  "geometry": {"coordinates":[-111.986896,33.417023],"type":"Point"}
}