{
  "type": "Feature",
  "properties": {
    "iso:country":"US",
    "sg:address":"918 W Irvington Rd",
    "sg:city":"Tucson",
    "sg:classifiers":[
        {
            "category":"Utilities",
            "subcategory":"Mobile Phone",
            "type":"Services"
        }
    ],
    "sg:phone":"+1 520 746 0040",
    "sg:postcode":"85714",
    "sg:province":"AZ",
    "sg:tags":[
        "telephone",
        "cellular"
    ],
    "wof:name":"Alltel",
    "wof:placetype":"venue"
},
  "geometry": {"coordinates":[-110.991179,32.163264],"type":"Point"}
}