{
  "type": "Feature",
  "properties": {
    "iso:country":"US",
    "sg:address":"2121 S 48th St",
    "sg:city":"Tempe",
    "sg:classifiers":[
        {
            "category":"Insurance",
            "subcategory":"Insurance Agent",
            "type":"Services"
        }
    ],
    "sg:phone":"+1 602 438 9733",
    "sg:postcode":"85281",
    "sg:province":"AZ",
    "wof:name":"All Your Insurance Inc",
    "wof:placetype":"venue"
},
  "geometry": {"coordinates":[-111.977779,33.415289],"type":"Point"}
}