{
  "type": "Feature",
  "properties": {
    "iso:country":"US",
    "sg:address":"201 N Broad St",
    "sg:city":"Globe",
    "sg:classifiers":[
        {
            "category":"Food & Beverages",
            "subcategory":"Specialty",
            "type":"Retail Goods"
        }
    ],
    "sg:phone":"+1 928 425 2586",
    "sg:postcode":"85502",
    "sg:province":"AZ",
    "sg:tags":[
        "health"
    ],
    "wof:name":"Back To Basics",
    "wof:placetype":"venue"
},
  "geometry": {"coordinates":[-110.78797299999999,33.397577],"type":"Point"}
}