{
  "type": "Feature",
  "properties": {
    "iso:country":"US",
    "sg:address":"3828 N 33rd Pl",
    "sg:city":"Phoenix",
    "sg:classifiers":[
        {
            "category":"Real Estate",
            "subcategory":"Architect",
            "type":"Services"
        }
    ],
    "sg:phone":"+1 602 532 9978",
    "sg:postcode":"85018",
    "sg:province":"AZ",
    "sg:tags":[
        "architects'",
        "specification",
        "builders'",
        "construction",
        "architectural"
    ],
    "wof:name":"Michael Shelor Architect",
    "wof:placetype":"venue"
},
  "geometry": {"coordinates":[-112.009455,33.492609],"type":"Point"}
}