{
  "type": "Feature",
  "properties": {
    "iso:country":"US",
    "sg:address":"102 N Montezuma St",
    "sg:city":"Prescott",
    "sg:classifiers":[
        {
            "category":"Real Estate",
            "subcategory":"Real Estate Services",
            "type":"Services"
        },
        {
            "category":"Real Estate",
            "subcategory":"Real Estate Agent",
            "type":"Services"
        }
    ],
    "sg:phone":"+1 928 776 4111",
    "sg:postcode":"86301",
    "sg:province":"AZ",
    "sg:tags":[
        "buyer",
        "broker"
    ],
    "sg:website":"http://www.kw.com",
    "wof:name":"Keller Williams Check Realty",
    "wof:placetype":"venue"
},
  "geometry": {"coordinates":[-112.47013,34.541925],"type":"Point"}
}