{
  "type": "Feature",
  "properties": {
    "iso:country":"US",
    "sg:address":"105 W Main St",
    "sg:city":"Mesa",
    "sg:classifiers":[
        {
            "category":"Place Of Worship",
            "subcategory":"Church",
            "type":"Public Place"
        },
        {
            "category":"Place Of Worship",
            "type":"Public Place"
        }
    ],
    "sg:phone":"+1 480 962 0682",
    "sg:postcode":"85201",
    "sg:province":"AZ",
    "sg:tags":[
        "churches-non-denominational"
    ],
    "wof:name":"Faith Harvest Church",
    "wof:placetype":"venue"
},
  "geometry": {"coordinates":[-111.834176,33.415059],"type":"Point"}
}