{
  "type": "Feature",
  "properties": {
    "addr:full":"9518 W Pierce St Tolleson AZ 85353",
    "addr:housenumber":"9518",
    "addr:postcode":"85353",
    "addr:street":"W Pierce St",
    "iso:country":"US",
    "sg:address":"9518 W Pierce St",
    "sg:city":"Tolleson",
    "sg:classifiers":[
        {
            "category":"Shopping",
            "subcategory":"Florist",
            "type":"Retail Goods"
        }
    ],
    "sg:phone":"+1 623 907 4892",
    "sg:postcode":"85353",
    "sg:province":"AZ",
    "wof:name":"A White Orchid Flower Shop",
    "wof:placetype":"venue"
},
  "geometry": {"coordinates":[-112.265505,33.454428],"type":"Point"}
}