{
  "type": "Feature",
  "properties": {
    "iso:country":"US",
    "sg:address":"7741 W Cinnabar Ave",
    "sg:city":"Peoria",
    "sg:classifiers":[
        {
            "category":"Home & Garden",
            "subcategory":"Building Materials",
            "type":"Retail Goods"
        }
    ],
    "sg:phone":"+1 623 215 2163",
    "sg:postcode":"85345",
    "sg:province":"AZ",
    "sg:tags":[
        "door"
    ],
    "wof:name":"SOS Garage Doors",
    "wof:placetype":"venue"
},
  "geometry": {"coordinates":[-112.227024,33.576093],"type":"Point"}
}