{
  "type": "Feature",
  "properties": {
    "addr:full":"14075 N Fountain Hills Blvd Fountain Hills AZ 85268",
    "addr:housenumber":"14075",
    "addr:postcode":"85268",
    "addr:street":"N Fountain Hills Blvd",
    "iso:country":"US",
    "sg:address":"14075 N Fountain Hills Blvd",
    "sg:city":"Fountain Hills",
    "sg:classifiers":[
        {
            "category":"Professional",
            "subcategory":"Detective & Security Services",
            "type":"Services"
        }
    ],
    "sg:phone":"+1 480 391 1010",
    "sg:postcode":"85268",
    "sg:province":"AZ",
    "sg:tags":[
        "investigator"
    ],
    "wof:name":"Mate Check",
    "wof:placetype":"venue"
},
  "geometry": {"coordinates":[-111.72638499999999,33.61496],"type":"Point"}
}