{
  "type": "Feature",
  "properties": {
    "addr:full":"3400 E Sky Harbor Blvd Phoenix AZ 85034",
    "addr:housenumber":"3400",
    "addr:postcode":"85034",
    "addr:street":"E Sky Harbor Blvd",
    "iso:country":"US",
    "sg:address":"3400 E Sky Harbor Blvd",
    "sg:city":"Phoenix",
    "sg:classifiers":[
        {
            "category":"Restaurant",
            "type":"Food & Drink"
        }
    ],
    "sg:menulink":"http://www.allmenus.com/az/phoenix/217031-american-bandstand/menu/",
    "sg:phone":"0",
    "sg:postcode":"85034",
    "sg:province":"AZ",
    "sg:tags":[
        "american"
    ],
    "wof:name":"American Bandstand",
    "wof:placetype":"venue"
},
  "geometry": {"coordinates":[-112.00876700000001,33.435694],"type":"Point"}
}