{
  "type": "Feature",
  "properties": {
    "iso:country":"US",
    "sg:address":"2333 E Fry Blvd",
    "sg:city":"Sierra Vista",
    "sg:classifiers":[
        {
            "category":"Personal",
            "subcategory":"Beauty Salon",
            "type":"Services"
        }
    ],
    "sg:phone":"+1 520 459 5092",
    "sg:postcode":"85635",
    "sg:province":"AZ",
    "wof:name":"Smart Look",
    "wof:placetype":"venue"
},
  "geometry": {"coordinates":[-110.274062,31.554709],"type":"Point"}
}