{
  "type": "Feature",
  "properties": {
    "addr:full":"3861 E Baseline Rd Gilbert AZ 85234",
    "addr:housenumber":"3861",
    "addr:postcode":"85234",
    "addr:street":"E Baseline Rd",
    "iso:country":"US",
    "sg:address":"3861 E Baseline Rd",
    "sg:city":"Gilbert",
    "sg:classifiers":[
        {
            "category":"Bars & Pubs",
            "subcategory":"Sports Bar",
            "type":"Food & Drink"
        },
        {
            "category":"Restaurant",
            "type":"Food & Drink"
        }
    ],
    "sg:phone":"+1 480 558 7540",
    "sg:postcode":"85234",
    "sg:province":"AZ",
    "sg:website":"www.crabbydons.net/",
    "wof:name":"Crabby Don's Bar & Grill",
    "wof:placetype":"venue"
},
  "geometry": {"coordinates":[-111.74845999999999,33.379101],"type":"Point"}
}