{
  "type": "Feature",
  "properties": {
    "iso:country":"US",
    "sg:address":"3546 E Thomas Rd",
    "sg:city":"Phoenix",
    "sg:classifiers":[
        {
            "category":"Place Of Worship",
            "subcategory":"Church",
            "type":"Public Place"
        },
        {
            "category":"Place Of Worship",
            "type":"Public Place"
        }
    ],
    "sg:phone":"+1 602 956 1620",
    "sg:postcode":"85018",
    "sg:province":"AZ",
    "sg:tags":[
        "lutheran",
        "america",
        "churches-lutheran",
        "churches-lutheran-evangelical"
    ],
    "wof:name":"Mount Of Olives Lutheran Church Inc",
    "wof:placetype":"venue"
},
  "geometry": {"coordinates":[-112.005287,33.480469],"type":"Point"}
}