{
  "type": "Feature",
  "properties": {
    "addr:full":"5042 N Central Ave Phoenix AZ 85012",
    "addr:housenumber":"5042",
    "addr:postcode":"85012",
    "addr:street":"N Central Ave",
    "iso:country":"US",
    "sg:address":"5042 N Central Ave",
    "sg:city":"Phoenix",
    "sg:classifiers":[
        {
            "category":"Deli",
            "type":"Food & Drink"
        },
        {
            "category":"Food & Beverages",
            "subcategory":"Cheese",
            "type":"Retail Goods"
        },
        {
            "category":"Food & Beverages",
            "subcategory":"Specialty",
            "type":"Retail Goods"
        }
    ],
    "sg:phone":"+1 602 266 3636",
    "sg:postcode":"85012",
    "sg:province":"AZ",
    "sg:tags":[
        "gourmet",
        "shop",
        "delicatessen"
    ],
    "wof:name":"Cheese & Stuff",
    "wof:placetype":"venue"
},
  "geometry": {"coordinates":[-112.073742,33.510329],"type":"Point"}
}