{
  "type": "Feature",
  "properties": {
    "addr:full":"5540 E Broadway Rd Mesa AZ 85206",
    "addr:housenumber":"5540",
    "addr:postcode":"85206",
    "addr:street":"E Broadway Rd",
    "iso:country":"US",
    "sg:address":"5540 E Broadway Rd",
    "sg:city":"Mesa",
    "sg:classifiers":[
        {
            "category":"Personal",
            "subcategory":"Beauty Salon",
            "type":"Services"
        }
    ],
    "sg:phone":"+1 480 832 5231",
    "sg:postcode":"85206",
    "sg:province":"AZ",
    "wof:name":"Judy's Hair Designs",
    "wof:placetype":"venue"
},
  "geometry": {"coordinates":[-111.711082,33.408295],"type":"Point"}
}