{
  "type": "Feature",
  "properties": {
    "iso:country":"US",
    "sg:address":"3131 N Bentrup Cir",
    "sg:city":"Chandler",
    "sg:classifiers":[
        {
            "category":"Shopping",
            "subcategory":"Hobbies, Toys, & Games",
            "type":"Retail Goods"
        }
    ],
    "sg:phone":"+1 480 839 6797",
    "sg:postcode":"85224",
    "sg:province":"AZ",
    "wof:name":"Leon Brooks",
    "wof:placetype":"venue"
},
  "geometry": {"coordinates":[-111.891006,33.351826],"type":"Point"}
}