{
  "type": "Feature",
  "properties": {
    "iso:country":"US",
    "sg:address":"594 N Arizona Ave",
    "sg:city":"Chandler",
    "sg:classifiers":[
        {
            "category":"Wholesale",
            "subcategory":"Durable Goods & Equipment",
            "type":"Manufacturing & Wholesale Goods"
        }
    ],
    "sg:phone":"+1 480 857 4604",
    "sg:postcode":"85225",
    "sg:province":"AZ",
    "wof:name":"Triple T Gifts & Decor",
    "wof:placetype":"venue"
},
  "geometry": {"coordinates":[-111.841567,33.3126],"type":"Point"}
}