{
  "type": "Feature",
  "properties": {
    "addr:full":"811 E Freeman Pl Tucson AZ 85719",
    "addr:housenumber":"811",
    "addr:postcode":"85719",
    "addr:street":"E Freeman Pl",
    "iso:country":"US",
    "sg:address":"811 E Freeman Pl",
    "sg:city":"Tucson",
    "sg:classifiers":[
        {
            "category":"Building & Trades",
            "subcategory":"Construction",
            "type":"Services"
        }
    ],
    "sg:phone":"+1 520 293 6037",
    "sg:postcode":"85719",
    "sg:province":"AZ",
    "sg:tags":[
        "planning",
        "remodeling",
        "kitchen"
    ],
    "wof:name":"Artisitic Woodworks",
    "wof:placetype":"venue"
},
  "geometry": {"coordinates":[-110.95846400000001,32.268044],"type":"Point"}
}