{
  "type": "Feature",
  "properties": {
    "iso:country":"US",
    "sg:address":"6233 N 34th Dr",
    "sg:city":"Phoenix",
    "sg:classifiers":[
        {
            "category":"Restaurant",
            "type":"Food & Drink"
        }
    ],
    "sg:phone":"+1 602 547 1020",
    "sg:postcode":"85017",
    "sg:province":"AZ",
    "sg:tags":[
        "eating"
    ],
    "wof:name":"Panda Inn Restaurant",
    "wof:placetype":"venue"
},
  "geometry": {"coordinates":[-112.133145,33.52847],"type":"Point"}
}