{
  "type": "Feature",
  "properties": {
    "addr:full":"4801 E McKellips Rd Mesa AZ 85215",
    "addr:housenumber":"4801",
    "addr:postcode":"85215",
    "addr:street":"E Mckellips Rd",
    "iso:country":"US",
    "sg:address":"4801 E McKellips Rd",
    "sg:city":"Mesa",
    "sg:classifiers":[
        {
            "category":"Professional",
            "subcategory":"Management & Consulting",
            "type":"Services"
        }
    ],
    "sg:phone":"+1 480 985 7011",
    "sg:postcode":"85215",
    "sg:province":"AZ",
    "sg:tags":[
        "consultant",
        "business"
    ],
    "sg:website":"www.jefintl.com",
    "wof:name":"Jef International Inc",
    "wof:placetype":"venue"
},
  "geometry": {"coordinates":[-111.72324399999999,33.451772],"type":"Point"}
}