{
  "type": "Feature",
  "properties": {
    "iso:country":"US",
    "sg:address":"1695 Bronco Dr",
    "sg:city":"Camp Verde",
    "sg:classifiers":[
        {
            "category":"Building & Trades",
            "subcategory":"Construction",
            "type":"Services"
        }
    ],
    "sg:phone":"+1 928 567 5000",
    "sg:postcode":"86322",
    "sg:province":"AZ",
    "sg:tags":[
        "excavation",
        "work",
        "general",
        "contractor"
    ],
    "wof:name":"Ferguson Construction Company",
    "wof:placetype":"venue"
},
  "geometry": {"coordinates":[-111.884956,34.60936],"type":"Point"}
}