{
  "type": "Feature",
  "properties": {
    "iso:country":"US",
    "sg:address":"271 W Produce Row",
    "sg:city":"Nogales",
    "sg:classifiers":[
        {
            "category":"Professional",
            "subcategory":"Management & Consulting",
            "type":"Services"
        }
    ],
    "sg:phone":"+1 520 761 1654",
    "sg:postcode":"85621",
    "sg:province":"AZ",
    "sg:tags":[
        "food"
    ],
    "wof:name":"Arizona International Food",
    "wof:placetype":"venue"
},
  "geometry": {"coordinates":[-110.940841,31.378867],"type":"Point"}
}