{
  "type": "Feature",
  "properties": {
    "iso:country":"US",
    "sg:address":"6713 W Belmont Ave",
    "sg:city":"Glendale",
    "sg:classifiers":[
        {
            "category":"Retail",
            "subcategory":"Auto Repair",
            "type":"Services"
        }
    ],
    "sg:phone":"+1 623 915 0715",
    "sg:postcode":"85303",
    "sg:province":"AZ",
    "sg:tags":[
        "repairing",
        "automobile"
    ],
    "wof:name":"Aztec Auto",
    "wof:placetype":"venue"
},
  "geometry": {"coordinates":[-112.20727100000001,33.547645],"type":"Point"}
}