{
  "type": "Feature",
  "properties": {
    "addr:full":"2402 W Thomas Rd Phoenix AZ 85015",
    "addr:housenumber":"2402",
    "addr:postcode":"85015",
    "addr:street":"W Thomas Rd",
    "iso:country":"US",
    "sg:address":"2402 W Thomas Rd",
    "sg:city":"Phoenix",
    "sg:classifiers":[
        {
            "category":"Restaurant",
            "type":"Food & Drink"
        }
    ],
    "sg:menulink":"http://www.allmenus.com/az/phoenix/159830-arbys/menu/",
    "sg:phone":"+1 602 258 7112",
    "sg:postcode":"85015",
    "sg:province":"AZ",
    "sg:tags":[
        "burger",
        "american"
    ],
    "wof:name":"Arby's",
    "wof:placetype":"venue"
},
  "geometry": {"coordinates":[-112.110822,33.480622],"type":"Point"}
}