{
  "type": "Feature",
  "properties": {
    "iso:country":"US",
    "sg:address":"8273 W Union Hills Dr",
    "sg:city":"Glendale",
    "sg:classifiers":[
        {
            "category":"Restaurant",
            "type":"Food & Drink"
        }
    ],
    "sg:menulink":"http://www.allmenus.com/az/deer-valley/174032-wendys/menu/",
    "sg:phone":"+1 623 561 6827",
    "sg:postcode":"85308",
    "sg:province":"AZ",
    "sg:tags":[
        "burger",
        "american",
        "soup"
    ],
    "wof:name":"Wendy's",
    "wof:placetype":"venue"
},
  "geometry": {"coordinates":[-112.236014,33.652633],"type":"Point"}
}