{
  "type": "Feature",
  "properties": {
    "addr:full":"6242 N 59th Ave Glendale AZ 85301",
    "addr:housenumber":"6242",
    "addr:postcode":"85301",
    "addr:street":"N 59Th Ave",
    "iso:country":"US",
    "sg:address":"6242 N 59th Ave",
    "sg:city":"Glendale",
    "sg:classifiers":[
        {
            "category":"Organizations",
            "subcategory":"Community Association",
            "type":"Services"
        }
    ],
    "sg:phone":"+1 623 915 2263",
    "sg:postcode":"85301",
    "sg:province":"AZ",
    "wof:name":"Catholic Charities Community Services",
    "wof:placetype":"venue"
},
  "geometry": {"coordinates":[-112.186272,33.529079],"type":"Point"}
}