{
  "type": "Feature",
  "properties": {
    "addr:full":"6221 S Maple Avenue Tempe AZ 85283",
    "addr:housenumber":"6221",
    "addr:postcode":"85283",
    "addr:street":"S Maple Avenue",
    "iso:country":"US",
    "sg:address":"6221 S Maple Avenue",
    "sg:city":"Tempe",
    "sg:classifiers":[
        {
            "category":"Shopping",
            "subcategory":"Antiques",
            "type":"Retail Goods"
        }
    ],
    "sg:phone":"+1 480 820 5411",
    "sg:postcode":"85283",
    "sg:province":"AZ",
    "wof:name":"Antique Electronic Supply Limited Partnership",
    "wof:placetype":"venue"
},
  "geometry": {"coordinates":[-111.938501,33.365897],"type":"Point"}
}