{
  "type": "Feature",
  "properties": {
    "addr:full":"3930 E Ray Rd Phoenix AZ 85044",
    "addr:housenumber":"3930",
    "addr:postcode":"85044",
    "addr:street":"E Ray Rd",
    "iso:country":"US",
    "sg:address":"3930 E Ray Rd",
    "sg:city":"Phoenix",
    "sg:classifiers":[
        {
            "category":"Restaurant",
            "type":"Food & Drink"
        }
    ],
    "sg:menulink":"http://www.allmenus.com/az/phoenix/129030-subway/menu/",
    "sg:phone":"+1 480 705 8500",
    "sg:postcode":"85044",
    "sg:province":"AZ",
    "sg:tags":[
        "american",
        "sandwich"
    ],
    "wof:name":"Subway",
    "wof:placetype":"venue"
},
  "geometry": {"coordinates":[-112.001197,33.31829],"type":"Point"}
}