{
  "type": "Feature",
  "properties": {
    "iso:country":"US",
    "sg:address":"407 W Frontier St",
    "sg:city":"Payson",
    "sg:classifiers":[
        {
            "category":"Personal",
            "type":"Services"
        }
    ],
    "sg:phone":"+1 928 468 8897",
    "sg:postcode":"85541",
    "sg:province":"AZ",
    "sg:tags":[
        "therapist",
        "massage"
    ],
    "wof:name":"A Simple Touch",
    "wof:placetype":"venue"
},
  "geometry": {"coordinates":[-111.33041900000001,34.232126],"type":"Point"}
}