{
  "type": "Feature",
  "properties": {
    "addr:full":"6210 S 26th St Phoenix AZ 85042",
    "addr:housenumber":"6210",
    "addr:postcode":"85042",
    "addr:street":"S 26Th St",
    "iso:country":"US",
    "sg:address":"6210 S 26th St",
    "sg:city":"Phoenix",
    "sg:classifiers":[
        {
            "category":"Wholesale",
            "subcategory":"Plants",
            "type":"Manufacturing & Wholesale Goods"
        },
        {
            "category":"Farming",
            "subcategory":"Nursery",
            "type":"Manufacturing & Wholesale Goods"
        }
    ],
    "sg:phone":"+1 602 243 6797",
    "sg:postcode":"85042",
    "sg:province":"AZ",
    "sg:tags":[
        "ornamental",
        "tree",
        "supply"
    ],
    "wof:name":"Dean's Greens",
    "wof:placetype":"venue"
},
  "geometry": {"coordinates":[-112.02582700000001,33.391288],"type":"Point"}
}