{
  "type": "Feature",
  "properties": {
    "addr:full":"12001 W Peoria Ave El Mirage AZ 85335",
    "addr:housenumber":"12001",
    "addr:postcode":"85335",
    "addr:street":"W Peoria Ave",
    "iso:country":"US",
    "sg:address":"12001 W Peoria Ave",
    "sg:city":"El Mirage",
    "sg:classifiers":[
        {
            "category":"Utilities",
            "subcategory":"Refuse",
            "type":"Services"
        }
    ],
    "sg:phone":"+1 623 536 1015",
    "sg:postcode":"85335",
    "sg:province":"AZ",
    "sg:tags":[
        "garbage",
        "system",
        "collection"
    ],
    "wof:name":"Auerbach Waste",
    "wof:placetype":"venue"
},
  "geometry": {"coordinates":[-112.320348,33.579889],"type":"Point"}
}