{
  "type": "Feature",
  "properties": {
    "iso:country":"US",
    "sg:address":"15425 N Greenway Hayden Loop",
    "sg:city":"Scottsdale",
    "sg:classifiers":[
        {
            "category":"Health Services",
            "subcategory":"Health Practitioner",
            "type":"Services"
        }
    ],
    "sg:phone":"+1 480 998 2580",
    "sg:postcode":"85260",
    "sg:province":"AZ",
    "sg:tags":[
        "therapist",
        "physical"
    ],
    "wof:name":"RPN",
    "wof:placetype":"venue"
},
  "geometry": {"coordinates":[-111.924823,33.62571],"type":"Point"}
}