{
  "type": "Feature",
  "properties": {
    "addr:full":"6840 N Taylor Ln Tucson AZ 85743",
    "addr:housenumber":"6840",
    "addr:postcode":"85743",
    "addr:street":"N Taylor Ln",
    "iso:country":"US",
    "sg:address":"6840 N Taylor Ln",
    "sg:city":"Tucson",
    "sg:classifiers":[
        {
            "category":"Building & Trades",
            "subcategory":"Electrical",
            "type":"Services"
        }
    ],
    "sg:phone":"+1 520 682 7935",
    "sg:postcode":"85743",
    "sg:province":"AZ",
    "sg:tags":[
        "electrical",
        "contractor"
    ],
    "wof:name":"Mesquite Electric",
    "wof:placetype":"venue"
},
  "geometry": {"coordinates":[-111.226671,32.331696],"type":"Point"}
}