{
  "type": "Feature",
  "properties": {
    "iso:country":"US",
    "sg:address":"6812 E Thomas Rd",
    "sg:city":"Scottsdale",
    "sg:classifiers":[
        {
            "category":"Retail",
            "subcategory":"Funeral Services",
            "type":"Services"
        }
    ],
    "sg:phone":"+1 480 945 4440",
    "sg:postcode":"85251",
    "sg:province":"AZ",
    "sg:tags":[
        "director"
    ],
    "wof:name":"Life-Paths By Bunker Family",
    "wof:placetype":"venue"
},
  "geometry": {"coordinates":[-111.93485200000001,33.480346],"type":"Point"}
}