{
  "type": "Feature",
  "properties": {
    "iso:country":"US",
    "sg:address":"4817 E 5th St",
    "sg:city":"Tucson",
    "sg:classifiers":[
        {
            "category":"Real Estate",
            "subcategory":"Real Estate Agent",
            "type":"Services"
        }
    ],
    "sg:phone":"+1 520 320 5503",
    "sg:postcode":"85711",
    "sg:province":"AZ",
    "sg:tags":[
        "manager"
    ],
    "wof:name":"Centra Realty LLC",
    "wof:placetype":"venue"
},
  "geometry": {"coordinates":[-110.890462,32.228923],"type":"Point"}
}