{
  "type": "Feature",
  "properties": {
    "iso:country":"US",
    "sg:address":"2816 N 27th Ave",
    "sg:city":"Phoenix",
    "sg:classifiers":[
        {
            "category":"Building & Trades",
            "subcategory":"Equipment Rental",
            "type":"Services"
        }
    ],
    "sg:phone":"+1 602 233 0205",
    "sg:postcode":"85009",
    "sg:province":"AZ",
    "sg:tags":[
        "cranes-renting",
        "forklift",
        "leasing",
        "trucks-rental"
    ],
    "wof:name":"Bragg Crane Service",
    "wof:placetype":"venue"
},
  "geometry": {"coordinates":[-112.117073,33.479045],"type":"Point"}
}