{
  "type": "Feature",
  "properties": {
    "addr:full":"5568 N Cam de la Tierra Tucson AZ 85705",
    "addr:housenumber":"5568",
    "addr:postcode":"85705",
    "addr:street":"N Cam De La Tierra",
    "iso:country":"US",
    "sg:address":"5568 N Cam de la Tierra",
    "sg:city":"Tucson",
    "sg:classifiers":[
        {
            "category":"Retail",
            "subcategory":"Auto Repair",
            "type":"Services"
        }
    ],
    "sg:phone":"+1 520 744 1867",
    "sg:postcode":"85705",
    "sg:province":"AZ",
    "sg:tags":[
        "wrecker"
    ],
    "wof:name":"B & C Towing & Recovery",
    "wof:placetype":"venue"
},
  "geometry": {"coordinates":[-111.03731399999999,32.307805],"type":"Point"}
}