{
  "type": "Feature",
  "properties": {
    "iso:country":"US",
    "sg:address":"2020 S McClintock Dr",
    "sg:city":"Tempe",
    "sg:classifiers":[
        {
            "category":"Building & Trades",
            "subcategory":"Landscaping Services",
            "type":"Services"
        }
    ],
    "sg:phone":"+1 480 985 7777",
    "sg:postcode":"85281",
    "sg:province":"AZ",
    "sg:tags":[
        "landscape",
        "contractor"
    ],
    "wof:name":"Pdi Landscape Development",
    "wof:placetype":"venue"
},
  "geometry": {"coordinates":[-111.90918000000001,33.406754],"type":"Point"}
}