{
  "type": "Feature",
  "properties": {
    "iso:country":"US",
    "sg:address":"6145 N 99th Ave",
    "sg:city":"Glendale",
    "sg:classifiers":[
        {
            "category":"Professional",
            "type":"Services"
        }
    ],
    "sg:phone":"+1 623 872 8036",
    "sg:postcode":"85305",
    "sg:province":"AZ",
    "wof:name":"Conrad F Gingg",
    "wof:placetype":"venue"
},
  "geometry": {"coordinates":[-112.272313,33.522854],"type":"Point"}
}