{
  "type": "Feature",
  "properties": {
    "iso:country":"US",
    "sg:address":"6410 N 82nd Way",
    "sg:city":"Scottsdale",
    "sg:classifiers":[
        {
            "category":"Wholesale",
            "subcategory":"Construction Materials",
            "type":"Manufacturing & Wholesale Goods"
        }
    ],
    "sg:phone":"+1 602 274 4677",
    "sg:postcode":"85250",
    "sg:province":"AZ",
    "wof:name":"Dobbins Southwest Incorporated",
    "wof:placetype":"venue"
},
  "geometry": {"coordinates":[-111.903478,33.530186],"type":"Point"}
}