{
  "type": "Feature",
  "properties": {
    "iso:country":"US",
    "sg:address":"5115 N Dysart Rd",
    "sg:city":"Litchfield Park",
    "sg:classifiers":[
        {
            "category":"Shopping",
            "type":"Retail Goods"
        }
    ],
    "sg:phone":"+1 623 535 9080",
    "sg:postcode":"85340",
    "sg:province":"AZ",
    "sg:tags":[
        "merchandise"
    ],
    "wof:name":"Contours Express",
    "wof:placetype":"venue"
},
  "geometry": {"coordinates":[-112.340837,33.510219],"type":"Point"}
}