{
  "type": "Feature",
  "properties": {
    "iso:country":"US",
    "sg:address":"3823 W Yorkshire Dr",
    "sg:city":"Glendale",
    "sg:classifiers":[
        {
            "category":"Professional",
            "subcategory":"Accounting & Tax Preparation",
            "type":"Services"
        }
    ],
    "sg:phone":"+1 623 210 5045",
    "sg:postcode":"85308",
    "sg:province":"AZ",
    "sg:tags":[
        "bookkeeping",
        "billing"
    ],
    "wof:name":"Ktm Bookkeeping Services",
    "wof:placetype":"venue"
},
  "geometry": {"coordinates":[-112.141583,33.661916],"type":"Point"}
}