{
  "type": "Feature",
  "properties": {
    "addr:full":"525 E Dunlap Ave Phoenix AZ 85020",
    "addr:housenumber":"525",
    "addr:postcode":"85020",
    "addr:street":"E Dunlap Ave",
    "iso:country":"US",
    "sg:address":"525 E Dunlap Ave",
    "sg:city":"Phoenix",
    "sg:classifiers":[
        {
            "category":"Retail",
            "subcategory":"Auto Repair",
            "type":"Services"
        }
    ],
    "sg:phone":"+1 602 997 6341",
    "sg:postcode":"85020",
    "sg:province":"AZ",
    "sg:tags":[
        "body",
        "automobile",
        "painting"
    ],
    "wof:name":"Innovative Auto Creations",
    "wof:placetype":"venue"
},
  "geometry": {"coordinates":[-112.06571,33.567766],"type":"Point"}
}