{
  "type": "Feature",
  "properties": {
    "addr:full":"521 E Western Ave Avondale AZ 85323",
    "addr:housenumber":"521",
    "addr:postcode":"85323",
    "addr:street":"E Western Ave",
    "iso:country":"US",
    "sg:address":"521 E Western Ave",
    "sg:city":"Avondale",
    "sg:classifiers":[
        {
            "category":"Government",
            "subcategory":"Court House",
            "type":"Public Place"
        }
    ],
    "sg:phone":"+1 623 478 3120",
    "sg:postcode":"85323",
    "sg:province":"AZ",
    "sg:tags":[
        "city"
    ],
    "wof:name":"Avondale Magistrate Court",
    "wof:placetype":"venue"
},
  "geometry": {"coordinates":[-112.344075,33.435254],"type":"Point"}
}