{
  "type": "Feature",
  "properties": {
    "iso:country":"US",
    "sg:address":"3902 E Union Hills Dr",
    "sg:city":"Phoenix",
    "sg:classifiers":[
        {
            "category":"Organizations",
            "subcategory":"Religious Organization",
            "type":"Services"
        }
    ],
    "sg:phone":"+1 623 582 4515",
    "sg:postcode":"85050",
    "sg:province":"AZ",
    "sg:tags":[
        "church"
    ],
    "wof:name":"God's House-Worship Baptist",
    "wof:placetype":"venue"
},
  "geometry": {"coordinates":[-111.99859600000001,33.655291],"type":"Point"}
}