{
  "type": "Feature",
  "properties": {
    "iso:country":"US",
    "sg:address":"5930 S Sossaman Rd",
    "sg:city":"Mesa",
    "sg:classifiers":[
        {
            "category":"Education",
            "subcategory":"College",
            "type":"Public Place"
        }
    ],
    "sg:phone":"+1 480 279 1150",
    "sg:postcode":"85212",
    "sg:province":"AZ",
    "sg:tags":[
        "academic",
        "school"
    ],
    "sg:website":"www.erau.edu",
    "wof:name":"Embry-Riddle Aeronautical Univ",
    "wof:placetype":"venue"
},
  "geometry": {"coordinates":[-111.670174,33.308233],"type":"Point"}
}