{
  "type": "Feature",
  "properties": {
    "iso:country":"US",
    "sg:address":"1401 E Bell Rd",
    "sg:city":"Phoenix",
    "sg:classifiers":[
        {
            "category":"Restaurant",
            "type":"Food & Drink"
        }
    ],
    "sg:phone":"+1 602 942 0644",
    "sg:postcode":"85022",
    "sg:province":"AZ",
    "sg:tags":[
        "seafood"
    ],
    "wof:name":"Whale & Ale",
    "wof:placetype":"venue"
},
  "geometry": {"coordinates":[-112.050485,33.640387],"type":"Point"}
}