{
  "type": "Feature",
  "properties": {
    "iso:country":"US",
    "sg:address":"5741 W Paradise Ln",
    "sg:city":"Glendale",
    "sg:classifiers":[
        {
            "category":"Professional",
            "subcategory":"Business Services",
            "type":"Services"
        }
    ],
    "sg:phone":"+1 602 439 8897",
    "sg:postcode":"85306",
    "sg:province":"AZ",
    "sg:tags":[
        "painter",
        "sign"
    ],
    "wof:name":"Ed Young Lettering",
    "wof:placetype":"venue"
},
  "geometry": {"coordinates":[-112.184789,33.632309],"type":"Point"}
}