{
  "type": "Feature",
  "properties": {
    "iso:country":"US",
    "sg:address":"78 E University Dr",
    "sg:city":"Mesa",
    "sg:classifiers":[
        {
            "category":"Building & Trades",
            "subcategory":"Construction",
            "type":"Services"
        }
    ],
    "sg:phone":"+1 480 733 6313",
    "sg:postcode":"85201",
    "sg:province":"AZ",
    "sg:tags":[
        "floor",
        "covering",
        "rug",
        "contractor",
        "tile",
        "carpet"
    ],
    "wof:name":"Indigo Carpet & Tile",
    "wof:placetype":"venue"
},
  "geometry": {"coordinates":[-111.829142,33.422334],"type":"Point"}
}