{
  "type": "Feature",
  "properties": {
    "iso:country":"US",
    "sg:address":"13555 W McDowell Rd Ste 206",
    "sg:city":"Goodyear",
    "sg:classifiers":[
        {
            "category":"Health Services",
            "subcategory":"Doctor",
            "type":"Services"
        }
    ],
    "sg:phone":"+1 623 935 6452",
    "sg:postcode":"85395",
    "sg:province":"AZ",
    "wof:name":"Arizona Cardiology Group PC",
    "wof:placetype":"venue"
},
  "geometry": {"coordinates":[-112.35122800000001,33.463502],"type":"Point"}
}