{
  "type": "Feature",
  "properties": {
    "iso:country":"US",
    "sg:address":"4000 W Grant St",
    "sg:city":"Phoenix",
    "sg:classifiers":[
        {
            "category":"Freight",
            "type":"Transportation"
        }
    ],
    "sg:phone":"+1 602 799 2109",
    "sg:postcode":"85009",
    "sg:province":"AZ",
    "sg:tags":[
        "operator",
        "trucking"
    ],
    "wof:name":"Cobra Trucking Inc",
    "wof:placetype":"venue"
},
  "geometry": {"coordinates":[-112.147493,33.441848],"type":"Point"}
}