{
  "type": "Feature",
  "properties": {
    "addr:full":"7090 N Oracle Rd Tucson AZ 85704",
    "addr:housenumber":"7090",
    "addr:postcode":"85704",
    "addr:street":"N Oracle Rd",
    "iso:country":"US",
    "sg:address":"7090 N Oracle Rd",
    "sg:city":"Tucson",
    "sg:classifiers":[
        {
            "category":"Ice Cream",
            "type":"Food & Drink"
        }
    ],
    "sg:menulink":"http://www.allmenus.com/az/tucson/183757-cold-stone-creamery/menu/",
    "sg:phone":"+1 520 297 6522",
    "sg:postcode":"85704",
    "sg:province":"AZ",
    "sg:tags":[
        "smoothy",
        "juice",
        "american"
    ],
    "wof:name":"Cold Stone Creamery",
    "wof:placetype":"venue"
},
  "geometry": {"coordinates":[-110.97576599999999,32.335433],"type":"Point"}
}