{
  "type": "Feature",
  "properties": {
    "addr:full":"4712 E Virginia Ave Phoenix AZ 85008",
    "addr:housenumber":"4712",
    "addr:postcode":"85008",
    "addr:street":"E Virginia Ave",
    "iso:country":"US",
    "sg:address":"4712 E Virginia Ave",
    "sg:city":"Phoenix",
    "sg:classifiers":[
        {
            "category":"Building & Trades",
            "subcategory":"Construction",
            "type":"Services"
        }
    ],
    "sg:phone":"+1 480 981 8712",
    "sg:postcode":"85008",
    "sg:province":"AZ",
    "sg:tags":[
        "maker",
        "cabinet"
    ],
    "wof:name":"Sawmill Custom Cabinets",
    "wof:placetype":"venue"
},
  "geometry": {"coordinates":[-111.98043199999999,33.476495],"type":"Point"}
}