{
  "type": "Feature",
  "properties": {
    "iso:country":"US",
    "sg:address":"305 S 2nd Ave",
    "sg:city":"Yuma",
    "sg:classifiers":[
        {
            "category":"Professional",
            "subcategory":"Lawyer & Legal Services",
            "type":"Services"
        }
    ],
    "sg:phone":"+1 928 782 7511",
    "sg:postcode":"85364",
    "sg:province":"AZ",
    "sg:tags":[
        "attorney",
        "plan"
    ],
    "wof:name":"Community Legal Services",
    "wof:placetype":"venue"
},
  "geometry": {"coordinates":[-114.622101,32.721388],"type":"Point"}
}