{
  "type": "Feature",
  "properties": {
    "addr:full":"65 Coffee Pot Dr Sedona AZ 86336",
    "addr:housenumber":"65",
    "addr:postcode":"86336",
    "addr:street":"Coffee Pot Dr",
    "iso:country":"US",
    "sg:address":"65 Coffee Pot Dr",
    "sg:city":"Sedona",
    "sg:classifiers":[
        {
            "category":"Utilities",
            "subcategory":"Cable",
            "type":"Services"
        }
    ],
    "sg:phone":"+1 928 282 7711",
    "sg:postcode":"86336",
    "sg:province":"AZ",
    "sg:tags":[
        "television"
    ],
    "wof:name":"Cablevision",
    "wof:placetype":"venue"
},
  "geometry": {"coordinates":[-111.795466,34.863985],"type":"Point"}
}