{
  "type": "Feature",
  "properties": {
    "iso:country":"US",
    "sg:address":"2306 W Sherman St",
    "sg:city":"Phoenix",
    "sg:classifiers":[
        {
            "category":"Manufacturing",
            "subcategory":"Tools & Machinery",
            "type":"Manufacturing & Wholesale Goods"
        }
    ],
    "sg:phone":"+1 602 252 2029",
    "sg:postcode":"85009",
    "sg:province":"AZ",
    "sg:tags":[
        "equipment",
        "lighting",
        "commercial",
        "fixture",
        "mfg"
    ],
    "wof:name":"Moonlighting Inc",
    "wof:placetype":"venue"
},
  "geometry": {"coordinates":[-112.112948,33.440665],"type":"Point"}
}