{
  "type": "Feature",
  "properties": {
    "iso:country":"US",
    "sg:address":"5085 Sherwood Dr",
    "sg:city":"Lakeside",
    "sg:classifiers":[
        {
            "category":"Manufacturing",
            "subcategory":"Buildings",
            "type":"Manufacturing & Wholesale Goods"
        },
        {
            "category":"Building & Trades",
            "subcategory":"Construction",
            "type":"Services"
        }
    ],
    "sg:phone":"+1 928 532 0232",
    "sg:postcode":"85929",
    "sg:province":"AZ",
    "sg:tags":[
        "home",
        "builder",
        "contractor"
    ],
    "wof:name":"Langteau Construction Co",
    "wof:placetype":"venue"
},
  "geometry": {"coordinates":[-110.010644,34.186163],"type":"Point"}
}