{
  "type": "Feature",
  "properties": {
    "iso:country":"US",
    "sg:address":"3303 Park Ridge Ave",
    "sg:city":"Bullhead City",
    "sg:classifiers":[
        {
            "category":"Wholesale",
            "subcategory":"Hardware",
            "type":"Manufacturing & Wholesale Goods"
        }
    ],
    "sg:phone":"+1 928 754 4037",
    "sg:postcode":"86429",
    "sg:province":"AZ",
    "wof:name":"Randall & Co",
    "wof:placetype":"venue"
},
  "geometry": {"coordinates":[-114.54618,35.179141],"type":"Point"}
}