{
  "type": "Feature",
  "properties": {
    "addr:full":"22230 N 24th Ave Phoenix AZ 85027",
    "addr:housenumber":"22230",
    "addr:postcode":"85027",
    "addr:street":"N 24Th Ave",
    "iso:country":"US",
    "sg:address":"22230 N 24th Ave",
    "sg:city":"Phoenix",
    "sg:classifiers":[
        {
            "category":"Retail",
            "subcategory":"Auto Repair",
            "type":"Services"
        }
    ],
    "sg:phone":"+1 623 445 0208",
    "sg:postcode":"85027",
    "sg:province":"AZ",
    "sg:tags":[
        "repairing",
        "automobile"
    ],
    "wof:name":"Ray's Auto Repair",
    "wof:placetype":"venue"
},
  "geometry": {"coordinates":[-112.110071,33.688782],"type":"Point"}
}