{
  "type": "Feature",
  "properties": {
    "iso:country":"US",
    "sg:address":"3000 W Ironwood Hill Dr",
    "sg:city":"Tucson",
    "sg:classifiers":[
        {
            "category":"Social Services",
            "type":"Services"
        }
    ],
    "sg:phone":"+1 520 743 4500",
    "sg:postcode":"85745",
    "sg:province":"AZ",
    "sg:tags":[
        "restoration",
        "disaster",
        "emergency"
    ],
    "wof:name":"Emergency Restoration Experts",
    "wof:placetype":"venue"
},
  "geometry": {"coordinates":[-111.03068,32.250774],"type":"Point"}
}