{
  "type": "Feature",
  "properties": {
    "iso:country":"US",
    "sg:address":"812 W Lindner Ave",
    "sg:city":"Mesa",
    "sg:classifiers":[
        {
            "category":"Professional",
            "subcategory":"Computer Services",
            "type":"Services"
        }
    ],
    "sg:phone":"+1 480 827 0935",
    "sg:postcode":"85210",
    "sg:province":"AZ",
    "sg:tags":[
        "repair"
    ],
    "sg:website":"www.ervs.com",
    "wof:name":"Erv's Monitor Svc",
    "wof:placetype":"venue"
},
  "geometry": {"coordinates":[-111.8505,33.37686],"type":"Point"}
}