{
  "type": "Feature",
  "properties": {
    "addr:full":"15612 W Frontier Dr Surprise AZ 85387",
    "addr:housenumber":"15612",
    "addr:postcode":"85387",
    "addr:street":"W Frontier Dr",
    "iso:country":"US",
    "sg:address":"15612 W Frontier Dr",
    "sg:city":"Surprise",
    "sg:classifiers":[
        {
            "category":"Real Estate",
            "subcategory":"Real Estate Agent",
            "type":"Services"
        }
    ],
    "sg:phone":"+1 623 584 1276",
    "sg:postcode":"85387",
    "sg:province":"AZ",
    "wof:name":"Amy Gelley",
    "wof:placetype":"venue"
},
  "geometry": {"coordinates":[-112.396776,33.718518],"type":"Point"}
}