{
  "type": "Feature",
  "properties": {
    "addr:full":"9280 S Kyrene Rd Tempe AZ 85283",
    "addr:housenumber":"9280",
    "addr:postcode":"85283",
    "addr:street":"S Kyrene Rd",
    "iso:country":"US",
    "sg:address":"9280 S Kyrene Rd",
    "sg:city":"Tempe",
    "sg:classifiers":[
        {
            "category":"Professional",
            "subcategory":"Lawyer & Legal Services",
            "type":"Services"
        }
    ],
    "sg:phone":"+1 480 753 5888",
    "sg:postcode":"85283",
    "sg:province":"AZ",
    "sg:tags":[
        "attorney"
    ],
    "wof:name":"Craig W Penrod Law Offices",
    "wof:placetype":"venue"
},
  "geometry": {"coordinates":[-111.94572599999999,33.330701],"type":"Point"}
}