{
  "type": "Feature",
  "properties": {
    "iso:country":"US",
    "sg:address":"3015 S 40th St",
    "sg:city":"Phoenix",
    "sg:classifiers":[
        {
            "category":"Real Estate",
            "subcategory":"Real Estate Agent",
            "type":"Services"
        }
    ],
    "sg:phone":"+1 602 437 9777",
    "sg:postcode":"85040",
    "sg:province":"AZ",
    "sg:tags":[
        "investment"
    ],
    "wof:name":"Rick Hall",
    "wof:placetype":"venue"
},
  "geometry": {"coordinates":[-111.995365,33.419779],"type":"Point"}
}