{
  "type": "Feature",
  "properties": {
    "iso:country":"US",
    "sg:address":"4596 E Broadway Blvd",
    "sg:city":"Tucson",
    "sg:classifiers":[
        {
            "category":"Autos & Motor Vehicles",
            "subcategory":"Auto Supplies",
            "type":"Retail Goods"
        }
    ],
    "sg:phone":"+1 520 795 1111",
    "sg:postcode":"85711",
    "sg:province":"AZ",
    "sg:tags":[
        "unit",
        "conditioning",
        "install",
        "air"
    ],
    "wof:name":"Arizona Auto Refrigeration",
    "wof:placetype":"venue"
},
  "geometry": {"coordinates":[-110.896472,32.22143],"type":"Point"}
}