{
  "type": "Feature",
  "properties": {
    "iso:country":"US",
    "sg:address":"1825 E Guadalupe Rd",
    "sg:city":"Tempe",
    "sg:classifiers":[
        {
            "category":"Personal",
            "subcategory":"Beauty Salon",
            "type":"Services"
        }
    ],
    "sg:phone":"+1 480 775 1264",
    "sg:postcode":"85283",
    "sg:province":"AZ",
    "wof:name":"Hair Artz",
    "wof:placetype":"venue"
},
  "geometry": {"coordinates":[-111.907569,33.363697],"type":"Point"}
}