{
  "type": "Feature",
  "properties": {
    "addr:full":"13001 W Apodaca Dr Litchfield Park AZ 85340",
    "addr:housenumber":"13001",
    "addr:postcode":"85340",
    "addr:street":"W Apodaca Dr",
    "iso:country":"US",
    "sg:address":"13001 W Apodaca Dr",
    "sg:city":"Litchfield Park",
    "sg:classifiers":[
        {
            "category":"Building & Trades",
            "subcategory":"Construction",
            "type":"Services"
        }
    ],
    "sg:phone":"+1 623 561 8586",
    "sg:postcode":"85340",
    "sg:province":"AZ",
    "sg:tags":[
        "concrete",
        "contractor"
    ],
    "wof:name":"Elite Concrete Coating",
    "wof:placetype":"venue"
},
  "geometry": {"coordinates":[-112.338829,33.497414],"type":"Point"}
}