{
  "type": "Feature",
  "properties": {
    "iso:country":"US",
    "sg:address":"3220 S Fair Ln",
    "sg:city":"Tempe",
    "sg:classifiers":[
        {
            "category":"Professional",
            "subcategory":"Secretarial Services",
            "type":"Services"
        }
    ],
    "sg:phone":"+1 602 437 7277",
    "sg:postcode":"85282",
    "sg:province":"AZ",
    "sg:tags":[
        "preparation",
        "document"
    ],
    "wof:name":"Attach Plus",
    "wof:placetype":"venue"
},
  "geometry": {"coordinates":[-111.976067,33.393102],"type":"Point"}
}