{
  "type": "Feature",
  "properties": {
    "iso:country":"US",
    "sg:address":"1405 W 16th St",
    "sg:city":"Yuma",
    "sg:classifiers":[
        {
            "category":"Farming",
            "subcategory":"Farm",
            "type":"Manufacturing & Wholesale Goods"
        }
    ],
    "sg:phone":"+1 928 783 7204",
    "sg:postcode":"85364",
    "sg:province":"AZ",
    "sg:tags":[
        "food",
        "covered",
        "crop"
    ],
    "wof:name":"Syngenta Seeds Inc",
    "wof:placetype":"venue"
},
  "geometry": {"coordinates":[-114.639084,32.698412],"type":"Point"}
}