{
  "type": "Feature",
  "properties": {
    "iso:country":"US",
    "sg:address":"5202 N Central Ave",
    "sg:city":"Phoenix",
    "sg:classifiers":[
        {
            "category":"Restaurant",
            "type":"Food & Drink"
        },
        {
            "category":"Food & Beverages",
            "subcategory":"Bakery",
            "type":"Retail Goods"
        }
    ],
    "sg:menulink":"http://www.allmenus.com/az/phoenix/4426-panino-on-central/menu/",
    "sg:phone":"+1 602 336 1198",
    "sg:postcode":"85012",
    "sg:province":"AZ",
    "sg:tags":[
        "italian"
    ],
    "wof:name":"Panino on Central",
    "wof:placetype":"venue"
},
  "geometry": {"coordinates":[-112.07373,33.513206],"type":"Point"}
}