{
  "type": "Feature",
  "properties": {
    "iso:country":"US",
    "sg:address":"2828 W Whitman Ct",
    "sg:city":"Anthem",
    "sg:classifiers":[
        {
            "category":"Professional",
            "subcategory":"Lawyer & Legal Services",
            "type":"Services"
        }
    ],
    "sg:phone":"+1 623 551 5530",
    "sg:postcode":"85086",
    "sg:province":"AZ",
    "sg:tags":[
        "plan"
    ],
    "wof:name":"Chunn & Assoc",
    "wof:placetype":"venue"
},
  "geometry": {"coordinates":[-112.12062899999999,33.856841],"type":"Point"}
}