{
  "type": "Feature",
  "properties": {
    "iso:country":"US",
    "sg:address":"2255 W Orange Grove Rd",
    "sg:city":"Tucson",
    "sg:classifiers":[
        {
            "category":"Real Estate",
            "subcategory":"Real Estate Agent",
            "type":"Services"
        }
    ],
    "sg:phone":"+1 877 523 5195",
    "sg:postcode":"85741",
    "sg:province":"AZ",
    "sg:tags":[
        "finding",
        "apartment",
        "rental"
    ],
    "sg:website":"http://local.ingenio.com/Listings/Details.aspx?NUM=a%3a10248954%3a13%3a4859924%3a14%3a0%3a7",
    "wof:name":"Palm Canyon",
    "wof:placetype":"venue"
},
  "geometry": {"coordinates":[-111.015253,32.323151],"type":"Point"}
}