{
  "type": "Feature",
  "properties": {
    "iso:country":"US",
    "sg:address":"1515 E Osborn Rd",
    "sg:city":"Phoenix",
    "sg:classifiers":[
        {
            "category":"Government",
            "subcategory":"Office",
            "type":"Public Place"
        }
    ],
    "sg:phone":"+1 602 239 4149",
    "sg:postcode":"85014",
    "sg:province":"AZ",
    "sg:tags":[
        "state",
        "program",
        "health"
    ],
    "wof:name":"Health Fair",
    "wof:placetype":"venue"
},
  "geometry": {"coordinates":[-112.047881,33.487349],"type":"Point"}
}