{
  "type": "Feature",
  "properties": {
    "addr:full":"167 S Stapley Dr Mesa AZ 85204",
    "addr:housenumber":"167",
    "addr:postcode":"85204",
    "addr:street":"S Stapley Dr",
    "iso:country":"US",
    "sg:address":"167 S Stapley Dr",
    "sg:city":"Mesa",
    "sg:classifiers":[
        {
            "category":"Government",
            "subcategory":"Post Office",
            "type":"Public Place"
        }
    ],
    "sg:phone":"+1 480 844 3912",
    "sg:postcode":"85204",
    "sg:province":"AZ",
    "wof:name":"US Post Office",
    "wof:placetype":"venue"
},
  "geometry": {"coordinates":[-111.805245,33.411834],"type":"Point"}
}