{
  "type": "Feature",
  "properties": {
    "iso:country":"US",
    "sg:address":"13034 N Hayden Rd",
    "sg:city":"Scottsdale",
    "sg:classifiers":[
        {
            "category":"Building & Trades",
            "subcategory":"Construction",
            "type":"Services"
        }
    ],
    "sg:phone":"+1 480 948 6267",
    "sg:postcode":"85260",
    "sg:province":"AZ",
    "sg:tags":[
        "concrete",
        "contractor"
    ],
    "wof:name":"All Phase Contracting",
    "wof:placetype":"venue"
},
  "geometry": {"coordinates":[-111.908635,33.605579],"type":"Point"}
}