{
  "type": "Feature",
  "properties": {
    "addr:full":"762 N Palo Verde Mesa AZ 85207",
    "addr:housenumber":"762",
    "addr:postcode":"85207",
    "addr:street":"N",
    "iso:country":"US",
    "sg:address":"762 N Palo Verde",
    "sg:city":"Mesa",
    "sg:classifiers":[
        {
            "category":"Social Services",
            "subcategory":"Adult Care",
            "type":"Services"
        }
    ],
    "sg:phone":"+1 480 984 5480",
    "sg:postcode":"85207",
    "sg:province":"AZ",
    "sg:tags":[
        "home",
        "residential"
    ],
    "wof:name":"Palo Verde Care Home",
    "wof:placetype":"venue"
},
  "geometry": {"coordinates":[-111.664103,33.428901],"type":"Point"}
}