{
  "type": "Feature",
  "properties": {
    "iso:country":"US",
    "sg:address":"151 S 21st Ave",
    "sg:city":"Yuma",
    "sg:classifiers":[
        {
            "category":"Building & Trades",
            "subcategory":"Construction",
            "type":"Services"
        }
    ],
    "sg:phone":"+1 928 783 2906",
    "sg:postcode":"85364",
    "sg:province":"AZ",
    "sg:tags":[
        "residential"
    ],
    "wof:name":"Landview Construction LLC",
    "wof:placetype":"venue"
},
  "geometry": {"coordinates":[-114.64551,32.723798],"type":"Point"}
}