{
  "type": "Feature",
  "properties": {
    "iso:country":"US",
    "sg:address":"5015 N 7th Ave",
    "sg:city":"Phoenix",
    "sg:classifiers":[
        {
            "category":"Professional",
            "subcategory":"Lawyer & Legal Services",
            "type":"Services"
        }
    ],
    "sg:phone":"+1 602 264 4416",
    "sg:postcode":"85013",
    "sg:province":"AZ",
    "sg:tags":[
        "attorney"
    ],
    "wof:name":"Robert B Selman",
    "wof:placetype":"venue"
},
  "geometry": {"coordinates":[-112.082399,33.512269],"type":"Point"}
}