{
  "type": "Feature",
  "properties": {
    "iso:country":"US",
    "sg:address":"6140 E Finisterra",
    "sg:city":"Tucson",
    "sg:classifiers":[
        {
            "category":"Communications",
            "subcategory":"Film & Video Production",
            "type":"Services"
        }
    ],
    "sg:phone":"+1 520 577 9890",
    "sg:postcode":"85750",
    "sg:province":"AZ",
    "sg:tags":[
        "marketing",
        "book",
        "publishing"
    ],
    "wof:name":"Dashew Off Shore",
    "wof:placetype":"venue"
},
  "geometry": {"coordinates":[-110.860565,32.330188],"type":"Point"}
}