{
  "type": "Feature",
  "properties": {
    "iso:country":"US",
    "sg:address":"300 W Osborn Rd Ste 208",
    "sg:city":"Phoenix",
    "sg:classifiers":[
        {
            "category":"Home & Garden",
            "subcategory":"Building Materials",
            "type":"Retail Goods"
        },
        {
            "category":"Building & Trades",
            "subcategory":"Construction",
            "type":"Services"
        }
    ],
    "sg:phone":"+1 602 482 0010",
    "sg:postcode":"85013",
    "sg:province":"AZ",
    "sg:tags":[
        "concrete",
        "staining",
        "contractor"
    ],
    "sg:website":"http://www.arizonastructural.com",
    "wof:name":"Arizona Structural Concrete Construction Corporation",
    "wof:placetype":"venue"
},
  "geometry": {"coordinates":[-112.07820100000001,33.48753],"type":"Point"}
}