{
  "type": "Feature",
  "properties": {
    "addr:full":"6369 E Tanque Verde Rd Tucson AZ 85715",
    "addr:housenumber":"6369",
    "addr:postcode":"85715",
    "addr:street":"E Tanque Verde Rd",
    "iso:country":"US",
    "sg:address":"6369 E Tanque Verde Rd",
    "sg:city":"Tucson",
    "sg:classifiers":[
        {
            "category":"Health Services",
            "subcategory":"Doctor",
            "type":"Services"
        }
    ],
    "sg:phone":"+1 520 319 7811",
    "sg:postcode":"85715",
    "sg:province":"AZ",
    "sg:tags":[
        "physician",
        "surgeon"
    ],
    "wof:name":"Center For Spine Care",
    "wof:placetype":"venue"
},
  "geometry": {"coordinates":[-110.85482500000001,32.244983],"type":"Point"}
}