{
  "type": "Feature",
  "properties": {
    "addr:full":"1629 W Rancho Vistaso Rd Benson AZ 85602",
    "addr:housenumber":"1629",
    "addr:postcode":"85602",
    "addr:street":"W Rancho Vistaso Rd",
    "iso:country":"US",
    "sg:address":"1629 W Rancho Vistaso Rd",
    "sg:city":"Benson",
    "sg:phone":"+1 520 586 3870",
    "sg:postcode":"85602",
    "sg:province":"AZ",
    "sg:tags":[
        "farm",
        "field",
        "crop"
    ],
    "wof:name":"Layton Dobson Cattle Co",
    "wof:placetype":"venue"
},
  "geometry": {"coordinates":[-110.340047,32.086841],"type":"Point"}
}