{
  "type": "Feature",
  "properties": {
    "addr:full":"2119 E Southern Ave Tempe AZ 85282",
    "addr:housenumber":"2119",
    "addr:postcode":"85282",
    "addr:street":"E Southern Ave",
    "iso:country":"US",
    "sg:address":"2119 E Southern Ave",
    "sg:city":"Tempe",
    "sg:classifiers":[
        {
            "category":"Health Services",
            "subcategory":"Doctor",
            "type":"Services"
        }
    ],
    "sg:phone":"+1 480 831 1844",
    "sg:postcode":"85282",
    "sg:province":"AZ",
    "sg:tags":[
        "physician",
        "surgeon"
    ],
    "wof:name":"K James Busch LTD",
    "wof:placetype":"venue"
},
  "geometry": {"coordinates":[-111.892664,33.392904],"type":"Point"}
}