{
  "type": "Feature",
  "properties": {
    "iso:country":"US",
    "sg:address":"1924 E Campbell Ter",
    "sg:city":"Tucson",
    "sg:classifiers":[
        {
            "category":"Building & Trades",
            "subcategory":"Construction",
            "type":"Services"
        }
    ],
    "sg:phone":"+1 520 299 8778",
    "sg:postcode":"85718",
    "sg:province":"AZ",
    "sg:tags":[
        "hanging",
        "contractor"
    ],
    "wof:name":"Desert Peak Painting",
    "wof:placetype":"venue"
},
  "geometry": {"coordinates":[-110.943479,32.291507],"type":"Point"}
}