{
  "type": "Feature",
  "properties": {
    "iso:country":"US",
    "sg:address":"14816 W Parkwood Dr",
    "sg:city":"Surprise",
    "sg:classifiers":[
        {
            "category":"Manufacturing",
            "subcategory":"Furniture",
            "type":"Manufacturing & Wholesale Goods"
        }
    ],
    "sg:phone":"+1 623 214 5617",
    "sg:postcode":"85374",
    "sg:province":"AZ",
    "sg:tags":[
        "household",
        "metal",
        "mfg"
    ],
    "wof:name":"A Caress of Steel",
    "wof:placetype":"venue"
},
  "geometry": {"coordinates":[-112.378666,33.648746],"type":"Point"}
}