{
  "type": "Feature",
  "properties": {
    "iso:country":"US",
    "sg:address":"9406 E Gamble Ln",
    "sg:city":"Scottsdale",
    "sg:classifiers":[
        {
            "category":"Manufacturing",
            "subcategory":"Printing",
            "type":"Manufacturing & Wholesale Goods"
        }
    ],
    "sg:phone":"+1 480 488 6026",
    "sg:postcode":"85262",
    "sg:province":"AZ",
    "sg:tags":[
        "book"
    ],
    "wof:name":"Native Weavers",
    "wof:placetype":"venue"
},
  "geometry": {"coordinates":[-111.876696,33.742959],"type":"Point"}
}