{
  "type": "Feature",
  "properties": {
    "iso:country":"US",
    "sg:address":"1950 E Placita Sin Nombre",
    "sg:city":"Tucson",
    "sg:classifiers":[
        {
            "category":"Education",
            "subcategory":"School",
            "type":"Public Place"
        }
    ],
    "sg:phone":"+1 520 296 1092",
    "sg:postcode":"85718",
    "sg:province":"AZ",
    "sg:tags":[
        "k-",
        "private"
    ],
    "wof:name":"Academy Adventures, Inc.",
    "wof:placetype":"venue"
},
  "geometry": {"coordinates":[-110.942639,32.329444],"type":"Point"}
}