{
  "type": "Feature",
  "properties": {
    "iso:country":"US",
    "sg:address":"1502 E Sagebrush St",
    "sg:city":"Gilbert",
    "sg:classifiers":[
        {
            "category":"Building & Trades",
            "subcategory":"Electrical",
            "type":"Services"
        }
    ],
    "sg:phone":"+1 602 501 3644",
    "sg:postcode":"85296",
    "sg:province":"AZ",
    "sg:tags":[
        "electrician"
    ],
    "wof:name":"Trinity Electrical Contractors",
    "wof:placetype":"venue"
},
  "geometry": {"coordinates":[-111.75832,33.3405],"type":"Point"}
}