{
  "type": "Feature",
  "properties": {
    "addr:full":"1158 W Washington St Ste 108 Tempe AZ 85281",
    "addr:housenumber":"1158",
    "addr:postcode":"85281",
    "addr:street":"W Washington St Ste 108",
    "iso:country":"US",
    "sg:address":"1158 W Washington St Ste 108",
    "sg:city":"Tempe",
    "sg:classifiers":[
        {
            "category":"Utilities",
            "subcategory":"Mobile Phone",
            "type":"Services"
        },
        {
            "category":"Coffee & Tea",
            "type":"Food & Drink"
        }
    ],
    "sg:phone":"+1 602 225 0212",
    "sg:postcode":"85281",
    "sg:province":"AZ",
    "sg:tags":[
        "shop",
        "wi-fi",
        "espresso",
        "hotspot",
        "restaurant"
    ],
    "sg:website":"http://www.starbuckscoffee.com",
    "wof:name":"Starbucks Coffee",
    "wof:placetype":"venue"
},
  "geometry": {"coordinates":[-111.95509699999999,33.441093],"type":"Point"}
}