{
  "type": "Feature",
  "properties": {
    "addr:full":"2300 W Huntington Dr Tempe AZ 85282",
    "addr:housenumber":"2300",
    "addr:postcode":"85282",
    "addr:street":"W Huntington Dr",
    "iso:country":"US",
    "sg:address":"2300 W Huntington Dr",
    "sg:city":"Tempe",
    "sg:classifiers":[
        {
            "category":"Wholesale",
            "subcategory":"Electrical",
            "type":"Manufacturing & Wholesale Goods"
        }
    ],
    "sg:phone":"+1 602 438 2300",
    "sg:postcode":"85282",
    "sg:province":"AZ",
    "sg:tags":[
        "semiconductor",
        "device"
    ],
    "sg:website":"http://www.lsrl.com",
    "wof:name":"Lawrence Semiconductor Research Laboratory, Inc.",
    "wof:placetype":"venue"
},
  "geometry": {"coordinates":[-111.97232099999999,33.394192],"type":"Point"}
}