{
  "type": "Feature",
  "properties": {
    "iso:country":"US",
    "sg:address":"2910 N 7th Ave",
    "sg:city":"Phoenix",
    "sg:classifiers":[
        {
            "category":"Professional",
            "subcategory":"Lawyer & Legal Services",
            "type":"Services"
        }
    ],
    "sg:phone":"+1 602 241 1000",
    "sg:postcode":"85013",
    "sg:province":"AZ",
    "sg:tags":[
        "attorney"
    ],
    "wof:name":"Selden Law",
    "wof:placetype":"venue"
},
  "geometry": {"coordinates":[-112.08312100000001,33.481799],"type":"Point"}
}