{
  "type": "Feature",
  "properties": {
    "addr:full":"6910 W Bell Rd Glendale AZ 85308",
    "addr:housenumber":"6910",
    "addr:postcode":"85308",
    "addr:street":"W Bell Rd",
    "iso:country":"US",
    "sg:address":"6910 W Bell Rd",
    "sg:city":"Glendale",
    "sg:classifiers":[
        {
            "category":"Home & Garden",
            "subcategory":"Furniture",
            "type":"Retail Goods"
        }
    ],
    "sg:phone":"+1 623 334 5120",
    "sg:postcode":"85308",
    "sg:province":"AZ",
    "wof:name":"Designs West Home Furnishings",
    "wof:placetype":"venue"
},
  "geometry": {"coordinates":[-112.20987,33.638338],"type":"Point"}
}