{
  "type": "Feature",
  "properties": {
    "iso:country":"US",
    "sg:address":"11431 N 109th St",
    "sg:city":"Scottsdale",
    "sg:classifiers":[
        {
            "category":"Personal",
            "subcategory":"Beauty Salon",
            "type":"Services"
        }
    ],
    "sg:phone":"+1 480 816 6219",
    "sg:postcode":"85259",
    "sg:province":"AZ",
    "sg:tags":[
        "wig",
        "hair",
        "piece"
    ],
    "wof:name":"Divinely Inspired",
    "wof:placetype":"venue"
},
  "geometry": {"coordinates":[-111.845827,33.590007],"type":"Point"}
}