{
  "type": "Feature",
  "properties": {
    "addr:full":"2340 W Mission Ln Phoenix AZ 85021",
    "addr:housenumber":"2340",
    "addr:postcode":"85021",
    "addr:street":"W Mission Ln",
    "iso:country":"US",
    "sg:address":"2340 W Mission Ln",
    "sg:city":"Phoenix",
    "sg:classifiers":[
        {
            "category":"Autos & Motor Vehicles",
            "subcategory":"Automobile Sales",
            "type":"Retail Goods"
        },
        {
            "category":"Autos & Motor Vehicles",
            "subcategory":"Auto Supplies",
            "type":"Retail Goods"
        },
        {
            "category":"Professional",
            "subcategory":"Business Services",
            "type":"Services"
        },
        {
            "category":"Personal",
            "type":"Services"
        },
        {
            "category":"Retail",
            "subcategory":"Auto Repair",
            "type":"Services"
        }
    ],
    "sg:phone":"+1 623 239 4366",
    "sg:postcode":"85021",
    "sg:province":"AZ",
    "sg:tags":[
        "road",
        "repossessing",
        "towing",
        "transport",
        "utility",
        "trailer",
        "service-automotive"
    ],
    "sg:website":"http://www.phoenixtowingservice.com/home.html",
    "wof:name":"Phoenix Towing Service",
    "wof:placetype":"venue"
},
  "geometry": {"coordinates":[-112.10894399999999,33.569574],"type":"Point"}
}