{
  "type": "Feature",
  "properties": {
    "addr:full":"850 S Ironwood Dr Apache Junction AZ 85220",
    "addr:housenumber":"850",
    "addr:postcode":"85220",
    "addr:street":"S Ironwood Dr",
    "iso:country":"US",
    "sg:address":"850 S Ironwood Dr",
    "sg:city":"Apache Junction",
    "sg:classifiers":[
        {
            "category":"Insurance",
            "subcategory":"Insurance Agent",
            "type":"Services"
        }
    ],
    "sg:phone":"+1 480 983 2350",
    "sg:postcode":"85220",
    "sg:province":"AZ",
    "wof:name":"Lutheran Brotherhood Insurance",
    "wof:placetype":"venue"
},
  "geometry": {"coordinates":[-111.563411,33.404652],"type":"Point"}
}