{
  "type": "Feature",
  "properties": {
    "iso:country":"US",
    "sg:address":"2552 N Alvernon Way",
    "sg:city":"Tucson",
    "sg:classifiers":[
        {
            "category":"Building & Trades",
            "subcategory":"Construction",
            "type":"Services"
        }
    ],
    "sg:phone":"+1 520 320 9754",
    "sg:postcode":"85712",
    "sg:province":"AZ",
    "sg:tags":[
        "nonresidential"
    ],
    "wof:name":"La Quinta Homes",
    "wof:placetype":"venue"
},
  "geometry": {"coordinates":[-110.909656,32.251453],"type":"Point"}
}