{
  "type": "Feature",
  "properties": {
    "iso:country":"US",
    "sg:address":"16671 N 84th Ave",
    "sg:city":"Peoria",
    "sg:classifiers":[
        {
            "category":"Building & Trades",
            "subcategory":"Plumbing",
            "type":"Services"
        }
    ],
    "sg:phone":"+1 623 298 2337",
    "sg:postcode":"85382",
    "sg:province":"AZ",
    "sg:tags":[
        "contractor"
    ],
    "wof:name":"All Year Sports",
    "wof:placetype":"venue"
},
  "geometry": {"coordinates":[-112.241924,33.637743],"type":"Point"}
}