{
  "type": "Feature",
  "properties": {
    "addr:full":"2127 E Knox Rd Tempe AZ 85284",
    "addr:housenumber":"2127",
    "addr:postcode":"85284",
    "addr:street":"E Knox Rd",
    "iso:country":"US",
    "sg:address":"2127 E Knox Rd",
    "sg:city":"Tempe",
    "sg:classifiers":[
        {
            "category":"Banks & Credit Unions",
            "subcategory":"Financial Services",
            "type":"Services"
        }
    ],
    "sg:phone":"+1 480 345 1922",
    "sg:postcode":"85284",
    "sg:province":"AZ",
    "sg:tags":[
        "investor"
    ],
    "wof:name":"Tempe Cascade",
    "wof:placetype":"venue"
},
  "geometry": {"coordinates":[-111.89821999999999,33.327977],"type":"Point"}
}