{
  "type": "Feature",
  "properties": {
    "iso:country":"US",
    "sg:address":"6677 W Thunderbird Rd Ste H120",
    "sg:city":"Glendale",
    "sg:classifiers":[
        {
            "category":"Health Services",
            "subcategory":"Doctor",
            "type":"Services"
        }
    ],
    "sg:phone":"+1 602 792 5794",
    "sg:postcode":"85306",
    "sg:province":"AZ",
    "sg:tags":[
        "physician",
        "surgery",
        "surgeons",
        "oral"
    ],
    "wof:name":"Mansfield, Michael J, Dds - Southwest Center For Oral Surg",
    "wof:placetype":"venue"
},
  "geometry": {"coordinates":[-112.201744,33.610605],"type":"Point"}
}