{
  "type": "Feature",
  "properties": {
    "iso:country":"US",
    "sg:address":"65 Ridgecrest Dr",
    "sg:city":"Sedona",
    "sg:classifiers":[
        {
            "category":"Professional",
            "type":"Services"
        }
    ],
    "sg:phone":"+1 928 284 2486",
    "sg:postcode":"86351",
    "sg:province":"AZ",
    "wof:name":"A Dogs Dream LLC",
    "wof:placetype":"venue"
},
  "geometry": {"coordinates":[-111.7228,34.792357],"type":"Point"}
}