{
  "type": "Feature",
  "properties": {
    "addr:full":"435 E Ingram St Mesa AZ 85203",
    "addr:housenumber":"435",
    "addr:postcode":"85203",
    "addr:street":"E Ingram St",
    "iso:country":"US",
    "sg:address":"435 E Ingram St",
    "sg:city":"Mesa",
    "sg:classifiers":[
        {
            "category":"Professional",
            "subcategory":"Printing & Photocopies",
            "type":"Services"
        }
    ],
    "sg:phone":"+1 480 964 0495",
    "sg:postcode":"85203",
    "sg:province":"AZ",
    "sg:tags":[
        "photographers-commercial"
    ],
    "wof:name":"Photo Plus By Hector",
    "wof:placetype":"venue"
},
  "geometry": {"coordinates":[-111.82143000000001,33.446319],"type":"Point"}
}