{
  "type": "Feature",
  "properties": {
    "addr:full":"4120 N Goldwater Blvd Scottsdale AZ 85251",
    "addr:housenumber":"4120",
    "addr:postcode":"85251",
    "addr:street":"N Goldwater Blvd",
    "iso:country":"US",
    "sg:address":"4120 N Goldwater Blvd",
    "sg:city":"Scottsdale",
    "sg:classifiers":[
        {
            "category":"Wholesale",
            "subcategory":"Motor Vehicles",
            "type":"Manufacturing & Wholesale Goods"
        }
    ],
    "sg:phone":"+1 480 513 0602",
    "sg:postcode":"85251",
    "sg:province":"AZ",
    "wof:name":"Omni Auto Fleet Sales",
    "wof:placetype":"venue"
},
  "geometry": {"coordinates":[-111.930468,33.496004],"type":"Point"}
}