{
  "type": "Feature",
  "properties": {
    "addr:full":"95 W River Rd Tucson AZ 85704",
    "addr:housenumber":"95",
    "addr:postcode":"85704",
    "addr:street":"W River Rd",
    "iso:country":"US",
    "sg:address":"95 W River Rd",
    "sg:city":"Tucson",
    "sg:classifiers":[
        {
            "category":"Bars & Pubs",
            "type":"Food & Drink"
        },
        {
            "category":"Restaurant",
            "type":"Food & Drink"
        }
    ],
    "sg:phone":"+1 520 292 6500",
    "sg:postcode":"85704",
    "sg:province":"AZ",
    "sg:tags":[
        "drinking"
    ],
    "sg:website":"www.arizonaalehouse.com",
    "wof:name":"Arizona Ale House LLC",
    "wof:placetype":"venue"
},
  "geometry": {"coordinates":[-110.974238,32.297052],"type":"Point"}
}