{
  "type": "Feature",
  "properties": {
    "iso:country":"US",
    "sg:address":"4650 E 29th St",
    "sg:city":"Tucson",
    "sg:classifiers":[
        {
            "category":"Real Estate",
            "subcategory":"Real Estate Operator",
            "type":"Services"
        }
    ],
    "sg:phone":"+1 520 745 8276",
    "sg:postcode":"85711",
    "sg:province":"AZ",
    "sg:tags":[
        "apartment"
    ],
    "wof:name":"Villia Pacifica",
    "wof:placetype":"venue"
},
  "geometry": {"coordinates":[-110.893489,32.199669],"type":"Point"}
}