{
  "type": "Feature",
  "properties": {
    "iso:country":"US",
    "sg:address":"18440 N 15th Ave",
    "sg:city":"Phoenix",
    "sg:classifiers":[
        {
            "category":"Education",
            "subcategory":"School",
            "type":"Public Place"
        }
    ],
    "sg:phone":"+1 602 467 6100",
    "sg:postcode":"85023",
    "sg:province":"AZ",
    "wof:name":"Constitution Elementary School",
    "wof:placetype":"venue"
},
  "geometry": {"coordinates":[-112.091584,33.654421],"type":"Point"}
}