{
  "type": "Feature",
  "properties": {
    "iso:country":"US",
    "sg:address":"20738 N 56th Ave",
    "sg:city":"Glendale",
    "sg:phone":"+1 623 806 8493",
    "sg:postcode":"85308",
    "sg:province":"AZ",
    "sg:website":"http://www.worlockair.com",
    "wof:name":"Bill Worlock Mechanical Contractors",
    "wof:placetype":"venue"
},
  "geometry": {"coordinates":[-112.180252,33.674641],"type":"Point"}
}