{
  "type": "Feature",
  "properties": {
    "iso:country":"US",
    "sg:address":"3151 E Wier Ave",
    "sg:city":"Phoenix",
    "sg:classifiers":[
        {
            "category":"Local Transit",
            "type":"Transportation"
        }
    ],
    "sg:phone":"+1 480 217 5319",
    "sg:postcode":"85040",
    "sg:province":"AZ",
    "sg:tags":[
        "airport"
    ],
    "wof:name":"Cab Service",
    "wof:placetype":"venue"
},
  "geometry": {"coordinates":[-112.01383199999999,33.4033],"type":"Point"}
}