{
  "type": "Feature",
  "properties": {
    "iso:country":"US",
    "sg:address":"7185 S Hwy 95",
    "sg:city":"Mohave Valley",
    "sg:classifiers":[
        {
            "category":"Retail",
            "subcategory":"Auto Repair",
            "type":"Services"
        }
    ],
    "sg:phone":"+1 928 768 9309",
    "sg:postcode":"86440",
    "sg:province":"AZ",
    "sg:tags":[
        "repairing",
        "automobile"
    ],
    "wof:name":"CARE Automotive",
    "wof:placetype":"venue"
},
  "geometry": {"coordinates":[-114.598006,34.951908],"type":"Point"}
}