{
  "type": "Feature",
  "properties": {
    "iso:country":"US",
    "sg:address":"14358 N Frank Lloyd Wright Blvd",
    "sg:city":"Scottsdale",
    "sg:classifiers":[
        {
            "category":"Health Services",
            "subcategory":"Doctor",
            "type":"Services"
        }
    ],
    "sg:phone":"+1 480 477 7646",
    "sg:postcode":"85260",
    "sg:province":"AZ",
    "sg:tags":[
        "physician",
        "surgeon"
    ],
    "wof:name":"Arizona Vein & Skin Ctr",
    "wof:placetype":"venue"
},
  "geometry": {"coordinates":[-111.87119,33.616932],"type":"Point"}
}