{
  "type": "Feature",
  "properties": {
    "iso:country":"US",
    "sg:address":"4747 E Sunrise Dr",
    "sg:city":"Tucson",
    "sg:classifiers":[
        {
            "category":"Shopping",
            "type":"Retail Goods"
        }
    ],
    "sg:phone":"+1 520 577 9224",
    "sg:postcode":"85718",
    "sg:province":"AZ",
    "sg:tags":[
        "art",
        "gallery",
        "dealer"
    ],
    "wof:name":"Paloma Art",
    "wof:placetype":"venue"
},
  "geometry": {"coordinates":[-110.89107199999999,32.308451],"type":"Point"}
}