{
  "type": "Feature",
  "properties": {
    "addr:full":"850 W Southern Ave Tempe AZ 85282",
    "addr:housenumber":"850",
    "addr:postcode":"85282",
    "addr:street":"W Southern Ave",
    "iso:country":"US",
    "sg:address":"850 W Southern Ave",
    "sg:city":"Tempe",
    "sg:classifiers":[
        {
            "category":"Building & Trades",
            "subcategory":"Plumbing",
            "type":"Services"
        }
    ],
    "sg:phone":"+1 602 252 9100",
    "sg:postcode":"85282",
    "sg:province":"AZ",
    "sg:tags":[
        "conditioning",
        "air",
        "system",
        "contractor"
    ],
    "wof:name":"Arizona Trane Parts",
    "wof:placetype":"venue"
},
  "geometry": {"coordinates":[-111.949511,33.392934],"type":"Point"}
}