{
  "type": "Feature",
  "properties": {
    "iso:country":"US",
    "sg:address":"18551 N 83rd Ave #147",
    "sg:city":"Glendale",
    "sg:classifiers":[
        {
            "category":"Building & Trades",
            "subcategory":"Plumbing",
            "type":"Services"
        }
    ],
    "sg:phone":"+1 623 533 5688",
    "sg:postcode":"85308",
    "sg:province":"AZ",
    "sg:tags":[
        "plumber"
    ],
    "wof:name":"Newmatic Plumbing, Air Conditioning& Heat Specialist",
    "wof:placetype":"venue"
},
  "geometry": {"coordinates":[-112.237572,33.651855],"type":"Point"}
}