{
  "type": "Feature",
  "properties": {
    "addr:full":"21415 N 15th Ln Ste 118 Phoenix AZ 85027",
    "addr:housenumber":"21415",
    "addr:postcode":"85027",
    "addr:street":"N 15Th Ln Ste 118",
    "iso:country":"US",
    "sg:address":"21415 N 15th Ln Ste 118",
    "sg:city":"Phoenix",
    "sg:classifiers":[
        {
            "category":"Building & Trades",
            "subcategory":"Plumbing",
            "type":"Services"
        },
        {
            "category":"Building & Trades",
            "subcategory":"Construction",
            "type":"Services"
        }
    ],
    "sg:phone":"+1 623 434 1539",
    "sg:postcode":"85027",
    "sg:province":"AZ",
    "sg:tags":[
        "tank",
        "septic",
        "specialty",
        "heating",
        "system",
        "contractor",
        "air conditioning"
    ],
    "sg:website":"http://www.trane.com",
    "wof:name":"Trane Residential Systems",
    "wof:placetype":"venue"
},
  "geometry": {"coordinates":[-112.093103,33.67664],"type":"Point"}
}