{
  "type": "Feature",
  "properties": {
    "addr:full":"5025 N 1st Ave Tucson AZ 85718",
    "addr:housenumber":"5025",
    "addr:postcode":"85718",
    "addr:street":"N 1St Ave",
    "iso:country":"US",
    "sg:address":"5025 N 1st Ave",
    "sg:city":"Tucson",
    "sg:classifiers":[
        {
            "category":"Real Estate",
            "subcategory":"Real Estate Operator",
            "type":"Services"
        }
    ],
    "sg:phone":"+1 520 887 4146",
    "sg:postcode":"85718",
    "sg:province":"AZ",
    "sg:tags":[
        "apartment"
    ],
    "wof:name":"Valley View Apartments",
    "wof:placetype":"venue"
},
  "geometry": {"coordinates":[-110.961021,32.298994],"type":"Point"}
}