{
  "type": "Feature",
  "properties": {
    "iso:country":"US",
    "sg:address":"2622 E 13th St",
    "sg:city":"Yuma",
    "sg:classifiers":[
        {
            "category":"Farming",
            "subcategory":"Farm & Veterinary Services",
            "type":"Manufacturing & Wholesale Goods"
        }
    ],
    "sg:phone":"+1 928 726 8484",
    "sg:postcode":"85365",
    "sg:province":"AZ",
    "sg:tags":[
        "lettuce",
        "harvesting"
    ],
    "wof:name":"Bravo Packing Inc",
    "wof:placetype":"venue"
},
  "geometry": {"coordinates":[-114.584799,32.704203],"type":"Point"}
}