{
  "type": "Feature",
  "properties": {
    "addr:full":"4610 E Broadway Blvd Tucson AZ 85711",
    "addr:housenumber":"4610",
    "addr:postcode":"85711",
    "addr:street":"E Broadway Blvd",
    "iso:country":"US",
    "sg:address":"4610 E Broadway Blvd",
    "sg:city":"Tucson",
    "sg:classifiers":[
        {
            "category":"Retail",
            "subcategory":"Auto Repair",
            "type":"Services"
        }
    ],
    "sg:phone":"+1 520 322 8000",
    "sg:postcode":"85711",
    "sg:province":"AZ",
    "sg:tags":[
        "body",
        "automobile",
        "painting"
    ],
    "wof:name":"Spectrum Auto Paint",
    "wof:placetype":"venue"
},
  "geometry": {"coordinates":[-110.892498,32.221424],"type":"Point"}
}