{
  "type": "Feature",
  "properties": {
    "addr:full":"7911 US Hwy 89 Flagstaff AZ 86004",
    "addr:housenumber":"7911",
    "addr:postcode":"86004",
    "addr:street":"Us Hwy 89",
    "iso:country":"US",
    "sg:address":"7911 US Hwy 89",
    "sg:city":"Flagstaff",
    "sg:phone":"+1 928 526 1888",
    "sg:postcode":"86004",
    "sg:province":"AZ",
    "sg:tags":[
        "gas"
    ],
    "wof:name":"All Star Gas",
    "wof:placetype":"venue"
},
  "geometry": {"coordinates":[-111.55640099999999,35.253579],"type":"Point"}
}