{
  "type": "Feature",
  "properties": {
    "addr:full":"2700 S Woodlands Village Blvd Flagstaff AZ 86001",
    "addr:housenumber":"2700",
    "addr:postcode":"86001",
    "addr:street":"S Woodlands Village Blvd",
    "iso:country":"US",
    "sg:address":"2700 S Woodlands Village Blvd",
    "sg:city":"Flagstaff",
    "sg:classifiers":[
        {
            "category":"Restaurant",
            "type":"Food & Drink"
        }
    ],
    "sg:phone":"+1 928 774 3550",
    "sg:postcode":"86001",
    "sg:province":"AZ",
    "wof:name":"Buffalo Wild Wings Grill & Bar",
    "wof:placetype":"venue"
},
  "geometry": {"coordinates":[-111.668263,35.17713],"type":"Point"}
}