{
  "type": "Feature",
  "properties": {
    "addr:full":"4343 E Charleston Ave Phoenix AZ 85032",
    "addr:housenumber":"4343",
    "addr:postcode":"85032",
    "addr:street":"E Charleston Ave",
    "iso:country":"US",
    "sg:address":"4343 E Charleston Ave",
    "sg:city":"Phoenix",
    "sg:classifiers":[
        {
            "category":"Building & Trades",
            "subcategory":"Construction",
            "type":"Services"
        }
    ],
    "sg:phone":"+1 602 867 8373",
    "sg:postcode":"85032",
    "sg:province":"AZ",
    "sg:tags":[
        "contractor"
    ],
    "wof:name":"G P Contracting Co",
    "wof:placetype":"venue"
},
  "geometry": {"coordinates":[-111.986583,33.649344],"type":"Point"}
}