{
  "type": "Feature",
  "properties": {
    "iso:country":"US",
    "sg:address":"7650 S Mcclintock Dr",
    "sg:city":"Tempe",
    "sg:classifiers":[
        {
            "category":"Government",
            "subcategory":"Post Office",
            "type":"Public Place"
        }
    ],
    "sg:phone":"+1 602 230 1030",
    "sg:postcode":"85284",
    "sg:province":"AZ",
    "sg:tags":[
        "delivery",
        "courier"
    ],
    "wof:name":"Marathon Couriers",
    "wof:placetype":"venue"
},
  "geometry": {"coordinates":[-111.911197,33.34856],"type":"Point"}
}