{
  "type": "Feature",
  "properties": {
    "iso:country":"US",
    "sg:address":"4001 N Pima Rd",
    "sg:city":"Scottsdale",
    "sg:classifiers":[
        {
            "category":"Autos & Motor Vehicles",
            "subcategory":"Fuel & Gas Station",
            "type":"Retail Goods"
        }
    ],
    "sg:phone":"+1 623 362 1122",
    "sg:postcode":"85251",
    "sg:province":"AZ",
    "sg:tags":[
        "oil"
    ],
    "wof:name":"Indian Creek Texaco",
    "wof:placetype":"venue"
},
  "geometry": {"coordinates":[-111.891631,33.492477],"type":"Point"}
}