{
  "type": "Feature",
  "properties": {
    "iso:country":"US",
    "sg:address":"30 E Brown Rd",
    "sg:city":"Mesa",
    "sg:classifiers":[
        {
            "category":"Organizations",
            "subcategory":"Religious Organization",
            "type":"Services"
        }
    ],
    "sg:phone":"+1 480 733 1736",
    "sg:postcode":"85201",
    "sg:province":"AZ",
    "sg:tags":[
        "church"
    ],
    "wof:name":"Praxis Church",
    "wof:placetype":"venue"
},
  "geometry": {"coordinates":[-111.83066599999999,33.435013],"type":"Point"}
}