{
  "type": "Feature",
  "properties": {
    "iso:country":"US",
    "sg:address":"389 E Palm Ln",
    "sg:city":"Phoenix",
    "sg:classifiers":[
        {
            "category":"Professional",
            "subcategory":"Lawyer & Legal Services",
            "type":"Services"
        }
    ],
    "sg:phone":"+1 602 264 1007",
    "sg:postcode":"85004",
    "sg:province":"AZ",
    "sg:tags":[
        "attorney"
    ],
    "wof:name":"Janet Margrave",
    "wof:placetype":"venue"
},
  "geometry": {"coordinates":[-112.068667,33.469296],"type":"Point"}
}