{
  "type": "Feature",
  "properties": {
    "addr:full":"9420 E Golf Links Rd Tucson AZ 85730",
    "addr:housenumber":"9420",
    "addr:postcode":"85730",
    "addr:street":"E Golf Links Rd",
    "iso:country":"US",
    "sg:address":"9420 E Golf Links Rd",
    "sg:city":"Tucson",
    "sg:classifiers":[
        {
            "category":"Insurance",
            "subcategory":"Insurance Agent",
            "type":"Services"
        }
    ],
    "sg:phone":"+1 520 290 1195",
    "sg:postcode":"85730",
    "sg:province":"AZ",
    "wof:name":"Martinez Insurance & Financial",
    "wof:placetype":"venue"
},
  "geometry": {"coordinates":[-110.791962,32.191681],"type":"Point"}
}