{
  "type": "Feature",
  "properties": {
    "iso:country":"US",
    "sg:address":"3761 E Baseline Rd # 132",
    "sg:city":"Gilbert",
    "sg:classifiers":[
        {
            "category":"Airline",
            "type":"Transportation"
        },
        {
            "category":"Travel",
            "subcategory":"Travel Agent",
            "type":"Entertainment"
        }
    ],
    "sg:phone":"+1 480 892 1472",
    "sg:postcode":"85234",
    "sg:province":"AZ",
    "sg:tags":[
        "ticket",
        "agency",
        "services-commercial"
    ],
    "sg:website":"http://www.awottravel.com",
    "wof:name":"A World Of Travel, Ltd",
    "wof:placetype":"venue"
},
  "geometry": {"coordinates":[-111.750947,33.379189],"type":"Point"}
}