{
  "type": "Feature",
  "properties": {
    "addr:full":"194 Main St Oatman AZ 86433",
    "addr:housenumber":"194",
    "addr:postcode":"86433",
    "addr:street":"Main St",
    "iso:country":"US",
    "sg:address":"194 Main St",
    "sg:city":"Oatman",
    "sg:classifiers":[
        {
            "category":"Shopping",
            "subcategory":"Gifts & Souvenirs",
            "type":"Retail Goods"
        }
    ],
    "sg:phone":"+1 928 768 3839",
    "sg:postcode":"86433",
    "sg:province":"AZ",
    "sg:tags":[
        "shop"
    ],
    "wof:name":"Ore House Rock & Gift Shop",
    "wof:placetype":"venue"
},
  "geometry": {"coordinates":[-114.385155,35.027376],"type":"Point"}
}