{
  "type": "Feature",
  "properties": {
    "iso:country":"US",
    "sg:address":"8767 E Via de Ventura",
    "sg:city":"Scottsdale",
    "sg:classifiers":[
        {
            "category":"Shopping",
            "subcategory":"Computers & Home Electronics",
            "type":"Retail Goods"
        }
    ],
    "sg:phone":"+1 480 833 5010",
    "sg:postcode":"85258",
    "sg:province":"AZ",
    "sg:tags":[
        "software"
    ],
    "wof:name":"Carefx",
    "wof:placetype":"venue"
},
  "geometry": {"coordinates":[-111.894951,33.553627],"type":"Point"}
}