{
  "type": "Feature",
  "properties": {
    "iso:country":"US",
    "sg:address":"1030 E Main St",
    "sg:city":"Mesa",
    "sg:classifiers":[
        {
            "category":"Building & Trades",
            "subcategory":"Electrical",
            "type":"Services"
        },
        {
            "category":"Retail",
            "subcategory":"Auto Repair",
            "type":"Services"
        }
    ],
    "sg:phone":"+1 480 964 6567",
    "sg:postcode":"85203",
    "sg:province":"AZ",
    "sg:tags":[
        "automobile",
        "electrician",
        "electric"
    ],
    "sg:website":"http://www.villageautoaz.com",
    "wof:name":"Village Auto Electric",
    "wof:placetype":"venue"
},
  "geometry": {"coordinates":[-111.808455,33.415199],"type":"Point"}
}