{
  "type": "Feature",
  "properties": {
    "iso:country":"US",
    "sg:address":"927 W Hatcher Rd",
    "sg:city":"Phoenix",
    "sg:classifiers":[
        {
            "category":"Professional",
            "subcategory":"Engineering",
            "type":"Services"
        }
    ],
    "sg:phone":"+1 602 861 8097",
    "sg:postcode":"85021",
    "sg:province":"AZ",
    "sg:tags":[
        "engineer"
    ],
    "wof:name":"Baldwin & Assoc",
    "wof:placetype":"venue"
},
  "geometry": {"coordinates":[-112.085943,33.57117],"type":"Point"}
}