{
  "type": "Feature",
  "properties": {
    "addr:full":"1110 E Missouri Ave Phoenix AZ 85014",
    "addr:housenumber":"1110",
    "addr:postcode":"85014",
    "addr:street":"E Missouri Ave",
    "iso:country":"US",
    "sg:address":"1110 E Missouri Ave",
    "sg:city":"Phoenix",
    "sg:classifiers":[
        {
            "category":"Organizations",
            "subcategory":"Non-profit Organization",
            "type":"Services"
        }
    ],
    "sg:phone":"+1 602 944 4999",
    "sg:postcode":"85014",
    "sg:province":"AZ",
    "sg:tags":[
        "charitable",
        "institution"
    ],
    "wof:name":"Chrysalis Shelter",
    "wof:placetype":"venue"
},
  "geometry": {"coordinates":[-112.05759,33.516558],"type":"Point"}
}