{
  "type": "Feature",
  "properties": {
    "iso:country":"US",
    "sg:address":"3045 N Stone Ave",
    "sg:city":"Tucson",
    "sg:classifiers":[
        {
            "category":"Food & Beverages",
            "subcategory":"Bakery",
            "type":"Retail Goods"
        }
    ],
    "sg:phone":"+1 520 882 7083",
    "sg:postcode":"85705",
    "sg:province":"AZ",
    "wof:name":"Interstate Brands Corporation",
    "wof:placetype":"venue"
},
  "geometry": {"coordinates":[-110.972096,32.262225],"type":"Point"}
}