{
  "type": "Feature",
  "properties": {
    "iso:country":"US",
    "sg:address":"10732 N 96th Ave",
    "sg:city":"Peoria",
    "sg:classifiers":[
        {
            "category":"Retail",
            "subcategory":"Auto Repair",
            "type":"Services"
        }
    ],
    "sg:phone":"+1 623 486 5925",
    "sg:postcode":"85345",
    "sg:province":"AZ",
    "sg:tags":[
        "classic",
        "automobile",
        "recreational",
        "vehicle",
        "campers-repair",
        "restoration-antique"
    ],
    "wof:name":"The Stripping Shop",
    "wof:placetype":"venue"
},
  "geometry": {"coordinates":[-112.265944,33.582122],"type":"Point"}
}