{
  "type": "Feature",
  "properties": {
    "iso:country":"US",
    "sg:address":"25 W Warner Rd",
    "sg:city":"Chandler",
    "sg:classifiers":[
        {
            "category":"Banks & Credit Unions",
            "subcategory":"Bank",
            "type":"Services"
        }
    ],
    "sg:phone":"+1 480 726 2920",
    "sg:postcode":"85225",
    "sg:province":"AZ",
    "sg:tags":[
        "loan"
    ],
    "wof:name":"Community Loans",
    "wof:placetype":"venue"
},
  "geometry": {"coordinates":[-111.844116,33.335046],"type":"Point"}
}