{
  "type": "Feature",
  "properties": {
    "iso:country":"US",
    "sg:address":"5628 N 6th St",
    "sg:city":"Phoenix",
    "sg:classifiers":[
        {
            "category":"Building & Trades",
            "subcategory":"Construction",
            "type":"Services"
        }
    ],
    "sg:phone":"+1 602 618 8217",
    "sg:postcode":"85012",
    "sg:province":"AZ",
    "sg:tags":[
        "masonry",
        "contractor"
    ],
    "wof:name":"Arizona Block",
    "wof:placetype":"venue"
},
  "geometry": {"coordinates":[-112.066692,33.519772],"type":"Point"}
}