{
  "type": "Feature",
  "properties": {
    "iso:country":"US",
    "sg:address":"2720 E Thomas Rd",
    "sg:city":"Phoenix",
    "sg:classifiers":[
        {
            "category":"Professional",
            "subcategory":"Accounting & Tax Preparation",
            "type":"Services"
        }
    ],
    "sg:phone":"+1 602 840 2558",
    "sg:postcode":"85016",
    "sg:province":"AZ",
    "sg:tags":[
        "bookkeeping",
        "general"
    ],
    "wof:name":"Kolic Accounting Svc",
    "wof:placetype":"venue"
},
  "geometry": {"coordinates":[-112.021914,33.480468],"type":"Point"}
}