{
  "type": "Feature",
  "properties": {
    "addr:full":"10675 E Reitz Cir Cornville AZ 86325",
    "addr:housenumber":"10675",
    "addr:postcode":"az 86325",
    "addr:street":"E Reitz Cir",
    "iso:country":"US",
    "sg:address":"10675 E Reitz Cir",
    "sg:city":"Cornville",
    "sg:classifiers":[
        {
            "category":"Building & Trades",
            "subcategory":"Plumbing",
            "type":"Services"
        }
    ],
    "sg:phone":"+1 928 634 4633",
    "sg:postcode":"86325",
    "sg:province":"AZ",
    "sg:tags":[
        "contractor"
    ],
    "wof:name":"Arizona Air Conditioning",
    "wof:placetype":"venue"
},
  "geometry": {"coordinates":[-111.909963,34.694339],"type":"Point"}
}