{
  "type": "Feature",
  "properties": {
    "iso:country":"US",
    "sg:address":"5017 S Ranch Rd",
    "sg:city":"Sierra Vista",
    "sg:classifiers":[
        {
            "category":"Building & Trades",
            "subcategory":"Construction",
            "type":"Services"
        }
    ],
    "sg:phone":"+1 520 378 3663",
    "sg:postcode":"85650",
    "sg:province":"AZ",
    "sg:tags":[
        "excavation",
        "contractor"
    ],
    "wof:name":"Lewco Rainbow Creations Inc",
    "wof:placetype":"venue"
},
  "geometry": {"coordinates":[-110.172796,31.477874],"type":"Point"}
}