{
  "type": "Feature",
  "properties": {
    "addr:full":"5016 S Ash Ave Tempe AZ 85282",
    "addr:housenumber":"5016",
    "addr:postcode":"85282",
    "addr:street":"S Ash Ave",
    "iso:country":"US",
    "sg:address":"5016 S Ash Ave",
    "sg:city":"Tempe",
    "sg:classifiers":[
        {
            "category":"Health Services",
            "subcategory":"Health Practitioner",
            "type":"Services"
        }
    ],
    "sg:phone":"+1 480 831 5919",
    "sg:postcode":"85282",
    "sg:province":"AZ",
    "sg:tags":[
        "medicine",
        "alternative"
    ],
    "wof:name":"Az Vibe Ctr",
    "wof:placetype":"venue"
},
  "geometry": {"coordinates":[-111.94159399999999,33.37942],"type":"Point"}
}