{
  "type": "Feature",
  "properties": {
    "addr:full":"1481 E Williams Field Rd Gilbert AZ 85295",
    "addr:housenumber":"1481",
    "addr:postcode":"85295",
    "addr:street":"E Williams Field Rd",
    "iso:country":"US",
    "sg:address":"1481 E Williams Field Rd",
    "sg:city":"Gilbert",
    "sg:classifiers":[
        {
            "category":"Banks & Credit Unions",
            "subcategory":"Bank",
            "type":"Services"
        }
    ],
    "sg:phone":"+1 480 224 4960",
    "sg:postcode":"85295",
    "sg:province":"AZ",
    "sg:tags":[
        "saving",
        "commercial"
    ],
    "sg:website":"http://www.uhb-fl.com",
    "wof:name":"M & I Marshall & Ilsley Bank Inc",
    "wof:placetype":"venue"
},
  "geometry": {"coordinates":[-111.781364,33.306549],"type":"Point"}
}