{
  "type": "Feature",
  "properties": {
    "addr:full":"8874 W Shaw Butte Dr Peoria AZ 85345",
    "addr:housenumber":"8874",
    "addr:postcode":"85345",
    "addr:street":"W Shaw Butte Dr",
    "iso:country":"US",
    "sg:address":"8874 W Shaw Butte Dr",
    "sg:city":"Peoria",
    "sg:classifiers":[
        {
            "category":"Building & Trades",
            "subcategory":"Plumbing",
            "type":"Services"
        }
    ],
    "sg:phone":"+1 623 486 8861",
    "sg:postcode":"85345",
    "sg:province":"AZ",
    "sg:tags":[
        "contractor"
    ],
    "wof:name":"Colburn Plumbing Inc",
    "wof:placetype":"venue"
},
  "geometry": {"coordinates":[-112.25087499999999,33.594849],"type":"Point"}
}