{
  "type": "Feature",
  "properties": {
    "addr:full":"1074 Sycamore Ave Kingman AZ 86409",
    "addr:housenumber":"1074",
    "addr:postcode":"86409",
    "addr:street":"Sycamore Ave",
    "iso:country":"US",
    "sg:address":"1074 Sycamore Ave",
    "sg:city":"Kingman",
    "sg:classifiers":[
        {
            "category":"Real Estate",
            "subcategory":"Real Estate Operator",
            "type":"Services"
        }
    ],
    "sg:phone":"+1 928 692 6824",
    "sg:postcode":"86409",
    "sg:province":"AZ",
    "sg:tags":[
        "apartment"
    ],
    "wof:name":"Sellers Group",
    "wof:placetype":"venue"
},
  "geometry": {"coordinates":[-114.041909,35.222104],"type":"Point"}
}