{
  "type": "Feature",
  "properties": {
    "iso:country":"US",
    "sg:address":"2828 Plz del Plata",
    "sg:city":"Lake Havasu City",
    "sg:classifiers":[
        {
            "category":"Building & Trades",
            "subcategory":"Electrical",
            "type":"Services"
        }
    ],
    "sg:phone":"+1 928 854 5664",
    "sg:postcode":"86406",
    "sg:province":"AZ",
    "sg:tags":[
        "electrical",
        "contractor"
    ],
    "wof:name":"Southwest Electric Contractor",
    "wof:placetype":"venue"
},
  "geometry": {"coordinates":[-114.300042,34.473244],"type":"Point"}
}