{
  "type": "Feature",
  "properties": {
    "addr:full":"13660 N Sandario Rd Marana AZ 85653",
    "addr:housenumber":"13660",
    "addr:postcode":"85653",
    "addr:street":"N Sandario Rd",
    "iso:country":"US",
    "sg:address":"13660 N Sandario Rd",
    "sg:city":"Marana",
    "sg:classifiers":[
        {
            "category":"Retail",
            "subcategory":"Auto Repair",
            "type":"Services"
        }
    ],
    "sg:phone":"+1 520 682 2476",
    "sg:postcode":"85653",
    "sg:province":"AZ",
    "sg:tags":[
        "wrecker"
    ],
    "wof:name":"Eddies Towing Impound Facility",
    "wof:placetype":"venue"
},
  "geometry": {"coordinates":[-111.216916,32.455672],"type":"Point"}
}