{
  "type": "Feature",
  "properties": {
    "addr:full":"9243 S Cll Tomi Guadalupe AZ 85283",
    "addr:housenumber":"9243",
    "addr:postcode":"85283",
    "addr:street":"S Cll Tomi",
    "iso:country":"US",
    "sg:address":"9243 S Cll Tomi",
    "sg:city":"Guadalupe",
    "sg:classifiers":[
        {
            "category":"Real Estate",
            "subcategory":"Real Estate Agent",
            "type":"Services"
        }
    ],
    "sg:phone":"+1 480 820 0922",
    "sg:postcode":"85283",
    "sg:province":"AZ",
    "sg:tags":[
        "authorities",
        "housing"
    ],
    "wof:name":"Maricopa County Housing",
    "wof:placetype":"venue"
},
  "geometry": {"coordinates":[-111.95914399999999,33.361888],"type":"Point"}
}