{
  "type": "Feature",
  "properties": {
    "iso:country":"US",
    "sg:address":"4991 E Ave del Cazador",
    "sg:city":"Tucson",
    "sg:classifiers":[
        {
            "category":"Professional",
            "type":"Services"
        }
    ],
    "sg:phone":"+1 520 299 9260",
    "sg:postcode":"85718",
    "sg:province":"AZ",
    "wof:name":"Innovtive Sltons For Physcians",
    "wof:placetype":"venue"
},
  "geometry": {"coordinates":[-110.88802,32.279396],"type":"Point"}
}