{
  "type": "Feature",
  "properties": {
    "addr:full":"100 N Pantano Rd Tucson AZ 85710",
    "addr:housenumber":"100",
    "addr:postcode":"85710",
    "addr:street":"N Pantano Rd",
    "iso:country":"US",
    "sg:address":"100 N Pantano Rd",
    "sg:city":"Tucson",
    "sg:classifiers":[
        {
            "category":"Home & Garden",
            "subcategory":"Furniture",
            "type":"Retail Goods"
        }
    ],
    "sg:phone":"+1 520 917 2410",
    "sg:postcode":"85710",
    "sg:province":"AZ",
    "sg:website":"www.samlevitz.com",
    "wof:name":"Sam Levitz Furniture",
    "wof:placetype":"venue"
},
  "geometry": {"coordinates":[-110.823757,32.223247],"type":"Point"}
}