{
  "type": "Feature",
  "properties": {
    "iso:country":"US",
    "sg:address":"1900 N McClintock Dr",
    "sg:city":"Tempe",
    "sg:classifiers":[
        {
            "category":"Retail",
            "subcategory":"Auto Repair",
            "type":"Services"
        }
    ],
    "sg:phone":"+1 480 947 9586",
    "sg:postcode":"85281",
    "sg:province":"AZ",
    "sg:tags":[
        "transmission"
    ],
    "wof:name":"All-Pro Transmissions",
    "wof:placetype":"venue"
},
  "geometry": {"coordinates":[-111.909279,33.451281],"type":"Point"}
}