{
  "type": "Feature",
  "properties": {
    "iso:country":"US",
    "sg:address":"1228 Willow Creek Rd",
    "sg:city":"Prescott",
    "sg:classifiers":[
        {
            "category":"Government",
            "subcategory":"Office",
            "type":"Public Place"
        }
    ],
    "sg:phone":"+1 928 778 7438",
    "sg:postcode":"86301",
    "sg:province":"AZ",
    "sg:tags":[
        "federal",
        "program",
        "adm"
    ],
    "wof:name":"US Service Corps-Retired Execs",
    "wof:placetype":"venue"
},
  "geometry": {"coordinates":[-112.482325,34.566242],"type":"Point"}
}