{
  "type": "Feature",
  "properties": {
    "iso:country":"US",
    "sg:address":"15 E Glenn Dr",
    "sg:city":"Phoenix",
    "sg:classifiers":[
        {
            "category":"Wholesale",
            "subcategory":"Home Furnishings",
            "type":"Manufacturing & Wholesale Goods"
        }
    ],
    "sg:phone":"+1 602 944 2898",
    "sg:postcode":"85020",
    "sg:province":"AZ",
    "sg:tags":[
        "sterling",
        "linen",
        "china",
        "crystal"
    ],
    "wof:name":"Levine Linens",
    "wof:placetype":"venue"
},
  "geometry": {"coordinates":[-112.073027,33.5411],"type":"Point"}
}