{
  "type": "Feature",
  "properties": {
    "addr:full":"3606 Hearne Ave Kingman AZ 86409",
    "addr:housenumber":"3606",
    "addr:postcode":"86409",
    "addr:street":"Hearne Ave",
    "iso:country":"US",
    "sg:address":"3606 Hearne Ave",
    "sg:city":"Kingman",
    "sg:classifiers":[
        {
            "category":"Manufacturing",
            "subcategory":"Tools & Machinery",
            "type":"Manufacturing & Wholesale Goods"
        }
    ],
    "sg:phone":"+1 928 692 8393",
    "sg:postcode":"86409",
    "sg:province":"AZ",
    "sg:tags":[
        "machine",
        "screw",
        "automatic",
        "mfg"
    ],
    "wof:name":"Automatic Machining",
    "wof:placetype":"venue"
},
  "geometry": {"coordinates":[-113.989892,35.258866],"type":"Point"}
}