{
  "type": "Feature",
  "properties": {
    "iso:country":"US",
    "sg:address":"6050 State Hwy 179",
    "sg:city":"Sedona",
    "sg:classifiers":[
        {
            "category":"Personal",
            "type":"Services"
        }
    ],
    "sg:phone":"+1 928 284 9514",
    "sg:postcode":"86351",
    "sg:province":"AZ",
    "sg:tags":[
        "therapist",
        "massage"
    ],
    "wof:name":"Body Therapy & Massage",
    "wof:placetype":"venue"
},
  "geometry": {"coordinates":[-111.76355,34.774399],"type":"Point"}
}