{
  "type": "Feature",
  "properties": {
    "addr:full":"3340 W Lincoln St Phoenix AZ 85009",
    "addr:housenumber":"3340",
    "addr:postcode":"85009",
    "addr:street":"W Lincoln St",
    "iso:country":"US",
    "sg:address":"3340 W Lincoln St",
    "sg:city":"Phoenix",
    "sg:classifiers":[
        {
            "category":"Manufacturing",
            "subcategory":"Furniture",
            "type":"Manufacturing & Wholesale Goods"
        }
    ],
    "sg:phone":"+1 602 353 8266",
    "sg:postcode":"85009",
    "sg:province":"AZ",
    "sg:tags":[
        "wood",
        "mfg"
    ],
    "wof:name":"H & S Marble & Granite",
    "wof:placetype":"venue"
},
  "geometry": {"coordinates":[-112.133787,33.442409],"type":"Point"}
}