{
  "type": "Feature",
  "properties": {
    "iso:country":"US",
    "sg:address":"535 N Mesquite St",
    "sg:city":"Cottonwood",
    "sg:classifiers":[
        {
            "category":"Manufacturing",
            "subcategory":"Furniture",
            "type":"Manufacturing & Wholesale Goods"
        }
    ],
    "sg:phone":"+1 928 634 8398",
    "sg:postcode":"86326",
    "sg:province":"AZ",
    "sg:tags":[
        "equipment",
        "supply"
    ],
    "wof:name":"General Supply",
    "wof:placetype":"venue"
},
  "geometry": {"coordinates":[-112.03004900000001,34.745194],"type":"Point"}
}