{
  "type": "Feature",
  "properties": {
    "iso:country":"US",
    "sg:address":"370 E Virginia Ave",
    "sg:city":"Phoenix",
    "sg:classifiers":[
        {
            "category":"Personal",
            "type":"Services"
        }
    ],
    "sg:phone":"+1 602 277 0559",
    "sg:postcode":"85004",
    "sg:province":"AZ",
    "sg:tags":[
        "paying",
        "bill"
    ],
    "wof:name":"Desert Rose Bookkeeping Svc",
    "wof:placetype":"venue"
},
  "geometry": {"coordinates":[-112.06668000000001,33.476697],"type":"Point"}
}