{
  "type": "Feature",
  "properties": {
    "addr:full":"2205 N Crescent Dr Flagstaff AZ 86001",
    "addr:housenumber":"2205",
    "addr:postcode":"86001",
    "addr:street":"N Crescent Dr",
    "iso:country":"US",
    "sg:address":"2205 N Crescent Dr",
    "sg:city":"Flagstaff",
    "sg:classifiers":[
        {
            "category":"Building & Trades",
            "subcategory":"Plumbing",
            "type":"Services"
        }
    ],
    "sg:phone":"+1 928 214 0483",
    "sg:postcode":"86001",
    "sg:province":"AZ",
    "sg:tags":[
        "contractor"
    ],
    "wof:name":"Case Engineering Inc",
    "wof:placetype":"venue"
},
  "geometry": {"coordinates":[-111.657509,35.221589],"type":"Point"}
}