{
  "type": "Feature",
  "properties": {
    "addr:full":"3410 W Washington St Phoenix AZ 85009",
    "addr:housenumber":"3410",
    "addr:postcode":"85009",
    "addr:street":"W Washington St",
    "iso:country":"US",
    "sg:address":"3410 W Washington St",
    "sg:city":"Phoenix",
    "sg:classifiers":[
        {
            "category":"Wholesale",
            "subcategory":"Auto Parts",
            "type":"Manufacturing & Wholesale Goods"
        }
    ],
    "sg:phone":"+1 602 455 8113",
    "sg:postcode":"85009",
    "sg:province":"AZ",
    "sg:tags":[
        "automobile",
        "rebuilt",
        "supply"
    ],
    "wof:name":"A-A National Auto Parts",
    "wof:placetype":"venue"
},
  "geometry": {"coordinates":[-112.13260699999999,33.447709],"type":"Point"}
}