{
  "type": "Feature",
  "properties": {
    "addr:full":"3100 W Ray Road Chandler AZ 85226",
    "addr:housenumber":"3100",
    "addr:postcode":"85226",
    "addr:street":"W Ray Road",
    "iso:country":"US",
    "sg:address":"3100 W Ray Road",
    "sg:city":"Chandler",
    "sg:classifiers":[
        {
            "category":"Professional",
            "subcategory":"Lawyer & Legal Services",
            "type":"Services"
        }
    ],
    "sg:phone":"+1 480 792 9770",
    "sg:postcode":"85226",
    "sg:province":"AZ",
    "wof:name":"Donaldson and Associates PC",
    "wof:placetype":"venue"
},
  "geometry": {"coordinates":[-111.89474800000001,33.320427],"type":"Point"}
}