{
  "type": "Feature",
  "properties": {
    "iso:country":"US",
    "sg:address":"1001 N 9th St",
    "sg:city":"Phoenix",
    "sg:classifiers":[
        {
            "category":"Real Estate",
            "subcategory":"Real Estate Operator",
            "type":"Services"
        }
    ],
    "sg:phone":"+1 480 888 9700",
    "sg:postcode":"85006",
    "sg:province":"AZ",
    "sg:tags":[
        "apartment"
    ],
    "wof:name":"9th Street Apartments",
    "wof:placetype":"venue"
},
  "geometry": {"coordinates":[-112.062042,33.458672],"type":"Point"}
}