{
  "type": "Feature",
  "properties": {
    "iso:country":"US",
    "sg:address":"9018 N 39th Ave",
    "sg:city":"Phoenix",
    "sg:classifiers":[
        {
            "category":"Retail",
            "subcategory":"Repair Shop",
            "type":"Services"
        }
    ],
    "sg:phone":"+1 602 697 2392",
    "sg:postcode":"85051",
    "sg:province":"AZ",
    "sg:tags":[
        "fix-it"
    ],
    "wof:name":"Rns Improvements",
    "wof:placetype":"venue"
},
  "geometry": {"coordinates":[-112.14291,33.56826],"type":"Point"}
}