{
  "type": "Feature",
  "properties": {
    "iso:country":"US",
    "sg:address":"1545 E Van Buren St",
    "sg:city":"Phoenix",
    "sg:classifiers":[
        {
            "category":"Retail",
            "subcategory":"Auto Repair",
            "type":"Services"
        }
    ],
    "sg:phone":"+1 602 252 7041",
    "sg:postcode":"85006",
    "sg:province":"AZ",
    "sg:tags":[
        "body",
        "repairing",
        "painting",
        "automobile"
    ],
    "wof:name":"Ernesto's Auto Body",
    "wof:placetype":"venue"
},
  "geometry": {"coordinates":[-112.048579,33.451408],"type":"Point"}
}