{
  "type": "Feature",
  "properties": {
    "addr:full":"4545 N 36th St Phoenix AZ 85018",
    "addr:housenumber":"4545",
    "addr:postcode":"85018",
    "addr:street":"N 36Th St",
    "iso:country":"US",
    "sg:address":"4545 N 36th St",
    "sg:city":"Phoenix",
    "sg:classifiers":[
        {
            "category":"Arts & Performance",
            "subcategory":"Theater",
            "type":"Entertainment"
        }
    ],
    "sg:phone":"+1 602 368 5880",
    "sg:postcode":"85018",
    "sg:province":"AZ",
    "sg:tags":[
        "bureau"
    ],
    "wof:name":"Acme Entertainment Tech Inc",
    "wof:placetype":"venue"
},
  "geometry": {"coordinates":[-112.00408899999999,33.504764],"type":"Point"}
}