{
  "type": "Feature",
  "properties": {
    "iso:country":"US",
    "sg:address":"1442 E Los Arboles Dr",
    "sg:city":"Tempe",
    "sg:classifiers":[
        {
            "category":"Real Estate",
            "subcategory":"Real Estate Agent",
            "type":"Services"
        }
    ],
    "sg:phone":"+1 480 838 3247",
    "sg:postcode":"85284",
    "sg:province":"AZ",
    "wof:name":"Sharon Sandell Ltd",
    "wof:placetype":"venue"
},
  "geometry": {"coordinates":[-111.91682299999999,33.33547],"type":"Point"}
}