{
  "type": "Feature",
  "properties": {
    "iso:country":"US",
    "sg:address":"912 Dougherty St",
    "sg:city":"Prescott",
    "sg:classifiers":[
        {
            "category":"Building & Trades",
            "subcategory":"Construction",
            "type":"Services"
        }
    ],
    "sg:phone":"+1 928 541 1899",
    "sg:postcode":"86305",
    "sg:province":"AZ",
    "sg:tags":[
        "house"
    ],
    "wof:name":"Cienega Creek Home Design",
    "wof:placetype":"venue"
},
  "geometry": {"coordinates":[-112.488531,34.554316],"type":"Point"}
}