{
  "type": "Feature",
  "properties": {
    "addr:full":"1520 N 84th Dr Tolleson AZ 85353",
    "addr:housenumber":"1520",
    "addr:postcode":"85353",
    "addr:street":"N 84Th Dr",
    "iso:country":"US",
    "sg:address":"1520 N 84th Dr",
    "sg:city":"Tolleson",
    "sg:classifiers":[
        {
            "category":"Travel",
            "subcategory":"Hotels & Motels",
            "type":"Entertainment"
        },
        {
            "category":"Real Estate",
            "subcategory":"Real Estate Operator",
            "type":"Services"
        }
    ],
    "sg:phone":"+1 602 861 4900",
    "sg:postcode":"85353",
    "sg:province":"AZ",
    "sg:tags":[
        "apartment"
    ],
    "wof:name":"Candlewood Suites",
    "wof:placetype":"venue"
},
  "geometry": {"coordinates":[-112.241997,33.4646],"type":"Point"}
}