{
  "type": "Feature",
  "properties": {
    "iso:country":"US",
    "sg:address":"5450 E Emile Zola Ave",
    "sg:city":"Scottsdale",
    "sg:classifiers":[
        {
            "category":"Real Estate",
            "subcategory":"Real Estate Agent",
            "type":"Services"
        }
    ],
    "sg:phone":"+1 602 996 5418",
    "sg:postcode":"85254",
    "sg:province":"AZ",
    "wof:name":"Bettys Revenge LLC",
    "wof:placetype":"venue"
},
  "geometry": {"coordinates":[-111.961552,33.608047],"type":"Point"}
}