{
  "type": "Feature",
  "properties": {
    "addr:full":"1319 W Michigan Ave Phoenix AZ 85023",
    "addr:housenumber":"1319",
    "addr:postcode":"85023",
    "addr:street":"W Michigan Ave",
    "iso:country":"US",
    "sg:address":"1319 W Michigan Ave",
    "sg:city":"Phoenix",
    "sg:classifiers":[
        {
            "category":"Professional",
            "subcategory":"Management & Consulting",
            "type":"Services"
        }
    ],
    "sg:phone":"+1 602 866 3415",
    "sg:postcode":"85023",
    "sg:province":"AZ",
    "sg:tags":[
        "marketing",
        "consultant"
    ],
    "wof:name":"Regan Marketing Consultant",
    "wof:placetype":"venue"
},
  "geometry": {"coordinates":[-112.089787,33.650978],"type":"Point"}
}