{
  "type": "Feature",
  "properties": {
    "iso:country":"US",
    "sg:address":"3708 N Grand View Dr",
    "sg:city":"Flagstaff",
    "sg:classifiers":[
        {
            "category":"Building & Trades",
            "subcategory":"Construction",
            "type":"Services"
        }
    ],
    "sg:phone":"+1 928 779 1446",
    "sg:postcode":"86004",
    "sg:province":"AZ",
    "sg:tags":[
        "project"
    ],
    "wof:name":"High Top Construction",
    "wof:placetype":"venue"
},
  "geometry": {"coordinates":[-111.623111,35.221714],"type":"Point"}
}