{
  "type": "Feature",
  "properties": {
    "iso:country":"US",
    "sg:address":"11450 N Shannon Rd",
    "sg:city":"Tucson",
    "sg:classifiers":[
        {
            "category":"Retail",
            "subcategory":"Animal Services",
            "type":"Services"
        }
    ],
    "sg:phone":"+1 520 575 1249",
    "sg:postcode":"85742",
    "sg:province":"AZ",
    "sg:tags":[
        "breeder",
        "horse"
    ],
    "wof:name":"Tortolita Flats Warmbloods",
    "wof:placetype":"venue"
},
  "geometry": {"coordinates":[-111.029652,32.409636],"type":"Point"}
}