{
  "type": "Feature",
  "properties": {
    "iso:country":"US",
    "sg:address":"36889 N Tom Darlington Dr",
    "sg:city":"Carefree",
    "sg:classifiers":[
        {
            "category":"Restaurant",
            "type":"Food & Drink"
        }
    ],
    "sg:phone":"+1 480 488 6161",
    "sg:postcode":"85377",
    "sg:province":"AZ",
    "sg:tags":[
        "chinese"
    ],
    "wof:name":"China Joy",
    "wof:placetype":"venue"
},
  "geometry": {"coordinates":[-111.92425,33.821107],"type":"Point"}
}