{
  "type": "Feature",
  "properties": {
    "iso:country":"US",
    "sg:address":"725 Howards Rd",
    "sg:city":"Camp Verde",
    "sg:classifiers":[
        {
            "category":"Building & Trades",
            "subcategory":"Plumbing",
            "type":"Services"
        }
    ],
    "sg:phone":"+1 928 567 5339",
    "sg:postcode":"86322",
    "sg:province":"AZ",
    "sg:tags":[
        "plumbing",
        "contractor"
    ],
    "wof:name":"Roper Plumbing & Mechanical",
    "wof:placetype":"venue"
},
  "geometry": {"coordinates":[-111.847785,34.548128],"type":"Point"}
}