{
  "type": "Feature",
  "properties": {
    "addr:full":"5143 Show Low Lake Rd Lakeside AZ 85929",
    "addr:postcode":"5143;85929",
    "addr:street":"Show Low Lake Rd",
    "iso:country":"US",
    "sg:address":"5143 Show Low Lake Rd",
    "sg:city":"Lakeside",
    "sg:classifiers":[
        {
            "category":"Building & Trades",
            "subcategory":"Construction",
            "type":"Services"
        }
    ],
    "sg:phone":"+1 928 537 5028",
    "sg:postcode":"85929",
    "sg:province":"AZ",
    "sg:tags":[
        "dry wall",
        "contractor"
    ],
    "wof:name":"Tye Frank Dry Wall Company",
    "wof:placetype":"venue"
},
  "geometry": {"coordinates":[-110.005206,34.186842],"type":"Point"}
}