{
  "type": "Feature",
  "properties": {
    "addr:full":"40 W Veterans Blvd Tucson AZ 85713",
    "addr:housenumber":"40",
    "addr:postcode":"85713",
    "addr:street":"W Veterans Blvd",
    "iso:country":"US",
    "sg:address":"40 W Veterans Blvd",
    "sg:city":"Tucson",
    "sg:classifiers":[
        {
            "category":"Organizations",
            "subcategory":"Non-profit Organization",
            "type":"Services"
        }
    ],
    "sg:phone":"+1 520 622 8900",
    "sg:postcode":"85713",
    "sg:province":"AZ",
    "sg:website":"www.tatucson.org",
    "wof:name":"Travelers Aid Of Tucson",
    "wof:placetype":"venue"
},
  "geometry": {"coordinates":[-110.969179,32.181504],"type":"Point"}
}