{
  "type": "Feature",
  "properties": {
    "iso:country":"US",
    "sg:address":"261 E University Dr",
    "sg:city":"Phoenix",
    "sg:classifiers":[
        {
            "category":"Wholesale",
            "subcategory":"Furniture",
            "type":"Manufacturing & Wholesale Goods"
        },
        {
            "category":"Home & Garden",
            "subcategory":"Furniture",
            "type":"Retail Goods"
        }
    ],
    "sg:phone":"+1 602 253 9715",
    "sg:postcode":"85004",
    "sg:province":"AZ",
    "sg:tags":[
        "store",
        "furniture-wholesale",
        "manufacturer"
    ],
    "sg:website":"http://www.trendwood.com",
    "wof:name":"Trendwood Warehouse",
    "wof:placetype":"venue"
},
  "geometry": {"coordinates":[-112.070419,33.42479],"type":"Point"}
}