{
  "type": "Feature",
  "properties": {
    "iso:country":"US",
    "sg:address":"11811 N Tatum Blvd",
    "sg:city":"Phoenix",
    "sg:classifiers":[
        {
            "category":"Professional",
            "subcategory":"Detective & Security Services",
            "type":"Services"
        }
    ],
    "sg:phone":"+1 602 953 7800",
    "sg:postcode":"85028",
    "sg:province":"AZ",
    "sg:tags":[
        "investigator"
    ],
    "wof:name":"Evans & Assoc",
    "wof:placetype":"venue"
},
  "geometry": {"coordinates":[-111.97956,33.593276],"type":"Point"}
}