{
  "type": "Feature",
  "properties": {
    "addr:full":"2020 N 75th Ave Ste 25 Phoenix AZ 85035",
    "addr:housenumber":"2020",
    "addr:postcode":"85035",
    "addr:street":"N 75Th Ave Ste 25",
    "iso:country":"US",
    "sg:address":"2020 N 75th Ave Ste 25",
    "sg:city":"Phoenix",
    "sg:classifiers":[
        {
            "category":"Shopping",
            "subcategory":"Pets & Pet Supplies",
            "type":"Retail Goods"
        },
        {
            "category":"Retail",
            "subcategory":"Animal Services",
            "type":"Services"
        }
    ],
    "sg:phone":"+1 623 873 1130",
    "sg:postcode":"85035",
    "sg:province":"AZ",
    "sg:tags":[
        "store"
    ],
    "sg:website":"www.petsmart.com",
    "wof:name":"PetSmart",
    "wof:placetype":"venue"
},
  "geometry": {"coordinates":[-112.222855,33.471018],"type":"Point"}
}