{
  "type": "Feature",
  "properties": {
    "iso:country":"US",
    "sg:address":"10621 N 35th Ave",
    "sg:city":"Phoenix",
    "sg:classifiers":[
        {
            "category":"Restaurant",
            "type":"Food & Drink"
        }
    ],
    "sg:menulink":"http://www.allmenus.com/az/phoenix/180236-jack-in-the-box/menu/",
    "sg:phone":"+1 602 942 7941",
    "sg:postcode":"85029",
    "sg:province":"AZ",
    "sg:tags":[
        "burger",
        "american"
    ],
    "wof:name":"Jack in the Box",
    "wof:placetype":"venue"
},
  "geometry": {"coordinates":[-112.133651,33.582757],"type":"Point"}
}