{
  "type": "Feature",
  "properties": {
    "iso:country":"US",
    "sg:address":"4780 N Supai Pl",
    "sg:city":"Tucson",
    "sg:classifiers":[
        {
            "category":"Professional",
            "subcategory":"Accounting & Tax Preparation",
            "type":"Services"
        }
    ],
    "sg:phone":"+1 520 749 1857",
    "sg:postcode":"85749",
    "sg:province":"AZ",
    "sg:tags":[
        "accountant"
    ],
    "wof:name":"John F Lowrey CPA",
    "wof:placetype":"venue"
},
  "geometry": {"coordinates":[-110.796517,32.294625],"type":"Point"}
}