{
  "type": "Feature",
  "properties": {
    "iso:country":"US",
    "sg:address":"302 W Glenrosa Ave",
    "sg:city":"Phoenix",
    "sg:classifiers":[
        {
            "category":"Taxi",
            "type":"Transportation"
        }
    ],
    "sg:phone":"+1 602 340 8294",
    "sg:postcode":"85013",
    "sg:province":"AZ",
    "wof:name":"Always Available Trnsprtn",
    "wof:placetype":"venue"
},
  "geometry": {"coordinates":[-112.078154,33.498429],"type":"Point"}
}