{
  "type": "Feature",
  "properties": {
    "iso:country":"US",
    "sg:address":"1727 W Main St",
    "sg:city":"Mesa",
    "sg:classifiers":[
        {
            "category":"Education",
            "subcategory":"School",
            "type":"Public Place"
        }
    ],
    "sg:phone":"+1 480 472 6850",
    "sg:postcode":"85201",
    "sg:province":"AZ",
    "wof:name":"TAPP Alternative School",
    "wof:placetype":"venue"
},
  "geometry": {"coordinates":[-111.865707,33.414809],"type":"Point"}
}