{
  "type": "Feature",
  "properties": {
    "iso:country":"US",
    "sg:address":"4220 S 37th St",
    "sg:city":"Phoenix",
    "sg:classifiers":[
        {
            "category":"Wholesale",
            "subcategory":"Non-durable Goods",
            "type":"Manufacturing & Wholesale Goods"
        }
    ],
    "sg:phone":"+1 602 327 1557",
    "sg:postcode":"85040",
    "sg:province":"AZ",
    "wof:name":"Cool Crabs",
    "wof:placetype":"venue"
},
  "geometry": {"coordinates":[-112.00199,33.407781],"type":"Point"}
}