{
  "type": "Feature",
  "properties": {
    "addr:full":"8969 E Indian Bend Rd Scottsdale AZ 85250",
    "addr:housenumber":"8969",
    "addr:postcode":"85250",
    "addr:street":"E Indian Bend Rd",
    "iso:country":"US",
    "sg:address":"8969 E Indian Bend Rd",
    "sg:city":"Scottsdale",
    "sg:classifiers":[
        {
            "category":"Shopping",
            "subcategory":"Clothing, Apparel, & Fashions",
            "type":"Retail Goods"
        }
    ],
    "sg:phone":"+1 480 362 1204",
    "sg:postcode":"85250",
    "sg:province":"AZ",
    "sg:tags":[
        "item",
        "boutique"
    ],
    "wof:name":"Clairie's Boutique",
    "wof:placetype":"venue"
},
  "geometry": {"coordinates":[-111.890112,33.538345],"type":"Point"}
}