{
  "type": "Feature",
  "properties": {
    "iso:country":"US",
    "sg:address":"9157 E Helen St",
    "sg:city":"Tucson",
    "sg:classifiers":[
        {
            "category":"Building & Trades",
            "subcategory":"Construction",
            "type":"Services"
        }
    ],
    "sg:phone":"+1 520 296 8449",
    "sg:postcode":"85715",
    "sg:province":"AZ",
    "sg:tags":[
        "house"
    ],
    "wof:name":"Jws Construction Inc",
    "wof:placetype":"venue"
},
  "geometry": {"coordinates":[-110.795559,32.236503],"type":"Point"}
}