{
  "type": "Feature",
  "properties": {
    "iso:country":"US",
    "sg:address":"830 N 1st Ave Ste 215",
    "sg:city":"Phoenix",
    "sg:classifiers":[
        {
            "category":"Real Estate",
            "subcategory":"Real Estate Services",
            "type":"Services"
        },
        {
            "category":"Personal",
            "type":"Services"
        }
    ],
    "sg:phone":"+1 866 485 3135",
    "sg:postcode":"85003",
    "sg:province":"AZ",
    "sg:tags":[
        "property",
        "management",
        "maintenance"
    ],
    "sg:website":"http://local.ingenio.com/Listings/Details.aspx?NUM=a%3a10331767%3a13%3a4859924%3a14%3a0%3a7",
    "wof:name":"Desert Investment Advisors",
    "wof:placetype":"venue"
},
  "geometry": {"coordinates":[-112.07518,33.457859],"type":"Point"}
}