{
  "type": "Feature",
  "properties": {
    "iso:country":"US",
    "sg:address":"2915 N 59th Ave",
    "sg:city":"Phoenix",
    "sg:classifiers":[
        {
            "category":"Health Services",
            "subcategory":"Dentist",
            "type":"Services"
        }
    ],
    "sg:phone":"+1 623 846 0575",
    "sg:postcode":"85033",
    "sg:province":"AZ",
    "sg:tags":[
        "dental",
        "clinic"
    ],
    "wof:name":"Zapata Dental",
    "wof:placetype":"venue"
},
  "geometry": {"coordinates":[-112.186409,33.481516],"type":"Point"}
}