{
  "type": "Feature",
  "properties": {
    "addr:full":"11075 N Guava Dr Tucson AZ 85737",
    "addr:housenumber":"11075",
    "addr:postcode":"85737",
    "addr:street":"N Guava Dr",
    "iso:country":"US",
    "sg:address":"11075 N Guava Dr",
    "sg:city":"Tucson",
    "sg:classifiers":[
        {
            "category":"Wholesale",
            "subcategory":"Drugs",
            "type":"Manufacturing & Wholesale Goods"
        }
    ],
    "sg:phone":"+1 520 575 5589",
    "sg:postcode":"85737",
    "sg:province":"AZ",
    "wof:name":"Talana International",
    "wof:placetype":"venue"
},
  "geometry": {"coordinates":[-110.983294,32.404515],"type":"Point"}
}