{
  "type": "Feature",
  "properties": {
    "iso:country":"US",
    "sg:address":"1419 W 12th Pl Ste 103",
    "sg:city":"Tempe",
    "sg:classifiers":[
        {
            "category":"Home & Garden",
            "subcategory":"Home Furnishings",
            "type":"Retail Goods"
        },
        {
            "category":"Wholesale",
            "subcategory":"Furniture",
            "type":"Manufacturing & Wholesale Goods"
        },
        {
            "category":"Manufacturing",
            "subcategory":"Textiles",
            "type":"Manufacturing & Wholesale Goods"
        }
    ],
    "sg:phone":"+1 480 966 8100",
    "sg:postcode":"85281",
    "sg:province":"AZ",
    "sg:tags":[
        "pillows-wholesale",
        "house",
        "furniture-wholesale",
        "pillow",
        "manufacturer"
    ],
    "wof:name":"Pillow Shop",
    "wof:placetype":"venue"
},
  "geometry": {"coordinates":[-111.963883,33.415549],"type":"Point"}
}