{
  "type": "Feature",
  "properties": {
    "iso:country":"US",
    "sg:address":"4815 N 19th Ave",
    "sg:city":"Phoenix",
    "sg:classifiers":[
        {
            "category":"Building & Trades",
            "subcategory":"Plumbing",
            "type":"Services"
        }
    ],
    "sg:phone":"+1 602 274 4481",
    "sg:postcode":"85015",
    "sg:province":"AZ",
    "sg:tags":[
        "plumbing",
        "contractor"
    ],
    "wof:name":"Degeorge Plumbing & Htg Inc",
    "wof:placetype":"venue"
},
  "geometry": {"coordinates":[-112.099805,33.507734],"type":"Point"}
}