{
  "type": "Feature",
  "properties": {
    "iso:country":"US",
    "sg:address":"8149 E Evans Rd",
    "sg:city":"Scottsdale",
    "sg:classifiers":[
        {
            "category":"Real Estate",
            "subcategory":"Architect",
            "type":"Services"
        }
    ],
    "sg:phone":"+1 480 348 5818",
    "sg:postcode":"85260",
    "sg:province":"AZ",
    "wof:name":"David L Schmitt & Assoc",
    "wof:placetype":"venue"
},
  "geometry": {"coordinates":[-111.90527299999999,33.616495],"type":"Point"}
}