{
  "type": "Feature",
  "properties": {
    "addr:full":"6862 W Ironwood Dr Peoria AZ 85345",
    "addr:housenumber":"6862",
    "addr:postcode":"85345",
    "addr:street":"W Ironwood Dr",
    "iso:country":"US",
    "sg:address":"6862 W Ironwood Dr",
    "sg:city":"Peoria",
    "sg:classifiers":[
        {
            "category":"Building & Trades",
            "subcategory":"Construction",
            "type":"Services"
        }
    ],
    "sg:phone":"+1 623 776 3080",
    "sg:postcode":"85345",
    "sg:province":"AZ",
    "sg:tags":[
        "hanging",
        "contractor"
    ],
    "wof:name":"Morris Project Painting Inc",
    "wof:placetype":"venue"
},
  "geometry": {"coordinates":[-112.204472,33.575977],"type":"Point"}
}