{
  "type": "Feature",
  "properties": {
    "iso:country":"US",
    "sg:address":"10651 W Glendale Ave",
    "sg:city":"Glendale",
    "sg:classifiers":[
        {
            "category":"Retail",
            "subcategory":"Auto Repair",
            "type":"Services"
        }
    ],
    "sg:phone":"+1 623 877 8004",
    "sg:postcode":"85307",
    "sg:province":"AZ",
    "sg:tags":[
        "repairing",
        "automobile"
    ],
    "wof:name":"Nicolato's Hot Rod Shops",
    "wof:placetype":"venue"
},
  "geometry": {"coordinates":[-112.286596,33.53655],"type":"Point"}
}