{
  "type": "Feature",
  "properties": {
    "addr:full":"3101 W Palm Ln Phoenix AZ 85009",
    "addr:housenumber":"3101",
    "addr:postcode":"85009",
    "addr:street":"W Palm Ln",
    "iso:country":"US",
    "sg:address":"3101 W Palm Ln",
    "sg:city":"Phoenix",
    "sg:classifiers":[
        {
            "category":"Organizations",
            "subcategory":"Religious Organization",
            "type":"Services"
        }
    ],
    "sg:phone":"+1 602 272 1627",
    "sg:postcode":"85009",
    "sg:province":"AZ",
    "sg:tags":[
        "church"
    ],
    "wof:name":"Emmanuel Temple",
    "wof:placetype":"venue"
},
  "geometry": {"coordinates":[-112.127932,33.469597],"type":"Point"}
}