{
  "type": "Feature",
  "properties": {
    "iso:country":"US",
    "sg:address":"9162 W Cactus Rd",
    "sg:city":"Peoria",
    "sg:classifiers":[
        {
            "category":"Autos & Motor Vehicles",
            "subcategory":"Motorcycle Sales",
            "type":"Retail Goods"
        },
        {
            "category":"Retail",
            "subcategory":"Auto Repair",
            "type":"Services"
        }
    ],
    "sg:phone":"+1 781 706 2282",
    "sg:postcode":"85381",
    "sg:province":"AZ",
    "sg:tags":[
        "scooters-repairing",
        "scooters-parts",
        "motorcycles-customizing",
        "supply"
    ],
    "sg:website":"http://vintagecustomcyclesllc.com",
    "wof:name":"Vintage Custom Cycles llc.",
    "wof:placetype":"venue"
},
  "geometry": {"coordinates":[-112.25663400000001,33.595313],"type":"Point"}
}