{
  "type": "Feature",
  "properties": {
    "iso:country":"US",
    "sg:address":"23015 N Cave Creek Rd",
    "sg:city":"Phoenix",
    "sg:classifiers":[
        {
            "category":"Place Of Worship",
            "subcategory":"Church",
            "type":"Public Place"
        },
        {
            "category":"Place Of Worship",
            "type":"Public Place"
        }
    ],
    "sg:phone":"+1 480 513 3243",
    "sg:postcode":"85024",
    "sg:province":"AZ",
    "sg:tags":[
        "churches-catholic-traditional",
        "churches-catholic"
    ],
    "sg:website":"http://www.diocesephoenix.com/CEMETARY",
    "wof:name":"Catholic Cemeteries Of The Dio",
    "wof:placetype":"venue"
},
  "geometry": {"coordinates":[-112.028761,33.694956],"type":"Point"}
}