{
  "type": "Feature",
  "properties": {
    "iso:country":"US",
    "sg:address":"939 E Guadalupe Rd Ste 1",
    "sg:city":"Tempe",
    "sg:classifiers":[
        {
            "category":"Restaurant",
            "type":"Food & Drink"
        }
    ],
    "sg:phone":"+1 480 831 6685",
    "sg:postcode":"85283",
    "sg:province":"AZ",
    "sg:tags":[
        "chinese"
    ],
    "wof:name":"Chopstick Express",
    "wof:placetype":"venue"
},
  "geometry": {"coordinates":[-111.92746,33.363739],"type":"Point"}
}