{
  "type": "Feature",
  "properties": {
    "addr:full":"3880 Frontage Rd Bullhead City AZ 86442",
    "addr:housenumber":"3880",
    "addr:postcode":"86442",
    "addr:street":"Frontage Rd",
    "iso:country":"US",
    "sg:address":"3880 Frontage Rd",
    "sg:city":"Bullhead City",
    "sg:classifiers":[
        {
            "category":"Insurance",
            "subcategory":"Insurance Agent",
            "type":"Services"
        }
    ],
    "sg:phone":"+1 928 763 1003",
    "sg:postcode":"86442",
    "sg:province":"AZ",
    "wof:name":"Fulco Mavis A Insurance",
    "wof:placetype":"venue"
},
  "geometry": {"coordinates":[-114.58946400000001,35.044677],"type":"Point"}
}