{
  "type": "Feature",
  "properties": {
    "iso:country":"US",
    "sg:address":"528 McNally Dr",
    "sg:city":"Prescott",
    "sg:classifiers":[
        {
            "category":"Local Transit",
            "type":"Transportation"
        }
    ],
    "sg:phone":"+1 928 925 0447",
    "sg:postcode":"86305",
    "sg:province":"AZ",
    "sg:tags":[
        "airport"
    ],
    "wof:name":"Wills Sedan Svc",
    "wof:placetype":"venue"
},
  "geometry": {"coordinates":[-112.479907,34.549096],"type":"Point"}
}