{
  "type": "Feature",
  "properties": {
    "iso:country":"US",
    "sg:address":"1207 W Carol Ann Way",
    "sg:city":"Phoenix",
    "sg:classifiers":[
        {
            "category":"Professional",
            "subcategory":"Detective & Security Services",
            "type":"Services"
        }
    ],
    "sg:phone":"+1 602 538 4789",
    "sg:postcode":"85023",
    "sg:province":"AZ",
    "sg:tags":[
        "information",
        "bureau"
    ],
    "wof:name":"Ang Gxp Consulting Services",
    "wof:placetype":"venue"
},
  "geometry": {"coordinates":[-112.08844000000001,33.628445],"type":"Point"}
}