{
  "type": "Feature",
  "properties": {
    "iso:country":"US",
    "sg:address":"6133 W Glendale Ave",
    "sg:city":"Glendale",
    "sg:classifiers":[
        {
            "category":"Retail",
            "subcategory":"Repair Shop",
            "type":"Services"
        }
    ],
    "sg:phone":"+1 623 842 8414",
    "sg:postcode":"85301",
    "sg:province":"AZ",
    "sg:tags":[
        "welding"
    ],
    "wof:name":"DMD Welding",
    "wof:placetype":"venue"
},
  "geometry": {"coordinates":[-112.1922,33.538411],"type":"Point"}
}