{
  "type": "Feature",
  "properties": {
    "addr:full":"1202 E Broadway Blvd Tucson AZ 85719",
    "addr:housenumber":"1202",
    "addr:postcode":"85719",
    "addr:street":"E Broadway Blvd",
    "iso:country":"US",
    "sg:address":"1202 E Broadway Blvd",
    "sg:city":"Tucson",
    "sg:classifiers":[
        {
            "category":"Real Estate",
            "subcategory":"Architect",
            "type":"Services"
        }
    ],
    "sg:phone":"+1 520 792 0265",
    "sg:postcode":"85719",
    "sg:province":"AZ",
    "wof:name":"Lanning Architecture",
    "wof:placetype":"venue"
},
  "geometry": {"coordinates":[-110.952342,32.221276],"type":"Point"}
}