{
  "type": "Feature",
  "properties": {
    "iso:country":"US",
    "sg:address":"6840 N 35th Ave",
    "sg:city":"Phoenix",
    "sg:classifiers":[
        {
            "category":"Restaurant",
            "type":"Food & Drink"
        }
    ],
    "sg:phone":"+1 602 973 8556",
    "sg:postcode":"85017",
    "sg:province":"AZ",
    "wof:name":"Casa Carmen",
    "wof:placetype":"venue"
},
  "geometry": {"coordinates":[-112.1344,33.537648],"type":"Point"}
}