{
  "type": "Feature",
  "properties": {
    "addr:full":"1006 E Warner Rd Tempe AZ 85284",
    "addr:housenumber":"1006",
    "addr:postcode":"85284",
    "addr:street":"E Warner Rd",
    "iso:country":"US",
    "sg:address":"1006 E Warner Rd",
    "sg:city":"Tempe",
    "sg:classifiers":[
        {
            "category":"Building & Trades",
            "subcategory":"Locksmith",
            "type":"Services"
        }
    ],
    "sg:phone":"+1 877 550 3166",
    "sg:postcode":"85284",
    "sg:province":"AZ",
    "sg:tags":[
        "key"
    ],
    "wof:name":"24 Emergency Locksmith",
    "wof:placetype":"venue"
},
  "geometry": {"coordinates":[-111.92601500000001,33.334808],"type":"Point"}
}