{
  "type": "Feature",
  "properties": {
    "addr:full":"4541 N 7th St Phoenix AZ 85014",
    "addr:housenumber":"4541",
    "addr:postcode":"85014",
    "addr:street":"N 7Th St",
    "iso:country":"US",
    "sg:address":"4541 N 7th St",
    "sg:city":"Phoenix",
    "sg:classifiers":[
        {
            "category":"Social Services",
            "subcategory":"Child Care",
            "type":"Services"
        }
    ],
    "sg:phone":"+1 602 218 6039",
    "sg:postcode":"85014",
    "sg:province":"AZ",
    "wof:name":"Kidz Paradise",
    "wof:placetype":"venue"
},
  "geometry": {"coordinates":[-112.064954,33.502801],"type":"Point"}
}