{
  "type": "Feature",
  "properties": {
    "iso:country":"US",
    "sg:address":"1403 W Baseline Rd",
    "sg:city":"Tempe",
    "sg:classifiers":[
        {
            "category":"Recreation",
            "subcategory":"Boat Charter",
            "type":"Entertainment"
        },
        {
            "category":"Retail",
            "subcategory":"Storage",
            "type":"Services"
        }
    ],
    "sg:phone":"+1 480 820 8992",
    "sg:postcode":"85283",
    "sg:province":"AZ",
    "sg:tags":[
        "yard",
        "automobile",
        "household",
        "recreational",
        "commercial",
        "campers-storage",
        "vehicle",
        "self"
    ],
    "sg:website":"http://www.ams-storage.com",
    "wof:name":"All American Self Storage",
    "wof:placetype":"venue"
},
  "geometry": {"coordinates":[-111.961162,33.37825],"type":"Point"}
}