{
  "type": "Feature",
  "properties": {
    "addr:full":"3201 E Broadway Rd Phoenix AZ 85040",
    "addr:housenumber":"3201",
    "addr:postcode":"85040",
    "addr:street":"E Broadway Rd",
    "iso:country":"US",
    "sg:address":"3201 E Broadway Rd",
    "sg:city":"Phoenix",
    "sg:classifiers":[
        {
            "category":"Government",
            "subcategory":"Department Of Motor Vehicles",
            "type":"Public Place"
        },
        {
            "category":"Manufacturing",
            "subcategory":"Aerospace",
            "type":"Manufacturing & Wholesale Goods"
        }
    ],
    "sg:phone":"+1 602 305 8080",
    "sg:postcode":"85040",
    "sg:province":"AZ",
    "sg:tags":[
        "engine",
        "supply",
        "equipment",
        "aircraft",
        "part"
    ],
    "sg:website":"http://www.asbg.com",
    "wof:name":"Barnes Aerospace",
    "wof:placetype":"venue"
},
  "geometry": {"coordinates":[-112.01161999999999,33.40707],"type":"Point"}
}