{
  "type": "Feature",
  "properties": {
    "iso:country":"US",
    "sg:address":"4520 N 16th St Ste A",
    "sg:city":"Phoenix",
    "sg:classifiers":[
        {
            "category":"Building & Trades",
            "subcategory":"Locksmith",
            "type":"Services"
        }
    ],
    "sg:phone":"+1 602 242 6422",
    "sg:postcode":"85016",
    "sg:province":"AZ",
    "sg:tags":[
        "lock",
        "industrial",
        "locksmiths-commercial"
    ],
    "wof:name":"Mark's Lock & Key Service",
    "wof:placetype":"venue"
},
  "geometry": {"coordinates":[-112.047563,33.502801],"type":"Point"}
}