{
  "type": "Feature",
  "properties": {
    "addr:full":"2625 S Woodlands Village Blvd Flagstaff AZ 86001",
    "addr:housenumber":"2625",
    "addr:postcode":"86001",
    "addr:street":"S Woodlands Village Blvd",
    "iso:country":"US",
    "sg:address":"2625 S Woodlands Village Blvd",
    "sg:city":"Flagstaff",
    "sg:classifiers":[
        {
            "category":"Banks & Credit Unions",
            "subcategory":"Bank",
            "type":"Services"
        }
    ],
    "sg:phone":"+1 928 213 8034",
    "sg:postcode":"86001",
    "sg:province":"AZ",
    "wof:name":"Bank Of America",
    "wof:placetype":"venue"
},
  "geometry": {"coordinates":[-111.668307,35.17673],"type":"Point"}
}