{
  "type": "Feature",
  "properties": {
    "iso:country":"US",
    "sg:address":"3365 S Country Club Rd Ste 101",
    "sg:city":"Tucson",
    "sg:classifiers":[
        {
            "category":"Retail",
            "subcategory":"Auto Rental",
            "type":"Services"
        },
        {
            "category":"Airport",
            "type":"Transportation"
        },
        {
            "category":"Local Transit",
            "type":"Transportation"
        }
    ],
    "sg:phone":"+1 520 624 5466",
    "sg:postcode":"85713",
    "sg:province":"AZ",
    "sg:tags":[
        "shuttle",
        "limousine"
    ],
    "sg:website":"http://www.gainbroadband.com",
    "wof:name":"Catalina Limousine Svc Inc",
    "wof:placetype":"venue"
},
  "geometry": {"coordinates":[-110.926427,32.184077],"type":"Point"}
}