{
  "type": "Feature",
  "properties": {
    "addr:full":"8146 W Indian School Rd Phoenix AZ 85033",
    "addr:housenumber":"8146",
    "addr:postcode":"85033",
    "addr:street":"W Indian School Rd",
    "iso:country":"US",
    "sg:address":"8146 W Indian School Rd",
    "sg:city":"Phoenix",
    "sg:classifiers":[
        {
            "category":"Structure",
            "subcategory":"Office Building",
            "type":"Public Place"
        }
    ],
    "sg:phone":"+1 602 770 8839",
    "sg:postcode":"85033",
    "sg:province":"AZ",
    "sg:tags":[
        "park"
    ],
    "wof:name":"Lin's Property",
    "wof:placetype":"venue"
},
  "geometry": {"coordinates":[-112.234774,33.494348],"type":"Point"}
}