{
  "type": "Feature",
  "properties": {
    "iso:country":"US",
    "sg:address":"5555 E McDowell Rd",
    "sg:city":"Phoenix",
    "sg:classifiers":[
        {
            "category":"Travel",
            "subcategory":"Travel Agent",
            "type":"Entertainment"
        }
    ],
    "sg:phone":"+1 602 273 1898",
    "sg:postcode":"85008",
    "sg:province":"AZ",
    "sg:tags":[
        "agency",
        "bureau"
    ],
    "wof:name":"Carlson El Sol Travel",
    "wof:placetype":"venue"
},
  "geometry": {"coordinates":[-111.968762,33.465491],"type":"Point"}
}