{
  "type": "Feature",
  "properties": {
    "iso:country":"US",
    "sg:address":"15 E Southern Ave",
    "sg:city":"Tempe",
    "sg:classifiers":[
        {
            "category":"Building & Trades",
            "subcategory":"Equipment Rental",
            "type":"Services"
        }
    ],
    "sg:phone":"+1 480 967 0900",
    "sg:postcode":"85282",
    "sg:province":"AZ",
    "sg:tags":[
        "yard"
    ],
    "wof:name":"Rent-A-Center",
    "wof:placetype":"venue"
},
  "geometry": {"coordinates":[-111.93508799999999,33.392839],"type":"Point"}
}