{
  "type": "Feature",
  "properties": {
    "iso:country":"US",
    "sg:address":"19900 N Remington Dr",
    "sg:city":"Surprise",
    "sg:classifiers":[
        {
            "category":"Restaurant",
            "type":"Food & Drink"
        }
    ],
    "sg:phone":"+1 623 584 8494",
    "sg:postcode":"85374",
    "sg:province":"AZ",
    "sg:tags":[
        "eating"
    ],
    "sg:website":"www.dillonsrestaurant.com/",
    "wof:name":"Dillons' Grand Restaurant",
    "wof:placetype":"venue"
},
  "geometry": {"coordinates":[-112.405699,33.661511],"type":"Point"}
}