{
  "type": "Feature",
  "properties": {
    "iso:country":"US",
    "sg:address":"1714 W Van Buren St",
    "sg:city":"Phoenix",
    "sg:classifiers":[
        {
            "category":"Professional",
            "type":"Services"
        },
        {
            "category":"Professional",
            "subcategory":"Lawyer & Legal Services",
            "type":"Services"
        }
    ],
    "sg:phone":"+1 602 253 0071",
    "sg:postcode":"85007",
    "sg:province":"AZ",
    "sg:tags":[
        "attorney"
    ],
    "wof:name":"Diaz Law Firm",
    "wof:placetype":"venue"
},
  "geometry": {"coordinates":[-112.096898,33.451305],"type":"Point"}
}