{
  "type": "Feature",
  "properties": {
    "iso:country":"US",
    "sg:address":"18002 N 41st Pl",
    "sg:city":"Phoenix",
    "sg:classifiers":[
        {
            "category":"Building & Trades",
            "subcategory":"Landscaping Services",
            "type":"Services"
        }
    ],
    "sg:phone":"+1 602 980 2056",
    "sg:postcode":"85032",
    "sg:province":"AZ",
    "sg:tags":[
        "landscape",
        "contractor"
    ],
    "wof:name":"Da Vinci Landscapes",
    "wof:placetype":"venue"
},
  "geometry": {"coordinates":[-111.992918,33.650976],"type":"Point"}
}