{
  "type": "Feature",
  "properties": {
    "addr:full":"402 S Plumer Ave Tucson AZ 85719",
    "addr:housenumber":"402",
    "addr:postcode":"85719",
    "addr:street":"S Plumer Ave",
    "iso:country":"US",
    "sg:address":"402 S Plumer Ave",
    "sg:city":"Tucson",
    "sg:classifiers":[
        {
            "category":"Professional",
            "type":"Services"
        }
    ],
    "sg:phone":"+1 520 624 7337",
    "sg:postcode":"85719",
    "sg:province":"AZ",
    "sg:tags":[
        "establishment"
    ],
    "wof:name":"B & B Ent",
    "wof:placetype":"venue"
},
  "geometry": {"coordinates":[-110.939514,32.216582],"type":"Point"}
}