{
  "type": "Feature",
  "properties": {
    "addr:full":"6872 E Sunrise Dr Tucson AZ 85750",
    "addr:housenumber":"6872",
    "addr:postcode":"85750",
    "addr:street":"E Sunrise Dr",
    "iso:country":"US",
    "sg:address":"6872 E Sunrise Dr",
    "sg:city":"Tucson",
    "sg:classifiers":[
        {
            "category":"Banks & Credit Unions",
            "subcategory":"Bank",
            "type":"Services"
        }
    ],
    "sg:phone":"+1 520 529 5106",
    "sg:postcode":"85750",
    "sg:province":"AZ",
    "sg:tags":[
        "loan",
        "real estate"
    ],
    "wof:name":"Pinnacle Mortgage",
    "wof:placetype":"venue"
},
  "geometry": {"coordinates":[-110.845794,32.308761],"type":"Point"}
}