{
  "type": "Feature",
  "properties": {
    "iso:country":"US",
    "sg:address":"107 W Desert Ave",
    "sg:city":"Litchfield Park",
    "sg:classifiers":[
        {
            "category":"Banks & Credit Unions",
            "subcategory":"Bank",
            "type":"Services"
        }
    ],
    "sg:phone":"+1 623 535 8604",
    "sg:postcode":"85340",
    "sg:province":"AZ",
    "wof:name":"Armed Forces Bank",
    "wof:placetype":"venue"
},
  "geometry": {"coordinates":[-112.358731,33.486943],"type":"Point"}
}