{
  "type": "Feature",
  "properties": {
    "addr:full":"11144 N Frank Lloyd Wright Blvd Scottsdale AZ 85259",
    "addr:housenumber":"11144",
    "addr:postcode":"85259",
    "addr:street":"N Frank Lloyd Wright Blvd",
    "iso:country":"US",
    "sg:address":"11144 N Frank Lloyd Wright Blvd",
    "sg:city":"Scottsdale",
    "sg:classifiers":[
        {
            "category":"Restaurant",
            "type":"Food & Drink"
        }
    ],
    "sg:menulink":"http://www.allmenus.com/az/phoenix/4609-i-love-sushi--steak/menu/",
    "sg:phone":"+1 480 314 1222",
    "sg:postcode":"85259",
    "sg:province":"AZ",
    "sg:tags":[
        "japanese",
        "asian"
    ],
    "wof:name":"I love Sushi & Steak",
    "wof:placetype":"venue"
},
  "geometry": {"coordinates":[-111.835391,33.587748],"type":"Point"}
}