{
  "type": "Feature",
  "properties": {
    "iso:country":"US",
    "sg:address":"5201 N 7th Ave",
    "sg:city":"Phoenix",
    "sg:classifiers":[
        {
            "category":"Health Services",
            "subcategory":"Chiropractor",
            "type":"Services"
        }
    ],
    "sg:phone":"+1 602 264 3001",
    "sg:postcode":"85013",
    "sg:province":"AZ",
    "wof:name":"Morgan Chiropractic Ctr",
    "wof:placetype":"venue"
},
  "geometry": {"coordinates":[-112.082468,33.513889],"type":"Point"}
}