{
  "type": "Feature",
  "properties": {
    "iso:country":"US",
    "sg:address":"6951 W Emile Zola Ave",
    "sg:city":"Peoria",
    "sg:classifiers":[
        {
            "category":"Building & Trades",
            "subcategory":"Construction",
            "type":"Services"
        }
    ],
    "sg:phone":"+1 623 878 9883",
    "sg:postcode":"85381",
    "sg:province":"AZ",
    "sg:tags":[
        "excavation",
        "contractor"
    ],
    "wof:name":"Specialty Excavating",
    "wof:placetype":"venue"
},
  "geometry": {"coordinates":[-112.208324,33.607398],"type":"Point"}
}