{
  "type": "Feature",
  "properties": {
    "addr:full":"217 W Palmaire Ave Phoenix AZ 85021",
    "addr:housenumber":"217",
    "addr:postcode":"85021",
    "addr:street":"W Palmaire Ave",
    "iso:country":"US",
    "sg:address":"217 W Palmaire Ave",
    "sg:city":"Phoenix",
    "sg:classifiers":[
        {
            "category":"Professional",
            "subcategory":"Testing Lab",
            "type":"Services"
        }
    ],
    "sg:phone":"+1 602 861 1010",
    "sg:postcode":"85021",
    "sg:province":"AZ",
    "sg:tags":[
        "equipment",
        "electronic",
        "apparatus"
    ],
    "sg:website":"http://www.testsystems.com",
    "wof:name":"Test Systems Inc",
    "wof:placetype":"venue"
},
  "geometry": {"coordinates":[-112.076595,33.541531],"type":"Point"}
}