{
  "type": "Feature",
  "properties": {
    "addr:full":"940 N Solar Dr Vail AZ 85641",
    "addr:housenumber":"940",
    "addr:postcode":"85641",
    "addr:street":"N Solar Dr",
    "iso:country":"US",
    "sg:address":"940 N Solar Dr",
    "sg:city":"Vail",
    "sg:classifiers":[
        {
            "category":"Government",
            "subcategory":"Post Office",
            "type":"Public Place"
        }
    ],
    "sg:phone":"+1 520 762 5450",
    "sg:postcode":"85641",
    "sg:province":"AZ",
    "sg:tags":[
        "delivery",
        "courier"
    ],
    "sg:website":"http://www.machan.net",
    "wof:name":"Ajm Delivery Service",
    "wof:placetype":"venue"
},
  "geometry": {"coordinates":[-110.71727199999999,31.979975],"type":"Point"}
}