{
  "type": "Feature",
  "properties": {
    "iso:country":"US",
    "sg:address":"3108 E Holmes Ave",
    "sg:city":"Mesa",
    "sg:classifiers":[
        {
            "category":"Building & Trades",
            "subcategory":"Construction",
            "type":"Services"
        }
    ],
    "sg:phone":"+1 480 558 3598",
    "sg:postcode":"85204",
    "sg:province":"AZ",
    "sg:tags":[
        "contractor"
    ],
    "wof:name":"Shepherd Cleaning LLC",
    "wof:placetype":"venue"
},
  "geometry": {"coordinates":[-111.764696,33.388925],"type":"Point"}
}