{
  "type": "Feature",
  "properties": {
    "iso:country":"US",
    "sg:address":"1105 S Plaza Way",
    "sg:city":"Flagstaff",
    "sg:classifiers":[
        {
            "category":"Retail",
            "subcategory":"Self-service Laundry",
            "type":"Services"
        }
    ],
    "sg:phone":"+1 928 774 0390",
    "sg:postcode":"86001",
    "sg:province":"AZ",
    "wof:name":"Loggermat Laundry",
    "wof:placetype":"venue"
},
  "geometry": {"coordinates":[-111.661491,35.189366],"type":"Point"}
}