{
  "type": "Feature",
  "properties": {
    "iso:country":"US",
    "sg:address":"5806 W Market St",
    "sg:city":"Glendale",
    "sg:classifiers":[
        {
            "category":"Building & Trades",
            "subcategory":"Construction",
            "type":"Services"
        }
    ],
    "sg:phone":"+1 623 939 7867",
    "sg:postcode":"85301",
    "sg:province":"AZ",
    "sg:tags":[
        "pumping",
        "contractor"
    ],
    "wof:name":"Ace Commodities & Pumping",
    "wof:placetype":"venue"
},
  "geometry": {"coordinates":[-112.18373099999999,33.535474],"type":"Point"}
}