{
  "type": "Feature",
  "properties": {
    "iso:country":"US",
    "sg:address":"9189 E Indian Bend Rd",
    "sg:city":"Scottsdale",
    "sg:classifiers":[
        {
            "category":"Home & Garden",
            "subcategory":"Household Appliances",
            "type":"Retail Goods"
        }
    ],
    "sg:phone":"+1 480 951 6977",
    "sg:postcode":"85250",
    "sg:province":"AZ",
    "wof:name":"Viking Sewing Gallery",
    "wof:placetype":"venue"
},
  "geometry": {"coordinates":[-111.885847,33.538353],"type":"Point"}
}