{
  "type": "Feature",
  "properties": {
    "iso:country":"US",
    "sg:address":"1535 W Jefferson St",
    "sg:city":"Phoenix",
    "sg:classifiers":[
        {
            "category":"Government",
            "subcategory":"Office",
            "type":"Public Place"
        }
    ],
    "sg:phone":"+1 602 542 4351",
    "sg:postcode":"85007",
    "sg:province":"AZ",
    "sg:tags":[
        "government-united",
        "state"
    ],
    "sg:website":"http://www.eastpointehs.com",
    "wof:name":"School Finance Director",
    "wof:placetype":"venue"
},
  "geometry": {"coordinates":[-112.092141,33.447042],"type":"Point"}
}