{
  "type": "Feature",
  "properties": {
    "addr:full":"2048 E Indian School Rd Phoenix AZ 85016",
    "addr:housenumber":"2048",
    "addr:postcode":"85016",
    "addr:street":"E Indian School Rd",
    "iso:country":"US",
    "sg:address":"2048 E Indian School Rd",
    "sg:city":"Phoenix",
    "sg:classifiers":[
        {
            "category":"Retail",
            "subcategory":"Auto Repair",
            "type":"Services"
        }
    ],
    "sg:phone":"+1 602 277 7077",
    "sg:postcode":"85016",
    "sg:province":"AZ",
    "sg:tags":[
        "repairing",
        "automobile"
    ],
    "wof:name":"MD Classy Cars",
    "wof:placetype":"venue"
},
  "geometry": {"coordinates":[-112.03764099999999,33.494856],"type":"Point"}
}