{
  "type": "Feature",
  "properties": {
    "iso:country":"US",
    "sg:address":"13493 N 101st Way",
    "sg:city":"Scottsdale",
    "sg:classifiers":[
        {
            "category":"Wholesale",
            "subcategory":"Electrical",
            "type":"Manufacturing & Wholesale Goods"
        }
    ],
    "sg:phone":"+1 480 391 0226",
    "sg:postcode":"85260",
    "sg:province":"AZ",
    "sg:tags":[
        "equipment"
    ],
    "wof:name":"Whyle & Assoc",
    "wof:placetype":"venue"
},
  "geometry": {"coordinates":[-111.86412,33.608677],"type":"Point"}
}