{
  "type": "Feature",
  "properties": {
    "addr:full":"1440 S Euclid Ave Tucson AZ 85713",
    "addr:housenumber":"1440",
    "addr:postcode":"85713",
    "addr:street":"S Euclid Ave",
    "iso:country":"US",
    "sg:address":"1440 S Euclid Ave",
    "sg:city":"Tucson",
    "sg:classifiers":[
        {
            "category":"Recreation",
            "type":"Entertainment"
        },
        {
            "category":"Manufacturing",
            "subcategory":"Toys & Sporting Goods",
            "type":"Manufacturing & Wholesale Goods"
        }
    ],
    "sg:phone":"+1 520 624 6000",
    "sg:postcode":"85713",
    "sg:province":"AZ",
    "sg:tags":[
        "table",
        "parlor",
        "billiard",
        "mfg"
    ],
    "wof:name":"Connelly Billiard Mfg",
    "wof:placetype":"venue"
},
  "geometry": {"coordinates":[-110.95931899999999,32.203608],"type":"Point"}
}