{
  "type": "Feature",
  "properties": {
    "iso:country":"US",
    "sg:address":"5519 E Bloomfield Rd",
    "sg:city":"Scottsdale",
    "sg:classifiers":[
        {
            "category":"Real Estate",
            "subcategory":"Developer",
            "type":"Services"
        }
    ],
    "sg:phone":"+1 602 361 2027",
    "sg:postcode":"85254",
    "sg:province":"AZ",
    "wof:name":"Vendenlov Development",
    "wof:placetype":"venue"
},
  "geometry": {"coordinates":[-111.963107,33.599838],"type":"Point"}
}