{
  "type": "Feature",
  "properties": {
    "iso:country":"US",
    "sg:address":"14362 N Frank Lloyd Wright Blvd",
    "sg:city":"Scottsdale",
    "sg:classifiers":[
        {
            "category":"Professional",
            "subcategory":"Art Services",
            "type":"Services"
        }
    ],
    "sg:phone":"+1 480 477 7675",
    "sg:postcode":"85260",
    "sg:province":"AZ",
    "sg:tags":[
        "graphic",
        "designer"
    ],
    "wof:name":"Synergy Productions",
    "wof:placetype":"venue"
},
  "geometry": {"coordinates":[-111.87124799999999,33.616885],"type":"Point"}
}