{
  "type": "Feature",
  "properties": {
    "addr:full":"3120 N 19th Ave Ste 220 Phoenix AZ 85015",
    "addr:housenumber":"3120",
    "addr:postcode":"85015",
    "addr:street":"N 19Th Ave Ste 220",
    "iso:country":"US",
    "sg:address":"3120 N 19th Ave Ste 220",
    "sg:city":"Phoenix",
    "sg:classifiers":[
        {
            "category":"Home & Garden",
            "subcategory":"Furniture",
            "type":"Retail Goods"
        }
    ],
    "sg:phone":"+1 602 258 8491",
    "sg:postcode":"85015",
    "sg:province":"AZ",
    "sg:tags":[
        "store"
    ],
    "wof:name":"Orbit Furniture Mfg",
    "wof:placetype":"venue"
},
  "geometry": {"coordinates":[-112.099968,33.484784],"type":"Point"}
}