{
  "type": "Feature",
  "properties": {
    "addr:full":"12115 W Van Buren St Avondale AZ 85323",
    "addr:housenumber":"12115",
    "addr:postcode":"85323",
    "addr:street":"W Van Buren St",
    "iso:country":"US",
    "sg:address":"12115 W Van Buren St",
    "sg:city":"Avondale",
    "sg:classifiers":[
        {
            "category":"Real Estate",
            "subcategory":"Real Estate Operator",
            "type":"Services"
        }
    ],
    "sg:phone":"+1 623 882 2653",
    "sg:postcode":"85323",
    "sg:province":"AZ",
    "sg:tags":[
        "apartment"
    ],
    "sg:website":"www.coldwaterspringsapartments.com",
    "wof:name":"Coldwater Springs Apartments",
    "wof:placetype":"venue"
},
  "geometry": {"coordinates":[-112.32059099999999,33.449373],"type":"Point"}
}