{
  "type": "Feature",
  "properties": {
    "iso:country":"US",
    "sg:address":"2001 W Orange Grove Rd",
    "sg:city":"Tucson",
    "sg:classifiers":[
        {
            "category":"Health Services",
            "subcategory":"Medical Lab",
            "type":"Services"
        }
    ],
    "sg:phone":"+1 520 742 0206",
    "sg:postcode":"85704",
    "sg:province":"AZ",
    "sg:tags":[
        "laboratory"
    ],
    "wof:name":"Laboratory Corp Of America",
    "wof:placetype":"venue"
},
  "geometry": {"coordinates":[-111.010237,32.323065],"type":"Point"}
}