{
  "type": "Feature",
  "properties": {
    "iso:country":"US",
    "sg:address":"604 E Main St",
    "sg:city":"Avondale",
    "sg:classifiers":[
        {
            "category":"Retail",
            "subcategory":"Auto Repair",
            "type":"Services"
        }
    ],
    "sg:phone":"+1 623 932 2514",
    "sg:postcode":"85323",
    "sg:province":"AZ",
    "sg:tags":[
        "repairing",
        "automobile",
        "household",
        "appliance",
        "general"
    ],
    "wof:name":"Rhodes Auto Ctr LLC",
    "wof:placetype":"venue"
},
  "geometry": {"coordinates":[-112.341629,33.433699],"type":"Point"}
}