{
  "type": "Feature",
  "properties": {
    "iso:country":"US",
    "sg:address":"804 N Main St",
    "sg:city":"Cottonwood",
    "sg:classifiers":[
        {
            "category":"Professional",
            "subcategory":"Lawyer & Legal Services",
            "type":"Services"
        }
    ],
    "sg:phone":"+1 928 567 2350",
    "sg:postcode":"86326",
    "sg:province":"AZ",
    "sg:tags":[
        "attorney"
    ],
    "wof:name":"Richard M Grimsrud",
    "wof:placetype":"venue"
},
  "geometry": {"coordinates":[-112.02733600000001,34.746586],"type":"Point"}
}