{
  "type": "Feature",
  "properties": {
    "addr:full":"1423 N 27th Ln Phoenix AZ 85009",
    "addr:housenumber":"1423",
    "addr:postcode":"85009",
    "addr:street":"N 27Th Ln",
    "iso:country":"US",
    "sg:address":"1423 N 27th Ln",
    "sg:city":"Phoenix",
    "sg:classifiers":[
        {
            "category":"Wholesale",
            "subcategory":"Machinery & Supplies",
            "type":"Manufacturing & Wholesale Goods"
        }
    ],
    "sg:phone":"+1 602 484 9254",
    "sg:postcode":"85009",
    "sg:province":"AZ",
    "sg:tags":[
        "equipment",
        "sewing",
        "establishment"
    ],
    "wof:name":"Enriquez Materials & Quilting",
    "wof:placetype":"venue"
},
  "geometry": {"coordinates":[-112.118481,33.465702],"type":"Point"}
}