{
  "type": "Feature",
  "properties": {
    "iso:country":"US",
    "sg:address":"7342 E Lakeside Dr",
    "sg:city":"Tucson",
    "sg:classifiers":[
        {
            "category":"Health Services",
            "subcategory":"Clinic",
            "type":"Services"
        }
    ],
    "sg:phone":"+1 520 514 0738",
    "sg:postcode":"85730",
    "sg:province":"AZ",
    "wof:name":"Titan Health Management",
    "wof:placetype":"venue"
},
  "geometry": {"coordinates":[-110.8369,32.18122],"type":"Point"}
}