{
  "type": "Feature",
  "properties": {
    "iso:country":"US",
    "sg:address":"4342 W Country Gables Dr",
    "sg:city":"Glendale",
    "sg:classifiers":[
        {
            "category":"Building & Trades",
            "subcategory":"Construction",
            "type":"Services"
        }
    ],
    "sg:phone":"+1 602 547 8780",
    "sg:postcode":"85306",
    "sg:province":"AZ",
    "sg:tags":[
        "mobile",
        "home"
    ],
    "wof:name":"John Randel Mobile Home Svc",
    "wof:placetype":"venue"
},
  "geometry": {"coordinates":[-112.154574,33.621711],"type":"Point"}
}