{
  "type": "Feature",
  "properties": {
    "addr:full":"16050 N 76th St Scottsdale AZ 85260",
    "addr:housenumber":"16050",
    "addr:postcode":"85260",
    "addr:street":"N 76Th St",
    "iso:country":"US",
    "sg:address":"16050 N 76th St",
    "sg:city":"Scottsdale",
    "sg:classifiers":[
        {
            "category":"Autos & Motor Vehicles",
            "subcategory":"Automobile Sales",
            "type":"Retail Goods"
        }
    ],
    "sg:phone":"+1 480 607 1250",
    "sg:postcode":"85260",
    "sg:province":"AZ",
    "sg:tags":[
        "used"
    ],
    "wof:name":"Fred Okasick Sales",
    "wof:placetype":"venue"
},
  "geometry": {"coordinates":[-111.916865,33.632499],"type":"Point"}
}