{
  "type": "Feature",
  "properties": {
    "addr:full":"1724 S 6th Ave Tucson AZ 85713",
    "addr:housenumber":"1724",
    "addr:postcode":"85713",
    "addr:street":"S 6Th Ave",
    "iso:country":"US",
    "sg:address":"1724 S 6th Ave",
    "sg:city":"Tucson",
    "sg:classifiers":[
        {
            "category":"Retail",
            "subcategory":"Auto Rental",
            "type":"Services"
        }
    ],
    "sg:phone":"+1 520 620 0490",
    "sg:postcode":"85713",
    "sg:province":"AZ",
    "sg:tags":[
        "renting",
        "truck",
        "leasing"
    ],
    "wof:name":"U-Haul Co",
    "wof:placetype":"venue"
},
  "geometry": {"coordinates":[-110.968513,32.200838],"type":"Point"}
}