{
  "type": "Feature",
  "properties": {
    "iso:country":"US",
    "sg:address":"21522 N 57th Ave",
    "sg:city":"Glendale",
    "sg:classifiers":[
        {
            "category":"Shopping",
            "type":"Retail Goods"
        }
    ],
    "sg:phone":"+1 623 412 7788",
    "sg:postcode":"85308",
    "sg:province":"AZ",
    "sg:tags":[
        "art",
        "gallery",
        "dealer"
    ],
    "wof:name":"Carol's Art Gallery",
    "wof:placetype":"venue"
},
  "geometry": {"coordinates":[-112.182942,33.679052],"type":"Point"}
}