{
  "type": "Feature",
  "properties": {
    "iso:country":"US",
    "sg:address":"1711 E Missouri Ave",
    "sg:city":"Phoenix",
    "sg:classifiers":[
        {
            "category":"Arena",
            "subcategory":"Sports Club",
            "type":"Entertainment"
        }
    ],
    "sg:phone":"+1 602 692 5937",
    "sg:postcode":"85016",
    "sg:province":"AZ",
    "sg:tags":[
        "health"
    ],
    "wof:name":"Specific Fitness",
    "wof:placetype":"venue"
},
  "geometry": {"coordinates":[-112.045095,33.516481],"type":"Point"}
}