{
  "type": "Feature",
  "properties": {
    "iso:country":"US",
    "sg:address":"3119 W Mcrae Way",
    "sg:city":"Phoenix",
    "sg:classifiers":[
        {
            "category":"Building & Trades",
            "subcategory":"Landscaping Services",
            "type":"Services"
        }
    ],
    "sg:phone":"+1 623 780 2210",
    "sg:postcode":"85027",
    "sg:province":"AZ",
    "sg:tags":[
        "arborist",
        "tree"
    ],
    "wof:name":"American Arborist",
    "wof:placetype":"venue"
},
  "geometry": {"coordinates":[-112.126973,33.655313],"type":"Point"}
}