{
  "type": "Feature",
  "properties": {
    "iso:country":"US",
    "sg:address":"2560 E Cll Sin Pecado",
    "sg:city":"Tucson",
    "sg:classifiers":[
        {
            "category":"Building & Trades",
            "subcategory":"Construction",
            "type":"Services"
        }
    ],
    "sg:phone":"+1 520 575 8594",
    "sg:postcode":"85718",
    "sg:province":"AZ",
    "sg:tags":[
        "house",
        "general",
        "contractor"
    ],
    "wof:name":"Lutz Construction Inc",
    "wof:placetype":"venue"
},
  "geometry": {"coordinates":[-110.93371500000001,32.337773],"type":"Point"}
}