{
  "type": "Feature",
  "properties": {
    "addr:full":"20446 N 30th Dr Phoenix AZ 85027",
    "addr:housenumber":"20446",
    "addr:postcode":"85027",
    "addr:street":"N 30Th Dr",
    "iso:country":"US",
    "sg:address":"20446 N 30th Dr",
    "sg:city":"Phoenix",
    "sg:classifiers":[
        {
            "category":"Shopping",
            "subcategory":"Computers & Home Electronics",
            "type":"Retail Goods"
        }
    ],
    "sg:phone":"+1 623 580 9103",
    "sg:postcode":"85027",
    "sg:province":"AZ",
    "sg:tags":[
        "equipment",
        "audio-visual"
    ],
    "wof:name":"Projector Discount Store",
    "wof:placetype":"venue"
},
  "geometry": {"coordinates":[-112.125137,33.672459],"type":"Point"}
}