{
  "type": "Feature",
  "properties": {
    "iso:country":"US",
    "sg:address":"231 S 49th Ave",
    "sg:city":"Phoenix",
    "sg:classifiers":[
        {
            "category":"Freight",
            "type":"Transportation"
        }
    ],
    "sg:phone":"+1 602 278 0500",
    "sg:postcode":"85043",
    "sg:province":"AZ",
    "sg:tags":[
        "broker"
    ],
    "wof:name":"Mosqueda Transport",
    "wof:placetype":"venue"
},
  "geometry": {"coordinates":[-112.16598500000001,33.445993],"type":"Point"}
}