{
  "type": "Feature",
  "properties": {
    "iso:country":"US",
    "sg:address":"8230 N el Mirage Rd",
    "sg:city":"El Mirage",
    "sg:classifiers":[
        {
            "category":"Manufacturing",
            "subcategory":"Motor Vehicles & Parts",
            "type":"Manufacturing & Wholesale Goods"
        }
    ],
    "sg:phone":"+1 623 535 7700",
    "sg:postcode":"85335",
    "sg:province":"AZ",
    "sg:tags":[
        "equipment",
        "transportation",
        "mfg"
    ],
    "wof:name":"Haulmark Industries of Arizona",
    "wof:placetype":"venue"
},
  "geometry": {"coordinates":[-112.324369,33.551179],"type":"Point"}
}