{
  "type": "Feature",
  "properties": {
    "iso:country":"US",
    "sg:address":"4016 E Cortez St",
    "sg:city":"Phoenix",
    "sg:classifiers":[
        {
            "category":"Shopping",
            "subcategory":"Pharmacy",
            "type":"Retail Goods"
        }
    ],
    "sg:phone":"+1 602 867 0342",
    "sg:postcode":"85028",
    "sg:province":"AZ",
    "wof:name":"Coast To Coast Mortgage",
    "wof:placetype":"venue"
},
  "geometry": {"coordinates":[-111.994576,33.592524],"type":"Point"}
}