{
  "type": "Feature",
  "properties": {
    "iso:country":"US",
    "sg:address":"2330 S 4th Ave",
    "sg:city":"Yuma",
    "sg:classifiers":[
        {
            "category":"Autos & Motor Vehicles",
            "subcategory":"Auto Supplies",
            "type":"Retail Goods"
        },
        {
            "category":"Wholesale",
            "subcategory":"Auto Parts",
            "type":"Manufacturing & Wholesale Goods"
        }
    ],
    "sg:phone":"+1 928 783 5176",
    "sg:postcode":"85364",
    "sg:province":"AZ",
    "sg:tags":[
        "body",
        "automobile",
        "truck",
        "equipment",
        "accessory"
    ],
    "sg:website":"http://www.oreillyauto.com?utm_source=yellowpages&utm_medium=iyp&utm_campaign=2803",
    "wof:name":"O'Reilly Checker Auto Parts",
    "wof:placetype":"venue"
},
  "geometry": {"coordinates":[-114.623955,32.671545],"type":"Point"}
}