{
  "type": "Feature",
  "properties": {
    "iso:country":"US",
    "sg:address":"5026 E Main St",
    "sg:city":"Mesa",
    "sg:classifiers":[
        {
            "category":"Retail",
            "subcategory":"Auto Repair",
            "type":"Services"
        }
    ],
    "sg:phone":"+1 480 830 1110",
    "sg:postcode":"85205",
    "sg:province":"AZ",
    "sg:tags":[
        "transmission"
    ],
    "sg:website":"www.aamco.com",
    "wof:name":"AAMCO Transmissions",
    "wof:placetype":"venue"
},
  "geometry": {"coordinates":[-111.72056499999999,33.415627],"type":"Point"}
}