{
  "type": "Feature",
  "properties": {
    "addr:full":"20265 N 59th Ave Glendale AZ 85308",
    "addr:housenumber":"20265",
    "addr:postcode":"85308",
    "addr:street":"N 59Th Ave",
    "iso:country":"US",
    "sg:address":"20265 N 59th Ave",
    "sg:city":"Glendale",
    "sg:classifiers":[
        {
            "category":"Shopping",
            "subcategory":"Gifts & Souvenirs",
            "type":"Retail Goods"
        }
    ],
    "sg:phone":"+1 623 362 1744",
    "sg:postcode":"85308",
    "sg:province":"AZ",
    "wof:name":"Annies Hallmark Gold Crown",
    "wof:placetype":"venue"
},
  "geometry": {"coordinates":[-112.186671,33.66897],"type":"Point"}
}