{
  "type": "Feature",
  "properties": {
    "iso:country":"US",
    "sg:address":"5425 S Mitchell Dr",
    "sg:city":"Tempe",
    "sg:classifiers":[
        {
            "category":"Shopping",
            "subcategory":"Clothing, Apparel, & Fashions",
            "type":"Retail Goods"
        }
    ],
    "sg:phone":"+1 480 345 8796",
    "sg:postcode":"85283",
    "sg:province":"AZ",
    "sg:tags":[
        "t"
    ],
    "wof:name":"Amertex",
    "wof:placetype":"venue"
},
  "geometry": {"coordinates":[-111.950222,33.375738],"type":"Point"}
}