{
  "type": "Feature",
  "properties": {
    "addr:full":"345 S Arizona Blvd Coolidge AZ 85228",
    "addr:housenumber":"345",
    "addr:postcode":"85228",
    "addr:street":"S Arizona Blvd",
    "iso:country":"US",
    "sg:address":"345 S Arizona Blvd",
    "sg:city":"Coolidge",
    "sg:classifiers":[
        {
            "category":"Real Estate",
            "subcategory":"Real Estate Agent",
            "type":"Services"
        }
    ],
    "sg:phone":"+1 520 723 0021",
    "sg:postcode":"85228",
    "sg:province":"AZ",
    "wof:name":"Century 21 Desert Casa",
    "wof:placetype":"venue"
},
  "geometry": {"coordinates":[-111.52392999999999,32.975075],"type":"Point"}
}