{
  "type": "Feature",
  "properties": {
    "iso:country":"US",
    "sg:address":"410 N Grand Canyon Blvd",
    "sg:city":"Williams",
    "sg:classifiers":[
        {
            "category":"Banks & Credit Unions",
            "subcategory":"Financial Services",
            "type":"Services"
        }
    ],
    "sg:phone":"+1 928 635 1212",
    "sg:postcode":"86046",
    "sg:province":"AZ",
    "sg:tags":[
        "trust",
        "investment",
        "real estate"
    ],
    "wof:name":"Blue Cloud RE & Dev LLC",
    "wof:placetype":"venue"
},
  "geometry": {"coordinates":[-112.189911,35.253618],"type":"Point"}
}