{
  "type": "Feature",
  "properties": {
    "iso:country":"US",
    "sg:address":"37636 N Tom Darlington",
    "sg:city":"Carefree",
    "sg:classifiers":[
        {
            "category":"Restaurant",
            "type":"Food & Drink"
        },
        {
            "category":"Food & Beverages",
            "subcategory":"Bakery",
            "type":"Retail Goods"
        }
    ],
    "sg:phone":"+1 480 824 1500",
    "sg:postcode":"85377",
    "sg:province":"AZ",
    "sg:tags":[
        "sandwich",
        "pizza"
    ],
    "sg:website":"www.thebaddonkey.com/",
    "wof:name":"Bad Donkey Sub, Salad & Pizza Co.",
    "wof:placetype":"venue"
},
  "geometry": {"coordinates":[-111.92373499999999,33.827208],"type":"Point"}
}