{
  "type": "Feature",
  "properties": {
    "iso:country":"US",
    "sg:address":"18409 N Cave Creek Rd S2",
    "sg:city":"Phoenix",
    "sg:classifiers":[
        {
            "category":"Professional",
            "subcategory":"Management & Consulting",
            "type":"Services"
        }
    ],
    "sg:phone":"+1 602 617 2412",
    "sg:postcode":"85032",
    "sg:province":"AZ",
    "sg:tags":[
        "consultant",
        "educational"
    ],
    "wof:name":"Serendipity Educational Resources, Inc.",
    "wof:placetype":"venue"
},
  "geometry": {"coordinates":[-112.030868,33.653835],"type":"Point"}
}