{
  "type": "Feature",
  "properties": {
    "iso:country":"US",
    "sg:address":"9802 N 46th St",
    "sg:city":"Phoenix",
    "sg:classifiers":[
        {
            "category":"Professional",
            "subcategory":"Art Services",
            "type":"Services"
        }
    ],
    "sg:phone":"+1 480 648 2254",
    "sg:postcode":"85028",
    "sg:province":"AZ",
    "sg:tags":[
        "graphic",
        "commercial",
        "designer",
        "artist"
    ],
    "sg:website":"http://www.klinephoenixgraphics.com",
    "wof:name":"Kline-Phoenix Advertising Graphics",
    "wof:placetype":"venue"
},
  "geometry": {"coordinates":[-111.98133799999999,33.575321],"type":"Point"}
}