{
  "type": "Feature",
  "properties": {
    "iso:country":"US",
    "sg:address":"706 N Country Club Rd",
    "sg:city":"Tucson",
    "sg:classifiers":[
        {
            "category":"Health Services",
            "subcategory":"Doctor",
            "type":"Services"
        }
    ],
    "sg:phone":"+1 520 325 1111",
    "sg:postcode":"85716",
    "sg:province":"AZ",
    "sg:tags":[
        "physician",
        "surgeon"
    ],
    "wof:name":"R L Winsky Jr MD",
    "wof:placetype":"venue"
},
  "geometry": {"coordinates":[-110.926636,32.230477],"type":"Point"}
}