{
  "type": "Feature",
  "properties": {
    "iso:country":"US",
    "sg:address":"8712 E Via de Commercio",
    "sg:city":"Scottsdale",
    "sg:classifiers":[
        {
            "category":"Health Services",
            "subcategory":"Chiropractor",
            "type":"Services"
        }
    ],
    "sg:phone":"+1 480 951 4464",
    "sg:postcode":"85258",
    "sg:province":"AZ",
    "wof:name":"Mc Cormick Ranch Chiropractic",
    "wof:placetype":"venue"
},
  "geometry": {"coordinates":[-111.892933,33.551313],"type":"Point"}
}