{
  "type": "Feature",
  "properties": {
    "addr:full":"1871 W Prince Rd Tucson AZ 85705",
    "addr:housenumber":"1871",
    "addr:postcode":"85705",
    "addr:street":"W Prince Rd",
    "iso:country":"US",
    "sg:address":"1871 W Prince Rd",
    "sg:city":"Tucson",
    "sg:classifiers":[
        {
            "category":"Building & Trades",
            "subcategory":"Plumbing",
            "type":"Services"
        }
    ],
    "sg:phone":"+1 520 744 9192",
    "sg:postcode":"85705",
    "sg:province":"AZ",
    "sg:tags":[
        "contractor"
    ],
    "wof:name":"Ambient Air Htg & Coolg LLC",
    "wof:placetype":"venue"
},
  "geometry": {"coordinates":[-111.006032,32.272322],"type":"Point"}
}