{
  "type": "Feature",
  "properties": {
    "iso:country":"US",
    "sg:address":"1734 W Bell Rd",
    "sg:city":"Phoenix",
    "sg:classifiers":[
        {
            "category":"Professional",
            "type":"Services"
        }
    ],
    "sg:phone":"+1 602 938 4605",
    "sg:postcode":"85023",
    "sg:province":"AZ",
    "sg:tags":[
        "caterer"
    ],
    "wof:name":"5 Kids Catering",
    "wof:placetype":"venue"
},
  "geometry": {"coordinates":[-112.097086,33.640221],"type":"Point"}
}