{
  "type": "Feature",
  "properties": {
    "addr:full":"3710 E University Dr # 1 Phoenix AZ 85034",
    "addr:housenumber":"3710",
    "addr:postcode":"85034",
    "addr:street":"E University Dr # 1",
    "iso:country":"US",
    "sg:address":"3710 E University Dr # 1",
    "sg:city":"Phoenix",
    "sg:classifiers":[
        {
            "category":"Professional",
            "subcategory":"Computer Services",
            "type":"Services"
        },
        {
            "category":"Internet Cafe",
            "subcategory":"None",
            "type":"Food & Drink"
        }
    ],
    "sg:phone":"+1 602 470 0300",
    "sg:postcode":"85034",
    "sg:province":"AZ",
    "sg:tags":[
        "product",
        "software"
    ],
    "wof:name":"Auralog, Inc.",
    "wof:placetype":"venue"
},
  "geometry": {"coordinates":[-112.00158399999999,33.421764],"type":"Point"}
}