{
  "type": "Feature",
  "properties": {
    "iso:country":"US",
    "sg:address":"39414 N Daisy Mountain Dr",
    "sg:city":"Phoenix",
    "sg:classifiers":[
        {
            "category":"Food & Beverages",
            "subcategory":"Groceries & Convenience Stores",
            "type":"Retail Goods"
        }
    ],
    "sg:phone":"+1 623 551 1542",
    "sg:postcode":"85086",
    "sg:province":"AZ",
    "sg:website":"http://www.circlek.com",
    "wof:name":"Circle K",
    "wof:placetype":"venue"
},
  "geometry": {"coordinates":[-112.137939,33.842742],"type":"Point"}
}