{
  "type": "Feature",
  "properties": {
    "iso:country":"US",
    "sg:address":"10338 E Akron St",
    "sg:city":"Apache Junction",
    "sg:classifiers":[
        {
            "category":"Building & Trades",
            "subcategory":"Landscaping Services",
            "type":"Services"
        }
    ],
    "sg:phone":"+1 480 984 4612",
    "sg:postcode":"85220",
    "sg:province":"AZ",
    "sg:tags":[
        "landscape"
    ],
    "wof:name":"Windells Landscape",
    "wof:placetype":"venue"
},
  "geometry": {"coordinates":[-111.605161,33.4173],"type":"Point"}
}