{
  "type": "Feature",
  "properties": {
    "addr:full":"7016 W Hearn Rd Peoria AZ 85381",
    "addr:housenumber":"7016",
    "addr:postcode":"85381",
    "addr:street":"W Hearn Rd",
    "iso:country":"US",
    "sg:address":"7016 W Hearn Rd",
    "sg:city":"Peoria",
    "sg:classifiers":[
        {
            "category":"Real Estate",
            "subcategory":"Real Estate Services",
            "type":"Services"
        },
        {
            "category":"Building & Trades",
            "subcategory":"Cleaning & Sanitation",
            "type":"Services"
        }
    ],
    "sg:phone":"+1 623 512 0492",
    "sg:postcode":"85381",
    "sg:province":"AZ",
    "sg:tags":[
        "maintenance",
        "cleaners-interior"
    ],
    "wof:name":"Maintenance & More",
    "wof:placetype":"venue"
},
  "geometry": {"coordinates":[-112.209965,33.614203],"type":"Point"}
}