{
  "type": "Feature",
  "properties": {
    "iso:country":"US",
    "sg:address":"7054 E 5th Ave",
    "sg:city":"Scottsdale",
    "sg:classifiers":[
        {
            "category":"Shopping",
            "type":"Retail Goods"
        },
        {
            "category":"Shopping",
            "subcategory":"Books",
            "type":"Retail Goods"
        }
    ],
    "sg:phone":"+1 480 675 0444",
    "sg:postcode":"85251",
    "sg:province":"AZ",
    "sg:tags":[
        "metaphysical",
        "supply"
    ],
    "wof:name":"Creative Body & Mind",
    "wof:placetype":"venue"
},
  "geometry": {"coordinates":[-111.92906000000001,33.497923],"type":"Point"}
}