{
  "type": "Feature",
  "properties": {
    "iso:country":"US",
    "sg:address":"901 N San Francisco St",
    "sg:city":"Flagstaff",
    "sg:classifiers":[
        {
            "category":"Health Services",
            "subcategory":"Clinic",
            "type":"Services"
        }
    ],
    "sg:phone":"+1 928 773 2238",
    "sg:postcode":"86001",
    "sg:province":"AZ",
    "sg:tags":[
        "home"
    ],
    "wof:name":"Northern Arizona Homecare",
    "wof:placetype":"venue"
},
  "geometry": {"coordinates":[-111.643837,35.206302],"type":"Point"}
}