{
  "type": "Feature",
  "properties": {
    "addr:full":"6303 S Rural Rd Tempe AZ 85283",
    "addr:housenumber":"6303",
    "addr:postcode":"85283",
    "addr:street":"S Rural Rd",
    "iso:country":"US",
    "sg:address":"6303 S Rural Rd",
    "sg:city":"Tempe",
    "sg:classifiers":[
        {
            "category":"Insurance",
            "subcategory":"Insurance Agent",
            "type":"Services"
        }
    ],
    "sg:phone":"+1 480 839 3345",
    "sg:postcode":"85283",
    "sg:province":"AZ",
    "sg:tags":[
        "agency"
    ],
    "wof:name":"Farmers Insurance",
    "wof:placetype":"venue"
},
  "geometry": {"coordinates":[-111.928524,33.363783],"type":"Point"}
}