{
  "type": "Feature",
  "properties": {
    "iso:country":"US",
    "sg:address":"3855 S Evans Blvd",
    "sg:city":"Tucson",
    "sg:classifiers":[
        {
            "category":"Building & Trades",
            "subcategory":"Plumbing",
            "type":"Services"
        },
        {
            "category":"Manufacturing",
            "subcategory":"Tools & Machinery",
            "type":"Manufacturing & Wholesale Goods"
        }
    ],
    "sg:phone":"+1 520 622 0907",
    "sg:postcode":"85714",
    "sg:province":"AZ",
    "sg:tags":[
        "repair",
        "mfg",
        "system",
        "contractor",
        "refrigeration",
        "conditioning",
        "air"
    ],
    "wof:name":"Pro Services",
    "wof:placetype":"venue"
},
  "geometry": {"coordinates":[-110.95352,32.176899],"type":"Point"}
}