{
  "type": "Feature",
  "properties": {
    "addr:full":"4930 E Main St Mesa AZ 85205",
    "addr:housenumber":"4930",
    "addr:postcode":"85205",
    "addr:street":"E Main St",
    "iso:country":"US",
    "sg:address":"4930 E Main St",
    "sg:city":"Mesa",
    "sg:classifiers":[
        {
            "category":"Retail",
            "subcategory":"Auto Rental",
            "type":"Services"
        }
    ],
    "sg:phone":"+1 480 981 6746",
    "sg:postcode":"85205",
    "sg:province":"AZ",
    "sg:tags":[
        "renting",
        "automobile"
    ],
    "wof:name":"Enterprise Rent A Car",
    "wof:placetype":"venue"
},
  "geometry": {"coordinates":[-111.724403,33.415621],"type":"Point"}
}