{
  "type": "Feature",
  "properties": {
    "addr:full":"1462 Gemini St Fort Mohave AZ 86426",
    "addr:housenumber":"1462",
    "addr:postcode":"86426",
    "addr:street":"Gemini St",
    "iso:country":"US",
    "sg:address":"1462 Gemini St",
    "sg:city":"Fort Mohave",
    "sg:classifiers":[
        {
            "category":"Restaurant",
            "type":"Food & Drink"
        }
    ],
    "sg:phone":"+1 928 763 2990",
    "sg:postcode":"86426",
    "sg:province":"AZ",
    "sg:tags":[
        "eating"
    ],
    "wof:name":"Sonic Drive-In",
    "wof:placetype":"venue"
},
  "geometry": {"coordinates":[-114.597021,35.020591],"type":"Point"}
}