{
  "type": "Feature",
  "properties": {
    "addr:full":"1825 E Guadalupe Road Suite 108 Tempe AZ 85283",
    "addr:housenumber":"1825",
    "addr:postcode":"85283",
    "addr:street":"E Guadalupe Road Suite 108",
    "iso:country":"US",
    "sg:address":"1825 E Guadalupe Road Suite 108",
    "sg:city":"Tempe",
    "sg:classifiers":[
        {
            "category":"Shopping",
            "subcategory":"Clothing, Apparel, & Fashions",
            "type":"Retail Goods"
        },
        {
            "category":"Sports & Exercise",
            "subcategory":"Bicycle Rental",
            "type":"Entertainment"
        }
    ],
    "sg:phone":"+1 480 777 2535",
    "sg:postcode":"85283",
    "sg:province":"AZ",
    "sg:tags":[
        "accessory",
        "clothing",
        "wear",
        "women's"
    ],
    "sg:website":"www.whatwomenwantswimwear.com/",
    "wof:name":"What Women Want Swimwear",
    "wof:placetype":"venue"
},
  "geometry": {"coordinates":[-111.910079,33.363857],"type":"Point"}
}