{
  "type": "Feature",
  "properties": {
    "iso:country":"US",
    "sg:address":"2122 W 5th Pl",
    "sg:city":"Tempe",
    "sg:classifiers":[
        {
            "category":"Shopping",
            "subcategory":"Hobbies, Toys, & Games",
            "type":"Retail Goods"
        }
    ],
    "sg:phone":"+1 480 726 7519",
    "sg:postcode":"85281",
    "sg:province":"AZ",
    "sg:tags":[
        "toy",
        "store",
        "supply"
    ],
    "wof:name":"Aero Model Hacker Brushless",
    "wof:placetype":"venue"
},
  "geometry": {"coordinates":[-111.972381,33.425072],"type":"Point"}
}