{
  "type": "Feature",
  "properties": {
    "iso:country":"US",
    "sg:address":"31 W Lone Cactus Dr",
    "sg:city":"Phoenix",
    "sg:classifiers":[
        {
            "category":"Building & Trades",
            "subcategory":"Construction",
            "type":"Services"
        }
    ],
    "sg:phone":"+1 623 516 8865",
    "sg:postcode":"85027",
    "sg:province":"AZ",
    "sg:tags":[
        "general",
        "contractor"
    ],
    "wof:name":"ADS Construction",
    "wof:placetype":"venue"
},
  "geometry": {"coordinates":[-112.07443600000001,33.680785],"type":"Point"}
}