{
  "type": "Feature",
  "properties": {
    "iso:country":"US",
    "sg:address":"7075 W Bell Rd",
    "sg:city":"Glendale",
    "sg:classifiers":[
        {
            "category":"Insurance",
            "subcategory":"Insurance Agent",
            "type":"Services"
        }
    ],
    "sg:phone":"+1 623 486 2322",
    "sg:postcode":"85308",
    "sg:province":"AZ",
    "wof:name":"Farmers Insurance Group",
    "wof:placetype":"venue"
},
  "geometry": {"coordinates":[-112.212602,33.638183],"type":"Point"}
}