{
  "type": "Feature",
  "properties": {
    "addr:full":"3101 N Central Ave Ste 1500 Phoenix AZ 85012",
    "addr:housenumber":"3101",
    "addr:postcode":"85012",
    "addr:street":"N Central Ave Ste 1500",
    "iso:country":"US",
    "sg:address":"3101 N Central Ave Ste 1500",
    "sg:city":"Phoenix",
    "sg:classifiers":[
        {
            "category":"Social Services",
            "subcategory":"Child Care",
            "type":"Services"
        },
        {
            "category":"Professional",
            "subcategory":"Lawyer & Legal Services",
            "type":"Services"
        }
    ],
    "sg:phone":"+1 866 965 6421",
    "sg:postcode":"85012",
    "sg:province":"AZ",
    "sg:tags":[
        "attorney",
        "practice",
        "adoption",
        "family",
        "law"
    ],
    "sg:website":"http://www.azadoptionhelp.com",
    "wof:name":"Moore, Kerry Beth",
    "wof:placetype":"venue"
},
  "geometry": {"coordinates":[-112.07369199999999,33.483879],"type":"Point"}
}