{
  "type": "Feature",
  "properties": {
    "iso:country":"US",
    "sg:address":"2929 E Main St",
    "sg:city":"Mesa",
    "sg:classifiers":[
        {
            "category":"Professional",
            "type":"Services"
        }
    ],
    "sg:phone":"+1 480 854 8594",
    "sg:postcode":"85213",
    "sg:province":"AZ",
    "sg:tags":[
        "establishment"
    ],
    "wof:name":"Bold Technology-Glen Butler",
    "wof:placetype":"venue"
},
  "geometry": {"coordinates":[-111.766729,33.415397],"type":"Point"}
}