{
  "type": "Feature",
  "properties": {
    "iso:country":"US",
    "sg:address":"104 E Elliot Rd",
    "sg:city":"Gilbert",
    "sg:classifiers":[
        {
            "category":"Building & Trades",
            "subcategory":"Construction",
            "type":"Services"
        }
    ],
    "sg:phone":"+1 480 926 5290",
    "sg:postcode":"85234",
    "sg:province":"AZ",
    "sg:tags":[
        "system",
        "specialty",
        "heating",
        "contractor",
        "air conditioning"
    ],
    "wof:name":"Asap Air Conditionaing",
    "wof:placetype":"venue"
},
  "geometry": {"coordinates":[-111.786478,33.350105],"type":"Point"}
}