{
  "type": "Feature",
  "properties": {
    "iso:country":"US",
    "sg:address":"1441 W Dove Way",
    "sg:city":"Amado",
    "sg:classifiers":[
        {
            "category":"Building & Trades",
            "subcategory":"Construction",
            "type":"Services"
        }
    ],
    "sg:phone":"+1 520 625 9467",
    "sg:postcode":"85645",
    "sg:province":"AZ",
    "sg:tags":[
        "specializing",
        "general",
        "safety",
        "health",
        "home",
        "contractor"
    ],
    "wof:name":"Esry Construction",
    "wof:placetype":"venue"
},
  "geometry": {"coordinates":[-110.99945200000001,31.748132],"type":"Point"}
}