{
  "type": "Feature",
  "properties": {
    "iso:country":"US",
    "sg:address":"5450 E Pershing Ave",
    "sg:city":"Scottsdale",
    "sg:classifiers":[
        {
            "category":"Building & Trades",
            "subcategory":"Construction",
            "type":"Services"
        }
    ],
    "sg:phone":"+1 602 953 9184",
    "sg:postcode":"85254",
    "sg:province":"AZ",
    "sg:tags":[
        "contractor"
    ],
    "wof:name":"Neubauer Masonry",
    "wof:placetype":"venue"
},
  "geometry": {"coordinates":[-111.96147499999999,33.606248],"type":"Point"}
}