{
  "type": "Feature",
  "properties": {
    "iso:country":"US",
    "sg:address":"5870 E Broadway Blvd",
    "sg:city":"Tucson",
    "sg:classifiers":[
        {
            "category":"Utilities",
            "subcategory":"Mobile Phone",
            "type":"Services"
        }
    ],
    "sg:phone":"+1 520 748 0031",
    "sg:postcode":"85711",
    "sg:province":"AZ",
    "sg:tags":[
        "telephone",
        "cellular"
    ],
    "wof:name":"Nextel",
    "wof:placetype":"venue"
},
  "geometry": {"coordinates":[-110.866828,32.221501],"type":"Point"}
}