{
  "type": "Feature",
  "properties": {
    "iso:country":"US",
    "sg:address":"2304 N 4th St",
    "sg:city":"Flagstaff",
    "sg:classifiers":[
        {
            "category":"Wholesale",
            "subcategory":"Electrical",
            "type":"Manufacturing & Wholesale Goods"
        }
    ],
    "sg:phone":"+1 928 522 8516",
    "sg:postcode":"86004",
    "sg:province":"AZ",
    "sg:tags":[
        "control",
        "security",
        "system"
    ],
    "wof:name":"Aspen Alarm Systems Inc",
    "wof:placetype":"venue"
},
  "geometry": {"coordinates":[-111.613398,35.211598],"type":"Point"}
}