{
  "type": "Feature",
  "properties": {
    "addr:full":"1301 E University Blvd Tucson AZ 85719",
    "addr:housenumber":"1301",
    "addr:postcode":"85719",
    "addr:street":"E University Blvd",
    "iso:country":"US",
    "sg:address":"1301 E University Blvd",
    "sg:city":"Tucson",
    "sg:classifiers":[
        {
            "category":"Professional",
            "subcategory":"Business Services",
            "type":"Services"
        }
    ],
    "sg:phone":"+1 928 213 8686",
    "sg:postcode":"85719",
    "sg:province":"AZ",
    "sg:tags":[
        "automobile",
        "appraiser"
    ],
    "wof:name":"Property Damage Appraisers Inc",
    "wof:placetype":"venue"
},
  "geometry": {"coordinates":[-110.948132,32.231727],"type":"Point"}
}