{
  "type": "Feature",
  "properties": {
    "iso:country":"US",
    "sg:address":"1115 Stockton Hill Rd",
    "sg:city":"Kingman",
    "sg:classifiers":[
        {
            "category":"Insurance",
            "subcategory":"Insurance Agent",
            "type":"Services"
        }
    ],
    "sg:phone":"+1 928 753 4700",
    "sg:postcode":"86401",
    "sg:province":"AZ",
    "wof:name":"Erin P Collins & Assoc",
    "wof:placetype":"venue"
},
  "geometry": {"coordinates":[-114.033325,35.199392],"type":"Point"}
}