{
  "type": "Feature",
  "properties": {
    "iso:country":"US",
    "sg:address":"1451 Heritage Ln",
    "sg:city":"Holbrook",
    "sg:classifiers":[
        {
            "category":"Professional",
            "subcategory":"Detective & Security Services",
            "type":"Services"
        }
    ],
    "sg:phone":"+1 928 241 1524",
    "sg:postcode":"86025",
    "sg:province":"AZ",
    "sg:tags":[
        "information",
        "bureau"
    ],
    "wof:name":"Ctrp Services",
    "wof:placetype":"venue"
},
  "geometry": {"coordinates":[-110.254256,34.886418],"type":"Point"}
}