{
  "type": "Feature",
  "properties": {
    "iso:country":"US",
    "sg:address":"3580 W Ironwood Meadows Pl",
    "sg:city":"Tucson",
    "sg:classifiers":[
        {
            "category":"Retail",
            "subcategory":"Animal Services",
            "type":"Services"
        }
    ],
    "sg:phone":"+1 520 572 1467",
    "sg:postcode":"85742",
    "sg:province":"AZ",
    "sg:tags":[
        "pet",
        "exercising",
        "sitting"
    ],
    "wof:name":"Arizona Rainbow Pet Services",
    "wof:placetype":"venue"
},
  "geometry": {"coordinates":[-111.043578,32.371447],"type":"Point"}
}