{
  "type": "Feature",
  "properties": {
    "iso:country":"US",
    "sg:address":"1446 S Burlington St",
    "sg:city":"Flagstaff",
    "sg:classifiers":[
        {
            "category":"Building & Trades",
            "subcategory":"Construction",
            "type":"Services"
        }
    ],
    "sg:phone":"+1 928 779 3328",
    "sg:postcode":"86001",
    "sg:province":"AZ",
    "sg:tags":[
        "house"
    ],
    "wof:name":"Brown Contracting",
    "wof:placetype":"venue"
},
  "geometry": {"coordinates":[-111.683446,35.19289],"type":"Point"}
}