{
  "type": "Feature",
  "properties": {
    "iso:country":"US",
    "sg:address":"5250 S 43rd Ave",
    "sg:city":"Phoenix",
    "sg:classifiers":[
        {
            "category":"Freight",
            "type":"Transportation"
        }
    ],
    "sg:phone":"+1 602 237 2170",
    "sg:postcode":"85041",
    "sg:province":"AZ",
    "sg:tags":[
        "hauling",
        "trucking"
    ],
    "wof:name":"Tatel Inc Heavy Transport",
    "wof:placetype":"venue"
},
  "geometry": {"coordinates":[-112.150961,33.395899],"type":"Point"}
}