{
  "type": "Feature",
  "properties": {
    "iso:country":"US",
    "sg:address":"711 S 14th Ave",
    "sg:city":"Safford",
    "sg:classifiers":[
        {
            "category":"Government",
            "subcategory":"Office",
            "type":"Public Place"
        }
    ],
    "sg:phone":"+1 928 348 4577",
    "sg:postcode":"85546",
    "sg:province":"AZ",
    "sg:tags":[
        "township",
        "government-city",
        "village"
    ],
    "sg:website":"http://www.ci.safford.az.us",
    "wof:name":"Gila Watershed Partnership",
    "wof:placetype":"venue"
},
  "geometry": {"coordinates":[-109.724726,32.83233],"type":"Point"}
}