{
  "type": "Feature",
  "properties": {
    "iso:country":"US",
    "sg:address":"3740 S Arcadia Way",
    "sg:city":"Chandler",
    "sg:classifiers":[
        {
            "category":"Professional",
            "subcategory":"Management & Consulting",
            "type":"Services"
        }
    ],
    "sg:phone":"+1 480 855 4887",
    "sg:postcode":"85248",
    "sg:province":"AZ",
    "sg:tags":[
        "party",
        "planning"
    ],
    "wof:name":"Jumpin 4 Fun",
    "wof:placetype":"venue"
},
  "geometry": {"coordinates":[-111.87752399999999,33.248005],"type":"Point"}
}