{
  "type": "Feature",
  "properties": {
    "iso:country":"US",
    "sg:address":"3068 W White Mountain Blvd",
    "sg:city":"Lakeside",
    "sg:classifiers":[
        {
            "category":"Restaurant",
            "type":"Food & Drink"
        }
    ],
    "sg:phone":"+1 928 368 6019",
    "sg:postcode":"85929",
    "sg:province":"AZ",
    "wof:name":"The Islander",
    "wof:placetype":"venue"
},
  "geometry": {"coordinates":[-109.987746,34.16321],"type":"Point"}
}