{
  "type": "Feature",
  "properties": {
    "iso:country":"US",
    "sg:address":"117 S 1st St",
    "sg:city":"Sierra Vista",
    "sg:classifiers":[
        {
            "category":"Retail",
            "subcategory":"Auto Repair",
            "type":"Services"
        }
    ],
    "sg:phone":"+1 520 459 5200",
    "sg:postcode":"85635",
    "sg:province":"AZ",
    "sg:tags":[
        "repairing",
        "automobile"
    ],
    "wof:name":"Rinehart's Automotive",
    "wof:placetype":"venue"
},
  "geometry": {"coordinates":[-110.29743000000001,31.553541],"type":"Point"}
}