{
  "type": "Feature",
  "properties": {
    "addr:full":"10012 W Montecito Avenue Phoenix AZ 85037",
    "addr:housenumber":"10012",
    "addr:postcode":"85037",
    "addr:street":"W Montecito Avenue",
    "iso:country":"US",
    "sg:address":"10012 W Montecito Avenue",
    "sg:city":"Phoenix",
    "sg:classifiers":[
        {
            "category":"Building & Trades",
            "subcategory":"Cleaning & Sanitation",
            "type":"Services"
        }
    ],
    "sg:phone":"+1 623 872 5464",
    "sg:postcode":"85037",
    "sg:province":"AZ",
    "sg:tags":[
        "carpet"
    ],
    "wof:name":"Commercial Cleaning Solutions",
    "wof:placetype":"venue"
},
  "geometry": {"coordinates":[-112.276329,33.499745],"type":"Point"}
}