{
  "type": "Feature",
  "properties": {
    "iso:country":"US",
    "sg:address":"4001 S 34th St",
    "sg:city":"Phoenix",
    "sg:classifiers":[
        {
            "category":"Landmark",
            "subcategory":"Tourist Information",
            "type":"Public Place"
        },
        {
            "category":"Bus Charters",
            "type":"Transportation"
        },
        {
            "category":"Local Transit",
            "type":"Transportation"
        }
    ],
    "sg:phone":"+1 602 437 3484",
    "sg:postcode":"85040",
    "sg:province":"AZ",
    "sg:tags":[
        "buses-charter",
        "line",
        "rental",
        "tours-operators",
        "promoter"
    ],
    "sg:website":"http://www.arrowstagelines.com",
    "wof:name":"Arrow Stage Lines-Gray Line",
    "wof:placetype":"venue"
},
  "geometry": {"coordinates":[-112.008278,33.410381],"type":"Point"}
}