{
  "type": "Feature",
  "properties": {
    "iso:country":"US",
    "sg:address":"1256 W Chandler Blvd",
    "sg:city":"Chandler",
    "sg:classifiers":[
        {
            "category":"Real Estate",
            "subcategory":"Real Estate Services",
            "type":"Services"
        },
        {
            "category":"Real Estate",
            "subcategory":"Real Estate Agent",
            "type":"Services"
        }
    ],
    "sg:phone":"+1 480 792 9700",
    "sg:postcode":"85224",
    "sg:province":"AZ",
    "sg:tags":[
        "buyer",
        "management",
        "broker"
    ],
    "wof:name":"Donnelly Group Real Estate Services",
    "wof:placetype":"venue"
},
  "geometry": {"coordinates":[-111.865791,33.306099],"type":"Point"}
}