{
  "type": "Feature",
  "properties": {
    "iso:country":"US",
    "sg:address":"14401 N 20th St",
    "sg:city":"Phoenix",
    "sg:classifiers":[
        {
            "category":"Local Transit",
            "type":"Transportation"
        }
    ],
    "sg:phone":"+1 602 787 1887",
    "sg:postcode":"85022",
    "sg:province":"AZ",
    "sg:tags":[
        "handicapped"
    ],
    "wof:name":"Courtesy Wheelchair Transport",
    "wof:placetype":"venue"
},
  "geometry": {"coordinates":[-112.039384,33.618173],"type":"Point"}
}