{
  "type": "Feature",
  "properties": {
    "addr:full":"5894 W Thunderbird Rd Glendale AZ 85306",
    "addr:housenumber":"5894",
    "addr:postcode":"85306",
    "addr:street":"W Thunderbird Rd",
    "iso:country":"US",
    "sg:address":"5894 W Thunderbird Rd",
    "sg:city":"Glendale",
    "sg:classifiers":[
        {
            "category":"Bagels",
            "type":"Food & Drink"
        }
    ],
    "sg:menulink":"http://www.allmenus.com/az/phoenix/149452-einstein-bros/menu/",
    "sg:phone":"+1 602 547 8448",
    "sg:postcode":"85306",
    "sg:province":"AZ",
    "sg:tags":[
        "wrap",
        "soup",
        "american",
        "sandwich",
        "salad"
    ],
    "wof:name":"Einstein Bros",
    "wof:placetype":"venue"
},
  "geometry": {"coordinates":[-112.185292,33.611163],"type":"Point"}
}