{
  "type": "Feature",
  "properties": {
    "addr:full":"1080 East Pecos Road Suite 18 PMB #417 Chandler AZ 85225-2426",
    "addr:housenumber":"1080;18 pmb # 417",
    "addr:postcode":"85225-2426",
    "addr:street":"East Pecos Road Suite",
    "iso:country":"US",
    "sg:address":"1080 East Pecos Road Suite 18 PMB #417",
    "sg:city":"Chandler",
    "sg:classifiers":[
        {
            "category":"Professional",
            "subcategory":"Computer Services",
            "type":"Services"
        }
    ],
    "sg:phone":"+1 323 603 0188",
    "sg:postcode":"85225-2426",
    "sg:province":"AZ",
    "sg:website":"http://www.peoplemedia.com/",
    "wof:name":"People Media",
    "wof:placetype":"venue"
},
  "geometry": {"coordinates":[-111.82420999999999,33.291753],"type":"Point"}
}