{
  "type": "Feature",
  "properties": {
    "iso:country":"US",
    "sg:address":"14848 N Cave Creek Rd",
    "sg:city":"Phoenix",
    "sg:classifiers":[
        {
            "category":"Building & Trades",
            "subcategory":"Construction",
            "type":"Services"
        }
    ],
    "sg:phone":"+1 602 494 7387",
    "sg:postcode":"85032",
    "sg:province":"AZ",
    "sg:tags":[
        "house"
    ],
    "wof:name":"Jensen",
    "wof:placetype":"venue"
},
  "geometry": {"coordinates":[-112.030745,33.621851],"type":"Point"}
}