{
  "type": "Feature",
  "properties": {
    "iso:country":"US",
    "sg:address":"6791 N Glen Harbor Blvd",
    "sg:city":"Luke Afb",
    "sg:classifiers":[
        {
            "category":"Airport",
            "type":"Transportation"
        }
    ],
    "sg:phone":"+1 623 872 1902",
    "sg:postcode":"85307",
    "sg:province":"AZ",
    "sg:tags":[
        "aircraft",
        "storage"
    ],
    "wof:name":"Airwest Helicopters",
    "wof:placetype":"venue"
},
  "geometry": {"coordinates":[-112.29419300000001,33.536361],"type":"Point"}
}