{
  "type": "Feature",
  "properties": {
    "iso:country":"US",
    "sg:address":"6801 N 12th Ave",
    "sg:city":"Phoenix",
    "sg:classifiers":[
        {
            "category":"Real Estate",
            "subcategory":"Real Estate Operator",
            "type":"Services"
        }
    ],
    "sg:phone":"+1 602 246 9803",
    "sg:postcode":"85013",
    "sg:province":"AZ",
    "sg:tags":[
        "building",
        "nonresidential"
    ],
    "wof:name":"B&G Goettl LLC",
    "wof:placetype":"venue"
},
  "geometry": {"coordinates":[-112.088328,33.537243],"type":"Point"}
}