{
  "type": "Feature",
  "properties": {
    "iso:country":"US",
    "sg:address":"2212 E Torrey Pines Pl",
    "sg:city":"Chandler",
    "sg:classifiers":[
        {
            "category":"Autos & Motor Vehicles",
            "subcategory":"Motorcycle Sales",
            "type":"Retail Goods"
        }
    ],
    "sg:phone":"+1 602 291 6852",
    "sg:postcode":"85249",
    "sg:province":"AZ",
    "sg:tags":[
        "scooters-parts",
        "supply"
    ],
    "wof:name":"Parts 4 Play",
    "wof:placetype":"venue"
},
  "geometry": {"coordinates":[-111.802844,33.217655],"type":"Point"}
}