{
  "type": "Feature",
  "properties": {
    "iso:country":"US",
    "sg:address":"29455 N Cave Creek Rd",
    "sg:city":"Phoenix",
    "sg:classifiers":[
        {
            "category":"Food & Beverages",
            "subcategory":"Supermarket",
            "type":"Retail Goods"
        }
    ],
    "sg:phone":"+1 480 538 7130",
    "sg:postcode":"85024",
    "sg:province":"AZ",
    "sg:tags":[
        "super",
        "store"
    ],
    "wof:name":"Smith's",
    "wof:placetype":"venue"
},
  "geometry": {"coordinates":[-112.011543,33.721615],"type":"Point"}
}