{
  "type": "Feature",
  "properties": {
    "iso:country":"US",
    "sg:address":"14250 N Hohokam Village Pl",
    "sg:city":"Oro Valley",
    "sg:classifiers":[
        {
            "category":"Building & Trades",
            "subcategory":"Construction",
            "type":"Services"
        }
    ],
    "sg:phone":"+1 520 219 0571",
    "sg:postcode":"85755",
    "sg:province":"AZ",
    "sg:tags":[
        "general",
        "contractor"
    ],
    "wof:name":"Stone Canyon Construction",
    "wof:placetype":"venue"
},
  "geometry": {"coordinates":[-110.987415,32.464315],"type":"Point"}
}