{
  "type": "Feature",
  "properties": {
    "iso:country":"US",
    "sg:address":"7551 S Willow Drive",
    "sg:city":"Tempe",
    "sg:classifiers":[
        {
            "category":"Professional",
            "subcategory":"Lawyer & Legal Services",
            "type":"Services"
        }
    ],
    "sg:phone":"+1 480 777 5170",
    "sg:postcode":"85283",
    "sg:province":"AZ",
    "sg:tags":[
        "personal",
        "injury"
    ],
    "wof:name":"The Law Offices of Christopher J Palmisano",
    "wof:placetype":"venue"
},
  "geometry": {"coordinates":[-111.914807,33.349489],"type":"Point"}
}