{
  "type": "Feature",
  "properties": {
    "iso:country":"US",
    "sg:address":"7611 W Thomas Rd",
    "sg:city":"Phoenix",
    "sg:classifiers":[
        {
            "category":"Personal",
            "subcategory":"Hair Removal",
            "type":"Services"
        }
    ],
    "sg:phone":"+1 623 873 7709",
    "sg:postcode":"85033",
    "sg:province":"AZ",
    "sg:website":"www.jadabeauty.com",
    "wof:name":"Jada Beauty",
    "wof:placetype":"venue"
},
  "geometry": {"coordinates":[-112.22369,33.480019],"type":"Point"}
}