{
  "type": "Feature",
  "properties": {
    "addr:full":"1975 S Alma School Rd Chandler AZ 85248",
    "addr:housenumber":"1975",
    "addr:postcode":"85248",
    "addr:street":"S Alma School Rd",
    "iso:country":"US",
    "sg:address":"1975 S Alma School Rd",
    "sg:city":"Chandler",
    "sg:classifiers":[
        {
            "category":"Shopping",
            "subcategory":"Pharmacy",
            "type":"Retail Goods"
        }
    ],
    "sg:phone":"+1 480 722 1780",
    "sg:postcode":"85248",
    "sg:province":"AZ",
    "sg:tags":[
        "drugstore"
    ],
    "wof:name":"Walgreens",
    "wof:placetype":"venue"
},
  "geometry": {"coordinates":[-111.858002,33.276901],"type":"Point"}
}