{
  "type": "Feature",
  "properties": {
    "addr:full":"5675 N Oracle Rd Tucson AZ 85704",
    "addr:housenumber":"5675",
    "addr:postcode":"85704",
    "addr:street":"N Oracle Rd",
    "iso:country":"US",
    "sg:address":"5675 N Oracle Rd",
    "sg:city":"Tucson",
    "sg:classifiers":[
        {
            "category":"Professional",
            "subcategory":"Management & Consulting",
            "type":"Services"
        }
    ],
    "sg:phone":"+1 520 887 3099",
    "sg:postcode":"85704",
    "sg:province":"AZ",
    "sg:tags":[
        "consultant"
    ],
    "wof:name":"Chadwick Ecological Conslnt",
    "wof:placetype":"venue"
},
  "geometry": {"coordinates":[-110.978684,32.310259],"type":"Point"}
}