{
  "type": "Feature",
  "properties": {
    "addr:full":"1435 E Warner Rd Gilbert AZ 85296",
    "addr:housenumber":"1435",
    "addr:postcode":"85296",
    "addr:street":"E Warner Rd",
    "iso:country":"US",
    "sg:address":"1435 E Warner Rd",
    "sg:city":"Gilbert",
    "sg:classifiers":[
        {
            "category":"Shopping",
            "subcategory":"Shoes",
            "type":"Retail Goods"
        }
    ],
    "sg:phone":"+1 480 235 0255",
    "sg:postcode":"85296",
    "sg:province":"AZ",
    "wof:name":"Shoe In The Door",
    "wof:placetype":"venue"
},
  "geometry": {"coordinates":[-111.758723,33.335668],"type":"Point"}
}