{
  "type": "Feature",
  "properties": {
    "iso:country":"US",
    "sg:address":"802 E Clanton Ave",
    "sg:city":"Buckeye",
    "sg:classifiers":[
        {
            "category":"Building & Trades",
            "subcategory":"Plumbing",
            "type":"Services"
        }
    ],
    "sg:phone":"+1 623 386 4112",
    "sg:postcode":"85326",
    "sg:province":"AZ",
    "sg:tags":[
        "tank",
        "septic"
    ],
    "wof:name":"Ducks Septic Pump & Install",
    "wof:placetype":"venue"
},
  "geometry": {"coordinates":[-112.579913,33.367842],"type":"Point"}
}