{
  "type": "Feature",
  "properties": {
    "iso:country":"US",
    "sg:address":"3515 W Brown St",
    "sg:city":"Phoenix",
    "sg:classifiers":[
        {
            "category":"Food & Beverages",
            "subcategory":"Groceries & Convenience Stores",
            "type":"Retail Goods"
        }
    ],
    "sg:phone":"+1 602 275 4115",
    "sg:postcode":"85051",
    "sg:province":"AZ",
    "sg:tags":[
        "eating"
    ],
    "wof:name":"Gloria S NY Deli Restaurant",
    "wof:placetype":"venue"
},
  "geometry": {"coordinates":[-112.135561,33.577882],"type":"Point"}
}