{
  "type": "Feature",
  "properties": {
    "iso:country":"US",
    "sg:address":"2550 S Ellsworth Rd",
    "sg:city":"Mesa",
    "sg:classifiers":[
        {
            "category":"Professional",
            "type":"Services"
        }
    ],
    "sg:phone":"+1 480 354 4692",
    "sg:postcode":"85209",
    "sg:province":"AZ",
    "wof:name":"Hank Swierengas Scottsdale Ve",
    "wof:placetype":"venue"
},
  "geometry": {"coordinates":[-111.636083,33.369023],"type":"Point"}
}