{
  "type": "Feature",
  "properties": {
    "addr:full":"2201 E Brooks St Gilbert AZ 85296",
    "addr:housenumber":"2201",
    "addr:postcode":"85296",
    "addr:street":"E Brooks St",
    "iso:country":"US",
    "sg:address":"2201 E Brooks St",
    "sg:city":"Gilbert",
    "sg:classifiers":[
        {
            "category":"Building & Trades",
            "subcategory":"Locksmith",
            "type":"Services"
        }
    ],
    "sg:phone":"+1 480 477 9751",
    "sg:postcode":"85296",
    "sg:province":"AZ",
    "sg:tags":[
        "key"
    ],
    "wof:name":"Agilbert Always 24Hr Locksmith Emerg",
    "wof:placetype":"venue"
},
  "geometry": {"coordinates":[-111.742684,33.335013],"type":"Point"}
}