{
  "type": "Feature",
  "properties": {
    "addr:full":"4209 E University Dr Phoenix AZ 85034",
    "addr:housenumber":"4209",
    "addr:postcode":"85034",
    "addr:street":"E University Dr",
    "iso:country":"US",
    "sg:address":"4209 E University Dr",
    "sg:city":"Phoenix",
    "sg:classifiers":[
        {
            "category":"Autos & Motor Vehicles",
            "subcategory":"Fuel & Gas Station",
            "type":"Retail Goods"
        },
        {
            "category":"Professional",
            "subcategory":"Testing Lab",
            "type":"Services"
        },
        {
            "category":"Professional",
            "subcategory":"Business Services",
            "type":"Services"
        },
        {
            "category":"Utilities",
            "subcategory":"Natural Gas",
            "type":"Services"
        }
    ],
    "sg:phone":"+1 602 437 4600",
    "sg:postcode":"85034",
    "sg:province":"AZ",
    "sg:tags":[
        "laboratory",
        "repair",
        "plant",
        "equipment-service",
        "equipment"
    ],
    "wof:name":"Thunderbird Cylinder Inc",
    "wof:placetype":"venue"
},
  "geometry": {"coordinates":[-111.991062,33.421879],"type":"Point"}
}