{
  "type": "Feature",
  "properties": {
    "iso:country":"US",
    "sg:address":"7250 N 16th St",
    "sg:city":"Phoenix",
    "sg:classifiers":[
        {
            "category":"Professional",
            "subcategory":"Lawyer & Legal Services",
            "type":"Services"
        }
    ],
    "sg:phone":"+1 602 274 6996",
    "sg:postcode":"85020",
    "sg:province":"AZ",
    "sg:tags":[
        "attorney",
        "copyright",
        "patent",
        "trademark",
        "law"
    ],
    "sg:website":"http://www.patentmg.com",
    "wof:name":"Meschkow & Gresham PLC",
    "wof:placetype":"venue"
},
  "geometry": {"coordinates":[-112.047527,33.543268],"type":"Point"}
}