{
  "type": "Feature",
  "properties": {
    "iso:country":"US",
    "sg:address":"11615 N 136th St",
    "sg:city":"Scottsdale",
    "sg:classifiers":[
        {
            "category":"Food & Beverages",
            "subcategory":"Specialty",
            "type":"Retail Goods"
        }
    ],
    "sg:phone":"+1 480 657 7162",
    "sg:postcode":"85259",
    "sg:province":"AZ",
    "sg:tags":[
        "tea",
        "coffee"
    ],
    "sg:website":"www.cupzcoffee.com",
    "wof:name":"Cupz Coffee",
    "wof:placetype":"venue"
},
  "geometry": {"coordinates":[-111.787292,33.592983],"type":"Point"}
}