{
  "type": "Feature",
  "properties": {
    "iso:country":"US",
    "sg:address":"21050 N Tatum Blvd D-202",
    "sg:city":"Phoenix",
    "sg:classifiers":[
        {
            "category":"Arena",
            "subcategory":"Sports Club",
            "type":"Entertainment"
        }
    ],
    "sg:phone":"+1 480 419 7325",
    "sg:postcode":"85050",
    "sg:province":"AZ",
    "sg:tags":[
        "martial art",
        "instruction"
    ],
    "wof:name":"Peak Fitness & Martial Arts",
    "wof:placetype":"venue"
},
  "geometry": {"coordinates":[-111.977507,33.677827],"type":"Point"}
}