{
  "type": "Feature",
  "properties": {
    "iso:country":"US",
    "sg:address":"2680 S Val Vista Dr",
    "sg:city":"Gilbert",
    "sg:classifiers":[
        {
            "category":"Banks & Credit Unions",
            "subcategory":"Financial Services",
            "type":"Services"
        }
    ],
    "sg:phone":"+1 480 786 2829",
    "sg:postcode":"85295",
    "sg:province":"AZ",
    "sg:tags":[
        "broker",
        "mortgage"
    ],
    "sg:website":"homeloan.chase.com",
    "wof:name":"Chase Home Loans",
    "wof:placetype":"venue"
},
  "geometry": {"coordinates":[-111.75583,33.3016],"type":"Point"}
}