{
  "type": "Feature",
  "properties": {
    "iso:country":"US",
    "sg:address":"7207 N 19th Ave",
    "sg:city":"Phoenix",
    "sg:classifiers":[
        {
            "category":"Professional",
            "subcategory":"Lawyer & Legal Services",
            "type":"Services"
        }
    ],
    "sg:phone":"+1 602 589 5110",
    "sg:postcode":"85021",
    "sg:province":"AZ",
    "sg:tags":[
        "attorney"
    ],
    "wof:name":"Bruce D Brown",
    "wof:placetype":"venue"
},
  "geometry": {"coordinates":[-112.099503,33.538729],"type":"Point"}
}