{
  "type": "Feature",
  "properties": {
    "addr:full":"6017 E McKellips Rd Mesa AZ 85215",
    "addr:housenumber":"6017",
    "addr:postcode":"85215",
    "addr:street":"E Mckellips Rd",
    "iso:country":"US",
    "sg:address":"6017 E McKellips Rd",
    "sg:city":"Mesa",
    "sg:classifiers":[
        {
            "category":"Shopping",
            "subcategory":"Florist",
            "type":"Retail Goods"
        }
    ],
    "sg:phone":"+1 480 641 1503",
    "sg:postcode":"85215",
    "sg:province":"AZ",
    "wof:name":"Run Florist Run",
    "wof:placetype":"venue"
},
  "geometry": {"coordinates":[-111.697362,33.451798],"type":"Point"}
}