{
  "type": "Feature",
  "properties": {
    "addr:full":"1514 W Todd Dr Ste 101 Tempe AZ 85283",
    "addr:housenumber":"1514",
    "addr:postcode":"85283",
    "addr:street":"W Todd Dr Ste 101",
    "iso:country":"US",
    "sg:address":"1514 W Todd Dr Ste 101",
    "sg:city":"Tempe",
    "sg:classifiers":[
        {
            "category":"Health Services",
            "subcategory":"Doctor",
            "type":"Services"
        }
    ],
    "sg:phone":"+1 480 337 0222",
    "sg:postcode":"85283",
    "sg:province":"AZ",
    "sg:tags":[
        "physician",
        "surgeon"
    ],
    "wof:name":"Integrated Health Care Cooperative, Inc",
    "wof:placetype":"venue"
},
  "geometry": {"coordinates":[-111.963314,33.352747],"type":"Point"}
}