{
  "type": "Feature",
  "properties": {
    "addr:full":"21138 E Via del Oro Queen Creek AZ 85242",
    "addr:housenumber":"21138",
    "addr:postcode":"85242",
    "addr:street":"E Via Del Oro",
    "iso:country":"US",
    "sg:address":"21138 E Via del Oro",
    "sg:city":"Queen Creek",
    "sg:classifiers":[
        {
            "category":"Building & Trades",
            "subcategory":"Construction",
            "type":"Services"
        }
    ],
    "sg:phone":"+1 480 888 9027",
    "sg:postcode":"85242",
    "sg:province":"AZ",
    "sg:tags":[
        "residential",
        "concrete",
        "contractor"
    ],
    "wof:name":"Eagle Southwest Construction",
    "wof:placetype":"venue"
},
  "geometry": {"coordinates":[-111.626981,33.239582],"type":"Point"}
}