{
  "type": "Feature",
  "properties": {
    "iso:country":"US",
    "sg:address":"5975 W Western Way Cir",
    "sg:city":"Tucson",
    "sg:classifiers":[
        {
            "category":"Shopping",
            "subcategory":"Clothing, Apparel, & Fashions",
            "type":"Retail Goods"
        }
    ],
    "sg:phone":"+1 520 578 8800",
    "sg:postcode":"85713",
    "sg:province":"AZ",
    "wof:name":"Simply Beautiful Clothiers",
    "wof:placetype":"venue"
},
  "geometry": {"coordinates":[-111.092023,32.186252],"type":"Point"}
}