{
  "type": "Feature",
  "properties": {
    "addr:full":"2028 E Danbury Rd Phoenix AZ 85022",
    "addr:housenumber":"2028",
    "addr:postcode":"85022",
    "addr:street":"E Danbury Rd",
    "iso:country":"US",
    "sg:address":"2028 E Danbury Rd",
    "sg:city":"Phoenix",
    "sg:classifiers":[
        {
            "category":"Real Estate",
            "subcategory":"Real Estate Agent",
            "type":"Services"
        }
    ],
    "sg:phone":"+1 602 404 7833",
    "sg:postcode":"85022",
    "sg:province":"AZ",
    "sg:tags":[
        "management"
    ],
    "wof:name":"E R Property Management",
    "wof:placetype":"venue"
},
  "geometry": {"coordinates":[-112.03787199999999,33.642809],"type":"Point"}
}