{
  "type": "Feature",
  "properties": {
    "iso:country":"US",
    "sg:address":"4532 E Thomas Rd",
    "sg:city":"Phoenix",
    "sg:classifiers":[
        {
            "category":"Restaurant",
            "type":"Food & Drink"
        }
    ],
    "sg:phone":"+1 602 956 0013",
    "sg:postcode":"85018",
    "sg:province":"AZ",
    "sg:tags":[
        "eating"
    ],
    "wof:name":"New Dragon Buffet",
    "wof:placetype":"venue"
},
  "geometry": {"coordinates":[-111.983363,33.480266],"type":"Point"}
}