{
  "type": "Feature",
  "properties": {
    "iso:country":"US",
    "sg:address":"424 S Bay Shore Blvd",
    "sg:city":"Gilbert",
    "sg:classifiers":[
        {
            "category":"Wholesale",
            "subcategory":"Machinery & Supplies",
            "type":"Manufacturing & Wholesale Goods"
        }
    ],
    "sg:phone":"+1 480 545 7299",
    "sg:postcode":"85233",
    "sg:province":"AZ",
    "sg:tags":[
        "equipment",
        "industrial"
    ],
    "wof:name":"Viking Sales Company",
    "wof:placetype":"venue"
},
  "geometry": {"coordinates":[-111.818716,33.341527],"type":"Point"}
}