{
  "type": "Feature",
  "properties": {
    "addr:full":"9160 E Shea Blvd Ste 108 Scottsdale AZ 85260",
    "addr:housenumber":"9160",
    "addr:postcode":"85260",
    "addr:street":"E Shea Blvd Ste 108",
    "iso:country":"US",
    "sg:address":"9160 E Shea Blvd Ste 108",
    "sg:city":"Scottsdale",
    "sg:classifiers":[
        {
            "category":"Health Services",
            "subcategory":"Dentist",
            "type":"Services"
        }
    ],
    "sg:phone":"+1 480 661 6200",
    "sg:postcode":"85260",
    "sg:province":"AZ",
    "sg:tags":[
        "dental",
        "clinic"
    ],
    "wof:name":"Horizon Dental Group",
    "wof:placetype":"venue"
},
  "geometry": {"coordinates":[-111.88340599999999,33.582619],"type":"Point"}
}