{
  "type": "Feature",
  "properties": {
    "iso:country":"US",
    "sg:address":"3022 N Sourdough Pl",
    "sg:city":"Tucson",
    "sg:classifiers":[
        {
            "category":"Real Estate",
            "subcategory":"Real Estate Agent",
            "type":"Services"
        }
    ],
    "sg:phone":"+1 520 795 3100",
    "sg:postcode":"85749",
    "sg:province":"AZ",
    "sg:tags":[
        "management"
    ],
    "wof:name":"Merritt Realty Management",
    "wof:placetype":"venue"
},
  "geometry": {"coordinates":[-110.742051,32.263944],"type":"Point"}
}