{
  "type": "Feature",
  "properties": {
    "addr:full":"1026 W 6th Pl Mesa AZ 85201",
    "addr:housenumber":"1026",
    "addr:postcode":"85201",
    "addr:street":"W 6Th Pl",
    "iso:country":"US",
    "sg:address":"1026 W 6th Pl",
    "sg:city":"Mesa",
    "sg:classifiers":[
        {
            "category":"Shopping",
            "subcategory":"Gifts & Souvenirs",
            "type":"Retail Goods"
        }
    ],
    "sg:phone":"+1 480 610 8061",
    "sg:postcode":"85201",
    "sg:province":"AZ",
    "wof:name":"Isis East Gifts of Goddess",
    "wof:placetype":"venue"
},
  "geometry": {"coordinates":[-111.854889,33.426588],"type":"Point"}
}