{
  "type": "Feature",
  "properties": {
    "iso:country":"US",
    "sg:address":"5734 McKinney Ave",
    "sg:city":"Globe",
    "sg:classifiers":[
        {
            "category":"Communications",
            "subcategory":"Radio Station",
            "type":"Services"
        }
    ],
    "sg:phone":"+1 928 425 7186",
    "sg:postcode":"85501",
    "sg:province":"AZ",
    "sg:tags":[
        "company",
        "broadcasting"
    ],
    "wof:name":"KQSS",
    "wof:placetype":"venue"
},
  "geometry": {"coordinates":[-110.810488,33.409919],"type":"Point"}
}