{
  "type": "Feature",
  "properties": {
    "addr:full":"4605 E Chandler Blvd Phoenix AZ 85048",
    "addr:housenumber":"4605",
    "addr:postcode":"85048",
    "addr:street":"E Chandler Blvd",
    "iso:country":"US",
    "sg:address":"4605 E Chandler Blvd",
    "sg:city":"Phoenix",
    "sg:classifiers":[
        {
            "category":"Coffee & Tea",
            "type":"Food & Drink"
        }
    ],
    "sg:menulink":"http://www.allmenus.com/az/phoenix/108325-starbucks-coffee/menu/",
    "sg:phone":"+1 480 785 7795",
    "sg:postcode":"85048",
    "sg:province":"AZ",
    "sg:tags":[
        "american"
    ],
    "wof:name":"Starbucks Coffee",
    "wof:placetype":"venue"
},
  "geometry": {"coordinates":[-111.98347,33.304695],"type":"Point"}
}