{
  "type": "Feature",
  "properties": {
    "iso:country":"US",
    "sg:address":"7740 E Redfield Rd",
    "sg:city":"Scottsdale",
    "sg:classifiers":[
        {
            "category":"Home & Garden",
            "subcategory":"Building Materials",
            "type":"Retail Goods"
        }
    ],
    "sg:phone":"+1 480 368 0300",
    "sg:postcode":"85260",
    "sg:province":"AZ",
    "sg:tags":[
        "windows"
    ],
    "wof:name":"Discount Window & Door",
    "wof:placetype":"venue"
},
  "geometry": {"coordinates":[-111.912588,33.614015],"type":"Point"}
}