{
  "type": "Feature",
  "properties": {
    "iso:country":"US",
    "sg:address":"185 Coffee Pot Dr",
    "sg:city":"Sedona",
    "sg:classifiers":[
        {
            "category":"Building & Trades",
            "subcategory":"Plumbing",
            "type":"Services"
        }
    ],
    "sg:phone":"+1 928 282 5784",
    "sg:postcode":"86336",
    "sg:province":"AZ",
    "sg:tags":[
        "plumbing",
        "contractor"
    ],
    "wof:name":"Sedona Plumbing",
    "wof:placetype":"venue"
},
  "geometry": {"coordinates":[-111.795487,34.867335],"type":"Point"}
}