{
  "type": "Feature",
  "properties": {
    "iso:country":"US",
    "sg:address":"3065 E Nora St",
    "sg:city":"Mesa",
    "sg:classifiers":[
        {
            "category":"Manufacturing",
            "subcategory":"Buildings",
            "type":"Manufacturing & Wholesale Goods"
        }
    ],
    "sg:phone":"+1 602 791 7000",
    "sg:postcode":"85213",
    "sg:province":"AZ",
    "sg:tags":[
        "home",
        "log"
    ],
    "wof:name":"Precision Craft Log Structures",
    "wof:placetype":"venue"
},
  "geometry": {"coordinates":[-111.765413,33.465773],"type":"Point"}
}