{
  "type": "Feature",
  "properties": {
    "iso:country":"US",
    "sg:address":"510 E Fort Lowell Rd",
    "sg:city":"Tucson",
    "sg:classifiers":[
        {
            "category":"Home & Garden",
            "subcategory":"Furniture",
            "type":"Retail Goods"
        }
    ],
    "sg:phone":"+1 520 623 7901",
    "sg:postcode":"85705",
    "sg:province":"AZ",
    "wof:name":"Recliner City",
    "wof:placetype":"venue"
},
  "geometry": {"coordinates":[-110.961089,32.264735],"type":"Point"}
}