{
  "type": "Feature",
  "properties": {
    "iso:country":"US",
    "sg:address":"2632 S 83rd Ave Ste 102",
    "sg:city":"Phoenix",
    "sg:classifiers":[
        {
            "category":"Insurance",
            "subcategory":"Hazard Insurance",
            "type":"Services"
        }
    ],
    "sg:phone":"+1 623 848 6300",
    "sg:postcode":"85043",
    "sg:province":"AZ",
    "sg:website":"http://statefarm.mqgroup.com/url.asp?usr=031977",
    "wof:name":"State Farm Insurance Agent-Yolie Aleman-Rodriguez",
    "wof:placetype":"venue"
},
  "geometry": {"coordinates":[-112.238642,33.423679],"type":"Point"}
}