{
  "type": "Feature",
  "properties": {
    "iso:country":"US",
    "sg:address":"2320 N Silverbell Rd",
    "sg:city":"Tucson",
    "sg:classifiers":[
        {
            "category":"Restaurant",
            "type":"Food & Drink"
        }
    ],
    "sg:menulink":"http://www.allmenus.com/az/tucson/147519-famous-sams/menu/",
    "sg:phone":"+1 520 884 7267",
    "sg:postcode":"85745",
    "sg:province":"AZ",
    "sg:tags":[
        "wrap",
        "american",
        "sandwich"
    ],
    "wof:name":"Famous Sam's",
    "wof:placetype":"venue"
},
  "geometry": {"coordinates":[-111.012248,32.249572],"type":"Point"}
}