{
  "type": "Feature",
  "properties": {
    "iso:country":"US",
    "sg:address":"4485 S Heather Pl",
    "sg:city":"Tucson",
    "sg:classifiers":[
        {
            "category":"Personal",
            "type":"Services"
        }
    ],
    "sg:phone":"+1 520 748 1148",
    "sg:postcode":"85730",
    "sg:province":"AZ",
    "sg:tags":[
        "consultant",
        "program",
        "health",
        "fitness"
    ],
    "wof:name":"Fitness Today",
    "wof:placetype":"venue"
},
  "geometry": {"coordinates":[-110.83020500000001,32.170414],"type":"Point"}
}