{
  "type": "Feature",
  "properties": {
    "iso:country":"US",
    "sg:address":"1754 W Ajo Way",
    "sg:city":"Tucson",
    "sg:classifiers":[
        {
            "category":"Restaurant",
            "type":"Food & Drink"
        }
    ],
    "sg:phone":"+1 520 889 2563",
    "sg:postcode":"85713",
    "sg:province":"AZ",
    "wof:name":"Bamboo Terrace",
    "wof:placetype":"venue"
},
  "geometry": {"coordinates":[-111.002236,32.177949],"type":"Point"}
}