{
  "type": "Feature",
  "properties": {
    "addr:full":"2914 W Wethersfield Rd Phoenix AZ 85029",
    "addr:housenumber":"2914",
    "addr:postcode":"85029",
    "addr:street":"W Wethersfield Rd",
    "iso:country":"US",
    "sg:address":"2914 W Wethersfield Rd",
    "sg:city":"Phoenix",
    "sg:classifiers":[
        {
            "category":"Arena",
            "subcategory":"Indoor Arena",
            "type":"Entertainment"
        }
    ],
    "sg:phone":"+1 602 296 7595",
    "sg:postcode":"85029",
    "sg:province":"AZ",
    "sg:tags":[
        "bingo",
        "hall"
    ],
    "wof:name":"Bingo Company",
    "wof:placetype":"venue"
},
  "geometry": {"coordinates":[-112.121122,33.597229],"type":"Point"}
}