{
  "type": "Feature",
  "properties": {
    "iso:country":"US",
    "sg:address":"3159 W Danbury Dr",
    "sg:city":"Phoenix",
    "sg:classifiers":[
        {
            "category":"Professional",
            "subcategory":"Management & Consulting",
            "type":"Services"
        }
    ],
    "sg:phone":"+1 602 354 4079",
    "sg:postcode":"85053",
    "sg:province":"AZ",
    "sg:tags":[
        "retail",
        "direct",
        "sales"
    ],
    "wof:name":"Linda D Wimbish",
    "wof:placetype":"venue"
},
  "geometry": {"coordinates":[-112.12769,33.641726],"type":"Point"}
}