{
  "type": "Feature",
  "properties": {
    "addr:full":"2728 N 68th St # 4 Scottsdale AZ 85257",
    "addr:housenumber":"2728",
    "addr:postcode":"85257",
    "addr:street":"N 68Th St # 4",
    "iso:country":"US",
    "sg:address":"2728 N 68th St # 4",
    "sg:city":"Scottsdale",
    "sg:classifiers":[
        {
            "category":"Building & Trades",
            "subcategory":"Construction",
            "type":"Services"
        },
        {
            "category":"Manufacturing",
            "subcategory":"Building Materials",
            "type":"Manufacturing & Wholesale Goods"
        },
        {
            "category":"Home & Garden",
            "subcategory":"Carpets & Floor Coverings",
            "type":"Retail Goods"
        }
    ],
    "sg:phone":"+1 480 991 9605",
    "sg:postcode":"85257",
    "sg:province":"AZ",
    "sg:tags":[
        "flooring",
        "materials-wholesale",
        "rug",
        "contractor",
        "tile-contractors",
        "distributor",
        "manufacturer"
    ],
    "wof:name":"Flooring Resources",
    "wof:placetype":"venue"
},
  "geometry": {"coordinates":[-111.934765,33.478265],"type":"Point"}
}