{
  "type": "Feature",
  "properties": {
    "iso:country":"US",
    "sg:address":"7047 E Greenway Pkwy",
    "sg:city":"Scottsdale",
    "sg:classifiers":[
        {
            "category":"Real Estate",
            "subcategory":"Developer",
            "type":"Services"
        },
        {
            "category":"Real Estate",
            "subcategory":"Real Estate Agent",
            "type":"Services"
        }
    ],
    "sg:phone":"+1 480 219 1960",
    "sg:postcode":"85254",
    "sg:province":"AZ",
    "sg:tags":[
        "investment"
    ],
    "sg:website":"www.buttepropertiesinc.com",
    "wof:name":"Butte Properties Inc",
    "wof:placetype":"venue"
},
  "geometry": {"coordinates":[-111.932451,33.622748],"type":"Point"}
}