{
  "type": "Feature",
  "properties": {
    "addr:full":"2444 E Lockwood Cir Mesa AZ 85213",
    "addr:housenumber":"2444",
    "addr:postcode":"85213",
    "addr:street":"E Lockwood Cir",
    "iso:country":"US",
    "sg:address":"2444 E Lockwood Cir",
    "sg:city":"Mesa",
    "sg:classifiers":[
        {
            "category":"Travel",
            "subcategory":"Travel Agent",
            "type":"Entertainment"
        }
    ],
    "sg:phone":"+1 602 679 3969",
    "sg:postcode":"85213",
    "sg:province":"AZ",
    "sg:tags":[
        "trailer"
    ],
    "wof:name":"Airstride Trailer Sales",
    "wof:placetype":"venue"
},
  "geometry": {"coordinates":[-111.77799899999999,33.456512],"type":"Point"}
}