{
  "type": "Feature",
  "properties": {
    "iso:country":"US",
    "sg:address":"1600 W Camelback Rd",
    "sg:city":"Phoenix",
    "sg:classifiers":[
        {
            "category":"Insurance",
            "subcategory":"Insurance Agent",
            "type":"Services"
        }
    ],
    "sg:phone":"+1 602 264 2131",
    "sg:postcode":"85015",
    "sg:province":"AZ",
    "wof:name":"A American Agents Allianc Ntnl",
    "wof:placetype":"venue"
},
  "geometry": {"coordinates":[-112.095637,33.509546],"type":"Point"}
}