{
  "type": "Feature",
  "properties": {
    "addr:full":"635 N Country Club Dr Mesa AZ 85201",
    "addr:housenumber":"635",
    "addr:postcode":"85201",
    "addr:street":"N Country Club Dr",
    "iso:country":"US",
    "sg:address":"635 N Country Club Dr",
    "sg:city":"Mesa",
    "sg:classifiers":[
        {
            "category":"Shopping",
            "subcategory":"Clothing, Apparel, & Fashions",
            "type":"Retail Goods"
        }
    ],
    "sg:phone":"+1 480 827 3162",
    "sg:postcode":"85201",
    "sg:province":"AZ",
    "wof:name":"El Caporal",
    "wof:placetype":"venue"
},
  "geometry": {"coordinates":[-111.839879,33.426307],"type":"Point"}
}