{
  "type": "Feature",
  "properties": {
    "iso:country":"US",
    "sg:address":"51 E Camelback Rd",
    "sg:city":"Phoenix",
    "sg:classifiers":[
        {
            "category":"Airline",
            "type":"Transportation"
        }
    ],
    "sg:phone":"+1 602 954 8300",
    "sg:postcode":"85012",
    "sg:province":"AZ",
    "sg:tags":[
        "courier",
        "air"
    ],
    "wof:name":"Fedex",
    "wof:placetype":"venue"
},
  "geometry": {"coordinates":[-112.070553,33.509187],"type":"Point"}
}