{
  "type": "Feature",
  "properties": {
    "addr:full":"137 E Elliot Rd Gilbert AZ 85234",
    "addr:housenumber":"137",
    "addr:postcode":"85234",
    "addr:street":"E Elliot Rd",
    "iso:country":"US",
    "sg:address":"137 E Elliot Rd",
    "sg:city":"Gilbert",
    "sg:classifiers":[
        {
            "category":"Government",
            "subcategory":"Post Office",
            "type":"Public Place"
        }
    ],
    "sg:phone":"+1 480 539 6815",
    "sg:postcode":"85234",
    "sg:province":"AZ",
    "wof:name":"Gilbert Post Office",
    "wof:placetype":"venue"
},
  "geometry": {"coordinates":[-111.78554099999999,33.349947],"type":"Point"}
}