{
  "type": "Feature",
  "properties": {
    "iso:country":"US",
    "sg:address":"1422 N Cooper Rd",
    "sg:city":"Gilbert",
    "sg:classifiers":[
        {
            "category":"Food & Beverages",
            "subcategory":"Groceries & Convenience Stores",
            "type":"Retail Goods"
        }
    ],
    "sg:phone":"+1 480 214 1220",
    "sg:postcode":"85233",
    "sg:province":"AZ",
    "sg:tags":[
        "grocer"
    ],
    "sg:website":"www.henrysmarkets.com",
    "wof:name":"Henry's Marketplace",
    "wof:placetype":"venue"
},
  "geometry": {"coordinates":[-111.806995,33.323075],"type":"Point"}
}