{
  "type": "Feature",
  "properties": {
    "addr:full":"255 E McKellips Rd Mesa AZ 85201",
    "addr:housenumber":"255",
    "addr:postcode":"85201",
    "addr:street":"E Mckellips Rd",
    "iso:country":"US",
    "sg:address":"255 E McKellips Rd",
    "sg:city":"Mesa",
    "sg:classifiers":[
        {
            "category":"Freight",
            "type":"Transportation"
        }
    ],
    "sg:phone":"+1 480 834 4198",
    "sg:postcode":"85201",
    "sg:province":"AZ",
    "sg:tags":[
        "mini",
        "storage",
        "commercial"
    ],
    "wof:name":"Palo Verde Mini Storage LLC",
    "wof:placetype":"venue"
},
  "geometry": {"coordinates":[-111.8258,33.451407],"type":"Point"}
}