{
  "type": "Feature",
  "properties": {
    "iso:country":"US",
    "sg:address":"1819 W Vista Ave",
    "sg:city":"Phoenix",
    "sg:classifiers":[
        {
            "category":"Professional",
            "subcategory":"Management & Consulting",
            "type":"Services"
        }
    ],
    "sg:phone":"+1 602 997 9022",
    "sg:postcode":"85021",
    "sg:province":"AZ",
    "sg:tags":[
        "fuel"
    ],
    "wof:name":"M & M Facility Management Inc",
    "wof:placetype":"venue"
},
  "geometry": {"coordinates":[-112.099392,33.546762],"type":"Point"}
}