{
  "type": "Feature",
  "properties": {
    "iso:country":"US",
    "sg:address":"1349 E Lobster Bay Cir",
    "sg:city":"Gilbert",
    "sg:classifiers":[
        {
            "category":"Building & Trades",
            "subcategory":"Construction",
            "type":"Services"
        }
    ],
    "sg:phone":"+1 480 838 5688",
    "sg:postcode":"85234",
    "sg:province":"AZ",
    "sg:tags":[
        "floor",
        "laying",
        "contractor"
    ],
    "wof:name":"Randys Carpet Service",
    "wof:placetype":"venue"
},
  "geometry": {"coordinates":[-111.76206999999999,33.376426],"type":"Point"}
}