{
  "type": "Feature",
  "properties": {
    "addr:full":"4604 Rio Camino Loop Fort Mohave AZ 86426",
    "addr:housenumber":"4604",
    "addr:postcode":"86426",
    "addr:street":"Rio Camino Loop",
    "iso:country":"US",
    "sg:address":"4604 Rio Camino Loop",
    "sg:city":"Fort Mohave",
    "sg:classifiers":[
        {
            "category":"Professional",
            "subcategory":"Detective & Security Services",
            "type":"Services"
        }
    ],
    "sg:phone":"+1 928 763 6580",
    "sg:postcode":"86426",
    "sg:province":"AZ",
    "sg:tags":[
        "guard",
        "patrol"
    ],
    "wof:name":"Protectall Patrol",
    "wof:placetype":"venue"
},
  "geometry": {"coordinates":[-114.592904,35.022648],"type":"Point"}
}