{
  "type": "Feature",
  "properties": {
    "addr:full":"1100 E Sheldon St Prescott AZ 86301",
    "addr:housenumber":"1100",
    "addr:postcode":"86301",
    "addr:street":"E Sheldon St",
    "iso:country":"US",
    "sg:address":"1100 E Sheldon St",
    "sg:city":"Prescott",
    "sg:classifiers":[
        {
            "category":"Education",
            "subcategory":"School",
            "type":"Public Place"
        }
    ],
    "sg:phone":"+1 928 445 0965",
    "sg:postcode":"86301",
    "sg:province":"AZ",
    "wof:name":"Peak Alternative High School",
    "wof:placetype":"venue"
},
  "geometry": {"coordinates":[-112.45547999999999,34.545094],"type":"Point"}
}