{
  "type": "Feature",
  "properties": {
    "addr:full":"370 E Hillcrest Pl Tucson AZ 85704",
    "addr:housenumber":"370",
    "addr:postcode":"85704",
    "addr:street":"E Hillcrest Pl",
    "iso:country":"US",
    "sg:address":"370 E Hillcrest Pl",
    "sg:city":"Tucson",
    "sg:classifiers":[
        {
            "category":"Professional",
            "subcategory":"Computer Services",
            "type":"Services"
        }
    ],
    "sg:phone":"+1 520 292 0551",
    "sg:postcode":"85704",
    "sg:province":"AZ",
    "sg:tags":[
        "internet"
    ],
    "sg:website":"www.sports-trading.com",
    "wof:name":"Ocongi",
    "wof:placetype":"venue"
},
  "geometry": {"coordinates":[-110.966713,32.29907],"type":"Point"}
}