{
  "type": "Feature",
  "properties": {
    "iso:country":"US",
    "sg:address":"6440 S 10th St",
    "sg:city":"Phoenix",
    "sg:classifiers":[
        {
            "category":"Shopping",
            "subcategory":"Used Merchandise",
            "type":"Retail Goods"
        }
    ],
    "sg:phone":"+1 602 276 5330",
    "sg:postcode":"85042",
    "sg:province":"AZ",
    "sg:tags":[
        "clothing"
    ],
    "wof:name":"I & M's",
    "wof:placetype":"venue"
},
  "geometry": {"coordinates":[-112.058487,33.388746],"type":"Point"}
}