{
  "type": "Feature",
  "properties": {
    "iso:country":"US",
    "sg:address":"2626 Ricca Dr",
    "sg:city":"Kingman",
    "sg:classifiers":[
        {
            "category":"Wholesale",
            "subcategory":"Drugs",
            "type":"Manufacturing & Wholesale Goods"
        }
    ],
    "sg:phone":"+1 928 753 4650",
    "sg:postcode":"86401",
    "sg:province":"AZ",
    "wof:name":"Healthy Way With Bev Arbonne",
    "wof:placetype":"venue"
},
  "geometry": {"coordinates":[-114.017624,35.212678],"type":"Point"}
}