{
  "type": "Feature",
  "properties": {
    "addr:full":"8210 E Garfield St Scottsdale AZ 85257",
    "addr:housenumber":"8210",
    "addr:postcode":"85257",
    "addr:street":"E Garfield St",
    "iso:country":"US",
    "sg:address":"8210 E Garfield St",
    "sg:city":"Scottsdale",
    "sg:classifiers":[
        {
            "category":"Real Estate",
            "subcategory":"Real Estate Agent",
            "type":"Services"
        }
    ],
    "sg:phone":"+1 480 945 7561",
    "sg:postcode":"85257",
    "sg:province":"AZ",
    "sg:tags":[
        "cooperative"
    ],
    "wof:name":"SCOTTSDALE East Homes Inc",
    "wof:placetype":"venue"
},
  "geometry": {"coordinates":[-111.903706,33.457322],"type":"Point"}
}