{
  "type": "Feature",
  "properties": {
    "addr:full":"4015 E Maldonado Dr Phoenix AZ 85042",
    "addr:housenumber":"4015",
    "addr:postcode":"85042",
    "addr:street":"E Maldonado Dr",
    "iso:country":"US",
    "sg:address":"4015 E Maldonado Dr",
    "sg:city":"Phoenix",
    "sg:classifiers":[
        {
            "category":"Building & Trades",
            "subcategory":"Construction",
            "type":"Services"
        }
    ],
    "sg:phone":"+1 602 410 7776",
    "sg:postcode":"85042",
    "sg:province":"AZ",
    "sg:tags":[
        "wallcoverings-installation",
        "wallpaper",
        "painting",
        "contractor"
    ],
    "wof:name":"Young Painting",
    "wof:placetype":"venue"
},
  "geometry": {"coordinates":[-111.994743,33.383869],"type":"Point"}
}