{
  "type": "Feature",
  "properties": {
    "addr:full":"10222 E Rita Rd Tucson AZ 85747",
    "addr:housenumber":"10222",
    "addr:postcode":"85747",
    "addr:street":"E Rita Rd",
    "iso:country":"US",
    "sg:address":"10222 E Rita Rd",
    "sg:city":"Tucson",
    "sg:classifiers":[
        {
            "category":"Social Services",
            "subcategory":"Job Training",
            "type":"Services"
        }
    ],
    "sg:phone":"+1 520 873 3881",
    "sg:postcode":"85747",
    "sg:province":"AZ",
    "sg:tags":[
        "rehabilitation"
    ],
    "wof:name":"St Joseph's Se Medical Svc",
    "wof:placetype":"venue"
},
  "geometry": {"coordinates":[-110.77339499999999,32.102568],"type":"Point"}
}