{
  "type": "Feature",
  "properties": {
    "iso:country":"US",
    "sg:address":"21602 N 2nd Ave",
    "sg:city":"Phoenix",
    "sg:classifiers":[
        {
            "category":"Professional",
            "subcategory":"Art Services",
            "type":"Services"
        }
    ],
    "sg:phone":"+1 623 516 9111",
    "sg:postcode":"85027",
    "sg:province":"AZ",
    "sg:tags":[
        "artist"
    ],
    "wof:name":"Banner Wilson",
    "wof:placetype":"venue"
},
  "geometry": {"coordinates":[-112.076161,33.682324],"type":"Point"}
}