{
  "type": "Feature",
  "properties": {
    "iso:country":"US",
    "sg:address":"8689 E Fillmore St",
    "sg:city":"Scottsdale",
    "sg:classifiers":[
        {
            "category":"Professional",
            "subcategory":"Accounting & Tax Preparation",
            "type":"Services"
        }
    ],
    "sg:phone":"+1 480 675 8580",
    "sg:postcode":"85257",
    "sg:province":"AZ",
    "sg:tags":[
        "bookkeeping",
        "billing"
    ],
    "wof:name":"Riley Bookkeeping Services",
    "wof:placetype":"venue"
},
  "geometry": {"coordinates":[-111.893992,33.45528],"type":"Point"}
}