{
  "type": "Feature",
  "properties": {
    "iso:country":"US",
    "sg:address":"4101 W Campo Bello Dr",
    "sg:city":"Glendale",
    "sg:classifiers":[
        {
            "category":"Home & Garden",
            "subcategory":"Home Furnishings",
            "type":"Retail Goods"
        }
    ],
    "sg:phone":"+1 602 788 4880",
    "sg:postcode":"85308",
    "sg:province":"AZ",
    "sg:tags":[
        "draperies",
        "window",
        "treatment",
        "curtain",
        "drapery",
        "trimming"
    ],
    "wof:name":"Spring Crest Drapery Center",
    "wof:placetype":"venue"
},
  "geometry": {"coordinates":[-112.147179,33.643661],"type":"Point"}
}