{
  "type": "Feature",
  "properties": {
    "addr:full":"8008 W Melinda Ln Peoria AZ 85382",
    "addr:housenumber":"8008",
    "addr:postcode":"85382",
    "addr:street":"W Melinda Ln",
    "iso:country":"US",
    "sg:address":"8008 W Melinda Ln",
    "sg:city":"Peoria",
    "sg:classifiers":[
        {
            "category":"Real Estate",
            "subcategory":"Developer",
            "type":"Services"
        }
    ],
    "sg:phone":"+1 623 825 1961",
    "sg:postcode":"85382",
    "sg:province":"AZ",
    "sg:website":"http://www.seeryous.com",
    "wof:name":"Seeryous Web Development",
    "wof:placetype":"venue"
},
  "geometry": {"coordinates":[-112.231655,33.680178],"type":"Point"}
}