{
  "type": "Feature",
  "properties": {
    "iso:country":"US",
    "sg:address":"2539 N Balboa Ave",
    "sg:city":"Tucson",
    "sg:classifiers":[
        {
            "category":"Real Estate",
            "subcategory":"Real Estate Operator",
            "type":"Services"
        }
    ],
    "sg:phone":"+1 520 622 7488",
    "sg:postcode":"85705",
    "sg:province":"AZ",
    "sg:tags":[
        "owner",
        "property"
    ],
    "wof:name":"Falcon Automatic Inc",
    "wof:placetype":"venue"
},
  "geometry": {"coordinates":[-110.976311,32.252203],"type":"Point"}
}