{
  "type": "Feature",
  "properties": {
    "addr:full":"1957 Lipan Blvd Fort Mohave AZ 86426",
    "addr:housenumber":"1957",
    "addr:postcode":"86426",
    "addr:street":"Lipan Blvd",
    "iso:country":"US",
    "sg:address":"1957 Lipan Blvd",
    "sg:city":"Fort Mohave",
    "sg:classifiers":[
        {
            "category":"Building & Trades",
            "subcategory":"Construction",
            "type":"Services"
        }
    ],
    "sg:phone":"+1 928 768 8856",
    "sg:postcode":"86426",
    "sg:province":"AZ",
    "sg:tags":[
        "general",
        "contractor"
    ],
    "wof:name":"Borges Construction",
    "wof:placetype":"venue"
},
  "geometry": {"coordinates":[-114.580529,34.982555],"type":"Point"}
}