{
  "type": "Feature",
  "properties": {
    "iso:country":"US",
    "sg:address":"7850 E Old Walnut Canyon Rd",
    "sg:city":"Flagstaff",
    "sg:classifiers":[
        {
            "category":"Shopping",
            "subcategory":"Clothing, Apparel, & Fashions",
            "type":"Retail Goods"
        }
    ],
    "sg:phone":"+1 928 526 6833",
    "sg:postcode":"86004",
    "sg:province":"AZ",
    "wof:name":"United States Outfitters",
    "wof:placetype":"venue"
},
  "geometry": {"coordinates":[-111.562609,35.198767],"type":"Point"}
}