{
  "type": "Feature",
  "properties": {
    "addr:full":"1279 French Rd Winslow AZ 86047",
    "addr:housenumber":"1279",
    "addr:postcode":"86047",
    "addr:street":"French Rd",
    "iso:country":"US",
    "sg:address":"1279 French Rd",
    "sg:city":"Winslow",
    "sg:classifiers":[
        {
            "category":"Building & Trades",
            "subcategory":"Electrical",
            "type":"Services"
        }
    ],
    "sg:phone":"+1 928 289 3506",
    "sg:postcode":"86047",
    "sg:province":"AZ",
    "sg:tags":[
        "electrician"
    ],
    "wof:name":"Hancock Gene Northern Arizona Electric",
    "wof:placetype":"venue"
},
  "geometry": {"coordinates":[-110.675833,35.035897],"type":"Point"}
}