{
  "type": "Feature",
  "properties": {
    "addr:full":"1954 E Deer Valley Rd Phoenix AZ 85024",
    "addr:housenumber":"1954",
    "addr:postcode":"85024",
    "addr:street":"E Deer Valley Rd",
    "iso:country":"US",
    "sg:address":"1954 E Deer Valley Rd",
    "sg:city":"Phoenix",
    "sg:classifiers":[
        {
            "category":"Wholesale",
            "subcategory":"Home Furnishings",
            "type":"Manufacturing & Wholesale Goods"
        }
    ],
    "sg:phone":"+1 623 434 6900",
    "sg:postcode":"85024",
    "sg:province":"AZ",
    "sg:tags":[
        "window",
        "shades"
    ],
    "wof:name":"Carefree Shade Systems Inc",
    "wof:placetype":"venue"
},
  "geometry": {"coordinates":[-112.03929100000001,33.687615],"type":"Point"}
}