{
  "type": "Feature",
  "properties": {
    "iso:country":"US",
    "sg:address":"1954 E Deer Valley Rd",
    "sg:city":"Phoenix",
    "sg:classifiers":[
        {
            "category":"Wholesale",
            "subcategory":"Home Furnishings",
            "type":"Manufacturing & Wholesale Goods"
        }
    ],
    "sg:phone":"+1 623 434 6900",
    "sg:postcode":"85024",
    "sg:province":"AZ",
    "sg:tags":[
        "window",
        "shades"
    ],
    "wof:name":"Carefree Shade Systems Inc",
    "wof:placetype":"venue"
},
  "geometry": {"coordinates":[-112.039291,33.687615],"type":"Point"}
}