{
  "type": "Feature",
  "properties": {
    "iso:country":"US",
    "sg:address":"902 E Gurley St",
    "sg:city":"Prescott",
    "sg:classifiers":[
        {
            "category":"Real Estate",
            "subcategory":"Real Estate Agent",
            "type":"Services"
        }
    ],
    "sg:phone":"+1 928 771 0021",
    "sg:postcode":"86301",
    "sg:province":"AZ",
    "wof:name":"Realty Consultants Of Prescott",
    "wof:placetype":"venue"
},
  "geometry": {"coordinates":[-112.457875,34.542041],"type":"Point"}
}