{
  "type": "Feature",
  "properties": {
    "iso:country":"US",
    "sg:address":"7135 N 6th Ave",
    "sg:city":"Phoenix",
    "sg:classifiers":[
        {
            "category":"Shopping",
            "subcategory":"Gifts & Souvenirs",
            "type":"Retail Goods"
        }
    ],
    "sg:phone":"+1 602 944 2975",
    "sg:postcode":"85021",
    "sg:province":"AZ",
    "sg:tags":[
        "announcement",
        "invitation"
    ],
    "wof:name":"Creative Papers Ink",
    "wof:placetype":"venue"
},
  "geometry": {"coordinates":[-112.080689,33.540153],"type":"Point"}
}