{
  "type": "Feature",
  "properties": {
    "addr:full":"7135 N 6th Ave Phoenix AZ 85021",
    "addr:housenumber":"7135",
    "addr:postcode":"85021",
    "addr:street":"N 6Th Ave",
    "iso:country":"US",
    "sg:address":"7135 N 6th Ave",
    "sg:city":"Phoenix",
    "sg:classifiers":[
        {
            "category":"Shopping",
            "subcategory":"Gifts & Souvenirs",
            "type":"Retail Goods"
        }
    ],
    "sg:phone":"+1 602 944 2975",
    "sg:postcode":"85021",
    "sg:province":"AZ",
    "sg:tags":[
        "announcement",
        "invitation"
    ],
    "wof:name":"Creative Papers Ink",
    "wof:placetype":"venue"
},
  "geometry": {"coordinates":[-112.08068900000001,33.540153],"type":"Point"}
}