{
  "type": "Feature",
  "properties": {
    "iso:country":"US",
    "sg:address":"4714 W Charleston Ave",
    "sg:city":"Glendale",
    "sg:classifiers":[
        {
            "category":"Building & Trades",
            "subcategory":"Pest Control",
            "type":"Services"
        }
    ],
    "sg:phone":"+1 602 938 2424",
    "sg:postcode":"85308",
    "sg:province":"AZ",
    "wof:name":"Ohland's Family Pest Control",
    "wof:placetype":"venue"
},
  "geometry": {"coordinates":[-112.161224,33.649422],"type":"Point"}
}