{
  "type": "Feature",
  "properties": {
    "iso:country":"US",
    "sg:address":"2930 N Swan Rd",
    "sg:city":"Tucson",
    "sg:classifiers":[
        {
            "category":"Banks & Credit Unions",
            "subcategory":"Bank",
            "type":"Services"
        }
    ],
    "sg:phone":"+1 520 290 1000",
    "sg:postcode":"85712",
    "sg:province":"AZ",
    "sg:tags":[
        "home",
        "mortgage"
    ],
    "wof:name":"Homeamerican Mortgage Corp",
    "wof:placetype":"venue"
},
  "geometry": {"coordinates":[-110.892388,32.260927],"type":"Point"}
}