{
  "type": "Feature",
  "properties": {
    "addr:full":"2500 S Power Rd Ste 113 Mesa AZ 85209",
    "addr:housenumber":"2500",
    "addr:postcode":"85209",
    "addr:street":"S Power Rd Ste 113",
    "iso:country":"US",
    "sg:address":"2500 S Power Rd Ste 113",
    "sg:city":"Mesa",
    "sg:classifiers":[
        {
            "category":"Real Estate",
            "subcategory":"Real Estate Services",
            "type":"Services"
        }
    ],
    "sg:phone":"+1 480 892 9472",
    "sg:postcode":"85209",
    "sg:province":"AZ",
    "sg:tags":[
        "vacancy",
        "rental",
        "listing"
    ],
    "wof:name":"Maui Vacation Condos",
    "wof:placetype":"venue"
},
  "geometry": {"coordinates":[-111.687752,33.370104],"type":"Point"}
}