{
  "type": "Feature",
  "properties": {
    "addr:full":"2111 S Industrial Park Ave Suite 109 Tempe AZ 85282",
    "addr:housenumber":"2111",
    "addr:postcode":"85282",
    "addr:street":"S Industrial Park Ave Suite 109",
    "iso:country":"US",
    "sg:address":"2111 S Industrial Park Ave Suite 109",
    "sg:city":"Tempe",
    "sg:phone":"+1 480 567 9443",
    "sg:postcode":"85282",
    "sg:province":"AZ",
    "wof:name":"Affordable Windows",
    "wof:placetype":"venue"
},
  "geometry": {"coordinates":[-111.955179,33.407269],"type":"Point"}
}