{
  "type": "Feature",
  "properties": {
    "addr:full":"120 Deer Trail Dr Sedona AZ 86336",
    "addr:housenumber":"120",
    "addr:postcode":"86336",
    "addr:street":"Deer Trail Dr",
    "iso:country":"US",
    "sg:address":"120 Deer Trail Dr",
    "sg:city":"Sedona",
    "sg:classifiers":[
        {
            "category":"Professional",
            "type":"Services"
        }
    ],
    "sg:phone":"+1 928 204 1633",
    "sg:postcode":"86336",
    "sg:province":"AZ",
    "sg:tags":[
        "establishment"
    ],
    "wof:name":"Michael Rabasca Consulting",
    "wof:placetype":"venue"
},
  "geometry": {"coordinates":[-111.811312,34.860125],"type":"Point"}
}