{
  "type": "Feature",
  "properties": {
    "iso:country":"US",
    "sg:address":"1410 S 37th St",
    "sg:city":"Mesa",
    "sg:classifiers":[
        {
            "category":"Building & Trades",
            "subcategory":"Plumbing",
            "type":"Services"
        }
    ],
    "sg:phone":"+1 480 733 9471",
    "sg:postcode":"85206",
    "sg:province":"AZ",
    "sg:tags":[
        "contractor"
    ],
    "wof:name":"Rwb Plumbing Inc",
    "wof:placetype":"venue"
},
  "geometry": {"coordinates":[-111.751901,33.388682],"type":"Point"}
}