{
  "type": "Feature",
  "properties": {
    "iso:country":"US",
    "sg:address":"4050 N Eagle Dr",
    "sg:city":"Kingman",
    "sg:classifiers":[
        {
            "category":"Building & Trades",
            "subcategory":"Plumbing",
            "type":"Services"
        }
    ],
    "sg:phone":"+1 928 716 0763",
    "sg:postcode":"86409",
    "sg:province":"AZ",
    "sg:tags":[
        "tank",
        "system",
        "septic"
    ],
    "wof:name":"Mohave Septic & Excavating",
    "wof:placetype":"venue"
},
  "geometry": {"coordinates":[-113.99327099999999,35.241875],"type":"Point"}
}