{
  "type": "Feature",
  "properties": {
    "iso:country":"US",
    "sg:address":"9330 E Rocky Lake Dr",
    "sg:city":"Sun Lakes",
    "sg:classifiers":[
        {
            "category":"Real Estate",
            "subcategory":"Real Estate Agent",
            "type":"Services"
        }
    ],
    "sg:phone":"+1 480 895 0212",
    "sg:postcode":"85248",
    "sg:province":"AZ",
    "wof:name":"Curcio Enterprises",
    "wof:placetype":"venue"
},
  "geometry": {"coordinates":[-111.881896,33.224962],"type":"Point"}
}