{
  "type": "Feature",
  "properties": {
    "addr:full":"275 S 4th St Camp Verde AZ 86322",
    "addr:housenumber":"275",
    "addr:postcode":"az 86322",
    "addr:street":"S 4Th St",
    "iso:country":"US",
    "sg:address":"275 S 4th St",
    "sg:city":"Camp Verde",
    "sg:classifiers":[
        {
            "category":"Retail",
            "subcategory":"Repair Shop",
            "type":"Services"
        }
    ],
    "sg:phone":"+1 928 567 6180",
    "sg:postcode":"86322",
    "sg:province":"AZ",
    "sg:tags":[
        "refinishing",
        "furniture"
    ],
    "wof:name":"Leon Cardini Furn Restoration",
    "wof:placetype":"venue"
},
  "geometry": {"coordinates":[-111.857687,34.564956],"type":"Point"}
}