{
  "type": "Feature",
  "properties": {
    "addr:full":"720 E Palo Verde St Gilbert AZ 85296",
    "addr:housenumber":"720",
    "addr:postcode":"85296",
    "addr:street":"E Palo Verde St",
    "iso:country":"US",
    "sg:address":"720 E Palo Verde St",
    "sg:city":"Gilbert",
    "sg:classifiers":[
        {
            "category":"Insurance",
            "subcategory":"Insurance Agent",
            "type":"Services"
        }
    ],
    "sg:phone":"+1 480 545 9139",
    "sg:postcode":"85296",
    "sg:province":"AZ",
    "wof:name":"Bobadilla Associnc",
    "wof:placetype":"venue"
},
  "geometry": {"coordinates":[-111.774495,33.346396],"type":"Point"}
}