{
  "type": "Feature",
  "properties": {
    "iso:country":"US",
    "sg:address":"2520 W Ver Felicidad",
    "sg:city":"Tucson",
    "sg:classifiers":[
        {
            "category":"Wholesale",
            "subcategory":"Sporting Goods",
            "type":"Manufacturing & Wholesale Goods"
        }
    ],
    "sg:phone":"+1 520 578 1547",
    "sg:postcode":"85746",
    "sg:province":"AZ",
    "wof:name":"B&L Racing Promotions",
    "wof:placetype":"venue"
},
  "geometry": {"coordinates":[-111.021671,32.126919],"type":"Point"}
}