{
  "type": "Feature",
  "properties": {
    "iso:country":"US",
    "sg:address":"7090 E 22nd St",
    "sg:city":"Tucson",
    "sg:classifiers":[
        {
            "category":"Autos & Motor Vehicles",
            "subcategory":"Fuel & Gas Station",
            "type":"Retail Goods"
        }
    ],
    "sg:phone":"+1 520 571 0514",
    "sg:postcode":"85710",
    "sg:province":"AZ",
    "sg:tags":[
        "oil"
    ],
    "wof:name":"Chevron Food Mart",
    "wof:placetype":"venue"
},
  "geometry": {"coordinates":[-110.843689,32.206424],"type":"Point"}
}