{
  "type": "Feature",
  "properties": {
    "iso:country":"US",
    "sg:address":"135 S Power Rd",
    "sg:city":"Mesa",
    "sg:classifiers":[
        {
            "category":"Health Services",
            "subcategory":"Doctor",
            "type":"Services"
        }
    ],
    "sg:phone":"+1 480 325 7535",
    "sg:postcode":"85206",
    "sg:province":"AZ",
    "sg:tags":[
        "physician",
        "surgeon"
    ],
    "wof:name":"Southwest Kidney Institute",
    "wof:placetype":"venue"
},
  "geometry": {"coordinates":[-111.68444700000001,33.414221],"type":"Point"}
}