{
  "type": "Feature",
  "properties": {
    "addr:full":"2502 N 61st Pl Scottsdale AZ 85257",
    "addr:housenumber":"2502",
    "addr:postcode":"85257",
    "addr:street":"N 61St Pl",
    "iso:country":"US",
    "sg:address":"2502 N 61st Pl",
    "sg:city":"Scottsdale",
    "sg:classifiers":[
        {
            "category":"Building & Trades",
            "subcategory":"Construction",
            "type":"Services"
        }
    ],
    "sg:phone":"+1 480 947 4064",
    "sg:postcode":"85257",
    "sg:province":"AZ",
    "sg:tags":[
        "home",
        "builder"
    ],
    "wof:name":"Housing Tech Inc",
    "wof:placetype":"venue"
},
  "geometry": {"coordinates":[-111.949245,33.475395],"type":"Point"}
}