{
  "type": "Feature",
  "properties": {
    "iso:country":"US",
    "sg:address":"3860 S Palo Verde Rd",
    "sg:city":"Tucson",
    "sg:classifiers":[
        {
            "category":"Professional",
            "subcategory":"Management & Consulting",
            "type":"Services"
        }
    ],
    "sg:phone":"+1 520 885 7331",
    "sg:postcode":"85714",
    "sg:province":"AZ",
    "sg:tags":[
        "break",
        "coffee",
        "supply"
    ],
    "wof:name":"King Richard Coffee Svc Co",
    "wof:placetype":"venue"
},
  "geometry": {"coordinates":[-110.917782,32.176606],"type":"Point"}
}