{
  "type": "Feature",
  "properties": {
    "iso:country":"US",
    "sg:address":"815 E Maryland Ave",
    "sg:city":"Phoenix",
    "sg:classifiers":[
        {
            "category":"Real Estate",
            "subcategory":"Real Estate Operator",
            "type":"Services"
        }
    ],
    "sg:phone":"+1 602 265 3765",
    "sg:postcode":"85014",
    "sg:province":"AZ",
    "sg:tags":[
        "apartment"
    ],
    "wof:name":"Spiral Staircase",
    "wof:placetype":"venue"
},
  "geometry": {"coordinates":[-112.06400600000001,33.530909],"type":"Point"}
}