{
  "type": "Feature",
  "properties": {
    "iso:country":"US",
    "sg:address":"8620 E McDonald Dr",
    "sg:city":"Scottsdale",
    "sg:classifiers":[
        {
            "category":"Organizations",
            "subcategory":"Religious Organization",
            "type":"Services"
        }
    ],
    "sg:phone":"+1 480 948 8800",
    "sg:postcode":"85250",
    "sg:province":"AZ",
    "sg:tags":[
        "church"
    ],
    "sg:website":"www.rca.org",
    "wof:name":"Glass & Garden Drive-In Church",
    "wof:placetype":"venue"
},
  "geometry": {"coordinates":[-111.894414,33.523926],"type":"Point"}
}