{
  "type": "Feature",
  "properties": {
    "iso:country":"US",
    "sg:address":"6225 N 24th St",
    "sg:city":"Phoenix",
    "sg:classifiers":[
        {
            "category":"Banks & Credit Unions",
            "subcategory":"Bank",
            "type":"Services"
        }
    ],
    "sg:phone":"+1 602 553 7920",
    "sg:postcode":"85016",
    "sg:province":"AZ",
    "wof:name":"First National Bank Of Arizona",
    "wof:placetype":"venue"
},
  "geometry": {"coordinates":[-112.029903,33.524489],"type":"Point"}
}