{
  "type": "Feature",
  "properties": {
    "iso:country":"US",
    "sg:address":"6403 W McDowell Rd",
    "sg:city":"Phoenix",
    "sg:classifiers":[
        {
            "category":"Building & Trades",
            "subcategory":"Construction",
            "type":"Services"
        }
    ],
    "sg:phone":"+1 623 245 0647",
    "sg:postcode":"85035",
    "sg:province":"AZ",
    "sg:tags":[
        "contractor"
    ],
    "wof:name":"Ruggles Masonry",
    "wof:placetype":"venue"
},
  "geometry": {"coordinates":[-112.198077,33.46581],"type":"Point"}
}