{
  "type": "Feature",
  "properties": {
    "iso:country":"US",
    "sg:address":"1100 S Hwy 260",
    "sg:city":"Cottonwood",
    "sg:classifiers":[
        {
            "category":"Building & Trades",
            "subcategory":"Equipment Rental",
            "type":"Services"
        }
    ],
    "sg:phone":"+1 928 649 1131",
    "sg:postcode":"86326",
    "sg:province":"AZ",
    "sg:tags":[
        "leasing",
        "furniture"
    ],
    "wof:name":"Rent-A-Center",
    "wof:placetype":"venue"
},
  "geometry": {"coordinates":[-112.002557,34.72034],"type":"Point"}
}