{
  "type": "Feature",
  "properties": {
    "addr:full":"4716 E Thunderbird Rd # 101 Phoenix AZ 85032",
    "addr:housenumber":"4716",
    "addr:postcode":"85032",
    "addr:street":"E Thunderbird Rd # 101",
    "iso:country":"US",
    "sg:address":"4716 E Thunderbird Rd # 101",
    "sg:city":"Phoenix",
    "sg:classifiers":[
        {
            "category":"Manufacturing",
            "subcategory":"Tools & Machinery",
            "type":"Manufacturing & Wholesale Goods"
        }
    ],
    "sg:phone":"+1 602 996 3488",
    "sg:postcode":"85032",
    "sg:province":"AZ",
    "sg:tags":[
        "hand"
    ],
    "wof:name":"Rockler Retail Group, Inc.",
    "wof:placetype":"venue"
},
  "geometry": {"coordinates":[-111.97943100000001,33.611571],"type":"Point"}
}