{
  "type": "Feature",
  "properties": {
    "iso:country":"US",
    "sg:address":"9561 E Presidio Rd",
    "sg:city":"Scottsdale",
    "sg:classifiers":[
        {
            "category":"Manufacturing",
            "subcategory":"Retail Goods",
            "type":"Manufacturing & Wholesale Goods"
        }
    ],
    "sg:phone":"+1 480 314 7560",
    "sg:postcode":"85260",
    "sg:province":"AZ",
    "sg:tags":[
        "product",
        "mfg"
    ],
    "wof:name":"Cooler Industries LLC",
    "wof:placetype":"venue"
},
  "geometry": {"coordinates":[-111.874112,33.608271],"type":"Point"}
}