{
  "type": "Feature",
  "properties": {
    "iso:country":"US",
    "sg:address":"7277 N Oldfather Rd",
    "sg:city":"Tucson",
    "sg:classifiers":[
        {
            "category":"Social Services",
            "subcategory":"Child Care",
            "type":"Services"
        }
    ],
    "sg:phone":"+1 520 744 3084",
    "sg:postcode":"85741",
    "sg:province":"AZ",
    "sg:website":"www.knowledgelearning.com",
    "wof:name":"Children's World Learning Ctr",
    "wof:placetype":"venue"
},
  "geometry": {"coordinates":[-111.055527,32.337919],"type":"Point"}
}