{
  "type": "Feature",
  "properties": {
    "iso:country":"US",
    "sg:address":"6300 E Bell Rd",
    "sg:city":"Scottsdale",
    "sg:classifiers":[
        {
            "category":"Organizations",
            "subcategory":"Religious Organization",
            "type":"Services"
        }
    ],
    "sg:phone":"+1 480 948 1234",
    "sg:postcode":"85254",
    "sg:province":"AZ",
    "sg:tags":[
        "church"
    ],
    "sg:website":"www.lacasadecristo.com",
    "wof:name":"LA Casa De Cristo Lutheran",
    "wof:placetype":"venue"
},
  "geometry": {"coordinates":[-111.94285,33.640418],"type":"Point"}
}