{
  "type": "Feature",
  "properties": {
    "iso:country":"US",
    "sg:address":"3845 N Business Center Dr",
    "sg:city":"Tucson",
    "sg:classifiers":[
        {
            "category":"Building & Trades",
            "subcategory":"Plumbing",
            "type":"Services"
        }
    ],
    "sg:phone":"+1 520 888 0480",
    "sg:postcode":"85705",
    "sg:province":"AZ",
    "sg:tags":[
        "plumbing",
        "contractor"
    ],
    "wof:name":"Dwight T Haworth Jr",
    "wof:placetype":"venue"
},
  "geometry": {"coordinates":[-111.016113,32.277531],"type":"Point"}
}