{
  "type": "Feature",
  "properties": {
    "iso:country":"US",
    "sg:address":"16036 N 11th Ave",
    "sg:city":"Phoenix",
    "sg:classifiers":[
        {
            "category":"Building & Trades",
            "subcategory":"Cleaning & Sanitation",
            "type":"Services"
        }
    ],
    "sg:phone":"+1 602 439 5959",
    "sg:postcode":"85023",
    "sg:province":"AZ",
    "sg:tags":[
        "janitor"
    ],
    "wof:name":"Garcia's Commercial Cleaning",
    "wof:placetype":"venue"
},
  "geometry": {"coordinates":[-112.087074,33.632462],"type":"Point"}
}