{
  "type": "Feature",
  "properties": {
    "iso:country":"US",
    "sg:address":"5001 S 36th St",
    "sg:city":"Phoenix",
    "sg:classifiers":[
        {
            "category":"Wholesale",
            "subcategory":"Durable Goods & Equipment",
            "type":"Manufacturing & Wholesale Goods"
        }
    ],
    "sg:phone":"+1 602 258 1557",
    "sg:postcode":"85040",
    "sg:province":"AZ",
    "sg:tags":[
        "representative",
        "manufacturer"
    ],
    "wof:name":"Repnet",
    "wof:placetype":"venue"
},
  "geometry": {"coordinates":[-112.004058,33.399944],"type":"Point"}
}