{
  "type": "Feature",
  "properties": {
    "addr:full":"1640 W Thatcher Blvd Safford AZ 85546",
    "addr:housenumber":"1640",
    "addr:postcode":"85546",
    "addr:street":"W Thatcher Blvd",
    "iso:country":"US",
    "sg:address":"1640 W Thatcher Blvd",
    "sg:city":"Safford",
    "sg:classifiers":[
        {
            "category":"Shopping",
            "subcategory":"Department Store",
            "type":"Retail Goods"
        }
    ],
    "sg:phone":"+1 928 428 0386",
    "sg:postcode":"85546",
    "sg:province":"AZ",
    "wof:name":"Dollar General",
    "wof:placetype":"venue"
},
  "geometry": {"coordinates":[-109.729198,32.835098],"type":"Point"}
}