{
  "type": "Feature",
  "properties": {
    "iso:country":"US",
    "sg:address":"6234 E Cholla Ln",
    "sg:city":"Paradise Valley",
    "sg:classifiers":[
        {
            "category":"Real Estate",
            "subcategory":"Developer",
            "type":"Services"
        }
    ],
    "sg:phone":"+1 480 947 7028",
    "sg:postcode":"85253",
    "sg:province":"AZ",
    "wof:name":"Salero Corporation",
    "wof:placetype":"venue"
},
  "geometry": {"coordinates":[-111.948607,33.513704],"type":"Point"}
}