{
  "type": "Feature",
  "properties": {
    "iso:country":"US",
    "sg:address":"16211 E Red Mountain Trl",
    "sg:city":"Fountain Hills",
    "sg:classifiers":[
        {
            "category":"Banks & Credit Unions",
            "subcategory":"Bank",
            "type":"Services"
        }
    ],
    "sg:phone":"+1 480 836 7060",
    "sg:postcode":"85268",
    "sg:province":"AZ",
    "sg:tags":[
        "broker",
        "mortgage"
    ],
    "wof:name":"Hacienda Lending Inc",
    "wof:placetype":"venue"
},
  "geometry": {"coordinates":[-111.73101800000001,33.570462],"type":"Point"}
}