{
  "type": "Feature",
  "properties": {
    "iso:country":"US",
    "sg:address":"2615 E Beekman Pl",
    "sg:city":"Phoenix",
    "sg:classifiers":[
        {
            "category":"Shopping",
            "subcategory":"Computers & Home Electronics",
            "type":"Retail Goods"
        },
        {
            "category":"Wholesale",
            "subcategory":"Computers",
            "type":"Manufacturing & Wholesale Goods"
        }
    ],
    "sg:phone":"+1 602 955 4645",
    "sg:postcode":"85016",
    "sg:province":"AZ",
    "sg:tags":[
        "hardware",
        "manufacturer",
        "computer-wholesale",
        "supply"
    ],
    "wof:name":"E-Tech Spare Parts Inc",
    "wof:placetype":"venue"
},
  "geometry": {"coordinates":[-112.025368,33.486221],"type":"Point"}
}