{
  "type": "Feature",
  "properties": {
    "addr:full":"1430 S Power Rd Mesa AZ 85206",
    "addr:housenumber":"1430",
    "addr:postcode":"85206",
    "addr:street":"S Power Rd",
    "iso:country":"US",
    "sg:address":"1430 S Power Rd",
    "sg:city":"Mesa",
    "sg:classifiers":[
        {
            "category":"Home & Garden",
            "subcategory":"Furniture",
            "type":"Retail Goods"
        }
    ],
    "sg:phone":"+1 480 830 3300",
    "sg:postcode":"85206",
    "sg:province":"AZ",
    "sg:website":"www.la-z-boy.com",
    "wof:name":"La-Z-Boy Furniture Galleries",
    "wof:placetype":"venue"
},
  "geometry": {"coordinates":[-111.684865,33.388171],"type":"Point"}
}