{
  "type": "Feature",
  "properties": {
    "iso:country":"US",
    "sg:address":"207 N 12th Ave",
    "sg:city":"Phoenix",
    "sg:classifiers":[
        {
            "category":"Building & Trades",
            "subcategory":"Construction",
            "type":"Services"
        }
    ],
    "sg:phone":"+1 602 550 3158",
    "sg:postcode":"85007",
    "sg:province":"AZ",
    "sg:tags":[
        "altering",
        "house",
        "remodeling",
        "contractor"
    ],
    "wof:name":"Chuck & Twila's Home Repair",
    "wof:placetype":"venue"
},
  "geometry": {"coordinates":[-112.088123,33.45059],"type":"Point"}
}