{
  "type": "Feature",
  "properties": {
    "iso:country":"US",
    "sg:address":"3137 N 20th Pl",
    "sg:city":"Phoenix",
    "sg:classifiers":[
        {
            "category":"Freight",
            "type":"Transportation"
        }
    ],
    "sg:phone":"+1 602 955 0071",
    "sg:postcode":"85016",
    "sg:province":"AZ",
    "sg:tags":[
        "delivery"
    ],
    "wof:name":"Accurate Delivery Systems",
    "wof:placetype":"venue"
},
  "geometry": {"coordinates":[-112.037937,33.484996],"type":"Point"}
}