{
  "type": "Feature",
  "properties": {
    "iso:country":"US",
    "sg:address":"4615 W Indian School Rd",
    "sg:city":"Phoenix",
    "sg:classifiers":[
        {
            "category":"Home & Garden",
            "subcategory":"Building Materials",
            "type":"Retail Goods"
        }
    ],
    "sg:phone":"+1 602 447 0991",
    "sg:postcode":"85031",
    "sg:province":"AZ",
    "sg:tags":[
        "glass",
        "window",
        "plate"
    ],
    "sg:website":"www.valleywide.com",
    "wof:name":"Discount Auto Glass & Window",
    "wof:placetype":"venue"
},
  "geometry": {"coordinates":[-112.160001,33.494879],"type":"Point"}
}