{
  "type": "Feature",
  "properties": {
    "iso:country":"US",
    "sg:address":"3825 N 16th St",
    "sg:city":"Phoenix",
    "sg:classifiers":[
        {
            "category":"Banks & Credit Unions",
            "subcategory":"Bank",
            "type":"Services"
        }
    ],
    "sg:phone":"+1 602 230 1122",
    "sg:postcode":"85016",
    "sg:province":"AZ",
    "sg:tags":[
        "financing"
    ],
    "wof:name":"Contract Funding",
    "wof:placetype":"venue"
},
  "geometry": {"coordinates":[-112.047557,33.491692],"type":"Point"}
}