{
  "type": "Feature",
  "properties": {
    "addr:full":"531 E 28th St Tucson AZ 85713",
    "addr:housenumber":"531",
    "addr:postcode":"85713",
    "addr:street":"E 28Th St",
    "iso:country":"US",
    "sg:address":"531 E 28th St",
    "sg:city":"Tucson",
    "sg:classifiers":[
        {
            "category":"Building & Trades",
            "subcategory":"Plumbing",
            "type":"Services"
        }
    ],
    "sg:phone":"+1 520 770 9800",
    "sg:postcode":"85713",
    "sg:province":"AZ",
    "sg:tags":[
        "concrete",
        "waterproofing"
    ],
    "sg:website":"www.rsherder.com",
    "wof:name":"R S Herder Corp",
    "wof:placetype":"venue"
},
  "geometry": {"coordinates":[-110.961361,32.200697],"type":"Point"}
}