{
  "type": "Feature",
  "properties": {
    "iso:country":"US",
    "sg:address":"1111 W Maricopa Fwy",
    "sg:city":"Phoenix",
    "sg:classifiers":[
        {
            "category":"Manufacturing",
            "subcategory":"Metals",
            "type":"Manufacturing & Wholesale Goods"
        }
    ],
    "sg:phone":"+1 602 252 8061",
    "sg:postcode":"85007",
    "sg:province":"AZ",
    "sg:tags":[
        "steel",
        "distributor",
        "mill",
        "warehouse"
    ],
    "sg:website":"http://www.escocorp.com",
    "wof:name":"Heflin Steel Divison",
    "wof:placetype":"venue"
},
  "geometry": {"coordinates":[-112.086849,33.429332],"type":"Point"}
}