{
  "type": "Feature",
  "properties": {
    "iso:country":"US",
    "sg:address":"463 N Broad St",
    "sg:city":"Globe",
    "sg:classifiers":[
        {
            "category":"Personal",
            "subcategory":"Beauty Salon",
            "type":"Services"
        }
    ],
    "sg:phone":"+1 928 425 9420",
    "sg:postcode":"85501",
    "sg:province":"AZ",
    "wof:name":"Hope's Beauty Salon",
    "wof:placetype":"venue"
},
  "geometry": {"coordinates":[-110.78883,33.399506],"type":"Point"}
}