{
  "type": "Feature",
  "properties": {
    "iso:country":"US",
    "sg:address":"6002 E 21st St",
    "sg:city":"Tucson",
    "sg:classifiers":[
        {
            "category":"Retail",
            "subcategory":"Laundry & Dry Cleaning",
            "type":"Services"
        }
    ],
    "sg:phone":"+1 520 750 0748",
    "sg:postcode":"85711",
    "sg:province":"AZ",
    "sg:tags":[
        "cleaners",
        "rug",
        "carpet"
    ],
    "wof:name":"Reliance Carpet Cleaning",
    "wof:placetype":"venue"
},
  "geometry": {"coordinates":[-110.86228699999999,32.208188],"type":"Point"}
}