{
  "type": "Feature",
  "properties": {
    "addr:full":"2770 N Van Buren Ave Tucson AZ 85712",
    "addr:housenumber":"2770",
    "addr:postcode":"85712",
    "addr:street":"N Van Buren Ave",
    "iso:country":"US",
    "sg:address":"2770 N Van Buren Ave",
    "sg:city":"Tucson",
    "sg:classifiers":[
        {
            "category":"Social Services",
            "subcategory":"Adult Care",
            "type":"Services"
        }
    ],
    "sg:phone":"+1 520 298 2400",
    "sg:postcode":"85712",
    "sg:province":"AZ",
    "sg:tags":[
        "home",
        "residential"
    ],
    "wof:name":"A Desert Casita Assisted Lvng",
    "wof:placetype":"venue"
},
  "geometry": {"coordinates":[-110.871398,32.257133],"type":"Point"}
}