{
  "type": "Feature",
  "properties": {
    "addr:full":"1241 E Washington St Phoenix AZ 85034",
    "addr:housenumber":"1241",
    "addr:postcode":"85034",
    "addr:street":"E Washington St",
    "iso:country":"US",
    "sg:address":"1241 E Washington St",
    "sg:city":"Phoenix",
    "sg:classifiers":[
        {
            "category":"Social Services",
            "type":"Services"
        }
    ],
    "sg:phone":"+1 602 437 8664",
    "sg:postcode":"85034",
    "sg:province":"AZ",
    "sg:tags":[
        "organization",
        "welfare"
    ],
    "wof:name":"Child & Adult Comm Resources",
    "wof:placetype":"venue"
},
  "geometry": {"coordinates":[-112.054964,33.448206],"type":"Point"}
}