{
  "type": "Feature",
  "properties": {
    "iso:country":"US",
    "sg:address":"9514 1/2 N 8th St",
    "sg:city":"Phoenix",
    "sg:classifiers":[
        {
            "category":"Recreation",
            "subcategory":"Dog Park",
            "type":"Entertainment"
        },
        {
            "category":"Shopping",
            "subcategory":"Pets & Pet Supplies",
            "type":"Retail Goods"
        },
        {
            "category":"Retail",
            "subcategory":"Animal Services",
            "type":"Services"
        }
    ],
    "sg:phone":"+1 602 678 3664",
    "sg:postcode":"85020",
    "sg:province":"AZ",
    "sg:tags":[
        "training"
    ],
    "wof:name":"Desert Sky Canine",
    "wof:placetype":"venue"
},
  "geometry": {"coordinates":[-112.063056,33.5724],"type":"Point"}
}