{
  "type": "Feature",
  "properties": {
    "iso:country":"US",
    "sg:address":"2728 E Thomas Rd",
    "sg:city":"Phoenix",
    "sg:classifiers":[
        {
            "category":"Real Estate",
            "subcategory":"Architect",
            "type":"Services"
        }
    ],
    "sg:phone":"+1 602 954 4061",
    "sg:postcode":"85016",
    "sg:province":"AZ",
    "wof:name":"Stern & Assoc",
    "wof:placetype":"venue"
},
  "geometry": {"coordinates":[-112.022058,33.480465],"type":"Point"}
}