{
  "type": "Feature",
  "properties": {
    "addr:full":"12440 N 20th St Apt 207 Phoenix AZ 85022",
    "addr:housenumber":"12440;207",
    "addr:postcode":"85022",
    "addr:street":"N 20Th St Apt",
    "iso:country":"US",
    "sg:address":"12440 N 20th St Apt 207",
    "sg:city":"Phoenix",
    "sg:classifiers":[
        {
            "category":"Utilities",
            "subcategory":"Telephone",
            "type":"Services"
        }
    ],
    "sg:phone":"+1 602 314 5937",
    "sg:postcode":"85022",
    "sg:province":"AZ",
    "sg:tags":[
        "communication"
    ],
    "wof:name":"Joytech Telecom",
    "wof:placetype":"venue"
},
  "geometry": {"coordinates":[-112.03928399999999,33.59996],"type":"Point"}
}