{
  "type": "Feature",
  "properties": {
    "iso:country":"US",
    "sg:address":"14050 N 83rd Ave",
    "sg:city":"Peoria",
    "sg:classifiers":[
        {
            "category":"Farming",
            "subcategory":"Livestock Farm",
            "type":"Manufacturing & Wholesale Goods"
        }
    ],
    "sg:phone":"+1 623 878 1033",
    "sg:postcode":"85381",
    "sg:province":"AZ",
    "sg:tags":[
        "ranch"
    ],
    "wof:name":"Remuda Ranch",
    "wof:placetype":"venue"
},
  "geometry": {"coordinates":[-112.23761,33.612582],"type":"Point"}
}