{
  "type": "Feature",
  "properties": {
    "iso:country":"US",
    "sg:address":"2960 E Fry Blvd",
    "sg:city":"Sierra Vista",
    "sg:classifiers":[
        {
            "category":"Autos & Motor Vehicles",
            "subcategory":"Automobile Sales",
            "type":"Retail Goods"
        }
    ],
    "sg:phone":"+1 520 459 2000",
    "sg:postcode":"85635",
    "sg:province":"AZ",
    "wof:name":"Honda Nissan",
    "wof:placetype":"venue"
},
  "geometry": {"coordinates":[-110.268295,31.554557],"type":"Point"}
}