{
  "type": "Feature",
  "properties": {
    "iso:country":"US",
    "sg:address":"1819 S Dobson Rd",
    "sg:city":"Mesa",
    "sg:classifiers":[
        {
            "category":"Health Services",
            "subcategory":"Clinic",
            "type":"Services"
        }
    ],
    "sg:phone":"+1 480 820 5898",
    "sg:postcode":"85202",
    "sg:province":"AZ",
    "sg:tags":[
        "holistic",
        "practitioner"
    ],
    "wof:name":"Natural Alternatives Society",
    "wof:placetype":"venue"
},
  "geometry": {"coordinates":[-111.876289,33.381542],"type":"Point"}
}