{
  "type": "Feature",
  "properties": {
    "iso:country":"US",
    "sg:address":"9075 W Antoinette Way",
    "sg:city":"Flagstaff",
    "sg:classifiers":[
        {
            "category":"Professional",
            "type":"Services"
        }
    ],
    "sg:phone":"+1 928 556 0546",
    "sg:postcode":"86001",
    "sg:province":"AZ",
    "wof:name":"Erika Nowak",
    "wof:placetype":"venue"
},
  "geometry": {"coordinates":[-111.748856,35.255106],"type":"Point"}
}