{
  "type": "Feature",
  "properties": {
    "iso:country":"US",
    "sg:address":"7200 E Ventana Canyon Dr",
    "sg:city":"Tucson",
    "sg:classifiers":[
        {
            "category":"Building & Trades",
            "subcategory":"Construction",
            "type":"Services"
        }
    ],
    "sg:phone":"+1 520 577 6800",
    "sg:postcode":"85750",
    "sg:province":"AZ",
    "sg:tags":[
        "house"
    ],
    "wof:name":"Sonora Pacific Construction",
    "wof:placetype":"venue"
},
  "geometry": {"coordinates":[-110.837517,32.320297],"type":"Point"}
}