{
  "type": "Feature",
  "properties": {
    "addr:full":"8750 E Raintree Dr Scottsdale AZ 85260",
    "addr:housenumber":"8750",
    "addr:postcode":"85260",
    "addr:street":"E Raintree Dr",
    "iso:country":"US",
    "sg:address":"8750 E Raintree Dr",
    "sg:city":"Scottsdale",
    "sg:classifiers":[
        {
            "category":"Banks & Credit Unions",
            "subcategory":"Bank",
            "type":"Services"
        }
    ],
    "sg:phone":"+1 480 365 7280",
    "sg:postcode":"85260",
    "sg:province":"AZ",
    "wof:name":"Bank Of America",
    "wof:placetype":"venue"
},
  "geometry": {"coordinates":[-111.89235499999999,33.618229],"type":"Point"}
}