{
  "type": "Feature",
  "properties": {
    "iso:country":"US",
    "sg:address":"2828 N 36th St",
    "sg:city":"Phoenix",
    "sg:classifiers":[
        {
            "category":"Retail",
            "subcategory":"Laundry & Dry Cleaning",
            "type":"Services"
        },
        {
            "category":"Building & Trades",
            "subcategory":"Cleaning & Sanitation",
            "type":"Services"
        }
    ],
    "sg:phone":"+1 480 947 5286",
    "sg:postcode":"85008",
    "sg:province":"AZ",
    "sg:tags":[
        "cleaner",
        "upholstery",
        "rug",
        "carpet"
    ],
    "sg:website":"http://www.ecoclean-az.com",
    "wof:name":"Eco Clean - The Healthy Home Solution",
    "wof:placetype":"venue"
},
  "geometry": {"coordinates":[-112.004199,33.47882],"type":"Point"}
}