{
  "type": "Feature",
  "properties": {
    "addr:full":"745 E Manhatton Dr Tempe AZ 85282",
    "addr:housenumber":"745",
    "addr:postcode":"85282",
    "addr:street":"E Manhatton Dr",
    "iso:country":"US",
    "sg:address":"745 E Manhatton Dr",
    "sg:city":"Tempe",
    "sg:classifiers":[
        {
            "category":"Building & Trades",
            "subcategory":"Construction",
            "type":"Services"
        }
    ],
    "sg:phone":"+1 602 568 7642",
    "sg:postcode":"85282",
    "sg:province":"AZ",
    "sg:tags":[
        "cleaning",
        "contractor"
    ],
    "wof:name":"Mason Brothers",
    "wof:placetype":"venue"
},
  "geometry": {"coordinates":[-111.92770299999999,33.388538],"type":"Point"}
}