{
  "type": "Feature",
  "properties": {
    "iso:country":"US",
    "sg:address":"4550 N Oracle Rd",
    "sg:city":"Tucson",
    "sg:classifiers":[
        {
            "category":"Shopping",
            "subcategory":"Clothing, Apparel, & Fashions",
            "type":"Retail Goods"
        },
        {
            "category":"Shopping",
            "subcategory":"Beauty & Cosmetics",
            "type":"Retail Goods"
        },
        {
            "category":"Home & Garden",
            "subcategory":"Home Furnishings",
            "type":"Retail Goods"
        },
        {
            "category":"Shopping",
            "subcategory":"Department Store",
            "type":"Retail Goods"
        },
        {
            "category":"Manufacturing",
            "subcategory":"Metals",
            "type":"Manufacturing & Wholesale Goods"
        },
        {
            "category":"Manufacturing",
            "subcategory":"Glass & Minerals",
            "type":"Manufacturing & Wholesale Goods"
        }
    ],
    "sg:phone":"+1 520 293 4550",
    "sg:postcode":"85705",
    "sg:province":"AZ",
    "sg:tags":[
        "decor",
        "perfume",
        "crystal",
        "house",
        "bedding",
        "men's",
        "silverware",
        "glassware",
        "linen",
        "lingerie",
        "china",
        "apparel",
        "accessory",
        "handbag",
        "girls'",
        "women's",
        "clothing",
        "boys'"
    ],
    "sg:website":"http://www.dillards.com",
    "wof:name":"Dillard's",
    "wof:placetype":"venue"
},
  "geometry": {"coordinates":[-110.97814700000001,32.289479],"type":"Point"}
}