{
  "type": "Feature",
  "properties": {
    "iso:country":"US",
    "sg:address":"8960 W Bell Rd",
    "sg:city":"Peoria",
    "sg:classifiers":[
        {
            "category":"Personal",
            "subcategory":"Beauty Salon",
            "type":"Services"
        }
    ],
    "sg:phone":"+1 623 933 7040",
    "sg:postcode":"85382",
    "sg:province":"AZ",
    "wof:name":"Aveda/Salon Rituals",
    "wof:placetype":"venue"
},
  "geometry": {"coordinates":[-112.251729,33.638192],"type":"Point"}
}