{
  "type": "Feature",
  "properties": {
    "addr:full":"131 E Boca Raton Rd Phoenix AZ 85022",
    "addr:housenumber":"131",
    "addr:postcode":"85022",
    "addr:street":"E Boca Raton Rd",
    "iso:country":"US",
    "sg:address":"131 E Boca Raton Rd",
    "sg:city":"Phoenix",
    "sg:classifiers":[
        {
            "category":"Manufacturing",
            "subcategory":"Chemicals & Compounds",
            "type":"Manufacturing & Wholesale Goods"
        }
    ],
    "sg:phone":"+1 602 789 6381",
    "sg:postcode":"85022",
    "sg:province":"AZ",
    "sg:tags":[
        "mfg",
        "plastic"
    ],
    "wof:name":"K&M Products",
    "wof:placetype":"venue"
},
  "geometry": {"coordinates":[-112.07419899999999,33.611891],"type":"Point"}
}