{
  "type": "Feature",
  "properties": {
    "addr:full":"11023 Santa Columbia Dr Goodyear AZ 85338",
    "addr:housenumber":"11023",
    "addr:postcode":"85338",
    "addr:street":"Santa Columbia Dr",
    "iso:country":"US",
    "sg:address":"11023 Santa Columbia Dr",
    "sg:city":"Goodyear",
    "sg:classifiers":[
        {
            "category":"Retail",
            "subcategory":"Laundry & Dry Cleaning",
            "type":"Services"
        }
    ],
    "sg:phone":"+1 623 691 9550",
    "sg:postcode":"85338",
    "sg:province":"AZ",
    "sg:tags":[
        "cleaner",
        "rug",
        "carpet"
    ],
    "wof:name":"Desert Steemers Carpet Clrs",
    "wof:placetype":"venue"
},
  "geometry": {"coordinates":[-112.44675100000001,33.346142],"type":"Point"}
}