{
  "type": "Feature",
  "properties": {
    "iso:country":"US",
    "sg:address":"450 N Western Ave",
    "sg:city":"Nogales",
    "sg:classifiers":[
        {
            "category":"Autos & Motor Vehicles",
            "subcategory":"Automobile Sales",
            "type":"Retail Goods"
        }
    ],
    "sg:phone":"+1 520 287 4470",
    "sg:postcode":"85621",
    "sg:province":"AZ",
    "sg:tags":[
        "wrecker"
    ],
    "wof:name":"Hollers Auto Salvage-Used Cars",
    "wof:placetype":"venue"
},
  "geometry": {"coordinates":[-110.953041,31.34135],"type":"Point"}
}