{
  "type": "Feature",
  "properties": {
    "addr:full":"19614 W Dunlap Rd Buckeye AZ 85326",
    "addr:housenumber":"19614",
    "addr:postcode":"85326",
    "addr:street":"W Dunlap Rd",
    "iso:country":"US",
    "sg:address":"19614 W Dunlap Rd",
    "sg:city":"Buckeye",
    "sg:classifiers":[
        {
            "category":"Farming",
            "subcategory":"Livestock Farm",
            "type":"Manufacturing & Wholesale Goods"
        }
    ],
    "sg:phone":"+1 623 386 8717",
    "sg:postcode":"85326",
    "sg:province":"AZ",
    "sg:tags":[
        "boarding",
        "training",
        "horse",
        "breeding",
        "sales"
    ],
    "wof:name":"Cross A7 Ranch",
    "wof:placetype":"venue"
},
  "geometry": {"coordinates":[-112.48222199999999,33.413941],"type":"Point"}
}