{
  "type": "Feature",
  "properties": {
    "iso:country":"US",
    "sg:address":"453 S Main Ave",
    "sg:city":"Tucson",
    "sg:classifiers":[
        {
            "category":"Professional",
            "subcategory":"Lawyer & Legal Services",
            "type":"Services"
        }
    ],
    "sg:phone":"+1 520 628 7800",
    "sg:postcode":"85701",
    "sg:province":"AZ",
    "sg:tags":[
        "attorney"
    ],
    "wof:name":"John L Leiber Law Office",
    "wof:placetype":"venue"
},
  "geometry": {"coordinates":[-110.97425,32.215255],"type":"Point"}
}