{
  "type": "Feature",
  "properties": {
    "iso:country":"US",
    "sg:address":"12611 N Tatum Blvd",
    "sg:city":"Phoenix",
    "sg:classifiers":[
        {
            "category":"Shopping",
            "subcategory":"Computers & Home Electronics",
            "type":"Retail Goods"
        }
    ],
    "sg:phone":"+1 602 788 2032",
    "sg:postcode":"85032",
    "sg:province":"AZ",
    "sg:tags":[
        "game",
        "video"
    ],
    "wof:name":"Gamestop",
    "wof:placetype":"venue"
},
  "geometry": {"coordinates":[-111.97849100000001,33.602789],"type":"Point"}
}