{
  "type": "Feature",
  "properties": {
    "addr:full":"2915 E Baseline Rd Ste 101 Gilbert AZ 85234",
    "addr:housenumber":"2915",
    "addr:postcode":"85234",
    "addr:street":"E Baseline Rd Ste 101",
    "iso:country":"US",
    "sg:address":"2915 E Baseline Rd Ste 101",
    "sg:city":"Gilbert",
    "sg:classifiers":[
        {
            "category":"Health Services",
            "subcategory":"Doctor",
            "type":"Services"
        }
    ],
    "sg:phone":"+1 480 776 0622",
    "sg:postcode":"85234",
    "sg:province":"AZ",
    "wof:name":"Leavitt Sandra L",
    "wof:placetype":"venue"
},
  "geometry": {"coordinates":[-111.76822,33.378954],"type":"Point"}
}