{
  "type": "Feature",
  "properties": {
    "iso:country":"US",
    "sg:address":"8010 S 48th Dr",
    "sg:city":"Laveen",
    "sg:classifiers":[
        {
            "category":"Professional",
            "type":"Services"
        }
    ],
    "sg:phone":"+1 402 217 5055",
    "sg:postcode":"85339",
    "sg:province":"AZ",
    "sg:tags":[
        "transportation"
    ],
    "wof:name":"Superior Refrigerated Transport",
    "wof:placetype":"venue"
},
  "geometry": {"coordinates":[-112.163072,33.373421],"type":"Point"}
}