{
  "type": "Feature",
  "properties": {
    "iso:country":"US",
    "sg:address":"460 S Benson Ln Ste 3",
    "sg:city":"Chandler",
    "sg:classifiers":[
        {
            "category":"Communications",
            "type":"Services"
        }
    ],
    "sg:phone":"+1 480 897 0551",
    "sg:postcode":"85224",
    "sg:province":"AZ",
    "sg:tags":[
        "data"
    ],
    "wof:name":"Covalence, Inc.",
    "wof:placetype":"venue"
},
  "geometry": {"coordinates":[-111.887957,33.2962],"type":"Point"}
}