{
  "type": "Feature",
  "properties": {
    "iso:country":"US",
    "sg:address":"2525 E Camelback Rd",
    "sg:city":"Phoenix",
    "sg:classifiers":[
        {
            "category":"Professional",
            "subcategory":"Accounting & Tax Preparation",
            "type":"Services"
        }
    ],
    "sg:phone":"+1 602 808 0909",
    "sg:postcode":"85016",
    "sg:province":"AZ",
    "sg:tags":[
        "accountant"
    ],
    "wof:name":"Fitzpatrick Hopkins Kelly",
    "wof:placetype":"venue"
},
  "geometry": {"coordinates":[-112.028715,33.509286],"type":"Point"}
}