{
  "type": "Feature",
  "properties": {
    "addr:full":"1124 S 35th Ave Phoenix AZ 85009",
    "addr:housenumber":"1124",
    "addr:postcode":"85009",
    "addr:street":"S 35Th Ave",
    "iso:country":"US",
    "sg:address":"1124 S 35th Ave",
    "sg:city":"Phoenix",
    "sg:classifiers":[
        {
            "category":"Autos & Motor Vehicles",
            "subcategory":"Automobile Sales",
            "type":"Retail Goods"
        }
    ],
    "sg:phone":"+1 602 455 9709",
    "sg:postcode":"85009",
    "sg:province":"AZ",
    "sg:tags":[
        "car",
        "used"
    ],
    "wof:name":"Hinojos Auto Sales",
    "wof:placetype":"venue"
},
  "geometry": {"coordinates":[-112.134613,33.437801],"type":"Point"}
}