{
  "type": "Feature",
  "properties": {
    "addr:full":"5525 E Michelle Dr Scottsdale AZ 85254",
    "addr:housenumber":"5525",
    "addr:postcode":"85254",
    "addr:street":"E Michelle Dr",
    "iso:country":"US",
    "sg:address":"5525 E Michelle Dr",
    "sg:city":"Scottsdale",
    "sg:classifiers":[
        {
            "category":"Real Estate",
            "subcategory":"Real Estate Agent",
            "type":"Services"
        }
    ],
    "sg:phone":"+1 602 482 7500",
    "sg:postcode":"85254",
    "sg:province":"AZ",
    "sg:website":"www.sstproperties.com",
    "wof:name":"SST Properties",
    "wof:placetype":"venue"
},
  "geometry": {"coordinates":[-111.961832,33.649959],"type":"Point"}
}