{
  "type": "Feature",
  "properties": {
    "addr:full":"5436 W Latham St Phoenix AZ 85043",
    "addr:housenumber":"5436",
    "addr:postcode":"85043",
    "addr:street":"W Latham St",
    "iso:country":"US",
    "sg:address":"5436 W Latham St",
    "sg:city":"Phoenix",
    "sg:classifiers":[
        {
            "category":"Manufacturing",
            "subcategory":"Printing",
            "type":"Manufacturing & Wholesale Goods"
        }
    ],
    "sg:phone":"+1 602 254 0130",
    "sg:postcode":"85043",
    "sg:province":"AZ",
    "sg:tags":[
        "printer",
        "offset",
        "trade"
    ],
    "wof:name":"Action Envelope",
    "wof:placetype":"venue"
},
  "geometry": {"coordinates":[-112.17659,33.460625],"type":"Point"}
}