{
  "type": "Feature",
  "properties": {
    "iso:country":"US",
    "sg:address":"201 S 3rd Ave",
    "sg:city":"Yuma",
    "sg:classifiers":[
        {
            "category":"Government",
            "subcategory":"Office",
            "type":"Public Place"
        }
    ],
    "sg:phone":"+1 928 783 8859",
    "sg:postcode":"85364",
    "sg:province":"AZ",
    "sg:tags":[
        "executive"
    ],
    "wof:name":"Arizona State Government",
    "wof:placetype":"venue"
},
  "geometry": {"coordinates":[-114.623369,32.72307],"type":"Point"}
}