{
  "type": "Feature",
  "properties": {
    "addr:full":"2409 S 8th Ave Yuma AZ 85364",
    "addr:housenumber":"2409",
    "addr:postcode":"85364",
    "addr:street":"S 8Th Ave",
    "iso:country":"US",
    "sg:address":"2409 S 8th Ave",
    "sg:city":"Yuma",
    "sg:classifiers":[
        {
            "category":"Food & Beverages",
            "subcategory":"Groceries & Convenience Stores",
            "type":"Retail Goods"
        }
    ],
    "sg:phone":"+1 928 344 1613",
    "sg:postcode":"85364",
    "sg:province":"AZ",
    "sg:tags":[
        "station",
        "gasoline"
    ],
    "wof:name":"Circle K",
    "wof:placetype":"venue"
},
  "geometry": {"coordinates":[-114.628855,32.683106],"type":"Point"}
}