{
  "type": "Feature",
  "properties": {
    "iso:country":"US",
    "sg:address":"8281 N Firethorn Ave",
    "sg:city":"Tucson",
    "sg:classifiers":[
        {
            "category":"Insurance",
            "subcategory":"Insurance Agent",
            "type":"Services"
        }
    ],
    "sg:phone":"+1 520 744 2034",
    "sg:postcode":"85741",
    "sg:province":"AZ",
    "wof:name":"James Buckel Ins & Inv LLC",
    "wof:placetype":"venue"
},
  "geometry": {"coordinates":[-111.051687,32.356373],"type":"Point"}
}