{
  "type": "Feature",
  "properties": {
    "iso:country":"US",
    "sg:address":"4616 N 51st Ave",
    "sg:city":"Phoenix",
    "sg:classifiers":[
        {
            "category":"Health Services",
            "subcategory":"Doctor",
            "type":"Services"
        }
    ],
    "sg:phone":"+1 623 245 3250",
    "sg:postcode":"85031",
    "sg:province":"AZ",
    "sg:tags":[
        "clinic"
    ],
    "wof:name":"Bendel Clinic West",
    "wof:placetype":"venue"
},
  "geometry": {"coordinates":[-112.168873,33.504286],"type":"Point"}
}