{
  "type": "Feature",
  "properties": {
    "iso:country":"US",
    "sg:address":"20832 N 5th Dr",
    "sg:city":"Phoenix",
    "sg:classifiers":[
        {
            "category":"Building & Trades",
            "subcategory":"Construction",
            "type":"Services"
        }
    ],
    "sg:phone":"+1 623 780 9246",
    "sg:postcode":"85027",
    "sg:province":"AZ",
    "sg:tags":[
        "floor",
        "laying",
        "contractor"
    ],
    "wof:name":"Strictly Wood Floors",
    "wof:placetype":"venue"
},
  "geometry": {"coordinates":[-112.081414,33.675885],"type":"Point"}
}