{
  "type": "Feature",
  "properties": {
    "addr:full":"3101 W Topeka Dr Phoenix AZ 85027",
    "addr:housenumber":"3101",
    "addr:postcode":"85027",
    "addr:street":"W Topeka Dr",
    "iso:country":"US",
    "sg:address":"3101 W Topeka Dr",
    "sg:city":"Phoenix",
    "sg:classifiers":[
        {
            "category":"Home & Garden",
            "subcategory":"Building Materials",
            "type":"Retail Goods"
        }
    ],
    "sg:phone":"+1 602 524 5724",
    "sg:postcode":"85027",
    "sg:province":"AZ",
    "wof:name":"Solarfarms Inc",
    "wof:placetype":"venue"
},
  "geometry": {"coordinates":[-112.12586,33.659996],"type":"Point"}
}