{
  "type": "Feature",
  "properties": {
    "iso:country":"US",
    "sg:address":"2532 N 49th St Apt 1",
    "sg:city":"Phoenix",
    "sg:classifiers":[
        {
            "category":"Professional",
            "subcategory":"Computer Services",
            "type":"Services"
        }
    ],
    "sg:phone":"+1 602 989 3687",
    "sg:postcode":"85008",
    "sg:province":"AZ",
    "sg:tags":[
        "technical",
        "assistance",
        "support"
    ],
    "wof:name":"P&D Computer Solutions",
    "wof:placetype":"venue"
},
  "geometry": {"coordinates":[-111.975988,33.475494],"type":"Point"}
}