{
  "type": "Feature",
  "properties": {
    "iso:country":"US",
    "sg:address":"1133 N Arroya",
    "sg:city":"Mesa",
    "sg:classifiers":[
        {
            "category":"Food & Beverages",
            "subcategory":"Groceries & Convenience Stores",
            "type":"Retail Goods"
        }
    ],
    "sg:phone":"+1 480 832 2864",
    "sg:postcode":"85205",
    "sg:province":"AZ",
    "wof:name":"J P Brady LLC",
    "wof:placetype":"venue"
},
  "geometry": {"coordinates":[-111.711721,33.436625],"type":"Point"}
}