{
  "type": "Feature",
  "properties": {
    "iso:country":"US",
    "sg:address":"1800 S Milton Rd",
    "sg:city":"Flagstaff",
    "sg:classifiers":[
        {
            "category":"Personal",
            "subcategory":"Beauty Salon",
            "type":"Services"
        }
    ],
    "sg:phone":"+1 928 556 0882",
    "sg:postcode":"86001",
    "sg:province":"AZ",
    "wof:name":"Great Clips",
    "wof:placetype":"venue"
},
  "geometry": {"coordinates":[-111.661422,35.18335],"type":"Point"}
}