{
  "type": "Feature",
  "properties": {
    "iso:country":"US",
    "sg:address":"2051 S Dobson Road",
    "sg:city":"Mesa",
    "sg:classifiers":[
        {
            "category":"Personal",
            "subcategory":"Barber",
            "type":"Services"
        }
    ],
    "sg:phone":"+1 480 345 2407",
    "sg:postcode":"85202",
    "sg:province":"AZ",
    "sg:website":"www.costcutters.com",
    "wof:name":"Cost Cutters Family Hair Care",
    "wof:placetype":"venue"
},
  "geometry": {"coordinates":[-111.87782300000001,33.377488],"type":"Point"}
}