{
  "type": "Feature",
  "properties": {
    "iso:country":"US",
    "sg:address":"8601 N Black Canyon Hwy",
    "sg:city":"Phoenix",
    "sg:classifiers":[
        {
            "category":"Health Services",
            "subcategory":"Health Practitioner",
            "type":"Services"
        }
    ],
    "sg:phone":"+1 602 864 7662",
    "sg:postcode":"85021",
    "sg:province":"AZ",
    "sg:tags":[
        "psychotherapist"
    ],
    "wof:name":"Center-Extraordinary Outcomes",
    "wof:placetype":"venue"
},
  "geometry": {"coordinates":[-112.116201,33.563933],"type":"Point"}
}