{
  "type": "Feature",
  "properties": {
    "addr:full":"3202 E Grant Rd Tucson AZ 85716",
    "addr:housenumber":"3202",
    "addr:postcode":"85716",
    "addr:street":"E Grant Rd",
    "iso:country":"US",
    "sg:address":"3202 E Grant Rd",
    "sg:city":"Tucson",
    "sg:classifiers":[
        {
            "category":"Organizations",
            "subcategory":"Community Association",
            "type":"Services"
        }
    ],
    "sg:phone":"+1 520 321 9488",
    "sg:postcode":"85716",
    "sg:province":"AZ",
    "sg:tags":[
        "environmental",
        "org"
    ],
    "wof:name":"Sonora Environmental Research",
    "wof:placetype":"venue"
},
  "geometry": {"coordinates":[-110.92259799999999,32.250359],"type":"Point"}
}