{
  "type": "Feature",
  "properties": {
    "iso:country":"US",
    "sg:address":"10255 N 32nd St",
    "sg:city":"Phoenix",
    "sg:classifiers":[
        {
            "category":"Government",
            "subcategory":"Office",
            "type":"Public Place"
        }
    ],
    "sg:phone":"+1 602 494 0620",
    "sg:postcode":"85028",
    "sg:province":"AZ",
    "wof:name":"Honorable Jacqueline B Mc Vay",
    "wof:placetype":"venue"
},
  "geometry": {"coordinates":[-112.012984,33.580718],"type":"Point"}
}