{
  "type": "Feature",
  "properties": {
    "iso:country":"US",
    "sg:address":"1751 S Thompson St",
    "sg:city":"Flagstaff",
    "sg:classifiers":[
        {
            "category":"Manufacturing",
            "subcategory":"Printing",
            "type":"Manufacturing & Wholesale Goods"
        }
    ],
    "sg:phone":"+1 928 774 4545",
    "sg:postcode":"86001",
    "sg:province":"AZ",
    "sg:tags":[
        "newspaper"
    ],
    "sg:website":"www.azdailysun.com",
    "wof:name":"Arizona Daily Sun",
    "wof:placetype":"venue"
},
  "geometry": {"coordinates":[-111.67478,35.187423],"type":"Point"}
}