{
  "type": "Feature",
  "properties": {
    "iso:country":"US",
    "sg:address":"4514 E Broadway Blvd",
    "sg:city":"Tucson",
    "sg:classifiers":[
        {
            "category":"Professional",
            "subcategory":"Printing & Photocopies",
            "type":"Services"
        }
    ],
    "sg:phone":"+1 520 886 5227",
    "sg:postcode":"85711",
    "sg:province":"AZ",
    "sg:tags":[
        "duplicating",
        "copying"
    ],
    "wof:name":"Reproductions Inc",
    "wof:placetype":"venue"
},
  "geometry": {"coordinates":[-110.89466,32.221434],"type":"Point"}
}