{
  "type": "Feature",
  "properties": {
    "addr:full":"2810 N 71st Dr Phoenix AZ 85035",
    "addr:housenumber":"2810",
    "addr:postcode":"85035",
    "addr:street":"N 71St Dr",
    "iso:country":"US",
    "sg:address":"2810 N 71st Dr",
    "sg:city":"Phoenix",
    "sg:classifiers":[
        {
            "category":"Building & Trades",
            "subcategory":"Construction",
            "type":"Services"
        }
    ],
    "sg:phone":"+1 623 849 6324",
    "sg:postcode":"85035",
    "sg:province":"AZ",
    "sg:tags":[
        "house"
    ],
    "wof:name":"Townsend Rmdlg & Hm Imprvs",
    "wof:placetype":"venue"
},
  "geometry": {"coordinates":[-112.212587,33.478908],"type":"Point"}
}