{
  "type": "Feature",
  "properties": {
    "iso:country":"US",
    "sg:address":"15802 N Nicklaus Ln",
    "sg:city":"Sun City",
    "sg:classifiers":[
        {
            "category":"Autos & Motor Vehicles",
            "subcategory":"Fuel & Gas Station",
            "type":"Retail Goods"
        }
    ],
    "sg:phone":"+1 623 972 4289",
    "sg:postcode":"85351",
    "sg:province":"AZ",
    "sg:tags":[
        "grocery",
        "station",
        "gasoline",
        "rep",
        "general"
    ],
    "wof:name":"Premier Auto & Truck Repair",
    "wof:placetype":"venue"
},
  "geometry": {"coordinates":[-112.257296,33.62961],"type":"Point"}
}