{
  "type": "Feature",
  "properties": {
    "iso:country":"US",
    "sg:address":"433 W Gary Dr",
    "sg:city":"Chandler",
    "sg:classifiers":[
        {
            "category":"Shopping",
            "subcategory":"Discount & Variety Stores",
            "type":"Retail Goods"
        }
    ],
    "sg:phone":"+1 480 325 7576",
    "sg:postcode":"85225",
    "sg:province":"AZ",
    "sg:tags":[
        "merchandise",
        "general"
    ],
    "wof:name":"T K Sourcing Triple W Sales",
    "wof:placetype":"venue"
},
  "geometry": {"coordinates":[-111.847804,33.321747],"type":"Point"}
}