{
  "type": "Feature",
  "properties": {
    "iso:country":"US",
    "sg:address":"214 Henderson St",
    "sg:city":"Winslow",
    "sg:classifiers":[
        {
            "category":"Insurance",
            "subcategory":"Hazard Insurance",
            "type":"Services"
        }
    ],
    "sg:phone":"+1 928 289 5739",
    "sg:postcode":"86047",
    "sg:province":"AZ",
    "sg:tags":[
        "commercial",
        "business"
    ],
    "wof:name":"Shirley Light Insurance Res",
    "wof:placetype":"venue"
},
  "geometry": {"coordinates":[-110.694676,35.035332],"type":"Point"}
}