{
  "type": "Feature",
  "properties": {
    "iso:country":"US",
    "sg:address":"7040 W Olive Ave",
    "sg:city":"Peoria",
    "sg:classifiers":[
        {
            "category":"Retail",
            "subcategory":"Auto Repair",
            "type":"Services"
        }
    ],
    "sg:phone":"+1 602 938 4248",
    "sg:postcode":"85345",
    "sg:province":"AZ",
    "sg:tags":[
        "glass",
        "coating",
        "tinting"
    ],
    "wof:name":"Jim's Window Tinting",
    "wof:placetype":"venue"
},
  "geometry": {"coordinates":[-112.211119,33.56712],"type":"Point"}
}