{
  "type": "Feature",
  "properties": {
    "iso:country":"US",
    "sg:address":"503 E Z St",
    "sg:city":"Prescott",
    "sg:classifiers":[
        {
            "category":"Building & Trades",
            "subcategory":"Construction",
            "type":"Services"
        }
    ],
    "sg:phone":"+1 928 445 9383",
    "sg:postcode":"86301",
    "sg:province":"AZ",
    "sg:tags":[
        "excavating",
        "contractor"
    ],
    "wof:name":"Mcmains & Sons Excavation",
    "wof:placetype":"venue"
},
  "geometry": {"coordinates":[-112.464382,34.548705],"type":"Point"}
}