{
  "type": "Feature",
  "properties": {
    "iso:country":"US",
    "sg:address":"9500 E Ironwood Square Dr",
    "sg:city":"Scottsdale",
    "sg:classifiers":[
        {
            "category":"Real Estate",
            "subcategory":"Real Estate Services",
            "type":"Services"
        }
    ],
    "sg:phone":"+1 480 585 5888",
    "sg:postcode":"85258",
    "sg:province":"AZ",
    "sg:tags":[
        "company",
        "title"
    ],
    "wof:name":"Omega Title",
    "wof:placetype":"venue"
},
  "geometry": {"coordinates":[-111.874002,33.576833],"type":"Point"}
}