{
  "type": "Feature",
  "properties": {
    "iso:country":"US",
    "sg:address":"1250 E Hale St",
    "sg:city":"Mesa",
    "sg:classifiers":[
        {
            "category":"Professional",
            "subcategory":"Computer Services",
            "type":"Services"
        }
    ],
    "sg:phone":"+1 480 962 9101",
    "sg:postcode":"85203",
    "sg:province":"AZ",
    "sg:tags":[
        "consultant",
        "designer",
        "datum",
        "system"
    ],
    "wof:name":"RLF & Assoc",
    "wof:placetype":"venue"
},
  "geometry": {"coordinates":[-111.803652,33.443556],"type":"Point"}
}