{
  "type": "Feature",
  "properties": {
    "iso:country":"US",
    "sg:address":"2343 E Broadway Blvd",
    "sg:city":"Tucson",
    "sg:classifiers":[
        {
            "category":"Insurance",
            "subcategory":"Insurance Agent",
            "type":"Services"
        }
    ],
    "sg:phone":"+1 520 624 7959",
    "sg:postcode":"85719",
    "sg:province":"AZ",
    "wof:name":"American Family Insurance",
    "wof:placetype":"venue"
},
  "geometry": {"coordinates":[-110.938424,32.221544],"type":"Point"}
}