{
  "type": "Feature",
  "properties": {
    "iso:country":"US",
    "sg:address":"5620 W Thunderbird Rd",
    "sg:city":"Glendale",
    "sg:classifiers":[
        {
            "category":"Health Services",
            "subcategory":"Health Practitioner",
            "type":"Services"
        }
    ],
    "sg:phone":"+1 602 938 2422",
    "sg:postcode":"85306",
    "sg:province":"AZ",
    "sg:tags":[
        "therapist",
        "physical"
    ],
    "wof:name":"Hand & Orthopaedic Rehab Assoc",
    "wof:placetype":"venue"
},
  "geometry": {"coordinates":[-112.182922,33.610829],"type":"Point"}
}