{
  "type": "Feature",
  "properties": {
    "iso:country":"US",
    "sg:address":"3810 E Tanglewood Dr",
    "sg:city":"Phoenix",
    "sg:classifiers":[
        {
            "category":"Professional",
            "type":"Services"
        }
    ],
    "sg:phone":"+1 480 759 6600",
    "sg:postcode":"85048",
    "sg:province":"AZ",
    "sg:tags":[
        "establishment"
    ],
    "wof:name":"CWI",
    "wof:placetype":"venue"
},
  "geometry": {"coordinates":[-112.003044,33.29891],"type":"Point"}
}