{
  "type": "Feature",
  "properties": {
    "iso:country":"US",
    "sg:address":"2669 E Jasper Dr",
    "sg:city":"Gilbert",
    "sg:classifiers":[
        {
            "category":"Professional",
            "type":"Services"
        }
    ],
    "sg:phone":"+1 480 497 0047",
    "sg:postcode":"85296",
    "sg:province":"AZ",
    "wof:name":"Rebecca Lagman",
    "wof:placetype":"venue"
},
  "geometry": {"coordinates":[-111.730237,33.328572],"type":"Point"}
}