{
  "type": "Feature",
  "properties": {
    "iso:country":"US",
    "sg:address":"9180 E Indian Bend Rd",
    "sg:city":"Scottsdale",
    "sg:classifiers":[
        {
            "category":"Shopping",
            "subcategory":"Shoes",
            "type":"Retail Goods"
        }
    ],
    "sg:phone":"+1 480 443 8091",
    "sg:postcode":"85253",
    "sg:province":"AZ",
    "wof:name":"S A S Shoes",
    "wof:placetype":"venue"
},
  "geometry": {"coordinates":[-111.879899,33.538516],"type":"Point"}
}