{
  "type": "Feature",
  "properties": {
    "addr:full":"2161 Liough Dr Clarkdale AZ 86324",
    "addr:housenumber":"2161",
    "addr:postcode":"86324",
    "addr:street":"Liough Dr",
    "iso:country":"US",
    "sg:address":"2161 Liough Dr",
    "sg:city":"Clarkdale",
    "sg:classifiers":[
        {
            "category":"Building & Trades",
            "subcategory":"Construction",
            "type":"Services"
        }
    ],
    "sg:phone":"+1 928 634 5681",
    "sg:postcode":"86324",
    "sg:province":"AZ",
    "sg:tags":[
        "house"
    ],
    "wof:name":"Dd Padgett Construction",
    "wof:placetype":"venue"
},
  "geometry": {"coordinates":[-112.04517,34.741716],"type":"Point"}
}