{
  "type": "Feature",
  "properties": {
    "addr:full":"5000 S Arizona Mills Cir Tempe AZ 85282",
    "addr:housenumber":"5000",
    "addr:postcode":"85282",
    "addr:street":"S Arizona Mills Cir",
    "iso:country":"US",
    "sg:address":"5000 S Arizona Mills Cir",
    "sg:city":"Tempe",
    "sg:classifiers":[
        {
            "category":"Restaurant",
            "type":"Food & Drink"
        }
    ],
    "sg:menulink":"http://www.allmenus.com/az/phoenix/129046-subway/menu/",
    "sg:phone":"+1 480 775 6211",
    "sg:postcode":"85282",
    "sg:province":"AZ",
    "sg:tags":[
        "american",
        "sandwich"
    ],
    "wof:name":"Subway",
    "wof:placetype":"venue"
},
  "geometry": {"coordinates":[-111.965053,33.379419],"type":"Point"}
}