{
  "type": "Feature",
  "properties": {
    "addr:full":"7000 N Resort Dr Tucson AZ 85750",
    "addr:housenumber":"7000",
    "addr:postcode":"85750",
    "addr:street":"N Resort Dr",
    "iso:country":"US",
    "sg:address":"7000 N Resort Dr",
    "sg:city":"Tucson",
    "sg:classifiers":[
        {
            "category":"Restaurant",
            "type":"Food & Drink"
        }
    ],
    "sg:menulink":"http://www.allmenus.com/az/tucson/268316-the-flying-v/menu/",
    "sg:phone":"+1 520 615 5495",
    "sg:postcode":"85750",
    "sg:province":"AZ",
    "wof:name":"The Flying V",
    "wof:placetype":"venue"
},
  "geometry": {"coordinates":[-110.850745,32.329848],"type":"Point"}
}