{
  "type": "Feature",
  "properties": {
    "iso:country":"US",
    "sg:address":"7001 E Cave Creek Rd",
    "sg:city":"Cave Creek",
    "sg:classifiers":[
        {
            "category":"Wholesale",
            "subcategory":"Construction Materials",
            "type":"Manufacturing & Wholesale Goods"
        }
    ],
    "sg:phone":"+1 480 488 9003",
    "sg:postcode":"85331",
    "sg:province":"AZ",
    "sg:tags":[
        "sand",
        "gravel"
    ],
    "wof:name":"Foothills Granite Supply",
    "wof:placetype":"venue"
},
  "geometry": {"coordinates":[-111.931371,33.82984],"type":"Point"}
}