{
  "type": "Feature",
  "properties": {
    "iso:country":"US",
    "sg:address":"3545 W Dunlap Ave",
    "sg:city":"Phoenix",
    "sg:classifiers":[
        {
            "category":"Personal",
            "subcategory":"Beauty Salon",
            "type":"Services"
        }
    ],
    "sg:phone":"+1 602 242 4260",
    "sg:postcode":"85051",
    "sg:province":"AZ",
    "wof:name":"Expression Barber & Beauty Sln",
    "wof:placetype":"venue"
},
  "geometry": {"coordinates":[-112.13788,33.567451],"type":"Point"}
}