{
  "type": "Feature",
  "properties": {
    "iso:country":"US",
    "sg:address":"44 W Buffalo St",
    "sg:city":"Chandler",
    "sg:classifiers":[
        {
            "category":"Retail",
            "subcategory":"Repair Shop",
            "type":"Services"
        }
    ],
    "sg:phone":"+1 480 963 5222",
    "sg:postcode":"85225",
    "sg:province":"AZ",
    "sg:tags":[
        "us"
    ],
    "wof:name":"Radebaugh Radio & Television",
    "wof:placetype":"venue"
},
  "geometry": {"coordinates":[-111.84154700000001,33.304695],"type":"Point"}
}