{
  "type": "Feature",
  "properties": {
    "addr:full":"3418 S 48th St Ste 3 Phoenix AZ 85040",
    "addr:housenumber":"3418",
    "addr:postcode":"85040",
    "addr:street":"S 48Th St Ste 3",
    "iso:country":"US",
    "sg:address":"3418 S 48th St Ste 3",
    "sg:city":"Phoenix",
    "sg:classifiers":[
        {
            "category":"Professional",
            "subcategory":"Engineering",
            "type":"Services"
        }
    ],
    "sg:phone":"+1 480 921 4128",
    "sg:postcode":"85040",
    "sg:province":"AZ",
    "sg:tags":[
        "aeronautical",
        "engineer"
    ],
    "sg:website":"http://www.m-dot.com",
    "wof:name":"M-Dot Aerospace",
    "wof:placetype":"venue"
},
  "geometry": {"coordinates":[-111.97912100000001,33.419073],"type":"Point"}
}