{
  "type": "Feature",
  "properties": {
    "addr:full":"29737 W Roosevelt St Buckeye AZ 85396",
    "addr:housenumber":"29737",
    "addr:postcode":"85396",
    "addr:street":"W Roosevelt St",
    "iso:country":"US",
    "sg:address":"29737 W Roosevelt St",
    "sg:city":"Buckeye",
    "sg:classifiers":[
        {
            "category":"Building & Trades",
            "subcategory":"Electrical",
            "type":"Services"
        }
    ],
    "sg:phone":"+1 623 393 8194",
    "sg:postcode":"85396",
    "sg:province":"AZ",
    "sg:tags":[
        "electrical",
        "contractor"
    ],
    "wof:name":"Wm Automation & Cntrls Inc",
    "wof:placetype":"venue"
},
  "geometry": {"coordinates":[-112.694299,33.457315],"type":"Point"}
}