{
  "type": "Feature",
  "properties": {
    "iso:country":"US",
    "sg:address":"6200 E Thomas Rd Ste 203",
    "sg:city":"Scottsdale",
    "sg:classifiers":[
        {
            "category":"Professional",
            "subcategory":"Computer Services",
            "type":"Services"
        }
    ],
    "sg:phone":"+1 480 361 9983",
    "sg:postcode":"85251",
    "sg:province":"AZ",
    "sg:tags":[
        "designer",
        "technical",
        "consultant",
        "assistance",
        "system",
        "support"
    ],
    "wof:name":"Open Source Six Sigma",
    "wof:placetype":"venue"
},
  "geometry": {"coordinates":[-111.948952,33.48016],"type":"Point"}
}