{
  "type": "Feature",
  "properties": {
    "addr:full":"8366 W Thunderbird Rd Peoria AZ 85381",
    "addr:housenumber":"8366",
    "addr:postcode":"85381",
    "addr:street":"W Thunderbird Rd",
    "iso:country":"US",
    "sg:address":"8366 W Thunderbird Rd",
    "sg:city":"Peoria",
    "sg:classifiers":[
        {
            "category":"Banks & Credit Unions",
            "subcategory":"Bank",
            "type":"Services"
        }
    ],
    "sg:phone":"+1 623 878 2630",
    "sg:postcode":"85381",
    "sg:province":"AZ",
    "wof:name":"Chase Bank",
    "wof:placetype":"venue"
},
  "geometry": {"coordinates":[-112.240825,33.610011],"type":"Point"}
}