{
  "type": "Feature",
  "properties": {
    "addr:full":"18444 N 42nd St Phoenix AZ 85032",
    "addr:housenumber":"18444",
    "addr:postcode":"85032",
    "addr:street":"N 42Nd St",
    "iso:country":"US",
    "sg:address":"18444 N 42nd St",
    "sg:city":"Phoenix",
    "sg:classifiers":[
        {
            "category":"Place Of Worship",
            "subcategory":"Church",
            "type":"Public Place"
        },
        {
            "category":"Place Of Worship",
            "type":"Public Place"
        }
    ],
    "sg:phone":"+1 602 992 5850",
    "sg:postcode":"85032",
    "sg:province":"AZ",
    "sg:tags":[
        "churches-baptist-general",
        "churches-baptist"
    ],
    "wof:name":"Signs Of Life Baptist Church",
    "wof:placetype":"venue"
},
  "geometry": {"coordinates":[-111.99164500000001,33.654206],"type":"Point"}
}