{
  "type": "Feature",
  "properties": {
    "iso:country":"US",
    "sg:address":"2401 W Southern Ave",
    "sg:city":"Tempe",
    "sg:classifiers":[
        {
            "category":"Insurance",
            "subcategory":"Insurance Agent",
            "type":"Services"
        }
    ],
    "sg:phone":"+1 602 426 1630",
    "sg:postcode":"85282",
    "sg:province":"AZ",
    "sg:tags":[
        "processing"
    ],
    "wof:name":"M H Claims Svc Inc",
    "wof:placetype":"venue"
},
  "geometry": {"coordinates":[-111.974575,33.392773],"type":"Point"}
}