{
  "type": "Feature",
  "properties": {
    "iso:country":"US",
    "sg:address":"915 W Beale St",
    "sg:city":"Kingman",
    "sg:classifiers":[
        {
            "category":"Autos & Motor Vehicles",
            "subcategory":"Fuel & Gas Station",
            "type":"Retail Goods"
        }
    ],
    "sg:phone":"+1 928 718 0088",
    "sg:postcode":"86401",
    "sg:province":"AZ",
    "sg:tags":[
        "station",
        "gasoline",
        "oil"
    ],
    "wof:name":"Billy's Gas Inc",
    "wof:placetype":"venue"
},
  "geometry": {"coordinates":[-114.069329,35.191509],"type":"Point"}
}