{
  "type": "Feature",
  "properties": {
    "addr:full":"13321 W Indian School Rd Litchfield Park AZ 85340",
    "addr:housenumber":"13321",
    "addr:postcode":"85340",
    "addr:street":"W Indian School Rd",
    "iso:country":"US",
    "sg:address":"13321 W Indian School Rd",
    "sg:city":"Litchfield Park",
    "sg:classifiers":[
        {
            "category":"Building & Trades",
            "subcategory":"Construction",
            "type":"Services"
        },
        {
            "category":"Wholesale",
            "subcategory":"Home Furnishings",
            "type":"Manufacturing & Wholesale Goods"
        }
    ],
    "sg:phone":"+1 623 433 8442",
    "sg:postcode":"85340",
    "sg:province":"AZ",
    "sg:tags":[
        "blind",
        "window",
        "installation",
        "shade"
    ],
    "sg:website":"www.gosuperiorblinds.com",
    "wof:name":"Superior Blinds",
    "wof:placetype":"venue"
},
  "geometry": {"coordinates":[-112.34605999999999,33.491951],"type":"Point"}
}