{
  "type": "Feature",
  "properties": {
    "addr:full":"1990 W River Rd Tucson AZ 85704",
    "addr:housenumber":"1990",
    "addr:postcode":"85704",
    "addr:street":"W River Rd",
    "iso:country":"US",
    "sg:address":"1990 W River Rd",
    "sg:city":"Tucson",
    "sg:classifiers":[
        {
            "category":"Restaurant",
            "type":"Food & Drink"
        }
    ],
    "sg:phone":"+1 520 887 0134",
    "sg:postcode":"85704",
    "sg:province":"AZ",
    "sg:tags":[
        "shop",
        "coffee"
    ],
    "wof:name":"Coffee X Change",
    "wof:placetype":"venue"
},
  "geometry": {"coordinates":[-111.011796,32.305279],"type":"Point"}
}