{
  "type": "Feature",
  "properties": {
    "addr:full":"7314 E Canyon Wren Dr Apache Junction AZ 85218",
    "addr:housenumber":"7314",
    "addr:postcode":"85218",
    "addr:street":"E Canyon Wren Dr",
    "iso:country":"US",
    "sg:address":"7314 E Canyon Wren Dr",
    "sg:city":"Apache Junction",
    "sg:phone":"+1 480 983 2784",
    "sg:postcode":"85218",
    "sg:province":"AZ",
    "sg:tags":[
        "farm",
        "corn",
        "soybean"
    ],
    "wof:name":"Stan Truckenbrod",
    "wof:placetype":"venue"
},
  "geometry": {"coordinates":[-111.468637,33.360558],"type":"Point"}
}