{
  "type": "Feature",
  "properties": {
    "iso:country":"US",
    "sg:address":"3066 S Mollera",
    "sg:city":"Mesa",
    "sg:classifiers":[
        {
            "category":"Banks & Credit Unions",
            "subcategory":"Financial Services",
            "type":"Services"
        }
    ],
    "sg:phone":"+1 480 831 1632",
    "sg:postcode":"85210",
    "sg:province":"AZ",
    "sg:tags":[
        "trust",
        "management"
    ],
    "wof:name":"Wootton Family Trust",
    "wof:placetype":"venue"
},
  "geometry": {"coordinates":[-111.858532,33.359134],"type":"Point"}
}