{
  "type": "Feature",
  "properties": {
    "iso:country":"US",
    "sg:address":"17830 N Paradise Park Dr",
    "sg:city":"Phoenix",
    "sg:classifiers":[
        {
            "category":"Manufacturing",
            "subcategory":"Wood Products",
            "type":"Manufacturing & Wholesale Goods"
        }
    ],
    "sg:phone":"+1 602 971 5038",
    "sg:postcode":"85032",
    "sg:province":"AZ",
    "wof:name":"Handle Helpers",
    "wof:placetype":"venue"
},
  "geometry": {"coordinates":[-112.004888,33.648382],"type":"Point"}
}