{
  "type": "Feature",
  "properties": {
    "iso:country":"US",
    "sg:address":"401 N Main St",
    "sg:city":"Cottonwood",
    "sg:classifiers":[
        {
            "category":"Personal",
            "subcategory":"Tattoo Parlor",
            "type":"Services"
        }
    ],
    "sg:phone":"+1 928 634 9889",
    "sg:postcode":"86326",
    "sg:province":"AZ",
    "sg:tags":[
        "tattooing"
    ],
    "wof:name":"Inxon Inc",
    "wof:placetype":"venue"
},
  "geometry": {"coordinates":[-112.011858,34.743655],"type":"Point"}
}