{
  "type": "Feature",
  "properties": {
    "iso:country":"US",
    "sg:address":"10245 E Via Linda",
    "sg:city":"Scottsdale",
    "sg:classifiers":[
        {
            "category":"Health Services",
            "subcategory":"Doctor",
            "type":"Services"
        }
    ],
    "sg:phone":"+1 480 860 8017",
    "sg:postcode":"85258",
    "sg:province":"AZ",
    "sg:tags":[
        "physician",
        "surgeon"
    ],
    "wof:name":"Mc Phee Msk & Rehab Spec",
    "wof:placetype":"venue"
},
  "geometry": {"coordinates":[-111.860139,33.574716],"type":"Point"}
}