{
  "type": "Feature",
  "properties": {
    "iso:country":"US",
    "sg:address":"1125 W Baseline Rd",
    "sg:city":"Mesa",
    "sg:classifiers":[
        {
            "category":"Shopping",
            "type":"Retail Goods"
        }
    ],
    "sg:phone":"+1 480 827 8036",
    "sg:postcode":"85210",
    "sg:province":"AZ",
    "sg:tags":[
        "spa",
        "hot",
        "tub",
        "merchandise"
    ],
    "wof:name":"Acrylic Spas of Arizona",
    "wof:placetype":"venue"
},
  "geometry": {"coordinates":[-111.854292,33.378832],"type":"Point"}
}