{
  "type": "Feature",
  "properties": {
    "iso:country":"US",
    "sg:address":"16620 N 40th St Ste D4",
    "sg:city":"Phoenix",
    "sg:classifiers":[
        {
            "category":"Health Services",
            "subcategory":"Clinic",
            "type":"Services"
        },
        {
            "category":"Health Services",
            "subcategory":"Nursing And Care Facility",
            "type":"Services"
        },
        {
            "category":"Health Services",
            "subcategory":"Health Practitioner",
            "type":"Services"
        }
    ],
    "sg:phone":"+1 602 992 0709",
    "sg:postcode":"85032",
    "sg:province":"AZ",
    "sg:tags":[
        "physician",
        "assistant",
        "medical",
        "home",
        "nurse",
        "eldercare-home"
    ],
    "wof:name":"Gentiva Health Services I",
    "wof:placetype":"venue"
},
  "geometry": {"coordinates":[-111.99614,33.637551],"type":"Point"}
}