{
  "type": "Feature",
  "properties": {
    "iso:country":"US",
    "sg:address":"5755 W Beryl Ave",
    "sg:city":"Glendale",
    "sg:classifiers":[
        {
            "category":"Building & Trades",
            "subcategory":"Construction",
            "type":"Services"
        }
    ],
    "sg:phone":"+1 623 435 9829",
    "sg:postcode":"85302",
    "sg:province":"AZ",
    "sg:tags":[
        "painter"
    ],
    "wof:name":"Lacina Contracting & Painting",
    "wof:placetype":"venue"
},
  "geometry": {"coordinates":[-112.182723,33.578229],"type":"Point"}
}