{
  "type": "Feature",
  "properties": {
    "iso:country":"US",
    "sg:address":"12621 N Paradise Village Pkwy W",
    "sg:city":"Phoenix",
    "sg:classifiers":[
        {
            "category":"Retail",
            "subcategory":"Emissions Testing",
            "type":"Services"
        },
        {
            "category":"Retail",
            "subcategory":"Auto Repair",
            "type":"Services"
        }
    ],
    "sg:phone":"+1 877 291 5399",
    "sg:postcode":"85032",
    "sg:province":"AZ",
    "sg:tags":[
        "inspection"
    ],
    "sg:website":"http://local.ingenio.com/Listings/Details.aspx?NUM=a%3a10290049%3a13%3a4859924%3a14%3a0%3a7",
    "wof:name":"Honest One Auto Care Store",
    "wof:placetype":"venue"
},
  "geometry": {"coordinates":[-111.987909,33.600045],"type":"Point"}
}