{
  "type": "Feature",
  "properties": {
    "iso:country":"US",
    "sg:address":"3162 E Indian School Rd",
    "sg:city":"Phoenix",
    "sg:classifiers":[
        {
            "category":"Retail",
            "subcategory":"Photofinishing",
            "type":"Services"
        }
    ],
    "sg:phone":"+1 602 977 1234",
    "sg:postcode":"85016",
    "sg:province":"AZ",
    "sg:tags":[
        "photo",
        "finishing"
    ],
    "wof:name":"Mighty Imaging LLC",
    "wof:placetype":"venue"
},
  "geometry": {"coordinates":[-112.01493600000001,33.495268],"type":"Point"}
}