{
  "type": "Feature",
  "properties": {
    "addr:full":"6810 E Monterey Way Scottsdale AZ 85251",
    "addr:housenumber":"6810",
    "addr:postcode":"85251",
    "addr:street":"E Monterey Way",
    "iso:country":"US",
    "sg:address":"6810 E Monterey Way",
    "sg:city":"Scottsdale",
    "sg:classifiers":[
        {
            "category":"Real Estate",
            "subcategory":"Real Estate Operator",
            "type":"Services"
        }
    ],
    "sg:phone":"+1 480 941 5679",
    "sg:postcode":"85251",
    "sg:province":"AZ",
    "sg:tags":[
        "building",
        "nonresidential"
    ],
    "wof:name":"Tynor Properties LLC",
    "wof:placetype":"venue"
},
  "geometry": {"coordinates":[-111.931915,33.485481],"type":"Point"}
}