{
  "type": "Feature",
  "properties": {
    "iso:country":"US",
    "sg:address":"7702 N 181st Ave",
    "sg:city":"Waddell",
    "sg:classifiers":[
        {
            "category":"Professional",
            "subcategory":"Business Services",
            "type":"Services"
        }
    ],
    "sg:phone":"+1 928 637 6184",
    "sg:postcode":"85355",
    "sg:province":"AZ",
    "sg:tags":[
        "consultant",
        "coach"
    ],
    "wof:name":"Peak Outdoor Services",
    "wof:placetype":"venue"
},
  "geometry": {"coordinates":[-112.448594,33.54752],"type":"Point"}
}