{
  "type": "Feature",
  "properties": {
    "iso:country":"US",
    "sg:address":"8401 N Scenic Dr",
    "sg:city":"Tucson",
    "sg:classifiers":[
        {
            "category":"Travel",
            "subcategory":"Hotels & Motels",
            "type":"Entertainment"
        }
    ],
    "sg:phone":"+1 520 744 3050",
    "sg:postcode":"85743",
    "sg:province":"AZ",
    "sg:tags":[
        "ranch",
        "guest"
    ],
    "sg:website":"www.lazykbar.com",
    "wof:name":"Lazy K Bar Guest Ranch",
    "wof:placetype":"venue"
},
  "geometry": {"coordinates":[-111.13999699999999,32.362764],"type":"Point"}
}