{
  "type": "Feature",
  "properties": {
    "addr:full":"905 N 54th St Chandler AZ 85226",
    "addr:housenumber":"905",
    "addr:postcode":"85226",
    "addr:street":"N 54Th St",
    "iso:country":"US",
    "sg:address":"905 N 54th St",
    "sg:city":"Chandler",
    "sg:classifiers":[
        {
            "category":"Restaurant",
            "type":"Food & Drink"
        }
    ],
    "sg:phone":"+1 480 940 1900",
    "sg:postcode":"85226",
    "sg:province":"AZ",
    "sg:tags":[
        "house",
        "american",
        "steak"
    ],
    "sg:website":"http://www.flemingssteakhouse.com",
    "wof:name":"Fleming's Prime Steakhouse",
    "wof:placetype":"venue"
},
  "geometry": {"coordinates":[-111.96848,33.317991],"type":"Point"}
}