{
  "type": "Feature",
  "properties": {
    "addr:full":"63715 E Saddlebrooke Blvd Tucson AZ 85739",
    "addr:housenumber":"63715",
    "addr:postcode":"85739",
    "addr:street":"E Saddlebrooke Blvd",
    "iso:country":"US",
    "sg:address":"63715 E Saddlebrooke Blvd",
    "sg:city":"Tucson",
    "sg:classifiers":[
        {
            "category":"Food & Beverages",
            "subcategory":"Groceries & Convenience Stores",
            "type":"Retail Goods"
        }
    ],
    "sg:phone":"+1 520 818 0901",
    "sg:postcode":"85739",
    "sg:province":"AZ",
    "wof:name":"Minit Market",
    "wof:placetype":"venue"
},
  "geometry": {"coordinates":[-110.925003,32.5247],"type":"Point"}
}