{
  "type": "Feature",
  "properties": {
    "addr:full":"4200 Grand Ave Phoenix AZ 85019",
    "addr:housenumber":"4200",
    "addr:postcode":"85019",
    "addr:street":"Grand Ave",
    "iso:country":"US",
    "sg:address":"4200 Grand Ave",
    "sg:city":"Phoenix",
    "sg:classifiers":[
        {
            "category":"Autos & Motor Vehicles",
            "subcategory":"Automobile Sales",
            "type":"Retail Goods"
        }
    ],
    "sg:phone":"+1 602 242 3551",
    "sg:postcode":"85019",
    "sg:province":"AZ",
    "sg:tags":[
        "car",
        "used"
    ],
    "wof:name":"Used Car Mega Store Inc",
    "wof:placetype":"venue"
},
  "geometry": {"coordinates":[-112.151537,33.50945],"type":"Point"}
}