{
  "type": "Feature",
  "properties": {
    "addr:full":"3030 W Buckeye Rd Phoenix AZ 85009",
    "addr:housenumber":"3030",
    "addr:postcode":"85009",
    "addr:street":"W Buckeye Rd",
    "iso:country":"US",
    "sg:address":"3030 W Buckeye Rd",
    "sg:city":"Phoenix",
    "sg:classifiers":[
        {
            "category":"School Buses",
            "type":"Transportation"
        }
    ],
    "sg:phone":"+1 602 278 9339",
    "sg:postcode":"85009",
    "sg:province":"AZ",
    "wof:name":"A A A Bus Brokers",
    "wof:placetype":"venue"
},
  "geometry": {"coordinates":[-112.12501899999999,33.436902],"type":"Point"}
}