{
  "type": "Feature",
  "properties": {
    "iso:country":"US",
    "sg:address":"35001 N 25th Ln",
    "sg:city":"Phoenix",
    "sg:classifiers":[
        {
            "category":"Shopping",
            "subcategory":"Clothing, Apparel, & Fashions",
            "type":"Retail Goods"
        }
    ],
    "sg:phone":"+1 602 433 7777",
    "sg:postcode":"85086",
    "sg:province":"AZ",
    "sg:tags":[
        "t"
    ],
    "wof:name":"Gasoline Alley",
    "wof:placetype":"venue"
},
  "geometry": {"coordinates":[-112.11502,33.803103],"type":"Point"}
}