{
  "type": "Feature",
  "properties": {
    "addr:full":"500 E Hilton Ave Mesa AZ 85204",
    "addr:housenumber":"500",
    "addr:postcode":"85204",
    "addr:street":"E Hilton Ave",
    "iso:country":"US",
    "sg:address":"500 E Hilton Ave",
    "sg:city":"Mesa",
    "sg:classifiers":[
        {
            "category":"Education",
            "subcategory":"School",
            "type":"Public Place"
        }
    ],
    "sg:phone":"+1 480 497 9790",
    "sg:postcode":"85204",
    "sg:province":"AZ",
    "sg:tags":[
        "high",
        "middle",
        "elementary"
    ],
    "wof:name":"Gilbert",
    "wof:placetype":"venue"
},
  "geometry": {"coordinates":[-111.81999999999999,33.388],"type":"Point"}
}