{
  "type": "Feature",
  "properties": {
    "iso:country":"US",
    "sg:address":"11830 N 19th Ave",
    "sg:city":"Phoenix",
    "sg:classifiers":[
        {
            "category":"Health Services",
            "subcategory":"Nursing And Care Facility",
            "type":"Services"
        }
    ],
    "sg:phone":"+1 602 861 3970",
    "sg:postcode":"85029",
    "sg:province":"AZ",
    "sg:tags":[
        "homes-information",
        "life",
        "retirement",
        "bureau",
        "community"
    ],
    "wof:name":"Christian Care Manor",
    "wof:placetype":"venue"
},
  "geometry": {"coordinates":[-112.099631,33.593942],"type":"Point"}
}