{
  "type": "Feature",
  "properties": {
    "iso:country":"US",
    "sg:address":"1108 E 6th St",
    "sg:city":"Tucson",
    "sg:classifiers":[
        {
            "category":"Retail",
            "subcategory":"Laundry & Dry Cleaning",
            "type":"Services"
        }
    ],
    "sg:phone":"+1 520 798 0789",
    "sg:postcode":"85719",
    "sg:province":"AZ",
    "wof:name":"Fair Wash",
    "wof:placetype":"venue"
},
  "geometry": {"coordinates":[-110.953363,32.227699],"type":"Point"}
}