{
  "type": "Feature",
  "properties": {
    "iso:country":"US",
    "sg:address":"475 6th St",
    "sg:city":"Prescott",
    "sg:classifiers":[
        {
            "category":"Utilities",
            "subcategory":"Fuel Oil & Lpg",
            "type":"Services"
        }
    ],
    "sg:phone":"+1 928 445 3191",
    "sg:postcode":"86301",
    "sg:province":"AZ",
    "sg:tags":[
        "propane",
        "gasoline",
        "gas",
        "filling",
        "station",
        "retail"
    ],
    "wof:name":"Flame Propane",
    "wof:placetype":"venue"
},
  "geometry": {"coordinates":[-112.465388,34.547704],"type":"Point"}
}