{
  "type": "Feature",
  "properties": {
    "iso:country":"US",
    "sg:address":"5400 W Massingale Rd",
    "sg:city":"Tucson",
    "sg:classifiers":[
        {
            "category":"Wholesale",
            "subcategory":"Construction Materials",
            "type":"Manufacturing & Wholesale Goods"
        }
    ],
    "sg:phone":"+1 520 744 2500",
    "sg:postcode":"85743",
    "sg:province":"AZ",
    "wof:name":"Sunward Materials",
    "wof:placetype":"venue"
},
  "geometry": {"coordinates":[-111.07831,32.344991],"type":"Point"}
}