{
  "type": "Feature",
  "properties": {
    "iso:country":"US",
    "sg:address":"3431 W Frye Rd Chandler Fashion Center",
    "sg:city":"Chandler",
    "sg:classifiers":[
        {
            "category":"Retail",
            "subcategory":"Portrait Studio",
            "type":"Services"
        },
        {
            "category":"Professional",
            "subcategory":"Art Services",
            "type":"Services"
        }
    ],
    "sg:phone":"+1 480 917 9300",
    "sg:postcode":"85225",
    "sg:province":"AZ",
    "sg:tags":[
        "photographer",
        "photography",
        "store"
    ],
    "sg:website":"www.portraitinnovations.com/",
    "wof:name":"Portrait Innovations",
    "wof:placetype":"venue"
},
  "geometry": {"coordinates":[-111.900443,33.298069],"type":"Point"}
}