{
  "type": "Feature",
  "properties": {
    "iso:country":"US",
    "sg:address":"6502 E Golf Links Rd",
    "sg:city":"Tucson",
    "sg:classifiers":[
        {
            "category":"Real Estate",
            "subcategory":"Real Estate Operator",
            "type":"Services"
        }
    ],
    "sg:phone":"+1 877 537 4446",
    "sg:postcode":"85730",
    "sg:province":"AZ",
    "sg:tags":[
        "building",
        "apartment"
    ],
    "sg:website":"http://local.ingenio.com/Listings/Details.aspx?NUM=a%3a10248553%3a13%3a4859924%3a14%3a0%3a7",
    "wof:name":"Sunflower Apartments",
    "wof:placetype":"venue"
},
  "geometry": {"coordinates":[-110.85342,32.191895],"type":"Point"}
}