{
  "type": "Feature",
  "properties": {
    "addr:full":"3710 N Paradise Rd Flagstaff AZ 86004",
    "addr:housenumber":"3710",
    "addr:postcode":"86004",
    "addr:street":"N Paradise Rd",
    "iso:country":"US",
    "sg:address":"3710 N Paradise Rd",
    "sg:city":"Flagstaff",
    "sg:classifiers":[
        {
            "category":"Building & Trades",
            "subcategory":"Construction",
            "type":"Services"
        }
    ],
    "sg:phone":"+1 928 774 1670",
    "sg:postcode":"86004",
    "sg:province":"AZ",
    "sg:tags":[
        "contractor"
    ],
    "wof:name":"Earl D Nelson Tile Company",
    "wof:placetype":"venue"
},
  "geometry": {"coordinates":[-111.624067,35.222467],"type":"Point"}
}