{
  "type": "Feature",
  "properties": {
    "addr:full":"9970 W Lower Buckeye Rd Tolleson AZ 85353",
    "addr:housenumber":"9970",
    "addr:postcode":"85353",
    "addr:street":"W Lower Buckeye Rd",
    "iso:country":"US",
    "sg:address":"9970 W Lower Buckeye Rd",
    "sg:city":"Tolleson",
    "sg:classifiers":[
        {
            "category":"Autos & Motor Vehicles",
            "subcategory":"Auto Supplies",
            "type":"Retail Goods"
        },
        {
            "category":"Retail",
            "subcategory":"Auto Repair",
            "type":"Services"
        }
    ],
    "sg:phone":"+1 623 936 3133",
    "sg:postcode":"85353",
    "sg:province":"AZ",
    "sg:tags":[
        "lube",
        "oil",
        "tire"
    ],
    "sg:website":"http://www.firestonecompleteautocare.com/?s_kwcid=IYP_NTL",
    "wof:name":"Firestone Complete Auto Care Store",
    "wof:placetype":"venue"
},
  "geometry": {"coordinates":[-112.23975,33.422865],"type":"Point"}
}