{
  "type": "Feature",
  "properties": {
    "iso:country":"US",
    "sg:address":"4820 W Colter St",
    "sg:city":"Glendale",
    "sg:classifiers":[
        {
            "category":"Freight",
            "type":"Transportation"
        }
    ],
    "sg:phone":"+1 623 842 3672",
    "sg:postcode":"85301",
    "sg:province":"AZ",
    "sg:tags":[
        "broker",
        "trucking"
    ],
    "wof:name":"Blackhawk Transport Inc",
    "wof:placetype":"venue"
},
  "geometry": {"coordinates":[-112.165156,33.513484],"type":"Point"}
}