{
  "type": "Feature",
  "properties": {
    "iso:country":"US",
    "sg:address":"12003 N Oakhurst Way",
    "sg:city":"Scottsdale",
    "sg:classifiers":[
        {
            "category":"Place Of Worship",
            "subcategory":"Church",
            "type":"Public Place"
        },
        {
            "category":"Place Of Worship",
            "type":"Public Place"
        }
    ],
    "sg:phone":"+1 480 766 1237",
    "sg:postcode":"85254",
    "sg:province":"AZ",
    "sg:tags":[
        "churches-baptist-general",
        "churches-baptist"
    ],
    "wof:name":"Glaxosmthkline Hldngs Ame",
    "wof:placetype":"venue"
},
  "geometry": {"coordinates":[-111.957813,33.594954],"type":"Point"}
}