{
  "type": "Feature",
  "properties": {
    "iso:country":"US",
    "sg:address":"8701 E Rustler Dr",
    "sg:city":"Prescott Valley",
    "sg:classifiers":[
        {
            "category":"Building & Trades",
            "subcategory":"Construction",
            "type":"Services"
        }
    ],
    "sg:phone":"+1 928 772 9815",
    "sg:postcode":"86314",
    "sg:province":"AZ",
    "sg:tags":[
        "house"
    ],
    "wof:name":"Vintage Building & Remodeling",
    "wof:placetype":"venue"
},
  "geometry": {"coordinates":[-112.313741,34.611729],"type":"Point"}
}