{
  "type": "Feature",
  "properties": {
    "iso:country":"US",
    "sg:address":"3211 E Eva St",
    "sg:city":"Phoenix",
    "sg:classifiers":[
        {
            "category":"Professional",
            "type":"Services"
        }
    ],
    "sg:phone":"+1 602 870 3866",
    "sg:postcode":"85028",
    "sg:province":"AZ",
    "wof:name":"Eva Street Inc",
    "wof:placetype":"venue"
},
  "geometry": {"coordinates":[-112.011859,33.568354],"type":"Point"}
}