{
  "type": "Feature",
  "properties": {
    "iso:country":"US",
    "sg:address":"2151 W 3rd St",
    "sg:city":"Winslow",
    "sg:classifiers":[
        {
            "category":"Bars & Pubs",
            "type":"Food & Drink"
        }
    ],
    "sg:phone":"+1 928 289 3856",
    "sg:postcode":"86024",
    "sg:province":"AZ",
    "wof:name":"Broncos Sports Bar",
    "wof:placetype":"venue"
},
  "geometry": {"coordinates":[-110.720198,35.034783],"type":"Point"}
}