{
  "type": "Feature",
  "properties": {
    "addr:full":"1725 E Fry Blvd Sierra Vista AZ 85635",
    "addr:housenumber":"1725",
    "addr:postcode":"85635",
    "addr:street":"E Fry Blvd",
    "iso:country":"US",
    "sg:address":"1725 E Fry Blvd",
    "sg:city":"Sierra Vista",
    "sg:classifiers":[
        {
            "category":"Autos & Motor Vehicles",
            "subcategory":"Auto Supplies",
            "type":"Retail Goods"
        }
    ],
    "sg:phone":"+1 520 417 1541",
    "sg:postcode":"85635",
    "sg:province":"AZ",
    "sg:tags":[
        "automobile",
        "parts"
    ],
    "wof:name":"Checker Auto Parts 1611",
    "wof:placetype":"venue"
},
  "geometry": {"coordinates":[-110.280089,31.554712],"type":"Point"}
}