{
  "type": "Feature",
  "properties": {
    "iso:country":"US",
    "sg:address":"3023 N 59th Ave",
    "sg:city":"Phoenix",
    "sg:classifiers":[
        {
            "category":"Real Estate",
            "subcategory":"Real Estate Services",
            "type":"Services"
        },
        {
            "category":"Real Estate",
            "subcategory":"Real Estate Agent",
            "type":"Services"
        }
    ],
    "sg:phone":"+1 623 247 8662",
    "sg:postcode":"85033",
    "sg:province":"AZ",
    "sg:tags":[
        "buyer",
        "broker"
    ],
    "wof:name":"Jose Acosta Real Estate",
    "wof:placetype":"venue"
},
  "geometry": {"coordinates":[-112.186241,33.482901],"type":"Point"}
}