{
  "type": "Feature",
  "properties": {
    "iso:country":"US",
    "sg:address":"5661 S Ironwood Dr",
    "sg:city":"Apache Junction",
    "sg:classifiers":[
        {
            "category":"Manufacturing",
            "subcategory":"Tools & Machinery",
            "type":"Manufacturing & Wholesale Goods"
        }
    ],
    "sg:phone":"+1 480 982 3053",
    "sg:postcode":"85220",
    "sg:province":"AZ",
    "sg:tags":[
        "industry",
        "mfg"
    ],
    "wof:name":"United States Filter Corp",
    "wof:placetype":"venue"
},
  "geometry": {"coordinates":[-111.563422,33.365181],"type":"Point"}
}