{
  "type": "Feature",
  "properties": {
    "addr:full":"6609 W Aire Libre Ave Glendale AZ 85306",
    "addr:housenumber":"6609",
    "addr:postcode":"85306",
    "addr:street":"W Aire Libre Ave",
    "iso:country":"US",
    "sg:address":"6609 W Aire Libre Ave",
    "sg:city":"Glendale",
    "sg:classifiers":[
        {
            "category":"Retail",
            "subcategory":"Repair Shop",
            "type":"Services"
        }
    ],
    "sg:phone":"+1 623 486 1253",
    "sg:postcode":"85306",
    "sg:province":"AZ",
    "sg:tags":[
        "antique",
        "restoring"
    ],
    "wof:name":"Emmett's Fix-It Shop",
    "wof:placetype":"venue"
},
  "geometry": {"coordinates":[-112.201201,33.63484],"type":"Point"}
}