{
  "type": "Feature",
  "properties": {
    "addr:full":"3760 W Wahalla Ln Glendale AZ 85308",
    "addr:housenumber":"3760",
    "addr:postcode":"85308",
    "addr:street":"W Wahalla Ln",
    "iso:country":"US",
    "sg:address":"3760 W Wahalla Ln",
    "sg:city":"Glendale",
    "sg:classifiers":[
        {
            "category":"Organizations",
            "subcategory":"Religious Organization",
            "type":"Services"
        }
    ],
    "sg:phone":"+1 623 492 0094",
    "sg:postcode":"85308",
    "sg:province":"AZ",
    "sg:tags":[
        "church"
    ],
    "wof:name":"Body Of Christ Fellowship",
    "wof:placetype":"venue"
},
  "geometry": {"coordinates":[-112.141133,33.66732],"type":"Point"}
}