{
  "type": "Feature",
  "properties": {
    "iso:country":"US",
    "sg:address":"540 W Missouri Ave",
    "sg:city":"Phoenix",
    "sg:classifiers":[
        {
            "category":"Retail",
            "subcategory":"Auto Repair",
            "type":"Services"
        }
    ],
    "sg:phone":"+1 602 277 6651",
    "sg:postcode":"85013",
    "sg:province":"AZ",
    "sg:website":"http://www.davesimportservice.com",
    "wof:name":"Dave's British Import Service",
    "wof:placetype":"venue"
},
  "geometry": {"coordinates":[-112.081227,33.516585],"type":"Point"}
}