{
  "type": "Feature",
  "properties": {
    "addr:full":"7350 E Evans Rd Scottsdale AZ 85260",
    "addr:housenumber":"7350",
    "addr:postcode":"85260",
    "addr:street":"E Evans Rd",
    "iso:country":"US",
    "sg:address":"7350 E Evans Rd",
    "sg:city":"Scottsdale",
    "sg:classifiers":[
        {
            "category":"Banks & Credit Unions",
            "subcategory":"Bank",
            "type":"Services"
        }
    ],
    "sg:phone":"+1 480 951 7500",
    "sg:postcode":"85260",
    "sg:province":"AZ",
    "wof:name":"M & I Bank",
    "wof:placetype":"venue"
},
  "geometry": {"coordinates":[-111.923996,33.616108],"type":"Point"}
}