{
  "type": "Feature",
  "properties": {
    "iso:country":"US",
    "sg:address":"955 E Queen Creek Rd",
    "sg:city":"Chandler",
    "sg:classifiers":[
        {
            "category":"Professional",
            "subcategory":"Management & Consulting",
            "type":"Services"
        }
    ],
    "sg:phone":"+1 480 782 3516",
    "sg:postcode":"85249",
    "sg:province":"AZ",
    "sg:tags":[
        "industrial",
        "waste",
        "engineer"
    ],
    "wof:name":"Solid Waste & Recycling",
    "wof:placetype":"venue"
},
  "geometry": {"coordinates":[-111.831816,33.262184],"type":"Point"}
}