{
  "type": "Feature",
  "properties": {
    "iso:country":"US",
    "sg:address":"12816 E Turquoise Ave",
    "sg:city":"Scottsdale",
    "sg:classifiers":[
        {
            "category":"Organizations",
            "subcategory":"Non-profit Organization",
            "type":"Services"
        }
    ],
    "sg:phone":"+1 480 275 8542",
    "sg:postcode":"85259",
    "sg:province":"AZ",
    "sg:tags":[
        "info",
        "addiction",
        "abuse",
        "treatment",
        "drug"
    ],
    "wof:name":"Sundance Center",
    "wof:placetype":"venue"
},
  "geometry": {"coordinates":[-111.804408,33.577092],"type":"Point"}
}