{
  "type": "Feature",
  "properties": {
    "addr:full":"5054 E McDowell Rd Phoenix AZ 85008",
    "addr:housenumber":"5054",
    "addr:postcode":"85008",
    "addr:street":"E Mcdowell Rd",
    "iso:country":"US",
    "sg:address":"5054 E McDowell Rd",
    "sg:city":"Phoenix",
    "sg:classifiers":[
        {
            "category":"Shopping",
            "subcategory":"Clothing, Apparel, & Fashions",
            "type":"Retail Goods"
        }
    ],
    "sg:phone":"+1 602 231 9400",
    "sg:postcode":"85008",
    "sg:province":"AZ",
    "wof:name":"Amy's Ethnic Clothing Store",
    "wof:placetype":"venue"
},
  "geometry": {"coordinates":[-111.972858,33.465659],"type":"Point"}
}