{
  "type": "Feature",
  "properties": {
    "iso:country":"US",
    "sg:address":"532 E Maryland Ave",
    "sg:city":"Phoenix",
    "sg:classifiers":[
        {
            "category":"Real Estate",
            "subcategory":"Real Estate Agent",
            "type":"Services"
        }
    ],
    "sg:phone":"+1 602 277 4418",
    "sg:postcode":"85012",
    "sg:province":"AZ",
    "sg:tags":[
        "management"
    ],
    "wof:name":"Osselaer Co",
    "wof:placetype":"venue"
},
  "geometry": {"coordinates":[-112.067207,33.531071],"type":"Point"}
}