{
  "type": "Feature",
  "properties": {
    "addr:full":"2550 Haskell Springs Rd Clarkdale AZ 86324",
    "addr:housenumber":"2550",
    "addr:postcode":"86324",
    "addr:street":"Haskell Springs Rd",
    "iso:country":"US",
    "sg:address":"2550 Haskell Springs Rd",
    "sg:city":"Clarkdale",
    "sg:classifiers":[
        {
            "category":"Wholesale",
            "subcategory":"Machinery & Supplies",
            "type":"Manufacturing & Wholesale Goods"
        }
    ],
    "sg:phone":"+1 928 634 3081",
    "sg:postcode":"86324",
    "sg:province":"AZ",
    "wof:name":"Water Works Cottonwood",
    "wof:placetype":"venue"
},
  "geometry": {"coordinates":[-112.062021,34.736581],"type":"Point"}
}