{
  "type": "Feature",
  "properties": {
    "iso:country":"US",
    "sg:address":"9014 W Thomas Rd",
    "sg:city":"Phoenix",
    "sg:classifiers":[
        {
            "category":"Personal",
            "subcategory":"Beauty Salon",
            "type":"Services"
        }
    ],
    "sg:phone":"+1 623 772 0121",
    "sg:postcode":"85037",
    "sg:province":"AZ",
    "wof:name":"Fantastic Sam's",
    "wof:placetype":"venue"
},
  "geometry": {"coordinates":[-112.253716,33.47979],"type":"Point"}
}