{
  "type": "Feature",
  "properties": {
    "addr:full":"1732 W Mitchell Dr Phoenix AZ 85015",
    "addr:housenumber":"1732",
    "addr:postcode":"85015",
    "addr:street":"W Mitchell Dr",
    "iso:country":"US",
    "sg:address":"1732 W Mitchell Dr",
    "sg:city":"Phoenix",
    "sg:classifiers":[
        {
            "category":"Place Of Worship",
            "subcategory":"Church",
            "type":"Public Place"
        },
        {
            "category":"Place Of Worship",
            "type":"Public Place"
        },
        {
            "category":"Education",
            "subcategory":"School",
            "type":"Public Place"
        },
        {
            "category":"Organizations",
            "subcategory":"Community Association",
            "type":"Services"
        }
    ],
    "sg:phone":"+1 602 266 7118",
    "sg:postcode":"85015",
    "sg:province":"AZ",
    "sg:tags":[
        "churches-catholic-traditional",
        "consultant",
        "churches-catholic",
        "spiritual",
        "interest",
        "religious"
    ],
    "wof:name":"Saint Gregory's Office Of Religous Edducation",
    "wof:placetype":"venue"
},
  "geometry": {"coordinates":[-112.096388,33.488608],"type":"Point"}
}