{
  "type": "Feature",
  "properties": {
    "addr:full":"1601 S 59th Ave Phoenix AZ 85043",
    "addr:housenumber":"1601",
    "addr:postcode":"85043",
    "addr:street":"S 59Th Ave",
    "iso:country":"US",
    "sg:address":"1601 S 59th Ave",
    "sg:city":"Phoenix",
    "sg:classifiers":[
        {
            "category":"Home & Garden",
            "subcategory":"Garden Supply",
            "type":"Retail Goods"
        }
    ],
    "sg:phone":"+1 602 278 7958",
    "sg:postcode":"85043",
    "sg:province":"AZ",
    "sg:tags":[
        "equipment",
        "lawn",
        "landscaping",
        "mower"
    ],
    "wof:name":"Cub Cadet Lawn & Garden Eqpt",
    "wof:placetype":"venue"
},
  "geometry": {"coordinates":[-112.18652299999999,33.433074],"type":"Point"}
}