{
  "type": "Feature",
  "properties": {
    "iso:country":"US",
    "sg:address":"2016 N Via Madonna",
    "sg:city":"Nogales",
    "sg:classifiers":[
        {
            "category":"Building & Trades",
            "subcategory":"Construction",
            "type":"Services"
        }
    ],
    "sg:phone":"+1 520 281 1260",
    "sg:postcode":"85621",
    "sg:province":"AZ",
    "sg:tags":[
        "home",
        "custom"
    ],
    "wof:name":"Ljk Construction",
    "wof:placetype":"venue"
},
  "geometry": {"coordinates":[-110.92222,31.369106],"type":"Point"}
}