{
  "type": "Feature",
  "properties": {
    "addr:full":"2601 W Ver Verde Tucson AZ 85746",
    "addr:housenumber":"2601",
    "addr:postcode":"85746",
    "addr:street":"W Ver Verde",
    "iso:country":"US",
    "sg:address":"2601 W Ver Verde",
    "sg:city":"Tucson",
    "sg:classifiers":[
        {
            "category":"Communications",
            "type":"Services"
        }
    ],
    "sg:phone":"+1 520 792 1724",
    "sg:postcode":"85746",
    "sg:province":"AZ",
    "wof:name":"Voltar Communications Inc",
    "wof:placetype":"venue"
},
  "geometry": {"coordinates":[-111.02273,32.131123],"type":"Point"}
}