{
  "type": "Feature",
  "properties": {
    "iso:country":"US",
    "sg:address":"2440 E Geronimo St",
    "sg:city":"Chandler",
    "sg:classifiers":[
        {
            "category":"Professional",
            "subcategory":"Computer Services",
            "type":"Services"
        }
    ],
    "sg:phone":"+1 602 720 7133",
    "sg:postcode":"85225",
    "sg:province":"AZ",
    "sg:tags":[
        "consultant",
        "designer"
    ],
    "sg:website":"www.opentrack.com",
    "wof:name":"Open Track Solutions",
    "wof:placetype":"venue"
},
  "geometry": {"coordinates":[-111.79888,33.293324],"type":"Point"}
}