{
  "type": "Feature",
  "properties": {
    "iso:country":"US",
    "sg:address":"12918 S 131st St",
    "sg:city":"Gilbert",
    "sg:classifiers":[
        {
            "category":"Professional",
            "type":"Services"
        }
    ],
    "sg:phone":"+1 480 857 3537",
    "sg:postcode":"85233",
    "sg:province":"AZ",
    "wof:name":"Island Juice",
    "wof:placetype":"venue"
},
  "geometry": {"coordinates":[-111.800606,33.330704],"type":"Point"}
}