{
  "type": "Feature",
  "properties": {
    "iso:country":"US",
    "sg:address":"2655 N Campbell Ave",
    "sg:city":"Tucson",
    "sg:classifiers":[
        {
            "category":"Shopping",
            "subcategory":"Gifts & Souvenirs",
            "type":"Retail Goods"
        }
    ],
    "sg:phone":"+1 520 327 8402",
    "sg:postcode":"85719",
    "sg:province":"AZ",
    "sg:tags":[
        "shop",
        "novelty"
    ],
    "wof:name":"Continental Adult Shop",
    "wof:placetype":"venue"
},
  "geometry": {"coordinates":[-110.94396,32.25473],"type":"Point"}
}