{
  "type": "Feature",
  "properties": {
    "iso:country":"US",
    "sg:address":"20624 N 76th St",
    "sg:city":"Scottsdale",
    "sg:classifiers":[
        {
            "category":"Education",
            "subcategory":"School",
            "type":"Public Place"
        }
    ],
    "sg:phone":"+1 480 502 6878",
    "sg:postcode":"85255",
    "sg:province":"AZ",
    "sg:website":"www.eldoradops.com",
    "wof:name":"El Dorado Private School",
    "wof:placetype":"venue"
},
  "geometry": {"coordinates":[-111.916024,33.673748],"type":"Point"}
}