{
  "type": "Feature",
  "properties": {
    "addr:full":"20624 N 76th St Scottsdale AZ 85255",
    "addr:housenumber":"20624",
    "addr:postcode":"85255",
    "addr:street":"N 76Th St",
    "iso:country":"US",
    "sg:address":"20624 N 76th St",
    "sg:city":"Scottsdale",
    "sg:classifiers":[
        {
            "category":"Education",
            "subcategory":"School",
            "type":"Public Place"
        }
    ],
    "sg:phone":"+1 480 502 6878",
    "sg:postcode":"85255",
    "sg:province":"AZ",
    "sg:website":"www.eldoradops.com",
    "wof:name":"El Dorado Private School",
    "wof:placetype":"venue"
},
  "geometry": {"coordinates":[-111.91602399999999,33.673748],"type":"Point"}
}