{
  "type": "Feature",
  "properties": {
    "iso:country":"US",
    "sg:address":"3095 W Sandy Dr",
    "sg:city":"Chino Valley",
    "sg:classifiers":[
        {
            "category":"Organizations",
            "subcategory":"Non-profit Organization",
            "type":"Services"
        }
    ],
    "sg:phone":"+1 928 636 7922",
    "sg:postcode":"86323",
    "sg:province":"AZ",
    "wof:name":"Big Hearts For Little Souls",
    "wof:placetype":"venue"
},
  "geometry": {"coordinates":[-112.501542,34.72837],"type":"Point"}
}