{
  "type": "Feature",
  "properties": {
    "addr:full":"15223 N Northsight Blvd Scottsdale AZ 85260",
    "addr:housenumber":"15223",
    "addr:postcode":"85260",
    "addr:street":"N Northsight Blvd",
    "iso:country":"US",
    "sg:address":"15223 N Northsight Blvd",
    "sg:city":"Scottsdale",
    "sg:classifiers":[
        {
            "category":"Restaurant",
            "type":"Food & Drink"
        }
    ],
    "sg:phone":"+1 480 367 1603",
    "sg:postcode":"85260",
    "sg:province":"AZ",
    "sg:tags":[
        "eating"
    ],
    "wof:name":"Arizona's Mongolian Bbq",
    "wof:placetype":"venue"
},
  "geometry": {"coordinates":[-111.89605400000001,33.623274],"type":"Point"}
}