{
  "type": "Feature",
  "properties": {
    "iso:country":"US",
    "sg:address":"1625 W Ina Rd",
    "sg:city":"Tucson",
    "sg:classifiers":[
        {
            "category":"Health Services",
            "subcategory":"Podiatrist",
            "type":"Services"
        }
    ],
    "sg:phone":"+1 520 297 1366",
    "sg:postcode":"85704",
    "sg:province":"AZ",
    "wof:name":"Northwest Podiatry",
    "wof:placetype":"venue"
},
  "geometry": {"coordinates":[-111.002851,32.337149],"type":"Point"}
}