{
  "type": "Feature",
  "properties": {
    "addr:full":"5320 N 16th St Ste 207 Phoenix AZ 85016",
    "addr:housenumber":"5320",
    "addr:postcode":"85016",
    "addr:street":"N 16Th St Ste 207",
    "iso:country":"US",
    "sg:address":"5320 N 16th St Ste 207",
    "sg:city":"Phoenix",
    "sg:classifiers":[
        {
            "category":"Utilities",
            "subcategory":"Telephone",
            "type":"Services"
        },
        {
            "category":"Communications",
            "type":"Services"
        }
    ],
    "sg:phone":"+1 602 234 2004",
    "sg:postcode":"85016",
    "sg:province":"AZ",
    "sg:tags":[
        "equipment",
        "systems-repair"
    ],
    "wof:name":"Messagelink Communications Corporation",
    "wof:placetype":"venue"
},
  "geometry": {"coordinates":[-112.04753100000001,33.515035],"type":"Point"}
}