{
  "type": "Feature",
  "properties": {
    "iso:country":"US",
    "sg:address":"2741 W Polk St",
    "sg:city":"Phoenix",
    "sg:classifiers":[
        {
            "category":"Restaurant",
            "type":"Food & Drink"
        }
    ],
    "sg:phone":"+1 623 848 6120",
    "sg:postcode":"85009",
    "sg:province":"AZ",
    "sg:tags":[
        "eating"
    ],
    "wof:name":"Coy Ice Cream",
    "wof:placetype":"venue"
},
  "geometry": {"coordinates":[-112.12024,33.452924],"type":"Point"}
}