{
  "type": "Feature",
  "properties": {
    "iso:country":"US",
    "sg:address":"1840 E Warner Rd Ste 114",
    "sg:city":"Tempe",
    "sg:classifiers":[
        {
            "category":"Health Services",
            "subcategory":"Medical Lab",
            "type":"Services"
        }
    ],
    "sg:phone":"+1 480 768 2800",
    "sg:postcode":"85284",
    "sg:province":"AZ",
    "sg:tags":[
        "laboratory",
        "laboratories-pathological"
    ],
    "wof:name":"East Vly Diagnstc Med Imaging",
    "wof:placetype":"venue"
},
  "geometry": {"coordinates":[-111.908478,33.334663],"type":"Point"}
}