{
  "type": "Feature",
  "properties": {
    "addr:full":"4643 State Hwy 92 Sierra Vista AZ 85650",
    "addr:housenumber":"4643",
    "addr:postcode":"85650",
    "addr:street":"State Hwy 92",
    "iso:country":"US",
    "sg:address":"4643 State Hwy 92",
    "sg:city":"Sierra Vista",
    "sg:classifiers":[
        {
            "category":"Restaurant",
            "type":"Food & Drink"
        }
    ],
    "sg:phone":"+1 520 417 2650",
    "sg:postcode":"85650",
    "sg:province":"AZ",
    "sg:tags":[
        "eating"
    ],
    "wof:name":"La Mexicana",
    "wof:placetype":"venue"
},
  "geometry": {"coordinates":[-110.257324,31.484606],"type":"Point"}
}