{
  "type": "Feature",
  "properties": {
    "addr:full":"940 W Buckeye Rd Phoenix AZ 85007",
    "addr:housenumber":"940",
    "addr:postcode":"85007",
    "addr:street":"W Buckeye Rd",
    "iso:country":"US",
    "sg:address":"940 W Buckeye Rd",
    "sg:city":"Phoenix",
    "sg:classifiers":[
        {
            "category":"Autos & Motor Vehicles",
            "subcategory":"Automobile Sales",
            "type":"Retail Goods"
        },
        {
            "category":"Wholesale",
            "subcategory":"Scrap",
            "type":"Manufacturing & Wholesale Goods"
        },
        {
            "category":"Autos & Motor Vehicles",
            "subcategory":"Auto Supplies",
            "type":"Retail Goods"
        }
    ],
    "sg:phone":"+1 602 272 6785",
    "sg:postcode":"85007",
    "sg:province":"AZ",
    "sg:tags":[
        "salvage",
        "junk",
        "part",
        "supplies-used",
        "rebuilt"
    ],
    "sg:website":"http://www.phoenixpullapart.com",
    "wof:name":"Phoenix Pull-A-Part",
    "wof:placetype":"venue"
},
  "geometry": {"coordinates":[-112.085154,33.436809],"type":"Point"}
}