{
  "type": "Feature",
  "properties": {
    "iso:country":"US",
    "sg:address":"1906 E Elmwood St",
    "sg:city":"Mesa",
    "sg:classifiers":[
        {
            "category":"Shopping",
            "subcategory":"Gifts & Souvenirs",
            "type":"Retail Goods"
        }
    ],
    "sg:phone":"+1 480 835 2265",
    "sg:postcode":"85203",
    "sg:province":"AZ",
    "sg:tags":[
        "shop",
        "wrap",
        "balloon",
        "sales",
        "contract"
    ],
    "wof:name":"CNA Enterpr Present Clas Wrap",
    "wof:placetype":"venue"
},
  "geometry": {"coordinates":[-111.789938,33.433149],"type":"Point"}
}