{
  "type": "Feature",
  "properties": {
    "iso:country":"US",
    "sg:address":"6432 W Broadway Rd",
    "sg:city":"Phoenix",
    "sg:classifiers":[
        {
            "category":"Transit Center",
            "subcategory":"Freight",
            "type":"Transportation"
        },
        {
            "category":"Freight",
            "type":"Transportation"
        }
    ],
    "sg:phone":"+1 623 907 8336",
    "sg:postcode":"85043",
    "sg:province":"AZ",
    "sg:tags":[
        "trucking-motor",
        "trucking"
    ],
    "wof:name":"Aggregate Demo & Direct",
    "wof:placetype":"venue"
},
  "geometry": {"coordinates":[-112.199253,33.408352],"type":"Point"}
}