{
  "type": "Feature",
  "properties": {
    "iso:country":"US",
    "sg:address":"47810 N Kelley Rd",
    "sg:city":"Phoenix",
    "sg:classifiers":[
        {
            "category":"Shopping",
            "subcategory":"Catalog Store",
            "type":"Retail Goods"
        }
    ],
    "sg:phone":"+1 623 465 5813",
    "sg:postcode":"85087",
    "sg:province":"AZ",
    "sg:tags":[
        "house",
        "mail"
    ],
    "wof:name":"Barbara Wallers Mail Order",
    "wof:placetype":"venue"
},
  "geometry": {"coordinates":[-112.134948,33.922148],"type":"Point"}
}