{
  "type": "Feature",
  "properties": {
    "iso:country":"US",
    "sg:address":"815 E Grovers Ave",
    "sg:city":"Phoenix",
    "sg:classifiers":[
        {
            "category":"Autos & Motor Vehicles",
            "subcategory":"Auto Supplies",
            "type":"Retail Goods"
        }
    ],
    "sg:phone":"+1 602 493 1404",
    "sg:postcode":"85022",
    "sg:province":"AZ",
    "sg:tags":[
        "automobile",
        "stereo",
        "radio"
    ],
    "wof:name":"Image Autosports",
    "wof:placetype":"venue"
},
  "geometry": {"coordinates":[-112.063365,33.647577],"type":"Point"}
}