{
  "type": "Feature",
  "properties": {
    "iso:country":"US",
    "sg:address":"5800 E Thomas Rd Ste 109",
    "sg:city":"Scottsdale",
    "sg:classifiers":[
        {
            "category":"Wholesale",
            "subcategory":"Electrical",
            "type":"Manufacturing & Wholesale Goods"
        }
    ],
    "sg:phone":"+1 480 994 4840",
    "sg:postcode":"85251",
    "sg:province":"AZ",
    "sg:tags":[
        "semiconductor",
        "device"
    ],
    "sg:website":"http://www.wadsworth-pacific.com",
    "wof:name":"Wadsworth Pacific",
    "wof:placetype":"venue"
},
  "geometry": {"coordinates":[-111.956071,33.480081],"type":"Point"}
}