{
  "type": "Feature",
  "properties": {
    "addr:full":"2115 S Ash Cir Mesa AZ 85202",
    "addr:housenumber":"2115",
    "addr:postcode":"85202",
    "addr:street":"S Ash Cir",
    "iso:country":"US",
    "sg:address":"2115 S Ash Cir",
    "sg:city":"Mesa",
    "sg:classifiers":[
        {
            "category":"Professional",
            "type":"Services"
        }
    ],
    "sg:phone":"+1 480 777 2327",
    "sg:postcode":"85202",
    "sg:province":"AZ",
    "wof:name":"Transtech International LLC",
    "wof:placetype":"venue"
},
  "geometry": {"coordinates":[-111.86708,33.37618],"type":"Point"}
}