{
  "type": "Feature",
  "properties": {
    "iso:country":"US",
    "sg:address":"4234 N Winfield Scott Plz",
    "sg:city":"Scottsdale",
    "sg:classifiers":[
        {
            "category":"Professional",
            "subcategory":"Business Services",
            "type":"Services"
        },
        {
            "category":"Conference Center",
            "type":"Public Place"
        }
    ],
    "sg:phone":"+1 480 423 2352",
    "sg:postcode":"85251",
    "sg:province":"AZ",
    "sg:tags":[
        "facility",
        "supply",
        "convention"
    ],
    "wof:name":"Phoenix Conference Planners",
    "wof:placetype":"venue"
},
  "geometry": {"coordinates":[-111.925201,33.497599],"type":"Point"}
}