{
  "type": "Feature",
  "properties": {
    "iso:country":"US",
    "sg:address":"3790 W Ina Rd",
    "sg:city":"Tucson",
    "sg:classifiers":[
        {
            "category":"Restaurant",
            "type":"Food & Drink"
        }
    ],
    "sg:phone":"+1 520 744 0392",
    "sg:postcode":"85741",
    "sg:province":"AZ",
    "sg:tags":[
        "eating"
    ],
    "wof:name":"Carls Jr",
    "wof:placetype":"venue"
},
  "geometry": {"coordinates":[-111.045479,32.337576],"type":"Point"}
}