{
  "type": "Feature",
  "properties": {
    "iso:country":"US",
    "sg:address":"3737 W Villa Theresa Dr",
    "sg:city":"Glendale",
    "sg:classifiers":[
        {
            "category":"Professional",
            "subcategory":"Management & Consulting",
            "type":"Services"
        }
    ],
    "sg:phone":"+1 602 595 0625",
    "sg:postcode":"85308",
    "sg:province":"AZ",
    "sg:tags":[
        "construction"
    ],
    "wof:name":"Protouch Construction Mgt LLC",
    "wof:placetype":"venue"
},
  "geometry": {"coordinates":[-112.140493,33.654003],"type":"Point"}
}