{
  "type": "Feature",
  "properties": {
    "iso:country":"US",
    "sg:address":"890 W Elliot Rd Ste 102",
    "sg:city":"Gilbert",
    "sg:classifiers":[
        {
            "category":"Personal",
            "type":"Services"
        },
        {
            "category":"Retail",
            "subcategory":"Event Space",
            "type":"Services"
        }
    ],
    "sg:phone":"+1 480 782 7218",
    "sg:postcode":"85233",
    "sg:province":"AZ",
    "sg:tags":[
        "planning",
        "venue",
        "wedding"
    ],
    "wof:name":"Villa Siena",
    "wof:placetype":"venue"
},
  "geometry": {"coordinates":[-111.808865,33.350859],"type":"Point"}
}