{
  "type": "Feature",
  "properties": {
    "iso:country":"US",
    "sg:address":"2200 E Cedar Ave",
    "sg:city":"Flagstaff",
    "sg:classifiers":[
        {
            "category":"Real Estate",
            "subcategory":"Developer",
            "type":"Services"
        }
    ],
    "sg:phone":"+1 928 774 8141",
    "sg:postcode":"86004",
    "sg:province":"AZ",
    "sg:tags":[
        "development",
        "subdividing"
    ],
    "wof:name":"Global Management",
    "wof:placetype":"venue"
},
  "geometry": {"coordinates":[-111.614996,35.218097],"type":"Point"}
}