{
  "type": "Feature",
  "properties": {
    "addr:full":"30 Church St Quartzsite AZ 85346",
    "addr:housenumber":"30",
    "addr:postcode":"85346",
    "addr:street":"Church St",
    "iso:country":"US",
    "sg:address":"30 Church St",
    "sg:city":"Quartzsite",
    "sg:classifiers":[
        {
            "category":"Organizations",
            "subcategory":"Religious Organization",
            "type":"Services"
        }
    ],
    "sg:phone":"+1 928 927 6395",
    "sg:postcode":"85346",
    "sg:province":"AZ",
    "sg:tags":[
        "church"
    ],
    "wof:name":"First Baptist Church",
    "wof:placetype":"venue"
},
  "geometry": {"coordinates":[-114.22615500000001,33.66694],"type":"Point"}
}