{
  "type": "Feature",
  "properties": {
    "addr:full":"1406 W 14th St Tempe AZ 85281",
    "addr:housenumber":"1406",
    "addr:postcode":"85281",
    "addr:street":"W 14Th St",
    "iso:country":"US",
    "sg:address":"1406 W 14th St",
    "sg:city":"Tempe",
    "sg:classifiers":[
        {
            "category":"Wholesale",
            "subcategory":"Office Equipment",
            "type":"Manufacturing & Wholesale Goods"
        }
    ],
    "sg:phone":"+1 480 966 3444",
    "sg:postcode":"85281",
    "sg:province":"AZ",
    "sg:tags":[
        "machine",
        "duplicating",
        "copying"
    ],
    "wof:name":"Ace Office Equipment Svc",
    "wof:placetype":"venue"
},
  "geometry": {"coordinates":[-111.963054,33.413628],"type":"Point"}
}