{
  "type": "Feature",
  "properties": {
    "addr:full":"201 E Keogh Dr Phoenix AZ 85022",
    "addr:housenumber":"201",
    "addr:postcode":"85022",
    "addr:street":"E Keogh Dr",
    "iso:country":"US",
    "sg:address":"201 E Keogh Dr",
    "sg:city":"Phoenix",
    "sg:classifiers":[
        {
            "category":"Manufacturing",
            "subcategory":"Printing",
            "type":"Manufacturing & Wholesale Goods"
        }
    ],
    "sg:phone":"+1 602 942 4378",
    "sg:postcode":"85022",
    "sg:province":"AZ",
    "sg:tags":[
        "commercial"
    ],
    "wof:name":"Orrs Lettering Manufacturing",
    "wof:placetype":"venue"
},
  "geometry": {"coordinates":[-112.07102399999999,33.647074],"type":"Point"}
}