{
  "type": "Feature",
  "properties": {
    "iso:country":"US",
    "sg:address":"2355 E Camelback Rd # 605",
    "sg:city":"Phoenix",
    "sg:classifiers":[
        {
            "category":"Autos & Motor Vehicles",
            "subcategory":"Automobile Sales",
            "type":"Retail Goods"
        }
    ],
    "sg:phone":"+1 602 468 3660",
    "sg:postcode":"85016",
    "sg:province":"AZ",
    "sg:tags":[
        "new",
        "car"
    ],
    "wof:name":"Grand Auto Plaza",
    "wof:placetype":"venue"
},
  "geometry": {"coordinates":[-112.031076,33.509232],"type":"Point"}
}