{
  "type": "Feature",
  "properties": {
    "addr:full":"4025 W Chandler Blvd Chandler AZ 85226",
    "addr:housenumber":"4025",
    "addr:postcode":"85226",
    "addr:street":"W Chandler Blvd",
    "iso:country":"US",
    "sg:address":"4025 W Chandler Blvd",
    "sg:city":"Chandler",
    "sg:classifiers":[
        {
            "category":"Insurance",
            "subcategory":"Insurance Agent",
            "type":"Services"
        },
        {
            "category":"Insurance",
            "subcategory":"Hazard Insurance",
            "type":"Services"
        },
        {
            "category":"Insurance",
            "subcategory":"Title Insurance",
            "type":"Services"
        },
        {
            "category":"Insurance",
            "subcategory":"Life Insurance",
            "type":"Services"
        }
    ],
    "sg:phone":"+1 480 413 0715",
    "sg:postcode":"85226",
    "sg:province":"AZ",
    "sg:tags":[
        "business",
        "auto",
        "commercial",
        "homeowner",
        "motorcycle",
        "renter"
    ],
    "wof:name":"Allstate Insurance Company - Darin Nielson",
    "wof:placetype":"venue"
},
  "geometry": {"coordinates":[-111.91166200000001,33.30534],"type":"Point"}
}