{
  "type": "Feature",
  "properties": {
    "iso:country":"US",
    "sg:address":"218 N Central Ave",
    "sg:city":"Avondale",
    "sg:classifiers":[
        {
            "category":"Retail",
            "subcategory":"Funeral Services",
            "type":"Services"
        }
    ],
    "sg:phone":"+1 623 932 4418",
    "sg:postcode":"85323",
    "sg:province":"AZ",
    "sg:tags":[
        "director",
        "cemetery",
        "supply"
    ],
    "wof:name":"Adobe Chapel Funeral Home",
    "wof:placetype":"venue"
},
  "geometry": {"coordinates":[-112.34899900000001,33.437401],"type":"Point"}
}