{
  "type": "Feature",
  "properties": {
    "addr:full":"15652 S 26th Way Phoenix AZ 85048",
    "addr:housenumber":"15652",
    "addr:postcode":"85048",
    "addr:street":"S 26Th Way",
    "iso:country":"US",
    "sg:address":"15652 S 26th Way",
    "sg:city":"Phoenix",
    "sg:classifiers":[
        {
            "category":"Professional",
            "subcategory":"Lawyer & Legal Services",
            "type":"Services"
        }
    ],
    "sg:phone":"+1 480 496 8400",
    "sg:postcode":"85048",
    "sg:province":"AZ",
    "sg:tags":[
        "attorney"
    ],
    "wof:name":"Art Atonna",
    "wof:placetype":"venue"
},
  "geometry": {"coordinates":[-112.02695199999999,33.304487],"type":"Point"}
}