{
  "type": "Feature",
  "properties": {
    "iso:country":"US",
    "sg:address":"2123 S Priest Dr",
    "sg:city":"Tempe",
    "sg:classifiers":[
        {
            "category":"Building & Trades",
            "subcategory":"Electrical",
            "type":"Services"
        }
    ],
    "sg:phone":"+1 602 276 5550",
    "sg:postcode":"85282",
    "sg:province":"AZ",
    "sg:tags":[
        "electric",
        "contractor"
    ],
    "wof:name":"Double DD Electric Co",
    "wof:placetype":"venue"
},
  "geometry": {"coordinates":[-111.96068200000001,33.40379],"type":"Point"}
}