{
  "type": "Feature",
  "properties": {
    "iso:country":"US",
    "sg:address":"568 W Moon Valley Dr",
    "sg:city":"Phoenix",
    "sg:classifiers":[
        {
            "category":"Professional",
            "subcategory":"Engineering",
            "type":"Services"
        }
    ],
    "sg:phone":"+1 602 993 9924",
    "sg:postcode":"85023",
    "sg:province":"AZ",
    "sg:tags":[
        "engineer"
    ],
    "wof:name":"Hustead Engineering",
    "wof:placetype":"venue"
},
  "geometry": {"coordinates":[-112.081211,33.620027],"type":"Point"}
}