{
  "type": "Feature",
  "properties": {
    "iso:country":"US",
    "sg:address":"8445 N 23rd Ave",
    "sg:city":"Phoenix",
    "sg:classifiers":[
        {
            "category":"Professional",
            "type":"Services"
        }
    ],
    "sg:phone":"+1 602 347 8853",
    "sg:postcode":"85021",
    "sg:province":"AZ",
    "wof:name":"Jrt Creations",
    "wof:placetype":"venue"
},
  "geometry": {"coordinates":[-112.108175,33.559864],"type":"Point"}
}