{
  "type": "Feature",
  "properties": {
    "iso:country":"US",
    "sg:address":"16820 N 44th St",
    "sg:city":"Phoenix",
    "sg:classifiers":[
        {
            "category":"Manufacturing",
            "subcategory":"Food",
            "type":"Manufacturing & Wholesale Goods"
        }
    ],
    "sg:phone":"+1 602 765 8855",
    "sg:postcode":"85032",
    "sg:province":"AZ",
    "sg:tags":[
        "drink",
        "soft",
        "mfg"
    ],
    "wof:name":"Royal Crown Stables",
    "wof:placetype":"venue"
},
  "geometry": {"coordinates":[-111.986562,33.638373],"type":"Point"}
}