{
  "type": "Feature",
  "properties": {
    "iso:country":"US",
    "sg:address":"11902 W Adams St",
    "sg:city":"Avondale",
    "sg:classifiers":[
        {
            "category":"Professional",
            "subcategory":"Management & Consulting",
            "type":"Services"
        }
    ],
    "sg:phone":"+1 623 234 1833",
    "sg:postcode":"85323",
    "sg:province":"AZ",
    "sg:tags":[
        "consultant"
    ],
    "wof:name":"Jennifer Schaade",
    "wof:placetype":"venue"
},
  "geometry": {"coordinates":[-112.315087,33.445446],"type":"Point"}
}