{
  "type": "Feature",
  "properties": {
    "addr:full":"3400 S Houghton Rd Tucson AZ 85730",
    "addr:housenumber":"3400",
    "addr:postcode":"85730",
    "addr:street":"S Houghton Rd",
    "iso:country":"US",
    "sg:address":"3400 S Houghton Rd",
    "sg:city":"Tucson",
    "sg:classifiers":[
        {
            "category":"Education",
            "subcategory":"School",
            "type":"Public Place"
        }
    ],
    "sg:phone":"+1 520 731 5300",
    "sg:postcode":"85730",
    "sg:province":"AZ",
    "wof:name":"Secrist Middle School",
    "wof:placetype":"venue"
},
  "geometry": {"coordinates":[-110.77270300000001,32.18255],"type":"Point"}
}