{
  "type": "Feature",
  "properties": {
    "iso:country":"US",
    "sg:address":"2516 E Fairmont Dr",
    "sg:city":"Tempe",
    "sg:classifiers":[
        {
            "category":"Building & Trades",
            "subcategory":"Cleaning & Sanitation",
            "type":"Services"
        }
    ],
    "sg:phone":"+1 480 491 1733",
    "sg:postcode":"85282",
    "sg:province":"AZ",
    "sg:tags":[
        "cleaning-industrial",
        "contractor"
    ],
    "wof:name":"Scour Power",
    "wof:placetype":"venue"
},
  "geometry": {"coordinates":[-111.885274,33.396066],"type":"Point"}
}