{
  "type": "Feature",
  "properties": {
    "iso:country":"US",
    "sg:address":"1630 E Dobbins Rd",
    "sg:city":"Phoenix",
    "sg:classifiers":[
        {
            "category":"Professional",
            "type":"Services"
        }
    ],
    "sg:phone":"+1 602 304 9557",
    "sg:postcode":"85042",
    "sg:province":"AZ",
    "wof:name":"Bulldog Inc",
    "wof:placetype":"venue"
},
  "geometry": {"coordinates":[-112.04753599999999,33.363323],"type":"Point"}
}