{
  "type": "Feature",
  "properties": {
    "iso:country":"US",
    "sg:address":"4116 E Superior Ave",
    "sg:city":"Phoenix",
    "sg:classifiers":[
        {
            "category":"Shopping",
            "type":"Retail Goods"
        }
    ],
    "sg:phone":"+1 602 470 0720",
    "sg:postcode":"85040",
    "sg:province":"AZ",
    "sg:tags":[
        "equipment",
        "pool",
        "swimming"
    ],
    "wof:name":"Apartment Cleaning Supl & Pool",
    "wof:placetype":"venue"
},
  "geometry": {"coordinates":[-111.98902,33.417511],"type":"Point"}
}