{
  "type": "Feature",
  "properties": {
    "iso:country":"US",
    "sg:address":"525 N Central Ave",
    "sg:city":"Avondale",
    "sg:classifiers":[
        {
            "category":"Government",
            "subcategory":"Office",
            "type":"Public Place"
        }
    ],
    "sg:phone":"+1 623 932 2400",
    "sg:postcode":"85323",
    "sg:province":"AZ",
    "sg:tags":[
        "city"
    ],
    "sg:website":"www.avondale.org",
    "wof:name":"Avondale City Hall Adm",
    "wof:placetype":"venue"
},
  "geometry": {"coordinates":[-112.349603,33.440036],"type":"Point"}
}