{
  "type": "Feature",
  "properties": {
    "addr:full":"4305 W Saturn Way Chandler AZ 85226",
    "addr:housenumber":"4305",
    "addr:postcode":"85226",
    "addr:street":"W Saturn Way",
    "iso:country":"US",
    "sg:address":"4305 W Saturn Way",
    "sg:city":"Chandler",
    "sg:classifiers":[
        {
            "category":"Real Estate",
            "subcategory":"Real Estate Agent",
            "type":"Services"
        }
    ],
    "sg:phone":"+1 602 524 8323",
    "sg:postcode":"85226",
    "sg:province":"AZ",
    "sg:tags":[
        "manager"
    ],
    "wof:name":"Peralta One Enterprises LLC",
    "wof:placetype":"venue"
},
  "geometry": {"coordinates":[-111.918706,33.300906],"type":"Point"}
}