{
  "type": "Feature",
  "properties": {
    "addr:full":"1273 S 173rd Dr Goodyear AZ 85338",
    "addr:housenumber":"1273",
    "addr:postcode":"85338",
    "addr:street":"S 173Rd Dr",
    "iso:country":"US",
    "sg:address":"1273 S 173rd Dr",
    "sg:city":"Goodyear",
    "sg:classifiers":[
        {
            "category":"Wholesale",
            "subcategory":"Durable Goods & Equipment",
            "type":"Manufacturing & Wholesale Goods"
        }
    ],
    "sg:phone":"+1 623 215 8365",
    "sg:postcode":"85338",
    "sg:province":"AZ",
    "wof:name":"Action Fire Protection",
    "wof:placetype":"venue"
},
  "geometry": {"coordinates":[-112.43173899999999,33.434793],"type":"Point"}
}