{
  "type": "Feature",
  "properties": {
    "iso:country":"US",
    "sg:address":"3344 N Nevada St",
    "sg:city":"Chandler",
    "sg:classifiers":[
        {
            "category":"Wholesale",
            "subcategory":"Construction Materials",
            "type":"Manufacturing & Wholesale Goods"
        }
    ],
    "sg:phone":"+1 480 545 9494",
    "sg:postcode":"85225",
    "sg:province":"AZ",
    "sg:tags":[
        "stone"
    ],
    "wof:name":"Global Stone Imports Inc",
    "wof:placetype":"venue"
},
  "geometry": {"coordinates":[-111.83434,33.353425],"type":"Point"}
}