{
  "type": "Feature",
  "properties": {
    "iso:country":"US",
    "sg:address":"4901 E 29th St",
    "sg:city":"Tucson",
    "sg:classifiers":[
        {
            "category":"Wholesale",
            "subcategory":"Machinery & Supplies",
            "type":"Manufacturing & Wholesale Goods"
        }
    ],
    "sg:phone":"+1 520 748 2107",
    "sg:postcode":"85711",
    "sg:province":"AZ",
    "sg:tags":[
        "equipment",
        "material",
        "handling"
    ],
    "wof:name":"Tucson Truck & Caster Co",
    "wof:placetype":"venue"
},
  "geometry": {"coordinates":[-110.886985,32.199702],"type":"Point"}
}