{
  "type": "Feature",
  "properties": {
    "addr:full":"1890 W Hwy 89A Sedona AZ 86336",
    "addr:housenumber":"1890",
    "addr:postcode":"86336",
    "addr:street":"W Hwy 89A",
    "iso:country":"US",
    "sg:address":"1890 W Hwy 89A",
    "sg:city":"Sedona",
    "sg:classifiers":[
        {
            "category":"Professional",
            "subcategory":"Research",
            "type":"Services"
        }
    ],
    "sg:phone":"+1 928 282 1298",
    "sg:postcode":"86336",
    "sg:province":"AZ",
    "sg:tags":[
        "foundation",
        "philanthropic"
    ],
    "wof:name":"Ringing Rocks Foundation",
    "wof:placetype":"venue"
},
  "geometry": {"coordinates":[-111.790865,34.86367],"type":"Point"}
}