{
  "type": "Feature",
  "properties": {
    "addr:full":"409 E Watkins St Phoenix AZ 85004",
    "addr:housenumber":"409",
    "addr:postcode":"85004",
    "addr:street":"E Watkins St",
    "iso:country":"US",
    "sg:address":"409 E Watkins St",
    "sg:city":"Phoenix",
    "sg:classifiers":[
        {
            "category":"Wholesale",
            "subcategory":"Hardware",
            "type":"Manufacturing & Wholesale Goods"
        }
    ],
    "sg:phone":"+1 602 244 0717",
    "sg:postcode":"85004",
    "sg:province":"AZ",
    "sg:tags":[
        "purifying",
        "cleaning",
        "air"
    ],
    "wof:name":"Air Cleaning Specialists Inc",
    "wof:placetype":"venue"
},
  "geometry": {"coordinates":[-112.065198,33.425741],"type":"Point"}
}