{
  "type": "Feature",
  "properties": {
    "addr:full":"3101 E Thomas Rd Suite 101 Phoenix AZ 85016",
    "addr:housenumber":"3101",
    "addr:postcode":"85016",
    "addr:street":"E Thomas Rd Suite 101",
    "iso:country":"US",
    "sg:address":"3101 E Thomas Rd Suite 101",
    "sg:city":"Phoenix",
    "sg:classifiers":[
        {
            "category":"Professional",
            "subcategory":"Advertising",
            "type":"Services"
        },
        {
            "category":"Professional",
            "subcategory":"Computer Services",
            "type":"Services"
        }
    ],
    "sg:phone":"+1 602 434 9779",
    "sg:postcode":"85016",
    "sg:province":"AZ",
    "sg:tags":[
        "web",
        "marketing",
        "internet",
        "site",
        "design",
        "online"
    ],
    "sg:website":"http://www.webdesignlatino.com",
    "wof:name":"Web Design Latino",
    "wof:placetype":"venue"
},
  "geometry": {"coordinates":[-112.015083,33.48048],"type":"Point"}
}