{
  "type": "Feature",
  "properties": {
    "iso:country":"US",
    "sg:address":"333 N 16th St",
    "sg:city":"Cottonwood",
    "sg:classifiers":[
        {
            "category":"Real Estate",
            "subcategory":"Real Estate Operator",
            "type":"Services"
        }
    ],
    "sg:phone":"+1 928 634 5308",
    "sg:postcode":"86326",
    "sg:province":"AZ",
    "sg:tags":[
        "building",
        "apartment"
    ],
    "wof:name":"Earl Apartments",
    "wof:placetype":"venue"
},
  "geometry": {"coordinates":[-112.009578,34.742275],"type":"Point"}
}