{
  "type": "Feature",
  "properties": {
    "iso:country":"US",
    "sg:address":"84 Forest View Dr",
    "sg:city":"Sedona",
    "sg:classifiers":[
        {
            "category":"Professional",
            "type":"Services"
        }
    ],
    "sg:phone":"+1 928 204 1042",
    "sg:postcode":"86336",
    "sg:province":"AZ",
    "wof:name":"White Crow Ltd",
    "wof:placetype":"venue"
},
  "geometry": {"coordinates":[-111.759056,34.861079],"type":"Point"}
}