{
  "type": "Feature",
  "properties": {
    "iso:country":"US",
    "sg:address":"600 W Galveston Street",
    "sg:city":"Chandler",
    "sg:classifiers":[
        {
            "category":"Food & Beverages",
            "subcategory":"Groceries & Convenience Stores",
            "type":"Retail Goods"
        }
    ],
    "sg:phone":"+1 480 899 0699",
    "sg:postcode":"85225",
    "sg:province":"AZ",
    "wof:name":"Kwik Mart",
    "wof:placetype":"venue"
},
  "geometry": {"coordinates":[-111.850659,33.313465],"type":"Point"}
}