{
  "type": "Feature",
  "properties": {
    "iso:country":"US",
    "sg:address":"460 N Arroyo Blvd",
    "sg:city":"Nogales",
    "sg:classifiers":[
        {
            "category":"Restaurant",
            "type":"Food & Drink"
        }
    ],
    "sg:phone":"+1 520 287 2392",
    "sg:postcode":"85621",
    "sg:province":"AZ",
    "wof:name":"Los Consentidos",
    "wof:placetype":"venue"
},
  "geometry": {"coordinates":[-110.938571,31.340547],"type":"Point"}
}