{
  "type": "Feature",
  "properties": {
    "addr:full":"4828 N 27th Ave Phoenix AZ 85017",
    "addr:housenumber":"4828",
    "addr:postcode":"85017",
    "addr:street":"N 27Th Ave",
    "iso:country":"US",
    "sg:address":"4828 N 27th Ave",
    "sg:city":"Phoenix",
    "sg:classifiers":[
        {
            "category":"Government",
            "subcategory":"Post Office",
            "type":"Public Place"
        }
    ],
    "sg:phone":"+1 602 249 6411",
    "sg:postcode":"85017",
    "sg:province":"AZ",
    "sg:website":"http://www.usps.com",
    "wof:name":"USPS - United States Post Office",
    "wof:placetype":"venue"
},
  "geometry": {"coordinates":[-112.116989,33.50859],"type":"Point"}
}