{
  "type": "Feature",
  "properties": {
    "iso:country":"US",
    "sg:address":"4408 N 12th St",
    "sg:city":"Phoenix",
    "sg:classifiers":[
        {
            "category":"Personal",
            "type":"Services"
        }
    ],
    "sg:phone":"+1 602 248 0203",
    "sg:postcode":"85014",
    "sg:province":"AZ",
    "sg:tags":[
        "credit",
        "debt",
        "counseling"
    ],
    "wof:name":"First Arizona Credit Svc",
    "wof:placetype":"venue"
},
  "geometry": {"coordinates":[-112.056367,33.501799],"type":"Point"}
}