{
  "type": "Feature",
  "properties": {
    "addr:full":"7422 W Thunderbird Rd Peoria AZ 85381",
    "addr:housenumber":"7422",
    "addr:postcode":"85381",
    "addr:street":"W Thunderbird Rd",
    "iso:country":"US",
    "sg:address":"7422 W Thunderbird Rd",
    "sg:city":"Peoria",
    "sg:classifiers":[
        {
            "category":"Retail",
            "subcategory":"Auto Repair",
            "type":"Services"
        }
    ],
    "sg:phone":"+1 602 308 3080",
    "sg:postcode":"85381",
    "sg:province":"AZ",
    "sg:tags":[
        "repairing",
        "automobile"
    ],
    "sg:website":"http://www.aaa-arizona.com",
    "wof:name":"AAA Auto Repair",
    "wof:placetype":"venue"
},
  "geometry": {"coordinates":[-112.218723,33.610363],"type":"Point"}
}