{
  "type": "Feature",
  "properties": {
    "iso:country":"US",
    "sg:address":"3950 W Adams St",
    "sg:city":"Phoenix",
    "sg:classifiers":[
        {
            "category":"Wholesale",
            "subcategory":"Stationery",
            "type":"Manufacturing & Wholesale Goods"
        }
    ],
    "sg:phone":"+1 602 442 7777",
    "sg:postcode":"85009",
    "sg:province":"AZ",
    "sg:tags":[
        "product",
        "paper"
    ],
    "wof:name":"Greenleaf Paper",
    "wof:placetype":"venue"
},
  "geometry": {"coordinates":[-112.14403,33.449885],"type":"Point"}
}