{
  "type": "Feature",
  "properties": {
    "iso:country":"US",
    "sg:address":"1223 S Cll Alsando",
    "sg:city":"Tucson",
    "sg:classifiers":[
        {
            "category":"Real Estate",
            "subcategory":"Real Estate Agent",
            "type":"Services"
        }
    ],
    "sg:phone":"+1 520 886 3300",
    "sg:postcode":"85710",
    "sg:province":"AZ",
    "sg:tags":[
        "appraiser"
    ],
    "wof:name":"Jay V James & Assoc",
    "wof:placetype":"venue"
},
  "geometry": {"coordinates":[-110.800015,32.205469],"type":"Point"}
}