{
  "type": "Feature",
  "properties": {
    "addr:full":"2001 N 16th St Phoenix AZ 85006",
    "addr:housenumber":"2001",
    "addr:postcode":"85006",
    "addr:street":"N 16Th St",
    "iso:country":"US",
    "sg:address":"2001 N 16th St",
    "sg:city":"Phoenix",
    "sg:classifiers":[
        {
            "category":"Personal",
            "subcategory":"Beauty Salon",
            "type":"Services"
        }
    ],
    "sg:phone":"+1 602 262 2278",
    "sg:postcode":"85006",
    "sg:province":"AZ",
    "wof:name":"Lorena's Beauty Salon",
    "wof:placetype":"venue"
},
  "geometry": {"coordinates":[-112.047684,33.469372],"type":"Point"}
}