{
  "type": "Feature",
  "properties": {
    "iso:country":"US",
    "sg:address":"10617 N 43rd Ave",
    "sg:city":"Phoenix",
    "sg:phone":"+1 602 439 0052",
    "sg:postcode":"85029",
    "sg:province":"AZ",
    "sg:website":"http://www.alterationsinc.com",
    "wof:name":"Alterations Inc",
    "wof:placetype":"venue"
},
  "geometry": {"coordinates":[-112.151539,33.582121],"type":"Point"}
}