{
  "type": "Feature",
  "properties": {
    "iso:country":"US",
    "sg:address":"11430 N 37th Dr",
    "sg:city":"Phoenix",
    "sg:classifiers":[
        {
            "category":"Professional",
            "subcategory":"Computer Services",
            "type":"Services"
        }
    ],
    "sg:phone":"+1 602 300 7831",
    "sg:postcode":"85029",
    "sg:province":"AZ",
    "sg:tags":[
        "consultant",
        "designer",
        "system"
    ],
    "wof:name":"Kevin Geoffrey Services",
    "wof:placetype":"venue"
},
  "geometry": {"coordinates":[-112.139302,33.589685],"type":"Point"}
}