{
  "type": "Feature",
  "properties": {
    "iso:country":"US",
    "sg:address":"4760 N Rio Vista Dr",
    "sg:city":"Tucson",
    "sg:classifiers":[
        {
            "category":"Professional",
            "type":"Services"
        }
    ],
    "sg:phone":"+1 520 885 1932",
    "sg:postcode":"85749",
    "sg:province":"AZ",
    "wof:name":"Baker and Koehler PC",
    "wof:placetype":"venue"
},
  "geometry": {"coordinates":[-110.773108,32.293581],"type":"Point"}
}