{
  "type": "Feature",
  "properties": {
    "iso:country":"US",
    "sg:address":"3826 S 28th St",
    "sg:city":"Phoenix",
    "sg:classifiers":[
        {
            "category":"Wholesale",
            "subcategory":"Electrical",
            "type":"Manufacturing & Wholesale Goods"
        }
    ],
    "sg:phone":"+1 602 841 1922",
    "sg:postcode":"85040",
    "sg:province":"AZ",
    "sg:tags":[
        "alarm",
        "burglar",
        "system"
    ],
    "wof:name":"Alarm Screens By Tony",
    "wof:placetype":"venue"
},
  "geometry": {"coordinates":[-112.021298,33.410893],"type":"Point"}
}