{
  "type": "Feature",
  "properties": {
    "iso:country":"US",
    "sg:address":"11022 N 28th Ave",
    "sg:city":"Phoenix",
    "sg:classifiers":[
        {
            "category":"Banks & Credit Unions",
            "subcategory":"Bank",
            "type":"Services"
        }
    ],
    "sg:phone":"+1 623 875 9714",
    "sg:postcode":"85029",
    "sg:province":"AZ",
    "sg:tags":[
        "loan",
        "mortgage",
        "real estate"
    ],
    "wof:name":"American Mortgage Specialists",
    "wof:placetype":"venue"
},
  "geometry": {"coordinates":[-112.121613,33.58579],"type":"Point"}
}