{
  "type": "Feature",
  "properties": {
    "iso:country":"US",
    "sg:address":"16495 N Scottsdale Rd Ste 5B-2 ",
    "sg:city":"Scottsdale",
    "sg:classifiers":[
        {
            "category":"Restaurant",
            "type":"Food & Drink"
        }
    ],
    "sg:menulink":"http://www.allmenus.com/az/phoenix/284628-flos-asian-kitchen/menu/",
    "sg:phone":"+1 480 609 9888",
    "sg:postcode":"85254",
    "sg:province":"AZ",
    "sg:tags":[
        "asian",
        "chinese"
    ],
    "wof:name":"Flo's Asian Kitchen",
    "wof:placetype":"venue"
},
  "geometry": {"coordinates":[-111.92531099999999,33.635813],"type":"Point"}
}