{
  "type": "Feature",
  "properties": {
    "iso:country":"US",
    "sg:address":"2000 S Davis Cir",
    "sg:city":"Mesa",
    "sg:classifiers":[
        {
            "category":"Building & Trades",
            "subcategory":"Locksmith",
            "type":"Services"
        }
    ],
    "sg:phone":"+1 480 718 2199",
    "sg:postcode":"85210",
    "sg:province":"AZ",
    "sg:tags":[
        "key"
    ],
    "wof:name":"Any 24 Hour Emerg Locksmith",
    "wof:placetype":"venue"
},
  "geometry": {"coordinates":[-111.854024,33.378278],"type":"Point"}
}