{
  "type": "Feature",
  "properties": {
    "addr:full":"49 E 16th Pl Yuma AZ 85364",
    "addr:housenumber":"49",
    "addr:postcode":"85364",
    "addr:street":"E 16Th Pl",
    "iso:country":"US",
    "sg:address":"49 E 16th Pl",
    "sg:city":"Yuma",
    "sg:classifiers":[
        {
            "category":"Manufacturing",
            "subcategory":"Building Materials",
            "type":"Manufacturing & Wholesale Goods"
        }
    ],
    "sg:phone":"+1 928 783 7741",
    "sg:postcode":"85364",
    "sg:province":"AZ",
    "sg:tags":[
        "institutional",
        "mfg",
        "commercial",
        "cabinet"
    ],
    "wof:name":"Kris Kraft Cabinet Co",
    "wof:placetype":"venue"
},
  "geometry": {"coordinates":[-114.618449,32.697665],"type":"Point"}
}