{
  "type": "Feature",
  "properties": {
    "addr:full":"2401 E Baseline Road Gilbert AZ 85234",
    "addr:housenumber":"2401",
    "addr:postcode":"85234",
    "addr:street":"E Baseline Road",
    "iso:country":"US",
    "sg:address":"2401 E Baseline Road",
    "sg:city":"Gilbert",
    "sg:classifiers":[
        {
            "category":"Arena",
            "subcategory":"Sports Club",
            "type":"Entertainment"
        }
    ],
    "sg:phone":"+1 480 892 4240",
    "sg:postcode":"85234",
    "sg:province":"AZ",
    "sg:tags":[
        "martial art"
    ],
    "sg:website":"www.evma.net",
    "wof:name":"East Valley Martial Arts",
    "wof:placetype":"venue"
},
  "geometry": {"coordinates":[-111.779819,33.37893],"type":"Point"}
}