{
  "type": "Feature",
  "properties": {
    "iso:country":"US",
    "sg:address":"11342 E Hash Knife Cir",
    "sg:city":"Tucson",
    "sg:classifiers":[
        {
            "category":"Building & Trades",
            "subcategory":"Construction",
            "type":"Services"
        }
    ],
    "sg:phone":"+1 520 760 1809",
    "sg:postcode":"85749",
    "sg:province":"AZ",
    "sg:tags":[
        "house"
    ],
    "wof:name":"M Maintenance & Repair",
    "wof:placetype":"venue"
},
  "geometry": {"coordinates":[-110.752915,32.275844],"type":"Point"}
}