{
  "type": "Feature",
  "properties": {
    "iso:country":"US",
    "sg:address":"2233 W Dunlap Ave",
    "sg:city":"Phoenix",
    "sg:classifiers":[
        {
            "category":"Education",
            "subcategory":"Special Training",
            "type":"Public Place"
        }
    ],
    "sg:phone":"+1 877 216 7574",
    "sg:postcode":"85021",
    "sg:province":"AZ",
    "sg:tags":[
        "school",
        "instruction",
        "art"
    ],
    "sg:website":"http://local.ingenio.com/Listings/Details.aspx?NUM=a%3a10292047%3a13%3a4859924%3a14%3a0%3a7",
    "wof:name":"The Art Institutes",
    "wof:placetype":"venue"
},
  "geometry": {"coordinates":[-112.106543,33.567533],"type":"Point"}
}