{
  "type": "Feature",
  "properties": {
    "iso:country":"US",
    "sg:address":"4235 E Winslow Ave",
    "sg:city":"Phoenix",
    "sg:classifiers":[
        {
            "category":"Building & Trades",
            "subcategory":"Construction",
            "type":"Services"
        }
    ],
    "sg:phone":"+1 602 437 0092",
    "sg:postcode":"85040",
    "sg:province":"AZ",
    "sg:tags":[
        "contractor"
    ],
    "wof:name":"Schmid Insulation Contractors",
    "wof:placetype":"venue"
},
  "geometry": {"coordinates":[-111.98752899999999,33.421001],"type":"Point"}
}