{
  "type": "Feature",
  "properties": {
    "addr:full":"2002 W Quail Ave Phoenix AZ 85027",
    "addr:housenumber":"2002",
    "addr:postcode":"85027",
    "addr:street":"W Quail Ave",
    "iso:country":"US",
    "sg:address":"2002 W Quail Ave",
    "sg:city":"Phoenix",
    "sg:classifiers":[
        {
            "category":"Manufacturing",
            "subcategory":"Tools & Machinery",
            "type":"Manufacturing & Wholesale Goods"
        }
    ],
    "sg:phone":"+1 623 780 0700",
    "sg:postcode":"85027",
    "sg:province":"AZ",
    "sg:tags":[
        "mfg",
        "medical",
        "molding",
        "related",
        "equipment",
        "injection",
        "pl"
    ],
    "sg:website":"www.icmedical.com",
    "wof:name":"I C Medical Inc",
    "wof:placetype":"venue"
},
  "geometry": {"coordinates":[-112.101088,33.678474],"type":"Point"}
}