{
  "type": "Feature",
  "properties": {
    "iso:country":"US",
    "sg:address":"320 S Plumer Ave",
    "sg:city":"Tucson",
    "sg:classifiers":[
        {
            "category":"Education",
            "subcategory":"Dance Studio",
            "type":"Public Place"
        }
    ],
    "sg:phone":"+1 520 770 1860",
    "sg:postcode":"85719",
    "sg:province":"AZ",
    "sg:tags":[
        "instruction",
        "dancing"
    ],
    "sg:website":"www.tucsoncheeracademy.com",
    "wof:name":"Tucson Cheer Academy",
    "wof:placetype":"venue"
},
  "geometry": {"coordinates":[-110.939525,32.217724],"type":"Point"}
}