{
  "type": "Feature",
  "properties": {
    "addr:full":"2002 E Watkins St Phoenix AZ 85034",
    "addr:housenumber":"2002",
    "addr:postcode":"85034",
    "addr:street":"E Watkins St",
    "iso:country":"US",
    "sg:address":"2002 E Watkins St",
    "sg:city":"Phoenix",
    "sg:classifiers":[
        {
            "category":"Manufacturing",
            "subcategory":"Tools & Machinery",
            "type":"Manufacturing & Wholesale Goods"
        },
        {
            "category":"Manufacturing",
            "subcategory":"Electronics",
            "type":"Manufacturing & Wholesale Goods"
        },
        {
            "category":"Shopping",
            "subcategory":"Computers & Home Electronics",
            "type":"Retail Goods"
        }
    ],
    "sg:phone":"+1 602 759 1105",
    "sg:postcode":"85034",
    "sg:province":"AZ",
    "sg:tags":[
        "electric",
        "consumer",
        "equipment-testing",
        "equipment",
        "supplies-wholesale",
        "manufacturer"
    ],
    "wof:name":"Foresight Technologies",
    "wof:placetype":"venue"
},
  "geometry": {"coordinates":[-112.039067,33.425783],"type":"Point"}
}