{
  "type": "Feature",
  "properties": {
    "iso:country":"US",
    "sg:address":"3729 W McDowell Rd",
    "sg:city":"Phoenix",
    "sg:classifiers":[
        {
            "category":"Autos & Motor Vehicles",
            "subcategory":"Automobile Sales",
            "type":"Retail Goods"
        }
    ],
    "sg:phone":"+1 602 272 1314",
    "sg:postcode":"85009",
    "sg:province":"AZ",
    "sg:tags":[
        "car",
        "used",
        "dealer"
    ],
    "wof:name":"El Compass Auto Sales",
    "wof:placetype":"venue"
},
  "geometry": {"coordinates":[-112.139231,33.465876],"type":"Point"}
}