{
  "type": "Feature",
  "properties": {
    "iso:country":"US",
    "sg:address":"2801 N Central Ave",
    "sg:city":"Phoenix",
    "sg:classifiers":[
        {
            "category":"Bars & Pubs",
            "type":"Food & Drink"
        },
        {
            "category":"Restaurant",
            "type":"Food & Drink"
        }
    ],
    "sg:menulink":"http://www.allmenus.com/az/phoenix/4278-blueline-bar--grill/menu/",
    "sg:phone":"+1 602 230 7222",
    "sg:postcode":"85004",
    "sg:province":"AZ",
    "sg:tags":[
        "american"
    ],
    "wof:name":"Blueline Bar & Grill",
    "wof:placetype":"venue"
},
  "geometry": {"coordinates":[-112.073776,33.47893],"type":"Point"}
}