{
  "type": "Feature",
  "properties": {
    "iso:country":"US",
    "sg:address":"2202 E Flower St",
    "sg:city":"Phoenix",
    "sg:classifiers":[
        {
            "category":"Food & Beverages",
            "subcategory":"Farmers Market",
            "type":"Retail Goods"
        }
    ],
    "sg:phone":"+1 928 200 2736",
    "sg:postcode":"85016",
    "sg:province":"AZ",
    "sg:tags":[
        "vegetable",
        "fruit",
        "shipper",
        "grower"
    ],
    "wof:name":"Voita Gallery",
    "wof:placetype":"venue"
},
  "geometry": {"coordinates":[-112.034509,33.485729],"type":"Point"}
}