{
  "type": "Feature",
  "properties": {
    "addr:full":"2514 N Fontana Ave Tucson AZ 85705",
    "addr:housenumber":"2514",
    "addr:postcode":"85705",
    "addr:street":"N Fontana Ave",
    "iso:country":"US",
    "sg:address":"2514 N Fontana Ave",
    "sg:city":"Tucson",
    "sg:classifiers":[
        {
            "category":"Building & Trades",
            "subcategory":"Construction",
            "type":"Services"
        }
    ],
    "sg:phone":"+1 520 770 1960",
    "sg:postcode":"85705",
    "sg:province":"AZ",
    "sg:tags":[
        "planning",
        "remodeling",
        "kitchen"
    ],
    "wof:name":"Design Associates",
    "wof:placetype":"venue"
},
  "geometry": {"coordinates":[-110.967572,32.253736],"type":"Point"}
}