{
  "type": "Feature",
  "properties": {
    "iso:country":"US",
    "sg:address":"727 W Ray Road",
    "sg:city":"Gilbert",
    "sg:classifiers":[
        {
            "category":"Restaurant",
            "type":"Food & Drink"
        }
    ],
    "sg:phone":"+1 480 812 9555",
    "sg:postcode":"85233",
    "sg:province":"AZ",
    "wof:name":"Domino's Pizza",
    "wof:placetype":"venue"
},
  "geometry": {"coordinates":[-111.805498,33.320772],"type":"Point"}
}