{
  "type": "Feature",
  "properties": {
    "iso:country":"US",
    "sg:address":"559 Wilderness Pt",
    "sg:city":"Prescott",
    "sg:classifiers":[
        {
            "category":"Professional",
            "type":"Services"
        }
    ],
    "sg:phone":"+1 928 776 7145",
    "sg:postcode":"86303",
    "sg:province":"AZ",
    "wof:name":"Mike Treiber",
    "wof:placetype":"venue"
},
  "geometry": {"coordinates":[-112.467058,34.53249],"type":"Point"}
}