{
  "type": "Feature",
  "properties": {
    "iso:country":"US",
    "sg:address":"1490 S Price Rd",
    "sg:city":"Chandler",
    "sg:classifiers":[
        {
            "category":"Health Services",
            "subcategory":"Health Practitioner",
            "type":"Services"
        }
    ],
    "sg:phone":"+1 480 821 6020",
    "sg:postcode":"85286",
    "sg:province":"AZ",
    "sg:tags":[
        "acupuncture"
    ],
    "wof:name":"Accupuncture and Herbal Care",
    "wof:placetype":"venue"
},
  "geometry": {"coordinates":[-111.89125199999999,33.28293],"type":"Point"}
}