{
  "type": "Feature",
  "properties": {
    "iso:country":"US",
    "sg:address":"6721 E Inglewood St",
    "sg:city":"Mesa",
    "sg:classifiers":[
        {
            "category":"Building & Trades",
            "subcategory":"Construction",
            "type":"Services"
        }
    ],
    "sg:phone":"+1 480 464 2563",
    "sg:postcode":"85205",
    "sg:province":"AZ",
    "sg:tags":[
        "contractors-commercial",
        "industrial",
        "electric",
        "contractor"
    ],
    "sg:website":"http://www.arizonahomebuilders.com",
    "wof:name":"Masterpiece Construction",
    "wof:placetype":"venue"
},
  "geometry": {"coordinates":[-111.685852,33.448128],"type":"Point"}
}