{
  "type": "Feature",
  "properties": {
    "iso:country":"US",
    "sg:address":"1735 W Cortez St",
    "sg:city":"Phoenix",
    "sg:classifiers":[
        {
            "category":"Real Estate",
            "subcategory":"Real Estate Operator",
            "type":"Services"
        }
    ],
    "sg:phone":"+1 602 944 3854",
    "sg:postcode":"85029",
    "sg:province":"AZ",
    "sg:tags":[
        "apartment"
    ],
    "wof:name":"Santa Cruz Villas",
    "wof:placetype":"venue"
},
  "geometry": {"coordinates":[-112.095397,33.591107],"type":"Point"}
}