{
  "type": "Feature",
  "properties": {
    "iso:country":"US",
    "sg:address":"28336 N 227th Ave",
    "sg:city":"Wittmann",
    "sg:classifiers":[
        {
            "category":"Real Estate",
            "subcategory":"Real Estate Agent",
            "type":"Services"
        }
    ],
    "sg:phone":"+1 623 877 2031",
    "sg:postcode":"85361",
    "sg:province":"AZ",
    "wof:name":"Realty Executives",
    "wof:placetype":"venue"
},
  "geometry": {"coordinates":[-112.55108,33.739598],"type":"Point"}
}