{
  "type": "Feature",
  "properties": {
    "iso:country":"US",
    "sg:address":"300 W Clarendon Ave Ste 145",
    "sg:city":"Phoenix",
    "sg:phone":"+1 602 248 8962",
    "sg:postcode":"85013",
    "sg:province":"AZ",
    "sg:website":"http://www.bannerhealthaz.com",
    "wof:name":"Trachtenberg Neil MD F",
    "wof:placetype":"venue"
},
  "geometry": {"coordinates":[-112.078178,33.491428],"type":"Point"}
}