{
  "type": "Feature",
  "properties": {
    "addr:full":"800 W Washington St Phoenix AZ 85007",
    "addr:housenumber":"800",
    "addr:postcode":"85007",
    "addr:street":"W Washington St",
    "iso:country":"US",
    "sg:address":"800 W Washington St",
    "sg:city":"Phoenix",
    "sg:classifiers":[
        {
            "category":"Government",
            "subcategory":"Office",
            "type":"Public Place"
        }
    ],
    "sg:phone":"+1 602 542 5141",
    "sg:postcode":"85007",
    "sg:province":"AZ",
    "sg:website":"www.azliquor.gov",
    "wof:name":"Liquor License & Control Dept",
    "wof:placetype":"venue"
},
  "geometry": {"coordinates":[-112.084784,33.448208],"type":"Point"}
}