{
  "type": "Feature",
  "properties": {
    "iso:country":"US",
    "sg:address":"5128 W Olive Ave",
    "sg:city":"Glendale",
    "sg:classifiers":[
        {
            "category":"Shopping",
            "subcategory":"Tobacco",
            "type":"Retail Goods"
        }
    ],
    "sg:phone":"+1 623 931 0576",
    "sg:postcode":"85302",
    "sg:province":"AZ",
    "sg:tags":[
        "cigarette",
        "cigar",
        "dealer"
    ],
    "wof:name":"Smoke Cheap",
    "wof:placetype":"venue"
},
  "geometry": {"coordinates":[-112.170322,33.567581],"type":"Point"}
}