{
  "type": "Feature",
  "properties": {
    "iso:country":"US",
    "sg:address":"1840 S Lewis",
    "sg:city":"Mesa",
    "sg:classifiers":[
        {
            "category":"Government",
            "subcategory":"Police Station",
            "type":"Public Place"
        }
    ],
    "sg:phone":"+1 602 256 0322",
    "sg:postcode":"85210",
    "sg:province":"AZ",
    "sg:tags":[
        "protection"
    ],
    "wof:name":"Sheriffs Office-District 1",
    "wof:placetype":"venue"
},
  "geometry": {"coordinates":[-111.828295,33.381566],"type":"Point"}
}