{
  "type": "Feature",
  "properties": {
    "addr:full":"17141 W Gable End Ln Surprise AZ 85387",
    "addr:housenumber":"17141",
    "addr:postcode":"85387",
    "addr:street":"W Gable End Ln",
    "iso:country":"US",
    "sg:address":"17141 W Gable End Ln",
    "sg:city":"Surprise",
    "sg:classifiers":[
        {
            "category":"Professional",
            "type":"Services"
        }
    ],
    "sg:phone":"+1 623 546 4691",
    "sg:postcode":"85387",
    "sg:province":"AZ",
    "wof:name":"Sig Blowtec North America",
    "wof:placetype":"venue"
},
  "geometry": {"coordinates":[-112.427435,33.656942],"type":"Point"}
}