{
  "type": "Feature",
  "properties": {
    "iso:country":"US",
    "sg:address":"1258 E Bluefield Ave",
    "sg:city":"Phoenix",
    "sg:classifiers":[
        {
            "category":"Retail",
            "subcategory":"Repair Shop",
            "type":"Services"
        }
    ],
    "sg:phone":"+1 602 482 2578",
    "sg:postcode":"85022",
    "sg:province":"AZ",
    "sg:tags":[
        "equipment",
        "electronic",
        "supply"
    ],
    "wof:name":"Duane & Schultz",
    "wof:placetype":"venue"
},
  "geometry": {"coordinates":[-112.056296,33.652674],"type":"Point"}
}