{
  "type": "Feature",
  "properties": {
    "iso:country":"US",
    "sg:address":"7604 W Ocotillo Rd",
    "sg:city":"Glendale",
    "sg:classifiers":[
        {
            "category":"Building & Trades",
            "subcategory":"Construction",
            "type":"Services"
        }
    ],
    "sg:phone":"+1 623 934 4466",
    "sg:postcode":"85303",
    "sg:province":"AZ",
    "sg:tags":[
        "contractor"
    ],
    "wof:name":"Nizhoni Glass & Mirror",
    "wof:placetype":"venue"
},
  "geometry": {"coordinates":[-112.22223099999999,33.535561],"type":"Point"}
}