{
  "type": "Feature",
  "properties": {
    "addr:full":"431 N Litchfield Rd Goodyear AZ 85338",
    "addr:housenumber":"431",
    "addr:postcode":"85338",
    "addr:street":"N Litchfield Rd",
    "iso:country":"US",
    "sg:address":"431 N Litchfield Rd",
    "sg:city":"Goodyear",
    "sg:classifiers":[
        {
            "category":"Shopping",
            "type":"Retail Goods"
        }
    ],
    "sg:phone":"+1 623 875 5036",
    "sg:postcode":"85338",
    "sg:province":"AZ",
    "sg:website":"www.shopterris.com",
    "wof:name":"Terri's Home Store",
    "wof:placetype":"venue"
},
  "geometry": {"coordinates":[-112.358116,33.451729],"type":"Point"}
}