{
  "type": "Feature",
  "properties": {
    "iso:country":"US",
    "sg:address":"9155 E Tanque Verde Rd",
    "sg:city":"Tucson",
    "sg:classifiers":[
        {
            "category":"Personal",
            "type":"Services"
        }
    ],
    "sg:phone":"+1 520 760 1141",
    "sg:postcode":"85749",
    "sg:province":"AZ",
    "sg:tags":[
        "program",
        "physical",
        "exercise",
        "fitness"
    ],
    "wof:name":"Blitz",
    "wof:placetype":"venue"
},
  "geometry": {"coordinates":[-110.797043,32.257608],"type":"Point"}
}