{
  "type": "Feature",
  "properties": {
    "iso:country":"US",
    "sg:address":"610 E Butler Ave",
    "sg:city":"Flagstaff",
    "sg:classifiers":[
        {
            "category":"Freight",
            "type":"Transportation"
        }
    ],
    "sg:phone":"+1 928 779 2922",
    "sg:postcode":"86001",
    "sg:province":"AZ",
    "sg:tags":[
        "operator",
        "trucking"
    ],
    "wof:name":"Lively Shop Crane",
    "wof:placetype":"venue"
},
  "geometry": {"coordinates":[-111.642513,35.192612],"type":"Point"}
}