{
  "type": "Feature",
  "properties": {
    "addr:full":"100 Easy St Carefree AZ 85377",
    "addr:housenumber":"100",
    "addr:postcode":"az 85377",
    "addr:street":"Easy St",
    "iso:country":"US",
    "sg:address":"100 Easy St",
    "sg:city":"Carefree",
    "sg:classifiers":[
        {
            "category":"Government",
            "subcategory":"Post Office",
            "type":"Public Place"
        }
    ],
    "sg:phone":"+1 480 488 3781",
    "sg:postcode":"85377",
    "sg:province":"AZ",
    "sg:website":"http://www.usps.gov",
    "wof:name":"Us Post Office",
    "wof:placetype":"venue"
},
  "geometry": {"coordinates":[-111.92341999999999,33.824881],"type":"Point"}
}