{
  "type": "Feature",
  "properties": {
    "addr:full":"5445 E Speedway Blvd Tucson AZ 85712",
    "addr:housenumber":"5445",
    "addr:postcode":"85712",
    "addr:street":"E Speedway Blvd",
    "iso:country":"US",
    "sg:address":"5445 E Speedway Blvd",
    "sg:city":"Tucson",
    "sg:classifiers":[
        {
            "category":"Restaurant",
            "type":"Food & Drink"
        }
    ],
    "sg:menulink":"http://www.allmenus.com/az/tucson/190685-mcdonalds/menu/",
    "sg:postcode":"85712",
    "sg:province":"AZ",
    "sg:tags":[
        "burger",
        "american"
    ],
    "wof:name":"McDonald's",
    "wof:placetype":"venue"
},
  "geometry": {"coordinates":[-110.87631500000001,32.236456],"type":"Point"}
}