{
  "type": "Feature",
  "properties": {
    "addr:full":"1900 E Apache Blvd Tempe AZ 85281",
    "addr:housenumber":"1900",
    "addr:postcode":"85281",
    "addr:street":"E Apache Blvd",
    "iso:country":"US",
    "sg:address":"1900 E Apache Blvd",
    "sg:city":"Tempe",
    "sg:classifiers":[
        {
            "category":"Travel",
            "subcategory":"Hotels & Motels",
            "type":"Entertainment"
        }
    ],
    "sg:phone":"+1 480 966 2269",
    "sg:postcode":"85281",
    "sg:province":"AZ",
    "sg:tags":[
        "mobile",
        "home",
        "operation",
        "site",
        "operator"
    ],
    "wof:name":"Tradewinds Motel",
    "wof:placetype":"venue"
},
  "geometry": {"coordinates":[-111.90514899999999,33.414775],"type":"Point"}
}