{
  "type": "Feature",
  "properties": {
    "iso:country":"US",
    "sg:address":"19 Howell Ave",
    "sg:city":"Bisbee",
    "sg:classifiers":[
        {
            "category":"Social Services",
            "type":"Services"
        }
    ],
    "sg:phone":"+1 520 432 2285",
    "sg:postcode":"85603",
    "sg:province":"AZ",
    "sg:tags":[
        "organization",
        "welfare"
    ],
    "wof:name":"Catholic Community Svc",
    "wof:placetype":"venue"
},
  "geometry": {"coordinates":[-109.914134,31.442269],"type":"Point"}
}