{
  "type": "Feature",
  "properties": {
    "iso:country":"US",
    "sg:address":"60 Finley Dr",
    "sg:city":"Sedona",
    "sg:classifiers":[
        {
            "category":"Building & Trades",
            "subcategory":"Construction",
            "type":"Services"
        },
        {
            "category":"Home & Garden",
            "subcategory":"Furniture",
            "type":"Retail Goods"
        }
    ],
    "sg:phone":"+1 928 282 4634",
    "sg:postcode":"86336",
    "sg:province":"AZ",
    "sg:tags":[
        "cabinet",
        "carpentry",
        "contractor"
    ],
    "wof:name":"Traditional Craftsman",
    "wof:placetype":"venue"
},
  "geometry": {"coordinates":[-111.79897,34.853334],"type":"Point"}
}