{
  "type": "Feature",
  "properties": {
    "addr:full":"503 S Rockford Dr Tempe AZ 85281",
    "addr:housenumber":"503",
    "addr:postcode":"85281",
    "addr:street":"S Rockford Dr",
    "iso:country":"US",
    "sg:address":"503 S Rockford Dr",
    "sg:city":"Tempe",
    "sg:classifiers":[
        {
            "category":"Manufacturing",
            "subcategory":"Food",
            "type":"Manufacturing & Wholesale Goods"
        }
    ],
    "sg:phone":"+1 480 829 8918",
    "sg:postcode":"85281",
    "sg:province":"AZ",
    "sg:tags":[
        "confectionery",
        "candy"
    ],
    "sg:website":"www.rainbowcottoncandy.com",
    "wof:name":"Rainbow Cotton Candy",
    "wof:placetype":"venue"
},
  "geometry": {"coordinates":[-111.897058,33.424679],"type":"Point"}
}