{
  "type": "Feature",
  "properties": {
    "addr:full":"3012 W Elliot Rd Laveen AZ 85339",
    "addr:housenumber":"3012",
    "addr:postcode":"85339",
    "addr:street":"W Elliot Rd",
    "iso:country":"US",
    "sg:address":"3012 W Elliot Rd",
    "sg:city":"Laveen",
    "sg:classifiers":[
        {
            "category":"Wholesale",
            "subcategory":"Petroleum",
            "type":"Manufacturing & Wholesale Goods"
        }
    ],
    "sg:phone":"+1 602 237 0292",
    "sg:postcode":"85339",
    "sg:province":"AZ",
    "sg:tags":[
        "pipeline",
        "inspection",
        "cleaning"
    ],
    "wof:name":"Pipeline Video Inspection",
    "wof:placetype":"venue"
},
  "geometry": {"coordinates":[-112.124201,33.359338],"type":"Point"}
}