{
  "type": "Feature",
  "properties": {
    "iso:country":"US",
    "sg:address":"221 N Florence St",
    "sg:city":"Casa Grande",
    "sg:classifiers":[
        {
            "category":"Real Estate",
            "subcategory":"Developer",
            "type":"Services"
        }
    ],
    "sg:phone":"+1 520 836 8265",
    "sg:postcode":"85222",
    "sg:province":"AZ",
    "wof:name":"Terminus Development Inc",
    "wof:placetype":"venue"
},
  "geometry": {"coordinates":[-111.753694,32.876974],"type":"Point"}
}