{
  "type": "Feature",
  "properties": {
    "iso:country":"US",
    "sg:address":"2225 W Chandler Blvd",
    "sg:city":"Chandler",
    "sg:classifiers":[
        {
            "category":"Manufacturing",
            "subcategory":"Tools & Machinery",
            "type":"Manufacturing & Wholesale Goods"
        }
    ],
    "sg:phone":"+1 480 917 6000",
    "sg:postcode":"85226",
    "sg:province":"AZ",
    "sg:tags":[
        "equipment",
        "vehicular",
        "lighting"
    ],
    "wof:name":"Rogers Corp",
    "wof:placetype":"venue"
},
  "geometry": {"coordinates":[-111.877489,33.305913],"type":"Point"}
}