{
  "type": "Feature",
  "properties": {
    "addr:full":"2929 N Central Ave Ste 1500 Phoenix AZ 85012",
    "addr:housenumber":"2929",
    "addr:postcode":"85012",
    "addr:street":"N Central Ave Ste 1500",
    "iso:country":"US",
    "sg:address":"2929 N Central Ave Ste 1500",
    "sg:city":"Phoenix",
    "sg:classifiers":[
        {
            "category":"Internet Cafe",
            "subcategory":"None",
            "type":"Food & Drink"
        },
        {
            "category":"Professional",
            "subcategory":"Computer Services",
            "type":"Services"
        }
    ],
    "sg:phone":"+1 602 264 2828",
    "sg:postcode":"85012",
    "sg:province":"AZ",
    "sg:tags":[
        "product",
        "designer",
        "network",
        "consultant",
        "system",
        "design",
        "software"
    ],
    "wof:name":"Neudesic",
    "wof:placetype":"venue"
},
  "geometry": {"coordinates":[-112.07364800000001,33.481316],"type":"Point"}
}