{
  "type": "Feature",
  "properties": {
    "iso:country":"US",
    "sg:address":"6020 W Bethany Home Rd",
    "sg:city":"Glendale",
    "sg:classifiers":[
        {
            "category":"Shopping",
            "subcategory":"Music",
            "type":"Retail Goods"
        }
    ],
    "sg:phone":"+1 623 930 5297",
    "sg:postcode":"85301",
    "sg:province":"AZ",
    "sg:tags":[
        "video",
        "disc",
        "tape",
        "cassette"
    ],
    "wof:name":"Discolandia Paloma",
    "wof:placetype":"venue"
},
  "geometry": {"coordinates":[-112.190445,33.524093],"type":"Point"}
}