{
  "type": "Feature",
  "properties": {
    "iso:country":"US",
    "sg:address":"6049 S 14th Pl",
    "sg:city":"Phoenix",
    "sg:classifiers":[
        {
            "category":"Professional",
            "type":"Services"
        }
    ],
    "sg:phone":"+1 602 232 2060",
    "sg:postcode":"85042",
    "sg:province":"AZ",
    "wof:name":"Jose I Robles",
    "wof:placetype":"venue"
},
  "geometry": {"coordinates":[-112.051087,33.388649],"type":"Point"}
}