{
  "type": "Feature",
  "properties": {
    "iso:country":"US",
    "sg:address":"5125 N 16th St Ste B220",
    "sg:city":"Phoenix",
    "sg:classifiers":[
        {
            "category":"Professional",
            "subcategory":"Accounting & Tax Preparation",
            "type":"Services"
        }
    ],
    "sg:phone":"+1 602 230 8879",
    "sg:postcode":"85016",
    "sg:province":"AZ",
    "sg:tags":[
        "public",
        "accountants-certified"
    ],
    "wof:name":"John R Flynn",
    "wof:placetype":"venue"
},
  "geometry": {"coordinates":[-112.047531,33.511469],"type":"Point"}
}