{
  "type": "Feature",
  "properties": {
    "iso:country":"US",
    "sg:address":"671 Papoose Dr",
    "sg:city":"Lake Havasu City",
    "sg:classifiers":[
        {
            "category":"Building & Trades",
            "subcategory":"Construction",
            "type":"Services"
        }
    ],
    "sg:phone":"+1 928 453 7520",
    "sg:postcode":"86406",
    "sg:province":"AZ",
    "sg:tags":[
        "general",
        "contractor"
    ],
    "wof:name":"Roman Construction Co",
    "wof:placetype":"venue"
},
  "geometry": {"coordinates":[-114.29487899999999,34.462324],"type":"Point"}
}