{
  "type": "Feature",
  "properties": {
    "iso:country":"US",
    "sg:address":"16424 N 44th St",
    "sg:city":"Phoenix",
    "sg:classifiers":[
        {
            "category":"Retail",
            "subcategory":"Laundry & Dry Cleaning",
            "type":"Services"
        }
    ],
    "sg:phone":"+1 602 493 7499",
    "sg:postcode":"85032",
    "sg:province":"AZ",
    "sg:tags":[
        "cleaners",
        "rug",
        "carpet"
    ],
    "wof:name":"Mister Chem-Dry",
    "wof:placetype":"venue"
},
  "geometry": {"coordinates":[-111.98649500000001,33.635023],"type":"Point"}
}