{
  "type": "Feature",
  "properties": {
    "iso:country":"US",
    "sg:address":"5104 E Van Buren St",
    "sg:city":"Phoenix",
    "sg:classifiers":[
        {
            "category":"Organizations",
            "subcategory":"Professional Association",
            "type":"Services"
        }
    ],
    "sg:phone":"+1 512 791 8597",
    "sg:postcode":"85008",
    "sg:province":"AZ",
    "sg:tags":[
        "sale"
    ],
    "wof:name":"Home Products Distributors",
    "wof:placetype":"venue"
},
  "geometry": {"coordinates":[-111.971863,33.450951],"type":"Point"}
}