{
  "type": "Feature",
  "properties": {
    "addr:full":"520 Jordan Rd Sedona AZ 86336",
    "addr:housenumber":"520",
    "addr:postcode":"86336",
    "addr:street":"Jordan Rd",
    "iso:country":"US",
    "sg:address":"520 Jordan Rd",
    "sg:city":"Sedona",
    "sg:classifiers":[
        {
            "category":"Shopping",
            "subcategory":"Computers & Home Electronics",
            "type":"Retail Goods"
        }
    ],
    "sg:phone":"+1 928 204 9267",
    "sg:postcode":"86336",
    "sg:province":"AZ",
    "sg:tags":[
        "high",
        "fidelity",
        "stereophonic"
    ],
    "wof:name":"Artistic Systems",
    "wof:placetype":"venue"
},
  "geometry": {"coordinates":[-111.76102,34.87458],"type":"Point"}
}