{
  "type": "Feature",
  "properties": {
    "addr:full":"6850 N 35th Ave Phoenix AZ 85017",
    "addr:housenumber":"6850",
    "addr:postcode":"85017",
    "addr:street":"N 35Th Ave",
    "iso:country":"US",
    "sg:address":"6850 N 35th Ave",
    "sg:city":"Phoenix",
    "sg:classifiers":[
        {
            "category":"Restaurant",
            "type":"Food & Drink"
        }
    ],
    "sg:menulink":"http://www.allmenus.com/az/phoenix/159831-arbys/menu/",
    "sg:phone":"+1 602 841 8129",
    "sg:postcode":"85017",
    "sg:province":"AZ",
    "sg:tags":[
        "burger",
        "american"
    ],
    "wof:name":"Arby's",
    "wof:placetype":"venue"
},
  "geometry": {"coordinates":[-112.134809,33.537838],"type":"Point"}
}