{
  "type": "Feature",
  "properties": {
    "addr:full":"141 E Cloud Rd Phoenix AZ 85086",
    "addr:housenumber":"141",
    "addr:postcode":"85086",
    "addr:street":"E Cloud Rd",
    "iso:country":"US",
    "sg:address":"141 E Cloud Rd",
    "sg:city":"Phoenix",
    "sg:classifiers":[
        {
            "category":"Professional",
            "subcategory":"Computer Services",
            "type":"Services"
        }
    ],
    "sg:phone":"+1 623 587 1674",
    "sg:postcode":"85086",
    "sg:province":"AZ",
    "sg:tags":[
        "website",
        "design"
    ],
    "sg:website":"www.afniinc.com",
    "wof:name":"Afni Inc",
    "wof:placetype":"venue"
},
  "geometry": {"coordinates":[-112.070488,33.813566],"type":"Point"}
}