{
  "type": "Feature",
  "properties": {
    "iso:country":"US",
    "sg:address":"5215 W Edgemont Ave",
    "sg:city":"Phoenix",
    "sg:classifiers":[
        {
            "category":"Shopping",
            "subcategory":"Hobbies, Toys, & Games",
            "type":"Retail Goods"
        },
        {
            "category":"Recreation",
            "subcategory":"Gun Range",
            "type":"Entertainment"
        }
    ],
    "sg:phone":"+1 602 233 0694",
    "sg:postcode":"85035",
    "sg:province":"AZ",
    "sg:tags":[
        "safety",
        "instruction",
        "marksmanship",
        "gunsmith"
    ],
    "wof:name":"Joe's Gun Shop",
    "wof:placetype":"venue"
},
  "geometry": {"coordinates":[-112.171952,33.479471],"type":"Point"}
}