{
  "type": "Feature",
  "properties": {
    "iso:country":"US",
    "sg:address":"2962 W Clarendon Ave",
    "sg:city":"Phoenix",
    "sg:classifiers":[
        {
            "category":"Wholesale",
            "subcategory":"Electrical",
            "type":"Manufacturing & Wholesale Goods"
        }
    ],
    "sg:phone":"+1 602 222 6600",
    "sg:postcode":"85017",
    "sg:province":"AZ",
    "sg:tags":[
        "light",
        "tube",
        "bulb"
    ],
    "wof:name":"Light Brigade Lighting Co",
    "wof:placetype":"venue"
},
  "geometry": {"coordinates":[-112.122367,33.492311],"type":"Point"}
}