{
  "type": "Feature",
  "properties": {
    "addr:full":"11019 W Peoria Ave Sun City AZ 85351",
    "addr:housenumber":"11019",
    "addr:postcode":"85351",
    "addr:street":"W Peoria Ave",
    "iso:country":"US",
    "sg:address":"11019 W Peoria Ave",
    "sg:city":"Sun City",
    "sg:classifiers":[
        {
            "category":"Organizations",
            "subcategory":"Religious Organization",
            "type":"Services"
        }
    ],
    "sg:phone":"+1 623 933 6600",
    "sg:postcode":"85351",
    "sg:province":"AZ",
    "sg:tags":[
        "church"
    ],
    "wof:name":"First Baptist Church-Sun City",
    "wof:placetype":"venue"
},
  "geometry": {"coordinates":[-112.297021,33.579973],"type":"Point"}
}