{
  "type": "Feature",
  "properties": {
    "iso:country":"US",
    "sg:address":"15508 W Bell Rd Ste 105",
    "sg:city":"Surprise",
    "sg:classifiers":[
        {
            "category":"Health Services",
            "subcategory":"Chiropractor",
            "type":"Services"
        }
    ],
    "sg:phone":"+1 623 556 4772",
    "sg:postcode":"85374",
    "sg:province":"AZ",
    "sg:tags":[
        "chiropractic"
    ],
    "wof:name":"Charles W Enouen Dc",
    "wof:placetype":"venue"
},
  "geometry": {"coordinates":[-112.394107,33.638771],"type":"Point"}
}