{
  "type": "Feature",
  "properties": {
    "iso:country":"US",
    "sg:address":"3460 Grand Ave",
    "sg:city":"Phoenix",
    "sg:classifiers":[
        {
            "category":"Shopping",
            "subcategory":"Used Merchandise",
            "type":"Retail Goods"
        }
    ],
    "sg:phone":"+1 602 230 9443",
    "sg:postcode":"85017",
    "sg:province":"AZ",
    "sg:tags":[
        "pawnbroker"
    ],
    "wof:name":"Maxit Pawn & Retail",
    "wof:placetype":"venue"
},
  "geometry": {"coordinates":[-112.12438899999999,33.486336],"type":"Point"}
}