{
  "type": "Feature",
  "properties": {
    "iso:country":"US",
    "sg:address":"1712 W Prescott Dr",
    "sg:city":"Chandler",
    "sg:classifiers":[
        {
            "category":"Building & Trades",
            "subcategory":"Construction",
            "type":"Services"
        }
    ],
    "sg:phone":"+1 480 507 9060",
    "sg:postcode":"85248",
    "sg:province":"AZ",
    "sg:tags":[
        "concrete",
        "contractor"
    ],
    "wof:name":"Coss-Wilkins Enterprises Inc",
    "wof:placetype":"venue"
},
  "geometry": {"coordinates":[-111.871363,33.239706],"type":"Point"}
}