{
  "type": "Feature",
  "properties": {
    "iso:country":"US",
    "sg:address":"214 W Roosevelt St",
    "sg:city":"Phoenix",
    "sg:classifiers":[
        {
            "category":"Restaurant",
            "type":"Food & Drink"
        }
    ],
    "sg:phone":"+1 602 687 8796",
    "sg:postcode":"85003",
    "sg:province":"AZ",
    "sg:tags":[
        "continental",
        "american"
    ],
    "wof:name":"Centurion",
    "wof:placetype":"venue"
},
  "geometry": {"coordinates":[-112.07684,33.45866],"type":"Point"}
}