{
  "type": "Feature",
  "properties": {
    "iso:country":"US",
    "sg:address":"5136 S Rural Rd",
    "sg:city":"Tempe",
    "sg:classifiers":[
        {
            "category":"Personal",
            "subcategory":"Nail Salon",
            "type":"Services"
        }
    ],
    "sg:phone":"+1 480 756 6768",
    "sg:postcode":"85282",
    "sg:province":"AZ",
    "wof:name":"Ny Nails",
    "wof:placetype":"venue"
},
  "geometry": {"coordinates":[-111.928698,33.378886],"type":"Point"}
}