{
  "type": "Feature",
  "properties": {
    "iso:country":"US",
    "sg:address":"1921 W Hospital Dr",
    "sg:city":"Tucson",
    "sg:classifiers":[
        {
            "category":"Health Services",
            "subcategory":"Doctor",
            "type":"Services"
        }
    ],
    "sg:phone":"+1 520 544 5210",
    "sg:postcode":"85704",
    "sg:province":"AZ",
    "sg:tags":[
        "physician",
        "surgeon"
    ],
    "wof:name":"Jeffrey S Wick MD",
    "wof:placetype":"venue"
},
  "geometry": {"coordinates":[-111.007571,32.319275],"type":"Point"}
}