{
  "type": "Feature",
  "properties": {
    "addr:full":"21630 N 19th Ave Phoenix AZ 85027",
    "addr:housenumber":"21630",
    "addr:postcode":"85027",
    "addr:street":"N 19Th Ave",
    "iso:country":"US",
    "sg:address":"21630 N 19th Ave",
    "sg:city":"Phoenix",
    "sg:classifiers":[
        {
            "category":"Building & Trades",
            "subcategory":"Construction",
            "type":"Services"
        }
    ],
    "sg:phone":"+1 623 780 0285",
    "sg:postcode":"85027",
    "sg:province":"AZ",
    "sg:tags":[
        "handyman"
    ],
    "wof:name":"Mr Handyman",
    "wof:placetype":"venue"
},
  "geometry": {"coordinates":[-112.099861,33.682284],"type":"Point"}
}