{
  "type": "Feature",
  "properties": {
    "iso:country":"US",
    "sg:address":"3308 N Apollo Dr",
    "sg:city":"Chandler",
    "sg:classifiers":[
        {
            "category":"Arts & Performance",
            "subcategory":"Music",
            "type":"Entertainment"
        }
    ],
    "sg:phone":"+1 480 755 8217",
    "sg:postcode":"85224",
    "sg:province":"AZ",
    "sg:tags":[
        "musician"
    ],
    "sg:website":"http://www.reneesaxon.com",
    "wof:name":"Renee Saxon Music",
    "wof:placetype":"venue"
},
  "geometry": {"coordinates":[-111.87208800000001,33.354636],"type":"Point"}
}