{
  "type": "Feature",
  "properties": {
    "iso:country":"US",
    "sg:address":"7119 N 29th Ave",
    "sg:city":"Phoenix",
    "sg:classifiers":[
        {
            "category":"Home & Garden",
            "subcategory":"Building Materials",
            "type":"Retail Goods"
        },
        {
            "category":"Manufacturing",
            "subcategory":"Lumber",
            "type":"Manufacturing & Wholesale Goods"
        }
    ],
    "sg:phone":"+1 602 242 9603",
    "sg:postcode":"85051",
    "sg:province":"AZ",
    "sg:tags":[
        "lumber-wholesale",
        "lumber-used"
    ],
    "wof:name":"Lumber Salesman",
    "wof:placetype":"venue"
},
  "geometry": {"coordinates":[-112.121742,33.541019],"type":"Point"}
}