{
  "type": "Feature",
  "properties": {
    "iso:country":"US",
    "sg:address":"3902 N Brown Ave",
    "sg:city":"Scottsdale",
    "sg:classifiers":[
        {
            "category":"Personal",
            "subcategory":"Beauty Salon",
            "type":"Services"
        }
    ],
    "sg:phone":"+1 480 326 4603",
    "sg:postcode":"85251",
    "sg:province":"AZ",
    "sg:tags":[
        "spa",
        "day"
    ],
    "wof:name":"A Perfect Manicure & Pedicure",
    "wof:placetype":"venue"
},
  "geometry": {"coordinates":[-111.924615,33.493055],"type":"Point"}
}