{
  "type": "Feature",
  "properties": {
    "iso:country":"US",
    "sg:address":"471 E Montebello Ave",
    "sg:city":"Apache Junction",
    "sg:classifiers":[
        {
            "category":"Building & Trades",
            "subcategory":"Landscaping Services",
            "type":"Services"
        }
    ],
    "sg:phone":"+1 480 390 9428",
    "sg:postcode":"85219",
    "sg:province":"AZ",
    "wof:name":"Perez Landscaping",
    "wof:placetype":"venue"
},
  "geometry": {"coordinates":[-111.541052,33.397298],"type":"Point"}
}