{
  "type": "Feature",
  "properties": {
    "iso:country":"US",
    "sg:address":"6854 E Kelton Ln",
    "sg:city":"Scottsdale",
    "sg:classifiers":[
        {
            "category":"Building & Trades",
            "subcategory":"Landscaping Services",
            "type":"Services"
        }
    ],
    "sg:phone":"+1 480 948 4315",
    "sg:postcode":"85254",
    "sg:province":"AZ",
    "sg:tags":[
        "designer",
        "landscape"
    ],
    "wof:name":"L S Animations",
    "wof:placetype":"venue"
},
  "geometry": {"coordinates":[-111.93069300000001,33.637753],"type":"Point"}
}