{
  "type": "Feature",
  "properties": {
    "iso:country":"US",
    "sg:address":"15399 NW Grand Ave",
    "sg:city":"El Mirage",
    "sg:classifiers":[
        {
            "category":"Retail",
            "subcategory":"Funeral Services",
            "type":"Services"
        }
    ],
    "sg:phone":"+1 623 974 2054",
    "sg:postcode":"85335",
    "sg:province":"AZ",
    "sg:tags":[
        "crematory"
    ],
    "wof:name":"Sunwest Funeral Home",
    "wof:placetype":"venue"
},
  "geometry": {"coordinates":[-112.39093699999999,33.669716],"type":"Point"}
}