{
  "type": "Feature",
  "properties": {
    "iso:country":"US",
    "sg:address":"1730 E Warner Rd",
    "sg:city":"Tempe",
    "sg:classifiers":[
        {
            "category":"Professional",
            "subcategory":"Business Services",
            "type":"Services"
        }
    ],
    "sg:phone":"+1 480 926 4414",
    "sg:postcode":"85284",
    "sg:province":"AZ",
    "sg:tags":[
        "interior",
        "consultant",
        "design",
        "decorator"
    ],
    "wof:name":"Newlife Design Studio",
    "wof:placetype":"venue"
},
  "geometry": {"coordinates":[-111.912162,33.334554],"type":"Point"}
}