{
  "type": "Feature",
  "properties": {
    "iso:country":"US",
    "sg:address":"7975 N Hayden Rd",
    "sg:city":"Scottsdale",
    "sg:classifiers":[
        {
            "category":"Banks & Credit Unions",
            "subcategory":"Financial Services",
            "type":"Services"
        }
    ],
    "sg:phone":"+1 480 607 8608",
    "sg:postcode":"85258",
    "sg:province":"AZ",
    "sg:tags":[
        "sharing",
        "profit",
        "annuity",
        "retirement",
        "planning",
        "plan",
        "insurance",
        "pension"
    ],
    "wof:name":"Sapporo Pension Systems",
    "wof:placetype":"venue"
},
  "geometry": {"coordinates":[-111.899102,33.552002],"type":"Point"}
}