{
  "type": "Feature",
  "properties": {
    "addr:full":"2209 W Anklam Rd Tucson AZ 85745",
    "addr:housenumber":"2209",
    "addr:postcode":"85745",
    "addr:street":"W Anklam Rd",
    "iso:country":"US",
    "sg:address":"2209 W Anklam Rd",
    "sg:city":"Tucson",
    "sg:classifiers":[
        {
            "category":"Education",
            "subcategory":"Library",
            "type":"Public Place"
        }
    ],
    "sg:phone":"+1 520 206 6821",
    "sg:postcode":"85745",
    "sg:province":"AZ",
    "wof:name":"Pima Community College Library",
    "wof:placetype":"venue"
},
  "geometry": {"coordinates":[-111.014038,32.224979],"type":"Point"}
}