{
  "type": "Feature",
  "properties": {
    "iso:country":"US",
    "sg:address":"11485 W Civic Center Dr",
    "sg:city":"Avondale",
    "sg:classifiers":[
        {
            "category":"Government",
            "subcategory":"Police Station",
            "type":"Public Place"
        }
    ],
    "sg:phone":"+1 623 333 7001",
    "sg:postcode":"85323",
    "sg:province":"AZ",
    "sg:tags":[
        "department"
    ],
    "wof:name":"Avondale Police Department",
    "wof:placetype":"venue"
},
  "geometry": {"coordinates":[-112.305006,33.443187],"type":"Point"}
}