{
  "type": "Feature",
  "properties": {
    "addr:full":"11485 W Civic Center Dr Avondale AZ 85323",
    "addr:housenumber":"11485",
    "addr:postcode":"85323",
    "addr:street":"W Civic Center Dr",
    "iso:country":"US",
    "sg:address":"11485 W Civic Center Dr",
    "sg:city":"Avondale",
    "sg:classifiers":[
        {
            "category":"Government",
            "subcategory":"Police Station",
            "type":"Public Place"
        }
    ],
    "sg:phone":"+1 623 333 7001",
    "sg:postcode":"85323",
    "sg:province":"AZ",
    "sg:tags":[
        "department"
    ],
    "wof:name":"Avondale Police Department",
    "wof:placetype":"venue"
},
  "geometry": {"coordinates":[-112.30500600000001,33.443187],"type":"Point"}
}