{
  "type": "Feature",
  "properties": {
    "iso:country":"US",
    "sg:address":"2224 W Desert Cove Ave",
    "sg:city":"Phoenix",
    "sg:classifiers":[
        {
            "category":"Building & Trades",
            "subcategory":"Landscaping Services",
            "type":"Services"
        },
        {
            "category":"Building & Trades",
            "subcategory":"Pest Control",
            "type":"Services"
        }
    ],
    "sg:phone":"+1 480 967 4464",
    "sg:postcode":"85029",
    "sg:province":"AZ",
    "sg:tags":[
        "removal",
        "termite",
        "weed",
        "bee"
    ],
    "wof:name":"Burns Pest Elimination",
    "wof:placetype":"venue"
},
  "geometry": {"coordinates":[-112.105629,33.585774],"type":"Point"}
}