{
  "type": "Feature",
  "properties": {
    "iso:country":"US",
    "sg:address":"3030 E Washington St",
    "sg:city":"Phoenix",
    "sg:classifiers":[
        {
            "category":"Building & Trades",
            "subcategory":"Construction",
            "type":"Services"
        }
    ],
    "sg:phone":"+1 602 275 8700",
    "sg:postcode":"85034",
    "sg:province":"AZ",
    "wof:name":"Smart Steel Buildings LLC",
    "wof:placetype":"venue"
},
  "geometry": {"coordinates":[-112.013451,33.448255],"type":"Point"}
}