{
  "type": "Feature",
  "properties": {
    "iso:country":"US",
    "sg:address":"1440 S Country Club Dr",
    "sg:city":"Mesa",
    "sg:classifiers":[
        {
            "category":"Professional",
            "subcategory":"Research",
            "type":"Services"
        },
        {
            "category":"Education",
            "subcategory":"Library",
            "type":"Public Place"
        }
    ],
    "sg:phone":"+1 480 464 2966",
    "sg:postcode":"85210",
    "sg:province":"AZ",
    "wof:name":"Peter D Hart Research",
    "wof:placetype":"venue"
},
  "geometry": {"coordinates":[-111.840103,33.388981],"type":"Point"}
}