{
  "type": "Feature",
  "properties": {
    "iso:country":"US",
    "sg:address":"95 Arroyo Pinon Dr",
    "sg:city":"Sedona",
    "sg:classifiers":[
        {
            "category":"Travel",
            "subcategory":"Hotels & Motels",
            "type":"Entertainment"
        }
    ],
    "sg:phone":"+1 928 282 1414",
    "sg:postcode":"86336",
    "sg:province":"AZ",
    "wof:name":"Sedona Real Inn",
    "wof:placetype":"venue"
},
  "geometry": {"coordinates":[-111.814903,34.85987],"type":"Point"}
}