{
  "type": "Feature",
  "properties": {
    "iso:country":"US",
    "sg:address":"2929 W Yorkshire Dr",
    "sg:city":"Phoenix",
    "sg:classifiers":[
        {
            "category":"Restaurant",
            "type":"Food & Drink"
        }
    ],
    "sg:phone":"+1 602 723 9023",
    "sg:postcode":"85027",
    "sg:province":"AZ",
    "sg:tags":[
        "eating"
    ],
    "wof:name":"Que Gear",
    "wof:placetype":"venue"
},
  "geometry": {"coordinates":[-112.122517,33.662716],"type":"Point"}
}