{
  "type": "Feature",
  "properties": {
    "iso:country":"US",
    "sg:address":"9122 N Cave Creek Rd",
    "sg:city":"Phoenix",
    "sg:classifiers":[
        {
            "category":"Building & Trades",
            "subcategory":"Construction",
            "type":"Services"
        }
    ],
    "sg:phone":"+1 602 765 7772",
    "sg:postcode":"85020",
    "sg:province":"AZ",
    "sg:tags":[
        "concrete",
        "contractor"
    ],
    "wof:name":"Q Diamond Concrete Inc",
    "wof:placetype":"venue"
},
  "geometry": {"coordinates":[-112.062922,33.56966],"type":"Point"}
}