{
  "type": "Feature",
  "properties": {
    "iso:country":"US",
    "sg:address":"2630 E Camelback Rd",
    "sg:city":"Phoenix",
    "sg:classifiers":[
        {
            "category":"Travel",
            "subcategory":"Hotels & Motels",
            "type":"Entertainment"
        }
    ],
    "sg:phone":"+1 602 955 3992",
    "sg:postcode":"85016",
    "sg:province":"AZ",
    "sg:tags":[
        "operation",
        "eating"
    ],
    "wof:name":"Embassy Suites",
    "wof:placetype":"venue"
},
  "geometry": {"coordinates":[-112.022318,33.509741],"type":"Point"}
}