{
  "type": "Feature",
  "properties": {
    "iso:country":"US",
    "sg:address":"6250 S 23rd Ave",
    "sg:city":"Phoenix",
    "sg:classifiers":[
        {
            "category":"Banks & Credit Unions",
            "subcategory":"Investment Brokerage",
            "type":"Services"
        }
    ],
    "sg:phone":"+1 602 751 4367",
    "sg:postcode":"85041",
    "sg:province":"AZ",
    "sg:tags":[
        "trust"
    ],
    "wof:name":"Jain Center Of Greater Phoenix, Inc.",
    "wof:placetype":"venue"
},
  "geometry": {"coordinates":[-112.107713,33.389999],"type":"Point"}
}