{
  "type": "Feature",
  "properties": {
    "iso:country":"US",
    "sg:address":"1523 E Jarvis Ave",
    "sg:city":"Mesa",
    "sg:classifiers":[
        {
            "category":"Building & Trades",
            "subcategory":"Construction",
            "type":"Services"
        }
    ],
    "sg:phone":"+1 480 969 0121",
    "sg:postcode":"85204",
    "sg:province":"AZ",
    "sg:tags":[
        "residential"
    ],
    "wof:name":"Gene England",
    "wof:placetype":"venue"
},
  "geometry": {"coordinates":[-111.79744,33.409794],"type":"Point"}
}