{
  "type": "Feature",
  "properties": {
    "iso:country":"US",
    "sg:address":"2323 W 14th St",
    "sg:city":"Tempe",
    "sg:classifiers":[
        {
            "category":"Education",
            "subcategory":"College",
            "type":"Public Place"
        }
    ],
    "sg:phone":"+1 480 517 8000",
    "sg:postcode":"85281",
    "sg:province":"AZ",
    "sg:tags":[
        "academic",
        "school"
    ],
    "wof:name":"Maricopa Community College",
    "wof:placetype":"venue"
},
  "geometry": {"coordinates":[-111.97605,33.413525],"type":"Point"}
}