{
  "type": "Feature",
  "properties": {
    "iso:country":"US",
    "sg:address":"5350 E Poinsettia Dr",
    "sg:city":"Scottsdale",
    "sg:classifiers":[
        {
            "category":"Professional",
            "subcategory":"Management & Consulting",
            "type":"Services"
        }
    ],
    "sg:phone":"+1 480 607 7877",
    "sg:postcode":"85254",
    "sg:province":"AZ",
    "sg:tags":[
        "counselor",
        "relation",
        "public"
    ],
    "wof:name":"Kaplan Communications",
    "wof:placetype":"venue"
},
  "geometry": {"coordinates":[-111.96607400000001,33.593941],"type":"Point"}
}