{
  "type": "Feature",
  "properties": {
    "addr:full":"508 E Monroe Ave Buckeye AZ 85326",
    "addr:housenumber":"508",
    "addr:postcode":"85326",
    "addr:street":"E Monroe Ave",
    "iso:country":"US",
    "sg:address":"508 E Monroe Ave",
    "sg:city":"Buckeye",
    "sg:classifiers":[
        {
            "category":"Airport",
            "type":"Transportation"
        }
    ],
    "sg:phone":"+1 623 386 4691",
    "sg:postcode":"85326",
    "sg:province":"AZ",
    "sg:tags":[
        "municipal"
    ],
    "wof:name":"Municipal Airport",
    "wof:placetype":"venue"
},
  "geometry": {"coordinates":[-112.583682,33.370566],"type":"Point"}
}