{
  "type": "Feature",
  "properties": {
    "iso:country":"US",
    "sg:address":"2909 N Central Ave",
    "sg:city":"Phoenix",
    "sg:classifiers":[
        {
            "category":"Restaurant",
            "type":"Food & Drink"
        }
    ],
    "sg:menulink":"http://www.allmenus.com/az/phoenix/4409-midtown-grille/menu/",
    "sg:phone":"+1 602 241 0899",
    "sg:postcode":"85012",
    "sg:province":"AZ",
    "sg:tags":[
        "american"
    ],
    "wof:name":"Midtown Grille",
    "wof:placetype":"venue"
},
  "geometry": {"coordinates":[-112.07378,33.480698],"type":"Point"}
}