{
  "type": "Feature",
  "properties": {
    "addr:full":"1959 E 19th St Tucson AZ 85719",
    "addr:housenumber":"1959",
    "addr:postcode":"85719",
    "addr:street":"E 19Th St",
    "iso:country":"US",
    "sg:address":"1959 E 19th St",
    "sg:city":"Tucson",
    "sg:classifiers":[
        {
            "category":"Retail",
            "subcategory":"Repair Shop",
            "type":"Services"
        }
    ],
    "sg:phone":"+1 520 624 2323",
    "sg:postcode":"85719",
    "sg:province":"AZ",
    "sg:tags":[
        "pow",
        "fluid",
        "mfg"
    ],
    "wof:name":"Herco",
    "wof:placetype":"venue"
},
  "geometry": {"coordinates":[-110.942356,32.210636],"type":"Point"}
}