{
  "type": "Feature",
  "properties": {
    "iso:country":"US",
    "sg:address":"3802 W Augusta Ave",
    "sg:city":"Phoenix",
    "sg:classifiers":[
        {
            "category":"Building & Trades",
            "subcategory":"Electrical",
            "type":"Services"
        }
    ],
    "sg:phone":"+1 602 249 5451",
    "sg:postcode":"85051",
    "sg:province":"AZ",
    "sg:tags":[
        "electric",
        "contractor"
    ],
    "wof:name":"Enterprise Electric",
    "wof:placetype":"venue"
},
  "geometry": {"coordinates":[-112.142124,33.551904],"type":"Point"}
}