{
  "type": "Feature",
  "properties": {
    "addr:full":"4601 E Ray Rd Phoenix AZ 85044",
    "addr:housenumber":"4601",
    "addr:postcode":"85044",
    "addr:street":"E Ray Rd",
    "iso:country":"US",
    "sg:address":"4601 E Ray Rd",
    "sg:city":"Phoenix",
    "sg:classifiers":[
        {
            "category":"Personal",
            "subcategory":"Beauty Salon",
            "type":"Services"
        }
    ],
    "sg:phone":"+1 480 961 1769",
    "sg:postcode":"85044",
    "sg:province":"AZ",
    "sg:tags":[
        "manicuring"
    ],
    "wof:name":"Comeley Nails",
    "wof:placetype":"venue"
},
  "geometry": {"coordinates":[-111.98043199999999,33.31984],"type":"Point"}
}