{
  "type": "Feature",
  "properties": {
    "addr:full":"210 W 5th St Tucson AZ 85705",
    "addr:housenumber":"210",
    "addr:postcode":"85705",
    "addr:street":"W 5Th St",
    "iso:country":"US",
    "sg:address":"210 W 5th St",
    "sg:city":"Tucson",
    "sg:classifiers":[
        {
            "category":"Communications",
            "subcategory":"Film & Video Production",
            "type":"Services"
        }
    ],
    "sg:phone":"+1 520 623 3144",
    "sg:postcode":"85705",
    "sg:province":"AZ",
    "sg:tags":[
        "taping"
    ],
    "wof:name":"Misty Production Svc",
    "wof:placetype":"venue"
},
  "geometry": {"coordinates":[-110.975523,32.229061],"type":"Point"}
}