{
  "type": "Feature",
  "properties": {
    "addr:full":"205 N 22nd St Phoenix AZ 85034",
    "addr:housenumber":"205",
    "addr:postcode":"85034",
    "addr:street":"N 22Nd St",
    "iso:country":"US",
    "sg:address":"205 N 22nd St",
    "sg:city":"Phoenix",
    "sg:classifiers":[
        {
            "category":"Autos & Motor Vehicles",
            "subcategory":"Automobile Sales",
            "type":"Retail Goods"
        }
    ],
    "sg:phone":"+1 602 307 9350",
    "sg:postcode":"85034",
    "sg:province":"AZ",
    "sg:tags":[
        "car",
        "dealer"
    ],
    "wof:name":"League Auto Sales",
    "wof:placetype":"venue"
},
  "geometry": {"coordinates":[-112.03450100000001,33.451352],"type":"Point"}
}