{
  "type": "Feature",
  "properties": {
    "iso:country":"US",
    "sg:address":"620 E Nikolaus",
    "sg:city":"Show Low",
    "sg:classifiers":[
        {
            "category":"Building & Trades",
            "subcategory":"Construction",
            "type":"Services"
        }
    ],
    "sg:phone":"+1 928 537 0840",
    "sg:postcode":"85901",
    "sg:province":"AZ",
    "sg:tags":[
        "general",
        "contractor"
    ],
    "wof:name":"Schroder Mill Works",
    "wof:placetype":"venue"
},
  "geometry": {"coordinates":[-110.03586199999999,34.247431],"type":"Point"}
}