{
  "type": "Feature",
  "properties": {
    "iso:country":"US",
    "sg:address":"2812 Sweetwater Ave",
    "sg:city":"Lake Havasu City",
    "sg:classifiers":[
        {
            "category":"Banks & Credit Unions",
            "subcategory":"Bank",
            "type":"Services"
        }
    ],
    "sg:phone":"+1 928 505 5500",
    "sg:postcode":"86406",
    "sg:province":"AZ",
    "sg:tags":[
        "loan",
        "real estate"
    ],
    "wof:name":"Colonial Mortgage & Investment",
    "wof:placetype":"venue"
},
  "geometry": {"coordinates":[-114.293621,34.454799],"type":"Point"}
}