{
  "type": "Feature",
  "properties": {
    "addr:full":"1150 Pinewood Blvd Munds Park AZ 86017",
    "addr:housenumber":"1150",
    "addr:postcode":"86017",
    "addr:street":"Pinewood Blvd",
    "iso:country":"US",
    "sg:address":"1150 Pinewood Blvd",
    "sg:city":"Munds Park",
    "sg:classifiers":[
        {
            "category":"Wholesale",
            "subcategory":"Construction Materials",
            "type":"Manufacturing & Wholesale Goods"
        }
    ],
    "sg:phone":"+1 928 286 2271",
    "sg:postcode":"86017",
    "sg:province":"AZ",
    "wof:name":"Sun Valley Paving Inc",
    "wof:placetype":"venue"
},
  "geometry": {"coordinates":[-111.628866,34.939556],"type":"Point"}
}