{
  "type": "Feature",
  "properties": {
    "iso:country":"US",
    "sg:address":"9451 N Clayton Pl",
    "sg:city":"Marana",
    "sg:classifiers":[
        {
            "category":"Building & Trades",
            "subcategory":"Landscaping Services",
            "type":"Services"
        }
    ],
    "sg:phone":"+1 520 742 3533",
    "sg:postcode":"85653",
    "sg:province":"AZ",
    "sg:tags":[
        "lawn",
        "landscape",
        "maintenance",
        "contractor"
    ],
    "wof:name":"Touch Of Paris",
    "wof:placetype":"venue"
},
  "geometry": {"coordinates":[-111.244511,32.377471],"type":"Point"}
}