{
  "type": "Feature",
  "properties": {
    "iso:country":"US",
    "sg:address":"4920 S Wendler Dr",
    "sg:city":"Tempe",
    "sg:classifiers":[
        {
            "category":"Restaurant",
            "type":"Food & Drink"
        }
    ],
    "sg:menulink":"http://www.allmenus.com/az/phoenix/129043-subway/menu/",
    "sg:phone":"+1 602 426 0100",
    "sg:postcode":"85282",
    "sg:province":"AZ",
    "sg:tags":[
        "american",
        "sandwich"
    ],
    "wof:name":"Subway",
    "wof:placetype":"venue"
},
  "geometry": {"coordinates":[-111.970313,33.38141],"type":"Point"}
}