{
  "type": "Feature",
  "properties": {
    "iso:country":"US",
    "sg:address":"12325 W McDowell Rd",
    "sg:city":"Avondale",
    "sg:classifiers":[
        {
            "category":"Park",
            "type":"Public Place"
        },
        {
            "category":"Restaurant",
            "type":"Food & Drink"
        },
        {
            "category":"Shopping",
            "subcategory":"Pets & Pet Supplies",
            "type":"Retail Goods"
        }
    ],
    "sg:phone":"+1 623 333 1614",
    "sg:postcode":"85392",
    "sg:province":"AZ",
    "sg:tags":[
        "flavor",
        "local"
    ],
    "sg:website":"www.avondale.org/index.aspx?nid=132",
    "wof:name":"Avondale Friendship Park",
    "wof:placetype":"venue"
},
  "geometry": {"coordinates":[-112.31993799999999,33.46399],"type":"Point"}
}