{
  "type": "Feature",
  "properties": {
    "iso:country":"US",
    "sg:address":"3037 W Van Buren St",
    "sg:city":"Phoenix",
    "sg:classifiers":[
        {
            "category":"Restaurant",
            "type":"Food & Drink"
        }
    ],
    "sg:phone":"+1 602 278 3025",
    "sg:postcode":"85009",
    "sg:province":"AZ",
    "sg:tags":[
        "mexican"
    ],
    "wof:name":"Asadero Sinoloa Taco Costilla",
    "wof:placetype":"venue"
},
  "geometry": {"coordinates":[-112.12506500000001,33.451307],"type":"Point"}
}