{
  "type": "Feature",
  "properties": {
    "iso:country":"US",
    "sg:address":"703 W Ray Rd",
    "sg:city":"Phoenix",
    "sg:classifiers":[
        {
            "category":"Retail",
            "subcategory":"Auto Repair",
            "type":"Services"
        }
    ],
    "sg:phone":"+1 480 559 8605",
    "sg:postcode":"85003",
    "sg:province":"AZ",
    "wof:name":"Greulich's Automotive & Collision",
    "wof:placetype":"venue"
},
  "geometry": {"coordinates":[-111.852623,33.320619],"type":"Point"}
}