{
  "type": "Feature",
  "properties": {
    "addr:full":"4013 E University Dr Phoenix AZ 85034",
    "addr:housenumber":"4013",
    "addr:postcode":"85034",
    "addr:street":"E University Dr",
    "iso:country":"US",
    "sg:address":"4013 E University Dr",
    "sg:city":"Phoenix",
    "sg:classifiers":[
        {
            "category":"Wholesale",
            "subcategory":"Motor Vehicles",
            "type":"Manufacturing & Wholesale Goods"
        },
        {
            "category":"Retail",
            "subcategory":"Auto Repair",
            "type":"Services"
        }
    ],
    "sg:phone":"+1 602 437 1903",
    "sg:postcode":"85034",
    "sg:province":"AZ",
    "sg:tags":[
        "repairing",
        "automobile",
        "used"
    ],
    "wof:name":"Corporate Auto & Marine Inc",
    "wof:placetype":"venue"
},
  "geometry": {"coordinates":[-111.991455,33.421825],"type":"Point"}
}