{
  "type": "Feature",
  "properties": {
    "iso:country":"US",
    "sg:address":"506 Riviera Blvd",
    "sg:city":"Bullhead City",
    "sg:classifiers":[
        {
            "category":"Food & Beverages",
            "subcategory":"Groceries & Convenience Stores",
            "type":"Retail Goods"
        },
        {
            "category":"Food & Beverages",
            "subcategory":"Liquor & Beverages",
            "type":"Retail Goods"
        }
    ],
    "sg:phone":"+1 928 758 2501",
    "sg:postcode":"86442",
    "sg:province":"AZ",
    "sg:tags":[
        "packaged"
    ],
    "wof:name":"Bill's Quick Stop",
    "wof:placetype":"venue"
},
  "geometry": {"coordinates":[-114.630247,35.094615],"type":"Point"}
}