{
  "type": "Feature",
  "properties": {
    "iso:country":"US",
    "sg:address":"3929 E Main St",
    "sg:city":"Mesa",
    "sg:classifiers":[
        {
            "category":"Shopping",
            "type":"Retail Goods"
        },
        {
            "category":"Shopping",
            "subcategory":"Computers & Home Electronics",
            "type":"Retail Goods"
        }
    ],
    "sg:phone":"+1 480 832 4524",
    "sg:postcode":"85205",
    "sg:province":"AZ",
    "sg:tags":[
        "equipment",
        "prospecting",
        "metal",
        "locating"
    ],
    "wof:name":"A & B Prospecting & Mining Eqp",
    "wof:placetype":"venue"
},
  "geometry": {"coordinates":[-111.745059,33.415398],"type":"Point"}
}