{
  "type": "Feature",
  "properties": {
    "iso:country":"US",
    "sg:address":"1750 E Glendale Ave",
    "sg:city":"Phoenix",
    "sg:classifiers":[
        {
            "category":"Banks & Credit Unions",
            "subcategory":"Investment Brokerage",
            "type":"Services"
        },
        {
            "category":"Insurance",
            "subcategory":"Hazard Insurance",
            "type":"Services"
        }
    ],
    "sg:phone":"+1 602 277 3300",
    "sg:postcode":"85020",
    "sg:province":"AZ",
    "sg:tags":[
        "agent",
        "resume"
    ],
    "sg:website":"http://www.karnold.com",
    "wof:name":"Arnold & Associates, Inc.",
    "wof:placetype":"venue"
},
  "geometry": {"coordinates":[-112.044257,33.538306],"type":"Point"}
}