{
  "type": "Feature",
  "properties": {
    "addr:full":"5219 W Port au Prince Ln Glendale AZ 85306",
    "addr:housenumber":"5219",
    "addr:postcode":"85306",
    "addr:street":"W Port Au Prince Ln",
    "iso:country":"US",
    "sg:address":"5219 W Port au Prince Ln",
    "sg:city":"Glendale",
    "sg:classifiers":[
        {
            "category":"Building & Trades",
            "subcategory":"Construction",
            "type":"Services"
        }
    ],
    "sg:phone":"+1 602 489 1668",
    "sg:postcode":"85306",
    "sg:province":"AZ",
    "sg:tags":[
        "contractor"
    ],
    "wof:name":"Woodring Construction Co",
    "wof:placetype":"venue"
},
  "geometry": {"coordinates":[-112.173142,33.622387],"type":"Point"}
}