{
  "type": "Feature",
  "properties": {
    "iso:country":"US",
    "sg:address":"333 N Wilmot Rd",
    "sg:city":"Tucson",
    "sg:classifiers":[
        {
            "category":"Shopping",
            "subcategory":"Computers & Home Electronics",
            "type":"Retail Goods"
        }
    ],
    "sg:phone":"+1 520 721 1191",
    "sg:postcode":"85711",
    "sg:province":"AZ",
    "sg:tags":[
        "software"
    ],
    "wof:name":"Sigma Data Systems Inc",
    "wof:placetype":"venue"
},
  "geometry": {"coordinates":[-110.857935,32.22527],"type":"Point"}
}