{
  "type": "Feature",
  "properties": {
    "addr:full":"860 S 21st St Mesa AZ 85204",
    "addr:housenumber":"860",
    "addr:postcode":"85204",
    "addr:street":"S 21St St",
    "iso:country":"US",
    "sg:address":"860 S 21st St",
    "sg:city":"Mesa",
    "sg:classifiers":[
        {
            "category":"Building & Trades",
            "subcategory":"Electrical",
            "type":"Services"
        }
    ],
    "sg:phone":"+1 480 507 8168",
    "sg:postcode":"85204",
    "sg:province":"AZ",
    "sg:tags":[
        "electrical",
        "contractor"
    ],
    "wof:name":"Desert Green Technology",
    "wof:placetype":"venue"
},
  "geometry": {"coordinates":[-111.78597499999999,33.39861],"type":"Point"}
}