{
  "type": "Feature",
  "properties": {
    "iso:country":"US",
    "sg:address":"6650 N Oracle Rd",
    "sg:city":"Tucson",
    "sg:classifiers":[
        {
            "category":"Health Services",
            "subcategory":"Doctor",
            "type":"Services"
        }
    ],
    "sg:phone":"+1 520 797 4154",
    "sg:postcode":"85704",
    "sg:province":"AZ",
    "sg:tags":[
        "physician",
        "surgeon"
    ],
    "wof:name":"Raymond J Schumacher MD",
    "wof:placetype":"venue"
},
  "geometry": {"coordinates":[-110.97575,32.327125],"type":"Point"}
}