{
  "type": "Feature",
  "properties": {
    "iso:country":"US",
    "sg:address":"297 E Warner Road",
    "sg:city":"Chandler",
    "sg:classifiers":[
        {
            "category":"Home & Garden",
            "subcategory":"Home Furnishings",
            "type":"Retail Goods"
        }
    ],
    "sg:phone":"+1 480 899 1179",
    "sg:postcode":"85225",
    "sg:province":"AZ",
    "sg:tags":[
        "decor"
    ],
    "wof:name":"Arizona Storage Inns",
    "wof:placetype":"venue"
},
  "geometry": {"coordinates":[-111.83821500000001,33.335206],"type":"Point"}
}