{
  "type": "Feature",
  "properties": {
    "addr:full":"4907 E Fernwood Ct Cave Creek AZ 85331",
    "addr:housenumber":"4907",
    "addr:postcode":"85331",
    "addr:street":"E Fernwood Ct",
    "iso:country":"US",
    "sg:address":"4907 E Fernwood Ct",
    "sg:city":"Cave Creek",
    "sg:classifiers":[
        {
            "category":"Shopping",
            "subcategory":"Clothing, Apparel, & Fashions",
            "type":"Retail Goods"
        }
    ],
    "sg:phone":"+1 480 515 3833",
    "sg:postcode":"85331",
    "sg:province":"AZ",
    "sg:tags":[
        "family"
    ],
    "wof:name":"Inter Rep Inc",
    "wof:placetype":"venue"
},
  "geometry": {"coordinates":[-111.973795,33.75057],"type":"Point"}
}