{
  "type": "Feature",
  "properties": {
    "addr:full":"809 E Washington St Phoenix AZ 85034",
    "addr:housenumber":"809",
    "addr:postcode":"85034",
    "addr:street":"E Washington St",
    "iso:country":"US",
    "sg:address":"809 E Washington St",
    "sg:city":"Phoenix",
    "sg:classifiers":[
        {
            "category":"Health Services",
            "subcategory":"Doctor",
            "type":"Services"
        },
        {
            "category":"Shopping",
            "subcategory":"Beauty & Cosmetics",
            "type":"Retail Goods"
        }
    ],
    "sg:phone":"+1 602 258 7107",
    "sg:postcode":"85034",
    "sg:province":"AZ",
    "sg:tags":[
        "physician",
        "supply",
        "reconstructive",
        "surgeons",
        "plastic",
        "salons-equipment",
        "surgery",
        "perfume",
        "surgeon"
    ],
    "wof:name":"New Age Cosmetic Plastic",
    "wof:placetype":"venue"
},
  "geometry": {"coordinates":[-112.063256,33.448238],"type":"Point"}
}