{
  "type": "Feature",
  "properties": {
    "iso:country":"US",
    "sg:address":"9180 E Indian Bend Rd",
    "sg:city":"Scottsdale",
    "sg:classifiers":[
        {
            "category":"Education",
            "subcategory":"Special Training",
            "type":"Public Place"
        }
    ],
    "sg:phone":"+1 480 998 8886",
    "sg:postcode":"85250",
    "sg:province":"AZ",
    "sg:tags":[
        "school",
        "instruction",
        "art"
    ],
    "sg:website":"http://www.azbedmart.com/",
    "wof:name":"Sew From The Heart",
    "wof:placetype":"venue"
},
  "geometry": {"coordinates":[-111.883315,33.538452],"type":"Point"}
}