{
  "type": "Feature",
  "properties": {
    "addr:full":"5330 Pla Casa Ri Tucson AZ 85718",
    "addr:postcode":"5330;85718",
    "addr:street":"Pla Casa",
    "iso:country":"US",
    "sg:address":"5330 Pla Casa Ri",
    "sg:city":"Tucson",
    "sg:classifiers":[
        {
            "category":"Professional",
            "type":"Services"
        }
    ],
    "sg:phone":"+1 520 615 7600",
    "sg:postcode":"85718",
    "sg:province":"AZ",
    "sg:tags":[
        "establishment"
    ],
    "wof:name":"Meyers Group",
    "wof:placetype":"venue"
},
  "geometry": {"coordinates":[-110.878113,32.277473],"type":"Point"}
}