{
  "type": "Feature",
  "properties": {
    "iso:country":"US",
    "sg:address":"9325 E Wrightstown Rd",
    "sg:city":"Tucson",
    "sg:classifiers":[
        {
            "category":"Wholesale",
            "subcategory":"Construction Materials",
            "type":"Manufacturing & Wholesale Goods"
        }
    ],
    "sg:phone":"+1 520 298 5010",
    "sg:postcode":"85715",
    "sg:province":"AZ",
    "sg:tags":[
        "building",
        "used",
        "pool",
        "construct",
        "swimming"
    ],
    "wof:name":"Griggs Products Inc",
    "wof:placetype":"venue"
},
  "geometry": {"coordinates":[-110.793861,32.242757],"type":"Point"}
}