{
  "type": "Feature",
  "properties": {
    "iso:country":"US",
    "sg:address":"18925 W Narramore Rd",
    "sg:city":"Buckeye",
    "sg:classifiers":[
        {
            "category":"Autos & Motor Vehicles",
            "subcategory":"Motorcycle Sales",
            "type":"Retail Goods"
        }
    ],
    "sg:phone":"+1 623 386 9933",
    "sg:postcode":"85326",
    "sg:province":"AZ",
    "wof:name":"Lone Cactus Motorsports",
    "wof:placetype":"venue"
},
  "geometry": {"coordinates":[-112.45742199999999,33.333898],"type":"Point"}
}