{
  "type": "Feature",
  "properties": {
    "iso:country":"US",
    "sg:address":"2559 E 7th Ave",
    "sg:city":"Flagstaff",
    "sg:classifiers":[
        {
            "category":"Organizations",
            "subcategory":"Non-profit Organization",
            "type":"Services"
        }
    ],
    "sg:phone":"+1 928 714 0010",
    "sg:postcode":"86004",
    "sg:province":"AZ",
    "sg:tags":[
        "info",
        "addiction",
        "abuse",
        "treatment",
        "drug"
    ],
    "wof:name":"Community Medical Svc",
    "wof:placetype":"venue"
},
  "geometry": {"coordinates":[-111.610356,35.211564],"type":"Point"}
}