{
  "type": "Feature",
  "properties": {
    "iso:country":"US",
    "sg:address":"3029 W Emerald Cir",
    "sg:city":"Tucson",
    "sg:classifiers":[
        {
            "category":"Building & Trades",
            "subcategory":"Construction",
            "type":"Services"
        }
    ],
    "sg:phone":"+1 520 888 2072",
    "sg:postcode":"85705",
    "sg:province":"AZ",
    "sg:tags":[
        "hanging",
        "painter",
        "contractor"
    ],
    "wof:name":"Ken's Painting",
    "wof:placetype":"venue"
},
  "geometry": {"coordinates":[-111.031764,32.300369],"type":"Point"}
}