{
  "type": "Feature",
  "properties": {
    "iso:country":"US",
    "sg:address":"633 N Roosevelt Ave",
    "sg:city":"Chandler",
    "sg:classifiers":[
        {
            "category":"Wholesale",
            "subcategory":"Hardware",
            "type":"Manufacturing & Wholesale Goods"
        }
    ],
    "sg:phone":"+1 480 961 1214",
    "sg:postcode":"85226",
    "sg:province":"AZ",
    "sg:tags":[
        "prevention",
        "flow",
        "back",
        "devices"
    ],
    "wof:name":"Bavco",
    "wof:placetype":"venue"
},
  "geometry": {"coordinates":[-111.94916000000001,33.313306],"type":"Point"}
}