{
  "type": "Feature",
  "properties": {
    "iso:country":"US",
    "sg:address":"15688 N Pima Rd",
    "sg:city":"Scottsdale",
    "sg:classifiers":[
        {
            "category":"Restaurant",
            "type":"Food & Drink"
        }
    ],
    "sg:menulink":"http://www.allmenus.com/az/phoenix/163856-togos-eatery/menu/",
    "sg:phone":"+1 480 596 6522",
    "sg:postcode":"85260",
    "sg:province":"AZ",
    "sg:tags":[
        "wrap",
        "american",
        "sandwich"
    ],
    "wof:name":"Togo's Eatery",
    "wof:placetype":"venue"
},
  "geometry": {"coordinates":[-111.891004,33.62738],"type":"Point"}
}