{
  "type": "Feature",
  "properties": {
    "iso:country":"US",
    "sg:address":"6150 E Main St",
    "sg:city":"Mesa",
    "sg:classifiers":[
        {
            "category":"Retail",
            "subcategory":"Auto Repair",
            "type":"Services"
        }
    ],
    "sg:phone":"+1 480 654 9001",
    "sg:postcode":"85205",
    "sg:province":"AZ",
    "sg:tags":[
        "automobile",
        "lubrication"
    ],
    "sg:website":"http://www.jiffylube.com",
    "wof:name":"Jiffy Lube",
    "wof:placetype":"venue"
},
  "geometry": {"coordinates":[-111.697016,33.41568],"type":"Point"}
}