{
  "type": "Feature",
  "properties": {
    "iso:country":"US",
    "sg:address":"1520 Grand Ave",
    "sg:city":"Phoenix",
    "sg:classifiers":[
        {
            "category":"Autos & Motor Vehicles",
            "subcategory":"Automobile Sales",
            "type":"Retail Goods"
        }
    ],
    "sg:phone":"+1 602 246 9606",
    "sg:postcode":"85007",
    "sg:province":"AZ",
    "sg:tags":[
        "car",
        "dealer"
    ],
    "wof:name":"J C's Auto Sales",
    "wof:placetype":"venue"
},
  "geometry": {"coordinates":[-112.091529,33.458945],"type":"Point"}
}