{
  "type": "Feature",
  "properties": {
    "iso:country":"US",
    "sg:address":"1125 N Delmar",
    "sg:city":"Mesa",
    "sg:classifiers":[
        {
            "category":"Manufacturing",
            "subcategory":"Glass & Minerals",
            "type":"Manufacturing & Wholesale Goods"
        }
    ],
    "sg:phone":"+1 480 325 2684",
    "sg:postcode":"85203",
    "sg:province":"AZ",
    "wof:name":"Elements Music",
    "wof:placetype":"venue"
},
  "geometry": {"coordinates":[-111.801548,33.435703],"type":"Point"}
}