{
  "type": "Feature",
  "properties": {
    "addr:full":"3547 W Northern Ave Phoenix AZ 85051",
    "addr:housenumber":"3547",
    "addr:postcode":"85051",
    "addr:street":"W Northern Ave",
    "iso:country":"US",
    "sg:address":"3547 W Northern Ave",
    "sg:city":"Phoenix",
    "sg:classifiers":[
        {
            "category":"Personal",
            "subcategory":"Beauty Salon",
            "type":"Services"
        }
    ],
    "sg:phone":"+1 602 841 6938",
    "sg:postcode":"85051",
    "sg:province":"AZ",
    "sg:tags":[
        "shop",
        "clothing"
    ],
    "wof:name":"Gloria's Gazebo Salon & Btq",
    "wof:placetype":"venue"
},
  "geometry": {"coordinates":[-112.136312,33.553017],"type":"Point"}
}