{
  "type": "Feature",
  "properties": {
    "addr:full":"6868 N 7th Ave Ste 108 Phoenix AZ 85013",
    "addr:housenumber":"6868",
    "addr:postcode":"85013",
    "addr:street":"N 7Th Ave Ste 108",
    "iso:country":"US",
    "sg:address":"6868 N 7th Ave Ste 108",
    "sg:city":"Phoenix",
    "sg:classifiers":[
        {
            "category":"Insurance",
            "subcategory":"Insurance Agent",
            "type":"Services"
        },
        {
            "category":"Insurance",
            "subcategory":"Hazard Insurance",
            "type":"Services"
        },
        {
            "category":"Insurance",
            "subcategory":"Health Insurance",
            "type":"Services"
        }
    ],
    "sg:phone":"+1 602 938 0440",
    "sg:postcode":"85013",
    "sg:province":"AZ",
    "sg:tags":[
        "business",
        "auto",
        "commercial",
        "benefit",
        "employee"
    ],
    "sg:website":"http://www.farmersagent.com/jhenry",
    "wof:name":"Farmers Insurance Jw Henry",
    "wof:placetype":"venue"
},
  "geometry": {"coordinates":[-112.082454,33.537905],"type":"Point"}
}