{
  "type": "Feature",
  "properties": {
    "addr:full":"11035 N 23rd Dr Phoenix AZ 85029",
    "addr:housenumber":"11035",
    "addr:postcode":"85029",
    "addr:street":"N 23Rd Dr",
    "iso:country":"US",
    "sg:address":"11035 N 23rd Dr",
    "sg:city":"Phoenix",
    "sg:classifiers":[
        {
            "category":"Retail",
            "subcategory":"Auto Repair",
            "type":"Services"
        }
    ],
    "sg:phone":"+1 602 330 4057",
    "sg:postcode":"85029",
    "sg:province":"AZ",
    "sg:tags":[
        "repairing",
        "automobile"
    ],
    "wof:name":"Advanced Lexus Toyota",
    "wof:placetype":"venue"
},
  "geometry": {"coordinates":[-112.109787,33.587802],"type":"Point"}
}