{
  "type": "Feature",
  "properties": {
    "iso:country":"US",
    "sg:address":"634 Schemmer Dr",
    "sg:city":"Prescott",
    "sg:classifiers":[
        {
            "category":"Professional",
            "subcategory":"Management & Consulting",
            "type":"Services"
        }
    ],
    "sg:phone":"+1 928 445 2576",
    "sg:postcode":"86305",
    "sg:province":"AZ",
    "sg:tags":[
        "retail",
        "direct",
        "sales"
    ],
    "wof:name":"Alliant Foodservice",
    "wof:placetype":"venue"
},
  "geometry": {"coordinates":[-112.4781,34.548593],"type":"Point"}
}