{
  "type": "Feature",
  "properties": {
    "addr:full":"1906 E Desert Ln Phoenix AZ 85042",
    "addr:housenumber":"1906",
    "addr:postcode":"85042",
    "addr:street":"E Desert Ln",
    "iso:country":"US",
    "sg:address":"1906 E Desert Ln",
    "sg:city":"Phoenix",
    "sg:classifiers":[
        {
            "category":"Sports & Exercise",
            "subcategory":"Golf",
            "type":"Entertainment"
        }
    ],
    "sg:phone":"+1 602 625 9758",
    "sg:postcode":"85042",
    "sg:province":"AZ",
    "sg:tags":[
        "course"
    ],
    "wof:name":"Discover Golf",
    "wof:placetype":"venue"
},
  "geometry": {"coordinates":[-112.041991,33.372652],"type":"Point"}
}