{
  "type": "Feature",
  "properties": {
    "addr:full":"2617 S 21st St Phoenix AZ 85034",
    "addr:housenumber":"2617",
    "addr:postcode":"85034",
    "addr:street":"S 21St St",
    "iso:country":"US",
    "sg:address":"2617 S 21st St",
    "sg:city":"Phoenix",
    "sg:classifiers":[
        {
            "category":"Professional",
            "subcategory":"Computer Services",
            "type":"Services"
        }
    ],
    "sg:phone":"+1 602 629 0893",
    "sg:postcode":"85034",
    "sg:province":"AZ",
    "wof:name":"ITM Source",
    "wof:placetype":"venue"
},
  "geometry": {"coordinates":[-112.036618,33.422546],"type":"Point"}
}