{
  "type": "Feature",
  "properties": {
    "iso:country":"US",
    "sg:address":"45998 Vicksburg Rd",
    "sg:city":"Salome",
    "sg:classifiers":[
        {
            "category":"Retail",
            "subcategory":"Auto Repair",
            "type":"Services"
        }
    ],
    "sg:phone":"+1 928 859 3779",
    "sg:postcode":"85348",
    "sg:province":"AZ",
    "sg:tags":[
        "wrecker"
    ],
    "wof:name":"Everett Towing",
    "wof:placetype":"venue"
},
  "geometry": {"coordinates":[-113.767285,33.665114],"type":"Point"}
}