{
  "type": "Feature",
  "properties": {
    "iso:country":"US",
    "sg:address":"5050 N 2nd St",
    "sg:city":"Phoenix",
    "sg:classifiers":[
        {
            "category":"Shopping",
            "subcategory":"Used Merchandise",
            "type":"Retail Goods"
        }
    ],
    "sg:phone":"+1 602 265 4673",
    "sg:postcode":"85012",
    "sg:province":"AZ",
    "wof:name":"Millies Antiques",
    "wof:placetype":"venue"
},
  "geometry": {"coordinates":[-112.071201,33.510957],"type":"Point"}
}