{
  "type": "Feature",
  "properties": {
    "iso:country":"US",
    "sg:address":"7302 E Taylor St",
    "sg:city":"Scottsdale",
    "sg:classifiers":[
        {
            "category":"Building & Trades",
            "subcategory":"Plumbing",
            "type":"Services"
        }
    ],
    "sg:phone":"+1 480 663 1674",
    "sg:postcode":"85257",
    "sg:province":"AZ",
    "sg:tags":[
        "plumbing",
        "contractor"
    ],
    "wof:name":"Mc Dowell Mountain Plumbing",
    "wof:placetype":"venue"
},
  "geometry": {"coordinates":[-111.92307,33.45291],"type":"Point"}
}