{
  "type": "Feature",
  "properties": {
    "iso:country":"US",
    "sg:address":"1225 Hancock Rd",
    "sg:city":"Bullhead City",
    "sg:classifiers":[
        {
            "category":"Health Services",
            "subcategory":"Doctor",
            "type":"Services"
        }
    ],
    "sg:phone":"+1 928 763 1200",
    "sg:postcode":"86442",
    "sg:province":"AZ",
    "sg:tags":[
        "physician",
        "surgeon"
    ],
    "wof:name":"Anees Arshad MD",
    "wof:placetype":"venue"
},
  "geometry": {"coordinates":[-114.604845,35.107965],"type":"Point"}
}