{
  "type": "Feature",
  "properties": {
    "iso:country":"US",
    "sg:address":"909 N 1st St",
    "sg:city":"Phoenix",
    "sg:classifiers":[
        {
            "category":"Social Services",
            "subcategory":"Child Care",
            "type":"Services"
        }
    ],
    "sg:phone":"+1 602 252 1953",
    "sg:postcode":"85004",
    "sg:province":"AZ",
    "sg:tags":[
        "kindergarten",
        "academic",
        "school"
    ],
    "wof:name":"Montessori-Reed School",
    "wof:placetype":"venue"
},
  "geometry": {"coordinates":[-112.072455,33.458614],"type":"Point"}
}