{
  "type": "Feature",
  "properties": {
    "iso:country":"US",
    "sg:address":"751 Beachcomber Blvd",
    "sg:city":"Lake Havasu City",
    "sg:classifiers":[
        {
            "category":"Professional",
            "type":"Services"
        }
    ],
    "sg:phone":"+1 928 680 2405",
    "sg:postcode":"86403",
    "sg:province":"AZ",
    "wof:name":"Mrrp Inc",
    "wof:placetype":"venue"
},
  "geometry": {"coordinates":[-114.365688,34.454004],"type":"Point"}
}