{
  "type": "Feature",
  "properties": {
    "iso:country":"US",
    "sg:address":"4516 N 199th Ave",
    "sg:city":"Litchfield Park",
    "sg:classifiers":[
        {
            "category":"Manufacturing",
            "subcategory":"Metals",
            "type":"Manufacturing & Wholesale Goods"
        }
    ],
    "sg:phone":"+1 623 853 1123",
    "sg:postcode":"85340",
    "sg:province":"AZ",
    "sg:tags":[
        "product",
        "cutlery",
        "mfg"
    ],
    "wof:name":"Continental Divide Knife",
    "wof:placetype":"venue"
},
  "geometry": {"coordinates":[-112.48751,33.501116],"type":"Point"}
}