{
  "type": "Feature",
  "properties": {
    "iso:country":"US",
    "sg:address":"3530 N Oracle Rd",
    "sg:city":"Tucson",
    "sg:classifiers":[
        {
            "category":"Shopping",
            "subcategory":"Computers & Home Electronics",
            "type":"Retail Goods"
        }
    ],
    "sg:phone":"+1 520 293 6889",
    "sg:postcode":"85705",
    "sg:province":"AZ",
    "sg:tags":[
        "equipment",
        "dealer",
        "software"
    ],
    "wof:name":"Compusmart",
    "wof:placetype":"venue"
},
  "geometry": {"coordinates":[-110.978006,32.269969],"type":"Point"}
}