{
  "type": "Feature",
  "properties": {
    "iso:country":"US",
    "sg:address":"2050 N Arizona Avenue",
    "sg:city":"Chandler",
    "sg:classifiers":[
        {
            "category":"Shopping",
            "subcategory":"Bicycles & Sporting Goods",
            "type":"Retail Goods"
        }
    ],
    "sg:phone":"+1 480 821 9226",
    "sg:postcode":"85225",
    "sg:province":"AZ",
    "sg:website":"http://www.big5sportinggoods.com",
    "wof:name":"Big 5 Sporting Goods",
    "wof:placetype":"venue"
},
  "geometry": {"coordinates":[-111.841578,33.336419],"type":"Point"}
}