{
  "type": "Feature",
  "properties": {
    "iso:country":"US",
    "sg:address":"3229 W Caravaggio Ln",
    "sg:city":"Phoenix",
    "sg:classifiers":[
        {
            "category":"Professional",
            "subcategory":"Employment Agencies",
            "type":"Services"
        }
    ],
    "sg:phone":"+1 623 516 7997",
    "sg:postcode":"85086",
    "sg:province":"AZ",
    "sg:tags":[
        "bartending"
    ],
    "sg:website":"www.pourmasters.com",
    "wof:name":"Pour Masters Bartending Service",
    "wof:placetype":"venue"
},
  "geometry": {"coordinates":[-112.12965699999999,33.811495],"type":"Point"}
}