{
  "type": "Feature",
  "properties": {
    "addr:full":"14200 N Northsight Blvd Suite 160 Scottsdale AZ 85260",
    "addr:housenumber":"14200",
    "addr:postcode":"85260",
    "addr:street":"N Northsight Blvd Suite 160",
    "iso:country":"US",
    "sg:address":"14200 N Northsight Blvd Suite 160",
    "sg:city":"Scottsdale",
    "sg:classifiers":[
        {
            "category":"Health Services",
            "subcategory":"Health Practitioner",
            "type":"Services"
        }
    ],
    "sg:phone":"+1 480 659 9135",
    "sg:postcode":"85260",
    "sg:province":"AZ",
    "sg:tags":[
        "medicine",
        "alternative"
    ],
    "sg:website":"http://www.sunridgemedical.com/conditions",
    "wof:name":"Sunridge Medical Wellness Centers",
    "wof:placetype":"venue"
},
  "geometry": {"coordinates":[-111.897856,33.615161],"type":"Point"}
}