{
  "type": "Feature",
  "properties": {
    "addr:full":"1603 E Chicago St Chandler AZ 85225",
    "addr:housenumber":"1603",
    "addr:postcode":"85225",
    "addr:street":"E Chicago St",
    "iso:country":"US",
    "sg:address":"1603 E Chicago St",
    "sg:city":"Chandler",
    "sg:classifiers":[
        {
            "category":"Manufacturing",
            "subcategory":"Textiles",
            "type":"Manufacturing & Wholesale Goods"
        }
    ],
    "sg:phone":"+1 480 812 9762",
    "sg:postcode":"85225",
    "sg:province":"AZ",
    "sg:tags":[
        "sewing",
        "contractor"
    ],
    "wof:name":"Quail Trail Designs & Accessories",
    "wof:placetype":"venue"
},
  "geometry": {"coordinates":[-111.814966,33.30043],"type":"Point"}
}