{
  "type": "Feature",
  "properties": {
    "addr:full":"2243 E Rose Garden Loop Phoenix AZ 85024",
    "addr:housenumber":"2243",
    "addr:postcode":"85024",
    "addr:street":"E Rose Garden Loop",
    "iso:country":"US",
    "sg:address":"2243 E Rose Garden Loop",
    "sg:city":"Phoenix",
    "sg:classifiers":[
        {
            "category":"Recreation",
            "type":"Entertainment"
        }
    ],
    "sg:phone":"+1 480 502 9402",
    "sg:postcode":"85024",
    "sg:province":"AZ",
    "sg:tags":[
        "nonscheduled",
        "air"
    ],
    "sg:website":"www.hotairexpeditions.com",
    "wof:name":"Hot Air Expeditions",
    "wof:placetype":"venue"
},
  "geometry": {"coordinates":[-112.034811,33.678053],"type":"Point"}
}