{
  "type": "Feature",
  "properties": {
    "iso:country":"US",
    "sg:address":"710 E Tonto Dr",
    "sg:city":"Chandler",
    "sg:classifiers":[
        {
            "category":"Building & Trades",
            "subcategory":"Construction",
            "type":"Services"
        }
    ],
    "sg:phone":"+1 480 820 1300",
    "sg:postcode":"85249",
    "sg:province":"AZ",
    "sg:tags":[
        "steel"
    ],
    "wof:name":"Drafters",
    "wof:placetype":"venue"
},
  "geometry": {"coordinates":[-111.83076,33.241003],"type":"Point"}
}