{
  "type": "Feature",
  "properties": {
    "iso:country":"US",
    "sg:address":"6615 W Parkside Ln",
    "sg:city":"Glendale",
    "sg:classifiers":[
        {
            "category":"Building & Trades",
            "subcategory":"Plumbing",
            "type":"Services"
        }
    ],
    "sg:phone":"+1 623 561 6815",
    "sg:postcode":"85310",
    "sg:province":"AZ",
    "sg:tags":[
        "mechanical",
        "contractor"
    ],
    "wof:name":"Sun West Mechanical",
    "wof:placetype":"venue"
},
  "geometry": {"coordinates":[-112.203052,33.695896],"type":"Point"}
}