{
  "type": "Feature",
  "properties": {
    "iso:country":"US",
    "sg:address":"106 S 54th St",
    "sg:city":"Chandler",
    "sg:classifiers":[
        {
            "category":"Manufacturing",
            "subcategory":"Retail Goods",
            "type":"Manufacturing & Wholesale Goods"
        }
    ],
    "sg:phone":"+1 480 893 1244",
    "sg:postcode":"85226",
    "sg:province":"AZ",
    "sg:tags":[
        "handbags-wholesale",
        "manufacturer"
    ],
    "sg:website":"http://www.bowman-group.com",
    "wof:name":"Bag Habit Inc",
    "wof:placetype":"venue"
},
  "geometry": {"coordinates":[-111.967584,33.302365],"type":"Point"}
}