{
  "type": "Feature",
  "properties": {
    "iso:country":"US",
    "sg:address":"515 E Carefree Hwy",
    "sg:city":"Phoenix",
    "sg:classifiers":[
        {
            "category":"Shopping",
            "subcategory":"Crafts & Fabrics",
            "type":"Retail Goods"
        }
    ],
    "sg:phone":"+1 623 587 4831",
    "sg:postcode":"85085",
    "sg:province":"AZ",
    "sg:tags":[
        "scrapbooking"
    ],
    "wof:name":"Memories Be Scrapped By K",
    "wof:placetype":"venue"
},
  "geometry": {"coordinates":[-112.06736,33.799019],"type":"Point"}
}