{
  "type": "Feature",
  "properties": {
    "addr:full":"3131 W Durango St Phoenix AZ 85009",
    "addr:housenumber":"3131",
    "addr:postcode":"85009",
    "addr:street":"W Durango St",
    "iso:country":"US",
    "sg:address":"3131 W Durango St",
    "sg:city":"Phoenix",
    "sg:classifiers":[
        {
            "category":"Government",
            "subcategory":"Office",
            "type":"Public Place"
        }
    ],
    "sg:phone":"+1 602 506 4598",
    "sg:postcode":"85009",
    "sg:province":"AZ",
    "sg:tags":[
        "parish",
        "government-county"
    ],
    "sg:website":"http://www.phxses.com",
    "wof:name":"Juvenile Court Center",
    "wof:placetype":"venue"
},
  "geometry": {"coordinates":[-112.127241,33.429689],"type":"Point"}
}