{
  "type": "Feature",
  "properties": {
    "iso:country":"US",
    "sg:address":"7650 S McClintock Dr",
    "sg:city":"Tempe",
    "sg:classifiers":[
        {
            "category":"Manufacturing",
            "subcategory":"Chemicals & Compounds",
            "type":"Manufacturing & Wholesale Goods"
        }
    ],
    "sg:phone":"+1 480 897 0551",
    "sg:postcode":"85284",
    "sg:province":"AZ",
    "sg:tags":[
        "preparation",
        "toilet",
        "mfg"
    ],
    "wof:name":"Covalence",
    "wof:placetype":"venue"
},
  "geometry": {"coordinates":[-111.911252,33.346807],"type":"Point"}
}