{
  "type": "Feature",
  "properties": {
    "iso:country":"US",
    "sg:address":"459 N Gilbert Rd",
    "sg:city":"Gilbert",
    "sg:classifiers":[
        {
            "category":"Restaurant",
            "type":"Food & Drink"
        }
    ],
    "sg:phone":"+1 480 926 3681",
    "sg:postcode":"85234",
    "sg:province":"AZ",
    "wof:name":"Ole'",
    "wof:placetype":"venue"
},
  "geometry": {"coordinates":[-111.78964999999999,33.358195],"type":"Point"}
}