{
  "type": "Feature",
  "properties": {
    "iso:country":"US",
    "sg:address":"5037 W Ray Rd",
    "sg:city":"Chandler",
    "sg:classifiers":[
        {
            "category":"Wholesale",
            "subcategory":"Home Furnishings",
            "type":"Manufacturing & Wholesale Goods"
        }
    ],
    "sg:phone":"+1 480 753 2585",
    "sg:postcode":"85224",
    "sg:province":"AZ",
    "wof:name":"World of Rugs",
    "wof:placetype":"venue"
},
  "geometry": {"coordinates":[-111.929644,33.31993],"type":"Point"}
}