{
  "type": "Feature",
  "properties": {
    "iso:country":"US",
    "sg:address":"1430 N 27th Ave",
    "sg:city":"Phoenix",
    "sg:classifiers":[
        {
            "category":"Wholesale",
            "subcategory":"Machinery & Supplies",
            "type":"Manufacturing & Wholesale Goods"
        }
    ],
    "sg:phone":"+1 602 272 9211",
    "sg:postcode":"85009",
    "sg:province":"AZ",
    "sg:tags":[
        "equipment",
        "tool",
        "industrial"
    ],
    "wof:name":"Superior Tool & Repair Inc",
    "wof:placetype":"venue"
},
  "geometry": {"coordinates":[-112.117215,33.46564],"type":"Point"}
}