{
  "type": "Feature",
  "properties": {
    "iso:country":"US",
    "sg:address":"894 E Warner Rd",
    "sg:city":"Gilbert",
    "sg:classifiers":[
        {
            "category":"Cafe",
            "type":"Food & Drink"
        }
    ],
    "sg:menulink":"http://www.allmenus.com/az/phoenix/31354-euro-pizza-cafe/menu/",
    "sg:phone":"+1 480 507 3763",
    "sg:postcode":"85296",
    "sg:province":"AZ",
    "sg:tags":[
        "american",
        "pizza"
    ],
    "wof:name":"Euro Pizza Cafe",
    "wof:placetype":"venue"
},
  "geometry": {"coordinates":[-111.770906,33.336929],"type":"Point"}
}