{
  "type": "Feature",
  "properties": {
    "iso:country":"US",
    "sg:address":"115 E Goodwin St",
    "sg:city":"Prescott",
    "sg:classifiers":[
        {
            "category":"Real Estate",
            "subcategory":"Surveying",
            "type":"Services"
        }
    ],
    "sg:phone":"+1 928 778 5101",
    "sg:postcode":"86303",
    "sg:province":"AZ",
    "sg:tags":[
        "surveyor"
    ],
    "wof:name":"M Haywood Assoc Inc",
    "wof:placetype":"venue"
},
  "geometry": {"coordinates":[-112.468585,34.539872],"type":"Point"}
}