{
  "type": "Feature",
  "properties": {
    "addr:full":"771 Lake Havasu Ave N Lake Havasu City AZ 86403",
    "addr:housenumber":"771",
    "addr:postcode":"86403",
    "addr:street":"Lake Havasu Ave N",
    "iso:country":"US",
    "sg:address":"771 Lake Havasu Ave N",
    "sg:city":"Lake Havasu City",
    "sg:classifiers":[
        {
            "category":"Autos & Motor Vehicles",
            "subcategory":"Boat Sales",
            "type":"Retail Goods"
        },
        {
            "category":"Manufacturing",
            "subcategory":"Apparel",
            "type":"Manufacturing & Wholesale Goods"
        }
    ],
    "sg:phone":"+1 928 453 8222",
    "sg:postcode":"86403",
    "sg:province":"AZ",
    "sg:tags":[
        "product",
        "canvas",
        "related"
    ],
    "wof:name":"Cover ME Custom",
    "wof:placetype":"venue"
},
  "geometry": {"coordinates":[-114.34800300000001,34.499088],"type":"Point"}
}