{
  "type": "Feature",
  "properties": {
    "iso:country":"US",
    "sg:address":"6750 W Bell Rd",
    "sg:city":"Glendale",
    "sg:classifiers":[
        {
            "category":"Home & Garden",
            "subcategory":"Building Materials",
            "type":"Retail Goods"
        }
    ],
    "sg:phone":"+1 623 432 0929",
    "sg:postcode":"85308",
    "sg:province":"AZ",
    "sg:tags":[
        "repair",
        "brake",
        "automotive"
    ],
    "sg:website":"http://www.sundevilauto.com",
    "wof:name":"Sun Devil Auto",
    "wof:placetype":"venue"
},
  "geometry": {"coordinates":[-112.20357300000001,33.638348],"type":"Point"}
}