{
  "type": "Feature",
  "properties": {
    "iso:country":"US",
    "sg:address":"758 S Watson Rd",
    "sg:city":"Buckeye",
    "sg:classifiers":[
        {
            "category":"Fast Food",
            "type":"Food & Drink"
        },
        {
            "category":"Restaurant",
            "type":"Food & Drink"
        }
    ],
    "sg:phone":"+1 623 386 1037",
    "sg:postcode":"85326",
    "sg:province":"AZ",
    "sg:tags":[
        "chicken",
        "mexican",
        "take"
    ],
    "sg:website":"http://www.elpolloloco.com",
    "wof:name":"El Pollo Loco",
    "wof:placetype":"venue"
},
  "geometry": {"coordinates":[-112.55647999999999,33.440195],"type":"Point"}
}