{
  "type": "Feature",
  "properties": {
    "iso:country":"US",
    "sg:address":"3069 Peaks View Ln",
    "sg:city":"Prescott",
    "sg:classifiers":[
        {
            "category":"Building & Trades",
            "subcategory":"Construction",
            "type":"Services"
        }
    ],
    "sg:phone":"+1 928 771 9774",
    "sg:postcode":"86301",
    "sg:province":"AZ",
    "sg:tags":[
        "contractor"
    ],
    "wof:name":"Specialty Tile & Stone Inc",
    "wof:placetype":"venue"
},
  "geometry": {"coordinates":[-112.463164,34.590699],"type":"Point"}
}