{
  "type": "Feature",
  "properties": {
    "iso:country":"US",
    "sg:address":"13835 N Tatum Blvd 9440",
    "sg:city":"Phoenix",
    "sg:classifiers":[
        {
            "category":"Real Estate",
            "subcategory":"Real Estate Services",
            "type":"Services"
        },
        {
            "category":"Professional",
            "subcategory":"Business Services",
            "type":"Services"
        },
        {
            "category":"Real Estate",
            "subcategory":"Surveying",
            "type":"Services"
        }
    ],
    "sg:phone":"+1 602 795 8458",
    "sg:postcode":"85032",
    "sg:province":"AZ",
    "sg:tags":[
        "appraisers-business",
        "industrial",
        "appraisers-commercial",
        "commercial",
        "appraiser"
    ],
    "sg:website":"http://www.ticeappraisal.com",
    "wof:name":"Tice Appraisal",
    "wof:placetype":"venue"
},
  "geometry": {"coordinates":[-111.977798,33.612851],"type":"Point"}
}