{
  "type": "Feature",
  "properties": {
    "iso:country":"US",
    "sg:address":"3152 North 34th Drive, Ste. A",
    "sg:city":"Phoenix",
    "sg:classifiers":[
        {
            "category":"Health Services",
            "subcategory":"Doctor",
            "type":"Services"
        }
    ],
    "sg:phone":"+1 623 326 5260",
    "sg:postcode":"85017",
    "sg:province":"AZ",
    "sg:tags":[
        "waste",
        "disposal-medical"
    ],
    "sg:website":"http://www.ecotechmedicalwaste.com",
    "wof:name":"Ecotech Medical Waste Disposal",
    "wof:placetype":"venue"
},
  "geometry": {"coordinates":[-112.132406,33.485443],"type":"Point"}
}