{
  "type": "Feature",
  "properties": {
    "addr:full":"3512 S Central Ave Phoenix AZ 85040",
    "addr:housenumber":"3512",
    "addr:postcode":"85040",
    "addr:street":"S Central Ave",
    "iso:country":"US",
    "sg:address":"3512 S Central Ave",
    "sg:city":"Phoenix",
    "sg:classifiers":[
        {
            "category":"Restaurant",
            "type":"Food & Drink"
        }
    ],
    "sg:phone":"+1 602 276 8754",
    "sg:postcode":"85040",
    "sg:province":"AZ",
    "sg:tags":[
        "eating"
    ],
    "wof:name":"Benjamins Ice Cream",
    "wof:placetype":"venue"
},
  "geometry": {"coordinates":[-112.073487,33.414109],"type":"Point"}
}