{
  "type": "Feature",
  "properties": {
    "addr:full":"725 W Irvington Rd Tucson AZ 85714",
    "addr:housenumber":"725",
    "addr:postcode":"85714",
    "addr:street":"W Irvington Rd",
    "iso:country":"US",
    "sg:address":"725 W Irvington Rd",
    "sg:city":"Tucson",
    "sg:classifiers":[
        {
            "category":"Real Estate",
            "subcategory":"Real Estate Agent",
            "type":"Services"
        }
    ],
    "sg:phone":"+1 520 889 9613",
    "sg:postcode":"85714",
    "sg:province":"AZ",
    "wof:name":"LA Hacienda Real Estate",
    "wof:placetype":"venue"
},
  "geometry": {"coordinates":[-110.979231,32.163138],"type":"Point"}
}