{
  "type": "Feature",
  "properties": {
    "iso:country":"US",
    "sg:address":"111 S 34th St",
    "sg:city":"Phoenix",
    "sg:classifiers":[
        {
            "category":"Restaurant",
            "type":"Food & Drink"
        }
    ],
    "sg:phone":"+1 602 231 4280",
    "sg:postcode":"85034",
    "sg:province":"AZ",
    "sg:tags":[
        "eating"
    ],
    "wof:name":"Compass One LLC",
    "wof:placetype":"venue"
},
  "geometry": {"coordinates":[-112.00733,33.446252],"type":"Point"}
}