{
  "type": "Feature",
  "properties": {
    "iso:country":"US",
    "sg:address":"2702 N 44th St Ste 210A",
    "sg:city":"Phoenix",
    "sg:classifiers":[
        {
            "category":"Real Estate",
            "subcategory":"Real Estate Services",
            "type":"Services"
        },
        {
            "category":"Professional",
            "subcategory":"Research",
            "type":"Services"
        },
        {
            "category":"Insurance",
            "subcategory":"Hazard Insurance",
            "type":"Services"
        },
        {
            "category":"Insurance",
            "subcategory":"Title Insurance",
            "type":"Services"
        }
    ],
    "sg:phone":"+1 602 294 3200",
    "sg:postcode":"85008",
    "sg:province":"AZ",
    "sg:tags":[
        "abstracter",
        "mortgage"
    ],
    "sg:website":"http://www.natic.com",
    "wof:name":"North American Title Company, Inc.",
    "wof:placetype":"venue"
},
  "geometry": {"coordinates":[-111.987117,33.47744],"type":"Point"}
}