{
  "type": "Feature",
  "properties": {
    "iso:country":"US",
    "sg:address":"637 N 3rd Ave",
    "sg:city":"Phoenix",
    "sg:classifiers":[
        {
            "category":"Professional",
            "subcategory":"Lawyer & Legal Services",
            "type":"Services"
        }
    ],
    "sg:phone":"+1 602 253 9450",
    "sg:postcode":"85003",
    "sg:province":"AZ",
    "sg:tags":[
        "attorney"
    ],
    "wof:name":"Kenneth P Bemis",
    "wof:placetype":"venue"
},
  "geometry": {"coordinates":[-112.07762099999999,33.455983],"type":"Point"}
}