{
  "type": "Feature",
  "properties": {
    "iso:country":"US",
    "sg:address":"845 Kiowa Ave",
    "sg:city":"Lake Havasu City",
    "sg:classifiers":[
        {
            "category":"Home & Garden",
            "subcategory":"Building Materials",
            "type":"Retail Goods"
        },
        {
            "category":"Building & Trades",
            "subcategory":"Construction",
            "type":"Services"
        }
    ],
    "sg:phone":"+1 928 680 7848",
    "sg:postcode":"86403",
    "sg:province":"AZ",
    "sg:tags":[
        "glass",
        "window",
        "contractor",
        "plate"
    ],
    "wof:name":"Havasu Glass & Mirror Inc",
    "wof:placetype":"venue"
},
  "geometry": {"coordinates":[-114.35592800000001,34.498562],"type":"Point"}
}