{
  "type": "Feature",
  "properties": {
    "addr:full":"8260 W Indian School Road Phoenix AZ 85033",
    "addr:housenumber":"8260",
    "addr:postcode":"85033",
    "addr:street":"W Indian School Road",
    "iso:country":"US",
    "sg:address":"8260 W Indian School Road",
    "sg:city":"Phoenix",
    "sg:classifiers":[
        {
            "category":"Health Services",
            "subcategory":"Doctor",
            "type":"Services"
        }
    ],
    "sg:phone":"+1 623 247 2300",
    "sg:postcode":"85033",
    "sg:province":"AZ",
    "sg:tags":[
        "practice",
        "family"
    ],
    "wof:name":"B -Healthy Medical",
    "wof:placetype":"venue"
},
  "geometry": {"coordinates":[-112.236589,33.494318],"type":"Point"}
}