{
  "type": "Feature",
  "properties": {
    "iso:country":"US",
    "sg:address":"266 E Pastime Rd",
    "sg:city":"Tucson",
    "sg:classifiers":[
        {
            "category":"Education",
            "subcategory":"School",
            "type":"Public Place"
        }
    ],
    "sg:phone":"+1 520 696 6420",
    "sg:postcode":"85705",
    "sg:province":"AZ",
    "sg:website":"www.amphi.com",
    "wof:name":"Rillito Center",
    "wof:placetype":"venue"
},
  "geometry": {"coordinates":[-110.966596,32.275596],"type":"Point"}
}