{
  "type": "Feature",
  "properties": {
    "addr:full":"7941 W Dreyfus Dr Peoria AZ 85381",
    "addr:housenumber":"7941",
    "addr:postcode":"85381",
    "addr:street":"W Dreyfus Dr",
    "iso:country":"US",
    "sg:address":"7941 W Dreyfus Dr",
    "sg:city":"Peoria",
    "sg:classifiers":[
        {
            "category":"Freight",
            "type":"Transportation"
        }
    ],
    "sg:phone":"+1 623 979 1790",
    "sg:postcode":"85381",
    "sg:province":"AZ",
    "sg:tags":[
        "arrangement"
    ],
    "wof:name":"Roadway Package System",
    "wof:placetype":"venue"
},
  "geometry": {"coordinates":[-112.23052800000001,33.60364],"type":"Point"}
}