{
  "type": "Feature",
  "properties": {
    "iso:country":"US",
    "sg:address":"17150 N 134th Dr",
    "sg:city":"Surprise",
    "sg:classifiers":[
        {
            "category":"Building & Trades",
            "subcategory":"Construction",
            "type":"Services"
        }
    ],
    "sg:phone":"+1 623 556 8650",
    "sg:postcode":"85374",
    "sg:province":"AZ",
    "sg:tags":[
        "home",
        "builder"
    ],
    "wof:name":"Pulte Homes Corp",
    "wof:placetype":"venue"
},
  "geometry": {"coordinates":[-112.347566,33.640699],"type":"Point"}
}