{
  "type": "Feature",
  "properties": {
    "iso:country":"US",
    "sg:address":"1329 W Laguna Azul Ave",
    "sg:city":"Mesa",
    "sg:classifiers":[
        {
            "category":"Manufacturing",
            "subcategory":"Glass & Minerals",
            "type":"Manufacturing & Wholesale Goods"
        }
    ],
    "sg:phone":"+1 480 730 8706",
    "sg:postcode":"85202",
    "sg:province":"AZ",
    "sg:tags":[
        "mining"
    ],
    "wof:name":"Sbmc Santa Barbara Mining Comp",
    "wof:placetype":"venue"
},
  "geometry": {"coordinates":[-111.864724,33.372292],"type":"Point"}
}