{
  "type": "Feature",
  "properties": {
    "addr:full":"9247 E Wolfberry St Tucson AZ 85747",
    "addr:housenumber":"9247",
    "addr:postcode":"85747",
    "addr:street":"E Wolfberry St",
    "iso:country":"US",
    "sg:address":"9247 E Wolfberry St",
    "sg:city":"Tucson",
    "sg:classifiers":[
        {
            "category":"Professional",
            "type":"Services"
        }
    ],
    "sg:phone":"+1 520 663 1946",
    "sg:postcode":"85747",
    "sg:province":"AZ",
    "wof:name":"Patrick Besser",
    "wof:placetype":"venue"
},
  "geometry": {"coordinates":[-110.795708,32.113765],"type":"Point"}
}