{
  "type": "Feature",
  "properties": {
    "iso:country":"US",
    "sg:address":"402 W Hatcher Rd",
    "sg:city":"Phoenix",
    "sg:classifiers":[
        {
            "category":"Professional",
            "type":"Services"
        }
    ],
    "sg:phone":"+1 602 861 9471",
    "sg:postcode":"85021",
    "sg:province":"AZ",
    "sg:tags":[
        "establishment"
    ],
    "wof:name":"Plex",
    "wof:placetype":"venue"
},
  "geometry": {"coordinates":[-112.080674,33.571348],"type":"Point"}
}