{
  "type": "Feature",
  "properties": {
    "iso:country":"US",
    "sg:address":"2020 W Ruthrauff Rd",
    "sg:city":"Tucson",
    "sg:classifiers":[
        {
            "category":"Retail",
            "subcategory":"Auto Repair",
            "type":"Services"
        }
    ],
    "sg:phone":"+1 520 293 6472",
    "sg:postcode":"85705",
    "sg:province":"AZ",
    "sg:tags":[
        "repairing",
        "automobile"
    ],
    "wof:name":"Reliable Auto Care Enterprise",
    "wof:placetype":"venue"
},
  "geometry": {"coordinates":[-111.011647,32.294419],"type":"Point"}
}