{
  "type": "Feature",
  "properties": {
    "iso:country":"US",
    "sg:address":"8410 W Rockwood Dr",
    "sg:city":"Peoria",
    "sg:classifiers":[
        {
            "category":"Professional",
            "type":"Services"
        }
    ],
    "sg:phone":"+1 623 215 8088",
    "sg:postcode":"85382",
    "sg:province":"AZ",
    "wof:name":"Ron Marquardt",
    "wof:placetype":"venue"
},
  "geometry": {"coordinates":[-112.240179,33.654993],"type":"Point"}
}