{
  "type": "Feature",
  "properties": {
    "addr:full":"1920 S Dobson Rd Mesa AZ 85202",
    "addr:housenumber":"1920",
    "addr:postcode":"85202",
    "addr:street":"S Dobson Rd",
    "iso:country":"US",
    "sg:address":"1920 S Dobson Rd",
    "sg:city":"Mesa",
    "sg:classifiers":[
        {
            "category":"Restaurant",
            "type":"Food & Drink"
        }
    ],
    "sg:phone":"+1 480 820 0237",
    "sg:postcode":"85202",
    "sg:province":"AZ",
    "sg:tags":[
        "mexican"
    ],
    "sg:website":"www.macayo.com/",
    "wof:name":"Macayo's Mexican Restaurant",
    "wof:placetype":"venue"
},
  "geometry": {"coordinates":[-111.87751900000001,33.379761],"type":"Point"}
}