{
  "type": "Feature",
  "properties": {
    "iso:country":"US",
    "sg:address":"2229 E Mcdowell Rd",
    "sg:city":"Phoenix",
    "sg:classifiers":[
        {
            "category":"Health Services",
            "subcategory":"Dentist",
            "type":"Services"
        }
    ],
    "sg:phone":"+1 866 415 7890",
    "sg:postcode":"85006",
    "sg:province":"AZ",
    "sg:tags":[
        "clinic",
        "dental",
        "dentists-cosmetic",
        "dentistry"
    ],
    "sg:website":"http://www.abledental.com",
    "wof:name":"Able Dental Care",
    "wof:placetype":"venue"
},
  "geometry": {"coordinates":[-112.033568,33.465778],"type":"Point"}
}