{
  "type": "Feature",
  "properties": {
    "addr:full":"2408 E Apache Blvd Tempe AZ 85281",
    "addr:housenumber":"2408",
    "addr:postcode":"85281",
    "addr:street":"E Apache Blvd",
    "iso:country":"US",
    "sg:address":"2408 E Apache Blvd",
    "sg:city":"Tempe",
    "sg:classifiers":[
        {
            "category":"Utilities",
            "subcategory":"Natural Gas",
            "type":"Services"
        }
    ],
    "sg:phone":"+1 480 966 1442",
    "sg:postcode":"85281",
    "sg:province":"AZ",
    "wof:name":"Arizona Lcky Star Trnsmissions",
    "wof:placetype":"venue"
},
  "geometry": {"coordinates":[-111.88761599999999,33.414876],"type":"Point"}
}