{
  "type": "Feature",
  "properties": {
    "addr:full":"530 E Thomas Rd Phoenix AZ 85012",
    "addr:housenumber":"530",
    "addr:postcode":"85012",
    "addr:street":"E Thomas Rd",
    "iso:country":"US",
    "sg:address":"530 E Thomas Rd",
    "sg:city":"Phoenix",
    "sg:classifiers":[
        {
            "category":"Health Services",
            "subcategory":"Doctor",
            "type":"Services"
        }
    ],
    "sg:phone":"+1 602 351 2229",
    "sg:postcode":"85012",
    "sg:province":"AZ",
    "sg:tags":[
        "physician",
        "surgeon"
    ],
    "wof:name":"Bruce A Culbertson MD",
    "wof:placetype":"venue"
},
  "geometry": {"coordinates":[-112.065348,33.480284],"type":"Point"}
}