{
  "type": "Feature",
  "properties": {
    "iso:country":"US",
    "sg:address":"3426 E Monte Vista Dr",
    "sg:city":"Tucson",
    "sg:classifiers":[
        {
            "category":"Real Estate",
            "subcategory":"Architect",
            "type":"Services"
        }
    ],
    "sg:phone":"+1 520 325 8447",
    "sg:postcode":"85716",
    "sg:province":"AZ",
    "wof:name":"Fridlind Group Inc",
    "wof:placetype":"venue"
},
  "geometry": {"coordinates":[-110.918936,32.259498],"type":"Point"}
}