{
  "type": "Feature",
  "properties": {
    "addr:full":"2608 N Stone Ave Tucson AZ 85705",
    "addr:housenumber":"2608",
    "addr:postcode":"85705",
    "addr:street":"N Stone Ave",
    "iso:country":"US",
    "sg:address":"2608 N Stone Ave",
    "sg:city":"Tucson",
    "sg:classifiers":[
        {
            "category":"Real Estate",
            "subcategory":"Real Estate Services",
            "type":"Services"
        }
    ],
    "sg:phone":"+1 520 393 3286",
    "sg:postcode":"85705",
    "sg:province":"AZ",
    "sg:tags":[
        "company",
        "title"
    ],
    "wof:name":"B & A Title Svc",
    "wof:placetype":"venue"
},
  "geometry": {"coordinates":[-110.97189,32.255642],"type":"Point"}
}