{
  "type": "Feature",
  "properties": {
    "iso:country":"US",
    "sg:address":"1950 E University Dr # 104",
    "sg:city":"Mesa",
    "sg:classifiers":[
        {
            "category":"Shopping",
            "subcategory":"Optical Goods",
            "type":"Retail Goods"
        },
        {
            "category":"Health Services",
            "subcategory":"Optometrist",
            "type":"Services"
        },
        {
            "category":"Health Services",
            "subcategory":"Health Practitioner",
            "type":"Services"
        }
    ],
    "sg:phone":"+1 480 844 7097",
    "sg:postcode":"85203",
    "sg:province":"AZ",
    "sg:tags":[
        "eyeglass",
        "ophthalmology",
        "surgeons",
        "physician"
    ],
    "sg:website":"http://www.nationwidevision.com",
    "wof:name":"Nationwide Vision Ctr",
    "wof:placetype":"venue"
},
  "geometry": {"coordinates":[-111.790898,33.422609],"type":"Point"}
}