{
  "type": "Feature",
  "properties": {
    "iso:country":"US",
    "sg:address":"3906 E Grant Rd",
    "sg:city":"Tucson",
    "sg:classifiers":[
        {
            "category":"Shopping",
            "subcategory":"Department Store",
            "type":"Retail Goods"
        }
    ],
    "sg:phone":"+1 520 325 8050",
    "sg:postcode":"85712",
    "sg:province":"AZ",
    "wof:name":"99 Cent Discount Store",
    "wof:placetype":"venue"
},
  "geometry": {"coordinates":[-110.90722700000001,32.250555],"type":"Point"}
}