{
  "type": "Feature",
  "properties": {
    "iso:country":"US",
    "sg:address":"8450 Koch Field Rd",
    "sg:city":"Flagstaff",
    "sg:classifiers":[
        {
            "category":"Shopping",
            "type":"Retail Goods"
        }
    ],
    "sg:phone":"+1 928 526 1067",
    "sg:postcode":"86004",
    "sg:province":"AZ",
    "sg:tags":[
        "merchandise"
    ],
    "wof:name":"Ask For Pets Inc",
    "wof:placetype":"venue"
},
  "geometry": {"coordinates":[-111.52476799999999,35.261365],"type":"Point"}
}