{
  "type": "Feature",
  "properties": {
    "iso:country":"US",
    "sg:address":"12202 S 45th St",
    "sg:city":"Phoenix",
    "sg:classifiers":[
        {
            "category":"Government",
            "subcategory":"Fire Station",
            "type":"Public Place"
        }
    ],
    "sg:phone":"+1 480 496 6864",
    "sg:postcode":"85044",
    "sg:province":"AZ",
    "sg:tags":[
        "protection"
    ],
    "wof:name":"Greg Hoffman Fire Support Svc",
    "wof:placetype":"venue"
},
  "geometry": {"coordinates":[-111.987307,33.336167],"type":"Point"}
}