{
  "type": "Feature",
  "properties": {
    "addr:full":"4751 E Amberwood Dr Phoenix AZ 85048",
    "addr:housenumber":"4751",
    "addr:postcode":"85048",
    "addr:street":"E Amberwood Dr",
    "iso:country":"US",
    "sg:address":"4751 E Amberwood Dr",
    "sg:city":"Phoenix",
    "sg:classifiers":[
        {
            "category":"Wholesale",
            "subcategory":"Electrical",
            "type":"Manufacturing & Wholesale Goods"
        }
    ],
    "sg:phone":"+1 480 704 9385",
    "sg:postcode":"85048",
    "sg:province":"AZ",
    "sg:tags":[
        "equipment",
        "station",
        "radio"
    ],
    "wof:name":"Spacewise-Broadcast Furniture",
    "wof:placetype":"venue"
},
  "geometry": {"coordinates":[-111.98143,33.299506],"type":"Point"}
}