{
  "type": "Feature",
  "properties": {
    "addr:full":"3834 E Roeser Rd Phoenix AZ 85040",
    "addr:housenumber":"3834",
    "addr:postcode":"85040",
    "addr:street":"E Roeser Rd",
    "iso:country":"US",
    "sg:address":"3834 E Roeser Rd",
    "sg:city":"Phoenix",
    "sg:classifiers":[
        {
            "category":"Freight",
            "type":"Transportation"
        }
    ],
    "sg:phone":"+1 602 276 1909",
    "sg:postcode":"85040",
    "sg:province":"AZ",
    "sg:tags":[
        "operator",
        "local",
        "trucking"
    ],
    "wof:name":"Lynch Furniture Handlers Inc",
    "wof:placetype":"venue"
},
  "geometry": {"coordinates":[-111.995715,33.399904],"type":"Point"}
}