{
  "type": "Feature",
  "properties": {
    "addr:full":"56 W Weldon Ave Phoenix AZ 85013",
    "addr:housenumber":"56",
    "addr:postcode":"85013",
    "addr:street":"W Weldon Ave",
    "iso:country":"US",
    "sg:address":"56 W Weldon Ave",
    "sg:city":"Phoenix",
    "sg:classifiers":[
        {
            "category":"Parking",
            "type":"Transportation"
        },
        {
            "category":"Parking",
            "subcategory":"Garage",
            "type":"Transportation"
        }
    ],
    "sg:phone":"+1 602 274 1216",
    "sg:postcode":"85013",
    "sg:province":"AZ",
    "sg:tags":[
        "attendant",
        "lot"
    ],
    "sg:website":"http://www.aceparking.com",
    "wof:name":"Parking Booth",
    "wof:placetype":"venue"
},
  "geometry": {"coordinates":[-112.07462,33.490766],"type":"Point"}
}