{
  "type": "Feature",
  "properties": {
    "addr:full":"800 E University Blvd Tucson AZ 85719",
    "addr:housenumber":"800",
    "addr:postcode":"85719",
    "addr:street":"E University Blvd",
    "iso:country":"US",
    "sg:address":"800 E University Blvd",
    "sg:city":"Tucson",
    "sg:classifiers":[
        {
            "category":"Health Services",
            "subcategory":"Chiropractor",
            "type":"Services"
        }
    ],
    "sg:phone":"+1 520 622 3886",
    "sg:postcode":"85719",
    "sg:province":"AZ",
    "wof:name":"Joint A Chiropractic Place",
    "wof:placetype":"venue"
},
  "geometry": {"coordinates":[-110.95792899999999,32.231677],"type":"Point"}
}