{
  "type": "Feature",
  "properties": {
    "iso:country":"US",
    "sg:address":"7595 E Mcdonald Dr # 100",
    "sg:city":"Scottsdale",
    "sg:classifiers":[
        {
            "category":"Professional",
            "subcategory":"Management & Consulting",
            "type":"Services"
        }
    ],
    "sg:phone":"+1 480 889 9900",
    "sg:postcode":"85250",
    "sg:province":"AZ",
    "sg:tags":[
        "consultant"
    ],
    "wof:name":"Cra",
    "wof:placetype":"venue"
},
  "geometry": {"coordinates":[-111.917441,33.524052],"type":"Point"}
}