{
  "type": "Feature",
  "properties": {
    "iso:country":"US",
    "sg:address":"4250 N Campbell Ave",
    "sg:city":"Tucson",
    "sg:classifiers":[
        {
            "category":"Restaurant",
            "type":"Food & Drink"
        }
    ],
    "sg:phone":"+1 520 577 0007",
    "sg:postcode":"85718",
    "sg:province":"AZ",
    "sg:tags":[
        "banquet",
        "rooms"
    ],
    "wof:name":"Windmill Inn At St Philip's",
    "wof:placetype":"venue"
},
  "geometry": {"coordinates":[-110.943727,32.283253],"type":"Point"}
}