{
  "type": "Feature",
  "properties": {
    "iso:country":"US",
    "sg:address":"1290 N Scottsdale Rd",
    "sg:city":"Tempe",
    "sg:classifiers":[
        {
            "category":"Restaurant",
            "type":"Food & Drink"
        }
    ],
    "sg:phone":"+1 480 966 9116",
    "sg:postcode":"85281",
    "sg:province":"AZ",
    "wof:name":"Layalena",
    "wof:placetype":"venue"
},
  "geometry": {"coordinates":[-111.926382,33.442223],"type":"Point"}
}