{
  "type": "Feature",
  "properties": {
    "iso:country":"US",
    "sg:address":"2934 W Windsor Ave",
    "sg:city":"Phoenix",
    "sg:classifiers":[
        {
            "category":"Manufacturing",
            "subcategory":"Signs",
            "type":"Manufacturing & Wholesale Goods"
        }
    ],
    "sg:phone":"+1 602 415 9444",
    "sg:postcode":"85009",
    "sg:province":"AZ",
    "sg:tags":[
        "mfg"
    ],
    "wof:name":"National Sign Fabricators",
    "wof:placetype":"venue"
},
  "geometry": {"coordinates":[-112.125087,33.478055],"type":"Point"}
}