{
  "type": "Feature",
  "properties": {
    "iso:country":"US",
    "sg:address":"18835 N Thompson Peak Parkway",
    "sg:city":"Scottsdale",
    "sg:classifiers":[
        {
            "category":"Professional",
            "subcategory":"Management & Consulting",
            "type":"Services"
        }
    ],
    "sg:phone":"+1 480 281 8558",
    "sg:postcode":"85255",
    "sg:province":"AZ",
    "sg:tags":[
        "zooloo",
        "zog-media",
        "digital",
        "social-media",
        "facebook",
        "twitter",
        "myspace",
        "linkedin",
        "seo",
        "smo"
    ],
    "sg:website":"http://zogmedia.com",
    "wof:name":"Zog Media",
    "wof:placetype":"venue"
},
  "geometry": {"coordinates":[-111.888577,33.676651],"type":"Point"}
}