{
  "type": "Feature",
  "properties": {
    "iso:country":"US",
    "sg:address":"1906 N Higley Rd",
    "sg:city":"Mesa",
    "sg:classifiers":[
        {
            "category":"Shopping",
            "subcategory":"Stationery & Office Supplies",
            "type":"Retail Goods"
        }
    ],
    "sg:phone":"+1 480 924 5200",
    "sg:postcode":"85205",
    "sg:province":"AZ",
    "sg:tags":[
        "equipment"
    ],
    "sg:website":"http://www.MesaPaintballSupply.com",
    "wof:name":"Mesa Paintball Supply & Hobby",
    "wof:placetype":"venue"
},
  "geometry": {"coordinates":[-111.718818,33.449921],"type":"Point"}
}