{
  "type": "Feature",
  "properties": {
    "addr:full":"3421 E Broadway Blvd Tucson AZ 85716",
    "addr:housenumber":"3421",
    "addr:postcode":"85716",
    "addr:street":"E Broadway Blvd",
    "iso:country":"US",
    "sg:address":"3421 E Broadway Blvd",
    "sg:city":"Tucson",
    "sg:classifiers":[
        {
            "category":"Coffee & Tea",
            "type":"Food & Drink"
        }
    ],
    "sg:menulink":"http://www.allmenus.com/az/tucson/108426-starbucks-coffee/menu/",
    "sg:phone":"+1 520 323 4512",
    "sg:postcode":"85716",
    "sg:province":"AZ",
    "sg:tags":[
        "american"
    ],
    "wof:name":"Starbucks Coffee",
    "wof:placetype":"venue"
},
  "geometry": {"coordinates":[-110.919594,32.22166],"type":"Point"}
}