{
  "type": "Feature",
  "properties": {
    "iso:country":"US",
    "sg:address":"7800 S Nogales Hwy",
    "sg:city":"Tucson",
    "sg:classifiers":[
        {
            "category":"Shopping",
            "subcategory":"Hobbies, Toys, & Games",
            "type":"Retail Goods"
        },
        {
            "category":"Manufacturing",
            "subcategory":"Tools & Machinery",
            "type":"Manufacturing & Wholesale Goods"
        }
    ],
    "sg:phone":"+1 520 746 8005",
    "sg:postcode":"85706",
    "sg:province":"AZ",
    "sg:tags":[
        "equipment",
        "company",
        "ceramic",
        "ceramics",
        "supply"
    ],
    "wof:name":"Advanced Ceramics Mfg LLC",
    "wof:placetype":"venue"
},
  "geometry": {"coordinates":[-110.960216,32.108506],"type":"Point"}
}