{
  "type": "Feature",
  "properties": {
    "iso:country":"US",
    "sg:address":"134 E Broadway Rd",
    "sg:city":"Mesa",
    "sg:classifiers":[
        {
            "category":"Retail",
            "subcategory":"Auto Repair",
            "type":"Services"
        }
    ],
    "sg:phone":"+1 480 649 4343",
    "sg:postcode":"85210",
    "sg:province":"AZ",
    "sg:tags":[
        "repairing",
        "automobile"
    ],
    "wof:name":"Arizona Mobile Auto Repair",
    "wof:placetype":"venue"
},
  "geometry": {"coordinates":[-111.828142,33.407906],"type":"Point"}
}