{
  "type": "Feature",
  "properties": {
    "iso:country":"US",
    "sg:address":"500 W 10th Pl",
    "sg:city":"Mesa",
    "sg:classifiers":[
        {
            "category":"Health Services",
            "subcategory":"Doctor",
            "type":"Services"
        }
    ],
    "sg:phone":"+1 480 461 2081",
    "sg:postcode":"85201",
    "sg:province":"AZ",
    "sg:tags":[
        "clinic"
    ],
    "wof:name":"Mesa Lutheran Medical Records",
    "wof:placetype":"venue"
},
  "geometry": {"coordinates":[-111.841491,33.434235],"type":"Point"}
}