{
  "type": "Feature",
  "properties": {
    "iso:country":"US",
    "sg:address":"3111 W Chandler Boulevard",
    "sg:city":"Chandler",
    "sg:classifiers":[
        {
            "category":"Shopping",
            "subcategory":"Pets & Pet Supplies",
            "type":"Retail Goods"
        }
    ],
    "sg:phone":"+1 480 726 3682",
    "sg:postcode":"85226",
    "sg:province":"AZ",
    "sg:tags":[
        "store"
    ],
    "wof:name":"Puppies-N-Love",
    "wof:placetype":"venue"
},
  "geometry": {"coordinates":[-111.898099,33.305634],"type":"Point"}
}