{
  "type": "Feature",
  "properties": {
    "iso:country":"US",
    "sg:address":"400 E 38th St",
    "sg:city":"Tucson",
    "sg:classifiers":[
        {
            "category":"Building & Trades",
            "subcategory":"Construction",
            "type":"Services"
        }
    ],
    "sg:phone":"+1 520 623 0900",
    "sg:postcode":"85713",
    "sg:province":"AZ",
    "sg:tags":[
        "general",
        "contractor"
    ],
    "wof:name":"Borderland Construction Co",
    "wof:placetype":"venue"
},
  "geometry": {"coordinates":[-110.96371499999999,32.190388],"type":"Point"}
}