{
  "type": "Feature",
  "properties": {
    "iso:country":"US",
    "sg:address":"19213 N 12th Pl",
    "sg:city":"Phoenix",
    "sg:classifiers":[
        {
            "category":"Insurance",
            "subcategory":"Insurance Agent",
            "type":"Services"
        }
    ],
    "sg:phone":"+1 623 582 9301",
    "sg:postcode":"85024",
    "sg:province":"AZ",
    "wof:name":"Adjusters Choice Claim Service",
    "wof:placetype":"venue"
},
  "geometry": {"coordinates":[-112.055223,33.661293],"type":"Point"}
}