{
  "type": "Feature",
  "properties": {
    "iso:country":"US",
    "sg:address":"6200 E Huntress Dr",
    "sg:city":"Paradise Valley",
    "sg:classifiers":[
        {
            "category":"Banks & Credit Unions",
            "subcategory":"Financial Services",
            "type":"Services"
        }
    ],
    "sg:phone":"+1 480 483 2992",
    "sg:postcode":"85253",
    "sg:province":"AZ",
    "sg:tags":[
        "trust",
        "family"
    ],
    "wof:name":"K F T Limited",
    "wof:placetype":"venue"
},
  "geometry": {"coordinates":[-111.944464,33.529939],"type":"Point"}
}