{
  "type": "Feature",
  "properties": {
    "addr:full":"4139 W Bell Rd Phoenix AZ 85053",
    "addr:housenumber":"4139",
    "addr:postcode":"85053",
    "addr:street":"W Bell Rd",
    "iso:country":"US",
    "sg:address":"4139 W Bell Rd",
    "sg:city":"Phoenix",
    "sg:classifiers":[
        {
            "category":"Restaurant",
            "type":"Food & Drink"
        }
    ],
    "sg:menulink":"http://www.allmenus.com/az/phoenix/4492-streets-of-new-york/menu/",
    "sg:phone":"+1 602 843 3898",
    "sg:postcode":"85053",
    "sg:province":"AZ",
    "sg:tags":[
        "italian"
    ],
    "wof:name":"Streets of New York",
    "wof:placetype":"venue"
},
  "geometry": {"coordinates":[-112.147554,33.63931],"type":"Point"}
}