{
  "type": "Feature",
  "properties": {
    "addr:full":"724 W Baseline Rd Mesa AZ 85210",
    "addr:housenumber":"724",
    "addr:postcode":"85210",
    "addr:street":"W Baseline Rd",
    "iso:country":"US",
    "sg:address":"724 W Baseline Rd",
    "sg:city":"Mesa",
    "sg:classifiers":[
        {
            "category":"Shopping",
            "subcategory":"Department Store",
            "type":"Retail Goods"
        }
    ],
    "sg:phone":"+1 480 834 4063",
    "sg:postcode":"85210",
    "sg:province":"AZ",
    "sg:website":"www.restaurantdepot.com",
    "wof:name":"Restaurant Depo",
    "wof:placetype":"venue"
},
  "geometry": {"coordinates":[-111.847392,33.37883],"type":"Point"}
}