{
  "type": "Feature",
  "properties": {
    "addr:full":"3475 E Fort Lowell Rd Tucson AZ 85716",
    "addr:housenumber":"3475",
    "addr:postcode":"85716",
    "addr:street":"E Fort Lowell Rd",
    "iso:country":"US",
    "sg:address":"3475 E Fort Lowell Rd",
    "sg:city":"Tucson",
    "sg:classifiers":[
        {
            "category":"Real Estate",
            "subcategory":"Real Estate Operator",
            "type":"Services"
        }
    ],
    "sg:phone":"+1 520 326 9100",
    "sg:postcode":"85716",
    "sg:province":"AZ",
    "sg:tags":[
        "apartment"
    ],
    "wof:name":"Fort Lowell Place Apartments",
    "wof:placetype":"venue"
},
  "geometry": {"coordinates":[-110.91829300000001,32.265138],"type":"Point"}
}