{
  "type": "Feature",
  "properties": {
    "iso:country":"US",
    "sg:address":"1645 E Lockwood St",
    "sg:city":"Mesa",
    "sg:classifiers":[
        {
            "category":"Shopping",
            "subcategory":"Computers & Home Electronics",
            "type":"Retail Goods"
        }
    ],
    "sg:phone":"+1 480 222 0577",
    "sg:postcode":"85203",
    "sg:province":"AZ",
    "sg:tags":[
        "software"
    ],
    "wof:name":"Gold Vision Software",
    "wof:placetype":"venue"
},
  "geometry": {"coordinates":[-111.794926,33.456032],"type":"Point"}
}