{
  "type": "Feature",
  "properties": {
    "iso:country":"US",
    "sg:address":"4001 E Fort Lowell Rd",
    "sg:city":"Tucson",
    "sg:classifiers":[
        {
            "category":"Social Services",
            "type":"Services"
        }
    ],
    "sg:phone":"+1 520 250 0226",
    "sg:postcode":"85712",
    "sg:province":"AZ",
    "sg:tags":[
        "counselor",
        "marriage",
        "family"
    ],
    "wof:name":"Barbara G Palmer PHD",
    "wof:placetype":"venue"
},
  "geometry": {"coordinates":[-110.90716999999999,32.265195],"type":"Point"}
}