{
  "type": "Feature",
  "properties": {
    "addr:full":"713 W Kaler Dr Phoenix AZ 85021",
    "addr:housenumber":"713",
    "addr:postcode":"85021",
    "addr:street":"W Kaler Dr",
    "iso:country":"US",
    "sg:address":"713 W Kaler Dr",
    "sg:city":"Phoenix",
    "sg:classifiers":[
        {
            "category":"Shopping",
            "subcategory":"Crafts & Fabrics",
            "type":"Retail Goods"
        },
        {
            "category":"Professional",
            "subcategory":"Art Services",
            "type":"Services"
        },
        {
            "category":"Professional",
            "subcategory":"Printing & Photocopies",
            "type":"Services"
        }
    ],
    "sg:phone":"+1 602 870 4956",
    "sg:postcode":"85021",
    "sg:province":"AZ",
    "sg:tags":[
        "punching",
        "screen",
        "design",
        "embroidery"
    ],
    "wof:name":"Holland Apparel",
    "wof:placetype":"venue"
},
  "geometry": {"coordinates":[-112.083809,33.548302],"type":"Point"}
}