{
  "type": "Feature",
  "properties": {
    "iso:country":"US",
    "sg:address":"1414 N Cooper Rd",
    "sg:city":"Gilbert",
    "sg:classifiers":[
        {
            "category":"Health Services",
            "subcategory":"Health Practitioner",
            "type":"Services"
        }
    ],
    "sg:phone":"+1 480 706 1161",
    "sg:postcode":"85233",
    "sg:province":"AZ",
    "sg:tags":[
        "therapy",
        "physical"
    ],
    "sg:website":"www.foothillsrehab.com",
    "wof:name":"Foothills Sports Medicine Physical Therapy",
    "wof:placetype":"venue"
},
  "geometry": {"coordinates":[-111.80768,33.375616],"type":"Point"}
}