{
  "type": "Feature",
  "properties": {
    "iso:country":"US",
    "sg:address":"3307 W Maryland Ave",
    "sg:city":"Phoenix",
    "sg:classifiers":[
        {
            "category":"Utilities",
            "subcategory":"Refuse",
            "type":"Services"
        }
    ],
    "sg:phone":"+1 602 973 1153",
    "sg:postcode":"85017",
    "sg:province":"AZ",
    "sg:tags":[
        "truck",
        "dump"
    ],
    "wof:name":"Bounds Dump Truck Service",
    "wof:placetype":"venue"
},
  "geometry": {"coordinates":[-112.13006,33.531238],"type":"Point"}
}