{
  "type": "Feature",
  "properties": {
    "addr:full":"5110 N 19th Ave Phoenix AZ 85015",
    "addr:housenumber":"5110",
    "addr:postcode":"85015",
    "addr:street":"N 19Th Ave",
    "iso:country":"US",
    "sg:address":"5110 N 19th Ave",
    "sg:city":"Phoenix",
    "sg:classifiers":[
        {
            "category":"Real Estate",
            "subcategory":"Real Estate Operator",
            "type":"Services"
        }
    ],
    "sg:phone":"+1 602 246 7518",
    "sg:postcode":"85015",
    "sg:province":"AZ",
    "sg:tags":[
        "building",
        "apartment"
    ],
    "wof:name":"Villager Apartments Inc",
    "wof:placetype":"venue"
},
  "geometry": {"coordinates":[-112.099919,33.511641],"type":"Point"}
}