{
  "type": "Feature",
  "properties": {
    "addr:full":"1327 E Northern Ave Phoenix AZ 85020",
    "addr:housenumber":"1327",
    "addr:postcode":"85020",
    "addr:street":"E Northern Ave",
    "iso:country":"US",
    "sg:address":"1327 E Northern Ave",
    "sg:city":"Phoenix",
    "sg:classifiers":[
        {
            "category":"Manufacturing",
            "subcategory":"Printing",
            "type":"Manufacturing & Wholesale Goods"
        }
    ],
    "sg:phone":"+1 602 674 0688",
    "sg:postcode":"85020",
    "sg:province":"AZ",
    "sg:tags":[
        "printer"
    ],
    "wof:name":"Fed Ex",
    "wof:placetype":"venue"
},
  "geometry": {"coordinates":[-112.05275,33.5531],"type":"Point"}
}