{
  "type": "Feature",
  "properties": {
    "addr:full":"916 E Echo Ln Phoenix AZ 85020",
    "addr:housenumber":"916",
    "addr:postcode":"85020",
    "addr:street":"E Echo Ln",
    "iso:country":"US",
    "sg:address":"916 E Echo Ln",
    "sg:city":"Phoenix",
    "sg:classifiers":[
        {
            "category":"Shopping",
            "type":"Retail Goods"
        }
    ],
    "sg:phone":"+1 602 944 0830",
    "sg:postcode":"85020",
    "sg:province":"AZ",
    "sg:tags":[
        "miscellaneous",
        "store"
    ],
    "wof:name":"Rayvarn Enterprises",
    "wof:placetype":"venue"
},
  "geometry": {"coordinates":[-112.062471,33.559741],"type":"Point"}
}