{
  "type": "Feature",
  "properties": {
    "iso:country":"US",
    "sg:address":"2440 W Mission Ln Ste 1",
    "sg:city":"Phoenix",
    "sg:classifiers":[
        {
            "category":"Professional",
            "subcategory":"Detective & Security Services",
            "type":"Services"
        },
        {
            "category":"Communications",
            "type":"Services"
        }
    ],
    "sg:phone":"+1 602 674 6100",
    "sg:postcode":"85021",
    "sg:province":"AZ",
    "sg:tags":[
        "television",
        "system",
        "equipment",
        "systems-closed",
        "circuit",
        "telecasting",
        "data"
    ],
    "wof:name":"Hsm Security",
    "wof:placetype":"venue"
},
  "geometry": {"coordinates":[-112.110865,33.569163],"type":"Point"}
}