{
  "type": "Feature",
  "properties": {
    "addr:full":"6091 N Oracle Rd Tucson AZ 85704",
    "addr:housenumber":"6091",
    "addr:postcode":"85704",
    "addr:street":"N Oracle Rd",
    "iso:country":"US",
    "sg:address":"6091 N Oracle Rd",
    "sg:city":"Tucson",
    "sg:classifiers":[
        {
            "category":"Restaurant",
            "type":"Food & Drink"
        }
    ],
    "sg:phone":"+1 520 297 5555",
    "sg:postcode":"85704",
    "sg:province":"AZ",
    "sg:tags":[
        "eating"
    ],
    "wof:name":"Sakura Tppan Steak Safood Rest",
    "wof:placetype":"venue"
},
  "geometry": {"coordinates":[-110.97563700000001,32.317659],"type":"Point"}
}