{
  "type": "Feature",
  "properties": {
    "iso:country":"US",
    "sg:address":"218 Justin Dr",
    "sg:city":"Cottonwood",
    "sg:classifiers":[
        {
            "category":"Professional",
            "subcategory":"Management & Consulting",
            "type":"Services"
        }
    ],
    "sg:phone":"+1 928 634 0582",
    "sg:postcode":"86326",
    "sg:province":"AZ",
    "sg:tags":[
        "marketing",
        "program"
    ],
    "sg:website":"www.sedonalabs.com",
    "wof:name":"Nutri Health Products",
    "wof:placetype":"venue"
},
  "geometry": {"coordinates":[-112.03510799999999,34.736819],"type":"Point"}
}