{
  "type": "Feature",
  "properties": {
    "iso:country":"US",
    "sg:address":"1060 W Sahara Palms Dr",
    "sg:city":"Tucson",
    "sg:classifiers":[
        {
            "category":"Manufacturing",
            "subcategory":"Leather Goods",
            "type":"Manufacturing & Wholesale Goods"
        }
    ],
    "sg:phone":"+1 520 742 3664",
    "sg:postcode":"85704",
    "sg:province":"AZ",
    "sg:tags":[
        "mfg"
    ],
    "wof:name":"Walts Leather",
    "wof:placetype":"venue"
},
  "geometry": {"coordinates":[-110.98885900000001,32.321316],"type":"Point"}
}