{
  "type": "Feature",
  "properties": {
    "addr:full":"404 E Osage Ave Apache Junction AZ 85219",
    "addr:housenumber":"404",
    "addr:postcode":"85219",
    "addr:street":"E Osage Ave",
    "iso:country":"US",
    "sg:address":"404 E Osage Ave",
    "sg:city":"Apache Junction",
    "sg:classifiers":[
        {
            "category":"Real Estate",
            "subcategory":"Real Estate Agent",
            "type":"Services"
        }
    ],
    "sg:phone":"+1 480 983 1824",
    "sg:postcode":"85219",
    "sg:province":"AZ",
    "wof:name":"William Harold Ledingham",
    "wof:placetype":"venue"
},
  "geometry": {"coordinates":[-111.54142400000001,33.395876],"type":"Point"}
}