{
  "type": "Feature",
  "properties": {
    "addr:full":"2227 S Mission Rd Tucson AZ 85713",
    "addr:housenumber":"2227",
    "addr:postcode":"85713",
    "addr:street":"S Mission Rd",
    "iso:country":"US",
    "sg:address":"2227 S Mission Rd",
    "sg:city":"Tucson",
    "sg:classifiers":[
        {
            "category":"Home & Garden",
            "subcategory":"Furniture",
            "type":"Retail Goods"
        }
    ],
    "sg:phone":"+1 520 888 2227",
    "sg:postcode":"85713",
    "sg:province":"AZ",
    "sg:tags":[
        "equipment",
        "kitchen",
        "cabinet"
    ],
    "wof:name":"Arizona Cabinet Co",
    "wof:placetype":"venue"
},
  "geometry": {"coordinates":[-110.996458,32.199507],"type":"Point"}
}