{
  "type": "Feature",
  "properties": {
    "iso:country":"US",
    "sg:address":"4635 W McDowell Rd",
    "sg:city":"Phoenix",
    "sg:classifiers":[
        {
            "category":"Manufacturing",
            "subcategory":"Metals",
            "type":"Manufacturing & Wholesale Goods"
        },
        {
            "category":"Building & Trades",
            "subcategory":"Construction",
            "type":"Services"
        }
    ],
    "sg:phone":"+1 602 233 2400",
    "sg:postcode":"85035",
    "sg:province":"AZ",
    "sg:tags":[
        "machine",
        "shop",
        "fabricator"
    ],
    "sg:website":"www.multifab-inc.com",
    "wof:name":"Multimedia Fabrication Inc",
    "wof:placetype":"venue"
},
  "geometry": {"coordinates":[-112.156498,33.465881],"type":"Point"}
}