{
  "type": "Feature",
  "properties": {
    "iso:country":"US",
    "sg:address":"4225 N 1st Ave",
    "sg:city":"Tucson",
    "sg:classifiers":[
        {
            "category":"Wholesale",
            "subcategory":"Vending Machines",
            "type":"Manufacturing & Wholesale Goods"
        }
    ],
    "sg:phone":"+1 520 888 3060",
    "sg:postcode":"85719",
    "sg:province":"AZ",
    "wof:name":"Crown Vending Machines",
    "wof:placetype":"venue"
},
  "geometry": {"coordinates":[-110.961163,32.285148],"type":"Point"}
}