{
  "type": "Feature",
  "properties": {
    "iso:country":"US",
    "sg:address":"25 Pony Soldier Cir",
    "sg:city":"Sedona",
    "sg:classifiers":[
        {
            "category":"Building & Trades",
            "subcategory":"Construction",
            "type":"Services"
        }
    ],
    "sg:phone":"+1 928 282 9650",
    "sg:postcode":"86336",
    "sg:province":"AZ",
    "sg:tags":[
        "architectural",
        "contractor"
    ],
    "wof:name":"Bella Casa Tiles",
    "wof:placetype":"venue"
},
  "geometry": {"coordinates":[-111.792043,34.869585],"type":"Point"}
}