{
  "type": "Feature",
  "properties": {
    "addr:full":"2610 E Hulet Drive Chandler AZ 85225",
    "addr:housenumber":"2610",
    "addr:postcode":"85225",
    "addr:street":"E Hulet Drive",
    "iso:country":"US",
    "sg:address":"2610 E Hulet Drive",
    "sg:city":"Chandler",
    "sg:classifiers":[
        {
            "category":"Banks & Credit Unions",
            "subcategory":"Financial Services",
            "type":"Services"
        }
    ],
    "sg:phone":"+1 480 963 1149",
    "sg:postcode":"85225",
    "sg:province":"AZ",
    "sg:tags":[
        "broker",
        "mortgage"
    ],
    "wof:name":"Financial Freedom",
    "wof:placetype":"venue"
},
  "geometry": {"coordinates":[-111.79661900000001,33.309481],"type":"Point"}
}