{
  "type": "Feature",
  "properties": {
    "iso:country":"US",
    "sg:address":"14020 W Bell Rd",
    "sg:city":"Surprise",
    "sg:classifiers":[
        {
            "category":"Shopping",
            "subcategory":"Department Store",
            "type":"Retail Goods"
        }
    ],
    "sg:phone":"+1 623 544 6330",
    "sg:postcode":"85374",
    "sg:province":"AZ",
    "wof:name":"Kohls Department Stores Inc",
    "wof:placetype":"venue"
},
  "geometry": {"coordinates":[-112.366342,33.638785],"type":"Point"}
}