{
  "type": "Feature",
  "properties": {
    "iso:country":"US",
    "sg:address":"3812 E 37th St",
    "sg:city":"Tucson",
    "sg:classifiers":[
        {
            "category":"Building & Trades",
            "subcategory":"Construction",
            "type":"Services"
        }
    ],
    "sg:phone":"+1 520 748 2588",
    "sg:postcode":"85713",
    "sg:province":"AZ",
    "sg:tags":[
        "general",
        "contractor"
    ],
    "wof:name":"Tuhavi Corp",
    "wof:placetype":"venue"
},
  "geometry": {"coordinates":[-110.910805,32.191595],"type":"Point"}
}