{
  "type": "Feature",
  "properties": {
    "addr:full":"935 E Southern Ave Mesa AZ 85204",
    "addr:housenumber":"935",
    "addr:postcode":"85204",
    "addr:street":"E Southern Ave",
    "iso:country":"US",
    "sg:address":"935 E Southern Ave",
    "sg:city":"Mesa",
    "sg:classifiers":[
        {
            "category":"Home & Garden",
            "subcategory":"Hardware",
            "type":"Retail Goods"
        }
    ],
    "sg:phone":"+1 480 926 2131",
    "sg:postcode":"85204",
    "sg:province":"AZ",
    "sg:tags":[
        "equipment",
        "industrial"
    ],
    "wof:name":"Timber Woodworking Machinery",
    "wof:placetype":"venue"
},
  "geometry": {"coordinates":[-111.813755,33.393289],"type":"Point"}
}