{
  "type": "Feature",
  "properties": {
    "addr:full":"6129 W Olive Ave Glendale AZ 85302",
    "addr:housenumber":"6129",
    "addr:postcode":"85302",
    "addr:street":"W Olive Ave",
    "iso:country":"US",
    "sg:address":"6129 W Olive Ave",
    "sg:city":"Glendale",
    "sg:classifiers":[
        {
            "category":"Organizations",
            "subcategory":"Religious Organization",
            "type":"Services"
        }
    ],
    "sg:phone":"+1 623 937 2515",
    "sg:postcode":"85302",
    "sg:province":"AZ",
    "sg:tags":[
        "church"
    ],
    "wof:name":"Church Of Jesus Christ Of Lds",
    "wof:placetype":"venue"
},
  "geometry": {"coordinates":[-112.191857,33.567331],"type":"Point"}
}