{
  "type": "Feature",
  "properties": {
    "addr:full":"263 N Center St Bldg A Mesa AZ 85201",
    "addr:housenumber":"263",
    "addr:postcode":"85201",
    "addr:street":"N Center St;A",
    "iso:country":"US",
    "sg:address":"263 N Center St Bldg A",
    "sg:city":"Mesa",
    "sg:classifiers":[
        {
            "category":"Professional",
            "subcategory":"Business Services",
            "type":"Services"
        },
        {
            "category":"Conference Center",
            "type":"Public Place"
        }
    ],
    "sg:phone":"+1 480 644 2178",
    "sg:postcode":"85201",
    "sg:province":"AZ",
    "sg:tags":[
        "convention",
        "facility",
        "supply"
    ],
    "wof:name":"Mesa Convention Center",
    "wof:placetype":"venue"
},
  "geometry": {"coordinates":[-111.83143699999999,33.420791],"type":"Point"}
}