{
  "type": "Feature",
  "properties": {
    "iso:country":"US",
    "sg:address":"354 N Country Club Dr",
    "sg:city":"Mesa",
    "sg:classifiers":[
        {
            "category":"Restaurant",
            "type":"Food & Drink"
        }
    ],
    "sg:menulink":"http://www.allmenus.com/az/phoenix/88409-pizza-patron/menu/",
    "sg:phone":"+1 480 464 9191",
    "sg:postcode":"85201",
    "sg:province":"AZ",
    "sg:tags":[
        "american",
        "pizza"
    ],
    "wof:name":"Pizza Patron",
    "wof:placetype":"venue"
},
  "geometry": {"coordinates":[-111.840389,33.422067],"type":"Point"}
}