{
  "type": "Feature",
  "properties": {
    "iso:country":"US",
    "sg:address":"401 W Van Buren St",
    "sg:city":"Avondale",
    "sg:classifiers":[
        {
            "category":"Restaurant",
            "type":"Food & Drink"
        }
    ],
    "sg:phone":"+1 623 932 9613",
    "sg:postcode":"85323",
    "sg:province":"AZ",
    "wof:name":"China Empress",
    "wof:placetype":"venue"
},
  "geometry": {"coordinates":[-112.35111000000001,33.449767],"type":"Point"}
}