{
  "type": "Feature",
  "properties": {
    "addr:full":"821 Riordan Rd Flagstaff AZ 86001",
    "addr:housenumber":"821",
    "addr:postcode":"86001",
    "addr:street":"Riordan Rd",
    "iso:country":"US",
    "sg:address":"821 Riordan Rd",
    "sg:city":"Flagstaff",
    "sg:classifiers":[
        {
            "category":"Organizations",
            "subcategory":"Non-profit Organization",
            "type":"Services"
        }
    ],
    "sg:phone":"+1 928 556 8761",
    "sg:postcode":"86001",
    "sg:province":"AZ",
    "wof:name":"Meyerson Foundation",
    "wof:placetype":"venue"
},
  "geometry": {"coordinates":[-111.657864,35.187559],"type":"Point"}
}