{
  "type": "Feature",
  "properties": {
    "iso:country":"US",
    "sg:address":"4321 N 55th Dr",
    "sg:city":"Phoenix",
    "sg:classifiers":[
        {
            "category":"Professional",
            "type":"Services"
        }
    ],
    "sg:phone":"+1 623 247 0562",
    "sg:postcode":"85031",
    "sg:province":"AZ",
    "sg:tags":[
        "body",
        "automobile",
        "painting",
        "repairing"
    ],
    "wof:name":"Argentina Paint",
    "wof:placetype":"venue"
},
  "geometry": {"coordinates":[-112.178956,33.499203],"type":"Point"}
}