{
  "type": "Feature",
  "properties": {
    "iso:country":"US",
    "sg:address":"2523 N Campbell Ave",
    "sg:city":"Tucson",
    "sg:classifiers":[
        {
            "category":"Personal",
            "subcategory":"Barber",
            "type":"Services"
        }
    ],
    "sg:phone":"+1 520 881 4767",
    "sg:postcode":"85719",
    "sg:province":"AZ",
    "wof:name":"A-Model Barber Shop",
    "wof:placetype":"venue"
},
  "geometry": {"coordinates":[-110.944012,32.252528],"type":"Point"}
}