{
  "type": "Feature",
  "properties": {
    "addr:full":"3241 E Shea Blvd Phoenix AZ 85028",
    "addr:housenumber":"3241",
    "addr:postcode":"85028",
    "addr:street":"E Shea Blvd",
    "iso:country":"US",
    "sg:address":"3241 E Shea Blvd",
    "sg:city":"Phoenix",
    "sg:classifiers":[
        {
            "category":"Banks & Credit Unions",
            "subcategory":"Bank",
            "type":"Services"
        }
    ],
    "sg:phone":"+1 602 996 1630",
    "sg:postcode":"85028",
    "sg:province":"AZ",
    "sg:tags":[
        "other",
        "plan",
        "card"
    ],
    "wof:name":"Cardservice International",
    "wof:placetype":"venue"
},
  "geometry": {"coordinates":[-112.009818,33.582453],"type":"Point"}
}