{
  "type": "Feature",
  "properties": {
    "iso:country":"US",
    "sg:address":"110 S Kolb Rd",
    "sg:city":"Tucson",
    "sg:classifiers":[
        {
            "category":"Professional",
            "type":"Services"
        }
    ],
    "sg:phone":"+1 520 885 7289",
    "sg:postcode":"85710",
    "sg:province":"AZ",
    "sg:tags":[
        "establishment"
    ],
    "wof:name":"Dancin Savvy",
    "wof:placetype":"venue"
},
  "geometry": {"coordinates":[-110.841032,32.220002],"type":"Point"}
}