{
  "type": "Feature",
  "properties": {
    "iso:country":"US",
    "sg:address":"111 N Dobson Rd",
    "sg:city":"Chandler",
    "sg:classifiers":[
        {
            "category":"Retail",
            "subcategory":"Auto Repair",
            "type":"Services"
        }
    ],
    "sg:phone":"+1 480 857 7500",
    "sg:postcode":"85224",
    "sg:province":"AZ",
    "sg:website":"www.brakemasters.com",
    "wof:name":"Brake Masters",
    "wof:placetype":"venue"
},
  "geometry": {"coordinates":[-111.87599899999999,33.3055],"type":"Point"}
}