{
  "type": "Feature",
  "properties": {
    "iso:country":"US",
    "sg:address":"12210 W Washington St",
    "sg:city":"Avondale",
    "sg:classifiers":[
        {
            "category":"Shopping",
            "subcategory":"Stationery & Office Supplies",
            "type":"Retail Goods"
        },
        {
            "category":"Manufacturing",
            "subcategory":"Paper Products",
            "type":"Manufacturing & Wholesale Goods"
        }
    ],
    "sg:phone":"+1 623 907 0783",
    "sg:postcode":"85323",
    "sg:province":"AZ",
    "sg:tags":[
        "labels-wholesale",
        "labels-plastic",
        "metal",
        "label",
        "foil",
        "manufacturer"
    ],
    "wof:name":"Scalelabels Com",
    "wof:placetype":"venue"
},
  "geometry": {"coordinates":[-112.321113,33.445476],"type":"Point"}
}