{
  "type": "Feature",
  "properties": {
    "iso:country":"US",
    "sg:address":"7910 E Thompson Peak Pkwy",
    "sg:city":"Scottsdale",
    "sg:classifiers":[
        {
            "category":"Professional",
            "subcategory":"Lawyer & Legal Services",
            "type":"Services"
        }
    ],
    "sg:phone":"+1 480 296 2036",
    "sg:postcode":"85255",
    "sg:province":"AZ",
    "sg:tags":[
        "attorney"
    ],
    "wof:name":"Goldinov & Mc Cauley Attorney",
    "wof:placetype":"venue"
},
  "geometry": {"coordinates":[-111.906034,33.672796],"type":"Point"}
}