{
  "type": "Feature",
  "properties": {
    "iso:country":"US",
    "sg:address":"26533 N Babbling Brook Dr",
    "sg:city":"Phoenix",
    "sg:classifiers":[
        {
            "category":"Building & Trades",
            "subcategory":"Construction",
            "type":"Services"
        }
    ],
    "sg:phone":"+1 623 581 0380",
    "sg:postcode":"85083",
    "sg:province":"AZ",
    "sg:tags":[
        "systems-repairing",
        "system",
        "specialty",
        "equipment",
        "heating",
        "contractor",
        "air conditioning"
    ],
    "wof:name":"Guilkey And Son Heating And Air Conditioning",
    "wof:placetype":"venue"
},
  "geometry": {"coordinates":[-112.174617,33.724777],"type":"Point"}
}