{
  "type": "Feature",
  "properties": {
    "iso:country":"US",
    "sg:address":"3951 E Desert Cove Ave",
    "sg:city":"Phoenix",
    "sg:classifiers":[
        {
            "category":"Manufacturing",
            "subcategory":"Metals",
            "type":"Manufacturing & Wholesale Goods"
        }
    ],
    "sg:phone":"+1 602 568 9690",
    "sg:postcode":"85028",
    "sg:province":"AZ",
    "sg:tags":[
        "work",
        "iron"
    ],
    "wof:name":"Cnc Iron Works",
    "wof:placetype":"venue"
},
  "geometry": {"coordinates":[-111.997065,33.586321],"type":"Point"}
}