{
  "type": "Feature",
  "properties": {
    "iso:country":"US",
    "sg:address":"2051 S Dobson Rd Ste 3",
    "sg:city":"Mesa",
    "sg:classifiers":[
        {
            "category":"Home & Garden",
            "subcategory":"Building Materials",
            "type":"Retail Goods"
        },
        {
            "category":"Building & Trades",
            "subcategory":"Construction",
            "type":"Services"
        }
    ],
    "sg:phone":"+1 866 870 9263",
    "sg:postcode":"85202",
    "sg:province":"AZ",
    "sg:tags":[
        "windows-repair",
        "window",
        "replacement",
        "installation",
        "doors-vinyl"
    ],
    "sg:website":"http://redirect.searchignite.com/si/cm/tracking/DGTrackingRedirect.aspx?siclientid=3825&siredirect=http%3A%2F%2Fwww%2Epella%2Ecom%2Flocation%2Fwhere%2Dto%2Dbuy%2Fdefault%2Easpx&sisearchengine=155&siproduct=707%5FTL&clearppc=1",
    "wof:name":"Pella Windows & Doors of Mesa",
    "wof:placetype":"venue"
},
  "geometry": {"coordinates":[-111.87801,33.37709],"type":"Point"}
}