{
  "type": "Feature",
  "properties": {
    "iso:country":"US",
    "sg:address":"42101 N 41st Dr",
    "sg:city":"Anthem",
    "sg:classifiers":[
        {
            "category":"Real Estate",
            "subcategory":"Real Estate Agent",
            "type":"Services"
        }
    ],
    "sg:phone":"+1 623 551 8040",
    "sg:postcode":"85086",
    "sg:province":"AZ",
    "wof:name":"Daisy Mountain Real Estate",
    "wof:placetype":"venue"
},
  "geometry": {"coordinates":[-112.14749,33.865744],"type":"Point"}
}