{
  "type": "Feature",
  "properties": {
    "iso:country":"US",
    "sg:address":"2307 E Willetta St",
    "sg:city":"Phoenix",
    "sg:classifiers":[
        {
            "category":"Building & Trades",
            "subcategory":"Construction",
            "type":"Services"
        }
    ],
    "sg:phone":"+1 602 267 9147",
    "sg:postcode":"85006",
    "sg:province":"AZ",
    "sg:tags":[
        "roofing",
        "industrial",
        "contractors-commercial",
        "contractor"
    ],
    "wof:name":"H&K Roofing",
    "wof:placetype":"venue"
},
  "geometry": {"coordinates":[-112.031813,33.463986],"type":"Point"}
}