{
  "type": "Feature",
  "properties": {
    "iso:country":"US",
    "sg:address":"2675 Oatman Rd",
    "sg:city":"Golden Valley",
    "sg:classifiers":[
        {
            "category":"Wholesale",
            "subcategory":"Groceries",
            "type":"Manufacturing & Wholesale Goods"
        }
    ],
    "sg:phone":"+1 928 718 4000",
    "sg:postcode":"86413",
    "sg:province":"AZ",
    "sg:tags":[
        "baker"
    ],
    "wof:name":"Mc Kee Foods Corp",
    "wof:placetype":"venue"
},
  "geometry": {"coordinates":[-114.15377,35.106306],"type":"Point"}
}