{
  "type": "Feature",
  "properties": {
    "addr:full":"4613 E Karen Dr Phoenix AZ 85032",
    "addr:housenumber":"4613",
    "addr:postcode":"85032",
    "addr:street":"E Karen Dr",
    "iso:country":"US",
    "sg:address":"4613 E Karen Dr",
    "sg:city":"Phoenix",
    "sg:classifiers":[
        {
            "category":"Real Estate",
            "subcategory":"Architect",
            "type":"Services"
        },
        {
            "category":"Building & Trades",
            "subcategory":"Construction",
            "type":"Services"
        }
    ],
    "sg:phone":"+1 602 482 8817",
    "sg:postcode":"85032",
    "sg:province":"AZ",
    "sg:tags":[
        "general",
        "contractor"
    ],
    "wof:name":"Dane Designs Desert Studio",
    "wof:placetype":"venue"
},
  "geometry": {"coordinates":[-111.98201299999999,33.625517],"type":"Point"}
}