{
  "type": "Feature",
  "properties": {
    "addr:full":"1000 N Humphreys St Flagstaff AZ 86001",
    "addr:housenumber":"1000",
    "addr:postcode":"86001",
    "addr:street":"N Humphreys St",
    "iso:country":"US",
    "sg:address":"1000 N Humphreys St",
    "sg:city":"Flagstaff",
    "sg:classifiers":[
        {
            "category":"Restaurant",
            "type":"Food & Drink"
        }
    ],
    "sg:menulink":"http://www.allmenus.com/az/coconino/128922-subway/menu/",
    "sg:phone":"+1 928 773 1061",
    "sg:postcode":"86001",
    "sg:province":"AZ",
    "sg:tags":[
        "american",
        "sandwich"
    ],
    "wof:name":"Subway",
    "wof:placetype":"venue"
},
  "geometry": {"coordinates":[-111.64718999999999,35.207055],"type":"Point"}
}