{
  "type": "Feature",
  "properties": {
    "iso:country":"US",
    "sg:address":"7423 N 48th Dr",
    "sg:city":"Glendale",
    "sg:classifiers":[
        {
            "category":"Building & Trades",
            "subcategory":"Construction",
            "type":"Services"
        }
    ],
    "sg:phone":"+1 623 931 3533",
    "sg:postcode":"85301",
    "sg:province":"AZ",
    "sg:tags":[
        "contractor"
    ],
    "wof:name":"Double LL Acoustics Inc",
    "wof:placetype":"venue"
},
  "geometry": {"coordinates":[-112.163509,33.545474],"type":"Point"}
}