{
  "type": "Feature",
  "properties": {
    "iso:country":"US",
    "sg:address":"733 W Taylor St",
    "sg:city":"Phoenix",
    "sg:classifiers":[
        {
            "category":"Wholesale",
            "subcategory":"Non-durable Goods",
            "type":"Manufacturing & Wholesale Goods"
        },
        {
            "category":"Professional",
            "subcategory":"Business Services",
            "type":"Services"
        }
    ],
    "sg:phone":"+1 602 253 0400",
    "sg:postcode":"85007",
    "sg:province":"AZ",
    "sg:tags":[
        "broker",
        "merchandise",
        "merchandise-wholesale"
    ],
    "wof:name":"Nationwide Surplus",
    "wof:placetype":"venue"
},
  "geometry": {"coordinates":[-112.083282,33.45422],"type":"Point"}
}