{
  "type": "Feature",
  "properties": {
    "iso:country":"US",
    "sg:address":"3033 W Van Buren St",
    "sg:city":"Phoenix",
    "sg:classifiers":[
        {
            "category":"Shopping",
            "subcategory":"Music",
            "type":"Retail Goods"
        }
    ],
    "sg:phone":"+1 602 269 0229",
    "sg:postcode":"85009",
    "sg:province":"AZ",
    "wof:name":"Idolo De Oro",
    "wof:placetype":"venue"
},
  "geometry": {"coordinates":[-112.125948,33.451264],"type":"Point"}
}