{
  "type": "Feature",
  "properties": {
    "iso:country":"US",
    "sg:address":"7730 W Indian School Rd",
    "sg:city":"Phoenix",
    "sg:classifiers":[
        {
            "category":"Building & Trades",
            "subcategory":"Locksmith",
            "type":"Services"
        }
    ],
    "sg:phone":"+1 480 639 6852",
    "sg:postcode":"85033",
    "sg:province":"AZ",
    "sg:tags":[
        "key"
    ],
    "wof:name":"Emergency Locksmith On E Jefferson St",
    "wof:placetype":"venue"
},
  "geometry": {"coordinates":[-112.225928,33.494675],"type":"Point"}
}