{
  "type": "Feature",
  "properties": {
    "iso:country":"US",
    "sg:address":"260 S Scott Ave",
    "sg:city":"Tucson",
    "sg:classifiers":[
        {
            "category":"Health Services",
            "subcategory":"Doctor",
            "type":"Services"
        },
        {
            "category":"Health Services",
            "subcategory":"Clinic",
            "type":"Services"
        }
    ],
    "sg:phone":"+1 520 884 8470",
    "sg:postcode":"85701",
    "sg:province":"AZ",
    "sg:tags":[
        "physician",
        "mental",
        "information",
        "surgeons",
        "medicine",
        "addiction"
    ],
    "sg:website":"http://www.lafrontera.org",
    "wof:name":"Hope Center",
    "wof:placetype":"venue"
},
  "geometry": {"coordinates":[-110.969593,32.218204],"type":"Point"}
}