{
  "type": "Feature",
  "properties": {
    "iso:country":"US",
    "sg:address":"2730 W Belmont Ave",
    "sg:city":"Phoenix",
    "sg:classifiers":[
        {
            "category":"Shopping",
            "subcategory":"Crafts & Fabrics",
            "type":"Retail Goods"
        },
        {
            "category":"Manufacturing",
            "subcategory":"Pottery",
            "type":"Manufacturing & Wholesale Goods"
        }
    ],
    "sg:phone":"+1 602 864 7079",
    "sg:postcode":"85051",
    "sg:province":"AZ",
    "sg:tags":[
        "products-decorative",
        "ceramics-equipment",
        "ceramic",
        "supply"
    ],
    "wof:name":"His & Hers Ceramics",
    "wof:placetype":"venue"
},
  "geometry": {"coordinates":[-112.11752199999999,33.549421],"type":"Point"}
}