{
  "type": "Feature",
  "properties": {
    "iso:country":"US",
    "sg:address":"1220 N Spencer",
    "sg:city":"Mesa",
    "sg:classifiers":[
        {
            "category":"Professional",
            "subcategory":"Lawyer & Legal Services",
            "type":"Services"
        }
    ],
    "sg:phone":"+1 480 947 3232",
    "sg:postcode":"85203",
    "sg:province":"AZ",
    "sg:tags":[
        "attorney"
    ],
    "wof:name":"A Legal Awareness For Seniors",
    "wof:placetype":"venue"
},
  "geometry": {"coordinates":[-111.807247,33.437778],"type":"Point"}
}