{
  "type": "Feature",
  "properties": {
    "iso:country":"US",
    "sg:address":"1410 W Elliot Rd",
    "sg:city":"Gilbert",
    "sg:classifiers":[
        {
            "category":"Building & Trades",
            "subcategory":"Electrical",
            "type":"Services"
        }
    ],
    "sg:phone":"+1 480 966 0800",
    "sg:postcode":"85233",
    "sg:province":"AZ",
    "sg:tags":[
        "electrical",
        "contractor"
    ],
    "wof:name":"Arizona Breaker & Switch",
    "wof:placetype":"venue"
},
  "geometry": {"coordinates":[-111.820273,33.349874],"type":"Point"}
}