{
  "type": "Feature",
  "properties": {
    "iso:country":"US",
    "sg:address":"620 E Butler Ave",
    "sg:city":"Flagstaff",
    "sg:classifiers":[
        {
            "category":"Wholesale",
            "subcategory":"Hardware",
            "type":"Manufacturing & Wholesale Goods"
        },
        {
            "category":"Home & Garden",
            "subcategory":"Garden Supply",
            "type":"Retail Goods"
        },
        {
            "category":"Retail",
            "subcategory":"Repair Shop",
            "type":"Services"
        }
    ],
    "sg:phone":"+1 928 779 2211",
    "sg:postcode":"86001",
    "sg:province":"AZ",
    "sg:tags":[
        "renting",
        "lawn",
        "outdoor",
        "power",
        "landscaping",
        "equipment-sales",
        "equipment",
        "saw"
    ],
    "sg:website":"http://www.stihldealer.net/default-dealer-006137.aspx",
    "wof:name":"AZ Power And Lawn",
    "wof:placetype":"venue"
},
  "geometry": {"coordinates":[-111.642388,35.192539],"type":"Point"}
}