{
  "type": "Feature",
  "properties": {
    "iso:country":"US",
    "sg:address":"14861 N Cave Creek Rd",
    "sg:city":"Phoenix",
    "sg:classifiers":[
        {
            "category":"Health Services",
            "subcategory":"Doctor",
            "type":"Services"
        }
    ],
    "sg:phone":"+1 480 502 0250",
    "sg:postcode":"85032",
    "sg:province":"AZ",
    "sg:tags":[
        "physician",
        "surgeon"
    ],
    "wof:name":"Absolute Rehabilitation Med",
    "wof:placetype":"venue"
},
  "geometry": {"coordinates":[-112.03058900000001,33.62151],"type":"Point"}
}