{
  "type": "Feature",
  "properties": {
    "addr:full":"3336 Roadrunner Dr Lake Havasu City AZ 86406",
    "addr:housenumber":"3336",
    "addr:postcode":"86406",
    "addr:street":"Roadrunner Dr",
    "iso:country":"US",
    "sg:address":"3336 Roadrunner Dr",
    "sg:city":"Lake Havasu City",
    "sg:classifiers":[
        {
            "category":"Building & Trades",
            "subcategory":"Construction",
            "type":"Services"
        }
    ],
    "sg:phone":"+1 928 486 0874",
    "sg:postcode":"86406",
    "sg:province":"AZ",
    "sg:tags":[
        "contractor"
    ],
    "wof:name":"Stucco Tech of Arizona LLC",
    "wof:placetype":"venue"
},
  "geometry": {"coordinates":[-114.280722,34.472515],"type":"Point"}
}