{
  "type": "Feature",
  "properties": {
    "addr:full":"7580 N Rain Valley Rd Flagstaff AZ 86004",
    "addr:housenumber":"7580",
    "addr:postcode":"86004",
    "addr:street":"N Rain Valley Rd",
    "iso:country":"US",
    "sg:address":"7580 N Rain Valley Rd",
    "sg:city":"Flagstaff",
    "sg:classifiers":[
        {
            "category":"Professional",
            "subcategory":"Engineering",
            "type":"Services"
        }
    ],
    "sg:phone":"+1 928 714 0251",
    "sg:postcode":"86004",
    "sg:province":"AZ",
    "sg:tags":[
        "engineer"
    ],
    "wof:name":"C 5 Engineering",
    "wof:placetype":"venue"
},
  "geometry": {"coordinates":[-111.542204,35.249288],"type":"Point"}
}