{
  "type": "Feature",
  "properties": {
    "iso:country":"US",
    "sg:address":"8550 S Hwy 95",
    "sg:city":"Mohave Valley",
    "sg:classifiers":[
        {
            "category":"Insurance",
            "subcategory":"Insurance Agent",
            "type":"Services"
        }
    ],
    "sg:phone":"+1 928 768 4700",
    "sg:postcode":"86440",
    "sg:province":"AZ",
    "wof:name":"Hiestand Troy",
    "wof:placetype":"venue"
},
  "geometry": {"coordinates":[-114.597886,34.907875],"type":"Point"}
}