{
  "type": "Feature",
  "properties": {
    "iso:country":"US",
    "sg:address":"13724 W Glendale Ave",
    "sg:city":"Luke Afb",
    "sg:classifiers":[
        {
            "category":"Arts & Performance",
            "subcategory":"Theater",
            "type":"Entertainment"
        }
    ],
    "sg:phone":"+1 623 935 7335",
    "sg:postcode":"85307",
    "sg:province":"AZ",
    "sg:tags":[
        "entertainer"
    ],
    "wof:name":"Coyote Cabaret",
    "wof:placetype":"venue"
},
  "geometry": {"coordinates":[-112.356874,33.536959],"type":"Point"}
}