{
  "type": "Feature",
  "properties": {
    "iso:country":"US",
    "sg:address":"4202 E Speedway Blvd",
    "sg:city":"Tucson",
    "sg:classifiers":[
        {
            "category":"Retail",
            "subcategory":"Laundry & Dry Cleaning",
            "type":"Services"
        }
    ],
    "sg:phone":"+1 520 326 5335",
    "sg:postcode":"85712",
    "sg:province":"AZ",
    "sg:tags":[
        "rug"
    ],
    "wof:name":"Moroccan Rugs",
    "wof:placetype":"venue"
},
  "geometry": {"coordinates":[-110.90273500000001,32.236106],"type":"Point"}
}