{
  "type": "Feature",
  "properties": {
    "addr:full":"3210 W Donatello Dr Phoenix AZ 85086",
    "addr:housenumber":"3210",
    "addr:postcode":"85086",
    "addr:street":"W Donatello Dr",
    "iso:country":"US",
    "sg:address":"3210 W Donatello Dr",
    "sg:city":"Phoenix",
    "sg:classifiers":[
        {
            "category":"Building & Trades",
            "subcategory":"Construction",
            "type":"Services"
        }
    ],
    "sg:phone":"+1 623 869 9489",
    "sg:postcode":"85086",
    "sg:province":"AZ",
    "sg:tags":[
        "contractor"
    ],
    "wof:name":"Principle Builders",
    "wof:placetype":"venue"
},
  "geometry": {"coordinates":[-112.13042799999999,33.812361],"type":"Point"}
}