{
  "type": "Feature",
  "properties": {
    "iso:country":"US",
    "sg:address":"13936 N 134th Dr",
    "sg:city":"Surprise",
    "sg:classifiers":[
        {
            "category":"Professional",
            "subcategory":"Advertising",
            "type":"Services"
        }
    ],
    "sg:phone":"+1 623 214 7129",
    "sg:postcode":"85379",
    "sg:province":"AZ",
    "wof:name":"Brand Via Alliance Inc",
    "wof:placetype":"venue"
},
  "geometry": {"coordinates":[-112.349297,33.610598],"type":"Point"}
}