{
  "type": "Feature",
  "properties": {
    "iso:country":"US",
    "sg:address":"12409 N Tatum Blvd",
    "sg:city":"Phoenix",
    "sg:classifiers":[
        {
            "category":"Retail",
            "subcategory":"Photofinishing",
            "type":"Services"
        },
        {
            "category":"Shopping",
            "subcategory":"Pharmacy",
            "type":"Retail Goods"
        }
    ],
    "sg:phone":"+1 602 996 7320",
    "sg:postcode":"85032",
    "sg:province":"AZ",
    "sg:tags":[
        "photo",
        "finishing",
        "first",
        "aid",
        "supply"
    ],
    "sg:website":"http://www.cvs.com",
    "wof:name":"CVS/pharmacy",
    "wof:placetype":"venue"
},
  "geometry": {"coordinates":[-111.979996,33.599377],"type":"Point"}
}