{
  "type": "Feature",
  "properties": {
    "iso:country":"US",
    "sg:address":"2232 N 16th St",
    "sg:city":"Phoenix",
    "sg:classifiers":[
        {
            "category":"Organizations",
            "subcategory":"Professional Association",
            "type":"Services"
        }
    ],
    "sg:phone":"+1 602 254 8001",
    "sg:postcode":"85006",
    "sg:province":"AZ",
    "sg:tags":[
        "business",
        "trade"
    ],
    "wof:name":"Ying On Merchants & Labor Assn",
    "wof:placetype":"venue"
},
  "geometry": {"coordinates":[-112.04766100000001,33.472206],"type":"Point"}
}