{
  "type": "Feature",
  "properties": {
    "iso:country":"US",
    "sg:address":"6740 W Indian School Rd",
    "sg:city":"Phoenix",
    "sg:classifiers":[
        {
            "category":"Travel",
            "subcategory":"Travel Agent",
            "type":"Entertainment"
        }
    ],
    "sg:phone":"+1 623 247 6210",
    "sg:postcode":"85033",
    "sg:province":"AZ",
    "sg:tags":[
        "agency",
        "bureau"
    ],
    "wof:name":"A C Travel",
    "wof:placetype":"venue"
},
  "geometry": {"coordinates":[-112.204859,33.494915],"type":"Point"}
}