{
  "type": "Feature",
  "properties": {
    "addr:full":"1459 N Arizona Ave Chandler AZ 85225",
    "addr:housenumber":"1459",
    "addr:postcode":"85225",
    "addr:street":"N Arizona Ave",
    "iso:country":"US",
    "sg:address":"1459 N Arizona Ave",
    "sg:city":"Chandler",
    "sg:classifiers":[
        {
            "category":"Retail",
            "subcategory":"Auto Repair",
            "type":"Services"
        }
    ],
    "sg:phone":"+1 480 786 0861",
    "sg:postcode":"85225",
    "sg:province":"AZ",
    "wof:name":"Paul's Car Care",
    "wof:placetype":"venue"
},
  "geometry": {"coordinates":[-111.841588,33.329521],"type":"Point"}
}