{
  "type": "Feature",
  "properties": {
    "iso:country":"US",
    "sg:address":"680 W Wickenburg Way",
    "sg:city":"Wickenburg",
    "sg:classifiers":[
        {
            "category":"Travel",
            "subcategory":"Hotels & Motels",
            "type":"Entertainment"
        }
    ],
    "sg:phone":"+1 928 684 2493",
    "sg:postcode":"85390",
    "sg:province":"AZ",
    "wof:name":"Westerner Motel",
    "wof:placetype":"venue"
},
  "geometry": {"coordinates":[-112.742786,33.966219],"type":"Point"}
}