{
  "type": "Feature",
  "properties": {
    "iso:country":"US",
    "sg:address":"9221 E Wood Dr",
    "sg:city":"Scottsdale",
    "sg:classifiers":[
        {
            "category":"Recreation",
            "type":"Entertainment"
        }
    ],
    "sg:phone":"+1 480 767 0575",
    "sg:postcode":"85260",
    "sg:province":"AZ",
    "sg:tags":[
        "amusement"
    ],
    "wof:name":"Paraglide School & Store",
    "wof:placetype":"venue"
},
  "geometry": {"coordinates":[-111.880859,33.605892],"type":"Point"}
}