{
  "type": "Feature",
  "properties": {
    "iso:country":"US",
    "sg:address":"8426 E Indian School Rd",
    "sg:city":"Scottsdale",
    "sg:classifiers":[
        {
            "category":"Wholesale",
            "subcategory":"Jewelry",
            "type":"Manufacturing & Wholesale Goods"
        }
    ],
    "sg:phone":"+1 480 990 0880",
    "sg:postcode":"85251",
    "sg:province":"AZ",
    "sg:tags":[
        "diamond"
    ],
    "wof:name":"Geffen International Inc",
    "wof:placetype":"venue"
},
  "geometry": {"coordinates":[-111.898402,33.494956],"type":"Point"}
}