{
  "type": "Feature",
  "properties": {
    "iso:country":"US",
    "sg:address":"4431 S White Mountain Rd",
    "sg:city":"Show Low",
    "sg:classifiers":[
        {
            "category":"Wholesale",
            "subcategory":"Electrical",
            "type":"Manufacturing & Wholesale Goods"
        },
        {
            "category":"Shopping",
            "subcategory":"Computers & Home Electronics",
            "type":"Retail Goods"
        }
    ],
    "sg:phone":"+1 928 532 0462",
    "sg:postcode":"85901",
    "sg:province":"AZ",
    "sg:tags":[
        "equipment",
        "supply",
        "electronic",
        "merchandise",
        "re"
    ],
    "wof:name":"Radio Shack",
    "wof:placetype":"venue"
},
  "geometry": {"coordinates":[-110.02565199999999,34.210877],"type":"Point"}
}