{
  "type": "Feature",
  "properties": {
    "iso:country":"US",
    "sg:address":"3215 W Mountain Dr",
    "sg:city":"Flagstaff",
    "sg:classifiers":[
        {
            "category":"Shopping",
            "subcategory":"Bicycles & Sporting Goods",
            "type":"Retail Goods"
        }
    ],
    "sg:phone":"+1 928 773 8544",
    "sg:postcode":"86001",
    "sg:province":"AZ",
    "wof:name":"Arizona Spoke",
    "wof:placetype":"venue"
},
  "geometry": {"coordinates":[-111.672817,35.238371],"type":"Point"}
}