{
  "type": "Feature",
  "properties": {
    "iso:country":"US",
    "sg:address":"3518 E Grant Rd",
    "sg:city":"Tucson",
    "sg:classifiers":[
        {
            "category":"Education",
            "subcategory":"Special Training",
            "type":"Public Place"
        }
    ],
    "sg:phone":"+1 520 795 8107",
    "sg:postcode":"85716",
    "sg:province":"AZ",
    "sg:tags":[
        "school",
        "interest"
    ],
    "wof:name":"Great Harmony Tai Chi Chuan",
    "wof:placetype":"venue"
},
  "geometry": {"coordinates":[-110.916499,32.250447],"type":"Point"}
}