{
  "type": "Feature",
  "properties": {
    "addr:full":"11435 W Buckeye Rd Avondale AZ 85323",
    "addr:housenumber":"11435",
    "addr:postcode":"85323",
    "addr:street":"W Buckeye Rd",
    "iso:country":"US",
    "sg:address":"11435 W Buckeye Rd",
    "sg:city":"Avondale",
    "sg:classifiers":[
        {
            "category":"Ice Cream",
            "type":"Food & Drink"
        }
    ],
    "sg:menulink":"http://www.allmenus.com/az/phoenix/242965-baskin-robbins/menu/",
    "sg:phone":"+1 623 643 9000",
    "sg:postcode":"85323",
    "sg:province":"AZ",
    "sg:tags":[
        "american"
    ],
    "wof:name":"Baskin-Robbins",
    "wof:placetype":"venue"
},
  "geometry": {"coordinates":[-112.30506800000001,33.435395],"type":"Point"}
}