{
  "type": "Feature",
  "properties": {
    "addr:full":"2295 Bombay Dr Lake Havasu City AZ 86404",
    "addr:housenumber":"2295",
    "addr:postcode":"86404",
    "addr:street":"Bombay Dr",
    "iso:country":"US",
    "sg:address":"2295 Bombay Dr",
    "sg:city":"Lake Havasu City",
    "sg:classifiers":[
        {
            "category":"Building & Trades",
            "subcategory":"Construction",
            "type":"Services"
        }
    ],
    "sg:phone":"+1 928 505 8366",
    "sg:postcode":"86404",
    "sg:province":"AZ",
    "sg:tags":[
        "carpentry",
        "contractor"
    ],
    "wof:name":"Prime Overhead Doors",
    "wof:placetype":"venue"
},
  "geometry": {"coordinates":[-114.33839399999999,34.514281],"type":"Point"}
}