{
  "type": "Feature",
  "properties": {
    "iso:country":"US",
    "sg:address":"3143 N Freeway Industrial Loop",
    "sg:city":"Tucson",
    "sg:classifiers":[
        {
            "category":"Wholesale",
            "subcategory":"Construction Materials",
            "type":"Manufacturing & Wholesale Goods"
        }
    ],
    "sg:phone":"+1 520 623 4100",
    "sg:postcode":"85705",
    "sg:province":"AZ",
    "sg:tags":[
        "concrete",
        "form"
    ],
    "sg:website":"www.bordercorp.com",
    "wof:name":"Border Construction Specialty",
    "wof:placetype":"venue"
},
  "geometry": {"coordinates":[-111.005008,32.264585],"type":"Point"}
}