{
  "type": "Feature",
  "properties": {
    "addr:full":"103 W 4th St Benson AZ 85602",
    "addr:housenumber":"103",
    "addr:postcode":"85602",
    "addr:street":"W 4Th St",
    "iso:country":"US",
    "sg:address":"103 W 4th St",
    "sg:city":"Benson",
    "sg:classifiers":[
        {
            "category":"Retail",
            "subcategory":"Auto Repair",
            "type":"Services"
        }
    ],
    "sg:phone":"+1 520 586 9151",
    "sg:postcode":"85602",
    "sg:province":"AZ",
    "sg:tags":[
        "repairing",
        "automobile"
    ],
    "wof:name":"EGLNBRD Automotive",
    "wof:placetype":"venue"
},
  "geometry": {"coordinates":[-110.30001900000001,31.968939],"type":"Point"}
}