{
  "type": "Feature",
  "properties": {
    "addr:full":"2915 W Altadena Ave Phoenix AZ 85029",
    "addr:housenumber":"2915",
    "addr:postcode":"85029",
    "addr:street":"W Altadena Ave",
    "iso:country":"US",
    "sg:address":"2915 W Altadena Ave",
    "sg:city":"Phoenix",
    "sg:classifiers":[
        {
            "category":"Professional",
            "type":"Services"
        }
    ],
    "sg:phone":"+1 602 548 9148",
    "sg:postcode":"85029",
    "sg:province":"AZ",
    "wof:name":"Miner & Associaites",
    "wof:placetype":"venue"
},
  "geometry": {"coordinates":[-112.123154,33.592372],"type":"Point"}
}