{
  "type": "Feature",
  "properties": {
    "addr:full":"5650 W Desert Cove Ave Glendale AZ 85304",
    "addr:housenumber":"5650",
    "addr:postcode":"85304",
    "addr:street":"W Desert Cove Ave",
    "iso:country":"US",
    "sg:address":"5650 W Desert Cove Ave",
    "sg:city":"Glendale",
    "sg:classifiers":[
        {
            "category":"Home & Garden",
            "subcategory":"Home Furnishings",
            "type":"Retail Goods"
        }
    ],
    "sg:phone":"+1 623 205 6218",
    "sg:postcode":"85304",
    "sg:province":"AZ",
    "sg:tags":[
        "candle"
    ],
    "wof:name":"The Enchanted Chalice Candle Shop",
    "wof:placetype":"venue"
},
  "geometry": {"coordinates":[-112.180899,33.585529],"type":"Point"}
}