{
  "type": "Feature",
  "properties": {
    "iso:country":"US",
    "sg:address":"5032 E Hawthorne St",
    "sg:city":"Tucson",
    "sg:classifiers":[
        {
            "category":"Shopping",
            "subcategory":"Computers & Home Electronics",
            "type":"Retail Goods"
        }
    ],
    "sg:phone":"+1 520 907 3405",
    "sg:postcode":"85711",
    "sg:province":"AZ",
    "sg:tags":[
        "software"
    ],
    "wof:name":"Dick's Computer Concepts",
    "wof:placetype":"venue"
},
  "geometry": {"coordinates":[-110.884684,32.233399],"type":"Point"}
}