{
  "type": "Feature",
  "properties": {
    "iso:country":"US",
    "sg:address":"2447 N Stone Ave",
    "sg:city":"Tucson",
    "sg:classifiers":[
        {
            "category":"Building & Trades",
            "subcategory":"Plumbing",
            "type":"Services"
        }
    ],
    "sg:phone":"+1 520 882 7767",
    "sg:postcode":"85705",
    "sg:province":"AZ",
    "sg:tags":[
        "conditioning",
        "air",
        "system",
        "contractor"
    ],
    "wof:name":"American Home Maintainence",
    "wof:placetype":"venue"
},
  "geometry": {"coordinates":[-110.972005,32.251298],"type":"Point"}
}