{
  "type": "Feature",
  "properties": {
    "iso:country":"US",
    "sg:address":"602 W Baseline Rd",
    "sg:city":"Phoenix",
    "sg:classifiers":[
        {
            "category":"Restaurant",
            "type":"Food & Drink"
        }
    ],
    "sg:phone":"+1 602 276 4051",
    "sg:postcode":"85041",
    "sg:province":"AZ",
    "sg:tags":[
        "eating"
    ],
    "wof:name":"Baseline Cafe",
    "wof:placetype":"venue"
},
  "geometry": {"coordinates":[-112.080476,33.377821],"type":"Point"}
}