{
  "type": "Feature",
  "properties": {
    "iso:country":"US",
    "sg:address":"1253 W Mendoza Ave",
    "sg:city":"Mesa",
    "sg:classifiers":[
        {
            "category":"Professional",
            "subcategory":"Business Services",
            "type":"Services"
        }
    ],
    "sg:phone":"+1 480 831 2134",
    "sg:postcode":"85202",
    "sg:province":"AZ",
    "sg:tags":[
        "spa",
        "hot",
        "merchandise",
        "tubs-repair"
    ],
    "wof:name":"Qualichem Inc",
    "wof:placetype":"venue"
},
  "geometry": {"coordinates":[-111.860665,33.37],"type":"Point"}
}