{
  "type": "Feature",
  "properties": {
    "iso:country":"US",
    "sg:address":"10748 W Bell Rd",
    "sg:city":"Sun City",
    "sg:classifiers":[
        {
            "category":"Travel",
            "subcategory":"Travel Agent",
            "type":"Entertainment"
        }
    ],
    "sg:phone":"+1 623 974 3607",
    "sg:postcode":"85351",
    "sg:province":"AZ",
    "sg:tags":[
        "agency",
        "bureau"
    ],
    "sg:website":"www.suncitytravel.net",
    "wof:name":"Sun City Travel Svc",
    "wof:placetype":"venue"
},
  "geometry": {"coordinates":[-112.301229,33.638464],"type":"Point"}
}