{
  "type": "Feature",
  "properties": {
    "addr:full":"8742 W Coolidge St Phoenix AZ 85037",
    "addr:housenumber":"8742",
    "addr:postcode":"85037",
    "addr:street":"W Coolidge St",
    "iso:country":"US",
    "sg:address":"8742 W Coolidge St",
    "sg:city":"Phoenix",
    "sg:classifiers":[
        {
            "category":"Organizations",
            "subcategory":"Non-profit Organization",
            "type":"Services"
        }
    ],
    "sg:phone":"+1 623 877 7272",
    "sg:postcode":"85037",
    "sg:province":"AZ",
    "wof:name":"Great American Resourses",
    "wof:placetype":"venue"
},
  "geometry": {"coordinates":[-112.250142,33.504918],"type":"Point"}
}