{
  "type": "Feature",
  "properties": {
    "addr:full":"1688 W Adams St Phoenix AZ 85007",
    "addr:housenumber":"1688",
    "addr:postcode":"85007",
    "addr:street":"W Adams St",
    "iso:country":"US",
    "sg:address":"1688 W Adams St",
    "sg:city":"Phoenix",
    "sg:classifiers":[
        {
            "category":"Government",
            "subcategory":"Office",
            "type":"Public Place"
        }
    ],
    "sg:phone":"+1 602 470 8086",
    "sg:postcode":"85007",
    "sg:province":"AZ",
    "wof:name":"Cooperative Extension",
    "wof:placetype":"venue"
},
  "geometry": {"coordinates":[-112.095213,33.449324],"type":"Point"}
}