{
  "type": "Feature",
  "properties": {
    "addr:full":"839 N 102nd St Mesa AZ 85207",
    "addr:housenumber":"839",
    "addr:postcode":"85207",
    "addr:street":"N 102Nd St",
    "iso:country":"US",
    "sg:address":"839 N 102nd St",
    "sg:city":"Mesa",
    "sg:classifiers":[
        {
            "category":"Building & Trades",
            "subcategory":"Construction",
            "type":"Services"
        }
    ],
    "sg:phone":"+1 480 984 6658",
    "sg:postcode":"85207",
    "sg:province":"AZ",
    "sg:tags":[
        "house"
    ],
    "wof:name":"D Cubed Construction LLC",
    "wof:placetype":"venue"
},
  "geometry": {"coordinates":[-111.61086,33.430164],"type":"Point"}
}