{
  "type": "Feature",
  "properties": {
    "iso:country":"US",
    "sg:address":"8996 N Lawndale Dr",
    "sg:city":"Tucson",
    "sg:classifiers":[
        {
            "category":"Banks & Credit Unions",
            "subcategory":"Financial Services",
            "type":"Services"
        }
    ],
    "sg:phone":"+1 520 579 2039",
    "sg:postcode":"85743",
    "sg:province":"AZ",
    "sg:tags":[
        "trust",
        "management"
    ],
    "wof:name":"Snyder Family Revoc Trust",
    "wof:placetype":"venue"
},
  "geometry": {"coordinates":[-111.116659,32.369898],"type":"Point"}
}