{
  "type": "Feature",
  "properties": {
    "addr:full":"2306 E Indian School Rd Phoenix AZ 85016",
    "addr:housenumber":"2306",
    "addr:postcode":"85016",
    "addr:street":"E Indian School Rd",
    "iso:country":"US",
    "sg:address":"2306 E Indian School Rd",
    "sg:city":"Phoenix",
    "sg:classifiers":[
        {
            "category":"Shopping",
            "subcategory":"Florist",
            "type":"Retail Goods"
        }
    ],
    "sg:phone":"+1 602 954 2658",
    "sg:postcode":"85016",
    "sg:province":"AZ",
    "wof:name":"Universal Flowers",
    "wof:placetype":"venue"
},
  "geometry": {"coordinates":[-112.03222,33.494802],"type":"Point"}
}