{
  "type": "Feature",
  "properties": {
    "iso:country":"US",
    "sg:address":"7050 E Main St",
    "sg:city":"Scottsdale",
    "sg:classifiers":[
        {
            "category":"Shopping",
            "subcategory":"Used Merchandise",
            "type":"Retail Goods"
        }
    ],
    "sg:phone":"+1 480 946 9262",
    "sg:postcode":"85251",
    "sg:province":"AZ",
    "sg:tags":[
        "antique"
    ],
    "wof:name":"Pearson Antiques & Imports",
    "wof:placetype":"venue"
},
  "geometry": {"coordinates":[-111.929204,33.493177],"type":"Point"}
}