{
  "type": "Feature",
  "properties": {
    "addr:full":"628 W 5th St Safford AZ 85546",
    "addr:housenumber":"628",
    "addr:postcode":"85546",
    "addr:street":"W 5Th St",
    "iso:country":"US",
    "sg:address":"628 W 5th St",
    "sg:city":"Safford",
    "sg:classifiers":[
        {
            "category":"Wholesale",
            "subcategory":"Auto Parts",
            "type":"Manufacturing & Wholesale Goods"
        }
    ],
    "sg:phone":"+1 928 428 3873",
    "sg:postcode":"85546",
    "sg:province":"AZ",
    "wof:name":"NAPA Auto Parts",
    "wof:placetype":"venue"
},
  "geometry": {"coordinates":[-109.714046,32.834458],"type":"Point"}
}