{
  "type": "Feature",
  "properties": {
    "iso:country":"US",
    "sg:address":"780 S Park Centre Ave",
    "sg:city":"Green Valley",
    "sg:classifiers":[
        {
            "category":"Social Services",
            "subcategory":"Child Care",
            "type":"Services"
        }
    ],
    "sg:phone":"+1 520 625 2273",
    "sg:postcode":"85614",
    "sg:province":"AZ",
    "sg:website":"www.casacanhelp.com",
    "wof:name":"Casa De Esperanza",
    "wof:placetype":"venue"
},
  "geometry": {"coordinates":[-110.976685,31.858202],"type":"Point"}
}