{
  "type": "Feature",
  "properties": {
    "addr:full":"1949 E Broadway Rd Tempe AZ 85282",
    "addr:housenumber":"1949",
    "addr:postcode":"85282",
    "addr:street":"E Broadway Rd",
    "iso:country":"US",
    "sg:address":"1949 E Broadway Rd",
    "sg:city":"Tempe",
    "sg:classifiers":[
        {
            "category":"Professional",
            "subcategory":"Accounting & Tax Preparation",
            "type":"Services"
        }
    ],
    "sg:phone":"+1 480 820 4419",
    "sg:postcode":"85282",
    "sg:province":"AZ",
    "sg:tags":[
        "accountant"
    ],
    "wof:name":"Preston & Co",
    "wof:placetype":"venue"
},
  "geometry": {"coordinates":[-111.90419199999999,33.4075],"type":"Point"}
}