{
  "type": "Feature",
  "properties": {
    "iso:country":"US",
    "sg:address":"1720 S Los Feliz Dr",
    "sg:city":"Tempe",
    "sg:classifiers":[
        {
            "category":"Wholesale",
            "subcategory":"Construction Materials",
            "type":"Manufacturing & Wholesale Goods"
        },
        {
            "category":"Wholesale",
            "subcategory":"Machinery & Supplies",
            "type":"Manufacturing & Wholesale Goods"
        },
        {
            "category":"Home & Garden",
            "subcategory":"Building Materials",
            "type":"Retail Goods"
        },
        {
            "category":"Manufacturing",
            "subcategory":"Tools & Machinery",
            "type":"Manufacturing & Wholesale Goods"
        },
        {
            "category":"Wholesale",
            "subcategory":"Home Furnishings",
            "type":"Manufacturing & Wholesale Goods"
        },
        {
            "category":"Professional",
            "subcategory":"Engineering",
            "type":"Services"
        }
    ],
    "sg:phone":"+1 480 921 7860",
    "sg:postcode":"85281",
    "sg:province":"AZ",
    "sg:tags":[
        "heater",
        "valve",
        "fixture",
        "system",
        "water",
        "equipment",
        "part",
        "plumbing",
        "fixtures",
        "supplies-wholesale",
        "air conditioning",
        "manufacturer"
    ],
    "sg:website":"http://www-ferguson-com.netsolads.com/index.shtml?_nsag=39482",
    "wof:name":"Ferguson",
    "wof:placetype":"venue"
},
  "geometry": {"coordinates":[-111.904169,33.409791],"type":"Point"}
}