{
  "type": "Feature",
  "properties": {
    "iso:country":"US",
    "sg:address":"6401 W Chandler Blvd",
    "sg:city":"Chandler",
    "sg:classifiers":[
        {
            "category":"Restaurant",
            "type":"Food & Drink"
        }
    ],
    "sg:phone":"+1 480 763 8100",
    "sg:postcode":"85226",
    "sg:province":"AZ",
    "sg:tags":[
        "eating"
    ],
    "wof:name":"Wonderful Wandas LLC",
    "wof:placetype":"venue"
},
  "geometry": {"coordinates":[-111.952147,33.305239],"type":"Point"}
}