{
  "type": "Feature",
  "properties": {
    "iso:country":"US",
    "sg:address":"6812 E Cave Creek Rd",
    "sg:city":"Cave Creek",
    "sg:classifiers":[
        {
            "category":"Home & Garden",
            "subcategory":"Furniture",
            "type":"Retail Goods"
        }
    ],
    "sg:phone":"+1 480 595 8755",
    "sg:postcode":"85331",
    "sg:province":"AZ",
    "sg:tags":[
        "builder",
        "custom"
    ],
    "wof:name":"Killer Creek Furnishings",
    "wof:placetype":"venue"
},
  "geometry": {"coordinates":[-111.93463,33.83193],"type":"Point"}
}