{
  "type": "Feature",
  "properties": {
    "addr:full":"211 Cll Francesca Sedona AZ 86336",
    "addr:housenumber":"211",
    "addr:postcode":"86336",
    "addr:street":"Cll Francesca",
    "iso:country":"US",
    "sg:address":"211 Cll Francesca",
    "sg:city":"Sedona",
    "sg:classifiers":[
        {
            "category":"Professional",
            "type":"Services"
        }
    ],
    "sg:phone":"+1 928 204 1999",
    "sg:postcode":"86336",
    "sg:province":"AZ",
    "sg:tags":[
        "establishment"
    ],
    "wof:name":"Crimson View",
    "wof:placetype":"venue"
},
  "geometry": {"coordinates":[-111.779808,34.86957],"type":"Point"}
}