{
  "type": "Feature",
  "properties": {
    "iso:country":"US",
    "sg:address":"8021 N 43rd Ave",
    "sg:city":"Phoenix",
    "sg:classifiers":[
        {
            "category":"Place Of Worship",
            "subcategory":"Church",
            "type":"Public Place"
        },
        {
            "category":"Place Of Worship",
            "type":"Public Place"
        },
        {
            "category":"Organizations",
            "subcategory":"Religious Organization",
            "type":"Services"
        }
    ],
    "sg:phone":"+1 623 847 6700",
    "sg:postcode":"85051",
    "sg:province":"AZ",
    "sg:tags":[
        "churches-pentecostal-independent",
        "churches-pentecostal"
    ],
    "wof:name":"Forward In Faith Ministries",
    "wof:placetype":"venue"
},
  "geometry": {"coordinates":[-112.15158,33.55379],"type":"Point"}
}