{
  "type": "Feature",
  "properties": {
    "addr:full":"5520 W Maricopa St Ste 102 Phoenix AZ 85043",
    "addr:housenumber":"5520",
    "addr:postcode":"85043",
    "addr:street":"W Maricopa St Ste 102",
    "iso:country":"US",
    "sg:address":"5520 W Maricopa St Ste 102",
    "sg:city":"Phoenix",
    "sg:classifiers":[
        {
            "category":"Wholesale",
            "subcategory":"Machinery & Supplies",
            "type":"Manufacturing & Wholesale Goods"
        },
        {
            "category":"Home & Garden",
            "subcategory":"Furniture",
            "type":"Retail Goods"
        }
    ],
    "sg:phone":"+1 602 447 8084",
    "sg:postcode":"85043",
    "sg:province":"AZ",
    "sg:tags":[
        "used",
        "machinery-new",
        "store"
    ],
    "sg:website":"http://www.ethanallen.com",
    "wof:name":"Ethan Allen Warehouse/Svc Ctr",
    "wof:placetype":"venue"
},
  "geometry": {"coordinates":[-112.17845199999999,33.438399],"type":"Point"}
}