{
  "type": "Feature",
  "properties": {
    "iso:country":"US",
    "sg:address":"7720 E Redfield Rd",
    "sg:city":"Scottsdale",
    "sg:classifiers":[
        {
            "category":"Real Estate",
            "subcategory":"Real Estate Agent",
            "type":"Services"
        }
    ],
    "sg:phone":"+1 480 991 2288",
    "sg:postcode":"85260",
    "sg:province":"AZ",
    "wof:name":"Recorp-Frnklin Assoc Ltd Prtnr",
    "wof:placetype":"venue"
},
  "geometry": {"coordinates":[-111.91219,33.614013],"type":"Point"}
}