{
  "type": "Feature",
  "properties": {
    "addr:full":"2727 Beverly Ave Kingman AZ 86409",
    "addr:housenumber":"2727",
    "addr:postcode":"86409",
    "addr:street":"Beverly Ave",
    "iso:country":"US",
    "sg:address":"2727 Beverly Ave",
    "sg:city":"Kingman",
    "sg:classifiers":[
        {
            "category":"Autos & Motor Vehicles",
            "subcategory":"Auto Supplies",
            "type":"Retail Goods"
        }
    ],
    "sg:phone":"+1 928 757 9255",
    "sg:postcode":"86409",
    "sg:province":"AZ",
    "sg:tags":[
        "tire"
    ],
    "sg:website":"www.goodyear.com",
    "wof:name":"Great West Goodyear",
    "wof:placetype":"venue"
},
  "geometry": {"coordinates":[-114.01208800000001,35.219566],"type":"Point"}
}