{
  "type": "Feature",
  "properties": {
    "iso:country":"US",
    "sg:address":"2310 W Sherman St",
    "sg:city":"Phoenix",
    "sg:classifiers":[
        {
            "category":"Home & Garden",
            "subcategory":"Building Materials",
            "type":"Retail Goods"
        }
    ],
    "sg:phone":"+1 602 252 1171",
    "sg:postcode":"85009",
    "sg:province":"AZ",
    "sg:tags":[
        "granite"
    ],
    "sg:website":"http://www.aracruzgranite.com",
    "wof:name":"Aracruz International Granite",
    "wof:placetype":"venue"
},
  "geometry": {"coordinates":[-112.10893799999999,33.440601],"type":"Point"}
}