{
  "type": "Feature",
  "properties": {
    "iso:country":"US",
    "sg:address":"17300 N Sun Village Pkwy",
    "sg:city":"Surprise",
    "sg:classifiers":[
        {
            "category":"Shopping",
            "subcategory":"Computers & Home Electronics",
            "type":"Retail Goods"
        }
    ],
    "sg:phone":"+1 623 584 6904",
    "sg:postcode":"85374",
    "sg:province":"AZ",
    "wof:name":"Sun Village Assoc For Computer",
    "wof:placetype":"venue"
},
  "geometry": {"coordinates":[-112.368574,33.641038],"type":"Point"}
}