{
  "type": "Feature",
  "properties": {
    "iso:country":"US",
    "sg:address":"3502 W Union Hills Dr",
    "sg:city":"Glendale",
    "sg:classifiers":[
        {
            "category":"Food & Beverages",
            "subcategory":"Groceries & Convenience Stores",
            "type":"Retail Goods"
        }
    ],
    "sg:phone":"+1 623 869 7683",
    "sg:postcode":"85308",
    "sg:province":"AZ",
    "sg:tags":[
        "station",
        "gasoline"
    ],
    "wof:name":"Circle K",
    "wof:placetype":"venue"
},
  "geometry": {"coordinates":[-112.136736,33.654706],"type":"Point"}
}