{
  "type": "Feature",
  "properties": {
    "iso:country":"US",
    "sg:address":"4636 E University Dr # 255",
    "sg:city":"Phoenix",
    "sg:classifiers":[
        {
            "category":"Professional",
            "subcategory":"Management & Consulting",
            "type":"Services"
        },
        {
            "category":"Professional",
            "subcategory":"Employment Agencies",
            "type":"Services"
        }
    ],
    "sg:phone":"+1 602 266 5600",
    "sg:postcode":"85034",
    "sg:province":"AZ",
    "sg:tags":[
        "consultant",
        "search",
        "executive",
        "opportunity"
    ],
    "sg:website":"http://www.fishelhr.com",
    "wof:name":"Fishel & Bocker Hr Associates, Inc",
    "wof:placetype":"venue"
},
  "geometry": {"coordinates":[-111.982211,33.421879],"type":"Point"}
}