{
  "type": "Feature",
  "properties": {
    "iso:country":"US",
    "sg:address":"2115 W Mountain View Rd",
    "sg:city":"Phoenix",
    "sg:classifiers":[
        {
            "category":"Shopping",
            "subcategory":"Crafts & Fabrics",
            "type":"Retail Goods"
        }
    ],
    "sg:phone":"+1 602 278 1427",
    "sg:postcode":"85021",
    "sg:province":"AZ",
    "sg:tags":[
        "art",
        "supply"
    ],
    "wof:name":"Wholesale Baskets Unlimited",
    "wof:placetype":"venue"
},
  "geometry": {"coordinates":[-112.104538,33.574821],"type":"Point"}
}