{
  "type": "Feature",
  "properties": {
    "iso:country":"US",
    "sg:address":"1706 W 10th Pl",
    "sg:city":"Tempe",
    "sg:classifiers":[
        {
            "category":"Home & Garden",
            "subcategory":"Hardware",
            "type":"Retail Goods"
        }
    ],
    "sg:phone":"+1 480 829 3899",
    "sg:postcode":"85281",
    "sg:province":"AZ",
    "sg:tags":[
        "tool",
        "used"
    ],
    "wof:name":"Integrity Mold",
    "wof:placetype":"venue"
},
  "geometry": {"coordinates":[-111.969351,33.417612],"type":"Point"}
}