{
  "type": "Feature",
  "properties": {
    "iso:country":"US",
    "sg:address":"2850 W Ina Rd",
    "sg:city":"Tucson",
    "sg:classifiers":[
        {
            "category":"Home & Garden",
            "subcategory":"Furniture",
            "type":"Retail Goods"
        }
    ],
    "sg:phone":"+1 520 531 0090",
    "sg:postcode":"85741",
    "sg:province":"AZ",
    "wof:name":"Tres Amigos World Imports",
    "wof:placetype":"venue"
},
  "geometry": {"coordinates":[-111.026322,32.337425],"type":"Point"}
}