{
  "type": "Feature",
  "properties": {
    "iso:country":"US",
    "sg:address":"405 White Spar Rd",
    "sg:city":"Prescott",
    "sg:classifiers":[
        {
            "category":"Health Services",
            "subcategory":"Chiropractor",
            "type":"Services"
        }
    ],
    "sg:phone":"+1 928 776 8949",
    "sg:postcode":"86303",
    "sg:province":"AZ",
    "sg:tags":[
        "chiropractic"
    ],
    "wof:name":"Family Chiropractic Healt",
    "wof:placetype":"venue"
},
  "geometry": {"coordinates":[-112.473651,34.530519],"type":"Point"}
}