{
  "type": "Feature",
  "properties": {
    "iso:country":"US",
    "sg:address":"209 S Stellar Pkwy",
    "sg:city":"Chandler",
    "sg:classifiers":[
        {
            "category":"Professional",
            "type":"Services"
        }
    ],
    "sg:phone":"+1 480 785 2032",
    "sg:postcode":"85226",
    "sg:province":"AZ",
    "wof:name":"Accelerated Facilities Corp",
    "wof:placetype":"venue"
},
  "geometry": {"coordinates":[-111.918696,33.299786],"type":"Point"}
}