{
  "type": "Feature",
  "properties": {
    "iso:country":"US",
    "sg:address":"8132 W Sherman St",
    "sg:city":"Tolleson",
    "sg:classifiers":[
        {
            "category":"Manufacturing",
            "subcategory":"Building Materials",
            "type":"Manufacturing & Wholesale Goods"
        }
    ],
    "sg:phone":"+1 602 252 1772",
    "sg:postcode":"85353",
    "sg:province":"AZ",
    "sg:tags":[
        "member",
        "mfg",
        "wood",
        "structural"
    ],
    "wof:name":"Trutrus",
    "wof:placetype":"venue"
},
  "geometry": {"coordinates":[-112.235619,33.440754],"type":"Point"}
}