{
  "type": "Feature",
  "properties": {
    "addr:full":"14614 N Bowman Rd Tucson AZ 85739",
    "addr:housenumber":"14614",
    "addr:postcode":"85739",
    "addr:street":"N Bowman Rd",
    "iso:country":"US",
    "sg:address":"14614 N Bowman Rd",
    "sg:city":"Tucson",
    "sg:classifiers":[
        {
            "category":"Building & Trades",
            "subcategory":"Landscaping Services",
            "type":"Services"
        },
        {
            "category":"Home & Garden",
            "subcategory":"Garden Supply",
            "type":"Retail Goods"
        },
        {
            "category":"Manufacturing",
            "subcategory":"Paper Products",
            "type":"Manufacturing & Wholesale Goods"
        }
    ],
    "sg:phone":"+1 520 825 1470",
    "sg:postcode":"85739",
    "sg:province":"AZ",
    "sg:tags":[
        "lawn",
        "gardening",
        "tree",
        "nursery",
        "maintenance",
        "bamboo"
    ],
    "wof:name":"Best Trimming",
    "wof:placetype":"venue"
},
  "geometry": {"coordinates":[-110.910027,32.471111],"type":"Point"}
}