{
  "type": "Feature",
  "properties": {
    "iso:country":"US",
    "sg:address":"9024 W Thomas Road",
    "sg:city":"Phoenix",
    "sg:classifiers":[
        {
            "category":"Restaurant",
            "type":"Food & Drink"
        }
    ],
    "sg:phone":"+1 623 772 6688",
    "sg:postcode":"85037",
    "sg:province":"AZ",
    "sg:tags":[
        "pizza"
    ],
    "sg:website":"www.palermos.com",
    "wof:name":"Palermos Pizza",
    "wof:placetype":"venue"
},
  "geometry": {"coordinates":[-112.253746,33.479811],"type":"Point"}
}