{
  "type": "Feature",
  "properties": {
    "iso:country":"US",
    "sg:address":"6040 N 7th St",
    "sg:city":"Phoenix",
    "sg:classifiers":[
        {
            "category":"Health Services",
            "subcategory":"Clinic",
            "type":"Services"
        }
    ],
    "sg:phone":"+1 602 266 2203",
    "sg:postcode":"85014",
    "sg:province":"AZ",
    "sg:tags":[
        "home"
    ],
    "wof:name":"Quality Staffing Svc Home Care",
    "wof:placetype":"venue"
},
  "geometry": {"coordinates":[-112.065073,33.526644],"type":"Point"}
}