{
  "type": "Feature",
  "properties": {
    "iso:country":"US",
    "sg:address":"8545 E Pepper Tree Ln",
    "sg:city":"Scottsdale",
    "sg:classifiers":[
        {
            "category":"Utilities",
            "subcategory":"Mobile Phone",
            "type":"Services"
        }
    ],
    "sg:phone":"+1 480 443 0687",
    "sg:postcode":"85250",
    "sg:province":"AZ",
    "sg:tags":[
        "telephone",
        "cellular"
    ],
    "wof:name":"Phi Leasing Inc",
    "wof:placetype":"venue"
},
  "geometry": {"coordinates":[-111.896778,33.537499],"type":"Point"}
}