{
  "type": "Feature",
  "properties": {
    "iso:country":"US",
    "sg:address":"4256 N Brown Ave",
    "sg:city":"Scottsdale",
    "sg:classifiers":[
        {
            "category":"Shopping",
            "subcategory":"Department Store",
            "type":"Retail Goods"
        }
    ],
    "sg:phone":"+1 480 829 9560",
    "sg:postcode":"85251",
    "sg:province":"AZ",
    "wof:name":"Arizona General Stores",
    "wof:placetype":"venue"
},
  "geometry": {"coordinates":[-111.924289,33.498782],"type":"Point"}
}