{
  "type": "Feature",
  "properties": {
    "iso:country":"US",
    "sg:address":"19 W Main St",
    "sg:city":"Mesa",
    "sg:classifiers":[
        {
            "category":"Recreation",
            "type":"Entertainment"
        }
    ],
    "sg:phone":"+1 480 733 5939",
    "sg:postcode":"85201",
    "sg:province":"AZ",
    "sg:tags":[
        "club",
        "travel"
    ],
    "wof:name":"T J's Travel Club For Seniors",
    "wof:placetype":"venue"
},
  "geometry": {"coordinates":[-111.832256,33.415028],"type":"Point"}
}