{
  "type": "Feature",
  "properties": {
    "addr:full":"1837 N 27th Ave Phoenix AZ 85009",
    "addr:housenumber":"1837",
    "addr:postcode":"85009",
    "addr:street":"N 27Th Ave",
    "iso:country":"US",
    "sg:address":"1837 N 27th Ave",
    "sg:city":"Phoenix",
    "sg:classifiers":[
        {
            "category":"Manufacturing",
            "subcategory":"Tools & Machinery",
            "type":"Manufacturing & Wholesale Goods"
        }
    ],
    "sg:phone":"+1 602 269 9108",
    "sg:postcode":"85009",
    "sg:province":"AZ",
    "sg:tags":[
        "contractor"
    ],
    "wof:name":"American Chain",
    "wof:placetype":"venue"
},
  "geometry": {"coordinates":[-112.117057,33.466691],"type":"Point"}
}