{
  "type": "Feature",
  "properties": {
    "iso:country":"US",
    "sg:address":"13832 N 32nd St Ste E-1",
    "sg:city":"Phoenix",
    "sg:classifiers":[
        {
            "category":"Insurance",
            "subcategory":"Title Insurance",
            "type":"Services"
        }
    ],
    "sg:phone":"+1 602 788 5802",
    "sg:postcode":"85032",
    "sg:province":"AZ",
    "sg:tags":[
        "mortgage"
    ],
    "sg:website":"http://www.stewartaz.com",
    "wof:name":"Stewart Title",
    "wof:placetype":"venue"
},
  "geometry": {"coordinates":[-112.013268,33.61285],"type":"Point"}
}