{
  "type": "Feature",
  "properties": {
    "iso:country":"US",
    "sg:address":"15115 N Brenda Dr",
    "sg:city":"Prescott",
    "sg:classifiers":[
        {
            "category":"Building & Trades",
            "subcategory":"Construction",
            "type":"Services"
        }
    ],
    "sg:phone":"+1 928 708 0849",
    "sg:postcode":"86305",
    "sg:province":"AZ",
    "sg:tags":[
        "house"
    ],
    "wof:name":"D Bar K Construction Corp",
    "wof:placetype":"venue"
},
  "geometry": {"coordinates":[-112.547124,34.763025],"type":"Point"}
}