{
  "type": "Feature",
  "properties": {
    "iso:country":"US",
    "sg:address":"401 E Ray Rd",
    "sg:city":"Chandler",
    "sg:classifiers":[
        {
            "category":"Building & Trades",
            "subcategory":"Construction",
            "type":"Services"
        }
    ],
    "sg:phone":"+1 480 855 9988",
    "sg:postcode":"85225",
    "sg:province":"AZ",
    "sg:tags":[
        "tile",
        "dealer"
    ],
    "wof:name":"Monterrey Tile Co",
    "wof:placetype":"venue"
},
  "geometry": {"coordinates":[-111.833934,33.320631],"type":"Point"}
}