{
  "type": "Feature",
  "properties": {
    "iso:country":"US",
    "sg:address":"2334 N 1st Ave",
    "sg:city":"Tucson",
    "sg:classifiers":[
        {
            "category":"Deli",
            "type":"Food & Drink"
        }
    ],
    "sg:menulink":"http://www.allmenus.com/az/tucson/284691-sausage-deli/menu/",
    "sg:phone":"+1 520 623 8182",
    "sg:postcode":"85719",
    "sg:province":"AZ",
    "sg:tags":[
        "american"
    ],
    "wof:name":"Sausage Deli",
    "wof:placetype":"venue"
},
  "geometry": {"coordinates":[-110.960584,32.249814],"type":"Point"}
}