{
  "type": "Feature",
  "properties": {
    "iso:country":"US",
    "sg:address":"5015 W Royal Palm Rd",
    "sg:city":"Glendale",
    "sg:classifiers":[
        {
            "category":"Building & Trades",
            "subcategory":"Electrical",
            "type":"Services"
        }
    ],
    "sg:phone":"+1 623 435 1176",
    "sg:postcode":"85302",
    "sg:province":"AZ",
    "sg:tags":[
        "electrical",
        "contractor"
    ],
    "wof:name":"Ashley Electric Service",
    "wof:placetype":"venue"
},
  "geometry": {"coordinates":[-112.167294,33.556092],"type":"Point"}
}