{
  "type": "Feature",
  "properties": {
    "iso:country":"US",
    "sg:address":"8399 E Indian School Rd",
    "sg:city":"Scottsdale",
    "sg:classifiers":[
        {
            "category":"Professional",
            "subcategory":"Accounting & Tax Preparation",
            "type":"Services"
        }
    ],
    "sg:phone":"+1 480 945 9070",
    "sg:postcode":"85251",
    "sg:province":"AZ",
    "sg:tags":[
        "return",
        "filing"
    ],
    "wof:name":"Morici & Tanner",
    "wof:placetype":"venue"
},
  "geometry": {"coordinates":[-111.90192999999999,33.494875],"type":"Point"}
}