{
  "type": "Feature",
  "properties": {
    "addr:full":"106 E Mckellips Rd Mesa AZ 85201",
    "addr:housenumber":"106",
    "addr:postcode":"85201",
    "addr:street":"E Mckellips Rd",
    "iso:country":"US",
    "sg:address":"106 E Mckellips Rd",
    "sg:city":"Mesa",
    "sg:classifiers":[
        {
            "category":"Social Services",
            "type":"Services"
        },
        {
            "category":"Shopping",
            "subcategory":"Used Merchandise",
            "type":"Retail Goods"
        },
        {
            "category":"Banks & Credit Unions",
            "subcategory":"Bank",
            "type":"Services"
        },
        {
            "category":"Shopping",
            "subcategory":"Thrift Store",
            "type":"Retail Goods"
        },
        {
            "category":"Organizations",
            "subcategory":"Non-profit Organization",
            "type":"Services"
        }
    ],
    "sg:phone":"+1 480 835 8900",
    "sg:postcode":"85201",
    "sg:province":"AZ",
    "sg:tags":[
        "shop",
        "foundations-educational",
        "philanthropic",
        "research",
        "resale",
        "second",
        "hand",
        "furniture",
        "charity"
    ],
    "sg:website":"http://www.goodwill.org",
    "wof:name":"Goodwill Stores",
    "wof:placetype":"venue"
},
  "geometry": {"coordinates":[-111.82832500000001,33.451487],"type":"Point"}
}