{
  "type": "Feature",
  "properties": {
    "addr:full":"103 W Concorda Dr Tempe AZ 85282",
    "addr:housenumber":"103",
    "addr:postcode":"85282",
    "addr:street":"W Concorda Dr",
    "iso:country":"US",
    "sg:address":"103 W Concorda Dr",
    "sg:city":"Tempe",
    "sg:classifiers":[
        {
            "category":"Shopping",
            "subcategory":"Hobbies, Toys, & Games",
            "type":"Retail Goods"
        }
    ],
    "sg:phone":"+1 480 628 7407",
    "sg:postcode":"85282",
    "sg:province":"AZ",
    "sg:tags":[
        "model",
        "supply"
    ],
    "wof:name":"Archicraft",
    "wof:placetype":"venue"
},
  "geometry": {"coordinates":[-111.942227,33.401929],"type":"Point"}
}