{
  "type": "Feature",
  "properties": {
    "addr:full":"850 W Valencia Rd Tucson AZ 85706",
    "addr:housenumber":"850",
    "addr:postcode":"85706",
    "addr:street":"W Valencia Rd",
    "iso:country":"US",
    "sg:address":"850 W Valencia Rd",
    "sg:city":"Tucson",
    "sg:classifiers":[
        {
            "category":"Shopping",
            "subcategory":"Department Store",
            "type":"Retail Goods"
        }
    ],
    "sg:phone":"+1 520 294 7611",
    "sg:postcode":"85706",
    "sg:province":"AZ",
    "sg:tags":[
        "discount"
    ],
    "wof:name":"Kmart",
    "wof:placetype":"venue"
},
  "geometry": {"coordinates":[-110.983619,32.134014],"type":"Point"}
}