{
  "type": "Feature",
  "properties": {
    "iso:country":"US",
    "sg:address":"3750 E Enid Cir",
    "sg:city":"Mesa",
    "sg:classifiers":[
        {
            "category":"Building & Trades",
            "subcategory":"Construction",
            "type":"Services"
        }
    ],
    "sg:phone":"+1 480 218 0047",
    "sg:postcode":"85206",
    "sg:province":"AZ",
    "sg:tags":[
        "coping",
        "plastering",
        "tiling",
        "pool",
        "swimming"
    ],
    "wof:name":"Seven C's Pool Svc & Repair",
    "wof:placetype":"venue"
},
  "geometry": {"coordinates":[-111.74986800000001,33.39859],"type":"Point"}
}