{
  "type": "Feature",
  "properties": {
    "iso:country":"US",
    "sg:address":"2225 S Price Rd",
    "sg:city":"Chandler",
    "sg:classifiers":[
        {
            "category":"Manufacturing",
            "subcategory":"Chemicals & Compounds",
            "type":"Manufacturing & Wholesale Goods"
        }
    ],
    "sg:phone":"+1 602 531 5676",
    "sg:postcode":"85286",
    "sg:province":"AZ",
    "sg:tags":[
        "preparation",
        "pharmaceutical",
        "mfg"
    ],
    "wof:name":"Isagenix International",
    "wof:placetype":"venue"
},
  "geometry": {"coordinates":[-111.889191,33.275999],"type":"Point"}
}