{
  "type": "Feature",
  "properties": {
    "iso:country":"US",
    "sg:address":"16437 N 47th Ave",
    "sg:city":"Glendale",
    "sg:classifiers":[
        {
            "category":"Travel",
            "subcategory":"Travel Agent",
            "type":"Entertainment"
        }
    ],
    "sg:phone":"+1 602 938 0633",
    "sg:postcode":"85306",
    "sg:province":"AZ",
    "sg:tags":[
        "operator",
        "tour",
        "promoter",
        "tours-operators"
    ],
    "wof:name":"Explorer Tours Inc",
    "wof:placetype":"venue"
},
  "geometry": {"coordinates":[-112.160027,33.635712],"type":"Point"}
}