{
  "type": "Feature",
  "properties": {
    "addr:full":"1670 N Country Club Rd Tucson AZ 85716",
    "addr:housenumber":"1670",
    "addr:postcode":"85716",
    "addr:street":"N Country Club Rd",
    "iso:country":"US",
    "sg:address":"1670 N Country Club Rd",
    "sg:city":"Tucson",
    "sg:classifiers":[
        {
            "category":"Professional",
            "subcategory":"Lawyer & Legal Services",
            "type":"Services"
        }
    ],
    "sg:phone":"+1 520 327 9456",
    "sg:postcode":"85716",
    "sg:province":"AZ",
    "sg:tags":[
        "attorney"
    ],
    "wof:name":"James R Beaman",
    "wof:placetype":"venue"
},
  "geometry": {"coordinates":[-110.926704,32.242],"type":"Point"}
}