{
  "type": "Feature",
  "properties": {
    "addr:full":"1455 West Southern Avenue Mesa AZ 85210",
    "addr:housenumber":"1455",
    "addr:postcode":"85210",
    "addr:street":"West Southern Avenue",
    "iso:country":"US",
    "sg:address":"1455 West Southern Avenue",
    "sg:city":"Mesa",
    "sg:classifiers":[
        {
            "category":"Recreation",
            "type":"Entertainment"
        }
    ],
    "sg:phone":"+1 480 615 2748",
    "sg:postcode":"85210",
    "sg:province":"AZ",
    "sg:tags":[
        "active",
        "life"
    ],
    "sg:website":"dickssportinggoods.com",
    "wof:name":"Dick's Sporting Goods",
    "wof:placetype":"venue"
},
  "geometry": {"coordinates":[-111.86295,33.390232],"type":"Point"}
}