{
  "type": "Feature",
  "properties": {
    "iso:country":"US",
    "sg:address":"15231 N Northsight Blvd",
    "sg:city":"Scottsdale",
    "sg:classifiers":[
        {
            "category":"Home & Garden",
            "subcategory":"Furniture",
            "type":"Retail Goods"
        }
    ],
    "sg:phone":"+1 480 807 8181",
    "sg:postcode":"85260",
    "sg:province":"AZ",
    "sg:tags":[
        "mattress"
    ],
    "wof:name":"My Comfort",
    "wof:placetype":"venue"
},
  "geometry": {"coordinates":[-111.896019,33.623316],"type":"Point"}
}