{
  "type": "Feature",
  "properties": {
    "iso:country":"US",
    "sg:address":"1308 Navajo Blvd",
    "sg:city":"Holbrook",
    "sg:classifiers":[
        {
            "category":"Travel",
            "subcategory":"Hotels & Motels",
            "type":"Entertainment"
        }
    ],
    "sg:phone":"+1 928 524 1466",
    "sg:postcode":"86025",
    "sg:province":"AZ",
    "wof:name":"Holiday Inn Exp-Navajo Bvd",
    "wof:placetype":"venue"
},
  "geometry": {"coordinates":[-110.154148,34.915465],"type":"Point"}
}