{
  "type": "Feature",
  "properties": {
    "addr:full":"3337 W Orangewood Ave Phoenix AZ 85051",
    "addr:housenumber":"3337",
    "addr:postcode":"85051",
    "addr:street":"W Orangewood Ave",
    "iso:country":"US",
    "sg:address":"3337 W Orangewood Ave",
    "sg:city":"Phoenix",
    "sg:classifiers":[
        {
            "category":"Building & Trades",
            "subcategory":"Landscaping Services",
            "type":"Services"
        }
    ],
    "sg:phone":"+1 602 841 0999",
    "sg:postcode":"85051",
    "sg:province":"AZ",
    "sg:tags":[
        "landscape",
        "contractor"
    ],
    "wof:name":"J & D Lawn and Maintenance",
    "wof:placetype":"venue"
},
  "geometry": {"coordinates":[-112.13162,33.545753],"type":"Point"}
}