{
  "type": "Feature",
  "properties": {
    "iso:country":"US",
    "sg:address":"988 Sycamore Ave",
    "sg:city":"Kingman",
    "sg:classifiers":[
        {
            "category":"Health Services",
            "subcategory":"Doctor",
            "type":"Services"
        }
    ],
    "sg:phone":"+1 928 757 3223",
    "sg:postcode":"86409",
    "sg:province":"AZ",
    "sg:tags":[
        "dentist"
    ],
    "wof:name":"Bryan K Carlson DDS",
    "wof:placetype":"venue"
},
  "geometry": {"coordinates":[-114.040157,35.22219],"type":"Point"}
}