{
  "type": "Feature",
  "properties": {
    "addr:full":"2987 W Elliot Rd Chandler AZ 85224",
    "addr:housenumber":"2987",
    "addr:postcode":"85224",
    "addr:street":"W Elliot Rd",
    "iso:country":"US",
    "sg:address":"2987 W Elliot Rd",
    "sg:city":"Chandler",
    "sg:classifiers":[
        {
            "category":"Health Services",
            "subcategory":"Dentist",
            "type":"Services"
        }
    ],
    "sg:phone":"+1 480 963 6300",
    "sg:postcode":"85224",
    "sg:province":"AZ",
    "wof:name":"Elliott Anita W DDS",
    "wof:placetype":"venue"
},
  "geometry": {"coordinates":[-111.892506,33.348682],"type":"Point"}
}