{
  "type": "Feature",
  "properties": {
    "iso:country":"US",
    "sg:address":"4320 W Thunderbird Rd",
    "sg:city":"Glendale",
    "sg:classifiers":[
        {
            "category":"Food & Beverages",
            "subcategory":"Groceries & Convenience Stores",
            "type":"Retail Goods"
        }
    ],
    "sg:phone":"+1 602 547 5567",
    "sg:postcode":"85306",
    "sg:province":"AZ",
    "wof:name":"Albertson Foodstore",
    "wof:placetype":"venue"
},
  "geometry": {"coordinates":[-112.154459,33.610806],"type":"Point"}
}