{
  "type": "Feature",
  "properties": {
    "iso:country":"US",
    "sg:address":"1870 McCulloch Blvd N",
    "sg:city":"Lake Havasu City",
    "sg:classifiers":[
        {
            "category":"Shopping",
            "subcategory":"Pharmacy",
            "type":"Retail Goods"
        }
    ],
    "sg:phone":"+1 928 855 2145",
    "sg:postcode":"86403",
    "sg:province":"AZ",
    "wof:name":"Havasu Pharmacy",
    "wof:placetype":"venue"
},
  "geometry": {"coordinates":[-114.336856,34.477407],"type":"Point"}
}