{
  "type": "Feature",
  "properties": {
    "iso:country":"US",
    "sg:address":"3113 E Lincoln Dr",
    "sg:city":"Phoenix",
    "sg:classifiers":[
        {
            "category":"Restaurant",
            "type":"Food & Drink"
        }
    ],
    "sg:phone":"+1 602 808 9899",
    "sg:postcode":"85016",
    "sg:province":"AZ",
    "wof:name":"Cfu Fine Asian Dining Rest",
    "wof:placetype":"venue"
},
  "geometry": {"coordinates":[-112.01519,33.530794],"type":"Point"}
}