{
  "type": "Feature",
  "properties": {
    "addr:full":"2800 S Rural Rd Tempe AZ 85282",
    "addr:housenumber":"2800",
    "addr:postcode":"85282",
    "addr:street":"S Rural Rd",
    "iso:country":"US",
    "sg:address":"2800 S Rural Rd",
    "sg:city":"Tempe",
    "sg:classifiers":[
        {
            "category":"Real Estate",
            "subcategory":"Architect",
            "type":"Services"
        }
    ],
    "sg:phone":"+1 480 968 2474",
    "sg:postcode":"85282",
    "sg:province":"AZ",
    "wof:name":"Robert KLOB Designs",
    "wof:placetype":"venue"
},
  "geometry": {"coordinates":[-111.92631299999999,33.39776],"type":"Point"}
}