{
  "type": "Feature",
  "properties": {
    "iso:country":"US",
    "sg:address":"4501 N Cam del Rey",
    "sg:city":"Tucson",
    "sg:classifiers":[
        {
            "category":"Real Estate",
            "subcategory":"Real Estate Agent",
            "type":"Services"
        }
    ],
    "sg:phone":"+1 520 577 0131",
    "sg:postcode":"85718",
    "sg:province":"AZ",
    "sg:tags":[
        "manager"
    ],
    "wof:name":"Fred Seger & Associates",
    "wof:placetype":"venue"
},
  "geometry": {"coordinates":[-110.931858,32.288422],"type":"Point"}
}