{
  "type": "Feature",
  "properties": {
    "iso:country":"US",
    "sg:address":"840 W Cottonwood Ln",
    "sg:city":"Casa Grande",
    "sg:classifiers":[
        {
            "category":"Autos & Motor Vehicles",
            "subcategory":"Auto Supplies",
            "type":"Retail Goods"
        }
    ],
    "sg:phone":"+1 520 836 0552",
    "sg:postcode":"85222",
    "sg:province":"AZ",
    "sg:tags":[
        "parts",
        "store"
    ],
    "wof:name":"RG Salvage",
    "wof:placetype":"venue"
},
  "geometry": {"coordinates":[-111.76695,32.894103],"type":"Point"}
}