{
  "type": "Feature",
  "properties": {
    "addr:full":"349 E Bruce Ave Gilbert AZ 85234",
    "addr:housenumber":"349",
    "addr:postcode":"85234",
    "addr:street":"E Bruce Ave",
    "iso:country":"US",
    "sg:address":"349 E Bruce Ave",
    "sg:city":"Gilbert",
    "sg:classifiers":[
        {
            "category":"Real Estate",
            "subcategory":"Real Estate Agent",
            "type":"Services"
        }
    ],
    "sg:phone":"+1 480 497 8202",
    "sg:postcode":"85234",
    "sg:province":"AZ",
    "sg:tags":[
        "investment"
    ],
    "wof:name":"Silverado Ventures",
    "wof:placetype":"venue"
},
  "geometry": {"coordinates":[-111.78239000000001,33.352011],"type":"Point"}
}