{
  "type": "Feature",
  "properties": {
    "iso:country":"US",
    "sg:address":"601 E Old Linden Rd",
    "sg:city":"Show Low",
    "sg:classifiers":[
        {
            "category":"Wholesale",
            "subcategory":"Furniture",
            "type":"Manufacturing & Wholesale Goods"
        }
    ],
    "sg:phone":"+1 928 537 5851",
    "sg:postcode":"85901",
    "sg:province":"AZ",
    "wof:name":"Baker Office City",
    "wof:placetype":"venue"
},
  "geometry": {"coordinates":[-110.036421,34.254291],"type":"Point"}
}