{
  "type": "Feature",
  "properties": {
    "iso:country":"US",
    "sg:address":"4500 N Oracle Rd",
    "sg:city":"Tucson",
    "sg:classifiers":[
        {
            "category":"Shopping",
            "subcategory":"Shoes",
            "type":"Retail Goods"
        }
    ],
    "sg:phone":"+1 520 293 7873",
    "sg:postcode":"85705",
    "sg:province":"AZ",
    "sg:tags":[
        "athletic",
        "apparel"
    ],
    "wof:name":"Foot Locker",
    "wof:placetype":"venue"
},
  "geometry": {"coordinates":[-110.97812,32.28825],"type":"Point"}
}