{
  "type": "Feature",
  "properties": {
    "addr:full":"1462 Red Yucca Trl Tucson AZ 85715",
    "addr:housenumber":"1462",
    "addr:postcode":"85715",
    "addr:street":"Red Yucca Trl",
    "iso:country":"US",
    "sg:address":"1462 Red Yucca Trl",
    "sg:city":"Tucson",
    "sg:classifiers":[
        {
            "category":"Building & Trades",
            "subcategory":"Construction",
            "type":"Services"
        }
    ],
    "sg:phone":"+1 520 722 1424",
    "sg:postcode":"85715",
    "sg:province":"AZ",
    "sg:tags":[
        "house"
    ],
    "wof:name":"Builders Kitchens & Baths Inc",
    "wof:placetype":"venue"
},
  "geometry": {"coordinates":[-110.818984,32.239046],"type":"Point"}
}