{
  "type": "Feature",
  "properties": {
    "iso:country":"US",
    "sg:address":"2155 W 22nd Ln",
    "sg:city":"Yuma",
    "sg:classifiers":[
        {
            "category":"Building & Trades",
            "subcategory":"Landscaping Services",
            "type":"Services"
        }
    ],
    "sg:phone":"+1 928 782 7929",
    "sg:postcode":"85364",
    "sg:province":"AZ",
    "sg:tags":[
        "landscape"
    ],
    "wof:name":"Bowmans Landscaping LLC",
    "wof:placetype":"venue"
},
  "geometry": {"coordinates":[-114.64662,32.686225],"type":"Point"}
}