{
  "type": "Feature",
  "properties": {
    "addr:full":"4802 E Ray Rd Ste 23530 Phoenix AZ 85044",
    "addr:housenumber":"4802",
    "addr:postcode":"23530;85044",
    "addr:street":"E Ray Rd Ste",
    "iso:country":"US",
    "sg:address":"4802 E Ray Rd Ste 23530",
    "sg:city":"Phoenix",
    "sg:classifiers":[
        {
            "category":"Professional",
            "subcategory":"Business Services",
            "type":"Services"
        },
        {
            "category":"Wholesale",
            "subcategory":"Books, Periodicals, & Newspapers",
            "type":"Manufacturing & Wholesale Goods"
        }
    ],
    "sg:phone":"+1 602 721 3334",
    "sg:postcode":"85044",
    "sg:province":"AZ",
    "sg:tags":[
        "consultant",
        "publishing",
        "representative",
        "publisher"
    ],
    "wof:name":"Edward Ruth Publications",
    "wof:placetype":"venue"
},
  "geometry": {"coordinates":[-111.980334,33.319901],"type":"Point"}
}