{
  "type": "Feature",
  "properties": {
    "iso:country":"US",
    "sg:address":"1840 E Warner Rd Ste 126",
    "sg:city":"Tempe",
    "sg:classifiers":[
        {
            "category":"Shopping",
            "subcategory":"Bicycles & Sporting Goods",
            "type":"Retail Goods"
        }
    ],
    "sg:phone":"+1 480 345 6109",
    "sg:postcode":"85284",
    "sg:province":"AZ",
    "wof:name":"Play It Again Sports",
    "wof:placetype":"venue"
},
  "geometry": {"coordinates":[-111.90990499999999,33.335481],"type":"Point"}
}