{
  "type": "Feature",
  "properties": {
    "addr:full":"1901 N Cloverland Ave Tucson AZ 85712",
    "addr:housenumber":"1901",
    "addr:postcode":"85712",
    "addr:street":"N Cloverland Ave",
    "iso:country":"US",
    "sg:address":"1901 N Cloverland Ave",
    "sg:city":"Tucson",
    "sg:classifiers":[
        {
            "category":"Professional",
            "subcategory":"Art Services",
            "type":"Services"
        }
    ],
    "sg:phone":"+1 520 370 4775",
    "sg:postcode":"85712",
    "sg:province":"AZ",
    "sg:tags":[
        "graphic",
        "designer"
    ],
    "wof:name":"Id Methodology",
    "wof:placetype":"venue"
},
  "geometry": {"coordinates":[-110.88096,32.245008],"type":"Point"}
}