{
  "type": "Feature",
  "properties": {
    "iso:country":"US",
    "sg:address":"1400 N Miller Rd #C-1",
    "sg:city":"Scottsdale",
    "sg:phone":"+1 480 584 5024",
    "sg:postcode":"85257",
    "sg:province":"AZ",
    "sg:website":"http://www.atlaslocksmithphx.com",
    "wof:name":"Miller Lock and Safe",
    "wof:placetype":"venue"
},
  "geometry": {"coordinates":[-111.91756700000001,33.464103],"type":"Point"}
}