{
  "type": "Feature",
  "properties": {
    "addr:full":"2235 W Brook St Yuma AZ 85364",
    "addr:housenumber":"2235",
    "addr:postcode":"85364",
    "addr:street":"W Brook St",
    "iso:country":"US",
    "sg:address":"2235 W Brook St",
    "sg:city":"Yuma",
    "sg:classifiers":[
        {
            "category":"Personal",
            "type":"Services"
        }
    ],
    "sg:phone":"+1 928 783 6858",
    "sg:postcode":"85364",
    "sg:province":"AZ",
    "wof:name":"Happily Ever After",
    "wof:placetype":"venue"
},
  "geometry": {"coordinates":[-114.647068,32.693629],"type":"Point"}
}