{
  "type": "Feature",
  "properties": {
    "addr:full":"3333 E Camelback Rd Phoenix AZ 85018",
    "addr:housenumber":"3333",
    "addr:postcode":"85018",
    "addr:street":"E Camelback Rd",
    "iso:country":"US",
    "sg:address":"3333 E Camelback Rd",
    "sg:city":"Phoenix",
    "sg:classifiers":[
        {
            "category":"Airline",
            "type":"Transportation"
        }
    ],
    "sg:phone":"+1 602 433 7000",
    "sg:postcode":"85018",
    "sg:province":"AZ",
    "sg:tags":[
        "courier",
        "air"
    ],
    "wof:name":"Fedex",
    "wof:placetype":"venue"
},
  "geometry": {"coordinates":[-112.010963,33.50989],"type":"Point"}
}