{
  "type": "Feature",
  "properties": {
    "addr:full":"23015 N 15th Ave Phoenix AZ 85027",
    "addr:housenumber":"23015",
    "addr:postcode":"85027",
    "addr:street":"N 15Th Ave",
    "iso:country":"US",
    "sg:address":"23015 N 15th Ave",
    "sg:city":"Phoenix",
    "sg:classifiers":[
        {
            "category":"Social Services",
            "type":"Services"
        }
    ],
    "sg:phone":"+1 623 780 5690",
    "sg:postcode":"85027",
    "sg:province":"AZ",
    "sg:tags":[
        "organization",
        "welfare"
    ],
    "wof:name":"On Angel's Wings Inc",
    "wof:placetype":"venue"
},
  "geometry": {"coordinates":[-112.091672,33.696423],"type":"Point"}
}