{
  "type": "Feature",
  "properties": {
    "addr:full":"3640 Bar-Circle-A Rd Prescott AZ 86301",
    "addr:housenumber":"3640",
    "addr:postcode":"86301",
    "addr:street":"Bar-Circle-A Rd",
    "iso:country":"US",
    "sg:address":"3640 Bar-Circle-A Rd",
    "sg:city":"Prescott",
    "sg:classifiers":[
        {
            "category":"Building & Trades",
            "subcategory":"Landscaping Services",
            "type":"Services"
        }
    ],
    "sg:phone":"+1 928 925 6040",
    "sg:postcode":"86301",
    "sg:province":"AZ",
    "sg:tags":[
        "landscape"
    ],
    "wof:name":"North Country Landscaping & MA",
    "wof:placetype":"venue"
},
  "geometry": {"coordinates":[-112.403463,34.557325],"type":"Point"}
}