{
  "type": "Feature",
  "properties": {
    "addr:full":"6732 W Angela Dr Glendale AZ 85308",
    "addr:housenumber":"6732",
    "addr:postcode":"85308",
    "addr:street":"W Angela Dr",
    "iso:country":"US",
    "sg:address":"6732 W Angela Dr",
    "sg:city":"Glendale",
    "sg:classifiers":[
        {
            "category":"Building & Trades",
            "subcategory":"Construction",
            "type":"Services"
        }
    ],
    "sg:phone":"+1 623 486 0960",
    "sg:postcode":"85308",
    "sg:province":"AZ",
    "sg:tags":[
        "skylight"
    ],
    "wof:name":"Brandt Builders",
    "wof:placetype":"venue"
},
  "geometry": {"coordinates":[-112.203744,33.644459],"type":"Point"}
}