{
  "type": "Feature",
  "properties": {
    "iso:country":"US",
    "sg:address":"95 S Orpheum Way",
    "sg:city":"Tucson",
    "sg:classifiers":[
        {
            "category":"Shopping",
            "type":"Retail Goods"
        }
    ],
    "sg:phone":"+1 520 275 4603",
    "sg:postcode":"85748",
    "sg:province":"AZ",
    "sg:tags":[
        "album",
        "photo",
        "frame"
    ],
    "wof:name":"Red Poppy Designs",
    "wof:placetype":"venue"
},
  "geometry": {"coordinates":[-110.787822,32.219546],"type":"Point"}
}