{
  "type": "Feature",
  "properties": {
    "iso:country":"US",
    "sg:address":"3829 E Ahwatukee Dr",
    "sg:city":"Phoenix",
    "sg:classifiers":[
        {
            "category":"Professional",
            "type":"Services"
        }
    ],
    "sg:phone":"+1 480 893 0903",
    "sg:postcode":"85044",
    "sg:province":"AZ",
    "wof:name":"Corp Watson",
    "wof:placetype":"venue"
},
  "geometry": {"coordinates":[-112.00138,33.333639],"type":"Point"}
}