{
  "type": "Feature",
  "properties": {
    "iso:country":"US",
    "sg:address":"7617 N 67th Ave",
    "sg:city":"Glendale",
    "sg:classifiers":[
        {
            "category":"Building & Trades",
            "subcategory":"Construction",
            "type":"Services"
        }
    ],
    "sg:phone":"+1 623 939 5747",
    "sg:postcode":"85301",
    "sg:province":"AZ",
    "sg:tags":[
        "painter"
    ],
    "wof:name":"Barr Remodeling & Contracting",
    "wof:placetype":"venue"
},
  "geometry": {"coordinates":[-112.202956,33.545871],"type":"Point"}
}