{
  "type": "Feature",
  "properties": {
    "iso:country":"US",
    "sg:address":"4002 N 67th Avenue Suite 2",
    "sg:city":"Phoenix",
    "sg:classifiers":[
        {
            "category":"Food & Beverages",
            "subcategory":"Meat & Fish",
            "type":"Retail Goods"
        }
    ],
    "sg:phone":"+1 623 873 4646",
    "sg:postcode":"85033",
    "sg:province":"AZ",
    "sg:tags":[
        "shop",
        "seafood",
        "market"
    ],
    "wof:name":"Super Carniceria La Hereford",
    "wof:placetype":"venue"
},
  "geometry": {"coordinates":[-112.203241,33.493642],"type":"Point"}
}