{
  "type": "Feature",
  "properties": {
    "addr:full":"95 Hohokam Dr Sedona AZ 86336",
    "addr:housenumber":"95",
    "addr:postcode":"86336",
    "addr:street":"Hohokam Dr",
    "iso:country":"US",
    "sg:address":"95 Hohokam Dr",
    "sg:city":"Sedona",
    "sg:classifiers":[
        {
            "category":"Recreation",
            "type":"Entertainment"
        }
    ],
    "sg:phone":"+1 928 203 1123",
    "sg:postcode":"86336",
    "sg:province":"AZ",
    "sg:tags":[
        "tours",
        "sightseeing"
    ],
    "wof:name":"Grand Canyon Wild West Tours",
    "wof:placetype":"venue"
},
  "geometry": {"coordinates":[-111.825744,34.863895],"type":"Point"}
}