{
  "type": "Feature",
  "properties": {
    "iso:country":"US",
    "sg:address":"912 W 6th Ave",
    "sg:city":"San Manuel",
    "sg:classifiers":[
        {
            "category":"Wholesale",
            "subcategory":"Machinery & Supplies",
            "type":"Manufacturing & Wholesale Goods"
        }
    ],
    "sg:phone":"+1 520 385 9220",
    "sg:postcode":"85631",
    "sg:province":"AZ",
    "sg:tags":[
        "industrial"
    ],
    "wof:name":"Kyle Equipment Co",
    "wof:placetype":"venue"
},
  "geometry": {"coordinates":[-110.639169,32.604489],"type":"Point"}
}