{
  "type": "Feature",
  "properties": {
    "iso:country":"US",
    "sg:address":"450 S River Run Rd",
    "sg:city":"Flagstaff",
    "sg:classifiers":[
        {
            "category":"Manufacturing",
            "subcategory":"Lumber",
            "type":"Manufacturing & Wholesale Goods"
        }
    ],
    "sg:phone":"+1 928 779 7249",
    "sg:postcode":"86001",
    "sg:province":"AZ",
    "sg:tags":[
        "outdoor",
        "product",
        "wood",
        "structural"
    ],
    "wof:name":"Kahtoola Inc",
    "wof:placetype":"venue"
},
  "geometry": {"coordinates":[-111.636092,35.189654],"type":"Point"}
}