{
  "type": "Feature",
  "properties": {
    "addr:full":"286 N Frontier St Wickenburg AZ 85390",
    "addr:housenumber":"286",
    "addr:postcode":"85390",
    "addr:street":"N Frontier St",
    "iso:country":"US",
    "sg:address":"286 N Frontier St",
    "sg:city":"Wickenburg",
    "sg:classifiers":[
        {
            "category":"Manufacturing",
            "subcategory":"Glass & Minerals",
            "type":"Manufacturing & Wholesale Goods"
        }
    ],
    "sg:phone":"+1 928 684 7248",
    "sg:postcode":"85390",
    "sg:province":"AZ",
    "sg:tags":[
        "ready",
        "concrete",
        "mfg"
    ],
    "wof:name":"Red-E-Mix Inc",
    "wof:placetype":"venue"
},
  "geometry": {"coordinates":[-112.733627,33.97128],"type":"Point"}
}