{
  "type": "Feature",
  "properties": {
    "iso:country":"US",
    "sg:address":"4625 Interstate Way",
    "sg:city":"Kingman",
    "sg:classifiers":[
        {
            "category":"Real Estate",
            "subcategory":"Real Estate Agent",
            "type":"Services"
        }
    ],
    "sg:phone":"+1 928 681 4625",
    "sg:postcode":"86401",
    "sg:province":"AZ",
    "wof:name":"Kingman Properties",
    "wof:placetype":"venue"
},
  "geometry": {"coordinates":[-113.956847,35.260341],"type":"Point"}
}