{
  "type": "Feature",
  "properties": {
    "iso:country":"US",
    "sg:address":"1542 W Ocotillo Rd",
    "sg:city":"Queen Creek",
    "sg:classifiers":[
        {
            "category":"Building & Trades",
            "subcategory":"Landscaping Services",
            "type":"Services"
        }
    ],
    "sg:phone":"+1 480 888 1053",
    "sg:postcode":"85240",
    "sg:province":"AZ",
    "sg:tags":[
        "landscape"
    ],
    "wof:name":"Irontree Landscape",
    "wof:placetype":"venue"
},
  "geometry": {"coordinates":[-111.572288,33.249072],"type":"Point"}
}