{
  "type": "Feature",
  "properties": {
    "iso:country":"US",
    "sg:address":"7141 E Lincoln Dr",
    "sg:city":"Scottsdale",
    "sg:classifiers":[
        {
            "category":"Shopping",
            "subcategory":"Pharmacy",
            "type":"Retail Goods"
        }
    ],
    "sg:phone":"+1 480 998 2378",
    "sg:postcode":"85253",
    "sg:province":"AZ",
    "wof:name":"A J's United Drugs",
    "wof:placetype":"venue"
},
  "geometry": {"coordinates":[-111.926248,33.531356],"type":"Point"}
}