{
  "type": "Feature",
  "properties": {
    "iso:country":"US",
    "sg:address":"7134 E Earll Dr",
    "sg:city":"Scottsdale",
    "sg:classifiers":[
        {
            "category":"Manufacturing",
            "subcategory":"Metals",
            "type":"Manufacturing & Wholesale Goods"
        }
    ],
    "sg:phone":"+1 480 949 0499",
    "sg:postcode":"85251",
    "sg:province":"AZ",
    "sg:tags":[
        "sheet",
        "fabrication"
    ],
    "wof:name":"Jachowski Sheet Metal",
    "wof:placetype":"venue"
},
  "geometry": {"coordinates":[-111.92679,33.484082],"type":"Point"}
}