{
  "type": "Feature",
  "properties": {
    "addr:full":"1900 N McClintock Dr Tempe AZ 85281",
    "addr:housenumber":"1900",
    "addr:postcode":"85281",
    "addr:street":"N Mcclintock Dr",
    "iso:country":"US",
    "sg:address":"1900 N McClintock Dr",
    "sg:city":"Tempe",
    "sg:classifiers":[
        {
            "category":"Retail",
            "subcategory":"Auto Repair",
            "type":"Services"
        }
    ],
    "sg:phone":"+1 480 949 5464",
    "sg:postcode":"85281",
    "sg:province":"AZ",
    "sg:tags":[
        "body",
        "automobile",
        "painting"
    ],
    "wof:name":"Dent King",
    "wof:placetype":"venue"
},
  "geometry": {"coordinates":[-111.909279,33.451281],"type":"Point"}
}