{
  "type": "Feature",
  "properties": {
    "iso:country":"US",
    "sg:address":"585 W Cleveland St",
    "sg:city":"St Johns",
    "sg:classifiers":[
        {
            "category":"Shopping",
            "subcategory":"Music",
            "type":"Retail Goods"
        }
    ],
    "sg:phone":"+1 928 337 3848",
    "sg:postcode":"85936",
    "sg:province":"AZ",
    "sg:tags":[
        "video",
        "disc",
        "tape",
        "cassette"
    ],
    "wof:name":"Rodeo Video Inc",
    "wof:placetype":"venue"
},
  "geometry": {"coordinates":[-109.37397199999999,34.506749],"type":"Point"}
}