{
  "type": "Feature",
  "properties": {
    "iso:country":"US",
    "sg:address":"11600 N 75th Ave",
    "sg:city":"Peoria",
    "sg:classifiers":[
        {
            "category":"Real Estate",
            "subcategory":"Real Estate Operator",
            "type":"Services"
        }
    ],
    "sg:phone":"+1 623 412 1650",
    "sg:postcode":"85345",
    "sg:province":"AZ",
    "sg:tags":[
        "apartment"
    ],
    "wof:name":"Land Pointe",
    "wof:placetype":"venue"
},
  "geometry": {"coordinates":[-112.220328,33.590434],"type":"Point"}
}