{
  "type": "Feature",
  "properties": {
    "addr:full":"17596 N Escalante Ln Surprise AZ 85374",
    "addr:housenumber":"17596",
    "addr:postcode":"85374",
    "addr:street":"N Escalante Ln",
    "iso:country":"US",
    "sg:address":"17596 N Escalante Ln",
    "sg:city":"Surprise",
    "sg:classifiers":[
        {
            "category":"Manufacturing",
            "subcategory":"Chemicals & Compounds",
            "type":"Manufacturing & Wholesale Goods"
        }
    ],
    "sg:phone":"+1 623 975 6380",
    "sg:postcode":"85374",
    "sg:province":"AZ",
    "sg:tags":[
        "preparation",
        "mfg",
        "anti",
        "freeze"
    ],
    "wof:name":"Coolant Pro Corporation",
    "wof:placetype":"venue"
},
  "geometry": {"coordinates":[-112.410447,33.643778],"type":"Point"}
}