{
  "type": "Feature",
  "properties": {
    "addr:full":"2256 Kingman Ave Kingman AZ 86401",
    "addr:housenumber":"2256",
    "addr:postcode":"86401",
    "addr:street":"Kingman Ave",
    "iso:country":"US",
    "sg:address":"2256 Kingman Ave",
    "sg:city":"Kingman",
    "sg:classifiers":[
        {
            "category":"Banks & Credit Unions",
            "subcategory":"Bank",
            "type":"Services"
        },
        {
            "category":"Shopping",
            "subcategory":"Used Merchandise",
            "type":"Retail Goods"
        }
    ],
    "sg:phone":"+1 928 753 7511",
    "sg:postcode":"86401",
    "sg:province":"AZ",
    "sg:tags":[
        "resale",
        "shop",
        "second",
        "hand"
    ],
    "wof:name":"Bucks Second Time Around",
    "wof:placetype":"venue"
},
  "geometry": {"coordinates":[-114.025374,35.202673],"type":"Point"}
}