{
  "type": "Feature",
  "properties": {
    "iso:country":"US",
    "sg:address":"3413 Newport Dr",
    "sg:city":"Lake Havasu City",
    "sg:classifiers":[
        {
            "category":"Shopping",
            "subcategory":"Clothing, Apparel, & Fashions",
            "type":"Retail Goods"
        }
    ],
    "sg:phone":"+1 928 854 3851",
    "sg:postcode":"86406",
    "sg:province":"AZ",
    "sg:tags":[
        "wallet",
        "hat",
        "belt"
    ],
    "wof:name":"Redd Dog Enterprises",
    "wof:placetype":"venue"
},
  "geometry": {"coordinates":[-114.287899,34.492099],"type":"Point"}
}