{
  "type": "Feature",
  "properties": {
    "iso:country":"US",
    "sg:address":"3339 W Earll Dr",
    "sg:city":"Phoenix",
    "sg:classifiers":[
        {
            "category":"Manufacturing",
            "subcategory":"Tools & Machinery",
            "type":"Manufacturing & Wholesale Goods"
        },
        {
            "category":"Retail",
            "subcategory":"Repair Shop",
            "type":"Services"
        }
    ],
    "sg:phone":"+1 602 278 8665",
    "sg:postcode":"85017",
    "sg:province":"AZ",
    "sg:tags":[
        "machine",
        "machinery-rebuild"
    ],
    "wof:name":"Tn Machining",
    "wof:placetype":"venue"
},
  "geometry": {"coordinates":[-112.12924,33.483149],"type":"Point"}
}