{
  "type": "Feature",
  "properties": {
    "iso:country":"US",
    "sg:address":"5101 E Farness Dr",
    "sg:city":"Tucson",
    "sg:classifiers":[
        {
            "category":"Health Services",
            "subcategory":"Clinic",
            "type":"Services"
        }
    ],
    "sg:phone":"+1 520 296 2313",
    "sg:postcode":"85712",
    "sg:province":"AZ",
    "sg:tags":[
        "home"
    ],
    "wof:name":"Nursefinders Of Tucson",
    "wof:placetype":"venue"
},
  "geometry": {"coordinates":[-110.881207,32.247973],"type":"Point"}
}