{
  "type": "Feature",
  "properties": {
    "iso:country":"US",
    "sg:address":"2742 W Darien Way",
    "sg:city":"Phoenix",
    "sg:classifiers":[
        {
            "category":"Professional",
            "subcategory":"Business Services",
            "type":"Services"
        }
    ],
    "sg:phone":"+1 623 551 3559",
    "sg:postcode":"85086",
    "sg:province":"AZ",
    "sg:tags":[
        "interior",
        "consultant",
        "design",
        "decorator"
    ],
    "wof:name":"Madzak Interior Design",
    "wof:placetype":"venue"
},
  "geometry": {"coordinates":[-112.118638,33.803571],"type":"Point"}
}