{
  "type": "Feature",
  "properties": {
    "addr:full":"1530 W Flynn Ln Phoenix AZ 85015",
    "addr:housenumber":"1530",
    "addr:postcode":"85015",
    "addr:street":"W Flynn Ln",
    "iso:country":"US",
    "sg:address":"1530 W Flynn Ln",
    "sg:city":"Phoenix",
    "sg:classifiers":[
        {
            "category":"Banks & Credit Unions",
            "subcategory":"Financial Services",
            "type":"Services"
        }
    ],
    "sg:phone":"+1 602 870 1158",
    "sg:postcode":"85015",
    "sg:province":"AZ",
    "sg:tags":[
        "investor"
    ],
    "wof:name":"Quail Run Investments LLC",
    "wof:placetype":"venue"
},
  "geometry": {"coordinates":[-112.093143,33.537525],"type":"Point"}
}