{
  "type": "Feature",
  "properties": {
    "iso:country":"US",
    "sg:address":"1240 E 23rd St",
    "sg:city":"Douglas",
    "sg:classifiers":[
        {
            "category":"Restaurant",
            "type":"Food & Drink"
        }
    ],
    "sg:phone":"+1 520 364 7138",
    "sg:postcode":"85607",
    "sg:province":"AZ",
    "sg:tags":[
        "drinking",
        "eating"
    ],
    "wof:name":"Red Barn",
    "wof:placetype":"venue"
},
  "geometry": {"coordinates":[-109.542692,31.35762],"type":"Point"}
}