{
  "type": "Feature",
  "properties": {
    "iso:country":"US",
    "sg:address":"1795 Civic Center Blvd",
    "sg:city":"Lake Havasu City",
    "sg:classifiers":[
        {
            "category":"Health Services",
            "subcategory":"Health Practitioner",
            "type":"Services"
        }
    ],
    "sg:phone":"+1 928 854 4776",
    "sg:postcode":"86403",
    "sg:province":"AZ",
    "sg:tags":[
        "therapist",
        "physical"
    ],
    "wof:name":"Pro Therapy",
    "wof:placetype":"venue"
},
  "geometry": {"coordinates":[-114.337295,34.47734],"type":"Point"}
}