{
  "type": "Feature",
  "properties": {
    "iso:country":"US",
    "sg:address":"33 N Stone Ave",
    "sg:city":"Tucson",
    "sg:classifiers":[
        {
            "category":"Professional",
            "subcategory":"Printing & Photocopies",
            "type":"Services"
        }
    ],
    "sg:phone":"+1 520 622 2859",
    "sg:postcode":"85701",
    "sg:province":"AZ",
    "sg:tags":[
        "photocopying",
        "lithographic",
        "commercial"
    ],
    "wof:name":"Quikprint",
    "wof:placetype":"venue"
},
  "geometry": {"coordinates":[-110.971414,32.222512],"type":"Point"}
}