{
  "type": "Feature",
  "properties": {
    "iso:country":"US",
    "sg:address":"15215 S 48th St Ste 190",
    "sg:city":"Phoenix",
    "sg:classifiers":[
        {
            "category":"Health Services",
            "subcategory":"Dentist",
            "type":"Services"
        }
    ],
    "sg:phone":"+1 480 893 2474",
    "sg:postcode":"85044",
    "sg:province":"AZ",
    "sg:website":"http://www.jakohlerdds.net",
    "wof:name":"Kohler: Jeffery A DDS PC",
    "wof:placetype":"venue"
},
  "geometry": {"coordinates":[-111.980383,33.308219],"type":"Point"}
}