{
  "type": "Feature",
  "properties": {
    "iso:country":"US",
    "sg:address":"1385 W Thatcher Blvd",
    "sg:city":"Safford",
    "sg:classifiers":[
        {
            "category":"Restaurant",
            "type":"Food & Drink"
        }
    ],
    "sg:phone":"+1 928 348 3336",
    "sg:postcode":"85546",
    "sg:province":"AZ",
    "sg:tags":[
        "asian",
        "chinese",
        "pan"
    ],
    "wof:name":"China Taste",
    "wof:placetype":"venue"
},
  "geometry": {"coordinates":[-109.722053,32.834893],"type":"Point"}
}