{
  "type": "Feature",
  "properties": {
    "iso:country":"US",
    "sg:address":"2331 S 4th Ave",
    "sg:city":"Tucson",
    "sg:classifiers":[
        {
            "category":"Wholesale",
            "subcategory":"Hardware",
            "type":"Manufacturing & Wholesale Goods"
        }
    ],
    "sg:phone":"+1 520 624 0424",
    "sg:postcode":"85713",
    "sg:province":"AZ",
    "sg:tags":[
        "supply",
        "system",
        "heating",
        "equipment",
        "plumbing",
        "air conditioning"
    ],
    "wof:name":"Lou's Plumbing Supply Corp.",
    "wof:placetype":"venue"
},
  "geometry": {"coordinates":[-110.96534699999999,32.195188],"type":"Point"}
}