{
  "type": "Feature",
  "properties": {
    "addr:full":"3073 Willow Creek Rd Prescott AZ 86301",
    "addr:housenumber":"3073",
    "addr:postcode":"86301",
    "addr:street":"Willow Creek Rd",
    "iso:country":"US",
    "sg:address":"3073 Willow Creek Rd",
    "sg:city":"Prescott",
    "sg:classifiers":[
        {
            "category":"Retail",
            "subcategory":"Veterinary Services",
            "type":"Services"
        }
    ],
    "sg:phone":"+1 928 771 1340",
    "sg:postcode":"86301",
    "sg:province":"AZ",
    "sg:tags":[
        "veterinarian"
    ],
    "wof:name":"Granite Mountain Veterinary",
    "wof:placetype":"venue"
},
  "geometry": {"coordinates":[-112.467382,34.594671],"type":"Point"}
}