{
  "type": "Feature",
  "properties": {
    "iso:country":"US",
    "sg:address":"931 E Elliot Rd Ste 101",
    "sg:city":"Tempe",
    "sg:classifiers":[
        {
            "category":"Arts & Performance",
            "subcategory":"Arts Center",
            "type":"Entertainment"
        },
        {
            "category":"Education",
            "subcategory":"Dance Studio",
            "type":"Public Place"
        }
    ],
    "sg:phone":"+1 480 777 8877",
    "sg:postcode":"85284",
    "sg:province":"AZ",
    "sg:tags":[
        "performing"
    ],
    "sg:website":"paragondance.net",
    "wof:name":"Paragon Dance Center",
    "wof:placetype":"venue"
},
  "geometry": {"coordinates":[-111.928314,33.348912],"type":"Point"}
}