{
  "type": "Feature",
  "properties": {
    "iso:country":"US",
    "sg:address":"4560 E Broadway Blvd",
    "sg:city":"Tucson",
    "sg:classifiers":[
        {
            "category":"Professional",
            "subcategory":"Research",
            "type":"Services"
        }
    ],
    "sg:phone":"+1 520 445 3864",
    "sg:postcode":"85711",
    "sg:province":"AZ",
    "sg:tags":[
        "foundation",
        "philanthropic",
        "supply",
        "equipment",
        "health",
        "home",
        "care"
    ],
    "sg:website":"http://www.jdrf.org",
    "wof:name":"Juvenile Diabetes Research Foundation",
    "wof:placetype":"venue"
},
  "geometry": {"coordinates":[-110.895258,32.221425],"type":"Point"}
}