{
  "type": "Feature",
  "properties": {
    "iso:country":"US",
    "sg:address":"13732 W Bell Rd Ste 6",
    "sg:city":"Surprise",
    "sg:phone":"+1 623 877 1026",
    "sg:postcode":"85374",
    "sg:province":"AZ",
    "wof:name":"Karen's Kreamery",
    "wof:placetype":"venue"
},
  "geometry": {"coordinates":[-112.354952,33.638711],"type":"Point"}
}