{
  "type": "Feature",
  "properties": {
    "iso:country":"US",
    "sg:address":"4417 N 40th St Ste 100",
    "sg:city":"Phoenix",
    "sg:classifiers":[
        {
            "category":"Professional",
            "subcategory":"Accounting & Tax Preparation",
            "type":"Services"
        }
    ],
    "sg:phone":"+1 602 954 7130",
    "sg:postcode":"85018",
    "sg:province":"AZ",
    "sg:tags":[
        "bookkeeping",
        "public",
        "accountants-certified"
    ],
    "sg:website":"http://www.lqcpa.com",
    "wof:name":"Lori Quinn Cpa",
    "wof:placetype":"venue"
},
  "geometry": {"coordinates":[-111.995392,33.501301],"type":"Point"}
}