{
  "type": "Feature",
  "properties": {
    "iso:country":"US",
    "sg:address":"641 S Scallop Dr",
    "sg:city":"Gilbert",
    "sg:classifiers":[
        {
            "category":"Wholesale",
            "subcategory":"Durable Goods & Equipment",
            "type":"Manufacturing & Wholesale Goods"
        }
    ],
    "sg:phone":"+1 480 497 2700",
    "sg:postcode":"85233",
    "sg:province":"AZ",
    "sg:tags":[
        "antique",
        "dealers-wholesale"
    ],
    "wof:name":"Doris D Stephan",
    "wof:placetype":"venue"
},
  "geometry": {"coordinates":[-111.821427,33.338396],"type":"Point"}
}