{
  "type": "Feature",
  "properties": {
    "iso:country":"US",
    "sg:address":"3414 N Paiute Way",
    "sg:city":"Scottsdale",
    "sg:classifiers":[
        {
            "category":"Arena",
            "subcategory":"Sports Club",
            "type":"Entertainment"
        }
    ],
    "sg:phone":"+1 480 242 2444",
    "sg:postcode":"85251",
    "sg:province":"AZ",
    "sg:tags":[
        "health"
    ],
    "wof:name":"Pep",
    "wof:placetype":"venue"
},
  "geometry": {"coordinates":[-111.942223,33.487572],"type":"Point"}
}