{
  "type": "Feature",
  "properties": {
    "addr:full":"1841 E Weldon Ave Phoenix AZ 85016",
    "addr:housenumber":"1841",
    "addr:postcode":"85016",
    "addr:street":"E Weldon Ave",
    "iso:country":"US",
    "sg:address":"1841 E Weldon Ave",
    "sg:city":"Phoenix",
    "sg:classifiers":[
        {
            "category":"Manufacturing",
            "subcategory":"Glass & Minerals",
            "type":"Manufacturing & Wholesale Goods"
        },
        {
            "category":"Retail",
            "subcategory":"Auto Repair",
            "type":"Services"
        }
    ],
    "sg:phone":"+1 602 595 9596",
    "sg:postcode":"85016",
    "sg:province":"AZ",
    "sg:tags":[
        "plate",
        "shape",
        "glass-wholesale",
        "window",
        "special",
        "circle",
        "windshield",
        "glass-auto",
        "manufacturer"
    ],
    "wof:name":"Patriot Auto Glass",
    "wof:placetype":"venue"
},
  "geometry": {"coordinates":[-112.043125,33.490347],"type":"Point"}
}