{
  "type": "Feature",
  "properties": {
    "iso:country":"US",
    "sg:address":"20912 W Carver Rd",
    "sg:city":"Buckeye",
    "sg:classifiers":[
        {
            "category":"Building & Trades",
            "subcategory":"Landscaping Services",
            "type":"Services"
        }
    ],
    "sg:phone":"+1 623 386 2682",
    "sg:postcode":"85326",
    "sg:province":"AZ",
    "wof:name":"Price Fair Tree Service",
    "wof:placetype":"venue"
},
  "geometry": {"coordinates":[-112.500414,33.341236],"type":"Point"}
}