{
  "type": "Feature",
  "properties": {
    "iso:country":"US",
    "sg:address":"1628 N Sinova",
    "sg:city":"Mesa",
    "sg:classifiers":[
        {
            "category":"Building & Trades",
            "subcategory":"Landscaping Services",
            "type":"Services"
        }
    ],
    "sg:phone":"+1 480 924 7014",
    "sg:postcode":"85205",
    "sg:province":"AZ",
    "sg:tags":[
        "landscape"
    ],
    "wof:name":"Tooveys Custom Landscaping",
    "wof:placetype":"venue"
},
  "geometry": {"coordinates":[-111.715971,33.445126],"type":"Point"}
}