{
  "type": "Feature",
  "properties": {
    "iso:country":"US",
    "sg:address":"1872 E Apache Blvd",
    "sg:city":"Tempe",
    "sg:classifiers":[
        {
            "category":"Restaurant",
            "type":"Food & Drink"
        }
    ],
    "sg:menulink":"http://www.allmenus.com/az/phoenix/291127-the-dhaba/menu/",
    "sg:phone":"+1 480 446 2824",
    "sg:postcode":"85281",
    "sg:province":"AZ",
    "sg:tags":[
        "indian",
        "asian"
    ],
    "wof:name":"The Dhaba",
    "wof:placetype":"venue"
},
  "geometry": {"coordinates":[-111.906041,33.414838],"type":"Point"}
}