{
  "type": "Feature",
  "properties": {
    "iso:country":"US",
    "sg:address":"4041 N Central Ave",
    "sg:city":"Phoenix",
    "sg:classifiers":[
        {
            "category":"Banks & Credit Unions",
            "subcategory":"Investment Brokerage",
            "type":"Services"
        }
    ],
    "sg:phone":"+1 602 285 1392",
    "sg:postcode":"85012",
    "sg:province":"AZ",
    "sg:tags":[
        "advisory",
        "financial"
    ],
    "wof:name":"Premium Financial",
    "wof:placetype":"venue"
},
  "geometry": {"coordinates":[-112.073711,33.493832],"type":"Point"}
}