{
  "type": "Feature",
  "properties": {
    "iso:country":"US",
    "sg:address":"3443 E Speedway Blvd",
    "sg:city":"Tucson",
    "sg:classifiers":[
        {
            "category":"Shopping",
            "subcategory":"Computers & Home Electronics",
            "type":"Retail Goods"
        }
    ],
    "sg:phone":"+1 520 326 0551",
    "sg:postcode":"85716",
    "sg:province":"AZ",
    "sg:tags":[
        "high",
        "fidelity",
        "stereophonic"
    ],
    "wof:name":"Stereo Pad",
    "wof:placetype":"venue"
},
  "geometry": {"coordinates":[-110.918249,32.236234],"type":"Point"}
}