{
  "type": "Feature",
  "properties": {
    "iso:country":"US",
    "sg:address":"40 W Cortez Dr",
    "sg:city":"Sedona",
    "sg:classifiers":[
        {
            "category":"Bars & Pubs",
            "type":"Food & Drink"
        }
    ],
    "sg:phone":"+1 928 284 2250",
    "sg:postcode":"86351",
    "sg:province":"AZ",
    "sg:tags":[
        "drinking"
    ],
    "wof:name":"P J's Village Pub",
    "wof:placetype":"venue"
},
  "geometry": {"coordinates":[-111.764406,34.780211],"type":"Point"}
}