{
  "type": "Feature",
  "properties": {
    "addr:full":"2807 N Campbell Ave Tucson AZ 85719",
    "addr:housenumber":"2807",
    "addr:postcode":"85719",
    "addr:street":"N Campbell Ave",
    "iso:country":"US",
    "sg:address":"2807 N Campbell Ave",
    "sg:city":"Tucson",
    "sg:classifiers":[
        {
            "category":"Restaurant",
            "type":"Food & Drink"
        }
    ],
    "sg:phone":"+1 520 324 0800",
    "sg:postcode":"85719",
    "sg:province":"AZ",
    "sg:tags":[
        "eating"
    ],
    "wof:name":"Tokyo Rice Bowl 2",
    "wof:placetype":"venue"
},
  "geometry": {"coordinates":[-110.943911,32.259274],"type":"Point"}
}