{
  "type": "Feature",
  "properties": {
    "iso:country":"US",
    "sg:address":"1660 E Camelback Rd",
    "sg:city":"Phoenix",
    "sg:classifiers":[
        {
            "category":"Restaurant",
            "type":"Food & Drink"
        }
    ],
    "sg:menulink":"http://www.allmenus.com/az/phoenix/221599-chipotle/menu/",
    "sg:phone":"+1 602 274 4455",
    "sg:postcode":"85016",
    "sg:province":"AZ",
    "sg:tags":[
        "mexican"
    ],
    "wof:name":"Chipotle",
    "wof:placetype":"venue"
},
  "geometry": {"coordinates":[-112.04510999999999,33.509281],"type":"Point"}
}