{
  "type": "Feature",
  "properties": {
    "addr:full":"2648 N 15th St Phoenix AZ 85006",
    "addr:housenumber":"2648",
    "addr:postcode":"85006",
    "addr:street":"N 15Th St",
    "iso:country":"US",
    "sg:address":"2648 N 15th St",
    "sg:city":"Phoenix",
    "sg:classifiers":[
        {
            "category":"Building & Trades",
            "subcategory":"Construction",
            "type":"Services"
        }
    ],
    "sg:phone":"+1 602 277 5085",
    "sg:postcode":"85006",
    "sg:province":"AZ",
    "sg:tags":[
        "contractor"
    ],
    "wof:name":"20th Century Roofing Inc",
    "wof:placetype":"venue"
},
  "geometry": {"coordinates":[-112.049919,33.478116],"type":"Point"}
}