{
  "type": "Feature",
  "properties": {
    "iso:country":"US",
    "sg:address":"6602 E Cave Creek Rd",
    "sg:city":"Cave Creek",
    "sg:classifiers":[
        {
            "category":"Coffee & Tea",
            "type":"Food & Drink"
        }
    ],
    "sg:phone":"+1 480 575 6885",
    "sg:postcode":"85331",
    "sg:province":"AZ",
    "wof:name":"Janey's Coffeehouse",
    "wof:placetype":"venue"
},
  "geometry": {"coordinates":[-111.938652,33.833628],"type":"Point"}
}