{
  "type": "Feature",
  "properties": {
    "iso:country":"US",
    "sg:address":"5337 N 81st Pl",
    "sg:city":"Scottsdale",
    "sg:classifiers":[
        {
            "category":"Building & Trades",
            "subcategory":"Landscaping Services",
            "type":"Services"
        }
    ],
    "sg:phone":"+1 480 425 0903",
    "sg:postcode":"85250",
    "sg:province":"AZ",
    "sg:tags":[
        "landscape",
        "contractor"
    ],
    "wof:name":"Paul's Landscape & Dump Truck",
    "wof:placetype":"venue"
},
  "geometry": {"coordinates":[-111.905269,33.51613],"type":"Point"}
}