{
  "type": "Feature",
  "properties": {
    "iso:country":"US",
    "sg:address":"17611 N Lindgren Ave",
    "sg:city":"Sun City",
    "sg:classifiers":[
        {
            "category":"Real Estate",
            "subcategory":"Real Estate Agent",
            "type":"Services"
        }
    ],
    "sg:phone":"+1 623 566 0000",
    "sg:postcode":"85373",
    "sg:province":"AZ",
    "wof:name":"Tri Star Realty",
    "wof:placetype":"venue"
},
  "geometry": {"coordinates":[-112.262463,33.642778],"type":"Point"}
}