{
  "type": "Feature",
  "properties": {
    "iso:country":"US",
    "sg:address":"4225 E Camelback Rd",
    "sg:city":"Phoenix",
    "sg:classifiers":[
        {
            "category":"Shopping",
            "subcategory":"Jewelry",
            "type":"Retail Goods"
        },
        {
            "category":"Shopping",
            "subcategory":"Clothing, Apparel, & Fashions",
            "type":"Retail Goods"
        }
    ],
    "sg:phone":"+1 602 955 4721",
    "sg:postcode":"85018",
    "sg:province":"AZ",
    "sg:tags":[
        "accessory",
        "jeweler"
    ],
    "sg:website":"www.regalia.com",
    "wof:name":"Regalia Accessory Collection",
    "wof:placetype":"venue"
},
  "geometry": {"coordinates":[-111.99062600000001,33.509592],"type":"Point"}
}