{
  "type": "Feature",
  "properties": {
    "addr:full":"2830 E Roosevelt St Phoenix AZ 85008",
    "addr:housenumber":"2830",
    "addr:postcode":"85008",
    "addr:street":"E Roosevelt St",
    "iso:country":"US",
    "sg:address":"2830 E Roosevelt St",
    "sg:city":"Phoenix",
    "sg:classifiers":[
        {
            "category":"Real Estate",
            "subcategory":"Real Estate Operator",
            "type":"Services"
        }
    ],
    "sg:phone":"+1 602 275 7083",
    "sg:postcode":"85008",
    "sg:province":"AZ",
    "sg:tags":[
        "apartment"
    ],
    "wof:name":"Sienna Pointe Apartments",
    "wof:placetype":"venue"
},
  "geometry": {"coordinates":[-112.01994000000001,33.458639],"type":"Point"}
}