{
  "type": "Feature",
  "properties": {
    "iso:country":"US",
    "sg:address":"3336 N 7th Ave",
    "sg:city":"Phoenix",
    "sg:classifiers":[
        {
            "category":"Professional",
            "type":"Services"
        },
        {
            "category":"Restaurant",
            "type":"Food & Drink"
        }
    ],
    "sg:phone":"+1 602 264 0538",
    "sg:postcode":"85013",
    "sg:province":"AZ",
    "sg:tags":[
        "chinese",
        "caterer"
    ],
    "wof:name":"China Doll Restaurant INC",
    "wof:placetype":"venue"
},
  "geometry": {"coordinates":[-112.083167,33.486533],"type":"Point"}
}