{
  "type": "Feature",
  "properties": {
    "addr:full":"2310 Omaha Dr Kingman AZ 86401",
    "addr:housenumber":"2310",
    "addr:postcode":"86401",
    "addr:street":"Omaha Dr",
    "iso:country":"US",
    "sg:address":"2310 Omaha Dr",
    "sg:city":"Kingman",
    "sg:classifiers":[
        {
            "category":"Building & Trades",
            "subcategory":"Construction",
            "type":"Services"
        }
    ],
    "sg:phone":"+1 928 757 4292",
    "sg:postcode":"86401",
    "sg:province":"AZ",
    "sg:tags":[
        "general",
        "contractor"
    ],
    "wof:name":"Lawson Development Inc",
    "wof:placetype":"venue"
},
  "geometry": {"coordinates":[-113.984613,35.189363],"type":"Point"}
}