{
  "type": "Feature",
  "properties": {
    "iso:country":"US",
    "sg:address":"915 Hinman St",
    "sg:city":"Prescott",
    "sg:classifiers":[
        {
            "category":"Local Transit",
            "type":"Transportation"
        }
    ],
    "sg:phone":"+1 928 445 3814",
    "sg:postcode":"86305",
    "sg:province":"AZ",
    "sg:tags":[
        "ambulance"
    ],
    "wof:name":"Life Line Ambulance Service",
    "wof:placetype":"venue"
},
  "geometry": {"coordinates":[-112.48411400000001,34.559001],"type":"Point"}
}