{
  "type": "Feature",
  "properties": {
    "iso:country":"US",
    "sg:address":"2001 W Camelback Rd",
    "sg:city":"Phoenix",
    "sg:classifiers":[
        {
            "category":"Government",
            "subcategory":"Office",
            "type":"Public Place"
        }
    ],
    "sg:phone":"+1 480 551 2700",
    "sg:postcode":"85015",
    "sg:province":"AZ",
    "wof:name":"Joint Board-Regulation",
    "wof:placetype":"venue"
},
  "geometry": {"coordinates":[-112.104182,33.509574],"type":"Point"}
}