{
  "type": "Feature",
  "properties": {
    "iso:country":"US",
    "sg:address":"6819 N 55th Dr",
    "sg:city":"Glendale",
    "sg:classifiers":[
        {
            "category":"Manufacturing",
            "subcategory":"Furniture",
            "type":"Manufacturing & Wholesale Goods"
        }
    ],
    "sg:phone":"+1 623 934 0713",
    "sg:postcode":"85301",
    "sg:province":"AZ",
    "sg:tags":[
        "mfg"
    ],
    "wof:name":"Glendale Custom Cabinets",
    "wof:placetype":"venue"
},
  "geometry": {"coordinates":[-112.178636,33.538481],"type":"Point"}
}