{
  "type": "Feature",
  "properties": {
    "iso:country":"US",
    "sg:address":"15710 N 33rd Pl",
    "sg:city":"Phoenix",
    "sg:classifiers":[
        {
            "category":"Professional",
            "type":"Services"
        }
    ],
    "sg:phone":"+1 602 652 8278",
    "sg:postcode":"85032",
    "sg:province":"AZ",
    "wof:name":"Im Raven",
    "wof:placetype":"venue"
},
  "geometry": {"coordinates":[-112.00976300000001,33.630486],"type":"Point"}
}