{
  "type": "Feature",
  "properties": {
    "iso:country":"US",
    "sg:address":"4519 E Grove Ave",
    "sg:city":"Mesa",
    "sg:classifiers":[
        {
            "category":"Building & Trades",
            "subcategory":"Cleaning & Sanitation",
            "type":"Services"
        }
    ],
    "sg:phone":"+1 480 832 5181",
    "sg:postcode":"85206",
    "sg:province":"AZ",
    "sg:tags":[
        "janitor"
    ],
    "wof:name":"Buzzy Bee Cleaning Svc",
    "wof:placetype":"venue"
},
  "geometry": {"coordinates":[-111.732809,33.39067],"type":"Point"}
}