{
  "type": "Feature",
  "properties": {
    "iso:country":"US",
    "sg:address":"6106 W Kimberly Way",
    "sg:city":"Glendale",
    "sg:classifiers":[
        {
            "category":"Shopping",
            "subcategory":"Bicycles & Sporting Goods",
            "type":"Retail Goods"
        }
    ],
    "sg:phone":"+1 623 572 7910",
    "sg:postcode":"85308",
    "sg:province":"AZ",
    "wof:name":"Firearms Unlimited",
    "wof:placetype":"venue"
},
  "geometry": {"coordinates":[-112.191073,33.656991],"type":"Point"}
}