{
  "type": "Feature",
  "properties": {
    "addr:full":"2370 S Rio Verde Dr Cottonwood AZ 86326",
    "addr:housenumber":"2370",
    "addr:postcode":"86326",
    "addr:street":"S Rio Verde Dr",
    "iso:country":"US",
    "sg:address":"2370 S Rio Verde Dr",
    "sg:city":"Cottonwood",
    "sg:classifiers":[
        {
            "category":"Professional",
            "type":"Services"
        }
    ],
    "sg:phone":"+1 928 646 6534",
    "sg:postcode":"86326",
    "sg:province":"AZ",
    "sg:tags":[
        "writer"
    ],
    "wof:name":"Joy Gage",
    "wof:placetype":"venue"
},
  "geometry": {"coordinates":[-111.97487599999999,34.696471],"type":"Point"}
}