{
  "type": "Feature",
  "properties": {
    "addr:full":"19120 N Pima Rd Ste 115 Scottsdale AZ 85255",
    "addr:housenumber":"19120",
    "addr:postcode":"85255",
    "addr:street":"N Pima Rd Ste 115",
    "iso:country":"US",
    "sg:address":"19120 N Pima Rd Ste 115",
    "sg:city":"Scottsdale",
    "sg:classifiers":[
        {
            "category":"Home & Garden",
            "subcategory":"Building Materials",
            "type":"Retail Goods"
        }
    ],
    "sg:phone":"+1 480 941 4663",
    "sg:postcode":"85255",
    "sg:province":"AZ",
    "wof:name":"Home Design Idea Center",
    "wof:placetype":"venue"
},
  "geometry": {"coordinates":[-111.890625,33.72578],"type":"Point"}
}