{
  "type": "Feature",
  "properties": {
    "iso:country":"US",
    "sg:address":"1457 W Southern Ave",
    "sg:city":"Mesa",
    "sg:classifiers":[
        {
            "category":"Coffee & Tea",
            "type":"Food & Drink"
        }
    ],
    "sg:menulink":"http://www.allmenus.com/az/phoenix/108302-starbucks-coffee/menu/",
    "sg:phone":"+1 480 833 5593",
    "sg:postcode":"85202",
    "sg:province":"AZ",
    "sg:tags":[
        "american"
    ],
    "wof:name":"Starbucks Coffee",
    "wof:placetype":"venue"
},
  "geometry": {"coordinates":[-111.862436,33.392208],"type":"Point"}
}