{
  "type": "Feature",
  "properties": {
    "iso:country":"US",
    "sg:address":"1360 Quartz Ave",
    "sg:city":"Bullhead City",
    "sg:classifiers":[
        {
            "category":"Freight",
            "type":"Transportation"
        }
    ],
    "sg:phone":"+1 928 763 9079",
    "sg:postcode":"86442",
    "sg:province":"AZ",
    "sg:tags":[
        "operator",
        "trucking"
    ],
    "wof:name":"Chariots of Fire",
    "wof:placetype":"venue"
},
  "geometry": {"coordinates":[-114.599906,35.110707],"type":"Point"}
}