{
  "type": "Feature",
  "properties": {
    "iso:country":"US",
    "sg:address":"1635 Palo Verde Dr",
    "sg:city":"Chino Valley",
    "sg:classifiers":[
        {
            "category":"Manufacturing",
            "subcategory":"Metals",
            "type":"Manufacturing & Wholesale Goods"
        },
        {
            "category":"Home & Garden",
            "subcategory":"Building Materials",
            "type":"Retail Goods"
        }
    ],
    "sg:phone":"+1 928 636 5591",
    "sg:postcode":"86323",
    "sg:province":"AZ",
    "sg:tags":[
        "steel",
        "product",
        "door",
        "mfg",
        "devices",
        "operating",
        "gate"
    ],
    "wof:name":"Able Automatic Gates LLC",
    "wof:placetype":"venue"
},
  "geometry": {"coordinates":[-112.435903,34.757828],"type":"Point"}
}