{
  "type": "Feature",
  "properties": {
    "iso:country":"US",
    "sg:address":"4143 N 16th St",
    "sg:city":"Phoenix",
    "sg:classifiers":[
        {
            "category":"Manufacturing",
            "subcategory":"Jewelry",
            "type":"Manufacturing & Wholesale Goods"
        }
    ],
    "sg:phone":"+1 602 266 4823",
    "sg:postcode":"85016",
    "sg:province":"AZ",
    "sg:tags":[
        "costume"
    ],
    "wof:name":"Drumbeat Indian Arts",
    "wof:placetype":"venue"
},
  "geometry": {"coordinates":[-112.047521,33.497518],"type":"Point"}
}