{
  "type": "Feature",
  "properties": {
    "iso:country":"US",
    "sg:address":"909 S Country Club Dr",
    "sg:city":"Mesa",
    "sg:classifiers":[
        {
            "category":"Travel",
            "subcategory":"Travel Agent",
            "type":"Entertainment"
        },
        {
            "category":"Retail",
            "subcategory":"Storage",
            "type":"Services"
        }
    ],
    "sg:phone":"+1 602 635 9155",
    "sg:postcode":"85210",
    "sg:province":"AZ",
    "sg:tags":[
        "box",
        "travel-storage",
        "automobile",
        "household",
        "commercial",
        "trailers-camping",
        "self",
        "boat"
    ],
    "sg:website":"http://www.ustoreit.com/arizona-self-storage/mesa-self-storage/71.html",
    "wof:name":"U-Store-It Self Storage of Mesa",
    "wof:placetype":"venue"
},
  "geometry": {"coordinates":[-111.840073,33.398595],"type":"Point"}
}