{
  "type": "Feature",
  "properties": {
    "iso:country":"US",
    "sg:address":"7436 E Main St",
    "sg:city":"Mesa",
    "sg:classifiers":[
        {
            "category":"Health Services",
            "subcategory":"Doctor",
            "type":"Services"
        }
    ],
    "sg:phone":"+1 480 981 8386",
    "sg:postcode":"85207",
    "sg:province":"AZ",
    "sg:tags":[
        "clinic"
    ],
    "wof:name":"Medical Clinic",
    "wof:placetype":"venue"
},
  "geometry": {"coordinates":[-111.668088,33.41526],"type":"Point"}
}