{
  "type": "Feature",
  "properties": {
    "addr:full":"1375 N Litchfield Rd Goodyear AZ 85395",
    "addr:housenumber":"1375",
    "addr:postcode":"85395",
    "addr:street":"N Litchfield Rd",
    "iso:country":"US",
    "sg:address":"1375 N Litchfield Rd",
    "sg:city":"Goodyear",
    "sg:classifiers":[
        {
            "category":"Arts & Performance",
            "subcategory":"Arts Center",
            "type":"Entertainment"
        }
    ],
    "sg:phone":"+1 623 935 9244",
    "sg:postcode":"85395",
    "sg:province":"AZ",
    "sg:tags":[
        "performing"
    ],
    "wof:name":"Fred Astaire Franchised Dance Studios",
    "wof:placetype":"venue"
},
  "geometry": {"coordinates":[-112.357996,33.449545],"type":"Point"}
}