{
  "type": "Feature",
  "properties": {
    "addr:full":"2960 N Country Club Rd Tucson AZ 85716",
    "addr:housenumber":"2960",
    "addr:postcode":"85716",
    "addr:street":"N Country Club Rd",
    "iso:country":"US",
    "sg:address":"2960 N Country Club Rd",
    "sg:city":"Tucson",
    "sg:classifiers":[
        {
            "category":"Health Services",
            "subcategory":"Doctor",
            "type":"Services"
        }
    ],
    "sg:phone":"+1 520 287 8071",
    "sg:postcode":"85716",
    "sg:province":"AZ",
    "sg:tags":[
        "physician",
        "surgeon"
    ],
    "wof:name":"Allergy Associates Of Tucson",
    "wof:placetype":"venue"
},
  "geometry": {"coordinates":[-110.926722,32.260188],"type":"Point"}
}