{
  "type": "Feature",
  "properties": {
    "iso:country":"US",
    "sg:address":"10013 N 66th Ave",
    "sg:city":"Glendale",
    "sg:classifiers":[
        {
            "category":"Professional",
            "type":"Services"
        }
    ],
    "sg:phone":"+1 623 486 4428",
    "sg:postcode":"85302",
    "sg:province":"AZ",
    "wof:name":"Susan Servidio Somma",
    "wof:placetype":"venue"
},
  "geometry": {"coordinates":[-112.200683,33.577288],"type":"Point"}
}