{
  "type": "Feature",
  "properties": {
    "iso:country":"US",
    "sg:address":"18425 N 51st Ave",
    "sg:city":"Glendale",
    "sg:classifiers":[
        {
            "category":"Personal",
            "subcategory":"Beauty Salon",
            "type":"Services"
        }
    ],
    "sg:phone":"+1 602 439 4493",
    "sg:postcode":"85308",
    "sg:province":"AZ",
    "sg:tags":[
        "manicuring"
    ],
    "wof:name":"Le's Nail Master",
    "wof:placetype":"venue"
},
  "geometry": {"coordinates":[-112.168787,33.65245],"type":"Point"}
}