{
  "type": "Feature",
  "properties": {
    "addr:full":"8987 W Olive Ave Peoria AZ 85345",
    "addr:housenumber":"8987",
    "addr:postcode":"85345",
    "addr:street":"W Olive Ave",
    "iso:country":"US",
    "sg:address":"8987 W Olive Ave",
    "sg:city":"Peoria",
    "sg:classifiers":[
        {
            "category":"Restaurant",
            "type":"Food & Drink"
        }
    ],
    "sg:phone":"+1 623 878 8828",
    "sg:postcode":"85345",
    "sg:province":"AZ",
    "sg:tags":[
        "eating"
    ],
    "wof:name":"Good China",
    "wof:placetype":"venue"
},
  "geometry": {"coordinates":[-112.25391500000001,33.566239],"type":"Point"}
}