{
  "type": "Feature",
  "properties": {
    "iso:country":"US",
    "sg:address":"3622 W Charter Oak Rd",
    "sg:city":"Phoenix",
    "sg:classifiers":[
        {
            "category":"Shopping",
            "subcategory":"Music",
            "type":"Retail Goods"
        }
    ],
    "sg:phone":"+1 602 843 3150",
    "sg:postcode":"85029",
    "sg:province":"AZ",
    "wof:name":"Records Nastyboy",
    "wof:placetype":"venue"
},
  "geometry": {"coordinates":[-112.137969,33.597746],"type":"Point"}
}