{
  "type": "Feature",
  "properties": {
    "iso:country":"US",
    "sg:address":"6201 W Olive Ave",
    "sg:city":"Glendale",
    "sg:classifiers":[
        {
            "category":"Building & Trades",
            "subcategory":"Plumbing",
            "type":"Services"
        }
    ],
    "sg:phone":"+1 623 931 2382",
    "sg:postcode":"85302",
    "sg:province":"AZ",
    "sg:tags":[
        "contractor"
    ],
    "wof:name":"Rivery AC & Heating",
    "wof:placetype":"venue"
},
  "geometry": {"coordinates":[-112.19257899999999,33.567313],"type":"Point"}
}