{
  "type": "Feature",
  "properties": {
    "addr:full":"2809 W Church St Thatcher AZ 85552",
    "addr:housenumber":"2809",
    "addr:postcode":"85552",
    "addr:street":"W Church St",
    "iso:country":"US",
    "sg:address":"2809 W Church St",
    "sg:city":"Thatcher",
    "sg:classifiers":[
        {
            "category":"Shopping",
            "subcategory":"Clothing, Apparel, & Fashions",
            "type":"Retail Goods"
        }
    ],
    "sg:phone":"+1 928 428 2742",
    "sg:postcode":"85552",
    "sg:province":"AZ",
    "sg:tags":[
        "work",
        "uniform",
        "clothes"
    ],
    "wof:name":"Pro Line Uniforms",
    "wof:placetype":"venue"
},
  "geometry": {"coordinates":[-109.745141,32.845777],"type":"Point"}
}