{
  "type": "Feature",
  "properties": {
    "iso:country":"US",
    "sg:address":"5727 N 7th St",
    "sg:city":"Phoenix",
    "sg:classifiers":[
        {
            "category":"Health Services",
            "subcategory":"Clinic",
            "type":"Services"
        }
    ],
    "sg:phone":"+1 602 266 9971",
    "sg:postcode":"85014",
    "sg:province":"AZ",
    "sg:tags":[
        "home"
    ],
    "wof:name":"M D Home Health & Staffing",
    "wof:placetype":"venue"
},
  "geometry": {"coordinates":[-112.064915,33.521427],"type":"Point"}
}