{
  "type": "Feature",
  "properties": {
    "iso:country":"US",
    "sg:address":"4625 Silver Leaf Trl",
    "sg:city":"Cottonwood",
    "sg:classifiers":[
        {
            "category":"Building & Trades",
            "subcategory":"Construction",
            "type":"Services"
        }
    ],
    "sg:phone":"+1 928 646 5933",
    "sg:postcode":"86326",
    "sg:province":"AZ",
    "sg:tags":[
        "contractor"
    ],
    "wof:name":"Mingus Mountain Masonary",
    "wof:placetype":"venue"
},
  "geometry": {"coordinates":[-111.976829,34.703906],"type":"Point"}
}