{
  "type": "Feature",
  "properties": {
    "iso:country":"US",
    "sg:address":"36 N 35th Ave",
    "sg:city":"Phoenix",
    "sg:classifiers":[
        {
            "category":"Organizations",
            "subcategory":"Professional Association",
            "type":"Services"
        }
    ],
    "sg:phone":"+1 602 427 0003",
    "sg:postcode":"85009",
    "sg:province":"AZ",
    "sg:tags":[
        "business",
        "trade"
    ],
    "wof:name":"Arizona Industrial Ft Blind",
    "wof:placetype":"venue"
},
  "geometry": {"coordinates":[-112.13450899999999,33.448382],"type":"Point"}
}