{
  "type": "Feature",
  "properties": {
    "iso:country":"US",
    "sg:address":"661 W Palo Verde St",
    "sg:city":"Gilbert",
    "sg:classifiers":[
        {
            "category":"Professional",
            "type":"Services"
        }
    ],
    "sg:phone":"+1 480 497 5874",
    "sg:postcode":"85233",
    "sg:province":"AZ",
    "wof:name":"Custom Audit Applications Inc",
    "wof:placetype":"venue"
},
  "geometry": {"coordinates":[-111.806487,33.346985],"type":"Point"}
}