{
  "type": "Feature",
  "properties": {
    "iso:country":"US",
    "sg:address":"1830 E Irvington Rd",
    "sg:city":"Tucson",
    "sg:classifiers":[
        {
            "category":"Food & Beverages",
            "subcategory":"Groceries & Convenience Stores",
            "type":"Retail Goods"
        }
    ],
    "sg:phone":"+1 520 889 3008",
    "sg:postcode":"85714",
    "sg:province":"AZ",
    "sg:tags":[
        "grocer"
    ],
    "wof:name":"Food City",
    "wof:placetype":"venue"
},
  "geometry": {"coordinates":[-110.943855,32.16322],"type":"Point"}
}