{
  "type": "Feature",
  "properties": {
    "iso:country":"US",
    "sg:address":"5524 N 7th Ave",
    "sg:city":"Phoenix",
    "sg:phone":"+1 602 973 1238",
    "sg:postcode":"85013",
    "sg:province":"AZ",
    "wof:name":"Hana Japanese Eatery",
    "wof:placetype":"venue"
},
  "geometry": {"coordinates":[-112.082458,33.516819],"type":"Point"}
}