{
  "type": "Feature",
  "properties": {
    "iso:country":"US",
    "sg:address":"2092 State Hwy 90",
    "sg:city":"Huachuca City",
    "sg:classifiers":[
        {
            "category":"Bars & Pubs",
            "type":"Food & Drink"
        }
    ],
    "sg:phone":"+1 520 456 9815",
    "sg:postcode":"85616",
    "sg:province":"AZ",
    "sg:tags":[
        "drinking"
    ],
    "wof:name":"Fireside Lounge",
    "wof:placetype":"venue"
},
  "geometry": {"coordinates":[-110.350314,31.685085],"type":"Point"}
}