{
  "type": "Feature",
  "properties": {
    "iso:country":"US",
    "sg:address":"501 S Via Esperanza",
    "sg:city":"Tucson",
    "sg:classifiers":[
        {
            "category":"Professional",
            "type":"Services"
        }
    ],
    "sg:phone":"+1 520 325 8733",
    "sg:postcode":"85716",
    "sg:province":"AZ",
    "wof:name":"Intrinsic",
    "wof:placetype":"venue"
},
  "geometry": {"coordinates":[-110.92054899999999,32.214261],"type":"Point"}
}