{
  "type": "Feature",
  "properties": {
    "iso:country":"US",
    "sg:address":"6799 N Rattlesnake Canyon Rd",
    "sg:city":"Tucson",
    "sg:classifiers":[
        {
            "category":"Manufacturing",
            "subcategory":"Printing",
            "type":"Manufacturing & Wholesale Goods"
        }
    ],
    "sg:phone":"+1 520 615 3500",
    "sg:postcode":"85750",
    "sg:province":"AZ",
    "sg:tags":[
        "multimedia"
    ],
    "wof:name":"Media Group Research",
    "wof:placetype":"venue"
},
  "geometry": {"coordinates":[-110.828841,32.323623],"type":"Point"}
}