{
  "type": "Feature",
  "properties": {
    "addr:full":"Arizona Chandler AZ 85224",
    "addr:postcode":"85224",
    "iso:country":"US",
    "sg:address":"Arizona",
    "sg:city":"Chandler",
    "sg:classifiers":[
        {
            "category":"Autos & Motor Vehicles",
            "subcategory":"Automobile Sales",
            "type":"Retail Goods"
        },
        {
            "category":"Airline",
            "type":"Transportation"
        }
    ],
    "sg:phone":"+1 480 855 4990",
    "sg:postcode":"85224",
    "sg:province":"AZ",
    "sg:tags":[
        "shuttle",
        "airport",
        "limo"
    ],
    "wof:name":"Limousine",
    "wof:placetype":"venue"
},
  "geometry": {"coordinates":[-111.876999,33.3279],"type":"Point"}
}