{
  "type": "Feature",
  "properties": {
    "iso:country":"US",
    "sg:address":"4560 S Country Club Rd",
    "sg:city":"Tucson",
    "sg:classifiers":[
        {
            "category":"Freight",
            "type":"Transportation"
        }
    ],
    "sg:phone":"+1 520 748 9707",
    "sg:postcode":"85714",
    "sg:province":"AZ",
    "sg:tags":[
        "special"
    ],
    "wof:name":"Freds Self Storage",
    "wof:placetype":"venue"
},
  "geometry": {"coordinates":[-110.926399,32.168809],"type":"Point"}
}