{
  "type": "Feature",
  "properties": {
    "iso:country":"US",
    "sg:address":"10429 N 21st Ave",
    "sg:city":"Phoenix",
    "sg:classifiers":[
        {
            "category":"Retail",
            "subcategory":"Repair Shop",
            "type":"Services"
        }
    ],
    "sg:phone":"+1 480 575 5357",
    "sg:postcode":"85021",
    "sg:province":"AZ",
    "sg:tags":[
        "range",
        "oven"
    ],
    "wof:name":"G & A Appliance Svc",
    "wof:placetype":"venue"
},
  "geometry": {"coordinates":[-112.103797,33.581748],"type":"Point"}
}