{
  "type": "Feature",
  "properties": {
    "iso:country":"US",
    "sg:address":"2481 E Sierra Madre Ave",
    "sg:city":"Gilbert",
    "sg:classifiers":[
        {
            "category":"Social Services",
            "subcategory":"Adult Care",
            "type":"Services"
        }
    ],
    "sg:phone":"+1 480 507 0802",
    "sg:postcode":"85296",
    "sg:province":"AZ",
    "sg:tags":[
        "home",
        "residential"
    ],
    "wof:name":"Greenfield Assisted Living",
    "wof:placetype":"venue"
},
  "geometry": {"coordinates":[-111.736993,33.347197],"type":"Point"}
}