{
  "type": "Feature",
  "properties": {
    "addr:full":"1921 S Alma School Rd Mesa AZ 85210",
    "addr:housenumber":"1921",
    "addr:postcode":"85210",
    "addr:street":"S Alma School Rd",
    "iso:country":"US",
    "sg:address":"1921 S Alma School Rd",
    "sg:city":"Mesa",
    "sg:classifiers":[
        {
            "category":"Real Estate",
            "subcategory":"Real Estate Agent",
            "type":"Services"
        }
    ],
    "sg:phone":"+1 480 831 2220",
    "sg:postcode":"85210",
    "sg:province":"AZ",
    "sg:tags":[
        "investment"
    ],
    "wof:name":"Sholodan Llc",
    "wof:placetype":"venue"
},
  "geometry": {"coordinates":[-111.859678,33.379384],"type":"Point"}
}