{
  "type": "Feature",
  "properties": {
    "iso:country":"US",
    "sg:address":"728 N Bisbee Ave",
    "sg:city":"Willcox",
    "sg:classifiers":[
        {
            "category":"Restaurant",
            "type":"Food & Drink"
        }
    ],
    "sg:menulink":"http://www.allmenus.com/az/willcox/198818-kfc---kentucky-fried-chicken/menu/",
    "sg:phone":"+1 520 384 4411",
    "sg:postcode":"85643",
    "sg:province":"AZ",
    "sg:tags":[
        "american",
        "chicken"
    ],
    "wof:name":"KFC - Kentucky Fried Chicken",
    "wof:placetype":"venue"
},
  "geometry": {"coordinates":[-109.841401,32.26276],"type":"Point"}
}