{
  "type": "Feature",
  "properties": {
    "iso:country":"US",
    "sg:address":"5302 W Buckeye Rd",
    "sg:city":"Phoenix",
    "sg:classifiers":[
        {
            "category":"Home & Garden",
            "subcategory":"Building Materials",
            "type":"Retail Goods"
        }
    ],
    "sg:phone":"+1 602 278 5000",
    "sg:postcode":"85043",
    "sg:province":"AZ",
    "sg:tags":[
        "hardwood"
    ],
    "wof:name":"Hardwoods Inc",
    "wof:placetype":"venue"
},
  "geometry": {"coordinates":[-112.169403,33.436769],"type":"Point"}
}