{
  "type": "Feature",
  "properties": {
    "addr:full":"2040 W Gardner Ln Tucson AZ 85705",
    "addr:housenumber":"2040",
    "addr:postcode":"85705",
    "addr:street":"W Gardner Ln",
    "iso:country":"US",
    "sg:address":"2040 W Gardner Ln",
    "sg:city":"Tucson",
    "sg:classifiers":[
        {
            "category":"Building & Trades",
            "subcategory":"Construction",
            "type":"Services"
        }
    ],
    "sg:phone":"+1 520 696 9495",
    "sg:postcode":"85705",
    "sg:province":"AZ",
    "sg:tags":[
        "heavy",
        "explosive",
        "mfg",
        "boring",
        "contractor",
        "drilling"
    ],
    "sg:website":"www.swenergy.com",
    "wof:name":"Sasol Southwest Energy LLC",
    "wof:placetype":"venue"
},
  "geometry": {"coordinates":[-111.011162,32.281717],"type":"Point"}
}