{
  "type": "Feature",
  "properties": {
    "iso:country":"US",
    "sg:address":"8301 N 58th Pl",
    "sg:city":"Paradise Valley",
    "sg:classifiers":[
        {
            "category":"Food & Beverages",
            "subcategory":"Groceries & Convenience Stores",
            "type":"Retail Goods"
        }
    ],
    "sg:phone":"+1 480 367 8308",
    "sg:postcode":"85253",
    "sg:province":"AZ",
    "wof:name":"Market Studies Inc",
    "wof:placetype":"venue"
},
  "geometry": {"coordinates":[-111.95603,33.560178],"type":"Point"}
}