{
  "type": "Feature",
  "properties": {
    "addr:full":"19338 N Coyote Lakes Pkwy Surprise AZ 85374",
    "addr:housenumber":"19338",
    "addr:postcode":"85374",
    "addr:street":"N Coyote Lakes Pkwy",
    "iso:country":"US",
    "sg:address":"19338 N Coyote Lakes Pkwy",
    "sg:city":"Surprise",
    "sg:classifiers":[
        {
            "category":"Wholesale",
            "subcategory":"Groceries",
            "type":"Manufacturing & Wholesale Goods"
        }
    ],
    "sg:phone":"+1 623 566 7249",
    "sg:postcode":"85374",
    "sg:province":"AZ",
    "sg:tags":[
        "confectionery",
        "candy"
    ],
    "wof:name":"Convenience Sales & Mdse",
    "wof:placetype":"venue"
},
  "geometry": {"coordinates":[-112.310895,33.660716],"type":"Point"}
}