{
  "type": "Feature",
  "properties": {
    "iso:country":"US",
    "sg:address":"1530 S Freeway Rd",
    "sg:city":"Tucson",
    "sg:classifiers":[
        {
            "category":"Shopping",
            "subcategory":"Hobbies, Toys, & Games",
            "type":"Retail Goods"
        }
    ],
    "sg:phone":"+1 520 620 0007",
    "sg:postcode":"85713",
    "sg:province":"AZ",
    "sg:tags":[
        "shop",
        "rock"
    ],
    "wof:name":"Tucson Showplace",
    "wof:placetype":"venue"
},
  "geometry": {"coordinates":[-110.980151,32.205729],"type":"Point"}
}