{
  "type": "Feature",
  "properties": {
    "iso:country":"US",
    "sg:address":"28518 N 55th St",
    "sg:city":"Cave Creek",
    "sg:classifiers":[
        {
            "category":"Education",
            "subcategory":"School",
            "type":"Public Place"
        }
    ],
    "sg:phone":"+1 480 515 1800",
    "sg:postcode":"85331",
    "sg:province":"AZ",
    "wof:name":"North Phoenix Montessori Schl",
    "wof:placetype":"venue"
},
  "geometry": {"coordinates":[-111.963002,33.743336],"type":"Point"}
}