{
  "type": "Feature",
  "properties": {
    "iso:country":"US",
    "sg:address":"6505 S Anvil Ct",
    "sg:city":"Chandler",
    "sg:classifiers":[
        {
            "category":"Professional",
            "type":"Services"
        }
    ],
    "sg:phone":"+1 480 883 6636",
    "sg:postcode":"85249",
    "sg:province":"AZ",
    "wof:name":"Majestic Gaming LLC",
    "wof:placetype":"venue"
},
  "geometry": {"coordinates":[-111.82943,33.211152],"type":"Point"}
}