{
  "type": "Feature",
  "properties": {
    "addr:full":"7871 W Acoma Dr Peoria AZ 85381",
    "addr:housenumber":"7871",
    "addr:postcode":"85381",
    "addr:street":"W Acoma Dr",
    "iso:country":"US",
    "sg:address":"7871 W Acoma Dr",
    "sg:city":"Peoria",
    "sg:classifiers":[
        {
            "category":"Organizations",
            "subcategory":"Religious Organization",
            "type":"Services"
        }
    ],
    "sg:phone":"+1 623 412 0311",
    "sg:postcode":"85381",
    "sg:province":"AZ",
    "sg:tags":[
        "church"
    ],
    "wof:name":"Church Of Jesus Christ Of Lds",
    "wof:placetype":"venue"
},
  "geometry": {"coordinates":[-112.225167,33.617461],"type":"Point"}
}