{
  "type": "Feature",
  "properties": {
    "iso:country":"US",
    "sg:address":"23500 N 7th St",
    "sg:city":"Phoenix",
    "sg:classifiers":[
        {
            "category":"Home & Garden",
            "subcategory":"Garden Supply",
            "type":"Retail Goods"
        }
    ],
    "sg:phone":"+1 623 780 0333",
    "sg:postcode":"85024",
    "sg:province":"AZ",
    "sg:tags":[
        "equipment",
        "lawn",
        "mulch"
    ],
    "sg:website":"http://www.rocksourcellc.com",
    "wof:name":"Rock Source LLC",
    "wof:placetype":"venue"
},
  "geometry": {"coordinates":[-112.064941,33.69841],"type":"Point"}
}