{
  "type": "Feature",
  "properties": {
    "iso:country":"US",
    "sg:address":"3262 N Windsong Dr",
    "sg:city":"Prescott Valley",
    "sg:classifiers":[
        {
            "category":"Health Services",
            "subcategory":"Doctor",
            "type":"Services"
        }
    ],
    "sg:phone":"+1 928 776 7877",
    "sg:postcode":"86314",
    "sg:province":"AZ",
    "sg:tags":[
        "physician",
        "surgeon"
    ],
    "wof:name":"Rainbow Kid's Clinic",
    "wof:placetype":"venue"
},
  "geometry": {"coordinates":[-112.326727,34.587149],"type":"Point"}
}