{
  "type": "Feature",
  "properties": {
    "addr:full":"1155 W Elliot Rd Tempe AZ 85284",
    "addr:housenumber":"1155",
    "addr:postcode":"85284",
    "addr:street":"W Elliot Rd",
    "iso:country":"US",
    "sg:address":"1155 W Elliot Rd",
    "sg:city":"Tempe",
    "sg:classifiers":[
        {
            "category":"Recreation",
            "type":"Entertainment"
        }
    ],
    "sg:phone":"+1 480 940 3522",
    "sg:postcode":"85284",
    "sg:province":"AZ",
    "sg:tags":[
        "range",
        "practice",
        "golf"
    ],
    "sg:website":"www.fiddlesticksaz.com",
    "wof:name":"Fiddlesticks Golf Learning Ctr",
    "wof:placetype":"venue"
},
  "geometry": {"coordinates":[-111.95656700000001,33.34907],"type":"Point"}
}