{
  "type": "Feature",
  "properties": {
    "addr:full":"2268 N Walgreens St Flagstaff AZ 86004",
    "addr:housenumber":"2268",
    "addr:postcode":"86004",
    "addr:street":"N Walgreens St",
    "iso:country":"US",
    "sg:address":"2268 N Walgreens St",
    "sg:city":"Flagstaff",
    "sg:classifiers":[
        {
            "category":"Real Estate",
            "subcategory":"Real Estate Services",
            "type":"Services"
        },
        {
            "category":"Banks & Credit Unions",
            "subcategory":"Financial Services",
            "type":"Services"
        }
    ],
    "sg:phone":"+1 928 527 6800",
    "sg:postcode":"86004",
    "sg:province":"AZ",
    "sg:tags":[
        "loan",
        "processing"
    ],
    "wof:name":"Allstate Mortgage Co",
    "wof:placetype":"venue"
},
  "geometry": {"coordinates":[-111.603807,35.207181],"type":"Point"}
}