{
  "type": "Feature",
  "properties": {
    "addr:full":"551 W Magee Rd Tucson AZ 85704",
    "addr:housenumber":"551",
    "addr:postcode":"85704",
    "addr:street":"W Magee Rd",
    "iso:country":"US",
    "sg:address":"551 W Magee Rd",
    "sg:city":"Tucson",
    "sg:classifiers":[
        {
            "category":"Health Services",
            "subcategory":"Doctor",
            "type":"Services"
        }
    ],
    "sg:phone":"+1 520 498 6467",
    "sg:postcode":"85704",
    "sg:province":"AZ",
    "sg:tags":[
        "medicine",
        "physician",
        "practice",
        "surgeons",
        "family"
    ],
    "wof:name":"Shashi Goel Md",
    "wof:placetype":"venue"
},
  "geometry": {"coordinates":[-110.978607,32.351799],"type":"Point"}
}