{
  "type": "Feature",
  "properties": {
    "iso:country":"US",
    "sg:address":"6045 W Washington St",
    "sg:city":"Phoenix",
    "sg:classifiers":[
        {
            "category":"Transit Center",
            "subcategory":"Freight",
            "type":"Transportation"
        },
        {
            "category":"Freight",
            "type":"Transportation"
        }
    ],
    "sg:phone":"+1 602 278 9247",
    "sg:postcode":"85043",
    "sg:province":"AZ",
    "sg:tags":[
        "local",
        "trucking-motor",
        "trucking"
    ],
    "wof:name":"Beneto Bulk Transportation",
    "wof:placetype":"venue"
},
  "geometry": {"coordinates":[-112.188647,33.447895],"type":"Point"}
}