{
  "type": "Feature",
  "properties": {
    "addr:full":"450 S Valencia Mesa AZ 85202",
    "addr:housenumber":"450",
    "addr:postcode":"85202",
    "addr:street":"S Valencia",
    "iso:country":"US",
    "sg:address":"450 S Valencia",
    "sg:city":"Mesa",
    "sg:classifiers":[
        {
            "category":"Shopping",
            "subcategory":"Gifts & Souvenirs",
            "type":"Retail Goods"
        }
    ],
    "sg:phone":"+1 480 844 0309",
    "sg:postcode":"85202",
    "sg:province":"AZ",
    "sg:tags":[
        "shop"
    ],
    "wof:name":"Nancy's Gifts",
    "wof:placetype":"venue"
},
  "geometry": {"coordinates":[-111.881141,33.405978],"type":"Point"}
}