{
  "type": "Feature",
  "properties": {
    "iso:country":"US",
    "sg:address":"1105 E Broadway Rd",
    "sg:city":"Tempe",
    "sg:classifiers":[
        {
            "category":"Education",
            "subcategory":"Special Training",
            "type":"Public Place"
        }
    ],
    "sg:phone":"+1 480 736 2490",
    "sg:postcode":"85282",
    "sg:province":"AZ",
    "sg:tags":[
        "center"
    ],
    "wof:name":"Nava Net Learning Inc",
    "wof:placetype":"venue"
},
  "geometry": {"coordinates":[-111.917769,33.407436],"type":"Point"}
}