{
  "type": "Feature",
  "properties": {
    "iso:country":"US",
    "sg:address":"6345 N 15th St",
    "sg:city":"Phoenix",
    "sg:classifiers":[
        {
            "category":"Organizations",
            "subcategory":"Religious Organization",
            "type":"Services"
        }
    ],
    "sg:phone":"+1 602 279 3998",
    "sg:postcode":"85014",
    "sg:province":"AZ",
    "sg:tags":[
        "church"
    ],
    "sg:website":"www.the-cec.org",
    "wof:name":"Center-Expanding Consciousness",
    "wof:placetype":"venue"
},
  "geometry": {"coordinates":[-112.049132,33.528344],"type":"Point"}
}