{
  "type": "Feature",
  "properties": {
    "iso:country":"US",
    "sg:address":"5220 W Luke Ave Ste E4",
    "sg:city":"Glendale",
    "sg:classifiers":[
        {
            "category":"Manufacturing",
            "subcategory":"Metals",
            "type":"Manufacturing & Wholesale Goods"
        },
        {
            "category":"Manufacturing",
            "subcategory":"Building Materials",
            "type":"Manufacturing & Wholesale Goods"
        },
        {
            "category":"Retail",
            "subcategory":"Auto Repair",
            "type":"Services"
        }
    ],
    "sg:phone":"+1 623 435 7017",
    "sg:postcode":"85301",
    "sg:province":"AZ",
    "sg:tags":[
        "shop",
        "sheet",
        "automobile",
        "work",
        "machine",
        "work-manufacturers",
        "fabricator"
    ],
    "wof:name":"Hydratek",
    "wof:placetype":"venue"
},
  "geometry": {"coordinates":[-112.17111199999999,33.518533],"type":"Point"}
}