{
  "type": "Feature",
  "properties": {
    "iso:country":"US",
    "sg:address":"2811 S Black Moon Dr",
    "sg:city":"Tucson",
    "sg:classifiers":[
        {
            "category":"Freight",
            "type":"Transportation"
        }
    ],
    "sg:phone":"+1 520 886 0244",
    "sg:postcode":"85730",
    "sg:province":"AZ",
    "sg:tags":[
        "company"
    ],
    "wof:name":"Desert Eagle Transportation",
    "wof:placetype":"venue"
},
  "geometry": {"coordinates":[-110.784921,32.190375],"type":"Point"}
}