{
  "type": "Feature",
  "properties": {
    "iso:country":"US",
    "sg:address":"110 Morgan Dr",
    "sg:city":"Sedona",
    "sg:classifiers":[
        {
            "category":"Building & Trades",
            "subcategory":"Pest Control",
            "type":"Services"
        }
    ],
    "sg:phone":"+1 928 204 2053",
    "sg:postcode":"86351",
    "sg:province":"AZ",
    "sg:tags":[
        "industrial",
        "services-commercial",
        "mothproofing"
    ],
    "wof:name":"Sedona Bug Busters Inc",
    "wof:placetype":"venue"
},
  "geometry": {"coordinates":[-111.774121,34.769512],"type":"Point"}
}