{
  "type": "Feature",
  "properties": {
    "iso:country":"US",
    "sg:address":"701 E Comstock St",
    "sg:city":"Gilbert",
    "sg:classifiers":[
        {
            "category":"Building & Trades",
            "subcategory":"Construction",
            "type":"Services"
        }
    ],
    "sg:phone":"+1 480 213 3659",
    "sg:postcode":"85296",
    "sg:province":"AZ",
    "sg:tags":[
        "handyman"
    ],
    "wof:name":"IMD Handyman",
    "wof:placetype":"venue"
},
  "geometry": {"coordinates":[-111.774117,33.348602],"type":"Point"}
}