{
  "type": "Feature",
  "properties": {
    "addr:city":"Tucson",
    "addr:full":"2021 N Kinney Rd Tucson, Az 85743-9719",
    "addr:house_number":"2021",
    "addr:housenumber":"2021",
    "addr:postcode":"85743-9719",
    "addr:road":"N Kinney Rd",
    "addr:state":"AZ",
    "addr:street":"N Kinney Rd",
    "iso:country":"US",
    "sg:address":"2021 N Kinney Rd",
    "sg:city":"Tucson",
    "sg:classifiers":[
        {
            "category":"Organizations",
            "subcategory":"Non-profit Organization",
            "type":"Services"
        }
    ],
    "sg:phone":"+1 520 883 1380",
    "sg:postcode":"85743",
    "sg:province":"AZ",
    "wof:airports":[
        102529589
    ],
    "wof:name":"Arizona Sonora Desert Museum",
    "wof:placetype":"venue"
},
  "geometry": {"coordinates":[-111.16237,32.24472],"type":"Point"}
}