{
  "type": "Feature",
  "properties": {
    "addr:full":"2739 W Highland St Chandler AZ 85224",
    "addr:housenumber":"2739",
    "addr:postcode":"85224",
    "addr:street":"W Highland St",
    "iso:country":"US",
    "sg:address":"2739 W Highland St",
    "sg:city":"Chandler",
    "sg:classifiers":[
        {
            "category":"Utilities",
            "subcategory":"Telephone",
            "type":"Services"
        },
        {
            "category":"Professional",
            "subcategory":"Computer Services",
            "type":"Services"
        }
    ],
    "sg:phone":"+1 480 222 0330",
    "sg:postcode":"85224",
    "sg:province":"AZ",
    "sg:tags":[
        "website",
        "web",
        "consulting",
        "communication",
        "dev",
        "design",
        "internet",
        "home",
        "page"
    ],
    "sg:website":"www.hemispheresonline.com",
    "wof:name":"Hemispheres Internet",
    "wof:placetype":"venue"
},
  "geometry": {"coordinates":[-111.889,33.3316],"type":"Point"}
}