{
  "type": "Feature",
  "properties": {
    "iso:country":"US",
    "sg:address":"1741 W Camino Soledad",
    "sg:city":"Yuma",
    "sg:classifiers":[
        {
            "category":"Professional",
            "subcategory":"Business Services",
            "type":"Services"
        }
    ],
    "sg:phone":"+1 928 783 2806",
    "sg:postcode":"85364",
    "sg:province":"AZ",
    "sg:tags":[
        "consultant",
        "coach"
    ],
    "wof:name":"Davis Educational Consultant",
    "wof:placetype":"venue"
},
  "geometry": {"coordinates":[-114.640507,32.685014],"type":"Point"}
}