{
  "type": "Feature",
  "properties": {
    "iso:country":"US",
    "sg:address":"2601 W Claremont St # 2124",
    "sg:city":"Phoenix",
    "sg:classifiers":[
        {
            "category":"Building & Trades",
            "subcategory":"Landscaping Services",
            "type":"Services"
        }
    ],
    "sg:phone":"+1 626 232 3978",
    "sg:postcode":"85017",
    "sg:province":"AZ",
    "sg:tags":[
        "aged",
        "homes-institutional"
    ],
    "wof:name":"Oasis Valley Homes",
    "wof:placetype":"venue"
},
  "geometry": {"coordinates":[-112.114779,33.52858],"type":"Point"}
}