{
  "type": "Feature",
  "properties": {
    "iso:country":"US",
    "sg:address":"515 S Farmer Ave",
    "sg:city":"Tempe",
    "sg:classifiers":[
        {
            "category":"Manufacturing",
            "subcategory":"Building Materials",
            "type":"Manufacturing & Wholesale Goods"
        }
    ],
    "sg:phone":"+1 480 968 7886",
    "sg:postcode":"85281",
    "sg:province":"AZ",
    "sg:tags":[
        "molding"
    ],
    "wof:name":"Bakken's Moulding",
    "wof:placetype":"venue"
},
  "geometry": {"coordinates":[-111.944206,33.424499],"type":"Point"}
}