{
  "type": "Feature",
  "properties": {
    "iso:country":"US",
    "sg:address":"3017 W Sunnyside Dr",
    "sg:city":"Phoenix",
    "sg:classifiers":[
        {
            "category":"Professional",
            "subcategory":"Employment Agencies",
            "type":"Services"
        }
    ],
    "sg:phone":"+1 602 248 7766",
    "sg:postcode":"85029",
    "sg:province":"AZ",
    "sg:tags":[
        "opportunity"
    ],
    "wof:name":"Cosmopolitan Personnel Inc",
    "wof:placetype":"venue"
},
  "geometry": {"coordinates":[-112.122163,33.593127],"type":"Point"}
}