{
  "type": "Feature",
  "properties": {
    "iso:country":"US",
    "sg:address":"37517 N 24th St",
    "sg:city":"Phoenix",
    "sg:classifiers":[
        {
            "category":"Professional",
            "subcategory":"Management & Consulting",
            "type":"Services"
        }
    ],
    "sg:phone":"+1 623 742 6334",
    "sg:postcode":"85086",
    "sg:province":"AZ",
    "sg:tags":[
        "fuel"
    ],
    "wof:name":"Management Madness Inc",
    "wof:placetype":"venue"
},
  "geometry": {"coordinates":[-112.030389,33.828054],"type":"Point"}
}