{
  "type": "Feature",
  "properties": {
    "iso:country":"US",
    "sg:address":"8400 N US Hwy 89",
    "sg:city":"Prescott",
    "sg:classifiers":[
        {
            "category":"Farming",
            "subcategory":"Livestock Farm",
            "type":"Manufacturing & Wholesale Goods"
        }
    ],
    "sg:phone":"+1 928 445 4384",
    "sg:postcode":"86301",
    "sg:province":"AZ",
    "sg:tags":[
        "beef",
        "feedlot",
        "cattle"
    ],
    "wof:name":"Deep Well Ranch Office",
    "wof:placetype":"venue"
},
  "geometry": {"coordinates":[-112.438604,34.664705],"type":"Point"}
}