{
  "type": "Feature",
  "properties": {
    "iso:country":"US",
    "sg:address":"3739 Karicio Ln",
    "sg:city":"Prescott",
    "sg:classifiers":[
        {
            "category":"Wholesale",
            "subcategory":"Office Equipment",
            "type":"Manufacturing & Wholesale Goods"
        }
    ],
    "sg:phone":"+1 928 443 9500",
    "sg:postcode":"86303",
    "sg:province":"AZ",
    "sg:tags":[
        "machine",
        "duplicating",
        "copying"
    ],
    "sg:website":"www.imagingaz.com",
    "wof:name":"Imaging Systems Of Arizona",
    "wof:placetype":"venue"
},
  "geometry": {"coordinates":[-112.398245,34.546178],"type":"Point"}
}