{
  "type": "Feature",
  "properties": {
    "addr:full":"9299 W Olive Ave Peoria AZ 85345",
    "addr:housenumber":"9299",
    "addr:postcode":"85345",
    "addr:street":"W Olive Ave",
    "iso:country":"US",
    "sg:address":"9299 W Olive Ave",
    "sg:city":"Peoria",
    "sg:classifiers":[
        {
            "category":"Home & Garden",
            "subcategory":"Building Materials",
            "type":"Retail Goods"
        },
        {
            "category":"Building & Trades",
            "subcategory":"Construction",
            "type":"Services"
        },
        {
            "category":"Manufacturing",
            "subcategory":"Building Materials",
            "type":"Manufacturing & Wholesale Goods"
        }
    ],
    "sg:phone":"+1 623 266 9505",
    "sg:postcode":"85345",
    "sg:province":"AZ",
    "sg:tags":[
        "frames",
        "window",
        "specialty",
        "doors",
        "accessory"
    ],
    "wof:name":"Slideright",
    "wof:placetype":"venue"
},
  "geometry": {"coordinates":[-112.259365,33.566154],"type":"Point"}
}