{
  "type": "Feature",
  "properties": {
    "iso:country":"US",
    "sg:address":"1880 W Frye Rd Ste 1",
    "sg:city":"Chandler",
    "sg:classifiers":[
        {
            "category":"Health Services",
            "subcategory":"Doctor",
            "type":"Services"
        }
    ],
    "sg:phone":"+1 480 821 5500",
    "sg:postcode":"85224",
    "sg:province":"AZ",
    "sg:website":"www.wellnessmedicalclinic.com",
    "wof:name":"The Wellness Medical Clinic",
    "wof:placetype":"venue"
},
  "geometry": {"coordinates":[-111.874053,33.298823],"type":"Point"}
}