{
  "type": "Feature",
  "properties": {
    "iso:country":"US",
    "sg:address":"3636 E Speedway Blvd",
    "sg:city":"Tucson",
    "sg:classifiers":[
        {
            "category":"Building & Trades",
            "subcategory":"Pest Control",
            "type":"Services"
        }
    ],
    "sg:phone":"+1 520 322 4000",
    "sg:postcode":"85716",
    "sg:province":"AZ",
    "sg:website":"www.trulynolan.com",
    "wof:name":"Truly Nolen Of America Inc",
    "wof:placetype":"venue"
},
  "geometry": {"coordinates":[-110.914937,32.236102],"type":"Point"}
}