{
  "type": "Feature",
  "properties": {
    "addr:full":"1130 S San Jose Mesa AZ 85202",
    "addr:housenumber":"1130",
    "addr:postcode":"85202",
    "addr:street":"S San Jose",
    "iso:country":"US",
    "sg:address":"1130 S San Jose",
    "sg:city":"Mesa",
    "sg:classifiers":[
        {
            "category":"Social Services",
            "subcategory":"Child Care",
            "type":"Services"
        }
    ],
    "sg:phone":"+1 480 969 3781",
    "sg:postcode":"85202",
    "sg:province":"AZ",
    "sg:tags":[
        "kindergarten",
        "academic",
        "school"
    ],
    "sg:website":"www.dobsonmontessori.com",
    "wof:name":"Dobson Montessori School",
    "wof:placetype":"venue"
},
  "geometry": {"coordinates":[-111.878293,33.394182],"type":"Point"}
}