{
  "type": "Feature",
  "properties": {
    "iso:country":"US",
    "sg:address":"4769 W Erie St",
    "sg:city":"Chandler",
    "sg:classifiers":[
        {
            "category":"Building & Trades",
            "subcategory":"Construction",
            "type":"Services"
        }
    ],
    "sg:phone":"+1 480 893 2492",
    "sg:postcode":"85226",
    "sg:province":"AZ",
    "sg:tags":[
        "steel",
        "fabrication",
        "welding"
    ],
    "wof:name":"Gates City Steel Inc",
    "wof:placetype":"venue"
},
  "geometry": {"coordinates":[-111.92686500000001,33.308909],"type":"Point"}
}