{
  "type": "Feature",
  "properties": {
    "addr:full":"18425 N 51st Ave Glendale AZ 85308",
    "addr:housenumber":"18425",
    "addr:postcode":"85308",
    "addr:street":"N 51St Ave",
    "iso:country":"US",
    "sg:address":"18425 N 51st Ave",
    "sg:city":"Glendale",
    "sg:classifiers":[
        {
            "category":"Restaurant",
            "type":"Food & Drink"
        }
    ],
    "sg:menulink":"http://www.allmenus.com/az/phoenix/128974-subway/menu/",
    "sg:phone":"+1 602 863 2090",
    "sg:postcode":"85308",
    "sg:province":"AZ",
    "sg:tags":[
        "american",
        "sandwich"
    ],
    "wof:name":"Subway",
    "wof:placetype":"venue"
},
  "geometry": {"coordinates":[-112.168263,33.653132],"type":"Point"}
}