{
  "type": "Feature",
  "properties": {
    "iso:country":"US",
    "sg:address":"4932 W Pasadena Ave",
    "sg:city":"Glendale",
    "sg:classifiers":[
        {
            "category":"Wholesale",
            "subcategory":"Non-durable Goods",
            "type":"Manufacturing & Wholesale Goods"
        }
    ],
    "sg:phone":"+1 623 939 4108",
    "sg:postcode":"85301",
    "sg:province":"AZ",
    "wof:name":"Distributionservices Inc",
    "wof:placetype":"venue"
},
  "geometry": {"coordinates":[-112.162261,33.511752],"type":"Point"}
}