{
  "type": "Feature",
  "properties": {
    "iso:country":"US",
    "sg:address":"15721 N Greenway Hayden Loop",
    "sg:city":"Scottsdale",
    "sg:classifiers":[
        {
            "category":"Professional",
            "subcategory":"Accounting & Tax Preparation",
            "type":"Services"
        }
    ],
    "sg:phone":"+1 480 778 1751",
    "sg:postcode":"85260",
    "sg:province":"AZ",
    "sg:tags":[
        "accountant"
    ],
    "wof:name":"O'Malley & Laur & Assoc",
    "wof:placetype":"venue"
},
  "geometry": {"coordinates":[-111.914236,33.628289],"type":"Point"}
}