{
  "type": "Feature",
  "properties": {
    "iso:country":"US",
    "sg:address":"740 Mingus View Dr",
    "sg:city":"Cottonwood",
    "sg:classifiers":[
        {
            "category":"Farming",
            "subcategory":"Farm",
            "type":"Manufacturing & Wholesale Goods"
        }
    ],
    "sg:phone":"+1 928 634 8110",
    "sg:postcode":"86326",
    "sg:province":"AZ",
    "sg:tags":[
        "crop",
        "general"
    ],
    "wof:name":"Peter Groseta",
    "wof:placetype":"venue"
},
  "geometry": {"coordinates":[-112.000998,34.725257],"type":"Point"}
}