{
  "type": "Feature",
  "properties": {
    "iso:country":"US",
    "sg:address":"17816 W Dale Ln",
    "sg:city":"Surprise",
    "sg:classifiers":[
        {
            "category":"Building & Trades",
            "subcategory":"Construction",
            "type":"Services"
        }
    ],
    "sg:phone":"+1 623 556 0240",
    "sg:postcode":"85387",
    "sg:province":"AZ",
    "sg:tags":[
        "contractor"
    ],
    "wof:name":"Reyes Ornamental Iron LLC",
    "wof:placetype":"venue"
},
  "geometry": {"coordinates":[-112.44274299999999,33.742234],"type":"Point"}
}