{
  "type": "Feature",
  "properties": {
    "iso:country":"US",
    "sg:address":"604 W Warner Rd Ste B3",
    "sg:city":"Chandler",
    "sg:classifiers":[
        {
            "category":"Health Services",
            "subcategory":"Clinic",
            "type":"Services"
        },
        {
            "category":"Personal",
            "subcategory":"Skin Care",
            "type":"Services"
        },
        {
            "category":"Personal",
            "subcategory":"Beauty Salon",
            "type":"Services"
        }
    ],
    "sg:phone":"+1 480 393 2444",
    "sg:postcode":"85225",
    "sg:province":"AZ",
    "sg:tags":[
        "spa",
        "medical"
    ],
    "wof:name":"Rejuvenation Medical Spa MD",
    "wof:placetype":"venue"
},
  "geometry": {"coordinates":[-111.852341,33.335099],"type":"Point"}
}