{
  "type": "Feature",
  "properties": {
    "addr:full":"1320 San Antonio Ave Douglas AZ 85607",
    "addr:housenumber":"1320",
    "addr:postcode":"85607",
    "addr:street":"San Antonio Ave",
    "iso:country":"US",
    "sg:address":"1320 San Antonio Ave",
    "sg:city":"Douglas",
    "sg:classifiers":[
        {
            "category":"Shopping",
            "subcategory":"Gifts & Souvenirs",
            "type":"Retail Goods"
        }
    ],
    "sg:phone":"+1 520 364 7677",
    "sg:postcode":"85607",
    "sg:province":"AZ",
    "sg:tags":[
        "cards"
    ],
    "wof:name":"Wendys Hallmark Shop 2",
    "wof:placetype":"venue"
},
  "geometry": {"coordinates":[-109.53237799999999,31.348345],"type":"Point"}
}