{
  "type": "Feature",
  "properties": {
    "addr:full":"1497 Heritage Park Rd Prescott AZ 86301",
    "addr:housenumber":"1497",
    "addr:postcode":"86301",
    "addr:street":"Heritage Park Rd",
    "iso:country":"US",
    "sg:address":"1497 Heritage Park Rd",
    "sg:city":"Prescott",
    "sg:classifiers":[
        {
            "category":"Recreation",
            "type":"Entertainment"
        }
    ],
    "sg:phone":"+1 928 708 0795",
    "sg:postcode":"86301",
    "sg:province":"AZ",
    "sg:tags":[
        "parks"
    ],
    "wof:name":"Heritage Park",
    "wof:placetype":"venue"
},
  "geometry": {"coordinates":[-112.441428,34.614523],"type":"Point"}
}