{
  "type": "Feature",
  "properties": {
    "addr:full":"2309 E Lincoln Cir Phoenix AZ 85016",
    "addr:housenumber":"2309",
    "addr:postcode":"85016",
    "addr:street":"E Lincoln Cir",
    "iso:country":"US",
    "sg:address":"2309 E Lincoln Cir",
    "sg:city":"Phoenix",
    "sg:classifiers":[
        {
            "category":"Building & Trades",
            "subcategory":"Construction",
            "type":"Services"
        }
    ],
    "sg:phone":"+1 602 241 1110",
    "sg:postcode":"85016",
    "sg:province":"AZ",
    "sg:tags":[
        "general",
        "contractor"
    ],
    "wof:name":"Tell Construction Co",
    "wof:placetype":"venue"
},
  "geometry": {"coordinates":[-112.03245800000001,33.537557],"type":"Point"}
}