{
  "type": "Feature",
  "properties": {
    "iso:country":"US",
    "sg:address":"3131 W Lewis Ave",
    "sg:city":"Phoenix",
    "sg:classifiers":[
        {
            "category":"Professional",
            "subcategory":"Advertising",
            "type":"Services"
        }
    ],
    "sg:phone":"+1 602 278 3227",
    "sg:postcode":"85009",
    "sg:province":"AZ",
    "sg:tags":[
        "distributing",
        "sample",
        "service-circular"
    ],
    "wof:name":"Firebird Distributing",
    "wof:placetype":"venue"
},
  "geometry": {"coordinates":[-112.126393,33.475128],"type":"Point"}
}