{
  "type": "Feature",
  "properties": {
    "iso:country":"US",
    "sg:address":"2550 N Dragoon St",
    "sg:city":"Tucson",
    "sg:classifiers":[
        {
            "category":"Manufacturing",
            "subcategory":"Food",
            "type":"Manufacturing & Wholesale Goods"
        }
    ],
    "sg:phone":"+1 520 792 6631",
    "sg:postcode":"85745",
    "sg:province":"AZ",
    "sg:tags":[
        "bread"
    ],
    "wof:name":"Bakehouse Bread Company LLC",
    "wof:placetype":"venue"
},
  "geometry": {"coordinates":[-111.000508,32.251362],"type":"Point"}
}