{
  "type": "Feature",
  "properties": {
    "iso:country":"US",
    "sg:address":"4065 W Lower Buckeye Rd",
    "sg:city":"Phoenix",
    "sg:classifiers":[
        {
            "category":"Autos & Motor Vehicles",
            "subcategory":"Automobile Sales",
            "type":"Retail Goods"
        }
    ],
    "sg:phone":"+1 602 272 0085",
    "sg:postcode":"85009",
    "sg:province":"AZ",
    "sg:tags":[
        "auction",
        "car",
        "used"
    ],
    "sg:website":"http://www.saisc.com",
    "wof:name":"Saisc Inc",
    "wof:placetype":"venue"
},
  "geometry": {"coordinates":[-112.146766,33.422552],"type":"Point"}
}