{
  "type": "Feature",
  "properties": {
    "iso:country":"US",
    "sg:address":"3000 W Lobo Rd",
    "sg:city":"Tucson",
    "sg:classifiers":[
        {
            "category":"Professional",
            "subcategory":"Business Services",
            "type":"Services"
        }
    ],
    "sg:phone":"+1 520 742 2003",
    "sg:postcode":"85742",
    "sg:province":"AZ",
    "sg:tags":[
        "services-commercial",
        "printing",
        "commercial",
        "lithographic"
    ],
    "wof:name":"Menu Specialist & Rest Conslt",
    "wof:placetype":"venue"
},
  "geometry": {"coordinates":[-111.031515,32.369906],"type":"Point"}
}