{
  "type": "Feature",
  "properties": {
    "iso:country":"US",
    "sg:address":"4754 S Highway 95",
    "sg:city":"Fort Mohave",
    "sg:classifiers":[
        {
            "category":"Restaurant",
            "type":"Food & Drink"
        }
    ],
    "sg:menulink":"http://www.allmenus.com/az/kingman-south/190502-mcdonalds/menu/",
    "sg:postcode":"86426",
    "sg:province":"AZ",
    "sg:tags":[
        "burger",
        "american"
    ],
    "wof:name":"McDonald's",
    "wof:placetype":"venue"
},
  "geometry": {"coordinates":[-114.597854,35.018268],"type":"Point"}
}