{
  "type": "Feature",
  "properties": {
    "iso:country":"US",
    "sg:address":"16520 E Laser Dr",
    "sg:city":"Fountain Hills",
    "sg:classifiers":[
        {
            "category":"Wholesale",
            "subcategory":"Motor Vehicles",
            "type":"Manufacturing & Wholesale Goods"
        }
    ],
    "sg:phone":"+1 480 836 0556",
    "sg:postcode":"85268",
    "sg:province":"AZ",
    "sg:tags":[
        "automobile",
        "truck",
        "broker"
    ],
    "wof:name":"DRG Express",
    "wof:placetype":"venue"
},
  "geometry": {"coordinates":[-111.72235,33.573236],"type":"Point"}
}