{
  "type": "Feature",
  "properties": {
    "iso:country":"US",
    "sg:address":"1120 Hwy 95",
    "sg:city":"Bullhead City",
    "sg:classifiers":[
        {
            "category":"Shopping",
            "subcategory":"Gifts & Souvenirs",
            "type":"Retail Goods"
        }
    ],
    "sg:phone":"+1 928 754 2355",
    "sg:postcode":"86429",
    "sg:province":"AZ",
    "sg:tags":[
        "shop"
    ],
    "wof:name":"Alicia's Gift Shop",
    "wof:placetype":"venue"
},
  "geometry": {"coordinates":[-114.568461,35.147034],"type":"Point"}
}