{
  "type": "Feature",
  "properties": {
    "iso:country":"US",
    "sg:address":"9100 E Tanque Verde Rd",
    "sg:city":"Tucson",
    "sg:classifiers":[
        {
            "category":"Retail",
            "subcategory":"Veterinary Services",
            "type":"Services"
        }
    ],
    "sg:phone":"+1 520 749 1446",
    "sg:postcode":"85749",
    "sg:province":"AZ",
    "sg:tags":[
        "veterinarian"
    ],
    "wof:name":"Reata Equine Veterinary Svcs",
    "wof:placetype":"venue"
},
  "geometry": {"coordinates":[-110.796055,32.257112],"type":"Point"}
}