{
  "type": "Feature",
  "properties": {
    "addr:full":"4025 E Gold Dust Ave Phoenix AZ 85028",
    "addr:housenumber":"4025",
    "addr:postcode":"85028",
    "addr:street":"E Gold Dust Ave",
    "iso:country":"US",
    "sg:address":"4025 E Gold Dust Ave",
    "sg:city":"Phoenix",
    "sg:classifiers":[
        {
            "category":"Retail",
            "subcategory":"Laundry & Dry Cleaning",
            "type":"Services"
        }
    ],
    "sg:phone":"+1 602 569 1762",
    "sg:postcode":"85028",
    "sg:province":"AZ",
    "sg:tags":[
        "cleaner",
        "commercial"
    ],
    "wof:name":"Pro Cleaners Program",
    "wof:placetype":"venue"
},
  "geometry": {"coordinates":[-111.993559,33.579111],"type":"Point"}
}