{
  "type": "Feature",
  "properties": {
    "iso:country":"US",
    "sg:address":"2015 W Wickenburg Way",
    "sg:city":"Wickenburg",
    "sg:classifiers":[
        {
            "category":"Manufacturing",
            "subcategory":"Tools & Machinery",
            "type":"Manufacturing & Wholesale Goods"
        }
    ],
    "sg:phone":"+1 928 684 2815",
    "sg:postcode":"85390",
    "sg:province":"AZ",
    "sg:tags":[
        "mfg"
    ],
    "wof:name":"Gantrex USA Inc",
    "wof:placetype":"venue"
},
  "geometry": {"coordinates":[-112.772301,33.962158],"type":"Point"}
}