{
  "type": "Feature",
  "properties": {
    "addr:full":"6352 S Nogales Hwy Tucson AZ 85706",
    "addr:housenumber":"6352",
    "addr:postcode":"85706",
    "addr:street":"S Nogales Hwy",
    "iso:country":"US",
    "sg:address":"6352 S Nogales Hwy",
    "sg:city":"Tucson",
    "sg:classifiers":[
        {
            "category":"Food & Beverages",
            "subcategory":"Groceries & Convenience Stores",
            "type":"Retail Goods"
        }
    ],
    "sg:phone":"+1 520 741 7303",
    "sg:postcode":"85706",
    "sg:province":"AZ",
    "wof:name":"Obregone Market",
    "wof:placetype":"venue"
},
  "geometry": {"coordinates":[-110.961631,32.136852],"type":"Point"}
}