{
  "type": "Feature",
  "properties": {
    "iso:country":"US",
    "sg:address":"11615 N 136th St",
    "sg:city":"Scottsdale",
    "sg:classifiers":[
        {
            "category":"Sports & Exercise",
            "subcategory":"Gym",
            "type":"Entertainment"
        }
    ],
    "sg:phone":"+1 480 836 1665",
    "sg:postcode":"85259",
    "sg:province":"AZ",
    "sg:tags":[
        "club",
        "health",
        "studio",
        "gymnasium"
    ],
    "wof:name":"Circuit",
    "wof:placetype":"venue"
},
  "geometry": {"coordinates":[-111.787292,33.592983],"type":"Point"}
}