{
  "type": "Feature",
  "properties": {
    "iso:country":"US",
    "sg:address":"1950 E Southern Ave",
    "sg:city":"Tempe",
    "sg:classifiers":[
        {
            "category":"Insurance",
            "subcategory":"Insurance Agent",
            "type":"Services"
        }
    ],
    "sg:phone":"+1 480 897 6500",
    "sg:postcode":"85282",
    "sg:province":"AZ",
    "wof:name":"Roslyn A Bankston Insurance",
    "wof:placetype":"venue"
},
  "geometry": {"coordinates":[-111.903859,33.392987],"type":"Point"}
}