{
  "type": "Feature",
  "properties": {
    "addr:full":"7750 E Broadway Rd Mesa AZ 85208",
    "addr:housenumber":"7750",
    "addr:postcode":"85208",
    "addr:street":"E Broadway Rd",
    "iso:country":"US",
    "sg:address":"7750 E Broadway Rd",
    "sg:city":"Mesa",
    "sg:classifiers":[
        {
            "category":"Travel",
            "subcategory":"Campground",
            "type":"Entertainment"
        }
    ],
    "sg:phone":"+1 480 984 1111",
    "sg:postcode":"85208",
    "sg:province":"AZ",
    "sg:tags":[
        "recreational",
        "parks",
        "vehicle"
    ],
    "sg:website":"www.carriagemanorrv.com",
    "wof:name":"Carriage Manor RV Resort",
    "wof:placetype":"venue"
},
  "geometry": {"coordinates":[-111.66040099999999,33.407899],"type":"Point"}
}