{
  "type": "Feature",
  "properties": {
    "addr:full":"903 S Rural Rd Tempe AZ 85281",
    "addr:housenumber":"903",
    "addr:postcode":"85281",
    "addr:street":"S Rural Rd",
    "iso:country":"US",
    "sg:address":"903 S Rural Rd",
    "sg:city":"Tempe",
    "sg:classifiers":[
        {
            "category":"Restaurant",
            "type":"Food & Drink"
        }
    ],
    "sg:phone":"+1 480 731 9499",
    "sg:postcode":"85281",
    "sg:province":"AZ",
    "sg:tags":[
        "middle",
        "style",
        "family",
        "eastern"
    ],
    "wof:name":"Cafe Istanbul",
    "wof:placetype":"venue"
},
  "geometry": {"coordinates":[-111.926292,33.420081],"type":"Point"}
}