{
  "type": "Feature",
  "properties": {
    "iso:country":"US",
    "sg:address":"9543 E Guardian Ln",
    "sg:city":"Hereford",
    "sg:classifiers":[
        {
            "category":"Building & Trades",
            "subcategory":"Construction",
            "type":"Services"
        }
    ],
    "sg:phone":"+1 520 366 0399",
    "sg:postcode":"85615",
    "sg:province":"AZ",
    "sg:tags":[
        "house"
    ],
    "wof:name":"Cdt Construction LLC",
    "wof:placetype":"venue"
},
  "geometry": {"coordinates":[-110.150716,31.382542],"type":"Point"}
}