{
  "type": "Feature",
  "properties": {
    "iso:country":"US",
    "sg:address":"118 N Sacaton St",
    "sg:city":"Casa Grande",
    "sg:classifiers":[
        {
            "category":"Local Transit",
            "type":"Transportation"
        }
    ],
    "sg:phone":"+1 520 836 5121",
    "sg:postcode":"85222",
    "sg:province":"AZ",
    "sg:tags":[
        "bus",
        "line"
    ],
    "wof:name":"Greyhound Bus Lines",
    "wof:placetype":"venue"
},
  "geometry": {"coordinates":[-111.756089,32.877314],"type":"Point"}
}