{
  "type": "Feature",
  "properties": {
    "iso:country":"US",
    "sg:address":"5720 W Peoria Ave",
    "sg:city":"Glendale",
    "sg:classifiers":[
        {
            "category":"Personal",
            "type":"Services"
        },
        {
            "category":"Sports & Exercise",
            "subcategory":"Gym",
            "type":"Entertainment"
        },
        {
            "category":"Arena",
            "subcategory":"Sports Club",
            "type":"Entertainment"
        }
    ],
    "sg:phone":"+1 623 432 0894",
    "sg:postcode":"85302",
    "sg:province":"AZ",
    "sg:tags":[
        "trainer",
        "consultant",
        "gymnasium",
        "program",
        "health",
        "fitness",
        "physical"
    ],
    "sg:website":"http://clickserve.dartsearch.net/link/click?lid=43000000196565615",
    "wof:name":"Bally Total Fitness",
    "wof:placetype":"venue"
},
  "geometry": {"coordinates":[-112.182244,33.581991],"type":"Point"}
}