{
  "type": "Feature",
  "properties": {
    "iso:country":"US",
    "sg:address":"19 N Rolland Ridge Rd",
    "sg:city":"Apache Junction",
    "sg:classifiers":[
        {
            "category":"Banks & Credit Unions",
            "subcategory":"Financial Services",
            "type":"Services"
        }
    ],
    "sg:phone":"+1 480 982 1353",
    "sg:postcode":"85219",
    "sg:province":"AZ",
    "sg:tags":[
        "trust",
        "management"
    ],
    "wof:name":"Loney Family Trust 05 06",
    "wof:placetype":"venue"
},
  "geometry": {"coordinates":[-111.499667,33.417928],"type":"Point"}
}