{
  "type": "Feature",
  "properties": {
    "addr:full":"8591 E Bell Rd Ste 101 Scottsdale AZ 85260",
    "addr:housenumber":"8591",
    "addr:postcode":"85260",
    "addr:street":"E Bell Rd Ste 101",
    "iso:country":"US",
    "sg:address":"8591 E Bell Rd Ste 101",
    "sg:city":"Scottsdale",
    "sg:phone":"+1 602 635 4866",
    "sg:postcode":"85260",
    "sg:province":"AZ",
    "sg:website":"http://phoenix.citysearch.com/profile/external/1686834/scottsdale_az/dr_brannon_reed_dds.html?publisher=yellowpages&reference_id=1&placement=ypwebsitemip",
    "wof:name":"Dr. Brannon Reed DDS",
    "wof:placetype":"venue"
},
  "geometry": {"coordinates":[-111.899625,33.640055],"type":"Point"}
}