{
  "type": "Feature",
  "properties": {
    "addr:full":"57 N Valentine St Wickenburg AZ 85390",
    "addr:housenumber":"57",
    "addr:postcode":"85390",
    "addr:street":"N Valentine St",
    "iso:country":"US",
    "sg:address":"57 N Valentine St",
    "sg:city":"Wickenburg",
    "sg:classifiers":[
        {
            "category":"Restaurant",
            "type":"Food & Drink"
        }
    ],
    "sg:phone":"+1 928 684 5777",
    "sg:postcode":"85390",
    "sg:province":"AZ",
    "sg:tags":[
        "eating"
    ],
    "wof:name":"Anitas",
    "wof:placetype":"venue"
},
  "geometry": {"coordinates":[-112.72900199999999,33.969957],"type":"Point"}
}