{
  "type": "Feature",
  "properties": {
    "iso:country":"US",
    "sg:address":"1116 N Stanley Pl",
    "sg:city":"Chandler",
    "sg:classifiers":[
        {
            "category":"Autos & Motor Vehicles",
            "subcategory":"Auto Supplies",
            "type":"Retail Goods"
        },
        {
            "category":"Retail",
            "subcategory":"Auto Repair",
            "type":"Services"
        }
    ],
    "sg:phone":"+1 480 650 3625",
    "sg:postcode":"85226",
    "sg:province":"AZ",
    "sg:tags":[
        "part"
    ],
    "sg:website":"sites.ibizlocal.net/1032/85226.ibiz",
    "wof:name":"Pro-Tech RV",
    "wof:placetype":"venue"
},
  "geometry": {"coordinates":[-111.920968,33.32172],"type":"Point"}
}