{
  "type": "Feature",
  "properties": {
    "iso:country":"US",
    "sg:address":"4558 N 1st Ave",
    "sg:city":"Tucson",
    "sg:classifiers":[
        {
            "category":"Manufacturing",
            "subcategory":"Printing",
            "type":"Manufacturing & Wholesale Goods"
        }
    ],
    "sg:phone":"+1 520 888 1131",
    "sg:postcode":"85718",
    "sg:province":"AZ",
    "sg:tags":[
        "publisher"
    ],
    "wof:name":"Holland Publishing Co",
    "wof:placetype":"venue"
},
  "geometry": {"coordinates":[-110.961086,32.289493],"type":"Point"}
}