{
  "type": "Feature",
  "properties": {
    "addr:full":"16235 N 41st Pl Phoenix AZ 85032",
    "addr:housenumber":"16235",
    "addr:postcode":"85032",
    "addr:street":"N 41St Pl",
    "iso:country":"US",
    "sg:address":"16235 N 41st Pl",
    "sg:city":"Phoenix",
    "sg:classifiers":[
        {
            "category":"Building & Trades",
            "subcategory":"Construction",
            "type":"Services"
        }
    ],
    "sg:phone":"+1 602 493 3146",
    "sg:postcode":"85032",
    "sg:province":"AZ",
    "sg:tags":[
        "general",
        "contractor"
    ],
    "wof:name":"P J Construction Co",
    "wof:placetype":"venue"
},
  "geometry": {"coordinates":[-111.991895,33.634789],"type":"Point"}
}