{
  "type": "Feature",
  "properties": {
    "iso:country":"US",
    "sg:address":"10575 W Indian School Road",
    "sg:city":"Avondale",
    "sg:classifiers":[
        {
            "category":"Personal",
            "subcategory":"Nail Salon",
            "type":"Services"
        }
    ],
    "sg:phone":"+1 623 772 7212",
    "sg:postcode":"85323",
    "sg:province":"AZ",
    "wof:name":"Vs* Nails & Spa",
    "wof:placetype":"venue"
},
  "geometry": {"coordinates":[-112.28785000000001,33.493641],"type":"Point"}
}