{
  "type": "Feature",
  "properties": {
    "iso:country":"US",
    "sg:address":"720 W 4th St",
    "sg:city":"Benson",
    "sg:classifiers":[
        {
            "category":"Shopping",
            "type":"Retail Goods"
        }
    ],
    "sg:phone":"+1 520 586 7227",
    "sg:postcode":"85602",
    "sg:province":"AZ",
    "sg:tags":[
        "farm",
        "truck",
        "merchandise",
        "sup"
    ],
    "wof:name":"Rocking R Mercantile",
    "wof:placetype":"venue"
},
  "geometry": {"coordinates":[-110.31018400000001,31.970794],"type":"Point"}
}