{
  "type": "Feature",
  "properties": {
    "iso:country":"US",
    "sg:address":"4340 E Indian School Rd # 21",
    "sg:city":"Phoenix",
    "sg:classifiers":[
        {
            "category":"Wholesale",
            "subcategory":"Books, Periodicals, & Newspapers",
            "type":"Manufacturing & Wholesale Goods"
        }
    ],
    "sg:phone":"+1 602 955 8414",
    "sg:postcode":"85018",
    "sg:province":"AZ",
    "sg:tags":[
        "publisher",
        "book"
    ],
    "wof:name":"Elemental Light Distributing",
    "wof:placetype":"venue"
},
  "geometry": {"coordinates":[-111.98777699999999,33.49488],"type":"Point"}
}