{
  "type": "Feature",
  "properties": {
    "addr:full":"2935 Maricopa Ave Lake Havasu City AZ 86406",
    "addr:housenumber":"2935",
    "addr:postcode":"86406",
    "addr:street":"Maricopa Ave",
    "iso:country":"US",
    "sg:address":"2935 Maricopa Ave",
    "sg:city":"Lake Havasu City",
    "sg:classifiers":[
        {
            "category":"Building & Trades",
            "subcategory":"Plumbing",
            "type":"Services"
        }
    ],
    "sg:phone":"+1 928 680 8222",
    "sg:postcode":"86406",
    "sg:province":"AZ",
    "sg:tags":[
        "product",
        "management",
        "energy",
        "system"
    ],
    "wof:name":"Energy Control Ctr",
    "wof:placetype":"venue"
},
  "geometry": {"coordinates":[-114.291308,34.456098],"type":"Point"}
}