{
  "type": "Feature",
  "properties": {
    "iso:country":"US",
    "sg:address":"4701 N Stone Ave",
    "sg:city":"Tucson",
    "sg:classifiers":[
        {
            "category":"Shopping",
            "subcategory":"Department Store",
            "type":"Retail Goods"
        }
    ],
    "sg:phone":"+1 520 292 9789",
    "sg:postcode":"85704",
    "sg:province":"AZ",
    "sg:tags":[
        "club",
        "wholesale"
    ],
    "sg:website":"www.samsclub.com",
    "wof:name":"Sam's Club",
    "wof:placetype":"venue"
},
  "geometry": {"coordinates":[-110.971208,32.294677],"type":"Point"}
}