{
  "type": "Feature",
  "properties": {
    "iso:country":"US",
    "sg:address":"6180 W Encanto Blvd",
    "sg:city":"Phoenix",
    "sg:classifiers":[
        {
            "category":"Government",
            "subcategory":"Office",
            "type":"Public Place"
        }
    ],
    "sg:phone":"+1 602 495 5008",
    "sg:postcode":"85035",
    "sg:province":"AZ",
    "wof:name":"Phoenix Police Station",
    "wof:placetype":"venue"
},
  "geometry": {"coordinates":[-112.19247900000001,33.473276],"type":"Point"}
}