{
  "type": "Feature",
  "properties": {
    "iso:country":"US",
    "sg:address":"748 W Hatcher Rd",
    "sg:city":"Phoenix",
    "sg:classifiers":[
        {
            "category":"Wholesale",
            "subcategory":"Durable Goods & Equipment",
            "type":"Manufacturing & Wholesale Goods"
        }
    ],
    "sg:phone":"+1 602 861 1261",
    "sg:postcode":"85021",
    "sg:province":"AZ",
    "sg:tags":[
        "printing",
        "bookbinding",
        "supply"
    ],
    "sg:website":"www.multibusiness.com",
    "wof:name":"Multi Business Systems Inc",
    "wof:placetype":"venue"
},
  "geometry": {"coordinates":[-112.083683,33.571321],"type":"Point"}
}