{
  "type": "Feature",
  "properties": {
    "addr:full":"6066 N Oracle Rd Tucson AZ 85704",
    "addr:housenumber":"6066",
    "addr:postcode":"85704",
    "addr:street":"N Oracle Rd",
    "iso:country":"US",
    "sg:address":"6066 N Oracle Rd",
    "sg:city":"Tucson",
    "sg:classifiers":[
        {
            "category":"Shopping",
            "subcategory":"Computers & Home Electronics",
            "type":"Retail Goods"
        }
    ],
    "sg:phone":"+1 520 742 9300",
    "sg:postcode":"85704",
    "sg:province":"AZ",
    "sg:tags":[
        "equipment",
        "satellite",
        "system"
    ],
    "sg:website":"www.digitalsatellitefree.com",
    "wof:name":"Satellite City",
    "wof:placetype":"venue"
},
  "geometry": {"coordinates":[-110.97627,32.316173],"type":"Point"}
}