{
  "type": "Feature",
  "properties": {
    "addr:full":"6818 N 13th St Phoenix AZ 85014",
    "addr:housenumber":"6818",
    "addr:postcode":"85014",
    "addr:street":"N 13Th St",
    "iso:country":"US",
    "sg:address":"6818 N 13th St",
    "sg:city":"Phoenix",
    "sg:classifiers":[
        {
            "category":"Professional",
            "type":"Services"
        }
    ],
    "sg:phone":"+1 602 277 1045",
    "sg:postcode":"85014",
    "sg:province":"AZ",
    "wof:name":"Courageous Creativity LLC",
    "wof:placetype":"venue"
},
  "geometry": {"coordinates":[-112.05362100000001,33.536076],"type":"Point"}
}