{
  "type": "Feature",
  "properties": {
    "addr:full":"661 S Hawes Rd Mesa AZ 85208",
    "addr:housenumber":"661",
    "addr:postcode":"85208",
    "addr:street":"S Hawes Rd",
    "iso:country":"US",
    "sg:address":"661 S Hawes Rd",
    "sg:city":"Mesa",
    "sg:classifiers":[
        {
            "category":"Real Estate",
            "subcategory":"Developer",
            "type":"Services"
        },
        {
            "category":"Real Estate",
            "subcategory":"Real Estate Operator",
            "type":"Services"
        }
    ],
    "sg:phone":"+1 480 984 2323",
    "sg:postcode":"85208",
    "sg:province":"AZ",
    "sg:tags":[
        "mobile",
        "home",
        "site"
    ],
    "wof:name":"Casa Serena Mobile Home Park",
    "wof:placetype":"venue"
},
  "geometry": {"coordinates":[-111.650021,33.403556],"type":"Point"}
}