{
  "type": "Feature",
  "properties": {
    "iso:country":"US",
    "sg:address":"6408 W Monte Cristo Ave",
    "sg:city":"Glendale",
    "sg:classifiers":[
        {
            "category":"Shopping",
            "type":"Retail Goods"
        }
    ],
    "sg:phone":"+1 623 412 1400",
    "sg:postcode":"85306",
    "sg:province":"AZ",
    "sg:tags":[
        "mail",
        "voice",
        "system"
    ],
    "wof:name":"Arch Communications Inc",
    "wof:placetype":"venue"
},
  "geometry": {"coordinates":[-112.196955,33.631164],"type":"Point"}
}