{
  "type": "Feature",
  "properties": {
    "iso:country":"US",
    "sg:address":"4719 W Thomas Rd",
    "sg:city":"Phoenix",
    "sg:classifiers":[
        {
            "category":"Utilities",
            "subcategory":"Mobile Phone",
            "type":"Services"
        },
        {
            "category":"Utilities",
            "subcategory":"Telephone",
            "type":"Services"
        },
        {
            "category":"Manufacturing",
            "subcategory":"Electronics",
            "type":"Manufacturing & Wholesale Goods"
        }
    ],
    "sg:phone":"+1 602 759 8522",
    "sg:postcode":"85031",
    "sg:province":"AZ",
    "sg:tags":[
        "equipment",
        "telecommunications-equipment",
        "system",
        "cellular",
        "supply"
    ],
    "wof:name":"Coneczion De Luz Cellulars",
    "wof:placetype":"venue"
},
  "geometry": {"coordinates":[-112.160313,33.480511],"type":"Point"}
}