{
  "type": "Feature",
  "properties": {
    "iso:country":"US",
    "sg:address":"4214 W Carter Rd",
    "sg:city":"Phoenix",
    "sg:classifiers":[
        {
            "category":"Building & Trades",
            "subcategory":"Construction",
            "type":"Services"
        }
    ],
    "sg:phone":"+1 602 677 6448",
    "sg:postcode":"85041",
    "sg:province":"AZ",
    "sg:tags":[
        "rack"
    ],
    "wof:name":"The Hat Rack",
    "wof:placetype":"venue"
},
  "geometry": {"coordinates":[-112.14900900000001,33.381903],"type":"Point"}
}