{
  "type": "Feature",
  "properties": {
    "iso:country":"US",
    "sg:address":"5011 W Davis Rd",
    "sg:city":"Glendale",
    "sg:classifiers":[
        {
            "category":"Professional",
            "subcategory":"Detective & Security Services",
            "type":"Services"
        }
    ],
    "sg:phone":"+1 602 938 0100",
    "sg:postcode":"85306",
    "sg:province":"AZ",
    "sg:tags":[
        "information",
        "bureau"
    ],
    "wof:name":"Empire Pool Service",
    "wof:placetype":"venue"
},
  "geometry": {"coordinates":[-112.165692,33.63136],"type":"Point"}
}