{
  "type": "Feature",
  "properties": {
    "addr:full":"806 N 3rd St Cottonwood AZ 86326",
    "addr:housenumber":"806",
    "addr:postcode":"86326",
    "addr:street":"N 3Rd St",
    "iso:country":"US",
    "sg:address":"806 N 3rd St",
    "sg:city":"Cottonwood",
    "sg:classifiers":[
        {
            "category":"Organizations",
            "subcategory":"Religious Organization",
            "type":"Services"
        }
    ],
    "sg:phone":"+1 928 634 9643",
    "sg:postcode":"86326",
    "sg:province":"AZ",
    "sg:tags":[
        "church"
    ],
    "wof:name":"Church Of Christ",
    "wof:placetype":"venue"
},
  "geometry": {"coordinates":[-112.024902,34.745848],"type":"Point"}
}