{
  "type": "Feature",
  "properties": {
    "addr:full":"1124 S Dobson Rd Mesa AZ 85202",
    "addr:housenumber":"1124",
    "addr:postcode":"85202",
    "addr:street":"S Dobson Rd",
    "iso:country":"US",
    "sg:address":"1124 S Dobson Rd",
    "sg:city":"Mesa",
    "sg:classifiers":[
        {
            "category":"Restaurant",
            "type":"Food & Drink"
        }
    ],
    "sg:menulink":"http://www.allmenus.com/az/phoenix/204959-taco-bell/menu/",
    "sg:postcode":"85202",
    "sg:province":"AZ",
    "sg:tags":[
        "mexican"
    ],
    "wof:name":"Taco Bell",
    "wof:placetype":"venue"
},
  "geometry": {"coordinates":[-111.874593,33.394186],"type":"Point"}
}