{
  "type": "Feature",
  "properties": {
    "iso:country":"US",
    "sg:address":"3233 S Magda Ave",
    "sg:city":"Tucson",
    "sg:classifiers":[
        {
            "category":"Retail",
            "subcategory":"Portrait Studio",
            "type":"Services"
        }
    ],
    "sg:phone":"+1 520 358 9083",
    "sg:postcode":"85730",
    "sg:province":"AZ",
    "sg:tags":[
        "photographer"
    ],
    "wof:name":"Wellbeloved Photography",
    "wof:placetype":"venue"
},
  "geometry": {"coordinates":[-110.807331,32.18216],"type":"Point"}
}