{
  "type": "Feature",
  "properties": {
    "iso:country":"US",
    "sg:address":"4534 N 44th Ave",
    "sg:city":"Phoenix",
    "sg:classifiers":[
        {
            "category":"Manufacturing",
            "subcategory":"Rubber & Plastics",
            "type":"Manufacturing & Wholesale Goods"
        }
    ],
    "sg:phone":"+1 623 846 2940",
    "sg:postcode":"85031",
    "sg:province":"AZ",
    "sg:tags":[
        "injection",
        "product",
        "mfg"
    ],
    "wof:name":"Laich Industries Corp",
    "wof:placetype":"venue"
},
  "geometry": {"coordinates":[-112.15425999999999,33.504455],"type":"Point"}
}