{
  "type": "Feature",
  "properties": {
    "iso:country":"US",
    "sg:address":"5635 E Grant Rd",
    "sg:city":"Tucson",
    "sg:classifiers":[
        {
            "category":"Health Services",
            "subcategory":"Doctor",
            "type":"Services"
        }
    ],
    "sg:phone":"+1 520 721 7995",
    "sg:postcode":"85712",
    "sg:province":"AZ",
    "sg:tags":[
        "physician",
        "surgeon"
    ],
    "wof:name":"Southern Arizona Ophthalmology",
    "wof:placetype":"venue"
},
  "geometry": {"coordinates":[-110.871236,32.250743],"type":"Point"}
}