{
  "type": "Feature",
  "properties": {
    "iso:country":"US",
    "sg:address":"4336 E Beck Ln",
    "sg:city":"Phoenix",
    "sg:classifiers":[
        {
            "category":"Real Estate",
            "subcategory":"Real Estate Operator",
            "type":"Services"
        }
    ],
    "sg:phone":"+1 602 788 1931",
    "sg:postcode":"85032",
    "sg:province":"AZ",
    "sg:tags":[
        "building",
        "nonresidential"
    ],
    "wof:name":"Barrick Properties",
    "wof:placetype":"venue"
},
  "geometry": {"coordinates":[-111.98683200000001,33.62689],"type":"Point"}
}