{
  "type": "Feature",
  "properties": {
    "iso:country":"US",
    "sg:address":"4629 E Caron St",
    "sg:city":"Phoenix",
    "sg:classifiers":[
        {
            "category":"Health Services",
            "subcategory":"Doctor",
            "type":"Services"
        }
    ],
    "sg:phone":"+1 480 368 0368",
    "sg:postcode":"85028",
    "sg:province":"AZ",
    "sg:tags":[
        "physician",
        "surgeon"
    ],
    "wof:name":"Center For Pain & Rehab",
    "wof:placetype":"venue"
},
  "geometry": {"coordinates":[-111.980555,33.568841],"type":"Point"}
}