{
  "type": "Feature",
  "properties": {
    "addr:full":"3314 W Rose Ln Phoenix AZ 85017",
    "addr:housenumber":"3314",
    "addr:postcode":"85017",
    "addr:street":"W Rose Ln",
    "iso:country":"US",
    "sg:address":"3314 W Rose Ln",
    "sg:city":"Phoenix",
    "sg:classifiers":[
        {
            "category":"Place Of Worship",
            "subcategory":"Church",
            "type":"Public Place"
        },
        {
            "category":"Place Of Worship",
            "type":"Public Place"
        }
    ],
    "sg:phone":"+1 602 246 6400",
    "sg:postcode":"85017",
    "sg:province":"AZ",
    "sg:tags":[
        "churches-presbyterian-arp",
        "churches-presbyterian"
    ],
    "wof:name":"Korean New Life Presbyterian",
    "wof:placetype":"venue"
},
  "geometry": {"coordinates":[-112.13033,33.527607],"type":"Point"}
}