{
  "type": "Feature",
  "properties": {
    "addr:full":"828 E Broadway Rd Mesa AZ 85204",
    "addr:housenumber":"828",
    "addr:postcode":"85204",
    "addr:street":"E Broadway Rd",
    "iso:country":"US",
    "sg:address":"828 E Broadway Rd",
    "sg:city":"Mesa",
    "sg:classifiers":[
        {
            "category":"Government",
            "subcategory":"Office",
            "type":"Public Place"
        }
    ],
    "sg:phone":"+1 602 644 2377",
    "sg:postcode":"85204",
    "sg:province":"AZ",
    "sg:tags":[
        "village"
    ],
    "wof:name":"Mesa City Government",
    "wof:placetype":"venue"
},
  "geometry": {"coordinates":[-111.811948,33.407857],"type":"Point"}
}