{
  "type": "Feature",
  "properties": {
    "iso:country":"US",
    "sg:address":"2808 N 46th St",
    "sg:city":"Phoenix",
    "sg:classifiers":[
        {
            "category":"Education",
            "subcategory":"Library",
            "type":"Public Place"
        },
        {
            "category":"Government",
            "subcategory":"Office",
            "type":"Public Place"
        }
    ],
    "sg:phone":"+1 602 262 4636",
    "sg:postcode":"85008",
    "sg:province":"AZ",
    "sg:tags":[
        "township",
        "government-city",
        "village"
    ],
    "sg:website":"http://www.realestatedivision.com",
    "wof:name":"Saguaro Branch Library",
    "wof:placetype":"venue"
},
  "geometry": {"coordinates":[-111.982586,33.478316],"type":"Point"}
}