{
  "type": "Feature",
  "properties": {
    "iso:country":"US",
    "sg:address":"339 S Broad St",
    "sg:city":"Globe",
    "sg:classifiers":[
        {
            "category":"Education",
            "subcategory":"Library",
            "type":"Public Place"
        }
    ],
    "sg:phone":"+1 928 425 6111",
    "sg:postcode":"85501",
    "sg:province":"AZ",
    "wof:name":"Globe Public Library",
    "wof:placetype":"venue"
},
  "geometry": {"coordinates":[-110.786151,33.394184],"type":"Point"}
}