{
  "type": "Feature",
  "properties": {
    "addr:full":"4030 N 44th Ave Phoenix AZ 85031",
    "addr:housenumber":"4030",
    "addr:postcode":"85031",
    "addr:street":"N 44Th Ave",
    "iso:country":"US",
    "sg:address":"4030 N 44th Ave",
    "sg:city":"Phoenix",
    "sg:classifiers":[
        {
            "category":"Real Estate",
            "subcategory":"Real Estate Operator",
            "type":"Services"
        }
    ],
    "sg:phone":"+1 602 233 2749",
    "sg:postcode":"85031",
    "sg:province":"AZ",
    "sg:tags":[
        "apartment"
    ],
    "wof:name":"Cove On 44th Apartments",
    "wof:placetype":"venue"
},
  "geometry": {"coordinates":[-112.15451400000001,33.494722],"type":"Point"}
}