{
  "type": "Feature",
  "properties": {
    "addr:full":"2458 E Billings St Mesa AZ 85213",
    "addr:housenumber":"2458",
    "addr:postcode":"85213",
    "addr:street":"E Billings St",
    "iso:country":"US",
    "sg:address":"2458 E Billings St",
    "sg:city":"Mesa",
    "sg:classifiers":[
        {
            "category":"Manufacturing",
            "subcategory":"Building Materials",
            "type":"Manufacturing & Wholesale Goods"
        }
    ],
    "sg:phone":"+1 480 649 3197",
    "sg:postcode":"85213",
    "sg:province":"AZ",
    "sg:tags":[
        "mfg",
        "wood",
        "kitchen",
        "cabinet"
    ],
    "wof:name":"S&M Cabinet & Trim Co LLC",
    "wof:placetype":"venue"
},
  "geometry": {"coordinates":[-111.777151,33.420784],"type":"Point"}
}