{
  "type": "Feature",
  "properties": {
    "iso:country":"US",
    "sg:address":"23169 N 79th Ave",
    "sg:city":"Peoria",
    "sg:classifiers":[
        {
            "category":"Building & Trades",
            "subcategory":"Construction",
            "type":"Services"
        }
    ],
    "sg:phone":"+1 623 572 0446",
    "sg:postcode":"85383",
    "sg:province":"AZ",
    "sg:tags":[
        "paving",
        "contractor"
    ],
    "wof:name":"A-1 Paving and Grading Inc",
    "wof:placetype":"venue"
},
  "geometry": {"coordinates":[-112.229011,33.695558],"type":"Point"}
}