{
  "type": "Feature",
  "properties": {
    "addr:full":"4040 W Ray Rd Ste 8 Chandler AZ 85226",
    "addr:housenumber":"4040",
    "addr:postcode":"85226",
    "addr:street":"W Ray Rd Ste 8",
    "iso:country":"US",
    "sg:address":"4040 W Ray Rd Ste 8",
    "sg:city":"Chandler",
    "sg:classifiers":[
        {
            "category":"Real Estate",
            "subcategory":"Real Estate Services",
            "type":"Services"
        },
        {
            "category":"Real Estate",
            "subcategory":"Real Estate Agent",
            "type":"Services"
        }
    ],
    "sg:phone":"+1 480 539 8500",
    "sg:postcode":"85226",
    "sg:province":"AZ",
    "sg:tags":[
        "management"
    ],
    "sg:website":"http://www.lucasrealtygroup.com",
    "wof:name":"Lucas Group-Re-Source One Real",
    "wof:placetype":"venue"
},
  "geometry": {"coordinates":[-111.912049,33.320095],"type":"Point"}
}