{
  "type": "Feature",
  "properties": {
    "addr:full":"1366 W Broadway Rd Mesa AZ 85202",
    "addr:housenumber":"1366",
    "addr:postcode":"85202",
    "addr:street":"W Broadway Rd",
    "iso:country":"US",
    "sg:address":"1366 W Broadway Rd",
    "sg:city":"Mesa",
    "sg:classifiers":[
        {
            "category":"Autos & Motor Vehicles",
            "subcategory":"Automobile Sales",
            "type":"Retail Goods"
        }
    ],
    "sg:phone":"+1 480 615 8881",
    "sg:postcode":"85202",
    "sg:province":"AZ",
    "sg:tags":[
        "car",
        "dealer"
    ],
    "wof:name":"J J Auto Sales",
    "wof:placetype":"venue"
},
  "geometry": {"coordinates":[-111.86097599999999,33.407693],"type":"Point"}
}