{
  "type": "Feature",
  "properties": {
    "iso:country":"US",
    "sg:address":"2225 W Indian School Rd",
    "sg:city":"Phoenix",
    "sg:classifiers":[
        {
            "category":"Wholesale",
            "subcategory":"Vending Machines",
            "type":"Manufacturing & Wholesale Goods"
        }
    ],
    "sg:phone":"+1 602 332 6323",
    "sg:postcode":"85015",
    "sg:province":"AZ",
    "sg:tags":[
        "merchandise"
    ],
    "wof:name":"Becerra Novelty Vending",
    "wof:placetype":"venue"
},
  "geometry": {"coordinates":[-112.10804,33.495022],"type":"Point"}
}