{
  "type": "Feature",
  "properties": {
    "iso:country":"US",
    "sg:address":"1470 Iron Springs Rd",
    "sg:city":"Prescott",
    "sg:classifiers":[
        {
            "category":"Autos & Motor Vehicles",
            "subcategory":"Motorcycle Sales",
            "type":"Retail Goods"
        }
    ],
    "sg:phone":"+1 928 778 3078",
    "sg:postcode":"86305",
    "sg:province":"AZ",
    "wof:name":"Chico Custom Choppers",
    "wof:placetype":"venue"
},
  "geometry": {"coordinates":[-112.494043,34.567248],"type":"Point"}
}