{
  "type": "Feature",
  "properties": {
    "iso:country":"US",
    "sg:address":"1615 W Camelback Rd",
    "sg:city":"Phoenix",
    "sg:classifiers":[
        {
            "category":"Restaurant",
            "type":"Food & Drink"
        }
    ],
    "sg:menulink":"http://www.allmenus.com/az/phoenix/87641-little-caesars-pizza/menu/",
    "sg:phone":"+1 602 631 9449",
    "sg:postcode":"85015",
    "sg:province":"AZ",
    "sg:tags":[
        "american",
        "pizza"
    ],
    "wof:name":"Little Caesar's Pizza",
    "wof:placetype":"venue"
},
  "geometry": {"coordinates":[-112.09481700000001,33.508614],"type":"Point"}
}