{
  "type": "Feature",
  "properties": {
    "iso:country":"US",
    "sg:address":"15679 N 83rd Way",
    "sg:city":"Scottsdale",
    "sg:classifiers":[
        {
            "category":"Building & Trades",
            "subcategory":"Construction",
            "type":"Services"
        }
    ],
    "sg:phone":"+1 480 391 7222",
    "sg:postcode":"85260",
    "sg:province":"AZ",
    "sg:tags":[
        "painter"
    ],
    "wof:name":"Desert Canyon Epoxy Inc",
    "wof:placetype":"venue"
},
  "geometry": {"coordinates":[-111.90235,33.626214],"type":"Point"}
}