{
  "type": "Feature",
  "properties": {
    "addr:full":"5801 S 15th Ave Phoenix AZ 85041",
    "addr:housenumber":"5801",
    "addr:postcode":"85041",
    "addr:street":"S 15Th Ave",
    "iso:country":"US",
    "sg:address":"5801 S 15th Ave",
    "sg:city":"Phoenix",
    "sg:classifiers":[
        {
            "category":"Building & Trades",
            "subcategory":"Construction",
            "type":"Services"
        }
    ],
    "sg:phone":"+1 602 268 7067",
    "sg:postcode":"85041",
    "sg:province":"AZ",
    "sg:tags":[
        "wallcoverings-installation",
        "wallpaper",
        "painting",
        "contractor"
    ],
    "wof:name":"Blend Painting",
    "wof:placetype":"venue"
},
  "geometry": {"coordinates":[-112.09053299999999,33.393419],"type":"Point"}
}