{
  "type": "Feature",
  "properties": {
    "addr:full":"2950 S Alma School Rd Mesa AZ 85210",
    "addr:housenumber":"2950",
    "addr:postcode":"85210",
    "addr:street":"S Alma School Rd",
    "iso:country":"US",
    "sg:address":"2950 S Alma School Rd",
    "sg:city":"Mesa",
    "sg:classifiers":[
        {
            "category":"Social Services",
            "type":"Services"
        }
    ],
    "sg:phone":"+1 480 821 1330",
    "sg:postcode":"85210",
    "sg:province":"AZ",
    "sg:tags":[
        "counselor",
        "marriage",
        "family"
    ],
    "wof:name":"Good Works Counseling",
    "wof:placetype":"venue"
},
  "geometry": {"coordinates":[-111.859146,33.36297],"type":"Point"}
}