{
  "type": "Feature",
  "properties": {
    "addr:full":"2223 W Pecos Rd Ste 10 Chandler AZ 85224",
    "addr:housenumber":"2223;10",
    "addr:postcode":"85224",
    "addr:street":"W Pecos Rd Ste",
    "iso:country":"US",
    "sg:address":"2223 W Pecos Rd Ste 10",
    "sg:city":"Chandler",
    "sg:classifiers":[
        {
            "category":"Health Services",
            "subcategory":"Nursing And Care Facility",
            "type":"Services"
        },
        {
            "category":"Health Services",
            "subcategory":"Health Practitioner",
            "type":"Services"
        },
        {
            "category":"Health Services",
            "subcategory":"Chiropractor",
            "type":"Services"
        }
    ],
    "sg:phone":"+1 480 390 1962",
    "sg:postcode":"85224",
    "sg:province":"AZ",
    "sg:tags":[
        "control",
        "management",
        "pain",
        "weight",
        "chiropractic",
        "reducing",
        "medicine",
        "therapist",
        "therapy",
        "treatment",
        "nutritionist",
        "injury",
        "sport",
        "physical"
    ],
    "sg:website":"elitesportstherapyaz.com",
    "wof:name":"Elite Chiropractic & Sports Therapy",
    "wof:placetype":"venue"
},
  "geometry": {"coordinates":[-111.880098,33.29134],"type":"Point"}
}