{
  "type": "Feature",
  "properties": {
    "addr:full":"2155 Shelby Dr Sedona AZ 86336",
    "addr:housenumber":"2155",
    "addr:postcode":"86336",
    "addr:street":"Shelby Dr",
    "iso:country":"US",
    "sg:address":"2155 Shelby Dr",
    "sg:city":"Sedona",
    "sg:classifiers":[
        {
            "category":"Real Estate",
            "subcategory":"Real Estate Agent",
            "type":"Services"
        }
    ],
    "sg:phone":"+1 928 282 0850",
    "sg:postcode":"86336",
    "sg:province":"AZ",
    "sg:tags":[
        "appraiser"
    ],
    "wof:name":"Bock Appraisal Svc",
    "wof:placetype":"venue"
},
  "geometry": {"coordinates":[-111.798174,34.853637],"type":"Point"}
}