{
  "type": "Feature",
  "properties": {
    "addr:full":"7343 W Angela Dr Glendale AZ 85308",
    "addr:housenumber":"7343",
    "addr:postcode":"85308",
    "addr:street":"W Angela Dr",
    "iso:country":"US",
    "sg:address":"7343 W Angela Dr",
    "sg:city":"Glendale",
    "sg:classifiers":[
        {
            "category":"Building & Trades",
            "subcategory":"Construction",
            "type":"Services"
        }
    ],
    "sg:phone":"+1 623 695 2622",
    "sg:postcode":"85308",
    "sg:province":"AZ",
    "sg:tags":[
        "demolition",
        "contractor"
    ],
    "wof:name":"Jbs Demolition And Services",
    "wof:placetype":"venue"
},
  "geometry": {"coordinates":[-112.216476,33.642566],"type":"Point"}
}