{
  "type": "Feature",
  "properties": {
    "iso:country":"US",
    "sg:address":"1826 W Sahuaro Dr",
    "sg:city":"Phoenix",
    "sg:classifiers":[
        {
            "category":"Manufacturing",
            "subcategory":"Motor Vehicles & Parts",
            "type":"Manufacturing & Wholesale Goods"
        }
    ],
    "sg:phone":"+1 602 870 0048",
    "sg:postcode":"85029",
    "sg:province":"AZ",
    "sg:tags":[
        "automobile",
        "supply"
    ],
    "wof:name":"Cactus Drive-Axle",
    "wof:placetype":"venue"
},
  "geometry": {"coordinates":[-112.09921,33.58398],"type":"Point"}
}