{
  "type": "Feature",
  "properties": {
    "addr:full":"8603 E Royal Palm Rd Scottsdale AZ 85258",
    "addr:housenumber":"8603",
    "addr:postcode":"85258",
    "addr:street":"E Royal Palm Rd",
    "iso:country":"US",
    "sg:address":"8603 E Royal Palm Rd",
    "sg:city":"Scottsdale",
    "sg:classifiers":[
        {
            "category":"Professional",
            "subcategory":"Management & Consulting",
            "type":"Services"
        }
    ],
    "sg:phone":"+1 480 991 3103",
    "sg:postcode":"85258",
    "sg:province":"AZ",
    "sg:tags":[
        "consultant",
        "business"
    ],
    "wof:name":"Gender Corp",
    "wof:placetype":"venue"
},
  "geometry": {"coordinates":[-111.895492,33.556852],"type":"Point"}
}