{
  "type": "Feature",
  "properties": {
    "iso:country":"US",
    "sg:address":"1225 N 25th Ave",
    "sg:city":"Phoenix",
    "sg:classifiers":[
        {
            "category":"Government",
            "subcategory":"Office",
            "type":"Public Place"
        }
    ],
    "sg:phone":"+1 602 712 8851",
    "sg:postcode":"85009",
    "sg:province":"AZ",
    "sg:tags":[
        "government-united",
        "state"
    ],
    "sg:website":"http://www.arizonahighways.com",
    "wof:name":"Arizona Dept Of Transportation",
    "wof:placetype":"venue"
},
  "geometry": {"coordinates":[-112.113017,33.461464],"type":"Point"}
}