{
  "type": "Feature",
  "properties": {
    "iso:country":"US",
    "sg:address":"338 N 61st St",
    "sg:city":"Mesa",
    "sg:classifiers":[
        {
            "category":"Professional",
            "type":"Services"
        }
    ],
    "sg:phone":"+1 480 924 6754",
    "sg:postcode":"85205",
    "sg:province":"AZ",
    "wof:name":"Christiansen La",
    "wof:placetype":"venue"
},
  "geometry": {"coordinates":[-111.699892,33.422424],"type":"Point"}
}