{
  "type": "Feature",
  "properties": {
    "iso:country":"US",
    "sg:address":"2985 N Centre Ct",
    "sg:city":"Prescott Valley",
    "sg:classifiers":[
        {
            "category":"Restaurant",
            "type":"Food & Drink"
        }
    ],
    "sg:phone":"+1 928 759 9800",
    "sg:postcode":"86314",
    "sg:province":"AZ",
    "sg:website":"www.buffalowildwings.com",
    "wof:name":"Buffalo Wild Wings Grill & Bar",
    "wof:placetype":"venue"
},
  "geometry": {"coordinates":[-112.339447,34.584994],"type":"Point"}
}