{
  "type": "Feature",
  "properties": {
    "iso:country":"US",
    "sg:address":"8438 W Pinnacle Peak Rd",
    "sg:city":"Peoria",
    "sg:classifiers":[
        {
            "category":"Wholesale",
            "subcategory":"Groceries",
            "type":"Manufacturing & Wholesale Goods"
        }
    ],
    "sg:phone":"+1 623 566 6647",
    "sg:postcode":"85383",
    "sg:province":"AZ",
    "sg:tags":[
        "food",
        "product"
    ],
    "wof:name":"Dansher Inc",
    "wof:placetype":"venue"
},
  "geometry": {"coordinates":[-112.240463,33.696307],"type":"Point"}
}