{
  "type": "Feature",
  "properties": {
    "iso:country":"US",
    "sg:address":"747 E Brown Rd",
    "sg:city":"Mesa",
    "sg:classifiers":[
        {
            "category":"Retail",
            "subcategory":"Repair Shop",
            "type":"Services"
        }
    ],
    "sg:phone":"+1 602 252 0330",
    "sg:postcode":"85203",
    "sg:province":"AZ",
    "sg:tags":[
        "appliance"
    ],
    "wof:name":"Appliance Specialists Svc Co",
    "wof:placetype":"venue"
},
  "geometry": {"coordinates":[-111.814778,33.43542],"type":"Point"}
}