{
  "type": "Feature",
  "properties": {
    "iso:country":"US",
    "sg:address":"529 N Stone Ave",
    "sg:city":"Tucson",
    "sg:classifiers":[
        {
            "category":"Shopping",
            "subcategory":"Computers & Home Electronics",
            "type":"Retail Goods"
        }
    ],
    "sg:phone":"+1 520 382 3474",
    "sg:postcode":"85705",
    "sg:province":"AZ",
    "sg:tags":[
        "equipment",
        "satellite",
        "system"
    ],
    "wof:name":"Prime Home Inc",
    "wof:placetype":"venue"
},
  "geometry": {"coordinates":[-110.971815,32.22863],"type":"Point"}
}