{
  "type": "Feature",
  "properties": {
    "iso:country":"US",
    "sg:address":"1525 N Granite Reef Rd",
    "sg:city":"Scottsdale",
    "sg:classifiers":[
        {
            "category":"Education",
            "subcategory":"Vocational School",
            "type":"Public Place"
        }
    ],
    "sg:phone":"+1 480 874 2732",
    "sg:postcode":"85257",
    "sg:province":"AZ",
    "wof:name":"Arizona State Dental Assisting",
    "wof:placetype":"venue"
},
  "geometry": {"coordinates":[-111.900445,33.463542],"type":"Point"}
}