{
  "type": "Feature",
  "properties": {
    "iso:country":"US",
    "sg:address":"455 N 3rd St",
    "sg:city":"Phoenix",
    "sg:classifiers":[
        {
            "category":"Utilities",
            "subcategory":"Mobile Phone",
            "type":"Services"
        }
    ],
    "sg:phone":"+1 602 254 9808",
    "sg:postcode":"85004",
    "sg:province":"AZ",
    "sg:tags":[
        "telephone",
        "cellular"
    ],
    "sg:website":"www.cingularwireless.com",
    "wof:name":"Cingular Wireless",
    "wof:placetype":"venue"
},
  "geometry": {"coordinates":[-112.069895,33.452967],"type":"Point"}
}