{
  "type": "Feature",
  "properties": {
    "iso:country":"US",
    "sg:address":"2855 S 4th Ave",
    "sg:city":"Yuma",
    "sg:classifiers":[
        {
            "category":"Professional",
            "type":"Services"
        }
    ],
    "sg:phone":"+1 928 314 0215",
    "sg:postcode":"85364",
    "sg:province":"AZ",
    "wof:name":"MI Playita",
    "wof:placetype":"venue"
},
  "geometry": {"coordinates":[-114.624483,32.676413],"type":"Point"}
}