{
  "type": "Feature",
  "properties": {
    "addr:full":"1342 W Thomas Rd Phoenix AZ 85013",
    "addr:housenumber":"1342",
    "addr:postcode":"85013",
    "addr:street":"W Thomas Rd",
    "iso:country":"US",
    "sg:address":"1342 W Thomas Rd",
    "sg:city":"Phoenix",
    "sg:classifiers":[
        {
            "category":"Food & Beverages",
            "subcategory":"Groceries & Convenience Stores",
            "type":"Retail Goods"
        }
    ],
    "sg:phone":"+1 602 279 6675",
    "sg:postcode":"85013",
    "sg:province":"AZ",
    "sg:website":"http://www.circlek.com",
    "wof:name":"Circle K",
    "wof:placetype":"venue"
},
  "geometry": {"coordinates":[-112.090526,33.480481],"type":"Point"}
}