{
  "type": "Feature",
  "properties": {
    "addr:full":"6033 W Bethany Home Rd Glendale AZ 85301",
    "addr:housenumber":"6033",
    "addr:postcode":"85301",
    "addr:street":"W Bethany Home Rd",
    "iso:country":"US",
    "sg:address":"6033 W Bethany Home Rd",
    "sg:city":"Glendale",
    "sg:classifiers":[
        {
            "category":"Real Estate",
            "subcategory":"Real Estate Operator",
            "type":"Services"
        }
    ],
    "sg:phone":"+1 623 937 4693",
    "sg:postcode":"85301",
    "sg:province":"AZ",
    "sg:tags":[
        "building",
        "apartment"
    ],
    "wof:name":"Ridgeway Village",
    "wof:placetype":"venue"
},
  "geometry": {"coordinates":[-112.190307,33.523945],"type":"Point"}
}