{
  "type": "Feature",
  "properties": {
    "iso:country":"US",
    "sg:address":"332 London Bridge Rd",
    "sg:city":"Lake Havasu City",
    "sg:classifiers":[
        {
            "category":"Home & Garden",
            "subcategory":"Carpets & Floor Coverings",
            "type":"Retail Goods"
        }
    ],
    "sg:phone":"+1 928 505 9735",
    "sg:postcode":"86403",
    "sg:province":"AZ",
    "sg:tags":[
        "dealer",
        "rug"
    ],
    "wof:name":"3 Boyz Custom Floor Covering",
    "wof:placetype":"venue"
},
  "geometry": {"coordinates":[-114.350569,34.478727],"type":"Point"}
}