{
  "type": "Feature",
  "properties": {
    "addr:full":"1331 Baseline Rd Bullhead City AZ 86442",
    "addr:housenumber":"1331",
    "addr:postcode":"86442",
    "addr:street":"Baseline Rd",
    "iso:country":"US",
    "sg:address":"1331 Baseline Rd",
    "sg:city":"Bullhead City",
    "sg:classifiers":[
        {
            "category":"Bars & Pubs",
            "type":"Food & Drink"
        }
    ],
    "sg:phone":"+1 928 704 2277",
    "sg:postcode":"86442",
    "sg:province":"AZ",
    "wof:name":"Bars & Cars",
    "wof:placetype":"venue"
},
  "geometry": {"coordinates":[-114.60195299999999,35.116445],"type":"Point"}
}