{
  "type": "Feature",
  "properties": {
    "iso:country":"US",
    "sg:address":"5225 Hwy 95",
    "sg:city":"Fort Mohave",
    "sg:classifiers":[
        {
            "category":"Shopping",
            "subcategory":"Books",
            "type":"Retail Goods"
        }
    ],
    "sg:phone":"+1 928 788 1991",
    "sg:postcode":"86426",
    "sg:province":"AZ",
    "sg:tags":[
        "dealer"
    ],
    "wof:name":"Mustard Seed",
    "wof:placetype":"venue"
},
  "geometry": {"coordinates":[-114.598142,35.004574],"type":"Point"}
}