{
  "type": "Feature",
  "properties": {
    "iso:country":"US",
    "sg:address":"1019 W Pecos Ave",
    "sg:city":"Mesa",
    "sg:classifiers":[
        {
            "category":"Manufacturing",
            "subcategory":"Retail Goods",
            "type":"Manufacturing & Wholesale Goods"
        }
    ],
    "sg:phone":"+1 480 838 2871",
    "sg:postcode":"85210",
    "sg:province":"AZ",
    "sg:tags":[
        "product",
        "mfg"
    ],
    "wof:name":"Ventriloquist Dummy Co",
    "wof:placetype":"venue"
},
  "geometry": {"coordinates":[-111.858151,33.360124],"type":"Point"}
}