{
  "type": "Feature",
  "properties": {
    "iso:country":"US",
    "sg:address":"1140 W Skyview Dr",
    "sg:city":"Prescott",
    "sg:classifiers":[
        {
            "category":"Professional",
            "type":"Services"
        }
    ],
    "sg:phone":"+1 928 445 5097",
    "sg:postcode":"86303",
    "sg:province":"AZ",
    "wof:name":"Jean Clinch",
    "wof:placetype":"venue"
},
  "geometry": {"coordinates":[-112.49099200000001,34.521986],"type":"Point"}
}