{
  "type": "Feature",
  "properties": {
    "iso:country":"US",
    "sg:address":"1515 W Deer Valley Rd",
    "sg:city":"Phoenix",
    "sg:classifiers":[
        {
            "category":"Autos & Motor Vehicles",
            "subcategory":"Automobile Sales",
            "type":"Retail Goods"
        },
        {
            "category":"Autos & Motor Vehicles",
            "subcategory":"Auto Supplies",
            "type":"Retail Goods"
        }
    ],
    "sg:phone":"+1 623 582 2829",
    "sg:postcode":"85027",
    "sg:province":"AZ",
    "sg:tags":[
        "parts",
        "truck"
    ],
    "wof:name":"Inyati Sprayed In Truck Bdlnrs",
    "wof:placetype":"venue"
},
  "geometry": {"coordinates":[-112.092558,33.683767],"type":"Point"}
}