{
  "type": "Feature",
  "properties": {
    "iso:country":"US",
    "sg:address":"9346 W Pontiac Dr",
    "sg:city":"Peoria",
    "sg:classifiers":[
        {
            "category":"Personal",
            "subcategory":"Beauty Salon",
            "type":"Services"
        },
        {
            "category":"Personal",
            "subcategory":"Skin Care",
            "type":"Services"
        }
    ],
    "sg:phone":"+1 602 703 8623",
    "sg:postcode":"85382",
    "sg:province":"AZ",
    "sg:tags":[
        "cosmetologist",
        "cosmetic"
    ],
    "wof:name":"Toad Ally Creative",
    "wof:placetype":"venue"
},
  "geometry": {"coordinates":[-112.259979,33.667816],"type":"Point"}
}