{
  "type": "Feature",
  "properties": {
    "addr:full":"9209 E Wrightstown Rd Tucson AZ 85715",
    "addr:housenumber":"9209",
    "addr:postcode":"85715",
    "addr:street":"E Wrightstown Rd",
    "iso:country":"US",
    "sg:address":"9209 E Wrightstown Rd",
    "sg:city":"Tucson",
    "sg:classifiers":[
        {
            "category":"Education",
            "subcategory":"School",
            "type":"Public Place"
        }
    ],
    "sg:phone":"+1 520 886 6076",
    "sg:postcode":"85715",
    "sg:province":"AZ",
    "wof:name":"Academy Of Tucson",
    "wof:placetype":"venue"
},
  "geometry": {"coordinates":[-110.797363,32.242755],"type":"Point"}
}