{
  "type": "Feature",
  "properties": {
    "iso:country":"US",
    "sg:address":"4827 E Fairfield St",
    "sg:city":"Mesa",
    "sg:classifiers":[
        {
            "category":"Autos & Motor Vehicles",
            "subcategory":"Automobile Sales",
            "type":"Retail Goods"
        }
    ],
    "sg:phone":"+1 602 743 5768",
    "sg:postcode":"85205",
    "sg:province":"AZ",
    "sg:tags":[
        "new",
        "car"
    ],
    "wof:name":"Utah Honda Dealers",
    "wof:placetype":"venue"
},
  "geometry": {"coordinates":[-111.726131,33.434769],"type":"Point"}
}