{
  "type": "Feature",
  "properties": {
    "iso:country":"US",
    "sg:address":"4805 E Speedway Blvd",
    "sg:city":"Tucson",
    "sg:classifiers":[
        {
            "category":"Home & Garden",
            "subcategory":"Building Materials",
            "type":"Retail Goods"
        }
    ],
    "sg:phone":"+1 520 323 7105",
    "sg:postcode":"85712",
    "sg:province":"AZ",
    "sg:tags":[
        "covering"
    ],
    "wof:name":"Sherwin-Williams",
    "wof:placetype":"venue"
},
  "geometry": {"coordinates":[-110.88840999999999,32.236289],"type":"Point"}
}