{
  "type": "Feature",
  "properties": {
    "iso:country":"US",
    "sg:address":"730 W Chapala Dr",
    "sg:city":"Tucson",
    "sg:classifiers":[
        {
            "category":"Freight",
            "type":"Transportation"
        }
    ],
    "sg:phone":"+1 520 603 2264",
    "sg:postcode":"85704",
    "sg:province":"AZ",
    "sg:tags":[
        "mobile",
        "home"
    ],
    "wof:name":"K & M Installers Inc",
    "wof:placetype":"venue"
},
  "geometry": {"coordinates":[-110.981937,32.344671],"type":"Point"}
}