{
  "type": "Feature",
  "properties": {
    "addr:full":"4815 W McNeil Dr Laveen AZ 85339",
    "addr:housenumber":"4815",
    "addr:postcode":"85339",
    "addr:street":"W Mcneil Dr",
    "iso:country":"US",
    "sg:address":"4815 W McNeil Dr",
    "sg:city":"Laveen",
    "sg:classifiers":[
        {
            "category":"Wholesale",
            "subcategory":"Machinery & Supplies",
            "type":"Manufacturing & Wholesale Goods"
        }
    ],
    "sg:phone":"+1 602 237 3956",
    "sg:postcode":"85339",
    "sg:province":"AZ",
    "sg:tags":[
        "broker"
    ],
    "wof:name":"Koudelka Sales Inc",
    "wof:placetype":"venue"
},
  "geometry": {"coordinates":[-112.162829,33.357473],"type":"Point"}
}