{
  "type": "Feature",
  "properties": {
    "addr:full":"7611 S 29th Ave Laveen AZ 85339",
    "addr:housenumber":"7611",
    "addr:postcode":"85339",
    "addr:street":"S 29Th Ave",
    "iso:country":"US",
    "sg:address":"7611 S 29th Ave",
    "sg:city":"Laveen",
    "sg:classifiers":[
        {
            "category":"Recreation",
            "type":"Entertainment"
        }
    ],
    "sg:phone":"+1 602 237 4685",
    "sg:postcode":"85339",
    "sg:province":"AZ",
    "sg:tags":[
        "hall",
        "auditorium"
    ],
    "sg:website":"www.coronaranch.com",
    "wof:name":"Corona Promotions",
    "wof:placetype":"venue"
},
  "geometry": {"coordinates":[-112.121871,33.370392],"type":"Point"}
}