{
  "type": "Feature",
  "properties": {
    "iso:country":"US",
    "sg:address":"2042 W Spring St",
    "sg:city":"Tucson",
    "sg:classifiers":[
        {
            "category":"Shopping",
            "subcategory":"Gifts & Souvenirs",
            "type":"Retail Goods"
        }
    ],
    "sg:phone":"+1 520 405 3533",
    "sg:postcode":"85745",
    "sg:province":"AZ",
    "sg:tags":[
        "sales"
    ],
    "wof:name":"Citrus-9 Business Group Inc",
    "wof:placetype":"venue"
},
  "geometry": {"coordinates":[-111.011403,32.251633],"type":"Point"}
}