{
  "type": "Feature",
  "properties": {
    "addr:full":"6741 W Latham St Phoenix AZ 85043",
    "addr:housenumber":"6741",
    "addr:postcode":"85043",
    "addr:street":"W Latham St",
    "iso:country":"US",
    "sg:address":"6741 W Latham St",
    "sg:city":"Phoenix",
    "sg:classifiers":[
        {
            "category":"Shopping",
            "subcategory":"Computers & Home Electronics",
            "type":"Retail Goods"
        }
    ],
    "sg:phone":"+1 623 907 1000",
    "sg:postcode":"85043",
    "sg:province":"AZ",
    "sg:tags":[
        "band",
        "stereo",
        "radio",
        "system",
        "automobile"
    ],
    "wof:name":"Kustom Cb & Stereo",
    "wof:placetype":"venue"
},
  "geometry": {"coordinates":[-112.206537,33.46011],"type":"Point"}
}