{
  "type": "Feature",
  "properties": {
    "iso:country":"US",
    "sg:address":"16258 E Balsam Dr",
    "sg:city":"Fountain Hills",
    "sg:classifiers":[
        {
            "category":"Real Estate",
            "subcategory":"Real Estate Operator",
            "type":"Services"
        }
    ],
    "sg:phone":"+1 480 816 3419",
    "sg:postcode":"85268",
    "sg:province":"AZ",
    "sg:tags":[
        "property",
        "lease"
    ],
    "wof:name":"Thomas & Kim Mergen LLC",
    "wof:placetype":"venue"
},
  "geometry": {"coordinates":[-111.729066,33.620915],"type":"Point"}
}