{
  "type": "Feature",
  "properties": {
    "iso:country":"US",
    "sg:address":"14928 N 103rd Way",
    "sg:city":"Scottsdale",
    "sg:classifiers":[
        {
            "category":"Professional",
            "subcategory":"Business Services",
            "type":"Services"
        }
    ],
    "sg:phone":"+1 480 563 2933",
    "sg:postcode":"85255",
    "sg:province":"AZ",
    "wof:name":"Business Web Solutions",
    "wof:placetype":"venue"
},
  "geometry": {"coordinates":[-111.856844,33.621576],"type":"Point"}
}