{
  "type": "Feature",
  "properties": {
    "addr:full":"14822 N Flamenco Dr Phoenix AZ 85053",
    "addr:housenumber":"14822",
    "addr:postcode":"85053",
    "addr:street":"N Flamenco Dr",
    "iso:country":"US",
    "sg:address":"14822 N Flamenco Dr",
    "sg:city":"Phoenix",
    "sg:classifiers":[
        {
            "category":"Retail",
            "subcategory":"Animal Services",
            "type":"Services"
        }
    ],
    "sg:phone":"+1 623 930 1730",
    "sg:postcode":"85053",
    "sg:province":"AZ",
    "wof:name":"Gold Dust Mobile Pet Grooming",
    "wof:placetype":"venue"
},
  "geometry": {"coordinates":[-112.12470500000001,33.621008],"type":"Point"}
}