{
  "type": "Feature",
  "properties": {
    "iso:country":"US",
    "sg:address":"15635 N 32nd St",
    "sg:city":"Phoenix",
    "sg:classifiers":[
        {
            "category":"Retail",
            "subcategory":"Storage",
            "type":"Services"
        }
    ],
    "sg:phone":"+1 520 955 6068",
    "sg:postcode":"85032",
    "sg:province":"AZ",
    "sg:tags":[
        "automobile",
        "self",
        "commercial",
        "household"
    ],
    "sg:website":"http://phoenix.citysearch.com/profile/external/1650788/phoenix_az/guardian_self_storage.html?publisher=yellowpages&reference_id=1&placement=ypwebsitemip",
    "wof:name":"Guardian Self Storage",
    "wof:placetype":"venue"
},
  "geometry": {"coordinates":[-112.013391,33.629476],"type":"Point"}
}