{
  "type": "Feature",
  "properties": {
    "iso:country":"US",
    "sg:address":"1808 N 32nd St",
    "sg:city":"Phoenix",
    "sg:classifiers":[
        {
            "category":"Real Estate",
            "subcategory":"Real Estate Operator",
            "type":"Services"
        }
    ],
    "sg:phone":"+1 602 273 7758",
    "sg:postcode":"85008",
    "sg:province":"AZ",
    "sg:tags":[
        "management",
        "condominium"
    ],
    "wof:name":"Montego Court Condo Council",
    "wof:placetype":"venue"
},
  "geometry": {"coordinates":[-112.01290899999999,33.467982],"type":"Point"}
}