{
  "type": "Feature",
  "properties": {
    "iso:country":"US",
    "sg:address":"3080 E Ina Rd",
    "sg:city":"Tucson",
    "sg:classifiers":[
        {
            "category":"Wholesale",
            "subcategory":"Office Equipment",
            "type":"Manufacturing & Wholesale Goods"
        },
        {
            "category":"Shopping",
            "type":"Retail Goods"
        }
    ],
    "sg:phone":"+1 520 529 4100",
    "sg:postcode":"85718",
    "sg:province":"AZ",
    "sg:tags":[
        "bank",
        "supply"
    ],
    "wof:name":"First Choice Bank Systems Inc",
    "wof:placetype":"venue"
},
  "geometry": {"coordinates":[-110.931365,32.334657],"type":"Point"}
}