{
  "type": "Feature",
  "properties": {
    "iso:country":"US",
    "sg:address":"3632 W Pinnacle Peak Rd",
    "sg:city":"Glendale",
    "sg:classifiers":[
        {
            "category":"Insurance",
            "subcategory":"Insurance Agent",
            "type":"Services"
        }
    ],
    "sg:phone":"+1 623 587 5544",
    "sg:postcode":"85310",
    "sg:province":"AZ",
    "wof:name":"Farmers Insurance Group",
    "wof:placetype":"venue"
},
  "geometry": {"coordinates":[-112.139588,33.698389],"type":"Point"}
}