{
  "type": "Feature",
  "properties": {
    "iso:country":"US",
    "sg:address":"14805 N 100th Pl",
    "sg:city":"Scottsdale",
    "sg:classifiers":[
        {
            "category":"Building & Trades",
            "subcategory":"Construction",
            "type":"Services"
        }
    ],
    "sg:phone":"+1 480 767 0154",
    "sg:postcode":"85260",
    "sg:province":"AZ",
    "sg:tags":[
        "house"
    ],
    "wof:name":"Arrowhead Remodeling & Cnstr",
    "wof:placetype":"venue"
},
  "geometry": {"coordinates":[-111.865939,33.619284],"type":"Point"}
}