{
  "type": "Feature",
  "properties": {
    "iso:country":"US",
    "sg:address":"4637 E 25th St",
    "sg:city":"Tucson",
    "sg:classifiers":[
        {
            "category":"Professional",
            "subcategory":"Business Services",
            "type":"Services"
        }
    ],
    "sg:phone":"+1 520 861 7470",
    "sg:postcode":"85711",
    "sg:province":"AZ",
    "wof:name":"B & C Multibusiness",
    "wof:placetype":"venue"
},
  "geometry": {"coordinates":[-110.894937,32.203729],"type":"Point"}
}