{
  "type": "Feature",
  "properties": {
    "iso:country":"US",
    "sg:address":"525 W Brown Rd",
    "sg:city":"Mesa",
    "sg:classifiers":[
        {
            "category":"Health Services",
            "subcategory":"Nursing And Care Facility",
            "type":"Services"
        }
    ],
    "sg:phone":"+1 480 461 2920",
    "sg:postcode":"85201",
    "sg:province":"AZ",
    "sg:tags":[
        "home",
        "convalescent"
    ],
    "wof:name":"Banner Health Arizona",
    "wof:placetype":"venue"
},
  "geometry": {"coordinates":[-111.841905,33.435067],"type":"Point"}
}