{
  "type": "Feature",
  "properties": {
    "iso:country":"US",
    "sg:address":"5047 E Cheery Lynn Rd",
    "sg:city":"Phoenix",
    "sg:classifiers":[
        {
            "category":"Recreation",
            "type":"Entertainment"
        }
    ],
    "sg:phone":"+1 602 840 1166",
    "sg:postcode":"85018",
    "sg:province":"AZ",
    "sg:tags":[
        "instruction",
        "yoga"
    ],
    "wof:name":"Carol Mitchell's Studio-Yoga",
    "wof:placetype":"venue"
},
  "geometry": {"coordinates":[-111.972268,33.484412],"type":"Point"}
}