{
  "type": "Feature",
  "properties": {
    "iso:country":"US",
    "sg:address":"7440 N Oracle Rd Ste 7",
    "sg:city":"Tucson",
    "sg:classifiers":[
        {
            "category":"Professional",
            "subcategory":"Lawyer & Legal Services",
            "type":"Services"
        }
    ],
    "sg:phone":"+1 520 623 1461",
    "sg:postcode":"85704",
    "sg:province":"AZ",
    "sg:tags":[
        "attorney",
        "criminal",
        "family",
        "personal",
        "divorce",
        "practice",
        "injury",
        "insurance",
        "law"
    ],
    "wof:name":"Gee, Lawrence Y. - Benavidez Law Group, P.C.",
    "wof:placetype":"venue"
},
  "geometry": {"coordinates":[-110.976958,32.341549],"type":"Point"}
}