{
  "type": "Feature",
  "properties": {
    "iso:country":"US",
    "sg:address":"7025 E Greenway Pkwy",
    "sg:city":"Scottsdale",
    "sg:classifiers":[
        {
            "category":"Banks & Credit Unions",
            "subcategory":"Bank",
            "type":"Services"
        }
    ],
    "sg:phone":"+1 480 443 3102",
    "sg:postcode":"85254",
    "sg:province":"AZ",
    "wof:name":"First Indiana Bank",
    "wof:placetype":"venue"
},
  "geometry": {"coordinates":[-111.932344,33.622747],"type":"Point"}
}