{
  "type": "Feature",
  "properties": {
    "iso:country":"US",
    "sg:address":"1070 E Ray Rd",
    "sg:city":"Chandler",
    "sg:classifiers":[
        {
            "category":"Real Estate",
            "subcategory":"Real Estate Agent",
            "type":"Services"
        }
    ],
    "sg:phone":"+1 480 895 2121",
    "sg:postcode":"85225",
    "sg:province":"AZ",
    "sg:website":"www.century21metroalliance.com",
    "wof:name":"Metro Co",
    "wof:placetype":"venue"
},
  "geometry": {"coordinates":[-111.821593,33.320856],"type":"Point"}
}