{
  "type": "Feature",
  "properties": {
    "addr:full":"1070 E Ray Rd Chandler AZ 85225",
    "addr:housenumber":"1070",
    "addr:postcode":"85225",
    "addr:street":"E Ray Rd",
    "iso:country":"US",
    "sg:address":"1070 E Ray Rd",
    "sg:city":"Chandler",
    "sg:classifiers":[
        {
            "category":"Real Estate",
            "subcategory":"Real Estate Agent",
            "type":"Services"
        }
    ],
    "sg:phone":"+1 480 895 2121",
    "sg:postcode":"85225",
    "sg:province":"AZ",
    "sg:website":"www.century21metroalliance.com",
    "wof:name":"Metro Co",
    "wof:placetype":"venue"
},
  "geometry": {"coordinates":[-111.82159299999999,33.320856],"type":"Point"}
}