{
  "type": "Feature",
  "properties": {
    "iso:country":"US",
    "sg:address":"2350 N 1st Ave",
    "sg:city":"Tucson",
    "sg:classifiers":[
        {
            "category":"Autos & Motor Vehicles",
            "subcategory":"Fuel & Gas Station",
            "type":"Retail Goods"
        }
    ],
    "sg:phone":"+1 520 623 8322",
    "sg:postcode":"85719",
    "sg:province":"AZ",
    "sg:tags":[
        "station",
        "gasoline"
    ],
    "wof:name":"Texaco",
    "wof:placetype":"venue"
},
  "geometry": {"coordinates":[-110.960888,32.250187],"type":"Point"}
}