{
  "type": "Feature",
  "properties": {
    "addr:full":"7720 E Gelding Dr Scottsdale AZ 85260",
    "addr:housenumber":"7720",
    "addr:postcode":"85260",
    "addr:street":"E Gelding Dr",
    "iso:country":"US",
    "sg:address":"7720 E Gelding Dr",
    "sg:city":"Scottsdale",
    "sg:classifiers":[
        {
            "category":"Real Estate",
            "subcategory":"Real Estate Agent",
            "type":"Services"
        },
        {
            "category":"Home & Garden",
            "subcategory":"Household Appliances",
            "type":"Retail Goods"
        }
    ],
    "sg:phone":"+1 480 556 9890",
    "sg:postcode":"85260",
    "sg:province":"AZ",
    "sg:tags":[
        "house",
        "cleaners",
        "construct",
        "vacuum"
    ],
    "wof:name":"Custom Home Store",
    "wof:placetype":"venue"
},
  "geometry": {"coordinates":[-111.912668,33.615308],"type":"Point"}
}