{
  "type": "Feature",
  "properties": {
    "iso:country":"US",
    "sg:address":"4660 N Valley Park Ave",
    "sg:city":"Tucson",
    "sg:classifiers":[
        {
            "category":"Building & Trades",
            "subcategory":"Construction",
            "type":"Services"
        }
    ],
    "sg:phone":"+1 520 292 1125",
    "sg:postcode":"85705",
    "sg:province":"AZ",
    "sg:tags":[
        "paving",
        "contractor"
    ],
    "sg:website":"www.tucsonasphalt.com",
    "wof:name":"Tucson Asphalt",
    "wof:placetype":"venue"
},
  "geometry": {"coordinates":[-111.02167,32.292785],"type":"Point"}
}