{
  "type": "Feature",
  "properties": {
    "iso:country":"US",
    "sg:address":"7206 N 55th Ave",
    "sg:city":"Glendale",
    "sg:classifiers":[
        {
            "category":"Banks & Credit Unions",
            "subcategory":"Investment Brokerage",
            "type":"Services"
        }
    ],
    "sg:phone":"+1 623 463 8424",
    "sg:postcode":"85301",
    "sg:province":"AZ",
    "sg:tags":[
        "advisory",
        "financial"
    ],
    "wof:name":"Financial Bases",
    "wof:placetype":"venue"
},
  "geometry": {"coordinates":[-112.177464,33.542899],"type":"Point"}
}