{
  "type": "Feature",
  "properties": {
    "addr:full":"10455 E Pinnacle Peak Rd Scottsdale AZ 85255",
    "addr:housenumber":"10455",
    "addr:postcode":"85255",
    "addr:street":"E Pinnacle Peak Rd",
    "iso:country":"US",
    "sg:address":"10455 E Pinnacle Peak Rd",
    "sg:city":"Scottsdale",
    "sg:classifiers":[
        {
            "category":"Restaurant",
            "type":"Food & Drink"
        }
    ],
    "sg:menulink":"http://www.allmenus.com/az/phoenix/4050-sassi/menu/",
    "sg:phone":"+1 480 502 3335",
    "sg:postcode":"85255",
    "sg:province":"AZ",
    "sg:tags":[
        "italian"
    ],
    "wof:name":"Sassi",
    "wof:placetype":"venue"
},
  "geometry": {"coordinates":[-111.858141,33.700519],"type":"Point"}
}