{
  "type": "Feature",
  "properties": {
    "iso:country":"US",
    "sg:address":"3325 E Pinchot Ave",
    "sg:city":"Phoenix",
    "sg:classifiers":[
        {
            "category":"Real Estate",
            "subcategory":"Real Estate Operator",
            "type":"Services"
        }
    ],
    "sg:phone":"+1 602 508 8032",
    "sg:postcode":"85018",
    "sg:province":"AZ",
    "sg:tags":[
        "apartment"
    ],
    "wof:name":"Pecan Tree",
    "wof:placetype":"venue"
},
  "geometry": {"coordinates":[-112.008954,33.482253],"type":"Point"}
}