{
  "type": "Feature",
  "properties": {
    "iso:country":"US",
    "sg:address":"51 Bell Rock Plz Ste B",
    "sg:city":"Sedona",
    "sg:classifiers":[
        {
            "category":"Personal",
            "subcategory":"Beauty Salon",
            "type":"Services"
        }
    ],
    "sg:phone":"+1 928 284 1703",
    "sg:postcode":"86351",
    "sg:province":"AZ",
    "wof:name":"Sedona Online Radio",
    "wof:placetype":"venue"
},
  "geometry": {"coordinates":[-111.76414200000001,34.787895],"type":"Point"}
}