{
  "type": "Feature",
  "properties": {
    "addr:full":"4051 S Longfellow Ave Tucson AZ 85714",
    "addr:housenumber":"4051",
    "addr:postcode":"85714",
    "addr:street":"S Longfellow Ave",
    "iso:country":"US",
    "sg:address":"4051 S Longfellow Ave",
    "sg:city":"Tucson",
    "sg:classifiers":[
        {
            "category":"Freight",
            "type":"Transportation"
        }
    ],
    "sg:phone":"+1 520 622 6461",
    "sg:postcode":"85714",
    "sg:province":"AZ",
    "sg:tags":[
        "mover"
    ],
    "sg:website":"www.ralphsnorthamerican.com",
    "wof:name":"Ralph's Transfer",
    "wof:placetype":"venue"
},
  "geometry": {"coordinates":[-110.90603400000001,32.173863],"type":"Point"}
}