{
  "type": "Feature",
  "properties": {
    "addr:full":"625 W Mckellips Rd # 369 Mesa AZ 85201",
    "addr:housenumber":"625",
    "addr:postcode":"85201",
    "addr:street":"W Mckellips Rd # 369",
    "iso:country":"US",
    "sg:address":"625 W Mckellips Rd # 369",
    "sg:city":"Mesa",
    "sg:classifiers":[
        {
            "category":"Home & Garden",
            "subcategory":"Carpets & Floor Coverings",
            "type":"Retail Goods"
        }
    ],
    "sg:phone":"+1 602 796 6482",
    "sg:postcode":"85201",
    "sg:province":"AZ",
    "sg:tags":[
        "installation"
    ],
    "wof:name":"Aguirre Carpet Installer",
    "wof:placetype":"venue"
},
  "geometry": {"coordinates":[-111.84414200000001,33.451382],"type":"Point"}
}