{
  "type": "Feature",
  "properties": {
    "addr:full":"14482 W Edgemont Ave Goodyear AZ 85395",
    "addr:housenumber":"14482",
    "addr:postcode":"85395",
    "addr:street":"W Edgemont Ave",
    "iso:country":"US",
    "sg:address":"14482 W Edgemont Ave",
    "sg:city":"Goodyear",
    "sg:classifiers":[
        {
            "category":"Professional",
            "subcategory":"Detective & Security Services",
            "type":"Services"
        }
    ],
    "sg:phone":"+1 623 266 2445",
    "sg:postcode":"85395",
    "sg:province":"AZ",
    "sg:tags":[
        "information",
        "bureau"
    ],
    "wof:name":"Service In E&I Cooperative",
    "wof:placetype":"venue"
},
  "geometry": {"coordinates":[-112.369664,33.477929],"type":"Point"}
}