{
  "type": "Feature",
  "properties": {
    "iso:country":"US",
    "sg:address":"5 E Southern Ave",
    "sg:city":"Tempe",
    "sg:classifiers":[
        {
            "category":"Real Estate",
            "subcategory":"Real Estate Operator",
            "type":"Services"
        }
    ],
    "sg:phone":"+1 480 507 8200",
    "sg:postcode":"85282",
    "sg:province":"AZ",
    "sg:tags":[
        "mall",
        "shopping",
        "center"
    ],
    "wof:name":"E C Valley Fair",
    "wof:placetype":"venue"
},
  "geometry": {"coordinates":[-111.934957,33.392841],"type":"Point"}
}