{
  "type": "Feature",
  "properties": {
    "iso:country":"US",
    "sg:address":"329 W Lone Cactus Dr Ste 4",
    "sg:city":"Phoenix",
    "sg:classifiers":[
        {
            "category":"Building & Trades",
            "subcategory":"Plumbing",
            "type":"Services"
        },
        {
            "category":"Building & Trades",
            "subcategory":"Cleaning & Sanitation",
            "type":"Services"
        },
        {
            "category":"Building & Trades",
            "subcategory":"Construction",
            "type":"Services"
        }
    ],
    "sg:phone":"+1 623 434 7644",
    "sg:postcode":"85027",
    "sg:province":"AZ",
    "sg:tags":[
        "cleaner",
        "plumber",
        "industrial",
        "repairer",
        "heating",
        "specialty",
        "sewer",
        "contractors-commercial",
        "contractor",
        "plumbing-drain"
    ],
    "wof:name":"Turbo Rooter Plumbing",
    "wof:placetype":"venue"
},
  "geometry": {"coordinates":[-112.079727,33.680831],"type":"Point"}
}