{
  "type": "Feature",
  "properties": {
    "iso:country":"US",
    "sg:address":"1235 S Akimel Dr Ste 5063",
    "sg:city":"Chandler",
    "sg:classifiers":[
        {
            "category":"Home & Garden",
            "subcategory":"Hardware",
            "type":"Retail Goods"
        }
    ],
    "sg:phone":"+1 520 796 5193",
    "sg:postcode":"85226",
    "sg:province":"AZ",
    "sg:tags":[
        "closet",
        "accessory"
    ],
    "wof:name":"Classy Closets Etc. Inc.",
    "wof:placetype":"venue"
},
  "geometry": {"coordinates":[-111.968881,33.288078],"type":"Point"}
}