{
  "type": "Feature",
  "properties": {
    "addr:full":"6040 E Brown Rd Mesa AZ 85205",
    "addr:housenumber":"6040",
    "addr:postcode":"85205",
    "addr:street":"E Brown Rd",
    "iso:country":"US",
    "sg:address":"6040 E Brown Rd",
    "sg:city":"Mesa",
    "sg:classifiers":[
        {
            "category":"Sports & Exercise",
            "subcategory":"Gym",
            "type":"Entertainment"
        }
    ],
    "sg:phone":"+1 480 807 5080",
    "sg:postcode":"85205",
    "sg:province":"AZ",
    "sg:tags":[
        "club",
        "health",
        "studio",
        "gymnasium"
    ],
    "wof:name":"Fitness Works",
    "wof:placetype":"venue"
},
  "geometry": {"coordinates":[-111.69926599999999,33.437449],"type":"Point"}
}