{
  "type": "Feature",
  "properties": {
    "iso:country":"US",
    "sg:address":"3210 W Bell Rd",
    "sg:city":"Phoenix",
    "sg:classifiers":[
        {
            "category":"Restaurant",
            "type":"Food & Drink"
        }
    ],
    "sg:phone":"+1 602 993 5887",
    "sg:postcode":"85053",
    "sg:province":"AZ",
    "sg:tags":[
        "eating"
    ],
    "wof:name":"Subway",
    "wof:placetype":"venue"
},
  "geometry": {"coordinates":[-112.12797999999999,33.639779],"type":"Point"}
}