{
  "type": "Feature",
  "properties": {
    "addr:full":"19426 N 13th Ave Phoenix AZ 85027",
    "addr:housenumber":"19426",
    "addr:postcode":"85027",
    "addr:street":"N 13Th Ave",
    "iso:country":"US",
    "sg:address":"19426 N 13th Ave",
    "sg:city":"Phoenix",
    "sg:classifiers":[
        {
            "category":"Professional",
            "subcategory":"Computer Services",
            "type":"Services"
        }
    ],
    "sg:phone":"+1 623 476 7908",
    "sg:postcode":"85027",
    "sg:province":"AZ",
    "sg:tags":[
        "technical",
        "assistance",
        "support"
    ],
    "wof:name":"Springboard Consulting",
    "wof:placetype":"venue"
},
  "geometry": {"coordinates":[-112.08716800000001,33.662925],"type":"Point"}
}