{
  "type": "Feature",
  "properties": {
    "addr:full":"3419 S Ave 41 E Roll AZ 85347",
    "addr:housenumber":"3419;41 e",
    "addr:postcode":"85347",
    "addr:street":"S Ave;Roll",
    "iso:country":"US",
    "sg:address":"3419 S Ave 41 E",
    "sg:city":"Roll",
    "sg:classifiers":[
        {
            "category":"Building & Trades",
            "subcategory":"Construction",
            "type":"Services"
        }
    ],
    "sg:phone":"+1 928 785 4253",
    "sg:postcode":"85347",
    "sg:province":"AZ",
    "sg:tags":[
        "earth",
        "moving",
        "contractor"
    ],
    "wof:name":"Naquin Precision Earthmoving",
    "wof:placetype":"venue"
},
  "geometry": {"coordinates":[-113.936357,32.776619],"type":"Point"}
}