{
  "type": "Feature",
  "properties": {
    "iso:country":"US",
    "sg:address":"13190 Cam la Cebadilla",
    "sg:city":"Tucson",
    "sg:classifiers":[
        {
            "category":"Banks & Credit Unions",
            "subcategory":"Investment Brokerage",
            "type":"Services"
        }
    ],
    "sg:phone":"+1 520 760 9625",
    "sg:postcode":"85749",
    "sg:province":"AZ",
    "sg:tags":[
        "security"
    ],
    "wof:name":"Earl R Snodgrass Mda Professio",
    "wof:placetype":"venue"
},
  "geometry": {"coordinates":[-110.711729,32.249386],"type":"Point"}
}