{
  "type": "Feature",
  "properties": {
    "iso:country":"US",
    "sg:address":"1818 E Southern Ave",
    "sg:city":"Mesa",
    "sg:classifiers":[
        {
            "category":"Real Estate",
            "subcategory":"Real Estate Agent",
            "type":"Services"
        }
    ],
    "sg:phone":"+1 480 545 5588",
    "sg:postcode":"85204",
    "sg:province":"AZ",
    "wof:name":"Larsen & Assoc Inc",
    "wof:placetype":"venue"
},
  "geometry": {"coordinates":[-111.793212,33.393575],"type":"Point"}
}