{
  "type": "Feature",
  "properties": {
    "iso:country":"US",
    "sg:address":"2902 E Michelle Dr",
    "sg:city":"Phoenix",
    "sg:classifiers":[
        {
            "category":"Home & Garden",
            "subcategory":"Carpets & Floor Coverings",
            "type":"Retail Goods"
        }
    ],
    "sg:phone":"+1 602 971 8016",
    "sg:postcode":"85032",
    "sg:province":"AZ",
    "wof:name":"Art of Stone LLC",
    "wof:placetype":"venue"
},
  "geometry": {"coordinates":[-112.01927000000001,33.65085],"type":"Point"}
}