{
  "type": "Feature",
  "properties": {
    "iso:country":"US",
    "sg:address":"4726 S 6th Ave",
    "sg:city":"Tucson",
    "sg:classifiers":[
        {
            "category":"Autos & Motor Vehicles",
            "subcategory":"Auto Supplies",
            "type":"Retail Goods"
        }
    ],
    "sg:phone":"+1 520 294 8473",
    "sg:postcode":"85714",
    "sg:province":"AZ",
    "sg:tags":[
        "tire"
    ],
    "wof:name":"El Sinaloense Tire Shop & Svc",
    "wof:placetype":"venue"
},
  "geometry": {"coordinates":[-110.96825,32.166807],"type":"Point"}
}