{
  "type": "Feature",
  "properties": {
    "addr:full":"20830 N 25th Pl Ste 104 Phoenix AZ 85050",
    "addr:housenumber":"20830",
    "addr:postcode":"85050",
    "addr:street":"N 25Th Pl Ste 104",
    "iso:country":"US",
    "sg:address":"20830 N 25th Pl Ste 104",
    "sg:city":"Phoenix",
    "sg:classifiers":[
        {
            "category":"Manufacturing",
            "subcategory":"Metals",
            "type":"Manufacturing & Wholesale Goods"
        },
        {
            "category":"Manufacturing",
            "subcategory":"Jewelry",
            "type":"Manufacturing & Wholesale Goods"
        }
    ],
    "sg:phone":"+1 602 787 4653",
    "sg:postcode":"85050",
    "sg:province":"AZ",
    "sg:tags":[
        "platinum",
        "buyer",
        "metals-precious",
        "silver",
        "gold"
    ],
    "wof:name":"Ntr Metals",
    "wof:placetype":"venue"
},
  "geometry": {"coordinates":[-112.02801700000001,33.676125],"type":"Point"}
}