{
  "type": "Feature",
  "properties": {
    "iso:country":"US",
    "sg:address":"1605 N Bullmoose Dr",
    "sg:city":"Chandler",
    "sg:classifiers":[
        {
            "category":"Food & Beverages",
            "subcategory":"Groceries & Convenience Stores",
            "type":"Retail Goods"
        }
    ],
    "sg:phone":"+1 480 821 0397",
    "sg:postcode":"85224",
    "sg:province":"AZ",
    "wof:name":"Market Makers Agency",
    "wof:placetype":"venue"
},
  "geometry": {"coordinates":[-111.883745,33.329877],"type":"Point"}
}