{
  "type": "Feature",
  "properties": {
    "iso:country":"US",
    "sg:address":"2051 N Arizona Avenue Suite 101",
    "sg:city":"Chandler",
    "sg:classifiers":[
        {
            "category":"Social Services",
            "subcategory":"Child Care",
            "type":"Services"
        },
        {
            "category":"Education",
            "subcategory":"Preschool",
            "type":"Public Place"
        },
        {
            "category":"Education",
            "subcategory":"School",
            "type":"Public Place"
        }
    ],
    "sg:phone":"+1 480 855 4000",
    "sg:postcode":"85225",
    "sg:province":"AZ",
    "sg:tags":[
        "elementary",
        "day"
    ],
    "sg:website":"www.kidsworldaz.com",
    "wof:name":"Kids World Learning Center",
    "wof:placetype":"venue"
},
  "geometry": {"coordinates":[-111.841683,33.336396],"type":"Point"}
}