{
  "type": "Feature",
  "properties": {
    "iso:country":"US",
    "sg:address":"1015 W Prince Rd",
    "sg:city":"Tucson",
    "sg:classifiers":[
        {
            "category":"Building & Trades",
            "subcategory":"Construction",
            "type":"Services"
        }
    ],
    "sg:phone":"+1 520 292 6300",
    "sg:postcode":"85705",
    "sg:province":"AZ",
    "sg:tags":[
        "swimming",
        "designer",
        "dealer",
        "pool",
        "contractor"
    ],
    "sg:website":"www.bluehavenpools.com",
    "wof:name":"Blue Haven Pools & Spas",
    "wof:placetype":"venue"
},
  "geometry": {"coordinates":[-110.989635,32.271994],"type":"Point"}
}