{
  "type": "Feature",
  "properties": {
    "iso:country":"US",
    "sg:address":"2801 W Weldon Ave",
    "sg:city":"Phoenix",
    "sg:classifiers":[
        {
            "category":"Professional",
            "type":"Services"
        }
    ],
    "sg:phone":"+1 602 604 9140",
    "sg:postcode":"85017",
    "sg:province":"AZ",
    "sg:tags":[
        "establishment"
    ],
    "wof:name":"ADH Inc",
    "wof:placetype":"venue"
},
  "geometry": {"coordinates":[-112.123887,33.490972],"type":"Point"}
}