{
  "type": "Feature",
  "properties": {
    "addr:full":"2655 W Guadalupe Road Mesa AZ 85202",
    "addr:housenumber":"2655",
    "addr:postcode":"85202",
    "addr:street":"W Guadalupe Road",
    "iso:country":"US",
    "sg:address":"2655 W Guadalupe Road",
    "sg:city":"Mesa",
    "sg:classifiers":[
        {
            "category":"Bars & Pubs",
            "subcategory":"Dive Bar",
            "type":"Food & Drink"
        }
    ],
    "sg:phone":"+1 480 897 1006",
    "sg:postcode":"85202",
    "sg:province":"AZ",
    "wof:name":"Jupe's",
    "wof:placetype":"venue"
},
  "geometry": {"coordinates":[-111.890672,33.36386],"type":"Point"}
}