{
  "type": "Feature",
  "properties": {
    "iso:country":"US",
    "sg:address":"3026 E Minton St",
    "sg:city":"Mesa",
    "sg:phone":"+1 480 807 5217",
    "sg:postcode":"85213",
    "sg:province":"AZ",
    "wof:name":"Sam Buzuleciu",
    "wof:placetype":"venue"
},
  "geometry": {"coordinates":[-111.765398,33.462364],"type":"Point"}
}