{
  "type": "Feature",
  "properties": {
    "iso:country":"US",
    "sg:address":"3509 E Shea Blvd",
    "sg:city":"Phoenix",
    "sg:classifiers":[
        {
            "category":"Arts & Performance",
            "subcategory":"Theater",
            "type":"Entertainment"
        }
    ],
    "sg:phone":"+1 602 953 0598",
    "sg:postcode":"85028",
    "sg:province":"AZ",
    "sg:tags":[
        "bureau"
    ],
    "wof:name":"Krigsten Agency",
    "wof:placetype":"venue"
},
  "geometry": {"coordinates":[-112.004476,33.582533],"type":"Point"}
}