{
  "type": "Feature",
  "properties": {
    "addr:full":"8040 E Morgan Trl Scottsdale AZ 85258",
    "addr:housenumber":"8040",
    "addr:postcode":"85258",
    "addr:street":"E Morgan Trl",
    "iso:country":"US",
    "sg:address":"8040 E Morgan Trl",
    "sg:city":"Scottsdale",
    "sg:classifiers":[
        {
            "category":"Insurance",
            "subcategory":"Insurance Agent",
            "type":"Services"
        }
    ],
    "sg:phone":"+1 480 607 7049",
    "sg:postcode":"85258",
    "sg:province":"AZ",
    "wof:name":"Anderson Insurance Svc",
    "wof:placetype":"venue"
},
  "geometry": {"coordinates":[-111.907483,33.576811],"type":"Point"}
}