{
  "type": "Feature",
  "properties": {
    "iso:country":"US",
    "sg:address":"741 Paxton Ave",
    "sg:city":"Miami",
    "sg:classifiers":[
        {
            "category":"Personal",
            "subcategory":"Beauty Salon",
            "type":"Services"
        }
    ],
    "sg:phone":"+1 928 425 9790",
    "sg:postcode":"85539",
    "sg:province":"AZ",
    "wof:name":"A & A Beauty & Barber Salon",
    "wof:placetype":"venue"
},
  "geometry": {"coordinates":[-110.819022,33.417664],"type":"Point"}
}