{
  "type": "Feature",
  "properties": {
    "iso:country":"US",
    "sg:address":"3031 W Northern Ave Ste 281",
    "sg:city":"Phoenix",
    "sg:classifiers":[
        {
            "category":"Professional",
            "subcategory":"Management & Consulting",
            "type":"Services"
        },
        {
            "category":"Banks & Credit Unions",
            "subcategory":"Financial Services",
            "type":"Services"
        }
    ],
    "sg:phone":"+1 602 995 4024",
    "sg:postcode":"85051",
    "sg:province":"AZ",
    "sg:tags":[
        "consultant",
        "financing",
        "planning"
    ],
    "wof:name":"Ohana Corporation",
    "wof:placetype":"venue"
},
  "geometry": {"coordinates":[-112.124132,33.553074],"type":"Point"}
}