{
  "type": "Feature",
  "properties": {
    "iso:country":"US",
    "sg:address":"7843 N 13th Ave",
    "sg:city":"Phoenix",
    "sg:classifiers":[
        {
            "category":"Building & Trades",
            "subcategory":"Electrical",
            "type":"Services"
        }
    ],
    "sg:phone":"+1 602 374 6814",
    "sg:postcode":"85021",
    "sg:province":"AZ",
    "sg:tags":[
        "electrician"
    ],
    "wof:name":"Kenyon Electric",
    "wof:placetype":"venue"
},
  "geometry": {"coordinates":[-112.089072,33.552258],"type":"Point"}
}