{
  "type": "Feature",
  "properties": {
    "addr:full":"302 E Rancho Rd Payson AZ 85541",
    "addr:housenumber":"302",
    "addr:postcode":"85541",
    "addr:street":"E Rancho Rd",
    "iso:country":"US",
    "sg:address":"302 E Rancho Rd",
    "sg:city":"Payson",
    "sg:classifiers":[
        {
            "category":"Place Of Worship",
            "subcategory":"Church",
            "type":"Public Place"
        },
        {
            "category":"Place Of Worship",
            "type":"Public Place"
        }
    ],
    "sg:phone":"+1 928 472 7800",
    "sg:postcode":"85541",
    "sg:province":"AZ",
    "sg:tags":[
        "covenant",
        "churches-evangelical",
        "denomination",
        "churches-interdenominational",
        "churches-covenant",
        "churches-various"
    ],
    "sg:website":"http://www.mountainbible.org",
    "wof:name":"Mountain Bible Church",
    "wof:placetype":"venue"
},
  "geometry": {"coordinates":[-111.319138,34.257721],"type":"Point"}
}