{
  "type": "Feature",
  "properties": {
    "addr:full":"4215 W Dunlap Ave Phoenix AZ 85051",
    "addr:housenumber":"4215",
    "addr:postcode":"85051",
    "addr:street":"W Dunlap Ave",
    "iso:country":"US",
    "sg:address":"4215 W Dunlap Ave",
    "sg:city":"Phoenix",
    "sg:classifiers":[
        {
            "category":"Real Estate",
            "subcategory":"Real Estate Agent",
            "type":"Services"
        }
    ],
    "sg:phone":"+1 623 915 1500",
    "sg:postcode":"85051",
    "sg:province":"AZ",
    "sg:tags":[
        "management"
    ],
    "wof:name":"Arizona Management Group Inc",
    "wof:placetype":"venue"
},
  "geometry": {"coordinates":[-112.14917699999999,33.567444],"type":"Point"}
}