{
  "type": "Feature",
  "properties": {
    "addr:full":"402 E Main St Mesa AZ 85203",
    "addr:housenumber":"402",
    "addr:postcode":"85203",
    "addr:street":"E Main St",
    "iso:country":"US",
    "sg:address":"402 E Main St",
    "sg:city":"Mesa",
    "sg:classifiers":[
        {
            "category":"Autos & Motor Vehicles",
            "subcategory":"Auto Supplies",
            "type":"Retail Goods"
        }
    ],
    "sg:phone":"+1 480 962 9154",
    "sg:postcode":"85203",
    "sg:province":"AZ",
    "wof:name":"Wilkys Machine Shop",
    "wof:placetype":"venue"
},
  "geometry": {"coordinates":[-111.821877,33.415153],"type":"Point"}
}