{
  "type": "Feature",
  "properties": {
    "iso:country":"US",
    "sg:address":"4022 E Greenway Rd",
    "sg:city":"Phoenix",
    "sg:classifiers":[
        {
            "category":"Retail",
            "subcategory":"Laundry & Dry Cleaning",
            "type":"Services"
        }
    ],
    "sg:phone":"+1 602 971 7636",
    "sg:postcode":"85032",
    "sg:province":"AZ",
    "sg:tags":[
        "cleaner"
    ],
    "wof:name":"Perfect Touch Cleaners",
    "wof:placetype":"venue"
},
  "geometry": {"coordinates":[-111.995239,33.626465],"type":"Point"}
}