{
  "type": "Feature",
  "properties": {
    "iso:country":"US",
    "sg:address":"11046 N Saguaro Blvd",
    "sg:city":"Fountain Hills",
    "sg:classifiers":[
        {
            "category":"Personal",
            "subcategory":"Beauty Salon",
            "type":"Services"
        }
    ],
    "sg:phone":"+1 480 837 7343",
    "sg:postcode":"85268",
    "sg:province":"AZ",
    "wof:name":"Fountain Hills Shear Indlgnc",
    "wof:placetype":"venue"
},
  "geometry": {"coordinates":[-111.708445,33.587384],"type":"Point"}
}