{
  "type": "Feature",
  "properties": {
    "addr:full":"2668 E Commonwealth Cir Chandler AZ 85225",
    "addr:housenumber":"2668",
    "addr:postcode":"85225",
    "addr:street":"E Commonwealth Cir",
    "iso:country":"US",
    "sg:address":"2668 E Commonwealth Cir",
    "sg:city":"Chandler",
    "sg:classifiers":[
        {
            "category":"Retail",
            "subcategory":"Repair Shop",
            "type":"Services"
        }
    ],
    "sg:phone":"+1 480 899 3438",
    "sg:postcode":"85225",
    "sg:province":"AZ",
    "sg:tags":[
        "refrigeration"
    ],
    "wof:name":"Four Winds Refrigeration",
    "wof:placetype":"venue"
},
  "geometry": {"coordinates":[-111.79672100000001,33.305854],"type":"Point"}
}