{
  "type": "Feature",
  "properties": {
    "iso:country":"US",
    "sg:address":"333 E Speedway Blvd",
    "sg:city":"Tucson",
    "sg:classifiers":[
        {
            "category":"Banks & Credit Unions",
            "subcategory":"Financial Services",
            "type":"Services"
        }
    ],
    "sg:phone":"+1 520 321 3333",
    "sg:postcode":"85705",
    "sg:province":"AZ",
    "sg:tags":[
        "investor"
    ],
    "wof:name":"Palice Investments LLC",
    "wof:placetype":"venue"
},
  "geometry": {"coordinates":[-110.965733,32.235992],"type":"Point"}
}