{
  "type": "Feature",
  "properties": {
    "addr:full":"1951 W Baseline Rd Mesa AZ 85202",
    "addr:housenumber":"1951",
    "addr:postcode":"85202",
    "addr:street":"W Baseline Rd",
    "iso:country":"US",
    "sg:address":"1951 W Baseline Rd",
    "sg:city":"Mesa",
    "sg:classifiers":[
        {
            "category":"Building & Trades",
            "subcategory":"Locksmith",
            "type":"Services"
        }
    ],
    "sg:phone":"+1 866 278 3275",
    "sg:postcode":"85202",
    "sg:province":"AZ",
    "sg:tags":[
        "key"
    ],
    "wof:name":"1 24 Hour Emergency Locksmith",
    "wof:placetype":"venue"
},
  "geometry": {"coordinates":[-111.87657400000001,33.378359],"type":"Point"}
}