{
  "type": "Feature",
  "properties": {
    "iso:country":"US",
    "sg:address":"663 N 2nd Ave",
    "sg:city":"Ajo",
    "sg:classifiers":[
        {
            "category":"Restaurant",
            "type":"Food & Drink"
        }
    ],
    "sg:phone":"+1 520 387 6226",
    "sg:postcode":"85321",
    "sg:province":"AZ",
    "sg:tags":[
        "style",
        "family"
    ],
    "wof:name":"Ranch House Restaurant",
    "wof:placetype":"venue"
},
  "geometry": {"coordinates":[-112.872448,32.377238],"type":"Point"}
}