{
  "type": "Feature",
  "properties": {
    "iso:country":"US",
    "sg:address":"806 S 56th Ave Ste 5",
    "sg:city":"Phoenix",
    "sg:classifiers":[
        {
            "category":"Transit Center",
            "subcategory":"Freight",
            "type":"Transportation"
        },
        {
            "category":"Professional",
            "subcategory":"Employment Agencies",
            "type":"Services"
        },
        {
            "category":"Professional",
            "subcategory":"Business Services",
            "type":"Services"
        }
    ],
    "sg:phone":"+1 602 233 3855",
    "sg:postcode":"85043",
    "sg:province":"AZ",
    "sg:tags":[
        "consultant",
        "forwarding",
        "broker",
        "custom"
    ],
    "sg:website":"http://www.schayer.com",
    "wof:name":"Charles M Schayer & Co",
    "wof:placetype":"venue"
},
  "geometry": {"coordinates":[-112.18068700000001,33.439941],"type":"Point"}
}