{
  "type": "Feature",
  "properties": {
    "iso:country":"US",
    "sg:address":"15730 N Pima Rd",
    "sg:city":"Scottsdale",
    "sg:classifiers":[
        {
            "category":"Brewery",
            "type":"Food & Drink"
        }
    ],
    "sg:menulink":"http://www.allmenus.com/az/phoenix/4612-ice-breakers-restaurant--brewery/menu/",
    "sg:phone":"+1 480 948 6789",
    "sg:postcode":"85260",
    "sg:province":"AZ",
    "sg:tags":[
        "american"
    ],
    "wof:name":"Ice Breakers Restaurant & Brewery",
    "wof:placetype":"venue"
},
  "geometry": {"coordinates":[-111.89100000000001,33.628707],"type":"Point"}
}