{
  "type": "Feature",
  "properties": {
    "addr:full":"2428 W Lone Cactus Dr Phoenix AZ 85027",
    "addr:housenumber":"2428",
    "addr:postcode":"85027",
    "addr:street":"W Lone Cactus Dr",
    "iso:country":"US",
    "sg:address":"2428 W Lone Cactus Dr",
    "sg:city":"Phoenix",
    "sg:classifiers":[
        {
            "category":"Building & Trades",
            "subcategory":"Construction",
            "type":"Services"
        }
    ],
    "sg:phone":"+1 623 581 5787",
    "sg:postcode":"85027",
    "sg:province":"AZ",
    "sg:tags":[
        "insulation",
        "heat",
        "contractor"
    ],
    "wof:name":"King Insulation",
    "wof:placetype":"venue"
},
  "geometry": {"coordinates":[-112.11132499999999,33.679777],"type":"Point"}
}