{
  "type": "Feature",
  "properties": {
    "iso:country":"US",
    "sg:address":"2050 N Alma School Rd #8",
    "sg:city":"Chandler",
    "sg:classifiers":[
        {
            "category":"Bars & Pubs",
            "type":"Food & Drink"
        },
        {
            "category":"Restaurant",
            "type":"Food & Drink"
        }
    ],
    "sg:phone":"+1 480 857 9444",
    "sg:postcode":"85224",
    "sg:province":"AZ",
    "sg:website":"www.churchillspubandgrill.com",
    "wof:name":"Churchill's Pub & Grill",
    "wof:placetype":"venue"
},
  "geometry": {"coordinates":[-111.85918,33.336013],"type":"Point"}
}