{
  "type": "Feature",
  "properties": {
    "iso:country":"US",
    "sg:address":"15414 N 19th Ave",
    "sg:city":"Phoenix",
    "sg:phone":"+1 602 993 7472",
    "sg:postcode":"85023",
    "sg:province":"AZ",
    "wof:name":"Lovejoy's Kansas City Bar-B-Q",
    "wof:placetype":"venue"
},
  "geometry": {"coordinates":[-112.099693,33.62585],"type":"Point"}
}