{
  "type": "Feature",
  "properties": {
    "iso:country":"US",
    "sg:address":"8500 E Long Mesa Dr",
    "sg:city":"Prescott Valley",
    "sg:classifiers":[
        {
            "category":"Freight",
            "type":"Transportation"
        }
    ],
    "sg:phone":"+1 928 775 4595",
    "sg:postcode":"86314",
    "sg:province":"AZ",
    "sg:tags":[
        "special",
        "general"
    ],
    "wof:name":"Budget Mini Storage",
    "wof:placetype":"venue"
},
  "geometry": {"coordinates":[-112.310333,34.62584],"type":"Point"}
}