{
  "type": "Feature",
  "properties": {
    "addr:full":"598 Jordan Rd Sedona AZ 86336",
    "addr:housenumber":"598",
    "addr:postcode":"86336",
    "addr:street":"Jordan Rd",
    "iso:country":"US",
    "sg:address":"598 Jordan Rd",
    "sg:city":"Sedona",
    "sg:classifiers":[
        {
            "category":"Professional",
            "type":"Services"
        }
    ],
    "sg:phone":"+1 928 204 1473",
    "sg:postcode":"86336",
    "sg:province":"AZ",
    "wof:name":"Sedona Hiking Adventures",
    "wof:placetype":"venue"
},
  "geometry": {"coordinates":[-111.761036,34.876121],"type":"Point"}
}