{
  "type": "Feature",
  "properties": {
    "iso:country":"US",
    "sg:address":"4911 E Edgemont Ave",
    "sg:city":"Phoenix",
    "sg:classifiers":[
        {
            "category":"Restaurant",
            "type":"Food & Drink"
        }
    ],
    "sg:phone":"+1 602 571 3977",
    "sg:postcode":"85008",
    "sg:province":"AZ",
    "sg:tags":[
        "eating"
    ],
    "wof:name":"Crispy Credit",
    "wof:placetype":"venue"
},
  "geometry": {"coordinates":[-111.975034,33.479609],"type":"Point"}
}