{
  "type": "Feature",
  "properties": {
    "iso:country":"US",
    "sg:address":"8522 N 7th St",
    "sg:city":"Phoenix",
    "sg:classifiers":[
        {
            "category":"Restaurant",
            "type":"Food & Drink"
        }
    ],
    "sg:phone":"+1 602 861 1379",
    "sg:postcode":"85020",
    "sg:province":"AZ",
    "sg:tags":[
        "eating"
    ],
    "wof:name":"Kitchen Connection Express",
    "wof:placetype":"venue"
},
  "geometry": {"coordinates":[-112.06534,33.562033],"type":"Point"}
}