{
  "type": "Feature",
  "properties": {
    "addr:full":"11475 E Via Linda Scottsdale AZ 85259",
    "addr:housenumber":"11475",
    "addr:postcode":"85259",
    "addr:street":"E Via Linda",
    "iso:country":"US",
    "sg:address":"11475 E Via Linda",
    "sg:city":"Scottsdale",
    "sg:classifiers":[
        {
            "category":"Coffee & Tea",
            "type":"Food & Drink"
        }
    ],
    "sg:menulink":"http://www.allmenus.com/az/phoenix/108375-starbucks-coffee/menu/",
    "sg:phone":"+1 480 767 0819",
    "sg:postcode":"85259",
    "sg:province":"AZ",
    "sg:tags":[
        "american"
    ],
    "wof:name":"Starbucks Coffee",
    "wof:placetype":"venue"
},
  "geometry": {"coordinates":[-111.834509,33.589649],"type":"Point"}
}