{
  "type": "Feature",
  "properties": {
    "iso:country":"US",
    "sg:address":"620 Myer Dr",
    "sg:city":"Sierra Vista",
    "sg:classifiers":[
        {
            "category":"Social Services",
            "subcategory":"Child Care",
            "type":"Services"
        }
    ],
    "sg:phone":"+1 520 458 3520",
    "sg:postcode":"85635",
    "sg:province":"AZ",
    "sg:tags":[
        "kindergarten",
        "academic",
        "school"
    ],
    "wof:name":"Learning Tree Preschool",
    "wof:placetype":"venue"
},
  "geometry": {"coordinates":[-110.29336,31.551348],"type":"Point"}
}