{
  "type": "Feature",
  "properties": {
    "iso:country":"US",
    "sg:address":"2510 N Campbell Ave",
    "sg:city":"Tucson",
    "sg:classifiers":[
        {
            "category":"Home & Garden",
            "subcategory":"Furniture",
            "type":"Retail Goods"
        }
    ],
    "sg:phone":"+1 520 320 5914",
    "sg:postcode":"85719",
    "sg:province":"AZ",
    "sg:tags":[
        "store"
    ],
    "wof:name":"El Mesquite",
    "wof:placetype":"venue"
},
  "geometry": {"coordinates":[-110.943968,32.25221],"type":"Point"}
}