{
  "type": "Feature",
  "properties": {
    "iso:country":"US",
    "sg:address":"2319 E Highland Ave",
    "sg:city":"Phoenix",
    "sg:classifiers":[
        {
            "category":"Wholesale",
            "subcategory":"Groceries",
            "type":"Manufacturing & Wholesale Goods"
        }
    ],
    "sg:phone":"+1 602 274 6818",
    "sg:postcode":"85016",
    "sg:province":"AZ",
    "sg:tags":[
        "gourmet",
        "food"
    ],
    "wof:name":"Feb 14th Gourmet LLC",
    "wof:placetype":"venue"
},
  "geometry": {"coordinates":[-112.030507,33.505627],"type":"Point"}
}