{
  "type": "Feature",
  "properties": {
    "iso:country":"US",
    "sg:address":"36930 N 104th Pl",
    "sg:city":"Scottsdale",
    "sg:classifiers":[
        {
            "category":"Professional",
            "subcategory":"Business Services",
            "type":"Services"
        }
    ],
    "sg:phone":"+1 480 451 9227",
    "sg:postcode":"85262",
    "sg:province":"AZ",
    "sg:tags":[
        "consultant",
        "coach"
    ],
    "wof:name":"Tiger Consulting",
    "wof:placetype":"venue"
},
  "geometry": {"coordinates":[-111.855115,33.82008],"type":"Point"}
}