{
  "type": "Feature",
  "properties": {
    "addr:full":"42109 N 46th Dr Phoenix AZ 85086",
    "addr:housenumber":"42109",
    "addr:postcode":"85086",
    "addr:street":"N 46Th Dr",
    "iso:country":"US",
    "sg:address":"42109 N 46th Dr",
    "sg:city":"Phoenix",
    "sg:classifiers":[
        {
            "category":"Retail",
            "subcategory":"Laundry & Dry Cleaning",
            "type":"Services"
        }
    ],
    "sg:phone":"+1 602 275 4966",
    "sg:postcode":"85086",
    "sg:province":"AZ",
    "sg:tags":[
        "cleaner",
        "rug",
        "carpet"
    ],
    "wof:name":"Jesse Johnson",
    "wof:placetype":"venue"
},
  "geometry": {"coordinates":[-112.158258,33.866133],"type":"Point"}
}