{
  "type": "Feature",
  "properties": {
    "addr:full":"4444 E Broadway Blvd Tucson AZ 85711",
    "addr:housenumber":"4444",
    "addr:postcode":"85711",
    "addr:street":"E Broadway Blvd",
    "iso:country":"US",
    "sg:address":"4444 E Broadway Blvd",
    "sg:city":"Tucson",
    "sg:classifiers":[
        {
            "category":"Professional",
            "subcategory":"Engineering",
            "type":"Services"
        }
    ],
    "sg:phone":"+1 520 881 7480",
    "sg:postcode":"85711",
    "sg:province":"AZ",
    "sg:tags":[
        "engineer"
    ],
    "sg:website":"www.wlb.com",
    "wof:name":"WLB Group",
    "wof:placetype":"venue"
},
  "geometry": {"coordinates":[-110.897465,32.221427],"type":"Point"}
}