{
  "type": "Feature",
  "properties": {
    "iso:country":"US",
    "sg:address":"6016 S Mcclintock Dr",
    "sg:city":"Tempe",
    "sg:classifiers":[
        {
            "category":"Manufacturing",
            "subcategory":"Buildings",
            "type":"Manufacturing & Wholesale Goods"
        },
        {
            "category":"Building & Trades",
            "subcategory":"Construction",
            "type":"Services"
        }
    ],
    "sg:phone":"+1 480 345 2680",
    "sg:postcode":"85283",
    "sg:province":"AZ",
    "sg:tags":[
        "home",
        "siding",
        "builder",
        "contractor"
    ],
    "wof:name":"Precision Siding & Construction",
    "wof:placetype":"venue"
},
  "geometry": {"coordinates":[-111.911277,33.36762],"type":"Point"}
}