{
  "type": "Feature",
  "properties": {
    "iso:country":"US",
    "sg:address":"750 E Foothills Dr",
    "sg:city":"Tucson",
    "sg:classifiers":[
        {
            "category":"Health Services",
            "subcategory":"Nursing And Care Facility",
            "type":"Services"
        }
    ],
    "sg:phone":"+1 520 292 3955",
    "sg:postcode":"85718",
    "sg:province":"AZ",
    "sg:tags":[
        "hospice"
    ],
    "wof:name":"Odyssey Inpatient Hospice Home",
    "wof:placetype":"venue"
},
  "geometry": {"coordinates":[-110.958843,32.299789],"type":"Point"}
}