{
  "type": "Feature",
  "properties": {
    "iso:country":"US",
    "sg:address":"4832 N 27th Ave",
    "sg:city":"Phoenix",
    "sg:classifiers":[
        {
            "category":"Food & Beverages",
            "subcategory":"Meat & Fish",
            "type":"Retail Goods"
        }
    ],
    "sg:phone":"+1 602 336 0234",
    "sg:postcode":"85017",
    "sg:province":"AZ",
    "wof:name":"Carniceria LA Pinos",
    "wof:placetype":"venue"
},
  "geometry": {"coordinates":[-112.117069,33.508256],"type":"Point"}
}