{
  "type": "Feature",
  "properties": {
    "iso:country":"US",
    "sg:address":"2340 W Bell Rd",
    "sg:city":"Phoenix",
    "sg:classifiers":[
        {
            "category":"Real Estate",
            "subcategory":"Real Estate Agent",
            "type":"Services"
        }
    ],
    "sg:phone":"+1 602 942 4400",
    "sg:postcode":"85023",
    "sg:province":"AZ",
    "wof:name":"Realty Choices USA",
    "wof:placetype":"venue"
},
  "geometry": {"coordinates":[-112.111902,33.640037],"type":"Point"}
}