{
  "type": "Feature",
  "properties": {
    "addr:full":"6544 Old US Hwy 80 Yuma AZ 85365",
    "addr:housenumber":"6544",
    "addr:postcode":"85365",
    "addr:street":"Old Us Hwy 80",
    "iso:country":"US",
    "sg:address":"6544 Old US Hwy 80",
    "sg:city":"Yuma",
    "sg:classifiers":[
        {
            "category":"Food & Beverages",
            "subcategory":"Groceries & Convenience Stores",
            "type":"Retail Goods"
        }
    ],
    "sg:phone":"+1 928 344 0960",
    "sg:postcode":"85365",
    "sg:province":"AZ",
    "wof:name":"Circle K Store",
    "wof:placetype":"venue"
},
  "geometry": {"coordinates":[-114.520178,32.67016],"type":"Point"}
}