{
  "type": "Feature",
  "properties": {
    "addr:full":"325 S Westwood Mesa AZ 85210",
    "addr:housenumber":"325",
    "addr:postcode":"85210",
    "addr:street":"S Westwood",
    "iso:country":"US",
    "sg:address":"325 S Westwood",
    "sg:city":"Mesa",
    "sg:classifiers":[
        {
            "category":"Manufacturing",
            "subcategory":"Tools & Machinery",
            "type":"Manufacturing & Wholesale Goods"
        },
        {
            "category":"Wholesale",
            "subcategory":"Electrical",
            "type":"Manufacturing & Wholesale Goods"
        }
    ],
    "sg:phone":"+1 480 834 4005",
    "sg:postcode":"85210",
    "sg:province":"AZ",
    "sg:tags":[
        "equipment",
        "manufacturer",
        "supplies-wholesale",
        "electric",
        "supply"
    ],
    "wof:name":"Rockys Electric Supply",
    "wof:placetype":"venue"
},
  "geometry": {"coordinates":[-111.852497,33.408601],"type":"Point"}
}