{
  "type": "Feature",
  "properties": {
    "iso:country":"US",
    "sg:address":"6042 E Speedway Blvd",
    "sg:city":"Tucson",
    "sg:classifiers":[
        {
            "category":"Retail",
            "subcategory":"Car Wash",
            "type":"Services"
        }
    ],
    "sg:phone":"+1 520 747 3775",
    "sg:postcode":"85712",
    "sg:province":"AZ",
    "sg:tags":[
        "polishing",
        "washing"
    ],
    "sg:website":"www.washdepot.com",
    "wof:name":"Simoniz Car Wash",
    "wof:placetype":"venue"
},
  "geometry": {"coordinates":[-110.863193,32.236059],"type":"Point"}
}