{
  "type": "Feature",
  "properties": {
    "iso:country":"US",
    "sg:address":"334 W Los Reales Rd",
    "sg:city":"Tucson",
    "sg:classifiers":[
        {
            "category":"Organizations",
            "subcategory":"Religious Organization",
            "type":"Services"
        }
    ],
    "sg:phone":"+1 520 806 4700",
    "sg:postcode":"85706",
    "sg:province":"AZ",
    "sg:tags":[
        "church"
    ],
    "wof:name":"Maranatha Christian Ctr",
    "wof:placetype":"venue"
},
  "geometry": {"coordinates":[-110.977159,32.11952],"type":"Point"}
}