{
  "type": "Feature",
  "properties": {
    "iso:country":"US",
    "sg:address":"8413 S Avenida del Yaqui",
    "sg:city":"Guadalupe",
    "sg:classifiers":[
        {
            "category":"Government",
            "subcategory":"Fire Station",
            "type":"Public Place"
        }
    ],
    "sg:phone":"+1 480 839 1112",
    "sg:postcode":"85283",
    "sg:province":"AZ",
    "sg:tags":[
        "department"
    ],
    "sg:website":"http://www.guadalupeaz.org",
    "wof:name":"Guadalupe Fire Dept",
    "wof:placetype":"venue"
},
  "geometry": {"coordinates":[-111.963158,33.369919],"type":"Point"}
}