{
  "type": "Feature",
  "properties": {
    "addr:full":"2039 N 16th St Phoenix AZ 85006",
    "addr:housenumber":"2039",
    "addr:postcode":"85006",
    "addr:street":"N 16Th St",
    "iso:country":"US",
    "sg:address":"2039 N 16th St",
    "sg:city":"Phoenix",
    "sg:classifiers":[
        {
            "category":"Manufacturing",
            "subcategory":"Apparel",
            "type":"Manufacturing & Wholesale Goods"
        },
        {
            "category":"Home & Garden",
            "subcategory":"Home Furnishings",
            "type":"Retail Goods"
        }
    ],
    "sg:phone":"+1 602 254 6905",
    "sg:postcode":"85006",
    "sg:province":"AZ",
    "sg:tags":[
        "curtain",
        "made",
        "drapery",
        "mfg"
    ],
    "wof:name":"Leah's Complete Drapery Svc",
    "wof:placetype":"venue"
},
  "geometry": {"coordinates":[-112.047588,33.470479],"type":"Point"}
}