{
  "type": "Feature",
  "properties": {
    "iso:country":"US",
    "sg:address":"6740 W McDowell Road",
    "sg:city":"Phoenix",
    "sg:classifiers":[
        {
            "category":"Restaurant",
            "type":"Food & Drink"
        }
    ],
    "sg:phone":"+1 623 247 1199",
    "sg:postcode":"85035",
    "sg:province":"AZ",
    "sg:tags":[
        "mexican"
    ],
    "wof:name":"Sainz Mexican Restaurant",
    "wof:placetype":"venue"
},
  "geometry": {"coordinates":[-112.206538,33.465922],"type":"Point"}
}