{
  "type": "Feature",
  "properties": {
    "iso:country":"US",
    "sg:address":"1431 W Miracle Mile",
    "sg:city":"Tucson",
    "sg:classifiers":[
        {
            "category":"Home & Garden",
            "subcategory":"Garden Supply",
            "type":"Retail Goods"
        }
    ],
    "sg:phone":"+1 520 884 4772",
    "sg:postcode":"85705",
    "sg:province":"AZ",
    "sg:tags":[
        "fountain",
        "display"
    ],
    "wof:name":"LA Cantera Store",
    "wof:placetype":"venue"
},
  "geometry": {"coordinates":[-110.995816,32.261232],"type":"Point"}
}