{
  "type": "Feature",
  "properties": {
    "iso:country":"US",
    "sg:address":"1520 W Southern Ave",
    "sg:city":"Mesa",
    "sg:classifiers":[
        {
            "category":"Shopping",
            "subcategory":"Bicycles & Sporting Goods",
            "type":"Retail Goods"
        }
    ],
    "sg:phone":"+1 480 962 6910",
    "sg:postcode":"85202",
    "sg:province":"AZ",
    "sg:tags":[
        "surfboard"
    ],
    "wof:name":"Ski Pro",
    "wof:placetype":"venue"
},
  "geometry": {"coordinates":[-111.864982,33.393144],"type":"Point"}
}