{
  "type": "Feature",
  "properties": {
    "addr:full":"10645 N Tatum Blvd Phoenix AZ 85028",
    "addr:housenumber":"10645",
    "addr:postcode":"85028",
    "addr:street":"N Tatum Blvd",
    "iso:country":"US",
    "sg:address":"10645 N Tatum Blvd",
    "sg:city":"Phoenix",
    "sg:classifiers":[
        {
            "category":"Banks & Credit Unions",
            "subcategory":"Bank",
            "type":"Services"
        }
    ],
    "sg:phone":"+1 480 368 8668",
    "sg:postcode":"85028",
    "sg:province":"AZ",
    "sg:tags":[
        "financing",
        "banker",
        "mortgage",
        "broker"
    ],
    "sg:website":"www.foreclosurerescue.com",
    "wof:name":"Foreclosure Rescue LLC",
    "wof:placetype":"venue"
},
  "geometry": {"coordinates":[-111.97779800000001,33.583514],"type":"Point"}
}