{
  "type": "Feature",
  "properties": {
    "iso:country":"US",
    "sg:address":"4248 E Broadway Rd",
    "sg:city":"Mesa",
    "sg:classifiers":[
        {
            "category":"Organizations",
            "subcategory":"Religious Organization",
            "type":"Services"
        }
    ],
    "sg:phone":"+1 480 832 1150",
    "sg:postcode":"85206",
    "sg:province":"AZ",
    "sg:tags":[
        "church"
    ],
    "wof:name":"Cornerstone Bible Fellowship",
    "wof:placetype":"venue"
},
  "geometry": {"coordinates":[-111.739664,33.408363],"type":"Point"}
}