{
  "type": "Feature",
  "properties": {
    "addr:full":"705 Marina Blvd Bullhead City AZ 86442",
    "addr:housenumber":"705",
    "addr:postcode":"86442",
    "addr:street":"Marina Blvd",
    "iso:country":"US",
    "sg:address":"705 Marina Blvd",
    "sg:city":"Bullhead City",
    "sg:classifiers":[
        {
            "category":"Shopping",
            "type":"Retail Goods"
        }
    ],
    "sg:phone":"+1 928 758 2444",
    "sg:postcode":"86442",
    "sg:province":"AZ",
    "sg:tags":[
        "pet",
        "grooming",
        "supply"
    ],
    "wof:name":"Desert Dogs",
    "wof:placetype":"venue"
},
  "geometry": {"coordinates":[-114.622882,35.100643],"type":"Point"}
}