{
  "type": "Feature",
  "properties": {
    "iso:country":"US",
    "sg:address":"7102 W Roosevelt St",
    "sg:city":"Phoenix",
    "sg:classifiers":[
        {
            "category":"Professional",
            "subcategory":"Employment Agencies",
            "type":"Services"
        }
    ],
    "sg:phone":"+1 623 936 8976",
    "sg:postcode":"85043",
    "sg:province":"AZ",
    "wof:name":"Sos Staffing",
    "wof:placetype":"venue"
},
  "geometry": {"coordinates":[-112.21212300000001,33.458796],"type":"Point"}
}