{
  "type": "Feature",
  "properties": {
    "iso:country":"US",
    "sg:address":"37645 N Cave Creek Rd",
    "sg:city":"Cave Creek",
    "sg:classifiers":[
        {
            "category":"Restaurant",
            "type":"Food & Drink"
        }
    ],
    "sg:phone":"+1 480 488 0489",
    "sg:postcode":"85331",
    "sg:province":"AZ",
    "sg:tags":[
        "mexican"
    ],
    "wof:name":"Los Mesquites Taqueria",
    "wof:placetype":"venue"
},
  "geometry": {"coordinates":[-111.953797,33.827589],"type":"Point"}
}