{
  "type": "Feature",
  "properties": {
    "iso:country":"US",
    "sg:address":"4466 E Princess Dr",
    "sg:city":"Mesa",
    "sg:classifiers":[
        {
            "category":"Building & Trades",
            "subcategory":"Construction",
            "type":"Services"
        }
    ],
    "sg:phone":"+1 480 969 5111",
    "sg:postcode":"85205",
    "sg:province":"AZ",
    "sg:tags":[
        "contractor",
        "specialty",
        "mfg"
    ],
    "wof:name":"Sign This Manufacturing",
    "wof:placetype":"venue"
},
  "geometry": {"coordinates":[-111.733757,33.440993],"type":"Point"}
}