{
  "type": "Feature",
  "properties": {
    "addr:full":"707 S Myrtle Ave Tempe AZ 85281",
    "addr:housenumber":"707",
    "addr:postcode":"85281",
    "addr:street":"S Myrtle Ave",
    "iso:country":"US",
    "sg:address":"707 S Myrtle Ave",
    "sg:city":"Tempe",
    "sg:classifiers":[
        {
            "category":"Shopping",
            "type":"Retail Goods"
        }
    ],
    "sg:phone":"+1 480 966 2945",
    "sg:postcode":"85281",
    "sg:province":"AZ",
    "sg:tags":[
        "merchandise"
    ],
    "wof:name":"Trophy Den Inc",
    "wof:placetype":"venue"
},
  "geometry": {"coordinates":[-111.938061,33.422034],"type":"Point"}
}