{
  "type": "Feature",
  "properties": {
    "addr:full":"1040 Whipple St Prescott AZ 86305",
    "addr:housenumber":"1040",
    "addr:postcode":"86305",
    "addr:street":"Whipple St",
    "iso:country":"US",
    "sg:address":"1040 Whipple St",
    "sg:city":"Prescott",
    "sg:classifiers":[
        {
            "category":"Professional",
            "subcategory":"Accounting & Tax Preparation",
            "type":"Services"
        }
    ],
    "sg:phone":"+1 928 771 2201",
    "sg:postcode":"86305",
    "sg:province":"AZ",
    "sg:tags":[
        "bookkeeping",
        "general"
    ],
    "wof:name":"Dodie Klein",
    "wof:placetype":"venue"
},
  "geometry": {"coordinates":[-112.48379,34.556797],"type":"Point"}
}