{
  "type": "Feature",
  "properties": {
    "addr:full":"19712 W Pasadena Ave Litchfield Park AZ 85340",
    "addr:housenumber":"19712",
    "addr:postcode":"85340",
    "addr:street":"W Pasadena Ave",
    "iso:country":"US",
    "sg:address":"19712 W Pasadena Ave",
    "sg:city":"Litchfield Park",
    "sg:classifiers":[
        {
            "category":"Professional",
            "subcategory":"Business Services",
            "type":"Services"
        }
    ],
    "sg:phone":"+1 623 853 1244",
    "sg:postcode":"85340",
    "sg:province":"AZ",
    "sg:tags":[
        "information",
        "referral"
    ],
    "wof:name":"Database Research",
    "wof:placetype":"venue"
},
  "geometry": {"coordinates":[-112.48473799999999,33.509264],"type":"Point"}
}