{
  "type": "Feature",
  "properties": {
    "iso:country":"US",
    "sg:address":"8380 E Gelding Dr",
    "sg:city":"Scottsdale",
    "sg:classifiers":[
        {
            "category":"Retail",
            "subcategory":"Repair Shop",
            "type":"Services"
        }
    ],
    "sg:phone":"+1 480 998 2950",
    "sg:postcode":"85260",
    "sg:province":"AZ",
    "sg:tags":[
        "system",
        "freezer",
        "contractor",
        "air conditioning",
        "refrigerator"
    ],
    "sg:website":"http://www.ars-net.com",
    "wof:name":"American Refrigeration Supplies, Inc.",
    "wof:placetype":"venue"
},
  "geometry": {"coordinates":[-111.900109,33.615454],"type":"Point"}
}