{
  "type": "Feature",
  "properties": {
    "iso:country":"US",
    "sg:address":"811 E Wetmore Rd",
    "sg:city":"Tucson",
    "sg:classifiers":[
        {
            "category":"Professional",
            "subcategory":"Management & Consulting",
            "type":"Services"
        }
    ],
    "sg:phone":"+1 520 887 0521",
    "sg:postcode":"85719",
    "sg:province":"AZ",
    "wof:name":"Frontier Management",
    "wof:placetype":"venue"
},
  "geometry": {"coordinates":[-110.960223,32.286685],"type":"Point"}
}