{
  "type": "Feature",
  "properties": {
    "iso:country":"US",
    "sg:address":"1824 S 19th Ave",
    "sg:city":"Phoenix",
    "sg:classifiers":[
        {
            "category":"Retail",
            "subcategory":"Auto Repair",
            "type":"Services"
        }
    ],
    "sg:phone":"+1 602 254 2042",
    "sg:postcode":"85009",
    "sg:province":"AZ",
    "sg:tags":[
        "wrecker"
    ],
    "wof:name":"Barnett's Towing",
    "wof:placetype":"venue"
},
  "geometry": {"coordinates":[-112.099975,33.431051],"type":"Point"}
}