{
  "type": "Feature",
  "properties": {
    "iso:country":"US",
    "sg:address":"1200 N Sickles Dr",
    "sg:city":"Tempe",
    "sg:classifiers":[
        {
            "category":"Building & Trades",
            "subcategory":"Plumbing",
            "type":"Services"
        }
    ],
    "sg:phone":"+1 480 921 0903",
    "sg:postcode":"85281",
    "sg:province":"AZ",
    "sg:tags":[
        "engineering",
        "contractor",
        "mechanical"
    ],
    "sg:website":"http://www.umec.com",
    "wof:name":"University Mechanical",
    "wof:placetype":"venue"
},
  "geometry": {"coordinates":[-111.91158299999999,33.441851],"type":"Point"}
}