{
  "type": "Feature",
  "properties": {
    "iso:country":"US",
    "sg:address":"704 E Hampton Ct",
    "sg:city":"Gilbert",
    "sg:classifiers":[
        {
            "category":"Social Services",
            "type":"Services"
        },
        {
            "category":"Professional",
            "subcategory":"Employment Agencies",
            "type":"Services"
        }
    ],
    "sg:phone":"+1 480 497 4510",
    "sg:postcode":"85295",
    "sg:province":"AZ",
    "sg:tags":[
        "workers'",
        "placement",
        "volunteer"
    ],
    "wof:name":"Botanical Education Foundation",
    "wof:placetype":"venue"
},
  "geometry": {"coordinates":[-111.77432,33.300949],"type":"Point"}
}