{
  "type": "Feature",
  "properties": {
    "addr:full":"1817 E Southern Ave Tempe AZ 85282",
    "addr:housenumber":"1817",
    "addr:postcode":"85282",
    "addr:street":"E Southern Ave",
    "iso:country":"US",
    "sg:address":"1817 E Southern Ave",
    "sg:city":"Tempe",
    "sg:classifiers":[
        {
            "category":"Education",
            "subcategory":"Vocational School",
            "type":"Public Place"
        }
    ],
    "sg:phone":"+1 480 777 3475",
    "sg:postcode":"85282",
    "sg:province":"AZ",
    "wof:name":"Az Technical Institute",
    "wof:placetype":"venue"
},
  "geometry": {"coordinates":[-111.90751400000001,33.39289],"type":"Point"}
}