{
  "type": "Feature",
  "properties": {
    "addr:full":"7950 E Starlight Way # 248 Scottsdale AZ 85250",
    "addr:housenumber":"7950",
    "addr:postcode":"85250",
    "addr:street":"E Starlight Way # 248",
    "iso:country":"US",
    "sg:address":"7950 E Starlight Way # 248",
    "sg:city":"Scottsdale",
    "sg:classifiers":[
        {
            "category":"Retail",
            "subcategory":"Laundry & Dry Cleaning",
            "type":"Services"
        }
    ],
    "sg:phone":"+1 602 424 0345",
    "sg:postcode":"85250",
    "sg:province":"AZ",
    "sg:tags":[
        "cleaner",
        "rug",
        "carpet"
    ],
    "wof:name":"Chem-Dry",
    "wof:placetype":"venue"
},
  "geometry": {"coordinates":[-111.909166,33.520882],"type":"Point"}
}