{
  "type": "Feature",
  "properties": {
    "iso:country":"US",
    "sg:address":"4280 E Benson Hwy",
    "sg:city":"Tucson",
    "sg:classifiers":[
        {
            "category":"Food & Beverages",
            "subcategory":"Groceries & Convenience Stores",
            "type":"Retail Goods"
        }
    ],
    "sg:phone":"+1 520 574 0170",
    "sg:postcode":"85706",
    "sg:province":"AZ",
    "wof:name":"Quik Mart",
    "wof:placetype":"venue"
},
  "geometry": {"coordinates":[-110.902603,32.142554],"type":"Point"}
}