{
  "type": "Feature",
  "properties": {
    "iso:country":"US",
    "sg:address":"1712 E Broadway Rd",
    "sg:city":"Phoenix",
    "sg:classifiers":[
        {
            "category":"Shopping",
            "subcategory":"Clothing, Apparel, & Fashions",
            "type":"Retail Goods"
        }
    ],
    "sg:phone":"+1 602 276 0873",
    "sg:postcode":"85040",
    "sg:province":"AZ",
    "wof:name":"Yisrayl Connection",
    "wof:placetype":"venue"
},
  "geometry": {"coordinates":[-112.043481,33.406876],"type":"Point"}
}