{
  "type": "Feature",
  "properties": {
    "iso:country":"US",
    "sg:address":"205 S Sunset Dr",
    "sg:city":"Sedona",
    "sg:classifiers":[
        {
            "category":"Food & Beverages",
            "subcategory":"Liquor & Beverages",
            "type":"Retail Goods"
        },
        {
            "category":"Wholesale",
            "subcategory":"Wine & Distilled Alcoholic Beverages",
            "type":"Manufacturing & Wholesale Goods"
        }
    ],
    "sg:phone":"+1 928 554 4072",
    "sg:postcode":"86336",
    "sg:province":"AZ",
    "sg:tags":[
        "broker"
    ],
    "wof:name":"Verde Valley Wine Tours",
    "wof:placetype":"venue"
},
  "geometry": {"coordinates":[-111.795517,34.861469],"type":"Point"}
}