{
  "type": "Feature",
  "properties": {
    "addr:full":"14064 W Yuma St Phoenix AZ 85009",
    "addr:housenumber":"14064",
    "addr:postcode":"85009",
    "addr:street":"W Yuma St",
    "iso:country":"US",
    "sg:address":"14064 W Yuma St",
    "sg:city":"Phoenix",
    "sg:classifiers":[
        {
            "category":"Professional",
            "subcategory":"Computer Services",
            "type":"Services"
        },
        {
            "category":"Communications",
            "type":"Services"
        },
        {
            "category":"Communications",
            "subcategory":"Television Station",
            "type":"Services"
        }
    ],
    "sg:phone":"+1 866 310 4761",
    "sg:postcode":"85009",
    "sg:province":"AZ",
    "sg:tags":[
        "satellite",
        "cable",
        "tv",
        "isp",
        "system",
        "equipment",
        "internet",
        "provider"
    ],
    "sg:website":"http://www.directsattv.com/directv/?tfid=ypm",
    "wof:name":"Direct Sat TV - An Authorized DIRECTV Dealer",
    "wof:placetype":"venue"
},
  "geometry": {"coordinates":[-112.125935,33.435081],"type":"Point"}
}