{
  "type": "Feature",
  "properties": {
    "iso:country":"US",
    "sg:address":"4502 E Oak St",
    "sg:city":"Phoenix",
    "sg:classifiers":[
        {
            "category":"Shopping",
            "subcategory":"Pharmacy",
            "type":"Retail Goods"
        }
    ],
    "sg:phone":"+1 602 808 0111",
    "sg:postcode":"85008",
    "sg:province":"AZ",
    "wof:name":"Cost Co Pharmacy",
    "wof:placetype":"venue"
},
  "geometry": {"coordinates":[-111.986603,33.473037],"type":"Point"}
}