{
  "type": "Feature",
  "properties": {
    "iso:country":"US",
    "sg:address":"3351 W Joan de Arc Ave",
    "sg:city":"Phoenix",
    "sg:classifiers":[
        {
            "category":"Shopping",
            "subcategory":"Catalog Store",
            "type":"Retail Goods"
        }
    ],
    "sg:phone":"+1 602 942 6468",
    "sg:postcode":"85029",
    "sg:province":"AZ",
    "sg:tags":[
        "mail",
        "house"
    ],
    "wof:name":"J & M Closeouts",
    "wof:placetype":"venue"
},
  "geometry": {"coordinates":[-112.132255,33.606768],"type":"Point"}
}