{
  "type": "Feature",
  "properties": {
    "iso:country":"US",
    "sg:address":"2605 E Lemon St",
    "sg:city":"Tempe",
    "sg:classifiers":[
        {
            "category":"Building & Trades",
            "subcategory":"Construction",
            "type":"Services"
        }
    ],
    "sg:phone":"+1 602 618 3703",
    "sg:postcode":"85281",
    "sg:province":"AZ",
    "sg:tags":[
        "contractor"
    ],
    "wof:name":"Down Settle",
    "wof:placetype":"venue"
},
  "geometry": {"coordinates":[-111.883036,33.417339],"type":"Point"}
}