{
  "type": "Feature",
  "properties": {
    "iso:country":"US",
    "sg:address":"1208 N Alvernon Way",
    "sg:city":"Tucson",
    "sg:classifiers":[
        {
            "category":"Personal",
            "subcategory":"Beauty Salon",
            "type":"Services"
        }
    ],
    "sg:phone":"+1 520 327 6454",
    "sg:postcode":"85712",
    "sg:province":"AZ",
    "wof:name":"David's Hair",
    "wof:placetype":"venue"
},
  "geometry": {"coordinates":[-110.90965199999999,32.238825],"type":"Point"}
}