{
  "type": "Feature",
  "properties": {
    "addr:full":"545 S Robson Mesa AZ 85210",
    "addr:housenumber":"545",
    "addr:postcode":"85210",
    "addr:street":"S Robson",
    "iso:country":"US",
    "sg:address":"545 S Robson",
    "sg:city":"Mesa",
    "sg:classifiers":[
        {
            "category":"Home & Garden",
            "subcategory":"Furniture",
            "type":"Retail Goods"
        }
    ],
    "sg:phone":"+1 480 834 4862",
    "sg:postcode":"85210",
    "sg:province":"AZ",
    "sg:tags":[
        "builder",
        "custom"
    ],
    "wof:name":"T D Oneil & Co",
    "wof:placetype":"venue"
},
  "geometry": {"coordinates":[-111.836624,33.405072],"type":"Point"}
}