{
  "type": "Feature",
  "properties": {
    "iso:country":"US",
    "sg:address":"4285 N Saratoga Dr",
    "sg:city":"Prescott Valley",
    "sg:classifiers":[
        {
            "category":"Bars & Pubs",
            "type":"Food & Drink"
        }
    ],
    "sg:phone":"+1 928 632 8689",
    "sg:postcode":"86314",
    "sg:province":"AZ",
    "wof:name":"Billy Jacks Saloon & Grill",
    "wof:placetype":"venue"
},
  "geometry": {"coordinates":[-112.305362,34.602158],"type":"Point"}
}