{
  "type": "Feature",
  "properties": {
    "iso:country":"US",
    "sg:address":"3137 E Elwood St",
    "sg:city":"Phoenix",
    "sg:classifiers":[
        {
            "category":"Professional",
            "subcategory":"Engineering",
            "type":"Services"
        }
    ],
    "sg:phone":"+1 602 431 8036",
    "sg:postcode":"85034",
    "sg:province":"AZ",
    "sg:tags":[
        "engineer"
    ],
    "sg:website":"www.cdicorp.com",
    "wof:name":"CDI Corp",
    "wof:placetype":"venue"
},
  "geometry": {"coordinates":[-112.012665,33.417161],"type":"Point"}
}