{
  "type": "Feature",
  "properties": {
    "addr:full":"1203 W San Pedro St Gilbert AZ 85233",
    "addr:housenumber":"1203",
    "addr:postcode":"85233",
    "addr:street":"W San Pedro St",
    "iso:country":"US",
    "sg:address":"1203 W San Pedro St",
    "sg:city":"Gilbert",
    "sg:classifiers":[
        {
            "category":"Building & Trades",
            "subcategory":"Construction",
            "type":"Services"
        }
    ],
    "sg:phone":"+1 480 892 0197",
    "sg:postcode":"85233",
    "sg:province":"AZ",
    "sg:tags":[
        "general",
        "contractor"
    ],
    "wof:name":"Nitti Brothers Construction",
    "wof:placetype":"venue"
},
  "geometry": {"coordinates":[-111.815298,33.367542],"type":"Point"}
}