{
  "type": "Feature",
  "properties": {
    "iso:country":"US",
    "sg:address":"8912 E Pinnacle Peak Rd",
    "sg:city":"Scottsdale",
    "sg:classifiers":[
        {
            "category":"Utilities",
            "subcategory":"Telephone",
            "type":"Services"
        },
        {
            "category":"Wholesale",
            "subcategory":"Electrical",
            "type":"Manufacturing & Wholesale Goods"
        }
    ],
    "sg:phone":"+1 480 515 0087",
    "sg:postcode":"85255",
    "sg:province":"AZ",
    "sg:tags":[
        "distance",
        "telecommunication",
        "long",
        "communications"
    ],
    "wof:name":"Advanced Telemanagement Group",
    "wof:placetype":"venue"
},
  "geometry": {"coordinates":[-111.889355,33.698696],"type":"Point"}
}