{
  "type": "Feature",
  "properties": {
    "iso:country":"US",
    "sg:address":"3131 E Transcon Way",
    "sg:city":"Tucson",
    "sg:classifiers":[
        {
            "category":"Real Estate",
            "subcategory":"Real Estate Agent",
            "type":"Services"
        }
    ],
    "sg:phone":"+1 520 742 4586",
    "sg:postcode":"85706",
    "sg:province":"AZ",
    "wof:name":"Culebra Arizona Properties LLC",
    "wof:placetype":"venue"
},
  "geometry": {"coordinates":[-110.92363,32.137425],"type":"Point"}
}