{
  "type": "Feature",
  "properties": {
    "iso:country":"US",
    "sg:address":"11839 N 28th Dr",
    "sg:city":"Phoenix",
    "sg:classifiers":[
        {
            "category":"Banks & Credit Unions",
            "subcategory":"Financial Services",
            "type":"Services"
        }
    ],
    "sg:phone":"+1 602 863 2006",
    "sg:postcode":"85029",
    "sg:province":"AZ",
    "sg:tags":[
        "sharing",
        "profit",
        "annuity",
        "retirement",
        "planning",
        "plan",
        "insurance",
        "pension"
    ],
    "wof:name":"Qualified Benefit Systems Inc",
    "wof:placetype":"venue"
},
  "geometry": {"coordinates":[-112.119945,33.59411],"type":"Point"}
}