{
  "type": "Feature",
  "properties": {
    "iso:country":"US",
    "sg:address":"1010 E Missouri Ave",
    "sg:city":"Phoenix",
    "sg:classifiers":[
        {
            "category":"Manufacturing",
            "subcategory":"Printing",
            "type":"Manufacturing & Wholesale Goods"
        }
    ],
    "sg:phone":"+1 602 395 5850",
    "sg:postcode":"85014",
    "sg:province":"AZ",
    "sg:tags":[
        "periodical"
    ],
    "wof:name":"Mc Murry Advertising Group",
    "wof:placetype":"venue"
},
  "geometry": {"coordinates":[-112.059198,33.516569],"type":"Point"}
}