{
  "type": "Feature",
  "properties": {
    "iso:country":"US",
    "sg:address":"15444 N Boswell Blvd",
    "sg:city":"Sun City",
    "sg:classifiers":[
        {
            "category":"Professional",
            "type":"Services"
        }
    ],
    "sg:phone":"+1 623 974 0873",
    "sg:postcode":"85351",
    "sg:province":"AZ",
    "wof:name":"Paul Handman",
    "wof:placetype":"venue"
},
  "geometry": {"coordinates":[-112.278638,33.625278],"type":"Point"}
}