{
  "type": "Feature",
  "properties": {
    "iso:country":"US",
    "sg:address":"1212 W Thatcher Blvd",
    "sg:city":"Safford",
    "sg:classifiers":[
        {
            "category":"Building & Trades",
            "subcategory":"Plumbing",
            "type":"Services"
        }
    ],
    "sg:phone":"+1 928 428 5480",
    "sg:postcode":"85546",
    "sg:province":"AZ",
    "sg:tags":[
        "air",
        "archery",
        "heating",
        "conditioning",
        "contractor"
    ],
    "wof:name":"Sokol Archery Shop",
    "wof:placetype":"venue"
},
  "geometry": {"coordinates":[-109.721736,32.834964],"type":"Point"}
}