{
  "type": "Feature",
  "properties": {
    "addr:full":"1931 Hwy 95 Bullhead City AZ 86442",
    "addr:housenumber":"1931",
    "addr:postcode":"86442",
    "addr:street":"Hwy 95",
    "iso:country":"US",
    "sg:address":"1931 Hwy 95",
    "sg:city":"Bullhead City",
    "sg:classifiers":[
        {
            "category":"Communications",
            "subcategory":"Radio Station",
            "type":"Services"
        }
    ],
    "sg:phone":"+1 928 704 9305",
    "sg:postcode":"86442",
    "sg:province":"AZ",
    "sg:tags":[
        "company",
        "broadcasting"
    ],
    "sg:website":"www.maddog.net",
    "wof:name":"Mad Dog Wireless",
    "wof:placetype":"venue"
},
  "geometry": {"coordinates":[-114.596329,35.118944],"type":"Point"}
}