{
  "type": "Feature",
  "properties": {
    "addr:full":"360 Henry St Prescott AZ 86301",
    "addr:housenumber":"360",
    "addr:postcode":"86301",
    "addr:street":"Henry St",
    "iso:country":"US",
    "sg:address":"360 Henry St",
    "sg:city":"Prescott",
    "sg:classifiers":[
        {
            "category":"Building & Trades",
            "subcategory":"Plumbing",
            "type":"Services"
        }
    ],
    "sg:phone":"+1 928 445 8355",
    "sg:postcode":"86301",
    "sg:province":"AZ",
    "sg:tags":[
        "air",
        "heating",
        "conditioning",
        "contractor"
    ],
    "wof:name":"Prescott Sheet Metal Inc",
    "wof:placetype":"venue"
},
  "geometry": {"coordinates":[-112.465188,34.550111],"type":"Point"}
}