{
  "type": "Feature",
  "properties": {
    "iso:country":"US",
    "sg:address":"11 S 69th Ave",
    "sg:city":"Phoenix",
    "sg:classifiers":[
        {
            "category":"Freight",
            "type":"Transportation"
        }
    ],
    "sg:phone":"+1 623 936 1753",
    "sg:postcode":"85043",
    "sg:province":"AZ",
    "sg:tags":[
        "hauling",
        "trucking"
    ],
    "wof:name":"F E Gilbert Trucking",
    "wof:placetype":"venue"
},
  "geometry": {"coordinates":[-112.20681999999999,33.447863],"type":"Point"}
}