{
  "type": "Feature",
  "properties": {
    "iso:country":"US",
    "sg:address":"2408 N 68th Dr",
    "sg:city":"Phoenix",
    "sg:classifiers":[
        {
            "category":"Retail",
            "subcategory":"Repair Shop",
            "type":"Services"
        }
    ],
    "sg:phone":"+1 602 918 7706",
    "sg:postcode":"85035",
    "sg:province":"AZ",
    "sg:tags":[
        "machine",
        "sewing"
    ],
    "wof:name":"KWIK Stitch Repair",
    "wof:placetype":"venue"
},
  "geometry": {"coordinates":[-112.207295,33.47428],"type":"Point"}
}