{
  "type": "Feature",
  "properties": {
    "addr:full":"7271 N Meredith Blvd Tucson AZ 85741",
    "addr:housenumber":"7271",
    "addr:postcode":"85741",
    "addr:street":"N Meredith Blvd",
    "iso:country":"US",
    "sg:address":"7271 N Meredith Blvd",
    "sg:city":"Tucson",
    "sg:classifiers":[
        {
            "category":"Restaurant",
            "type":"Food & Drink"
        }
    ],
    "sg:phone":"+1 520 744 7168",
    "sg:postcode":"85741",
    "sg:province":"AZ",
    "sg:tags":[
        "caterer"
    ],
    "wof:name":"Ellobo Services",
    "wof:placetype":"venue"
},
  "geometry": {"coordinates":[-111.04033699999999,32.339718],"type":"Point"}
}