{
  "type": "Feature",
  "properties": {
    "addr:full":"3645 W Bethany Home Rd Phoenix AZ 85019",
    "addr:housenumber":"3645",
    "addr:postcode":"85019",
    "addr:street":"W Bethany Home Rd",
    "iso:country":"US",
    "sg:address":"3645 W Bethany Home Rd",
    "sg:city":"Phoenix",
    "sg:classifiers":[
        {
            "category":"Social Services",
            "subcategory":"Child Care",
            "type":"Services"
        }
    ],
    "sg:phone":"+1 602 841 7338",
    "sg:postcode":"85019",
    "sg:province":"AZ",
    "wof:name":"Kiddie Country Club Preschool",
    "wof:placetype":"venue"
},
  "geometry": {"coordinates":[-112.13627200000001,33.523891],"type":"Point"}
}