{
  "type": "Feature",
  "properties": {
    "iso:country":"US",
    "sg:address":"116 N Roosevelt Ave",
    "sg:city":"Chandler",
    "sg:classifiers":[
        {
            "category":"Building & Trades",
            "subcategory":"Electrical",
            "type":"Services"
        }
    ],
    "sg:phone":"+1 480 358 0308",
    "sg:postcode":"85226",
    "sg:province":"AZ",
    "sg:tags":[
        "electrical",
        "contractor"
    ],
    "wof:name":"Caps Electric",
    "wof:placetype":"venue"
},
  "geometry": {"coordinates":[-111.951125,33.304026],"type":"Point"}
}