{
  "type": "Feature",
  "properties": {
    "iso:country":"US",
    "sg:address":"18805 S Frontage Rd",
    "sg:city":"Green Valley",
    "sg:classifiers":[
        {
            "category":"Home & Garden",
            "subcategory":"Furniture",
            "type":"Retail Goods"
        }
    ],
    "sg:phone":"+1 520 648 1112",
    "sg:postcode":"85614",
    "sg:province":"AZ",
    "sg:tags":[
        "mattress"
    ],
    "wof:name":"Bed Mart",
    "wof:placetype":"venue"
},
  "geometry": {"coordinates":[-110.985176,31.911303],"type":"Point"}
}