{
  "type": "Feature",
  "properties": {
    "iso:country":"US",
    "sg:address":"2050 S 59th Ave",
    "sg:city":"Phoenix",
    "sg:classifiers":[
        {
            "category":"Freight",
            "type":"Transportation"
        }
    ],
    "sg:phone":"+1 303 288 3673",
    "sg:postcode":"85043",
    "sg:province":"AZ",
    "sg:tags":[
        "operator",
        "trucking"
    ],
    "wof:name":"T & M Transportation Co Inc",
    "wof:placetype":"venue"
},
  "geometry": {"coordinates":[-112.186501,33.429656],"type":"Point"}
}