{
  "type": "Feature",
  "properties": {
    "iso:country":"US",
    "sg:address":"858 W Royal Palms Dr",
    "sg:city":"Gilbert",
    "sg:classifiers":[
        {
            "category":"Professional",
            "subcategory":"Printing & Photocopies",
            "type":"Services"
        }
    ],
    "sg:phone":"+1 602 315 7083",
    "sg:postcode":"85233",
    "sg:province":"AZ",
    "sg:tags":[
        "screen"
    ],
    "wof:name":"C T Designs",
    "wof:placetype":"venue"
},
  "geometry": {"coordinates":[-111.809483,33.340611],"type":"Point"}
}