{
  "type": "Feature",
  "properties": {
    "iso:country":"US",
    "sg:address":"4558 S 6th Ave",
    "sg:city":"Tucson",
    "sg:classifiers":[
        {
            "category":"Local Transit",
            "type":"Transportation"
        }
    ],
    "sg:phone":"+1 520 746 4100",
    "sg:postcode":"85714",
    "sg:province":"AZ",
    "sg:tags":[
        "taxicab"
    ],
    "wof:name":"Rodeo Express",
    "wof:placetype":"venue"
},
  "geometry": {"coordinates":[-110.968112,32.167855],"type":"Point"}
}