{
  "type": "Feature",
  "properties": {
    "iso:country":"US",
    "sg:address":"721 W Portland St",
    "sg:city":"Phoenix",
    "sg:classifiers":[
        {
            "category":"Personal",
            "subcategory":"Beauty Salon",
            "type":"Services"
        }
    ],
    "sg:phone":"+1 602 262 4298",
    "sg:postcode":"85007",
    "sg:province":"AZ",
    "sg:tags":[
        "hair",
        "stylist"
    ],
    "wof:name":"Flamingo Haircutters",
    "wof:placetype":"venue"
},
  "geometry": {"coordinates":[-112.083077,33.459693],"type":"Point"}
}