{
  "type": "Feature",
  "properties": {
    "iso:country":"US",
    "sg:address":"3432 E Las Rocas Dr",
    "sg:city":"Phoenix",
    "sg:classifiers":[
        {
            "category":"Professional",
            "type":"Services"
        }
    ],
    "sg:phone":"+1 602 953 2034",
    "sg:postcode":"85028",
    "sg:province":"AZ",
    "wof:name":"Anchor Aviation LLC",
    "wof:placetype":"venue"
},
  "geometry": {"coordinates":[-112.006953,33.569335],"type":"Point"}
}