{
  "type": "Feature",
  "properties": {
    "iso:country":"US",
    "sg:address":"1550 W Warner Rd",
    "sg:city":"Gilbert",
    "sg:classifiers":[
        {
            "category":"Restaurant",
            "type":"Food & Drink"
        }
    ],
    "sg:phone":"+1 480 539 9986",
    "sg:postcode":"85233",
    "sg:province":"AZ",
    "sg:website":"www.tacobell.com",
    "wof:name":"Taco Bell",
    "wof:placetype":"venue"
},
  "geometry": {"coordinates":[-111.822982,33.335314],"type":"Point"}
}