{
  "type": "Feature",
  "properties": {
    "iso:country":"US",
    "sg:address":"3911 N Highway Dr",
    "sg:city":"Tucson",
    "sg:classifiers":[
        {
            "category":"Home & Garden",
            "subcategory":"Building Materials",
            "type":"Retail Goods"
        }
    ],
    "sg:phone":"+1 520 407 8800",
    "sg:postcode":"85705",
    "sg:province":"AZ",
    "sg:tags":[
        "lumber"
    ],
    "wof:name":"Knipp Brothers Inc",
    "wof:placetype":"venue"
},
  "geometry": {"coordinates":[-111.012016,32.276072],"type":"Point"}
}