{
  "type": "Feature",
  "properties": {
    "iso:country":"US",
    "sg:address":"5255 W Phelps Rd",
    "sg:city":"Glendale",
    "sg:classifiers":[
        {
            "category":"Retail",
            "subcategory":"Portrait Studio",
            "type":"Services"
        }
    ],
    "sg:phone":"+1 602 547 0420",
    "sg:postcode":"85306",
    "sg:province":"AZ",
    "sg:tags":[
        "photographer"
    ],
    "sg:website":"www.lifetouch.com",
    "wof:name":"Lifetouch National Schl Studio",
    "wof:placetype":"venue"
},
  "geometry": {"coordinates":[-112.170496,33.636855],"type":"Point"}
}