{
  "type": "Feature",
  "properties": {
    "iso:country":"US",
    "sg:address":"6410 E State Rte 69",
    "sg:city":"Prescott Valley",
    "sg:classifiers":[
        {
            "category":"Home & Garden",
            "subcategory":"Furniture",
            "type":"Retail Goods"
        }
    ],
    "sg:phone":"+1 928 775 7588",
    "sg:postcode":"86314",
    "sg:province":"AZ",
    "wof:name":"Joanna's Furniture",
    "wof:placetype":"venue"
},
  "geometry": {"coordinates":[-112.352375,34.58126],"type":"Point"}
}