{
  "type": "Feature",
  "properties": {
    "iso:country":"US",
    "sg:address":"3623 S Finch Cir",
    "sg:city":"Sierra Vista",
    "sg:classifiers":[
        {
            "category":"Real Estate",
            "subcategory":"Developer",
            "type":"Services"
        }
    ],
    "sg:phone":"+1 520 378 6991",
    "sg:postcode":"85650",
    "sg:province":"AZ",
    "sg:tags":[
        "mobile",
        "home"
    ],
    "wof:name":"Golden Acres Estates Clubhouse",
    "wof:placetype":"venue"
},
  "geometry": {"coordinates":[-110.243192,31.502929],"type":"Point"}
}