{
  "type": "Feature",
  "properties": {
    "iso:country":"US",
    "sg:address":"9238 W Montana de Oro Dr",
    "sg:city":"Peoria",
    "sg:classifiers":[
        {
            "category":"Home & Garden",
            "subcategory":"Home Furnishings",
            "type":"Retail Goods"
        }
    ],
    "sg:phone":"+1 623 376 8481",
    "sg:postcode":"85383",
    "sg:province":"AZ",
    "sg:tags":[
        "repair"
    ],
    "wof:name":"Peoria Custom Uphl & Shds",
    "wof:placetype":"venue"
},
  "geometry": {"coordinates":[-112.259418,33.697975],"type":"Point"}
}