{
  "type": "Feature",
  "properties": {
    "iso:country":"US",
    "sg:address":"3360 N Country Club Rd",
    "sg:city":"Tucson",
    "sg:classifiers":[
        {
            "category":"Manufacturing",
            "subcategory":"Apparel",
            "type":"Manufacturing & Wholesale Goods"
        }
    ],
    "sg:phone":"+1 520 881 8388",
    "sg:postcode":"85716",
    "sg:province":"AZ",
    "sg:tags":[
        "finishing",
        "plant"
    ],
    "wof:name":"Logotech Inc",
    "wof:placetype":"venue"
},
  "geometry": {"coordinates":[-110.926655,32.265665],"type":"Point"}
}