{
  "type": "Feature",
  "properties": {
    "iso:country":"US",
    "sg:address":"202 W Southern Ave",
    "sg:city":"Tempe",
    "sg:classifiers":[
        {
            "category":"Building & Trades",
            "subcategory":"Cleaning & Sanitation",
            "type":"Services"
        }
    ],
    "sg:phone":"+1 480 394 0039",
    "sg:postcode":"85282",
    "sg:province":"AZ",
    "sg:tags":[
        "house"
    ],
    "sg:website":"www.maids.com",
    "wof:name":"Maids Of Tempe",
    "wof:placetype":"venue"
},
  "geometry": {"coordinates":[-111.94056,33.39295],"type":"Point"}
}