{
  "type": "Feature",
  "properties": {
    "iso:country":"US",
    "sg:address":"1833 W Main St",
    "sg:city":"Mesa",
    "sg:classifiers":[
        {
            "category":"Home & Garden",
            "subcategory":"Furniture",
            "type":"Retail Goods"
        }
    ],
    "sg:phone":"+1 602 644 9307",
    "sg:postcode":"85201",
    "sg:province":"AZ",
    "wof:name":"Bedroom Expressions",
    "wof:placetype":"venue"
},
  "geometry": {"coordinates":[-111.873869,33.414787],"type":"Point"}
}