{
  "type": "Feature",
  "properties": {
    "iso:country":"US",
    "sg:address":"2150 E Huntington Dr",
    "sg:city":"Flagstaff",
    "sg:classifiers":[
        {
            "category":"Manufacturing",
            "subcategory":"Glass & Minerals",
            "type":"Manufacturing & Wholesale Goods"
        }
    ],
    "sg:phone":"+1 928 773 9139",
    "sg:postcode":"86004",
    "sg:province":"AZ",
    "sg:tags":[
        "ready",
        "concrete",
        "mfg"
    ],
    "wof:name":"Flagstaff Aggregate Supply",
    "wof:placetype":"venue"
},
  "geometry": {"coordinates":[-111.624965,35.19412],"type":"Point"}
}