{
  "type": "Feature",
  "properties": {
    "addr:full":"1032 E 7th Ave Mesa AZ 85204",
    "addr:housenumber":"1032",
    "addr:postcode":"85204",
    "addr:street":"E 7Th Ave",
    "iso:country":"US",
    "sg:address":"1032 E 7th Ave",
    "sg:city":"Mesa",
    "sg:classifiers":[
        {
            "category":"Food & Beverages",
            "subcategory":"Bakery",
            "type":"Retail Goods"
        },
        {
            "category":"Wholesale",
            "subcategory":"Groceries",
            "type":"Manufacturing & Wholesale Goods"
        }
    ],
    "sg:phone":"+1 480 964 3143",
    "sg:postcode":"85204",
    "sg:province":"AZ",
    "sg:tags":[
        "cooky",
        "crackers-wholesale",
        "bakers-wholesale",
        "manufacturer"
    ],
    "wof:name":"Lee Cookie",
    "wof:placetype":"venue"
},
  "geometry": {"coordinates":[-111.809029,33.402036],"type":"Point"}
}