{
  "type": "Feature",
  "properties": {
    "iso:country":"US",
    "sg:address":"4211 S 47th St",
    "sg:city":"Phoenix",
    "sg:classifiers":[
        {
            "category":"Building & Trades",
            "subcategory":"Cleaning & Sanitation",
            "type":"Services"
        }
    ],
    "sg:phone":"+1 602 431 8186",
    "sg:postcode":"85040",
    "sg:province":"AZ",
    "sg:tags":[
        "janitor"
    ],
    "wof:name":"J & J Diversified Svc",
    "wof:placetype":"venue"
},
  "geometry": {"coordinates":[-111.98037,33.409388],"type":"Point"}
}