{
  "type": "Feature",
  "properties": {
    "iso:country":"US",
    "sg:address":"640 W McKellips Rd",
    "sg:city":"Mesa",
    "sg:classifiers":[
        {
            "category":"Retail",
            "subcategory":"Auto Rental",
            "type":"Services"
        }
    ],
    "sg:phone":"+1 480 461 5916",
    "sg:postcode":"85201",
    "sg:province":"AZ",
    "sg:tags":[
        "renting",
        "truck",
        "leasing"
    ],
    "wof:name":"Budget Truck Rental",
    "wof:placetype":"venue"
},
  "geometry": {"coordinates":[-111.84206,33.451501],"type":"Point"}
}