{
  "type": "Feature",
  "properties": {
    "iso:country":"US",
    "sg:address":"3125 S 52nd St",
    "sg:city":"Tempe",
    "sg:classifiers":[
        {
            "category":"Building & Trades",
            "subcategory":"Construction",
            "type":"Services"
        }
    ],
    "sg:phone":"+1 602 453 8973",
    "sg:postcode":"85282",
    "sg:province":"AZ",
    "sg:tags":[
        "general",
        "contractor"
    ],
    "wof:name":"Novus Construction LLC",
    "wof:placetype":"venue"
},
  "geometry": {"coordinates":[-111.970557,33.395471],"type":"Point"}
}