{
  "type": "Feature",
  "properties": {
    "iso:country":"US",
    "sg:address":"301 S May Ave",
    "sg:city":"Yuma",
    "sg:classifiers":[
        {
            "category":"Mining & Drilling",
            "type":"Manufacturing & Wholesale Goods"
        }
    ],
    "sg:phone":"+1 928 785 4584",
    "sg:postcode":"85364",
    "sg:province":"AZ",
    "sg:tags":[
        "construction"
    ],
    "wof:name":"Tacna Sand & Gravel LLC",
    "wof:placetype":"venue"
},
  "geometry": {"coordinates":[-114.658974,32.722606],"type":"Point"}
}