{
  "type": "Feature",
  "properties": {
    "iso:country":"US",
    "sg:address":"7408 W Bloomfield Rd",
    "sg:city":"Peoria",
    "sg:classifiers":[
        {
            "category":"Building & Trades",
            "subcategory":"Landscaping Services",
            "type":"Services"
        }
    ],
    "sg:phone":"+1 623 203 2388",
    "sg:postcode":"85381",
    "sg:province":"AZ",
    "sg:tags":[
        "lawn",
        "maintenance"
    ],
    "wof:name":"Bill Quegan's Lawn Service",
    "wof:placetype":"venue"
},
  "geometry": {"coordinates":[-112.218505,33.598118],"type":"Point"}
}