{
  "type": "Feature",
  "properties": {
    "addr:full":"1270 N Industrial Park Ave Nogales AZ 85621",
    "addr:housenumber":"1270",
    "addr:postcode":"85621",
    "addr:street":"N Industrial Park Ave",
    "iso:country":"US",
    "sg:address":"1270 N Industrial Park Ave",
    "sg:city":"Nogales",
    "sg:classifiers":[
        {
            "category":"Shopping",
            "subcategory":"Discount & Variety Stores",
            "type":"Retail Goods"
        }
    ],
    "sg:phone":"+1 520 281 1508",
    "sg:postcode":"85621",
    "sg:province":"AZ",
    "sg:tags":[
        "merchandise",
        "general"
    ],
    "wof:name":"Cella Imports",
    "wof:placetype":"venue"
},
  "geometry": {"coordinates":[-110.95871099999999,31.35293],"type":"Point"}
}