{
  "type": "Feature",
  "properties": {
    "iso:country":"US",
    "sg:address":"7575 N 16th St",
    "sg:city":"Phoenix",
    "sg:classifiers":[
        {
            "category":"Personal",
            "subcategory":"Beauty Salon",
            "type":"Services"
        },
        {
            "category":"Personal",
            "subcategory":"Day Spa",
            "type":"Services"
        }
    ],
    "sg:phone":"+1 602 795 3338",
    "sg:postcode":"85020",
    "sg:province":"AZ",
    "sg:tags":[
        "hair",
        "stylist"
    ],
    "sg:website":"http://Enchantmentssalon.com",
    "wof:name":"Enchantments Salon And Day Spa",
    "wof:placetype":"venue"
},
  "geometry": {"coordinates":[-112.047625,33.546963],"type":"Point"}
}