{
  "type": "Feature",
  "properties": {
    "iso:country":"US",
    "sg:address":"1229 E Mckellips Rd Ste 1",
    "sg:city":"Mesa",
    "sg:classifiers":[
        {
            "category":"Utilities",
            "subcategory":"Mobile Phone",
            "type":"Services"
        },
        {
            "category":"Coffee & Tea",
            "type":"Food & Drink"
        }
    ],
    "sg:phone":"+1 480 833 0056",
    "sg:postcode":"85203",
    "sg:province":"AZ",
    "sg:tags":[
        "shop",
        "restaurant",
        "espresso",
        "hotspot",
        "wi-fi"
    ],
    "sg:website":"http://www.starbuckscoffee.com",
    "wof:name":"Starbucks Coffee",
    "wof:placetype":"venue"
},
  "geometry": {"coordinates":[-111.804286,33.45151],"type":"Point"}
}