{
  "type": "Feature",
  "properties": {
    "iso:country":"US",
    "sg:address":"13439 N Cave Creek Rd # 4",
    "sg:city":"Phoenix",
    "sg:classifiers":[
        {
            "category":"Shopping",
            "subcategory":"Jewelry",
            "type":"Retail Goods"
        },
        {
            "category":"Manufacturing",
            "subcategory":"Jewelry",
            "type":"Manufacturing & Wholesale Goods"
        }
    ],
    "sg:phone":"+1 602 765 7227",
    "sg:postcode":"85022",
    "sg:province":"AZ",
    "sg:tags":[
        "manufacturer",
        "designer",
        "jewelers-wholesale",
        "jeweler"
    ],
    "sg:website":"http://www.jostens.com",
    "wof:name":"Jostens, Inc.",
    "wof:placetype":"venue"
},
  "geometry": {"coordinates":[-112.036179,33.609138],"type":"Point"}
}