{
  "type": "Feature",
  "properties": {
    "iso:country":"US",
    "sg:address":"54 W Rio Solado Pkwy",
    "sg:city":"Tempe",
    "sg:classifiers":[
        {
            "category":"Arts & Performance",
            "subcategory":"Theater",
            "type":"Entertainment"
        }
    ],
    "sg:phone":"+1 480 921 2918",
    "sg:postcode":"85281",
    "sg:province":"AZ",
    "sg:tags":[
        "bureau"
    ],
    "wof:name":"Entertainment Solutions",
    "wof:placetype":"venue"
},
  "geometry": {"coordinates":[-111.94118,33.432775],"type":"Point"}
}