{
  "type": "Feature",
  "properties": {
    "iso:country":"US",
    "sg:address":"1404 E Prince Rd",
    "sg:city":"Tucson",
    "sg:classifiers":[
        {
            "category":"Health Services",
            "subcategory":"Doctor",
            "type":"Services"
        }
    ],
    "sg:phone":"+1 520 327 7494",
    "sg:postcode":"85719",
    "sg:province":"AZ",
    "sg:tags":[
        "physician",
        "surgeon"
    ],
    "wof:name":"Tucson Cardiology LTD",
    "wof:placetype":"venue"
},
  "geometry": {"coordinates":[-110.949392,32.272094],"type":"Point"}
}