{
  "type": "Feature",
  "properties": {
    "iso:country":"US",
    "sg:address":"1389 E Canyon Way",
    "sg:city":"Chandler",
    "sg:classifiers":[
        {
            "category":"Professional",
            "type":"Services"
        }
    ],
    "sg:phone":"+1 480 802 7199",
    "sg:postcode":"85249",
    "sg:province":"AZ",
    "wof:name":"Arizona Exterior Feng Shui",
    "wof:placetype":"venue"
},
  "geometry": {"coordinates":[-111.81734899999999,33.239192],"type":"Point"}
}