{
  "type": "Feature",
  "properties": {
    "addr:full":"10217 N Metro Pkwy Phoenix AZ 85051",
    "addr:housenumber":"10217",
    "addr:postcode":"85051",
    "addr:street":"N Metro Pkwy",
    "iso:country":"US",
    "sg:address":"10217 N Metro Pkwy",
    "sg:city":"Phoenix",
    "sg:classifiers":[
        {
            "category":"Food & Beverages",
            "subcategory":"Specialty",
            "type":"Retail Goods"
        },
        {
            "category":"Restaurant",
            "type":"Food & Drink"
        }
    ],
    "sg:phone":"+1 602 692 7879",
    "sg:postcode":"85051",
    "sg:province":"AZ",
    "sg:tags":[
        "tea",
        "coffee",
        "eating"
    ],
    "wof:name":"Java Metro Caffe Corp",
    "wof:placetype":"venue"
},
  "geometry": {"coordinates":[-112.121683,33.579445],"type":"Point"}
}