{
  "type": "Feature",
  "properties": {
    "iso:country":"US",
    "sg:address":"1 W Campbell Ave",
    "sg:city":"Phoenix",
    "sg:classifiers":[
        {
            "category":"Professional",
            "type":"Services"
        }
    ],
    "sg:phone":"+1 602 674 3449",
    "sg:postcode":"85013",
    "sg:province":"AZ",
    "wof:name":"Rob Woodfill",
    "wof:placetype":"venue"
},
  "geometry": {"coordinates":[-112.074912,33.502046],"type":"Point"}
}