{
  "type": "Feature",
  "properties": {
    "iso:country":"US",
    "sg:address":"3751 S Clubhouse Dr",
    "sg:city":"Chandler",
    "sg:classifiers":[
        {
            "category":"Restaurant",
            "type":"Food & Drink"
        },
        {
            "category":"Sports & Exercise",
            "subcategory":"Golf",
            "type":"Entertainment"
        }
    ],
    "sg:phone":"+1 480 917 6660",
    "sg:postcode":"85248",
    "sg:province":"AZ",
    "sg:tags":[
        "traditional",
        "american"
    ],
    "sg:website":"www.ocotillogolf.com",
    "wof:name":"Ocotillo Golf Resort & Bernard's Fine Dining",
    "wof:placetype":"venue"
},
  "geometry": {"coordinates":[-111.868433,33.254746],"type":"Point"}
}