{
  "type": "Feature",
  "properties": {
    "addr:full":"1321 E Don Carlos Ave Tempe AZ 85281",
    "addr:housenumber":"1321",
    "addr:postcode":"85281",
    "addr:street":"E Don Carlos Ave",
    "iso:country":"US",
    "sg:address":"1321 E Don Carlos Ave",
    "sg:city":"Tempe",
    "sg:classifiers":[
        {
            "category":"Manufacturing",
            "subcategory":"Metals",
            "type":"Manufacturing & Wholesale Goods"
        }
    ],
    "sg:phone":"+1 480 968 2920",
    "sg:postcode":"85281",
    "sg:province":"AZ",
    "sg:tags":[
        "fabrication",
        "structural"
    ],
    "wof:name":"Ferguson Fabrication Inc",
    "wof:placetype":"venue"
},
  "geometry": {"coordinates":[-111.915198,33.417582],"type":"Point"}
}