{
  "type": "Feature",
  "properties": {
    "iso:country":"US",
    "sg:address":"6872 E Sunrise Dr",
    "sg:city":"Tucson",
    "sg:classifiers":[
        {
            "category":"Real Estate",
            "subcategory":"Real Estate Agent",
            "type":"Services"
        }
    ],
    "sg:phone":"+1 520 247 3999",
    "sg:postcode":"85750",
    "sg:province":"AZ",
    "wof:name":"Cahan Team",
    "wof:placetype":"venue"
},
  "geometry": {"coordinates":[-110.845794,32.308761],"type":"Point"}
}