{
  "type": "Feature",
  "properties": {
    "iso:country":"US",
    "sg:address":"4545 N 36th St",
    "sg:city":"Phoenix",
    "sg:classifiers":[
        {
            "category":"Professional",
            "subcategory":"Detective & Security Services",
            "type":"Services"
        }
    ],
    "sg:phone":"+1 602 258 7128",
    "sg:postcode":"85018",
    "sg:province":"AZ",
    "sg:tags":[
        "guard",
        "patrol"
    ],
    "wof:name":"Cramer Security",
    "wof:placetype":"venue"
},
  "geometry": {"coordinates":[-112.004089,33.504764],"type":"Point"}
}