{
  "type": "Feature",
  "properties": {
    "addr:full":"903 S Rural Rd Tempe AZ 85281",
    "addr:housenumber":"903",
    "addr:postcode":"85281",
    "addr:street":"S Rural Rd",
    "iso:country":"US",
    "sg:address":"903 S Rural Rd",
    "sg:city":"Tempe",
    "sg:classifiers":[
        {
            "category":"Restaurant",
            "type":"Food & Drink"
        }
    ],
    "sg:menulink":"http://www.allmenus.com/az/phoenix/69405-dominos-pizza/menu/",
    "sg:phone":"+1 480 968 5555",
    "sg:postcode":"85281",
    "sg:province":"AZ",
    "sg:tags":[
        "american",
        "wing",
        "pizza"
    ],
    "wof:name":"Domino's Pizza",
    "wof:placetype":"venue"
},
  "geometry": {"coordinates":[-111.92586,33.420181],"type":"Point"}
}