{
  "type": "Feature",
  "properties": {
    "iso:country":"US",
    "sg:address":"4836 W Snowberry Ln",
    "sg:city":"Tucson",
    "sg:classifiers":[
        {
            "category":"Bars & Pubs",
            "type":"Food & Drink"
        }
    ],
    "sg:phone":"+1 520 887 3096",
    "sg:postcode":"85742",
    "sg:province":"AZ",
    "sg:tags":[
        "lounge",
        "cocktail"
    ],
    "wof:name":"Sports Page Lounge",
    "wof:placetype":"venue"
},
  "geometry": {"coordinates":[-111.068003,32.364185],"type":"Point"}
}