{
  "type": "Feature",
  "properties": {
    "iso:country":"US",
    "sg:address":"618 E Germann Rd",
    "sg:city":"Gilbert",
    "sg:classifiers":[
        {
            "category":"Professional",
            "subcategory":"Business Services",
            "type":"Services"
        }
    ],
    "sg:phone":"+1 480 882 9984",
    "sg:postcode":"85297",
    "sg:province":"AZ",
    "sg:tags":[
        "appraiser"
    ],
    "sg:website":"http://www.azmetromix.com",
    "wof:name":"Arizona Metro Mix",
    "wof:placetype":"venue"
},
  "geometry": {"coordinates":[-111.686226,33.278191],"type":"Point"}
}