{
  "type": "Feature",
  "properties": {
    "addr:full":"1421 E Birch St Cottonwood AZ 86326",
    "addr:housenumber":"1421",
    "addr:postcode":"86326",
    "addr:street":"E Birch St",
    "iso:country":"US",
    "sg:address":"1421 E Birch St",
    "sg:city":"Cottonwood",
    "sg:classifiers":[
        {
            "category":"Manufacturing",
            "subcategory":"Electronics",
            "type":"Manufacturing & Wholesale Goods"
        }
    ],
    "sg:phone":"+1 928 634 6450",
    "sg:postcode":"86326",
    "sg:province":"AZ",
    "sg:tags":[
        "electronic",
        "component",
        "mfg"
    ],
    "wof:name":"Cooler Pad",
    "wof:placetype":"venue"
},
  "geometry": {"coordinates":[-112.011968,34.733925],"type":"Point"}
}