{
  "type": "Feature",
  "properties": {
    "iso:country":"US",
    "sg:address":"3950 E Blacklidge Dr",
    "sg:city":"Tucson",
    "sg:classifiers":[
        {
            "category":"Retail",
            "subcategory":"Animal Services",
            "type":"Services"
        }
    ],
    "sg:phone":"+1 520 326 5116",
    "sg:postcode":"85712",
    "sg:province":"AZ",
    "wof:name":"Craig Messina",
    "wof:placetype":"venue"
},
  "geometry": {"coordinates":[-110.909806,32.261491],"type":"Point"}
}