{
  "type": "Feature",
  "properties": {
    "iso:country":"US",
    "sg:address":"14427 W Mandalay Ln",
    "sg:city":"Surprise",
    "sg:classifiers":[
        {
            "category":"Building & Trades",
            "subcategory":"Construction",
            "type":"Services"
        }
    ],
    "sg:phone":"+1 623 544 1540",
    "sg:postcode":"85379",
    "sg:province":"AZ",
    "sg:tags":[
        "house"
    ],
    "wof:name":"Fulton Homes",
    "wof:placetype":"venue"
},
  "geometry": {"coordinates":[-112.371354,33.616197],"type":"Point"}
}