{
  "type": "Feature",
  "properties": {
    "iso:country":"US",
    "sg:address":"818 S 30th Ave",
    "sg:city":"Phoenix",
    "sg:classifiers":[
        {
            "category":"Building & Trades",
            "subcategory":"Construction",
            "type":"Services"
        }
    ],
    "sg:phone":"+1 602 992 4820",
    "sg:postcode":"85009",
    "sg:province":"AZ",
    "sg:tags":[
        "house"
    ],
    "wof:name":"Tomorrows Homebuilders LLC",
    "wof:placetype":"venue"
},
  "geometry": {"coordinates":[-112.123887,33.438146],"type":"Point"}
}