{
  "type": "Feature",
  "properties": {
    "iso:country":"US",
    "sg:address":"4201 E Camelback Rd",
    "sg:city":"Phoenix",
    "sg:classifiers":[
        {
            "category":"Manufacturing",
            "subcategory":"Textiles",
            "type":"Manufacturing & Wholesale Goods"
        }
    ],
    "sg:phone":"+1 602 957 8962",
    "sg:postcode":"85018",
    "sg:province":"AZ",
    "sg:tags":[
        "tile",
        "mfg",
        "carpet"
    ],
    "wof:name":"Interface Flooring Systems",
    "wof:placetype":"venue"
},
  "geometry": {"coordinates":[-111.990076,33.509639],"type":"Point"}
}