{
  "type": "Feature",
  "properties": {
    "iso:country":"US",
    "sg:address":"7142 E 5th Ave",
    "sg:city":"Scottsdale",
    "sg:classifiers":[
        {
            "category":"Shopping",
            "subcategory":"Gifts & Souvenirs",
            "type":"Retail Goods"
        }
    ],
    "sg:phone":"+1 480 947 1997",
    "sg:postcode":"85251",
    "sg:province":"AZ",
    "wof:name":"Two Gray Hills",
    "wof:placetype":"venue"
},
  "geometry": {"coordinates":[-111.926412,33.498285],"type":"Point"}
}