{
  "type": "Feature",
  "properties": {
    "addr:full":"1027 W Whitten St Chandler AZ 85224",
    "addr:housenumber":"1027",
    "addr:postcode":"85224",
    "addr:street":"W Whitten St",
    "iso:country":"US",
    "sg:address":"1027 W Whitten St",
    "sg:city":"Chandler",
    "sg:classifiers":[
        {
            "category":"Donuts",
            "subcategory":"None",
            "type":"Food & Drink"
        }
    ],
    "sg:phone":"+1 480 747 1726",
    "sg:postcode":"85224",
    "sg:province":"AZ",
    "sg:website":"www.nanisfunfoods.com",
    "wof:name":"Nani's Fun Foods",
    "wof:placetype":"venue"
},
  "geometry": {"coordinates":[-111.860052,33.29613],"type":"Point"}
}