{
  "type": "Feature",
  "properties": {
    "addr:full":"4820 W Palo Verde Dr Glendale AZ 85301",
    "addr:housenumber":"4820",
    "addr:postcode":"85301",
    "addr:street":"W Palo Verde Dr",
    "iso:country":"US",
    "sg:address":"4820 W Palo Verde Dr",
    "sg:city":"Glendale",
    "sg:classifiers":[
        {
            "category":"Real Estate",
            "subcategory":"Real Estate Agent",
            "type":"Services"
        }
    ],
    "sg:phone":"+1 623 842 1010",
    "sg:postcode":"85301",
    "sg:province":"AZ",
    "sg:tags":[
        "manager"
    ],
    "wof:name":"Villas West",
    "wof:placetype":"venue"
},
  "geometry": {"coordinates":[-112.16353700000001,33.523633],"type":"Point"}
}