{
  "type": "Feature",
  "properties": {
    "iso:country":"US",
    "sg:address":"5660 N Kolb Rd",
    "sg:city":"Tucson",
    "sg:classifiers":[
        {
            "category":"Social Services",
            "subcategory":"Adult Care",
            "type":"Services"
        }
    ],
    "sg:phone":"+1 520 577 6940",
    "sg:postcode":"85750",
    "sg:province":"AZ",
    "sg:tags":[
        "home",
        "residential"
    ],
    "wof:name":"Epoch Assisted Living",
    "wof:placetype":"venue"
},
  "geometry": {"coordinates":[-110.844324,32.309606],"type":"Point"}
}