{
  "type": "Feature",
  "properties": {
    "iso:country":"US",
    "sg:address":"4302 E Lone Mountain Rd",
    "sg:city":"Cave Creek",
    "sg:classifiers":[
        {
            "category":"Building & Trades",
            "subcategory":"Landscaping Services",
            "type":"Services"
        }
    ],
    "sg:phone":"+1 480 488 8700",
    "sg:postcode":"85331",
    "sg:province":"AZ",
    "sg:tags":[
        "landscape",
        "contractor"
    ],
    "wof:name":"Superior Ldscp Specialists Inc",
    "wof:placetype":"venue"
},
  "geometry": {"coordinates":[-111.98697,33.770147],"type":"Point"}
}