{
  "type": "Feature",
  "properties": {
    "iso:country":"US",
    "sg:address":"5917 E Pima St",
    "sg:city":"Tucson",
    "sg:classifiers":[
        {
            "category":"Personal",
            "subcategory":"Barber",
            "type":"Services"
        }
    ],
    "sg:phone":"+1 520 885 7599",
    "sg:postcode":"85712",
    "sg:province":"AZ",
    "wof:name":"Terry's Barber Shop",
    "wof:placetype":"venue"
},
  "geometry": {"coordinates":[-110.86553000000001,32.243467],"type":"Point"}
}