{
  "type": "Feature",
  "properties": {
    "iso:country":"US",
    "sg:address":"1628 Coyote Rd",
    "sg:city":"Prescott",
    "sg:classifiers":[
        {
            "category":"Freight",
            "type":"Transportation"
        }
    ],
    "sg:phone":"+1 928 717 1957",
    "sg:postcode":"86303",
    "sg:province":"AZ",
    "sg:tags":[
        "operator",
        "trucking"
    ],
    "wof:name":"Ligon Nationwide Truck Lines",
    "wof:placetype":"venue"
},
  "geometry": {"coordinates":[-112.466047,34.514981],"type":"Point"}
}