{
  "type": "Feature",
  "properties": {
    "addr:full":"18826 Grandview Dr Sun City West AZ 85375",
    "addr:housenumber":"18826",
    "addr:postcode":"85375",
    "addr:street":"Grandview Dr",
    "iso:country":"US",
    "sg:address":"18826 Grandview Dr",
    "sg:city":"Sun City West",
    "sg:classifiers":[
        {
            "category":"Banks & Credit Unions",
            "subcategory":"Financial Services",
            "type":"Services"
        }
    ],
    "sg:phone":"+1 623 584 4500",
    "sg:postcode":"85375",
    "sg:province":"AZ",
    "sg:tags":[
        "investor"
    ],
    "wof:name":"Snell Family Investments LP",
    "wof:placetype":"venue"
},
  "geometry": {"coordinates":[-112.36627900000001,33.656361],"type":"Point"}
}