{
  "type": "Feature",
  "properties": {
    "iso:country":"US",
    "sg:address":"1436 E Vermont Ave",
    "sg:city":"Phoenix",
    "sg:classifiers":[
        {
            "category":"Wholesale",
            "subcategory":"Furniture",
            "type":"Manufacturing & Wholesale Goods"
        },
        {
            "category":"Building & Trades",
            "subcategory":"Construction",
            "type":"Services"
        }
    ],
    "sg:phone":"+1 602 263 9461",
    "sg:postcode":"85014",
    "sg:province":"AZ",
    "sg:tags":[
        "grandstand",
        "bleachers",
        "installation"
    ],
    "wof:name":"Danco Specialties Inc",
    "wof:placetype":"venue"
},
  "geometry": {"coordinates":[-112.050763,33.515575],"type":"Point"}
}