{
  "type": "Feature",
  "properties": {
    "addr:full":"8426 W Aster Dr Peoria AZ 85381",
    "addr:housenumber":"8426",
    "addr:postcode":"85381",
    "addr:street":"W Aster Dr",
    "iso:country":"US",
    "sg:address":"8426 W Aster Dr",
    "sg:city":"Peoria",
    "sg:classifiers":[
        {
            "category":"Autos & Motor Vehicles",
            "subcategory":"Auto Supplies",
            "type":"Retail Goods"
        }
    ],
    "sg:phone":"+1 623 878 7238",
    "sg:postcode":"85381",
    "sg:province":"AZ",
    "wof:name":"Sun Cities Tire & Auto",
    "wof:placetype":"venue"
},
  "geometry": {"coordinates":[-112.240871,33.601241],"type":"Point"}
}