{
  "type": "Feature",
  "properties": {
    "iso:country":"US",
    "sg:address":"16845 N 29th Ave",
    "sg:city":"Phoenix",
    "sg:classifiers":[
        {
            "category":"Utilities",
            "subcategory":"Mobile Phone",
            "type":"Services"
        }
    ],
    "sg:phone":"+1 602 504 1900",
    "sg:postcode":"85053",
    "sg:province":"AZ",
    "sg:tags":[
        "telephone",
        "cellular"
    ],
    "wof:name":"Planet Wireless",
    "wof:placetype":"venue"
},
  "geometry": {"coordinates":[-112.12139,33.638635],"type":"Point"}
}