{
  "type": "Feature",
  "properties": {
    "iso:country":"US",
    "sg:address":"1325 N Melba Ct",
    "sg:city":"Gilbert",
    "sg:classifiers":[
        {
            "category":"Professional",
            "type":"Services"
        }
    ],
    "sg:phone":"+1 480 222 0285",
    "sg:postcode":"85233",
    "sg:province":"AZ",
    "sg:tags":[
        "novelty",
        "neon"
    ],
    "sg:website":"http://www.plasmaglow.com",
    "wof:name":"Plasmaglow Neon",
    "wof:placetype":"venue"
},
  "geometry": {"coordinates":[-111.813362,33.374584],"type":"Point"}
}