{
  "type": "Feature",
  "properties": {
    "iso:country":"US",
    "sg:address":"261 N Kenneth Pl",
    "sg:city":"Chandler",
    "sg:classifiers":[
        {
            "category":"Building & Trades",
            "subcategory":"Construction",
            "type":"Services"
        }
    ],
    "sg:phone":"+1 480 940 9303",
    "sg:postcode":"85226",
    "sg:province":"AZ",
    "sg:tags":[
        "painter"
    ],
    "wof:name":"Color FX, Inc",
    "wof:placetype":"venue"
},
  "geometry": {"coordinates":[-111.920196,33.30648],"type":"Point"}
}