{
  "type": "Feature",
  "properties": {
    "iso:country":"US",
    "sg:address":"447 W Watkins St",
    "sg:city":"Phoenix",
    "sg:classifiers":[
        {
            "category":"Freight",
            "type":"Transportation"
        }
    ],
    "sg:phone":"+1 602 254 3548",
    "sg:postcode":"85003",
    "sg:province":"AZ",
    "sg:tags":[
        "moving",
        "mover",
        "storage"
    ],
    "wof:name":"Mountain Moving & Storage Co",
    "wof:placetype":"venue"
},
  "geometry": {"coordinates":[-112.078695,33.4258],"type":"Point"}
}