{
  "type": "Feature",
  "properties": {
    "iso:country":"US",
    "sg:address":"15000 N Hayden Rd",
    "sg:city":"Scottsdale",
    "sg:classifiers":[
        {
            "category":"Home & Garden",
            "subcategory":"Furniture",
            "type":"Retail Goods"
        }
    ],
    "sg:phone":"+1 480 355 6050",
    "sg:postcode":"85260",
    "sg:province":"AZ",
    "wof:name":"Absolute Home",
    "wof:placetype":"venue"
},
  "geometry": {"coordinates":[-111.905518,33.622261],"type":"Point"}
}