{
  "type": "Feature",
  "properties": {
    "iso:country":"US",
    "sg:address":"9331 E Sands Dr",
    "sg:city":"Scottsdale",
    "sg:classifiers":[
        {
            "category":"Autos & Motor Vehicles",
            "subcategory":"Automobile Sales",
            "type":"Retail Goods"
        }
    ],
    "sg:phone":"+1 480 315 0829",
    "sg:postcode":"85255",
    "sg:province":"AZ",
    "sg:tags":[
        "aircraft"
    ],
    "sg:website":"www.jmcaviation.com",
    "wof:name":"JMC Aviation",
    "wof:placetype":"venue"
},
  "geometry": {"coordinates":[-111.880318,33.686403],"type":"Point"}
}