{
  "type": "Feature",
  "properties": {
    "addr:full":"2075 Montezuma Heights Rd Camp Verde AZ 86322",
    "addr:housenumber":"2075",
    "addr:postcode":"az 86322",
    "addr:street":"Montezuma Heights Rd",
    "iso:country":"US",
    "sg:address":"2075 Montezuma Heights Rd",
    "sg:city":"Camp Verde",
    "sg:classifiers":[
        {
            "category":"Building & Trades",
            "subcategory":"Construction",
            "type":"Services"
        }
    ],
    "sg:phone":"+1 928 554 0110",
    "sg:postcode":"86322",
    "sg:province":"AZ",
    "sg:tags":[
        "dry wall",
        "contractor"
    ],
    "wof:name":"Scott Brothers Drywall",
    "wof:placetype":"venue"
},
  "geometry": {"coordinates":[-111.864588,34.597539],"type":"Point"}
}