{
  "type": "Feature",
  "properties": {
    "iso:country":"US",
    "sg:address":"115 W Baseline Rd",
    "sg:city":"Gilbert",
    "sg:classifiers":[
        {
            "category":"Manufacturing",
            "subcategory":"Tools & Machinery",
            "type":"Manufacturing & Wholesale Goods"
        }
    ],
    "sg:phone":"+1 480 926 0979",
    "sg:postcode":"85233",
    "sg:province":"AZ",
    "sg:tags":[
        "building",
        "equipment",
        "construction"
    ],
    "wof:name":"Hughes Supply Inc",
    "wof:placetype":"venue"
},
  "geometry": {"coordinates":[-111.83443,33.378729],"type":"Point"}
}