{
  "type": "Feature",
  "properties": {
    "iso:country":"US",
    "sg:address":"4222 E Thomas Rd",
    "sg:city":"Phoenix",
    "sg:classifiers":[
        {
            "category":"Building & Trades",
            "subcategory":"Construction",
            "type":"Services"
        }
    ],
    "sg:phone":"+1 602 224 5050",
    "sg:postcode":"85018",
    "sg:province":"AZ",
    "sg:tags":[
        "contractor",
        "commercial",
        "general"
    ],
    "sg:website":"www.holderconstruction.com",
    "wof:name":"Holder Construction Company",
    "wof:placetype":"venue"
},
  "geometry": {"coordinates":[-111.98965800000001,33.480404],"type":"Point"}
}