{
  "type": "Feature",
  "properties": {
    "iso:country":"US",
    "sg:address":"1500 E Valencia Rd",
    "sg:city":"Tucson",
    "sg:classifiers":[
        {
            "category":"Travel",
            "subcategory":"Travel Agent",
            "type":"Entertainment"
        }
    ],
    "sg:phone":"+1 520 889 4966",
    "sg:postcode":"85706",
    "sg:province":"AZ",
    "sg:tags":[
        "agency"
    ],
    "wof:name":"Alamo Travel & Tour",
    "wof:placetype":"venue"
},
  "geometry": {"coordinates":[-110.949083,32.134104],"type":"Point"}
}