{
  "type": "Feature",
  "properties": {
    "addr:full":"2504 N 3rd St Phoenix AZ 85004",
    "addr:housenumber":"2504",
    "addr:postcode":"85004",
    "addr:street":"N 3Rd St",
    "iso:country":"US",
    "sg:address":"2504 N 3rd St",
    "sg:city":"Phoenix",
    "sg:classifiers":[
        {
            "category":"Professional",
            "subcategory":"Lawyer & Legal Services",
            "type":"Services"
        }
    ],
    "sg:phone":"+1 602 341 5967",
    "sg:postcode":"85004",
    "sg:province":"AZ",
    "sg:tags":[
        "personal",
        "attorney",
        "injury",
        "law"
    ],
    "sg:website":"http://www.arizonapilawyer.com",
    "wof:name":"Wilmer Thomas C PC",
    "wof:placetype":"venue"
},
  "geometry": {"coordinates":[-112.06943699999999,33.474545],"type":"Point"}
}