{
  "type": "Feature",
  "properties": {
    "iso:country":"US",
    "sg:address":"1566 Palace Way",
    "sg:city":"Lake Havasu City",
    "sg:classifiers":[
        {
            "category":"Shopping",
            "subcategory":"Bicycles & Sporting Goods",
            "type":"Retail Goods"
        }
    ],
    "sg:phone":"+1 928 505 4922",
    "sg:postcode":"86403",
    "sg:province":"AZ",
    "sg:tags":[
        "ski",
        "jet"
    ],
    "wof:name":"Place Diverter & Controls",
    "wof:placetype":"venue"
},
  "geometry": {"coordinates":[-114.341523,34.467727],"type":"Point"}
}