{
  "type": "Feature",
  "properties": {
    "iso:country":"US",
    "sg:address":"1145 Marina Blvd",
    "sg:city":"Bullhead City",
    "sg:classifiers":[
        {
            "category":"Health Services",
            "subcategory":"Hospital",
            "type":"Services"
        }
    ],
    "sg:phone":"+1 928 758 5905",
    "sg:postcode":"86442",
    "sg:province":"AZ",
    "sg:tags":[
        "mental"
    ],
    "wof:name":"Mohave Mental Health Clinic",
    "wof:placetype":"venue"
},
  "geometry": {"coordinates":[-114.605839,35.100636],"type":"Point"}
}