{
  "type": "Feature",
  "properties": {
    "iso:country":"US",
    "sg:address":"3745 E Illini St",
    "sg:city":"Phoenix",
    "sg:classifiers":[
        {
            "category":"Manufacturing",
            "subcategory":"Printing",
            "type":"Manufacturing & Wholesale Goods"
        }
    ],
    "sg:phone":"+1 602 426 9299",
    "sg:postcode":"85040",
    "sg:province":"AZ",
    "sg:tags":[
        "lithographic",
        "commercial"
    ],
    "wof:name":"Globe Instant Ofc",
    "wof:placetype":"venue"
},
  "geometry": {"coordinates":[-112.000051,33.411812],"type":"Point"}
}