{
  "type": "Feature",
  "properties": {
    "iso:country":"US",
    "sg:address":"14350 N Frank Lloyd Wright Blvd",
    "sg:city":"Scottsdale",
    "sg:classifiers":[
        {
            "category":"Banks & Credit Unions",
            "subcategory":"Bank",
            "type":"Services"
        }
    ],
    "sg:phone":"+1 480 477 6444",
    "sg:postcode":"85260",
    "sg:province":"AZ",
    "sg:tags":[
        "loan",
        "real estate"
    ],
    "wof:name":"Markour Funding & Invstmnt Inc",
    "wof:placetype":"venue"
},
  "geometry": {"coordinates":[-111.868507,33.61375],"type":"Point"}
}