{
  "type": "Feature",
  "properties": {
    "addr:full":"1520 S Dobson Rd Mesa AZ 85202",
    "addr:housenumber":"1520",
    "addr:postcode":"85202",
    "addr:street":"S Dobson Rd",
    "iso:country":"US",
    "sg:address":"1520 S Dobson Rd",
    "sg:city":"Mesa",
    "sg:classifiers":[
        {
            "category":"Health Services",
            "subcategory":"Doctor",
            "type":"Services"
        }
    ],
    "sg:phone":"+1 480 835 6100",
    "sg:postcode":"85202",
    "sg:province":"AZ",
    "sg:tags":[
        "cardiologist"
    ],
    "sg:website":"www.tricitycardiology.com",
    "wof:name":"Kaplan Andrew J MD Facc",
    "wof:placetype":"venue"
},
  "geometry": {"coordinates":[-111.876999,33.382999],"type":"Point"}
}