{
  "type": "Feature",
  "properties": {
    "addr:full":"3145 E Chandler Blvd Phoenix AZ 85048",
    "addr:housenumber":"3145",
    "addr:postcode":"85048",
    "addr:street":"E Chandler Blvd",
    "iso:country":"US",
    "sg:address":"3145 E Chandler Blvd",
    "sg:city":"Phoenix",
    "sg:classifiers":[
        {
            "category":"Shopping",
            "subcategory":"Used Merchandise",
            "type":"Retail Goods"
        }
    ],
    "sg:phone":"+1 480 759 9722",
    "sg:postcode":"85048",
    "sg:province":"AZ",
    "sg:tags":[
        "clothing"
    ],
    "wof:name":"Good Threads Consignment",
    "wof:placetype":"venue"
},
  "geometry": {"coordinates":[-112.015657,33.305139],"type":"Point"}
}