{
  "type": "Feature",
  "properties": {
    "iso:country":"US",
    "sg:address":"4905 E Ray Rd",
    "sg:city":"Phoenix",
    "sg:classifiers":[
        {
            "category":"Food & Beverages",
            "subcategory":"Candy",
            "type":"Retail Goods"
        }
    ],
    "sg:phone":"+1 480 753 6412",
    "sg:postcode":"85044",
    "sg:province":"AZ",
    "sg:tags":[
        "confectionery",
        "store"
    ],
    "wof:name":"Peppermint Bay",
    "wof:placetype":"venue"
},
  "geometry": {"coordinates":[-111.977928,33.319782],"type":"Point"}
}