{
  "type": "Feature",
  "properties": {
    "addr:full":"3401 E Harbour Dr Phoenix AZ 85034",
    "addr:housenumber":"3401",
    "addr:postcode":"85034",
    "addr:street":"E Harbour Dr",
    "iso:country":"US",
    "sg:address":"3401 E Harbour Dr",
    "sg:city":"Phoenix",
    "sg:classifiers":[
        {
            "category":"Freight",
            "type":"Transportation"
        }
    ],
    "sg:phone":"+1 602 333 4300",
    "sg:postcode":"85034",
    "sg:province":"AZ",
    "sg:tags":[
        "courier"
    ],
    "wof:name":"California Overnight",
    "wof:placetype":"venue"
},
  "geometry": {"coordinates":[-112.01031500000001,33.418009],"type":"Point"}
}