{
  "type": "Feature",
  "properties": {
    "iso:country":"US",
    "sg:address":"1243 S Dorsey Ln",
    "sg:city":"Tempe",
    "sg:classifiers":[
        {
            "category":"Real Estate",
            "subcategory":"Real Estate Operator",
            "type":"Services"
        }
    ],
    "sg:phone":"+1 480 966 6755",
    "sg:postcode":"85281",
    "sg:province":"AZ",
    "sg:tags":[
        "apartment"
    ],
    "wof:name":"Butterfield Park Apartments",
    "wof:placetype":"venue"
},
  "geometry": {"coordinates":[-111.917615,33.415589],"type":"Point"}
}