{
  "type": "Feature",
  "properties": {
    "addr:full":"635 E Indian School Rd Phoenix AZ 85012",
    "addr:housenumber":"635",
    "addr:postcode":"85012",
    "addr:street":"E Indian School Rd",
    "iso:country":"US",
    "sg:address":"635 E Indian School Rd",
    "sg:city":"Phoenix",
    "sg:classifiers":[
        {
            "category":"Restaurant",
            "type":"Food & Drink"
        }
    ],
    "sg:menulink":"http://www.allmenus.com/az/phoenix/110824-quiznos-sub/menu/",
    "sg:phone":"+1 602 264 5792",
    "sg:postcode":"85012",
    "sg:province":"AZ",
    "sg:tags":[
        "wrap",
        "american",
        "sandwich"
    ],
    "wof:name":"Quiznos Sub",
    "wof:placetype":"venue"
},
  "geometry": {"coordinates":[-112.06541300000001,33.494435],"type":"Point"}
}