{
  "type": "Feature",
  "properties": {
    "addr:full":"435 W Valencia Rd Tucson AZ 85706",
    "addr:housenumber":"435",
    "addr:postcode":"85706",
    "addr:street":"W Valencia Rd",
    "iso:country":"US",
    "sg:address":"435 W Valencia Rd",
    "sg:city":"Tucson",
    "sg:classifiers":[
        {
            "category":"Restaurant",
            "type":"Food & Drink"
        }
    ],
    "sg:menulink":"http://www.allmenus.com/az/tucson/156879-whataburger/menu/",
    "sg:phone":"+1 520 294 9540",
    "sg:postcode":"85706",
    "sg:province":"AZ",
    "sg:tags":[
        "burger",
        "american"
    ],
    "wof:name":"Whataburger",
    "wof:placetype":"venue"
},
  "geometry": {"coordinates":[-110.97589000000001,32.13392],"type":"Point"}
}