{
  "type": "Feature",
  "properties": {
    "addr:full":"3644 S Jamaica Blvd Lake Havasu City AZ 86406",
    "addr:housenumber":"3644",
    "addr:postcode":"86406",
    "addr:street":"S Jamaica Blvd",
    "iso:country":"US",
    "sg:address":"3644 S Jamaica Blvd",
    "sg:city":"Lake Havasu City",
    "sg:classifiers":[
        {
            "category":"Building & Trades",
            "subcategory":"Electrical",
            "type":"Services"
        }
    ],
    "sg:phone":"+1 928 855 7373",
    "sg:postcode":"86406",
    "sg:province":"AZ",
    "sg:tags":[
        "communications",
        "electronic",
        "contractor"
    ],
    "wof:name":"Tower Communications",
    "wof:placetype":"venue"
},
  "geometry": {"coordinates":[-114.28423600000001,34.498],"type":"Point"}
}