{
  "type": "Feature",
  "properties": {
    "iso:country":"US",
    "sg:address":"501 N Arizona Ave Ste 1",
    "sg:city":"Chandler",
    "sg:classifiers":[
        {
            "category":"Personal",
            "subcategory":"Beauty Salon",
            "type":"Services"
        }
    ],
    "sg:phone":"+1 480 219 2279",
    "sg:postcode":"85225",
    "sg:province":"AZ",
    "sg:tags":[
        "hair"
    ],
    "wof:name":"Jim Jeon Hair Studio",
    "wof:placetype":"venue"
},
  "geometry": {"coordinates":[-111.841058,33.311751],"type":"Point"}
}