{
  "type": "Feature",
  "properties": {
    "iso:country":"US",
    "sg:address":"2514 E Heatherbrae Dr",
    "sg:city":"Phoenix",
    "sg:classifiers":[
        {
            "category":"Social Services",
            "subcategory":"Adult Care",
            "type":"Services"
        }
    ],
    "sg:phone":"+1 602 977 2686",
    "sg:postcode":"85016",
    "sg:province":"AZ",
    "sg:tags":[
        "living",
        "assisted",
        "elder"
    ],
    "wof:name":"Enchantment Assisted Livi",
    "wof:placetype":"venue"
},
  "geometry": {"coordinates":[-112.027726,33.497598],"type":"Point"}
}