{
  "type": "Feature",
  "properties": {
    "iso:country":"US",
    "sg:address":"28 N Center St",
    "sg:city":"Mesa",
    "sg:classifiers":[
        {
            "category":"Insurance",
            "subcategory":"Insurance Agent",
            "type":"Services"
        }
    ],
    "sg:phone":"+1 480 969 2291",
    "sg:postcode":"85201",
    "sg:province":"AZ",
    "sg:website":"www.passeybond.com",
    "wof:name":"Passey-Bond Co",
    "wof:placetype":"venue"
},
  "geometry": {"coordinates":[-111.831545,33.415577],"type":"Point"}
}