{
  "type": "Feature",
  "properties": {
    "addr:full":"20707 N 67th Ave Glendale AZ 85308",
    "addr:housenumber":"20707",
    "addr:postcode":"85308",
    "addr:street":"N 67Th Ave",
    "iso:country":"US",
    "sg:address":"20707 N 67th Ave",
    "sg:city":"Glendale",
    "sg:classifiers":[
        {
            "category":"Shopping",
            "subcategory":"Computers & Home Electronics",
            "type":"Retail Goods"
        }
    ],
    "sg:phone":"+1 602 570 5710",
    "sg:postcode":"85308",
    "sg:province":"AZ",
    "sg:tags":[
        "equipment",
        "dealer"
    ],
    "wof:name":"Cyclone Tek",
    "wof:placetype":"venue"
},
  "geometry": {"coordinates":[-112.202955,33.673608],"type":"Point"}
}