{
  "type": "Feature",
  "properties": {
    "iso:country":"US",
    "sg:address":"301 E le Marche Ave",
    "sg:city":"Phoenix",
    "sg:classifiers":[
        {
            "category":"Manufacturing",
            "subcategory":"Electronics",
            "type":"Manufacturing & Wholesale Goods"
        }
    ],
    "sg:phone":"+1 480 991 8181",
    "sg:postcode":"85022",
    "sg:province":"AZ",
    "sg:tags":[
        "equipment-wholesale",
        "supplies-wholesale",
        "equipment",
        "manufacturer",
        "electronic",
        "audio-visual"
    ],
    "wof:name":"Dedicated Audio",
    "wof:placetype":"venue"
},
  "geometry": {"coordinates":[-112.070572,33.632599],"type":"Point"}
}