{
  "type": "Feature",
  "properties": {
    "iso:country":"US",
    "sg:address":"3102 N 56th St",
    "sg:city":"Phoenix",
    "sg:classifiers":[
        {
            "category":"Wholesale",
            "subcategory":"Electrical",
            "type":"Manufacturing & Wholesale Goods"
        }
    ],
    "sg:phone":"+1 602 952 3000",
    "sg:postcode":"85018",
    "sg:province":"AZ",
    "sg:tags":[
        "semiconductor",
        "device"
    ],
    "sg:website":"http://www.motorola.com",
    "wof:name":"Motorola",
    "wof:placetype":"venue"
},
  "geometry": {"coordinates":[-111.960922,33.483657],"type":"Point"}
}