{
  "type": "Feature",
  "properties": {
    "iso:country":"US",
    "sg:address":"7205 N 51st Ave",
    "sg:city":"Glendale",
    "sg:classifiers":[
        {
            "category":"Organizations",
            "subcategory":"Religious Organization",
            "type":"Services"
        }
    ],
    "sg:phone":"+1 623 931 2451",
    "sg:postcode":"85301",
    "sg:province":"AZ",
    "sg:tags":[
        "churches-lutheran",
        "church"
    ],
    "sg:website":"www.sjchurch.com",
    "wof:name":"St John's Lutheran Church",
    "wof:placetype":"venue"
},
  "geometry": {"coordinates":[-112.1686,33.542257],"type":"Point"}
}