{
  "type": "Feature",
  "properties": {
    "iso:country":"US",
    "sg:address":"2232E Michigan Ave",
    "sg:city":"Phoenix",
    "sg:classifiers":[
        {
            "category":"Building & Trades",
            "subcategory":"Landscaping Services",
            "type":"Services"
        },
        {
            "category":"Home & Garden",
            "subcategory":"Building Materials",
            "type":"Retail Goods"
        },
        {
            "category":"Building & Trades",
            "subcategory":"Construction",
            "type":"Services"
        }
    ],
    "sg:phone":"+1 602 405 3785",
    "sg:postcode":"85022",
    "sg:province":"AZ",
    "sg:tags":[
        "repair",
        "lawn",
        "installation",
        "sprinklers-garden",
        "improvement",
        "maintenance",
        "builder",
        "patio"
    ],
    "wof:name":"LM HANDYMAN SERVICES",
    "wof:placetype":"venue"
},
  "geometry": {"coordinates":[-112.034411,33.651364],"type":"Point"}
}