{
  "type": "Feature",
  "properties": {
    "iso:country":"US",
    "sg:address":"725 N Central Ave",
    "sg:city":"Avondale",
    "sg:classifiers":[
        {
            "category":"Home & Garden",
            "subcategory":"Carpets & Floor Coverings",
            "type":"Retail Goods"
        }
    ],
    "sg:phone":"+1 623 932 0078",
    "sg:postcode":"85323",
    "sg:province":"AZ",
    "wof:name":"Big D Floor Covering",
    "wof:placetype":"venue"
},
  "geometry": {"coordinates":[-112.349603,33.4424],"type":"Point"}
}