{
  "type": "Feature",
  "properties": {
    "iso:country":"US",
    "sg:address":"801 E Deuce of Clubs",
    "sg:city":"Show Low",
    "sg:classifiers":[
        {
            "category":"Sports & Exercise",
            "subcategory":"Gym",
            "type":"Entertainment"
        }
    ],
    "sg:phone":"+1 928 537 8320",
    "sg:postcode":"85901",
    "sg:province":"AZ",
    "sg:tags":[
        "club",
        "health",
        "studio",
        "gymnasium"
    ],
    "wof:name":"Curves",
    "wof:placetype":"venue"
},
  "geometry": {"coordinates":[-110.032585,34.253395],"type":"Point"}
}