{
  "type": "Feature",
  "properties": {
    "iso:country":"US",
    "sg:address":"1256 E Broadway Rd",
    "sg:city":"Mesa",
    "sg:classifiers":[
        {
            "category":"Home & Garden",
            "subcategory":"Building Materials",
            "type":"Retail Goods"
        }
    ],
    "sg:phone":"+1 877 602 4044",
    "sg:postcode":"85204",
    "sg:province":"AZ",
    "sg:tags":[
        "screen",
        "window"
    ],
    "wof:name":"Mesa Screen & Glass Specialty",
    "wof:placetype":"venue"
},
  "geometry": {"coordinates":[-111.803847,33.407927],"type":"Point"}
}