{
  "type": "Feature",
  "properties": {
    "iso:country":"US",
    "sg:address":"1212 E Osborn Rd Frnt",
    "sg:city":"Phoenix",
    "sg:classifiers":[
        {
            "category":"Professional",
            "subcategory":"Accounting & Tax Preparation",
            "type":"Services"
        }
    ],
    "sg:phone":"+1 602 222 9478",
    "sg:postcode":"85014",
    "sg:province":"AZ",
    "sg:tags":[
        "public",
        "accountants-certified"
    ],
    "wof:name":"John Degnan & Co",
    "wof:placetype":"venue"
},
  "geometry": {"coordinates":[-112.055461,33.487408],"type":"Point"}
}