{
  "type": "Feature",
  "properties": {
    "iso:country":"US",
    "sg:address":"1277 E Missouri Ave Ste 210",
    "sg:city":"Phoenix",
    "sg:classifiers":[
        {
            "category":"Health Services",
            "subcategory":"Dentist",
            "type":"Services"
        }
    ],
    "sg:phone":"+1 602 230 9902",
    "sg:postcode":"85014",
    "sg:province":"AZ",
    "sg:tags":[
        "dentists-endodontists"
    ],
    "wof:name":"Dennis E. Hanna, DDS",
    "wof:placetype":"venue"
},
  "geometry": {"coordinates":[-112.054536,33.516472],"type":"Point"}
}