{
  "type": "Feature",
  "properties": {
    "addr:full":"980 W Wickenburg Way Wickenburg AZ 85390",
    "addr:housenumber":"980",
    "addr:postcode":"85390",
    "addr:street":"W Wickenburg Way",
    "iso:country":"US",
    "sg:address":"980 W Wickenburg Way",
    "sg:city":"Wickenburg",
    "sg:classifiers":[
        {
            "category":"Wholesale",
            "subcategory":"Machinery & Supplies",
            "type":"Manufacturing & Wholesale Goods"
        }
    ],
    "sg:phone":"+1 928 684 2442",
    "sg:postcode":"85390",
    "sg:province":"AZ",
    "sg:tags":[
        "hose",
        "valve",
        "hydraulic"
    ],
    "wof:name":"Golden Eagle Hydraulics LLC",
    "wof:placetype":"venue"
},
  "geometry": {"coordinates":[-112.74969299999999,33.965327],"type":"Point"}
}