{
  "type": "Feature",
  "properties": {
    "iso:country":"US",
    "sg:address":"629 W Broadway Rd",
    "sg:city":"Mesa",
    "sg:classifiers":[
        {
            "category":"Manufacturing",
            "subcategory":"Retail Goods",
            "type":"Manufacturing & Wholesale Goods"
        }
    ],
    "sg:phone":"+1 480 655 7068",
    "sg:postcode":"85210",
    "sg:province":"AZ",
    "sg:tags":[
        "manufacturer"
    ],
    "wof:name":"Rival Industries",
    "wof:placetype":"venue"
},
  "geometry": {"coordinates":[-111.847894,33.407665],"type":"Point"}
}