{
  "type": "Feature",
  "properties": {
    "addr:full":"9191 E San Salvador Dr Scottsdale AZ 85258",
    "addr:housenumber":"9191",
    "addr:postcode":"85258",
    "addr:street":"E San Salvador Dr",
    "iso:country":"US",
    "sg:address":"9191 E San Salvador Dr",
    "sg:city":"Scottsdale",
    "sg:classifiers":[
        {
            "category":"Government",
            "subcategory":"Office",
            "type":"Public Place"
        }
    ],
    "sg:phone":"+1 480 312 5700",
    "sg:postcode":"85258",
    "sg:province":"AZ",
    "sg:tags":[
        "village"
    ],
    "sg:website":"www.scottsdaleaz.gov",
    "wof:name":"Scottsdale City Purchasing",
    "wof:placetype":"venue"
},
  "geometry": {"coordinates":[-111.88335499999999,33.570057],"type":"Point"}
}