{
  "type": "Feature",
  "properties": {
    "iso:country":"US",
    "sg:address":"202 W Southern Ave",
    "sg:city":"Tempe",
    "sg:classifiers":[
        {
            "category":"Professional",
            "subcategory":"Printing & Photocopies",
            "type":"Services"
        },
        {
            "category":"Professional",
            "subcategory":"Credit Reporting & Collection",
            "type":"Services"
        }
    ],
    "sg:phone":"+1 480 966 2945",
    "sg:postcode":"85282",
    "sg:province":"AZ",
    "sg:tags":[
        "plaque",
        "medal",
        "award",
        "trophies"
    ],
    "sg:website":"http://www.trophyden.com",
    "wof:name":"Trophy Den",
    "wof:placetype":"venue"
},
  "geometry": {"coordinates":[-111.94222,33.392846],"type":"Point"}
}