{
  "type": "Feature",
  "properties": {
    "iso:country":"US",
    "sg:address":"7106 N 35th Ave Ste 105",
    "sg:city":"Phoenix",
    "sg:classifiers":[
        {
            "category":"Structure",
            "subcategory":"Office Building",
            "type":"Public Place"
        }
    ],
    "sg:phone":"+1 602 841 7904",
    "sg:postcode":"85051",
    "sg:province":"AZ",
    "sg:tags":[
        "park"
    ],
    "wof:name":"Suncrest Mobile Home Park Ii",
    "wof:placetype":"venue"
},
  "geometry": {"coordinates":[-112.134331,33.540915],"type":"Point"}
}