{
  "type": "Feature",
  "properties": {
    "iso:country":"US",
    "sg:address":"1543 Grand Ave",
    "sg:city":"Phoenix",
    "sg:classifiers":[
        {
            "category":"Retail",
            "subcategory":"Repair Shop",
            "type":"Services"
        },
        {
            "category":"Professional",
            "subcategory":"Detective & Security Services",
            "type":"Services"
        }
    ],
    "sg:phone":"+1 602 252 8000",
    "sg:postcode":"85007",
    "sg:province":"AZ",
    "sg:tags":[
        "skip",
        "tracing",
        "bail",
        "bond"
    ],
    "wof:name":"Always Open Bail Bonds",
    "wof:placetype":"venue"
},
  "geometry": {"coordinates":[-112.092657,33.459811],"type":"Point"}
}