{
  "type": "Feature",
  "properties": {
    "addr:full":"1010 W Chandler Heights Road Chandler AZ 85248",
    "addr:housenumber":"1010",
    "addr:postcode":"85248",
    "addr:street":"W Chandler Heights Road",
    "iso:country":"US",
    "sg:address":"1010 W Chandler Heights Road",
    "sg:city":"Chandler",
    "sg:classifiers":[
        {
            "category":"Personal",
            "subcategory":"Barber",
            "type":"Services"
        }
    ],
    "sg:phone":"+1 480 895 5548",
    "sg:postcode":"85248",
    "sg:province":"AZ",
    "wof:name":"Ocotillo Barber Shop",
    "wof:placetype":"venue"
},
  "geometry": {"coordinates":[-111.85873599999999,33.232827],"type":"Point"}
}