{
  "type": "Feature",
  "properties": {
    "addr:full":"2401 W Bell Rd Phoenix AZ 85023",
    "addr:housenumber":"2401",
    "addr:postcode":"85023",
    "addr:street":"W Bell Rd",
    "iso:country":"US",
    "sg:address":"2401 W Bell Rd",
    "sg:city":"Phoenix",
    "sg:classifiers":[
        {
            "category":"Banks & Credit Unions",
            "subcategory":"Bank",
            "type":"Services"
        }
    ],
    "sg:phone":"+1 602 866 1458",
    "sg:postcode":"85023",
    "sg:province":"AZ",
    "sg:tags":[
        "financing"
    ],
    "wof:name":"Corporate Capital",
    "wof:placetype":"venue"
},
  "geometry": {"coordinates":[-112.110736,33.639907],"type":"Point"}
}