{
  "type": "Feature",
  "properties": {
    "iso:country":"US",
    "sg:address":"3301 E Washington St",
    "sg:city":"Phoenix",
    "sg:classifiers":[
        {
            "category":"Shopping",
            "type":"Retail Goods"
        }
    ],
    "sg:phone":"+1 602 275 1800",
    "sg:postcode":"85034",
    "sg:province":"AZ",
    "sg:tags":[
        "picture",
        "frame"
    ],
    "wof:name":"Picture Peddler Showroom",
    "wof:placetype":"venue"
},
  "geometry": {"coordinates":[-112.007402,33.448166],"type":"Point"}
}