{
  "type": "Feature",
  "properties": {
    "iso:country":"US",
    "sg:address":"8036 E Yavapai Rd",
    "sg:city":"Prescott Valley",
    "sg:classifiers":[
        {
            "category":"Wholesale",
            "subcategory":"Machinery & Supplies",
            "type":"Manufacturing & Wholesale Goods"
        }
    ],
    "sg:phone":"+1 928 775 5497",
    "sg:postcode":"86314",
    "sg:province":"AZ",
    "sg:tags":[
        "equipment",
        "establishment"
    ],
    "wof:name":"Big D Arizona Floor Cvg Sups",
    "wof:placetype":"venue"
},
  "geometry": {"coordinates":[-112.324937,34.589441],"type":"Point"}
}