{
  "type": "Feature",
  "properties": {
    "iso:country":"US",
    "sg:address":"3110 N 16th St",
    "sg:city":"Phoenix",
    "sg:classifiers":[
        {
            "category":"Real Estate",
            "subcategory":"Architect",
            "type":"Services"
        }
    ],
    "sg:phone":"+1 602 279 4232",
    "sg:postcode":"85016",
    "sg:province":"AZ",
    "sg:tags":[
        "architects'",
        "specification",
        "builders'",
        "construction",
        "architectural"
    ],
    "wof:name":"Keith Foster & Associates",
    "wof:placetype":"venue"
},
  "geometry": {"coordinates":[-112.047653,33.483923],"type":"Point"}
}