{
  "type": "Feature",
  "properties": {
    "iso:country":"US",
    "sg:address":"5110 N 40th St",
    "sg:city":"Phoenix",
    "sg:classifiers":[
        {
            "category":"Social Services",
            "type":"Services"
        }
    ],
    "sg:phone":"+1 602 954 7544",
    "sg:postcode":"85018",
    "sg:province":"AZ",
    "sg:tags":[
        "youth",
        "organization",
        "center"
    ],
    "wof:name":"Camp Fire Boys & Girls",
    "wof:placetype":"venue"
},
  "geometry": {"coordinates":[-111.995362,33.512224],"type":"Point"}
}