{
  "type": "Feature",
  "properties": {
    "iso:country":"US",
    "sg:address":"9030 N 40th Ave",
    "sg:city":"Phoenix",
    "sg:phone":"+1 602 280 7256",
    "sg:postcode":"85051",
    "sg:province":"AZ",
    "wof:name":"Ashley Clyde",
    "wof:placetype":"venue"
},
  "geometry": {"coordinates":[-112.14473700000001,33.568554],"type":"Point"}
}