{
  "type": "Feature",
  "properties": {
    "iso:country":"US",
    "sg:address":"24 N 2nd St",
    "sg:city":"Phoenix",
    "sg:phone":"+1 602 253 9004",
    "sg:postcode":"85004",
    "sg:province":"AZ",
    "wof:name":"Majerie's Sports Grill",
    "wof:placetype":"venue"
},
  "geometry": {"coordinates":[-112.071226,33.448478],"type":"Point"}
}