{
  "type": "Feature",
  "properties": {
    "iso:country":"US",
    "sg:address":"2550 N Thunderbird Cir",
    "sg:city":"Mesa",
    "sg:classifiers":[
        {
            "category":"Professional",
            "subcategory":"Employment Agencies",
            "type":"Services"
        }
    ],
    "sg:phone":"+1 480 830 6400",
    "sg:postcode":"85215",
    "sg:province":"AZ",
    "sg:tags":[
        "help",
        "contractor"
    ],
    "wof:name":"Resolve Staffing",
    "wof:placetype":"venue"
},
  "geometry": {"coordinates":[-111.719835,33.462528],"type":"Point"}
}