{
  "type": "Feature",
  "properties": {
    "addr:full":"1220 W Magee Rd Tucson AZ 85704",
    "addr:housenumber":"1220",
    "addr:postcode":"85704",
    "addr:street":"W Magee Rd",
    "iso:country":"US",
    "sg:address":"1220 W Magee Rd",
    "sg:city":"Tucson",
    "sg:classifiers":[
        {
            "category":"Organizations",
            "subcategory":"Religious Organization",
            "type":"Services"
        }
    ],
    "sg:phone":"+1 520 297 3095",
    "sg:postcode":"85704",
    "sg:province":"AZ",
    "sg:tags":[
        "church"
    ],
    "sg:website":"www.ascensiontucson.org",
    "wof:name":"Ascension Lutheran Church",
    "wof:placetype":"venue"
},
  "geometry": {"coordinates":[-110.995383,32.351862],"type":"Point"}
}