{
  "type": "Feature",
  "properties": {
    "addr:full":"3515 W Campbell Phoenix AZ 85019",
    "addr:housenumber":"3515",
    "addr:postcode":"85019",
    "addr:street":"W Campbell",
    "iso:country":"US",
    "sg:address":"3515 W Campbell",
    "sg:city":"Phoenix",
    "sg:classifiers":[
        {
            "category":"Building & Trades",
            "subcategory":"Construction",
            "type":"Services"
        }
    ],
    "sg:phone":"+1 602 689 5352",
    "sg:postcode":"85019",
    "sg:province":"AZ",
    "sg:tags":[
        "roofing",
        "contractor"
    ],
    "wof:name":"Roofing",
    "wof:placetype":"venue"
},
  "geometry": {"coordinates":[-112.13468899999999,33.502272],"type":"Point"}
}