{
  "type": "Feature",
  "properties": {
    "iso:country":"US",
    "sg:address":"1664 W Boston St",
    "sg:city":"Chandler",
    "sg:classifiers":[
        {
            "category":"Shopping",
            "subcategory":"Used Merchandise",
            "type":"Retail Goods"
        }
    ],
    "sg:phone":"+1 480 732 1541",
    "sg:postcode":"85224",
    "sg:province":"AZ",
    "wof:name":"Joseph J Mucha",
    "wof:placetype":"venue"
},
  "geometry": {"coordinates":[-111.870764,33.302249],"type":"Point"}
}