{
  "type": "Feature",
  "properties": {
    "iso:country":"US",
    "sg:address":"3322 E Broadway Rd",
    "sg:city":"Phoenix",
    "sg:classifiers":[
        {
            "category":"Shopping",
            "subcategory":"Crafts & Fabrics",
            "type":"Retail Goods"
        }
    ],
    "sg:phone":"+1 602 431 1772",
    "sg:postcode":"85040",
    "sg:province":"AZ",
    "sg:tags":[
        "florists'",
        "supply",
        "florist",
        "supplies-wholesale",
        "manufacturer"
    ],
    "wof:name":"Floral Supply Syndicate",
    "wof:placetype":"venue"
},
  "geometry": {"coordinates":[-112.009519,33.40709],"type":"Point"}
}