{
  "type": "Feature",
  "properties": {
    "iso:country":"US",
    "sg:address":"2309 E Indian School Rd",
    "sg:city":"Phoenix",
    "sg:classifiers":[
        {
            "category":"Bars & Pubs",
            "type":"Food & Drink"
        },
        {
            "category":"Bars & Pubs",
            "subcategory":"Lounge",
            "type":"Food & Drink"
        }
    ],
    "sg:phone":"+1 602 957 2444",
    "sg:postcode":"85016",
    "sg:province":"AZ",
    "sg:tags":[
        "tavern",
        "brew",
        "cocktail"
    ],
    "wof:name":"Kat's",
    "wof:placetype":"venue"
},
  "geometry": {"coordinates":[-112.032175,33.494802],"type":"Point"}
}