{
  "type": "Feature",
  "properties": {
    "iso:country":"US",
    "sg:address":"4077 N US Hwy 89",
    "sg:city":"Prescott",
    "sg:classifiers":[
        {
            "category":"Shopping",
            "subcategory":"Used Merchandise",
            "type":"Retail Goods"
        }
    ],
    "sg:phone":"+1 928 777 0107",
    "sg:postcode":"86301",
    "sg:province":"AZ",
    "sg:tags":[
        "antique"
    ],
    "wof:name":"Lizz's Consignment",
    "wof:placetype":"venue"
},
  "geometry": {"coordinates":[-112.420445,34.608976],"type":"Point"}
}