{
  "type": "Feature",
  "properties": {
    "addr:full":"5243 W Glendale Ave Glendale AZ 85301",
    "addr:housenumber":"5243",
    "addr:postcode":"85301",
    "addr:street":"W Glendale Ave",
    "iso:country":"US",
    "sg:address":"5243 W Glendale Ave",
    "sg:city":"Glendale",
    "sg:classifiers":[
        {
            "category":"Wholesale",
            "subcategory":"Meat",
            "type":"Manufacturing & Wholesale Goods"
        }
    ],
    "sg:phone":"+1 623 979 7927",
    "sg:postcode":"85301",
    "sg:province":"AZ",
    "wof:name":"Country Fresh Meats",
    "wof:placetype":"venue"
},
  "geometry": {"coordinates":[-112.172006,33.538405],"type":"Point"}
}