{
  "type": "Feature",
  "properties": {
    "addr:full":"605 E Broadway Rd Tempe AZ 85282",
    "addr:housenumber":"605",
    "addr:postcode":"85282",
    "addr:street":"E Broadway Rd",
    "iso:country":"US",
    "sg:address":"605 E Broadway Rd",
    "sg:city":"Tempe",
    "sg:classifiers":[
        {
            "category":"Professional",
            "subcategory":"Computer Services",
            "type":"Services"
        }
    ],
    "sg:phone":"+1 480 804 1915",
    "sg:postcode":"85282",
    "sg:province":"AZ",
    "sg:tags":[
        "consultant",
        "designer"
    ],
    "sg:website":"www.netmedix.net",
    "wof:name":"Netconx",
    "wof:placetype":"venue"
},
  "geometry": {"coordinates":[-111.927981,33.407422],"type":"Point"}
}