{
  "type": "Feature",
  "properties": {
    "iso:country":"US",
    "sg:address":"492 E Cathy Dr",
    "sg:city":"Gilbert",
    "sg:classifiers":[
        {
            "category":"Restaurant",
            "type":"Food & Drink"
        }
    ],
    "sg:phone":"+1 602 418 8086",
    "sg:postcode":"85296",
    "sg:province":"AZ",
    "sg:tags":[
        "caterer"
    ],
    "wof:name":"Lil Pink Porker",
    "wof:placetype":"venue"
},
  "geometry": {"coordinates":[-111.778808,33.329524],"type":"Point"}
}