{
  "type": "Feature",
  "properties": {
    "iso:country":"US",
    "sg:address":"4605 S Priest Dr",
    "sg:city":"Tempe",
    "sg:classifiers":[
        {
            "category":"Shopping",
            "subcategory":"Department Store",
            "type":"Retail Goods"
        }
    ],
    "sg:phone":"+1 480 839 6733",
    "sg:postcode":"85282",
    "sg:province":"AZ",
    "sg:tags":[
        "shop"
    ],
    "wof:name":"Russella's",
    "wof:placetype":"venue"
},
  "geometry": {"coordinates":[-111.96092,33.382792],"type":"Point"}
}