{
  "type": "Feature",
  "properties": {
    "iso:country":"US",
    "sg:address":"2700 Sweetwater Ave",
    "sg:city":"Lake Havasu City",
    "sg:classifiers":[
        {
            "category":"Retail",
            "subcategory":"Auto Repair",
            "type":"Services"
        }
    ],
    "sg:phone":"+1 928 680 7200",
    "sg:postcode":"86406",
    "sg:province":"AZ",
    "sg:tags":[
        "repairing",
        "automobile"
    ],
    "wof:name":"Arizona Repair & Towing",
    "wof:placetype":"venue"
},
  "geometry": {"coordinates":[-114.295045,34.454637],"type":"Point"}
}