{
  "type": "Feature",
  "properties": {
    "iso:country":"US",
    "sg:address":"2102 E Broadway Blvd",
    "sg:city":"Tucson",
    "sg:classifiers":[
        {
            "category":"Education",
            "subcategory":"School",
            "type":"Public Place"
        }
    ],
    "sg:phone":"+1 520 225 2500",
    "sg:postcode":"85719",
    "sg:province":"AZ",
    "sg:website":"www.tusd.k12.az.us",
    "wof:name":"PASS Alternative High School",
    "wof:placetype":"venue"
},
  "geometry": {"coordinates":[-110.9395,32.221391],"type":"Point"}
}