{
  "type": "Feature",
  "properties": {
    "iso:country":"US",
    "sg:address":"4831 N 11th St",
    "sg:city":"Phoenix",
    "sg:classifiers":[
        {
            "category":"Professional",
            "subcategory":"Business Services",
            "type":"Services"
        }
    ],
    "sg:phone":"+1 602 266 9097",
    "sg:postcode":"85014",
    "sg:province":"AZ",
    "sg:tags":[
        "recording",
        "studio"
    ],
    "wof:name":"Fortitude Studios",
    "wof:placetype":"venue"
},
  "geometry": {"coordinates":[-112.05845100000001,33.509217],"type":"Point"}
}