{
  "type": "Feature",
  "properties": {
    "iso:country":"US",
    "sg:address":"1152 N Revere",
    "sg:city":"Mesa",
    "sg:classifiers":[
        {
            "category":"Building & Trades",
            "subcategory":"Construction",
            "type":"Services"
        }
    ],
    "sg:phone":"+1 480 567 9309",
    "sg:postcode":"85201",
    "sg:province":"AZ",
    "sg:tags":[
        "roofing",
        "contractor"
    ],
    "wof:name":"First Heritage Restoration",
    "wof:placetype":"venue"
},
  "geometry": {"coordinates":[-111.847199,33.436036],"type":"Point"}
}