{
  "type": "Feature",
  "properties": {
    "addr:full":"6137 N Scottsdale Rd Ste B14 Scottsdale AZ 85250",
    "addr:housenumber":"6137",
    "addr:postcode":"85250",
    "addr:street":"N Scottsdale Rd Ste B14",
    "iso:country":"US",
    "sg:address":"6137 N Scottsdale Rd Ste B14",
    "sg:city":"Scottsdale",
    "sg:classifiers":[
        {
            "category":"Utilities",
            "subcategory":"Mobile Phone",
            "type":"Services"
        },
        {
            "category":"Coffee & Tea",
            "type":"Food & Drink"
        }
    ],
    "sg:phone":"+1 480 483 5698",
    "sg:postcode":"85250",
    "sg:province":"AZ",
    "sg:tags":[
        "shop",
        "wi-fi",
        "espresso",
        "hotspot",
        "restaurant"
    ],
    "sg:website":"http://www.starbuckscoffee.com",
    "wof:name":"Starbucks Coffee",
    "wof:placetype":"venue"
},
  "geometry": {"coordinates":[-111.925754,33.526645],"type":"Point"}
}