{
  "type": "Feature",
  "properties": {
    "iso:country":"US",
    "sg:address":"2320 E Indian School Rd",
    "sg:city":"Phoenix",
    "sg:classifiers":[
        {
            "category":"Wholesale",
            "subcategory":"Stationery",
            "type":"Manufacturing & Wholesale Goods"
        }
    ],
    "sg:phone":"+1 602 957 2320",
    "sg:postcode":"85016",
    "sg:province":"AZ",
    "sg:tags":[
        "business",
        "form",
        "system"
    ],
    "wof:name":"Compucolor West Inc",
    "wof:placetype":"venue"
},
  "geometry": {"coordinates":[-112.030565,33.494919],"type":"Point"}
}