{
  "type": "Feature",
  "properties": {
    "addr:full":"8040 N 7th Ave Phoenix AZ 85021",
    "addr:housenumber":"8040",
    "addr:postcode":"85021",
    "addr:street":"N 7Th Ave",
    "iso:country":"US",
    "sg:address":"8040 N 7th Ave",
    "sg:city":"Phoenix",
    "sg:classifiers":[
        {
            "category":"Building & Trades",
            "subcategory":"Construction",
            "type":"Services"
        }
    ],
    "sg:phone":"+1 602 307 5992",
    "sg:postcode":"85021",
    "sg:province":"AZ",
    "sg:tags":[
        "plastering",
        "contractor"
    ],
    "wof:name":"Fourth Generation",
    "wof:placetype":"venue"
},
  "geometry": {"coordinates":[-112.08265400000001,33.554262],"type":"Point"}
}