{
  "type": "Feature",
  "properties": {
    "iso:country":"US",
    "sg:address":"245 E Bell Rd Ste 2",
    "sg:city":"Phoenix",
    "sg:classifiers":[
        {
            "category":"Health Services",
            "subcategory":"Dentist",
            "type":"Services"
        }
    ],
    "sg:phone":"+1 602 993 2960",
    "sg:postcode":"85022",
    "sg:province":"AZ",
    "wof:name":"Desert Sands Dentistry North",
    "wof:placetype":"venue"
},
  "geometry": {"coordinates":[-112.07061400000001,33.640188],"type":"Point"}
}