{
  "type": "Feature",
  "properties": {
    "iso:country":"US",
    "sg:address":"5239 W Lamar Rd",
    "sg:city":"Glendale",
    "sg:classifiers":[
        {
            "category":"Autos & Motor Vehicles",
            "subcategory":"Automobile Sales",
            "type":"Retail Goods"
        },
        {
            "category":"Wholesale",
            "subcategory":"Scrap",
            "type":"Manufacturing & Wholesale Goods"
        }
    ],
    "sg:phone":"+1 623 939 2096",
    "sg:postcode":"85301",
    "sg:province":"AZ",
    "sg:tags":[
        "material",
        "wrecker"
    ],
    "wof:name":"J B's Imports",
    "wof:placetype":"venue"
},
  "geometry": {"coordinates":[-112.171953,33.536589],"type":"Point"}
}