{
  "type": "Feature",
  "properties": {
    "iso:country":"US",
    "sg:address":"7220 N 16th St Ste I",
    "sg:city":"Phoenix",
    "sg:classifiers":[
        {
            "category":"Insurance",
            "subcategory":"Hazard Insurance",
            "type":"Services"
        }
    ],
    "sg:phone":"+1 602 870 1991",
    "sg:postcode":"85020",
    "sg:province":"AZ",
    "sg:tags":[
        "commercial",
        "business"
    ],
    "wof:name":"Robert Loftus",
    "wof:placetype":"venue"
},
  "geometry": {"coordinates":[-112.047524,33.542729],"type":"Point"}
}