{
  "type": "Feature",
  "properties": {
    "iso:country":"US",
    "sg:address":"720 S Ashbrook",
    "sg:city":"Mesa",
    "sg:classifiers":[
        {
            "category":"Building & Trades",
            "subcategory":"Construction",
            "type":"Services"
        }
    ],
    "sg:phone":"+1 480 649 1287",
    "sg:postcode":"85204",
    "sg:province":"AZ",
    "sg:tags":[
        "painter"
    ],
    "wof:name":"Fordyce Painting",
    "wof:placetype":"venue"
},
  "geometry": {"coordinates":[-111.787733,33.402333],"type":"Point"}
}