{
  "type": "Feature",
  "properties": {
    "iso:country":"US",
    "sg:address":"3332 N 67th St",
    "sg:city":"Scottsdale",
    "sg:classifiers":[
        {
            "category":"Professional",
            "type":"Services"
        }
    ],
    "sg:phone":"+1 480 941 4557",
    "sg:postcode":"85251",
    "sg:province":"AZ",
    "wof:name":"Melissa Castle",
    "wof:placetype":"venue"
},
  "geometry": {"coordinates":[-111.936685,33.487079],"type":"Point"}
}