{
  "type": "Feature",
  "properties": {
    "iso:country":"US",
    "sg:address":"3636 E Baseline Rd",
    "sg:city":"Phoenix",
    "sg:classifiers":[
        {
            "category":"Manufacturing",
            "subcategory":"Petroleum Products",
            "type":"Manufacturing & Wholesale Goods"
        }
    ],
    "sg:phone":"+1 602 268 7636",
    "sg:postcode":"85042",
    "sg:province":"AZ",
    "sg:tags":[
        "contract"
    ],
    "wof:name":"Pride Manufacturing Co Llc Dba Pride Sports",
    "wof:placetype":"venue"
},
  "geometry": {"coordinates":[-112.002316,33.378079],"type":"Point"}
}