{
  "type": "Feature",
  "properties": {
    "iso:country":"US",
    "sg:address":"1325 E Benson Hwy",
    "sg:city":"Tucson",
    "sg:classifiers":[
        {
            "category":"Shopping",
            "subcategory":"Used Merchandise",
            "type":"Retail Goods"
        }
    ],
    "sg:phone":"+1 520 623 0410",
    "sg:postcode":"85714",
    "sg:province":"AZ",
    "sg:tags":[
        "building",
        "material"
    ],
    "wof:name":"Taylors Demolition & Recycling",
    "wof:placetype":"venue"
},
  "geometry": {"coordinates":[-110.949592,32.175226],"type":"Point"}
}