{
  "type": "Feature",
  "properties": {
    "addr:full":"271 E Chilton Dr Chandler AZ 85225",
    "addr:housenumber":"271",
    "addr:postcode":"85225",
    "addr:street":"E Chilton Dr",
    "iso:country":"US",
    "sg:address":"271 E Chilton Dr",
    "sg:city":"Chandler",
    "sg:classifiers":[
        {
            "category":"Autos & Motor Vehicles",
            "subcategory":"Automobile Sales",
            "type":"Retail Goods"
        }
    ],
    "sg:phone":"+1 480 545 1693",
    "sg:postcode":"85225",
    "sg:province":"AZ",
    "sg:tags":[
        "new",
        "used",
        "car"
    ],
    "wof:name":"Jmc Motors",
    "wof:placetype":"venue"
},
  "geometry": {"coordinates":[-111.837158,33.354967],"type":"Point"}
}