{
  "type": "Feature",
  "properties": {
    "iso:country":"US",
    "sg:address":"1819 W Cheyenne Dr",
    "sg:city":"Chandler",
    "sg:classifiers":[
        {
            "category":"Restaurant",
            "type":"Food & Drink"
        }
    ],
    "sg:phone":"+1 480 570 9992",
    "sg:postcode":"85224",
    "sg:province":"AZ",
    "sg:tags":[
        "mexican"
    ],
    "wof:name":"Garcia Sparkling Pool",
    "wof:placetype":"venue"
},
  "geometry": {"coordinates":[-111.874595,33.345902],"type":"Point"}
}