{
  "type": "Feature",
  "properties": {
    "iso:country":"US",
    "sg:address":"148 6th Ave Ste 1",
    "sg:city":"Page",
    "sg:classifiers":[
        {
            "category":"Place Of Worship",
            "subcategory":"Church",
            "type":"Public Place"
        },
        {
            "category":"Place Of Worship",
            "type":"Public Place"
        },
        {
            "category":"Organizations",
            "subcategory":"Religious Organization",
            "type":"Services"
        }
    ],
    "sg:phone":"+1 928 600 7978",
    "sg:postcode":"86040",
    "sg:province":"AZ",
    "sg:tags":[
        "god",
        "churches-church",
        "churches-pentecostal"
    ],
    "wof:name":"Faith Covenant Ministries",
    "wof:placetype":"venue"
},
  "geometry": {"coordinates":[-111.459222,36.914469],"type":"Point"}
}