{
  "type": "Feature",
  "properties": {
    "iso:country":"US",
    "sg:address":"1905 W Washington St",
    "sg:city":"Phoenix",
    "sg:classifiers":[
        {
            "category":"Organizations",
            "subcategory":"Professional Association",
            "type":"Services"
        }
    ],
    "sg:phone":"+1 602 252 5521",
    "sg:postcode":"85009",
    "sg:province":"AZ",
    "wof:name":"County Supervisors Assn Of Az",
    "wof:placetype":"venue"
},
  "geometry": {"coordinates":[-112.10026999999999,33.448029],"type":"Point"}
}