{
  "type": "Feature",
  "properties": {
    "iso:country":"US",
    "sg:address":"2423 N Grand Ave",
    "sg:city":"Nogales",
    "sg:classifiers":[
        {
            "category":"Building & Trades",
            "subcategory":"Construction",
            "type":"Services"
        }
    ],
    "sg:phone":"+1 520 377 9502",
    "sg:postcode":"85621",
    "sg:province":"AZ",
    "sg:tags":[
        "resurfacing",
        "laying",
        "refinishing",
        "floor"
    ],
    "wof:name":"Stone & Floor Creations",
    "wof:placetype":"venue"
},
  "geometry": {"coordinates":[-110.937421,31.375701],"type":"Point"}
}