{
  "type": "Feature",
  "properties": {
    "addr:full":"4120 E Valley Auto Dr Mesa AZ 85206",
    "addr:housenumber":"4120",
    "addr:postcode":"85206",
    "addr:street":"E Valley Auto Dr",
    "iso:country":"US",
    "sg:address":"4120 E Valley Auto Dr",
    "sg:city":"Mesa",
    "sg:classifiers":[
        {
            "category":"Utilities",
            "subcategory":"Cable",
            "type":"Services"
        }
    ],
    "sg:phone":"+1 480 558 7260",
    "sg:postcode":"85206",
    "sg:province":"AZ",
    "sg:tags":[
        "television"
    ],
    "sg:website":"www.cableamerica.com",
    "wof:name":"Cable America Corp",
    "wof:placetype":"venue"
},
  "geometry": {"coordinates":[-111.74115500000001,33.383575],"type":"Point"}
}