{
  "type": "Feature",
  "properties": {
    "addr:full":"2640 N Lake Valley Rd Prescott Valley AZ 86314",
    "addr:housenumber":"2640",
    "addr:postcode":"86314",
    "addr:street":"N Lake Valley Rd",
    "iso:country":"US",
    "sg:address":"2640 N Lake Valley Rd",
    "sg:city":"Prescott Valley",
    "sg:classifiers":[
        {
            "category":"Utilities",
            "subcategory":"Refuse",
            "type":"Services"
        }
    ],
    "sg:phone":"+1 928 759 9400",
    "sg:postcode":"86314",
    "sg:province":"AZ",
    "sg:tags":[
        "garbage",
        "collection"
    ],
    "wof:name":"Prescott Valley Constr Debris",
    "wof:placetype":"venue"
},
  "geometry": {"coordinates":[-112.33434099999999,34.585175],"type":"Point"}
}