{
  "type": "Feature",
  "properties": {
    "iso:country":"US",
    "sg:address":"5441 E Williams Cir",
    "sg:city":"Tucson",
    "sg:classifiers":[
        {
            "category":"Manufacturing",
            "subcategory":"Electronics",
            "type":"Manufacturing & Wholesale Goods"
        }
    ],
    "sg:phone":"+1 520 745 0045",
    "sg:postcode":"85711",
    "sg:province":"AZ",
    "sg:tags":[
        "semiconductor",
        "related",
        "devices"
    ],
    "sg:website":"www.smsc.com",
    "wof:name":"Standard Microsystems Corp",
    "wof:placetype":"venue"
},
  "geometry": {"coordinates":[-110.878337,32.220577],"type":"Point"}
}