{
  "type": "Feature",
  "properties": {
    "iso:country":"US",
    "sg:address":"1966 Hwy 95",
    "sg:city":"Bullhead City",
    "sg:classifiers":[
        {
            "category":"Shopping",
            "subcategory":"Jewelry",
            "type":"Retail Goods"
        }
    ],
    "sg:phone":"+1 928 763 4722",
    "sg:postcode":"86442",
    "sg:province":"AZ",
    "sg:tags":[
        "jeweler"
    ],
    "wof:name":"Michael's Jewelers",
    "wof:placetype":"venue"
},
  "geometry": {"coordinates":[-114.598071,35.11723],"type":"Point"}
}