{
  "type": "Feature",
  "properties": {
    "iso:country":"US",
    "sg:address":"9816 S Nogales Hwy",
    "sg:city":"Tucson",
    "sg:classifiers":[
        {
            "category":"Shopping",
            "subcategory":"Used Merchandise",
            "type":"Retail Goods"
        },
        {
            "category":"Retail",
            "subcategory":"Auto Repair",
            "type":"Services"
        }
    ],
    "sg:phone":"+1 520 889 6273",
    "sg:postcode":"85706",
    "sg:province":"AZ",
    "sg:tags":[
        "repairing",
        "tire",
        "store"
    ],
    "wof:name":"Pepe's Tire Shop",
    "wof:placetype":"venue"
},
  "geometry": {"coordinates":[-110.958501,32.073483],"type":"Point"}
}