{
  "type": "Feature",
  "properties": {
    "iso:country":"US",
    "sg:address":"17500 N 67th Ave",
    "sg:city":"Glendale",
    "sg:classifiers":[
        {
            "category":"Personal",
            "subcategory":"Beauty Salon",
            "type":"Services"
        }
    ],
    "sg:phone":"+1 602 843 2524",
    "sg:postcode":"85308",
    "sg:province":"AZ",
    "wof:name":"Sandy's Barber & Beauty",
    "wof:placetype":"venue"
},
  "geometry": {"coordinates":[-112.203021,33.642207],"type":"Point"}
}