{
  "type": "Feature",
  "properties": {
    "addr:full":"1815 E Speedway Blvd Tucson AZ 85719",
    "addr:housenumber":"1815",
    "addr:postcode":"85719",
    "addr:street":"E Speedway Blvd",
    "iso:country":"US",
    "sg:address":"1815 E Speedway Blvd",
    "sg:city":"Tucson",
    "sg:classifiers":[
        {
            "category":"Real Estate",
            "subcategory":"Real Estate Operator",
            "type":"Services"
        }
    ],
    "sg:phone":"+1 520 325 4291",
    "sg:postcode":"85719",
    "sg:province":"AZ",
    "sg:tags":[
        "apartment",
        "complex"
    ],
    "wof:name":"Palm Shadows Apartments",
    "wof:placetype":"venue"
},
  "geometry": {"coordinates":[-110.94400899999999,32.23613],"type":"Point"}
}