{
  "type": "Feature",
  "properties": {
    "iso:country":"US",
    "sg:address":"5122 N 95th Ave",
    "sg:city":"Glendale",
    "sg:classifiers":[
        {
            "category":"Shopping",
            "subcategory":"Jewelry",
            "type":"Retail Goods"
        }
    ],
    "sg:phone":"+1 623 772 8800",
    "sg:postcode":"85305",
    "sg:province":"AZ",
    "wof:name":"Crescent Jewelers",
    "wof:placetype":"venue"
},
  "geometry": {"coordinates":[-112.263839,33.515329],"type":"Point"}
}