{
  "type": "Feature",
  "properties": {
    "addr:full":"7149 N 45th Ave Glendale AZ 85301",
    "addr:housenumber":"7149",
    "addr:postcode":"85301",
    "addr:street":"N 45Th Ave",
    "iso:country":"US",
    "sg:address":"7149 N 45th Ave",
    "sg:city":"Glendale",
    "sg:classifiers":[
        {
            "category":"Real Estate",
            "subcategory":"Real Estate Agent",
            "type":"Services"
        }
    ],
    "sg:phone":"+1 623 435 8181",
    "sg:postcode":"85301",
    "sg:province":"AZ",
    "wof:name":"Israel Finley & Ramos Realters",
    "wof:placetype":"venue"
},
  "geometry": {"coordinates":[-112.155672,33.541878],"type":"Point"}
}