{
  "type": "Feature",
  "properties": {
    "iso:country":"US",
    "sg:address":"7735 E Redfield Rd # 100",
    "sg:city":"Scottsdale",
    "sg:classifiers":[
        {
            "category":"Personal",
            "subcategory":"Beauty Salon",
            "type":"Services"
        },
        {
            "category":"Personal",
            "subcategory":"Barber",
            "type":"Services"
        },
        {
            "category":"Shopping",
            "subcategory":"Beauty & Cosmetics",
            "type":"Retail Goods"
        }
    ],
    "sg:phone":"+1 480 483 8676",
    "sg:postcode":"85260",
    "sg:province":"AZ",
    "sg:tags":[
        "stylist",
        "supply",
        "accessory",
        "hair",
        "equipment",
        "salons-equipment",
        "perfume"
    ],
    "wof:name":"Design 1 Hair Company",
    "wof:placetype":"venue"
},
  "geometry": {"coordinates":[-111.914017,33.613938],"type":"Point"}
}