{
  "type": "Feature",
  "properties": {
    "iso:country":"US",
    "sg:address":"22001 W Ripple Rd",
    "sg:city":"Buckeye",
    "sg:classifiers":[
        {
            "category":"Transit Center",
            "subcategory":"Freight",
            "type":"Transportation"
        }
    ],
    "sg:phone":"+1 623 386 7417",
    "sg:postcode":"85326",
    "sg:province":"AZ",
    "sg:tags":[
        "trucking-light",
        "hauling"
    ],
    "wof:name":"Kld Transport Inc",
    "wof:placetype":"venue"
},
  "geometry": {"coordinates":[-112.523529,33.42382],"type":"Point"}
}