{
  "type": "Feature",
  "properties": {
    "iso:country":"US",
    "sg:address":"4153 S Tigre del Mar Dr",
    "sg:city":"Apache Junction",
    "sg:classifiers":[
        {
            "category":"Building & Trades",
            "subcategory":"Landscaping Services",
            "type":"Services"
        }
    ],
    "sg:phone":"+1 480 671 5188",
    "sg:postcode":"85218",
    "sg:province":"AZ",
    "wof:name":"Coyote Landscape LLC",
    "wof:placetype":"venue"
},
  "geometry": {"coordinates":[-111.474305,33.377085],"type":"Point"}
}