{
  "type": "Feature",
  "properties": {
    "iso:country":"US",
    "sg:address":"222 W Clarendon Ave Ofc",
    "sg:city":"Phoenix",
    "sg:classifiers":[
        {
            "category":"Real Estate",
            "subcategory":"Real Estate Services",
            "type":"Services"
        },
        {
            "category":"Real Estate",
            "subcategory":"Real Estate Operator",
            "type":"Services"
        }
    ],
    "sg:phone":"+1 602 595 0468",
    "sg:postcode":"85013",
    "sg:province":"AZ",
    "sg:tags":[
        "apartment",
        "vacancy",
        "listing",
        "rental",
        "finder"
    ],
    "wof:name":"Park Clarendon Apartments",
    "wof:placetype":"venue"
},
  "geometry": {"coordinates":[-112.076871,33.491428],"type":"Point"}
}