{
  "type": "Feature",
  "properties": {
    "addr:full":"4801 E Brown Rd Mesa AZ 85205",
    "addr:housenumber":"4801",
    "addr:postcode":"85205",
    "addr:street":"E Brown Rd",
    "iso:country":"US",
    "sg:address":"4801 E Brown Rd",
    "sg:city":"Mesa",
    "sg:classifiers":[
        {
            "category":"Organizations",
            "subcategory":"Religious Organization",
            "type":"Services"
        }
    ],
    "sg:phone":"+1 480 981 9684",
    "sg:postcode":"85205",
    "sg:province":"AZ",
    "sg:tags":[
        "church"
    ],
    "sg:website":"www.fbcmesa.org",
    "wof:name":"First Baptist Church",
    "wof:placetype":"venue"
},
  "geometry": {"coordinates":[-111.725368,33.437315],"type":"Point"}
}