{
  "type": "Feature",
  "properties": {
    "iso:country":"US",
    "sg:address":"3710 E Beaver Creek Rd",
    "sg:city":"Rimrock",
    "sg:classifiers":[
        {
            "category":"Professional",
            "subcategory":"Accounting & Tax Preparation",
            "type":"Services"
        }
    ],
    "sg:phone":"+1 928 592 9414",
    "sg:postcode":"86335",
    "sg:province":"AZ",
    "sg:tags":[
        "billing"
    ],
    "wof:name":"Arizona Billing Svc",
    "wof:placetype":"venue"
},
  "geometry": {"coordinates":[-111.785326,34.646179],"type":"Point"}
}