{
  "type": "Feature",
  "properties": {
    "iso:country":"US",
    "sg:address":"516 Main St",
    "sg:city":"Snowflake",
    "sg:classifiers":[
        {
            "category":"Retail",
            "subcategory":"Laundry & Dry Cleaning",
            "type":"Services"
        }
    ],
    "sg:phone":"+1 928 536 3330",
    "sg:postcode":"85937",
    "sg:province":"AZ",
    "wof:name":"Silver Creek Wash",
    "wof:placetype":"venue"
},
  "geometry": {"coordinates":[-110.09119,34.458777],"type":"Point"}
}