{
  "type": "Feature",
  "properties": {
    "iso:country":"US",
    "sg:address":"17007 E Colony Dr",
    "sg:city":"Fountain Hills",
    "sg:classifiers":[
        {
            "category":"Personal",
            "subcategory":"Beauty Salon",
            "type":"Services"
        }
    ],
    "sg:phone":"+1 480 980 4272",
    "sg:postcode":"85268",
    "sg:province":"AZ",
    "sg:tags":[
        "treatment",
        "skin"
    ],
    "wof:name":"At The Fountain Sherry's Skin",
    "wof:placetype":"venue"
},
  "geometry": {"coordinates":[-111.71474,33.596789],"type":"Point"}
}