{
  "type": "Feature",
  "properties": {
    "addr:full":"2920 N Swan Rd Tucson AZ 85712",
    "addr:housenumber":"2920",
    "addr:postcode":"85712",
    "addr:street":"N Swan Rd",
    "iso:country":"US",
    "sg:address":"2920 N Swan Rd",
    "sg:city":"Tucson",
    "sg:classifiers":[
        {
            "category":"Shopping",
            "subcategory":"Clothing, Apparel, & Fashions",
            "type":"Retail Goods"
        }
    ],
    "sg:phone":"+1 520 325 1240",
    "sg:postcode":"85712",
    "sg:province":"AZ",
    "sg:tags":[
        "boutique"
    ],
    "wof:name":"Changes",
    "wof:placetype":"venue"
},
  "geometry": {"coordinates":[-110.892383,32.261111],"type":"Point"}
}