{
  "type": "Feature",
  "properties": {
    "iso:country":"US",
    "sg:address":"2040 Meadowridge Rd",
    "sg:city":"Prescott",
    "sg:classifiers":[
        {
            "category":"Retail",
            "subcategory":"Auto Repair",
            "type":"Services"
        }
    ],
    "sg:phone":"+1 928 445 9479",
    "sg:postcode":"86305",
    "sg:province":"AZ",
    "sg:tags":[
        "repairing",
        "automobile"
    ],
    "wof:name":"Jim-N-I Mobile Repair",
    "wof:placetype":"venue"
},
  "geometry": {"coordinates":[-112.48865499999999,34.57551],"type":"Point"}
}