{
  "type": "Feature",
  "properties": {
    "iso:country":"US",
    "sg:address":"798 W Kingbird Dr",
    "sg:city":"Chandler",
    "sg:classifiers":[
        {
            "category":"Shopping",
            "subcategory":"Gifts & Souvenirs",
            "type":"Retail Goods"
        }
    ],
    "sg:phone":"+1 480 899 0300",
    "sg:postcode":"85286",
    "sg:province":"AZ",
    "wof:name":"Expression Gift",
    "wof:placetype":"venue"
},
  "geometry": {"coordinates":[-111.850041,33.272577],"type":"Point"}
}