{
  "type": "Feature",
  "properties": {
    "addr:full":"2231 E Fountain St Mesa AZ 85213",
    "addr:housenumber":"2231",
    "addr:postcode":"85213",
    "addr:street":"E Fountain St",
    "iso:country":"US",
    "sg:address":"2231 E Fountain St",
    "sg:city":"Mesa",
    "sg:classifiers":[
        {
            "category":"Building & Trades",
            "subcategory":"Pest Control",
            "type":"Services"
        }
    ],
    "sg:phone":"+1 480 641 9494",
    "sg:postcode":"85213",
    "sg:province":"AZ",
    "wof:name":"Red Mountain Pest Control",
    "wof:placetype":"venue"
},
  "geometry": {"coordinates":[-111.780991,33.435252],"type":"Point"}
}