{
  "type": "Feature",
  "properties": {
    "addr:full":"1149 N Santa Rosa Ave Tucson AZ 85712",
    "addr:housenumber":"1149",
    "addr:postcode":"85712",
    "addr:street":"N Santa Rosa Ave",
    "iso:country":"US",
    "sg:address":"1149 N Santa Rosa Ave",
    "sg:city":"Tucson",
    "sg:classifiers":[
        {
            "category":"Social Services",
            "type":"Services"
        }
    ],
    "sg:phone":"+1 520 326 5980",
    "sg:postcode":"85712",
    "sg:province":"AZ",
    "sg:tags":[
        "counselor",
        "marriage",
        "family"
    ],
    "wof:name":"Linda Bowers Ma NCC Lpc",
    "wof:placetype":"venue"
},
  "geometry": {"coordinates":[-110.88626499999999,32.237128],"type":"Point"}
}