{
  "type": "Feature",
  "properties": {
    "iso:country":"US",
    "sg:address":"11880 Arabian Ln",
    "sg:city":"Dewey",
    "sg:classifiers":[
        {
            "category":"Banks & Credit Unions",
            "subcategory":"Bank",
            "type":"Services"
        }
    ],
    "sg:phone":"+1 928 772 5868",
    "sg:postcode":"86327",
    "sg:province":"AZ",
    "sg:tags":[
        "loan",
        "real estate"
    ],
    "sg:website":"www.cherrycreekmortgage.com",
    "wof:name":"Cherry Creek Mortgage",
    "wof:placetype":"venue"
},
  "geometry": {"coordinates":[-112.258325,34.557696],"type":"Point"}
}