{
  "type": "Feature",
  "properties": {
    "iso:country":"US",
    "sg:address":"8951 E Cll Bolivar",
    "sg:city":"Tucson",
    "sg:classifiers":[
        {
            "category":"Building & Trades",
            "subcategory":"Construction",
            "type":"Services"
        }
    ],
    "sg:phone":"+1 520 886 2503",
    "sg:postcode":"85715",
    "sg:province":"AZ",
    "sg:tags":[
        "handyman"
    ],
    "wof:name":"Ed Wheeler Maintenance",
    "wof:placetype":"venue"
},
  "geometry": {"coordinates":[-110.801119,32.24013],"type":"Point"}
}