{
  "type": "Feature",
  "properties": {
    "iso:country":"US",
    "sg:address":"7469 S Lasso Ln",
    "sg:city":"Tucson",
    "sg:classifiers":[
        {
            "category":"Building & Trades",
            "subcategory":"Construction",
            "type":"Services"
        }
    ],
    "sg:phone":"+1 520 574 0721",
    "sg:postcode":"85747",
    "sg:province":"AZ",
    "sg:tags":[
        "contractor"
    ],
    "wof:name":"Award Installations",
    "wof:placetype":"venue"
},
  "geometry": {"coordinates":[-110.79992900000001,32.116491],"type":"Point"}
}