{
  "type": "Feature",
  "properties": {
    "addr:full":"701 S Joshua Ave Parker AZ 85344",
    "addr:housenumber":"701",
    "addr:postcode":"az 85344",
    "addr:street":"S Joshua Ave",
    "iso:country":"US",
    "sg:address":"701 S Joshua Ave",
    "sg:city":"Parker",
    "sg:classifiers":[
        {
            "category":"Freight",
            "type":"Transportation"
        }
    ],
    "sg:phone":"+1 928 669 6500",
    "sg:postcode":"85344",
    "sg:province":"AZ",
    "sg:tags":[
        "commercial",
        "storage"
    ],
    "wof:name":"All Boat RV & Storage",
    "wof:placetype":"venue"
},
  "geometry": {"coordinates":[-114.29216099999999,34.152783],"type":"Point"}
}