{
  "type": "Feature",
  "properties": {
    "iso:country":"US",
    "sg:address":"9201 N 29th Ave - 404",
    "sg:city":"Phoenix",
    "sg:classifiers":[
        {
            "category":"Manufacturing",
            "subcategory":"Tools & Machinery",
            "type":"Manufacturing & Wholesale Goods"
        }
    ],
    "sg:phone":"+1 602 589 5419",
    "sg:postcode":"85051",
    "sg:province":"AZ",
    "sg:tags":[
        "spraying",
        "equipment"
    ],
    "wof:name":"Aceco Turf Spraying Equipment",
    "wof:placetype":"venue"
},
  "geometry": {"coordinates":[-112.120752,33.570203],"type":"Point"}
}