{
  "type": "Feature",
  "properties": {
    "iso:country":"US",
    "sg:address":"1855 Hwy 95",
    "sg:city":"Bullhead City",
    "sg:classifiers":[
        {
            "category":"Restaurant",
            "type":"Food & Drink"
        }
    ],
    "sg:phone":"+1 928 763 6304",
    "sg:postcode":"86442",
    "sg:province":"AZ",
    "wof:name":"Famous Sam's",
    "wof:placetype":"venue"
},
  "geometry": {"coordinates":[-114.591624,35.120094],"type":"Point"}
}