{
  "type": "Feature",
  "properties": {
    "iso:country":"US",
    "sg:address":"1850 S 7th St",
    "sg:city":"Phoenix",
    "sg:classifiers":[
        {
            "category":"Fast Food",
            "type":"Food & Drink"
        },
        {
            "category":"Restaurant",
            "type":"Food & Drink"
        }
    ],
    "sg:phone":"+1 602 252 4532",
    "sg:postcode":"85034",
    "sg:province":"AZ",
    "sg:tags":[
        "hamburger",
        "hot",
        "dog",
        "american",
        "take",
        "chicken"
    ],
    "sg:website":"http://www.mcdonalds.com",
    "wof:name":"McDonald's",
    "wof:placetype":"venue"
},
  "geometry": {"coordinates":[-112.06529500000001,33.430238],"type":"Point"}
}