{
  "type": "Feature",
  "properties": {
    "iso:country":"US",
    "sg:address":"4626 E Fort Lowell Rd",
    "sg:city":"Tucson",
    "sg:classifiers":[
        {
            "category":"Wholesale",
            "subcategory":"Office Equipment",
            "type":"Manufacturing & Wholesale Goods"
        }
    ],
    "sg:phone":"+1 520 881 6588",
    "sg:postcode":"85712",
    "sg:province":"AZ",
    "sg:tags":[
        "register",
        "cash",
        "supply"
    ],
    "wof:name":"F & B Management",
    "wof:placetype":"venue"
},
  "geometry": {"coordinates":[-110.893005,32.261403],"type":"Point"}
}