{
  "type": "Feature",
  "properties": {
    "addr:full":"504 E Sheldon St Prescott AZ 86301",
    "addr:housenumber":"504",
    "addr:postcode":"86301",
    "addr:street":"E Sheldon St",
    "iso:country":"US",
    "sg:address":"504 E Sheldon St",
    "sg:city":"Prescott",
    "sg:classifiers":[
        {
            "category":"Home & Garden",
            "subcategory":"Building Materials",
            "type":"Retail Goods"
        }
    ],
    "sg:phone":"+1 928 777 0091",
    "sg:postcode":"86301",
    "sg:province":"AZ",
    "sg:tags":[
        "glass",
        "window",
        "plate"
    ],
    "wof:name":"Free & Clear Auto Glass",
    "wof:placetype":"venue"
},
  "geometry": {"coordinates":[-112.46317500000001,34.545443],"type":"Point"}
}