{
  "type": "Feature",
  "properties": {
    "addr:full":"4422 W Desert Cove Ave Glendale AZ 85304",
    "addr:housenumber":"4422",
    "addr:postcode":"85304",
    "addr:street":"W Desert Cove Ave",
    "iso:country":"US",
    "sg:address":"4422 W Desert Cove Ave",
    "sg:city":"Glendale",
    "sg:classifiers":[
        {
            "category":"Wholesale",
            "subcategory":"Machinery & Supplies",
            "type":"Manufacturing & Wholesale Goods"
        }
    ],
    "sg:phone":"+1 602 843 4419",
    "sg:postcode":"85304",
    "sg:province":"AZ",
    "sg:tags":[
        "equipment",
        "establishment"
    ],
    "wof:name":"Martys Hauling",
    "wof:placetype":"venue"
},
  "geometry": {"coordinates":[-112.153668,33.585669],"type":"Point"}
}