{
  "type": "Feature",
  "properties": {
    "iso:country":"US",
    "sg:address":"2595 S 4th Ave",
    "sg:city":"Yuma",
    "sg:classifiers":[
        {
            "category":"Restaurant",
            "type":"Food & Drink"
        }
    ],
    "sg:menulink":"http://www.allmenus.com/az/yuma/104498-hometown-buffet/menu/",
    "sg:phone":"+1 520 317 1303",
    "sg:postcode":"85364",
    "sg:province":"AZ",
    "sg:tags":[
        "new",
        "american"
    ],
    "wof:name":"Hometown Buffet",
    "wof:placetype":"venue"
},
  "geometry": {"coordinates":[-114.624596,32.68043],"type":"Point"}
}