{
  "type": "Feature",
  "properties": {
    "iso:country":"US",
    "sg:address":"15045 N 30th Dr",
    "sg:city":"Phoenix",
    "sg:classifiers":[
        {
            "category":"Building & Trades",
            "subcategory":"Construction",
            "type":"Services"
        }
    ],
    "sg:phone":"+1 602 863 6753",
    "sg:postcode":"85053",
    "sg:province":"AZ",
    "sg:tags":[
        "concrete",
        "contractor"
    ],
    "wof:name":"Concrete By Kelly Sundeaus",
    "wof:placetype":"venue"
},
  "geometry": {"coordinates":[-112.123353,33.623635],"type":"Point"}
}