{
  "type": "Feature",
  "properties": {
    "addr:full":"16950 N Lago del Oro Pkwy Tucson AZ 85739",
    "addr:housenumber":"16950",
    "addr:postcode":"85739",
    "addr:street":"N Lago Del Oro Pkwy",
    "iso:country":"US",
    "sg:address":"16950 N Lago del Oro Pkwy",
    "sg:city":"Tucson",
    "sg:classifiers":[
        {
            "category":"Building & Trades",
            "subcategory":"Landscaping Services",
            "type":"Services"
        }
    ],
    "sg:phone":"+1 520 825 2454",
    "sg:postcode":"85739",
    "sg:province":"AZ",
    "wof:name":"Quality Grounds Maintenance",
    "wof:placetype":"venue"
},
  "geometry": {"coordinates":[-110.886134,32.511352],"type":"Point"}
}