{
  "type": "Feature",
  "properties": {
    "addr:full":"725 E Rd 2 N Chino Valley AZ 86323",
    "addr:housenumber":"725",
    "addr:postcode":"86323",
    "addr:street":"E Rd 2 N Chino Valley",
    "iso:country":"US",
    "sg:address":"725 E Rd 2 N",
    "sg:city":"Chino Valley",
    "sg:classifiers":[
        {
            "category":"Government",
            "subcategory":"Post Office",
            "type":"Public Place"
        }
    ],
    "sg:phone":"+1 928 636 2907",
    "sg:postcode":"86323",
    "sg:province":"AZ",
    "sg:tags":[
        "postal",
        "us"
    ],
    "sg:website":"www.usps.com",
    "wof:name":"US Post Office",
    "wof:placetype":"venue"
},
  "geometry": {"coordinates":[-112.449113,34.760049],"type":"Point"}
}