{
  "type": "Feature",
  "properties": {
    "addr:full":"13040 N 36th St Phoenix AZ 85032",
    "addr:housenumber":"13040",
    "addr:postcode":"85032",
    "addr:street":"N 36Th St",
    "iso:country":"US",
    "sg:address":"13040 N 36th St",
    "sg:city":"Phoenix",
    "sg:classifiers":[
        {
            "category":"Home & Garden",
            "subcategory":"Furniture",
            "type":"Retail Goods"
        }
    ],
    "sg:phone":"+1 602 404 2664",
    "sg:postcode":"85032",
    "sg:province":"AZ",
    "sg:tags":[
        "equipment",
        "kitchen",
        "cabinet"
    ],
    "wof:name":"Aconda",
    "wof:placetype":"venue"
},
  "geometry": {"coordinates":[-112.00461,33.606296],"type":"Point"}
}