{
  "type": "Feature",
  "properties": {
    "addr:full":"1906 W Orangewood Ave Phoenix AZ 85021",
    "addr:housenumber":"1906",
    "addr:postcode":"85021",
    "addr:street":"W Orangewood Ave",
    "iso:country":"US",
    "sg:address":"1906 W Orangewood Ave",
    "sg:city":"Phoenix",
    "sg:classifiers":[
        {
            "category":"Place Of Worship",
            "subcategory":"Church",
            "type":"Public Place"
        },
        {
            "category":"Place Of Worship",
            "type":"Public Place"
        }
    ],
    "sg:phone":"+1 602 995 3537",
    "sg:postcode":"85021",
    "sg:province":"AZ",
    "sg:tags":[
        "churches-interdenominational",
        "churches-various",
        "denomination"
    ],
    "wof:name":"Palms Gospel Chapel",
    "wof:placetype":"venue"
},
  "geometry": {"coordinates":[-112.099763,33.545849],"type":"Point"}
}