{
  "type": "Feature",
  "properties": {
    "iso:country":"US",
    "sg:address":"705 Kiowa Ave",
    "sg:city":"Lake Havasu City",
    "sg:classifiers":[
        {
            "category":"Utilities",
            "subcategory":"Telephone",
            "type":"Services"
        }
    ],
    "sg:phone":"+1 928 453 0522",
    "sg:postcode":"86403",
    "sg:province":"AZ",
    "sg:tags":[
        "communication"
    ],
    "wof:name":"Citizens Communications Co",
    "wof:placetype":"venue"
},
  "geometry": {"coordinates":[-114.354282,34.493126],"type":"Point"}
}