{
  "type": "Feature",
  "properties": {
    "iso:country":"US",
    "sg:address":"3116 E Shea Blvd",
    "sg:city":"Phoenix",
    "sg:classifiers":[
        {
            "category":"Real Estate",
            "subcategory":"Real Estate Operator",
            "type":"Services"
        }
    ],
    "sg:phone":"+1 602 692 8205",
    "sg:postcode":"85028",
    "sg:province":"AZ",
    "sg:tags":[
        "investment"
    ],
    "wof:name":"F M S V Investments LLC",
    "wof:placetype":"venue"
},
  "geometry": {"coordinates":[-112.013402,33.582546],"type":"Point"}
}