{
  "type": "Feature",
  "properties": {
    "addr:full":"109 Whipple Pl Prescott AZ 86301",
    "addr:housenumber":"109",
    "addr:postcode":"86301",
    "addr:street":"Whipple Pl",
    "iso:country":"US",
    "sg:address":"109 Whipple Pl",
    "sg:city":"Prescott",
    "sg:classifiers":[
        {
            "category":"Manufacturing",
            "subcategory":"Signs",
            "type":"Manufacturing & Wholesale Goods"
        }
    ],
    "sg:phone":"+1 928 778 6148",
    "sg:postcode":"86301",
    "sg:province":"AZ",
    "sg:tags":[
        "specialty",
        "mfg"
    ],
    "wof:name":"George Crawford Signs",
    "wof:placetype":"venue"
},
  "geometry": {"coordinates":[-112.46880299999999,34.556388],"type":"Point"}
}