{
  "type": "Feature",
  "properties": {
    "iso:country":"US",
    "sg:address":"1520 N Scottsdale Rd",
    "sg:city":"Tempe",
    "sg:classifiers":[
        {
            "category":"Personal",
            "subcategory":"Beauty Salon",
            "type":"Services"
        }
    ],
    "sg:phone":"+1 480 946 0400",
    "sg:postcode":"85281",
    "sg:province":"AZ",
    "wof:name":"Fringez Hair Svc",
    "wof:placetype":"venue"
},
  "geometry": {"coordinates":[-111.926513,33.445035],"type":"Point"}
}