{
  "type": "Feature",
  "properties": {
    "iso:country":"US",
    "sg:address":"11782 N 91st Ave Ste 2",
    "sg:city":"Peoria",
    "sg:classifiers":[
        {
            "category":"Home & Garden",
            "subcategory":"Home Furnishings",
            "type":"Retail Goods"
        },
        {
            "category":"Building & Trades",
            "subcategory":"Construction",
            "type":"Services"
        },
        {
            "category":"Manufacturing",
            "subcategory":"Building Materials",
            "type":"Manufacturing & Wholesale Goods"
        },
        {
            "category":"Home & Garden",
            "subcategory":"Furniture",
            "type":"Retail Goods"
        }
    ],
    "sg:phone":"+1 623 878 4085",
    "sg:postcode":"85345",
    "sg:province":"AZ",
    "sg:tags":[
        "industrial",
        "cabinetmakers-commercial",
        "carpenter",
        "cabinet",
        "refacing",
        "resurfacing",
        "equipment-household",
        "maker",
        "cabinets-refinishing",
        "kitchen"
    ],
    "wof:name":"Custom Woodworking & Remodeling",
    "wof:placetype":"venue"
},
  "geometry": {"coordinates":[-112.255127,33.591652],"type":"Point"}
}