{
  "type": "Feature",
  "properties": {
    "iso:country":"US",
    "sg:address":"1826 W Broadway Rd",
    "sg:city":"Mesa",
    "sg:classifiers":[
        {
            "category":"Manufacturing",
            "subcategory":"Metals",
            "type":"Manufacturing & Wholesale Goods"
        }
    ],
    "sg:phone":"+1 480 968 5007",
    "sg:postcode":"85202",
    "sg:province":"AZ",
    "sg:tags":[
        "auto",
        "mfg"
    ],
    "wof:name":"Distrbutor Globl Pet Win Films",
    "wof:placetype":"venue"
},
  "geometry": {"coordinates":[-111.87443,33.407662],"type":"Point"}
}