{
  "type": "Feature",
  "properties": {
    "iso:country":"US",
    "sg:address":"2322 W Northern Ave",
    "sg:city":"Phoenix",
    "sg:classifiers":[
        {
            "category":"Real Estate",
            "subcategory":"Real Estate Agent",
            "type":"Services"
        }
    ],
    "sg:phone":"+1 602 734 7217",
    "sg:postcode":"85021",
    "sg:province":"AZ",
    "sg:tags":[
        "investment"
    ],
    "wof:name":"Northern Village",
    "wof:placetype":"venue"
},
  "geometry": {"coordinates":[-112.109696,33.553198],"type":"Point"}
}