{
  "type": "Feature",
  "properties": {
    "addr:full":"6900 E 2nd St Scottsdale AZ 85251",
    "addr:housenumber":"6900",
    "addr:postcode":"85251",
    "addr:street":"E 2Nd St",
    "iso:country":"US",
    "sg:address":"6900 E 2nd St",
    "sg:city":"Scottsdale",
    "sg:classifiers":[
        {
            "category":"Banks & Credit Unions",
            "subcategory":"Bank",
            "type":"Services"
        }
    ],
    "sg:phone":"+1 480 505 2222",
    "sg:postcode":"85251",
    "sg:province":"AZ",
    "sg:tags":[
        "broker",
        "mortgage"
    ],
    "wof:name":"Westtec Mortgage",
    "wof:placetype":"venue"
},
  "geometry": {"coordinates":[-111.930487,33.491264],"type":"Point"}
}