{
  "type": "Feature",
  "properties": {
    "iso:country":"US",
    "sg:address":"4401 E Kleindale Rd",
    "sg:city":"Tucson",
    "sg:classifiers":[
        {
            "category":"Banks & Credit Unions",
            "subcategory":"Investment Brokerage",
            "type":"Services"
        }
    ],
    "sg:phone":"+1 520 319 9747",
    "sg:postcode":"85712",
    "sg:province":"AZ",
    "sg:tags":[
        "security"
    ],
    "wof:name":"Ah Distributors",
    "wof:placetype":"venue"
},
  "geometry": {"coordinates":[-110.89887,32.269216],"type":"Point"}
}