{
  "type": "Feature",
  "properties": {
    "iso:country":"US",
    "sg:address":"2245 W University Dr",
    "sg:city":"Tempe",
    "sg:classifiers":[
        {
            "category":"Autos & Motor Vehicles",
            "subcategory":"Auto Supplies",
            "type":"Retail Goods"
        }
    ],
    "sg:phone":"+1 480 228 8940",
    "sg:postcode":"85281",
    "sg:province":"AZ",
    "sg:tags":[
        "wheel"
    ],
    "wof:name":"Rim 1 Custom Wheels",
    "wof:placetype":"venue"
},
  "geometry": {"coordinates":[-111.972472,33.421925],"type":"Point"}
}