{
  "type": "Feature",
  "properties": {
    "iso:country":"US",
    "sg:address":"6772 W Louise Dr",
    "sg:city":"Glendale",
    "sg:classifiers":[
        {
            "category":"Professional",
            "type":"Services"
        }
    ],
    "sg:phone":"+1 623 561 2849",
    "sg:postcode":"85310",
    "sg:province":"AZ",
    "wof:name":"Jumpee Things Incorporated",
    "wof:placetype":"venue"
},
  "geometry": {"coordinates":[-112.205791,33.684387],"type":"Point"}
}