{
  "type": "Feature",
  "properties": {
    "iso:country":"US",
    "sg:address":"3525 E Grant Rd",
    "sg:city":"Tucson",
    "sg:classifiers":[
        {
            "category":"Shopping",
            "subcategory":"Clothing, Apparel, & Fashions",
            "type":"Retail Goods"
        }
    ],
    "sg:phone":"+1 520 795 3493",
    "sg:postcode":"85716",
    "sg:province":"AZ",
    "sg:tags":[
        "uniform"
    ],
    "wof:name":"Jeri's Old Town Uniforms",
    "wof:placetype":"venue"
},
  "geometry": {"coordinates":[-110.916679,32.250594],"type":"Point"}
}