{
  "type": "Feature",
  "properties": {
    "iso:country":"US",
    "sg:address":"2456 N Pantano Rd",
    "sg:city":"Tucson",
    "sg:classifiers":[
        {
            "category":"Building & Trades",
            "subcategory":"Construction",
            "type":"Services"
        }
    ],
    "sg:phone":"+1 520 733 0400",
    "sg:postcode":"85715",
    "sg:province":"AZ",
    "sg:tags":[
        "company"
    ],
    "wof:name":"S E Construction",
    "wof:placetype":"venue"
},
  "geometry": {"coordinates":[-110.823544,32.252012],"type":"Point"}
}