{
  "type": "Feature",
  "properties": {
    "iso:country":"US",
    "sg:address":"3731 E Main St",
    "sg:city":"Mesa",
    "sg:classifiers":[
        {
            "category":"Bars & Pubs",
            "type":"Food & Drink"
        }
    ],
    "sg:phone":"+1 480 641 2125",
    "sg:postcode":"85205",
    "sg:province":"AZ",
    "sg:tags":[
        "drinking"
    ],
    "wof:name":"Roosters Country",
    "wof:placetype":"venue"
},
  "geometry": {"coordinates":[-111.749736,33.415447],"type":"Point"}
}