{
  "type": "Feature",
  "properties": {
    "iso:country":"US",
    "sg:address":"100 N Stone Ave",
    "sg:city":"Tucson",
    "sg:classifiers":[
        {
            "category":"Professional",
            "subcategory":"Lawyer & Legal Services",
            "type":"Services"
        }
    ],
    "sg:phone":"+1 520 623 5721",
    "sg:postcode":"85701",
    "sg:province":"AZ",
    "sg:tags":[
        "attorney"
    ],
    "wof:name":"Aboud & Aboud",
    "wof:placetype":"venue"
},
  "geometry": {"coordinates":[-110.971621,32.224311],"type":"Point"}
}