{
  "type": "Feature",
  "properties": {
    "iso:country":"US",
    "sg:address":"1322 W Saint Marys Rd",
    "sg:city":"Tucson",
    "sg:classifiers":[
        {
            "category":"Real Estate",
            "subcategory":"Real Estate Agent",
            "type":"Services"
        }
    ],
    "sg:phone":"+1 520 623 8200",
    "sg:postcode":"85745",
    "sg:province":"AZ",
    "wof:name":"Palo Verde Real Estate",
    "wof:placetype":"venue"
},
  "geometry": {"coordinates":[-110.994137,32.229277],"type":"Point"}
}