{
  "type": "Feature",
  "properties": {
    "addr:full":"1322 W Saint Marys Rd Tucson AZ 85745",
    "addr:housenumber":"1322",
    "addr:postcode":"85745",
    "addr:street":"W Saint Marys Rd",
    "iso:country":"US",
    "sg:address":"1322 W Saint Marys Rd",
    "sg:city":"Tucson",
    "sg:classifiers":[
        {
            "category":"Real Estate",
            "subcategory":"Real Estate Agent",
            "type":"Services"
        }
    ],
    "sg:phone":"+1 520 623 8200",
    "sg:postcode":"85745",
    "sg:province":"AZ",
    "wof:name":"Palo Verde Real Estate",
    "wof:placetype":"venue"
},
  "geometry": {"coordinates":[-110.99413699999999,32.229277],"type":"Point"}
}