{
  "type": "Feature",
  "properties": {
    "addr:full":"1500 N Priest Dr Tempe AZ 85281",
    "addr:housenumber":"1500",
    "addr:postcode":"85281",
    "addr:street":"N Priest Dr",
    "iso:country":"US",
    "sg:address":"1500 N Priest Dr",
    "sg:city":"Tempe",
    "sg:classifiers":[
        {
            "category":"Food & Beverages",
            "subcategory":"Groceries & Convenience Stores",
            "type":"Retail Goods"
        }
    ],
    "sg:phone":"+1 520 722 6434",
    "sg:postcode":"85281",
    "sg:province":"AZ",
    "sg:website":"http://www.circlek.com",
    "wof:name":"Circle K",
    "wof:placetype":"venue"
},
  "geometry": {"coordinates":[-111.954971,33.44458],"type":"Point"}
}