{
  "type": "Feature",
  "properties": {
    "iso:country":"US",
    "sg:address":"4080 S Fairway Groves Pl",
    "sg:city":"Tucson",
    "sg:classifiers":[
        {
            "category":"Manufacturing",
            "subcategory":"Glass & Minerals",
            "type":"Manufacturing & Wholesale Goods"
        }
    ],
    "sg:phone":"+1 520 733 9275",
    "sg:postcode":"85730",
    "sg:province":"AZ",
    "sg:tags":[
        "product",
        "nonmetallic",
        "mfg"
    ],
    "wof:name":"Steel Mirage LLC",
    "wof:placetype":"venue"
},
  "geometry": {"coordinates":[-110.80137999999999,32.17491],"type":"Point"}
}