{
  "type": "Feature",
  "properties": {
    "addr:full":"1457 W Harvard Ave Gilbert AZ 85233",
    "addr:housenumber":"1457",
    "addr:postcode":"85233",
    "addr:street":"W Harvard Ave",
    "iso:country":"US",
    "sg:address":"1457 W Harvard Ave",
    "sg:city":"Gilbert",
    "sg:classifiers":[
        {
            "category":"Building & Trades",
            "subcategory":"Construction",
            "type":"Services"
        }
    ],
    "sg:phone":"+1 480 838 8850",
    "sg:postcode":"85233",
    "sg:province":"AZ",
    "sg:tags":[
        "contractor"
    ],
    "sg:website":"www.avgdoor.com",
    "wof:name":"All Valley Garage Door Company",
    "wof:placetype":"venue"
},
  "geometry": {"coordinates":[-111.821376,33.36691],"type":"Point"}
}