{
  "type": "Feature",
  "properties": {
    "iso:country":"US",
    "sg:address":"2320 W Mission Ln",
    "sg:city":"Phoenix",
    "sg:classifiers":[
        {
            "category":"Professional",
            "subcategory":"Business Services",
            "type":"Services"
        },
        {
            "category":"Building & Trades",
            "subcategory":"Construction",
            "type":"Services"
        }
    ],
    "sg:phone":"+1 602 997 6595",
    "sg:postcode":"85021",
    "sg:province":"AZ",
    "sg:tags":[
        "television",
        "telephone",
        "cable",
        "contractor"
    ],
    "wof:name":"Applied Business Comm LLC",
    "wof:placetype":"venue"
},
  "geometry": {"coordinates":[-112.109271,33.569503],"type":"Point"}
}