{
  "type": "Feature",
  "properties": {
    "iso:country":"US",
    "sg:address":"6009 E 22nd St",
    "sg:city":"Tucson",
    "sg:classifiers":[
        {
            "category":"Personal",
            "subcategory":"Beauty Salon",
            "type":"Services"
        }
    ],
    "sg:phone":"+1 520 745 0932",
    "sg:postcode":"85711",
    "sg:province":"AZ",
    "wof:name":"Exclusive Touch Llc",
    "wof:placetype":"venue"
},
  "geometry": {"coordinates":[-110.864317,32.207051],"type":"Point"}
}