{
  "type": "Feature",
  "properties": {
    "iso:country":"US",
    "sg:address":"2146 E Sherri Dr",
    "sg:city":"Gilbert",
    "sg:classifiers":[
        {
            "category":"Shopping",
            "type":"Retail Goods"
        }
    ],
    "sg:phone":"+1 480 219 8982",
    "sg:postcode":"85296",
    "sg:province":"AZ",
    "sg:tags":[
        "merchandise"
    ],
    "wof:name":"This Little Light Mine Candles",
    "wof:placetype":"venue"
},
  "geometry": {"coordinates":[-111.741903,33.328965],"type":"Point"}
}