{
  "type": "Feature",
  "properties": {
    "iso:country":"US",
    "sg:address":"111 Elk Rd",
    "sg:city":"Page",
    "sg:classifiers":[
        {
            "category":"Organizations",
            "subcategory":"Religious Organization",
            "type":"Services"
        }
    ],
    "sg:phone":"+1 928 645 0236",
    "sg:postcode":"86040",
    "sg:province":"AZ",
    "sg:tags":[
        "church"
    ],
    "wof:name":"Navajo Fellowship Baptist Chr",
    "wof:placetype":"venue"
},
  "geometry": {"coordinates":[-111.471651,36.906066],"type":"Point"}
}