{
  "type": "Feature",
  "properties": {
    "addr:full":"68 N Harrison Rd Tucson AZ 85748",
    "addr:housenumber":"68",
    "addr:postcode":"85748",
    "addr:street":"N Harrison Rd",
    "iso:country":"US",
    "sg:address":"68 N Harrison Rd",
    "sg:city":"Tucson",
    "sg:classifiers":[
        {
            "category":"Restaurant",
            "type":"Food & Drink"
        }
    ],
    "sg:phone":"+1 520 296 3628",
    "sg:postcode":"85748",
    "sg:province":"AZ",
    "sg:website":"www.buffalowildwings.com",
    "wof:name":"Buffalo Wild Wings Grill & Bar",
    "wof:placetype":"venue"
},
  "geometry": {"coordinates":[-110.78967900000001,32.222362],"type":"Point"}
}