{
  "type": "Feature",
  "properties": {
    "addr:full":"1950 Centers Ave Lake Havasu City AZ 86403",
    "addr:postcode":"86403",
    "addr:street":"Centers Ave",
    "iso:country":"US",
    "sg:address":"1950 Centers Ave",
    "sg:city":"Lake Havasu City",
    "sg:classifiers":[
        {
            "category":"Manufacturing",
            "subcategory":"Metals",
            "type":"Manufacturing & Wholesale Goods"
        }
    ],
    "sg:phone":"+1 928 453 4444",
    "sg:postcode":"86403",
    "sg:province":"AZ",
    "sg:tags":[
        "machine",
        "parts",
        "mfg"
    ],
    "wof:name":"Graphite Machining Torrance",
    "wof:placetype":"venue"
},
  "geometry": {"coordinates":[-114.34459,34.505852],"type":"Point"}
}