{
  "type": "Feature",
  "properties": {
    "iso:country":"US",
    "sg:address":"1090 W Hwy 89A",
    "sg:city":"Sedona",
    "sg:classifiers":[
        {
            "category":"Organizations",
            "subcategory":"Religious Organization",
            "type":"Services"
        }
    ],
    "sg:phone":"+1 928 282 7405",
    "sg:postcode":"86336",
    "sg:province":"AZ",
    "sg:tags":[
        "church"
    ],
    "wof:name":"Crestview Community Church",
    "wof:placetype":"venue"
},
  "geometry": {"coordinates":[-111.780264,34.862707],"type":"Point"}
}