{
  "type": "Feature",
  "properties": {
    "iso:country":"US",
    "sg:address":"59 N Grand Ave",
    "sg:city":"Nogales",
    "sg:classifiers":[
        {
            "category":"Shopping",
            "subcategory":"Shoes",
            "type":"Retail Goods"
        }
    ],
    "sg:phone":"+1 520 287 3536",
    "sg:postcode":"85621",
    "sg:province":"AZ",
    "wof:name":"Nogales Shoes",
    "wof:placetype":"venue"
},
  "geometry": {"coordinates":[-110.940585,31.335837],"type":"Point"}
}