{
  "type": "Feature",
  "properties": {
    "addr:full":"11221 S Dean Rd Buckeye AZ 85326",
    "addr:housenumber":"11221",
    "addr:postcode":"85326",
    "addr:street":"S Dean Rd",
    "iso:country":"US",
    "sg:address":"11221 S Dean Rd",
    "sg:city":"Buckeye",
    "sg:classifiers":[
        {
            "category":"Personal",
            "subcategory":"Beauty Salon",
            "type":"Services"
        }
    ],
    "sg:phone":"+1 623 523 2272",
    "sg:postcode":"85326",
    "sg:province":"AZ",
    "wof:name":"Spa Skin Care Sales",
    "wof:placetype":"venue"
},
  "geometry": {"coordinates":[-112.521477,33.342628],"type":"Point"}
}