{
  "type": "Feature",
  "properties": {
    "iso:country":"US",
    "sg:address":"8920 S. Hardy Dr",
    "sg:city":"Tempe",
    "sg:classifiers":[
        {
            "category":"Building & Trades",
            "subcategory":"Landscaping Services",
            "type":"Services"
        },
        {
            "category":"Home & Garden",
            "subcategory":"Building Materials",
            "type":"Retail Goods"
        },
        {
            "category":"Building & Trades",
            "subcategory":"Construction",
            "type":"Services"
        },
        {
            "category":"Sports & Exercise",
            "subcategory":"Swimming Pool",
            "type":"Entertainment"
        }
    ],
    "sg:phone":"+1 480 777 9305",
    "sg:postcode":"85284",
    "sg:province":"AZ",
    "sg:tags":[
        "consulting",
        "designer",
        "wall",
        "consultant",
        "builder",
        "landscape",
        "designing",
        "retaining",
        "gazebo",
        "patio"
    ],
    "sg:website":"http://www.creativeenvironments.com",
    "wof:name":"Creative Environments Design and Landscape",
    "wof:placetype":"venue"
},
  "geometry": {"coordinates":[-111.954301,33.33167],"type":"Point"}
}