{
  "type": "Feature",
  "properties": {
    "iso:country":"US",
    "sg:address":"3404 S McClintock Dr",
    "sg:city":"Tempe",
    "sg:classifiers":[
        {
            "category":"Professional",
            "subcategory":"Research",
            "type":"Services"
        }
    ],
    "sg:phone":"+1 602 495 1472",
    "sg:postcode":"85281",
    "sg:province":"AZ",
    "sg:tags":[
        "foundation",
        "philanthropic"
    ],
    "wof:name":"Leukemia Foundation Of Arizona",
    "wof:placetype":"venue"
},
  "geometry": {"coordinates":[-111.90921,33.391915],"type":"Point"}
}