{
  "type": "Feature",
  "properties": {
    "iso:country":"US",
    "sg:address":"3433 W Van Buren St",
    "sg:city":"Phoenix",
    "sg:classifiers":[
        {
            "category":"Banks & Credit Unions",
            "subcategory":"Bank",
            "type":"Services"
        }
    ],
    "sg:phone":"+1 602 353 9549",
    "sg:postcode":"85009",
    "sg:province":"AZ",
    "sg:tags":[
        "depository",
        "banking"
    ],
    "wof:name":"Order Express Inc",
    "wof:placetype":"venue"
},
  "geometry": {"coordinates":[-112.132133,33.45134],"type":"Point"}
}