{
  "type": "Feature",
  "properties": {
    "addr:full":"19965 E Elliot Rd Mesa AZ 85212",
    "addr:housenumber":"19965",
    "addr:postcode":"85212",
    "addr:street":"E Elliot Rd",
    "iso:country":"US",
    "sg:address":"19965 E Elliot Rd",
    "sg:city":"Mesa",
    "sg:classifiers":[
        {
            "category":"Farming",
            "subcategory":"Dairy Farm",
            "type":"Manufacturing & Wholesale Goods"
        }
    ],
    "sg:phone":"+1 480 984 4693",
    "sg:postcode":"85212",
    "sg:province":"AZ",
    "wof:name":"Jim Boyle Dairy",
    "wof:placetype":"venue"
},
  "geometry": {"coordinates":[-111.65590400000001,33.350253],"type":"Point"}
}