{
  "type": "Feature",
  "properties": {
    "iso:country":"US",
    "sg:address":"3250 E Speedway Blvd",
    "sg:city":"Tucson",
    "sg:classifiers":[
        {
            "category":"Restaurant",
            "type":"Food & Drink"
        }
    ],
    "sg:menulink":"http://www.allmenus.com/az/tucson/284705-guilin-chinese-restaurant/menu/",
    "sg:phone":"+1 520 320 7768",
    "sg:postcode":"85716",
    "sg:province":"AZ",
    "sg:tags":[
        "asian",
        "chinese"
    ],
    "wof:name":"Guilin Chinese Restaurant",
    "wof:placetype":"venue"
},
  "geometry": {"coordinates":[-110.923404,32.235779],"type":"Point"}
}