{
  "type": "Feature",
  "properties": {
    "addr:full":"14010 N 127th Dr El Mirage AZ 85335",
    "addr:housenumber":"14010",
    "addr:postcode":"85335",
    "addr:street":"N 127Th Dr",
    "iso:country":"US",
    "sg:address":"14010 N 127th Dr",
    "sg:city":"El Mirage",
    "sg:classifiers":[
        {
            "category":"Freight",
            "type":"Transportation"
        }
    ],
    "sg:phone":"+1 623 523 0235",
    "sg:postcode":"85335",
    "sg:province":"AZ",
    "sg:tags":[
        "trucking"
    ],
    "wof:name":"Desert Auto Transport",
    "wof:placetype":"venue"
},
  "geometry": {"coordinates":[-112.334035,33.611728],"type":"Point"}
}