{
  "type": "Feature",
  "properties": {
    "iso:country":"US",
    "sg:address":"204 N Fraser Dr E",
    "sg:city":"Mesa",
    "sg:classifiers":[
        {
            "category":"Building & Trades",
            "subcategory":"Construction",
            "type":"Services"
        }
    ],
    "sg:phone":"+1 480 495 9967",
    "sg:postcode":"85203",
    "sg:province":"AZ",
    "sg:tags":[
        "fence",
        "contractor"
    ],
    "wof:name":"English Gardener",
    "wof:placetype":"venue"
},
  "geometry": {"coordinates":[-111.810863,33.421286],"type":"Point"}
}