{
  "type": "Feature",
  "properties": {
    "addr:full":"7777 E Paradise Ln # 100 Scottsdale AZ 85260",
    "addr:housenumber":"7777",
    "addr:postcode":"85260",
    "addr:street":"E Paradise Ln # 100",
    "iso:country":"US",
    "sg:address":"7777 E Paradise Ln # 100",
    "sg:city":"Scottsdale",
    "sg:classifiers":[
        {
            "category":"Food & Beverages",
            "subcategory":"Liquor & Beverages",
            "type":"Retail Goods"
        }
    ],
    "sg:phone":"+1 480 922 6161",
    "sg:postcode":"85260",
    "sg:province":"AZ",
    "sg:tags":[
        "bottler",
        "beverages-distributors"
    ],
    "wof:name":"Aloe Splash Inc",
    "wof:placetype":"venue"
},
  "geometry": {"coordinates":[-111.913639,33.632952],"type":"Point"}
}