{
  "type": "Feature",
  "properties": {
    "iso:country":"US",
    "sg:address":"1539 W Hatcher Rd",
    "sg:city":"Phoenix",
    "sg:classifiers":[
        {
            "category":"Autos & Motor Vehicles",
            "subcategory":"Auto Supplies",
            "type":"Retail Goods"
        },
        {
            "category":"Retail",
            "subcategory":"Auto Repair",
            "type":"Services"
        }
    ],
    "sg:phone":"+1 480 751 5564",
    "sg:postcode":"85021",
    "sg:province":"AZ",
    "sg:tags":[
        "oil",
        "transmission",
        "automobile",
        "lube",
        "brake",
        "equipment-service",
        "air conditioning"
    ],
    "sg:website":"http://www.3aautomotive.com",
    "wof:name":"3A Automotive Services",
    "wof:placetype":"venue"
},
  "geometry": {"coordinates":[-112.09204800000001,33.571216],"type":"Point"}
}