{
  "type": "Feature",
  "properties": {
    "iso:country":"US",
    "sg:address":"4182 N Sunset Cliff Dr",
    "sg:city":"Tucson",
    "sg:classifiers":[
        {
            "category":"Building & Trades",
            "subcategory":"Construction",
            "type":"Services"
        }
    ],
    "sg:phone":"+1 520 760 5084",
    "sg:postcode":"85750",
    "sg:province":"AZ",
    "sg:tags":[
        "home",
        "builder"
    ],
    "wof:name":"Monterey Homes Sabino Mountain",
    "wof:placetype":"venue"
},
  "geometry": {"coordinates":[-110.827194,32.282412],"type":"Point"}
}