{
  "type": "Feature",
  "properties": {
    "iso:country":"US",
    "sg:address":"140 Elmersville Rd",
    "sg:city":"Sedona",
    "sg:classifiers":[
        {
            "category":"Professional",
            "subcategory":"Computer Services",
            "type":"Services"
        }
    ],
    "sg:phone":"+1 928 204 1444",
    "sg:postcode":"86336",
    "sg:province":"AZ",
    "sg:tags":[
        "internet"
    ],
    "wof:name":"Red Planet Technologies",
    "wof:placetype":"venue"
},
  "geometry": {"coordinates":[-111.857685,34.831122],"type":"Point"}
}