{
  "type": "Feature",
  "properties": {
    "iso:country":"US",
    "sg:address":"501 N 3rd St",
    "sg:city":"Kingman",
    "sg:classifiers":[
        {
            "category":"Utilities",
            "subcategory":"Telephone",
            "type":"Services"
        }
    ],
    "sg:phone":"+1 928 753 6385",
    "sg:postcode":"86401",
    "sg:province":"AZ",
    "sg:tags":[
        "company"
    ],
    "wof:name":"American Telephone & Telegraph",
    "wof:placetype":"venue"
},
  "geometry": {"coordinates":[-114.054106,35.19301],"type":"Point"}
}