{
  "type": "Feature",
  "properties": {
    "iso:country":"US",
    "sg:address":"4140 N 78th St",
    "sg:city":"Scottsdale",
    "sg:classifiers":[
        {
            "category":"Professional",
            "type":"Services"
        }
    ],
    "sg:phone":"+1 480 941 3179",
    "sg:postcode":"85251",
    "sg:province":"AZ",
    "wof:name":"Katherine McCleery",
    "wof:placetype":"venue"
},
  "geometry": {"coordinates":[-111.913249,33.497404],"type":"Point"}
}