{
  "type": "Feature",
  "properties": {
    "addr:full":"9515 W Camelback Rd Ste 140 Phoenix AZ 85037",
    "addr:housenumber":"9515",
    "addr:postcode":"85037",
    "addr:street":"W Camelback Rd Ste 140",
    "iso:country":"US",
    "sg:address":"9515 W Camelback Rd Ste 140",
    "sg:city":"Phoenix",
    "sg:classifiers":[
        {
            "category":"Health Services",
            "subcategory":"Dentist",
            "type":"Services"
        }
    ],
    "sg:phone":"+1 623 872 2662",
    "sg:postcode":"85037",
    "sg:province":"AZ",
    "sg:tags":[
        "pediatric"
    ],
    "wof:name":"Kids Dental Place",
    "wof:placetype":"venue"
},
  "geometry": {"coordinates":[-112.26444600000001,33.508479],"type":"Point"}
}