{
  "type": "Feature",
  "properties": {
    "iso:country":"US",
    "sg:address":"6839 E Evans Dr",
    "sg:city":"Scottsdale",
    "sg:classifiers":[
        {
            "category":"Manufacturing",
            "subcategory":"Jewelry",
            "type":"Manufacturing & Wholesale Goods"
        }
    ],
    "sg:phone":"+1 480 607 6697",
    "sg:postcode":"85254",
    "sg:province":"AZ",
    "sg:tags":[
        "stone",
        "jewels-imitation"
    ],
    "wof:name":"Brag Beads",
    "wof:placetype":"venue"
},
  "geometry": {"coordinates":[-111.93292,33.617777],"type":"Point"}
}