{
  "type": "Feature",
  "properties": {
    "addr:full":"3535 W Dunlap Ave Phoenix AZ 85051",
    "addr:housenumber":"3535",
    "addr:postcode":"85051",
    "addr:street":"W Dunlap Ave",
    "iso:country":"US",
    "sg:address":"3535 W Dunlap Ave",
    "sg:city":"Phoenix",
    "sg:classifiers":[
        {
            "category":"Professional",
            "subcategory":"Computer Services",
            "type":"Services"
        }
    ],
    "sg:phone":"+1 602 527 0568",
    "sg:postcode":"85051",
    "sg:province":"AZ",
    "sg:tags":[
        "consultant",
        "designer"
    ],
    "sg:website":"www.progcpu.com",
    "wof:name":"Progressive Computing",
    "wof:placetype":"venue"
},
  "geometry": {"coordinates":[-112.138063,33.56745],"type":"Point"}
}