{
  "type": "Feature",
  "properties": {
    "iso:country":"US",
    "sg:address":"4040 E Superior Ave",
    "sg:city":"Phoenix",
    "sg:classifiers":[
        {
            "category":"Wholesale",
            "subcategory":"Construction Materials",
            "type":"Manufacturing & Wholesale Goods"
        }
    ],
    "sg:phone":"+1 602 454 2900",
    "sg:postcode":"85040",
    "sg:province":"AZ",
    "sg:tags":[
        "lumber"
    ],
    "wof:name":"Banks Lumber",
    "wof:placetype":"venue"
},
  "geometry": {"coordinates":[-111.987635,33.417527],"type":"Point"}
}