{
  "type": "Feature",
  "properties": {
    "iso:country":"US",
    "sg:address":"615 W Congress St",
    "sg:city":"Tucson",
    "sg:classifiers":[
        {
            "category":"Restaurant",
            "type":"Food & Drink"
        }
    ],
    "sg:menulink":"http://www.allmenus.com/az/tucson/161029-carls-jr/menu/",
    "sg:phone":"+1 520 622 0210",
    "sg:postcode":"85745",
    "sg:province":"AZ",
    "sg:tags":[
        "burger",
        "american"
    ],
    "wof:name":"Carl's Jr.",
    "wof:placetype":"venue"
},
  "geometry": {"coordinates":[-110.98112,32.220496],"type":"Point"}
}