{
  "type": "Feature",
  "properties": {
    "addr:full":"6501 E Greenway Pkwy Scottsdale AZ 85254",
    "addr:housenumber":"6501",
    "addr:postcode":"85254",
    "addr:street":"E Greenway Pkwy",
    "iso:country":"US",
    "sg:address":"6501 E Greenway Pkwy",
    "sg:city":"Scottsdale",
    "sg:classifiers":[
        {
            "category":"Health Services",
            "subcategory":"Doctor",
            "type":"Services"
        }
    ],
    "sg:phone":"+1 480 922 0336",
    "sg:postcode":"85254",
    "sg:province":"AZ",
    "sg:tags":[
        "dentist"
    ],
    "wof:name":"Eagle Bend Dentistry",
    "wof:placetype":"venue"
},
  "geometry": {"coordinates":[-111.939499,33.624976],"type":"Point"}
}