{
  "type": "Feature",
  "properties": {
    "iso:country":"US",
    "sg:address":"12436 N 28th Dr",
    "sg:city":"Phoenix",
    "sg:classifiers":[
        {
            "category":"Recreation",
            "type":"Entertainment"
        }
    ],
    "sg:phone":"+1 602 942 9745",
    "sg:postcode":"85029",
    "sg:province":"AZ",
    "sg:tags":[
        "amusement"
    ],
    "wof:name":"Anime Gamer",
    "wof:placetype":"venue"
},
  "geometry": {"coordinates":[-112.11997599999999,33.597906],"type":"Point"}
}