{
  "type": "Feature",
  "properties": {
    "addr:full":"2339 E Indian School Rd Phoenix AZ 85016",
    "addr:housenumber":"2339",
    "addr:postcode":"85016",
    "addr:street":"E Indian School Rd",
    "iso:country":"US",
    "sg:address":"2339 E Indian School Rd",
    "sg:city":"Phoenix",
    "sg:classifiers":[
        {
            "category":"Professional",
            "subcategory":"Business Services",
            "type":"Services"
        },
        {
            "category":"Shopping",
            "subcategory":"Florist",
            "type":"Retail Goods"
        }
    ],
    "sg:phone":"+1 602 955 6591",
    "sg:postcode":"85016",
    "sg:province":"AZ",
    "sg:tags":[
        "product",
        "design",
        "plant",
        "maintenance",
        "bamboo"
    ],
    "sg:website":"http://www.bobstropicalsinc.com",
    "wof:name":"Bob's Tropicals Inc",
    "wof:placetype":"venue"
},
  "geometry": {"coordinates":[-112.03154000000001,33.494808],"type":"Point"}
}