{
  "type": "Feature",
  "properties": {
    "iso:country":"US",
    "sg:address":"7631 E Greenway Rd",
    "sg:city":"Scottsdale",
    "sg:classifiers":[
        {
            "category":"Manufacturing",
            "subcategory":"Tools & Machinery",
            "type":"Manufacturing & Wholesale Goods"
        }
    ],
    "sg:phone":"+1 480 991 1085",
    "sg:postcode":"85260",
    "sg:province":"AZ",
    "sg:tags":[
        "equipment",
        "lighting"
    ],
    "wof:name":"CEMI",
    "wof:placetype":"venue"
},
  "geometry": {"coordinates":[-111.915895,33.625607],"type":"Point"}
}