{
  "type": "Feature",
  "properties": {
    "iso:country":"US",
    "sg:address":"5148 N Cll Bujia",
    "sg:city":"Tucson",
    "sg:classifiers":[
        {
            "category":"Real Estate",
            "subcategory":"Architect",
            "type":"Services"
        }
    ],
    "sg:phone":"+1 520 299 8093",
    "sg:postcode":"85718",
    "sg:province":"AZ",
    "wof:name":"David B Howell",
    "wof:placetype":"venue"
},
  "geometry": {"coordinates":[-110.905233,32.299842],"type":"Point"}
}