{
  "type": "Feature",
  "properties": {
    "iso:country":"US",
    "sg:address":"1661 N Swan Rd",
    "sg:city":"Tucson",
    "sg:classifiers":[
        {
            "category":"Professional",
            "subcategory":"Lawyer & Legal Services",
            "type":"Services"
        }
    ],
    "sg:phone":"+1 520 795 7711",
    "sg:postcode":"85712",
    "sg:province":"AZ",
    "sg:tags":[
        "attorney"
    ],
    "wof:name":"Molin Law Firm",
    "wof:placetype":"venue"
},
  "geometry": {"coordinates":[-110.892717,32.242336],"type":"Point"}
}