{
  "type": "Feature",
  "properties": {
    "iso:country":"US",
    "sg:address":"301 W Camelback Rd",
    "sg:city":"Phoenix",
    "sg:classifiers":[
        {
            "category":"Retail",
            "subcategory":"Funeral Services",
            "type":"Services"
        }
    ],
    "sg:phone":"+1 602 277 2603",
    "sg:postcode":"85013",
    "sg:province":"AZ",
    "sg:tags":[
        "director"
    ],
    "wof:name":"Camelback Sunset Funeral Home",
    "wof:placetype":"venue"
},
  "geometry": {"coordinates":[-112.08248399999999,33.509341],"type":"Point"}
}