{
  "type": "Feature",
  "properties": {
    "iso:country":"US",
    "sg:address":"313 S 7th St",
    "sg:city":"Camp Verde",
    "sg:classifiers":[
        {
            "category":"Professional",
            "subcategory":"Accounting & Tax Preparation",
            "type":"Services"
        }
    ],
    "sg:phone":"+1 928 567 3547",
    "sg:postcode":"86322",
    "sg:province":"AZ",
    "sg:tags":[
        "accountant"
    ],
    "sg:website":"www.shelinecpa.com",
    "wof:name":"Calvin L Sheline CPA Pllc",
    "wof:placetype":"venue"
},
  "geometry": {"coordinates":[-111.861019,34.564457],"type":"Point"}
}