{
  "type": "Feature",
  "properties": {
    "addr:full":"750 N McClintock Dr Tempe AZ 85281",
    "addr:housenumber":"750",
    "addr:postcode":"85281",
    "addr:street":"N Mcclintock Dr",
    "iso:country":"US",
    "sg:address":"750 N McClintock Dr",
    "sg:city":"Tempe",
    "sg:classifiers":[
        {
            "category":"Building & Trades",
            "subcategory":"Construction",
            "type":"Services"
        }
    ],
    "sg:phone":"+1 480 968 2112",
    "sg:postcode":"85281",
    "sg:province":"AZ",
    "sg:tags":[
        "foundation"
    ],
    "wof:name":"Case Foundation",
    "wof:placetype":"venue"
},
  "geometry": {"coordinates":[-111.909646,33.438095],"type":"Point"}
}