{
  "type": "Feature",
  "properties": {
    "iso:country":"US",
    "sg:address":"8311 E Stella Rd",
    "sg:city":"Tucson",
    "sg:classifiers":[
        {
            "category":"Organizations",
            "subcategory":"Religious Organization",
            "type":"Services"
        }
    ],
    "sg:phone":"+1 520 886 7392",
    "sg:postcode":"85730",
    "sg:province":"AZ",
    "sg:tags":[
        "church"
    ],
    "sg:website":"www.watchtower.org",
    "wof:name":"Jehovah's Witnesses",
    "wof:placetype":"venue"
},
  "geometry": {"coordinates":[-110.81088099999999,32.184506],"type":"Point"}
}