{
  "type": "Feature",
  "properties": {
    "addr:full":"835 W 35th St Yuma AZ 85365",
    "addr:housenumber":"835",
    "addr:postcode":"85365",
    "addr:street":"W 35Th St",
    "iso:country":"US",
    "sg:address":"835 W 35th St",
    "sg:city":"Yuma",
    "sg:classifiers":[
        {
            "category":"Farming",
            "subcategory":"Orchard",
            "type":"Manufacturing & Wholesale Goods"
        }
    ],
    "sg:phone":"+1 928 344 0133",
    "sg:postcode":"85365",
    "sg:province":"AZ",
    "sg:tags":[
        "citrus",
        "grove",
        "fruit"
    ],
    "wof:name":"Loghry John",
    "wof:placetype":"venue"
},
  "geometry": {"coordinates":[-114.63025,32.663361],"type":"Point"}
}