{
  "type": "Feature",
  "properties": {
    "iso:country":"US",
    "sg:address":"13419 N 54th Dr",
    "sg:city":"Glendale",
    "sg:classifiers":[
        {
            "category":"Communications",
            "type":"Services"
        }
    ],
    "sg:phone":"+1 602 843 8141",
    "sg:postcode":"85304",
    "sg:province":"AZ",
    "sg:tags":[
        "communication"
    ],
    "wof:name":"Illuminata Communications LLC",
    "wof:placetype":"venue"
},
  "geometry": {"coordinates":[-112.176041,33.605371],"type":"Point"}
}