{
  "type": "Feature",
  "properties": {
    "addr:full":"601 N Jackrabbit Trl Buckeye AZ 85326",
    "addr:housenumber":"601",
    "addr:postcode":"85326",
    "addr:street":"N Jackrabbit Trl",
    "iso:country":"US",
    "sg:address":"601 N Jackrabbit Trl",
    "sg:city":"Buckeye",
    "sg:classifiers":[
        {
            "category":"Home & Garden",
            "subcategory":"Building Materials",
            "type":"Retail Goods"
        }
    ],
    "sg:phone":"+1 623 853 8300",
    "sg:postcode":"85326",
    "sg:province":"AZ",
    "wof:name":"Preach Building & Masonry",
    "wof:placetype":"venue"
},
  "geometry": {"coordinates":[-112.478804,33.453877],"type":"Point"}
}