{
  "type": "Feature",
  "properties": {
    "iso:country":"US",
    "sg:address":"6544 E Osborn Rd",
    "sg:city":"Scottsdale",
    "sg:classifiers":[
        {
            "category":"Building & Trades",
            "subcategory":"Construction",
            "type":"Services"
        }
    ],
    "sg:phone":"+1 480 946 9664",
    "sg:postcode":"85251",
    "sg:province":"AZ",
    "sg:tags":[
        "hanging",
        "contractor"
    ],
    "wof:name":"Procraft Painting",
    "wof:placetype":"venue"
},
  "geometry": {"coordinates":[-111.938889,33.487592],"type":"Point"}
}