{
  "type": "Feature",
  "properties": {
    "iso:country":"US",
    "sg:address":"4525 W Moon Blossum Ln",
    "sg:city":"Phoenix",
    "sg:classifiers":[
        {
            "category":"Real Estate",
            "subcategory":"Real Estate Services",
            "type":"Services"
        },
        {
            "category":"Banks & Credit Unions",
            "subcategory":"Financial Services",
            "type":"Services"
        }
    ],
    "sg:phone":"+1 623 879 6111",
    "sg:postcode":"85083",
    "sg:province":"AZ",
    "sg:tags":[
        "loan",
        "processing"
    ],
    "wof:name":"Moon Valley Mortgage LLC",
    "wof:placetype":"venue"
},
  "geometry": {"coordinates":[-112.156466,33.720755],"type":"Point"}
}