{
  "type": "Feature",
  "properties": {
    "iso:country":"US",
    "sg:address":"4355 E University Dr",
    "sg:city":"Mesa",
    "sg:classifiers":[
        {
            "category":"Restaurant",
            "type":"Food & Drink"
        }
    ],
    "sg:menulink":"http://www.allmenus.com/az/phoenix/64028-subway/menu/",
    "sg:phone":"+1 480 654 8479",
    "sg:postcode":"85205",
    "sg:province":"AZ",
    "sg:tags":[
        "american",
        "sandwich"
    ],
    "wof:name":"Subway",
    "wof:placetype":"venue"
},
  "geometry": {"coordinates":[-111.738297,33.422713],"type":"Point"}
}