{
  "type": "Feature",
  "properties": {
    "addr:full":"22023 N 20th Ave Phoenix AZ 85027",
    "addr:housenumber":"22023",
    "addr:postcode":"85027",
    "addr:street":"N 20Th Ave",
    "iso:country":"US",
    "sg:address":"22023 N 20th Ave",
    "sg:city":"Phoenix",
    "sg:classifiers":[
        {
            "category":"Building & Trades",
            "subcategory":"Construction",
            "type":"Services"
        }
    ],
    "sg:phone":"+1 623 780 2221",
    "sg:postcode":"85027",
    "sg:province":"AZ",
    "wof:name":"C S Construction Inc",
    "wof:placetype":"venue"
},
  "geometry": {"coordinates":[-112.102012,33.686009],"type":"Point"}
}