{
  "type": "Feature",
  "properties": {
    "iso:country":"US",
    "sg:address":"804 US Hwy 60",
    "sg:city":"Superior",
    "sg:classifiers":[
        {
            "category":"Autos & Motor Vehicles",
            "subcategory":"Auto Supplies",
            "type":"Retail Goods"
        }
    ],
    "sg:phone":"+1 520 689 5357",
    "sg:postcode":"85273",
    "sg:province":"AZ",
    "wof:name":"Southwest 24 Hr Towing",
    "wof:placetype":"venue"
},
  "geometry": {"coordinates":[-111.104679,33.287585],"type":"Point"}
}