{
  "type": "Feature",
  "properties": {
    "iso:country":"US",
    "sg:address":"13203 N 103rd Ave",
    "sg:city":"Sun City",
    "sg:classifiers":[
        {
            "category":"Wholesale",
            "subcategory":"Medical Equipment & Supplies",
            "type":"Manufacturing & Wholesale Goods"
        },
        {
            "category":"Shopping",
            "subcategory":"Pharmacy",
            "type":"Retail Goods"
        }
    ],
    "sg:phone":"+1 623 933 9399",
    "sg:postcode":"85351",
    "sg:province":"AZ",
    "sg:tags":[
        "physician",
        "surgeon"
    ],
    "wof:name":"Respiratory Solutions",
    "wof:placetype":"venue"
},
  "geometry": {"coordinates":[-112.281155,33.604641],"type":"Point"}
}