{
  "type": "Feature",
  "properties": {
    "iso:country":"US",
    "sg:address":"4081 N Harrison Rd",
    "sg:city":"Tucson",
    "sg:classifiers":[
        {
            "category":"Home & Garden",
            "subcategory":"Home Furnishings",
            "type":"Retail Goods"
        }
    ],
    "sg:phone":"+1 520 326 1551",
    "sg:postcode":"85749",
    "sg:province":"AZ",
    "wof:name":"Arizona Ultrasonics Blind Clea",
    "wof:placetype":"venue"
},
  "geometry": {"coordinates":[-110.789183,32.277437],"type":"Point"}
}