{
  "type": "Feature",
  "properties": {
    "iso:country":"US",
    "sg:address":"1605 N 7th Ave",
    "sg:city":"Phoenix",
    "sg:classifiers":[
        {
            "category":"Shopping",
            "subcategory":"Gifts & Souvenirs",
            "type":"Retail Goods"
        }
    ],
    "sg:phone":"+1 602 712 9338",
    "sg:postcode":"85007",
    "sg:province":"AZ",
    "sg:tags":[
        "used",
        "merchandise"
    ],
    "wof:name":"Root Seller",
    "wof:placetype":"venue"
},
  "geometry": {"coordinates":[-112.082575,33.466745],"type":"Point"}
}