{
  "type": "Feature",
  "properties": {
    "addr:full":"9623 E Ludlow Dr Scottsdale AZ 85260",
    "addr:housenumber":"9623",
    "addr:postcode":"85260",
    "addr:street":"E Ludlow Dr",
    "iso:country":"US",
    "sg:address":"9623 E Ludlow Dr",
    "sg:city":"Scottsdale",
    "sg:classifiers":[
        {
            "category":"Building & Trades",
            "subcategory":"Construction",
            "type":"Services"
        }
    ],
    "sg:phone":"+1 480 551 1404",
    "sg:postcode":"85260",
    "sg:province":"AZ",
    "sg:tags":[
        "painter"
    ],
    "wof:name":"Mc Andrews Painting Co",
    "wof:placetype":"venue"
},
  "geometry": {"coordinates":[-111.873052,33.61252],"type":"Point"}
}