{
  "type": "Feature",
  "properties": {
    "addr:full":"7479 E Sand Hills Rd Scottsdale AZ 85255",
    "addr:housenumber":"7479",
    "addr:postcode":"85255",
    "addr:street":"E Sand Hills Rd",
    "iso:country":"US",
    "sg:address":"7479 E Sand Hills Rd",
    "sg:city":"Scottsdale",
    "sg:classifiers":[
        {
            "category":"Professional",
            "type":"Services"
        }
    ],
    "sg:phone":"+1 480 585 5046",
    "sg:postcode":"85255",
    "sg:province":"AZ",
    "wof:name":"Lauren Brodsky",
    "wof:placetype":"venue"
},
  "geometry": {"coordinates":[-111.919776,33.705595],"type":"Point"}
}