{
  "type": "Feature",
  "properties": {
    "iso:country":"US",
    "sg:address":"1133 N Arroya",
    "sg:city":"Mesa",
    "sg:classifiers":[
        {
            "category":"Wholesale",
            "subcategory":"Groceries",
            "type":"Manufacturing & Wholesale Goods"
        }
    ],
    "sg:phone":"+1 480 924 9763",
    "sg:postcode":"85205",
    "sg:province":"AZ",
    "sg:tags":[
        "general"
    ],
    "wof:name":"Convenience Marketing Network",
    "wof:placetype":"venue"
},
  "geometry": {"coordinates":[-111.711721,33.436625],"type":"Point"}
}