{
  "type": "Feature",
  "properties": {
    "iso:country":"US",
    "sg:address":"4430 E Thistle Landing Dr",
    "sg:city":"Phoenix",
    "sg:classifiers":[
        {
            "category":"Professional",
            "type":"Services"
        },
        {
            "category":"Sports & Exercise",
            "subcategory":"Swimming Pool",
            "type":"Entertainment"
        }
    ],
    "sg:phone":"+1 480 940 7034",
    "sg:postcode":"85044",
    "sg:province":"AZ",
    "sg:tags":[
        "spa",
        "repair",
        "hot",
        "tubs-repair"
    ],
    "wof:name":"Sea Clear Pool Service",
    "wof:placetype":"venue"
},
  "geometry": {"coordinates":[-111.987759,33.31208],"type":"Point"}
}