{
  "type": "Feature",
  "properties": {
    "iso:country":"US",
    "sg:address":"1101 S Rural Rd",
    "sg:city":"Tempe",
    "sg:classifiers":[
        {
            "category":"Professional",
            "type":"Services"
        }
    ],
    "sg:phone":"+1 480 966 1845",
    "sg:postcode":"85281",
    "sg:province":"AZ",
    "sg:tags":[
        "establishment"
    ],
    "wof:name":"Infotouch Technologies",
    "wof:placetype":"venue"
},
  "geometry": {"coordinates":[-111.926286,33.414771],"type":"Point"}
}