{
  "type": "Feature",
  "properties": {
    "addr:full":"731 E Andy Devine Ave Kingman AZ 86401",
    "addr:housenumber":"731",
    "addr:postcode":"86401",
    "addr:street":"E Andy Devine Ave",
    "iso:country":"US",
    "sg:address":"731 E Andy Devine Ave",
    "sg:city":"Kingman",
    "sg:classifiers":[
        {
            "category":"Recreation",
            "type":"Entertainment"
        }
    ],
    "sg:phone":"+1 928 718 1771",
    "sg:postcode":"86401",
    "sg:province":"AZ",
    "sg:tags":[
        "amusement"
    ],
    "wof:name":"All Seasons Motorsports",
    "wof:placetype":"venue"
},
  "geometry": {"coordinates":[-114.046959,35.187632],"type":"Point"}
}