{
  "type": "Feature",
  "properties": {
    "iso:country":"US",
    "sg:address":"1950 E 24th St Lot 151",
    "sg:city":"Yuma",
    "sg:classifiers":[
        {
            "category":"Building & Trades",
            "subcategory":"Construction",
            "type":"Services"
        }
    ],
    "sg:phone":"+1 928 344 4060",
    "sg:postcode":"85365",
    "sg:province":"AZ",
    "sg:tags":[
        "manufactured",
        "housing-communities"
    ],
    "wof:name":"Sunrise Mobile Home Estates",
    "wof:placetype":"venue"
},
  "geometry": {"coordinates":[-114.601791,32.684071],"type":"Point"}
}