{
  "type": "Feature",
  "properties": {
    "iso:country":"US",
    "sg:address":"5524 N 51st Ave",
    "sg:city":"Glendale",
    "sg:classifiers":[
        {
            "category":"Wholesale",
            "subcategory":"Hardware",
            "type":"Manufacturing & Wholesale Goods"
        }
    ],
    "sg:phone":"+1 623 939 1597",
    "sg:postcode":"85301",
    "sg:province":"AZ",
    "sg:tags":[
        "fastener",
        "construction"
    ],
    "wof:name":"Carson Sales Company Inc",
    "wof:placetype":"venue"
},
  "geometry": {"coordinates":[-112.168779,33.517945],"type":"Point"}
}