{
  "type": "Feature",
  "properties": {
    "iso:country":"US",
    "sg:address":"4655 E Lavender Ln",
    "sg:city":"Phoenix",
    "sg:classifiers":[
        {
            "category":"Professional",
            "type":"Services"
        }
    ],
    "sg:phone":"+1 480 705 4363",
    "sg:postcode":"85044",
    "sg:province":"AZ",
    "sg:tags":[
        "establishment"
    ],
    "wof:name":"Mercy Care Plan",
    "wof:placetype":"venue"
},
  "geometry": {"coordinates":[-111.98272,33.322664],"type":"Point"}
}