{
  "type": "Feature",
  "properties": {
    "addr:full":"213 S 11th Ave Phoenix AZ 85007",
    "addr:housenumber":"213",
    "addr:postcode":"85007",
    "addr:street":"S 11Th Ave",
    "iso:country":"US",
    "sg:address":"213 S 11th Ave",
    "sg:city":"Phoenix",
    "sg:classifiers":[
        {
            "category":"Organizations",
            "subcategory":"Religious Organization",
            "type":"Services"
        }
    ],
    "sg:phone":"+1 602 252 9023",
    "sg:postcode":"85007",
    "sg:province":"AZ",
    "sg:website":"http://www.andrehouseaz.org",
    "wof:name":"Andre House",
    "wof:placetype":"venue"
},
  "geometry": {"coordinates":[-112.08699,33.445916],"type":"Point"}
}