{
  "type": "Feature",
  "properties": {
    "addr:full":"2155 E Broadway Rd Mesa AZ 85204",
    "addr:housenumber":"2155",
    "addr:postcode":"85204",
    "addr:street":"E Broadway Rd",
    "iso:country":"US",
    "sg:address":"2155 E Broadway Rd",
    "sg:city":"Mesa",
    "sg:classifiers":[
        {
            "category":"Social Services",
            "subcategory":"Child Care",
            "type":"Services"
        }
    ],
    "sg:phone":"+1 480 962 7205",
    "sg:postcode":"85204",
    "sg:province":"AZ",
    "sg:website":"www.stairstepstolearning.com",
    "wof:name":"Stairsteps To Learning",
    "wof:placetype":"venue"
},
  "geometry": {"coordinates":[-111.785273,33.408048],"type":"Point"}
}