{
  "type": "Feature",
  "properties": {
    "iso:country":"US",
    "sg:address":"2114 W Legends Way",
    "sg:city":"Phoenix",
    "sg:classifiers":[
        {
            "category":"Banks & Credit Unions",
            "subcategory":"Bank",
            "type":"Services"
        }
    ],
    "sg:phone":"+1 602 290 6055",
    "sg:postcode":"85086",
    "sg:province":"AZ",
    "sg:tags":[
        "mortgage"
    ],
    "wof:name":"Anthem Funding Company",
    "wof:placetype":"venue"
},
  "geometry": {"coordinates":[-112.104181,33.870575],"type":"Point"}
}