{
  "type": "Feature",
  "properties": {
    "iso:country":"US",
    "sg:address":"4338 N Scottsdale Rd",
    "sg:city":"Scottsdale",
    "sg:classifiers":[
        {
            "category":"Manufacturing",
            "subcategory":"Pottery",
            "type":"Manufacturing & Wholesale Goods"
        }
    ],
    "sg:phone":"+1 480 945 5122",
    "sg:postcode":"85251",
    "sg:province":"AZ",
    "sg:tags":[
        "pottery-wholesale",
        "manufacturer"
    ],
    "wof:name":"Pottery Paradise Inc",
    "wof:placetype":"venue"
},
  "geometry": {"coordinates":[-111.926182,33.499481],"type":"Point"}
}