{
  "type": "Feature",
  "properties": {
    "iso:country":"US",
    "sg:address":"2988 N Alma School Rd",
    "sg:city":"Chandler",
    "sg:classifiers":[
        {
            "category":"Professional",
            "subcategory":"Business Services",
            "type":"Services"
        }
    ],
    "sg:phone":"+1 480 857 7408",
    "sg:postcode":"85224",
    "sg:province":"AZ",
    "sg:tags":[
        "sewing"
    ],
    "wof:name":"Arizona Stitches",
    "wof:placetype":"venue"
},
  "geometry": {"coordinates":[-111.859149,33.346672],"type":"Point"}
}