{
  "type": "Feature",
  "properties": {
    "iso:country":"US",
    "sg:address":"2514 Navajo Blvd",
    "sg:city":"Holbrook",
    "sg:classifiers":[
        {
            "category":"Travel",
            "subcategory":"Hotels & Motels",
            "type":"Entertainment"
        }
    ],
    "sg:phone":"+1 928 524 6101",
    "sg:postcode":"86025",
    "sg:province":"AZ",
    "wof:name":"Lodging Management Inc",
    "wof:placetype":"venue"
},
  "geometry": {"coordinates":[-110.13115000000001,34.939056],"type":"Point"}
}