{
  "type": "Feature",
  "properties": {
    "iso:country":"US",
    "sg:address":"16602 N 23rd Ave",
    "sg:city":"Phoenix",
    "sg:classifiers":[
        {
            "category":"Utilities",
            "subcategory":"Mobile Phone",
            "type":"Services"
        }
    ],
    "sg:phone":"+1 602 993 4122",
    "sg:postcode":"85023",
    "sg:province":"AZ",
    "sg:tags":[
        "communication",
        "radiotelephone"
    ],
    "wof:name":"Aztex Wireless LLC",
    "wof:placetype":"venue"
},
  "geometry": {"coordinates":[-112.108341,33.636453],"type":"Point"}
}