{
  "type": "Feature",
  "properties": {
    "iso:country":"US",
    "sg:address":"2121 E Larry Caldwell Dr",
    "sg:city":"Prescott",
    "sg:classifiers":[
        {
            "category":"Place Of Worship",
            "type":"Public Place"
        }
    ],
    "sg:phone":"+1 928 445 1421",
    "sg:postcode":"86301",
    "sg:province":"AZ",
    "sg:tags":[
        "church"
    ],
    "wof:name":"The Heights Church",
    "wof:placetype":"venue"
},
  "geometry": {"coordinates":[-112.42066800000001,34.636681],"type":"Point"}
}