{
  "type": "Feature",
  "properties": {
    "addr:full":"1801 S Jentilly Ln Tempe AZ 85281",
    "addr:housenumber":"1801",
    "addr:postcode":"85281",
    "addr:street":"S Jentilly Ln",
    "iso:country":"US",
    "sg:address":"1801 S Jentilly Ln",
    "sg:city":"Tempe",
    "sg:classifiers":[
        {
            "category":"Restaurant",
            "type":"Food & Drink"
        }
    ],
    "sg:phone":"+1 480 968 7763",
    "sg:postcode":"85281",
    "sg:province":"AZ",
    "sg:tags":[
        "eating"
    ],
    "wof:name":"Subway",
    "wof:placetype":"venue"
},
  "geometry": {"coordinates":[-111.923597,33.408381],"type":"Point"}
}