{
  "type": "Feature",
  "properties": {
    "addr:full":"2157 E Teakwood Pl Chandler AZ 85249",
    "addr:housenumber":"2157",
    "addr:postcode":"85249",
    "addr:street":"E Teakwood Pl",
    "iso:country":"US",
    "sg:address":"2157 E Teakwood Pl",
    "sg:city":"Chandler",
    "sg:classifiers":[
        {
            "category":"Autos & Motor Vehicles",
            "subcategory":"Automobile Sales",
            "type":"Retail Goods"
        }
    ],
    "sg:phone":"+1 480 812 3548",
    "sg:postcode":"85249",
    "sg:province":"AZ",
    "sg:tags":[
        "used"
    ],
    "wof:name":"Elite Auto",
    "wof:placetype":"venue"
},
  "geometry": {"coordinates":[-111.80345699999999,33.228077],"type":"Point"}
}