{
  "type": "Feature",
  "properties": {
    "iso:country":"US",
    "sg:address":"8956 E Saguaro Blossom Rd",
    "sg:city":"Apache Junction",
    "sg:classifiers":[
        {
            "category":"Banks & Credit Unions",
            "subcategory":"Financial Services",
            "type":"Services"
        }
    ],
    "sg:phone":"+1 480 982 4808",
    "sg:postcode":"85218",
    "sg:province":"AZ",
    "sg:tags":[
        "trust",
        "management"
    ],
    "wof:name":"Davis Family Trust",
    "wof:placetype":"venue"
},
  "geometry": {"coordinates":[-111.45017900000001,33.362719],"type":"Point"}
}