{
  "type": "Feature",
  "properties": {
    "iso:country":"US",
    "sg:address":"2090 E University Dr",
    "sg:city":"Tempe",
    "sg:classifiers":[
        {
            "category":"Wholesale",
            "subcategory":"Auto Parts",
            "type":"Manufacturing & Wholesale Goods"
        }
    ],
    "sg:phone":"+1 480 894 9641",
    "sg:postcode":"85281",
    "sg:province":"AZ",
    "sg:tags":[
        "supply"
    ],
    "wof:name":"B & K Auto",
    "wof:placetype":"venue"
},
  "geometry": {"coordinates":[-111.895692,33.422171],"type":"Point"}
}