{
  "type": "Feature",
  "properties": {
    "iso:country":"US",
    "sg:address":"29775 122nd Dr",
    "sg:city":"Peoria",
    "sg:classifiers":[
        {
            "category":"Home & Garden",
            "subcategory":"Furniture",
            "type":"Retail Goods"
        }
    ],
    "sg:phone":"+1 602 290 7877",
    "sg:postcode":"85383",
    "sg:province":"AZ",
    "sg:tags":[
        "equipment",
        "kitchen",
        "cabinet"
    ],
    "wof:name":"American Cabinet Refacing",
    "wof:placetype":"venue"
},
  "geometry": {"coordinates":[-112.32419899999999,33.752851],"type":"Point"}
}