{
  "type": "Feature",
  "properties": {
    "iso:country":"US",
    "sg:address":"601 E Alpha Dr",
    "sg:city":"Tempe",
    "sg:classifiers":[
        {
            "category":"Organizations",
            "subcategory":"Community Association",
            "type":"Services"
        }
    ],
    "sg:phone":"+1 480 965 5242",
    "sg:postcode":"85281",
    "sg:province":"AZ",
    "sg:tags":[
        "fraternal"
    ],
    "sg:website":"www.sigmanu.org",
    "wof:name":"Sigma Nu Fraternity",
    "wof:placetype":"venue"
},
  "geometry": {"coordinates":[-111.928339,33.42346],"type":"Point"}
}