{
  "type": "Feature",
  "properties": {
    "addr:full":"2727 E Broadway Rd Mesa AZ 85204",
    "addr:housenumber":"2727",
    "addr:postcode":"85204",
    "addr:street":"E Broadway Rd",
    "iso:country":"US",
    "sg:address":"2727 E Broadway Rd",
    "sg:city":"Mesa",
    "sg:classifiers":[
        {
            "category":"Shopping",
            "subcategory":"Pharmacy",
            "type":"Retail Goods"
        }
    ],
    "sg:phone":"+1 480 464 4742",
    "sg:postcode":"85204",
    "sg:province":"AZ",
    "wof:name":"Fry S 123 Rx",
    "wof:placetype":"venue"
},
  "geometry": {"coordinates":[-111.772769,33.408141],"type":"Point"}
}