{
  "type": "Feature",
  "properties": {
    "iso:country":"US",
    "sg:address":"27318 N 37th Ave",
    "sg:city":"Phoenix",
    "sg:classifiers":[
        {
            "category":"Professional",
            "type":"Services"
        }
    ],
    "sg:phone":"+1 623 434 8314",
    "sg:postcode":"85083",
    "sg:province":"AZ",
    "sg:tags":[
        "spa",
        "hot",
        "tubs-repair"
    ],
    "wof:name":"Jon Mills Enterprises Inc",
    "wof:placetype":"venue"
},
  "geometry": {"coordinates":[-112.138398,33.731441],"type":"Point"}
}