{
  "type": "Feature",
  "properties": {
    "iso:country":"US",
    "sg:address":"4568 E Cactus Rd",
    "sg:city":"Phoenix",
    "sg:classifiers":[
        {
            "category":"Food & Beverages",
            "subcategory":"Bakery",
            "type":"Retail Goods"
        }
    ],
    "sg:phone":"+1 602 494 1400",
    "sg:postcode":"85032",
    "sg:province":"AZ",
    "sg:tags":[
        "baker"
    ],
    "sg:website":"www.cinnabon.com",
    "wof:name":"Cinnabon",
    "wof:placetype":"venue"
},
  "geometry": {"coordinates":[-111.980934,33.598934],"type":"Point"}
}