{
  "type": "Feature",
  "properties": {
    "addr:full":"2795 Northern Ave Kingman AZ 86409",
    "addr:housenumber":"2795",
    "addr:postcode":"86409",
    "addr:street":"Northern Ave",
    "iso:country":"US",
    "sg:address":"2795 Northern Ave",
    "sg:city":"Kingman",
    "sg:classifiers":[
        {
            "category":"Social Services",
            "type":"Services"
        }
    ],
    "sg:phone":"+1 928 692 2046",
    "sg:postcode":"86409",
    "sg:province":"AZ",
    "sg:tags":[
        "organization",
        "welfare"
    ],
    "wof:name":"Kingman Resource Ctr",
    "wof:placetype":"venue"
},
  "geometry": {"coordinates":[-114.01624200000001,35.25403],"type":"Point"}
}