{
  "type": "Feature",
  "properties": {
    "addr:full":"5055 E University Dr Mesa AZ 85205",
    "addr:housenumber":"5055",
    "addr:postcode":"85205",
    "addr:street":"E University Dr",
    "iso:country":"US",
    "sg:address":"5055 E University Dr",
    "sg:city":"Mesa",
    "sg:classifiers":[
        {
            "category":"Professional",
            "type":"Services"
        }
    ],
    "sg:phone":"+1 480 641 3371",
    "sg:postcode":"85205",
    "sg:province":"AZ",
    "wof:name":"Tech Harry",
    "wof:placetype":"venue"
},
  "geometry": {"coordinates":[-111.719364,33.422724],"type":"Point"}
}