{
  "type": "Feature",
  "properties": {
    "addr:full":"2415 E Camelback Rd Suite 700 Phoenix AZ 85016",
    "addr:housenumber":"2415",
    "addr:postcode":"85016",
    "addr:street":"E Camelback Rd Suite 700",
    "iso:country":"US",
    "sg:address":"2415 E Camelback Rd Suite 700",
    "sg:city":"Phoenix",
    "sg:classifiers":[
        {
            "category":"Building & Trades",
            "subcategory":"Cleaning & Sanitation",
            "type":"Services"
        },
        {
            "category":"Building & Trades",
            "subcategory":"Construction",
            "type":"Services"
        }
    ],
    "sg:phone":"+1 602 765 1603",
    "sg:postcode":"85016",
    "sg:province":"AZ",
    "sg:tags":[
        "altering",
        "cleaners-interior",
        "remodeling",
        "contractor"
    ],
    "sg:website":"http://www.waterdamage911.com",
    "wof:name":"WATER DAMAGE 911",
    "wof:placetype":"venue"
},
  "geometry": {"coordinates":[-112.029034,33.509245],"type":"Point"}
}