{
  "type": "Feature",
  "properties": {
    "iso:country":"US",
    "sg:address":"20717 N 59th Dr",
    "sg:city":"Glendale",
    "sg:classifiers":[
        {
            "category":"Communications",
            "subcategory":"Film & Video Production",
            "type":"Services"
        }
    ],
    "sg:phone":"+1 623 572 8214",
    "sg:postcode":"85308",
    "sg:province":"AZ",
    "sg:tags":[
        "audio"
    ],
    "wof:name":"Red Mountain Productions",
    "wof:placetype":"venue"
},
  "geometry": {"coordinates":[-112.187269,33.675007],"type":"Point"}
}