{
  "type": "Feature",
  "properties": {
    "addr:full":"7535 N 63rd Ave Glendale AZ 85301",
    "addr:housenumber":"7535",
    "addr:postcode":"85301",
    "addr:street":"N 63Rd Ave",
    "iso:country":"US",
    "sg:address":"7535 N 63rd Ave",
    "sg:city":"Glendale",
    "sg:classifiers":[
        {
            "category":"Building & Trades",
            "subcategory":"Plumbing",
            "type":"Services"
        }
    ],
    "sg:phone":"+1 623 931 2918",
    "sg:postcode":"85301",
    "sg:province":"AZ",
    "sg:tags":[
        "plumbing",
        "contractor"
    ],
    "wof:name":"Ampam Riggs Plumbing Inc",
    "wof:placetype":"venue"
},
  "geometry": {"coordinates":[-112.19486499999999,33.547034],"type":"Point"}
}