{
  "type": "Feature",
  "properties": {
    "addr:full":"1845 N Daley Mesa AZ 85203",
    "addr:housenumber":"1845",
    "addr:postcode":"85203",
    "addr:street":"N Daley",
    "iso:country":"US",
    "sg:address":"1845 N Daley",
    "sg:city":"Mesa",
    "sg:classifiers":[
        {
            "category":"Manufacturing",
            "subcategory":"Wood Products",
            "type":"Manufacturing & Wholesale Goods"
        }
    ],
    "sg:phone":"+1 480 892 2691",
    "sg:postcode":"85203",
    "sg:province":"AZ",
    "sg:tags":[
        "wooden",
        "mfg",
        "custom",
        "kitchen",
        "cabinet"
    ],
    "wof:name":"Hertiage Woodworking",
    "wof:placetype":"venue"
},
  "geometry": {"coordinates":[-111.79710799999999,33.448921],"type":"Point"}
}