{
  "type": "Feature",
  "properties": {
    "addr:full":"11415 N 35th Ave Phoenix AZ 85029",
    "addr:housenumber":"11415",
    "addr:postcode":"85029",
    "addr:street":"N 35Th Ave",
    "iso:country":"US",
    "sg:address":"11415 N 35th Ave",
    "sg:city":"Phoenix",
    "sg:classifiers":[
        {
            "category":"Place Of Worship",
            "subcategory":"Church",
            "type":"Public Place"
        },
        {
            "category":"Place Of Worship",
            "type":"Public Place"
        }
    ],
    "sg:phone":"+1 602 993 8213",
    "sg:postcode":"85029",
    "sg:province":"AZ",
    "sg:tags":[
        "churches-baptist-general",
        "churches-baptist"
    ],
    "wof:name":"Westown First Southern Baptist Church",
    "wof:placetype":"venue"
},
  "geometry": {"coordinates":[-112.133888,33.589279],"type":"Point"}
}