{
  "type": "Feature",
  "properties": {
    "addr:full":"2218 Navajo Blvd Holbrook AZ 86025",
    "addr:housenumber":"2218",
    "addr:postcode":"86025",
    "addr:street":"Navajo Blvd",
    "iso:country":"US",
    "sg:address":"2218 Navajo Blvd",
    "sg:city":"Holbrook",
    "sg:classifiers":[
        {
            "category":"Restaurant",
            "type":"Food & Drink"
        }
    ],
    "sg:phone":"+1 928 524 3663",
    "sg:postcode":"86025",
    "sg:province":"AZ",
    "sg:tags":[
        "asian",
        "chinese",
        "pan"
    ],
    "wof:name":"Mandarin Beauty Chinese Restaurant",
    "wof:placetype":"venue"
},
  "geometry": {"coordinates":[-110.13279799999999,34.936772],"type":"Point"}
}