{
  "type": "Feature",
  "properties": {
    "iso:country":"US",
    "sg:address":"2332 N Stone Ave",
    "sg:city":"Tucson",
    "sg:classifiers":[
        {
            "category":"Wholesale",
            "subcategory":"Auto Parts",
            "type":"Manufacturing & Wholesale Goods"
        }
    ],
    "sg:phone":"+1 520 882 8288",
    "sg:postcode":"85705",
    "sg:province":"AZ",
    "sg:tags":[
        "body",
        "automobile",
        "shop"
    ],
    "sg:website":"www.finishmaster.com",
    "wof:name":"Finish Master",
    "wof:placetype":"venue"
},
  "geometry": {"coordinates":[-110.971841,32.249962],"type":"Point"}
}