{
  "type": "Feature",
  "properties": {
    "iso:country":"US",
    "sg:address":"2437 W Yuma St",
    "sg:city":"Phoenix",
    "sg:classifiers":[
        {
            "category":"Organizations",
            "subcategory":"Religious Organization",
            "type":"Services"
        }
    ],
    "sg:phone":"+1 602 336 9696",
    "sg:postcode":"85009",
    "sg:province":"AZ",
    "sg:tags":[
        "church"
    ],
    "wof:name":"Tabernaculo De Alabanza",
    "wof:placetype":"venue"
},
  "geometry": {"coordinates":[-112.112302,33.434888],"type":"Point"}
}