{
  "type": "Feature",
  "properties": {
    "iso:country":"US",
    "sg:address":"7010 E Continental Dr",
    "sg:city":"Scottsdale",
    "sg:classifiers":[
        {
            "category":"Freight",
            "type":"Transportation"
        }
    ],
    "sg:phone":"+1 480 946 0805",
    "sg:postcode":"85257",
    "sg:province":"AZ",
    "sg:tags":[
        "operator",
        "local",
        "trucking"
    ],
    "wof:name":"John La Barbera Trucking",
    "wof:placetype":"venue"
},
  "geometry": {"coordinates":[-111.927525,33.458558],"type":"Point"}
}