{
  "type": "Feature",
  "properties": {
    "addr:full":"601 W Peralta Ave Mesa AZ 85210",
    "addr:housenumber":"601",
    "addr:postcode":"85210",
    "addr:street":"W Peralta Ave",
    "iso:country":"US",
    "sg:address":"601 W Peralta Ave",
    "sg:city":"Mesa",
    "sg:classifiers":[
        {
            "category":"Building & Trades",
            "subcategory":"Construction",
            "type":"Services"
        }
    ],
    "sg:phone":"+1 480 633 6540",
    "sg:postcode":"85210",
    "sg:province":"AZ",
    "sg:tags":[
        "coping",
        "plastering",
        "tiling",
        "pool",
        "swimming"
    ],
    "wof:name":"Sharkey's Pool Svc & Repair",
    "wof:placetype":"venue"
},
  "geometry": {"coordinates":[-111.84710699999999,33.35739],"type":"Point"}
}