{
  "type": "Feature",
  "properties": {
    "addr:full":"13555 W McDowell Rd Goodyear AZ 85395",
    "addr:housenumber":"13555",
    "addr:postcode":"85395",
    "addr:street":"W Mcdowell Rd",
    "iso:country":"US",
    "sg:address":"13555 W McDowell Rd",
    "sg:city":"Goodyear",
    "sg:classifiers":[
        {
            "category":"Health Services",
            "subcategory":"Doctor",
            "type":"Services"
        }
    ],
    "sg:phone":"+1 623 536 2580",
    "sg:postcode":"85395",
    "sg:province":"AZ",
    "sg:tags":[
        "physician",
        "surgeon"
    ],
    "wof:name":"Az Center For Hematology",
    "wof:placetype":"venue"
},
  "geometry": {"coordinates":[-112.350016,33.464273],"type":"Point"}
}