{
  "type": "Feature",
  "properties": {
    "iso:country":"US",
    "sg:address":"3256 E Speedway Blvd",
    "sg:city":"Tucson",
    "sg:classifiers":[
        {
            "category":"Retail",
            "subcategory":"Portrait Studio",
            "type":"Services"
        }
    ],
    "sg:phone":"+1 520 881 0945",
    "sg:postcode":"85716",
    "sg:province":"AZ",
    "sg:tags":[
        "photographer"
    ],
    "sg:website":"www.freezeframefoto.com",
    "wof:name":"Freeze Frame Photography",
    "wof:placetype":"venue"
},
  "geometry": {"coordinates":[-110.92351,32.236015],"type":"Point"}
}