{
  "type": "Feature",
  "properties": {
    "iso:country":"US",
    "sg:address":"1525 W 10th Pl",
    "sg:city":"Tempe",
    "sg:classifiers":[
        {
            "category":"Wholesale",
            "subcategory":"Hardware",
            "type":"Manufacturing & Wholesale Goods"
        }
    ],
    "sg:phone":"+1 480 894 8622",
    "sg:postcode":"85281",
    "sg:province":"AZ",
    "wof:name":"Ivm Fasteners",
    "wof:placetype":"venue"
},
  "geometry": {"coordinates":[-111.964024,33.417538],"type":"Point"}
}