{
  "type": "Feature",
  "properties": {
    "iso:country":"US",
    "sg:address":"8113 E del Acero Dr",
    "sg:city":"Scottsdale",
    "sg:classifiers":[
        {
            "category":"Shopping",
            "type":"Retail Goods"
        }
    ],
    "sg:phone":"+1 480 991 6819",
    "sg:postcode":"85258",
    "sg:province":"AZ",
    "sg:tags":[
        "merchandise"
    ],
    "wof:name":"Wvp Management LLC",
    "wof:placetype":"venue"
},
  "geometry": {"coordinates":[-111.906329,33.560021],"type":"Point"}
}