{
  "type": "Feature",
  "properties": {
    "iso:country":"US",
    "sg:address":"6602 E Cll Luna",
    "sg:city":"Tucson",
    "sg:classifiers":[
        {
            "category":"Shopping",
            "subcategory":"Clothing, Apparel, & Fashions",
            "type":"Retail Goods"
        }
    ],
    "sg:phone":"+1 520 319 0829",
    "sg:postcode":"85710",
    "sg:province":"AZ",
    "sg:tags":[
        "shop",
        "bridal"
    ],
    "wof:name":"Saigon Video & Fashion",
    "wof:placetype":"venue"
},
  "geometry": {"coordinates":[-110.85321,32.195054],"type":"Point"}
}