{
  "type": "Feature",
  "properties": {
    "addr:full":"1551 E Tangerine Rd Oro Valley AZ 85755",
    "addr:housenumber":"1551",
    "addr:postcode":"85755",
    "addr:street":"E Tangerine Rd Oro",
    "iso:country":"US",
    "sg:address":"1551 E Tangerine Rd",
    "sg:city":"Oro Valley",
    "sg:classifiers":[
        {
            "category":"Health Services",
            "subcategory":"Hospital",
            "type":"Services"
        }
    ],
    "sg:phone":"+1 520 901 3500",
    "sg:postcode":"85755",
    "sg:province":"AZ",
    "sg:website":"www.nmcorovalley.com",
    "wof:name":"Oro Valley Hospital",
    "wof:placetype":"venue"
},
  "geometry": {"coordinates":[-110.950247,32.427237],"type":"Point"}
}