{
  "type": "Feature",
  "properties": {
    "iso:country":"US",
    "sg:address":"1515 W Missouri Ave",
    "sg:city":"Phoenix",
    "sg:classifiers":[
        {
            "category":"Real Estate",
            "subcategory":"Real Estate Operator",
            "type":"Services"
        }
    ],
    "sg:phone":"+1 602 274 8806",
    "sg:postcode":"85015",
    "sg:province":"AZ",
    "sg:tags":[
        "building",
        "apartment"
    ],
    "wof:name":"Acacia Garden Apartments",
    "wof:placetype":"venue"
},
  "geometry": {"coordinates":[-112.092944,33.516699],"type":"Point"}
}