{
  "type": "Feature",
  "properties": {
    "iso:country":"US",
    "sg:address":"6941 E 5th Ave",
    "sg:city":"Scottsdale",
    "sg:classifiers":[
        {
            "category":"Shopping",
            "type":"Retail Goods"
        }
    ],
    "sg:phone":"+1 480 945 0209",
    "sg:postcode":"85251",
    "sg:province":"AZ",
    "sg:tags":[
        "picture",
        "frame"
    ],
    "wof:name":"Dan's Frame & Arts Gallery",
    "wof:placetype":"venue"
},
  "geometry": {"coordinates":[-111.930769,33.496994],"type":"Point"}
}