{
  "type": "Feature",
  "properties": {
    "iso:country":"US",
    "sg:address":"2733 N Power Rd Ste 102-508",
    "sg:city":"Mesa",
    "sg:classifiers":[
        {
            "category":"Insurance",
            "subcategory":"Insurance Agent",
            "type":"Services"
        },
        {
            "category":"Insurance",
            "subcategory":"Hazard Insurance",
            "type":"Services"
        },
        {
            "category":"Insurance",
            "subcategory":"Health Insurance",
            "type":"Services"
        }
    ],
    "sg:phone":"+1 480 419 7758",
    "sg:postcode":"85215",
    "sg:province":"AZ",
    "sg:tags":[
        "consultant",
        "analyst"
    ],
    "wof:name":"Arizona Pro Benefits",
    "wof:placetype":"venue"
},
  "geometry": {"coordinates":[-111.683899,33.465587],"type":"Point"}
}