{
  "type": "Feature",
  "properties": {
    "iso:country":"US",
    "sg:address":"3575 E Red Baron Dr",
    "sg:city":"Rimrock",
    "sg:classifiers":[
        {
            "category":"Autos & Motor Vehicles",
            "subcategory":"Automobile Sales",
            "type":"Retail Goods"
        }
    ],
    "sg:phone":"+1 623 566 8068",
    "sg:postcode":"86335",
    "sg:province":"AZ",
    "sg:tags":[
        "aircraft"
    ],
    "wof:name":"Kemmeries Aviation Ultralight",
    "wof:placetype":"venue"
},
  "geometry": {"coordinates":[-111.788449,34.649388],"type":"Point"}
}