{
  "type": "Feature",
  "properties": {
    "iso:country":"US",
    "sg:address":"2328 N 16th St",
    "sg:city":"Phoenix",
    "sg:classifiers":[
        {
            "category":"Shopping",
            "subcategory":"Computers & Home Electronics",
            "type":"Retail Goods"
        }
    ],
    "sg:phone":"+1 602 254 6132",
    "sg:postcode":"85006",
    "sg:province":"AZ",
    "wof:name":"Uno Cellular & Paging",
    "wof:placetype":"venue"
},
  "geometry": {"coordinates":[-112.047728,33.473618],"type":"Point"}
}