{
  "type": "Feature",
  "properties": {
    "iso:country":"US",
    "sg:address":"3641 E Campbell Ave",
    "sg:city":"Phoenix",
    "sg:classifiers":[
        {
            "category":"Professional",
            "type":"Services"
        }
    ],
    "sg:phone":"+1 602 956 9679",
    "sg:postcode":"85018",
    "sg:province":"AZ",
    "wof:name":"TW Farms LLC",
    "wof:placetype":"venue"
},
  "geometry": {"coordinates":[-112.003029,33.502464],"type":"Point"}
}