{
  "type": "Feature",
  "properties": {
    "iso:country":"US",
    "sg:address":"945 N Saffron",
    "sg:city":"Mesa",
    "sg:classifiers":[
        {
            "category":"Building & Trades",
            "subcategory":"Plumbing",
            "type":"Services"
        }
    ],
    "sg:phone":"+1 480 577 4400",
    "sg:postcode":"85205",
    "sg:province":"AZ",
    "sg:tags":[
        "plumbing",
        "contractor"
    ],
    "wof:name":"Mr Ponto Plumbing & Rooter",
    "wof:placetype":"venue"
},
  "geometry": {"coordinates":[-111.687998,33.433095],"type":"Point"}
}