{
  "type": "Feature",
  "properties": {
    "iso:country":"US",
    "sg:address":"1755 W Apache Trl",
    "sg:city":"Apache Junction",
    "sg:classifiers":[
        {
            "category":"Autos & Motor Vehicles",
            "subcategory":"Auto Supplies",
            "type":"Retail Goods"
        }
    ],
    "sg:phone":"+1 480 982 7422",
    "sg:postcode":"85220",
    "sg:province":"AZ",
    "sg:tags":[
        "automotive",
        "repair"
    ],
    "wof:name":"James Tire & Auto Center",
    "wof:placetype":"venue"
},
  "geometry": {"coordinates":[-111.56502,33.414978],"type":"Point"}
}