{
  "type": "Feature",
  "properties": {
    "addr:full":"798 US Hwy 60 Superior AZ 85273",
    "addr:housenumber":"798",
    "addr:postcode":"85273",
    "addr:street":"Us Hwy 60",
    "iso:country":"US",
    "sg:address":"798 US Hwy 60",
    "sg:city":"Superior",
    "sg:classifiers":[
        {
            "category":"Food & Beverages",
            "subcategory":"Groceries & Convenience Stores",
            "type":"Retail Goods"
        }
    ],
    "sg:phone":"+1 520 689 5845",
    "sg:postcode":"85273",
    "sg:province":"AZ",
    "wof:name":"Farmers Market",
    "wof:placetype":"venue"
},
  "geometry": {"coordinates":[-111.104624,33.287523],"type":"Point"}
}