{
  "type": "Feature",
  "properties": {
    "iso:country":"US",
    "sg:address":"3219 S 40th St",
    "sg:city":"Phoenix",
    "sg:classifiers":[
        {
            "category":"Autos & Motor Vehicles",
            "subcategory":"Auto Supplies",
            "type":"Retail Goods"
        },
        {
            "category":"Retail",
            "subcategory":"Auto Repair",
            "type":"Services"
        }
    ],
    "sg:phone":"+1 602 458 7732",
    "sg:postcode":"85040",
    "sg:province":"AZ",
    "sg:tags":[
        "transmission",
        "transmissions-other"
    ],
    "wof:name":"Discount Transmission",
    "wof:placetype":"venue"
},
  "geometry": {"coordinates":[-111.99543,33.418179],"type":"Point"}
}