{
  "type": "Feature",
  "properties": {
    "iso:country":"US",
    "sg:address":"9119 N 68th Dr",
    "sg:city":"Peoria",
    "sg:classifiers":[
        {
            "category":"Professional",
            "type":"Services"
        }
    ],
    "sg:phone":"+1 623 334 1652",
    "sg:postcode":"85345",
    "sg:province":"AZ",
    "wof:name":"Light A Universal Teaching",
    "wof:placetype":"venue"
},
  "geometry": {"coordinates":[-112.206129,33.568142],"type":"Point"}
}