{
  "type": "Feature",
  "properties": {
    "iso:country":"US",
    "sg:address":"512 W 17th Pl",
    "sg:city":"Tempe",
    "sg:classifiers":[
        {
            "category":"Restaurant",
            "type":"Food & Drink"
        }
    ],
    "sg:phone":"+1 480 966 4810",
    "sg:postcode":"85281",
    "sg:province":"AZ",
    "sg:tags":[
        "eating"
    ],
    "wof:name":"Grannys Sub Corp",
    "wof:placetype":"venue"
},
  "geometry": {"coordinates":[-111.94748800000001,33.410331],"type":"Point"}
}