{
  "type": "Feature",
  "properties": {
    "iso:country":"US",
    "sg:address":"7091 E 5th Ave",
    "sg:city":"Scottsdale",
    "sg:classifiers":[
        {
            "category":"Shopping",
            "subcategory":"Gifts & Souvenirs",
            "type":"Retail Goods"
        }
    ],
    "sg:phone":"+1 480 994 1451",
    "sg:postcode":"85251",
    "sg:province":"AZ",
    "wof:name":"Kokopelli Gifts",
    "wof:placetype":"venue"
},
  "geometry": {"coordinates":[-111.928754,33.498214],"type":"Point"}
}