{
  "type": "Feature",
  "properties": {
    "addr:full":"7091 E 5th Ave Scottsdale AZ 85251",
    "addr:housenumber":"7091",
    "addr:postcode":"85251",
    "addr:street":"E 5Th Ave",
    "iso:country":"US",
    "sg:address":"7091 E 5th Ave",
    "sg:city":"Scottsdale",
    "sg:classifiers":[
        {
            "category":"Shopping",
            "subcategory":"Gifts & Souvenirs",
            "type":"Retail Goods"
        }
    ],
    "sg:phone":"+1 480 994 1451",
    "sg:postcode":"85251",
    "sg:province":"AZ",
    "wof:name":"Kokopelli Gifts",
    "wof:placetype":"venue"
},
  "geometry": {"coordinates":[-111.928754,33.498214],"type":"Point"}
}