{
  "type": "Feature",
  "properties": {
    "iso:country":"US",
    "sg:address":"1008 E Village Circle Dr S",
    "sg:city":"Phoenix",
    "sg:classifiers":[
        {
            "category":"Building & Trades",
            "subcategory":"Construction",
            "type":"Services"
        }
    ],
    "sg:phone":"+1 602 620 7435",
    "sg:postcode":"85022",
    "sg:province":"AZ",
    "sg:tags":[
        "roofing",
        "industrial",
        "contractors-commercial",
        "contractor"
    ],
    "wof:name":"Arizona Reign Roof Systems Inc",
    "wof:placetype":"venue"
},
  "geometry": {"coordinates":[-112.060154,33.608755],"type":"Point"}
}