{
  "type": "Feature",
  "properties": {
    "addr:full":"1810 E La Salle Road Phoenix AZ 85086",
    "addr:housenumber":"1810",
    "addr:postcode":"85086",
    "addr:street":"E La Salle Road",
    "iso:country":"US",
    "sg:address":"1810 E La Salle Road",
    "sg:city":"Phoenix",
    "sg:classifiers":[
        {
            "category":"Shopping",
            "subcategory":"Gifts & Souvenirs",
            "type":"Retail Goods"
        },
        {
            "category":"Manufacturing",
            "subcategory":"Retail Goods",
            "type":"Manufacturing & Wholesale Goods"
        }
    ],
    "sg:phone":"+1 623 465 9201",
    "sg:postcode":"85086",
    "sg:province":"AZ",
    "sg:tags":[
        "shop",
        "flower",
        "giftware's-wholesale",
        "manufacturer"
    ],
    "wof:name":"Wood Masters Kitchenware",
    "wof:placetype":"venue"
},
  "geometry": {"coordinates":[-112.043015,33.835285],"type":"Point"}
}