{
  "type": "Feature",
  "properties": {
    "iso:country":"US",
    "sg:address":"1221 W Gila Bend Hwy",
    "sg:city":"Casa Grande",
    "sg:classifiers":[
        {
            "category":"Freight",
            "type":"Transportation"
        }
    ],
    "sg:phone":"+1 520 316 0048",
    "sg:postcode":"85293",
    "sg:province":"AZ",
    "wof:name":"Schanno Transportation Inc",
    "wof:placetype":"venue"
},
  "geometry": {"coordinates":[-111.784414,32.879375],"type":"Point"}
}