{
  "type": "Feature",
  "properties": {
    "addr:full":"3320 N Kelvin Blvd Tucson AZ 85716",
    "addr:housenumber":"3320",
    "addr:postcode":"85716",
    "addr:street":"N Kelvin Blvd",
    "iso:country":"US",
    "sg:address":"3320 N Kelvin Blvd",
    "sg:city":"Tucson",
    "sg:classifiers":[
        {
            "category":"Retail",
            "subcategory":"Laundry & Dry Cleaning",
            "type":"Services"
        }
    ],
    "sg:phone":"+1 520 327 3613",
    "sg:postcode":"85716",
    "sg:province":"AZ",
    "sg:tags":[
        "cleaners",
        "rug",
        "carpet"
    ],
    "wof:name":"Fast-N-Dry Carpet",
    "wof:placetype":"venue"
},
  "geometry": {"coordinates":[-110.92022299999999,32.268315],"type":"Point"}
}