{
  "type": "Feature",
  "properties": {
    "iso:country":"US",
    "sg:address":"2598 US Hwy 70",
    "sg:city":"Safford",
    "sg:classifiers":[
        {
            "category":"Manufacturing",
            "subcategory":"Tools & Machinery",
            "type":"Manufacturing & Wholesale Goods"
        },
        {
            "category":"Autos & Motor Vehicles",
            "subcategory":"Auto Supplies",
            "type":"Retail Goods"
        }
    ],
    "sg:phone":"+1 928 428 2468",
    "sg:postcode":"85546",
    "sg:province":"AZ",
    "sg:tags":[
        "alternator",
        "generator",
        "starter"
    ],
    "wof:name":"Morcomb Diesel & Electric Svc",
    "wof:placetype":"venue"
},
  "geometry": {"coordinates":[-109.74247699999999,32.844143],"type":"Point"}
}