{
  "type": "Feature",
  "properties": {
    "iso:country":"US",
    "sg:address":"755 E Hatcher Rd",
    "sg:city":"Phoenix",
    "sg:classifiers":[
        {
            "category":"Organizations",
            "subcategory":"Non-profit Organization",
            "type":"Services"
        }
    ],
    "sg:phone":"+1 602 944 0941",
    "sg:postcode":"85020",
    "sg:province":"AZ",
    "wof:name":"Sunnyslope Village Alliance",
    "wof:placetype":"venue"
},
  "geometry": {"coordinates":[-112.062606,33.571306],"type":"Point"}
}