{
  "type": "Feature",
  "properties": {
    "iso:country":"US",
    "sg:address":"52476 W Esch Trl",
    "sg:city":"Maricopa",
    "sg:classifiers":[
        {
            "category":"Banks & Credit Unions",
            "subcategory":"Financial Services",
            "type":"Services"
        }
    ],
    "sg:phone":"+1 520 568 2354",
    "sg:postcode":"85239",
    "sg:province":"AZ",
    "sg:tags":[
        "investor"
    ],
    "wof:name":"Starfish Investments LLC",
    "wof:placetype":"venue"
},
  "geometry": {"coordinates":[-112.13203799999999,32.974724],"type":"Point"}
}