{
  "type": "Feature",
  "properties": {
    "addr:full":"400 E Ray Rd Chandler AZ 85225",
    "addr:housenumber":"400",
    "addr:postcode":"85225",
    "addr:street":"E Ray Rd",
    "iso:country":"US",
    "sg:address":"400 E Ray Rd",
    "sg:city":"Chandler",
    "sg:classifiers":[
        {
            "category":"Wholesale",
            "subcategory":"Machinery & Supplies",
            "type":"Manufacturing & Wholesale Goods"
        }
    ],
    "sg:phone":"+1 480 792 0145",
    "sg:postcode":"85225",
    "sg:province":"AZ",
    "sg:tags":[
        "dry wall",
        "contractor"
    ],
    "wof:name":"Coyote Building Materials Inc",
    "wof:placetype":"venue"
},
  "geometry": {"coordinates":[-111.833934,33.320781],"type":"Point"}
}