{
  "type": "Feature",
  "properties": {
    "iso:country":"US",
    "sg:address":"1802 W Camargo Ct",
    "sg:city":"Phoenix",
    "sg:classifiers":[
        {
            "category":"Banks & Credit Unions",
            "subcategory":"Financial Services",
            "type":"Services"
        }
    ],
    "sg:phone":"+1 623 551 9140",
    "sg:postcode":"85086",
    "sg:province":"AZ",
    "sg:tags":[
        "investor"
    ],
    "wof:name":"Smf Investments LLC",
    "wof:placetype":"venue"
},
  "geometry": {"coordinates":[-112.098115,33.867007],"type":"Point"}
}