{
  "type": "Feature",
  "properties": {
    "iso:country":"US",
    "sg:address":"20 S 69th Ave",
    "sg:city":"Phoenix",
    "sg:classifiers":[
        {
            "category":"Shopping",
            "type":"Retail Goods"
        }
    ],
    "sg:phone":"+1 623 936 5874",
    "sg:postcode":"85043",
    "sg:province":"AZ",
    "sg:tags":[
        "merchandise"
    ],
    "wof:name":"Gilbert Development Warehouse",
    "wof:placetype":"venue"
},
  "geometry": {"coordinates":[-112.206971,33.447834],"type":"Point"}
}