{
  "type": "Feature",
  "properties": {
    "addr:full":"220 N Mckemy Ave Chandler AZ 85226",
    "addr:housenumber":"220",
    "addr:postcode":"85226",
    "addr:street":"N Mckemy Ave",
    "iso:country":"US",
    "sg:address":"220 N Mckemy Ave",
    "sg:city":"Chandler",
    "sg:classifiers":[
        {
            "category":"Insurance",
            "subcategory":"Hazard Insurance",
            "type":"Services"
        }
    ],
    "sg:phone":"+1 480 961 1702",
    "sg:postcode":"85226",
    "sg:province":"AZ",
    "sg:tags":[
        "group"
    ],
    "sg:website":"http://www.sightcare.net",
    "wof:name":"Sightcare Inc",
    "wof:placetype":"venue"
},
  "geometry": {"coordinates":[-111.95348799999999,33.305868],"type":"Point"}
}