{
  "type": "Feature",
  "properties": {
    "addr:full":"1835 E Missouri Ave Phoenix AZ 85016",
    "addr:housenumber":"1835",
    "addr:postcode":"85016",
    "addr:street":"E Missouri Ave",
    "iso:country":"US",
    "sg:address":"1835 E Missouri Ave",
    "sg:city":"Phoenix",
    "sg:classifiers":[
        {
            "category":"Place Of Worship",
            "subcategory":"Church",
            "type":"Public Place"
        },
        {
            "category":"Place Of Worship",
            "type":"Public Place"
        }
    ],
    "sg:phone":"+1 602 266 2199",
    "sg:postcode":"85016",
    "sg:province":"AZ",
    "sg:tags":[
        "christ",
        "latter-day",
        "jesus",
        "churches-church",
        "saint"
    ],
    "sg:website":"http://www.lds.org",
    "wof:name":"The Corporation Of The President Of The Church Of Jesus Christ Of Latter-Day Saints",
    "wof:placetype":"venue"
},
  "geometry": {"coordinates":[-112.04246999999999,33.516501],"type":"Point"}
}