{
  "type": "Feature",
  "properties": {
    "addr:full":"1712 W Bell Rd Phoenix AZ 85023",
    "addr:housenumber":"1712",
    "addr:postcode":"85023",
    "addr:street":"W Bell Rd",
    "iso:country":"US",
    "sg:address":"1712 W Bell Rd",
    "sg:city":"Phoenix",
    "sg:classifiers":[
        {
            "category":"Food & Beverages",
            "subcategory":"Meat & Fish",
            "type":"Retail Goods"
        }
    ],
    "sg:phone":"+1 602 375 3999",
    "sg:postcode":"85023",
    "sg:province":"AZ",
    "sg:tags":[
        "sausage",
        "market"
    ],
    "wof:name":"Stanely's Homemade Polish",
    "wof:placetype":"venue"
},
  "geometry": {"coordinates":[-112.096451,33.640221],"type":"Point"}
}