{
  "type": "Feature",
  "properties": {
    "iso:country":"US",
    "sg:address":"8814 S Lakeshore Dr",
    "sg:city":"Tempe",
    "sg:classifiers":[
        {
            "category":"Autos & Motor Vehicles",
            "subcategory":"Automobile Sales",
            "type":"Retail Goods"
        }
    ],
    "sg:phone":"+1 480 456 4270",
    "sg:postcode":"85284",
    "sg:province":"AZ",
    "sg:tags":[
        "used"
    ],
    "wof:name":"Take Over Payment Sales",
    "wof:placetype":"venue"
},
  "geometry": {"coordinates":[-111.919329,33.33445],"type":"Point"}
}