{
  "type": "Feature",
  "properties": {
    "addr:full":"4515 S. McClintock Dr. Suite 120 Tempe AZ 85282",
    "addr:housenumber":"4515",
    "addr:postcode":"85282",
    "addr:street":"S. Mcclintock Dr. Suite 120",
    "iso:country":"US",
    "sg:address":"4515 S. McClintock Dr. Suite 120",
    "sg:city":"Tempe",
    "sg:classifiers":[
        {
            "category":"Health Services",
            "subcategory":"Chiropractor",
            "type":"Services"
        }
    ],
    "sg:phone":"+1 480 413 0586",
    "sg:postcode":"85282",
    "sg:province":"AZ",
    "sg:website":"www.azpain.com",
    "wof:name":"Triad Pain Management Clinic",
    "wof:placetype":"venue"
},
  "geometry": {"coordinates":[-111.90826300000001,33.384655],"type":"Point"}
}