{
  "type": "Feature",
  "properties": {
    "addr:full":"1133 Boulder Park Ave Prescott AZ 86305",
    "addr:housenumber":"1133",
    "addr:postcode":"86305",
    "addr:street":"Boulder Park Ave",
    "iso:country":"US",
    "sg:address":"1133 Boulder Park Ave",
    "sg:city":"Prescott",
    "sg:classifiers":[
        {
            "category":"Retail",
            "subcategory":"Repair Shop",
            "type":"Services"
        }
    ],
    "sg:phone":"+1 928 775 0455",
    "sg:postcode":"86305",
    "sg:province":"AZ",
    "sg:tags":[
        "instrument",
        "musical"
    ],
    "wof:name":"Kurt's Amps & Keyboards",
    "wof:placetype":"venue"
},
  "geometry": {"coordinates":[-112.49092,34.562735],"type":"Point"}
}