{
  "type": "Feature",
  "properties": {
    "iso:country":"US",
    "sg:address":"12120 N Dove Mountain Blvd",
    "sg:city":"Marana",
    "sg:classifiers":[
        {
            "category":"Home & Garden",
            "subcategory":"Furniture",
            "type":"Retail Goods"
        }
    ],
    "sg:phone":"+1 520 579 1270",
    "sg:postcode":"85658",
    "sg:province":"AZ",
    "sg:tags":[
        "store"
    ],
    "wof:name":"Monterra Furnishings",
    "wof:placetype":"venue"
},
  "geometry": {"coordinates":[-111.080381,32.425848],"type":"Point"}
}