{
  "type": "Feature",
  "properties": {
    "iso:country":"US",
    "sg:address":"10855 N 116th St",
    "sg:city":"Scottsdale",
    "sg:classifiers":[
        {
            "category":"Personal",
            "subcategory":"Beauty Salon",
            "type":"Services"
        }
    ],
    "sg:phone":"+1 480 661 8881",
    "sg:postcode":"85259",
    "sg:province":"AZ",
    "sg:tags":[
        "manicuring"
    ],
    "wof:name":"Elite Nails",
    "wof:placetype":"venue"
},
  "geometry": {"coordinates":[-111.83081799999999,33.58487],"type":"Point"}
}