{
  "type": "Feature",
  "properties": {
    "iso:country":"US",
    "sg:address":"3811 N Oracle Rd",
    "sg:city":"Tucson",
    "sg:classifiers":[
        {
            "category":"Home & Garden",
            "subcategory":"Building Materials",
            "type":"Retail Goods"
        }
    ],
    "sg:phone":"+1 520 293 5200",
    "sg:postcode":"85705",
    "sg:province":"AZ",
    "sg:tags":[
        "glass",
        "window",
        "plate"
    ],
    "wof:name":"Atlas Glass",
    "wof:placetype":"venue"
},
  "geometry": {"coordinates":[-110.978145,32.275894],"type":"Point"}
}