{
  "type": "Feature",
  "properties": {
    "iso:country":"US",
    "sg:address":"5480 E Speedway Blvd",
    "sg:city":"Tucson",
    "sg:classifiers":[
        {
            "category":"Restaurant",
            "type":"Food & Drink"
        }
    ],
    "sg:menulink":"http://www.allmenus.com/az/tucson/63850-subway/menu/",
    "sg:phone":"+1 520 327 7827",
    "sg:postcode":"85712",
    "sg:province":"AZ",
    "sg:tags":[
        "american",
        "sandwich"
    ],
    "wof:name":"Subway",
    "wof:placetype":"venue"
},
  "geometry": {"coordinates":[-110.87593099999999,32.236112],"type":"Point"}
}