{
  "type": "Feature",
  "properties": {
    "iso:country":"US",
    "sg:address":"4075 W Ina Rd",
    "sg:city":"Tucson",
    "sg:classifiers":[
        {
            "category":"Shopping",
            "subcategory":"Pharmacy",
            "type":"Retail Goods"
        }
    ],
    "sg:phone":"+1 520 744 6900",
    "sg:postcode":"85741",
    "sg:province":"AZ",
    "wof:name":"Kmart Pharmacies Inc",
    "wof:placetype":"venue"
},
  "geometry": {"coordinates":[-111.047686,32.337463],"type":"Point"}
}