{
  "type": "Feature",
  "properties": {
    "iso:country":"US",
    "sg:address":"1990 McCulloch Blvd N",
    "sg:city":"Lake Havasu City",
    "sg:classifiers":[
        {
            "category":"Real Estate",
            "subcategory":"Real Estate Agent",
            "type":"Services"
        }
    ],
    "sg:phone":"+1 928 768 4658",
    "sg:postcode":"86403",
    "sg:province":"AZ",
    "sg:tags":[
        "inspection"
    ],
    "wof:name":"House Detective Home",
    "wof:placetype":"venue"
},
  "geometry": {"coordinates":[-114.332479,34.476729],"type":"Point"}
}