{
  "type": "Feature",
  "properties": {
    "addr:full":"9029 E Indian Bend Rd Scottsdale AZ 85250",
    "addr:housenumber":"9029",
    "addr:postcode":"85250",
    "addr:street":"E Indian Bend Rd",
    "iso:country":"US",
    "sg:address":"9029 E Indian Bend Rd",
    "sg:city":"Scottsdale",
    "sg:classifiers":[
        {
            "category":"Bakery",
            "type":"Food & Drink"
        }
    ],
    "sg:menulink":"http://www.allmenus.com/az/salt-river/238019-sweet-tomatoes/menu/",
    "sg:phone":"+1 480 991 6010",
    "sg:postcode":"85250",
    "sg:province":"AZ",
    "sg:tags":[
        "soup",
        "american",
        "pastry",
        "salad"
    ],
    "wof:name":"Sweet Tomatoes",
    "wof:placetype":"venue"
},
  "geometry": {"coordinates":[-111.88639499999999,33.538384],"type":"Point"}
}