{
  "type": "Feature",
  "properties": {
    "iso:country":"US",
    "sg:address":"555 W University Dr Ste 3",
    "sg:city":"Mesa",
    "sg:classifiers":[
        {
            "category":"Wholesale",
            "subcategory":"Office Equipment",
            "type":"Manufacturing & Wholesale Goods"
        },
        {
            "category":"Professional",
            "subcategory":"Accounting & Tax Preparation",
            "type":"Services"
        }
    ],
    "sg:phone":"+1 480 593 5498",
    "sg:postcode":"85201",
    "sg:province":"AZ",
    "sg:tags":[
        "machine",
        "bookkeeping",
        "return",
        "supply"
    ],
    "wof:name":"Facil Income Tax",
    "wof:placetype":"venue"
},
  "geometry": {"coordinates":[-111.843405,33.422363],"type":"Point"}
}