{
  "type": "Feature",
  "properties": {
    "iso:country":"US",
    "sg:address":"14018 N 58th St",
    "sg:city":"Scottsdale",
    "sg:classifiers":[
        {
            "category":"Marine",
            "type":"Transportation"
        }
    ],
    "sg:phone":"+1 480 441 4262",
    "sg:postcode":"85254",
    "sg:province":"AZ",
    "sg:tags":[
        "surveyor"
    ],
    "wof:name":"Jarvie Marine Surveyors",
    "wof:placetype":"venue"
},
  "geometry": {"coordinates":[-111.95528400000001,33.613402],"type":"Point"}
}