{
  "type": "Feature",
  "properties": {
    "iso:country":"US",
    "sg:address":"4501 London Bridge Rd",
    "sg:city":"Lake Havasu City",
    "sg:classifiers":[
        {
            "category":"Restaurant",
            "type":"Food & Drink"
        }
    ],
    "sg:phone":"+1 928 764 3800",
    "sg:postcode":"86404",
    "sg:province":"AZ",
    "wof:name":"Golden Horseshoe Farrell's",
    "wof:placetype":"venue"
},
  "geometry": {"coordinates":[-114.36831,34.550643],"type":"Point"}
}