{
  "type": "Feature",
  "properties": {
    "addr:full":"15406 N Greasewood St Surprise AZ 85374",
    "addr:housenumber":"15406",
    "addr:postcode":"85374",
    "addr:street":"N Greasewood St",
    "iso:country":"US",
    "sg:address":"15406 N Greasewood St",
    "sg:city":"Surprise",
    "sg:classifiers":[
        {
            "category":"Place Of Worship",
            "subcategory":"Church",
            "type":"Public Place"
        },
        {
            "category":"Place Of Worship",
            "type":"Public Place"
        },
        {
            "category":"Organizations",
            "subcategory":"Religious Organization",
            "type":"Services"
        }
    ],
    "sg:phone":"+1 623 583 7734",
    "sg:postcode":"85374",
    "sg:province":"AZ",
    "sg:tags":[
        "god",
        "god-independent",
        "churches-assemblies"
    ],
    "wof:name":"Iglesia Del Valle",
    "wof:placetype":"venue"
},
  "geometry": {"coordinates":[-112.32907299999999,33.623613],"type":"Point"}
}