{
  "type": "Feature",
  "properties": {
    "iso:country":"US",
    "sg:address":"1777 W Cessna Way",
    "sg:city":"Tucson",
    "sg:classifiers":[
        {
            "category":"Airline",
            "type":"Transportation"
        }
    ],
    "sg:phone":"+1 520 297 8096",
    "sg:postcode":"85737",
    "sg:province":"AZ",
    "sg:tags":[
        "airport"
    ],
    "wof:name":"La Cholla Airpark Inc",
    "wof:placetype":"venue"
},
  "geometry": {"coordinates":[-111.003998,32.446602],"type":"Point"}
}