{
  "type": "Feature",
  "properties": {
    "iso:country":"US",
    "sg:address":"595 West Harrison Street",
    "sg:city":"Chandler",
    "sg:classifiers":[
        {
            "category":"Building & Trades",
            "subcategory":"Landscaping Services",
            "type":"Services"
        },
        {
            "category":"Building & Trades",
            "subcategory":"Construction",
            "type":"Services"
        }
    ],
    "sg:phone":"+1 480 306 0084",
    "sg:postcode":"85225",
    "sg:province":"AZ",
    "sg:tags":[
        "painter"
    ],
    "wof:name":"Montero Landscaping and Painting Services",
    "wof:placetype":"venue"
},
  "geometry": {"coordinates":[-111.850105,33.316363],"type":"Point"}
}