{
  "type": "Feature",
  "properties": {
    "addr:full":"575 E 18th Pl Yuma AZ 85365",
    "addr:housenumber":"575",
    "addr:postcode":"85365",
    "addr:street":"E 18Th Pl",
    "iso:country":"US",
    "sg:address":"575 E 18th Pl",
    "sg:city":"Yuma",
    "sg:classifiers":[
        {
            "category":"Home & Garden",
            "subcategory":"Carpets & Floor Coverings",
            "type":"Retail Goods"
        }
    ],
    "sg:phone":"+1 928 329 0015",
    "sg:postcode":"85365",
    "sg:province":"AZ",
    "wof:name":"Yuma Carpets",
    "wof:placetype":"venue"
},
  "geometry": {"coordinates":[-114.615191,32.693952],"type":"Point"}
}