{
  "type": "Feature",
  "properties": {
    "iso:country":"US",
    "sg:address":"2502 Demaret Dr",
    "sg:city":"Lake Havasu City",
    "sg:classifiers":[
        {
            "category":"Building & Trades",
            "subcategory":"Construction",
            "type":"Services"
        }
    ],
    "sg:phone":"+1 928 453 1459",
    "sg:postcode":"86406",
    "sg:province":"AZ",
    "sg:tags":[
        "contractor"
    ],
    "wof:name":"Jewett Acoustics",
    "wof:placetype":"venue"
},
  "geometry": {"coordinates":[-114.308448,34.461082],"type":"Point"}
}