{
  "type": "Feature",
  "properties": {
    "iso:country":"US",
    "sg:address":"5055 E Broadway Blvd",
    "sg:city":"Tucson",
    "sg:classifiers":[
        {
            "category":"Restaurant",
            "type":"Food & Drink"
        }
    ],
    "sg:phone":"+1 520 292 6900",
    "sg:postcode":"85711",
    "sg:province":"AZ",
    "wof:name":"Tucson Chinese Assc",
    "wof:placetype":"venue"
},
  "geometry": {"coordinates":[-110.886113,32.221711],"type":"Point"}
}