{
  "type": "Feature",
  "properties": {
    "iso:country":"US",
    "sg:address":"109 E Birch Ave",
    "sg:city":"Flagstaff",
    "sg:classifiers":[
        {
            "category":"Professional",
            "subcategory":"Lawyer & Legal Services",
            "type":"Services"
        }
    ],
    "sg:phone":"+1 928 774 6070",
    "sg:postcode":"86001",
    "sg:province":"AZ",
    "sg:tags":[
        "attorney"
    ],
    "wof:name":"Ralph W Pepino",
    "wof:placetype":"venue"
},
  "geometry": {"coordinates":[-111.64714,35.19895],"type":"Point"}
}