{
  "type": "Feature",
  "properties": {
    "addr:full":"304 W Sunrise Vista Dr Green Valley AZ 85614",
    "addr:housenumber":"304",
    "addr:postcode":"85614",
    "addr:street":"W Sunrise Vista Dr",
    "iso:country":"US",
    "sg:address":"304 W Sunrise Vista Dr",
    "sg:city":"Green Valley",
    "sg:classifiers":[
        {
            "category":"Manufacturing",
            "subcategory":"Retail Goods",
            "type":"Manufacturing & Wholesale Goods"
        }
    ],
    "sg:phone":"+1 520 399 3529",
    "sg:postcode":"85614",
    "sg:province":"AZ",
    "sg:tags":[
        "product",
        "mfg"
    ],
    "wof:name":"C&S Bbq Cabinets Inc",
    "wof:placetype":"venue"
},
  "geometry": {"coordinates":[-110.995625,31.829603],"type":"Point"}
}