{
  "type": "Feature",
  "properties": {
    "iso:country":"US",
    "sg:address":"5200 Lakewood Rd",
    "sg:city":"Fort Mohave",
    "sg:classifiers":[
        {
            "category":"Building & Trades",
            "subcategory":"Plumbing",
            "type":"Services"
        }
    ],
    "sg:phone":"+1 928 768 2525",
    "sg:postcode":"86426",
    "sg:province":"AZ",
    "sg:tags":[
        "sheet",
        "air",
        "metal",
        "conditioning",
        "contractor"
    ],
    "wof:name":"Arrow Air Conditioning",
    "wof:placetype":"venue"
},
  "geometry": {"coordinates":[-114.599774,35.005655],"type":"Point"}
}