{
  "type": "Feature",
  "properties": {
    "addr:full":"10375 E Whispering Wind Dr Scottsdale AZ 85255",
    "addr:housenumber":"10375",
    "addr:postcode":"85255",
    "addr:street":"E Whispering Wind Dr",
    "iso:country":"US",
    "sg:address":"10375 E Whispering Wind Dr",
    "sg:city":"Scottsdale",
    "sg:classifiers":[
        {
            "category":"Building & Trades",
            "subcategory":"Construction",
            "type":"Services"
        }
    ],
    "sg:phone":"+1 480 614 3558",
    "sg:postcode":"85255",
    "sg:province":"AZ",
    "sg:tags":[
        "new",
        "residential"
    ],
    "wof:name":"Grayson Homes Lc",
    "wof:placetype":"venue"
},
  "geometry": {"coordinates":[-111.857162,33.70715],"type":"Point"}
}