{
  "type": "Feature",
  "properties": {
    "iso:country":"US",
    "sg:address":"6221 E Montecito Ave",
    "sg:city":"Scottsdale",
    "sg:classifiers":[
        {
            "category":"Professional",
            "subcategory":"Management & Consulting",
            "type":"Services"
        }
    ],
    "sg:phone":"+1 480 945 0433",
    "sg:postcode":"85251",
    "sg:province":"AZ",
    "sg:tags":[
        "personnel",
        "consultant"
    ],
    "sg:website":"http://www.judylinkous.com",
    "wof:name":"Linkous & Assoc",
    "wof:placetype":"venue"
},
  "geometry": {"coordinates":[-111.947225,33.499474],"type":"Point"}
}