{
  "type": "Feature",
  "properties": {
    "iso:country":"US",
    "sg:address":"1907 E Campbell Ave",
    "sg:city":"Phoenix",
    "sg:classifiers":[
        {
            "category":"Professional",
            "type":"Services"
        },
        {
            "category":"Shopping",
            "subcategory":"Florist",
            "type":"Retail Goods"
        }
    ],
    "sg:phone":"+1 602 248 4460",
    "sg:postcode":"85016",
    "sg:province":"AZ",
    "wof:name":"Avant Garden Flowers & Events",
    "wof:placetype":"venue"
},
  "geometry": {"coordinates":[-112.038991,33.501936],"type":"Point"}
}