{
  "type": "Feature",
  "properties": {
    "addr:full":"2702 E Devon St Tucson AZ 85716",
    "addr:housenumber":"2702",
    "addr:postcode":"85716",
    "addr:street":"E Devon St",
    "iso:country":"US",
    "sg:address":"2702 E Devon St",
    "sg:city":"Tucson",
    "sg:classifiers":[
        {
            "category":"Wholesale",
            "subcategory":"Books, Periodicals, & Newspapers",
            "type":"Manufacturing & Wholesale Goods"
        }
    ],
    "sg:phone":"+1 520 325 0195",
    "sg:postcode":"85716",
    "sg:province":"AZ",
    "wof:name":"Hometown Newspaper Distrs",
    "wof:placetype":"venue"
},
  "geometry": {"coordinates":[-110.929496,32.218945],"type":"Point"}
}