{
  "type": "Feature",
  "properties": {
    "addr:full":"200 E Yavapai Rd Tucson AZ 85705",
    "addr:housenumber":"200",
    "addr:postcode":"85705",
    "addr:street":"E Yavapai Rd",
    "iso:country":"US",
    "sg:address":"200 E Yavapai Rd",
    "sg:city":"Tucson",
    "sg:classifiers":[
        {
            "category":"Education",
            "subcategory":"School",
            "type":"Public Place"
        }
    ],
    "sg:phone":"+1 520 292 9300",
    "sg:postcode":"85705",
    "sg:province":"AZ",
    "sg:website":"www.turningpointschool.com",
    "wof:name":"Turning Point School",
    "wof:placetype":"venue"
},
  "geometry": {"coordinates":[-110.968619,32.269938],"type":"Point"}
}