{
  "type": "Feature",
  "properties": {
    "iso:country":"US",
    "sg:address":"3565 S Broadmont Dr",
    "sg:city":"Tucson",
    "sg:classifiers":[
        {
            "category":"Government",
            "subcategory":"Office",
            "type":"Public Place"
        }
    ],
    "sg:phone":"+1 520 629 7700",
    "sg:postcode":"85713",
    "sg:province":"AZ",
    "sg:tags":[
        "state",
        "program",
        "transportation"
    ],
    "sg:website":"www.dot.state.az.us",
    "wof:name":"Transportation Arizona Dept",
    "wof:placetype":"venue"
},
  "geometry": {"coordinates":[-110.91961499999999,32.182564],"type":"Point"}
}