{
  "type": "Feature",
  "properties": {
    "iso:country":"US",
    "sg:address":"428 E Thunderbird Rd Suite 521",
    "sg:city":"Phoenix",
    "sg:classifiers":[
        {
            "category":"Home & Garden",
            "subcategory":"Building Materials",
            "type":"Retail Goods"
        },
        {
            "category":"Building & Trades",
            "subcategory":"Construction",
            "type":"Services"
        }
    ],
    "sg:phone":"+1 602 377 3755",
    "sg:postcode":"85022",
    "sg:province":"AZ",
    "sg:tags":[
        "industrial",
        "contractor",
        "concrete",
        "contractors-commercial",
        "staining",
        "masonry",
        "mason"
    ],
    "wof:name":"Nature's Best Landscape, Inc.",
    "wof:placetype":"venue"
},
  "geometry": {"coordinates":[-112.067718,33.607702],"type":"Point"}
}