{
  "type": "Feature",
  "properties": {
    "addr:full":"1 E Jackson St Phoenix AZ 85004",
    "addr:housenumber":"1",
    "addr:postcode":"85004",
    "addr:street":"E Jackson St",
    "iso:country":"US",
    "sg:address":"1 E Jackson St",
    "sg:city":"Phoenix",
    "sg:classifiers":[
        {
            "category":"Restaurant",
            "type":"Food & Drink"
        }
    ],
    "sg:phone":"+1 602 258 7880",
    "sg:postcode":"85004",
    "sg:province":"AZ",
    "wof:name":"Chop Shop",
    "wof:placetype":"venue"
},
  "geometry": {"coordinates":[-112.072513,33.44505],"type":"Point"}
}