{
  "type": "Feature",
  "properties": {
    "iso:country":"US",
    "sg:address":"911 N Industrial Park Ave",
    "sg:city":"Nogales",
    "sg:classifiers":[
        {
            "category":"Manufacturing",
            "subcategory":"Retail Goods",
            "type":"Manufacturing & Wholesale Goods"
        }
    ],
    "sg:phone":"+1 520 624 6663",
    "sg:postcode":"85621",
    "sg:province":"AZ",
    "sg:tags":[
        "oils-essential"
    ],
    "wof:name":"Superior Natural Oils",
    "wof:placetype":"venue"
},
  "geometry": {"coordinates":[-110.960688,31.347551],"type":"Point"}
}