{
  "type": "Feature",
  "properties": {
    "iso:country":"US",
    "sg:address":"10177 E San Salvador Dr",
    "sg:city":"Scottsdale",
    "sg:classifiers":[
        {
            "category":"Real Estate",
            "subcategory":"Real Estate Agent",
            "type":"Services"
        }
    ],
    "sg:phone":"+1 480 614 0712",
    "sg:postcode":"85258",
    "sg:province":"AZ",
    "wof:name":"Sylvia R McDowell PC",
    "wof:placetype":"venue"
},
  "geometry": {"coordinates":[-111.86006999999999,33.570674],"type":"Point"}
}