{
  "type": "Feature",
  "properties": {
    "iso:country":"US",
    "sg:address":"4323 E Broadway Rd",
    "sg:city":"Mesa",
    "sg:classifiers":[
        {
            "category":"Building & Trades",
            "subcategory":"Construction",
            "type":"Services"
        }
    ],
    "sg:phone":"+1 480 962 1986",
    "sg:postcode":"85206",
    "sg:province":"AZ",
    "sg:tags":[
        "designer",
        "dealer",
        "pool",
        "swimming"
    ],
    "wof:name":"Blue Sapphire Pools",
    "wof:placetype":"venue"
},
  "geometry": {"coordinates":[-111.738429,33.408219],"type":"Point"}
}