{
  "type": "Feature",
  "properties": {
    "addr:full":"2041 S Craycroft Rd Tucson AZ 85711",
    "addr:housenumber":"2041",
    "addr:postcode":"85711",
    "addr:street":"S Craycroft Rd",
    "iso:country":"US",
    "sg:address":"2041 S Craycroft Rd",
    "sg:city":"Tucson",
    "sg:classifiers":[
        {
            "category":"Professional",
            "type":"Services"
        },
        {
            "category":"Restaurant",
            "type":"Food & Drink"
        }
    ],
    "sg:phone":"+1 520 549 1143",
    "sg:postcode":"85711",
    "sg:province":"AZ",
    "sg:tags":[
        "caterer"
    ],
    "sg:website":"http://www.mamalouisas.com",
    "wof:name":"Mama Louisa's Italian Restaurant",
    "wof:placetype":"venue"
},
  "geometry": {"coordinates":[-110.875123,32.198493],"type":"Point"}
}