{
  "type": "Feature",
  "properties": {
    "iso:country":"US",
    "sg:address":"1430 W Warner Rd",
    "sg:city":"Gilbert",
    "sg:classifiers":[
        {
            "category":"Building & Trades",
            "subcategory":"Locksmith",
            "type":"Services"
        }
    ],
    "sg:phone":"+1 480 319 8013",
    "sg:postcode":"85233",
    "sg:province":"AZ",
    "sg:tags":[
        "key"
    ],
    "wof:name":"Locksmith",
    "wof:placetype":"venue"
},
  "geometry": {"coordinates":[-111.822511,33.335433],"type":"Point"}
}