{
  "type": "Feature",
  "properties": {
    "iso:country":"US",
    "sg:address":"2255 W Northern Ave",
    "sg:city":"Phoenix",
    "sg:classifiers":[
        {
            "category":"Professional",
            "subcategory":"Credit Reporting & Collection",
            "type":"Services"
        }
    ],
    "sg:phone":"+1 602 995 8991",
    "sg:postcode":"85021",
    "sg:province":"AZ",
    "sg:tags":[
        "agency"
    ],
    "wof:name":"Canyon State Professional Inc",
    "wof:placetype":"venue"
},
  "geometry": {"coordinates":[-112.106382,33.553025],"type":"Point"}
}