{
  "type": "Feature",
  "properties": {
    "iso:country":"US",
    "sg:address":"6732 E Kenyon Dr",
    "sg:city":"Tucson",
    "sg:classifiers":[
        {
            "category":"Shopping",
            "subcategory":"Florist",
            "type":"Retail Goods"
        }
    ],
    "sg:phone":"+1 520 750 1575",
    "sg:postcode":"85710",
    "sg:province":"AZ",
    "wof:name":"Linda Tierra Designs",
    "wof:placetype":"venue"
},
  "geometry": {"coordinates":[-110.84865,32.210884],"type":"Point"}
}