{
  "type": "Feature",
  "properties": {
    "iso:country":"US",
    "sg:address":"75 W Cleveland St",
    "sg:city":"St Johns",
    "sg:classifiers":[
        {
            "category":"Government",
            "subcategory":"Office",
            "type":"Public Place"
        }
    ],
    "sg:phone":"+1 928 337 3565",
    "sg:postcode":"85936",
    "sg:province":"AZ",
    "sg:tags":[
        "state",
        "program"
    ],
    "wof:name":"Environmental Quality Dept",
    "wof:placetype":"venue"
},
  "geometry": {"coordinates":[-109.36523200000001,34.50688],"type":"Point"}
}