{
  "type": "Feature",
  "properties": {
    "iso:country":"US",
    "sg:address":"3242 E Bell Rd",
    "sg:city":"Phoenix",
    "sg:classifiers":[
        {
            "category":"Education",
            "subcategory":"School",
            "type":"Public Place"
        }
    ],
    "sg:phone":"+1 602 485 9872",
    "sg:postcode":"85032",
    "sg:province":"AZ",
    "wof:name":"Ombudsman Educational",
    "wof:placetype":"venue"
},
  "geometry": {"coordinates":[-112.010078,33.640689],"type":"Point"}
}