{
  "type": "Feature",
  "properties": {
    "iso:country":"US",
    "sg:address":"311 E Rose Ln",
    "sg:city":"Phoenix",
    "sg:classifiers":[
        {
            "category":"Banks & Credit Unions",
            "subcategory":"Investment Brokerage",
            "type":"Services"
        }
    ],
    "sg:phone":"+1 602 277 1800",
    "sg:postcode":"85012",
    "sg:province":"AZ",
    "wof:name":"Mckellar & Co",
    "wof:placetype":"venue"
},
  "geometry": {"coordinates":[-112.066906,33.527334],"type":"Point"}
}