{
  "type": "Feature",
  "properties": {
    "iso:country":"US",
    "sg:address":"12035 N Saguaro Blvd",
    "sg:city":"Fountain Hills",
    "sg:classifiers":[
        {
            "category":"Wholesale",
            "subcategory":"Machinery & Supplies",
            "type":"Manufacturing & Wholesale Goods"
        }
    ],
    "sg:phone":"+1 480 816 8373",
    "sg:postcode":"85268",
    "sg:province":"AZ",
    "sg:tags":[
        "machine",
        "tool"
    ],
    "wof:name":"Agile Manufacturing Technology",
    "wof:placetype":"venue"
},
  "geometry": {"coordinates":[-111.714926,33.594985],"type":"Point"}
}