{
  "type": "Feature",
  "properties": {
    "iso:country":"US",
    "sg:address":"1002 S Campbell Ave",
    "sg:city":"Tucson",
    "sg:classifiers":[
        {
            "category":"Building & Trades",
            "subcategory":"Landscaping Services",
            "type":"Services"
        },
        {
            "category":"Building & Trades",
            "subcategory":"Plumbing",
            "type":"Services"
        },
        {
            "category":"Home & Garden",
            "subcategory":"Building Materials",
            "type":"Retail Goods"
        },
        {
            "category":"Utilities",
            "subcategory":"Sewage",
            "type":"Services"
        },
        {
            "category":"Building & Trades",
            "subcategory":"Cleaning & Sanitation",
            "type":"Services"
        }
    ],
    "sg:phone":"+1 520 886 4159",
    "sg:postcode":"85719",
    "sg:province":"AZ",
    "sg:tags":[
        "cleaner",
        "plumber",
        "industrial",
        "heater",
        "leak",
        "repairer",
        "contractor",
        "water",
        "sewer",
        "contractors-commercial",
        "detecting",
        "plumbing-drain"
    ],
    "sg:website":"http://www.spartantucson.com/",
    "wof:name":"Spartan Plumbing",
    "wof:placetype":"venue"
},
  "geometry": {"coordinates":[-110.943699,32.209586],"type":"Point"}
}