{
  "type": "Feature",
  "properties": {
    "iso:country":"US",
    "sg:address":"6630 W Cactus Rd",
    "sg:city":"Glendale",
    "sg:classifiers":[
        {
            "category":"Real Estate",
            "subcategory":"Real Estate Agent",
            "type":"Services"
        }
    ],
    "sg:phone":"+1 602 288 3305",
    "sg:postcode":"85029",
    "sg:province":"AZ",
    "sg:website":"www.azhotproperties.com",
    "wof:name":"Northwest Realty",
    "wof:placetype":"venue"
},
  "geometry": {"coordinates":[-112.202476,33.596295],"type":"Point"}
}