{
  "type": "Feature",
  "properties": {
    "iso:country":"US",
    "sg:address":"925 W Monona Dr",
    "sg:city":"Phoenix",
    "sg:classifiers":[
        {
            "category":"Building & Trades",
            "subcategory":"Construction",
            "type":"Services"
        }
    ],
    "sg:phone":"+1 623 780 9504",
    "sg:postcode":"85027",
    "sg:province":"AZ",
    "sg:tags":[
        "concrete",
        "contractor"
    ],
    "wof:name":"Cdr Concrete Inc",
    "wof:placetype":"venue"
},
  "geometry": {"coordinates":[-112.085384,33.674787],"type":"Point"}
}