{
  "type": "Feature",
  "properties": {
    "iso:country":"US",
    "sg:address":"2331 W Toledo Pl",
    "sg:city":"Chandler",
    "sg:classifiers":[
        {
            "category":"Utilities",
            "subcategory":"Telephone",
            "type":"Services"
        }
    ],
    "sg:phone":"+1 480 634 4304",
    "sg:postcode":"85224",
    "sg:province":"AZ",
    "sg:tags":[
        "communications"
    ],
    "wof:name":"Scrappablescom",
    "wof:placetype":"venue"
},
  "geometry": {"coordinates":[-111.881479,33.307387],"type":"Point"}
}