{
  "type": "Feature",
  "properties": {
    "addr:full":"16222 W Young St Surprise AZ 85374",
    "addr:housenumber":"16222",
    "addr:postcode":"85374",
    "addr:street":"W Young St",
    "iso:country":"US",
    "sg:address":"16222 W Young St",
    "sg:city":"Surprise",
    "sg:classifiers":[
        {
            "category":"Professional",
            "type":"Services"
        }
    ],
    "sg:phone":"+1 623 584 4782",
    "sg:postcode":"85374",
    "sg:province":"AZ",
    "wof:name":"Santacasa Anthony P Roche",
    "wof:placetype":"venue"
},
  "geometry": {"coordinates":[-112.408272,33.635785],"type":"Point"}
}