{
  "type": "Feature",
  "properties": {
    "addr:full":"3916 W Morrow Dr Glendale AZ 85308",
    "addr:housenumber":"3916",
    "addr:postcode":"85308",
    "addr:street":"W Morrow Dr",
    "iso:country":"US",
    "sg:address":"3916 W Morrow Dr",
    "sg:city":"Glendale",
    "sg:classifiers":[
        {
            "category":"Freight",
            "type":"Transportation"
        }
    ],
    "sg:phone":"+1 602 618 3009",
    "sg:postcode":"85308",
    "sg:province":"AZ",
    "sg:tags":[
        "operator",
        "local",
        "trucking"
    ],
    "wof:name":"Jeff Rhodes Trucking",
    "wof:placetype":"venue"
},
  "geometry": {"coordinates":[-112.14729,33.656499],"type":"Point"}
}