{
  "type": "Feature",
  "properties": {
    "addr:full":"1450 E White Mountain Blvd Pinetop AZ 85935",
    "addr:housenumber":"1450",
    "addr:postcode":"az 85935",
    "addr:street":"E White Mountain Blvd",
    "iso:country":"US",
    "sg:address":"1450 E White Mountain Blvd",
    "sg:city":"Pinetop",
    "sg:classifiers":[
        {
            "category":"Sports & Exercise",
            "subcategory":"Gym",
            "type":"Entertainment"
        }
    ],
    "sg:phone":"+1 928 367 5522",
    "sg:postcode":"85935",
    "sg:province":"AZ",
    "sg:tags":[
        "club",
        "health",
        "studio",
        "gymnasium"
    ],
    "wof:name":"Curves",
    "wof:placetype":"venue"
},
  "geometry": {"coordinates":[-109.938728,34.125946],"type":"Point"}
}