{
  "type": "Feature",
  "properties": {
    "iso:country":"US",
    "sg:address":"7102 S 8th St",
    "sg:city":"Phoenix",
    "sg:classifiers":[
        {
            "category":"Communications",
            "subcategory":"Film & Video Production",
            "type":"Services"
        }
    ],
    "sg:phone":"+1 602 276 3770",
    "sg:postcode":"85042",
    "sg:province":"AZ",
    "sg:tags":[
        "tv",
        "radio",
        "services-commercial",
        "companies-film"
    ],
    "wof:name":"8th Street Production",
    "wof:placetype":"venue"
},
  "geometry": {"coordinates":[-112.06221,33.382066],"type":"Point"}
}