{
  "type": "Feature",
  "properties": {
    "iso:country":"US",
    "sg:address":"3215 E Camelback Rd",
    "sg:city":"Phoenix",
    "sg:classifiers":[
        {
            "category":"Shopping",
            "subcategory":"Jewelry",
            "type":"Retail Goods"
        }
    ],
    "sg:phone":"+1 623 979 4445",
    "sg:postcode":"85018",
    "sg:province":"AZ",
    "sg:tags":[
        "manufacturer",
        "jewelers-wholesale",
        "jeweler"
    ],
    "sg:website":"www.londongold.com",
    "wof:name":"London Gold",
    "wof:placetype":"venue"
},
  "geometry": {"coordinates":[-112.01239,33.509899],"type":"Point"}
}