{
  "type": "Feature",
  "properties": {
    "addr:full":"1545 W Horseshoe Bend Dr Camp Verde AZ 86322",
    "addr:housenumber":"1545",
    "addr:postcode":"az 86322",
    "addr:street":"W Horseshoe Bend Dr",
    "iso:country":"US",
    "sg:address":"1545 W Horseshoe Bend Dr",
    "sg:city":"Camp Verde",
    "sg:classifiers":[
        {
            "category":"Freight",
            "type":"Transportation"
        }
    ],
    "sg:phone":"+1 928 567 4579",
    "sg:postcode":"86322",
    "sg:province":"AZ",
    "sg:tags":[
        "operator",
        "landscape",
        "trucking"
    ],
    "wof:name":"Garys Hauling",
    "wof:placetype":"venue"
},
  "geometry": {"coordinates":[-111.87944299999999,34.60817],"type":"Point"}
}