{
  "type": "Feature",
  "properties": {
    "iso:country":"US",
    "sg:address":"7987 N 53rd Ave",
    "sg:city":"Glendale",
    "sg:classifiers":[
        {
            "category":"Professional",
            "type":"Services"
        }
    ],
    "sg:phone":"+1 623 435 1754",
    "sg:postcode":"85301",
    "sg:province":"AZ",
    "wof:name":"In Kyong Hak",
    "wof:placetype":"venue"
},
  "geometry": {"coordinates":[-112.173114,33.55293],"type":"Point"}
}