{
  "type": "Feature",
  "properties": {
    "iso:country":"US",
    "sg:address":"2618 E Lupine Ave",
    "sg:city":"Phoenix",
    "sg:classifiers":[
        {
            "category":"Professional",
            "subcategory":"Business Services",
            "type":"Services"
        }
    ],
    "sg:phone":"+1 602 992 2595",
    "sg:postcode":"85028",
    "sg:province":"AZ",
    "sg:tags":[
        "embroidery"
    ],
    "wof:name":"Susan's Studio",
    "wof:placetype":"venue"
},
  "geometry": {"coordinates":[-112.024541,33.590572],"type":"Point"}
}