{
  "type": "Feature",
  "properties": {
    "iso:country":"US",
    "sg:address":"575 W Valoro Dr",
    "sg:city":"Tucson",
    "sg:classifiers":[
        {
            "category":"Organizations",
            "subcategory":"Religious Organization",
            "type":"Services"
        }
    ],
    "sg:phone":"+1 520 297 4011",
    "sg:postcode":"85737",
    "sg:province":"AZ",
    "sg:tags":[
        "church"
    ],
    "wof:name":"Church Of Jesus Christ Of Lds",
    "wof:placetype":"venue"
},
  "geometry": {"coordinates":[-110.97507899999999,32.387705],"type":"Point"}
}