{
  "type": "Feature",
  "properties": {
    "iso:country":"US",
    "sg:address":"5317 E Speedway Blvd",
    "sg:city":"Tucson",
    "sg:classifiers":[
        {
            "category":"Arts & Performance",
            "subcategory":"Theater",
            "type":"Entertainment"
        }
    ],
    "sg:phone":"+1 520 327 0160",
    "sg:postcode":"85712",
    "sg:province":"AZ",
    "wof:name":"Live Theatre Workshop",
    "wof:placetype":"venue"
},
  "geometry": {"coordinates":[-110.877923,32.23626],"type":"Point"}
}