{
  "type": "Feature",
  "properties": {
    "addr:full":"3305 E Marconi Ave Phoenix AZ 85032",
    "addr:housenumber":"3305",
    "addr:postcode":"85032",
    "addr:street":"E Marconi Ave",
    "iso:country":"US",
    "sg:address":"3305 E Marconi Ave",
    "sg:city":"Phoenix",
    "sg:classifiers":[
        {
            "category":"Manufacturing",
            "subcategory":"Electronics",
            "type":"Manufacturing & Wholesale Goods"
        }
    ],
    "sg:phone":"+1 602 493 5905",
    "sg:postcode":"85032",
    "sg:province":"AZ",
    "sg:tags":[
        "electronic",
        "resistor",
        "mfg"
    ],
    "wof:name":"Vishay Intertechnology Inc",
    "wof:placetype":"venue"
},
  "geometry": {"coordinates":[-112.010366,33.631251],"type":"Point"}
}