{
  "type": "Feature",
  "properties": {
    "iso:country":"US",
    "sg:address":"3244 E Speedway Blvd",
    "sg:city":"Tucson",
    "sg:classifiers":[
        {
            "category":"Retail",
            "subcategory":"Photofinishing",
            "type":"Services"
        }
    ],
    "sg:phone":"+1 520 325 0065",
    "sg:postcode":"85716",
    "sg:province":"AZ",
    "sg:tags":[
        "photo",
        "finishing"
    ],
    "sg:website":"www.centricphoto.com",
    "wof:name":"Centric Photo Processing",
    "wof:placetype":"venue"
},
  "geometry": {"coordinates":[-110.923255,32.236034],"type":"Point"}
}