{
  "type": "Feature",
  "properties": {
    "iso:country":"US",
    "sg:address":"7325 E 3rd Ave",
    "sg:city":"Scottsdale",
    "sg:classifiers":[
        {
            "category":"Restaurant",
            "type":"Food & Drink"
        }
    ],
    "sg:menulink":"http://www.allmenus.com/az/phoenix/4975-bada-boom-pasta-room/menu/",
    "sg:phone":"+1 480 214 2666",
    "sg:postcode":"85251",
    "sg:province":"AZ",
    "sg:tags":[
        "italian"
    ],
    "wof:name":"Bada Boom Pasta Room",
    "wof:placetype":"venue"
},
  "geometry": {"coordinates":[-111.924426,33.496903],"type":"Point"}
}