{
  "type": "Feature",
  "properties": {
    "iso:country":"US",
    "sg:address":"19848 W Dunlap Rd",
    "sg:city":"Buckeye",
    "sg:classifiers":[
        {
            "category":"Retail",
            "subcategory":"Veterinary Services",
            "type":"Services"
        }
    ],
    "sg:phone":"+1 623 327 1811",
    "sg:postcode":"85326",
    "sg:province":"AZ",
    "sg:tags":[
        "specialty"
    ],
    "wof:name":"Estrella Equine Practice Inc",
    "wof:placetype":"venue"
},
  "geometry": {"coordinates":[-112.48685999999999,33.41386],"type":"Point"}
}