{
  "type": "Feature",
  "properties": {
    "iso:country":"US",
    "sg:address":"2040 E Minton Dr",
    "sg:city":"Tempe",
    "sg:classifiers":[
        {
            "category":"Building & Trades",
            "subcategory":"Construction",
            "type":"Services"
        }
    ],
    "sg:phone":"+1 480 215 7875",
    "sg:postcode":"85282",
    "sg:province":"AZ",
    "sg:tags":[
        "repairing",
        "remodeling",
        "contractor"
    ],
    "wof:name":"Kokopelli Building Solutions",
    "wof:placetype":"venue"
},
  "geometry": {"coordinates":[-111.897269,33.381799],"type":"Point"}
}