{
  "type": "Feature",
  "properties": {
    "iso:country":"US",
    "sg:address":"6306 W Hardscrabble Mesa Rd",
    "sg:city":"Pine",
    "sg:classifiers":[
        {
            "category":"Real Estate",
            "subcategory":"Real Estate Services",
            "type":"Services"
        },
        {
            "category":"Real Estate",
            "subcategory":"Real Estate Agent",
            "type":"Services"
        }
    ],
    "sg:phone":"+1 928 476 2400",
    "sg:postcode":"85544",
    "sg:province":"AZ",
    "sg:tags":[
        "buyer",
        "broker"
    ],
    "wof:name":"Sunny Mountain Realty",
    "wof:placetype":"venue"
},
  "geometry": {"coordinates":[-111.459493,34.384135],"type":"Point"}
}