{
  "type": "Feature",
  "properties": {
    "addr:full":"7375 E Stetson Dr Scottsdale AZ 85251",
    "addr:housenumber":"7375",
    "addr:postcode":"85251",
    "addr:street":"E Stetson Dr",
    "iso:country":"US",
    "sg:address":"7375 E Stetson Dr",
    "sg:city":"Scottsdale",
    "sg:classifiers":[
        {
            "category":"Banks & Credit Unions",
            "subcategory":"Financial Services",
            "type":"Services"
        }
    ],
    "sg:phone":"+1 602 421 3626",
    "sg:postcode":"85251",
    "sg:province":"AZ",
    "sg:tags":[
        "investment",
        "real estate"
    ],
    "wof:name":"Sleeping Bear Partners LLC",
    "wof:placetype":"venue"
},
  "geometry": {"coordinates":[-111.921874,33.499485],"type":"Point"}
}