{
  "type": "Feature",
  "properties": {
    "addr:full":"832 W Baseline Rd Ste 25 Mesa AZ 85210",
    "addr:housenumber":"832",
    "addr:postcode":"85210",
    "addr:street":"W Baseline Rd Ste 25",
    "iso:country":"US",
    "sg:address":"832 W Baseline Rd Ste 25",
    "sg:city":"Mesa",
    "sg:classifiers":[
        {
            "category":"Health Services",
            "subcategory":"Chiropractor",
            "type":"Services"
        }
    ],
    "sg:phone":"+1 480 345 1791",
    "sg:postcode":"85210",
    "sg:province":"AZ",
    "wof:name":"Crystal Clear Chiropractic",
    "wof:placetype":"venue"
},
  "geometry": {"coordinates":[-111.846001,33.391998],"type":"Point"}
}