{
  "type": "Feature",
  "properties": {
    "iso:country":"US",
    "sg:address":"527 E Fairmont Dr",
    "sg:city":"Tempe",
    "sg:classifiers":[
        {
            "category":"Building & Trades",
            "subcategory":"Construction",
            "type":"Services"
        }
    ],
    "sg:phone":"+1 480 966 2529",
    "sg:postcode":"85282",
    "sg:province":"AZ",
    "sg:tags":[
        "new",
        "remodeling",
        "home"
    ],
    "wof:name":"Amco Enterprises Inc",
    "wof:placetype":"venue"
},
  "geometry": {"coordinates":[-111.930081,33.39538],"type":"Point"}
}