{
  "type": "Feature",
  "properties": {
    "iso:country":"US",
    "sg:address":"13006 W Indian School Rd",
    "sg:city":"Litchfield Park",
    "sg:classifiers":[
        {
            "category":"Restaurant",
            "type":"Food & Drink"
        }
    ],
    "sg:menulink":"http://www.allmenus.com/az/phoenix/198780-kfc---kentucky-fried-chicken/menu/",
    "sg:phone":"+1 623 535 5528",
    "sg:postcode":"85340",
    "sg:province":"AZ",
    "sg:tags":[
        "american",
        "chicken"
    ],
    "wof:name":"KFC - Kentucky Fried Chicken",
    "wof:placetype":"venue"
},
  "geometry": {"coordinates":[-112.338897,33.493296],"type":"Point"}
}