{
  "type": "Feature",
  "properties": {
    "iso:country":"US",
    "sg:address":"3029 E Thomas Rd",
    "sg:city":"Phoenix",
    "sg:classifiers":[
        {
            "category":"Wholesale",
            "subcategory":"Motor Vehicles",
            "type":"Manufacturing & Wholesale Goods"
        },
        {
            "category":"Retail",
            "subcategory":"Auto Repair",
            "type":"Services"
        }
    ],
    "sg:phone":"+1 602 955 8444",
    "sg:postcode":"85016",
    "sg:province":"AZ",
    "sg:tags":[
        "automobile",
        "inspection"
    ],
    "wof:name":"A-Advanced Emissions",
    "wof:placetype":"venue"
},
  "geometry": {"coordinates":[-112.015074,33.480471],"type":"Point"}
}