{
  "type": "Feature",
  "properties": {
    "addr:full":"7170 E McDowell Rd Scottsdale AZ 85008",
    "addr:housenumber":"7170",
    "addr:postcode":"85008",
    "addr:street":"E Mcdowell Rd",
    "iso:country":"US",
    "sg:address":"7170 E McDowell Rd",
    "sg:city":"Scottsdale",
    "sg:classifiers":[
        {
            "category":"Restaurant",
            "type":"Food & Drink"
        }
    ],
    "sg:phone":"+1 480 945 1689",
    "sg:postcode":"85008",
    "sg:province":"AZ",
    "sg:tags":[
        "eating"
    ],
    "wof:name":"Jbs Family Restaurants Inc",
    "wof:placetype":"venue"
},
  "geometry": {"coordinates":[-111.929641,33.465742],"type":"Point"}
}