{
  "type": "Feature",
  "properties": {
    "addr:full":"1415 W 3rd St Tempe AZ 85281",
    "addr:housenumber":"1415",
    "addr:postcode":"85281",
    "addr:street":"W 3Rd St",
    "iso:country":"US",
    "sg:address":"1415 W 3rd St",
    "sg:city":"Tempe",
    "sg:classifiers":[
        {
            "category":"Manufacturing",
            "subcategory":"Tools & Machinery",
            "type":"Manufacturing & Wholesale Goods"
        }
    ],
    "sg:phone":"+1 480 967 2489",
    "sg:postcode":"85281",
    "sg:province":"AZ",
    "sg:tags":[
        "physician",
        "surgeon"
    ],
    "wof:name":"Orth Rehab",
    "wof:placetype":"venue"
},
  "geometry": {"coordinates":[-111.964474,33.427301],"type":"Point"}
}