{
  "type": "Feature",
  "properties": {
    "iso:country":"US",
    "sg:address":"1500 S Dobson Rd Ste 311",
    "sg:city":"Mesa",
    "sg:classifiers":[
        {
            "category":"Health Services",
            "subcategory":"Doctor",
            "type":"Services"
        }
    ],
    "sg:phone":"+1 480 969 5958",
    "sg:postcode":"85202",
    "sg:province":"AZ",
    "sg:tags":[
        "gynecology",
        "physician",
        "surgeon",
        "surgeons",
        "obstetrics"
    ],
    "wof:name":"Samaritan Obstetrics & Gynecology, Inc",
    "wof:placetype":"venue"
},
  "geometry": {"coordinates":[-111.874641,33.387821],"type":"Point"}
}