{
  "type": "Feature",
  "properties": {
    "iso:country":"US",
    "sg:address":"1043 S Lewis",
    "sg:city":"Mesa",
    "sg:classifiers":[
        {
            "category":"Professional",
            "subcategory":"Management & Consulting",
            "type":"Services"
        }
    ],
    "sg:phone":"+1 480 777 7632",
    "sg:postcode":"85210",
    "sg:province":"AZ",
    "wof:name":"Nova Asset Management Ent",
    "wof:placetype":"venue"
},
  "geometry": {"coordinates":[-111.829049,33.394099],"type":"Point"}
}