{
  "type": "Feature",
  "properties": {
    "addr:full":"6900 E Camelback Rd Scottsdale AZ 85251",
    "addr:housenumber":"6900",
    "addr:postcode":"85251",
    "addr:street":"E Camelback Rd",
    "iso:country":"US",
    "sg:address":"6900 E Camelback Rd",
    "sg:city":"Scottsdale",
    "sg:classifiers":[
        {
            "category":"Utilities",
            "subcategory":"Telephone",
            "type":"Services"
        }
    ],
    "sg:phone":"+1 480 874 2700",
    "sg:postcode":"85251",
    "sg:province":"AZ",
    "sg:tags":[
        "company"
    ],
    "sg:website":"www.dancris.com",
    "wof:name":"Dancris Telecommunications",
    "wof:placetype":"venue"
},
  "geometry": {"coordinates":[-111.926451,33.502345],"type":"Point"}
}