{
  "type": "Feature",
  "properties": {
    "iso:country":"US",
    "sg:address":"100 el Camino Rd",
    "sg:city":"Sedona",
    "sg:classifiers":[
        {
            "category":"Food & Beverages",
            "subcategory":"Specialty",
            "type":"Retail Goods"
        }
    ],
    "sg:phone":"+1 928 282 9362",
    "sg:postcode":"86336",
    "sg:province":"AZ",
    "wof:name":"Life Resources",
    "wof:placetype":"venue"
},
  "geometry": {"coordinates":[-111.812905,34.859975],"type":"Point"}
}