{
  "type": "Feature",
  "properties": {
    "iso:country":"US",
    "sg:address":"3003 N Central Ave Suite 100",
    "sg:city":"Phoenix",
    "sg:classifiers":[
        {
            "category":"Banks & Credit Unions",
            "subcategory":"Bank",
            "type":"Services"
        },
        {
            "category":"Banks & Credit Unions",
            "subcategory":"Financial Services",
            "type":"Services"
        }
    ],
    "sg:phone":"+1 480 783 6790",
    "sg:postcode":"85012",
    "sg:province":"AZ",
    "sg:tags":[
        "saving",
        "loan",
        "commercial"
    ],
    "sg:website":"http://www.compassbank.com",
    "wof:name":"Compass Bank",
    "wof:placetype":"venue"
},
  "geometry": {"coordinates":[-112.073662,33.482254],"type":"Point"}
}