{
  "type": "Feature",
  "properties": {
    "addr:full":"1500 E Cedar Ave Flagstaff AZ 86004",
    "addr:housenumber":"1500",
    "addr:postcode":"86004",
    "addr:street":"E Cedar Ave",
    "iso:country":"US",
    "sg:address":"1500 E Cedar Ave",
    "sg:city":"Flagstaff",
    "sg:classifiers":[
        {
            "category":"Insurance",
            "subcategory":"Insurance Agent",
            "type":"Services"
        }
    ],
    "sg:phone":"+1 928 779 5047",
    "sg:postcode":"86004",
    "sg:province":"AZ",
    "sg:tags":[
        "all",
        "type",
        "ins"
    ],
    "wof:name":"Prudential",
    "wof:placetype":"venue"
},
  "geometry": {"coordinates":[-111.623019,35.218357],"type":"Point"}
}