{
  "type": "Feature",
  "properties": {
    "addr:full":"2020 E Broadway Rd Tempe AZ 85282",
    "addr:housenumber":"2020",
    "addr:postcode":"85282",
    "addr:street":"E Broadway Rd",
    "iso:country":"US",
    "sg:address":"2020 E Broadway Rd",
    "sg:city":"Tempe",
    "sg:classifiers":[
        {
            "category":"Professional",
            "subcategory":"Management & Consulting",
            "type":"Services"
        }
    ],
    "sg:phone":"+1 480 921 8642",
    "sg:postcode":"85282",
    "sg:province":"AZ",
    "sg:tags":[
        "retail",
        "direct",
        "sales"
    ],
    "wof:name":"North American Advanced Market",
    "wof:placetype":"venue"
},
  "geometry": {"coordinates":[-111.899699,33.407572],"type":"Point"}
}