{
  "type": "Feature",
  "properties": {
    "iso:country":"US",
    "sg:address":"2275 Lariat Rd",
    "sg:city":"Sedona",
    "sg:classifiers":[
        {
            "category":"Professional",
            "subcategory":"Advertising",
            "type":"Services"
        }
    ],
    "sg:phone":"+1 928 203 9229",
    "sg:postcode":"86336",
    "sg:province":"AZ",
    "sg:tags":[
        "counselor"
    ],
    "wof:name":"Hawthorne Direct Inc",
    "wof:placetype":"venue"
},
  "geometry": {"coordinates":[-111.800085,34.875698],"type":"Point"}
}