{
  "type": "Feature",
  "properties": {
    "iso:country":"US",
    "sg:address":"549 N 4th Ave",
    "sg:city":"Tucson",
    "sg:classifiers":[
        {
            "category":"Shopping",
            "subcategory":"Gifts & Souvenirs",
            "type":"Retail Goods"
        }
    ],
    "sg:phone":"+1 520 792 9910",
    "sg:postcode":"85705",
    "sg:province":"AZ",
    "sg:tags":[
        "shop"
    ],
    "wof:name":"Creative Spirit Gallery",
    "wof:placetype":"venue"
},
  "geometry": {"coordinates":[-110.965671,32.228396],"type":"Point"}
}