{
  "type": "Feature",
  "properties": {
    "iso:country":"US",
    "sg:address":"9810 E Desert Cove Ave",
    "sg:city":"Scottsdale",
    "sg:classifiers":[
        {
            "category":"Real Estate",
            "subcategory":"Developer",
            "type":"Services"
        }
    ],
    "sg:phone":"+1 480 991 1111",
    "sg:postcode":"85260",
    "sg:province":"AZ",
    "wof:name":"Northsight Corp",
    "wof:placetype":"venue"
},
  "geometry": {"coordinates":[-111.868291,33.586191],"type":"Point"}
}