{
  "type": "Feature",
  "properties": {
    "iso:country":"US",
    "sg:address":"10785 W Grand Ave",
    "sg:city":"Sun City",
    "sg:classifiers":[
        {
            "category":"Professional",
            "subcategory":"Advertising",
            "type":"Services"
        }
    ],
    "sg:phone":"+1 623 974 4973",
    "sg:postcode":"85351",
    "sg:province":"AZ",
    "sg:tags":[
        "mailing",
        "shipping"
    ],
    "wof:name":"Postal Contract Station 702",
    "wof:placetype":"venue"
},
  "geometry": {"coordinates":[-112.29057299999999,33.602771],"type":"Point"}
}