{
  "type": "Feature",
  "properties": {
    "iso:country":"US",
    "sg:address":"1003 E 2nd St",
    "sg:city":"Winslow",
    "sg:classifiers":[
        {
            "category":"Real Estate",
            "subcategory":"Real Estate Operator",
            "type":"Services"
        }
    ],
    "sg:phone":"+1 928 289 2943",
    "sg:postcode":"86047",
    "sg:province":"AZ",
    "sg:tags":[
        "apartment"
    ],
    "wof:name":"Bel Air Motel",
    "wof:placetype":"venue"
},
  "geometry": {"coordinates":[-110.688894,35.019878],"type":"Point"}
}