{
  "type": "Feature",
  "properties": {
    "addr:full":"20515 W Arlington Rd Buckeye AZ 85326",
    "addr:housenumber":"20515",
    "addr:postcode":"85326",
    "addr:street":"W Arlington Rd",
    "iso:country":"US",
    "sg:address":"20515 W Arlington Rd",
    "sg:city":"Buckeye",
    "sg:classifiers":[
        {
            "category":"Building & Trades",
            "subcategory":"Landscaping Services",
            "type":"Services"
        }
    ],
    "sg:phone":"+1 623 386 4771",
    "sg:postcode":"85326",
    "sg:province":"AZ",
    "wof:name":"Mansanares Landscaping",
    "wof:placetype":"venue"
},
  "geometry": {"coordinates":[-112.491635,33.326536],"type":"Point"}
}