{
  "type": "Feature",
  "properties": {
    "iso:country":"US",
    "sg:address":"8005 N Wildomar Dr",
    "sg:city":"Tucson",
    "sg:classifiers":[
        {
            "category":"Professional",
            "subcategory":"Advertising",
            "type":"Services"
        }
    ],
    "sg:phone":"+1 520 405 5635",
    "sg:postcode":"85743",
    "sg:province":"AZ",
    "wof:name":"EXL Promotions",
    "wof:placetype":"venue"
},
  "geometry": {"coordinates":[-111.103639,32.352144],"type":"Point"}
}