{
  "type": "Feature",
  "properties": {
    "iso:country":"US",
    "sg:address":"835 W Warner Road",
    "sg:city":"Gilbert",
    "sg:classifiers":[
        {
            "category":"Cinema",
            "subcategory":"Movie Rental",
            "type":"Entertainment"
        }
    ],
    "sg:phone":"+1 480 892 2922",
    "sg:postcode":"85233",
    "sg:province":"AZ",
    "sg:tags":[
        "game",
        "video"
    ],
    "wof:name":"Blockbuster Video",
    "wof:placetype":"venue"
},
  "geometry": {"coordinates":[-111.811762,33.346503],"type":"Point"}
}