{
  "type": "Feature",
  "properties": {
    "iso:country":"US",
    "sg:address":"15248 N 38th St",
    "sg:city":"Phoenix",
    "sg:classifiers":[
        {
            "category":"Utilities",
            "subcategory":"Telephone",
            "type":"Services"
        },
        {
            "category":"Manufacturing",
            "subcategory":"Electronics",
            "type":"Manufacturing & Wholesale Goods"
        },
        {
            "category":"Communications",
            "subcategory":"Television Station",
            "type":"Services"
        }
    ],
    "sg:phone":"+1 602 788 6500",
    "sg:postcode":"85032",
    "sg:province":"AZ",
    "sg:tags":[
        "satellite",
        "telecommunications-equipment",
        "cable",
        "supply",
        "system",
        "equipment"
    ],
    "wof:name":"Telesys Communications Company",
    "wof:placetype":"venue"
},
  "geometry": {"coordinates":[-112.000331,33.62563],"type":"Point"}
}