{
  "type": "Feature",
  "properties": {
    "addr:full":"4810 N Black Canyon Hwy Phoenix AZ 85017",
    "addr:housenumber":"4810",
    "addr:postcode":"85017",
    "addr:street":"N Black Canyon Hwy",
    "iso:country":"US",
    "sg:address":"4810 N Black Canyon Hwy",
    "sg:city":"Phoenix",
    "sg:classifiers":[
        {
            "category":"Organizations",
            "subcategory":"Professional Association",
            "type":"Services"
        }
    ],
    "sg:phone":"+1 602 230 2019",
    "sg:postcode":"85017",
    "sg:province":"AZ",
    "wof:name":"Korean Association Of Arizona",
    "wof:placetype":"venue"
},
  "geometry": {"coordinates":[-112.11286699999999,33.505871],"type":"Point"}
}