{
  "type": "Feature",
  "properties": {
    "iso:country":"US",
    "sg:address":"29834 N Cave Creek Rd",
    "sg:city":"Cave Creek",
    "sg:classifiers":[
        {
            "category":"Insurance",
            "subcategory":"Life Insurance",
            "type":"Services"
        }
    ],
    "sg:phone":"+1 480 513 4565",
    "sg:postcode":"85331",
    "sg:province":"AZ",
    "sg:tags":[
        "carrier",
        "carrie"
    ],
    "wof:name":"Quality Benefits Inc",
    "wof:placetype":"venue"
},
  "geometry": {"coordinates":[-111.988314,33.75947],"type":"Point"}
}