{
  "type": "Feature",
  "properties": {
    "iso:country":"US",
    "sg:address":"1010 E Palmaire Ave",
    "sg:city":"Phoenix",
    "sg:classifiers":[
        {
            "category":"Recreation",
            "type":"Entertainment"
        }
    ],
    "sg:phone":"+1 602 957 3639",
    "sg:postcode":"85020",
    "sg:province":"AZ",
    "sg:tags":[
        "astrologer"
    ],
    "wof:name":"Charlotte Anderson LTD",
    "wof:placetype":"venue"
},
  "geometry": {"coordinates":[-112.058212,33.540667],"type":"Point"}
}