{
  "type": "Feature",
  "properties": {
    "iso:country":"US",
    "sg:address":"3021 W Mcdowell Rd",
    "sg:city":"Phoenix",
    "sg:classifiers":[
        {
            "category":"Autos & Motor Vehicles",
            "subcategory":"Automobile Sales",
            "type":"Retail Goods"
        }
    ],
    "sg:phone":"+1 602 278 6563",
    "sg:postcode":"85009",
    "sg:province":"AZ",
    "sg:tags":[
        "used",
        "car",
        "dealers-used",
        "new",
        "cars-wholesale"
    ],
    "wof:name":"Moon Valley Used Cars Inc",
    "wof:placetype":"venue"
},
  "geometry": {"coordinates":[-112.12407,33.46595],"type":"Point"}
}