{
  "type": "Feature",
  "properties": {
    "iso:country":"US",
    "sg:address":"2237 S 16th St Ste C2",
    "sg:city":"Phoenix",
    "sg:classifiers":[
        {
            "category":"Manufacturing",
            "subcategory":"Wood Products",
            "type":"Manufacturing & Wholesale Goods"
        },
        {
            "category":"Building & Trades",
            "subcategory":"Construction",
            "type":"Services"
        }
    ],
    "sg:phone":"+1 602 442 4400",
    "sg:postcode":"85034",
    "sg:province":"AZ",
    "sg:tags":[
        "millwork-wholesale",
        "manufacturer",
        "carpenter",
        "millwork"
    ],
    "wof:name":"Cutting Edge Components",
    "wof:placetype":"venue"
},
  "geometry": {"coordinates":[-112.047813,33.425857],"type":"Point"}
}