{
  "type": "Feature",
  "properties": {
    "iso:country":"US",
    "sg:address":"1550 E Prince Rd",
    "sg:city":"Tucson",
    "sg:classifiers":[
        {
            "category":"Professional",
            "subcategory":"Research",
            "type":"Services"
        }
    ],
    "sg:phone":"+1 520 881 4912",
    "sg:postcode":"85719",
    "sg:province":"AZ",
    "sg:tags":[
        "environmental",
        "ecological"
    ],
    "sg:website":"www.elmontgomery.com",
    "wof:name":"Errol L Montgomery & Assoc Inc",
    "wof:placetype":"venue"
},
  "geometry": {"coordinates":[-110.948615,32.2721],"type":"Point"}
}