{
  "type": "Feature",
  "properties": {
    "iso:country":"US",
    "sg:address":"3145 E Chandler Blvd",
    "sg:city":"Phoenix",
    "sg:classifiers":[
        {
            "category":"Recreation",
            "type":"Entertainment"
        }
    ],
    "sg:phone":"+1 480 706 6946",
    "sg:postcode":"85048",
    "sg:province":"AZ",
    "sg:tags":[
        "diving",
        "instruction"
    ],
    "wof:name":"N-Depth Scuba",
    "wof:placetype":"venue"
},
  "geometry": {"coordinates":[-112.015657,33.305139],"type":"Point"}
}