{
  "type": "Feature",
  "properties": {
    "iso:country":"US",
    "sg:address":"6320 E Golf Links Rd",
    "sg:city":"Tucson",
    "sg:classifiers":[
        {
            "category":"Real Estate",
            "subcategory":"Real Estate Agent",
            "type":"Services"
        }
    ],
    "sg:phone":"+1 520 790 0920",
    "sg:postcode":"85730",
    "sg:province":"AZ",
    "wof:name":"A & C Properties Inc",
    "wof:placetype":"venue"
},
  "geometry": {"coordinates":[-110.855203,32.191966],"type":"Point"}
}