{
  "type": "Feature",
  "properties": {
    "addr:full":"1749 W Claremont St Phoenix AZ 85015",
    "addr:housenumber":"1749",
    "addr:postcode":"85015",
    "addr:street":"W Claremont St",
    "iso:country":"US",
    "sg:address":"1749 W Claremont St",
    "sg:city":"Phoenix",
    "sg:classifiers":[
        {
            "category":"Bakery",
            "type":"Food & Drink"
        }
    ],
    "sg:phone":"+1 602 544 1521",
    "sg:postcode":"85015",
    "sg:province":"AZ",
    "wof:name":"P&M Pastries",
    "wof:placetype":"venue"
},
  "geometry": {"coordinates":[-112.097007,33.528502],"type":"Point"}
}