{
  "type": "Feature",
  "properties": {
    "iso:country":"US",
    "sg:address":"801 E Rose Ln",
    "sg:city":"Phoenix",
    "sg:classifiers":[
        {
            "category":"Real Estate",
            "subcategory":"Real Estate Operator",
            "type":"Services"
        }
    ],
    "sg:phone":"+1 602 248 4420",
    "sg:postcode":"85014",
    "sg:province":"AZ",
    "sg:tags":[
        "building",
        "apartment"
    ],
    "wof:name":"Roselane Garden Apartments",
    "wof:placetype":"venue"
},
  "geometry": {"coordinates":[-112.06442800000001,33.527295],"type":"Point"}
}