{
  "type": "Feature",
  "properties": {
    "iso:country":"US",
    "sg:address":"2818 N Campbell Ave",
    "sg:city":"Tucson",
    "sg:classifiers":[
        {
            "category":"Professional",
            "subcategory":"Business Services",
            "type":"Services"
        }
    ],
    "sg:phone":"+1 520 325 4273",
    "sg:postcode":"85719",
    "sg:province":"AZ",
    "sg:tags":[
        "box",
        "mail"
    ],
    "wof:name":"Postnet",
    "wof:placetype":"venue"
},
  "geometry": {"coordinates":[-110.94376,32.25905],"type":"Point"}
}