{
  "type": "Feature",
  "properties": {
    "iso:country":"US",
    "sg:address":"8225 E Speedway Blvd",
    "sg:city":"Tucson",
    "sg:classifiers":[
        {
            "category":"Manufacturing",
            "subcategory":"Retail Goods",
            "type":"Manufacturing & Wholesale Goods"
        }
    ],
    "sg:phone":"+1 520 722 6257",
    "sg:postcode":"85710",
    "sg:province":"AZ",
    "sg:tags":[
        "product",
        "mfg"
    ],
    "wof:name":"Basket Shoppe",
    "wof:placetype":"venue"
},
  "geometry": {"coordinates":[-110.811968,32.235583],"type":"Point"}
}