{
  "type": "Feature",
  "properties": {
    "iso:country":"US",
    "sg:address":"3411 W Northern Ave",
    "sg:city":"Phoenix",
    "sg:classifiers":[
        {
            "category":"Restaurant",
            "type":"Food & Drink"
        }
    ],
    "sg:phone":"+1 602 246 8004",
    "sg:postcode":"85051",
    "sg:province":"AZ",
    "sg:tags":[
        "eating"
    ],
    "wof:name":"Cafe Sarajevo",
    "wof:placetype":"venue"
},
  "geometry": {"coordinates":[-112.134055,33.55304],"type":"Point"}
}