{
  "type": "Feature",
  "properties": {
    "addr:full":"3801 E Roeser Rd Ste 11 Phoenix AZ 85040",
    "addr:housenumber":"3801",
    "addr:postcode":"85040",
    "addr:street":"E Roeser Rd Ste 11",
    "iso:country":"US",
    "sg:address":"3801 E Roeser Rd Ste 11",
    "sg:city":"Phoenix",
    "sg:classifiers":[
        {
            "category":"Professional",
            "subcategory":"Advertising",
            "type":"Services"
        }
    ],
    "sg:phone":"+1 602 437 4776",
    "sg:postcode":"85040",
    "sg:province":"AZ",
    "sg:tags":[
        "distributing",
        "sample",
        "service-circular"
    ],
    "wof:name":"Certified Folder Display Svc",
    "wof:placetype":"venue"
},
  "geometry": {"coordinates":[-111.999357,33.399748],"type":"Point"}
}