{
  "type": "Feature",
  "properties": {
    "addr:full":"3250 Gateway Blvd Prescott AZ 86303",
    "addr:housenumber":"3250",
    "addr:postcode":"86303",
    "addr:street":"Gateway Blvd",
    "iso:country":"US",
    "sg:address":"3250 Gateway Blvd",
    "sg:city":"Prescott",
    "sg:classifiers":[
        {
            "category":"Shopping",
            "subcategory":"Gifts & Souvenirs",
            "type":"Retail Goods"
        }
    ],
    "sg:phone":"+1 928 776 0957",
    "sg:postcode":"86303",
    "sg:province":"AZ",
    "sg:tags":[
        "shop"
    ],
    "wof:name":"Spencer Gifts",
    "wof:placetype":"venue"
},
  "geometry": {"coordinates":[-112.411411,34.547659],"type":"Point"}
}