{
  "type": "Feature",
  "properties": {
    "iso:country":"US",
    "sg:address":"13881 N Casa Grande Hwy",
    "sg:city":"Marana",
    "sg:classifiers":[
        {
            "category":"Organizations",
            "subcategory":"Professional Association",
            "type":"Services"
        }
    ],
    "sg:phone":"+1 520 682 4314",
    "sg:postcode":"85653",
    "sg:province":"AZ",
    "sg:tags":[
        "chambers",
        "commerce"
    ],
    "sg:website":"www.maranachamber.com",
    "wof:name":"Marana Chamber Of Commerce",
    "wof:placetype":"venue"
},
  "geometry": {"coordinates":[-111.214298,32.459527],"type":"Point"}
}