{
  "type": "Feature",
  "properties": {
    "iso:country":"US",
    "sg:address":"1550 N Dysart Rd Ste A11",
    "sg:city":"Goodyear",
    "sg:classifiers":[
        {
            "category":"Restaurant",
            "type":"Food & Drink"
        }
    ],
    "sg:phone":"+1 623 547 1919",
    "sg:postcode":"85338",
    "sg:province":"AZ",
    "sg:tags":[
        "chinese"
    ],
    "sg:website":"www.pandaexpress.com",
    "wof:name":"Panda Express",
    "wof:placetype":"venue"
},
  "geometry": {"coordinates":[-112.34115799999999,33.453522],"type":"Point"}
}