{
  "type": "Feature",
  "properties": {
    "iso:country":"US",
    "sg:address":"700 Primrose Ln",
    "sg:city":"Bullhead City",
    "sg:classifiers":[
        {
            "category":"Building & Trades",
            "subcategory":"Construction",
            "type":"Services"
        }
    ],
    "sg:phone":"+1 928 758 9162",
    "sg:postcode":"86442",
    "sg:province":"AZ",
    "sg:tags":[
        "heavy"
    ],
    "wof:name":"Rej Construction LLC",
    "wof:placetype":"venue"
},
  "geometry": {"coordinates":[-114.62378699999999,35.104624],"type":"Point"}
}