{
  "type": "Feature",
  "properties": {
    "iso:country":"US",
    "sg:address":"8300 E Dixileta Dr Unit 2",
    "sg:city":"Scottsdale",
    "sg:classifiers":[
        {
            "category":"Parking",
            "subcategory":"Lot",
            "type":"Transportation"
        }
    ],
    "sg:phone":"+1 623 533 1608",
    "sg:postcode":"85266",
    "sg:province":"AZ",
    "sg:tags":[
        "airport"
    ],
    "wof:name":"Greenway Airpark Family",
    "wof:placetype":"venue"
},
  "geometry": {"coordinates":[-111.904213,33.755829],"type":"Point"}
}