{
  "type": "Feature",
  "properties": {
    "iso:country":"US",
    "sg:address":"8109 E del Timbre Dr",
    "sg:city":"Scottsdale",
    "sg:classifiers":[
        {
            "category":"Wholesale",
            "subcategory":"Machinery & Supplies",
            "type":"Manufacturing & Wholesale Goods"
        }
    ],
    "sg:phone":"+1 480 998 9698",
    "sg:postcode":"85258",
    "sg:province":"AZ",
    "sg:tags":[
        "equipment",
        "industrial",
        "manufacturer",
        "pumps-wholesale"
    ],
    "sg:website":"http://www.flowserve.com",
    "wof:name":"Flowserve",
    "wof:placetype":"venue"
},
  "geometry": {"coordinates":[-111.90653500000001,33.572935],"type":"Point"}
}