{
  "type": "Feature",
  "properties": {
    "addr:full":"14474 S Cholla Canyon Dr Phoenix AZ 85044",
    "addr:housenumber":"14474",
    "addr:postcode":"85044",
    "addr:street":"S Cholla Canyon Dr",
    "iso:country":"US",
    "sg:address":"14474 S Cholla Canyon Dr",
    "sg:city":"Phoenix",
    "sg:classifiers":[
        {
            "category":"Professional",
            "type":"Services"
        }
    ],
    "sg:phone":"+1 480 704 5524",
    "sg:postcode":"85044",
    "sg:province":"AZ",
    "wof:name":"Sara Flatt",
    "wof:placetype":"venue"
},
  "geometry": {"coordinates":[-111.99206599999999,33.315722],"type":"Point"}
}