{
  "type": "Feature",
  "properties": {
    "iso:country":"US",
    "sg:address":"6115 N 7th St Ste 6",
    "sg:city":"Phoenix",
    "sg:classifiers":[
        {
            "category":"Personal",
            "subcategory":"Beauty Salon",
            "type":"Services"
        },
        {
            "category":"Personal",
            "subcategory":"Nail Salon",
            "type":"Services"
        }
    ],
    "sg:phone":"+1 602 266 9828",
    "sg:postcode":"85014",
    "sg:province":"AZ",
    "wof:name":"Nails By Marie",
    "wof:placetype":"venue"
},
  "geometry": {"coordinates":[-112.06501,33.526364],"type":"Point"}
}