{
  "type": "Feature",
  "properties": {
    "iso:country":"US",
    "sg:address":"16 Black Oak Dr",
    "sg:city":"Sonoita",
    "sg:classifiers":[
        {
            "category":"Building & Trades",
            "subcategory":"Construction",
            "type":"Services"
        }
    ],
    "sg:phone":"+1 520 455 5244",
    "sg:postcode":"85637",
    "sg:province":"AZ",
    "sg:tags":[
        "house"
    ],
    "wof:name":"Elizabeth Kailing Chfc CLU",
    "wof:placetype":"venue"
},
  "geometry": {"coordinates":[-110.656749,31.666808],"type":"Point"}
}