{
  "type": "Feature",
  "properties": {
    "iso:country":"US",
    "sg:address":"5609 W Latham St",
    "sg:city":"Phoenix",
    "sg:classifiers":[
        {
            "category":"Freight",
            "type":"Transportation"
        }
    ],
    "sg:phone":"+1 602 278 0544",
    "sg:postcode":"85043",
    "sg:province":"AZ",
    "sg:tags":[
        "hauling",
        "trucking"
    ],
    "wof:name":"K S Tran Svc",
    "wof:placetype":"venue"
},
  "geometry": {"coordinates":[-112.18197,33.460538],"type":"Point"}
}