{
  "type": "Feature",
  "properties": {
    "iso:country":"US",
    "sg:address":"5324 W Palo Verde Ave",
    "sg:city":"Glendale",
    "sg:classifiers":[
        {
            "category":"Building & Trades",
            "subcategory":"Construction",
            "type":"Services"
        }
    ],
    "sg:phone":"+1 623 931 3009",
    "sg:postcode":"85302",
    "sg:province":"AZ",
    "sg:tags":[
        "concrete",
        "contractor"
    ],
    "wof:name":"Budget West Concrete Inc",
    "wof:placetype":"venue"
},
  "geometry": {"coordinates":[-112.17592399999999,33.573168],"type":"Point"}
}