{
  "type": "Feature",
  "properties": {
    "iso:country":"US",
    "sg:address":"2322 W Straight Arrow Ln",
    "sg:city":"Phoenix",
    "sg:classifiers":[
        {
            "category":"Autos & Motor Vehicles",
            "subcategory":"Auto Supplies",
            "type":"Retail Goods"
        }
    ],
    "sg:phone":"+1 602 315 2883",
    "sg:postcode":"85085",
    "sg:province":"AZ",
    "sg:tags":[
        "automobile",
        "part"
    ],
    "wof:name":"Bumper To Bumper Collision Ctr",
    "wof:placetype":"venue"
},
  "geometry": {"coordinates":[-112.109065,33.733369],"type":"Point"}
}