{
  "type": "Feature",
  "properties": {
    "iso:country":"US",
    "sg:address":"1720 E Broadway Rd",
    "sg:city":"Tempe",
    "sg:classifiers":[
        {
            "category":"Shopping",
            "subcategory":"Clothing, Apparel, & Fashions",
            "type":"Retail Goods"
        }
    ],
    "sg:phone":"+1 480 205 9024",
    "sg:postcode":"85282",
    "sg:province":"AZ",
    "wof:name":"Kopius",
    "wof:placetype":"venue"
},
  "geometry": {"coordinates":[-111.910617,33.407586],"type":"Point"}
}