{
  "type": "Feature",
  "properties": {
    "iso:country":"US",
    "sg:address":"4747 N 7th St Ste 170",
    "sg:city":"Phoenix",
    "sg:classifiers":[
        {
            "category":"Banks & Credit Unions",
            "subcategory":"Investment Brokerage",
            "type":"Services"
        },
        {
            "category":"Banks & Credit Unions",
            "subcategory":"Bank",
            "type":"Services"
        }
    ],
    "sg:phone":"+1 602 485 1346",
    "sg:postcode":"85014",
    "sg:province":"AZ",
    "sg:tags":[
        "transfer",
        "broker",
        "agent",
        "security",
        "stock",
        "bond"
    ],
    "wof:name":"Fastco",
    "wof:placetype":"venue"
},
  "geometry": {"coordinates":[-112.06501,33.506416],"type":"Point"}
}