{
  "type": "Feature",
  "properties": {
    "addr:full":"13198 S 27th Ave Yuma AZ 85365",
    "addr:housenumber":"13198",
    "addr:postcode":"85365",
    "addr:street":"S 27Th Ave",
    "iso:country":"US",
    "sg:address":"13198 S 27th Ave",
    "sg:city":"Yuma",
    "sg:classifiers":[
        {
            "category":"Building & Trades",
            "subcategory":"Construction",
            "type":"Services"
        }
    ],
    "sg:phone":"+1 928 341 0738",
    "sg:postcode":"85365",
    "sg:province":"AZ",
    "sg:tags":[
        "contractor"
    ],
    "wof:name":"Desert Insulation LLC",
    "wof:placetype":"venue"
},
  "geometry": {"coordinates":[-114.653491,32.639176],"type":"Point"}
}