{
  "type": "Feature",
  "properties": {
    "iso:country":"US",
    "sg:address":"13182 N 103rd St",
    "sg:city":"Scottsdale",
    "sg:classifiers":[
        {
            "category":"Building & Trades",
            "subcategory":"Construction",
            "type":"Services"
        }
    ],
    "sg:phone":"+1 480 767 6994",
    "sg:postcode":"85260",
    "sg:province":"AZ",
    "sg:tags":[
        "house",
        "builder",
        "home"
    ],
    "wof:name":"Mc Neely Construction Inc",
    "wof:placetype":"venue"
},
  "geometry": {"coordinates":[-111.859645,33.60573],"type":"Point"}
}