{
  "type": "Feature",
  "properties": {
    "iso:country":"US",
    "sg:address":"554 W Main St",
    "sg:city":"Mesa",
    "sg:classifiers":[
        {
            "category":"Autos & Motor Vehicles",
            "subcategory":"Automobile Sales",
            "type":"Retail Goods"
        }
    ],
    "sg:phone":"+1 480 827 2710",
    "sg:postcode":"85201",
    "sg:province":"AZ",
    "sg:tags":[
        "car",
        "dealer"
    ],
    "wof:name":"Main Street Motors Inc",
    "wof:placetype":"venue"
},
  "geometry": {"coordinates":[-111.843209,33.415165],"type":"Point"}
}