{
  "type": "Feature",
  "properties": {
    "iso:country":"US",
    "sg:address":"8777 N Gainey Center Dr # 200",
    "sg:city":"Scottsdale",
    "sg:classifiers":[
        {
            "category":"Real Estate",
            "subcategory":"Real Estate Services",
            "type":"Services"
        }
    ],
    "sg:phone":"+1 480 483 9111",
    "sg:postcode":"85258",
    "sg:province":"AZ",
    "sg:tags":[
        "commercial"
    ],
    "wof:name":"Gabel Investments Inc",
    "wof:placetype":"venue"
},
  "geometry": {"coordinates":[-111.912881,33.564965],"type":"Point"}
}