{
  "type": "Feature",
  "properties": {
    "iso:country":"US",
    "sg:address":"3102 N Country Club Rd",
    "sg:city":"Tucson",
    "sg:classifiers":[
        {
            "category":"Health Services",
            "subcategory":"Chiropractor",
            "type":"Services"
        }
    ],
    "sg:phone":"+1 520 327 6100",
    "sg:postcode":"85716",
    "sg:province":"AZ",
    "wof:name":"Wellness Chiropractic Ctr",
    "wof:placetype":"venue"
},
  "geometry": {"coordinates":[-110.926663,32.264908],"type":"Point"}
}