{
  "type": "Feature",
  "properties": {
    "iso:country":"US",
    "sg:address":"208 S Country Club Dr",
    "sg:city":"Mesa",
    "sg:classifiers":[
        {
            "category":"Wholesale",
            "subcategory":"Hardware",
            "type":"Manufacturing & Wholesale Goods"
        }
    ],
    "sg:phone":"+1 480 834 5817",
    "sg:postcode":"85210",
    "sg:province":"AZ",
    "sg:tags":[
        "plumbing",
        "air",
        "heating",
        "conditioning",
        "supply"
    ],
    "wof:name":"Central Arizona Supply",
    "wof:placetype":"venue"
},
  "geometry": {"coordinates":[-111.839832,33.409584],"type":"Point"}
}