{
  "type": "Feature",
  "properties": {
    "iso:country":"US",
    "sg:address":"2300 N Tanque Verde Loop Rd",
    "sg:city":"Tucson",
    "sg:classifiers":[
        {
            "category":"Education",
            "subcategory":"School",
            "type":"Public Place"
        }
    ],
    "sg:phone":"+1 520 749 1413",
    "sg:postcode":"85749",
    "sg:province":"AZ",
    "wof:name":"Academy Of Tucson",
    "wof:placetype":"venue"
},
  "geometry": {"coordinates":[-110.755516,32.249792],"type":"Point"}
}