{
  "type": "Feature",
  "properties": {
    "iso:country":"US",
    "sg:address":"3460 N Treasure Dr",
    "sg:city":"Prescott Valley",
    "sg:classifiers":[
        {
            "category":"Manufacturing",
            "subcategory":"Metals",
            "type":"Manufacturing & Wholesale Goods"
        }
    ],
    "sg:phone":"+1 928 775 4964",
    "sg:postcode":"86314",
    "sg:province":"AZ",
    "sg:tags":[
        "spring",
        "wire",
        "mfg"
    ],
    "wof:name":"Rogers Precision",
    "wof:placetype":"venue"
},
  "geometry": {"coordinates":[-112.353345,34.594717],"type":"Point"}
}