{
  "type": "Feature",
  "properties": {
    "iso:country":"US",
    "sg:address":"20013 N Clear Canyon Dr",
    "sg:city":"Surprise",
    "sg:classifiers":[
        {
            "category":"Real Estate",
            "subcategory":"Real Estate Operator",
            "type":"Services"
        }
    ],
    "sg:phone":"+1 623 214 3685",
    "sg:postcode":"85374",
    "sg:province":"AZ",
    "sg:tags":[
        "building",
        "nonresidential"
    ],
    "wof:name":"Newcolo Properties",
    "wof:placetype":"venue"
},
  "geometry": {"coordinates":[-112.395309,33.666772],"type":"Point"}
}