{
  "type": "Feature",
  "properties": {
    "addr:full":"5803 W Marconi Ave Glendale AZ 85306",
    "addr:housenumber":"5803",
    "addr:postcode":"85306",
    "addr:street":"W Marconi Ave",
    "iso:country":"US",
    "sg:address":"5803 W Marconi Ave",
    "sg:city":"Glendale",
    "sg:classifiers":[
        {
            "category":"Professional",
            "subcategory":"Secretarial Services",
            "type":"Services"
        }
    ],
    "sg:phone":"+1 602 547 8192",
    "sg:postcode":"85306",
    "sg:province":"AZ",
    "sg:tags":[
        "transcription",
        "medical"
    ],
    "wof:name":"Stat Medical Transcription",
    "wof:placetype":"venue"
},
  "geometry": {"coordinates":[-112.183622,33.629773],"type":"Point"}
}