{
  "type": "Feature",
  "properties": {
    "addr:full":"7372 N Cer Guerrero Tucson AZ 85704",
    "addr:housenumber":"7372",
    "addr:postcode":"85704",
    "addr:street":"N Cer",
    "iso:country":"US",
    "sg:address":"7372 N Cer Guerrero",
    "sg:city":"Tucson",
    "sg:classifiers":[
        {
            "category":"Food & Beverages",
            "subcategory":"Specialty",
            "type":"Retail Goods"
        }
    ],
    "sg:phone":"+1 520 297 3877",
    "sg:postcode":"85704",
    "sg:province":"AZ",
    "wof:name":"Young Ventures",
    "wof:placetype":"venue"
},
  "geometry": {"coordinates":[-110.99623800000001,32.339692],"type":"Point"}
}