{
  "type": "Feature",
  "properties": {
    "iso:country":"US",
    "sg:address":"6737 E Cam Principal",
    "sg:city":"Tucson",
    "sg:classifiers":[
        {
            "category":"Health Services",
            "subcategory":"Health Practitioner",
            "type":"Services"
        }
    ],
    "sg:phone":"+1 520 721 8821",
    "sg:postcode":"85715",
    "sg:province":"AZ",
    "sg:tags":[
        "physician"
    ],
    "wof:name":"Flagler & Flager",
    "wof:placetype":"venue"
},
  "geometry": {"coordinates":[-110.849203,32.250516],"type":"Point"}
}