{
  "type": "Feature",
  "properties": {
    "addr:full":"20359 N 59th Ave Glendale AZ 85308",
    "addr:housenumber":"20359",
    "addr:postcode":"85308",
    "addr:street":"N 59Th Ave",
    "iso:country":"US",
    "sg:address":"20359 N 59th Ave",
    "sg:city":"Glendale",
    "sg:classifiers":[
        {
            "category":"Insurance",
            "subcategory":"Insurance Agent",
            "type":"Services"
        }
    ],
    "sg:phone":"+1 623 561 9969",
    "sg:postcode":"85308",
    "sg:province":"AZ",
    "wof:name":"Farmers Insurance Group",
    "wof:placetype":"venue"
},
  "geometry": {"coordinates":[-112.186649,33.671799],"type":"Point"}
}