{
  "type": "Feature",
  "properties": {
    "addr:full":"1208 E Broadway Rd Tempe AZ 85282",
    "addr:housenumber":"1208",
    "addr:postcode":"85282",
    "addr:street":"E Broadway Rd",
    "iso:country":"US",
    "sg:address":"1208 E Broadway Rd",
    "sg:city":"Tempe",
    "sg:classifiers":[
        {
            "category":"Professional",
            "subcategory":"Employment Agencies",
            "type":"Services"
        }
    ],
    "sg:phone":"+1 480 968 4000",
    "sg:postcode":"85282",
    "sg:province":"AZ",
    "sg:tags":[
        "consultant",
        "search",
        "executive"
    ],
    "wof:name":"Comprehensive Recruiting",
    "wof:placetype":"venue"
},
  "geometry": {"coordinates":[-111.91992399999999,33.407586],"type":"Point"}
}