{
  "type": "Feature",
  "properties": {
    "iso:country":"US",
    "sg:address":"221 N 79th Ave",
    "sg:city":"Tolleson",
    "sg:classifiers":[
        {
            "category":"Banks & Credit Unions",
            "subcategory":"Bank",
            "type":"Services"
        }
    ],
    "sg:phone":"+1 602 797 3000",
    "sg:postcode":"85353",
    "sg:province":"AZ",
    "wof:name":"Srp Credit Union",
    "wof:placetype":"venue"
},
  "geometry": {"coordinates":[-112.230003,33.4506],"type":"Point"}
}