{
  "type": "Feature",
  "properties": {
    "iso:country":"US",
    "sg:address":"2404 S Industrial Park Ave",
    "sg:city":"Tempe",
    "sg:classifiers":[
        {
            "category":"Manufacturing",
            "subcategory":"Tools & Machinery",
            "type":"Manufacturing & Wholesale Goods"
        }
    ],
    "sg:phone":"+1 480 968 0957",
    "sg:postcode":"85282",
    "sg:province":"AZ",
    "sg:tags":[
        "machine",
        "industrial",
        "accessory",
        "mfg"
    ],
    "wof:name":"Horizon Carbide Tool Inc",
    "wof:placetype":"venue"
},
  "geometry": {"coordinates":[-111.9553,33.401071],"type":"Point"}
}