{
  "type": "Feature",
  "properties": {
    "iso:country":"US",
    "sg:address":"2601 W Holly St",
    "sg:city":"Phoenix",
    "sg:classifiers":[
        {
            "category":"Retail",
            "subcategory":"Auto Repair",
            "type":"Services"
        }
    ],
    "sg:phone":"+1 602 442 2105",
    "sg:postcode":"85009",
    "sg:province":"AZ",
    "sg:tags":[
        "repairing",
        "automobile"
    ],
    "wof:name":"Quality Engine Installations",
    "wof:placetype":"venue"
},
  "geometry": {"coordinates":[-112.11556400000001,33.470393],"type":"Point"}
}