{
  "type": "Feature",
  "properties": {
    "addr:full":"452 N Cholla Mesa AZ 85201",
    "addr:housenumber":"452",
    "addr:postcode":"85201",
    "addr:street":"N Cholla",
    "iso:country":"US",
    "sg:address":"452 N Cholla",
    "sg:city":"Mesa",
    "sg:classifiers":[
        {
            "category":"Building & Trades",
            "subcategory":"Plumbing",
            "type":"Services"
        }
    ],
    "sg:phone":"+1 480 461 8009",
    "sg:postcode":"85201",
    "sg:province":"AZ",
    "sg:tags":[
        "contractor"
    ],
    "wof:name":"Paul Hawkins AC & Htg",
    "wof:placetype":"venue"
},
  "geometry": {"coordinates":[-111.870555,33.423407],"type":"Point"}
}