{
  "type": "Feature",
  "properties": {
    "addr:full":"7480 W Bell Rd Glendale AZ 85308",
    "addr:housenumber":"7480",
    "addr:postcode":"85308",
    "addr:street":"W Bell Rd",
    "iso:country":"US",
    "sg:address":"7480 W Bell Rd",
    "sg:city":"Glendale",
    "sg:classifiers":[
        {
            "category":"Home & Garden",
            "subcategory":"Furniture",
            "type":"Retail Goods"
        }
    ],
    "sg:phone":"+1 623 334 1100",
    "sg:postcode":"85308",
    "sg:province":"AZ",
    "sg:tags":[
        "bedding",
        "mattress"
    ],
    "wof:name":"Sleep America Inc",
    "wof:placetype":"venue"
},
  "geometry": {"coordinates":[-112.216702,33.63832],"type":"Point"}
}