{
  "type": "Feature",
  "properties": {
    "addr:full":"525 Boynton Canyon Road Sedona AZ 86336",
    "addr:housenumber":"525",
    "addr:postcode":"86336",
    "addr:street":"Boynton Canyon Road",
    "iso:country":"US",
    "sg:address":"525 Boynton Canyon Road",
    "sg:city":"Sedona",
    "sg:phone":"+1 928 203 8500",
    "sg:postcode":"86336",
    "sg:province":"AZ",
    "sg:website":"http://www.miiamo.com/",
    "wof:name":"Mii amo",
    "wof:placetype":"venue"
},
  "geometry": {"coordinates":[-111.850853,34.912209],"type":"Point"}
}