{
  "type": "Feature",
  "properties": {
    "iso:country":"US",
    "sg:address":"4201 S Cam del Sol",
    "sg:city":"Green Valley",
    "sg:classifiers":[
        {
            "category":"Sports & Exercise",
            "subcategory":"Golf",
            "type":"Entertainment"
        }
    ],
    "sg:phone":"+1 520 648 3468",
    "sg:postcode":"85614",
    "sg:province":"AZ",
    "sg:tags":[
        "course"
    ],
    "wof:name":"San Ignacio Golf Club",
    "wof:placetype":"venue"
},
  "geometry": {"coordinates":[-111.019749,31.814771],"type":"Point"}
}