{
  "type": "Feature",
  "properties": {
    "iso:country":"US",
    "sg:address":"454 N Lindsay Rd",
    "sg:city":"Mesa",
    "sg:classifiers":[
        {
            "category":"Personal",
            "subcategory":"Beauty Salon",
            "type":"Services"
        }
    ],
    "sg:phone":"+1 480 833 3133",
    "sg:postcode":"85213",
    "sg:province":"AZ",
    "sg:tags":[
        "manicuring"
    ],
    "wof:name":"Darling Nails",
    "wof:placetype":"venue"
},
  "geometry": {"coordinates":[-111.771078,33.424888],"type":"Point"}
}