{
  "type": "Feature",
  "properties": {
    "iso:country":"US",
    "sg:address":"1045 N Jerrie Ave",
    "sg:city":"Tucson",
    "sg:classifiers":[
        {
            "category":"Home & Garden",
            "subcategory":"Building Materials",
            "type":"Retail Goods"
        }
    ],
    "sg:phone":"+1 520 323 7321",
    "sg:postcode":"85711",
    "sg:province":"AZ",
    "sg:tags":[
        "paint"
    ],
    "wof:name":"Dunn-Edwards Paints",
    "wof:placetype":"venue"
},
  "geometry": {"coordinates":[-110.900175,32.235372],"type":"Point"}
}