{
  "type": "Feature",
  "properties": {
    "iso:country":"US",
    "sg:address":"4102 N 24th St",
    "sg:city":"Phoenix",
    "sg:classifiers":[
        {
            "category":"Restaurant",
            "type":"Food & Drink"
        }
    ],
    "sg:phone":"+1 602 468 9737",
    "sg:postcode":"85016",
    "sg:province":"AZ",
    "sg:tags":[
        "japanese"
    ],
    "wof:name":"Yoshis Restaurant",
    "wof:placetype":"venue"
},
  "geometry": {"coordinates":[-112.030271,33.495725],"type":"Point"}
}