{
  "type": "Feature",
  "properties": {
    "iso:country":"US",
    "sg:address":"5738 W Mariposa St",
    "sg:city":"Phoenix",
    "sg:classifiers":[
        {
            "category":"Shopping",
            "subcategory":"Used Merchandise",
            "type":"Retail Goods"
        }
    ],
    "sg:phone":"+1 623 873 2720",
    "sg:postcode":"85031",
    "sg:province":"AZ",
    "sg:tags":[
        "ribbon"
    ],
    "wof:name":"Blue Ribbon Transcription",
    "wof:placetype":"venue"
},
  "geometry": {"coordinates":[-112.182932,33.50749],"type":"Point"}
}