{
  "type": "Feature",
  "properties": {
    "addr:full":"901 Tombstone Canyon Rd Bisbee AZ 85603",
    "addr:housenumber":"901",
    "addr:postcode":"85603",
    "addr:street":"Tombstone Canyon Rd",
    "iso:country":"US",
    "sg:address":"901 Tombstone Canyon Rd",
    "sg:city":"Bisbee",
    "sg:classifiers":[
        {
            "category":"Travel",
            "subcategory":"Hotels & Motels",
            "type":"Entertainment"
        }
    ],
    "sg:phone":"+1 520 432 3866",
    "sg:postcode":"85603",
    "sg:province":"AZ",
    "sg:tags":[
        "breakfast",
        "accommodation",
        "bed"
    ],
    "wof:name":"Gardens At Mile High Ranch",
    "wof:placetype":"venue"
},
  "geometry": {"coordinates":[-109.936099,31.452719],"type":"Point"}
}