{
  "type": "Feature",
  "properties": {
    "iso:country":"US",
    "sg:address":"13148 N 153rd Dr",
    "sg:city":"Surprise",
    "sg:classifiers":[
        {
            "category":"Building & Trades",
            "subcategory":"Construction",
            "type":"Services"
        }
    ],
    "sg:phone":"+1 623 594 9619",
    "sg:postcode":"85379",
    "sg:province":"AZ",
    "sg:tags":[
        "home",
        "builder"
    ],
    "wof:name":"Engle Homes Marley Park",
    "wof:placetype":"venue"
},
  "geometry": {"coordinates":[-112.39007,33.603687],"type":"Point"}
}