{
  "type": "Feature",
  "properties": {
    "iso:country":"US",
    "sg:address":"7342 W Indian School Rd",
    "sg:city":"Phoenix",
    "sg:classifiers":[
        {
            "category":"Retail",
            "subcategory":"Veterinary Services",
            "type":"Services"
        }
    ],
    "sg:phone":"+1 623 846 3979",
    "sg:postcode":"85033",
    "sg:province":"AZ",
    "sg:tags":[
        "veterinarian"
    ],
    "wof:name":"Spay & Neuter Clinic",
    "wof:placetype":"venue"
},
  "geometry": {"coordinates":[-112.217602,33.494792],"type":"Point"}
}