{
  "type": "Feature",
  "properties": {
    "iso:country":"US",
    "sg:address":"326 E Wildwood Dr",
    "sg:city":"Phoenix",
    "sg:classifiers":[
        {
            "category":"Insurance",
            "subcategory":"Insurance Agent",
            "type":"Services"
        }
    ],
    "sg:phone":"+1 480 460 4644",
    "sg:postcode":"85048",
    "sg:province":"AZ",
    "wof:name":"Hunt Management",
    "wof:placetype":"venue"
},
  "geometry": {"coordinates":[-112.070137,33.297929],"type":"Point"}
}