{
  "type": "Feature",
  "properties": {
    "iso:country":"US",
    "sg:address":"3150 E Benson Hwy",
    "sg:city":"Tucson",
    "sg:classifiers":[
        {
            "category":"Autos & Motor Vehicles",
            "subcategory":"Auto Supplies",
            "type":"Retail Goods"
        }
    ],
    "sg:phone":"+1 520 741 2886",
    "sg:postcode":"85706",
    "sg:province":"AZ",
    "sg:tags":[
        "tire"
    ],
    "wof:name":"Moreno Tire & Wheel",
    "wof:placetype":"venue"
},
  "geometry": {"coordinates":[-110.924879,32.156565],"type":"Point"}
}