{
  "type": "Feature",
  "properties": {
    "iso:country":"US",
    "sg:address":"2560 Sandia Dr",
    "sg:city":"Prescott",
    "sg:classifiers":[
        {
            "category":"Recreation",
            "type":"Entertainment"
        }
    ],
    "sg:phone":"+1 928 533 7942",
    "sg:postcode":"86301",
    "sg:province":"AZ",
    "sg:tags":[
        "martial",
        "arts",
        "instruction"
    ],
    "wof:name":"Mountain Breeze Tai Chi Chuan",
    "wof:placetype":"venue"
},
  "geometry": {"coordinates":[-112.471467,34.584158],"type":"Point"}
}