{
  "type": "Feature",
  "properties": {
    "addr:full":"10869 N Scottsdale Rd Scottsdale AZ 85254",
    "addr:housenumber":"10869",
    "addr:postcode":"85254",
    "addr:street":"N Scottsdale Rd",
    "iso:country":"US",
    "sg:address":"10869 N Scottsdale Rd",
    "sg:city":"Scottsdale",
    "sg:phone":"+1 877 552 3969",
    "sg:postcode":"85254",
    "sg:province":"AZ",
    "sg:website":"http://phoenix.citysearch.com/profile/external/41791532/scottsdale_az/beauty_bar_soon_to_be_salon_etro_.html?publisher=yellowpages&reference_id=1&placement=ypwebsitemip",
    "wof:name":"Beauty Bar (Soon to be Salon Etro)",
    "wof:placetype":"venue"
},
  "geometry": {"coordinates":[-111.925926,33.585039],"type":"Point"}
}