{
  "type": "Feature",
  "properties": {
    "addr:full":"4445 E Cortez St Phoenix AZ 85028",
    "addr:housenumber":"4445",
    "addr:postcode":"85028",
    "addr:street":"E Cortez St",
    "iso:country":"US",
    "sg:address":"4445 E Cortez St",
    "sg:city":"Phoenix",
    "sg:classifiers":[
        {
            "category":"Real Estate",
            "subcategory":"Real Estate Agent",
            "type":"Services"
        }
    ],
    "sg:phone":"+1 602 494 8068",
    "sg:postcode":"85028",
    "sg:province":"AZ",
    "wof:name":"Suttin Realty",
    "wof:placetype":"venue"
},
  "geometry": {"coordinates":[-111.985472,33.591635],"type":"Point"}
}