{
  "type": "Feature",
  "properties": {
    "iso:country":"US",
    "sg:address":"4260 E Illinois St",
    "sg:city":"Tucson",
    "sg:classifiers":[
        {
            "category":"Wholesale",
            "subcategory":"Auto Parts",
            "type":"Manufacturing & Wholesale Goods"
        }
    ],
    "sg:phone":"+1 520 748 1444",
    "sg:postcode":"85714",
    "sg:province":"AZ",
    "sg:tags":[
        "automobile",
        "rebuilt"
    ],
    "wof:name":"Millie's Auto & Truck Salvage",
    "wof:placetype":"venue"
},
  "geometry": {"coordinates":[-110.904331,32.169037],"type":"Point"}
}