{
  "type": "Feature",
  "properties": {
    "iso:country":"US",
    "sg:address":"4747 N 20th St",
    "sg:city":"Phoenix",
    "sg:phone":"+1 602 954 2394",
    "sg:postcode":"85016",
    "sg:province":"AZ",
    "wof:name":"Cyprus Grill",
    "wof:placetype":"venue"
},
  "geometry": {"coordinates":[-112.038872,33.506206],"type":"Point"}
}