{
  "type": "Feature",
  "properties": {
    "iso:country":"US",
    "sg:address":"3538 W Peoria Ave",
    "sg:city":"Phoenix",
    "sg:classifiers":[
        {
            "category":"Personal",
            "subcategory":"Beauty Salon",
            "type":"Services"
        }
    ],
    "sg:phone":"+1 602 439 6815",
    "sg:postcode":"85029",
    "sg:province":"AZ",
    "sg:tags":[
        "manicuring"
    ],
    "wof:name":"Finest Nails",
    "wof:placetype":"venue"
},
  "geometry": {"coordinates":[-112.13590000000001,33.582029],"type":"Point"}
}