{
  "type": "Feature",
  "properties": {
    "addr:full":"1007 E Southern Ave Mesa AZ 85204",
    "addr:housenumber":"1007",
    "addr:postcode":"85204",
    "addr:street":"E Southern Ave",
    "iso:country":"US",
    "sg:address":"1007 E Southern Ave",
    "sg:city":"Mesa",
    "sg:classifiers":[
        {
            "category":"Professional",
            "type":"Services"
        }
    ],
    "sg:phone":"+1 480 892 0845",
    "sg:postcode":"85204",
    "sg:province":"AZ",
    "wof:name":"AZ Road Spec",
    "wof:placetype":"venue"
},
  "geometry": {"coordinates":[-111.805555,33.393297],"type":"Point"}
}