{
  "type": "Feature",
  "properties": {
    "iso:country":"US",
    "sg:address":"6456 N 77th Way",
    "sg:city":"Scottsdale",
    "sg:classifiers":[
        {
            "category":"Autos & Motor Vehicles",
            "subcategory":"Automobile Sales",
            "type":"Retail Goods"
        }
    ],
    "sg:phone":"+1 480 998 4749",
    "sg:postcode":"85250",
    "sg:province":"AZ",
    "wof:name":"Cadillac Lasalle Club Sonoran",
    "wof:placetype":"venue"
},
  "geometry": {"coordinates":[-111.914682,33.530187],"type":"Point"}
}