{
  "type": "Feature",
  "properties": {
    "iso:country":"US",
    "sg:address":"740 E Ajo Way",
    "sg:city":"Tucson",
    "sg:classifiers":[
        {
            "category":"Wholesale",
            "subcategory":"Office Equipment",
            "type":"Manufacturing & Wholesale Goods"
        }
    ],
    "sg:phone":"+1 520 792 4999",
    "sg:postcode":"85713",
    "sg:province":"AZ",
    "sg:tags":[
        "machine",
        "duplicating",
        "copying"
    ],
    "sg:website":"www.tucsoncopiers.com",
    "wof:name":"Copygraphix",
    "wof:placetype":"venue"
},
  "geometry": {"coordinates":[-110.957902,32.177809],"type":"Point"}
}