{
  "type": "Feature",
  "properties": {
    "addr:full":"7307 E Indian Plz Scottsdale AZ 85251",
    "addr:housenumber":"7307",
    "addr:postcode":"85251",
    "addr:street":"E Indian Plz",
    "iso:country":"US",
    "sg:address":"7307 E Indian Plz",
    "sg:city":"Scottsdale",
    "sg:classifiers":[
        {
            "category":"Banks & Credit Unions",
            "subcategory":"Bank",
            "type":"Services"
        }
    ],
    "sg:phone":"+1 480 941 2021",
    "sg:postcode":"85251",
    "sg:province":"AZ",
    "sg:tags":[
        "loan"
    ],
    "wof:name":"Direct Lender",
    "wof:placetype":"venue"
},
  "geometry": {"coordinates":[-111.923439,33.501334],"type":"Point"}
}