{
  "type": "Feature",
  "properties": {
    "iso:country":"US",
    "sg:address":"5 S Mountain Ave",
    "sg:city":"Springerville",
    "sg:classifiers":[
        {
            "category":"Shopping",
            "subcategory":"Florist",
            "type":"Retail Goods"
        }
    ],
    "sg:phone":"+1 928 333 2522",
    "sg:postcode":"85938",
    "sg:province":"AZ",
    "wof:name":"Springerville Flower Shop",
    "wof:placetype":"venue"
},
  "geometry": {"coordinates":[-109.28746700000001,34.13052],"type":"Point"}
}