{
  "type": "Feature",
  "properties": {
    "iso:country":"US",
    "sg:address":"3853 E Thomas Rd",
    "sg:city":"Phoenix",
    "sg:classifiers":[
        {
            "category":"Recreation",
            "type":"Entertainment"
        }
    ],
    "sg:phone":"+1 602 957 9966",
    "sg:postcode":"85018",
    "sg:province":"AZ",
    "sg:tags":[
        "skating",
        "rink"
    ],
    "wof:name":"Arcadia Ice",
    "wof:placetype":"venue"
},
  "geometry": {"coordinates":[-111.998642,33.480362],"type":"Point"}
}