{
  "type": "Feature",
  "properties": {
    "iso:country":"US",
    "sg:address":"3115 N Stockton Hill Rd",
    "sg:city":"Kingman",
    "sg:classifiers":[
        {
            "category":"Shopping",
            "subcategory":"Department Store",
            "type":"Retail Goods"
        },
        {
            "category":"Home & Garden",
            "subcategory":"Garden Supply",
            "type":"Retail Goods"
        },
        {
            "category":"Shopping",
            "subcategory":"Computers & Home Electronics",
            "type":"Retail Goods"
        },
        {
            "category":"Shopping",
            "subcategory":"Clothing, Apparel, & Fashions",
            "type":"Retail Goods"
        },
        {
            "category":"Home & Garden",
            "subcategory":"Household Appliances",
            "type":"Retail Goods"
        }
    ],
    "sg:phone":"+1 888 867 5309",
    "sg:postcode":"86401",
    "sg:province":"AZ",
    "sg:tags":[
        "lawn",
        "clothing",
        "major",
        "mower",
        "consumer"
    ],
    "sg:website":"http://www.searshomeservices.com",
    "wof:name":"Sears Hometown Store",
    "wof:placetype":"venue"
},
  "geometry": {"coordinates":[-114.035133,35.213604],"type":"Point"}
}