{
  "type": "Feature",
  "properties": {
    "addr:full":"129 US Hwy 66 Williams AZ 86046",
    "addr:housenumber":"129",
    "addr:postcode":"86046",
    "addr:street":"Us Hwy 66",
    "iso:country":"US",
    "sg:address":"129 US Hwy 66",
    "sg:city":"Williams",
    "sg:classifiers":[
        {
            "category":"Retail",
            "subcategory":"Laundry & Dry Cleaning",
            "type":"Services"
        }
    ],
    "sg:phone":"+1 928 635 4712",
    "sg:postcode":"86046",
    "sg:province":"AZ",
    "sg:tags":[
        "cleaners"
    ],
    "wof:name":"Gateway Cleaners",
    "wof:placetype":"venue"
},
  "geometry": {"coordinates":[-112.187556,35.250653],"type":"Point"}
}