{
  "type": "Feature",
  "properties": {
    "iso:country":"US",
    "sg:address":"2845 W Fresno St",
    "sg:city":"Tucson",
    "sg:classifiers":[
        {
            "category":"Retail",
            "subcategory":"Auto Repair",
            "type":"Services"
        }
    ],
    "sg:phone":"+1 520 272 7247",
    "sg:postcode":"85745",
    "sg:province":"AZ",
    "sg:tags":[
        "glass",
        "coating",
        "tinting"
    ],
    "wof:name":"Arizona Window Tinting",
    "wof:placetype":"venue"
},
  "geometry": {"coordinates":[-111.028381,32.223409],"type":"Point"}
}