{
  "type": "Feature",
  "properties": {
    "addr:full":"4650 US Hwy 89 Flagstaff AZ 86004",
    "addr:housenumber":"4650",
    "addr:postcode":"86004",
    "addr:street":"Us Hwy 89",
    "iso:country":"US",
    "sg:address":"4650 US Hwy 89",
    "sg:city":"Flagstaff",
    "sg:classifiers":[
        {
            "category":"Restaurant",
            "type":"Food & Drink"
        }
    ],
    "sg:phone":"+1 928 526 1387",
    "sg:postcode":"86004",
    "sg:province":"AZ",
    "sg:tags":[
        "eating"
    ],
    "wof:name":"Sbarro",
    "wof:placetype":"venue"
},
  "geometry": {"coordinates":[-111.581242,35.226199],"type":"Point"}
}