{
  "type": "Feature",
  "properties": {
    "iso:country":"US",
    "sg:address":"400 Prescott Lakes Pkwy",
    "sg:city":"Prescott",
    "sg:classifiers":[
        {
            "category":"Retail",
            "subcategory":"Auto Rental",
            "type":"Services"
        }
    ],
    "sg:phone":"+1 928 777 9350",
    "sg:postcode":"86301",
    "sg:province":"AZ",
    "sg:tags":[
        "renting",
        "automobile"
    ],
    "wof:name":"Enterprise Rent A Car",
    "wof:placetype":"venue"
},
  "geometry": {"coordinates":[-112.410714,34.551836],"type":"Point"}
}