{
  "type": "Feature",
  "properties": {
    "iso:country":"US",
    "sg:address":"5897 W Indian School Rd",
    "sg:city":"Phoenix",
    "sg:classifiers":[
        {
            "category":"Food & Beverages",
            "subcategory":"Liquor & Beverages",
            "type":"Retail Goods"
        }
    ],
    "sg:phone":"+1 623 245 1567",
    "sg:postcode":"85031",
    "sg:province":"AZ",
    "sg:tags":[
        "convenience",
        "store"
    ],
    "wof:name":"Rj Liquors",
    "wof:placetype":"venue"
},
  "geometry": {"coordinates":[-112.184799,33.494989],"type":"Point"}
}