{
  "type": "Feature",
  "properties": {
    "iso:country":"US",
    "sg:address":"3641 N 35th Ave",
    "sg:city":"Phoenix",
    "sg:classifiers":[
        {
            "category":"Professional",
            "type":"Services"
        }
    ],
    "sg:phone":"+1 602 272 9675",
    "sg:postcode":"85017",
    "sg:province":"AZ",
    "wof:name":"New Age Kitchen & Bath LLC",
    "wof:placetype":"venue"
},
  "geometry": {"coordinates":[-112.134209,33.490783],"type":"Point"}
}