{
  "type": "Feature",
  "properties": {
    "iso:country":"US",
    "sg:address":"790 S 12th St",
    "sg:city":"Cottonwood",
    "sg:classifiers":[
        {
            "category":"Building & Trades",
            "subcategory":"Construction",
            "type":"Services"
        }
    ],
    "sg:phone":"+1 928 639 4599",
    "sg:postcode":"86326",
    "sg:province":"AZ",
    "sg:tags":[
        "general",
        "contractor"
    ],
    "wof:name":"Noble Heritage Builders Inc",
    "wof:placetype":"venue"
},
  "geometry": {"coordinates":[-112.01415900000001,34.725256],"type":"Point"}
}