{
  "type": "Feature",
  "properties": {
    "iso:country":"US",
    "sg:address":"13450 N Lon Adams Rd",
    "sg:city":"Marana",
    "sg:classifiers":[
        {
            "category":"Organizations",
            "subcategory":"Religious Organization",
            "type":"Services"
        }
    ],
    "sg:phone":"+1 520 682 2413",
    "sg:postcode":"85653",
    "sg:province":"AZ",
    "sg:tags":[
        "church"
    ],
    "wof:name":"Church Of Jesus CHRIST-Lds",
    "wof:placetype":"venue"
},
  "geometry": {"coordinates":[-111.208364,32.446981],"type":"Point"}
}