{
  "type": "Feature",
  "properties": {
    "addr:full":"1644 W Hatcher Rd Phoenix AZ 85021",
    "addr:housenumber":"1644",
    "addr:postcode":"85021",
    "addr:street":"W Hatcher Rd",
    "iso:country":"US",
    "sg:address":"1644 W Hatcher Rd",
    "sg:city":"Phoenix",
    "sg:classifiers":[
        {
            "category":"Building & Trades",
            "subcategory":"Plumbing",
            "type":"Services"
        }
    ],
    "sg:phone":"+1 602 749 0625",
    "sg:postcode":"85021",
    "sg:province":"AZ",
    "sg:tags":[
        "contractor"
    ],
    "wof:name":"Freedom Plumbing & Maintenance",
    "wof:placetype":"venue"
},
  "geometry": {"coordinates":[-112.094705,33.571306],"type":"Point"}
}