{
  "type": "Feature",
  "properties": {
    "iso:country":"US",
    "sg:address":"2015 Yavapai Dr",
    "sg:city":"Sedona",
    "sg:classifiers":[
        {
            "category":"Freight",
            "type":"Transportation"
        }
    ],
    "sg:phone":"+1 928 282 4773",
    "sg:postcode":"86336",
    "sg:province":"AZ",
    "sg:tags":[
        "general"
    ],
    "wof:name":"Sedona Lock-Up",
    "wof:placetype":"venue"
},
  "geometry": {"coordinates":[-111.796252,34.866095],"type":"Point"}
}