{
  "type": "Feature",
  "properties": {
    "iso:country":"US",
    "sg:address":"3922 US Hwy 191",
    "sg:city":"Safford",
    "sg:classifiers":[
        {
            "category":"Retail",
            "subcategory":"Animal Services",
            "type":"Services"
        }
    ],
    "sg:phone":"+1 928 428 7322",
    "sg:postcode":"85546",
    "sg:province":"AZ",
    "sg:tags":[
        "pet",
        "grooming",
        "washing"
    ],
    "wof:name":"Rene's Pampered Pooch",
    "wof:placetype":"venue"
},
  "geometry": {"coordinates":[-109.707923,32.792376],"type":"Point"}
}