{
  "type": "Feature",
  "properties": {
    "iso:country":"US",
    "sg:address":"3700 N 75th St Ste B",
    "sg:city":"Scottsdale",
    "sg:classifiers":[
        {
            "category":"Government",
            "subcategory":"Office",
            "type":"Public Place"
        }
    ],
    "sg:phone":"+1 480 312 2716",
    "sg:postcode":"85251",
    "sg:province":"AZ",
    "sg:tags":[
        "township",
        "government-city",
        "village"
    ],
    "wof:name":"City Of Scottsdale",
    "wof:placetype":"venue"
},
  "geometry": {"coordinates":[-111.91964,33.490181],"type":"Point"}
}