{
  "type": "Feature",
  "properties": {
    "iso:country":"US",
    "sg:address":"7463 E Beryl Ave",
    "sg:city":"Scottsdale",
    "sg:classifiers":[
        {
            "category":"Professional",
            "type":"Services"
        }
    ],
    "sg:phone":"+1 480 998 8136",
    "sg:postcode":"85258",
    "sg:province":"AZ",
    "wof:name":"Jjj Fund LLC",
    "wof:placetype":"venue"
},
  "geometry": {"coordinates":[-111.920299,33.578893],"type":"Point"}
}