{
  "type": "Feature",
  "properties": {
    "addr:full":"3420 E Bell Rd Phoenix AZ 85032",
    "addr:housenumber":"3420",
    "addr:postcode":"85032",
    "addr:street":"E Bell Rd",
    "iso:country":"US",
    "sg:address":"3420 E Bell Rd",
    "sg:city":"Phoenix",
    "sg:classifiers":[
        {
            "category":"Cinema",
            "subcategory":"Movie Theater",
            "type":"Entertainment"
        }
    ],
    "sg:phone":"+1 602 222 4275",
    "sg:postcode":"85032",
    "sg:province":"AZ",
    "wof:name":"North Valley 16",
    "wof:placetype":"venue"
},
  "geometry": {"coordinates":[-112.00656499999999,33.640714],"type":"Point"}
}