{
  "type": "Feature",
  "properties": {
    "iso:country":"US",
    "sg:address":"2135 E Knudsen Dr",
    "sg:city":"Phoenix",
    "sg:classifiers":[
        {
            "category":"Professional",
            "subcategory":"Detective & Security Services",
            "type":"Services"
        }
    ],
    "sg:phone":"+1 480 513 0350",
    "sg:postcode":"85024",
    "sg:province":"AZ",
    "sg:tags":[
        "guard",
        "patrol"
    ],
    "wof:name":"21st Century Security",
    "wof:placetype":"venue"
},
  "geometry": {"coordinates":[-112.037404,33.69566],"type":"Point"}
}