{
  "type": "Feature",
  "properties": {
    "iso:country":"US",
    "sg:address":"3125 S Alma School Rd",
    "sg:city":"Chandler",
    "sg:classifiers":[
        {
            "category":"Restaurant",
            "type":"Food & Drink"
        }
    ],
    "sg:phone":"+1 480 726 0255",
    "sg:postcode":"85248",
    "sg:province":"AZ",
    "sg:tags":[
        "sushi",
        "bar"
    ],
    "sg:website":"www.mikadoaz.com",
    "wof:name":"Mikado Sushi",
    "wof:placetype":"venue"
},
  "geometry": {"coordinates":[-111.85844899999999,33.260968],"type":"Point"}
}