{
  "type": "Feature",
  "properties": {
    "addr:full":"7308 W Alexandria Way Peoria AZ 85381",
    "addr:housenumber":"7308",
    "addr:postcode":"85381",
    "addr:street":"W Alexandria Way",
    "iso:country":"US",
    "sg:address":"7308 W Alexandria Way",
    "sg:city":"Peoria",
    "sg:classifiers":[
        {
            "category":"Banks & Credit Unions",
            "subcategory":"Financial Services",
            "type":"Services"
        }
    ],
    "sg:phone":"+1 623 776 0967",
    "sg:postcode":"85381",
    "sg:province":"AZ",
    "sg:tags":[
        "investment",
        "closed"
    ],
    "wof:name":"Manns Retirement",
    "wof:placetype":"venue"
},
  "geometry": {"coordinates":[-112.21923700000001,33.606742],"type":"Point"}
}