{
  "type": "Feature",
  "properties": {
    "iso:country":"US",
    "sg:address":"2162 E Williams Field Rd",
    "sg:city":"Gilbert",
    "sg:classifiers":[
        {
            "category":"Banks & Credit Unions",
            "subcategory":"Bank",
            "type":"Services"
        }
    ],
    "sg:phone":"+1 480 782 1318",
    "sg:postcode":"85295",
    "sg:province":"AZ",
    "wof:name":"Jos A Bank Clotheirs",
    "wof:placetype":"venue"
},
  "geometry": {"coordinates":[-111.744564,33.307003],"type":"Point"}
}