{
  "type": "Feature",
  "properties": {
    "iso:country":"US",
    "sg:address":"6930 E Granada St",
    "sg:city":"Mesa",
    "sg:classifiers":[
        {
            "category":"Social Services",
            "subcategory":"Adult Care",
            "type":"Services"
        }
    ],
    "sg:phone":"+1 480 641 7445",
    "sg:postcode":"85207",
    "sg:province":"AZ",
    "sg:tags":[
        "home",
        "residential"
    ],
    "wof:name":"Mayfair Assisted Living Home",
    "wof:placetype":"venue"
},
  "geometry": {"coordinates":[-111.680301,33.440102],"type":"Point"}
}