{
  "type": "Feature",
  "properties": {
    "iso:country":"US",
    "sg:address":"711 N 107th St",
    "sg:city":"Mesa",
    "sg:classifiers":[
        {
            "category":"Banks & Credit Unions",
            "subcategory":"Bank",
            "type":"Services"
        }
    ],
    "sg:phone":"+1 480 926 4112",
    "sg:postcode":"85207",
    "sg:province":"AZ",
    "sg:tags":[
        "loan",
        "real estate"
    ],
    "wof:name":"Southwest Professional Mrtge",
    "wof:placetype":"venue"
},
  "geometry": {"coordinates":[-111.600025,33.427924],"type":"Point"}
}