{
  "type": "Feature",
  "properties": {
    "addr:full":"4041 N Central Ave Phoenix AZ 85012",
    "addr:housenumber":"4041",
    "addr:postcode":"85012",
    "addr:street":"N Central Ave",
    "iso:country":"US",
    "sg:address":"4041 N Central Ave",
    "sg:city":"Phoenix",
    "sg:classifiers":[
        {
            "category":"Banks & Credit Unions",
            "subcategory":"Bank",
            "type":"Services"
        }
    ],
    "sg:phone":"+1 602 241 1900",
    "sg:postcode":"85012",
    "sg:province":"AZ",
    "sg:tags":[
        "loan",
        "real estate"
    ],
    "wof:name":"Pacific National Mortgage",
    "wof:placetype":"venue"
},
  "geometry": {"coordinates":[-112.073711,33.493832],"type":"Point"}
}