{
  "type": "Feature",
  "properties": {
    "iso:country":"US",
    "sg:address":"1640 N 36th St",
    "sg:city":"Phoenix",
    "sg:classifiers":[
        {
            "category":"Restaurant",
            "type":"Food & Drink"
        }
    ],
    "sg:menulink":"http://www.allmenus.com/az/phoenix/88410-pizza-patron/menu/",
    "sg:phone":"+1 602 685 9191",
    "sg:postcode":"85008",
    "sg:province":"AZ",
    "sg:tags":[
        "american",
        "pizza"
    ],
    "wof:name":"Pizza Patron",
    "wof:placetype":"venue"
},
  "geometry": {"coordinates":[-112.00422500000001,33.466958],"type":"Point"}
}