{
  "type": "Feature",
  "properties": {
    "iso:country":"US",
    "sg:address":"803 W Brooks St",
    "sg:city":"Chandler",
    "sg:classifiers":[
        {
            "category":"Travel",
            "subcategory":"Travel Agent",
            "type":"Entertainment"
        }
    ],
    "sg:phone":"+1 480 545 7174",
    "sg:postcode":"85225",
    "sg:province":"AZ",
    "sg:tags":[
        "operator",
        "tour",
        "agency"
    ],
    "wof:name":"Speedway Racing Tours",
    "wof:placetype":"venue"
},
  "geometry": {"coordinates":[-111.855958,33.334002],"type":"Point"}
}