{
  "type": "Feature",
  "properties": {
    "iso:country":"US",
    "sg:address":"1312 N 66th St",
    "sg:city":"Mesa",
    "sg:classifiers":[
        {
            "category":"Manufacturing",
            "subcategory":"Apparel",
            "type":"Manufacturing & Wholesale Goods"
        }
    ],
    "sg:phone":"+1 480 807 0557",
    "sg:postcode":"85205",
    "sg:province":"AZ",
    "wof:name":"AAA Embroidery",
    "wof:placetype":"venue"
},
  "geometry": {"coordinates":[-111.688699,33.439417],"type":"Point"}
}