{
  "type": "Feature",
  "properties": {
    "iso:country":"US",
    "sg:address":"2201 N Park Dr",
    "sg:city":"Winslow",
    "sg:classifiers":[
        {
            "category":"Food & Beverages",
            "subcategory":"Groceries & Convenience Stores",
            "type":"Retail Goods"
        }
    ],
    "sg:phone":"+1 928 289 9531",
    "sg:postcode":"86047",
    "sg:province":"AZ",
    "wof:name":"Super American Truck Stop",
    "wof:placetype":"venue"
},
  "geometry": {"coordinates":[-110.697983,35.041085],"type":"Point"}
}