{
  "type": "Feature",
  "properties": {
    "iso:country":"US",
    "sg:address":"3015 E Speedway Blvd",
    "sg:city":"Tucson",
    "sg:classifiers":[
        {
            "category":"Personal",
            "subcategory":"Beauty Salon",
            "type":"Services"
        }
    ],
    "sg:phone":"+1 520 881 5889",
    "sg:postcode":"85716",
    "sg:province":"AZ",
    "sg:tags":[
        "manicuring"
    ],
    "wof:name":"California Nails",
    "wof:placetype":"venue"
},
  "geometry": {"coordinates":[-110.926973,32.236082],"type":"Point"}
}