{
  "type": "Feature",
  "properties": {
    "iso:country":"US",
    "sg:address":"1 N Central Ave",
    "sg:city":"Phoenix",
    "sg:classifiers":[
        {
            "category":"Restaurant",
            "type":"Food & Drink"
        }
    ],
    "sg:phone":"+1 602 252 8450",
    "sg:postcode":"85004",
    "sg:province":"AZ",
    "sg:tags":[
        "coffee",
        "eating",
        "roasted"
    ],
    "wof:name":"Seattles Best Coffee Inc",
    "wof:placetype":"venue"
},
  "geometry": {"coordinates":[-112.073815,33.449314],"type":"Point"}
}