{
  "type": "Feature",
  "properties": {
    "iso:country":"US",
    "sg:address":"5285 E Williams Cir",
    "sg:city":"Tucson",
    "sg:classifiers":[
        {
            "category":"Restaurant",
            "type":"Food & Drink"
        }
    ],
    "sg:phone":"+1 520 748 2535",
    "sg:postcode":"85711",
    "sg:province":"AZ",
    "sg:tags":[
        "cafe"
    ],
    "wof:name":"Take 5",
    "wof:placetype":"venue"
},
  "geometry": {"coordinates":[-110.88131300000001,32.220596],"type":"Point"}
}