{
  "type": "Feature",
  "properties": {
    "iso:country":"US",
    "sg:address":"418 US Hwy 66",
    "sg:city":"Flagstaff",
    "sg:classifiers":[
        {
            "category":"Banks & Credit Unions",
            "subcategory":"Bank",
            "type":"Services"
        }
    ],
    "sg:phone":"+1 928 779 2797",
    "sg:postcode":"86001",
    "sg:province":"AZ",
    "sg:tags":[
        "loan"
    ],
    "wof:name":"Quik Cash",
    "wof:placetype":"venue"
},
  "geometry": {"coordinates":[-111.644583,35.196144],"type":"Point"}
}