{
  "type": "Feature",
  "properties": {
    "addr:full":"16435 N 40th Pl Phoenix AZ 85032",
    "addr:housenumber":"16435",
    "addr:postcode":"85032",
    "addr:street":"N 40Th Pl",
    "iso:country":"US",
    "sg:address":"16435 N 40th Pl",
    "sg:city":"Phoenix",
    "sg:classifiers":[
        {
            "category":"Building & Trades",
            "subcategory":"Landscaping Services",
            "type":"Services"
        }
    ],
    "sg:phone":"+1 602 493 7060",
    "sg:postcode":"85032",
    "sg:province":"AZ",
    "wof:name":"Sun Ray Landscape Management",
    "wof:placetype":"venue"
},
  "geometry": {"coordinates":[-111.99403700000001,33.636802],"type":"Point"}
}