{
  "type": "Feature",
  "properties": {
    "iso:country":"US",
    "sg:address":"2626 Heidi Loop",
    "sg:city":"Flagstaff",
    "sg:classifiers":[
        {
            "category":"Arts & Performance",
            "subcategory":"Theater",
            "type":"Entertainment"
        }
    ],
    "sg:phone":"+1 928 774 2373",
    "sg:postcode":"86004",
    "sg:province":"AZ",
    "sg:tags":[
        "live",
        "music"
    ],
    "sg:website":"www.azdj.com",
    "wof:name":"Arizona DJ Express",
    "wof:placetype":"venue"
},
  "geometry": {"coordinates":[-111.610388,35.215344],"type":"Point"}
}