{
  "type": "Feature",
  "properties": {
    "iso:country":"US",
    "sg:address":"1565 N Pso la Tinaja",
    "sg:city":"Green Valley",
    "sg:classifiers":[
        {
            "category":"Building & Trades",
            "subcategory":"Construction",
            "type":"Services"
        }
    ],
    "sg:phone":"+1 520 648 2508",
    "sg:postcode":"85614",
    "sg:province":"AZ",
    "sg:tags":[
        "house"
    ],
    "wof:name":"First Integrity Development",
    "wof:placetype":"venue"
},
  "geometry": {"coordinates":[-110.996024,31.893492],"type":"Point"}
}