{
  "type": "Feature",
  "properties": {
    "addr:full":"2400 N Central Ave Phoenix AZ 85004",
    "addr:housenumber":"2400",
    "addr:postcode":"85004",
    "addr:street":"N Central Ave",
    "iso:country":"US",
    "sg:address":"2400 N Central Ave",
    "sg:city":"Phoenix",
    "sg:classifiers":[
        {
            "category":"Professional",
            "type":"Services"
        }
    ],
    "sg:phone":"+1 602 253 5671",
    "sg:postcode":"85004",
    "sg:province":"AZ",
    "sg:tags":[
        "establishment"
    ],
    "wof:name":"KOLL Bren Fund VLP",
    "wof:placetype":"venue"
},
  "geometry": {"coordinates":[-112.07377099999999,33.474857],"type":"Point"}
}