{
  "type": "Feature",
  "properties": {
    "iso:country":"US",
    "sg:address":"3042 E Rockwood Dr",
    "sg:city":"Phoenix",
    "sg:classifiers":[
        {
            "category":"Shopping",
            "subcategory":"Bicycles & Sporting Goods",
            "type":"Retail Goods"
        }
    ],
    "sg:phone":"+1 602 499 1350",
    "sg:postcode":"85050",
    "sg:province":"AZ",
    "wof:name":"Bell Sport Services",
    "wof:placetype":"venue"
},
  "geometry": {"coordinates":[-112.016428,33.656531],"type":"Point"}
}