{
  "type": "Feature",
  "properties": {
    "addr:full":"14875 N Cave Creek Rd Phoenix AZ 85032",
    "addr:housenumber":"14875",
    "addr:postcode":"85032",
    "addr:street":"N Cave Creek Rd",
    "iso:country":"US",
    "sg:address":"14875 N Cave Creek Rd",
    "sg:city":"Phoenix",
    "sg:classifiers":[
        {
            "category":"Autos & Motor Vehicles",
            "subcategory":"Fuel & Gas Station",
            "type":"Retail Goods"
        },
        {
            "category":"Food & Beverages",
            "subcategory":"Groceries & Convenience Stores",
            "type":"Retail Goods"
        }
    ],
    "sg:phone":"+1 602 992 3465",
    "sg:postcode":"85032",
    "sg:province":"AZ",
    "wof:name":"Quick Stop",
    "wof:placetype":"venue"
},
  "geometry": {"coordinates":[-112.030689,33.622509],"type":"Point"}
}