{
  "type": "Feature",
  "properties": {
    "addr:full":"902 W Glendale Ave Phoenix AZ 85021",
    "addr:housenumber":"902",
    "addr:postcode":"85021",
    "addr:street":"W Glendale Ave",
    "iso:country":"US",
    "sg:address":"902 W Glendale Ave",
    "sg:city":"Phoenix",
    "sg:classifiers":[
        {
            "category":"Professional",
            "type":"Services"
        }
    ],
    "sg:phone":"+1 602 371 8128",
    "sg:postcode":"85021",
    "sg:province":"AZ",
    "wof:name":"Davis Ltd Lawyers",
    "wof:placetype":"venue"
},
  "geometry": {"coordinates":[-112.08575999999999,33.538481],"type":"Point"}
}