{
  "type": "Feature",
  "properties": {
    "addr:full":"9189 N 59th Ave Glendale AZ 85302",
    "addr:housenumber":"9189",
    "addr:postcode":"85302",
    "addr:street":"N 59Th Ave",
    "iso:country":"US",
    "sg:address":"9189 N 59th Ave",
    "sg:city":"Glendale",
    "sg:classifiers":[
        {
            "category":"Shopping",
            "subcategory":"Books",
            "type":"Retail Goods"
        }
    ],
    "sg:phone":"+1 623 435 6800",
    "sg:postcode":"85302",
    "sg:province":"AZ",
    "sg:tags":[
        "dealer"
    ],
    "sg:website":"www.collegebookcenter.com",
    "wof:name":"College Book Ctr",
    "wof:placetype":"venue"
},
  "geometry": {"coordinates":[-112.18619099999999,33.567787],"type":"Point"}
}