{
  "type": "Feature",
  "properties": {
    "iso:country":"US",
    "sg:address":"9709 W Hatcher Rd",
    "sg:city":"Peoria",
    "sg:classifiers":[
        {
            "category":"Real Estate",
            "subcategory":"Real Estate Agent",
            "type":"Services"
        }
    ],
    "sg:phone":"+1 623 334 8602",
    "sg:postcode":"85345",
    "sg:province":"AZ",
    "wof:name":"Walker/Felice Invst",
    "wof:placetype":"venue"
},
  "geometry": {"coordinates":[-112.26953,33.569755],"type":"Point"}
}