{
  "type": "Feature",
  "properties": {
    "iso:country":"US",
    "sg:address":"434 S Harvard Dr",
    "sg:city":"Tucson",
    "sg:classifiers":[
        {
            "category":"Retail",
            "subcategory":"Animal Services",
            "type":"Services"
        }
    ],
    "sg:phone":"+1 520 440 5040",
    "sg:postcode":"85710",
    "sg:province":"AZ",
    "sg:tags":[
        "training",
        "dog"
    ],
    "wof:name":"Animal Magnetism",
    "wof:placetype":"venue"
},
  "geometry": {"coordinates":[-110.853479,32.215546],"type":"Point"}
}