{
  "type": "Feature",
  "properties": {
    "addr:full":"220 S 83rd Pl Mesa AZ 85208",
    "addr:housenumber":"220",
    "addr:postcode":"85208",
    "addr:street":"S 83Rd Pl",
    "iso:country":"US",
    "sg:address":"220 S 83rd Pl",
    "sg:city":"Mesa",
    "sg:classifiers":[
        {
            "category":"Building & Trades",
            "subcategory":"Construction",
            "type":"Services"
        }
    ],
    "sg:phone":"+1 480 984 0237",
    "sg:postcode":"85208",
    "sg:province":"AZ",
    "sg:tags":[
        "house"
    ],
    "wof:name":"General Constructuion & Design",
    "wof:placetype":"venue"
},
  "geometry": {"coordinates":[-111.65178899999999,33.410451],"type":"Point"}
}