{
  "type": "Feature",
  "properties": {
    "iso:country":"US",
    "sg:address":"377 N Montezuma St",
    "sg:city":"Prescott",
    "sg:classifiers":[
        {
            "category":"Insurance",
            "subcategory":"Insurance Agent",
            "type":"Services"
        }
    ],
    "sg:phone":"+1 928 776 8100",
    "sg:postcode":"86301",
    "sg:province":"AZ",
    "wof:name":"State Farm Insurance",
    "wof:placetype":"venue"
},
  "geometry": {"coordinates":[-112.469374,34.547742],"type":"Point"}
}