{
  "type": "Feature",
  "properties": {
    "addr:full":"13647 N 33rd Ave Phoenix AZ 85029",
    "addr:housenumber":"13647",
    "addr:postcode":"85029",
    "addr:street":"N 33Rd Ave",
    "iso:country":"US",
    "sg:address":"13647 N 33rd Ave",
    "sg:city":"Phoenix",
    "sg:classifiers":[
        {
            "category":"Professional",
            "subcategory":"Advertising",
            "type":"Services"
        },
        {
            "category":"Manufacturing",
            "subcategory":"Signs",
            "type":"Manufacturing & Wholesale Goods"
        }
    ],
    "sg:phone":"+1 928 592 0433",
    "sg:postcode":"85029",
    "sg:province":"AZ",
    "sg:tags":[
        "specialty"
    ],
    "wof:name":"Barclay's Metal Magic",
    "wof:placetype":"venue"
},
  "geometry": {"coordinates":[-112.128895,33.610062],"type":"Point"}
}