{
  "type": "Feature",
  "properties": {
    "addr:full":"249 E Eugie Ave Phoenix AZ 85022",
    "addr:housenumber":"249",
    "addr:postcode":"85022",
    "addr:street":"E Eugie Ave",
    "iso:country":"US",
    "sg:address":"249 E Eugie Ave",
    "sg:city":"Phoenix",
    "sg:classifiers":[
        {
            "category":"Retail",
            "subcategory":"Auto Repair",
            "type":"Services"
        }
    ],
    "sg:phone":"+1 602 978 1746",
    "sg:postcode":"85022",
    "sg:province":"AZ",
    "sg:tags":[
        "automobile",
        "restoration-antique",
        "classic"
    ],
    "wof:name":"Rs Gauge Works",
    "wof:placetype":"venue"
},
  "geometry": {"coordinates":[-112.070532,33.608952],"type":"Point"}
}