{
  "type": "Feature",
  "properties": {
    "iso:country":"US",
    "sg:address":"1540 W Rillito St",
    "sg:city":"Tucson",
    "sg:classifiers":[
        {
            "category":"Shopping",
            "subcategory":"Beauty & Cosmetics",
            "type":"Retail Goods"
        }
    ],
    "sg:phone":"+1 520 293 0455",
    "sg:postcode":"85705",
    "sg:province":"AZ",
    "sg:tags":[
        "product",
        "skin",
        "care"
    ],
    "wof:name":"Body & Soul",
    "wof:placetype":"venue"
},
  "geometry": {"coordinates":[-110.998645,32.290434],"type":"Point"}
}