{
  "type": "Feature",
  "properties": {
    "iso:country":"US",
    "sg:address":"3051 E Adams",
    "sg:city":"Show Low",
    "sg:classifiers":[
        {
            "category":"Building & Trades",
            "subcategory":"Construction",
            "type":"Services"
        }
    ],
    "sg:phone":"+1 928 537 9441",
    "sg:postcode":"85901",
    "sg:province":"AZ",
    "wof:name":"Hatch Construction & Paving",
    "wof:placetype":"venue"
},
  "geometry": {"coordinates":[-110.010541,34.256858],"type":"Point"}
}