{
  "type": "Feature",
  "properties": {
    "addr:full":"6217 W Saguaro Park Ln Glendale AZ 85310",
    "addr:housenumber":"6217",
    "addr:postcode":"85310",
    "addr:street":"W Saguaro Park Ln",
    "iso:country":"US",
    "sg:address":"6217 W Saguaro Park Ln",
    "sg:city":"Glendale",
    "sg:classifiers":[
        {
            "category":"Professional",
            "subcategory":"Research",
            "type":"Services"
        }
    ],
    "sg:phone":"+1 623 776 1330",
    "sg:postcode":"85310",
    "sg:province":"AZ",
    "sg:tags":[
        "information",
        "medical"
    ],
    "wof:name":"Alternative Cancer Research Funds",
    "wof:placetype":"venue"
},
  "geometry": {"coordinates":[-112.193573,33.707539],"type":"Point"}
}