{
  "type": "Feature",
  "properties": {
    "iso:country":"US",
    "sg:address":"1101 S Joshua Ave",
    "sg:city":"Parker",
    "sg:classifiers":[
        {
            "category":"Place Of Worship",
            "subcategory":"Church",
            "type":"Public Place"
        },
        {
            "category":"Place Of Worship",
            "type":"Public Place"
        }
    ],
    "sg:phone":"+1 928 669 6311",
    "sg:postcode":"85344",
    "sg:province":"AZ",
    "sg:tags":[
        "churches-catholic-traditional",
        "churches-catholic"
    ],
    "wof:name":"St Vincent De Paul Sacred Heart",
    "wof:placetype":"venue"
},
  "geometry": {"coordinates":[-114.289749,34.148869],"type":"Point"}
}