{
  "type": "Feature",
  "properties": {
    "iso:country":"US",
    "sg:address":"4749 S Irving Ave",
    "sg:city":"Tucson",
    "sg:classifiers":[
        {
            "category":"Building & Trades",
            "subcategory":"Construction",
            "type":"Services"
        }
    ],
    "sg:phone":"+1 520 745 0994",
    "sg:postcode":"85714",
    "sg:province":"AZ",
    "sg:tags":[
        "concrete",
        "contractor"
    ],
    "wof:name":"William J Hardy Concrete Inc",
    "wof:placetype":"venue"
},
  "geometry": {"coordinates":[-110.904348,32.165913],"type":"Point"}
}