{
  "type": "Feature",
  "properties": {
    "iso:country":"US",
    "sg:address":"243 E Ponderosa Ln",
    "sg:city":"Phoenix",
    "sg:classifiers":[
        {
            "category":"Building & Trades",
            "subcategory":"Landscaping Services",
            "type":"Services"
        }
    ],
    "sg:phone":"+1 602 448 8093",
    "sg:postcode":"85022",
    "sg:province":"AZ",
    "sg:tags":[
        "landscape"
    ],
    "wof:name":"Desert Showcase Landscaping",
    "wof:placetype":"venue"
},
  "geometry": {"coordinates":[-112.070275,33.626656],"type":"Point"}
}