{
  "type": "Feature",
  "properties": {
    "addr:full":"305 N 54th St Chandler AZ 85226",
    "addr:housenumber":"305",
    "addr:postcode":"85226",
    "addr:street":"N 54Th St",
    "iso:country":"US",
    "sg:address":"305 N 54th St",
    "sg:city":"Chandler",
    "sg:classifiers":[
        {
            "category":"Shopping",
            "subcategory":"Computers & Home Electronics",
            "type":"Retail Goods"
        }
    ],
    "sg:phone":"+1 480 222 1611",
    "sg:postcode":"85226",
    "sg:province":"AZ",
    "sg:tags":[
        "equipment",
        "electronic",
        "supply"
    ],
    "wof:name":"Ebuyer Us Inc",
    "wof:placetype":"venue"
},
  "geometry": {"coordinates":[-111.96730599999999,33.307118],"type":"Point"}
}