{
  "type": "Feature",
  "properties": {
    "addr:full":"6112 E 22nd St Tucson AZ 85711",
    "addr:housenumber":"6112",
    "addr:postcode":"85711",
    "addr:street":"E 22Nd St",
    "iso:country":"US",
    "sg:address":"6112 E 22nd St",
    "sg:city":"Tucson",
    "sg:classifiers":[
        {
            "category":"Professional",
            "subcategory":"Accounting & Tax Preparation",
            "type":"Services"
        }
    ],
    "sg:phone":"+1 520 571 8989",
    "sg:postcode":"85711",
    "sg:province":"AZ",
    "sg:tags":[
        "accountant"
    ],
    "wof:name":"John L Torrez CPA",
    "wof:placetype":"venue"
},
  "geometry": {"coordinates":[-110.860713,32.206907],"type":"Point"}
}