{
  "type": "Feature",
  "properties": {
    "iso:country":"US",
    "sg:address":"7025 N 75th Ave Ste 103",
    "sg:city":"Glendale",
    "sg:classifiers":[
        {
            "category":"Personal",
            "subcategory":"Nail Salon",
            "type":"Services"
        }
    ],
    "sg:phone":"+1 623 842 0888",
    "sg:postcode":"85303",
    "sg:province":"AZ",
    "wof:name":"Angel Touch Nails",
    "wof:placetype":"venue"
},
  "geometry": {"coordinates":[-112.220451,33.53883],"type":"Point"}
}