{
  "type": "Feature",
  "properties": {
    "addr:full":"1422 N 44th St Ste 208 Phoenix AZ 85008",
    "addr:housenumber":"1422",
    "addr:postcode":"85008",
    "addr:street":"N 44Th St Ste 208",
    "iso:country":"US",
    "sg:address":"1422 N 44th St Ste 208",
    "sg:city":"Phoenix",
    "sg:classifiers":[
        {
            "category":"Professional",
            "subcategory":"Engineering",
            "type":"Services"
        },
        {
            "category":"Professional",
            "subcategory":"Management & Consulting",
            "type":"Services"
        }
    ],
    "sg:phone":"+1 602 267 0336",
    "sg:postcode":"85008",
    "sg:province":"AZ",
    "sg:tags":[
        "consultant",
        "energy",
        "engineer",
        "ecological",
        "environmental"
    ],
    "sg:website":"http://www.bas.com",
    "wof:name":"Bryan A. Stirrat & Associates",
    "wof:placetype":"venue"
},
  "geometry": {"coordinates":[-111.987213,33.463899],"type":"Point"}
}