{
  "type": "Feature",
  "properties": {
    "addr:full":"222 W Center St Pima AZ 85543",
    "addr:housenumber":"222",
    "addr:postcode":"85543",
    "addr:street":"W Center St",
    "iso:country":"US",
    "sg:address":"222 W Center St",
    "sg:city":"Pima",
    "sg:classifiers":[
        {
            "category":"Health Services",
            "subcategory":"Clinic",
            "type":"Services"
        }
    ],
    "sg:phone":"+1 928 485 0007",
    "sg:postcode":"85543",
    "sg:province":"AZ",
    "wof:name":"Optimal Health Systems",
    "wof:placetype":"venue"
},
  "geometry": {"coordinates":[-109.83193300000001,32.896301],"type":"Point"}
}