{
  "type": "Feature",
  "properties": {
    "iso:country":"US",
    "sg:address":"2420 N 3rd St Ste A",
    "sg:city":"Flagstaff",
    "sg:classifiers":[
        {
            "category":"Retail",
            "subcategory":"Laundry & Dry Cleaning",
            "type":"Services"
        },
        {
            "category":"Retail",
            "subcategory":"Repair Shop",
            "type":"Services"
        },
        {
            "category":"Home & Garden",
            "subcategory":"Carpets & Floor Coverings",
            "type":"Retail Goods"
        }
    ],
    "sg:phone":"+1 928 226 8948",
    "sg:postcode":"86004",
    "sg:province":"AZ",
    "sg:tags":[
        "cleaner",
        "rug",
        "flooring",
        "contractor"
    ],
    "wof:name":"Triple R Flooring",
    "wof:placetype":"venue"
},
  "geometry": {"coordinates":[-111.61464,35.212505],"type":"Point"}
}