{
  "type": "Feature",
  "properties": {
    "addr:full":"18084 W Udall Dr Surprise AZ 85374",
    "addr:housenumber":"18084",
    "addr:postcode":"85374",
    "addr:street":"W Udall Dr",
    "iso:country":"US",
    "sg:address":"18084 W Udall Dr",
    "sg:city":"Surprise",
    "sg:classifiers":[
        {
            "category":"Shopping",
            "subcategory":"Gifts & Souvenirs",
            "type":"Retail Goods"
        }
    ],
    "sg:phone":"+1 623 975 9132",
    "sg:postcode":"85374",
    "sg:province":"AZ",
    "wof:name":"Jnb LLC",
    "wof:placetype":"venue"
},
  "geometry": {"coordinates":[-112.449566,33.639903],"type":"Point"}
}