{
  "type": "Feature",
  "properties": {
    "iso:country":"US",
    "sg:address":"15803 N 60th Ave",
    "sg:city":"Glendale",
    "sg:classifiers":[
        {
            "category":"Building & Trades",
            "subcategory":"Construction",
            "type":"Services"
        }
    ],
    "sg:phone":"+1 602 743 3669",
    "sg:postcode":"85306",
    "sg:province":"AZ",
    "sg:tags":[
        "contractor"
    ],
    "wof:name":"Nova Drywall",
    "wof:placetype":"venue"
},
  "geometry": {"coordinates":[-112.188175,33.629274],"type":"Point"}
}