{
  "type": "Feature",
  "properties": {
    "iso:country":"US",
    "sg:address":"1121 E Sheldon St",
    "sg:city":"Prescott",
    "sg:classifiers":[
        {
            "category":"Real Estate",
            "subcategory":"Real Estate Operator",
            "type":"Services"
        }
    ],
    "sg:phone":"+1 928 445 3730",
    "sg:postcode":"86301",
    "sg:province":"AZ",
    "sg:tags":[
        "building",
        "nonresidential"
    ],
    "wof:name":"Cooke Properties LLC",
    "wof:placetype":"venue"
},
  "geometry": {"coordinates":[-112.455071,34.544901],"type":"Point"}
}