{
  "type": "Feature",
  "properties": {
    "addr:full":"2702 N 3rd St Ste 1050 Phoenix AZ 85004",
    "addr:housenumber":"2702",
    "addr:postcode":"85004",
    "addr:street":"N 3Rd St Ste 1050",
    "iso:country":"US",
    "sg:address":"2702 N 3rd St Ste 1050",
    "sg:city":"Phoenix",
    "sg:classifiers":[
        {
            "category":"Education",
            "subcategory":"Special Training",
            "type":"Public Place"
        },
        {
            "category":"Education",
            "subcategory":"University",
            "type":"Public Place"
        }
    ],
    "sg:phone":"+1 602 279 1011",
    "sg:postcode":"85004",
    "sg:province":"AZ",
    "sg:tags":[
        "educational",
        "college",
        "adult"
    ],
    "sg:website":"http://www.wbu.edu/phoenix/",
    "wof:name":"Wayland Baptist University",
    "wof:placetype":"venue"
},
  "geometry": {"coordinates":[-112.069427,33.477998],"type":"Point"}
}