{
  "type": "Feature",
  "properties": {
    "iso:country":"US",
    "sg:address":"2724 E Lakin Dr",
    "sg:city":"Flagstaff",
    "sg:classifiers":[
        {
            "category":"Building & Trades",
            "subcategory":"Equipment Rental",
            "type":"Services"
        }
    ],
    "sg:phone":"+1 928 526 6355",
    "sg:postcode":"86004",
    "sg:province":"AZ",
    "sg:tags":[
        "medical",
        "merchandise"
    ],
    "wof:name":"American Homepatient",
    "wof:placetype":"venue"
},
  "geometry": {"coordinates":[-111.607693,35.21123],"type":"Point"}
}