{
  "type": "Feature",
  "properties": {
    "iso:country":"US",
    "sg:address":"3915 W Cholla St",
    "sg:city":"Phoenix",
    "sg:classifiers":[
        {
            "category":"Government",
            "subcategory":"Department Of Motor Vehicles",
            "type":"Public Place"
        }
    ],
    "sg:phone":"+1 602 639 6700",
    "sg:postcode":"85029",
    "sg:province":"AZ",
    "sg:tags":[
        "information",
        "van",
        "pool",
        "car"
    ],
    "wof:name":"Lecar Transportation Of Phoenix",
    "wof:placetype":"venue"
},
  "geometry": {"coordinates":[-112.142771,33.58873],"type":"Point"}
}