{
  "type": "Feature",
  "properties": {
    "iso:country":"US",
    "sg:address":"50 S Carlton Park Pl",
    "sg:city":"Tucson",
    "sg:classifiers":[
        {
            "category":"Real Estate",
            "subcategory":"Real Estate Operator",
            "type":"Services"
        }
    ],
    "sg:phone":"+1 520 546 0360",
    "sg:postcode":"85748",
    "sg:province":"AZ",
    "sg:tags":[
        "building",
        "nonresidential"
    ],
    "wof:name":"D&A Comeau Properties & Invest",
    "wof:placetype":"venue"
},
  "geometry": {"coordinates":[-110.76755,32.220109],"type":"Point"}
}