{
  "type": "Feature",
  "properties": {
    "iso:country":"US",
    "sg:address":"6835 N 57th Dr",
    "sg:city":"Glendale",
    "sg:classifiers":[
        {
            "category":"Government",
            "subcategory":"Fire Station",
            "type":"Public Place"
        },
        {
            "category":"Government",
            "subcategory":"Office",
            "type":"Public Place"
        }
    ],
    "sg:phone":"+1 623 930 3400",
    "sg:postcode":"85301",
    "sg:province":"AZ",
    "sg:tags":[
        "protection",
        "village",
        "department",
        "township",
        "government-city"
    ],
    "wof:name":"Glendale Fire Dept",
    "wof:placetype":"venue"
},
  "geometry": {"coordinates":[-112.182452,33.537424],"type":"Point"}
}