{
  "type": "Feature",
  "properties": {
    "addr:full":"14980 N 78th Ave Ste 202 Phoenix AZ 85033",
    "addr:housenumber":"14980",
    "addr:postcode":"85033",
    "addr:street":"N 78Th Ave Ste 202",
    "iso:country":"US",
    "sg:address":"14980 N 78th Ave Ste 202",
    "sg:city":"Phoenix",
    "sg:classifiers":[
        {
            "category":"Home & Garden",
            "subcategory":"Hardware",
            "type":"Retail Goods"
        }
    ],
    "sg:phone":"+1 480 473 9674",
    "sg:postcode":"85033",
    "sg:province":"AZ",
    "sg:tags":[
        "water",
        "filtration",
        "equipment",
        "purification"
    ],
    "wof:name":"Soluble Solutions Inc",
    "wof:placetype":"venue"
},
  "geometry": {"coordinates":[-112.22703199999999,33.488369],"type":"Point"}
}