{
  "type": "Feature",
  "properties": {
    "iso:country":"US",
    "sg:address":"14980 N 78th Ave Ste 202",
    "sg:city":"Phoenix",
    "sg:classifiers":[
        {
            "category":"Home & Garden",
            "subcategory":"Hardware",
            "type":"Retail Goods"
        }
    ],
    "sg:phone":"+1 480 473 9674",
    "sg:postcode":"85033",
    "sg:province":"AZ",
    "sg:tags":[
        "water",
        "filtration",
        "equipment",
        "purification"
    ],
    "wof:name":"Soluble Solutions Inc",
    "wof:placetype":"venue"
},
  "geometry": {"coordinates":[-112.227032,33.488369],"type":"Point"}
}