{
  "type": "Feature",
  "properties": {
    "iso:country":"US",
    "sg:address":"7652 E Greenway Rd",
    "sg:city":"Scottsdale",
    "sg:classifiers":[
        {
            "category":"Building & Trades",
            "subcategory":"Construction",
            "type":"Services"
        }
    ],
    "sg:phone":"+1 480 948 0021",
    "sg:postcode":"85260",
    "sg:province":"AZ",
    "sg:tags":[
        "repairing",
        "remodeling",
        "contractor"
    ],
    "wof:name":"Clearly Au Caurant Restoration",
    "wof:placetype":"venue"
},
  "geometry": {"coordinates":[-111.916327,33.62576],"type":"Point"}
}