{
  "type": "Feature",
  "properties": {
    "iso:country":"US",
    "sg:address":"570 S Ave A",
    "sg:city":"San Manuel",
    "sg:classifiers":[
        {
            "category":"Restaurant",
            "type":"Food & Drink"
        }
    ],
    "sg:phone":"+1 520 385 2278",
    "sg:postcode":"85631",
    "sg:province":"AZ",
    "sg:tags":[
        "eating"
    ],
    "wof:name":"Tastee-Freez",
    "wof:placetype":"venue"
},
  "geometry": {"coordinates":[-110.632105,32.603878],"type":"Point"}
}