{
  "type": "Feature",
  "properties": {
    "addr:full":"1071 White Tail Dr Show Low AZ 85901",
    "addr:housenumber":"1071",
    "addr:postcode":"85901",
    "addr:street":"White Tail Dr",
    "iso:country":"US",
    "sg:address":"1071 White Tail Dr",
    "sg:city":"Show Low",
    "sg:classifiers":[
        {
            "category":"Wholesale",
            "subcategory":"Vending Machines",
            "type":"Manufacturing & Wholesale Goods"
        }
    ],
    "sg:phone":"+1 928 537 2389",
    "sg:postcode":"85901",
    "sg:province":"AZ",
    "sg:tags":[
        "operator"
    ],
    "wof:name":"Javelina Vending",
    "wof:placetype":"venue"
},
  "geometry": {"coordinates":[-110.03071,34.20969],"type":"Point"}
}