{
  "type": "Feature",
  "properties": {
    "iso:country":"US",
    "sg:address":"3122 E Pennsylvania St",
    "sg:city":"Tucson",
    "sg:classifiers":[
        {
            "category":"Manufacturing",
            "subcategory":"Metals",
            "type":"Manufacturing & Wholesale Goods"
        },
        {
            "category":"Building & Trades",
            "subcategory":"Plumbing",
            "type":"Services"
        }
    ],
    "sg:phone":"+1 520 434 6188",
    "sg:postcode":"85714",
    "sg:province":"AZ",
    "sg:tags":[
        "contractor",
        "work",
        "sheet",
        "metalwork",
        "mfg"
    ],
    "wof:name":"Air Control Sheet Metal Fabric",
    "wof:placetype":"venue"
},
  "geometry": {"coordinates":[-110.922551,32.171557],"type":"Point"}
}