{
  "type": "Feature",
  "properties": {
    "iso:country":"US",
    "sg:address":"2620 S 83rd Ave",
    "sg:city":"Phoenix",
    "sg:classifiers":[
        {
            "category":"Food & Beverages",
            "subcategory":"Specialty",
            "type":"Retail Goods"
        }
    ],
    "sg:phone":"+1 623 478 9267",
    "sg:postcode":"85043",
    "sg:province":"AZ",
    "sg:tags":[
        "water",
        "bulk",
        "company"
    ],
    "wof:name":"Jacobs Well Water & Ice",
    "wof:placetype":"venue"
},
  "geometry": {"coordinates":[-112.238612,33.425038],"type":"Point"}
}