{
  "type": "Feature",
  "properties": {
    "iso:country":"US",
    "sg:address":"5646 W Bethany Home Rd",
    "sg:city":"Glendale",
    "sg:classifiers":[
        {
            "category":"Wholesale",
            "subcategory":"Scrap",
            "type":"Manufacturing & Wholesale Goods"
        }
    ],
    "sg:phone":"+1 623 931 5233",
    "sg:postcode":"85301",
    "sg:province":"AZ",
    "sg:tags":[
        "disposal",
        "waste",
        "equipment"
    ],
    "wof:name":"City Cans",
    "wof:placetype":"venue"
},
  "geometry": {"coordinates":[-112.181012,33.524121],"type":"Point"}
}