{
  "type": "Feature",
  "properties": {
    "iso:country":"US",
    "sg:address":"2507 N Santa Rita Ave",
    "sg:city":"Tucson",
    "sg:classifiers":[
        {
            "category":"Building & Trades",
            "subcategory":"Construction",
            "type":"Services"
        }
    ],
    "sg:phone":"+1 520 882 9428",
    "sg:postcode":"85719",
    "sg:province":"AZ",
    "sg:tags":[
        "contractor"
    ],
    "wof:name":"Tribolet Roofing Co",
    "wof:placetype":"venue"
},
  "geometry": {"coordinates":[-110.953977,32.252732],"type":"Point"}
}