{
  "type": "Feature",
  "properties": {
    "iso:country":"US",
    "sg:address":"1919 W Whitman Ct",
    "sg:city":"Anthem",
    "sg:classifiers":[
        {
            "category":"Travel",
            "subcategory":"Travel Agent",
            "type":"Entertainment"
        }
    ],
    "sg:phone":"+1 623 551 2041",
    "sg:postcode":"85086",
    "sg:province":"AZ",
    "sg:tags":[
        "cruise"
    ],
    "wof:name":"Feiner & Feiner",
    "wof:placetype":"venue"
},
  "geometry": {"coordinates":[-112.10061399999999,33.857157],"type":"Point"}
}