{
  "type": "Feature",
  "properties": {
    "iso:country":"US",
    "sg:address":"11596 Sierra Dawn Blvd",
    "sg:city":"Surprise",
    "sg:classifiers":[
        {
            "category":"Real Estate",
            "subcategory":"Real Estate Operator",
            "type":"Services"
        }
    ],
    "sg:phone":"+1 602 395 2628",
    "sg:postcode":"85374",
    "sg:province":"AZ",
    "sg:tags":[
        "mobile",
        "home",
        "park",
        "sales"
    ],
    "wof:name":"Rose Garden The",
    "wof:placetype":"venue"
},
  "geometry": {"coordinates":[-112.309868,33.636672],"type":"Point"}
}