{
  "type": "Feature",
  "properties": {
    "addr:full":"28609 N 251st Ave Wittmann AZ 85361",
    "addr:housenumber":"28609",
    "addr:postcode":"85361",
    "addr:street":"N 251St Ave",
    "iso:country":"US",
    "sg:address":"28609 N 251st Ave",
    "sg:city":"Wittmann",
    "sg:classifiers":[
        {
            "category":"Wholesale",
            "subcategory":"Plants",
            "type":"Manufacturing & Wholesale Goods"
        }
    ],
    "sg:phone":"+1 623 388 9793",
    "sg:postcode":"85361",
    "sg:province":"AZ",
    "sg:tags":[
        "nursery",
        "tree"
    ],
    "wof:name":"New Growth Wholesale Nursery",
    "wof:placetype":"venue"
},
  "geometry": {"coordinates":[-112.60305,33.739514],"type":"Point"}
}