{
  "type": "Feature",
  "properties": {
    "addr:full":"4513 S Salt Mine Rd Camp Verde AZ 86322",
    "addr:housenumber":"4513",
    "addr:postcode":"86322",
    "addr:street":"S Salt Mine Rd",
    "iso:country":"US",
    "sg:address":"4513 S Salt Mine Rd",
    "sg:city":"Camp Verde",
    "sg:classifiers":[
        {
            "category":"Recreation",
            "type":"Entertainment"
        }
    ],
    "sg:phone":"+1 928 567 5362",
    "sg:postcode":"86322",
    "sg:province":"AZ",
    "sg:tags":[
        "stable"
    ],
    "wof:name":"Rockin' River Ranch",
    "wof:placetype":"venue"
},
  "geometry": {"coordinates":[-111.83732000000001,34.500733],"type":"Point"}
}