{
  "type": "Feature",
  "properties": {
    "iso:country":"US",
    "sg:address":"3434 W Anthem Way",
    "sg:city":"Anthem",
    "sg:classifiers":[
        {
            "category":"Manufacturing",
            "subcategory":"Printing",
            "type":"Manufacturing & Wholesale Goods"
        }
    ],
    "sg:phone":"+1 928 567 4417",
    "sg:postcode":"85086",
    "sg:province":"AZ",
    "sg:tags":[
        "publisher"
    ],
    "wof:name":"Bee Unlimited",
    "wof:placetype":"venue"
},
  "geometry": {"coordinates":[-112.135672,33.865311],"type":"Point"}
}