{
  "type": "Feature",
  "properties": {
    "iso:country":"US",
    "sg:address":"638 S 27th Ave",
    "sg:city":"Phoenix",
    "sg:classifiers":[
        {
            "category":"Autos & Motor Vehicles",
            "subcategory":"Automobile Sales",
            "type":"Retail Goods"
        },
        {
            "category":"Retail",
            "subcategory":"Auto Repair",
            "type":"Services"
        }
    ],
    "sg:phone":"+1 602 442 5199",
    "sg:postcode":"85009",
    "sg:province":"AZ",
    "sg:tags":[
        "new",
        "restoration-antique",
        "car",
        "classic"
    ],
    "wof:name":"All-Ways Hotrods",
    "wof:placetype":"venue"
},
  "geometry": {"coordinates":[-112.11744299999999,33.44145],"type":"Point"}
}