{
  "type": "Feature",
  "properties": {
    "iso:country":"US",
    "sg:address":"26 Tom McMillan",
    "sg:city":"Flagstaff",
    "sg:classifiers":[
        {
            "category":"Real Estate",
            "subcategory":"Developer",
            "type":"Services"
        }
    ],
    "sg:phone":"+1 928 525 9752",
    "sg:postcode":"86001",
    "sg:province":"AZ",
    "wof:name":"Cottage Development Co",
    "wof:placetype":"venue"
},
  "geometry": {"coordinates":[-111.70594,35.106681],"type":"Point"}
}