{
  "type": "Feature",
  "properties": {
    "iso:country":"US",
    "sg:address":"6320 W Union Hills Dr Stea207",
    "sg:city":"Glendale",
    "sg:classifiers":[
        {
            "category":"Health Services",
            "subcategory":"Chiropractor",
            "type":"Services"
        }
    ],
    "sg:phone":"+1 623 487 3444",
    "sg:postcode":"85308",
    "sg:province":"AZ",
    "sg:tags":[
        "chiropractic"
    ],
    "wof:name":"The Back Center",
    "wof:placetype":"venue"
},
  "geometry": {"coordinates":[-112.19745,33.654096],"type":"Point"}
}