{
  "type": "Feature",
  "properties": {
    "addr:full":"10505 E Brown Rd Mesa AZ 85207",
    "addr:housenumber":"10505",
    "addr:postcode":"85207",
    "addr:street":"E Brown Rd",
    "iso:country":"US",
    "sg:address":"10505 E Brown Rd",
    "sg:city":"Mesa",
    "sg:classifiers":[
        {
            "category":"Organizations",
            "subcategory":"Religious Organization",
            "type":"Services"
        }
    ],
    "sg:phone":"+1 480 986 5021",
    "sg:postcode":"85207",
    "sg:province":"AZ",
    "sg:tags":[
        "church"
    ],
    "wof:name":"Hi-Way Baptist Church",
    "wof:placetype":"venue"
},
  "geometry": {"coordinates":[-111.605851,33.436755],"type":"Point"}
}