{
  "type": "Feature",
  "properties": {
    "addr:full":"7020 N 22nd St Phoenix AZ 85020",
    "addr:housenumber":"7020",
    "addr:postcode":"85020",
    "addr:street":"N 22Nd St",
    "iso:country":"US",
    "sg:address":"7020 N 22nd St",
    "sg:city":"Phoenix",
    "sg:classifiers":[
        {
            "category":"Arts & Performance",
            "subcategory":"Theater",
            "type":"Entertainment"
        }
    ],
    "sg:phone":"+1 602 663 4032",
    "sg:postcode":"85020",
    "sg:province":"AZ",
    "sg:tags":[
        "theatres-concert",
        "venue",
        "hall",
        "theatre"
    ],
    "wof:name":"Space 55 Theatre Ensenmble",
    "wof:placetype":"venue"
},
  "geometry": {"coordinates":[-112.03454000000001,33.538889],"type":"Point"}
}