{
  "type": "Feature",
  "properties": {
    "addr:full":"4445 S 283rd Ave Buckeye AZ 85326",
    "addr:housenumber":"4445",
    "addr:postcode":"85326",
    "addr:street":"S 283Rd Ave",
    "iso:country":"US",
    "sg:address":"4445 S 283rd Ave",
    "sg:city":"Buckeye",
    "sg:phone":"+1 623 386 5019",
    "sg:postcode":"85326",
    "sg:province":"AZ",
    "sg:tags":[
        "agricultural",
        "product"
    ],
    "wof:name":"Buckeye Ag Belt",
    "wof:placetype":"venue"
},
  "geometry": {"coordinates":[-112.667421,33.18278],"type":"Point"}
}