{
  "type": "Feature",
  "properties": {
    "addr:full":"3570 S Val Vista Dr Gilbert AZ 85297",
    "addr:housenumber":"3570",
    "addr:postcode":"85297",
    "addr:street":"S Val Vista Dr",
    "iso:country":"US",
    "sg:address":"3570 S Val Vista Dr",
    "sg:city":"Gilbert",
    "sg:classifiers":[
        {
            "category":"Health Services",
            "subcategory":"Chiropractor",
            "type":"Services"
        }
    ],
    "sg:phone":"+1 480 899 9923",
    "sg:postcode":"85297",
    "sg:province":"AZ",
    "wof:name":"Az Chiropractic",
    "wof:placetype":"venue"
},
  "geometry": {"coordinates":[-111.7557,33.286209],"type":"Point"}
}