{
  "type": "Feature",
  "properties": {
    "addr:full":"2765 N Scottsdale Rd Scottsdale AZ 85257",
    "addr:housenumber":"2765",
    "addr:postcode":"85257",
    "addr:street":"N Scottsdale Rd",
    "iso:country":"US",
    "sg:address":"2765 N Scottsdale Rd",
    "sg:city":"Scottsdale",
    "sg:classifiers":[
        {
            "category":"Retail",
            "subcategory":"Laundry & Dry Cleaning",
            "type":"Services"
        }
    ],
    "sg:phone":"+1 480 990 8778",
    "sg:postcode":"85257",
    "sg:province":"AZ",
    "sg:tags":[
        "cleaners"
    ],
    "wof:name":"Diamond Cleaners",
    "wof:placetype":"venue"
},
  "geometry": {"coordinates":[-111.92608199999999,33.480055],"type":"Point"}
}