{
  "type": "Feature",
  "properties": {
    "iso:country":"US",
    "sg:address":"1665 W Sunkist Rd",
    "sg:city":"Tucson",
    "sg:classifiers":[
        {
            "category":"Building & Trades",
            "subcategory":"Construction",
            "type":"Services"
        }
    ],
    "sg:phone":"+1 520 797 2808",
    "sg:postcode":"85737",
    "sg:province":"AZ",
    "sg:tags":[
        "contractor"
    ],
    "wof:name":"Mesa Verde Development Llc",
    "wof:placetype":"venue"
},
  "geometry": {"coordinates":[-111.001999,32.431],"type":"Point"}
}