{
  "type": "Feature",
  "properties": {
    "addr:full":"3225 Skye Way Flagstaff AZ 86001",
    "addr:housenumber":"3225",
    "addr:postcode":"86001",
    "addr:street":"Skye Way",
    "iso:country":"US",
    "sg:address":"3225 Skye Way",
    "sg:city":"Flagstaff",
    "sg:classifiers":[
        {
            "category":"Real Estate",
            "subcategory":"Architect",
            "type":"Services"
        },
        {
            "category":"Professional",
            "subcategory":"Business Services",
            "type":"Services"
        }
    ],
    "sg:phone":"+1 928 527 0020",
    "sg:postcode":"86001",
    "sg:province":"AZ",
    "sg:tags":[
        "contract",
        "trade",
        "planning",
        "design",
        "architectural",
        "home"
    ],
    "wof:name":"Sandelin & Associates Design",
    "wof:placetype":"venue"
},
  "geometry": {"coordinates":[-111.69461800000001,35.177349],"type":"Point"}
}