{
  "type": "Feature",
  "properties": {
    "iso:country":"US",
    "sg:address":"9213 N 83rd Way",
    "sg:city":"Scottsdale",
    "sg:classifiers":[
        {
            "category":"Real Estate",
            "subcategory":"Real Estate Agent",
            "type":"Services"
        }
    ],
    "sg:phone":"+1 480 348 2773",
    "sg:postcode":"85258",
    "sg:province":"AZ",
    "sg:tags":[
        "residential",
        "manager",
        "property"
    ],
    "wof:name":"CSP Hunting Company LLC",
    "wof:placetype":"venue"
},
  "geometry": {"coordinates":[-111.900375,33.570719],"type":"Point"}
}