{
  "type": "Feature",
  "properties": {
    "iso:country":"US",
    "sg:address":"640 N Center St",
    "sg:city":"Mesa",
    "sg:classifiers":[
        {
            "category":"Personal",
            "type":"Services"
        }
    ],
    "sg:phone":"+1 480 969 1992",
    "sg:postcode":"85201",
    "sg:province":"AZ",
    "sg:tags":[
        "wedding",
        "chapel"
    ],
    "sg:website":"www.mesajaycees.com",
    "wof:name":"Mesa Jaycees",
    "wof:placetype":"venue"
},
  "geometry": {"coordinates":[-111.831494,33.425595],"type":"Point"}
}