{
  "type": "Feature",
  "properties": {
    "iso:country":"US",
    "sg:address":"5041 E Elliot Rd",
    "sg:city":"Phoenix",
    "sg:classifiers":[
        {
            "category":"Recreation",
            "type":"Entertainment"
        }
    ],
    "sg:phone":"+1 480 783 4885",
    "sg:postcode":"85044",
    "sg:province":"AZ",
    "sg:tags":[
        "martial",
        "arts",
        "instruction"
    ],
    "wof:name":"Dahn Yoga Ctr",
    "wof:placetype":"venue"
},
  "geometry": {"coordinates":[-111.976677,33.349063],"type":"Point"}
}