{
  "type": "Feature",
  "properties": {
    "iso:country":"US",
    "sg:address":"164 Coffee Pot Dr",
    "sg:city":"Sedona",
    "sg:classifiers":[
        {
            "category":"Shopping",
            "subcategory":"Hobbies, Toys, & Games",
            "type":"Retail Goods"
        },
        {
            "category":"Shopping",
            "type":"Retail Goods"
        }
    ],
    "sg:phone":"+1 928 282 4009",
    "sg:postcode":"86336",
    "sg:province":"AZ",
    "sg:tags":[
        "craft",
        "merchandise",
        "supply"
    ],
    "wof:name":"Sedona Art Supplies",
    "wof:placetype":"venue"
},
  "geometry": {"coordinates":[-111.795346,34.867729],"type":"Point"}
}