{
  "type": "Feature",
  "properties": {
    "addr:full":"2030 E Cherry St Cottonwood AZ 86326",
    "addr:housenumber":"2030",
    "addr:postcode":"86326",
    "addr:street":"E Cherry St",
    "iso:country":"US",
    "sg:address":"2030 E Cherry St",
    "sg:city":"Cottonwood",
    "sg:classifiers":[
        {
            "category":"Education",
            "subcategory":"School",
            "type":"Public Place"
        }
    ],
    "sg:phone":"+1 928 634 2144",
    "sg:postcode":"86326",
    "sg:province":"AZ",
    "sg:website":"www.americanheritageacademy.com",
    "wof:name":"American Heritage Academy",
    "wof:placetype":"venue"
},
  "geometry": {"coordinates":[-112.005185,34.731749],"type":"Point"}
}