{
  "type": "Feature",
  "properties": {
    "iso:country":"US",
    "sg:address":"4505 W Vogel Ave",
    "sg:city":"Glendale",
    "sg:classifiers":[
        {
            "category":"Real Estate",
            "subcategory":"Developer",
            "type":"Services"
        }
    ],
    "sg:phone":"+1 602 881 0164",
    "sg:postcode":"85302",
    "sg:province":"AZ",
    "sg:tags":[
        "investing"
    ],
    "wof:name":"Mijoca Ventures",
    "wof:placetype":"venue"
},
  "geometry": {"coordinates":[-112.15639,33.57222],"type":"Point"}
}