{
  "type": "Feature",
  "properties": {
    "addr:full":"405 W Tortolita Mountain Cir Oro Valley AZ 85755",
    "addr:housenumber":"405",
    "addr:postcode":"85755",
    "addr:street":"W Tortolita Mountain Cir",
    "iso:country":"US",
    "sg:address":"405 W Tortolita Mountain Cir",
    "sg:city":"Oro Valley",
    "sg:classifiers":[
        {
            "category":"Sports & Exercise",
            "subcategory":"Golf",
            "type":"Entertainment"
        }
    ],
    "sg:phone":"+1 520 219 9000",
    "sg:postcode":"85755",
    "sg:province":"AZ",
    "wof:name":"Stone Canyon",
    "wof:placetype":"venue"
},
  "geometry": {"coordinates":[-110.97872099999999,32.472285],"type":"Point"}
}