{
  "type": "Feature",
  "properties": {
    "addr:full":"2345 N 34th Dr Phoenix AZ 85009",
    "addr:housenumber":"2345",
    "addr:postcode":"85009",
    "addr:street":"N 34Th Dr",
    "iso:country":"US",
    "sg:address":"2345 N 34th Dr",
    "sg:city":"Phoenix",
    "sg:classifiers":[
        {
            "category":"Building & Trades",
            "subcategory":"Construction",
            "type":"Services"
        }
    ],
    "sg:phone":"+1 602 269 5801",
    "sg:postcode":"85009",
    "sg:province":"AZ",
    "sg:tags":[
        "nonresidential",
        "contract",
        "real estate",
        "manufacturing"
    ],
    "sg:website":"http://www.marzee.com",
    "wof:name":"Marzee Inc",
    "wof:placetype":"venue"
},
  "geometry": {"coordinates":[-112.132847,33.47419],"type":"Point"}
}