{
  "type": "Feature",
  "properties": {
    "addr:full":"25851 S Power Rd Queen Creek AZ 85242",
    "addr:housenumber":"25851",
    "addr:postcode":"85242",
    "addr:street":"S Power Rd",
    "iso:country":"US",
    "sg:address":"25851 S Power Rd",
    "sg:city":"Queen Creek",
    "sg:classifiers":[
        {
            "category":"Food & Beverages",
            "subcategory":"Groceries & Convenience Stores",
            "type":"Retail Goods"
        }
    ],
    "sg:phone":"+1 480 988 2016",
    "sg:postcode":"85242",
    "sg:province":"AZ",
    "sg:tags":[
        "grocer"
    ],
    "wof:name":"Diamond Dot Market",
    "wof:placetype":"venue"
},
  "geometry": {"coordinates":[-111.68595500000001,33.214863],"type":"Point"}
}