{
  "type": "Feature",
  "properties": {
    "iso:country":"US",
    "sg:address":"1201 Iron Springs Rd",
    "sg:city":"Prescott",
    "sg:classifiers":[
        {
            "category":"Shopping",
            "subcategory":"Used Merchandise",
            "type":"Retail Goods"
        },
        {
            "category":"Shopping",
            "subcategory":"Clothing, Apparel, & Fashions",
            "type":"Retail Goods"
        }
    ],
    "sg:phone":"+1 928 717 9349",
    "sg:postcode":"86305",
    "sg:province":"AZ",
    "wof:name":"Lucky You Boutique",
    "wof:placetype":"venue"
},
  "geometry": {"coordinates":[-112.486619,34.561745],"type":"Point"}
}