{
  "type": "Feature",
  "properties": {
    "iso:country":"US",
    "sg:address":"710 N Beaver St",
    "sg:city":"Flagstaff",
    "sg:classifiers":[
        {
            "category":"Health Services",
            "subcategory":"Doctor",
            "type":"Services"
        }
    ],
    "sg:phone":"+1 928 774 0181",
    "sg:postcode":"86001",
    "sg:province":"AZ",
    "sg:tags":[
        "dentist"
    ],
    "wof:name":"Richard D Nelson LTD",
    "wof:placetype":"venue"
},
  "geometry": {"coordinates":[-111.64675800000001,35.205157],"type":"Point"}
}