{
  "type": "Feature",
  "properties": {
    "iso:country":"US",
    "sg:address":"4851 N 81st Dr",
    "sg:city":"Phoenix",
    "sg:classifiers":[
        {
            "category":"Building & Trades",
            "subcategory":"Locksmith",
            "type":"Services"
        }
    ],
    "sg:phone":"+1 623 476 3866",
    "sg:postcode":"85033",
    "sg:province":"AZ",
    "sg:tags":[
        "key"
    ],
    "wof:name":"A 1 2 3 24 Hour A Locksmith",
    "wof:placetype":"venue"
},
  "geometry": {"coordinates":[-112.234854,33.508517],"type":"Point"}
}