{
  "type": "Feature",
  "properties": {
    "iso:country":"US",
    "sg:address":"3830 W Pinnacle Peak Rd Ste 105",
    "sg:city":"Phoenix",
    "sg:classifiers":[
        {
            "category":"Arts & Performance",
            "subcategory":"Dance",
            "type":"Entertainment"
        }
    ],
    "sg:phone":"+1 623 869 6551",
    "sg:postcode":"85027",
    "sg:province":"AZ",
    "sg:tags":[
        "instruction",
        "dancing"
    ],
    "sg:website":"http://www.michaelasdancemagic.com",
    "wof:name":"Michaela's Dance Magic",
    "wof:placetype":"venue"
},
  "geometry": {"coordinates":[-112.095539,33.698254],"type":"Point"}
}