{
  "type": "Feature",
  "properties": {
    "addr:full":"7090 Bullion Hill Rd Flagstaff AZ 86004",
    "addr:housenumber":"7090",
    "addr:postcode":"86004",
    "addr:street":"Bullion Hill Rd",
    "iso:country":"US",
    "sg:address":"7090 Bullion Hill Rd",
    "sg:city":"Flagstaff",
    "sg:classifiers":[
        {
            "category":"Manufacturing",
            "subcategory":"Signs",
            "type":"Manufacturing & Wholesale Goods"
        }
    ],
    "sg:phone":"+1 928 526 9259",
    "sg:postcode":"86004",
    "sg:province":"AZ",
    "wof:name":"Sign Shop",
    "wof:placetype":"venue"
},
  "geometry": {"coordinates":[-111.505324,35.246216],"type":"Point"}
}