{
  "type": "Feature",
  "properties": {
    "iso:country":"US",
    "sg:address":"399 S Malpais Ln",
    "sg:city":"Flagstaff",
    "sg:classifiers":[
        {
            "category":"Freight",
            "type":"Transportation"
        }
    ],
    "sg:phone":"+1 928 774 4573",
    "sg:postcode":"86001",
    "sg:province":"AZ",
    "sg:tags":[
        "operator",
        "local",
        "trucking"
    ],
    "wof:name":"Greyhound Bus Lines",
    "wof:placetype":"venue"
},
  "geometry": {"coordinates":[-111.657318,35.194759],"type":"Point"}
}