{
  "type": "Feature",
  "properties": {
    "addr:full":"6530 W Indian School Road Phoenix AZ 85033",
    "addr:housenumber":"6530",
    "addr:postcode":"85033",
    "addr:street":"W Indian School Road",
    "iso:country":"US",
    "sg:address":"6530 W Indian School Road",
    "sg:city":"Phoenix",
    "sg:classifiers":[
        {
            "category":"Retail",
            "subcategory":"Veterinary Services",
            "type":"Services"
        }
    ],
    "sg:phone":"+1 623 432 1599",
    "sg:postcode":"85033",
    "sg:province":"AZ",
    "sg:tags":[
        "veterinarian"
    ],
    "sg:website":"www.vcaphoenixwest.com",
    "wof:name":"VCA Phoenix West Animal Hospital",
    "wof:placetype":"venue"
},
  "geometry": {"coordinates":[-112.201387,33.495434],"type":"Point"}
}