{
  "type": "Feature",
  "properties": {
    "iso:country":"US",
    "sg:address":"5630 N Abington Rd",
    "sg:city":"Tucson",
    "sg:classifiers":[
        {
            "category":"Retail",
            "subcategory":"Animal Services",
            "type":"Services"
        }
    ],
    "sg:phone":"+1 520 743 3117",
    "sg:postcode":"85743",
    "sg:province":"AZ",
    "wof:name":"Kennel Nirvana",
    "wof:placetype":"venue"
},
  "geometry": {"coordinates":[-111.10178,32.310656],"type":"Point"}
}