{
  "type": "Feature",
  "properties": {
    "addr:full":"2323 N Campbell Ave Tucson AZ 85719",
    "addr:housenumber":"2323",
    "addr:postcode":"85719",
    "addr:street":"N Campbell Ave",
    "iso:country":"US",
    "sg:address":"2323 N Campbell Ave",
    "sg:city":"Tucson",
    "sg:classifiers":[
        {
            "category":"Professional",
            "subcategory":"Lawyer & Legal Services",
            "type":"Services"
        }
    ],
    "sg:phone":"+1 520 620 3935",
    "sg:postcode":"85719",
    "sg:province":"AZ",
    "sg:tags":[
        "attorney"
    ],
    "wof:name":"Goldberg & Osborne",
    "wof:placetype":"venue"
},
  "geometry": {"coordinates":[-110.94417799999999,32.249947],"type":"Point"}
}