{
  "type": "Feature",
  "properties": {
    "iso:country":"US",
    "sg:address":"2825 E Gemini St",
    "sg:city":"Gilbert",
    "sg:classifiers":[
        {
            "category":"Building & Trades",
            "subcategory":"Construction",
            "type":"Services"
        }
    ],
    "sg:phone":"+1 480 557 7014",
    "sg:postcode":"85234",
    "sg:province":"AZ",
    "sg:tags":[
        "concrete-stamped",
        "decorative",
        "contractor",
        "paving",
        "pool",
        "swimming"
    ],
    "sg:website":"http://www.sierradeck.com",
    "wof:name":"Sierra Deck",
    "wof:placetype":"venue"
},
  "geometry": {"coordinates":[-111.730486,33.370326],"type":"Point"}
}