{
  "type": "Feature",
  "properties": {
    "iso:country":"US",
    "sg:address":"805 N 4th Ave Unit 302",
    "sg:city":"Phoenix",
    "sg:classifiers":[
        {
            "category":"Professional",
            "subcategory":"Art Services",
            "type":"Services"
        }
    ],
    "sg:phone":"+1 602 434 8911",
    "sg:postcode":"85003",
    "sg:province":"AZ",
    "sg:tags":[
        "designer",
        "display",
        "producer"
    ],
    "wof:name":"Jm Design Company",
    "wof:placetype":"venue"
},
  "geometry": {"coordinates":[-112.078941,33.456761],"type":"Point"}
}