{
  "type": "Feature",
  "properties": {
    "iso:country":"US",
    "sg:address":"7206 N 55th Ave",
    "sg:city":"Glendale",
    "sg:classifiers":[
        {
            "category":"Professional",
            "subcategory":"Research",
            "type":"Services"
        }
    ],
    "sg:phone":"+1 623 847 0157",
    "sg:postcode":"85301",
    "sg:province":"AZ",
    "sg:tags":[
        "environmental",
        "ecological"
    ],
    "wof:name":"J M Huber & Assoc",
    "wof:placetype":"venue"
},
  "geometry": {"coordinates":[-112.177464,33.542899],"type":"Point"}
}