{
  "type": "Feature",
  "properties": {
    "addr:full":"3800 S Clubhouse Dr Chandler AZ 85248",
    "addr:housenumber":"3800",
    "addr:postcode":"85248",
    "addr:street":"S Clubhouse Dr",
    "iso:country":"US",
    "sg:address":"3800 S Clubhouse Dr",
    "sg:city":"Chandler",
    "sg:classifiers":[
        {
            "category":"Building & Trades",
            "subcategory":"Electrical",
            "type":"Services"
        }
    ],
    "sg:phone":"+1 480 855 1145",
    "sg:postcode":"85248",
    "sg:province":"AZ",
    "sg:tags":[
        "electrician"
    ],
    "wof:name":"Tucson Electric Power",
    "wof:placetype":"venue"
},
  "geometry": {"coordinates":[-111.87139500000001,33.249069],"type":"Point"}
}