{
  "type": "Feature",
  "properties": {
    "iso:country":"US",
    "sg:address":"19509 N Sunrise Blvd",
    "sg:city":"Surprise",
    "sg:classifiers":[
        {
            "category":"Banks & Credit Unions",
            "subcategory":"Investment Brokerage",
            "type":"Services"
        }
    ],
    "sg:phone":"+1 623 584 0929",
    "sg:postcode":"85374",
    "sg:province":"AZ",
    "sg:tags":[
        "security"
    ],
    "wof:name":"Edward Jones 23824",
    "wof:placetype":"venue"
},
  "geometry": {"coordinates":[-112.404385,33.654696],"type":"Point"}
}