{
  "type": "Feature",
  "properties": {
    "iso:country":"US",
    "sg:address":"5130 E Broadway Blvd",
    "sg:city":"Tucson",
    "sg:classifiers":[
        {
            "category":"Shopping",
            "subcategory":"Books",
            "type":"Retail Goods"
        }
    ],
    "sg:phone":"+1 520 512 1166",
    "sg:postcode":"85711",
    "sg:province":"AZ",
    "sg:tags":[
        "dealer"
    ],
    "wof:name":"Barnes & Noble Booksellers",
    "wof:placetype":"venue"
},
  "geometry": {"coordinates":[-110.88279300000001,32.221599],"type":"Point"}
}