{
  "type": "Feature",
  "properties": {
    "iso:country":"US",
    "sg:address":"5225 Hwy 95",
    "sg:city":"Fort Mohave",
    "sg:classifiers":[
        {
            "category":"Shopping",
            "subcategory":"Stationery & Office Supplies",
            "type":"Retail Goods"
        },
        {
            "category":"Wholesale",
            "subcategory":"Stationery",
            "type":"Manufacturing & Wholesale Goods"
        }
    ],
    "sg:phone":"+1 928 788 1995",
    "sg:postcode":"86426",
    "sg:province":"AZ",
    "sg:tags":[
        "school",
        "store"
    ],
    "wof:name":"School Adventures",
    "wof:placetype":"venue"
},
  "geometry": {"coordinates":[-114.598142,35.004574],"type":"Point"}
}