{
  "type": "Feature",
  "properties": {
    "iso:country":"US",
    "sg:address":"1201 Jagerson Ave",
    "sg:city":"Kingman",
    "sg:classifiers":[
        {
            "category":"Home & Garden",
            "subcategory":"Mobile Homes",
            "type":"Retail Goods"
        }
    ],
    "sg:phone":"+1 928 681 3771",
    "sg:postcode":"86409",
    "sg:province":"AZ",
    "wof:name":"Riverwest Homes",
    "wof:placetype":"venue"
},
  "geometry": {"coordinates":[-114.038761,35.268413],"type":"Point"}
}