{
  "type": "Feature",
  "properties": {
    "iso:country":"US",
    "sg:address":"1420 N Greenfield Rd",
    "sg:city":"Gilbert",
    "sg:classifiers":[
        {
            "category":"Farming",
            "subcategory":"Farm & Veterinary Services",
            "type":"Manufacturing & Wholesale Goods"
        }
    ],
    "sg:phone":"+1 480 481 0682",
    "sg:postcode":"85234",
    "sg:province":"AZ",
    "sg:tags":[
        "consultant",
        "irrigation"
    ],
    "wof:name":"Coates Irrigation Consultants",
    "wof:placetype":"venue"
},
  "geometry": {"coordinates":[-111.739545,33.375599],"type":"Point"}
}