{
  "type": "Feature",
  "properties": {
    "iso:country":"US",
    "sg:address":"4515 S Lakeshore Dr Ste 104",
    "sg:city":"Tempe",
    "sg:classifiers":[
        {
            "category":"Real Estate",
            "subcategory":"Surveying",
            "type":"Services"
        }
    ],
    "sg:phone":"+1 480 345 1990",
    "sg:postcode":"85282",
    "sg:province":"AZ",
    "sg:tags":[
        "appraiser"
    ],
    "wof:name":"A Z Home Valuations",
    "wof:placetype":"venue"
},
  "geometry": {"coordinates":[-111.926466,33.382227],"type":"Point"}
}