{
  "type": "Feature",
  "properties": {
    "iso:country":"US",
    "sg:address":"1530 S Parkcrest Cir",
    "sg:city":"Mesa",
    "sg:classifiers":[
        {
            "category":"Building & Trades",
            "subcategory":"Plumbing",
            "type":"Services"
        }
    ],
    "sg:phone":"+1 480 985 5912",
    "sg:postcode":"85206",
    "sg:province":"AZ",
    "sg:tags":[
        "contractor"
    ],
    "wof:name":"Easters Plumbing",
    "wof:placetype":"venue"
},
  "geometry": {"coordinates":[-111.733929,33.388805],"type":"Point"}
}