{
  "type": "Feature",
  "properties": {
    "addr:full":"988 W Ebony Dr Chandler AZ 85248",
    "addr:housenumber":"988",
    "addr:postcode":"85248",
    "addr:street":"W Ebony Dr",
    "iso:country":"US",
    "sg:address":"988 W Ebony Dr",
    "sg:city":"Chandler",
    "sg:classifiers":[
        {
            "category":"Banks & Credit Unions",
            "subcategory":"Investment Brokerage",
            "type":"Services"
        }
    ],
    "sg:phone":"+1 480 659 8029",
    "sg:postcode":"85248",
    "sg:province":"AZ",
    "sg:tags":[
        "security"
    ],
    "wof:name":"Edward Jones 23712",
    "wof:placetype":"venue"
},
  "geometry": {"coordinates":[-111.863078,33.248593],"type":"Point"}
}