{
  "type": "Feature",
  "properties": {
    "iso:country":"US",
    "sg:address":"7805 E Paloma Ave",
    "sg:city":"Mesa",
    "sg:classifiers":[
        {
            "category":"Building & Trades",
            "subcategory":"Construction",
            "type":"Services"
        }
    ],
    "sg:phone":"+1 480 987 5000",
    "sg:postcode":"85212",
    "sg:province":"AZ",
    "sg:tags":[
        "home",
        "builder"
    ],
    "wof:name":"Mateo Inc",
    "wof:placetype":"venue"
},
  "geometry": {"coordinates":[-111.663698,33.357581],"type":"Point"}
}