{
  "type": "Feature",
  "properties": {
    "iso:country":"US",
    "sg:address":"1101 E Bell Rd",
    "sg:city":"Phoenix",
    "sg:classifiers":[
        {
            "category":"Building & Trades",
            "subcategory":"Landscaping Services",
            "type":"Services"
        }
    ],
    "sg:phone":"+1 602 795 7719",
    "sg:postcode":"85022",
    "sg:province":"AZ",
    "sg:tags":[
        "landscape",
        "contractor"
    ],
    "wof:name":"J C's Landscaping",
    "wof:placetype":"venue"
},
  "geometry": {"coordinates":[-112.059485,33.640247],"type":"Point"}
}