{
  "type": "Feature",
  "properties": {
    "iso:country":"US",
    "sg:address":"2732 N Alvernon Way",
    "sg:city":"Tucson",
    "sg:classifiers":[
        {
            "category":"Health Services",
            "subcategory":"Doctor",
            "type":"Services"
        }
    ],
    "sg:phone":"+1 520 382 3330",
    "sg:postcode":"85712",
    "sg:province":"AZ",
    "sg:tags":[
        "physician",
        "surgeon"
    ],
    "sg:website":"www.clearskindoctor.com",
    "wof:name":"Specialists In Dermatology",
    "wof:placetype":"venue"
},
  "geometry": {"coordinates":[-110.909707,32.257632],"type":"Point"}
}