{
  "type": "Feature",
  "properties": {
    "addr:full":"937 E Broadway Rd Ste 7 Tempe AZ 85282",
    "addr:housenumber":"937",
    "addr:postcode":"85282",
    "addr:street":"E Broadway Rd Ste 7",
    "iso:country":"US",
    "sg:address":"937 E Broadway Rd Ste 7",
    "sg:city":"Tempe",
    "sg:classifiers":[
        {
            "category":"Shopping",
            "subcategory":"Clothing, Apparel, & Fashions",
            "type":"Retail Goods"
        },
        {
            "category":"Shopping",
            "subcategory":"Bicycles & Sporting Goods",
            "type":"Retail Goods"
        }
    ],
    "sg:phone":"+1 480 929 9600",
    "sg:postcode":"85282",
    "sg:province":"AZ",
    "sg:tags":[
        "racing",
        "sportswear",
        "store",
        "apparel",
        "clothing",
        "merchandise"
    ],
    "wof:name":"Baum's Sporting Goods",
    "wof:placetype":"venue"
},
  "geometry": {"coordinates":[-111.926135,33.407471],"type":"Point"}
}