{
  "type": "Feature",
  "properties": {
    "iso:country":"US",
    "sg:address":"1944 Acoma Blvd W",
    "sg:city":"Lake Havasu City",
    "sg:classifiers":[
        {
            "category":"Autos & Motor Vehicles",
            "subcategory":"Auto Supplies",
            "type":"Retail Goods"
        }
    ],
    "sg:phone":"+1 928 680 8646",
    "sg:postcode":"86403",
    "sg:province":"AZ",
    "sg:tags":[
        "alternator",
        "generator"
    ],
    "wof:name":"Alternator Specialties Auto",
    "wof:placetype":"venue"
},
  "geometry": {"coordinates":[-114.344347,34.496053],"type":"Point"}
}