{
  "type": "Feature",
  "properties": {
    "addr:full":"10685 S Fortuna Rd Yuma AZ 85367",
    "addr:housenumber":"10685",
    "addr:postcode":"85367",
    "addr:street":"S Fortuna Rd",
    "iso:country":"US",
    "sg:address":"10685 S Fortuna Rd",
    "sg:city":"Yuma",
    "sg:classifiers":[
        {
            "category":"Restaurant",
            "type":"Food & Drink"
        }
    ],
    "sg:menulink":"http://www.allmenus.com/az/yuma/180322-jack-in-the-box/menu/",
    "sg:phone":"+1 928 305 1901",
    "sg:postcode":"85367",
    "sg:province":"AZ",
    "sg:tags":[
        "burger",
        "american"
    ],
    "wof:name":"Jack in the Box",
    "wof:placetype":"venue"
},
  "geometry": {"coordinates":[-114.444112,32.677523],"type":"Point"}
}