{
  "type": "Feature",
  "properties": {
    "iso:country":"US",
    "sg:address":"5111 N Scottsdale Rd # 206",
    "sg:city":"Scottsdale",
    "sg:classifiers":[
        {
            "category":"Manufacturing",
            "subcategory":"Tools & Machinery",
            "type":"Manufacturing & Wholesale Goods"
        }
    ],
    "sg:phone":"+1 480 344 1020",
    "sg:postcode":"85250",
    "sg:province":"AZ",
    "sg:tags":[
        "hand"
    ],
    "sg:website":"http://www.woodworkerssource.net",
    "wof:name":"Woodworkers Source",
    "wof:placetype":"venue"
},
  "geometry": {"coordinates":[-111.925972,33.511471],"type":"Point"}
}