{
  "type": "Feature",
  "properties": {
    "iso:country":"US",
    "sg:address":"3503 E Kristal Way",
    "sg:city":"Phoenix",
    "sg:classifiers":[
        {
            "category":"Professional",
            "subcategory":"Accounting & Tax Preparation",
            "type":"Services"
        }
    ],
    "sg:phone":"+1 602 569 3303",
    "sg:postcode":"85050",
    "sg:province":"AZ",
    "sg:tags":[
        "accountant"
    ],
    "wof:name":"Walter Kleinstein",
    "wof:placetype":"venue"
},
  "geometry": {"coordinates":[-112.007116,33.66157],"type":"Point"}
}