{
  "type": "Feature",
  "properties": {
    "addr:full":"6727 W Peoria Ave Peoria AZ 85345",
    "addr:housenumber":"6727",
    "addr:postcode":"85345",
    "addr:street":"W Peoria Ave",
    "iso:country":"US",
    "sg:address":"6727 W Peoria Ave",
    "sg:city":"Peoria",
    "sg:classifiers":[
        {
            "category":"Banks & Credit Unions",
            "subcategory":"Financial Services",
            "type":"Services"
        }
    ],
    "sg:phone":"+1 623 776 1000",
    "sg:postcode":"85345",
    "sg:province":"AZ",
    "sg:tags":[
        "loan",
        "plan"
    ],
    "wof:name":"Checkmate",
    "wof:placetype":"venue"
},
  "geometry": {"coordinates":[-112.203391,33.581622],"type":"Point"}
}