{
  "type": "Feature",
  "properties": {
    "iso:country":"US",
    "sg:address":"37 S Val Vista Dr",
    "sg:city":"Gilbert",
    "sg:classifiers":[
        {
            "category":"Food & Beverages",
            "subcategory":"Groceries & Convenience Stores",
            "type":"Retail Goods"
        }
    ],
    "sg:phone":"+1 480 632 1625",
    "sg:postcode":"85296",
    "sg:province":"AZ",
    "wof:name":"Conocophillips Company",
    "wof:placetype":"venue"
},
  "geometry": {"coordinates":[-111.75560900000001,33.348678],"type":"Point"}
}