{
  "type": "Feature",
  "properties": {
    "iso:country":"US",
    "sg:address":"3126 N Scottsdale Rd",
    "sg:city":"Scottsdale",
    "sg:classifiers":[
        {
            "category":"Wholesale",
            "subcategory":"Office Equipment",
            "type":"Manufacturing & Wholesale Goods"
        },
        {
            "category":"Professional",
            "subcategory":"Printing & Photocopies",
            "type":"Services"
        },
        {
            "category":"Shopping",
            "subcategory":"Computers & Home Electronics",
            "type":"Retail Goods"
        }
    ],
    "sg:phone":"+1 480 994 5520",
    "sg:postcode":"85251",
    "sg:province":"AZ",
    "sg:tags":[
        "scanning",
        "printer",
        "supply",
        "duplicating",
        "copying",
        "plotting"
    ],
    "sg:website":"http://www.thomasrepro.com",
    "wof:name":"Thomas Reprographics, Inc",
    "wof:placetype":"venue"
},
  "geometry": {"coordinates":[-111.926163,33.483637],"type":"Point"}
}