{
  "type": "Feature",
  "properties": {
    "iso:country":"US",
    "sg:address":"3139 W Anderson Dr",
    "sg:city":"Phoenix",
    "sg:classifiers":[
        {
            "category":"Real Estate",
            "subcategory":"Real Estate Agent",
            "type":"Services"
        }
    ],
    "sg:phone":"+1 602 993 4198",
    "sg:postcode":"85053",
    "sg:province":"AZ",
    "wof:name":"Atkinson Richard & Leta",
    "wof:placetype":"venue"
},
  "geometry": {"coordinates":[-112.12701,33.643652],"type":"Point"}
}