{
  "type": "Feature",
  "properties": {
    "addr:full":"3141 S McClintock Dr Tempe AZ 85282",
    "addr:housenumber":"3141",
    "addr:postcode":"85282",
    "addr:street":"S Mcclintock Dr",
    "iso:country":"US",
    "sg:address":"3141 S McClintock Dr",
    "sg:city":"Tempe",
    "sg:classifiers":[
        {
            "category":"Banks & Credit Unions",
            "subcategory":"Bank",
            "type":"Services"
        }
    ],
    "sg:phone":"+1 480 491 6703",
    "sg:postcode":"85282",
    "sg:province":"AZ",
    "sg:tags":[
        "financing"
    ],
    "wof:name":"Citi Financial",
    "wof:placetype":"venue"
},
  "geometry": {"coordinates":[-111.909046,33.394953],"type":"Point"}
}