{
  "type": "Feature",
  "properties": {
    "iso:country":"US",
    "sg:address":"2846 E Nora St",
    "sg:city":"Mesa",
    "sg:classifiers":[
        {
            "category":"Professional",
            "subcategory":"Computer Services",
            "type":"Services"
        }
    ],
    "sg:phone":"+1 602 750 4556",
    "sg:postcode":"85213",
    "sg:province":"AZ",
    "sg:tags":[
        "publisher",
        "designer",
        "consultant",
        "system",
        "software",
        "developer"
    ],
    "wof:name":"School Webmasters",
    "wof:placetype":"venue"
},
  "geometry": {"coordinates":[-111.768968,33.465848],"type":"Point"}
}