{
  "type": "Feature",
  "properties": {
    "iso:country":"US",
    "sg:address":"312 Marketplace Dr",
    "sg:city":"Chino Valley",
    "sg:classifiers":[
        {
            "category":"Restaurant",
            "type":"Food & Drink"
        }
    ],
    "sg:menulink":"http://www.allmenus.com/az/prescott/74711-pizza-hut/menu/",
    "sg:phone":"+1 928 636 6400",
    "sg:postcode":"86323",
    "sg:province":"AZ",
    "sg:tags":[
        "american",
        "pizza"
    ],
    "wof:name":"Pizza Hut",
    "wof:placetype":"venue"
},
  "geometry": {"coordinates":[-112.45424,34.768712],"type":"Point"}
}