{
  "type": "Feature",
  "properties": {
    "iso:country":"US",
    "sg:address":"800 W Main St",
    "sg:city":"Safford",
    "sg:classifiers":[
        {
            "category":"Government",
            "subcategory":"Office",
            "type":"Public Place"
        }
    ],
    "sg:phone":"+1 928 428 3250",
    "sg:postcode":"85546",
    "sg:province":"AZ",
    "sg:tags":[
        "executive"
    ],
    "wof:name":"Court House",
    "wof:placetype":"venue"
},
  "geometry": {"coordinates":[-109.716963,32.833309],"type":"Point"}
}