{
  "type": "Feature",
  "properties": {
    "iso:country":"US",
    "sg:address":"126 N Marina St",
    "sg:city":"Prescott",
    "sg:classifiers":[
        {
            "category":"Real Estate",
            "subcategory":"Real Estate Services",
            "type":"Services"
        },
        {
            "category":"Professional",
            "subcategory":"Business Services",
            "type":"Services"
        },
        {
            "category":"Real Estate",
            "subcategory":"Real Estate Agent",
            "type":"Services"
        }
    ],
    "sg:phone":"+1 928 443 5966",
    "sg:postcode":"86301",
    "sg:province":"AZ",
    "sg:tags":[
        "auction",
        "buyer",
        "broker"
    ],
    "wof:name":"Russ Lyon Realty",
    "wof:placetype":"venue"
},
  "geometry": {"coordinates":[-112.467309,34.542034],"type":"Point"}
}