{
  "type": "Feature",
  "properties": {
    "iso:country":"US",
    "sg:address":"14620 N 150th Ave",
    "sg:city":"Surprise",
    "sg:classifiers":[
        {
            "category":"Professional",
            "subcategory":"Management & Consulting",
            "type":"Services"
        }
    ],
    "sg:phone":"+1 623 214 7950",
    "sg:postcode":"85379",
    "sg:province":"AZ",
    "sg:tags":[
        "retail",
        "direct",
        "sales"
    ],
    "wof:name":"Two Poor Guys LLC",
    "wof:placetype":"venue"
},
  "geometry": {"coordinates":[-112.384137,33.617163],"type":"Point"}
}