{
  "type": "Feature",
  "properties": {
    "iso:country":"US",
    "sg:address":"2551 S Cliffview St",
    "sg:city":"Flagstaff",
    "sg:classifiers":[
        {
            "category":"Home & Garden",
            "subcategory":"Furniture",
            "type":"Retail Goods"
        }
    ],
    "sg:phone":"+1 928 779 2345",
    "sg:postcode":"86001",
    "sg:province":"AZ",
    "sg:tags":[
        "cabinet"
    ],
    "wof:name":"TGB Woodworks",
    "wof:placetype":"venue"
},
  "geometry": {"coordinates":[-111.672644,35.178265],"type":"Point"}
}