{
  "type": "Feature",
  "properties": {
    "iso:country":"US",
    "sg:address":"102 W Main St",
    "sg:city":"Payson",
    "sg:classifiers":[
        {
            "category":"Manufacturing",
            "subcategory":"Buildings",
            "type":"Manufacturing & Wholesale Goods"
        }
    ],
    "sg:phone":"+1 928 474 9213",
    "sg:postcode":"85541",
    "sg:province":"AZ",
    "sg:tags":[
        "home",
        "log",
        "cabin"
    ],
    "wof:name":"Classic Cabins",
    "wof:placetype":"venue"
},
  "geometry": {"coordinates":[-111.325877,34.231112],"type":"Point"}
}