{
  "type": "Feature",
  "properties": {
    "iso:country":"US",
    "sg:address":"1001 W Magee Rd",
    "sg:city":"Tucson",
    "sg:classifiers":[
        {
            "category":"Wholesale",
            "subcategory":"Machinery & Supplies",
            "type":"Manufacturing & Wholesale Goods"
        }
    ],
    "sg:phone":"+1 520 575 8747",
    "sg:postcode":"85704",
    "sg:province":"AZ",
    "sg:tags":[
        "equipment",
        "mining"
    ],
    "wof:name":"Arizona Mine & Mill Equipment",
    "wof:placetype":"venue"
},
  "geometry": {"coordinates":[-110.983074,32.351708],"type":"Point"}
}