{
  "type": "Feature",
  "properties": {
    "addr:full":"240 E Marapai Rd Prescott AZ 86303",
    "addr:housenumber":"240",
    "addr:postcode":"86303",
    "addr:street":"E Marapai Rd",
    "iso:country":"US",
    "sg:address":"240 E Marapai Rd",
    "sg:city":"Prescott",
    "sg:classifiers":[
        {
            "category":"Building & Trades",
            "subcategory":"Construction",
            "type":"Services"
        }
    ],
    "sg:phone":"+1 928 777 0868",
    "sg:postcode":"86303",
    "sg:province":"AZ",
    "sg:tags":[
        "house"
    ],
    "wof:name":"Dreamcatcher Homes LLC",
    "wof:placetype":"venue"
},
  "geometry": {"coordinates":[-112.45958400000001,34.476235],"type":"Point"}
}