{
  "type": "Feature",
  "properties": {
    "iso:country":"US",
    "sg:address":"7150 N 27th Ave",
    "sg:city":"Phoenix",
    "sg:classifiers":[
        {
            "category":"Real Estate",
            "subcategory":"Real Estate Operator",
            "type":"Services"
        }
    ],
    "sg:phone":"+1 602 864 3484",
    "sg:postcode":"85051",
    "sg:province":"AZ",
    "sg:tags":[
        "apartment"
    ],
    "wof:name":"Glen Vista Apartments",
    "wof:placetype":"venue"
},
  "geometry": {"coordinates":[-112.116989,33.539451],"type":"Point"}
}