{
  "type": "Feature",
  "properties": {
    "addr:full":"12778 N 130th Pl Scottsdale AZ 85259",
    "addr:housenumber":"12778",
    "addr:postcode":"85259",
    "addr:street":"N 130Th Pl",
    "iso:country":"US",
    "sg:address":"12778 N 130th Pl",
    "sg:city":"Scottsdale",
    "sg:classifiers":[
        {
            "category":"Manufacturing",
            "subcategory":"Food",
            "type":"Manufacturing & Wholesale Goods"
        }
    ],
    "sg:phone":"+1 480 419 9936",
    "sg:postcode":"85259",
    "sg:province":"AZ",
    "sg:tags":[
        "mfg"
    ],
    "wof:name":"Wild Noodle",
    "wof:placetype":"venue"
},
  "geometry": {"coordinates":[-111.799667,33.602637],"type":"Point"}
}