{
  "type": "Feature",
  "properties": {
    "iso:country":"US",
    "sg:address":"7305 S Kyrene Rd",
    "sg:city":"Tempe",
    "sg:classifiers":[
        {
            "category":"Shopping",
            "subcategory":"Gifts & Souvenirs",
            "type":"Retail Goods"
        }
    ],
    "sg:phone":"+1 480 755 3313",
    "sg:postcode":"85283",
    "sg:province":"AZ",
    "wof:name":"Dos Amgos Mxican Imports L L C",
    "wof:placetype":"venue"
},
  "geometry": {"coordinates":[-111.945832,33.35483],"type":"Point"}
}