{
  "type": "Feature",
  "properties": {
    "addr:full":"8918 W Cypress St Phoenix AZ 85037",
    "addr:housenumber":"8918",
    "addr:postcode":"85037",
    "addr:street":"W Cypress St",
    "iso:country":"US",
    "sg:address":"8918 W Cypress St",
    "sg:city":"Phoenix",
    "sg:classifiers":[
        {
            "category":"Building & Trades",
            "subcategory":"Locksmith",
            "type":"Services"
        }
    ],
    "sg:phone":"+1 602 357 6616",
    "sg:postcode":"85037",
    "sg:province":"AZ",
    "sg:tags":[
        "key"
    ],
    "wof:name":"Locksmith 24 Hour",
    "wof:placetype":"venue"
},
  "geometry": {"coordinates":[-112.251046,33.471863],"type":"Point"}
}