{
  "type": "Feature",
  "properties": {
    "iso:country":"US",
    "sg:address":"2019 W Quail Ave",
    "sg:city":"Phoenix",
    "sg:classifiers":[
        {
            "category":"Manufacturing",
            "subcategory":"Leather Goods",
            "type":"Manufacturing & Wholesale Goods"
        }
    ],
    "sg:phone":"+1 623 581 8181",
    "sg:postcode":"85027",
    "sg:province":"AZ",
    "sg:tags":[
        "manufacturer"
    ],
    "wof:name":"Bellatoff Luxury Leather Goods",
    "wof:placetype":"venue"
},
  "geometry": {"coordinates":[-112.103558,33.67837],"type":"Point"}
}