{
  "type": "Feature",
  "properties": {
    "iso:country":"US",
    "sg:address":"313 N 15th Ave",
    "sg:city":"Phoenix",
    "sg:classifiers":[
        {
            "category":"Real Estate",
            "subcategory":"Real Estate Operator",
            "type":"Services"
        }
    ],
    "sg:phone":"+1 602 218 6310",
    "sg:postcode":"85007",
    "sg:province":"AZ",
    "sg:tags":[
        "apartment"
    ],
    "wof:name":"Dakota Apartments",
    "wof:placetype":"venue"
},
  "geometry": {"coordinates":[-112.091307,33.451397],"type":"Point"}
}