{
  "type": "Feature",
  "properties": {
    "iso:country":"US",
    "sg:address":"491 N Broad St",
    "sg:city":"Globe",
    "sg:classifiers":[
        {
            "category":"Autos & Motor Vehicles",
            "subcategory":"Auto Supplies",
            "type":"Retail Goods"
        },
        {
            "category":"Retail",
            "subcategory":"Auto Repair",
            "type":"Services"
        }
    ],
    "sg:phone":"+1 928 425 4414",
    "sg:postcode":"85501",
    "sg:province":"AZ",
    "sg:tags":[
        "engines-rebuild",
        "automobile",
        "part",
        "accessory",
        "exchange"
    ],
    "sg:website":"http://www.cskauto.com",
    "wof:name":"Checker Auto Parts",
    "wof:placetype":"venue"
},
  "geometry": {"coordinates":[-110.789069,33.399796],"type":"Point"}
}