{
  "type": "Feature",
  "properties": {
    "iso:country":"US",
    "sg:address":"431 W Coolidge Ave",
    "sg:city":"Coolidge",
    "sg:classifiers":[
        {
            "category":"Professional",
            "type":"Services"
        }
    ],
    "sg:phone":"+1 520 723 5555",
    "sg:postcode":"85228",
    "sg:province":"AZ",
    "wof:name":"Amies Touch of Class",
    "wof:placetype":"venue"
},
  "geometry": {"coordinates":[-111.523263,32.973397],"type":"Point"}
}