{
  "type": "Feature",
  "properties": {
    "iso:country":"US",
    "sg:address":"1701 W Sequoia Dr",
    "sg:city":"Phoenix",
    "sg:classifiers":[
        {
            "category":"Wholesale",
            "subcategory":"Non-durable Goods",
            "type":"Manufacturing & Wholesale Goods"
        }
    ],
    "sg:phone":"+1 623 203 8391",
    "sg:postcode":"85027",
    "sg:province":"AZ",
    "sg:tags":[
        "dry",
        "goods-wholesale"
    ],
    "wof:name":"Peerless Supply Co",
    "wof:placetype":"venue"
},
  "geometry": {"coordinates":[-112.095322,33.663059],"type":"Point"}
}