{
  "type": "Feature",
  "properties": {
    "iso:country":"US",
    "sg:address":"16700 N Thompson Peak Pkwy",
    "sg:city":"Scottsdale",
    "sg:classifiers":[
        {
            "category":"Real Estate",
            "subcategory":"Real Estate Agent",
            "type":"Services"
        }
    ],
    "sg:phone":"+1 480 483 1238",
    "sg:postcode":"85260",
    "sg:province":"AZ",
    "sg:tags":[
        "investment"
    ],
    "wof:name":"Heinonen Associates",
    "wof:placetype":"venue"
},
  "geometry": {"coordinates":[-111.860696,33.636463],"type":"Point"}
}