{
  "type": "Feature",
  "properties": {
    "iso:country":"US",
    "sg:address":"7500 N Dreamy Draw Dr",
    "sg:city":"Phoenix",
    "sg:classifiers":[
        {
            "category":"Transit Center",
            "subcategory":"Freight",
            "type":"Transportation"
        },
        {
            "category":"Professional",
            "subcategory":"Business Services",
            "type":"Services"
        },
        {
            "category":"Taxi",
            "type":"Transportation"
        },
        {
            "category":"Government",
            "subcategory":"Post Office",
            "type":"Public Place"
        }
    ],
    "sg:phone":"+1 602 266 5227",
    "sg:postcode":"85020",
    "sg:province":"AZ",
    "sg:tags":[
        "cargo",
        "courier",
        "package",
        "express",
        "shipping",
        "air",
        "delivery",
        "mail",
        "forwarding"
    ],
    "sg:website":"http://www.federalexpress.com",
    "wof:name":"Fedex",
    "wof:placetype":"venue"
},
  "geometry": {"coordinates":[-112.042503,33.546499],"type":"Point"}
}