{
  "type": "Feature",
  "properties": {
    "iso:country":"US",
    "sg:address":"5441 E Kelton Ln",
    "sg:city":"Scottsdale",
    "sg:classifiers":[
        {
            "category":"Shopping",
            "subcategory":"Musical Instruments",
            "type":"Retail Goods"
        }
    ],
    "sg:phone":"+1 602 692 8740",
    "sg:postcode":"85254",
    "sg:province":"AZ",
    "sg:tags":[
        "piano",
        "organ"
    ],
    "wof:name":"School Of Piano And Music",
    "wof:placetype":"venue"
},
  "geometry": {"coordinates":[-111.962984,33.637374],"type":"Point"}
}