{
  "type": "Feature",
  "properties": {
    "iso:country":"US",
    "sg:address":"704 E Prince Rd",
    "sg:city":"Tucson",
    "sg:classifiers":[
        {
            "category":"Professional",
            "type":"Services"
        }
    ],
    "sg:phone":"+1 520 690 6947",
    "sg:postcode":"85719",
    "sg:province":"AZ",
    "wof:name":"Carnicieria La Nora",
    "wof:placetype":"venue"
},
  "geometry": {"coordinates":[-110.959639,32.272004],"type":"Point"}
}