{
  "type": "Feature",
  "properties": {
    "iso:country":"US",
    "sg:address":"14402 N 19th Ave",
    "sg:city":"Phoenix",
    "sg:classifiers":[
        {
            "category":"Professional",
            "subcategory":"Advertising",
            "type":"Services"
        }
    ],
    "sg:phone":"+1 888 996 6643",
    "sg:postcode":"85023",
    "sg:province":"AZ",
    "sg:tags":[
        "agency",
        "specialty"
    ],
    "sg:website":"http://phoenix.citysearch.com/profile/external/604281492/phoenix_az/advertise_at_the_top.html?publisher=yellowpages&reference_id=1&placement=ypwebsitemip",
    "wof:name":"Advertise At The Top",
    "wof:placetype":"venue"
},
  "geometry": {"coordinates":[-112.09966900000001,33.617246],"type":"Point"}
}