{
  "type": "Feature",
  "properties": {
    "iso:country":"US",
    "sg:address":"1633 W Pershing Ave",
    "sg:city":"Phoenix",
    "sg:classifiers":[
        {
            "category":"Building & Trades",
            "subcategory":"Construction",
            "type":"Services"
        }
    ],
    "sg:phone":"+1 602 375 9215",
    "sg:postcode":"85029",
    "sg:province":"AZ",
    "sg:tags":[
        "estimate"
    ],
    "wof:name":"Belzamante Enterprises Inc",
    "wof:placetype":"venue"
},
  "geometry": {"coordinates":[-112.09442900000001,33.605751],"type":"Point"}
}