{
  "type": "Feature",
  "properties": {
    "addr:full":"4900 State Hwy 69 Prescott AZ 86301",
    "addr:housenumber":"4900",
    "addr:postcode":"86301",
    "addr:street":"State Hwy 69",
    "iso:country":"US",
    "sg:address":"4900 State Hwy 69",
    "sg:city":"Prescott",
    "sg:classifiers":[
        {
            "category":"Shopping",
            "subcategory":"Discount & Variety Stores",
            "type":"Retail Goods"
        }
    ],
    "sg:phone":"+1 928 445 6336",
    "sg:postcode":"86301",
    "sg:province":"AZ",
    "sg:tags":[
        "merchandise",
        "general"
    ],
    "wof:name":"J B Hickock Mercantile",
    "wof:placetype":"venue"
},
  "geometry": {"coordinates":[-112.384137,34.552319],"type":"Point"}
}