{
  "type": "Feature",
  "properties": {
    "addr:full":"16350 W Wilshire Dr Goodyear AZ 85395",
    "addr:housenumber":"16350",
    "addr:postcode":"85395",
    "addr:street":"W Wilshire Dr",
    "iso:country":"US",
    "sg:address":"16350 W Wilshire Dr",
    "sg:city":"Goodyear",
    "sg:classifiers":[
        {
            "category":"Communications",
            "type":"Services"
        }
    ],
    "sg:phone":"+1 623 547 3036",
    "sg:postcode":"85395",
    "sg:province":"AZ",
    "wof:name":"Overdrive Media",
    "wof:placetype":"venue"
},
  "geometry": {"coordinates":[-112.405282,33.471861],"type":"Point"}
}