{
  "type": "Feature",
  "properties": {
    "iso:country":"US",
    "sg:address":"1099 Hancock Rd",
    "sg:city":"Bullhead City",
    "sg:classifiers":[
        {
            "category":"Social Services",
            "type":"Services"
        }
    ],
    "sg:phone":"+1 928 758 0671",
    "sg:postcode":"86442",
    "sg:province":"AZ",
    "sg:tags":[
        "organization",
        "welfare"
    ],
    "wof:name":"Arizona's Children Assn",
    "wof:placetype":"venue"
},
  "geometry": {"coordinates":[-114.609212,35.10798],"type":"Point"}
}