{
  "type": "Feature",
  "properties": {
    "addr:full":"4700 N Central Ave Phoenix AZ 85012",
    "addr:housenumber":"4700",
    "addr:postcode":"85012",
    "addr:street":"N Central Ave",
    "iso:country":"US",
    "sg:address":"4700 N Central Ave",
    "sg:city":"Phoenix",
    "sg:classifiers":[
        {
            "category":"Personal",
            "subcategory":"Tanning Parlor",
            "type":"Services"
        }
    ],
    "sg:phone":"+1 602 285 1861",
    "sg:postcode":"85012",
    "sg:province":"AZ",
    "sg:tags":[
        "salon"
    ],
    "wof:name":"Energy Tanning Corp",
    "wof:placetype":"venue"
},
  "geometry": {"coordinates":[-112.073832,33.505456],"type":"Point"}
}