{
  "type": "Feature",
  "properties": {
    "iso:country":"US",
    "sg:address":"2059 W Noreen St",
    "sg:city":"Tucson",
    "sg:classifiers":[
        {
            "category":"Manufacturing",
            "subcategory":"Tools & Machinery",
            "type":"Manufacturing & Wholesale Goods"
        }
    ],
    "sg:phone":"+1 520 292 9140",
    "sg:postcode":"85705",
    "sg:province":"AZ",
    "sg:tags":[
        "measuring",
        "instrument",
        "electrical",
        "mfg"
    ],
    "wof:name":"Rons Quality Sweeping",
    "wof:placetype":"venue"
},
  "geometry": {"coordinates":[-111.011898,32.295295],"type":"Point"}
}