{
  "type": "Feature",
  "properties": {
    "iso:country":"US",
    "sg:address":"1760 E Southern Ave",
    "sg:city":"Tempe",
    "sg:classifiers":[
        {
            "category":"Food & Beverages",
            "subcategory":"Groceries & Convenience Stores",
            "type":"Retail Goods"
        }
    ],
    "sg:phone":"+1 480 820 4900",
    "sg:postcode":"85282",
    "sg:province":"AZ",
    "sg:tags":[
        "market"
    ],
    "wof:name":"Newflower Market",
    "wof:placetype":"venue"
},
  "geometry": {"coordinates":[-111.909521,33.393055],"type":"Point"}
}