{
  "type": "Feature",
  "properties": {
    "addr:full":"12535 E Los Reales Rd Tucson AZ 85747",
    "addr:housenumber":"12535",
    "addr:postcode":"85747",
    "addr:street":"E Los Reales Rd",
    "iso:country":"US",
    "sg:address":"12535 E Los Reales Rd",
    "sg:city":"Tucson",
    "sg:classifiers":[
        {
            "category":"Building & Trades",
            "subcategory":"Construction",
            "type":"Services"
        }
    ],
    "sg:phone":"+1 520 647 3499",
    "sg:postcode":"85747",
    "sg:province":"AZ",
    "sg:tags":[
        "housing"
    ],
    "wof:name":"Ed Shunk Construction",
    "wof:placetype":"venue"
},
  "geometry": {"coordinates":[-110.725326,32.1138],"type":"Point"}
}