{
  "type": "Feature",
  "properties": {
    "iso:country":"US",
    "sg:address":"4102 W Monona Dr",
    "sg:city":"Glendale",
    "sg:classifiers":[
        {
            "category":"Building & Trades",
            "subcategory":"Construction",
            "type":"Services"
        }
    ],
    "sg:phone":"+1 602 266 7781",
    "sg:postcode":"85308",
    "sg:province":"AZ",
    "sg:tags":[
        "handyman"
    ],
    "wof:name":"First Choice Handyman",
    "wof:placetype":"venue"
},
  "geometry": {"coordinates":[-112.149613,33.675329],"type":"Point"}
}