{
  "type": "Feature",
  "properties": {
    "iso:country":"US",
    "sg:address":"202 E Earll Dr Ste 400",
    "sg:city":"Phoenix",
    "sg:classifiers":[
        {
            "category":"Shopping",
            "subcategory":"Pets & Pet Supplies",
            "type":"Retail Goods"
        }
    ],
    "sg:phone":"+1 602 264 8849",
    "sg:postcode":"85012",
    "sg:province":"AZ",
    "sg:tags":[
        "furnishing",
        "dog",
        "store",
        "cat"
    ],
    "wof:name":"Pet Vaccinations",
    "wof:placetype":"venue"
},
  "geometry": {"coordinates":[-112.071743,33.483869],"type":"Point"}
}