{
  "type": "Feature",
  "properties": {
    "addr:full":"13915 N Dysart Rd El Mirage AZ 85335",
    "addr:housenumber":"13915",
    "addr:postcode":"85335",
    "addr:street":"N Dysart Rd",
    "iso:country":"US",
    "sg:address":"13915 N Dysart Rd",
    "sg:city":"El Mirage",
    "sg:classifiers":[
        {
            "category":"Personal",
            "subcategory":"Beauty Salon",
            "type":"Services"
        }
    ],
    "sg:phone":"+1 623 974 3635",
    "sg:postcode":"85335",
    "sg:province":"AZ",
    "sg:tags":[
        "manicuring"
    ],
    "wof:name":"Donna Nails & Spa",
    "wof:placetype":"venue"
},
  "geometry": {"coordinates":[-112.34192,33.610628],"type":"Point"}
}