{
  "type": "Feature",
  "properties": {
    "addr:full":"3140 N 77th Ln Phoenix AZ 85033",
    "addr:housenumber":"3140",
    "addr:postcode":"85033",
    "addr:street":"N 77Th Ln",
    "iso:country":"US",
    "sg:address":"3140 N 77th Ln",
    "sg:city":"Phoenix",
    "sg:classifiers":[
        {
            "category":"Building & Trades",
            "subcategory":"Electrical",
            "type":"Services"
        }
    ],
    "sg:phone":"+1 623 873 1748",
    "sg:postcode":"85033",
    "sg:province":"AZ",
    "sg:tags":[
        "electrician"
    ],
    "wof:name":"Mckeeman Electric, Inc",
    "wof:placetype":"venue"
},
  "geometry": {"coordinates":[-112.22582800000001,33.485029],"type":"Point"}
}