{
  "type": "Feature",
  "properties": {
    "iso:country":"US",
    "sg:address":"15049 N 74th Ave",
    "sg:city":"Peoria",
    "sg:classifiers":[
        {
            "category":"Building & Trades",
            "subcategory":"Construction",
            "type":"Services"
        }
    ],
    "sg:phone":"+1 623 878 0016",
    "sg:postcode":"85381",
    "sg:province":"AZ",
    "sg:tags":[
        "contractor",
        "painting",
        "hanging"
    ],
    "wof:name":"Quality Paper Hanging",
    "wof:placetype":"venue"
},
  "geometry": {"coordinates":[-112.218552,33.621196],"type":"Point"}
}