{
  "type": "Feature",
  "properties": {
    "addr:full":"67 N Dobson Rd Mesa AZ 85201",
    "addr:housenumber":"67",
    "addr:postcode":"85201",
    "addr:street":"N Dobson Rd",
    "iso:country":"US",
    "sg:address":"67 N Dobson Rd",
    "sg:city":"Mesa",
    "sg:classifiers":[
        {
            "category":"Health Services",
            "subcategory":"Doctor",
            "type":"Services"
        }
    ],
    "sg:phone":"+1 480 833 3677",
    "sg:postcode":"85201",
    "sg:province":"AZ",
    "sg:tags":[
        "dentist"
    ],
    "wof:name":"Mainstream Dental",
    "wof:placetype":"venue"
},
  "geometry": {"coordinates":[-111.874369,33.416617],"type":"Point"}
}