{
  "type": "Feature",
  "properties": {
    "iso:country":"US",
    "sg:address":"18753 E Swan Dr",
    "sg:city":"Queen Creek",
    "sg:classifiers":[
        {
            "category":"Building & Trades",
            "subcategory":"Construction",
            "type":"Services"
        }
    ],
    "sg:phone":"+1 480 694 7545",
    "sg:postcode":"85242",
    "sg:province":"AZ",
    "sg:tags":[
        "wallpaper"
    ],
    "wof:name":"Expert Wallpaper Installation",
    "wof:placetype":"venue"
},
  "geometry": {"coordinates":[-111.678947,33.276312],"type":"Point"}
}