{
  "type": "Feature",
  "properties": {
    "iso:country":"US",
    "sg:address":"2120 S 7th Ave Ste 120",
    "sg:city":"Phoenix",
    "sg:classifiers":[
        {
            "category":"Wholesale",
            "subcategory":"Fruits & Vegetables",
            "type":"Manufacturing & Wholesale Goods"
        }
    ],
    "sg:phone":"+1 602 253 0210",
    "sg:postcode":"85007",
    "sg:province":"AZ",
    "sg:tags":[
        "vegetables-wholesale"
    ],
    "wof:name":"Coosemans-Phoenix",
    "wof:placetype":"venue"
},
  "geometry": {"coordinates":[-112.082453,33.4274],"type":"Point"}
}