{
  "type": "Feature",
  "properties": {
    "iso:country":"US",
    "sg:address":"7250 W Chandler Blvd",
    "sg:city":"Chandler",
    "sg:classifiers":[
        {
            "category":"Restaurant",
            "type":"Food & Drink"
        }
    ],
    "sg:menulink":"http://www.allmenus.com/az/chandler/109195-village-inn/menu/",
    "sg:phone":"+1 480 961 0861",
    "sg:postcode":"85226",
    "sg:province":"AZ",
    "sg:tags":[
        "new",
        "american"
    ],
    "wof:name":"Village Inn",
    "wof:placetype":"venue"
},
  "geometry": {"coordinates":[-111.966336,33.305351],"type":"Point"}
}