{
  "type": "Feature",
  "properties": {
    "iso:country":"US",
    "sg:address":"8070 E Morgan Trl",
    "sg:city":"Scottsdale",
    "sg:classifiers":[
        {
            "category":"Shopping",
            "subcategory":"Computers & Home Electronics",
            "type":"Retail Goods"
        }
    ],
    "sg:phone":"+1 480 556 6000",
    "sg:postcode":"85258",
    "sg:province":"AZ",
    "sg:tags":[
        "equipment",
        "dealer"
    ],
    "wof:name":"Qcm Technologies Inc",
    "wof:placetype":"venue"
},
  "geometry": {"coordinates":[-111.907985,33.576596],"type":"Point"}
}