{
  "type": "Feature",
  "properties": {
    "addr:full":"1903 W Parkside Ln # 110 Phoenix AZ 85027",
    "addr:housenumber":"1903",
    "addr:postcode":"85027",
    "addr:street":"W Parkside Ln # 110",
    "iso:country":"US",
    "sg:address":"1903 W Parkside Ln # 110",
    "sg:city":"Phoenix",
    "sg:classifiers":[
        {
            "category":"Utilities",
            "subcategory":"Refuse",
            "type":"Services"
        }
    ],
    "sg:phone":"+1 623 869 6700",
    "sg:postcode":"85027",
    "sg:province":"AZ",
    "sg:tags":[
        "container",
        "garbage",
        "collection",
        "removal",
        "rubbish"
    ],
    "sg:website":"http://www.desertwaste.com",
    "wof:name":"Dwr",
    "wof:placetype":"venue"
},
  "geometry": {"coordinates":[-112.099969,33.695781],"type":"Point"}
}