{
  "type": "Feature",
  "properties": {
    "iso:country":"US",
    "sg:address":"11778 N 91st Ave",
    "sg:city":"Peoria",
    "sg:classifiers":[
        {
            "category":"Building & Trades",
            "subcategory":"Plumbing",
            "type":"Services"
        }
    ],
    "sg:phone":"+1 623 486 4361",
    "sg:postcode":"85345",
    "sg:province":"AZ",
    "sg:tags":[
        "contractor"
    ],
    "wof:name":"Axis Automatic Fire Protection",
    "wof:placetype":"venue"
},
  "geometry": {"coordinates":[-112.255121,33.592622],"type":"Point"}
}