{
  "type": "Feature",
  "properties": {
    "iso:country":"US",
    "sg:address":"529 S Forest Ave",
    "sg:city":"Tempe",
    "sg:classifiers":[
        {
            "category":"Retail",
            "subcategory":"Repair Shop",
            "type":"Services"
        }
    ],
    "sg:phone":"+1 480 226 5739",
    "sg:postcode":"85281",
    "sg:province":"AZ",
    "sg:tags":[
        "refinish",
        "furniture"
    ],
    "wof:name":"Ganceda Tub Refinishing",
    "wof:placetype":"venue"
},
  "geometry": {"coordinates":[-111.936649,33.425181],"type":"Point"}
}