{
  "type": "Feature",
  "properties": {
    "iso:country":"US",
    "sg:address":"6819 E Diamond St",
    "sg:city":"Scottsdale",
    "sg:classifiers":[
        {
            "category":"Professional",
            "subcategory":"Management & Consulting",
            "type":"Services"
        }
    ],
    "sg:phone":"+1 480 947 8969",
    "sg:postcode":"85257",
    "sg:province":"AZ",
    "sg:tags":[
        "counselor",
        "public",
        "relations"
    ],
    "wof:name":"David Perry Public Relations",
    "wof:placetype":"venue"
},
  "geometry": {"coordinates":[-111.93479600000001,33.459052],"type":"Point"}
}