{
  "type": "Feature",
  "properties": {
    "iso:country":"US",
    "sg:address":"2715 E Hwy 89A",
    "sg:city":"Cottonwood",
    "sg:classifiers":[
        {
            "category":"Organizations",
            "subcategory":"Religious Organization",
            "type":"Services"
        }
    ],
    "sg:phone":"+1 928 649 0624",
    "sg:postcode":"86326",
    "sg:province":"AZ",
    "sg:tags":[
        "church"
    ],
    "wof:name":"St Joseph's Catholic",
    "wof:placetype":"venue"
},
  "geometry": {"coordinates":[-111.99363099999999,34.721102],"type":"Point"}
}