{
  "type": "Feature",
  "properties": {
    "iso:country":"US",
    "sg:address":"3855 E Speedway Blvd",
    "sg:city":"Tucson",
    "sg:classifiers":[
        {
            "category":"Travel",
            "subcategory":"Hotels & Motels",
            "type":"Entertainment"
        },
        {
            "category":"Restaurant",
            "type":"Food & Drink"
        }
    ],
    "sg:phone":"+1 520 318 3777",
    "sg:postcode":"85716",
    "sg:province":"AZ",
    "sg:tags":[
        "resort",
        "eating"
    ],
    "sg:website":"www.ilxresorts.com",
    "wof:name":"Varsity Clubs of America",
    "wof:placetype":"venue"
},
  "geometry": {"coordinates":[-110.910747,32.236265],"type":"Point"}
}