{
  "type": "Feature",
  "properties": {
    "iso:country":"US",
    "sg:address":"2924 E Route 66",
    "sg:city":"Flagstaff",
    "sg:classifiers":[
        {
            "category":"Coffee & Tea",
            "type":"Food & Drink"
        },
        {
            "category":"Restaurant",
            "type":"Food & Drink"
        }
    ],
    "sg:phone":"+1 928 526 0104",
    "sg:postcode":"86004",
    "sg:province":"AZ",
    "sg:tags":[
        "espresso"
    ],
    "wof:name":"Miz Zip's",
    "wof:placetype":"venue"
},
  "geometry": {"coordinates":[-111.607681,35.209273],"type":"Point"}
}