{
  "type": "Feature",
  "properties": {
    "iso:country":"US",
    "sg:address":"2720 W Broadway Rd",
    "sg:city":"Phoenix",
    "sg:classifiers":[
        {
            "category":"Wholesale",
            "subcategory":"Auto Parts",
            "type":"Manufacturing & Wholesale Goods"
        }
    ],
    "sg:phone":"+1 602 276 6010",
    "sg:postcode":"85041",
    "sg:province":"AZ",
    "sg:tags":[
        "automobile",
        "rebuilt"
    ],
    "wof:name":"H & L Auto Salvage",
    "wof:placetype":"venue"
},
  "geometry": {"coordinates":[-112.116544,33.406717],"type":"Point"}
}