{
  "type": "Feature",
  "properties": {
    "iso:country":"US",
    "sg:address":"2929 E Thomas Rd",
    "sg:city":"Phoenix",
    "sg:classifiers":[
        {
            "category":"Organizations",
            "subcategory":"Professional Association",
            "type":"Services"
        }
    ],
    "sg:phone":"+1 602 553 7129",
    "sg:postcode":"85016",
    "sg:province":"AZ",
    "sg:website":"www.cancer.org",
    "wof:name":"American Cancer Society Sw Div",
    "wof:placetype":"venue"
},
  "geometry": {"coordinates":[-112.01723,33.480446],"type":"Point"}
}