{
  "type": "Feature",
  "properties": {
    "iso:country":"US",
    "sg:address":"415 E Mabel St",
    "sg:city":"Tucson",
    "sg:classifiers":[
        {
            "category":"Manufacturing",
            "subcategory":"Printing",
            "type":"Manufacturing & Wholesale Goods"
        }
    ],
    "sg:phone":"+1 520 624 4887",
    "sg:postcode":"85705",
    "sg:province":"AZ",
    "sg:tags":[
        "book"
    ],
    "wof:name":"Black Mountain Publishers",
    "wof:placetype":"venue"
},
  "geometry": {"coordinates":[-110.965108,32.238617],"type":"Point"}
}