{
  "type": "Feature",
  "properties": {
    "iso:country":"US",
    "sg:address":"456 E Vine Ave",
    "sg:city":"Mesa",
    "sg:classifiers":[
        {
            "category":"Farming",
            "subcategory":"Farm & Veterinary Services",
            "type":"Manufacturing & Wholesale Goods"
        }
    ],
    "sg:phone":"+1 480 668 6718",
    "sg:postcode":"85204",
    "sg:province":"AZ",
    "sg:tags":[
        "crop",
        "harvesting"
    ],
    "wof:name":"Barreras Harvesting Ente",
    "wof:placetype":"venue"
},
  "geometry": {"coordinates":[-111.821156,33.405118],"type":"Point"}
}