{
  "type": "Feature",
  "properties": {
    "iso:country":"US",
    "sg:address":"8225 E Raintree Dr",
    "sg:city":"Scottsdale",
    "sg:classifiers":[
        {
            "category":"Retail",
            "subcategory":"Auto Rental",
            "type":"Services"
        }
    ],
    "sg:phone":"+1 480 905 8645",
    "sg:postcode":"85260",
    "sg:province":"AZ",
    "sg:tags":[
        "renting",
        "truck",
        "leasing"
    ],
    "sg:website":"www.penske.com",
    "wof:name":"Penske Truck Leasing",
    "wof:placetype":"venue"
},
  "geometry": {"coordinates":[-111.903724,33.619219],"type":"Point"}
}