{
  "type": "Feature",
  "properties": {
    "iso:country":"US",
    "sg:address":"24 E Keim Dr",
    "sg:city":"Phoenix",
    "sg:classifiers":[
        {
            "category":"Shopping",
            "subcategory":"Computers & Home Electronics",
            "type":"Retail Goods"
        }
    ],
    "sg:phone":"+1 602 373 9724",
    "sg:postcode":"85012",
    "sg:province":"AZ",
    "sg:tags":[
        "equipment",
        "audio-visual"
    ],
    "wof:name":"Audio Pirates",
    "wof:placetype":"venue"
},
  "geometry": {"coordinates":[-112.073424,33.526779],"type":"Point"}
}