{
  "type": "Feature",
  "properties": {
    "iso:country":"US",
    "sg:address":"14906 W Lisbon Ln",
    "sg:city":"Surprise",
    "sg:classifiers":[
        {
            "category":"Building & Trades",
            "subcategory":"Electrical",
            "type":"Services"
        }
    ],
    "sg:phone":"+1 623 584 9693",
    "sg:postcode":"85379",
    "sg:province":"AZ",
    "sg:tags":[
        "electrical",
        "contractor"
    ],
    "wof:name":"Peninsula Electric Contg Co",
    "wof:placetype":"venue"
},
  "geometry": {"coordinates":[-112.382644,33.616335],"type":"Point"}
}