{
  "type": "Feature",
  "properties": {
    "addr:full":"13275 E Sorrel Ln Scottsdale AZ 85259",
    "addr:housenumber":"13275",
    "addr:postcode":"85259",
    "addr:street":"E Sorrel Ln",
    "iso:country":"US",
    "sg:address":"13275 E Sorrel Ln",
    "sg:city":"Scottsdale",
    "sg:classifiers":[
        {
            "category":"Recreation",
            "type":"Entertainment"
        }
    ],
    "sg:phone":"+1 480 951 6282",
    "sg:postcode":"85259",
    "sg:province":"AZ",
    "sg:tags":[
        "tours",
        "sightseeing"
    ],
    "wof:name":"Scottsdale Helicopters",
    "wof:placetype":"venue"
},
  "geometry": {"coordinates":[-111.793903,33.573296],"type":"Point"}
}