{
  "type": "Feature",
  "properties": {
    "iso:country":"US",
    "sg:address":"1325 W Cove Dr",
    "sg:city":"Gilbert",
    "sg:classifiers":[
        {
            "category":"Utilities",
            "subcategory":"Telephone",
            "type":"Services"
        }
    ],
    "sg:phone":"+1 480 633 7015",
    "sg:postcode":"85233",
    "sg:province":"AZ",
    "sg:tags":[
        "telecommunication"
    ],
    "wof:name":"R Floman",
    "wof:placetype":"venue"
},
  "geometry": {"coordinates":[-111.816592,33.339566],"type":"Point"}
}