{
  "type": "Feature",
  "properties": {
    "addr:full":"3353 N 19th Ave Phoenix AZ 85015",
    "addr:housenumber":"3353",
    "addr:postcode":"85015",
    "addr:street":"N 19Th Ave",
    "iso:country":"US",
    "sg:address":"3353 N 19th Ave",
    "sg:city":"Phoenix",
    "sg:classifiers":[
        {
            "category":"Farming",
            "subcategory":"Farm",
            "type":"Manufacturing & Wholesale Goods"
        }
    ],
    "sg:phone":"+1 602 241 6292",
    "sg:postcode":"85015",
    "sg:province":"AZ",
    "sg:tags":[
        "crop",
        "general"
    ],
    "wof:name":"Phoenix Farms",
    "wof:placetype":"venue"
},
  "geometry": {"coordinates":[-112.09984799999999,33.487723],"type":"Point"}
}