{
  "type": "Feature",
  "properties": {
    "iso:country":"US",
    "sg:address":"809 S Dora Ave",
    "sg:city":"Yuma",
    "sg:classifiers":[
        {
            "category":"Building & Trades",
            "subcategory":"Construction",
            "type":"Services"
        }
    ],
    "sg:phone":"+1 928 329 1419",
    "sg:postcode":"85364",
    "sg:province":"AZ",
    "sg:tags":[
        "house"
    ],
    "wof:name":"A & I Builders LLC",
    "wof:placetype":"venue"
},
  "geometry": {"coordinates":[-114.645487,32.711719],"type":"Point"}
}