{
  "type": "Feature",
  "properties": {
    "addr:full":"7920 E Camelback Rd # 502 Scottsdale AZ 85251",
    "addr:housenumber":"7920",
    "addr:postcode":"85251",
    "addr:street":"E Camelback Rd # 502",
    "iso:country":"US",
    "sg:address":"7920 E Camelback Rd # 502",
    "sg:city":"Scottsdale",
    "sg:classifiers":[
        {
            "category":"Wholesale",
            "subcategory":"Hardware",
            "type":"Manufacturing & Wholesale Goods"
        }
    ],
    "sg:phone":"+1 480 818 0888",
    "sg:postcode":"85251",
    "sg:province":"AZ",
    "sg:tags":[
        "hardware-wholesale",
        "manufacturer"
    ],
    "wof:name":"Toth Industries, Inc",
    "wof:placetype":"venue"
},
  "geometry": {"coordinates":[-111.910521,33.502159],"type":"Point"}
}