{
  "type": "Feature",
  "properties": {
    "addr:full":"1015 Fair St Prescott AZ 86305",
    "addr:housenumber":"1015",
    "addr:postcode":"86305",
    "addr:street":"Fair St",
    "iso:country":"US",
    "sg:address":"1015 Fair St",
    "sg:city":"Prescott",
    "sg:classifiers":[
        {
            "category":"Government",
            "subcategory":"Office",
            "type":"Public Place"
        }
    ],
    "sg:phone":"+1 928 771 3100",
    "sg:postcode":"86305",
    "sg:province":"AZ",
    "sg:website":"www.co.yavapai.az.us",
    "wof:name":"Yavapai County Government",
    "wof:placetype":"venue"
},
  "geometry": {"coordinates":[-112.48341600000001,34.553363],"type":"Point"}
}