{
  "type": "Feature",
  "properties": {
    "iso:country":"US",
    "sg:address":"115 E Saint John Rd",
    "sg:city":"Phoenix",
    "sg:classifiers":[
        {
            "category":"Professional",
            "subcategory":"Computer Services",
            "type":"Services"
        }
    ],
    "sg:phone":"+1 602 374 2232",
    "sg:postcode":"85022",
    "sg:province":"AZ",
    "sg:tags":[
        "publisher",
        "developer",
        "software"
    ],
    "wof:name":"Sr Consultants",
    "wof:placetype":"venue"
},
  "geometry": {"coordinates":[-112.072549,33.646443],"type":"Point"}
}