{
  "type": "Feature",
  "properties": {
    "addr:full":"2523 N Via Serena Cir Mesa AZ 85207",
    "addr:housenumber":"2523",
    "addr:postcode":"85207",
    "addr:street":"N Via Serena Cir",
    "iso:country":"US",
    "sg:address":"2523 N Via Serena Cir",
    "sg:city":"Mesa",
    "sg:classifiers":[
        {
            "category":"Utilities",
            "subcategory":"Electric",
            "type":"Services"
        },
        {
            "category":"Wholesale",
            "subcategory":"Construction Materials",
            "type":"Manufacturing & Wholesale Goods"
        },
        {
            "category":"Home & Garden",
            "subcategory":"Building Materials",
            "type":"Retail Goods"
        }
    ],
    "sg:phone":"+1 480 832 1785",
    "sg:postcode":"85207",
    "sg:province":"AZ",
    "sg:tags":[
        "energy",
        "heating",
        "systems-wholesale",
        "equipment",
        "systems-manufacturers",
        "solar",
        "distributor",
        "systems-dealers"
    ],
    "sg:website":"http://www.jonrobinsonsolarandplumbing.com",
    "wof:name":"Jon Robinson's Solar & Plbg",
    "wof:placetype":"venue"
},
  "geometry": {"coordinates":[-111.62815999999999,33.460505],"type":"Point"}
}