{
  "type": "Feature",
  "properties": {
    "iso:country":"US",
    "sg:address":"999 N Grand Canyon Blvd",
    "sg:city":"Williams",
    "sg:classifiers":[
        {
            "category":"Retail",
            "subcategory":"Auto Repair",
            "type":"Services"
        }
    ],
    "sg:phone":"+1 928 635 1934",
    "sg:postcode":"86046",
    "sg:province":"AZ",
    "sg:tags":[
        "repairing",
        "automobile"
    ],
    "wof:name":"Sandoval's Auto Repair",
    "wof:placetype":"venue"
},
  "geometry": {"coordinates":[-112.192133,35.25792],"type":"Point"}
}