{
  "type": "Feature",
  "properties": {
    "addr:full":"15001 N Hayden Rd Scottsdale AZ 85260",
    "addr:housenumber":"15001",
    "addr:postcode":"85260",
    "addr:street":"N Hayden Rd",
    "iso:country":"US",
    "sg:address":"15001 N Hayden Rd",
    "sg:city":"Scottsdale",
    "sg:classifiers":[
        {
            "category":"Organizations",
            "subcategory":"Community Association",
            "type":"Services"
        }
    ],
    "sg:phone":"+1 480 348 7809",
    "sg:postcode":"85260",
    "sg:province":"AZ",
    "sg:tags":[
        "club"
    ],
    "wof:name":"Scottsdale Gun Club",
    "wof:placetype":"venue"
},
  "geometry": {"coordinates":[-111.905518,33.622261],"type":"Point"}
}