{
  "type": "Feature",
  "properties": {
    "addr:full":"3510 E Hampton Ave Mesa AZ 85204",
    "addr:housenumber":"3510",
    "addr:postcode":"85204",
    "addr:street":"E Hampton Ave",
    "iso:country":"US",
    "sg:address":"3510 E Hampton Ave",
    "sg:city":"Mesa",
    "sg:classifiers":[
        {
            "category":"Professional",
            "type":"Services"
        }
    ],
    "sg:phone":"+1 480 629 4411",
    "sg:postcode":"85204",
    "sg:province":"AZ",
    "wof:name":"Alan Sapakie",
    "wof:placetype":"venue"
},
  "geometry": {"coordinates":[-111.75545200000001,33.389983],"type":"Point"}
}