{
  "type": "Feature",
  "properties": {
    "addr:full":"18515 W McNeil St Goodyear AZ 85338",
    "addr:housenumber":"18515",
    "addr:postcode":"85338",
    "addr:street":"W Mcneil St",
    "iso:country":"US",
    "sg:address":"18515 W McNeil St",
    "sg:city":"Goodyear",
    "sg:classifiers":[
        {
            "category":"Real Estate",
            "subcategory":"Real Estate Operator",
            "type":"Services"
        }
    ],
    "sg:phone":"+1 623 932 1866",
    "sg:postcode":"85338",
    "sg:province":"AZ",
    "sg:tags":[
        "building",
        "nonresidential"
    ],
    "wof:name":"Syberger Properties LLC",
    "wof:placetype":"venue"
},
  "geometry": {"coordinates":[-112.448352,33.354885],"type":"Point"}
}