{
  "type": "Feature",
  "properties": {
    "addr:full":"2629 S 21st St Phoenix AZ 85034",
    "addr:housenumber":"2629",
    "addr:postcode":"85034",
    "addr:street":"S 21St St",
    "iso:country":"US",
    "sg:address":"2629 S 21st St",
    "sg:city":"Phoenix",
    "sg:classifiers":[
        {
            "category":"Government",
            "subcategory":"Office",
            "type":"Public Place"
        }
    ],
    "sg:phone":"+1 602 273 2789",
    "sg:postcode":"85034",
    "sg:province":"AZ",
    "sg:tags":[
        "county",
        "program",
        "health"
    ],
    "wof:name":"Maricopa Home Health Care Svc",
    "wof:placetype":"venue"
},
  "geometry": {"coordinates":[-112.036626,33.42274],"type":"Point"}
}