{
  "type": "Feature",
  "properties": {
    "iso:country":"US",
    "sg:address":"7302 E Helm Dr",
    "sg:city":"Scottsdale",
    "sg:classifiers":[
        {
            "category":"Professional",
            "type":"Services"
        }
    ],
    "sg:phone":"+1 480 991 0779",
    "sg:postcode":"85260",
    "sg:province":"AZ",
    "sg:tags":[
        "establishment"
    ],
    "wof:name":"Practice Systems",
    "wof:placetype":"venue"
},
  "geometry": {"coordinates":[-111.922726,33.620016],"type":"Point"}
}