{
  "type": "Feature",
  "properties": {
    "addr:full":"3200 N Central Ave # 100 Phoenix AZ 85012",
    "addr:housenumber":"3200",
    "addr:postcode":"85012",
    "addr:street":"N Central Ave # 100",
    "iso:country":"US",
    "sg:address":"3200 N Central Ave # 100",
    "sg:city":"Phoenix",
    "sg:classifiers":[
        {
            "category":"Banks & Credit Unions",
            "subcategory":"Bank",
            "type":"Services"
        }
    ],
    "sg:phone":"+1 480 361 0900",
    "sg:postcode":"85012",
    "sg:province":"AZ",
    "sg:website":"http://www.comerica.com",
    "wof:name":"Comerica",
    "wof:placetype":"venue"
},
  "geometry": {"coordinates":[-112.073898,33.485271],"type":"Point"}
}