{
  "type": "Feature",
  "properties": {
    "iso:country":"US",
    "sg:address":"2211 S Mill Ave",
    "sg:city":"Tempe",
    "sg:classifiers":[
        {
            "category":"Health Services",
            "subcategory":"Doctor",
            "type":"Services"
        }
    ],
    "sg:phone":"+1 480 784 2211",
    "sg:postcode":"85282",
    "sg:province":"AZ",
    "sg:tags":[
        "dentist"
    ],
    "wof:name":"Denham Crafton II Dmd",
    "wof:placetype":"venue"
},
  "geometry": {"coordinates":[-111.939688,33.404815],"type":"Point"}
}