{
  "type": "Feature",
  "properties": {
    "iso:country":"US",
    "sg:address":"1328 E Main St",
    "sg:city":"Mesa",
    "sg:classifiers":[
        {
            "category":"Social Services",
            "type":"Services"
        }
    ],
    "sg:phone":"+1 480 655 9352",
    "sg:postcode":"85203",
    "sg:province":"AZ",
    "sg:tags":[
        "organization",
        "welfare"
    ],
    "wof:name":"Goodwill Industries",
    "wof:placetype":"venue"
},
  "geometry": {"coordinates":[-111.802609,33.415302],"type":"Point"}
}