{
  "type": "Feature",
  "properties": {
    "addr:full":"9603 E Skinner Dr Scottsdale AZ 85262",
    "addr:housenumber":"9603",
    "addr:postcode":"85262",
    "addr:street":"E Skinner Dr",
    "iso:country":"US",
    "sg:address":"9603 E Skinner Dr",
    "sg:city":"Scottsdale",
    "sg:classifiers":[
        {
            "category":"Building & Trades",
            "subcategory":"Construction",
            "type":"Services"
        }
    ],
    "sg:phone":"+1 480 502 5155",
    "sg:postcode":"85262",
    "sg:province":"AZ",
    "sg:tags":[
        "residential"
    ],
    "wof:name":"Sonoran Concepts Corp",
    "wof:placetype":"venue"
},
  "geometry": {"coordinates":[-111.872007,33.750474],"type":"Point"}
}