{
  "type": "Feature",
  "properties": {
    "iso:country":"US",
    "sg:address":"9132 W Cactus Rd",
    "sg:city":"Peoria",
    "sg:classifiers":[
        {
            "category":"Shopping",
            "type":"Retail Goods"
        }
    ],
    "sg:phone":"+1 623 487 4050",
    "sg:postcode":"85381",
    "sg:province":"AZ",
    "sg:tags":[
        "metaphysical",
        "supply"
    ],
    "wof:name":"Spiritual Corner",
    "wof:placetype":"venue"
},
  "geometry": {"coordinates":[-112.257388,33.595358],"type":"Point"}
}