{
  "type": "Feature",
  "properties": {
    "addr:full":"17233 N 56th Ave Glendale AZ 85308",
    "addr:housenumber":"17233",
    "addr:postcode":"85308",
    "addr:street":"N 56Th Ave",
    "iso:country":"US",
    "sg:address":"17233 N 56th Ave",
    "sg:city":"Glendale",
    "sg:classifiers":[
        {
            "category":"Shopping",
            "type":"Retail Goods"
        }
    ],
    "sg:phone":"+1 602 547 1121",
    "sg:postcode":"85308",
    "sg:province":"AZ",
    "sg:tags":[
        "merchandise"
    ],
    "wof:name":"Pampered Pets Plants Inc",
    "wof:placetype":"venue"
},
  "geometry": {"coordinates":[-112.180036,33.641539],"type":"Point"}
}