{
  "type": "Feature",
  "properties": {
    "addr:full":"1620 W University Dr Tempe AZ 85281",
    "addr:housenumber":"1620",
    "addr:postcode":"85281",
    "addr:street":"W University Dr",
    "iso:country":"US",
    "sg:address":"1620 W University Dr",
    "sg:city":"Tempe",
    "sg:classifiers":[
        {
            "category":"Autos & Motor Vehicles",
            "subcategory":"Motorcycle Sales",
            "type":"Retail Goods"
        }
    ],
    "sg:phone":"+1 480 615 9200",
    "sg:postcode":"85281",
    "sg:province":"AZ",
    "sg:tags":[
        "scooter"
    ],
    "wof:name":"Arizona Motorcycle Sales",
    "wof:placetype":"venue"
},
  "geometry": {"coordinates":[-111.965985,33.42203],"type":"Point"}
}