{
  "type": "Feature",
  "properties": {
    "iso:country":"US",
    "sg:address":"2051 W Cll Placida",
    "sg:city":"Tucson",
    "sg:classifiers":[
        {
            "category":"Professional",
            "subcategory":"Computer Services",
            "type":"Services"
        }
    ],
    "sg:phone":"+1 520 770 0000",
    "sg:postcode":"85745",
    "sg:province":"AZ",
    "sg:tags":[
        "processing",
        "datum"
    ],
    "wof:name":"TDEC Intl LLC",
    "wof:placetype":"venue"
},
  "geometry": {"coordinates":[-111.010998,32.228201],"type":"Point"}
}