{
  "type": "Feature",
  "properties": {
    "iso:country":"US",
    "sg:address":"8550 N 91st Ave",
    "sg:city":"Peoria",
    "sg:classifiers":[
        {
            "category":"Manufacturing",
            "subcategory":"Tools & Machinery",
            "type":"Manufacturing & Wholesale Goods"
        }
    ],
    "sg:phone":"+1 623 587 4883",
    "sg:postcode":"85305",
    "sg:province":"AZ",
    "sg:tags":[
        "machine",
        "shop"
    ],
    "wof:name":"Jones Engineering",
    "wof:placetype":"venue"
},
  "geometry": {"coordinates":[-112.255114,33.559838],"type":"Point"}
}