{
  "type": "Feature",
  "properties": {
    "iso:country":"US",
    "sg:address":"20802 N Cave Creek Rd",
    "sg:city":"Phoenix",
    "sg:classifiers":[
        {
            "category":"Organizations",
            "subcategory":"Non-profit Organization",
            "type":"Services"
        }
    ],
    "sg:phone":"+1 602 569 0508",
    "sg:postcode":"85024",
    "sg:province":"AZ",
    "wof:name":"Baptist Village North East",
    "wof:placetype":"venue"
},
  "geometry": {"coordinates":[-112.0311,33.675628],"type":"Point"}
}