{
  "type": "Feature",
  "properties": {
    "iso:country":"US",
    "sg:address":"5473 N Black Canyon Hwy",
    "sg:city":"Phoenix",
    "sg:classifiers":[
        {
            "category":"Real Estate",
            "subcategory":"Real Estate Agent",
            "type":"Services"
        }
    ],
    "sg:phone":"+1 602 758 4897",
    "sg:postcode":"85015",
    "sg:province":"AZ",
    "sg:tags":[
        "cooperative"
    ],
    "wof:name":"Bethany Crest Co-Op",
    "wof:placetype":"venue"
},
  "geometry": {"coordinates":[-112.112003,33.515235],"type":"Point"}
}