{
  "type": "Feature",
  "properties": {
    "iso:country":"US",
    "sg:address":"16179 W Dixileta Dr",
    "sg:city":"Surprise",
    "sg:classifiers":[
        {
            "category":"Wholesale",
            "subcategory":"Farm Supplies",
            "type":"Manufacturing & Wholesale Goods"
        }
    ],
    "sg:phone":"+1 623 214 1633",
    "sg:postcode":"85387",
    "sg:province":"AZ",
    "sg:tags":[
        "livestock"
    ],
    "wof:name":"Hope Springs Ranch",
    "wof:placetype":"venue"
},
  "geometry": {"coordinates":[-112.411012,33.753035],"type":"Point"}
}