{
  "type": "Feature",
  "properties": {
    "addr:full":"6225 E Southern Ave Mesa AZ 85206",
    "addr:housenumber":"6225",
    "addr:postcode":"85206",
    "addr:street":"E Southern Ave",
    "iso:country":"US",
    "sg:address":"6225 E Southern Ave",
    "sg:city":"Mesa",
    "sg:classifiers":[
        {
            "category":"Shopping",
            "subcategory":"Clothing, Apparel, & Fashions",
            "type":"Retail Goods"
        }
    ],
    "sg:phone":"+1 480 325 4796",
    "sg:postcode":"85206",
    "sg:province":"AZ",
    "sg:tags":[
        "family"
    ],
    "wof:name":"Burlington Coat Factory",
    "wof:placetype":"venue"
},
  "geometry": {"coordinates":[-111.700434,33.393811],"type":"Point"}
}