{
  "type": "Feature",
  "properties": {
    "iso:country":"US",
    "sg:address":"3915 N Campbell Ave",
    "sg:city":"Tucson",
    "sg:classifiers":[
        {
            "category":"Shopping",
            "type":"Retail Goods"
        }
    ],
    "sg:phone":"+1 520 887 2688",
    "sg:postcode":"85719",
    "sg:province":"AZ",
    "sg:tags":[
        "awning",
        "canopy"
    ],
    "wof:name":"Way Build Better Awning",
    "wof:placetype":"venue"
},
  "geometry": {"coordinates":[-110.943861,32.277803],"type":"Point"}
}