{
  "type": "Feature",
  "properties": {
    "addr:full":"5340 E Broadway Blvd Tucson AZ 85711",
    "addr:housenumber":"5340",
    "addr:postcode":"85711",
    "addr:street":"E Broadway Blvd",
    "iso:country":"US",
    "sg:address":"5340 E Broadway Blvd",
    "sg:city":"Tucson",
    "sg:classifiers":[
        {
            "category":"Restaurant",
            "type":"Food & Drink"
        }
    ],
    "sg:menulink":"http://www.allmenus.com/az/tucson/268925-58-degrees--holding-co---plaza-at-williams-cente/menu/",
    "sg:phone":"+1 520 747 5858",
    "sg:postcode":"85711",
    "sg:province":"AZ",
    "wof:name":"58 Degrees & Holding Co. - Plaza at Williams Cente",
    "wof:placetype":"venue"
},
  "geometry": {"coordinates":[-110.878595,32.221077],"type":"Point"}
}