{
  "type": "Feature",
  "properties": {
    "iso:country":"US",
    "sg:address":"7119 E Shea Blvd Ste 109",
    "sg:city":"Scottsdale",
    "sg:classifiers":[
        {
            "category":"Real Estate",
            "subcategory":"Developer",
            "type":"Services"
        }
    ],
    "sg:phone":"+1 480 947 5900",
    "sg:postcode":"85254",
    "sg:province":"AZ",
    "sg:tags":[
        "investing"
    ],
    "wof:name":"Tmr Investors",
    "wof:placetype":"venue"
},
  "geometry": {"coordinates":[-111.927693,33.582081],"type":"Point"}
}