{
  "type": "Feature",
  "properties": {
    "iso:country":"US",
    "sg:address":"1402 E Van Buren St",
    "sg:city":"Phoenix",
    "sg:classifiers":[
        {
            "category":"Shopping",
            "subcategory":"Department Store",
            "type":"Retail Goods"
        }
    ],
    "sg:phone":"+1 602 462 5079",
    "sg:postcode":"85006",
    "sg:province":"AZ",
    "wof:name":"Phoenix Dollar Store's",
    "wof:placetype":"venue"
},
  "geometry": {"coordinates":[-112.052115,33.451469],"type":"Point"}
}