{
  "type": "Feature",
  "properties": {
    "iso:country":"US",
    "sg:address":"5305 E Speedway Blvd",
    "sg:city":"Tucson",
    "sg:classifiers":[
        {
            "category":"Restaurant",
            "type":"Food & Drink"
        }
    ],
    "sg:phone":"+1 520 323 1840",
    "sg:postcode":"85712",
    "sg:province":"AZ",
    "wof:name":"Colors Food & Spirits",
    "wof:placetype":"venue"
},
  "geometry": {"coordinates":[-110.877702,32.236259],"type":"Point"}
}