{
  "type": "Feature",
  "properties": {
    "iso:country":"US",
    "sg:address":"3761 E Baseline Road",
    "sg:city":"Gilbert",
    "sg:classifiers":[
        {
            "category":"Shopping",
            "subcategory":"Hobbies, Toys, & Games",
            "type":"Retail Goods"
        },
        {
            "category":"Personal",
            "type":"Services"
        }
    ],
    "sg:phone":"+1 480 507 9420",
    "sg:postcode":"85234",
    "sg:province":"AZ",
    "sg:tags":[
        "shop",
        "hobby",
        "planning",
        "event",
        "party"
    ],
    "wof:name":"PC Gaming the Front",
    "wof:placetype":"venue"
},
  "geometry": {"coordinates":[-111.751341,33.379106],"type":"Point"}
}