{
  "type": "Feature",
  "properties": {
    "iso:country":"US",
    "sg:address":"2937 N 29th St",
    "sg:city":"Phoenix",
    "sg:classifiers":[
        {
            "category":"Manufacturing",
            "subcategory":"Chemicals & Compounds",
            "type":"Manufacturing & Wholesale Goods"
        }
    ],
    "sg:phone":"+1 602 957 7350",
    "sg:postcode":"85016",
    "sg:province":"AZ",
    "sg:tags":[
        "preparation",
        "mfg"
    ],
    "wof:name":"Any Pyro",
    "wof:placetype":"venue"
},
  "geometry": {"coordinates":[-112.019325,33.480585],"type":"Point"}
}