{
  "type": "Feature",
  "properties": {
    "iso:country":"US",
    "sg:address":"20633 N 35th Ave",
    "sg:city":"Phoenix",
    "sg:classifiers":[
        {
            "category":"Social Services",
            "subcategory":"Child Care",
            "type":"Services"
        }
    ],
    "sg:phone":"+1 623 582 2226",
    "sg:postcode":"85027",
    "sg:province":"AZ",
    "wof:name":"Deer Valley Christian Pre-Schl",
    "wof:placetype":"venue"
},
  "geometry": {"coordinates":[-112.13461100000001,33.674488],"type":"Point"}
}