{
  "type": "Feature",
  "properties": {
    "iso:country":"US",
    "sg:address":"4143 N 43rd Ave",
    "sg:city":"Phoenix",
    "sg:classifiers":[
        {
            "category":"Place Of Worship",
            "subcategory":"Church",
            "type":"Public Place"
        },
        {
            "category":"Place Of Worship",
            "type":"Public Place"
        }
    ],
    "sg:phone":"+1 602 278 0917",
    "sg:postcode":"85031",
    "sg:province":"AZ",
    "sg:tags":[
        "churches-methodist"
    ],
    "wof:name":"Japanese Free Methodist Church",
    "wof:placetype":"venue"
},
  "geometry": {"coordinates":[-112.151686,33.496158],"type":"Point"}
}