{
  "type": "Feature",
  "properties": {
    "iso:country":"US",
    "sg:address":"1838 W Lincoln St",
    "sg:city":"Phoenix",
    "sg:classifiers":[
        {
            "category":"Retail",
            "subcategory":"Auto Repair",
            "type":"Services"
        }
    ],
    "sg:phone":"+1 602 254 7351",
    "sg:postcode":"85007",
    "sg:province":"AZ",
    "sg:tags":[
        "repairing",
        "automobile"
    ],
    "wof:name":"R H Align",
    "wof:placetype":"venue"
},
  "geometry": {"coordinates":[-112.099401,33.442409],"type":"Point"}
}