{
  "type": "Feature",
  "properties": {
    "iso:country":"US",
    "sg:address":"16545 E Palisades Blvd",
    "sg:city":"Fountain Hills",
    "sg:classifiers":[
        {
            "category":"Shopping",
            "subcategory":"Pharmacy",
            "type":"Retail Goods"
        }
    ],
    "sg:phone":"+1 480 836 8337",
    "sg:postcode":"85268",
    "sg:province":"AZ",
    "wof:name":"Osco Drug 9279",
    "wof:placetype":"venue"
},
  "geometry": {"coordinates":[-111.725288,33.610232],"type":"Point"}
}