{
  "type": "Feature",
  "properties": {
    "addr:full":"16545 E Palisades Blvd Fountain Hills AZ 85268",
    "addr:housenumber":"16545",
    "addr:postcode":"85268",
    "addr:street":"E Palisades Blvd",
    "iso:country":"US",
    "sg:address":"16545 E Palisades Blvd",
    "sg:city":"Fountain Hills",
    "sg:classifiers":[
        {
            "category":"Shopping",
            "subcategory":"Pharmacy",
            "type":"Retail Goods"
        }
    ],
    "sg:phone":"+1 480 836 8337",
    "sg:postcode":"85268",
    "sg:province":"AZ",
    "wof:name":"Osco Drug 9279",
    "wof:placetype":"venue"
},
  "geometry": {"coordinates":[-111.72528800000001,33.610232],"type":"Point"}
}