{
  "type": "Feature",
  "properties": {
    "iso:country":"US",
    "sg:address":"14843 N Northsight Blvd",
    "sg:city":"Scottsdale",
    "sg:classifiers":[
        {
            "category":"Sports & Exercise",
            "subcategory":"Gym",
            "type":"Entertainment"
        }
    ],
    "sg:phone":"+1 480 661 1022",
    "sg:postcode":"85260",
    "sg:province":"AZ",
    "sg:tags":[
        "club",
        "health",
        "studio",
        "gymnasium"
    ],
    "sg:website":"www.goldsgym.com",
    "wof:name":"Gold's Gym",
    "wof:placetype":"venue"
},
  "geometry": {"coordinates":[-111.897612,33.620753],"type":"Point"}
}