{
  "type": "Feature",
  "properties": {
    "addr:full":"175 S Hamilton Pl Bdg 2 1 Bldg 2 Ste 102 Gilbert AZ 85233",
    "addr:housenumber":"175;2 1 bldg 2 ste 102",
    "addr:postcode":"85233",
    "addr:street":"S Hamilton Pl Bdg",
    "iso:country":"US",
    "sg:address":"175 S Hamilton Pl Bdg 2 1 Bldg 2 Ste 102",
    "sg:city":"Gilbert",
    "sg:classifiers":[
        {
            "category":"Professional",
            "subcategory":"Detective & Security Services",
            "type":"Services"
        }
    ],
    "sg:phone":"+1 480 855 9359",
    "sg:postcode":"85233",
    "sg:province":"AZ",
    "sg:tags":[
        "guard",
        "patrol"
    ],
    "wof:name":"Surveillance Security, Inc.",
    "wof:placetype":"venue"
},
  "geometry": {"coordinates":[-111.832185,33.348842],"type":"Point"}
}