{
  "type": "Feature",
  "properties": {
    "addr:full":"614 N Warren Ave Winslow AZ 86047",
    "addr:housenumber":"614",
    "addr:postcode":"86047",
    "addr:street":"N Warren Ave",
    "iso:country":"US",
    "sg:address":"614 N Warren Ave",
    "sg:city":"Winslow",
    "sg:classifiers":[
        {
            "category":"Organizations",
            "subcategory":"Religious Organization",
            "type":"Services"
        }
    ],
    "sg:phone":"+1 928 289 1272",
    "sg:postcode":"86047",
    "sg:province":"AZ",
    "sg:tags":[
        "testament",
        "churches-church",
        "christ-new",
        "church"
    ],
    "wof:name":"Church Of Christ",
    "wof:placetype":"venue"
},
  "geometry": {"coordinates":[-110.697011,35.027384],"type":"Point"}
}