{
  "type": "Feature",
  "properties": {
    "addr:full":"1163 S Naco Hwy Bisbee AZ 85603",
    "addr:housenumber":"1163",
    "addr:postcode":"85603",
    "addr:street":"S Naco Hwy",
    "iso:country":"US",
    "sg:address":"1163 S Naco Hwy",
    "sg:city":"Bisbee",
    "sg:classifiers":[
        {
            "category":"Insurance",
            "subcategory":"Hazard Insurance",
            "type":"Services"
        }
    ],
    "sg:phone":"+1 520 432 5411",
    "sg:postcode":"85603",
    "sg:province":"AZ",
    "sg:tags":[
        "commercial",
        "business"
    ],
    "sg:website":"http://www.statefarm.com",
    "wof:name":"State Farm Insurance",
    "wof:placetype":"venue"
},
  "geometry": {"coordinates":[-109.924688,31.379267],"type":"Point"}
}