{
  "type": "Feature",
  "properties": {
    "addr:full":"7042 W Tether Trl Peoria AZ 85383",
    "addr:housenumber":"7042",
    "addr:postcode":"85383",
    "addr:street":"W Tether Trl",
    "iso:country":"US",
    "sg:address":"7042 W Tether Trl",
    "sg:city":"Peoria",
    "sg:classifiers":[
        {
            "category":"Communications",
            "subcategory":"Radio Station",
            "type":"Services"
        }
    ],
    "sg:phone":"+1 623 572 8338",
    "sg:postcode":"85383",
    "sg:province":"AZ",
    "sg:tags":[
        "broadcasting",
        "music",
        "except"
    ],
    "wof:name":"Vnn",
    "wof:placetype":"venue"
},
  "geometry": {"coordinates":[-112.212774,33.723627],"type":"Point"}
}