{
  "type": "Feature",
  "properties": {
    "iso:country":"US",
    "sg:address":"5471 N Roadrunner Dr",
    "sg:city":"Prescott Valley",
    "sg:classifiers":[
        {
            "category":"Building & Trades",
            "subcategory":"Construction",
            "type":"Services"
        }
    ],
    "sg:phone":"+1 928 775 3542",
    "sg:postcode":"86314",
    "sg:province":"AZ",
    "sg:tags":[
        "nonresidential"
    ],
    "wof:name":"Raf Construction",
    "wof:placetype":"venue"
},
  "geometry": {"coordinates":[-112.316247,34.625526],"type":"Point"}
}