{
  "type": "Feature",
  "properties": {
    "iso:country":"US",
    "sg:address":"3718 W Calavar Rd",
    "sg:city":"Phoenix",
    "sg:classifiers":[
        {
            "category":"Building & Trades",
            "subcategory":"Cleaning & Sanitation",
            "type":"Services"
        }
    ],
    "sg:phone":"+1 602 861 8077",
    "sg:postcode":"85053",
    "sg:province":"AZ",
    "sg:tags":[
        "window"
    ],
    "wof:name":"Dc Window Washing",
    "wof:placetype":"venue"
},
  "geometry": {"coordinates":[-112.139336,33.612386],"type":"Point"}
}