{
  "type": "Feature",
  "properties": {
    "iso:country":"US",
    "sg:address":"16801 N 49th St",
    "sg:city":"Scottsdale",
    "sg:classifiers":[
        {
            "category":"Health Services",
            "subcategory":"Clinic",
            "type":"Services"
        }
    ],
    "sg:phone":"+1 480 595 6353",
    "sg:postcode":"85254",
    "sg:province":"AZ",
    "sg:tags":[
        "holistic",
        "practitioner"
    ],
    "wof:name":"Stellar Mind Communications",
    "wof:placetype":"venue"
},
  "geometry": {"coordinates":[-111.974666,33.639556],"type":"Point"}
}