{
  "type": "Feature",
  "properties": {
    "addr:full":"11201 N 23rd Ave Ste 104 Phoenix AZ 85029",
    "addr:housenumber":"11201",
    "addr:postcode":"85029",
    "addr:street":"N 23Rd Ave Ste 104",
    "iso:country":"US",
    "sg:address":"11201 N 23rd Ave Ste 104",
    "sg:city":"Phoenix",
    "sg:classifiers":[
        {
            "category":"Building & Trades",
            "subcategory":"Plumbing",
            "type":"Services"
        }
    ],
    "sg:phone":"+1 602 678 0008",
    "sg:postcode":"85029",
    "sg:province":"AZ",
    "sg:tags":[
        "plumber",
        "industrial",
        "contractors-commercial"
    ],
    "wof:name":"San Cor Plumbing",
    "wof:placetype":"venue"
},
  "geometry": {"coordinates":[-112.108093,33.587879],"type":"Point"}
}