{
  "type": "Feature",
  "properties": {
    "iso:country":"US",
    "sg:address":"7219 E Lakeview Ave",
    "sg:city":"Mesa",
    "sg:classifiers":[
        {
            "category":"Shopping",
            "subcategory":"Books",
            "type":"Retail Goods"
        },
        {
            "category":"Shopping",
            "type":"Retail Goods"
        }
    ],
    "sg:phone":"+1 602 617 4104",
    "sg:postcode":"85209",
    "sg:province":"AZ",
    "sg:tags":[
        "bible",
        "religious"
    ],
    "wof:name":"All Source",
    "wof:placetype":"venue"
},
  "geometry": {"coordinates":[-111.677035,33.375542],"type":"Point"}
}