{
  "type": "Feature",
  "properties": {
    "iso:country":"US",
    "sg:address":"926 Black Dr",
    "sg:city":"Prescott",
    "sg:classifiers":[
        {
            "category":"Retail",
            "subcategory":"Animal Services",
            "type":"Services"
        }
    ],
    "sg:phone":"+1 928 776 1720",
    "sg:postcode":"86305",
    "sg:province":"AZ",
    "sg:tags":[
        "pet",
        "grooming",
        "washing"
    ],
    "wof:name":"Donna's Dog Grooming",
    "wof:placetype":"venue"
},
  "geometry": {"coordinates":[-112.48393299999999,34.56662],"type":"Point"}
}