{
  "type": "Feature",
  "properties": {
    "iso:country":"US",
    "sg:address":"4657 E Cotton Gin Loop",
    "sg:city":"Phoenix",
    "sg:classifiers":[
        {
            "category":"Wholesale",
            "subcategory":"Computers",
            "type":"Manufacturing & Wholesale Goods"
        },
        {
            "category":"Retail",
            "subcategory":"Repair Shop",
            "type":"Services"
        },
        {
            "category":"Professional",
            "subcategory":"Computer Services",
            "type":"Services"
        }
    ],
    "sg:phone":"+1 480 998 0555",
    "sg:postcode":"85040",
    "sg:province":"AZ",
    "sg:tags":[
        "designer",
        "network",
        "technical",
        "consultant",
        "assistance",
        "system",
        "equipment",
        "design",
        "equipment-service",
        "support",
        "repair-business"
    ],
    "sg:website":"http://www.extremeintegration.net",
    "wof:name":"Extreme Integration",
    "wof:placetype":"venue"
},
  "geometry": {"coordinates":[-111.980918,33.404788],"type":"Point"}
}