{
  "type": "Feature",
  "properties": {
    "iso:country":"US",
    "sg:address":"8402 S Avenida del Yaqui",
    "sg:city":"Guadalupe",
    "sg:classifiers":[
        {
            "category":"Food & Beverages",
            "subcategory":"Bakery",
            "type":"Retail Goods"
        },
        {
            "category":"Bakery",
            "type":"Food & Drink"
        }
    ],
    "sg:phone":"+1 480 284 4830",
    "sg:postcode":"85283",
    "sg:province":"AZ",
    "sg:tags":[
        "bakers-wholesale"
    ],
    "wof:name":"El Pan Nuestro Bakery",
    "wof:placetype":"venue"
},
  "geometry": {"coordinates":[-111.96315199999999,33.370733],"type":"Point"}
}