{
  "type": "Feature",
  "properties": {
    "iso:country":"US",
    "sg:address":"7110 N Giaconda Way",
    "sg:city":"Tucson",
    "sg:classifiers":[
        {
            "category":"Building & Trades",
            "subcategory":"Pest Control",
            "type":"Services"
        }
    ],
    "sg:phone":"+1 520 531 1390",
    "sg:postcode":"85704",
    "sg:province":"AZ",
    "wof:name":"Frank Pinnell's Prime Pest",
    "wof:placetype":"venue"
},
  "geometry": {"coordinates":[-110.985955,32.336362],"type":"Point"}
}