{
  "type": "Feature",
  "properties": {
    "iso:country":"US",
    "sg:address":"800 N 54th St",
    "sg:city":"Chandler",
    "sg:classifiers":[
        {
            "category":"Shopping",
            "type":"Retail Goods"
        }
    ],
    "sg:phone":"+1 480 783 5550",
    "sg:postcode":"85226",
    "sg:province":"AZ",
    "sg:tags":[
        "phone",
        "cellular"
    ],
    "wof:name":"Verizon",
    "wof:placetype":"venue"
},
  "geometry": {"coordinates":[-111.96839900000001,33.31607],"type":"Point"}
}