{
  "type": "Feature",
  "properties": {
    "addr:full":"99 E 5th St Douglas AZ 85607",
    "addr:housenumber":"99",
    "addr:postcode":"85607",
    "addr:street":"E 5Th St",
    "iso:country":"US",
    "sg:address":"99 E 5th St",
    "sg:city":"Douglas",
    "sg:classifiers":[
        {
            "category":"Fast Food",
            "type":"Food & Drink"
        },
        {
            "category":"Restaurant",
            "type":"Food & Drink"
        }
    ],
    "sg:phone":"+1 520 805 0597",
    "sg:postcode":"85607",
    "sg:province":"AZ",
    "sg:tags":[
        "american",
        "hot",
        "hamburger",
        "dog"
    ],
    "sg:website":"http://www.bk.com",
    "wof:name":"Burger King",
    "wof:placetype":"venue"
},
  "geometry": {"coordinates":[-109.55847199999999,31.33924],"type":"Point"}
}