{
  "type": "Feature",
  "properties": {
    "iso:country":"US",
    "sg:address":"8600 State Hwy 99",
    "sg:city":"Winslow",
    "sg:classifiers":[
        {
            "category":"Professional",
            "subcategory":"Research",
            "type":"Services"
        }
    ],
    "sg:phone":"+1 928 289 3757",
    "sg:postcode":"86047",
    "sg:province":"AZ",
    "sg:tags":[
        "environmental",
        "ecological"
    ],
    "wof:name":"Despain Environmental Managmnt",
    "wof:placetype":"venue"
},
  "geometry": {"coordinates":[-110.67087,34.994564],"type":"Point"}
}