{
  "type": "Feature",
  "properties": {
    "iso:country":"US",
    "sg:address":"3401 E Illini St",
    "sg:city":"Phoenix",
    "sg:classifiers":[
        {
            "category":"Building & Trades",
            "subcategory":"Construction",
            "type":"Services"
        }
    ],
    "sg:phone":"+1 602 437 4461",
    "sg:postcode":"85040",
    "sg:province":"AZ",
    "sg:tags":[
        "paving",
        "utility"
    ],
    "wof:name":"Specialized Servicing Utility",
    "wof:placetype":"venue"
},
  "geometry": {"coordinates":[-112.004019,33.412566],"type":"Point"}
}