{
  "type": "Feature",
  "properties": {
    "iso:country":"US",
    "sg:address":"6505 E Desert Cove Ave",
    "sg:city":"Scottsdale",
    "sg:classifiers":[
        {
            "category":"Banks & Credit Unions",
            "subcategory":"Bank",
            "type":"Services"
        }
    ],
    "sg:phone":"+1 480 905 0141",
    "sg:postcode":"85254",
    "sg:province":"AZ",
    "sg:tags":[
        "financing"
    ],
    "wof:name":"Arizona Development Finance Gr",
    "wof:placetype":"venue"
},
  "geometry": {"coordinates":[-111.939664,33.584603],"type":"Point"}
}