{
  "type": "Feature",
  "properties": {
    "addr:full":"1799 Kiowa Ave Lake Havasu City AZ 86403",
    "addr:housenumber":"1799",
    "addr:postcode":"86403",
    "addr:street":"Kiowa Ave",
    "iso:country":"US",
    "sg:address":"1799 Kiowa Ave",
    "sg:city":"Lake Havasu City",
    "sg:classifiers":[
        {
            "category":"Professional",
            "subcategory":"Accounting & Tax Preparation",
            "type":"Services"
        }
    ],
    "sg:phone":"+1 928 854 3469",
    "sg:postcode":"86403",
    "sg:province":"AZ",
    "sg:tags":[
        "accountant"
    ],
    "wof:name":"Kim Jackson Accounting & Taxes",
    "wof:placetype":"venue"
},
  "geometry": {"coordinates":[-114.350993,34.502987],"type":"Point"}
}