{
  "type": "Feature",
  "properties": {
    "iso:country":"US",
    "sg:address":"3767 Karicio Ln",
    "sg:city":"Prescott",
    "sg:classifiers":[
        {
            "category":"Banks & Credit Unions",
            "subcategory":"Bank",
            "type":"Services"
        }
    ],
    "sg:phone":"+1 928 777 8451",
    "sg:postcode":"86303",
    "sg:province":"AZ",
    "sg:tags":[
        "loan",
        "real estate"
    ],
    "wof:name":"Wallick & Volk Mortgage",
    "wof:placetype":"venue"
},
  "geometry": {"coordinates":[-112.398771,34.545571],"type":"Point"}
}