{
  "type": "Feature",
  "properties": {
    "iso:country":"US",
    "sg:address":"3635 E Turney Ave Apt 14",
    "sg:city":"Phoenix",
    "sg:classifiers":[
        {
            "category":"Manufacturing",
            "subcategory":"Glass & Minerals",
            "type":"Manufacturing & Wholesale Goods"
        }
    ],
    "sg:phone":"+1 602 539 7642",
    "sg:postcode":"85018",
    "sg:province":"AZ",
    "wof:name":"Element Productions Group",
    "wof:placetype":"venue"
},
  "geometry": {"coordinates":[-112.00293600000001,33.500701],"type":"Point"}
}