{
  "type": "Feature",
  "properties": {
    "iso:country":"US",
    "sg:address":"81 N White Mountain Rd",
    "sg:city":"Show Low",
    "sg:classifiers":[
        {
            "category":"Home & Garden",
            "subcategory":"Building Materials",
            "type":"Retail Goods"
        }
    ],
    "sg:phone":"+1 928 537 7272",
    "sg:postcode":"85901",
    "sg:province":"AZ",
    "sg:tags":[
        "glass",
        "window",
        "plate"
    ],
    "wof:name":"J & L Mobile Glass Co",
    "wof:placetype":"venue"
},
  "geometry": {"coordinates":[-110.028555,34.250573],"type":"Point"}
}