{
  "type": "Feature",
  "properties": {
    "iso:country":"US",
    "sg:address":"411 W Congress St",
    "sg:city":"Tucson",
    "sg:classifiers":[
        {
            "category":"Real Estate",
            "subcategory":"Real Estate Agent",
            "type":"Services"
        }
    ],
    "sg:phone":"+1 520 882 4200",
    "sg:postcode":"85701",
    "sg:province":"AZ",
    "wof:name":"Financial Associates Inc",
    "wof:placetype":"venue"
},
  "geometry": {"coordinates":[-110.978121,32.221044],"type":"Point"}
}