{
  "type": "Feature",
  "properties": {
    "iso:country":"US",
    "sg:address":"2160 N Alma School Rd",
    "sg:city":"Chandler",
    "sg:classifiers":[
        {
            "category":"Manufacturing",
            "subcategory":"Signs",
            "type":"Manufacturing & Wholesale Goods"
        }
    ],
    "sg:phone":"+1 480 821 1100",
    "sg:postcode":"85224",
    "sg:province":"AZ",
    "sg:tags":[
        "manufacture"
    ],
    "wof:name":"Sign-A-Rama",
    "wof:placetype":"venue"
},
  "geometry": {"coordinates":[-111.85913499999999,33.335421],"type":"Point"}
}