{
  "type": "Feature",
  "properties": {
    "iso:country":"US",
    "sg:address":"1455 S Stapley Drive Suite 9",
    "sg:city":"Mesa",
    "sg:classifiers":[
        {
            "category":"Shopping",
            "subcategory":"Shoes",
            "type":"Retail Goods"
        }
    ],
    "sg:phone":"+1 480 497 5502",
    "sg:postcode":"85204",
    "sg:province":"AZ",
    "sg:tags":[
        "store"
    ],
    "wof:name":"American Uniform",
    "wof:placetype":"venue"
},
  "geometry": {"coordinates":[-111.80551800000001,33.388972],"type":"Point"}
}