{
  "type": "Feature",
  "properties": {
    "iso:country":"US",
    "sg:address":"2727 N Swan Rd",
    "sg:city":"Tucson",
    "sg:classifiers":[
        {
            "category":"Education",
            "subcategory":"School",
            "type":"Public Place"
        }
    ],
    "sg:phone":"+1 520 318 3824",
    "sg:postcode":"85712",
    "sg:province":"AZ",
    "sg:tags":[
        "religious"
    ],
    "wof:name":"Carden Christian Academy",
    "wof:placetype":"venue"
},
  "geometry": {"coordinates":[-110.892603,32.257827],"type":"Point"}
}