{
  "type": "Feature",
  "properties": {
    "addr:full":"2224 W Desert Cove Ave Phoenix AZ 85029",
    "addr:housenumber":"2224",
    "addr:postcode":"85029",
    "addr:street":"W Desert Cove Ave",
    "iso:country":"US",
    "sg:address":"2224 W Desert Cove Ave",
    "sg:city":"Phoenix",
    "sg:classifiers":[
        {
            "category":"Manufacturing",
            "subcategory":"Building Materials",
            "type":"Manufacturing & Wholesale Goods"
        },
        {
            "category":"Home & Garden",
            "subcategory":"Furniture",
            "type":"Retail Goods"
        }
    ],
    "sg:phone":"+1 602 674 8088",
    "sg:postcode":"85029",
    "sg:province":"AZ",
    "sg:tags":[
        "cabinet",
        "wood",
        "kitchen",
        "mfg"
    ],
    "wof:name":"Saguaro Custom Cabinets",
    "wof:placetype":"venue"
},
  "geometry": {"coordinates":[-112.107438,33.58583],"type":"Point"}
}