{
  "type": "Feature",
  "properties": {
    "addr:full":"4220 S Arizona Avenue Chandler AZ 85248",
    "addr:housenumber":"4220",
    "addr:postcode":"85248",
    "addr:street":"S Arizona Avenue",
    "iso:country":"US",
    "sg:address":"4220 S Arizona Avenue",
    "sg:city":"Chandler",
    "sg:classifiers":[
        {
            "category":"Shopping",
            "subcategory":"Pets & Pet Supplies",
            "type":"Retail Goods"
        }
    ],
    "sg:phone":"+1 480 802 4504",
    "sg:postcode":"85248",
    "sg:province":"AZ",
    "sg:tags":[
        "store"
    ],
    "sg:website":"www.petco.com",
    "wof:name":"Petco",
    "wof:placetype":"venue"
},
  "geometry": {"coordinates":[-111.84850299999999,33.250118],"type":"Point"}
}