{
  "type": "Feature",
  "properties": {
    "iso:country":"US",
    "sg:address":"700 S 52nd St",
    "sg:city":"Tempe",
    "sg:classifiers":[
        {
            "category":"Wholesale",
            "subcategory":"Machinery & Supplies",
            "type":"Manufacturing & Wholesale Goods"
        }
    ],
    "sg:phone":"+1 480 968 8187",
    "sg:postcode":"85281",
    "sg:province":"AZ",
    "sg:tags":[
        "industrial"
    ],
    "wof:name":"Pro Fasteners Inc",
    "wof:placetype":"venue"
},
  "geometry": {"coordinates":[-111.969694,33.425532],"type":"Point"}
}