{
  "type": "Feature",
  "properties": {
    "iso:country":"US",
    "sg:address":"4709 N 10th St",
    "sg:city":"Phoenix",
    "sg:phone":"+1 602 615 6100",
    "sg:postcode":"85014",
    "sg:province":"AZ",
    "wof:name":"Candles White Light",
    "wof:placetype":"venue"
},
  "geometry": {"coordinates":[-112.06063,33.505736],"type":"Point"}
}