{
  "type": "Feature",
  "properties": {
    "iso:country":"US",
    "sg:address":"5253 W Jupiter Way S",
    "sg:city":"Chandler",
    "sg:classifiers":[
        {
            "category":"Professional",
            "subcategory":"Business Services",
            "type":"Services"
        }
    ],
    "sg:phone":"+1 480 628 9004",
    "sg:postcode":"85226",
    "sg:province":"AZ",
    "wof:name":"Iron Images",
    "wof:placetype":"venue"
},
  "geometry": {"coordinates":[-111.931926,33.300392],"type":"Point"}
}