{
  "type": "Feature",
  "properties": {
    "iso:country":"US",
    "sg:address":"7400 E Mcdonald Dr # 110",
    "sg:city":"Scottsdale",
    "sg:classifiers":[
        {
            "category":"Wholesale",
            "subcategory":"Jewelry",
            "type":"Manufacturing & Wholesale Goods"
        }
    ],
    "sg:phone":"+1 480 609 8777",
    "sg:postcode":"85250",
    "sg:province":"AZ",
    "sg:tags":[
        "diamond",
        "cutter"
    ],
    "sg:website":"http://www.bellarri.com",
    "wof:name":"Bellarri Intl Collectn",
    "wof:placetype":"venue"
},
  "geometry": {"coordinates":[-111.921612,33.524079],"type":"Point"}
}