{
  "type": "Feature",
  "properties": {
    "iso:country":"US",
    "sg:address":"1475 S Alvernon Way",
    "sg:city":"Tucson",
    "sg:classifiers":[
        {
            "category":"Professional",
            "type":"Services"
        }
    ],
    "sg:phone":"+1 520 750 0654",
    "sg:postcode":"85711",
    "sg:province":"AZ",
    "wof:name":"James Moseley Jr",
    "wof:placetype":"venue"
},
  "geometry": {"coordinates":[-110.909503,32.205012],"type":"Point"}
}