{
  "type": "Feature",
  "properties": {
    "iso:country":"US",
    "sg:address":"729 S 77th St",
    "sg:city":"Mesa",
    "sg:classifiers":[
        {
            "category":"Professional",
            "type":"Services"
        }
    ],
    "sg:phone":"+1 480 984 3626",
    "sg:postcode":"85208",
    "sg:province":"AZ",
    "wof:name":"Mgi Inc",
    "wof:placetype":"venue"
},
  "geometry": {"coordinates":[-111.665824,33.402209],"type":"Point"}
}