{
  "type": "Feature",
  "properties": {
    "addr:full":"2895 S Alma School Road Chandler AZ 85248",
    "addr:housenumber":"2895",
    "addr:postcode":"85248",
    "addr:street":"S Alma School Road",
    "iso:country":"US",
    "sg:address":"2895 S Alma School Road",
    "sg:city":"Chandler",
    "sg:classifiers":[
        {
            "category":"Shopping",
            "subcategory":"Hobbies, Toys, & Games",
            "type":"Retail Goods"
        }
    ],
    "sg:phone":"+1 480 917 3285",
    "sg:postcode":"85248",
    "sg:province":"AZ",
    "sg:tags":[
        "shop",
        "hobby"
    ],
    "sg:website":"www.ebgames.com",
    "wof:name":"Eb Games",
    "wof:placetype":"venue"
},
  "geometry": {"coordinates":[-111.85847,33.263564],"type":"Point"}
}