{
  "type": "Feature",
  "properties": {
    "addr:full":"670 N Tower Ave Chandler AZ 85225",
    "addr:housenumber":"670",
    "addr:postcode":"85225",
    "addr:street":"N Tower Ave",
    "iso:country":"US",
    "sg:address":"670 N Tower Ave",
    "sg:city":"Chandler",
    "sg:classifiers":[
        {
            "category":"Manufacturing",
            "subcategory":"Building Materials",
            "type":"Manufacturing & Wholesale Goods"
        }
    ],
    "sg:phone":"+1 480 820 1120",
    "sg:postcode":"85225",
    "sg:province":"AZ",
    "sg:tags":[
        "mfg"
    ],
    "wof:name":"Splinters Woodworks",
    "wof:placetype":"venue"
},
  "geometry": {"coordinates":[-111.811324,33.314456],"type":"Point"}
}