{
  "type": "Feature",
  "properties": {
    "iso:country":"US",
    "sg:address":"5854 E Albany St",
    "sg:city":"Mesa",
    "sg:classifiers":[
        {
            "category":"Real Estate",
            "subcategory":"Real Estate Agent",
            "type":"Services"
        }
    ],
    "sg:phone":"+1 480 641 4400",
    "sg:postcode":"85205",
    "sg:province":"AZ",
    "wof:name":"Farnsworth Realty & Management",
    "wof:placetype":"venue"
},
  "geometry": {"coordinates":[-111.702883,33.418472],"type":"Point"}
}