{
  "type": "Feature",
  "properties": {
    "iso:country":"US",
    "sg:address":"2343 N 27th Ave",
    "sg:city":"Phoenix",
    "sg:classifiers":[
        {
            "category":"Manufacturing",
            "subcategory":"Petroleum Products",
            "type":"Manufacturing & Wholesale Goods"
        }
    ],
    "sg:phone":"+1 602 353 4935",
    "sg:postcode":"85009",
    "sg:province":"AZ",
    "sg:tags":[
        "bulk",
        "station",
        "refiner"
    ],
    "sg:website":"www.phoenixfuel.com",
    "wof:name":"Phoenix Fuel Co Inc",
    "wof:placetype":"venue"
},
  "geometry": {"coordinates":[-112.117008,33.476384],"type":"Point"}
}