{
  "type": "Feature",
  "properties": {
    "addr:full":"2140 W Shady Glen Ave Phoenix AZ 85023",
    "addr:housenumber":"2140",
    "addr:postcode":"85023",
    "addr:street":"W Shady Glen Ave",
    "iso:country":"US",
    "sg:address":"2140 W Shady Glen Ave",
    "sg:city":"Phoenix",
    "sg:classifiers":[
        {
            "category":"Travel",
            "subcategory":"Hotels & Motels",
            "type":"Entertainment"
        },
        {
            "category":"Personal",
            "type":"Services"
        }
    ],
    "sg:phone":"+1 602 993 8524",
    "sg:postcode":"85023",
    "sg:province":"AZ",
    "sg:tags":[
        "assistant",
        "concierge"
    ],
    "wof:name":"Shannon Vitkovich",
    "wof:placetype":"venue"
},
  "geometry": {"coordinates":[-112.106431,33.64771],"type":"Point"}
}