{
  "type": "Feature",
  "properties": {
    "addr:full":"1825 N Kolb Rd Tucson AZ 85715",
    "addr:housenumber":"1825",
    "addr:postcode":"85715",
    "addr:street":"N Kolb Rd",
    "iso:country":"US",
    "sg:address":"1825 N Kolb Rd",
    "sg:city":"Tucson",
    "sg:classifiers":[
        {
            "category":"Professional",
            "subcategory":"Research",
            "type":"Services"
        }
    ],
    "sg:phone":"+1 520 290 2510",
    "sg:postcode":"85715",
    "sg:province":"AZ",
    "sg:tags":[
        "medical"
    ],
    "sg:website":"www.xeric.org",
    "wof:name":"Acrc/Arizona Clinical Research",
    "wof:placetype":"venue"
},
  "geometry": {"coordinates":[-110.844649,32.243442],"type":"Point"}
}