{
  "type": "Feature",
  "properties": {
    "iso:country":"US",
    "sg:address":"2950 S Alma School Rd",
    "sg:city":"Mesa",
    "sg:classifiers":[
        {
            "category":"Shopping",
            "type":"Retail Goods"
        }
    ],
    "sg:phone":"+1 480 730 5999",
    "sg:postcode":"85210",
    "sg:province":"AZ",
    "sg:tags":[
        "aquarium"
    ],
    "wof:name":"All Aquatics",
    "wof:placetype":"venue"
},
  "geometry": {"coordinates":[-111.859146,33.36297],"type":"Point"}
}