{
  "type": "Feature",
  "properties": {
    "iso:country":"US",
    "sg:address":"6015 N 57th Dr",
    "sg:city":"Glendale",
    "sg:classifiers":[
        {
            "category":"Autos & Motor Vehicles",
            "subcategory":"Motorcycle Sales",
            "type":"Retail Goods"
        }
    ],
    "sg:phone":"+1 623 931 9965",
    "sg:postcode":"85301",
    "sg:province":"AZ",
    "sg:tags":[
        "scooter"
    ],
    "wof:name":"Special Maching Technology",
    "wof:placetype":"venue"
},
  "geometry": {"coordinates":[-112.18303299999999,33.524257],"type":"Point"}
}