{
  "type": "Feature",
  "properties": {
    "addr:full":"1803 S Beverly Mesa AZ 85210",
    "addr:housenumber":"1803",
    "addr:postcode":"85210",
    "addr:street":"S Beverly",
    "iso:country":"US",
    "sg:address":"1803 S Beverly",
    "sg:city":"Mesa",
    "sg:classifiers":[
        {
            "category":"Communications",
            "subcategory":"Film & Video Production",
            "type":"Services"
        }
    ],
    "sg:phone":"+1 480 545 5344",
    "sg:postcode":"85210",
    "sg:province":"AZ",
    "sg:tags":[
        "services-commercial"
    ],
    "wof:name":"Jerry's Video Transfer Service",
    "wof:placetype":"venue"
},
  "geometry": {"coordinates":[-111.854946,33.381831],"type":"Point"}
}