{
  "type": "Feature",
  "properties": {
    "iso:country":"US",
    "sg:address":"1320 E Benson Hwy",
    "sg:city":"Tucson",
    "sg:classifiers":[
        {
            "category":"Home & Garden",
            "subcategory":"Building Materials",
            "type":"Retail Goods"
        },
        {
            "category":"Building & Trades",
            "subcategory":"Construction",
            "type":"Services"
        }
    ],
    "sg:phone":"+1 520 624 3255",
    "sg:postcode":"85714",
    "sg:province":"AZ",
    "sg:tags":[
        "glass",
        "window",
        "contractor",
        "plate"
    ],
    "wof:name":"Diamond Glass Works",
    "wof:placetype":"venue"
},
  "geometry": {"coordinates":[-110.949653,32.175066],"type":"Point"}
}