{
  "type": "Feature",
  "properties": {
    "addr:full":"16008 N 81st St Scottsdale AZ 85260",
    "addr:housenumber":"16008",
    "addr:postcode":"85260",
    "addr:street":"N 81St St",
    "iso:country":"US",
    "sg:address":"16008 N 81st St",
    "sg:city":"Scottsdale",
    "sg:classifiers":[
        {
            "category":"Manufacturing",
            "subcategory":"Tools & Machinery",
            "type":"Manufacturing & Wholesale Goods"
        }
    ],
    "sg:phone":"+1 480 483 1214",
    "sg:postcode":"85260",
    "sg:province":"AZ",
    "sg:tags":[
        "manufacture",
        "design",
        "laser",
        "system"
    ],
    "wof:name":"Universal Laser Systems Inc",
    "wof:placetype":"venue"
},
  "geometry": {"coordinates":[-111.905997,33.631636],"type":"Point"}
}