{
  "type": "Feature",
  "properties": {
    "addr:full":"8946 E Millett Dr Tucson AZ 85710",
    "addr:housenumber":"8946",
    "addr:postcode":"85710",
    "addr:street":"E Millett Dr",
    "iso:country":"US",
    "sg:address":"8946 E Millett Dr",
    "sg:city":"Tucson",
    "sg:classifiers":[
        {
            "category":"Real Estate",
            "subcategory":"Real Estate Agent",
            "type":"Services"
        }
    ],
    "sg:phone":"+1 520 790 0015",
    "sg:postcode":"85710",
    "sg:province":"AZ",
    "sg:tags":[
        "appraiser"
    ],
    "sg:website":"http://www.azproappraisal.com",
    "wof:name":"J-D Biggers Appraisal & Cnsltn",
    "wof:placetype":"venue"
},
  "geometry": {"coordinates":[-110.801314,32.214927],"type":"Point"}
}