{
  "type": "Feature",
  "properties": {
    "iso:country":"US",
    "sg:address":"3151 Stockton Hill Rd",
    "sg:city":"Kingman",
    "sg:classifiers":[
        {
            "category":"Banks & Credit Unions",
            "subcategory":"Bank",
            "type":"Services"
        }
    ],
    "sg:phone":"+1 928 692 7057",
    "sg:postcode":"86401",
    "sg:province":"AZ",
    "sg:tags":[
        "financing"
    ],
    "wof:name":"Arizona Auto Lenders",
    "wof:placetype":"venue"
},
  "geometry": {"coordinates":[-114.035163,35.213307],"type":"Point"}
}