{
  "type": "Feature",
  "properties": {
    "iso:country":"US",
    "sg:address":"9305 W Thomas Rd Ste 300",
    "sg:city":"Phoenix",
    "sg:classifiers":[
        {
            "category":"Health Services",
            "subcategory":"Clinic",
            "type":"Services"
        },
        {
            "category":"Health Services",
            "subcategory":"Medical Lab",
            "type":"Services"
        },
        {
            "category":"Professional",
            "subcategory":"Testing Lab",
            "type":"Services"
        }
    ],
    "sg:phone":"+1 480 477 0980",
    "sg:postcode":"85037",
    "sg:province":"AZ",
    "sg:tags":[
        "information",
        "aid",
        "blood",
        "drug",
        "typing"
    ],
    "sg:website":"http://www.samedaystdtesting.com",
    "wof:name":"Phoenix Same Day HIV / STD Testing",
    "wof:placetype":"venue"
},
  "geometry": {"coordinates":[-112.261757,33.479549],"type":"Point"}
}