{
  "type": "Feature",
  "properties": {
    "iso:country":"US",
    "sg:address":"5226 W Glass Ln",
    "sg:city":"Laveen",
    "sg:classifiers":[
        {
            "category":"Building & Trades",
            "subcategory":"Construction",
            "type":"Services"
        }
    ],
    "sg:phone":"+1 602 237 0405",
    "sg:postcode":"85339",
    "sg:province":"AZ",
    "sg:tags":[
        "home",
        "builder"
    ],
    "wof:name":"Pulte Homes Corp",
    "wof:placetype":"venue"
},
  "geometry": {"coordinates":[-112.171049,33.384513],"type":"Point"}
}