{
  "type": "Feature",
  "properties": {
    "addr:full":"10636 N 71st Way Scottsdale AZ 85254",
    "addr:housenumber":"10636",
    "addr:postcode":"85254",
    "addr:street":"N 71St Way",
    "iso:country":"US",
    "sg:address":"10636 N 71st Way",
    "sg:city":"Scottsdale",
    "sg:classifiers":[
        {
            "category":"Home & Garden",
            "subcategory":"Home Furnishings",
            "type":"Retail Goods"
        },
        {
            "category":"Home & Garden",
            "subcategory":"Carpets & Floor Coverings",
            "type":"Retail Goods"
        }
    ],
    "sg:phone":"+1 480 948 1147",
    "sg:postcode":"85254",
    "sg:province":"AZ",
    "sg:tags":[
        "draperies",
        "curtain",
        "window",
        "material",
        "treatment"
    ],
    "wof:name":"The Decorating Center",
    "wof:placetype":"venue"
},
  "geometry": {"coordinates":[-111.92716,33.583696],"type":"Point"}
}