{
  "type": "Feature",
  "properties": {
    "iso:country":"US",
    "sg:address":"5235 S Kyrene Rd",
    "sg:city":"Tempe",
    "sg:classifiers":[
        {
            "category":"Insurance",
            "subcategory":"Insurance Agent",
            "type":"Services"
        }
    ],
    "sg:phone":"+1 480 838 8622",
    "sg:postcode":"85283",
    "sg:province":"AZ",
    "sg:tags":[
        "agency"
    ],
    "wof:name":"AFLAC",
    "wof:placetype":"venue"
},
  "geometry": {"coordinates":[-111.94589999999999,33.376771],"type":"Point"}
}