{
  "type": "Feature",
  "properties": {
    "iso:country":"US",
    "sg:address":"1395 E Warner Rd",
    "sg:city":"Gilbert",
    "sg:classifiers":[
        {
            "category":"Utilities",
            "subcategory":"Mobile Phone",
            "type":"Services"
        }
    ],
    "sg:phone":"+1 480 633 3188",
    "sg:postcode":"85296",
    "sg:province":"AZ",
    "sg:tags":[
        "communication",
        "radiotelephone"
    ],
    "wof:name":"Bullseye Wireless",
    "wof:placetype":"venue"
},
  "geometry": {"coordinates":[-111.760002,33.335602],"type":"Point"}
}