{
  "type": "Feature",
  "properties": {
    "iso:country":"US",
    "sg:address":"1250 E Fort Lowell Rd",
    "sg:city":"Tucson",
    "sg:classifiers":[
        {
            "category":"Food & Beverages",
            "subcategory":"Groceries & Convenience Stores",
            "type":"Retail Goods"
        }
    ],
    "sg:phone":"+1 520 623 4052",
    "sg:postcode":"85719",
    "sg:province":"AZ",
    "wof:name":"Quik Mart",
    "wof:placetype":"venue"
},
  "geometry": {"coordinates":[-110.952887,32.264712],"type":"Point"}
}