{
  "type": "Feature",
  "properties": {
    "iso:country":"US",
    "sg:address":"2735 W Union Hills Dr",
    "sg:city":"Phoenix",
    "sg:classifiers":[
        {
            "category":"Health Services",
            "subcategory":"Chiropractor",
            "type":"Services"
        }
    ],
    "sg:phone":"+1 602 973 1630",
    "sg:postcode":"85027",
    "sg:province":"AZ",
    "wof:name":"Gonstead Family Chiropractic",
    "wof:placetype":"venue"
},
  "geometry": {"coordinates":[-112.117743,33.654598],"type":"Point"}
}