{
  "type": "Feature",
  "properties": {
    "addr:full":"2478 E Camelback Rd Phoenix AZ 85016",
    "addr:housenumber":"2478",
    "addr:postcode":"85016",
    "addr:street":"E Camelback Rd",
    "iso:country":"US",
    "sg:address":"2478 E Camelback Rd",
    "sg:city":"Phoenix",
    "sg:classifiers":[
        {
            "category":"Shopping",
            "subcategory":"Clothing, Apparel, & Fashions",
            "type":"Retail Goods"
        }
    ],
    "sg:phone":"+1 602 468 4172",
    "sg:postcode":"85016",
    "sg:province":"AZ",
    "wof:name":"Mothers Work",
    "wof:placetype":"venue"
},
  "geometry": {"coordinates":[-112.027473,33.509495],"type":"Point"}
}