{
  "type": "Feature",
  "properties": {
    "iso:country":"US",
    "sg:address":"255524 State Hwy 260",
    "sg:city":"Payson",
    "sg:classifiers":[
        {
            "category":"Food & Beverages",
            "subcategory":"Groceries & Convenience Stores",
            "type":"Retail Goods"
        }
    ],
    "sg:phone":"+1 928 474 9527",
    "sg:postcode":"85541",
    "sg:province":"AZ",
    "wof:name":"Circle K",
    "wof:placetype":"venue"
},
  "geometry": {"coordinates":[-111.265002,34.253436],"type":"Point"}
}