{
  "type": "Feature",
  "properties": {
    "iso:country":"US",
    "sg:address":"724 N Balboa St",
    "sg:city":"Cottonwood",
    "sg:classifiers":[
        {
            "category":"Shopping",
            "subcategory":"Clothing, Apparel, & Fashions",
            "type":"Retail Goods"
        }
    ],
    "sg:phone":"+1 928 634 0544",
    "sg:postcode":"86326",
    "sg:province":"AZ",
    "sg:tags":[
        "military",
        "surplus",
        "store"
    ],
    "wof:name":"Barter Inn",
    "wof:placetype":"venue"
},
  "geometry": {"coordinates":[-112.027372,34.745399],"type":"Point"}
}