{
  "type": "Feature",
  "properties": {
    "addr:full":"985 W Chandler Heights Rd Chandler AZ 85248",
    "addr:housenumber":"985",
    "addr:postcode":"85248",
    "addr:street":"W Chandler Heights Rd",
    "iso:country":"US",
    "sg:address":"985 W Chandler Heights Rd",
    "sg:city":"Chandler",
    "sg:classifiers":[
        {
            "category":"Sports & Exercise",
            "subcategory":"Gym",
            "type":"Entertainment"
        }
    ],
    "sg:phone":"+1 480 276 6436",
    "sg:postcode":"85248",
    "sg:province":"AZ",
    "sg:tags":[
        "trainer"
    ],
    "sg:website":"www.teamcanefitness.com",
    "wof:name":"TCF Ladies Boot Camp",
    "wof:placetype":"venue"
},
  "geometry": {"coordinates":[-111.857552,33.232399],"type":"Point"}
}