{
  "type": "Feature",
  "properties": {
    "iso:country":"US",
    "sg:address":"557 E Juanita Ave",
    "sg:city":"Mesa",
    "sg:classifiers":[
        {
            "category":"Building & Trades",
            "subcategory":"Electrical",
            "type":"Services"
        },
        {
            "category":"Professional",
            "subcategory":"Computer Services",
            "type":"Services"
        }
    ],
    "sg:phone":"+1 480 545 4102",
    "sg:postcode":"85204",
    "sg:province":"AZ",
    "sg:tags":[
        "voltage",
        "wiring",
        "low",
        "contractor"
    ],
    "wof:name":"Smartcom Solutions Inc",
    "wof:placetype":"venue"
},
  "geometry": {"coordinates":[-111.821787,33.38122],"type":"Point"}
}