{
  "type": "Feature",
  "properties": {
    "addr:full":"3601 E Baseline Rd Gilbert AZ 85234",
    "addr:housenumber":"3601",
    "addr:postcode":"85234",
    "addr:street":"E Baseline Rd",
    "iso:country":"US",
    "sg:address":"3601 E Baseline Rd",
    "sg:city":"Gilbert",
    "sg:classifiers":[
        {
            "category":"Restaurant",
            "type":"Food & Drink"
        }
    ],
    "sg:menulink":"http://www.allmenus.com/az/phoenix/204937-taco-bell/menu/",
    "sg:postcode":"85234",
    "sg:province":"AZ",
    "sg:tags":[
        "mexican"
    ],
    "wof:name":"Taco Bell",
    "wof:placetype":"venue"
},
  "geometry": {"coordinates":[-111.753209,33.378373],"type":"Point"}
}