{
  "type": "Feature",
  "properties": {
    "iso:country":"US",
    "sg:address":"3208 N Woodburne Dr",
    "sg:city":"Chandler",
    "sg:classifiers":[
        {
            "category":"Home & Garden",
            "subcategory":"Carpets & Floor Coverings",
            "type":"Retail Goods"
        }
    ],
    "sg:phone":"+1 480 236 4426",
    "sg:postcode":"85224",
    "sg:province":"AZ",
    "wof:name":"Aztech Floor Coatings LLC",
    "wof:placetype":"venue"
},
  "geometry": {"coordinates":[-111.887864,33.352501],"type":"Point"}
}