{
  "type": "Feature",
  "properties": {
    "iso:country":"US",
    "sg:address":"16816 N 53rd St",
    "sg:city":"Scottsdale",
    "sg:classifiers":[
        {
            "category":"Real Estate",
            "subcategory":"Architect",
            "type":"Services"
        }
    ],
    "sg:phone":"+1 602 992 1861",
    "sg:postcode":"85254",
    "sg:province":"AZ",
    "wof:name":"James R Blakeslee",
    "wof:placetype":"venue"
},
  "geometry": {"coordinates":[-111.967488,33.639879],"type":"Point"}
}