{
  "type": "Feature",
  "properties": {
    "iso:country":"US",
    "sg:address":"3914 E Chandler Blvd",
    "sg:city":"Chandler",
    "sg:classifiers":[
        {
            "category":"Restaurant",
            "type":"Food & Drink"
        }
    ],
    "sg:phone":"+1 480 706 0717",
    "sg:postcode":"85224",
    "sg:province":"AZ",
    "wof:name":"Kfc",
    "wof:placetype":"venue"
},
  "geometry": {"coordinates":[-111.876999,33.3279],"type":"Point"}
}