{
  "type": "Feature",
  "properties": {
    "addr:full":"268 W Fry Blvd Sierra Vista AZ 85635",
    "addr:housenumber":"268",
    "addr:postcode":"85635",
    "addr:street":"W Fry Blvd",
    "iso:country":"US",
    "sg:address":"268 W Fry Blvd",
    "sg:city":"Sierra Vista",
    "sg:classifiers":[
        {
            "category":"Deli",
            "type":"Food & Drink"
        }
    ],
    "sg:menulink":"http://www.allmenus.com/az/sierra-vista/125892-blimpie-subs--sandwiches/menu/",
    "sg:phone":"+1 520 439 8808",
    "sg:postcode":"85635",
    "sg:province":"AZ",
    "sg:tags":[
        "wrap",
        "american",
        "sandwich"
    ],
    "wof:name":"Blimpie Subs & Sandwiches",
    "wof:placetype":"venue"
},
  "geometry": {"coordinates":[-110.30217,31.554484],"type":"Point"}
}