{
  "type": "Feature",
  "properties": {
    "addr:full":"6202 N 12th St Phoenix AZ 85014",
    "addr:housenumber":"6202",
    "addr:postcode":"85014",
    "addr:street":"N 12Th St",
    "iso:country":"US",
    "sg:address":"6202 N 12th St",
    "sg:city":"Phoenix",
    "sg:classifiers":[
        {
            "category":"Organizations",
            "subcategory":"Religious Organization",
            "type":"Services"
        }
    ],
    "sg:phone":"+1 602 277 1720",
    "sg:postcode":"85014",
    "sg:province":"AZ",
    "sg:tags":[
        "church"
    ],
    "wof:name":"Madison Baptist Church",
    "wof:placetype":"venue"
},
  "geometry": {"coordinates":[-112.05631,33.52945],"type":"Point"}
}