{
  "type": "Feature",
  "properties": {
    "iso:country":"US",
    "sg:address":"2942 N 24TH ST ST 114443",
    "sg:city":"Phoenix",
    "sg:classifiers":[
        {
            "category":"Professional",
            "subcategory":"Business Services",
            "type":"Services"
        }
    ],
    "sg:phone":"+1 602 424 5746",
    "sg:postcode":"85016",
    "sg:province":"AZ",
    "sg:tags":[
        "management"
    ],
    "wof:name":"CSH Management, Inc",
    "wof:placetype":"venue"
},
  "geometry": {"coordinates":[-112.029739,33.49983],"type":"Point"}
}