{
  "type": "Feature",
  "properties": {
    "addr:full":"8285 E Bowline Rd Tucson AZ 85710",
    "addr:housenumber":"8285",
    "addr:postcode":"85710",
    "addr:street":"E Bowline Rd",
    "iso:country":"US",
    "sg:address":"8285 E Bowline Rd",
    "sg:city":"Tucson",
    "sg:classifiers":[
        {
            "category":"Retail",
            "subcategory":"Auto Repair",
            "type":"Services"
        }
    ],
    "sg:phone":"+1 520 296 6166",
    "sg:postcode":"85710",
    "sg:province":"AZ",
    "sg:tags":[
        "repairing",
        "automobile"
    ],
    "wof:name":"Accurate Automotive",
    "wof:placetype":"venue"
},
  "geometry": {"coordinates":[-110.81721400000001,32.204946],"type":"Point"}
}