{
  "type": "Feature",
  "properties": {
    "addr:full":"3549 N Meadowlark Dr Prescott Valley AZ 86314",
    "addr:housenumber":"3549",
    "addr:postcode":"86314",
    "addr:street":"N Meadowlark Dr",
    "iso:country":"US",
    "sg:address":"3549 N Meadowlark Dr",
    "sg:city":"Prescott Valley",
    "sg:classifiers":[
        {
            "category":"Building & Trades",
            "subcategory":"Landscaping Services",
            "type":"Services"
        }
    ],
    "sg:phone":"+1 928 772 9044",
    "sg:postcode":"86314",
    "sg:province":"AZ",
    "sg:tags":[
        "design",
        "landscape"
    ],
    "wof:name":"Jim Cording Designs",
    "wof:placetype":"venue"
},
  "geometry": {"coordinates":[-112.349368,34.596603],"type":"Point"}
}