{
  "type": "Feature",
  "properties": {
    "iso:country":"US",
    "sg:address":"6404 S Nogales Hwy",
    "sg:city":"Tucson",
    "sg:classifiers":[
        {
            "category":"Shopping",
            "subcategory":"Used Merchandise",
            "type":"Retail Goods"
        },
        {
            "category":"Retail",
            "subcategory":"Repair Shop",
            "type":"Services"
        }
    ],
    "sg:phone":"+1 520 741 7784",
    "sg:postcode":"85706",
    "sg:province":"AZ",
    "sg:tags":[
        "appliance",
        "electrical"
    ],
    "wof:name":"Manny's Appliance",
    "wof:placetype":"venue"
},
  "geometry": {"coordinates":[-110.9616,32.135058],"type":"Point"}
}