{
  "type": "Feature",
  "properties": {
    "iso:country":"US",
    "sg:address":"4464 E Peach Tree Dr",
    "sg:city":"Chandler",
    "sg:classifiers":[
        {
            "category":"Real Estate",
            "subcategory":"Real Estate Services",
            "type":"Services"
        },
        {
            "category":"Real Estate",
            "subcategory":"Real Estate Agent",
            "type":"Services"
        }
    ],
    "sg:phone":"+1 480 917 6987",
    "sg:postcode":"85249",
    "sg:province":"AZ",
    "sg:tags":[
        "buyer",
        "management",
        "broker"
    ],
    "wof:name":"Desert Breeze Realty",
    "wof:placetype":"venue"
},
  "geometry": {"coordinates":[-111.763777,33.208435],"type":"Point"}
}