{
  "type": "Feature",
  "properties": {
    "iso:country":"US",
    "sg:address":"720 S Sabrina",
    "sg:city":"Mesa",
    "sg:classifiers":[
        {
            "category":"Shopping",
            "type":"Retail Goods"
        }
    ],
    "sg:phone":"+1 480 354 5670",
    "sg:postcode":"85208",
    "sg:province":"AZ",
    "sg:tags":[
        "electronic",
        "merchandise"
    ],
    "wof:name":"Airwave Communications",
    "wof:placetype":"venue"
},
  "geometry": {"coordinates":[-111.604387,33.40119],"type":"Point"}
}