{
  "type": "Feature",
  "properties": {
    "iso:country":"US",
    "sg:address":"681 E Nashville Ave",
    "sg:city":"Vail",
    "sg:classifiers":[
        {
            "category":"Building & Trades",
            "subcategory":"Construction",
            "type":"Services"
        }
    ],
    "sg:phone":"+1 520 325 8681",
    "sg:postcode":"85641",
    "sg:province":"AZ",
    "sg:tags":[
        "system",
        "specialty",
        "heating",
        "contractor",
        "air conditioning"
    ],
    "wof:name":"All Pro Rooter & Home Improvement",
    "wof:placetype":"venue"
},
  "geometry": {"coordinates":[-110.75835,31.961005],"type":"Point"}
}