{
  "type": "Feature",
  "properties": {
    "iso:country":"US",
    "sg:address":"2177 E Warner Road",
    "sg:city":"Tempe",
    "sg:classifiers":[
        {
            "category":"Health Services",
            "subcategory":"Doctor",
            "type":"Services"
        },
        {
            "category":"Personal",
            "subcategory":"Hair Removal",
            "type":"Services"
        }
    ],
    "sg:phone":"+1 480 897 3623",
    "sg:postcode":"85284",
    "sg:province":"AZ",
    "sg:tags":[
        "dermatologist"
    ],
    "wof:name":"Burgmeier Richard",
    "wof:placetype":"venue"
},
  "geometry": {"coordinates":[-111.895104,33.334757],"type":"Point"}
}