{
  "type": "Feature",
  "properties": {
    "addr:full":"3515 E Cherokee St Phoenix AZ 85044",
    "addr:housenumber":"3515",
    "addr:postcode":"85044",
    "addr:street":"E Cherokee St",
    "iso:country":"US",
    "sg:address":"3515 E Cherokee St",
    "sg:city":"Phoenix",
    "sg:classifiers":[
        {
            "category":"Health Services",
            "subcategory":"Doctor",
            "type":"Services"
        }
    ],
    "sg:phone":"+1 480 893 8366",
    "sg:postcode":"85044",
    "sg:province":"AZ",
    "sg:tags":[
        "physician",
        "radiology",
        "pediatrics-radiology",
        "surgeons",
        "surgeon"
    ],
    "wof:name":"Medical X Ray Consultants Inc",
    "wof:placetype":"venue"
},
  "geometry": {"coordinates":[-112.00723499999999,33.332153],"type":"Point"}
}