{
  "type": "Feature",
  "properties": {
    "iso:country":"US",
    "sg:address":"5750 W Thunderbird Rd Ste D480",
    "sg:city":"Glendale",
    "sg:classifiers":[
        {
            "category":"Health Services",
            "subcategory":"Doctor",
            "type":"Services"
        },
        {
            "category":"Health Services",
            "subcategory":"Dentist",
            "type":"Services"
        }
    ],
    "sg:phone":"+1 602 547 1916",
    "sg:postcode":"85306",
    "sg:province":"AZ",
    "sg:tags":[
        "dentists-oral",
        "physician",
        "maxillofacial",
        "surgeons",
        "surgery",
        "oral"
    ],
    "wof:name":"Liu W Jane DMD P",
    "wof:placetype":"venue"
},
  "geometry": {"coordinates":[-112.182432,33.610748],"type":"Point"}
}