{
  "type": "Feature",
  "properties": {
    "iso:country":"US",
    "sg:address":"4340 E Indian School Rd",
    "sg:city":"Phoenix",
    "sg:classifiers":[
        {
            "category":"Utilities",
            "subcategory":"Mobile Phone",
            "type":"Services"
        },
        {
            "category":"Shopping",
            "subcategory":"Mobile Phones",
            "type":"Retail Goods"
        },
        {
            "category":"Manufacturing",
            "subcategory":"Electronics",
            "type":"Manufacturing & Wholesale Goods"
        },
        {
            "category":"Communications",
            "type":"Services"
        }
    ],
    "sg:phone":"+1 602 667 0888",
    "sg:postcode":"85018",
    "sg:province":"AZ",
    "sg:tags":[
        "equipment",
        "telecommunications-equipment",
        "telephone",
        "cellular",
        "supply"
    ],
    "wof:name":"2B Wireless",
    "wof:placetype":"venue"
},
  "geometry": {"coordinates":[-111.987777,33.49488],"type":"Point"}
}