{
  "type": "Feature",
  "properties": {
    "addr:full":"14550 N Frank Lloyd Wright Blvd Scottsdale AZ 85260",
    "addr:housenumber":"14550",
    "addr:postcode":"85260",
    "addr:street":"N Frank Lloyd Wright Blvd",
    "iso:country":"US",
    "sg:address":"14550 N Frank Lloyd Wright Blvd",
    "sg:city":"Scottsdale",
    "sg:classifiers":[
        {
            "category":"Health Services",
            "subcategory":"Nursing And Care Facility",
            "type":"Services"
        }
    ],
    "sg:phone":"+1 480 767 9500",
    "sg:postcode":"85260",
    "sg:province":"AZ",
    "sg:tags":[
        "home",
        "retirement",
        "community"
    ],
    "wof:name":"Southwest Retirement",
    "wof:placetype":"venue"
},
  "geometry": {"coordinates":[-111.871909,33.617552],"type":"Point"}
}