{
  "type": "Feature",
  "properties": {
    "iso:country":"US",
    "sg:address":"10105 E Via Linda",
    "sg:city":"Scottsdale",
    "sg:classifiers":[
        {
            "category":"Organizations",
            "subcategory":"Community Association",
            "type":"Services"
        }
    ],
    "sg:phone":"+1 480 661 0775",
    "sg:postcode":"85258",
    "sg:province":"AZ",
    "sg:tags":[
        "club"
    ],
    "wof:name":"Mountainview Little League",
    "wof:placetype":"venue"
},
  "geometry": {"coordinates":[-111.862483,33.574637],"type":"Point"}
}