{
  "type": "Feature",
  "properties": {
    "addr:full":"14439 N 73rd St Scottsdale AZ 85260",
    "addr:housenumber":"14439",
    "addr:postcode":"85260",
    "addr:street":"N 73Rd St",
    "iso:country":"US",
    "sg:address":"14439 N 73rd St",
    "sg:city":"Scottsdale",
    "sg:classifiers":[
        {
            "category":"Health Services",
            "subcategory":"Doctor",
            "type":"Services"
        }
    ],
    "sg:phone":"+1 480 998 4400",
    "sg:postcode":"85260",
    "sg:province":"AZ",
    "sg:tags":[
        "dentist"
    ],
    "wof:name":"Michael S Barnes Dds",
    "wof:placetype":"venue"
},
  "geometry": {"coordinates":[-111.924474,33.614815],"type":"Point"}
}