{
  "type": "Feature",
  "properties": {
    "addr:full":"1600 W 4th St Yuma AZ 85364",
    "addr:housenumber":"1600",
    "addr:postcode":"85364",
    "addr:street":"W 4Th St",
    "iso:country":"US",
    "sg:address":"1600 W 4th St",
    "sg:city":"Yuma",
    "sg:classifiers":[
        {
            "category":"Building & Trades",
            "subcategory":"Construction",
            "type":"Services"
        }
    ],
    "sg:phone":"+1 928 782 9741",
    "sg:postcode":"85364",
    "sg:province":"AZ",
    "sg:tags":[
        "hanging",
        "contractor"
    ],
    "wof:name":"Ace Painting",
    "wof:placetype":"venue"
},
  "geometry": {"coordinates":[-114.640637,32.719687],"type":"Point"}
}