{
  "type": "Feature",
  "properties": {
    "addr:full":"700 W 1st St Tempe AZ 85281",
    "addr:housenumber":"700",
    "addr:postcode":"85281",
    "addr:street":"W 1St St",
    "iso:country":"US",
    "sg:address":"700 W 1st St",
    "sg:city":"Tempe",
    "sg:classifiers":[
        {
            "category":"Building & Trades",
            "subcategory":"Plumbing",
            "type":"Services"
        }
    ],
    "sg:phone":"+1 480 966 3313",
    "sg:postcode":"85281",
    "sg:province":"AZ",
    "sg:tags":[
        "plumbing",
        "air",
        "heating",
        "conditioning",
        "mechanical"
    ],
    "wof:name":"Premier Mechanical Corporation",
    "wof:placetype":"venue"
},
  "geometry": {"coordinates":[-111.94888400000001,33.429182],"type":"Point"}
}