{
  "type": "Feature",
  "properties": {
    "iso:country":"US",
    "sg:address":"223 E Monroe Ave",
    "sg:city":"Buckeye",
    "sg:classifiers":[
        {
            "category":"Autos & Motor Vehicles",
            "subcategory":"Fuel & Gas Station",
            "type":"Retail Goods"
        }
    ],
    "sg:phone":"+1 623 386 2469",
    "sg:postcode":"85326",
    "sg:province":"AZ",
    "sg:tags":[
        "gasoline"
    ],
    "wof:name":"Powers Automotive",
    "wof:placetype":"venue"
},
  "geometry": {"coordinates":[-112.589045,33.370465],"type":"Point"}
}