{
  "type": "Feature",
  "properties": {
    "addr:full":"4873 Loma Loop Sierra Vista AZ 85635",
    "addr:housenumber":"4873",
    "addr:postcode":"85635",
    "addr:street":"Loma Loop",
    "iso:country":"US",
    "sg:address":"4873 Loma Loop",
    "sg:city":"Sierra Vista",
    "sg:classifiers":[
        {
            "category":"Real Estate",
            "subcategory":"Real Estate Agent",
            "type":"Services"
        }
    ],
    "sg:phone":"+1 520 458 5541",
    "sg:postcode":"85635",
    "sg:province":"AZ",
    "wof:name":"Patricia Reed Realty",
    "wof:placetype":"venue"
},
  "geometry": {"coordinates":[-110.24841499999999,31.537707],"type":"Point"}
}