{
  "type": "Feature",
  "properties": {
    "iso:country":"US",
    "sg:address":"2139 Swanson Ave",
    "sg:city":"Lake Havasu City",
    "sg:classifiers":[
        {
            "category":"Professional",
            "subcategory":"Accounting & Tax Preparation",
            "type":"Services"
        }
    ],
    "sg:phone":"+1 928 855 7827",
    "sg:postcode":"86403",
    "sg:province":"AZ",
    "sg:tags":[
        "accountant"
    ],
    "sg:website":"www.aztaxbusters.com",
    "wof:name":"Green & Seyfert",
    "wof:placetype":"venue"
},
  "geometry": {"coordinates":[-114.326708,34.473339],"type":"Point"}
}