{
  "type": "Feature",
  "properties": {
    "iso:country":"US",
    "sg:address":"345 E Drachman St",
    "sg:city":"Tucson",
    "sg:classifiers":[
        {
            "category":"Manufacturing",
            "subcategory":"Glass & Minerals",
            "type":"Manufacturing & Wholesale Goods"
        }
    ],
    "sg:phone":"+1 520 884 9049",
    "sg:postcode":"85705",
    "sg:province":"AZ",
    "sg:tags":[
        "hydraulic",
        "cement",
        "mfg"
    ],
    "wof:name":"Jose R Bautista Masonry",
    "wof:placetype":"venue"
},
  "geometry": {"coordinates":[-110.966297,32.239594],"type":"Point"}
}