{
  "type": "Feature",
  "properties": {
    "addr:full":"2929 W Clarendon Ave Phoenix AZ 85017",
    "addr:housenumber":"2929",
    "addr:postcode":"85017",
    "addr:street":"W Clarendon Ave",
    "iso:country":"US",
    "sg:address":"2929 W Clarendon Ave",
    "sg:city":"Phoenix",
    "sg:classifiers":[
        {
            "category":"Taxi",
            "type":"Transportation"
        }
    ],
    "sg:phone":"+1 602 200 2000",
    "sg:postcode":"85017",
    "sg:province":"AZ",
    "sg:tags":[
        "taxicab"
    ],
    "wof:name":"Metro Taxi",
    "wof:placetype":"venue"
},
  "geometry": {"coordinates":[-112.122686,33.492162],"type":"Point"}
}