{
  "type": "Feature",
  "properties": {
    "iso:country":"US",
    "sg:address":"550 W 3rd Ave",
    "sg:city":"Mesa",
    "sg:classifiers":[
        {
            "category":"Building & Trades",
            "subcategory":"Electrical",
            "type":"Services"
        }
    ],
    "sg:phone":"+1 480 833 0461",
    "sg:postcode":"85210",
    "sg:province":"AZ",
    "sg:tags":[
        "electrical",
        "contractor"
    ],
    "wof:name":"Sonoran Electric Inc",
    "wof:placetype":"venue"
},
  "geometry": {"coordinates":[-111.841281,33.409564],"type":"Point"}
}