{
  "type": "Feature",
  "properties": {
    "iso:country":"US",
    "sg:address":"2301 E Broadway Blvd",
    "sg:city":"Tucson",
    "sg:classifiers":[
        {
            "category":"Communications",
            "subcategory":"Film & Video Production",
            "type":"Services"
        }
    ],
    "sg:phone":"+1 520 624 9710",
    "sg:postcode":"85719",
    "sg:province":"AZ",
    "sg:tags":[
        "taping"
    ],
    "wof:name":"Sound & Fury Productions",
    "wof:placetype":"venue"
},
  "geometry": {"coordinates":[-110.93790300000001,32.221545],"type":"Point"}
}