{
  "type": "Feature",
  "properties": {
    "iso:country":"US",
    "sg:address":"14402 N 60th Pl",
    "sg:city":"Scottsdale",
    "sg:classifiers":[
        {
            "category":"Education",
            "subcategory":"School",
            "type":"Public Place"
        }
    ],
    "sg:phone":"+1 480 991 7648",
    "sg:postcode":"85254",
    "sg:province":"AZ",
    "wof:name":"Les Petites Gourmettes School",
    "wof:placetype":"venue"
},
  "geometry": {"coordinates":[-111.951058,33.617223],"type":"Point"}
}