{
  "type": "Feature",
  "properties": {
    "iso:country":"US",
    "sg:address":"17599 W Wind Song Ave",
    "sg:city":"Goodyear",
    "sg:classifiers":[
        {
            "category":"Professional",
            "type":"Services"
        }
    ],
    "sg:phone":"+1 623 327 9700",
    "sg:postcode":"85338",
    "sg:province":"AZ",
    "sg:tags":[
        "establishment"
    ],
    "wof:name":"Advanced Modular Space Inc",
    "wof:placetype":"venue"
},
  "geometry": {"coordinates":[-112.426944,33.327463],"type":"Point"}
}