{
  "type": "Feature",
  "properties": {
    "iso:country":"US",
    "sg:address":"5116 W Olive Ave",
    "sg:city":"Glendale",
    "sg:classifiers":[
        {
            "category":"Food & Beverages",
            "subcategory":"Groceries & Convenience Stores",
            "type":"Retail Goods"
        }
    ],
    "sg:phone":"+1 623 937 4771",
    "sg:postcode":"85302",
    "sg:province":"AZ",
    "wof:name":"Smiths",
    "wof:placetype":"venue"
},
  "geometry": {"coordinates":[-112.170497,33.567581],"type":"Point"}
}