{
  "type": "Feature",
  "properties": {
    "iso:country":"US",
    "sg:address":"661 W Hackberry Dr",
    "sg:city":"Chandler",
    "sg:classifiers":[
        {
            "category":"Building & Trades",
            "subcategory":"Construction",
            "type":"Services"
        }
    ],
    "sg:phone":"+1 480 857 8530",
    "sg:postcode":"85248",
    "sg:province":"AZ",
    "sg:tags":[
        "contractor"
    ],
    "wof:name":"Klontz Builders Inc",
    "wof:placetype":"venue"
},
  "geometry": {"coordinates":[-111.853024,33.257267],"type":"Point"}
}