{
  "type": "Feature",
  "properties": {
    "addr:full":"11365 W Amole Cir Marana AZ 85658",
    "addr:housenumber":"11365",
    "addr:postcode":"85658",
    "addr:street":"W Amole Cir",
    "iso:country":"US",
    "sg:address":"11365 W Amole Cir",
    "sg:city":"Marana",
    "sg:classifiers":[
        {
            "category":"Building & Trades",
            "subcategory":"Construction",
            "type":"Services"
        }
    ],
    "sg:phone":"+1 520 820 0883",
    "sg:postcode":"85658",
    "sg:province":"AZ",
    "sg:tags":[
        "wallcoverings-installation",
        "wallpaper",
        "painting",
        "contractor"
    ],
    "wof:name":"Meza Custom Painting",
    "wof:placetype":"venue"
},
  "geometry": {"coordinates":[-111.207348,32.460199],"type":"Point"}
}