{
  "type": "Feature",
  "properties": {
    "iso:country":"US",
    "sg:address":"9967 N Sumter Creek Pl",
    "sg:city":"Tucson",
    "sg:classifiers":[
        {
            "category":"Professional",
            "subcategory":"Engineering",
            "type":"Services"
        }
    ],
    "sg:phone":"+1 520 820 1294",
    "sg:postcode":"85742",
    "sg:province":"AZ",
    "sg:tags":[
        "engineer"
    ],
    "wof:name":"Innova Environmental Engnrng",
    "wof:placetype":"venue"
},
  "geometry": {"coordinates":[-111.059148,32.384999],"type":"Point"}
}