{
  "type": "Feature",
  "properties": {
    "iso:country":"US",
    "sg:address":"2962 S Marvin Ave",
    "sg:city":"Tucson",
    "sg:classifiers":[
        {
            "category":"Building & Trades",
            "subcategory":"Plumbing",
            "type":"Services"
        }
    ],
    "sg:phone":"+1 520 790 3214",
    "sg:postcode":"85730",
    "sg:province":"AZ",
    "sg:tags":[
        "contractor"
    ],
    "wof:name":"G & R Plumbing",
    "wof:placetype":"venue"
},
  "geometry": {"coordinates":[-110.839764,32.188229],"type":"Point"}
}