{
  "type": "Feature",
  "properties": {
    "iso:country":"US",
    "sg:address":"3130 E Broadway Blvd",
    "sg:city":"Tucson",
    "sg:classifiers":[
        {
            "category":"Real Estate",
            "subcategory":"Real Estate Agent",
            "type":"Services"
        }
    ],
    "sg:phone":"+1 520 290 4500",
    "sg:postcode":"85716",
    "sg:province":"AZ",
    "sg:tags":[
        "investment"
    ],
    "wof:name":"Southwest Commercial Mgmt",
    "wof:placetype":"venue"
},
  "geometry": {"coordinates":[-110.925514,32.221477],"type":"Point"}
}