{
  "type": "Feature",
  "properties": {
    "iso:country":"US",
    "sg:address":"6910 N Cam Martin",
    "sg:city":"Tucson",
    "sg:classifiers":[
        {
            "category":"Food & Beverages",
            "subcategory":"Bakery",
            "type":"Retail Goods"
        }
    ],
    "sg:phone":"+1 520 742 7626",
    "sg:postcode":"85741",
    "sg:province":"AZ",
    "sg:tags":[
        "cookie",
        "cracker"
    ],
    "wof:name":"Cookie Wagon",
    "wof:placetype":"venue"
},
  "geometry": {"coordinates":[-111.05744,32.337552],"type":"Point"}
}