{
  "type": "Feature",
  "properties": {
    "iso:country":"US",
    "sg:address":"2301 E Lind Rd",
    "sg:city":"Tucson",
    "sg:classifiers":[
        {
            "category":"Home & Garden",
            "subcategory":"Home Furnishings",
            "type":"Retail Goods"
        }
    ],
    "sg:phone":"+1 520 318 9762",
    "sg:postcode":"85719",
    "sg:province":"AZ",
    "sg:tags":[
        "kitchen",
        "accessory"
    ],
    "wof:name":"Serious Frills Inc",
    "wof:placetype":"venue"
},
  "geometry": {"coordinates":[-110.935241,32.266768],"type":"Point"}
}