{
  "type": "Feature",
  "properties": {
    "iso:country":"US",
    "sg:address":"10600 S Nogales Hwy",
    "sg:city":"Tucson",
    "sg:classifiers":[
        {
            "category":"Organizations",
            "subcategory":"Community Association",
            "type":"Services"
        }
    ],
    "sg:phone":"+1 520 889 2435",
    "sg:postcode":"85706",
    "sg:province":"AZ",
    "sg:tags":[
        "fraternal"
    ],
    "wof:name":"San Xavier Moose Lodge",
    "wof:placetype":"venue"
},
  "geometry": {"coordinates":[-110.95464,32.057214],"type":"Point"}
}