{
  "type": "Feature",
  "properties": {
    "iso:country":"US",
    "sg:address":"7014 E Camelback Rd",
    "sg:city":"Scottsdale",
    "sg:classifiers":[
        {
            "category":"Shopping",
            "subcategory":"Luggage & Leather Goods",
            "type":"Retail Goods"
        }
    ],
    "sg:phone":"+1 480 994 8092",
    "sg:postcode":"85251",
    "sg:province":"AZ",
    "wof:name":"Malm Luggage",
    "wof:placetype":"venue"
},
  "geometry": {"coordinates":[-111.928892,33.502307],"type":"Point"}
}