{
  "type": "Feature",
  "properties": {
    "iso:country":"US",
    "sg:address":"4545 E Shea Blvd",
    "sg:city":"Phoenix",
    "sg:classifiers":[
        {
            "category":"Insurance",
            "subcategory":"Insurance Agent",
            "type":"Services"
        }
    ],
    "sg:phone":"+1 602 953 3762",
    "sg:postcode":"85028",
    "sg:province":"AZ",
    "wof:name":"Allstate Insurance Co",
    "wof:placetype":"venue"
},
  "geometry": {"coordinates":[-111.984509,33.582582],"type":"Point"}
}