{
  "type": "Feature",
  "properties": {
    "iso:country":"US",
    "sg:address":"535 Santa Cruz Dr",
    "sg:city":"Bisbee",
    "sg:classifiers":[
        {
            "category":"Retail",
            "subcategory":"Repair Shop",
            "type":"Services"
        }
    ],
    "sg:phone":"+1 520 432 3936",
    "sg:postcode":"85603",
    "sg:province":"AZ",
    "sg:tags":[
        "refrigerator",
        "freezer"
    ],
    "wof:name":"Franklin Refrigeration Svc",
    "wof:placetype":"venue"
},
  "geometry": {"coordinates":[-109.928283,31.394772],"type":"Point"}
}