{
  "type": "Feature",
  "properties": {
    "iso:country":"US",
    "sg:address":"3247 W Christy Dr",
    "sg:city":"Phoenix",
    "sg:classifiers":[
        {
            "category":"Professional",
            "type":"Services"
        }
    ],
    "sg:phone":"+1 602 866 2400",
    "sg:postcode":"85029",
    "sg:province":"AZ",
    "wof:name":"Empire Window Fashions",
    "wof:placetype":"venue"
},
  "geometry": {"coordinates":[-112.130122,33.58452],"type":"Point"}
}