{
  "type": "Feature",
  "properties": {
    "iso:country":"US",
    "sg:address":"248 E Bethany Home Rd",
    "sg:city":"Phoenix",
    "sg:classifiers":[
        {
            "category":"Professional",
            "subcategory":"Art Services",
            "type":"Services"
        }
    ],
    "sg:phone":"+1 602 240 6789",
    "sg:postcode":"85012",
    "sg:province":"AZ",
    "sg:tags":[
        "graphic",
        "commercial",
        "designer",
        "artist"
    ],
    "wof:name":"Eddie Shea",
    "wof:placetype":"venue"
},
  "geometry": {"coordinates":[-112.070368,33.5238],"type":"Point"}
}