{
  "type": "Feature",
  "properties": {
    "iso:country":"US",
    "sg:address":"824 W Shellfish Dr",
    "sg:city":"Gilbert",
    "sg:classifiers":[
        {
            "category":"Manufacturing",
            "subcategory":"Chemicals & Compounds",
            "type":"Manufacturing & Wholesale Goods"
        }
    ],
    "sg:phone":"+1 480 545 6075",
    "sg:postcode":"85233",
    "sg:province":"AZ",
    "sg:tags":[
        "preparation",
        "pharmaceutical",
        "mfg"
    ],
    "wof:name":"Qxl Corporation",
    "wof:placetype":"venue"
},
  "geometry": {"coordinates":[-111.807765,33.332204],"type":"Point"}
}