{
  "type": "Feature",
  "properties": {
    "addr:full":"100 S Haskell Ave Willcox AZ 85643",
    "addr:housenumber":"100",
    "addr:postcode":"85643",
    "addr:street":"S Haskell Ave",
    "iso:country":"US",
    "sg:address":"100 S Haskell Ave",
    "sg:city":"Willcox",
    "sg:classifiers":[
        {
            "category":"Shopping",
            "subcategory":"Hobbies, Toys, & Games",
            "type":"Retail Goods"
        }
    ],
    "sg:phone":"+1 520 384 3197",
    "sg:postcode":"85643",
    "sg:province":"AZ",
    "wof:name":"World Wide Hobbies",
    "wof:placetype":"venue"
},
  "geometry": {"coordinates":[-109.833378,32.251241],"type":"Point"}
}