{
  "type": "Feature",
  "properties": {
    "addr:full":"10120 W Bell Rd Sun City AZ 85351",
    "addr:housenumber":"10120",
    "addr:postcode":"85351",
    "addr:street":"W Bell Rd",
    "iso:country":"US",
    "sg:address":"10120 W Bell Rd",
    "sg:city":"Sun City",
    "sg:classifiers":[
        {
            "category":"Autos & Motor Vehicles",
            "subcategory":"Fuel & Gas Station",
            "type":"Retail Goods"
        }
    ],
    "sg:phone":"+1 623 933 1182",
    "sg:postcode":"85351",
    "sg:province":"AZ",
    "sg:tags":[
        "oil"
    ],
    "wof:name":"Sun City 76 Mike's",
    "wof:placetype":"venue"
},
  "geometry": {"coordinates":[-112.276026,33.638228],"type":"Point"}
}