{
  "type": "Feature",
  "properties": {
    "iso:country":"US",
    "sg:address":"7683 Old Mission Dr",
    "sg:city":"Kingman",
    "sg:classifiers":[
        {
            "category":"Shopping",
            "subcategory":"Hobbies, Toys, & Games",
            "type":"Retail Goods"
        }
    ],
    "sg:phone":"+1 928 757 9571",
    "sg:postcode":"86401",
    "sg:province":"AZ",
    "wof:name":"Artycon",
    "wof:placetype":"venue"
},
  "geometry": {"coordinates":[-113.859714,35.402596],"type":"Point"}
}