{
  "type": "Feature",
  "properties": {
    "addr:full":"33 W Boxelder Pl Chandler AZ 85225",
    "addr:housenumber":"33",
    "addr:postcode":"85225",
    "addr:street":"W Boxelder Pl",
    "iso:country":"US",
    "sg:address":"33 W Boxelder Pl",
    "sg:city":"Chandler",
    "sg:classifiers":[
        {
            "category":"Manufacturing",
            "subcategory":"Printing",
            "type":"Manufacturing & Wholesale Goods"
        }
    ],
    "sg:phone":"+1 480 892 9464",
    "sg:postcode":"85225",
    "sg:province":"AZ",
    "sg:tags":[
        "printer"
    ],
    "sg:website":"www.iiprinting.com",
    "wof:name":"Impress In Printing",
    "wof:placetype":"venue"
},
  "geometry": {"coordinates":[-111.843666,33.355718],"type":"Point"}
}