{
  "type": "Feature",
  "properties": {
    "iso:country":"US",
    "sg:address":"1455 N Rose St",
    "sg:city":"Tempe",
    "sg:classifiers":[
        {
            "category":"Building & Trades",
            "subcategory":"Construction",
            "type":"Services"
        }
    ],
    "sg:phone":"+1 480 990 2468",
    "sg:postcode":"85281",
    "sg:province":"AZ",
    "sg:tags":[
        "nonresidential"
    ],
    "wof:name":"Bill Trenter and Associates",
    "wof:placetype":"venue"
},
  "geometry": {"coordinates":[-111.92096100000001,33.444217],"type":"Point"}
}