{
  "type": "Feature",
  "properties": {
    "iso:country":"US",
    "sg:address":"420 S 7th Ave",
    "sg:city":"Phoenix",
    "sg:classifiers":[
        {
            "category":"Home & Garden",
            "subcategory":"Furniture",
            "type":"Retail Goods"
        },
        {
            "category":"Manufacturing",
            "subcategory":"Lumber",
            "type":"Manufacturing & Wholesale Goods"
        }
    ],
    "sg:phone":"+1 602 253 8938",
    "sg:postcode":"85007",
    "sg:province":"AZ",
    "sg:tags":[
        "custom",
        "builder",
        "work",
        "mill",
        "mfg"
    ],
    "wof:name":"Blue Horizons",
    "wof:placetype":"venue"
},
  "geometry": {"coordinates":[-112.082555,33.444452],"type":"Point"}
}