{
  "type": "Feature",
  "properties": {
    "iso:country":"US",
    "sg:address":"3821 E Bronco Trl",
    "sg:city":"Phoenix",
    "sg:classifiers":[
        {
            "category":"Professional",
            "subcategory":"Computer Services",
            "type":"Services"
        }
    ],
    "sg:phone":"+1 480 893 3866",
    "sg:postcode":"85044",
    "sg:province":"AZ",
    "sg:tags":[
        "publisher",
        "software",
        "developer"
    ],
    "wof:name":"Abstraction Artists Inc",
    "wof:placetype":"venue"
},
  "geometry": {"coordinates":[-112.001361,33.340764],"type":"Point"}
}