{
  "type": "Feature",
  "properties": {
    "addr:full":"7323 E Valley View Rd Scottsdale AZ 85250",
    "addr:housenumber":"7323",
    "addr:postcode":"85250",
    "addr:street":"E Valley View Rd",
    "iso:country":"US",
    "sg:address":"7323 E Valley View Rd",
    "sg:city":"Scottsdale",
    "sg:classifiers":[
        {
            "category":"Bakery",
            "type":"Food & Drink"
        }
    ],
    "sg:phone":"+1 480 947 7315",
    "sg:postcode":"85250",
    "sg:province":"AZ",
    "wof:name":"Gluten Free Fabulous",
    "wof:placetype":"venue"
},
  "geometry": {"coordinates":[-111.922718,33.518622],"type":"Point"}
}