{
  "type": "Feature",
  "properties": {
    "addr:full":"2549 E McDowell Rd Phoenix AZ 85008",
    "addr:housenumber":"2549",
    "addr:postcode":"85008",
    "addr:street":"E Mcdowell Rd",
    "iso:country":"US",
    "sg:address":"2549 E McDowell Rd",
    "sg:city":"Phoenix",
    "sg:classifiers":[
        {
            "category":"Autos & Motor Vehicles",
            "subcategory":"Auto Supplies",
            "type":"Retail Goods"
        }
    ],
    "sg:phone":"+1 602 273 0307",
    "sg:postcode":"85008",
    "sg:province":"AZ",
    "sg:tags":[
        "automobile",
        "parts"
    ],
    "wof:name":"Matz Conversions & Accessories",
    "wof:placetype":"venue"
},
  "geometry": {"coordinates":[-112.026045,33.465681],"type":"Point"}
}