{
  "type": "Feature",
  "properties": {
    "iso:country":"US",
    "sg:address":"7575 E Princess Dr",
    "sg:city":"Scottsdale",
    "sg:phone":"+1 480 559 8229",
    "sg:postcode":"85255",
    "sg:province":"AZ",
    "wof:name":"Stone Rose",
    "wof:placetype":"venue"
},
  "geometry": {"coordinates":[-111.916917,33.645937],"type":"Point"}
}