{
  "type": "Feature",
  "properties": {
    "addr:full":"6130 S Kino Rd Hereford AZ 85615",
    "addr:housenumber":"6130",
    "addr:postcode":"85615",
    "addr:street":"S Kino Rd",
    "iso:country":"US",
    "sg:address":"6130 S Kino Rd",
    "sg:city":"Hereford",
    "sg:classifiers":[
        {
            "category":"Wholesale",
            "subcategory":"Electrical",
            "type":"Manufacturing & Wholesale Goods"
        }
    ],
    "sg:phone":"+1 520 266 4026",
    "sg:postcode":"85615",
    "sg:province":"AZ",
    "sg:tags":[
        "control",
        "security",
        "system"
    ],
    "wof:name":"Vincent Surveillance & Scrty",
    "wof:placetype":"venue"
},
  "geometry": {"coordinates":[-110.20674699999999,31.452814],"type":"Point"}
}