{
  "type": "Feature",
  "properties": {
    "addr:full":"7225 N Oracle Rd Ste 106 Tucson AZ 85704",
    "addr:housenumber":"7225",
    "addr:postcode":"85704",
    "addr:street":"N Oracle Rd Ste 106",
    "iso:country":"US",
    "sg:address":"7225 N Oracle Rd Ste 106",
    "sg:city":"Tucson",
    "sg:classifiers":[
        {
            "category":"Autos & Motor Vehicles",
            "subcategory":"Automobile Sales",
            "type":"Retail Goods"
        },
        {
            "category":"Retail",
            "subcategory":"Auto Repair",
            "type":"Services"
        }
    ],
    "sg:phone":"+1 520 797 5661",
    "sg:postcode":"85704",
    "sg:province":"AZ",
    "sg:tags":[
        "used",
        "car",
        "dealers-used",
        "new",
        "cars-wholesale"
    ],
    "wof:name":"Arizona'sauto Savings Co",
    "wof:placetype":"venue"
},
  "geometry": {"coordinates":[-110.97758899999999,32.337305],"type":"Point"}
}