{
  "type": "Feature",
  "properties": {
    "addr:full":"62 N 92nd Dr Ofc Tolleson AZ 85353",
    "addr:housenumber":"62",
    "addr:postcode":"85353",
    "addr:street":"N 92Nd Dr",
    "iso:country":"US",
    "sg:address":"62 N 92nd Dr Ofc",
    "sg:city":"Tolleson",
    "sg:classifiers":[
        {
            "category":"Real Estate",
            "subcategory":"Real Estate Operator",
            "type":"Services"
        }
    ],
    "sg:phone":"+1 623 936 9668",
    "sg:postcode":"85353",
    "sg:province":"AZ",
    "sg:tags":[
        "apartment"
    ],
    "wof:name":"Casa De Merced",
    "wof:placetype":"venue"
},
  "geometry": {"coordinates":[-112.25900300000001,33.448101],"type":"Point"}
}