{
  "type": "Feature",
  "properties": {
    "iso:country":"US",
    "sg:address":"521 E 26th Pl",
    "sg:city":"Yuma",
    "sg:classifiers":[
        {
            "category":"Building & Trades",
            "subcategory":"Construction",
            "type":"Services"
        }
    ],
    "sg:phone":"+1 928 580 8749",
    "sg:postcode":"85365",
    "sg:province":"AZ",
    "sg:tags":[
        "contractor"
    ],
    "wof:name":"Top Notch Tile",
    "wof:placetype":"venue"
},
  "geometry": {"coordinates":[-114.614012,32.679875],"type":"Point"}
}