{
  "type": "Feature",
  "properties": {
    "iso:country":"US",
    "sg:address":"9034 E Olive Ln S",
    "sg:city":"Sun Lakes",
    "sg:classifiers":[
        {
            "category":"Real Estate",
            "subcategory":"Real Estate Agent",
            "type":"Services"
        }
    ],
    "sg:phone":"+1 480 895 6294",
    "sg:postcode":"85248",
    "sg:province":"AZ",
    "wof:name":"Martin Edward Church LTD",
    "wof:placetype":"venue"
},
  "geometry": {"coordinates":[-111.887889,33.206146],"type":"Point"}
}