{
  "type": "Feature",
  "properties": {
    "addr:full":"7450 W Orchid Ln Chandler AZ 85226",
    "addr:housenumber":"7450",
    "addr:postcode":"85226",
    "addr:street":"W Orchid Ln",
    "iso:country":"US",
    "sg:address":"7450 W Orchid Ln",
    "sg:city":"Chandler",
    "sg:classifiers":[
        {
            "category":"Autos & Motor Vehicles",
            "subcategory":"Automobile Sales",
            "type":"Retail Goods"
        }
    ],
    "sg:phone":"+1 480 403 3400",
    "sg:postcode":"85226",
    "sg:province":"AZ",
    "wof:name":"United Auto Group",
    "wof:placetype":"venue"
},
  "geometry": {"coordinates":[-111.971155,33.323622],"type":"Point"}
}