{
  "type": "Feature",
  "properties": {
    "addr:full":"901 N Country Plz E Gilbert AZ 85234",
    "addr:housenumber":"901",
    "addr:postcode":"85234",
    "addr:street":"N Country Plz E",
    "iso:country":"US",
    "sg:address":"901 N Country Plz E",
    "sg:city":"Gilbert",
    "sg:classifiers":[
        {
            "category":"Professional",
            "subcategory":"Advertising",
            "type":"Services"
        }
    ],
    "sg:phone":"+1 480 861 4957",
    "sg:postcode":"85234",
    "sg:province":"AZ",
    "sg:tags":[
        "guide"
    ],
    "sg:website":"www.lawncaredirectory.com",
    "wof:name":"LAWNCAREDIRECTORY.COM",
    "wof:placetype":"venue"
},
  "geometry": {"coordinates":[-111.77472,33.365921],"type":"Point"}
}