{
  "type": "Feature",
  "properties": {
    "iso:country":"US",
    "sg:address":"3977 E Douglas Loop",
    "sg:city":"Gilbert",
    "sg:classifiers":[
        {
            "category":"Professional",
            "type":"Services"
        }
    ],
    "sg:phone":"+1 480 832 0061",
    "sg:postcode":"85234",
    "sg:province":"AZ",
    "wof:name":"Candice Vicha",
    "wof:placetype":"venue"
},
  "geometry": {"coordinates":[-111.70735500000001,33.365949],"type":"Point"}
}