{
  "type": "Feature",
  "properties": {
    "iso:country":"US",
    "sg:address":"5564 N 10th St",
    "sg:city":"Phoenix",
    "sg:classifiers":[
        {
            "category":"Home & Garden",
            "subcategory":"Garden Supply",
            "type":"Retail Goods"
        }
    ],
    "sg:phone":"+1 602 532 7025",
    "sg:postcode":"85014",
    "sg:province":"AZ",
    "sg:tags":[
        "fountain",
        "display"
    ],
    "wof:name":"Aunt Rita's Foundation",
    "wof:placetype":"venue"
},
  "geometry": {"coordinates":[-112.060692,33.517262],"type":"Point"}
}