{
  "type": "Feature",
  "properties": {
    "iso:country":"US",
    "sg:address":"415 W Main St",
    "sg:city":"Safford",
    "sg:classifiers":[
        {
            "category":"Manufacturing",
            "subcategory":"Printing",
            "type":"Manufacturing & Wholesale Goods"
        }
    ],
    "sg:phone":"+1 928 428 3463",
    "sg:postcode":"85546",
    "sg:province":"AZ",
    "sg:tags":[
        "commercial"
    ],
    "wof:name":"Print & Copy",
    "wof:placetype":"venue"
},
  "geometry": {"coordinates":[-109.711423,32.83323],"type":"Point"}
}