{
  "type": "Feature",
  "properties": {
    "iso:country":"US",
    "sg:address":"717 White Spar Rd",
    "sg:city":"Prescott",
    "sg:classifiers":[
        {
            "category":"Personal",
            "subcategory":"Beauty Salon",
            "type":"Services"
        }
    ],
    "sg:phone":"+1 928 445 0040",
    "sg:postcode":"86303",
    "sg:province":"AZ",
    "sg:tags":[
        "shop"
    ],
    "wof:name":"Thomas Styling",
    "wof:placetype":"venue"
},
  "geometry": {"coordinates":[-112.47705499999999,34.528451],"type":"Point"}
}