{
  "type": "Feature",
  "properties": {
    "addr:full":"8361 E Lee St Tucson AZ 85715",
    "addr:housenumber":"8361",
    "addr:postcode":"85715",
    "addr:street":"E Lee St",
    "iso:country":"US",
    "sg:address":"8361 E Lee St",
    "sg:city":"Tucson",
    "sg:classifiers":[
        {
            "category":"Organizations",
            "subcategory":"Religious Organization",
            "type":"Services"
        }
    ],
    "sg:phone":"+1 520 886 3002",
    "sg:postcode":"85715",
    "sg:province":"AZ",
    "sg:tags":[
        "church"
    ],
    "sg:website":"www.lds.org",
    "wof:name":"Church Of Jesus Christ Of Lds",
    "wof:placetype":"venue"
},
  "geometry": {"coordinates":[-110.81406,32.240628],"type":"Point"}
}