{
  "type": "Feature",
  "properties": {
    "addr:full":"2709 W Pla Mesa Alta Tucson AZ 85742",
    "addr:housenumber":"2709",
    "addr:postcode":"85742",
    "addr:street":"W Pla",
    "iso:country":"US",
    "sg:address":"2709 W Pla Mesa Alta",
    "sg:city":"Tucson",
    "sg:classifiers":[
        {
            "category":"Real Estate",
            "subcategory":"Real Estate Agent",
            "type":"Services"
        }
    ],
    "sg:phone":"+1 520 531 8362",
    "sg:postcode":"85742",
    "sg:province":"AZ",
    "wof:name":"Wenrose Properties LLC",
    "wof:placetype":"venue"
},
  "geometry": {"coordinates":[-111.026138,32.364961],"type":"Point"}
}