{
  "type": "Feature",
  "properties": {
    "iso:country":"US",
    "sg:address":"7848 E Redfield Rd",
    "sg:city":"Scottsdale",
    "sg:classifiers":[
        {
            "category":"Shopping",
            "subcategory":"Used Merchandise",
            "type":"Retail Goods"
        }
    ],
    "sg:phone":"+1 480 862 7666",
    "sg:postcode":"85260",
    "sg:province":"AZ",
    "sg:tags":[
        "antique"
    ],
    "wof:name":"Oriental Antiques",
    "wof:placetype":"venue"
},
  "geometry": {"coordinates":[-111.915097,33.614028],"type":"Point"}
}