{
  "type": "Feature",
  "properties": {
    "iso:country":"US",
    "sg:address":"836 E South Mountain Ave",
    "sg:city":"Phoenix",
    "sg:classifiers":[
        {
            "category":"Social Services",
            "type":"Services"
        },
        {
            "category":"Professional",
            "subcategory":"Employment Agencies",
            "type":"Services"
        }
    ],
    "sg:phone":"+1 602 243 7211",
    "sg:postcode":"85042",
    "sg:province":"AZ",
    "sg:tags":[
        "workers'",
        "placement",
        "volunteer"
    ],
    "wof:name":"Tiger Mountain Foundation",
    "wof:placetype":"venue"
},
  "geometry": {"coordinates":[-112.063035,33.370586],"type":"Point"}
}