{
  "type": "Feature",
  "properties": {
    "addr:full":"6277 W Chandler Blvd Chandler AZ 85226",
    "addr:housenumber":"6277",
    "addr:postcode":"85226",
    "addr:street":"W Chandler Blvd",
    "iso:country":"US",
    "sg:address":"6277 W Chandler Blvd",
    "sg:city":"Chandler",
    "sg:classifiers":[
        {
            "category":"Retail",
            "subcategory":"Animal Services",
            "type":"Services"
        }
    ],
    "sg:phone":"+1 480 951 1337",
    "sg:postcode":"85226",
    "sg:province":"AZ",
    "sg:tags":[
        "training",
        "dog"
    ],
    "wof:name":"Sit Happens",
    "wof:placetype":"venue"
},
  "geometry": {"coordinates":[-111.953006,33.305235],"type":"Point"}
}