{
  "type": "Feature",
  "properties": {
    "addr:full":"7555 E Dogwood St Tucson AZ 85730",
    "addr:housenumber":"7555",
    "addr:postcode":"85730",
    "addr:street":"E Dogwood St",
    "iso:country":"US",
    "sg:address":"7555 E Dogwood St",
    "sg:city":"Tucson",
    "sg:classifiers":[
        {
            "category":"Education",
            "subcategory":"School",
            "type":"Public Place"
        }
    ],
    "sg:phone":"+1 520 584 6600",
    "sg:postcode":"85730",
    "sg:province":"AZ",
    "wof:name":"Nan E Lyons Elementary School",
    "wof:placetype":"venue"
},
  "geometry": {"coordinates":[-110.831394,32.170712],"type":"Point"}
}