{
  "type": "Feature",
  "properties": {
    "addr:full":"5021 E Yale St Phoenix AZ 85008",
    "addr:housenumber":"5021",
    "addr:postcode":"85008",
    "addr:street":"E Yale St",
    "iso:country":"US",
    "sg:address":"5021 E Yale St",
    "sg:city":"Phoenix",
    "sg:classifiers":[
        {
            "category":"Food & Beverages",
            "subcategory":"Specialty",
            "type":"Retail Goods"
        }
    ],
    "sg:phone":"+1 602 840 6305",
    "sg:postcode":"85008",
    "sg:province":"AZ",
    "wof:name":"Arizona Health Depot",
    "wof:placetype":"venue"
},
  "geometry": {"coordinates":[-111.973297,33.475641],"type":"Point"}
}