{
  "type": "Feature",
  "properties": {
    "addr:full":"1860 S Milton Rd Flagstaff AZ 86001",
    "addr:housenumber":"1860",
    "addr:postcode":"86001",
    "addr:street":"S Milton Rd",
    "iso:country":"US",
    "sg:address":"1860 S Milton Rd",
    "sg:city":"Flagstaff",
    "sg:classifiers":[
        {
            "category":"Restaurant",
            "type":"Food & Drink"
        }
    ],
    "sg:menulink":"http://www.allmenus.com/az/coconino/74716-pizza-hut/menu/",
    "sg:phone":"+1 928 774 3259",
    "sg:postcode":"86001",
    "sg:province":"AZ",
    "sg:tags":[
        "american",
        "pizza"
    ],
    "wof:name":"Pizza Hut",
    "wof:placetype":"venue"
},
  "geometry": {"coordinates":[-111.661261,35.180506],"type":"Point"}
}