{
  "type": "Feature",
  "properties": {
    "iso:country":"US",
    "sg:address":"1101 E 23rd St",
    "sg:city":"Douglas",
    "sg:classifiers":[
        {
            "category":"Shopping",
            "subcategory":"Computers & Home Electronics",
            "type":"Retail Goods"
        }
    ],
    "sg:phone":"+1 520 364 2329",
    "sg:postcode":"85607",
    "sg:province":"AZ",
    "sg:tags":[
        "equipment",
        "satellite",
        "system"
    ],
    "wof:name":"B & S Satellite",
    "wof:placetype":"venue"
},
  "geometry": {"coordinates":[-109.545337,31.357529],"type":"Point"}
}