{
  "type": "Feature",
  "properties": {
    "addr:full":"1515 S 22nd Ave Phoenix AZ 85009",
    "addr:housenumber":"1515",
    "addr:postcode":"85009",
    "addr:street":"S 22Nd Ave",
    "iso:country":"US",
    "sg:address":"1515 S 22nd Ave",
    "sg:city":"Phoenix",
    "sg:classifiers":[
        {
            "category":"Building & Trades",
            "subcategory":"Construction",
            "type":"Services"
        }
    ],
    "sg:phone":"+1 602 256 7256",
    "sg:postcode":"85009",
    "sg:province":"AZ",
    "sg:tags":[
        "shoring"
    ],
    "wof:name":"Aluma Systems USA Inc",
    "wof:placetype":"venue"
},
  "geometry": {"coordinates":[-112.106385,33.434133],"type":"Point"}
}