{
  "type": "Feature",
  "properties": {
    "iso:country":"US",
    "sg:address":"14224 N Scottsdale Rd Ste 177 1st Flr",
    "sg:city":"Scottsdale",
    "sg:classifiers":[
        {
            "category":"Banks & Credit Unions",
            "subcategory":"Bank",
            "type":"Services"
        },
        {
            "category":"Banks & Credit Unions",
            "subcategory":"Financial Services",
            "type":"Services"
        }
    ],
    "sg:phone":"+1 480 998 1399",
    "sg:postcode":"85254",
    "sg:province":"AZ",
    "sg:tags":[
        "saving",
        "loan",
        "commercial"
    ],
    "sg:website":"https://www.chase.com/",
    "wof:name":"Chase",
    "wof:placetype":"venue"
},
  "geometry": {"coordinates":[-111.925875,33.615526],"type":"Point"}
}