{
  "type": "Feature",
  "properties": {
    "addr:full":"3280 Thunderbird Dr Lake Havasu City AZ 86406",
    "addr:housenumber":"3280",
    "addr:postcode":"86406",
    "addr:street":"Thunderbird Dr",
    "iso:country":"US",
    "sg:address":"3280 Thunderbird Dr",
    "sg:city":"Lake Havasu City",
    "sg:classifiers":[
        {
            "category":"Autos & Motor Vehicles",
            "subcategory":"Auto Supplies",
            "type":"Retail Goods"
        }
    ],
    "sg:phone":"+1 928 854 4259",
    "sg:postcode":"86406",
    "sg:province":"AZ",
    "wof:name":"Adamsautocentercom",
    "wof:placetype":"venue"
},
  "geometry": {"coordinates":[-114.288973,34.48357],"type":"Point"}
}