{
  "type": "Feature",
  "properties": {
    "addr:full":"1134 S Oak St Gilbert AZ 85233",
    "addr:housenumber":"1134",
    "addr:postcode":"85233",
    "addr:street":"S Oak St",
    "iso:country":"US",
    "sg:address":"1134 S Oak St",
    "sg:city":"Gilbert",
    "sg:classifiers":[
        {
            "category":"Education",
            "subcategory":"Special Training",
            "type":"Public Place"
        }
    ],
    "sg:phone":"+1 480 632 8575",
    "sg:postcode":"85233",
    "sg:province":"AZ",
    "sg:tags":[
        "instruction",
        "driving"
    ],
    "wof:name":"A Crash Course Traffic Survial",
    "wof:placetype":"venue"
},
  "geometry": {"coordinates":[-111.797572,33.328854],"type":"Point"}
}