{
  "type": "Feature",
  "properties": {
    "iso:country":"US",
    "sg:address":"393 N Broad St",
    "sg:city":"Globe",
    "sg:classifiers":[
        {
            "category":"Personal",
            "subcategory":"Beauty Salon",
            "type":"Services"
        }
    ],
    "sg:phone":"+1 928 425 9008",
    "sg:postcode":"85502",
    "sg:province":"AZ",
    "wof:name":"Fashion Gap Salon",
    "wof:placetype":"venue"
},
  "geometry": {"coordinates":[-110.788871,33.399486],"type":"Point"}
}