{
  "type": "Feature",
  "properties": {
    "iso:country":"US",
    "sg:address":"2255 N 44th St",
    "sg:city":"Phoenix",
    "sg:classifiers":[
        {
            "category":"Wholesale",
            "subcategory":"Farm Supplies",
            "type":"Manufacturing & Wholesale Goods"
        }
    ],
    "sg:phone":"+1 602 889 8300",
    "sg:postcode":"85008",
    "sg:province":"AZ",
    "sg:tags":[
        "fertilizer"
    ],
    "sg:website":"www.tkinet.com",
    "wof:name":"Tessenderlo Kerley Inc",
    "wof:placetype":"venue"
},
  "geometry": {"coordinates":[-111.986964,33.472085],"type":"Point"}
}