{
  "type": "Feature",
  "properties": {
    "iso:country":"US",
    "sg:address":"4235 N Brown Ave Ste 100",
    "sg:city":"Scottsdale",
    "sg:classifiers":[
        {
            "category":"Banks & Credit Unions",
            "subcategory":"Investment Brokerage",
            "type":"Services"
        },
        {
            "category":"Professional",
            "subcategory":"Business Services",
            "type":"Services"
        }
    ],
    "sg:phone":"+1 480 200 5700",
    "sg:postcode":"85251",
    "sg:province":"AZ",
    "sg:tags":[
        "broker",
        "commodity"
    ],
    "wof:name":"Ballistita Maximus Inc",
    "wof:placetype":"venue"
},
  "geometry": {"coordinates":[-111.92437200000001,33.497597],"type":"Point"}
}