{
  "type": "Feature",
  "properties": {
    "iso:country":"US",
    "sg:address":"2972 E Morgan Dr",
    "sg:city":"Gilbert",
    "sg:classifiers":[
        {
            "category":"Professional",
            "subcategory":"Art Services",
            "type":"Services"
        }
    ],
    "sg:phone":"+1 480 988 9785",
    "sg:postcode":"85295",
    "sg:province":"AZ",
    "sg:tags":[
        "photographers-portrait"
    ],
    "wof:name":"Bell Photographers Inc",
    "wof:placetype":"venue"
},
  "geometry": {"coordinates":[-111.726347,33.307523],"type":"Point"}
}