{
  "type": "Feature",
  "properties": {
    "addr:full":"2034 W Rose Garden Ln Phoenix AZ 85027",
    "addr:housenumber":"2034",
    "addr:postcode":"85027",
    "addr:street":"W Rose Garden Ln",
    "iso:country":"US",
    "sg:address":"2034 W Rose Garden Ln",
    "sg:city":"Phoenix",
    "sg:classifiers":[
        {
            "category":"Freight",
            "type":"Transportation"
        }
    ],
    "sg:phone":"+1 623 215 0019",
    "sg:postcode":"85027",
    "sg:province":"AZ",
    "sg:tags":[
        "warehouse",
        "self",
        "storage",
        "store",
        "furniture"
    ],
    "wof:name":"Ramatz",
    "wof:placetype":"venue"
},
  "geometry": {"coordinates":[-112.10373,33.676491],"type":"Point"}
}