{
  "type": "Feature",
  "properties": {
    "iso:country":"US",
    "sg:address":"2603 Poplar Dr",
    "sg:city":"Pinetop",
    "sg:classifiers":[
        {
            "category":"Real Estate",
            "subcategory":"Real Estate Operator",
            "type":"Services"
        }
    ],
    "sg:phone":"+1 928 367 4518",
    "sg:postcode":"85935",
    "sg:province":"AZ",
    "sg:tags":[
        "mobile",
        "home",
        "community"
    ],
    "wof:name":"Holiday Forest Mobile Home Pk",
    "wof:placetype":"venue"
},
  "geometry": {"coordinates":[-109.924856,34.125731],"type":"Point"}
}