{
  "type": "Feature",
  "properties": {
    "iso:country":"US",
    "sg:address":"16128 E Via de Arboles",
    "sg:city":"Gilbert",
    "sg:classifiers":[
        {
            "category":"Building & Trades",
            "subcategory":"Landscaping Services",
            "type":"Services"
        }
    ],
    "sg:phone":"+1 602 478 0259",
    "sg:postcode":"85297",
    "sg:province":"AZ",
    "sg:tags":[
        "landscape",
        "contractor"
    ],
    "wof:name":"Best Landscaping Co",
    "wof:placetype":"venue"
},
  "geometry": {"coordinates":[-111.731342,33.227565],"type":"Point"}
}