{
  "type": "Feature",
  "properties": {
    "iso:country":"US",
    "sg:address":"14961 W Bell Rd",
    "sg:city":"Surprise",
    "sg:classifiers":[
        {
            "category":"Real Estate",
            "subcategory":"Real Estate Agent",
            "type":"Services"
        }
    ],
    "sg:phone":"+1 623 399 9157",
    "sg:postcode":"85374",
    "sg:province":"AZ",
    "wof:name":"Diamond GMAC Real Estate",
    "wof:placetype":"venue"
},
  "geometry": {"coordinates":[-112.378828,33.638644],"type":"Point"}
}