{
  "type": "Feature",
  "properties": {
    "iso:country":"US",
    "sg:address":"13759 W Bell Rd",
    "sg:city":"Surprise",
    "sg:classifiers":[
        {
            "category":"Food & Beverages",
            "subcategory":"Farmers Market",
            "type":"Retail Goods"
        }
    ],
    "sg:phone":"+1 623 544 3121",
    "sg:postcode":"85374",
    "sg:province":"AZ",
    "sg:tags":[
        "vegetable",
        "fruit"
    ],
    "wof:name":"Sprouts Farmers Market 12",
    "wof:placetype":"venue"
},
  "geometry": {"coordinates":[-112.35611,33.63858],"type":"Point"}
}