{
  "type": "Feature",
  "properties": {
    "addr:full":"15020 N 40th St Phoenix AZ 85032",
    "addr:housenumber":"15020",
    "addr:postcode":"85032",
    "addr:street":"N 40Th St",
    "iso:country":"US",
    "sg:address":"15020 N 40th St",
    "sg:city":"Phoenix",
    "sg:classifiers":[
        {
            "category":"Retail",
            "subcategory":"Repair Shop",
            "type":"Services"
        }
    ],
    "sg:phone":"+1 602 434 3800",
    "sg:postcode":"85032",
    "sg:province":"AZ",
    "sg:tags":[
        "appliance"
    ],
    "wof:name":"In Home Appliance",
    "wof:placetype":"venue"
},
  "geometry": {"coordinates":[-111.996089,33.623176],"type":"Point"}
}