{
  "type": "Feature",
  "properties": {
    "iso:country":"US",
    "sg:address":"1219 W Baseline Rd",
    "sg:city":"Mesa",
    "sg:classifiers":[
        {
            "category":"Restaurant",
            "type":"Food & Drink"
        }
    ],
    "sg:phone":"+1 480 839 3451",
    "sg:postcode":"85202",
    "sg:province":"AZ",
    "sg:tags":[
        "eating"
    ],
    "wof:name":"Yees Chinese Restaurant",
    "wof:placetype":"venue"
},
  "geometry": {"coordinates":[-111.862783,33.378629],"type":"Point"}
}