{
  "type": "Feature",
  "properties": {
    "iso:country":"US",
    "sg:address":"11202 E Germann Rd",
    "sg:city":"Queen Creek",
    "sg:classifiers":[
        {
            "category":"Manufacturing",
            "subcategory":"Motor Vehicles & Parts",
            "type":"Manufacturing & Wholesale Goods"
        }
    ],
    "sg:phone":"+1 480 987 4000",
    "sg:postcode":"85212",
    "sg:province":"AZ",
    "sg:tags":[
        "automotive",
        "mfg",
        "bag",
        "air"
    ],
    "wof:name":"TRW Safety Systems Inc",
    "wof:placetype":"venue"
},
  "geometry": {"coordinates":[-111.583195,33.277383],"type":"Point"}
}