{
  "type": "Feature",
  "properties": {
    "addr:full":"7440 S Jesse Owens Pkwy Phoenix AZ 85042",
    "addr:housenumber":"7440",
    "addr:postcode":"85042",
    "addr:street":"S Jesse Owens Pkwy",
    "iso:country":"US",
    "sg:address":"7440 S Jesse Owens Pkwy",
    "sg:city":"Phoenix",
    "sg:classifiers":[
        {
            "category":"Restaurant",
            "type":"Food & Drink"
        }
    ],
    "sg:menulink":"http://www.allmenus.com/az/phoenix/231435-sonic/menu/",
    "sg:phone":"+1 602 268 6904",
    "sg:postcode":"85042",
    "sg:province":"AZ",
    "sg:tags":[
        "burger",
        "american"
    ],
    "wof:name":"Sonic",
    "wof:placetype":"venue"
},
  "geometry": {"coordinates":[-112.069487,33.378332],"type":"Point"}
}