{
  "type": "Feature",
  "properties": {
    "iso:country":"US",
    "sg:address":"550 E Cottonwood Ln",
    "sg:city":"Casa Grande",
    "sg:classifiers":[
        {
            "category":"Real Estate",
            "subcategory":"Real Estate Operator",
            "type":"Services"
        }
    ],
    "sg:phone":"+1 520 836 8771",
    "sg:postcode":"85222",
    "sg:province":"AZ",
    "sg:tags":[
        "building",
        "commercial"
    ],
    "wof:name":"Andersen",
    "wof:placetype":"venue"
},
  "geometry": {"coordinates":[-111.747556,32.894212],"type":"Point"}
}