{
  "type": "Feature",
  "properties": {
    "addr:full":"4940 N 103rd Ave Phoenix AZ 85037",
    "addr:housenumber":"4940",
    "addr:postcode":"85037",
    "addr:street":"N 103Rd Ave",
    "iso:country":"US",
    "sg:address":"4940 N 103rd Ave",
    "sg:city":"Phoenix",
    "sg:classifiers":[
        {
            "category":"Education",
            "subcategory":"School",
            "type":"Public Place"
        }
    ],
    "sg:phone":"+1 623 877 1856",
    "sg:postcode":"85037",
    "sg:province":"AZ",
    "sg:tags":[
        "high",
        "middle",
        "elementary"
    ],
    "wof:name":"Villa De Paz Elementary School",
    "wof:placetype":"venue"
},
  "geometry": {"coordinates":[-112.28299699999999,33.506699],"type":"Point"}
}