{
  "type": "Feature",
  "properties": {
    "iso:country":"US",
    "sg:address":"2940 W Ina Rd",
    "sg:city":"Tucson",
    "sg:classifiers":[
        {
            "category":"Retail",
            "subcategory":"Laundry & Dry Cleaning",
            "type":"Services"
        }
    ],
    "sg:phone":"+1 520 797 1533",
    "sg:postcode":"85741",
    "sg:province":"AZ",
    "sg:tags":[
        "cleaners"
    ],
    "wof:name":"Sunset Cleaners",
    "wof:placetype":"venue"
},
  "geometry": {"coordinates":[-111.032383,32.337481],"type":"Point"}
}