{
  "type": "Feature",
  "properties": {
    "iso:country":"US",
    "sg:address":"3801 N Miller Rd",
    "sg:city":"Scottsdale",
    "sg:classifiers":[
        {
            "category":"Place Of Worship",
            "subcategory":"Church",
            "type":"Public Place"
        },
        {
            "category":"Place Of Worship",
            "type":"Public Place"
        },
        {
            "category":"Education",
            "subcategory":"School",
            "type":"Public Place"
        }
    ],
    "sg:phone":"+1 480 874 3720",
    "sg:postcode":"85251",
    "sg:province":"AZ",
    "sg:tags":[
        "churches-catholic",
        "churches-catholic-traditional",
        "private",
        "k-"
    ],
    "sg:website":"http://www.st-gregory.com",
    "wof:name":"Our Lady Perpetual Help School",
    "wof:placetype":"venue"
},
  "geometry": {"coordinates":[-111.917481,33.492095],"type":"Point"}
}