{
  "type": "Feature",
  "properties": {
    "iso:country":"US",
    "sg:address":"409 S 6th St",
    "sg:city":"Cottonwood",
    "sg:classifiers":[
        {
            "category":"Recreation",
            "type":"Entertainment"
        }
    ],
    "sg:phone":"+1 928 639 1120",
    "sg:postcode":"86326",
    "sg:province":"AZ",
    "sg:tags":[
        "amusement"
    ],
    "wof:name":"C & L Motorsports",
    "wof:placetype":"venue"
},
  "geometry": {"coordinates":[-112.022711,34.732075],"type":"Point"}
}