{
  "type": "Feature",
  "properties": {
    "iso:country":"US",
    "sg:address":"3304 N Los Altos Dr",
    "sg:city":"Chandler",
    "sg:classifiers":[
        {
            "category":"Social Services",
            "subcategory":"Adult Care",
            "type":"Services"
        }
    ],
    "sg:phone":"+1 480 897 7236",
    "sg:postcode":"85224",
    "sg:province":"AZ",
    "sg:tags":[
        "home",
        "residential"
    ],
    "wof:name":"Comfort Living Home",
    "wof:placetype":"venue"
},
  "geometry": {"coordinates":[-111.879658,33.35426],"type":"Point"}
}