{
  "type": "Feature",
  "properties": {
    "iso:country":"US",
    "sg:address":"16929 E Enterprise Dr",
    "sg:city":"Fountain Hills",
    "sg:classifiers":[
        {
            "category":"Retail",
            "subcategory":"Repair Shop",
            "type":"Services"
        }
    ],
    "sg:phone":"+1 480 837 7798",
    "sg:postcode":"85268",
    "sg:province":"AZ",
    "sg:tags":[
        "ironwork"
    ],
    "wof:name":"Maycom Iron",
    "wof:placetype":"venue"
},
  "geometry": {"coordinates":[-111.712512,33.595466],"type":"Point"}
}