{
  "type": "Feature",
  "properties": {
    "iso:country":"US",
    "sg:address":"9880 W Pasedena Dr",
    "sg:city":"Casa Grande",
    "sg:phone":"+1 520 836 9096",
    "sg:postcode":"85222",
    "sg:province":"AZ",
    "sg:tags":[
        "farm",
        "field",
        "crop"
    ],
    "wof:name":"Desert Herbalist",
    "wof:placetype":"venue"
},
  "geometry": {"coordinates":[-111.673984,32.947353],"type":"Point"}
}