{
  "type": "Feature",
  "properties": {
    "iso:country":"US",
    "sg:address":"4205 N Winfield Scott Plz",
    "sg:city":"Scottsdale",
    "sg:classifiers":[
        {
            "category":"Social Services",
            "type":"Services"
        }
    ],
    "sg:phone":"+1 480 947 3655",
    "sg:postcode":"85251",
    "sg:province":"AZ",
    "sg:tags":[
        "stress",
        "management"
    ],
    "wof:name":"Scottsdale Institute-Health",
    "wof:placetype":"venue"
},
  "geometry": {"coordinates":[-111.92514,33.49783],"type":"Point"}
}