{
  "type": "Feature",
  "properties": {
    "iso:country":"US",
    "sg:address":"700 N 7th Ave",
    "sg:city":"Tucson",
    "sg:classifiers":[
        {
            "category":"Health Services",
            "subcategory":"Hospital",
            "type":"Services"
        }
    ],
    "sg:phone":"+1 520 740 1850",
    "sg:postcode":"85705",
    "sg:province":"AZ",
    "sg:tags":[
        "mental"
    ],
    "wof:name":"Codac Behavioral Health Svc",
    "wof:placetype":"venue"
},
  "geometry": {"coordinates":[-110.970208,32.231616],"type":"Point"}
}