{
  "type": "Feature",
  "properties": {
    "addr:full":"10943 E Palomino Rd Scottsdale AZ 85259",
    "addr:housenumber":"10943",
    "addr:postcode":"85259",
    "addr:street":"E Palomino Rd",
    "iso:country":"US",
    "sg:address":"10943 E Palomino Rd",
    "sg:city":"Scottsdale",
    "sg:classifiers":[
        {
            "category":"Professional",
            "subcategory":"Management & Consulting",
            "type":"Services"
        }
    ],
    "sg:phone":"+1 480 661 5765",
    "sg:postcode":"85259",
    "sg:province":"AZ",
    "sg:tags":[
        "consultant",
        "business"
    ],
    "sg:website":"www.aluver.com",
    "wof:name":"Sonora Consulting",
    "wof:placetype":"venue"
},
  "geometry": {"coordinates":[-111.843474,33.570786],"type":"Point"}
}