{
  "type": "Feature",
  "properties": {
    "iso:country":"US",
    "sg:address":"220 S Plumer Ave",
    "sg:city":"Tucson",
    "sg:classifiers":[
        {
            "category":"Shopping",
            "subcategory":"Books",
            "type":"Retail Goods"
        }
    ],
    "sg:phone":"+1 520 628 7214",
    "sg:postcode":"85719",
    "sg:province":"AZ",
    "wof:name":"Twelve Step Book and Gift Str",
    "wof:placetype":"venue"
},
  "geometry": {"coordinates":[-110.939532,32.219039],"type":"Point"}
}