{
  "type": "Feature",
  "properties": {
    "addr:full":"17222 N Cave Creek Rd Phoenix AZ 85032",
    "addr:housenumber":"17222",
    "addr:postcode":"85032",
    "addr:street":"N Cave Creek Rd",
    "iso:country":"US",
    "sg:address":"17222 N Cave Creek Rd",
    "sg:city":"Phoenix",
    "sg:classifiers":[
        {
            "category":"Bars & Pubs",
            "type":"Food & Drink"
        }
    ],
    "sg:phone":"+1 602 788 0507",
    "sg:postcode":"85032",
    "sg:province":"AZ",
    "wof:name":"Brigett's Last Laugh",
    "wof:placetype":"venue"
},
  "geometry": {"coordinates":[-112.030919,33.642403],"type":"Point"}
}