{
  "type": "Feature",
  "properties": {
    "iso:country":"US",
    "sg:address":"5364 S Oregon Dr",
    "sg:city":"Tucson",
    "sg:classifiers":[
        {
            "category":"Building & Trades",
            "subcategory":"Construction",
            "type":"Services"
        }
    ],
    "sg:phone":"+1 520 741 9764",
    "sg:postcode":"85706",
    "sg:province":"AZ",
    "sg:tags":[
        "contractor"
    ],
    "wof:name":"T C Roofing Co",
    "wof:placetype":"venue"
},
  "geometry": {"coordinates":[-110.98269500000001,32.155116],"type":"Point"}
}