{
  "type": "Feature",
  "properties": {
    "iso:country":"US",
    "sg:address":"5460 N Dodge Ave",
    "sg:city":"Flagstaff",
    "sg:classifiers":[
        {
            "category":"Manufacturing",
            "subcategory":"Food",
            "type":"Manufacturing & Wholesale Goods"
        },
        {
            "category":"Food & Beverages",
            "subcategory":"Bakery",
            "type":"Retail Goods"
        }
    ],
    "sg:phone":"+1 928 526 0662",
    "sg:postcode":"86004",
    "sg:province":"AZ",
    "sg:tags":[
        "baker",
        "product",
        "mfg"
    ],
    "wof:name":"Holsum Bakery Inc",
    "wof:placetype":"venue"
},
  "geometry": {"coordinates":[-111.570123,35.227616],"type":"Point"}
}