{
  "type": "Feature",
  "properties": {
    "addr:full":"3920 S Rural Rd Ste 100 Tempe AZ 85282",
    "addr:housenumber":"3920",
    "addr:postcode":"85282",
    "addr:street":"S Rural Rd Ste 100",
    "iso:country":"US",
    "sg:address":"3920 S Rural Rd Ste 100",
    "sg:city":"Tempe",
    "sg:classifiers":[
        {
            "category":"Real Estate",
            "subcategory":"Real Estate Agent",
            "type":"Services"
        }
    ],
    "sg:phone":"+1 480 768 9333",
    "sg:postcode":"85282",
    "sg:province":"AZ",
    "wof:name":"Patrick Walsh",
    "wof:placetype":"venue"
},
  "geometry": {"coordinates":[-111.92667899999999,33.386644],"type":"Point"}
}