{
  "type": "Feature",
  "properties": {
    "iso:country":"US",
    "sg:address":"1201 E Desert Park Ln",
    "sg:city":"Phoenix",
    "sg:classifiers":[
        {
            "category":"Food & Beverages",
            "subcategory":"Specialty",
            "type":"Retail Goods"
        }
    ],
    "sg:phone":"+1 602 277 8363",
    "sg:postcode":"85020",
    "sg:province":"AZ",
    "sg:tags":[
        "vitamin"
    ],
    "wof:name":"Greenfingers Herbal Clinic",
    "wof:placetype":"venue"
},
  "geometry": {"coordinates":[-112.054372,33.551229],"type":"Point"}
}