{
  "type": "Feature",
  "properties": {
    "iso:country":"US",
    "sg:address":"8058 N Oracle Rd",
    "sg:city":"Tucson",
    "sg:classifiers":[
        {
            "category":"Restaurant",
            "type":"Food & Drink"
        }
    ],
    "sg:menulink":"http://www.allmenus.com/az/tucson/147513-famous-sams/menu/",
    "sg:phone":"+1 520 531 9464",
    "sg:postcode":"85704",
    "sg:province":"AZ",
    "sg:tags":[
        "wrap",
        "american",
        "sandwich"
    ],
    "wof:name":"Famous Sam's",
    "wof:placetype":"venue"
},
  "geometry": {"coordinates":[-110.97331699999999,32.352721],"type":"Point"}
}