{
  "type": "Feature",
  "properties": {
    "addr:full":"14300 N Northsight Blvd Scottsdale AZ 85260",
    "addr:housenumber":"14300",
    "addr:postcode":"85260",
    "addr:street":"N Northsight Blvd",
    "iso:country":"US",
    "sg:address":"14300 N Northsight Blvd",
    "sg:city":"Scottsdale",
    "sg:classifiers":[
        {
            "category":"Building & Trades",
            "subcategory":"Construction",
            "type":"Services"
        }
    ],
    "sg:phone":"+1 480 443 9100",
    "sg:postcode":"85260",
    "sg:province":"AZ",
    "sg:tags":[
        "house",
        "builder",
        "home"
    ],
    "wof:name":"Carlson Homes LLC",
    "wof:placetype":"venue"
},
  "geometry": {"coordinates":[-111.897852,33.614886],"type":"Point"}
}