{
  "type": "Feature",
  "properties": {
    "addr:full":"3109 E Cactus Rd Phoenix AZ 85032",
    "addr:housenumber":"3109",
    "addr:postcode":"85032",
    "addr:street":"E Cactus Rd",
    "iso:country":"US",
    "sg:address":"3109 E Cactus Rd",
    "sg:city":"Phoenix",
    "sg:classifiers":[
        {
            "category":"Health Services",
            "subcategory":"Chiropractor",
            "type":"Services"
        }
    ],
    "sg:phone":"+1 602 788 6696",
    "sg:postcode":"85032",
    "sg:province":"AZ",
    "wof:name":"Chiropractic Health Ctr",
    "wof:placetype":"venue"
},
  "geometry": {"coordinates":[-112.013305,33.596923],"type":"Point"}
}