{
  "type": "Feature",
  "properties": {
    "iso:country":"US",
    "sg:address":"1837 S Mesa Dr Ste B103",
    "sg:city":"Mesa",
    "sg:classifiers":[
        {
            "category":"Government",
            "subcategory":"Court House",
            "type":"Public Place"
        },
        {
            "category":"Government",
            "subcategory":"Office",
            "type":"Public Place"
        }
    ],
    "sg:phone":"+1 480 926 9731",
    "sg:postcode":"85210",
    "sg:province":"AZ",
    "sg:tags":[
        "justice",
        "parish",
        "government-county"
    ],
    "sg:website":"http://www.mcjc.maricopa.gov",
    "wof:name":"Maricopa County Justice Court",
    "wof:placetype":"venue"
},
  "geometry": {"coordinates":[-111.823257,33.382287],"type":"Point"}
}