{
  "type": "Feature",
  "properties": {
    "iso:country":"US",
    "sg:address":"2151 S Avenida Los Reyes",
    "sg:city":"Tucson",
    "sg:classifiers":[
        {
            "category":"Retail",
            "subcategory":"Funeral Services",
            "type":"Services"
        }
    ],
    "sg:phone":"+1 520 885 9173",
    "sg:postcode":"85748",
    "sg:province":"AZ",
    "sg:tags":[
        "cemetery"
    ],
    "wof:name":"All Faiths Cemeteries",
    "wof:placetype":"venue"
},
  "geometry": {"coordinates":[-110.764136,32.195904],"type":"Point"}
}