{
  "type": "Feature",
  "properties": {
    "addr:full":"5244 N 25th St Phoenix AZ 85016",
    "addr:housenumber":"5244",
    "addr:postcode":"85016",
    "addr:street":"N 25Th St",
    "iso:country":"US",
    "sg:address":"5244 N 25th St",
    "sg:city":"Phoenix",
    "sg:classifiers":[
        {
            "category":"Banks & Credit Unions",
            "subcategory":"Investment Brokerage",
            "type":"Services"
        }
    ],
    "sg:phone":"+1 602 553 9229",
    "sg:postcode":"85016",
    "sg:province":"AZ",
    "sg:tags":[
        "trust"
    ],
    "wof:name":"Heffner Revocable Trust",
    "wof:placetype":"venue"
},
  "geometry": {"coordinates":[-112.027986,33.51371],"type":"Point"}
}