{
  "type": "Feature",
  "properties": {
    "iso:country":"US",
    "sg:address":"3501 W Encanto Blvd",
    "sg:city":"Phoenix",
    "sg:classifiers":[
        {
            "category":"Retail",
            "subcategory":"Auto Repair",
            "type":"Services"
        }
    ],
    "sg:phone":"+1 602 484 9276",
    "sg:postcode":"85009",
    "sg:province":"AZ",
    "sg:tags":[
        "repairing",
        "automobile",
        "radiator"
    ],
    "wof:name":"Pacific Radiator",
    "wof:placetype":"venue"
},
  "geometry": {"coordinates":[-112.136556,33.473169],"type":"Point"}
}