{
  "type": "Feature",
  "properties": {
    "addr:full":"242 E University Dr Phoenix AZ 85004",
    "addr:housenumber":"242",
    "addr:postcode":"85004",
    "addr:street":"E University Dr",
    "iso:country":"US",
    "sg:address":"242 E University Dr",
    "sg:city":"Phoenix",
    "sg:classifiers":[
        {
            "category":"Wholesale",
            "subcategory":"Groceries",
            "type":"Manufacturing & Wholesale Goods"
        }
    ],
    "sg:phone":"+1 602 252 1233",
    "sg:postcode":"85004",
    "sg:province":"AZ",
    "sg:tags":[
        "equipment",
        "pizza",
        "supply"
    ],
    "wof:name":"Khoury's Specialty Foods-Az",
    "wof:placetype":"venue"
},
  "geometry": {"coordinates":[-112.069095,33.423568],"type":"Point"}
}