{
  "type": "Feature",
  "properties": {
    "iso:country":"US",
    "sg:address":"5638 E Thomas Rd",
    "sg:city":"Phoenix",
    "sg:classifiers":[
        {
            "category":"Health Services",
            "subcategory":"Dentist",
            "type":"Services"
        }
    ],
    "sg:phone":"+1 480 990 2343",
    "sg:postcode":"85018",
    "sg:province":"AZ",
    "wof:name":"Bryan T Tran Dds & Assoc Pc",
    "wof:placetype":"venue"
},
  "geometry": {"coordinates":[-111.959762,33.480053],"type":"Point"}
}