{
  "type": "Feature",
  "properties": {
    "addr:full":"905 S Yucca Dr Wickenburg AZ 85390",
    "addr:housenumber":"905",
    "addr:postcode":"85390",
    "addr:street":"S Yucca Dr",
    "iso:country":"US",
    "sg:address":"905 S Yucca Dr",
    "sg:city":"Wickenburg",
    "sg:classifiers":[
        {
            "category":"Organizations",
            "subcategory":"Religious Organization",
            "type":"Services"
        }
    ],
    "sg:phone":"+1 928 684 3525",
    "sg:postcode":"85390",
    "sg:province":"AZ",
    "sg:tags":[
        "church"
    ],
    "wof:name":"Community Alliance Church",
    "wof:placetype":"venue"
},
  "geometry": {"coordinates":[-112.762936,33.956191],"type":"Point"}
}