{
  "type": "Feature",
  "properties": {
    "iso:country":"US",
    "sg:address":"1024 S 1st Ave",
    "sg:city":"Phoenix",
    "sg:classifiers":[
        {
            "category":"Banks & Credit Unions",
            "subcategory":"Financial Services",
            "type":"Services"
        }
    ],
    "sg:phone":"+1 602 258 3731",
    "sg:postcode":"85003",
    "sg:province":"AZ",
    "sg:tags":[
        "accountant",
        "referral"
    ],
    "wof:name":"Lopez Tax Service",
    "wof:placetype":"venue"
},
  "geometry": {"coordinates":[-112.075081,33.437839],"type":"Point"}
}