{
  "type": "Feature",
  "properties": {
    "iso:country":"US",
    "sg:address":"14925 N 150th Ave",
    "sg:city":"Surprise",
    "sg:classifiers":[
        {
            "category":"Food & Beverages",
            "subcategory":"Specialty",
            "type":"Retail Goods"
        }
    ],
    "sg:phone":"+1 623 326 3991",
    "sg:postcode":"85379",
    "sg:province":"AZ",
    "wof:name":"Herbalife",
    "wof:placetype":"venue"
},
  "geometry": {"coordinates":[-112.38390200000001,33.619475],"type":"Point"}
}