{
  "type": "Feature",
  "properties": {
    "iso:country":"US",
    "sg:address":"16001 N 34th St",
    "sg:city":"Phoenix",
    "sg:classifiers":[
        {
            "category":"Organizations",
            "subcategory":"Non-profit Organization",
            "type":"Services"
        }
    ],
    "sg:phone":"+1 602 971 8501",
    "sg:postcode":"85032",
    "sg:province":"AZ",
    "sg:website":"www.jewishvoice.org",
    "wof:name":"Jewish Voice Broadcasting Inc",
    "wof:placetype":"venue"
},
  "geometry": {"coordinates":[-112.009013,33.631722],"type":"Point"}
}