{
  "type": "Feature",
  "properties": {
    "iso:country":"US",
    "sg:address":"3255 W Orange Grove Rd",
    "sg:city":"Tucson",
    "sg:classifiers":[
        {
            "category":"Restaurant",
            "type":"Food & Drink"
        }
    ],
    "sg:menulink":"http://www.allmenus.com/az/tucson/231458-sonic/menu/",
    "sg:phone":"+1 520 219 4303",
    "sg:postcode":"85741",
    "sg:province":"AZ",
    "sg:tags":[
        "burger",
        "american"
    ],
    "wof:name":"Sonic",
    "wof:placetype":"venue"
},
  "geometry": {"coordinates":[-111.036362,32.322511],"type":"Point"}
}