{
  "type": "Feature",
  "properties": {
    "iso:country":"US",
    "sg:address":"427 N 44th St",
    "sg:city":"Phoenix",
    "sg:classifiers":[
        {
            "category":"Travel",
            "subcategory":"Hotels & Motels",
            "type":"Entertainment"
        }
    ],
    "sg:phone":"+1 602 220 4400",
    "sg:postcode":"85008",
    "sg:province":"AZ",
    "sg:tags":[
        "lodging"
    ],
    "sg:website":"http://www.radisson.com/phoenixaz_airportnorth",
    "wof:name":"Radisson Hotel Phoenix Airport North",
    "wof:placetype":"venue"
},
  "geometry": {"coordinates":[-111.987074,33.453136],"type":"Point"}
}