{
  "type": "Feature",
  "properties": {
    "addr:full":"1551 E Elliot Rd Gilbert AZ 85234",
    "addr:housenumber":"1551",
    "addr:postcode":"85234",
    "addr:street":"E Elliot Rd",
    "iso:country":"US",
    "sg:address":"1551 E Elliot Rd",
    "sg:city":"Gilbert",
    "sg:classifiers":[
        {
            "category":"Shopping",
            "subcategory":"Florist",
            "type":"Retail Goods"
        }
    ],
    "sg:phone":"+1 480 558 9407",
    "sg:postcode":"85234",
    "sg:province":"AZ",
    "wof:name":"Lena Inzunza",
    "wof:placetype":"venue"
},
  "geometry": {"coordinates":[-111.755743,33.350109],"type":"Point"}
}