{
  "type": "Feature",
  "properties": {
    "addr:full":"434 S Beeline Hwy Payson AZ 85541",
    "addr:housenumber":"434",
    "addr:postcode":"85541",
    "addr:street":"S Beeline Hwy",
    "iso:country":"US",
    "sg:address":"434 S Beeline Hwy",
    "sg:city":"Payson",
    "sg:classifiers":[
        {
            "category":"Home & Garden",
            "subcategory":"Carpets & Floor Coverings",
            "type":"Retail Goods"
        }
    ],
    "sg:phone":"+1 928 474 5828",
    "sg:postcode":"85541",
    "sg:province":"AZ",
    "sg:tags":[
        "dealer",
        "rug"
    ],
    "wof:name":"Cash & Carry Carpet",
    "wof:placetype":"venue"
},
  "geometry": {"coordinates":[-111.32321399999999,34.235946],"type":"Point"}
}