{
  "type": "Feature",
  "properties": {
    "iso:country":"US",
    "sg:address":"815 E Mountain View Rd",
    "sg:city":"Phoenix",
    "sg:classifiers":[
        {
            "category":"Wholesale",
            "subcategory":"Drugs",
            "type":"Manufacturing & Wholesale Goods"
        }
    ],
    "sg:phone":"+1 602 943 3133",
    "sg:postcode":"85020",
    "sg:province":"AZ",
    "sg:tags":[
        "aid",
        "product",
        "health",
        "beauty"
    ],
    "wof:name":"Greenfield Shampoo",
    "wof:placetype":"venue"
},
  "geometry": {"coordinates":[-112.061155,33.574902],"type":"Point"}
}