{
  "type": "Feature",
  "properties": {
    "iso:country":"US",
    "sg:address":"1826 W Broadway Rd",
    "sg:city":"Mesa",
    "sg:classifiers":[
        {
            "category":"Home & Garden",
            "subcategory":"Building Materials",
            "type":"Retail Goods"
        },
        {
            "category":"Manufacturing",
            "subcategory":"Building Materials",
            "type":"Manufacturing & Wholesale Goods"
        }
    ],
    "sg:phone":"+1 480 664 0251",
    "sg:postcode":"85202",
    "sg:province":"AZ",
    "sg:tags":[
        "window",
        "doors-wholesale",
        "manufacturer"
    ],
    "wof:name":"American Vision Windows Of Arizona",
    "wof:placetype":"venue"
},
  "geometry": {"coordinates":[-111.870914,33.407603],"type":"Point"}
}