{
  "type": "Feature",
  "properties": {
    "iso:country":"US",
    "sg:address":"2120 E 6th St 10-11",
    "sg:city":"Tempe",
    "sg:classifiers":[
        {
            "category":"Utilities",
            "subcategory":"Mobile Phone",
            "type":"Services"
        },
        {
            "category":"Shopping",
            "subcategory":"Mobile Phones",
            "type":"Retail Goods"
        },
        {
            "category":"Utilities",
            "subcategory":"Telephone",
            "type":"Services"
        }
    ],
    "sg:phone":"+1 480 968 2074",
    "sg:postcode":"85281",
    "sg:province":"AZ",
    "sg:tags":[
        "supply",
        "communication",
        "system",
        "wireless",
        "equipment",
        "cellular"
    ],
    "sg:website":"http://www.mobilesolutions-usa.com",
    "wof:name":"Mobile Solutions",
    "wof:placetype":"venue"
},
  "geometry": {"coordinates":[-111.895639,33.42399],"type":"Point"}
}