{
  "type": "Feature",
  "properties": {
    "iso:country":"US",
    "sg:address":"1660 S Alma School Rd",
    "sg:city":"Mesa",
    "sg:classifiers":[
        {
            "category":"Professional",
            "subcategory":"Research",
            "type":"Services"
        }
    ],
    "sg:phone":"+1 480 777 8090",
    "sg:postcode":"85210",
    "sg:province":"AZ",
    "sg:tags":[
        "development",
        "technology-research"
    ],
    "wof:name":"Beige Technologies",
    "wof:placetype":"venue"
},
  "geometry": {"coordinates":[-111.857496,33.384258],"type":"Point"}
}