{
  "type": "Feature",
  "properties": {
    "iso:country":"US",
    "sg:address":"9044 S Dateland Dr",
    "sg:city":"Tempe",
    "sg:classifiers":[
        {
            "category":"Real Estate",
            "subcategory":"Real Estate Operator",
            "type":"Services"
        }
    ],
    "sg:phone":"+1 480 945 4287",
    "sg:postcode":"85284",
    "sg:province":"AZ",
    "sg:tags":[
        "building",
        "apartment"
    ],
    "wof:name":"Twenty Three Oaks LLC",
    "wof:placetype":"venue"
},
  "geometry": {"coordinates":[-111.941384,33.331735],"type":"Point"}
}