{
  "type": "Feature",
  "properties": {
    "addr:full":"3573 E Sunrise Dr Tucson AZ 85718",
    "addr:housenumber":"3573",
    "addr:postcode":"85718",
    "addr:street":"E Sunrise Dr",
    "iso:country":"US",
    "sg:address":"3573 E Sunrise Dr",
    "sg:city":"Tucson",
    "sg:classifiers":[
        {
            "category":"Professional",
            "subcategory":"Management & Consulting",
            "type":"Services"
        }
    ],
    "sg:phone":"+1 520 299 1995",
    "sg:postcode":"85718",
    "sg:province":"AZ",
    "sg:tags":[
        "construction"
    ],
    "sg:website":"www.heery.com",
    "wof:name":"Heery International",
    "wof:placetype":"venue"
},
  "geometry": {"coordinates":[-110.915318,32.318401],"type":"Point"}
}