{
  "type": "Feature",
  "properties": {
    "iso:country":"US",
    "sg:address":"417 E Forest Hills Dr",
    "sg:city":"Phoenix",
    "sg:classifiers":[
        {
            "category":"Professional",
            "subcategory":"Business Services",
            "type":"Services"
        }
    ],
    "sg:phone":"+1 602 938 3288",
    "sg:postcode":"85022",
    "sg:province":"AZ",
    "sg:tags":[
        "consultant",
        "coach"
    ],
    "wof:name":"Forest Hills Construction Consultants Ll",
    "wof:placetype":"venue"
},
  "geometry": {"coordinates":[-112.06739,33.619898],"type":"Point"}
}