{
  "type": "Feature",
  "properties": {
    "iso:country":"US",
    "sg:address":"3829 N 3rd St",
    "sg:city":"Phoenix",
    "sg:classifiers":[
        {
            "category":"Shopping",
            "type":"Retail Goods"
        },
        {
            "category":"Organizations",
            "subcategory":"Non-profit Organization",
            "type":"Services"
        }
    ],
    "sg:phone":"+1 602 200 0675",
    "sg:postcode":"85012",
    "sg:province":"AZ",
    "sg:tags":[
        "supply",
        "fund",
        "games",
        "merchandise",
        "raising"
    ],
    "wof:name":"Professional Fundraisers",
    "wof:placetype":"venue"
},
  "geometry": {"coordinates":[-112.06941999999999,33.492248],"type":"Point"}
}