{
  "type": "Feature",
  "properties": {
    "iso:country":"US",
    "sg:address":"708 State Hwy 260",
    "sg:city":"Payson",
    "sg:classifiers":[
        {
            "category":"Professional",
            "subcategory":"Accounting & Tax Preparation",
            "type":"Services"
        }
    ],
    "sg:phone":"+1 928 474 6171",
    "sg:postcode":"85541",
    "sg:province":"AZ",
    "sg:tags":[
        "accountant"
    ],
    "wof:name":"Valerie A Lubken CPA",
    "wof:placetype":"venue"
},
  "geometry": {"coordinates":[-111.322748,34.249437],"type":"Point"}
}