{
  "type": "Feature",
  "properties": {
    "addr:full":"882 Sunset Ave Prescott AZ 86305",
    "addr:housenumber":"882",
    "addr:postcode":"86305",
    "addr:street":"Sunset Ave",
    "iso:country":"US",
    "sg:address":"882 Sunset Ave",
    "sg:city":"Prescott",
    "sg:classifiers":[
        {
            "category":"Place Of Worship",
            "subcategory":"Church",
            "type":"Public Place"
        },
        {
            "category":"Place Of Worship",
            "type":"Public Place"
        }
    ],
    "sg:phone":"+1 928 541 0000",
    "sg:postcode":"86305",
    "sg:province":"AZ",
    "sg:tags":[
        "churches-interdenominational",
        "churches-various",
        "denomination"
    ],
    "wof:name":"Granite Peak Unitarian Church",
    "wof:placetype":"venue"
},
  "geometry": {"coordinates":[-112.484779,34.554845],"type":"Point"}
}