{
  "type": "Feature",
  "properties": {
    "iso:country":"US",
    "sg:address":"7515 E Mcdowell Rd",
    "sg:city":"Scottsdale",
    "sg:classifiers":[
        {
            "category":"Arena",
            "subcategory":"Sports Club",
            "type":"Entertainment"
        }
    ],
    "sg:phone":"+1 480 990 1814",
    "sg:postcode":"85257",
    "sg:province":"AZ",
    "sg:tags":[
        "martial art",
        "instruction"
    ],
    "wof:name":"Way Of Dragon",
    "wof:placetype":"venue"
},
  "geometry": {"coordinates":[-111.91946900000001,33.465693],"type":"Point"}
}