{
  "type": "Feature",
  "properties": {
    "iso:country":"US",
    "sg:address":"5044 W Blackbird Dr",
    "sg:city":"Tucson",
    "sg:classifiers":[
        {
            "category":"Professional",
            "subcategory":"Business Services",
            "type":"Services"
        }
    ],
    "sg:phone":"+1 520 546 9797",
    "sg:postcode":"85742",
    "sg:province":"AZ",
    "sg:tags":[
        "estate"
    ],
    "sg:website":"www.brownsareselling.com",
    "wof:name":"Browns Are Selling Inc",
    "wof:placetype":"venue"
},
  "geometry": {"coordinates":[-111.072433,32.380711],"type":"Point"}
}