{
  "type": "Feature",
  "properties": {
    "addr:full":"6522 W Glendale Ave Glendale AZ 85301",
    "addr:housenumber":"6522",
    "addr:postcode":"85301",
    "addr:street":"W Glendale Ave",
    "iso:country":"US",
    "sg:address":"6522 W Glendale Ave",
    "sg:city":"Glendale",
    "sg:classifiers":[
        {
            "category":"Restaurant",
            "type":"Food & Drink"
        }
    ],
    "sg:phone":"+1 623 847 9935",
    "sg:postcode":"85301",
    "sg:province":"AZ",
    "sg:tags":[
        "eating"
    ],
    "wof:name":"Supertacos Los Cuais",
    "wof:placetype":"venue"
},
  "geometry": {"coordinates":[-112.199955,33.538448],"type":"Point"}
}