{
  "type": "Feature",
  "properties": {
    "addr:full":"3033 N 3rd Ave Phoenix AZ 85013",
    "addr:housenumber":"3033",
    "addr:postcode":"85013",
    "addr:street":"N 3Rd Ave",
    "iso:country":"US",
    "sg:address":"3033 N 3rd Ave",
    "sg:city":"Phoenix",
    "sg:classifiers":[
        {
            "category":"Professional",
            "subcategory":"Accounting & Tax Preparation",
            "type":"Services"
        }
    ],
    "sg:phone":"+1 602 307 2237",
    "sg:postcode":"85013",
    "sg:province":"AZ",
    "sg:tags":[
        "bookkeeping"
    ],
    "sg:website":"http://www.perotsystems.com",
    "wof:name":"Perot Systems Corporation",
    "wof:placetype":"venue"
},
  "geometry": {"coordinates":[-112.07841500000001,33.482773],"type":"Point"}
}