{
  "type": "Feature",
  "properties": {
    "iso:country":"US",
    "sg:address":"15525 N 83rd Way",
    "sg:city":"Scottsdale",
    "sg:classifiers":[
        {
            "category":"Shopping",
            "subcategory":"Bicycles & Sporting Goods",
            "type":"Retail Goods"
        }
    ],
    "sg:phone":"+1 480 922 4517",
    "sg:postcode":"85260",
    "sg:province":"AZ",
    "wof:name":"Jaanus Bicycles Inc",
    "wof:placetype":"venue"
},
  "geometry": {"coordinates":[-111.901605,33.627958],"type":"Point"}
}