{
  "type": "Feature",
  "properties": {
    "iso:country":"US",
    "sg:address":"13231 N 35th Ave",
    "sg:city":"Phoenix",
    "sg:classifiers":[
        {
            "category":"Health Services",
            "subcategory":"Health Practitioner",
            "type":"Services"
        }
    ],
    "sg:phone":"+1 602 896 1312",
    "sg:postcode":"85029",
    "sg:province":"AZ",
    "sg:tags":[
        "therapist",
        "physical"
    ],
    "wof:name":"Star Physical Therapy & Ftnss",
    "wof:placetype":"venue"
},
  "geometry": {"coordinates":[-112.13379,33.606292],"type":"Point"}
}