{
  "type": "Feature",
  "properties": {
    "addr:full":"170 Blackhawk Ln Sedona AZ 86336",
    "addr:housenumber":"170",
    "addr:postcode":"86336",
    "addr:street":"Blackhawk Ln",
    "iso:country":"US",
    "sg:address":"170 Blackhawk Ln",
    "sg:city":"Sedona",
    "sg:classifiers":[
        {
            "category":"Food & Beverages",
            "subcategory":"Specialty",
            "type":"Retail Goods"
        }
    ],
    "sg:phone":"+1 928 204 2027",
    "sg:postcode":"86336",
    "sg:province":"AZ",
    "sg:tags":[
        "health",
        "diet"
    ],
    "wof:name":"Rainbow Amazon Herbs",
    "wof:placetype":"venue"
},
  "geometry": {"coordinates":[-111.767751,34.854445],"type":"Point"}
}