{
  "type": "Feature",
  "properties": {
    "iso:country":"US",
    "sg:address":"3655 W Anthem Way",
    "sg:city":"Anthem",
    "sg:classifiers":[
        {
            "category":"Wholesale",
            "subcategory":"Plants",
            "type":"Manufacturing & Wholesale Goods"
        },
        {
            "category":"Shopping",
            "subcategory":"Florist",
            "type":"Retail Goods"
        }
    ],
    "sg:phone":"+1 623 465 0343",
    "sg:postcode":"85086",
    "sg:province":"AZ",
    "sg:tags":[
        "supply"
    ],
    "wof:name":"Baskets Blossoms & Bears",
    "wof:placetype":"venue"
},
  "geometry": {"coordinates":[-112.136904,33.866036],"type":"Point"}
}