{
  "type": "Feature",
  "properties": {
    "addr:full":"8121 W Harrison St Tolleson AZ 85353",
    "addr:housenumber":"8121",
    "addr:postcode":"85353",
    "addr:street":"W Harrison St",
    "iso:country":"US",
    "sg:address":"8121 W Harrison St",
    "sg:city":"Tolleson",
    "sg:classifiers":[
        {
            "category":"Farming",
            "subcategory":"Farm & Veterinary Services",
            "type":"Manufacturing & Wholesale Goods"
        }
    ],
    "sg:phone":"+1 602 569 6553",
    "sg:postcode":"85353",
    "sg:province":"AZ",
    "sg:tags":[
        "specializing",
        "livestock",
        "provides"
    ],
    "wof:name":"Silage",
    "wof:placetype":"venue"
},
  "geometry": {"coordinates":[-112.234408,33.445028],"type":"Point"}
}