{
  "type": "Feature",
  "properties": {
    "addr:full":"7077 N Thornydale Rd Tucson AZ 85741",
    "addr:housenumber":"7077",
    "addr:postcode":"85741",
    "addr:street":"N Thornydale Rd",
    "iso:country":"US",
    "sg:address":"7077 N Thornydale Rd",
    "sg:city":"Tucson",
    "sg:classifiers":[
        {
            "category":"Restaurant",
            "type":"Food & Drink"
        }
    ],
    "sg:menulink":"http://www.allmenus.com/az/tucson/7538-rubios/menu/",
    "sg:phone":"+1 520 579 9300",
    "sg:postcode":"85741",
    "sg:province":"AZ",
    "sg:tags":[
        "seafood",
        "mexican",
        "american"
    ],
    "wof:name":"Rubio's",
    "wof:placetype":"venue"
},
  "geometry": {"coordinates":[-111.04739499999999,32.335442],"type":"Point"}
}