{
  "type": "Feature",
  "properties": {
    "iso:country":"US",
    "sg:address":"1364 Acacia Dr",
    "sg:city":"Sierra Vista",
    "sg:classifiers":[
        {
            "category":"Bars & Pubs",
            "type":"Food & Drink"
        }
    ],
    "sg:phone":"+1 520 459 1516",
    "sg:postcode":"85635",
    "sg:province":"AZ",
    "sg:tags":[
        "club"
    ],
    "wof:name":"Dream Catchers Nite Club",
    "wof:placetype":"venue"
},
  "geometry": {"coordinates":[-110.28631300000001,31.56174],"type":"Point"}
}