{
  "type": "Feature",
  "properties": {
    "iso:country":"US",
    "sg:address":"2331 E Osborn Rd",
    "sg:city":"Phoenix",
    "sg:classifiers":[
        {
            "category":"Insurance",
            "subcategory":"Insurance Agent",
            "type":"Services"
        }
    ],
    "sg:phone":"+1 602 957 8622",
    "sg:postcode":"85016",
    "sg:province":"AZ",
    "sg:website":"www.glassford.com",
    "wof:name":"Glassford Agency Inc",
    "wof:placetype":"venue"
},
  "geometry": {"coordinates":[-112.030783,33.487498],"type":"Point"}
}