{
  "type": "Feature",
  "properties": {
    "iso:country":"US",
    "sg:address":"8578 E Lee Pl",
    "sg:city":"Tucson",
    "sg:classifiers":[
        {
            "category":"Retail",
            "subcategory":"Portrait Studio",
            "type":"Services"
        }
    ],
    "sg:phone":"+1 520 885 2935",
    "sg:postcode":"85715",
    "sg:province":"AZ",
    "sg:tags":[
        "photographer"
    ],
    "wof:name":"Kraft & Co Photography",
    "wof:placetype":"venue"
},
  "geometry": {"coordinates":[-110.810074,32.241141],"type":"Point"}
}