{
  "type": "Feature",
  "properties": {
    "iso:country":"US",
    "sg:address":"6819 S 44th Pl",
    "sg:city":"Phoenix",
    "sg:classifiers":[
        {
            "category":"Shopping",
            "subcategory":"Gifts & Souvenirs",
            "type":"Retail Goods"
        }
    ],
    "sg:phone":"+1 602 438 8998",
    "sg:postcode":"85042",
    "sg:province":"AZ",
    "sg:tags":[
        "shop"
    ],
    "wof:name":"Sylvia's Gifts & Things",
    "wof:placetype":"venue"
},
  "geometry": {"coordinates":[-111.98620699999999,33.386177],"type":"Point"}
}