{
  "type": "Feature",
  "properties": {
    "iso:country":"US",
    "sg:address":"3133 E Greenway Rd # 503",
    "sg:city":"Phoenix",
    "sg:classifiers":[
        {
            "category":"Shopping",
            "subcategory":"Beauty & Cosmetics",
            "type":"Retail Goods"
        },
        {
            "category":"Personal",
            "subcategory":"Barber",
            "type":"Services"
        }
    ],
    "sg:phone":"+1 602 788 4767",
    "sg:postcode":"85032",
    "sg:province":"AZ",
    "sg:tags":[
        "equipment",
        "perfume",
        "salons-equipment",
        "supply"
    ],
    "wof:name":"Armstrong Mccall Scottsdale Inc",
    "wof:placetype":"venue"
},
  "geometry": {"coordinates":[-112.014488,33.62624],"type":"Point"}
}