{
  "type": "Feature",
  "properties": {
    "iso:country":"US",
    "sg:address":"4090 N Oracle Rd",
    "sg:city":"Tucson",
    "sg:classifiers":[
        {
            "category":"Restaurant",
            "type":"Food & Drink"
        }
    ],
    "sg:phone":"+1 520 292 9797",
    "sg:postcode":"85705",
    "sg:province":"AZ",
    "wof:name":"Nico's Mexican Food",
    "wof:placetype":"venue"
},
  "geometry": {"coordinates":[-110.9781,32.281177],"type":"Point"}
}