{
  "type": "Feature",
  "properties": {
    "iso:country":"US",
    "sg:address":"2612 E Broadway Blvd",
    "sg:city":"Tucson",
    "sg:classifiers":[
        {
            "category":"Personal",
            "subcategory":"Beauty Salon",
            "type":"Services"
        }
    ],
    "sg:phone":"+1 520 881 1417",
    "sg:postcode":"85716",
    "sg:province":"AZ",
    "sg:tags":[
        "spa",
        "day"
    ],
    "wof:name":"Mirror Image",
    "wof:placetype":"venue"
},
  "geometry": {"coordinates":[-110.93179000000001,32.221434],"type":"Point"}
}