{
  "type": "Feature",
  "properties": {
    "iso:country":"US",
    "sg:address":"1250 E Baseline Rd",
    "sg:city":"Tempe",
    "sg:classifiers":[
        {
            "category":"Real Estate",
            "subcategory":"Developer",
            "type":"Services"
        }
    ],
    "sg:phone":"+1 602 980 8248",
    "sg:postcode":"85283",
    "sg:province":"AZ",
    "wof:name":"Telesat Canada",
    "wof:placetype":"venue"
},
  "geometry": {"coordinates":[-111.91895,33.378413],"type":"Point"}
}