{
  "type": "Feature",
  "properties": {
    "addr:full":"7708 W Bell Rd Glendale AZ 85308",
    "addr:housenumber":"7708",
    "addr:postcode":"85308",
    "addr:street":"W Bell Rd",
    "iso:country":"US",
    "sg:address":"7708 W Bell Rd",
    "sg:city":"Glendale",
    "sg:classifiers":[
        {
            "category":"Restaurant",
            "type":"Food & Drink"
        }
    ],
    "sg:phone":"+1 623 334 9095",
    "sg:postcode":"85308",
    "sg:province":"AZ",
    "sg:tags":[
        "style",
        "american",
        "family"
    ],
    "sg:website":"http://www.rubytuesday.com",
    "wof:name":"Ruby Tuesday Restaurant",
    "wof:placetype":"venue"
},
  "geometry": {"coordinates":[-112.225724,33.638301],"type":"Point"}
}