{
  "type": "Feature",
  "properties": {
    "addr:full":"2502 E Camelback Rd Phoenix AZ 85016",
    "addr:housenumber":"2502",
    "addr:postcode":"85016",
    "addr:street":"E Camelback Rd",
    "iso:country":"US",
    "sg:address":"2502 E Camelback Rd",
    "sg:city":"Phoenix",
    "sg:classifiers":[
        {
            "category":"Shopping",
            "subcategory":"Clothing, Apparel, & Fashions",
            "type":"Retail Goods"
        }
    ],
    "sg:phone":"+1 602 952 0155",
    "sg:postcode":"85016",
    "sg:province":"AZ",
    "wof:name":"Ralph Lauren",
    "wof:placetype":"venue"
},
  "geometry": {"coordinates":[-112.02813399999999,33.509461],"type":"Point"}
}