{
  "type": "Feature",
  "properties": {
    "iso:country":"US",
    "sg:address":"4544 Hwy 95",
    "sg:city":"Fort Mohave",
    "sg:classifiers":[
        {
            "category":"Utilities",
            "subcategory":"Water",
            "type":"Services"
        }
    ],
    "sg:phone":"+1 928 763 6676",
    "sg:postcode":"86426",
    "sg:province":"AZ",
    "sg:tags":[
        "company",
        "private",
        "sewage"
    ],
    "wof:name":"Bermuda Water Company Inc",
    "wof:placetype":"venue"
},
  "geometry": {"coordinates":[-114.597975,35.02465],"type":"Point"}
}