{
  "type": "Feature",
  "properties": {
    "iso:country":"US",
    "sg:address":"2929 S Hardy Dr",
    "sg:city":"Tempe",
    "sg:classifiers":[
        {
            "category":"Professional",
            "subcategory":"Business Services",
            "type":"Services"
        }
    ],
    "sg:phone":"+1 480 969 2323",
    "sg:postcode":"85282",
    "sg:province":"AZ",
    "sg:tags":[
        "paper"
    ],
    "sg:website":"www.shredrite.com",
    "wof:name":"Secure Document Destruction",
    "wof:placetype":"venue"
},
  "geometry": {"coordinates":[-111.95205,33.399938],"type":"Point"}
}