{
  "type": "Feature",
  "properties": {
    "addr:full":"7055 E Shea Blvd Scottsdale AZ 85254",
    "addr:housenumber":"7055",
    "addr:postcode":"85254",
    "addr:street":"E Shea Blvd",
    "iso:country":"US",
    "sg:address":"7055 E Shea Blvd",
    "sg:city":"Scottsdale",
    "sg:classifiers":[
        {
            "category":"Restaurant",
            "type":"Food & Drink"
        }
    ],
    "sg:menulink":"http://www.allmenus.com/az/phoenix/198812-kfc---kentucky-fried-chicken/menu/",
    "sg:phone":"+1 480 596 0937",
    "sg:postcode":"85254",
    "sg:province":"AZ",
    "sg:tags":[
        "american",
        "chicken"
    ],
    "wof:name":"KFC - Kentucky Fried Chicken",
    "wof:placetype":"venue"
},
  "geometry": {"coordinates":[-111.92890300000001,33.582072],"type":"Point"}
}