{
  "type": "Feature",
  "properties": {
    "addr:full":"3840 N Cactus Blvd Tucson AZ 85716",
    "addr:housenumber":"3840",
    "addr:postcode":"85716",
    "addr:street":"N Cactus Blvd",
    "iso:country":"US",
    "sg:address":"3840 N Cactus Blvd",
    "sg:city":"Tucson",
    "sg:classifiers":[
        {
            "category":"Building & Trades",
            "subcategory":"Construction",
            "type":"Services"
        }
    ],
    "sg:phone":"+1 520 795 1623",
    "sg:postcode":"85716",
    "sg:province":"AZ",
    "sg:tags":[
        "house"
    ],
    "wof:name":"R F Held",
    "wof:placetype":"venue"
},
  "geometry": {"coordinates":[-110.930993,32.278515],"type":"Point"}
}