{
  "type": "Feature",
  "properties": {
    "iso:country":"US",
    "sg:address":"6963 E Main St",
    "sg:city":"Mesa",
    "sg:classifiers":[
        {
            "category":"Health Services",
            "subcategory":"Doctor",
            "type":"Services"
        }
    ],
    "sg:phone":"+1 480 981 3047",
    "sg:postcode":"85207",
    "sg:province":"AZ",
    "sg:tags":[
        "dentist"
    ],
    "sg:website":"www.dentalcare.home.att.net",
    "wof:name":"Dental Care",
    "wof:placetype":"venue"
},
  "geometry": {"coordinates":[-111.68251100000001,33.415565],"type":"Point"}
}