{
  "type": "Feature",
  "properties": {
    "iso:country":"US",
    "sg:address":"420 N San Francisco St",
    "sg:city":"Flagstaff",
    "sg:classifiers":[
        {
            "category":"Health Services",
            "subcategory":"Hospital",
            "type":"Services"
        }
    ],
    "sg:phone":"+1 928 779 5840",
    "sg:postcode":"86001",
    "sg:province":"AZ",
    "sg:tags":[
        "mental"
    ],
    "wof:name":"Guidance Center",
    "wof:placetype":"venue"
},
  "geometry": {"coordinates":[-111.645898,35.201605],"type":"Point"}
}