{
  "type": "Feature",
  "properties": {
    "iso:country":"US",
    "sg:address":"2615 N Peter Seward Dr",
    "sg:city":"Tucson",
    "sg:classifiers":[
        {
            "category":"Building & Trades",
            "subcategory":"Construction",
            "type":"Services"
        }
    ],
    "sg:phone":"+1 520 743 4943",
    "sg:postcode":"85745",
    "sg:province":"AZ",
    "sg:tags":[
        "company"
    ],
    "wof:name":"Corner House Construction Inc",
    "wof:placetype":"venue"
},
  "geometry": {"coordinates":[-111.038965,32.252679],"type":"Point"}
}