{
  "type": "Feature",
  "properties": {
    "iso:country":"US",
    "sg:address":"1600 A Ave",
    "sg:city":"Douglas",
    "sg:classifiers":[
        {
            "category":"Autos & Motor Vehicles",
            "subcategory":"Auto Supplies",
            "type":"Retail Goods"
        }
    ],
    "sg:phone":"+1 520 364 5583",
    "sg:postcode":"85607",
    "sg:province":"AZ",
    "sg:tags":[
        "gas",
        "tire"
    ],
    "wof:name":"Lone Star Service",
    "wof:placetype":"venue"
},
  "geometry": {"coordinates":[-109.545433,31.35058],"type":"Point"}
}