{
  "type": "Feature",
  "properties": {
    "iso:country":"US",
    "sg:address":"6246 N 27th Ave",
    "sg:city":"Phoenix",
    "sg:classifiers":[
        {
            "category":"Professional",
            "subcategory":"Business Services",
            "type":"Services"
        }
    ],
    "sg:phone":"+1 602 246 2174",
    "sg:postcode":"85017",
    "sg:province":"AZ",
    "sg:tags":[
        "mobile",
        "commercial",
        "unit"
    ],
    "wof:name":"Desert Modulars",
    "wof:placetype":"venue"
},
  "geometry": {"coordinates":[-112.116913,33.528898],"type":"Point"}
}