{
  "type": "Feature",
  "properties": {
    "iso:country":"US",
    "sg:address":"245 S Nina Dr",
    "sg:city":"Mesa",
    "sg:classifiers":[
        {
            "category":"Professional",
            "subcategory":"Engineering",
            "type":"Services"
        }
    ],
    "sg:phone":"+1 480 969 2021",
    "sg:postcode":"85210",
    "sg:province":"AZ",
    "sg:tags":[
        "aeronautical",
        "engineer"
    ],
    "wof:name":"Thorp See Op",
    "wof:placetype":"venue"
},
  "geometry": {"coordinates":[-111.850808,33.409609],"type":"Point"}
}