{
  "type": "Feature",
  "properties": {
    "iso:country":"US",
    "sg:address":"475 Finnie Flat Rd",
    "sg:city":"Camp Verde",
    "sg:classifiers":[
        {
            "category":"Food & Beverages",
            "subcategory":"Groceries & Convenience Stores",
            "type":"Retail Goods"
        }
    ],
    "sg:phone":"+1 928 567 7697",
    "sg:postcode":"86322",
    "sg:province":"AZ",
    "sg:tags":[
        "grocer"
    ],
    "wof:name":"Blue Hills Market",
    "wof:placetype":"venue"
},
  "geometry": {"coordinates":[-111.86251900000001,34.565643],"type":"Point"}
}