{
  "type": "Feature",
  "properties": {
    "iso:country":"US",
    "sg:address":"6593 N Pinon Rd",
    "sg:city":"Flagstaff",
    "sg:classifiers":[
        {
            "category":"Building & Trades",
            "subcategory":"Plumbing",
            "type":"Services"
        }
    ],
    "sg:phone":"+1 928 526 0295",
    "sg:postcode":"86004",
    "sg:province":"AZ",
    "sg:tags":[
        "plumbing",
        "contractor"
    ],
    "wof:name":"BWE Plumbing",
    "wof:placetype":"venue"
},
  "geometry": {"coordinates":[-111.489036,35.232433],"type":"Point"}
}