{
  "type": "Feature",
  "properties": {
    "iso:country":"US",
    "sg:address":"202 W Genematas Dr",
    "sg:city":"Tucson",
    "sg:classifiers":[
        {
            "category":"Professional",
            "type":"Services"
        }
    ],
    "sg:phone":"+1 520 408 1822",
    "sg:postcode":"85704",
    "sg:province":"AZ",
    "wof:name":"Craig Snow Inc",
    "wof:placetype":"venue"
},
  "geometry": {"coordinates":[-110.978299,32.300402],"type":"Point"}
}