{
  "type": "Feature",
  "properties": {
    "iso:country":"US",
    "sg:address":"1212 E 11th St",
    "sg:city":"Casa Grande",
    "sg:classifiers":[
        {
            "category":"Autos & Motor Vehicles",
            "subcategory":"Auto Supplies",
            "type":"Retail Goods"
        }
    ],
    "sg:phone":"+1 520 836 4816",
    "sg:postcode":"85222",
    "sg:province":"AZ",
    "wof:name":"Arizona Mustang Man",
    "wof:placetype":"venue"
},
  "geometry": {"coordinates":[-111.73563,32.885387],"type":"Point"}
}