{
  "type": "Feature",
  "properties": {
    "addr:full":"16628 N 53rd Pl Scottsdale AZ 85254",
    "addr:housenumber":"16628",
    "addr:postcode":"85254",
    "addr:street":"N 53Rd Pl",
    "iso:country":"US",
    "sg:address":"16628 N 53rd Pl",
    "sg:city":"Scottsdale",
    "sg:classifiers":[
        {
            "category":"Shopping",
            "type":"Retail Goods"
        }
    ],
    "sg:phone":"+1 602 482 2874",
    "sg:postcode":"85254",
    "sg:province":"AZ",
    "sg:tags":[
        "merchandise"
    ],
    "wof:name":"Sundance Med & Mobility Eqp",
    "wof:placetype":"venue"
},
  "geometry": {"coordinates":[-111.965929,33.637905],"type":"Point"}
}