{
  "type": "Feature",
  "properties": {
    "iso:country":"US",
    "sg:address":"439 N 6th Ave",
    "sg:city":"Tucson",
    "sg:classifiers":[
        {
            "category":"Professional",
            "type":"Services"
        }
    ],
    "sg:phone":"+1 520 882 3886",
    "sg:postcode":"85705",
    "sg:province":"AZ",
    "sg:tags":[
        "establishment"
    ],
    "wof:name":"Platform",
    "wof:placetype":"venue"
},
  "geometry": {"coordinates":[-110.968729,32.227204],"type":"Point"}
}