{
  "type": "Feature",
  "properties": {
    "iso:country":"US",
    "sg:address":"4902 E Shea Blvd",
    "sg:city":"Scottsdale",
    "sg:classifiers":[
        {
            "category":"Cinema",
            "subcategory":"Movie Rental",
            "type":"Entertainment"
        }
    ],
    "sg:phone":"+1 480 905 9811",
    "sg:postcode":"85254",
    "sg:province":"AZ",
    "sg:tags":[
        "leasing",
        "video",
        "disc",
        "tape"
    ],
    "sg:website":"www.blockbuster.com",
    "wof:name":"Blockbuster Video",
    "wof:placetype":"venue"
},
  "geometry": {"coordinates":[-111.976418,33.582777],"type":"Point"}
}