{
  "type": "Feature",
  "properties": {
    "iso:country":"US",
    "sg:address":"5345 W Port au Prince Ln",
    "sg:city":"Glendale",
    "sg:classifiers":[
        {
            "category":"Health Services",
            "subcategory":"Nursing And Care Facility",
            "type":"Services"
        }
    ],
    "sg:phone":"+1 602 843 6817",
    "sg:postcode":"85306",
    "sg:province":"AZ",
    "sg:tags":[
        "home",
        "convalescent"
    ],
    "wof:name":"Barrington Suites Inc",
    "wof:placetype":"venue"
},
  "geometry": {"coordinates":[-112.176402,33.622405],"type":"Point"}
}