{
  "type": "Feature",
  "properties": {
    "iso:country":"US",
    "sg:address":"7952 E Portobello Ave",
    "sg:city":"Mesa",
    "sg:classifiers":[
        {
            "category":"Autos & Motor Vehicles",
            "subcategory":"Automobile Sales",
            "type":"Retail Goods"
        },
        {
            "category":"Professional",
            "subcategory":"Business Services",
            "type":"Services"
        }
    ],
    "sg:phone":"+1 602 743 9920",
    "sg:postcode":"85212",
    "sg:province":"AZ",
    "sg:tags":[
        "locator",
        "repossessing"
    ],
    "wof:name":"Az Auto Rescue",
    "wof:placetype":"venue"
},
  "geometry": {"coordinates":[-111.66261,33.360759],"type":"Point"}
}