{
  "type": "Feature",
  "properties": {
    "addr:full":"268 State Hwy 260 Payson AZ 85541",
    "addr:housenumber":"268",
    "addr:postcode":"85541",
    "addr:street":"State Hwy 260",
    "iso:country":"US",
    "sg:address":"268 State Hwy 260",
    "sg:city":"Payson",
    "sg:classifiers":[
        {
            "category":"Travel",
            "subcategory":"Hotels & Motels",
            "type":"Entertainment"
        }
    ],
    "sg:phone":"+1 928 478 4211",
    "sg:postcode":"85541",
    "sg:province":"AZ",
    "sg:website":"www.kohlsvacation.com",
    "wof:name":"Kohl's Ranch Lodge",
    "wof:placetype":"venue"
},
  "geometry": {"coordinates":[-111.323018,34.242349],"type":"Point"}
}