{
  "type": "Feature",
  "properties": {
    "iso:country":"US",
    "sg:address":"10064 Rio Vista Rd",
    "sg:city":"Parker",
    "sg:classifiers":[
        {
            "category":"Home & Garden",
            "subcategory":"Carpets & Floor Coverings",
            "type":"Retail Goods"
        }
    ],
    "sg:phone":"+1 928 667 0034",
    "sg:postcode":"85344",
    "sg:province":"AZ",
    "wof:name":"Stroup Lonny F-C",
    "wof:placetype":"venue"
},
  "geometry": {"coordinates":[-114.224834,34.186328],"type":"Point"}
}