{
  "type": "Feature",
  "properties": {
    "iso:country":"US",
    "sg:address":"1403 W Glenmere Dr",
    "sg:city":"Chandler",
    "sg:classifiers":[
        {
            "category":"Home & Garden",
            "subcategory":"Building Materials",
            "type":"Retail Goods"
        }
    ],
    "sg:phone":"+1 480 659 2200",
    "sg:postcode":"85224",
    "sg:province":"AZ",
    "wof:name":"Anasazi Architectural Products",
    "wof:placetype":"venue"
},
  "geometry": {"coordinates":[-111.866218,33.295684],"type":"Point"}
}