{
  "type": "Feature",
  "properties": {
    "addr:full":"102 W Cypress St Phoenix AZ 85003",
    "addr:housenumber":"102",
    "addr:postcode":"85003",
    "addr:street":"W Cypress St",
    "iso:country":"US",
    "sg:address":"102 W Cypress St",
    "sg:city":"Phoenix",
    "sg:classifiers":[
        {
            "category":"Airline",
            "type":"Transportation"
        }
    ],
    "sg:phone":"+1 602 271 0202",
    "sg:postcode":"85003",
    "sg:province":"AZ",
    "sg:tags":[
        "nonscheduled",
        "air"
    ],
    "wof:name":"Jmt Designs Inc",
    "wof:placetype":"venue"
},
  "geometry": {"coordinates":[-112.076082,33.47187],"type":"Point"}
}