{
  "type": "Feature",
  "properties": {
    "addr:full":"1955 W Guadalupe Rd Mesa AZ 85202",
    "addr:housenumber":"1955",
    "addr:postcode":"85202",
    "addr:street":"W Guadalupe Rd",
    "iso:country":"US",
    "sg:address":"1955 W Guadalupe Rd",
    "sg:city":"Mesa",
    "sg:classifiers":[
        {
            "category":"Personal",
            "subcategory":"Beauty Salon",
            "type":"Services"
        }
    ],
    "sg:phone":"+1 480 730 1975",
    "sg:postcode":"85202",
    "sg:province":"AZ",
    "sg:website":"www.greatclips.com",
    "wof:name":"Great Clips",
    "wof:placetype":"venue"
},
  "geometry": {"coordinates":[-111.873868,33.364018],"type":"Point"}
}