{
  "type": "Feature",
  "properties": {
    "iso:country":"US",
    "sg:address":"16 US Hwy 66",
    "sg:city":"Flagstaff",
    "sg:classifiers":[
        {
            "category":"Real Estate",
            "subcategory":"Architect",
            "type":"Services"
        }
    ],
    "sg:phone":"+1 928 774 3444",
    "sg:postcode":"86001",
    "sg:province":"AZ",
    "wof:name":"Paul D Bustamante",
    "wof:placetype":"venue"
},
  "geometry": {"coordinates":[-111.652794,35.198541],"type":"Point"}
}