{
  "type": "Feature",
  "properties": {
    "iso:country":"US",
    "sg:address":"11 Howell Ave",
    "sg:city":"Bisbee",
    "sg:classifiers":[
        {
            "category":"Travel",
            "subcategory":"Hotels & Motels",
            "type":"Entertainment"
        }
    ],
    "sg:phone":"+1 520 432 2216",
    "sg:postcode":"85603",
    "sg:province":"AZ",
    "sg:tags":[
        "bar"
    ],
    "wof:name":"Copper Queen Hotel",
    "wof:placetype":"venue"
},
  "geometry": {"coordinates":[-109.914195,31.442276],"type":"Point"}
}