{
  "type": "Feature",
  "properties": {
    "addr:full":"7426 W Comet Ave Peoria AZ 85345",
    "addr:housenumber":"7426",
    "addr:postcode":"85345",
    "addr:street":"W Comet Ave",
    "iso:country":"US",
    "sg:address":"7426 W Comet Ave",
    "sg:city":"Peoria",
    "sg:classifiers":[
        {
            "category":"Building & Trades",
            "subcategory":"Construction",
            "type":"Services"
        }
    ],
    "sg:phone":"+1 623 521 2623",
    "sg:postcode":"85345",
    "sg:province":"AZ",
    "sg:tags":[
        "house"
    ],
    "wof:name":"Keller & Sons Enterprises",
    "wof:placetype":"venue"
},
  "geometry": {"coordinates":[-112.219133,33.579263],"type":"Point"}
}