{
  "type": "Feature",
  "properties": {
    "iso:country":"US",
    "sg:address":"16 E Route 66 Ste 204",
    "sg:city":"Flagstaff",
    "sg:classifiers":[
        {
            "category":"Professional",
            "subcategory":"Engineering",
            "type":"Services"
        }
    ],
    "sg:phone":"+1 928 774 1032",
    "sg:postcode":"86001",
    "sg:province":"AZ",
    "sg:tags":[
        "engineer",
        "structural"
    ],
    "wof:name":"Mancini William Structural Eng",
    "wof:placetype":"venue"
},
  "geometry": {"coordinates":[-111.648973,35.197431],"type":"Point"}
}