{
  "type": "Feature",
  "properties": {
    "addr:full":"1851 W Bell Rd Phoenix AZ 85023",
    "addr:housenumber":"1851",
    "addr:postcode":"85023",
    "addr:street":"W Bell Rd",
    "iso:country":"US",
    "sg:address":"1851 W Bell Rd",
    "sg:city":"Phoenix",
    "sg:classifiers":[
        {
            "category":"Restaurant",
            "type":"Food & Drink"
        }
    ],
    "sg:phone":"+1 602 866 8525",
    "sg:postcode":"85023",
    "sg:province":"AZ",
    "wof:name":"Mc Donald's",
    "wof:placetype":"venue"
},
  "geometry": {"coordinates":[-112.097014,33.640078],"type":"Point"}
}