{
  "type": "Feature",
  "properties": {
    "iso:country":"US",
    "sg:address":"1251 W Marina Dr",
    "sg:city":"Chandler",
    "sg:classifiers":[
        {
            "category":"Professional",
            "subcategory":"Business Services",
            "type":"Services"
        }
    ],
    "sg:phone":"+1 480 786 0762",
    "sg:postcode":"85248",
    "sg:province":"AZ",
    "sg:tags":[
        "interior",
        "consultant",
        "design",
        "decorator"
    ],
    "wof:name":"Jem Interior Design",
    "wof:placetype":"venue"
},
  "geometry": {"coordinates":[-111.863179,33.255433],"type":"Point"}
}