{
  "type": "Feature",
  "properties": {
    "iso:country":"US",
    "sg:address":"17403 N 66th Ave",
    "sg:city":"Glendale",
    "sg:classifiers":[
        {
            "category":"Food & Beverages",
            "subcategory":"Groceries & Convenience Stores",
            "type":"Retail Goods"
        }
    ],
    "sg:phone":"+1 623 486 1051",
    "sg:postcode":"85308",
    "sg:province":"AZ",
    "wof:name":"Randalls Doall",
    "wof:placetype":"venue"
},
  "geometry": {"coordinates":[-112.199815,33.644066],"type":"Point"}
}