{
  "type": "Feature",
  "properties": {
    "iso:country":"US",
    "sg:address":"10637 N Tatum Blvd",
    "sg:city":"Phoenix",
    "sg:classifiers":[
        {
            "category":"Restaurant",
            "type":"Food & Drink"
        }
    ],
    "sg:menulink":"http://www.allmenus.com/az/phoenix/4311-dustys-bbq/menu/",
    "sg:phone":"+1 602 991 8888",
    "sg:postcode":"85028",
    "sg:province":"AZ",
    "sg:tags":[
        "american",
        "southern"
    ],
    "wof:name":"Dusty's BBQ",
    "wof:placetype":"venue"
},
  "geometry": {"coordinates":[-111.97779300000001,33.583084],"type":"Point"}
}