{
  "type": "Feature",
  "properties": {
    "iso:country":"US",
    "sg:address":"2150 E Silvosa St",
    "sg:city":"Tucson",
    "sg:classifiers":[
        {
            "category":"Social Services",
            "subcategory":"Child Care",
            "type":"Services"
        }
    ],
    "sg:phone":"+1 520 624 2273",
    "sg:postcode":"85713",
    "sg:province":"AZ",
    "wof:name":"Tucson Nursery Schools",
    "wof:placetype":"venue"
},
  "geometry": {"coordinates":[-110.940269,32.194882],"type":"Point"}
}