{
  "type": "Feature",
  "properties": {
    "addr:full":"1843 W Union Hills Dr Phoenix AZ 85027",
    "addr:housenumber":"1843",
    "addr:postcode":"85027",
    "addr:street":"W Union Hills Dr",
    "iso:country":"US",
    "sg:address":"1843 W Union Hills Dr",
    "sg:city":"Phoenix",
    "sg:classifiers":[
        {
            "category":"Restaurant",
            "type":"Food & Drink"
        }
    ],
    "sg:menulink":"http://www.allmenus.com/az/phoenix/198776-kfc---kentucky-fried-chicken/menu/",
    "sg:phone":"+1 602 942 0572",
    "sg:postcode":"85027",
    "sg:province":"AZ",
    "sg:tags":[
        "american",
        "chicken"
    ],
    "wof:name":"KFC - Kentucky Fried Chicken",
    "wof:placetype":"venue"
},
  "geometry": {"coordinates":[-112.09921900000001,33.654326],"type":"Point"}
}