{
  "type": "Feature",
  "properties": {
    "iso:country":"US",
    "sg:address":"3402 S McClintock Dr",
    "sg:city":"Tempe",
    "sg:classifiers":[
        {
            "category":"Retail",
            "subcategory":"Veterinary Services",
            "type":"Services"
        }
    ],
    "sg:phone":"+1 480 820 2822",
    "sg:postcode":"85282",
    "sg:province":"AZ",
    "sg:tags":[
        "veterinarian"
    ],
    "wof:name":"McSouthern Animal Clinic PC",
    "wof:placetype":"venue"
},
  "geometry": {"coordinates":[-111.908997,33.3922],"type":"Point"}
}