{
  "type": "Feature",
  "properties": {
    "iso:country":"US",
    "sg:address":"5340 E Dynamite Blvd",
    "sg:city":"Cave Creek",
    "sg:classifiers":[
        {
            "category":"Farming",
            "subcategory":"Livestock Farm",
            "type":"Manufacturing & Wholesale Goods"
        },
        {
            "category":"Recreation",
            "type":"Entertainment"
        }
    ],
    "sg:phone":"+1 480 515 2191",
    "sg:postcode":"85331",
    "sg:province":"AZ",
    "sg:tags":[
        "equine",
        "stable"
    ],
    "wof:name":"Blue Grass Arabians",
    "wof:placetype":"venue"
},
  "geometry": {"coordinates":[-111.965879,33.741191],"type":"Point"}
}