{
  "type": "Feature",
  "properties": {
    "addr:full":"1523 E Apache Blvd Tempe AZ 85281",
    "addr:housenumber":"1523",
    "addr:postcode":"85281",
    "addr:street":"E Apache Blvd",
    "iso:country":"US",
    "sg:address":"1523 E Apache Blvd",
    "sg:city":"Tempe",
    "sg:classifiers":[
        {
            "category":"Restaurant",
            "type":"Food & Drink"
        }
    ],
    "sg:phone":"+1 480 966 5555",
    "sg:postcode":"85281",
    "sg:province":"AZ",
    "sg:tags":[
        "eating"
    ],
    "wof:name":"Cosmic Pizzeria",
    "wof:placetype":"venue"
},
  "geometry": {"coordinates":[-111.912786,33.414694],"type":"Point"}
}