{
  "type": "Feature",
  "properties": {
    "addr:full":"3417 W Indian School Rd Phoenix AZ 85017",
    "addr:housenumber":"3417",
    "addr:postcode":"85017",
    "addr:street":"W Indian School Rd",
    "iso:country":"US",
    "sg:address":"3417 W Indian School Rd",
    "sg:city":"Phoenix",
    "sg:classifiers":[
        {
            "category":"Professional",
            "subcategory":"Business Services",
            "type":"Services"
        }
    ],
    "sg:phone":"+1 602 678 0442",
    "sg:postcode":"85017",
    "sg:province":"AZ",
    "sg:tags":[
        "auctioneer"
    ],
    "wof:name":"Action Auction & Apprasials",
    "wof:placetype":"venue"
},
  "geometry": {"coordinates":[-112.133109,33.494805],"type":"Point"}
}