{
  "type": "Feature",
  "properties": {
    "iso:country":"US",
    "sg:address":"5090 E Gleneagles Dr",
    "sg:city":"Tucson",
    "sg:classifiers":[
        {
            "category":"Banks & Credit Unions",
            "subcategory":"Financial Services",
            "type":"Services"
        }
    ],
    "sg:phone":"+1 520 577 9154",
    "sg:postcode":"85718",
    "sg:province":"AZ",
    "sg:tags":[
        "trust",
        "management"
    ],
    "wof:name":"Pepper Family Trust No 1",
    "wof:placetype":"venue"
},
  "geometry": {"coordinates":[-110.875628,32.331773],"type":"Point"}
}