{
  "type": "Feature",
  "properties": {
    "iso:country":"US",
    "sg:address":"7711 N 51st Ave",
    "sg:city":"Glendale",
    "sg:classifiers":[
        {
            "category":"Real Estate",
            "subcategory":"Real Estate Operator",
            "type":"Services"
        }
    ],
    "sg:phone":"+1 623 939 1775",
    "sg:postcode":"85301",
    "sg:province":"AZ",
    "sg:tags":[
        "building",
        "apartment"
    ],
    "wof:name":"Stillwater Apartments",
    "wof:placetype":"venue"
},
  "geometry": {"coordinates":[-112.168731,33.549776],"type":"Point"}
}