{
  "type": "Feature",
  "properties": {
    "iso:country":"US",
    "sg:address":"8513 E Roma Ave",
    "sg:city":"Scottsdale",
    "sg:classifiers":[
        {
            "category":"Building & Trades",
            "subcategory":"Plumbing",
            "type":"Services"
        }
    ],
    "sg:phone":"+1 480 423 5665",
    "sg:postcode":"85251",
    "sg:province":"AZ",
    "sg:tags":[
        "contractor"
    ],
    "wof:name":"Kurts Air Conditioning and He",
    "wof:placetype":"venue"
},
  "geometry": {"coordinates":[-111.895771,33.500249],"type":"Point"}
}