{
  "type": "Feature",
  "properties": {
    "iso:country":"US",
    "sg:address":"1708 E Gable Ave",
    "sg:city":"Mesa",
    "sg:classifiers":[
        {
            "category":"Home & Garden",
            "subcategory":"Home Furnishings",
            "type":"Retail Goods"
        }
    ],
    "sg:phone":"+1 480 507 3333",
    "sg:postcode":"85204",
    "sg:province":"AZ",
    "sg:tags":[
        "window",
        "covering"
    ],
    "wof:name":"All About Blinds & Shutters",
    "wof:placetype":"venue"
},
  "geometry": {"coordinates":[-111.793115,33.39256],"type":"Point"}
}