{
  "type": "Feature",
  "properties": {
    "iso:country":"US",
    "sg:address":"8552 W Purdue Ave",
    "sg:city":"Peoria",
    "sg:classifiers":[
        {
            "category":"Utilities",
            "subcategory":"Recycling",
            "type":"Services"
        }
    ],
    "sg:phone":"+1 623 326 2800",
    "sg:postcode":"85345",
    "sg:province":"AZ",
    "sg:website":"http://www.slmwaste.com",
    "wof:name":"Slm Waste & Recycling Services Inc.",
    "wof:placetype":"venue"
},
  "geometry": {"coordinates":[-112.245409,33.573156],"type":"Point"}
}