{
  "type": "Feature",
  "properties": {
    "iso:country":"US",
    "sg:address":"5633 E Grant Rd",
    "sg:city":"Tucson",
    "sg:classifiers":[
        {
            "category":"Real Estate",
            "subcategory":"Developer",
            "type":"Services"
        }
    ],
    "sg:phone":"+1 520 721 1102",
    "sg:postcode":"85712",
    "sg:province":"AZ",
    "wof:name":"Shenitzer Development Co",
    "wof:placetype":"venue"
},
  "geometry": {"coordinates":[-110.871196,32.250742],"type":"Point"}
}