{
  "type": "Feature",
  "properties": {
    "addr:full":"2205 W Grant St Phoenix AZ 85009",
    "addr:housenumber":"2205",
    "addr:postcode":"85009",
    "addr:street":"W Grant St",
    "iso:country":"US",
    "sg:address":"2205 W Grant St",
    "sg:city":"Phoenix",
    "sg:classifiers":[
        {
            "category":"Retail",
            "subcategory":"Auto Repair",
            "type":"Services"
        }
    ],
    "sg:phone":"+1 602 442 1110",
    "sg:postcode":"85009",
    "sg:province":"AZ",
    "sg:tags":[
        "repairing",
        "automobile"
    ],
    "wof:name":"Southwest Waterworks Contrs",
    "wof:placetype":"venue"
},
  "geometry": {"coordinates":[-112.10766599999999,33.441239],"type":"Point"}
}