{
  "type": "Feature",
  "properties": {
    "iso:country":"US",
    "sg:address":"3825 W Ray Rd",
    "sg:city":"Chandler",
    "sg:classifiers":[
        {
            "category":"Shopping",
            "subcategory":"Bicycles & Sporting Goods",
            "type":"Retail Goods"
        },
        {
            "category":"Sports & Exercise",
            "subcategory":"Bowling",
            "type":"Entertainment"
        }
    ],
    "sg:phone":"+1 480 963 1006",
    "sg:postcode":"85226",
    "sg:province":"AZ",
    "wof:name":"Bowling With Leverage Pro Shop",
    "wof:placetype":"venue"
},
  "geometry": {"coordinates":[-111.907319,33.320022],"type":"Point"}
}