{
  "type": "Feature",
  "properties": {
    "addr:full":"8641 S 51st St Phoenix AZ 85044",
    "addr:housenumber":"8641",
    "addr:postcode":"85044",
    "addr:street":"S 51St St",
    "iso:country":"US",
    "sg:address":"8641 S 51st St",
    "sg:city":"Phoenix",
    "sg:classifiers":[
        {
            "category":"Shopping",
            "subcategory":"Computers & Home Electronics",
            "type":"Retail Goods"
        }
    ],
    "sg:phone":"+1 602 426 0755",
    "sg:postcode":"85044",
    "sg:province":"AZ",
    "sg:tags":[
        "equipment",
        "satellite",
        "system"
    ],
    "wof:name":"Dish Satellite Guys",
    "wof:placetype":"venue"
},
  "geometry": {"coordinates":[-111.972286,33.367997],"type":"Point"}
}