{
  "type": "Feature",
  "properties": {
    "iso:country":"US",
    "sg:address":"2438 E Earll Dr",
    "sg:city":"Phoenix",
    "sg:classifiers":[
        {
            "category":"Organizations",
            "subcategory":"Religious Organization",
            "type":"Services"
        }
    ],
    "sg:phone":"+1 602 956 5440",
    "sg:postcode":"85016",
    "sg:province":"AZ",
    "sg:tags":[
        "church"
    ],
    "wof:name":"Phoenix Christian Reform Chr",
    "wof:placetype":"venue"
},
  "geometry": {"coordinates":[-112.028721,33.484043],"type":"Point"}
}