{
  "type": "Feature",
  "properties": {
    "iso:country":"US",
    "sg:address":"1759 E Villa Dr",
    "sg:city":"Cottonwood",
    "sg:classifiers":[
        {
            "category":"Building & Trades",
            "subcategory":"Construction",
            "type":"Services"
        }
    ],
    "sg:phone":"+1 928 649 2055",
    "sg:postcode":"86326",
    "sg:province":"AZ",
    "sg:tags":[
        "general",
        "contractor"
    ],
    "wof:name":"Wellborn & Sons Constr Inc",
    "wof:placetype":"venue"
},
  "geometry": {"coordinates":[-112.006187,34.726065],"type":"Point"}
}