{
  "type": "Feature",
  "properties": {
    "addr:full":"1659 W White Mountain Blvd Lakeside AZ 85929",
    "addr:housenumber":"1659",
    "addr:postcode":"85929",
    "addr:street":"W White Mountain Blvd",
    "iso:country":"US",
    "sg:address":"1659 W White Mountain Blvd",
    "sg:city":"Lakeside",
    "sg:classifiers":[
        {
            "category":"Home & Garden",
            "subcategory":"Hardware",
            "type":"Retail Goods"
        }
    ],
    "sg:phone":"+1 928 368 5212",
    "sg:postcode":"85929",
    "sg:province":"AZ",
    "sg:tags":[
        "equipment",
        "janitor",
        "supply"
    ],
    "wof:name":"E & E Services Janitorial",
    "wof:placetype":"venue"
},
  "geometry": {"coordinates":[-109.97323900000001,34.152136],"type":"Point"}
}