{
  "type": "Feature",
  "properties": {
    "iso:country":"US",
    "sg:address":"19705 W Lower Buckeye Rd",
    "sg:city":"Buckeye",
    "sg:phone":"+1 623 386 2143",
    "sg:postcode":"85326",
    "sg:province":"AZ",
    "sg:tags":[
        "farm",
        "field",
        "crop"
    ],
    "wof:name":"Gladden Farms",
    "wof:placetype":"venue"
},
  "geometry": {"coordinates":[-112.485947,33.421057],"type":"Point"}
}