{
  "type": "Feature",
  "properties": {
    "addr:full":"826 N 5th Ave Phoenix AZ 85003",
    "addr:housenumber":"826",
    "addr:postcode":"85003",
    "addr:street":"N 5Th Ave",
    "iso:country":"US",
    "sg:address":"826 N 5th Ave",
    "sg:city":"Phoenix",
    "sg:classifiers":[
        {
            "category":"Insurance",
            "subcategory":"Insurance Agent",
            "type":"Services"
        }
    ],
    "sg:phone":"+1 602 439 7000",
    "sg:postcode":"85003",
    "sg:province":"AZ",
    "wof:name":"Nichole M Schaffer",
    "wof:placetype":"venue"
},
  "geometry": {"coordinates":[-112.08023799999999,33.458167],"type":"Point"}
}