{
  "type": "Feature",
  "properties": {
    "addr:full":"3620 London Bridge Rd Lake Havasu City AZ 86404",
    "addr:housenumber":"3620",
    "addr:postcode":"86404",
    "addr:street":"London Bridge Rd",
    "iso:country":"US",
    "sg:address":"3620 London Bridge Rd",
    "sg:city":"Lake Havasu City",
    "sg:classifiers":[
        {
            "category":"Restaurant",
            "type":"Food & Drink"
        }
    ],
    "sg:phone":"+1 928 764 3100",
    "sg:postcode":"86404",
    "sg:province":"AZ",
    "wof:name":"Santiago's Mexican Restaurant",
    "wof:placetype":"venue"
},
  "geometry": {"coordinates":[-114.36636,34.540761],"type":"Point"}
}