{
  "type": "Feature",
  "properties": {
    "iso:country":"US",
    "sg:address":"3420 E Baseline Rd",
    "sg:city":"Mesa",
    "sg:classifiers":[
        {
            "category":"Coffee & Tea",
            "type":"Food & Drink"
        }
    ],
    "sg:phone":"+1 480 633 3840",
    "sg:postcode":"85204",
    "sg:province":"AZ",
    "sg:website":"www.coffeebean.com",
    "wof:name":"The Coffee Bean & Tea Leaf",
    "wof:placetype":"venue"
},
  "geometry": {"coordinates":[-111.758003,33.379299],"type":"Point"}
}