{
  "type": "Feature",
  "properties": {
    "iso:country":"US",
    "sg:address":"5060 N 19th Ave",
    "sg:city":"Phoenix",
    "sg:classifiers":[
        {
            "category":"Education",
            "subcategory":"Special Training",
            "type":"Public Place"
        }
    ],
    "sg:phone":"+1 602 776 0650",
    "sg:postcode":"85015",
    "sg:province":"AZ",
    "sg:tags":[
        "reading",
        "instruction",
        "improvement"
    ],
    "wof:name":"Literacy Volunteers-Maricopa",
    "wof:placetype":"venue"
},
  "geometry": {"coordinates":[-112.099912,33.512371],"type":"Point"}
}