{
  "type": "Feature",
  "properties": {
    "iso:country":"US",
    "sg:address":"2703 N Pennington Dr",
    "sg:city":"Chandler",
    "sg:classifiers":[
        {
            "category":"Building & Trades",
            "subcategory":"Construction",
            "type":"Services"
        }
    ],
    "sg:phone":"+1 480 899 8038",
    "sg:postcode":"85224",
    "sg:province":"AZ",
    "sg:tags":[
        "concrete",
        "contractor"
    ],
    "wof:name":"Taurman Enterprises Inc",
    "wof:placetype":"venue"
},
  "geometry": {"coordinates":[-111.870831,33.345384],"type":"Point"}
}