{
  "type": "Feature",
  "properties": {
    "iso:country":"US",
    "sg:address":"5116 N Desert Ln",
    "sg:city":"Prescott Valley",
    "sg:classifiers":[
        {
            "category":"Shopping",
            "type":"Retail Goods"
        }
    ],
    "sg:phone":"+1 928 775 0480",
    "sg:postcode":"86314",
    "sg:province":"AZ",
    "sg:tags":[
        "radiator"
    ],
    "wof:name":"Hawkes Discount Radiator",
    "wof:placetype":"venue"
},
  "geometry": {"coordinates":[-112.316913,34.619115],"type":"Point"}
}