{
  "type": "Feature",
  "properties": {
    "iso:country":"US",
    "sg:address":"7701 N 17th Ave",
    "sg:city":"Phoenix",
    "sg:classifiers":[
        {
            "category":"Building & Trades",
            "subcategory":"Construction",
            "type":"Services"
        }
    ],
    "sg:phone":"+1 602 943 2154",
    "sg:postcode":"85021",
    "sg:province":"AZ",
    "sg:tags":[
        "house"
    ],
    "wof:name":"H&C Construction",
    "wof:placetype":"venue"
},
  "geometry": {"coordinates":[-112.096105,33.551989],"type":"Point"}
}