{
  "type": "Feature",
  "properties": {
    "iso:country":"US",
    "sg:address":"3480 Cypress St",
    "sg:city":"Kingman",
    "sg:classifiers":[
        {
            "category":"Restaurant",
            "type":"Food & Drink"
        }
    ],
    "sg:phone":"+1 928 753 3550",
    "sg:postcode":"86401",
    "sg:province":"AZ",
    "sg:tags":[
        "eating"
    ],
    "wof:name":"City Cafe",
    "wof:placetype":"venue"
},
  "geometry": {"coordinates":[-113.995044,35.224661],"type":"Point"}
}