{
  "type": "Feature",
  "properties": {
    "iso:country":"US",
    "sg:address":"7274 W Safford Bryce Rd",
    "sg:city":"Pima",
    "sg:classifiers":[
        {
            "category":"Utilities",
            "subcategory":"Water",
            "type":"Services"
        }
    ],
    "sg:phone":"+1 928 485 9639",
    "sg:postcode":"85543",
    "sg:province":"AZ",
    "sg:tags":[
        "pump",
        "well",
        "drilling",
        "contractor"
    ],
    "wof:name":"4 J Drilling & Pump Company",
    "wof:placetype":"venue"
},
  "geometry": {"coordinates":[-109.823595,32.925369],"type":"Point"}
}