{
  "type": "Feature",
  "properties": {
    "iso:country":"US",
    "sg:address":"902 N Lone Oak Way",
    "sg:city":"Flagstaff",
    "sg:classifiers":[
        {
            "category":"Real Estate",
            "subcategory":"Real Estate Agent",
            "type":"Services"
        }
    ],
    "sg:phone":"+1 928 853 8787",
    "sg:postcode":"86004",
    "sg:province":"AZ",
    "wof:name":"Century 21",
    "wof:placetype":"venue"
},
  "geometry": {"coordinates":[-111.58166799999999,35.185564],"type":"Point"}
}