{
  "type": "Feature",
  "properties": {
    "iso:country":"US",
    "sg:address":"1625 N 51st Ave",
    "sg:city":"Phoenix",
    "sg:classifiers":[
        {
            "category":"Banks & Credit Unions",
            "subcategory":"Bank",
            "type":"Services"
        }
    ],
    "sg:phone":"+1 602 233 3311",
    "sg:postcode":"85035",
    "sg:province":"AZ",
    "sg:tags":[
        "cashing",
        "loan",
        "check"
    ],
    "sg:website":"http://www.1stopcheckcashing.com",
    "wof:name":"1 Stop Check Cashing",
    "wof:placetype":"venue"
},
  "geometry": {"coordinates":[-112.169117,33.466965],"type":"Point"}
}