{
  "type": "Feature",
  "properties": {
    "addr:full":"9501 E Shea Blvd Scottsdale AZ 85260",
    "addr:housenumber":"9501",
    "addr:postcode":"85260",
    "addr:street":"E Shea Blvd",
    "iso:country":"US",
    "sg:address":"9501 E Shea Blvd",
    "sg:city":"Scottsdale",
    "sg:classifiers":[
        {
            "category":"Shopping",
            "subcategory":"Pharmacy",
            "type":"Retail Goods"
        }
    ],
    "sg:phone":"+1 480 391 4600",
    "sg:postcode":"85260",
    "sg:province":"AZ",
    "sg:website":"http://www.cvs.com",
    "wof:name":"Cvs Caremark Corporation",
    "wof:placetype":"venue"
},
  "geometry": {"coordinates":[-111.87624099999999,33.582458],"type":"Point"}
}