{
  "type": "Feature",
  "properties": {
    "iso:country":"US",
    "sg:address":"1111 N Gilbert Rd",
    "sg:city":"Gilbert",
    "sg:classifiers":[
        {
            "category":"Real Estate",
            "subcategory":"Real Estate Agent",
            "type":"Services"
        }
    ],
    "sg:phone":"+1 480 892 1969",
    "sg:postcode":"85234",
    "sg:province":"AZ",
    "wof:name":"RE/Max Alliance - Reeves Team",
    "wof:placetype":"venue"
},
  "geometry": {"coordinates":[-111.789913,33.370539],"type":"Point"}
}