{
  "type": "Feature",
  "properties": {
    "iso:country":"US",
    "sg:address":"4520 N Bank St",
    "sg:city":"Kingman",
    "sg:classifiers":[
        {
            "category":"Professional",
            "subcategory":"Computer Services",
            "type":"Services"
        }
    ],
    "sg:phone":"+1 928 757 1301",
    "sg:postcode":"86409",
    "sg:province":"AZ",
    "sg:tags":[
        "internet"
    ],
    "wof:name":"Gamers Zone Internet Access",
    "wof:placetype":"venue"
},
  "geometry": {"coordinates":[-114.011525,35.25561],"type":"Point"}
}