{
  "type": "Feature",
  "properties": {
    "iso:country":"US",
    "sg:address":"1526 E Windsong Dr",
    "sg:city":"Phoenix",
    "sg:classifiers":[
        {
            "category":"Shopping",
            "subcategory":"Computers & Home Electronics",
            "type":"Retail Goods"
        }
    ],
    "sg:phone":"+1 480 283 0900",
    "sg:postcode":"85048",
    "sg:province":"AZ",
    "sg:tags":[
        "software"
    ],
    "wof:name":"Logik Online",
    "wof:placetype":"venue"
},
  "geometry": {"coordinates":[-112.047765,33.292466],"type":"Point"}
}