{
  "type": "Feature",
  "properties": {
    "addr:full":"17301 E Spring Valley Rd Mayer AZ 86333",
    "addr:housenumber":"17301",
    "addr:postcode":"86333",
    "addr:street":"E Spring Valley Rd",
    "iso:country":"US",
    "sg:address":"17301 E Spring Valley Rd",
    "sg:city":"Mayer",
    "sg:classifiers":[
        {
            "category":"Retail",
            "subcategory":"Auto Rental",
            "type":"Services"
        }
    ],
    "sg:phone":"+1 928 632 4721",
    "sg:postcode":"86333",
    "sg:province":"AZ",
    "sg:tags":[
        "renting",
        "truck",
        "leasing"
    ],
    "wof:name":"U-Haul Co",
    "wof:placetype":"venue"
},
  "geometry": {"coordinates":[-112.159153,34.349651],"type":"Point"}
}