{
  "type": "Feature",
  "properties": {
    "addr:full":"1701 E 8th St Tempe AZ 85281",
    "addr:housenumber":"1701",
    "addr:postcode":"85281",
    "addr:street":"E 8Th St",
    "iso:country":"US",
    "sg:address":"1701 E 8th St",
    "sg:city":"Tempe",
    "sg:classifiers":[
        {
            "category":"Shopping",
            "subcategory":"Discount & Variety Stores",
            "type":"Retail Goods"
        }
    ],
    "sg:phone":"+1 602 793 0579",
    "sg:postcode":"85281",
    "sg:province":"AZ",
    "sg:tags":[
        "merchandise",
        "general"
    ],
    "wof:name":"HSL",
    "wof:placetype":"venue"
},
  "geometry": {"coordinates":[-111.91113,33.41945],"type":"Point"}
}