{
  "type": "Feature",
  "properties": {
    "iso:country":"US",
    "sg:address":"810 E Western Ave",
    "sg:city":"Avondale",
    "sg:classifiers":[
        {
            "category":"Personal",
            "type":"Services"
        }
    ],
    "sg:phone":"+1 623 932 2525",
    "sg:postcode":"85323",
    "sg:province":"AZ",
    "sg:tags":[
        "towing"
    ],
    "wof:name":"E-Z Towing Dispatch",
    "wof:placetype":"venue"
},
  "geometry": {"coordinates":[-112.341003,33.435398],"type":"Point"}
}