{
  "type": "Feature",
  "properties": {
    "addr:full":"1449 Sierra Dr Sierra Vista AZ 85635",
    "addr:housenumber":"1449",
    "addr:postcode":"85635",
    "addr:street":"Sierra Dr",
    "iso:country":"US",
    "sg:address":"1449 Sierra Dr",
    "sg:city":"Sierra Vista",
    "sg:classifiers":[
        {
            "category":"Freight",
            "type":"Transportation"
        }
    ],
    "sg:phone":"+1 520 515 3830",
    "sg:postcode":"85635",
    "sg:province":"AZ",
    "sg:tags":[
        "operator",
        "local",
        "trucking"
    ],
    "wof:name":"Local Moves Only",
    "wof:placetype":"venue"
},
  "geometry": {"coordinates":[-110.282489,31.556749],"type":"Point"}
}