{
  "type": "Feature",
  "properties": {
    "iso:country":"US",
    "sg:address":"105 Castle Rock Trl",
    "sg:city":"Sedona",
    "sg:classifiers":[
        {
            "category":"Building & Trades",
            "subcategory":"Construction",
            "type":"Services"
        }
    ],
    "sg:phone":"+1 928 282 7479",
    "sg:postcode":"86336",
    "sg:province":"AZ",
    "wof:name":"Terry & Sandra Medulla",
    "wof:placetype":"venue"
},
  "geometry": {"coordinates":[-111.780329,34.837288],"type":"Point"}
}