{
  "type": "Feature",
  "properties": {
    "iso:country":"US",
    "sg:address":"1636 S 7th St",
    "sg:city":"Phoenix",
    "sg:classifiers":[
        {
            "category":"Autos & Motor Vehicles",
            "subcategory":"Auto Supplies",
            "type":"Retail Goods"
        }
    ],
    "sg:phone":"+1 602 271 4715",
    "sg:postcode":"85034",
    "sg:province":"AZ",
    "wof:name":"Mannys Tires Shop",
    "wof:placetype":"venue"
},
  "geometry": {"coordinates":[-112.065194,33.432584],"type":"Point"}
}