{
  "type": "Feature",
  "properties": {
    "iso:country":"US",
    "sg:address":"790 W Broadway Rd",
    "sg:city":"Tempe",
    "sg:classifiers":[
        {
            "category":"Restaurant",
            "type":"Food & Drink"
        }
    ],
    "sg:phone":"+1 480 968 2708",
    "sg:postcode":"85282",
    "sg:province":"AZ",
    "sg:tags":[
        "eating"
    ],
    "wof:name":"Wendys",
    "wof:placetype":"venue"
},
  "geometry": {"coordinates":[-111.948272,33.407454],"type":"Point"}
}