{
  "type": "Feature",
  "properties": {
    "addr:full":"7689 E Paradise Ln Scottsdale AZ 85260",
    "addr:housenumber":"7689",
    "addr:postcode":"85260",
    "addr:street":"E Paradise Ln",
    "iso:country":"US",
    "sg:address":"7689 E Paradise Ln",
    "sg:city":"Scottsdale",
    "sg:classifiers":[
        {
            "category":"Home & Garden",
            "subcategory":"Home Furnishings",
            "type":"Retail Goods"
        }
    ],
    "sg:phone":"+1 480 947 1854",
    "sg:postcode":"85260",
    "sg:province":"AZ",
    "wof:name":"Mr PS Blind & Shade",
    "wof:placetype":"venue"
},
  "geometry": {"coordinates":[-111.916336,33.632924],"type":"Point"}
}