{
  "type": "Feature",
  "properties": {
    "addr:full":"1140 E Rawhide Ave Gilbert AZ 85296",
    "addr:housenumber":"1140",
    "addr:postcode":"85296",
    "addr:street":"E Rawhide Ave",
    "iso:country":"US",
    "sg:address":"1140 E Rawhide Ave",
    "sg:city":"Gilbert",
    "sg:classifiers":[
        {
            "category":"Building & Trades",
            "subcategory":"Plumbing",
            "type":"Services"
        }
    ],
    "sg:phone":"+1 480 722 1267",
    "sg:postcode":"85296",
    "sg:province":"AZ",
    "sg:tags":[
        "mechanical",
        "contractor"
    ],
    "wof:name":"Crawford Mechanical Services",
    "wof:placetype":"venue"
},
  "geometry": {"coordinates":[-111.76543100000001,33.341613],"type":"Point"}
}