{
  "type": "Feature",
  "properties": {
    "iso:country":"US",
    "sg:address":"1342 N 22nd St",
    "sg:city":"Mesa",
    "sg:classifiers":[
        {
            "category":"Building & Trades",
            "subcategory":"Landscaping Services",
            "type":"Services"
        }
    ],
    "sg:phone":"+1 480 834 4780",
    "sg:postcode":"85213",
    "sg:province":"AZ",
    "sg:tags":[
        "tree"
    ],
    "wof:name":"Cory Allen Tree Co",
    "wof:placetype":"venue"
},
  "geometry": {"coordinates":[-111.783643,33.440574],"type":"Point"}
}