{
  "type": "Feature",
  "properties": {
    "iso:country":"US",
    "sg:address":"2347 W Pampa Ave",
    "sg:city":"Mesa",
    "sg:classifiers":[
        {
            "category":"Building & Trades",
            "subcategory":"Construction",
            "type":"Services"
        }
    ],
    "sg:phone":"+1 480 839 5907",
    "sg:postcode":"85202",
    "sg:province":"AZ",
    "sg:tags":[
        "floor",
        "laying",
        "contractor"
    ],
    "wof:name":"Dynomite Flooring LLC",
    "wof:placetype":"venue"
},
  "geometry": {"coordinates":[-111.883916,33.358178],"type":"Point"}
}