{
  "type": "Feature",
  "properties": {
    "iso:country":"US",
    "sg:address":"7036 E Broadway Blvd",
    "sg:city":"Tucson",
    "sg:classifiers":[
        {
            "category":"Arts & Performance",
            "subcategory":"Theater",
            "type":"Entertainment"
        }
    ],
    "sg:phone":"+1 520 296 1383",
    "sg:postcode":"85710",
    "sg:province":"AZ",
    "sg:tags":[
        "dance",
        "company"
    ],
    "wof:name":"Hot Flashes",
    "wof:placetype":"venue"
},
  "geometry": {"coordinates":[-110.843587,32.220962],"type":"Point"}
}