{
  "type": "Feature",
  "properties": {
    "iso:country":"US",
    "sg:address":"12217 W Daley Ln",
    "sg:city":"Sun City",
    "sg:classifiers":[
        {
            "category":"Real Estate",
            "subcategory":"Real Estate Agent",
            "type":"Services"
        }
    ],
    "sg:phone":"+1 623 214 7850",
    "sg:postcode":"85373",
    "sg:province":"AZ",
    "wof:name":"Courtland Homes",
    "wof:placetype":"venue"
},
  "geometry": {"coordinates":[-112.324224,33.691581],"type":"Point"}
}