{
  "type": "Feature",
  "properties": {
    "iso:country":"US",
    "sg:address":"2302 E Indian School Rd",
    "sg:city":"Phoenix",
    "sg:classifiers":[
        {
            "category":"Real Estate",
            "subcategory":"Real Estate Operator",
            "type":"Services"
        }
    ],
    "sg:phone":"+1 602 955 1950",
    "sg:postcode":"85016",
    "sg:province":"AZ",
    "sg:tags":[
        "property",
        "commercial"
    ],
    "wof:name":"Tangs Realty",
    "wof:placetype":"venue"
},
  "geometry": {"coordinates":[-112.030232,33.494924],"type":"Point"}
}