{
  "type": "Feature",
  "properties": {
    "iso:country":"US",
    "sg:address":"1212 E Baseline Rd",
    "sg:city":"Tempe",
    "sg:classifiers":[
        {
            "category":"Professional",
            "subcategory":"Accounting & Tax Preparation",
            "type":"Services"
        }
    ],
    "sg:phone":"+1 480 730 8700",
    "sg:postcode":"85283",
    "sg:province":"AZ",
    "sg:tags":[
        "reporting"
    ],
    "sg:website":"http://www.ameriprise.com",
    "wof:name":"Ameriprise Financial",
    "wof:placetype":"venue"
},
  "geometry": {"coordinates":[-111.920047,33.378324],"type":"Point"}
}