{
  "type": "Feature",
  "properties": {
    "iso:country":"US",
    "sg:address":"1445 W Southern Ave",
    "sg:city":"Mesa",
    "sg:classifiers":[
        {
            "category":"Shopping",
            "subcategory":"Clothing, Apparel, & Fashions",
            "type":"Retail Goods"
        }
    ],
    "sg:phone":"+1 480 844 3771",
    "sg:postcode":"85202",
    "sg:province":"AZ",
    "sg:tags":[
        "infant",
        "wear"
    ],
    "sg:website":"www.childrensplace.com",
    "wof:name":"Children's Place",
    "wof:placetype":"venue"
},
  "geometry": {"coordinates":[-111.861182,33.393026],"type":"Point"}
}