{
  "type": "Feature",
  "properties": {
    "iso:country":"US",
    "sg:address":"4066 E 22nd St",
    "sg:city":"Tucson",
    "sg:classifiers":[
        {
            "category":"Shopping",
            "subcategory":"Clothing, Apparel, & Fashions",
            "type":"Retail Goods"
        }
    ],
    "sg:phone":"+1 520 748 9680",
    "sg:postcode":"85711",
    "sg:province":"AZ",
    "wof:name":"Fashiontime",
    "wof:placetype":"venue"
},
  "geometry": {"coordinates":[-110.90653,32.206923],"type":"Point"}
}