{
  "type": "Feature",
  "properties": {
    "iso:country":"US",
    "sg:address":"407 E Monroe Ave",
    "sg:city":"Buckeye",
    "sg:classifiers":[
        {
            "category":"Manufacturing",
            "subcategory":"Printing",
            "type":"Manufacturing & Wholesale Goods"
        }
    ],
    "sg:phone":"+1 623 393 0000",
    "sg:postcode":"85326",
    "sg:province":"AZ",
    "sg:tags":[
        "screen"
    ],
    "wof:name":"Absolute Screen Printing",
    "wof:placetype":"venue"
},
  "geometry": {"coordinates":[-112.58511,33.370409],"type":"Point"}
}