{
  "type": "Feature",
  "properties": {
    "addr:full":"224 W Canterbury Ln Phoenix AZ 85023",
    "addr:housenumber":"224",
    "addr:postcode":"85023",
    "addr:street":"W Canterbury Ln",
    "iso:country":"US",
    "sg:address":"224 W Canterbury Ln",
    "sg:city":"Phoenix",
    "sg:classifiers":[
        {
            "category":"Arts & Performance",
            "subcategory":"Theater",
            "type":"Entertainment"
        }
    ],
    "sg:phone":"+1 602 252 3396",
    "sg:postcode":"85023",
    "sg:province":"AZ",
    "sg:tags":[
        "musician"
    ],
    "wof:name":"Choralaires Of Phoenix",
    "wof:placetype":"venue"
},
  "geometry": {"coordinates":[-112.07679400000001,33.614624],"type":"Point"}
}