{
  "type": "Feature",
  "properties": {
    "iso:country":"US",
    "sg:address":"1520 S Dobson Road Suite 314",
    "sg:city":"Mesa",
    "sg:classifiers":[
        {
            "category":"Health Services",
            "subcategory":"Doctor",
            "type":"Services"
        }
    ],
    "sg:phone":"+1 480 833 5200",
    "sg:postcode":"85202",
    "sg:province":"AZ",
    "sg:website":"www.bunchman.com",
    "wof:name":"Bunchman H H II MD",
    "wof:placetype":"venue"
},
  "geometry": {"coordinates":[-111.874752,33.386742],"type":"Point"}
}