{
  "type": "Feature",
  "properties": {
    "iso:country":"US",
    "sg:address":"2801 W Newton Ct",
    "sg:city":"Chandler",
    "sg:classifiers":[
        {
            "category":"Professional",
            "subcategory":"Business Services",
            "type":"Services"
        }
    ],
    "sg:phone":"+1 480 897 0778",
    "sg:postcode":"85224",
    "sg:province":"AZ",
    "sg:tags":[
        "pool",
        "swimming"
    ],
    "wof:name":"Hoach's Pool Svc",
    "wof:placetype":"venue"
},
  "geometry": {"coordinates":[-111.89098300000001,33.353944],"type":"Point"}
}