{
  "type": "Feature",
  "properties": {
    "iso:country":"US",
    "sg:address":"216 N Montezuma St",
    "sg:city":"Prescott",
    "sg:classifiers":[
        {
            "category":"Restaurant",
            "type":"Food & Drink"
        }
    ],
    "sg:phone":"+1 928 777 0105",
    "sg:postcode":"86301",
    "sg:province":"AZ",
    "wof:name":"Hugo's Cocina",
    "wof:placetype":"venue"
},
  "geometry": {"coordinates":[-112.47015500000001,34.544038],"type":"Point"}
}