{
  "type": "Feature",
  "properties": {
    "iso:country":"US",
    "sg:address":"MOVING HELP",
    "sg:city":"Phoenix",
    "sg:phone":"+1 866 366 4457",
    "sg:postcode":"85051",
    "sg:province":"AZ",
    "sg:website":"http://www.movers4hire.com",
    "wof:name":"Movers4Hire",
    "wof:placetype":"venue"
},
  "geometry": {"coordinates":[-112.114639,33.558285],"type":"Point"}
}