{
  "type": "Feature",
  "properties": {
    "iso:country":"US",
    "sg:address":"6350 E State Rte 69",
    "sg:city":"Prescott Valley",
    "sg:classifiers":[
        {
            "category":"Insurance",
            "subcategory":"Insurance Agent",
            "type":"Services"
        }
    ],
    "sg:phone":"+1 928 775 5676",
    "sg:postcode":"86314",
    "sg:province":"AZ",
    "wof:name":"State Farm Insurance",
    "wof:placetype":"venue"
},
  "geometry": {"coordinates":[-112.351457,34.581475],"type":"Point"}
}