{
  "type": "Feature",
  "properties": {
    "addr:full":"3631 W Camelback Rd Phoenix AZ 85019",
    "addr:housenumber":"3631",
    "addr:postcode":"85019",
    "addr:street":"W Camelback Rd",
    "iso:country":"US",
    "sg:address":"3631 W Camelback Rd",
    "sg:city":"Phoenix",
    "sg:classifiers":[
        {
            "category":"Shopping",
            "subcategory":"Gifts & Souvenirs",
            "type":"Retail Goods"
        }
    ],
    "sg:phone":"+1 602 589 5328",
    "sg:postcode":"85019",
    "sg:province":"AZ",
    "sg:tags":[
        "shop",
        "party",
        "supply"
    ],
    "wof:name":"El Sol Balloon's & Pinata's",
    "wof:placetype":"venue"
},
  "geometry": {"coordinates":[-112.137321,33.509449],"type":"Point"}
}