{
  "type": "Feature",
  "properties": {
    "addr:full":"6714 W Frier Dr Glendale AZ 85303",
    "addr:housenumber":"6714",
    "addr:postcode":"85303",
    "addr:street":"W Frier Dr",
    "iso:country":"US",
    "sg:address":"6714 W Frier Dr",
    "sg:city":"Glendale",
    "sg:classifiers":[
        {
            "category":"Home & Garden",
            "subcategory":"Carpets & Floor Coverings",
            "type":"Retail Goods"
        }
    ],
    "sg:phone":"+1 623 435 1324",
    "sg:postcode":"85303",
    "sg:province":"AZ",
    "sg:tags":[
        "flooring",
        "contractor"
    ],
    "wof:name":"Arizona Polymer Flooring",
    "wof:placetype":"venue"
},
  "geometry": {"coordinates":[-112.203208,33.549155],"type":"Point"}
}