{
  "type": "Feature",
  "properties": {
    "iso:country":"US",
    "sg:address":"11225 N 28th Dr",
    "sg:city":"Phoenix",
    "sg:classifiers":[
        {
            "category":"Insurance",
            "subcategory":"Insurance Agent",
            "type":"Services"
        },
        {
            "category":"Insurance",
            "subcategory":"Hazard Insurance",
            "type":"Services"
        },
        {
            "category":"Insurance",
            "subcategory":"Title Insurance",
            "type":"Services"
        },
        {
            "category":"Insurance",
            "subcategory":"Life Insurance",
            "type":"Services"
        }
    ],
    "sg:phone":"+1 602 375 1983",
    "sg:postcode":"85029",
    "sg:province":"AZ",
    "sg:tags":[
        "auto",
        "commercial",
        "business",
        "homeowner"
    ],
    "sg:website":"http://www.farmersagent.com/mconnor/",
    "wof:name":"Millard Connor Iii - Farmers Insurance",
    "wof:placetype":"venue"
},
  "geometry": {"coordinates":[-112.120932,33.588867],"type":"Point"}
}