{
  "type": "Feature",
  "properties": {
    "addr:full":"301 W Deer Valley Rd Phoenix AZ 85027",
    "addr:housenumber":"301",
    "addr:postcode":"85027",
    "addr:street":"W Deer Valley Rd",
    "iso:country":"US",
    "sg:address":"301 W Deer Valley Rd",
    "sg:city":"Phoenix",
    "sg:classifiers":[
        {
            "category":"Manufacturing",
            "subcategory":"Tools & Machinery",
            "type":"Manufacturing & Wholesale Goods"
        }
    ],
    "sg:phone":"+1 623 587 6473",
    "sg:postcode":"85027",
    "sg:province":"AZ",
    "sg:tags":[
        "control"
    ],
    "sg:website":"www.microsmith.com",
    "wof:name":"Microsmith",
    "wof:placetype":"venue"
},
  "geometry": {"coordinates":[-112.077783,33.683752],"type":"Point"}
}