{
  "type": "Feature",
  "properties": {
    "iso:country":"US",
    "sg:address":"3075 W Chandler Boulevard",
    "sg:city":"Chandler",
    "sg:classifiers":[
        {
            "category":"Banks & Credit Unions",
            "subcategory":"Bank",
            "type":"Services"
        }
    ],
    "sg:phone":"+1 480 403 7820",
    "sg:postcode":"85226",
    "sg:province":"AZ",
    "sg:website":"www.compassbank.com",
    "wof:name":"Compass Bank",
    "wof:placetype":"venue"
},
  "geometry": {"coordinates":[-111.89624999999999,33.305619],"type":"Point"}
}