{
  "type": "Feature",
  "properties": {
    "iso:country":"US",
    "sg:address":"16480 W Hope Dr",
    "sg:city":"Surprise",
    "sg:classifiers":[
        {
            "category":"Building & Trades",
            "subcategory":"Construction",
            "type":"Services"
        }
    ],
    "sg:phone":"+1 623 975 1871",
    "sg:postcode":"85388",
    "sg:province":"AZ",
    "sg:tags":[
        "wallcoverings-installation",
        "wallpaper",
        "painting",
        "contractor"
    ],
    "wof:name":"Dz Paint Inc",
    "wof:placetype":"venue"
},
  "geometry": {"coordinates":[-112.413729,33.585286],"type":"Point"}
}