{
  "type": "Feature",
  "properties": {
    "iso:country":"US",
    "sg:address":"2980 N Campbell Ave",
    "sg:city":"Tucson",
    "sg:classifiers":[
        {
            "category":"Real Estate",
            "subcategory":"Architect",
            "type":"Services"
        }
    ],
    "sg:phone":"+1 520 318 9880",
    "sg:postcode":"85719",
    "sg:province":"AZ",
    "sg:website":"www.durrant.com",
    "wof:name":"Durrant Architects",
    "wof:placetype":"venue"
},
  "geometry": {"coordinates":[-110.94375700000001,32.259715],"type":"Point"}
}