{
  "type": "Feature",
  "properties": {
    "addr:full":"8477 E Mcdonald Dr Scottsdale AZ 85250",
    "addr:housenumber":"8477",
    "addr:postcode":"85250",
    "addr:street":"E Mcdonald Dr",
    "iso:country":"US",
    "sg:address":"8477 E Mcdonald Dr",
    "sg:city":"Scottsdale",
    "sg:classifiers":[
        {
            "category":"Personal",
            "subcategory":"Beauty Salon",
            "type":"Services"
        }
    ],
    "sg:phone":"+1 480 922 7424",
    "sg:postcode":"85250",
    "sg:province":"AZ",
    "wof:name":"Lady Gwenevere's Beauty Retreat",
    "wof:placetype":"venue"
},
  "geometry": {"coordinates":[-111.898629,33.523891],"type":"Point"}
}