{
  "type": "Feature",
  "properties": {
    "iso:country":"US",
    "sg:address":"9334 E Daniel Pl",
    "sg:city":"Tucson",
    "sg:classifiers":[
        {
            "category":"Professional",
            "type":"Services"
        }
    ],
    "sg:phone":"+1 520 298 9267",
    "sg:postcode":"85710",
    "sg:province":"AZ",
    "sg:tags":[
        "arts",
        "artist"
    ],
    "wof:name":"Maureen L Garrison Artist",
    "wof:placetype":"venue"
},
  "geometry": {"coordinates":[-110.792521,32.194956],"type":"Point"}
}