{
  "type": "Feature",
  "properties": {
    "addr:full":"9334 E Daniel Pl Tucson AZ 85710",
    "addr:housenumber":"9334",
    "addr:postcode":"85710",
    "addr:street":"E Daniel Pl",
    "iso:country":"US",
    "sg:address":"9334 E Daniel Pl",
    "sg:city":"Tucson",
    "sg:classifiers":[
        {
            "category":"Professional",
            "type":"Services"
        }
    ],
    "sg:phone":"+1 520 298 9267",
    "sg:postcode":"85710",
    "sg:province":"AZ",
    "sg:tags":[
        "arts",
        "artist"
    ],
    "wof:name":"Maureen L Garrison Artist",
    "wof:placetype":"venue"
},
  "geometry": {"coordinates":[-110.79252099999999,32.194956],"type":"Point"}
}