{
  "type": "Feature",
  "properties": {
    "iso:country":"US",
    "sg:address":"6435 W Chandler Blvd",
    "sg:city":"Chandler",
    "sg:classifiers":[
        {
            "category":"Home & Garden",
            "subcategory":"Building Materials",
            "type":"Retail Goods"
        }
    ],
    "sg:phone":"+1 480 330 7687",
    "sg:postcode":"85226",
    "sg:province":"AZ",
    "sg:tags":[
        "mixed",
        "concrete"
    ],
    "wof:name":"Az Short Pour",
    "wof:placetype":"venue"
},
  "geometry": {"coordinates":[-111.951912,33.305241],"type":"Point"}
}