{
  "type": "Feature",
  "properties": {
    "addr:full":"1230 W Lyle Ln Tucson AZ 85755",
    "addr:housenumber":"1230",
    "addr:postcode":"85755",
    "addr:street":"W Lyle Ln",
    "iso:country":"US",
    "sg:address":"1230 W Lyle Ln",
    "sg:city":"Tucson",
    "sg:classifiers":[
        {
            "category":"Personal",
            "subcategory":"Beauty Salon",
            "type":"Services"
        }
    ],
    "sg:phone":"+1 520 742 6285",
    "sg:postcode":"85755",
    "sg:province":"AZ",
    "wof:name":"Earth Strands",
    "wof:placetype":"venue"
},
  "geometry": {"coordinates":[-110.991799,32.44637],"type":"Point"}
}