{
  "type": "Feature",
  "properties": {
    "iso:country":"US",
    "sg:address":"7053 N Oracle Rd",
    "sg:city":"Tucson",
    "sg:classifiers":[
        {
            "category":"Restaurant",
            "type":"Food & Drink"
        }
    ],
    "sg:menulink":"http://www.allmenus.com/az/tucson/268358-bluefin-seafood-bistro/menu/",
    "sg:phone":"+1 520 531 8500",
    "sg:postcode":"85704",
    "sg:province":"AZ",
    "sg:tags":[
        "seafood",
        "american"
    ],
    "wof:name":"Bluefin Seafood Bistro",
    "wof:placetype":"venue"
},
  "geometry": {"coordinates":[-110.978211,32.335812],"type":"Point"}
}