{
  "type": "Feature",
  "properties": {
    "iso:country":"US",
    "sg:address":"1636 N 43rd Ave",
    "sg:city":"Phoenix",
    "sg:classifiers":[
        {
            "category":"Autos & Motor Vehicles",
            "subcategory":"Auto Supplies",
            "type":"Retail Goods"
        }
    ],
    "sg:phone":"+1 602 269 9918",
    "sg:postcode":"85009",
    "sg:province":"AZ",
    "sg:tags":[
        "tire"
    ],
    "wof:name":"Big O Tires",
    "wof:placetype":"venue"
},
  "geometry": {"coordinates":[-112.15184600000001,33.468298],"type":"Point"}
}