{
  "type": "Feature",
  "properties": {
    "iso:country":"US",
    "sg:address":"7010 E Chauncey Ln # 100",
    "sg:city":"Phoenix",
    "sg:classifiers":[
        {
            "category":"Place Of Worship",
            "subcategory":"Church",
            "type":"Public Place"
        },
        {
            "category":"Place Of Worship",
            "type":"Public Place"
        }
    ],
    "sg:phone":"+1 480 307 9216",
    "sg:postcode":"85054",
    "sg:province":"AZ",
    "sg:tags":[
        "churches-episcopal-anglican",
        "churches-episcopal"
    ],
    "wof:name":"The Episcopal Church Of The Nativity",
    "wof:placetype":"venue"
},
  "geometry": {"coordinates":[-111.92929700000001,33.651581],"type":"Point"}
}