{
  "type": "Feature",
  "properties": {
    "addr:full":"1800 E Broadway Blvd Tucson AZ 85719",
    "addr:housenumber":"1800",
    "addr:postcode":"85719",
    "addr:street":"E Broadway Blvd",
    "iso:country":"US",
    "sg:address":"1800 E Broadway Blvd",
    "sg:city":"Tucson",
    "sg:classifiers":[
        {
            "category":"Banks & Credit Unions",
            "subcategory":"Bank",
            "type":"Services"
        }
    ],
    "sg:phone":"+1 520 624 1014",
    "sg:postcode":"85719",
    "sg:province":"AZ",
    "sg:tags":[
        "cashing",
        "check"
    ],
    "wof:name":"Check Into Cash",
    "wof:placetype":"venue"
},
  "geometry": {"coordinates":[-110.94394800000001,32.221441],"type":"Point"}
}