{
  "type": "Feature",
  "properties": {
    "iso:country":"US",
    "sg:address":"13220 W Van Buren St Ste 110",
    "sg:city":"Goodyear",
    "sg:classifiers":[
        {
            "category":"Ice Cream",
            "type":"Food & Drink"
        }
    ],
    "sg:phone":"+1 623 932 4420",
    "sg:postcode":"85338",
    "sg:province":"AZ",
    "sg:tags":[
        "frozen",
        "yogurt"
    ],
    "wof:name":"Baskin-Robbins",
    "wof:placetype":"venue"
},
  "geometry": {"coordinates":[-112.358298,33.449847],"type":"Point"}
}