{
  "type": "Feature",
  "properties": {
    "addr:full":"2136 E Indian School Rd Phoenix AZ 85016",
    "addr:housenumber":"2136",
    "addr:postcode":"85016",
    "addr:street":"E Indian School Rd",
    "iso:country":"US",
    "sg:address":"2136 E Indian School Rd",
    "sg:city":"Phoenix",
    "sg:classifiers":[
        {
            "category":"Retail",
            "subcategory":"Auto Repair",
            "type":"Services"
        }
    ],
    "sg:phone":"+1 602 808 0794",
    "sg:postcode":"85016",
    "sg:province":"AZ",
    "sg:tags":[
        "body",
        "automobile",
        "painting"
    ],
    "wof:name":"New Earl Scheib Paint & Body",
    "wof:placetype":"venue"
},
  "geometry": {"coordinates":[-112.035203,33.49488],"type":"Point"}
}