{
  "type": "Feature",
  "properties": {
    "iso:country":"US",
    "sg:address":"3207 E Ajo Way",
    "sg:city":"Tucson",
    "sg:classifiers":[
        {
            "category":"Wholesale",
            "subcategory":"Auto Parts",
            "type":"Manufacturing & Wholesale Goods"
        }
    ],
    "sg:phone":"+1 520 792 9616",
    "sg:postcode":"85713",
    "sg:province":"AZ",
    "sg:tags":[
        "automobile",
        "rebuilt",
        "used"
    ],
    "wof:name":"Auto & Truck Salvage Co",
    "wof:placetype":"venue"
},
  "geometry": {"coordinates":[-110.924375,32.178063],"type":"Point"}
}