{
  "type": "Feature",
  "properties": {
    "addr:full":"730 N Montezuma St Prescott AZ 86301",
    "addr:housenumber":"730",
    "addr:postcode":"86301",
    "addr:street":"N Montezuma St",
    "iso:country":"US",
    "sg:address":"730 N Montezuma St",
    "sg:city":"Prescott",
    "sg:classifiers":[
        {
            "category":"Building & Trades",
            "subcategory":"Construction",
            "type":"Services"
        }
    ],
    "sg:phone":"+1 928 776 0515",
    "sg:postcode":"86301",
    "sg:province":"AZ",
    "sg:tags":[
        "planning",
        "remodeling",
        "kitchen"
    ],
    "wof:name":"Prescott Design Studio",
    "wof:placetype":"venue"
},
  "geometry": {"coordinates":[-112.469826,34.55439],"type":"Point"}
}