{
  "type": "Feature",
  "properties": {
    "iso:country":"US",
    "sg:address":"6731 E Cam Principal",
    "sg:city":"Tucson",
    "sg:classifiers":[
        {
            "category":"Health Services",
            "subcategory":"Doctor",
            "type":"Services"
        }
    ],
    "sg:phone":"+1 520 721 3471",
    "sg:postcode":"85715",
    "sg:province":"AZ",
    "sg:tags":[
        "physician",
        "surgeon"
    ],
    "wof:name":"Olson Facial Plastic Surgery",
    "wof:placetype":"venue"
},
  "geometry": {"coordinates":[-110.849278,32.250529],"type":"Point"}
}