{
  "type": "Feature",
  "properties": {
    "iso:country":"US",
    "sg:address":"211 N Granite St",
    "sg:city":"Prescott",
    "sg:classifiers":[
        {
            "category":"Retail",
            "subcategory":"Repair Shop",
            "type":"Services"
        }
    ],
    "sg:phone":"+1 928 777 0760",
    "sg:postcode":"86301",
    "sg:province":"AZ",
    "sg:tags":[
        "scooter",
        "motorcycle",
        "motor"
    ],
    "wof:name":"Electric Hog",
    "wof:placetype":"venue"
},
  "geometry": {"coordinates":[-112.47142599999999,34.545186],"type":"Point"}
}