{
  "type": "Feature",
  "properties": {
    "iso:country":"US",
    "sg:address":"10229 N 101st St",
    "sg:city":"Scottsdale",
    "sg:classifiers":[
        {
            "category":"Health Services",
            "subcategory":"Health Practitioner",
            "type":"Services"
        }
    ],
    "sg:phone":"+1 480 314 4299",
    "sg:postcode":"85258",
    "sg:province":"AZ",
    "sg:tags":[
        "psychologist"
    ],
    "wof:name":"Center For Attention Deficit",
    "wof:placetype":"venue"
},
  "geometry": {"coordinates":[-111.863483,33.579941],"type":"Point"}
}