{
  "type": "Feature",
  "properties": {
    "addr:full":"1175 N Tegner St Wickenburg AZ 85390",
    "addr:housenumber":"1175",
    "addr:postcode":"85390",
    "addr:street":"N Tegner St",
    "iso:country":"US",
    "sg:address":"1175 N Tegner St",
    "sg:city":"Wickenburg",
    "sg:classifiers":[
        {
            "category":"Autos & Motor Vehicles",
            "subcategory":"Auto Supplies",
            "type":"Retail Goods"
        }
    ],
    "sg:phone":"+1 928 684 2821",
    "sg:postcode":"85390",
    "sg:province":"AZ",
    "wof:name":"Goodyear",
    "wof:placetype":"venue"
},
  "geometry": {"coordinates":[-112.74069,33.986151],"type":"Point"}
}