{
  "type": "Feature",
  "properties": {
    "addr:full":"7030 E Bella Vista Dr Cave Creek AZ 85331",
    "addr:housenumber":"7030",
    "addr:postcode":"85331",
    "addr:street":"E Bella Vista Dr",
    "iso:country":"US",
    "sg:address":"7030 E Bella Vista Dr",
    "sg:city":"Cave Creek",
    "sg:classifiers":[
        {
            "category":"Restaurant",
            "type":"Food & Drink"
        }
    ],
    "sg:phone":"+1 480 488 2856",
    "sg:postcode":"85331",
    "sg:province":"AZ",
    "sg:tags":[
        "french"
    ],
    "sg:website":"www.sanssoucicavecreek.com/",
    "wof:name":"Le Sans Souci Restaurant",
    "wof:placetype":"venue"
},
  "geometry": {"coordinates":[-111.93000000000001,33.828602],"type":"Point"}
}