{
  "type": "Feature",
  "properties": {
    "addr:full":"6556 E Mary Dr Tucson AZ 85730",
    "addr:housenumber":"6556",
    "addr:postcode":"85730",
    "addr:street":"E Mary Dr",
    "iso:country":"US",
    "sg:address":"6556 E Mary Dr",
    "sg:city":"Tucson",
    "sg:classifiers":[
        {
            "category":"Building & Trades",
            "subcategory":"Plumbing",
            "type":"Services"
        }
    ],
    "sg:phone":"+1 520 624 8888",
    "sg:postcode":"85730",
    "sg:province":"AZ",
    "sg:tags":[
        "plumbing",
        "contractor"
    ],
    "wof:name":"Leak Doctor",
    "wof:placetype":"venue"
},
  "geometry": {"coordinates":[-110.850601,32.187735],"type":"Point"}
}