{
  "type": "Feature",
  "properties": {
    "iso:country":"US",
    "sg:address":"3325 W Durango St",
    "sg:city":"Phoenix",
    "sg:classifiers":[
        {
            "category":"Health Services",
            "subcategory":"Nursing And Care Facility",
            "type":"Services"
        },
        {
            "category":"Health Services",
            "subcategory":"Health Practitioner",
            "type":"Services"
        }
    ],
    "sg:phone":"+1 480 619 0930",
    "sg:postcode":"85009",
    "sg:province":"AZ",
    "sg:tags":[
        "home",
        "eldercare-home"
    ],
    "wof:name":"Maricopa County Sheriff's Medical Rescue Posse, Inc.",
    "wof:placetype":"venue"
},
  "geometry": {"coordinates":[-112.131809,33.429662],"type":"Point"}
}