{
  "type": "Feature",
  "properties": {
    "iso:country":"US",
    "sg:address":"2424 N Cll Segundo",
    "sg:city":"Huachuca City",
    "sg:classifiers":[
        {
            "category":"Utilities",
            "subcategory":"Water",
            "type":"Services"
        }
    ],
    "sg:phone":"+1 520 456 2125",
    "sg:postcode":"85616",
    "sg:province":"AZ",
    "sg:tags":[
        "company",
        "sewage"
    ],
    "wof:name":"Whetstone Water Improvement",
    "wof:placetype":"venue"
},
  "geometry": {"coordinates":[-110.348372,31.706531],"type":"Point"}
}