{
  "type": "Feature",
  "properties": {
    "iso:country":"US",
    "sg:address":"4145 N Bank St",
    "sg:city":"Kingman",
    "sg:classifiers":[
        {
            "category":"Organizations",
            "subcategory":"Religious Organization",
            "type":"Services"
        }
    ],
    "sg:phone":"+1 928 681 4673",
    "sg:postcode":"86409",
    "sg:province":"AZ",
    "sg:tags":[
        "church"
    ],
    "wof:name":"Canyon Community Church",
    "wof:placetype":"venue"
},
  "geometry": {"coordinates":[-114.011533,35.246683],"type":"Point"}
}