{
  "type": "Feature",
  "properties": {
    "iso:country":"US",
    "sg:address":"5461 E New River Rd",
    "sg:city":"Cave Creek",
    "sg:classifiers":[
        {
            "category":"Building & Trades",
            "subcategory":"Construction",
            "type":"Services"
        }
    ],
    "sg:phone":"+1 480 488 1171",
    "sg:postcode":"85331",
    "sg:province":"AZ",
    "sg:tags":[
        "contractor"
    ],
    "wof:name":"Desert Oasis Water Truck",
    "wof:placetype":"venue"
},
  "geometry": {"coordinates":[-111.966269,33.809233],"type":"Point"}
}