{
  "type": "Feature",
  "properties": {
    "iso:country":"US",
    "sg:address":"3799 N 127th Dr",
    "sg:city":"Avondale",
    "sg:classifiers":[
        {
            "category":"Building & Trades",
            "subcategory":"Locksmith",
            "type":"Services"
        }
    ],
    "sg:phone":"+1 623 687 3711",
    "sg:postcode":"85392",
    "sg:province":"AZ",
    "sg:tags":[
        "key"
    ],
    "wof:name":"23 7 A Locksmith",
    "wof:placetype":"venue"
},
  "geometry": {"coordinates":[-112.333743,33.491077],"type":"Point"}
}