{
  "type": "Feature",
  "properties": {
    "iso:country":"US",
    "sg:address":"2200 W 28th St",
    "sg:city":"Yuma",
    "sg:classifiers":[
        {
            "category":"Government",
            "subcategory":"Office",
            "type":"Public Place"
        }
    ],
    "sg:phone":"+1 928 317 4500",
    "sg:postcode":"85364",
    "sg:province":"AZ",
    "sg:tags":[
        "health"
    ],
    "wof:name":"District Columbia Government",
    "wof:placetype":"venue"
},
  "geometry": {"coordinates":[-114.646904,32.676733],"type":"Point"}
}