{
  "type": "Feature",
  "properties": {
    "iso:country":"US",
    "sg:address":"11942 N 85th Ave",
    "sg:city":"Peoria",
    "sg:classifiers":[
        {
            "category":"Local Transit",
            "type":"Transportation"
        }
    ],
    "sg:phone":"+1 623 334 3771",
    "sg:postcode":"85345",
    "sg:province":"AZ",
    "sg:tags":[
        "limousine"
    ],
    "wof:name":"A-Abbey Airport Sedan & Limo",
    "wof:placetype":"venue"
},
  "geometry": {"coordinates":[-112.242006,33.593124],"type":"Point"}
}