{
  "type": "Feature",
  "properties": {
    "iso:country":"US",
    "sg:address":"24340 N 74th Pl",
    "sg:city":"Scottsdale",
    "sg:classifiers":[
        {
            "category":"Professional",
            "subcategory":"Management & Consulting",
            "type":"Services"
        }
    ],
    "sg:phone":"+1 480 585 5343",
    "sg:postcode":"85255",
    "sg:province":"AZ",
    "sg:tags":[
        "consultant",
        "business"
    ],
    "wof:name":"Inter-American Associates",
    "wof:placetype":"venue"
},
  "geometry": {"coordinates":[-111.920618,33.707767],"type":"Point"}
}