{
  "type": "Feature",
  "properties": {
    "addr:full":"2057 S Alma School Road Suite 6 Mesa AZ 85210",
    "addr:housenumber":"2057",
    "addr:postcode":"85210",
    "addr:street":"S Alma School Road Suite 6",
    "iso:country":"US",
    "sg:address":"2057 S Alma School Road Suite 6",
    "sg:city":"Mesa",
    "sg:classifiers":[
        {
            "category":"Retail",
            "subcategory":"Laundry & Dry Cleaning",
            "type":"Services"
        }
    ],
    "sg:phone":"+1 480 820 0499",
    "sg:postcode":"85210",
    "sg:province":"AZ",
    "wof:name":"Comet 1 Hr Cleaners",
    "wof:placetype":"venue"
},
  "geometry": {"coordinates":[-111.85963700000001,33.378395],"type":"Point"}
}