{
  "type": "Feature",
  "properties": {
    "iso:country":"US",
    "sg:address":"4309 N 16th St",
    "sg:city":"Phoenix",
    "sg:classifiers":[
        {
            "category":"Professional",
            "subcategory":"Computer Services",
            "type":"Services"
        }
    ],
    "sg:phone":"+1 602 274 3686",
    "sg:postcode":"85016",
    "sg:province":"AZ",
    "sg:tags":[
        "consultant",
        "designer"
    ],
    "wof:name":"Quality Technical Svc Inc",
    "wof:placetype":"venue"
},
  "geometry": {"coordinates":[-112.047514,33.498911],"type":"Point"}
}