{
  "type": "Feature",
  "properties": {
    "iso:country":"US",
    "sg:address":"1221 S 2nd Ave",
    "sg:city":"Tucson",
    "sg:classifiers":[
        {
            "category":"Government",
            "subcategory":"Office",
            "type":"Public Place"
        }
    ],
    "sg:phone":"+1 520 620 5453",
    "sg:postcode":"85713",
    "sg:province":"AZ",
    "sg:tags":[
        "state",
        "program"
    ],
    "wof:name":"Right Of Way Encroachment Prmt",
    "wof:placetype":"venue"
},
  "geometry": {"coordinates":[-110.962262,32.206006],"type":"Point"}
}