{
  "type": "Feature",
  "properties": {
    "iso:country":"US",
    "sg:address":"5828 N Casa Blanca Dr",
    "sg:city":"Paradise Valley",
    "sg:classifiers":[
        {
            "category":"Travel",
            "subcategory":"Travel Agent",
            "type":"Entertainment"
        }
    ],
    "sg:phone":"+1 480 991 6994",
    "sg:postcode":"85253",
    "sg:province":"AZ",
    "sg:tags":[
        "tours",
        "promoter"
    ],
    "sg:website":"www.painteddesert.com",
    "wof:name":"Painted Desert Productions",
    "wof:placetype":"venue"
},
  "geometry": {"coordinates":[-111.938902,33.52339],"type":"Point"}
}