{
  "type": "Feature",
  "properties": {
    "iso:country":"US",
    "sg:address":"3311 Bright Ter",
    "sg:city":"Tucson",
    "sg:classifiers":[
        {
            "category":"Building & Trades",
            "subcategory":"Landscaping Services",
            "type":"Services"
        }
    ],
    "sg:phone":"+1 520 742 0362",
    "sg:postcode":"85741",
    "sg:province":"AZ",
    "sg:tags":[
        "landscape"
    ],
    "wof:name":"Rons Reasonable",
    "wof:placetype":"venue"
},
  "geometry": {"coordinates":[-111.035966,32.327628],"type":"Point"}
}