{
  "type": "Feature",
  "properties": {
    "iso:country":"US",
    "sg:address":"620 S 5th Ave",
    "sg:city":"Safford",
    "sg:classifiers":[
        {
            "category":"Banks & Credit Unions",
            "subcategory":"Investment Brokerage",
            "type":"Services"
        },
        {
            "category":"Banks & Credit Unions",
            "subcategory":"Financial Services",
            "type":"Services"
        }
    ],
    "sg:phone":"+1 928 428 7777",
    "sg:postcode":"85546",
    "sg:province":"AZ",
    "sg:tags":[
        "advisory",
        "planner"
    ],
    "wof:name":"Elite Financial Services",
    "wof:placetype":"venue"
},
  "geometry": {"coordinates":[-109.712473,32.833065],"type":"Point"}
}