{
  "type": "Feature",
  "properties": {
    "iso:country":"US",
    "sg:address":"4831 E 22nd St",
    "sg:city":"Tucson",
    "sg:classifiers":[
        {
            "category":"Social Services",
            "subcategory":"Child Care",
            "type":"Services"
        }
    ],
    "sg:phone":"+1 520 790 0117",
    "sg:postcode":"85711",
    "sg:province":"AZ",
    "wof:name":"Children's Center",
    "wof:placetype":"venue"
},
  "geometry": {"coordinates":[-110.884218,32.206992],"type":"Point"}
}