{
  "type": "Feature",
  "properties": {
    "iso:country":"US",
    "sg:address":"1037 E Tonto St",
    "sg:city":"Phoenix",
    "sg:classifiers":[
        {
            "category":"Manufacturing",
            "subcategory":"Tools & Machinery",
            "type":"Manufacturing & Wholesale Goods"
        },
        {
            "category":"Wholesale",
            "subcategory":"Electrical",
            "type":"Manufacturing & Wholesale Goods"
        }
    ],
    "sg:phone":"+1 602 258 1551",
    "sg:postcode":"85034",
    "sg:province":"AZ",
    "sg:tags":[
        "equipment",
        "mfg",
        "electric",
        "representative"
    ],
    "wof:name":"Kanouse-Harper & Assoc Inc",
    "wof:placetype":"venue"
},
  "geometry": {"coordinates":[-112.057187,33.437791],"type":"Point"}
}