{
  "type": "Feature",
  "properties": {
    "iso:country":"US",
    "sg:address":"4002 N 43rd Ave",
    "sg:city":"Phoenix",
    "sg:classifiers":[
        {
            "category":"Personal",
            "subcategory":"Beauty Salon",
            "type":"Services"
        }
    ],
    "sg:phone":"+1 602 278 4244",
    "sg:postcode":"85031",
    "sg:province":"AZ",
    "wof:name":"Gemenis",
    "wof:placetype":"venue"
},
  "geometry": {"coordinates":[-112.151759,33.494336],"type":"Point"}
}