{
  "type": "Feature",
  "properties": {
    "addr:full":"3275 N Mountain View Dr Prescott Valley AZ 86314",
    "addr:housenumber":"3275",
    "addr:postcode":"86314",
    "addr:street":"N Mountain View Dr",
    "iso:country":"US",
    "sg:address":"3275 N Mountain View Dr",
    "sg:city":"Prescott Valley",
    "sg:classifiers":[
        {
            "category":"Shopping",
            "subcategory":"Hobbies, Toys, & Games",
            "type":"Retail Goods"
        }
    ],
    "sg:phone":"+1 928 772 4344",
    "sg:postcode":"86314",
    "sg:province":"AZ",
    "wof:name":"Homestead Arts & Crafts",
    "wof:placetype":"venue"
},
  "geometry": {"coordinates":[-112.34671400000001,34.592141],"type":"Point"}
}