{
  "type": "Feature",
  "properties": {
    "addr:full":"6046 N 57th Ave Glendale AZ 85301",
    "addr:housenumber":"6046",
    "addr:postcode":"85301",
    "addr:street":"N 57Th Ave",
    "iso:country":"US",
    "sg:address":"6046 N 57th Ave",
    "sg:city":"Glendale",
    "sg:classifiers":[
        {
            "category":"Building & Trades",
            "subcategory":"Plumbing",
            "type":"Services"
        }
    ],
    "sg:phone":"+1 623 915 1377",
    "sg:postcode":"85301",
    "sg:province":"AZ",
    "sg:tags":[
        "specializing",
        "conditioning",
        "contractor",
        "system",
        "air"
    ],
    "wof:name":"Airtech Mechanical Inc",
    "wof:placetype":"venue"
},
  "geometry": {"coordinates":[-112.181945,33.52472],"type":"Point"}
}