{
  "type": "Feature",
  "properties": {
    "addr:full":"102 W Madison St Phoenix AZ 85003",
    "addr:housenumber":"102",
    "addr:postcode":"85003",
    "addr:street":"W Madison St",
    "iso:country":"US",
    "sg:address":"102 W Madison St",
    "sg:city":"Phoenix",
    "sg:classifiers":[
        {
            "category":"Communications",
            "type":"Services"
        }
    ],
    "sg:phone":"+1 602 253 0177",
    "sg:postcode":"85003",
    "sg:province":"AZ",
    "wof:name":"Fsh Communications",
    "wof:placetype":"venue"
},
  "geometry": {"coordinates":[-112.075183,33.446049],"type":"Point"}
}