{
  "type": "Feature",
  "properties": {
    "iso:country":"US",
    "sg:address":"260 Montezona Trl",
    "sg:city":"Sedona",
    "sg:classifiers":[
        {
            "category":"Wholesale",
            "subcategory":"Non-durable Goods",
            "type":"Manufacturing & Wholesale Goods"
        }
    ],
    "sg:phone":"+1 928 284 6880",
    "sg:postcode":"86351",
    "sg:province":"AZ",
    "wof:name":"Hummingbirds Etc Sedona",
    "wof:placetype":"venue"
},
  "geometry": {"coordinates":[-111.793458,34.789775],"type":"Point"}
}