{
  "type": "Feature",
  "properties": {
    "addr:full":"409 W Main St Payson AZ 85541",
    "addr:housenumber":"409",
    "addr:postcode":"85541",
    "addr:street":"W Main St",
    "iso:country":"US",
    "sg:address":"409 W Main St",
    "sg:city":"Payson",
    "sg:classifiers":[
        {
            "category":"Health Services",
            "subcategory":"Dentist",
            "type":"Services"
        }
    ],
    "sg:phone":"+1 928 472 8400",
    "sg:postcode":"85541",
    "sg:province":"AZ",
    "wof:name":"Mattern Thomas M DDS",
    "wof:placetype":"venue"
},
  "geometry": {"coordinates":[-111.33152800000001,34.23114],"type":"Point"}
}