{
  "type": "Feature",
  "properties": {
    "iso:country":"US",
    "sg:address":"85 E Saragosa St",
    "sg:city":"Chandler",
    "sg:classifiers":[
        {
            "category":"Social Services",
            "type":"Services"
        }
    ],
    "sg:phone":"+1 480 963 2041",
    "sg:postcode":"85225",
    "sg:province":"AZ",
    "sg:tags":[
        "organization",
        "welfare"
    ],
    "wof:name":"Salvation Army",
    "wof:placetype":"venue"
},
  "geometry": {"coordinates":[-111.83819099999999,33.294737],"type":"Point"}
}