{
  "type": "Feature",
  "properties": {
    "iso:country":"US",
    "sg:address":"47 E 1st Ave",
    "sg:city":"Mesa",
    "sg:classifiers":[
        {
            "category":"Health Services",
            "subcategory":"Chiropractor",
            "type":"Services"
        }
    ],
    "sg:phone":"+1 480 668 8780",
    "sg:postcode":"85210",
    "sg:province":"AZ",
    "sg:website":"www.hafkeychiropractic.com",
    "wof:name":"Michael Hafkey DC",
    "wof:placetype":"venue"
},
  "geometry": {"coordinates":[-111.831214,33.412845],"type":"Point"}
}