{
  "type": "Feature",
  "properties": {
    "iso:country":"US",
    "sg:address":"2402 S 19th Ave",
    "sg:city":"Phoenix",
    "sg:classifiers":[
        {
            "category":"Autos & Motor Vehicles",
            "subcategory":"Automobile Sales",
            "type":"Retail Goods"
        }
    ],
    "sg:phone":"+1 602 258 4500",
    "sg:postcode":"85009",
    "sg:province":"AZ",
    "sg:tags":[
        "parts",
        "truck"
    ],
    "sg:website":"www.aztruck.com",
    "wof:name":"Arizona Truck Center Inc",
    "wof:placetype":"venue"
},
  "geometry": {"coordinates":[-112.099863,33.425642],"type":"Point"}
}