{
  "type": "Feature",
  "properties": {
    "iso:country":"US",
    "sg:address":"10115 W Van Buren St",
    "sg:city":"Tolleson",
    "sg:classifiers":[
        {
            "category":"Building & Trades",
            "subcategory":"Construction",
            "type":"Services"
        }
    ],
    "sg:phone":"+1 623 386 2500",
    "sg:postcode":"85353",
    "sg:province":"AZ",
    "sg:tags":[
        "tile",
        "dealer"
    ],
    "wof:name":"Arizona Tile",
    "wof:placetype":"venue"
},
  "geometry": {"coordinates":[-112.275095,33.450127],"type":"Point"}
}