{
  "type": "Feature",
  "properties": {
    "addr:full":"5402 S 12th Ave Tucson AZ 85706",
    "addr:housenumber":"5402",
    "addr:postcode":"85706",
    "addr:street":"S 12Th Ave",
    "iso:country":"US",
    "sg:address":"5402 S 12th Ave",
    "sg:city":"Tucson",
    "sg:classifiers":[
        {
            "category":"Food & Beverages",
            "subcategory":"Liquor & Beverages",
            "type":"Retail Goods"
        }
    ],
    "sg:phone":"+1 520 889 0160",
    "sg:postcode":"85706",
    "sg:province":"AZ",
    "sg:tags":[
        "store"
    ],
    "wof:name":"Liquor Express II",
    "wof:placetype":"venue"
},
  "geometry": {"coordinates":[-110.97761199999999,32.153293],"type":"Point"}
}