{
  "type": "Feature",
  "properties": {
    "iso:country":"US",
    "sg:address":"9784 W Hedge Hog Pl",
    "sg:city":"Peoria",
    "sg:classifiers":[
        {
            "category":"Professional",
            "subcategory":"Detective & Security Services",
            "type":"Services"
        }
    ],
    "sg:phone":"+1 480 794 0930",
    "sg:postcode":"85383",
    "sg:province":"AZ",
    "sg:tags":[
        "inventory"
    ],
    "wof:name":"Bmd Inventory & Packing",
    "wof:placetype":"venue"
},
  "geometry": {"coordinates":[-112.269992,33.734341],"type":"Point"}
}