{
  "type": "Feature",
  "properties": {
    "addr:full":"8950 S 52nd St Ste 208 Tempe AZ 85284",
    "addr:housenumber":"8950",
    "addr:postcode":"85284",
    "addr:street":"S 52Nd St Ste 208",
    "iso:country":"US",
    "sg:address":"8950 S 52nd St Ste 208",
    "sg:city":"Tempe",
    "sg:classifiers":[
        {
            "category":"Building & Trades",
            "subcategory":"Landscaping Services",
            "type":"Services"
        },
        {
            "category":"Home & Garden",
            "subcategory":"Garden Supply",
            "type":"Retail Goods"
        }
    ],
    "sg:phone":"+1 480 785 8873",
    "sg:postcode":"85284",
    "sg:province":"AZ",
    "sg:tags":[
        "lawn",
        "sod",
        "sodding",
        "contractor",
        "landscape"
    ],
    "wof:name":"Western Sod",
    "wof:placetype":"venue"
},
  "geometry": {"coordinates":[-111.96975500000001,33.332367],"type":"Point"}
}