{
  "type": "Feature",
  "properties": {
    "iso:country":"US",
    "sg:address":"1628 W Williams Dr",
    "sg:city":"Phoenix",
    "sg:classifiers":[
        {
            "category":"Wholesale",
            "subcategory":"Apparel",
            "type":"Manufacturing & Wholesale Goods"
        }
    ],
    "sg:phone":"+1 623 209 2088",
    "sg:postcode":"85027",
    "sg:province":"AZ",
    "sg:tags":[
        "fabrics-wholesale",
        "fabric",
        "manufacturer"
    ],
    "wof:name":"Avlyn Inc",
    "wof:placetype":"venue"
},
  "geometry": {"coordinates":[-112.093355,33.69105],"type":"Point"}
}