{
  "type": "Feature",
  "properties": {
    "iso:country":"US",
    "sg:address":"560 W Centennial Blvd",
    "sg:city":"Casa Grande",
    "sg:classifiers":[
        {
            "category":"Manufacturing",
            "subcategory":"Chemicals & Compounds",
            "type":"Manufacturing & Wholesale Goods"
        }
    ],
    "sg:phone":"+1 520 421 9440",
    "sg:postcode":"85222",
    "sg:province":"AZ",
    "sg:tags":[
        "product",
        "mfg"
    ],
    "wof:name":"I V C Industrial Coatings Inc",
    "wof:placetype":"venue"
},
  "geometry": {"coordinates":[-111.757701,32.945847],"type":"Point"}
}