{
  "type": "Feature",
  "properties": {
    "iso:country":"US",
    "sg:address":"3110 N Central Ave",
    "sg:city":"Phoenix",
    "sg:classifiers":[
        {
            "category":"Restaurant",
            "type":"Food & Drink"
        }
    ],
    "sg:phone":"+1 602 266 1490",
    "sg:postcode":"85012",
    "sg:province":"AZ",
    "wof:name":"Fusilli's",
    "wof:placetype":"venue"
},
  "geometry": {"coordinates":[-112.073855,33.485136],"type":"Point"}
}