{
  "type": "Feature",
  "properties": {
    "addr:full":"2855 W. Ray Road Suite 1 Chandler AZ 85224",
    "addr:housenumber":"2855",
    "addr:postcode":"85224",
    "addr:street":"W. Ray Road Suite 1",
    "iso:country":"US",
    "sg:address":"2855 W. Ray Road Suite 1",
    "sg:city":"Chandler",
    "sg:classifiers":[
        {
            "category":"Fast Food",
            "type":"Food & Drink"
        },
        {
            "category":"Restaurant",
            "type":"Food & Drink"
        }
    ],
    "sg:phone":"+1 480 855 0411",
    "sg:postcode":"85224",
    "sg:province":"AZ",
    "sg:tags":[
        "mexican",
        "take"
    ],
    "sg:website":"www.qdoba.com/",
    "wof:name":"Qdoba Mexican Grill",
    "wof:placetype":"venue"
},
  "geometry": {"coordinates":[-111.89108,33.320289],"type":"Point"}
}