{
  "type": "Feature",
  "properties": {
    "addr:full":"1990 W Camelback Rd Phoenix AZ 85015",
    "addr:housenumber":"1990",
    "addr:postcode":"85015",
    "addr:street":"W Camelback Rd",
    "iso:country":"US",
    "sg:address":"1990 W Camelback Rd",
    "sg:city":"Phoenix",
    "sg:classifiers":[
        {
            "category":"Banks & Credit Unions",
            "subcategory":"Financial Services",
            "type":"Services"
        }
    ],
    "sg:phone":"+1 602 296 7833",
    "sg:postcode":"85015",
    "sg:province":"AZ",
    "sg:tags":[
        "card-merchant"
    ],
    "wof:name":"A And G Payment Solutions",
    "wof:placetype":"venue"
},
  "geometry": {"coordinates":[-112.102283,33.509602],"type":"Point"}
}