{
  "type": "Feature",
  "properties": {
    "addr:full":"5151 E Pima St Tucson AZ 85712",
    "addr:housenumber":"5151",
    "addr:postcode":"85712",
    "addr:street":"E Pima St",
    "iso:country":"US",
    "sg:address":"5151 E Pima St",
    "sg:city":"Tucson",
    "sg:classifiers":[
        {
            "category":"Education",
            "subcategory":"School",
            "type":"Public Place"
        }
    ],
    "sg:phone":"+1 520 232 7100",
    "sg:postcode":"85712",
    "sg:province":"AZ",
    "wof:name":"Fort Lowell Elementary School",
    "wof:placetype":"venue"
},
  "geometry": {"coordinates":[-110.882936,32.243502],"type":"Point"}
}