{
  "type": "Feature",
  "properties": {
    "iso:country":"US",
    "sg:address":"16097 N 82nd St",
    "sg:city":"Scottsdale",
    "sg:classifiers":[
        {
            "category":"Building & Trades",
            "subcategory":"Construction",
            "type":"Services"
        }
    ],
    "sg:phone":"+1 480 951 9611",
    "sg:postcode":"85260",
    "sg:province":"AZ",
    "sg:tags":[
        "contractor"
    ],
    "wof:name":"Madison Building Corp",
    "wof:placetype":"venue"
},
  "geometry": {"coordinates":[-111.903642,33.632212],"type":"Point"}
}