{
  "type": "Feature",
  "properties": {
    "iso:country":"US",
    "sg:address":"303 E Gurley St",
    "sg:city":"Prescott",
    "sg:classifiers":[
        {
            "category":"Wholesale",
            "subcategory":"Machinery & Supplies",
            "type":"Manufacturing & Wholesale Goods"
        },
        {
            "category":"Professional",
            "subcategory":"Advertising",
            "type":"Services"
        }
    ],
    "sg:phone":"+1 928 445 0099",
    "sg:postcode":"86301",
    "sg:province":"AZ",
    "sg:tags":[
        "transportation",
        "shipping",
        "equipment",
        "ar",
        "freight",
        "mailing"
    ],
    "wof:name":"UPS Store The",
    "wof:placetype":"venue"
},
  "geometry": {"coordinates":[-112.465835,34.541769],"type":"Point"}
}