{
  "type": "Feature",
  "properties": {
    "addr:full":"3711 W Fallen Leaf Ln Glendale AZ 85310",
    "addr:housenumber":"3711",
    "addr:postcode":"85310",
    "addr:street":"W Fallen Leaf Ln",
    "iso:country":"US",
    "sg:address":"3711 W Fallen Leaf Ln",
    "sg:city":"Glendale",
    "sg:classifiers":[
        {
            "category":"Shopping",
            "subcategory":"Hobbies, Toys, & Games",
            "type":"Retail Goods"
        }
    ],
    "sg:phone":"+1 623 780 8185",
    "sg:postcode":"85310",
    "sg:province":"AZ",
    "sg:tags":[
        "mail",
        "house"
    ],
    "wof:name":"Flying Scotsman Trains",
    "wof:placetype":"venue"
},
  "geometry": {"coordinates":[-112.142928,33.711367],"type":"Point"}
}