{
  "type": "Feature",
  "properties": {
    "addr:full":"3119 N Jackson Ave Tucson AZ 85719",
    "addr:housenumber":"3119",
    "addr:postcode":"85719",
    "addr:street":"N Jackson Ave",
    "iso:country":"US",
    "sg:address":"3119 N Jackson Ave",
    "sg:city":"Tucson",
    "sg:classifiers":[
        {
            "category":"Building & Trades",
            "subcategory":"Construction",
            "type":"Services"
        }
    ],
    "sg:phone":"+1 520 325 2130",
    "sg:postcode":"85719",
    "sg:province":"AZ",
    "sg:tags":[
        "general",
        "commercial",
        "contractor"
    ],
    "wof:name":"Damitio Construction Inc",
    "wof:placetype":"venue"
},
  "geometry": {"coordinates":[-110.937445,32.264544],"type":"Point"}
}