{
  "type": "Feature",
  "properties": {
    "addr:full":"5014 N 27th Ave Phoenix AZ 85017",
    "addr:housenumber":"5014",
    "addr:postcode":"85017",
    "addr:street":"N 27Th Ave",
    "iso:country":"US",
    "sg:address":"5014 N 27th Ave",
    "sg:city":"Phoenix",
    "sg:classifiers":[
        {
            "category":"Autos & Motor Vehicles",
            "subcategory":"Automobile Sales",
            "type":"Retail Goods"
        }
    ],
    "sg:phone":"+1 602 359 1000",
    "sg:postcode":"85017",
    "sg:province":"AZ",
    "sg:tags":[
        "dealers-used",
        "car",
        "used",
        "cars-wholesale"
    ],
    "wof:name":"Pre Owned Car Company",
    "wof:placetype":"venue"
},
  "geometry": {"coordinates":[-112.116985,33.509947],"type":"Point"}
}