{
  "type": "Feature",
  "properties": {
    "iso:country":"US",
    "sg:address":"1209 N Miller Rd",
    "sg:city":"Buckeye",
    "sg:classifiers":[
        {
            "category":"Health Services",
            "subcategory":"Health Practitioner",
            "type":"Services"
        }
    ],
    "sg:phone":"+1 623 386 2660",
    "sg:postcode":"85326",
    "sg:province":"AZ",
    "sg:tags":[
        "therapist",
        "physical"
    ],
    "wof:name":"Physicians Physical Thrpy Svc",
    "wof:placetype":"venue"
},
  "geometry": {"coordinates":[-112.590872,33.445214],"type":"Point"}
}