{
  "type": "Feature",
  "properties": {
    "addr:full":"14121 W Becker Ln Surprise AZ 85379",
    "addr:housenumber":"14121",
    "addr:postcode":"85379",
    "addr:street":"W Becker Ln",
    "iso:country":"US",
    "sg:address":"14121 W Becker Ln",
    "sg:city":"Surprise",
    "sg:classifiers":[
        {
            "category":"Professional",
            "subcategory":"Computer Services",
            "type":"Services"
        }
    ],
    "sg:phone":"+1 480 203 3772",
    "sg:postcode":"85379",
    "sg:province":"AZ",
    "sg:tags":[
        "design",
        "system",
        "network"
    ],
    "sg:website":"http://www.wctechservices.com",
    "wof:name":"I T Consulting",
    "wof:placetype":"venue"
},
  "geometry": {"coordinates":[-112.36451599999999,33.581185],"type":"Point"}
}