{
  "type": "Feature",
  "properties": {
    "addr:full":"5000 S Arizona Mills Cir Tempe AZ 85282",
    "addr:housenumber":"5000",
    "addr:postcode":"85282",
    "addr:street":"S Arizona Mills Cir",
    "iso:country":"US",
    "sg:address":"5000 S Arizona Mills Cir",
    "sg:city":"Tempe",
    "sg:classifiers":[
        {
            "category":"Restaurant",
            "type":"Food & Drink"
        }
    ],
    "sg:phone":"+1 480 491 9500",
    "sg:postcode":"85282",
    "sg:province":"AZ",
    "sg:tags":[
        "parlor",
        "ice",
        "cream"
    ],
    "wof:name":"Haagen-Dazs Ice Cream",
    "wof:placetype":"venue"
},
  "geometry": {"coordinates":[-111.967141,33.382202],"type":"Point"}
}