{
  "type": "Feature",
  "properties": {
    "iso:country":"US",
    "sg:address":"3822 W Muriel Dr",
    "sg:city":"Glendale",
    "sg:classifiers":[
        {
            "category":"Building & Trades",
            "subcategory":"Construction",
            "type":"Services"
        }
    ],
    "sg:phone":"+1 602 504 6140",
    "sg:postcode":"85308",
    "sg:province":"AZ",
    "sg:tags":[
        "concrete",
        "flooring",
        "contractor"
    ],
    "wof:name":"Norayr Balyan",
    "wof:placetype":"venue"
},
  "geometry": {"coordinates":[-112.141728,33.645788],"type":"Point"}
}