{
  "type": "Feature",
  "properties": {
    "iso:country":"US",
    "sg:address":"6621 N Scottsdale Rd",
    "sg:city":"Scottsdale",
    "sg:classifiers":[
        {
            "category":"Banks & Credit Unions",
            "subcategory":"Investment Brokerage",
            "type":"Services"
        },
        {
            "category":"Real Estate",
            "subcategory":"Developer",
            "type":"Services"
        }
    ],
    "sg:phone":"+1 480 367 1901",
    "sg:postcode":"85250",
    "sg:province":"AZ",
    "sg:tags":[
        "investing"
    ],
    "wof:name":"Monolith Capital Group & Rlty",
    "wof:placetype":"venue"
},
  "geometry": {"coordinates":[-111.925592,33.532661],"type":"Point"}
}