{
  "type": "Feature",
  "properties": {
    "iso:country":"US",
    "sg:address":"1701 S Ave B",
    "sg:city":"Yuma",
    "sg:classifiers":[
        {
            "category":"Restaurant",
            "type":"Food & Drink"
        }
    ],
    "sg:phone":"+1 928 783 6469",
    "sg:postcode":"85364",
    "sg:province":"AZ",
    "sg:tags":[
        "eating"
    ],
    "wof:name":"Eduardos Mexican Food",
    "wof:placetype":"venue"
},
  "geometry": {"coordinates":[-114.65038800000001,32.696787],"type":"Point"}
}