{
  "type": "Feature",
  "properties": {
    "addr:full":"1400 N 32nd St Ste I Phoenix AZ 85008",
    "addr:housenumber":"1400",
    "addr:postcode":"85008",
    "addr:street":"N 32Nd St Ste I",
    "iso:country":"US",
    "sg:address":"1400 N 32nd St Ste I",
    "sg:city":"Phoenix",
    "sg:classifiers":[
        {
            "category":"Real Estate",
            "subcategory":"Real Estate Services",
            "type":"Services"
        },
        {
            "category":"Real Estate",
            "subcategory":"Real Estate Agent",
            "type":"Services"
        }
    ],
    "sg:phone":"+1 602 231 6419",
    "sg:postcode":"85008",
    "sg:province":"AZ",
    "sg:tags":[
        "buyer",
        "management",
        "broker"
    ],
    "wof:name":"Joe Hernandez",
    "wof:placetype":"venue"
},
  "geometry": {"coordinates":[-112.01290899999999,33.46389],"type":"Point"}
}