{
  "type": "Feature",
  "properties": {
    "iso:country":"US",
    "sg:address":"10450 N 90th St",
    "sg:city":"Scottsdale",
    "sg:classifiers":[
        {
            "category":"Food & Beverages",
            "subcategory":"Bakery",
            "type":"Retail Goods"
        }
    ],
    "sg:phone":"+1 480 661 7284",
    "sg:postcode":"85258",
    "sg:province":"AZ",
    "wof:name":"Mrs Fields Original Cookies",
    "wof:placetype":"venue"
},
  "geometry": {"coordinates":[-111.88639499999999,33.581174],"type":"Point"}
}