{
  "type": "Feature",
  "properties": {
    "iso:country":"US",
    "sg:address":"1515 E Missouri Ave",
    "sg:city":"Phoenix",
    "sg:classifiers":[
        {
            "category":"Real Estate",
            "subcategory":"Real Estate Agent",
            "type":"Services"
        }
    ],
    "sg:phone":"+1 602 264 1300",
    "sg:postcode":"85014",
    "sg:province":"AZ",
    "wof:name":"Park West Realty & Management",
    "wof:placetype":"venue"
},
  "geometry": {"coordinates":[-112.047815,33.51641],"type":"Point"}
}