{
  "type": "Feature",
  "properties": {
    "iso:country":"US",
    "sg:address":"10603 N Hayden Rd",
    "sg:city":"Scottsdale",
    "sg:classifiers":[
        {
            "category":"Professional",
            "type":"Services"
        }
    ],
    "sg:phone":"+1 480 951 3115",
    "sg:postcode":"85260",
    "sg:province":"AZ",
    "sg:tags":[
        "establishment"
    ],
    "wof:name":"Comstock Records LTD",
    "wof:placetype":"venue"
},
  "geometry": {"coordinates":[-111.90864,33.584713],"type":"Point"}
}