{
  "type": "Feature",
  "properties": {
    "addr:full":"3587 W Deer Crossing Ct Tucson AZ 85745",
    "addr:housenumber":"3587",
    "addr:postcode":"85745",
    "addr:street":"W Deer Crossing Ct",
    "iso:country":"US",
    "sg:address":"3587 W Deer Crossing Ct",
    "sg:city":"Tucson",
    "sg:classifiers":[
        {
            "category":"Autos & Motor Vehicles",
            "subcategory":"Automobile Sales",
            "type":"Retail Goods"
        }
    ],
    "sg:phone":"+1 520 792 0878",
    "sg:postcode":"85745",
    "sg:province":"AZ",
    "sg:tags":[
        "used"
    ],
    "wof:name":"JMJ Auto Sales LLC",
    "wof:placetype":"venue"
},
  "geometry": {"coordinates":[-111.041977,32.211504],"type":"Point"}
}