{
  "type": "Feature",
  "properties": {
    "addr:full":"2760 N Salem Mesa AZ 85215",
    "addr:housenumber":"2760",
    "addr:postcode":"85215",
    "addr:street":"N Salem",
    "iso:country":"US",
    "sg:address":"2760 N Salem",
    "sg:city":"Mesa",
    "sg:classifiers":[
        {
            "category":"Real Estate",
            "subcategory":"Real Estate Operator",
            "type":"Services"
        }
    ],
    "sg:phone":"+1 480 981 1868",
    "sg:postcode":"85215",
    "sg:province":"AZ",
    "sg:tags":[
        "building",
        "apartment"
    ],
    "wof:name":"Oakland Apartments",
    "wof:placetype":"venue"
},
  "geometry": {"coordinates":[-111.702949,33.465755],"type":"Point"}
}