{
  "type": "Feature",
  "properties": {
    "iso:country":"US",
    "sg:address":"954 E Juanita Ave",
    "sg:city":"Gilbert",
    "sg:classifiers":[
        {
            "category":"Home & Garden",
            "subcategory":"Home Furnishings",
            "type":"Retail Goods"
        }
    ],
    "sg:phone":"+1 480 632 5634",
    "sg:postcode":"85234",
    "sg:province":"AZ",
    "sg:tags":[
        "window",
        "covering"
    ],
    "wof:name":"Lindenwood Manufacturing",
    "wof:placetype":"venue"
},
  "geometry": {"coordinates":[-111.769284,33.371006],"type":"Point"}
}