{
  "type": "Feature",
  "properties": {
    "iso:country":"US",
    "sg:address":"3144 W Lewis Ave",
    "sg:city":"Phoenix",
    "sg:classifiers":[
        {
            "category":"Building & Trades",
            "subcategory":"Electrical",
            "type":"Services"
        }
    ],
    "sg:phone":"+1 602 275 5245",
    "sg:postcode":"85009",
    "sg:province":"AZ",
    "sg:tags":[
        "electric",
        "contractor"
    ],
    "wof:name":"Inline Electrical Resources In",
    "wof:placetype":"venue"
},
  "geometry": {"coordinates":[-112.129247,33.475211],"type":"Point"}
}