{
  "type": "Feature",
  "properties": {
    "addr:full":"712 E Prince Rd Tucson AZ 85719",
    "addr:housenumber":"712",
    "addr:postcode":"85719",
    "addr:street":"E Prince Rd",
    "iso:country":"US",
    "sg:address":"712 E Prince Rd",
    "sg:city":"Tucson",
    "sg:classifiers":[
        {
            "category":"Personal",
            "subcategory":"Barber",
            "type":"Services"
        }
    ],
    "sg:phone":"+1 520 888 2464",
    "sg:postcode":"85719",
    "sg:province":"AZ",
    "wof:name":"J J's Barber Shop",
    "wof:placetype":"venue"
},
  "geometry": {"coordinates":[-110.96003899999999,32.271994],"type":"Point"}
}