{
  "type": "Feature",
  "properties": {
    "iso:country":"US",
    "sg:address":"20249 N 67th Ave",
    "sg:city":"Glendale",
    "sg:classifiers":[
        {
            "category":"Coffee & Tea",
            "type":"Food & Drink"
        }
    ],
    "sg:menulink":"http://www.allmenus.com/az/deer-valley/108328-starbucks-coffee/menu/",
    "sg:phone":"+1 623 362 9288",
    "sg:postcode":"85308",
    "sg:province":"AZ",
    "sg:tags":[
        "american"
    ],
    "wof:name":"Starbucks Coffee",
    "wof:placetype":"venue"
},
  "geometry": {"coordinates":[-112.20291899999999,33.669099],"type":"Point"}
}