{
  "type": "Feature",
  "properties": {
    "iso:country":"US",
    "sg:address":"4609 S 12th Ave",
    "sg:city":"Tucson",
    "sg:classifiers":[
        {
            "category":"Health Services",
            "subcategory":"Doctor",
            "type":"Services"
        }
    ],
    "sg:phone":"+1 520 889 9694",
    "sg:postcode":"85714",
    "sg:province":"AZ",
    "sg:tags":[
        "physician",
        "surgeon"
    ],
    "wof:name":"Valdez Family Clinic",
    "wof:placetype":"venue"
},
  "geometry": {"coordinates":[-110.97744400000001,32.166904],"type":"Point"}
}