{
  "type": "Feature",
  "properties": {
    "iso:country":"US",
    "sg:address":"7645 E Carol Way",
    "sg:city":"Scottsdale",
    "sg:classifiers":[
        {
            "category":"Building & Trades",
            "subcategory":"Construction",
            "type":"Services"
        }
    ],
    "sg:phone":"+1 480 596 8689",
    "sg:postcode":"85260",
    "sg:province":"AZ",
    "sg:tags":[
        "skylight",
        "roof",
        "contractor"
    ],
    "wof:name":"Sky-Met Inc",
    "wof:placetype":"venue"
},
  "geometry": {"coordinates":[-111.91485,33.598546],"type":"Point"}
}