{
  "type": "Feature",
  "properties": {
    "addr:full":"6845 W Cameron Dr Peoria AZ 85345",
    "addr:housenumber":"6845",
    "addr:postcode":"85345",
    "addr:street":"W Cameron Dr",
    "iso:country":"US",
    "sg:address":"6845 W Cameron Dr",
    "sg:city":"Peoria",
    "sg:classifiers":[
        {
            "category":"Building & Trades",
            "subcategory":"Construction",
            "type":"Services"
        }
    ],
    "sg:phone":"+1 623 322 9585",
    "sg:postcode":"85345",
    "sg:province":"AZ",
    "sg:tags":[
        "contractor"
    ],
    "wof:name":"Cooks Commercial Glazing",
    "wof:placetype":"venue"
},
  "geometry": {"coordinates":[-112.20591400000001,33.589597],"type":"Point"}
}