{
  "type": "Feature",
  "properties": {
    "iso:country":"US",
    "sg:address":"1846 W Rose Ln",
    "sg:city":"Phoenix",
    "sg:classifiers":[
        {
            "category":"Professional",
            "subcategory":"Art Services",
            "type":"Services"
        }
    ],
    "sg:phone":"+1 602 249 1781",
    "sg:postcode":"85015",
    "sg:province":"AZ",
    "sg:tags":[
        "photographer"
    ],
    "wof:name":"Photographs By Saddler",
    "wof:placetype":"venue"
},
  "geometry": {"coordinates":[-112.099427,33.527827],"type":"Point"}
}