{
  "type": "Feature",
  "properties": {
    "addr:full":"1440 S Country Club Drive Mesa AZ 85210",
    "addr:housenumber":"1440",
    "addr:postcode":"85210",
    "addr:street":"S Country Club Drive",
    "iso:country":"US",
    "sg:address":"1440 S Country Club Drive",
    "sg:city":"Mesa",
    "sg:classifiers":[
        {
            "category":"Health Services",
            "subcategory":"Doctor",
            "type":"Services"
        }
    ],
    "sg:phone":"+1 480 890 2273",
    "sg:postcode":"85210",
    "sg:province":"AZ",
    "wof:name":"Wee Care Family Clinic Corporation",
    "wof:placetype":"venue"
},
  "geometry": {"coordinates":[-111.84016699999999,33.388945],"type":"Point"}
}