{
  "type": "Feature",
  "properties": {
    "iso:country":"US",
    "sg:address":"4135 W Thomas Rd",
    "sg:city":"Phoenix",
    "sg:classifiers":[
        {
            "category":"Education",
            "subcategory":"School",
            "type":"Public Place"
        }
    ],
    "sg:phone":"+1 602 484 4123",
    "sg:postcode":"85019",
    "sg:province":"AZ",
    "wof:name":"Welcome Center",
    "wof:placetype":"venue"
},
  "geometry": {"coordinates":[-112.146866,33.480591],"type":"Point"}
}