{
  "type": "Feature",
  "properties": {
    "addr:full":"525 S 1st St Phoenix AZ 85004",
    "addr:housenumber":"525",
    "addr:postcode":"85004",
    "addr:street":"S 1St St",
    "iso:country":"US",
    "sg:address":"525 S 1st St",
    "sg:city":"Phoenix",
    "sg:classifiers":[
        {
            "category":"Arts & Performance",
            "subcategory":"Theater",
            "type":"Entertainment"
        }
    ],
    "sg:phone":"+1 602 253 8188",
    "sg:postcode":"85004",
    "sg:province":"AZ",
    "sg:tags":[
        "theatres-concert",
        "venue",
        "hall",
        "theatre"
    ],
    "wof:name":"Valley Youth Theatre",
    "wof:placetype":"venue"
},
  "geometry": {"coordinates":[-112.07253300000001,33.442952],"type":"Point"}
}