{
  "type": "Feature",
  "properties": {
    "iso:country":"US",
    "sg:address":"3451 E Encanto St",
    "sg:city":"Mesa",
    "sg:classifiers":[
        {
            "category":"Real Estate",
            "subcategory":"Real Estate Agent",
            "type":"Services"
        }
    ],
    "sg:phone":"+1 480 924 0633",
    "sg:postcode":"85213",
    "sg:province":"AZ",
    "wof:name":"Gouz Properties",
    "wof:placetype":"venue"
},
  "geometry": {"coordinates":[-111.756691,33.43319],"type":"Point"}
}