{
  "type": "Feature",
  "properties": {
    "iso:country":"US",
    "sg:address":"245 S Plumer Ave",
    "sg:city":"Tucson",
    "sg:classifiers":[
        {
            "category":"Wholesale",
            "subcategory":"Machinery & Supplies",
            "type":"Manufacturing & Wholesale Goods"
        }
    ],
    "sg:phone":"+1 520 798 3353",
    "sg:postcode":"85719",
    "sg:province":"AZ",
    "sg:tags":[
        "salon",
        "beauty"
    ],
    "wof:name":"Color Design Systems",
    "wof:placetype":"venue"
},
  "geometry": {"coordinates":[-110.939385,32.219361],"type":"Point"}
}