{
  "type": "Feature",
  "properties": {
    "addr:full":"4024 N 67th Avenue Phoenix AZ 85033",
    "addr:housenumber":"4024",
    "addr:postcode":"85033",
    "addr:street":"N 67Th Avenue",
    "iso:country":"US",
    "sg:address":"4024 N 67th Avenue",
    "sg:city":"Phoenix",
    "sg:classifiers":[
        {
            "category":"Personal",
            "type":"Services"
        },
        {
            "category":"Restaurant",
            "type":"Food & Drink"
        }
    ],
    "sg:phone":"+1 623 846 8000",
    "sg:postcode":"85033",
    "sg:province":"AZ",
    "sg:tags":[
        "party",
        "planning",
        "event",
        "pizza"
    ],
    "sg:website":"http://www.peterpiperpizza.com/",
    "wof:name":"Peter Piper Pizza",
    "wof:placetype":"venue"
},
  "geometry": {"coordinates":[-112.203091,33.494054],"type":"Point"}
}