{
  "type": "Feature",
  "properties": {
    "iso:country":"US",
    "sg:address":"3807 N 7th St",
    "sg:city":"Phoenix",
    "sg:classifiers":[
        {
            "category":"Wholesale",
            "subcategory":"Groceries",
            "type":"Manufacturing & Wholesale Goods"
        }
    ],
    "sg:phone":"+1 602 212 1111",
    "sg:postcode":"85014",
    "sg:province":"AZ",
    "sg:tags":[
        "mfg",
        "food",
        "broker",
        "general",
        "preparation",
        "frozen"
    ],
    "sg:website":"www.acosta.com",
    "wof:name":"Acosta Sales & Marketing Co",
    "wof:placetype":"venue"
},
  "geometry": {"coordinates":[-112.06497,33.492759],"type":"Point"}
}