{
  "type": "Feature",
  "properties": {
    "addr:full":"9000 E Speedway Blvd Tucson AZ 85710",
    "addr:housenumber":"9000",
    "addr:postcode":"85710",
    "addr:street":"E Speedway Blvd",
    "iso:country":"US",
    "sg:address":"9000 E Speedway Blvd",
    "sg:city":"Tucson",
    "sg:classifiers":[
        {
            "category":"Real Estate",
            "subcategory":"Real Estate Operator",
            "type":"Services"
        }
    ],
    "sg:phone":"+1 877 528 4885",
    "sg:postcode":"85710",
    "sg:province":"AZ",
    "sg:tags":[
        "apartment"
    ],
    "sg:website":"http://local.ingenio.com/Listings/Details.aspx?NUM=a%3a10248703%3a13%3a4859924%3a14%3a0%3a7",
    "wof:name":"Brittany Court - HSL",
    "wof:placetype":"venue"
},
  "geometry": {"coordinates":[-110.800545,32.235481],"type":"Point"}
}