{
  "type": "Feature",
  "properties": {
    "addr:full":"706 N Mazatzal Cir Payson AZ 85541",
    "addr:housenumber":"706",
    "addr:postcode":"85541",
    "addr:street":"N Mazatzal Cir",
    "iso:country":"US",
    "sg:address":"706 N Mazatzal Cir",
    "sg:city":"Payson",
    "sg:classifiers":[
        {
            "category":"Building & Trades",
            "subcategory":"Construction",
            "type":"Services"
        }
    ],
    "sg:phone":"+1 928 468 6484",
    "sg:postcode":"85541",
    "sg:province":"AZ",
    "sg:tags":[
        "general",
        "contractor"
    ],
    "wof:name":"Karik Construction",
    "wof:placetype":"venue"
},
  "geometry": {"coordinates":[-111.32435099999999,34.249227],"type":"Point"}
}