{
  "type": "Feature",
  "properties": {
    "iso:country":"US",
    "sg:address":"3858 W Whitton Ave",
    "sg:city":"Phoenix",
    "sg:classifiers":[
        {
            "category":"Wholesale",
            "subcategory":"Electrical",
            "type":"Manufacturing & Wholesale Goods"
        }
    ],
    "sg:phone":"+1 602 442 1857",
    "sg:postcode":"85019",
    "sg:province":"AZ",
    "sg:tags":[
        "electronic"
    ],
    "wof:name":"Ucom Supply LLC",
    "wof:placetype":"venue"
},
  "geometry": {"coordinates":[-112.14196699999999,33.490757],"type":"Point"}
}