{
  "type": "Feature",
  "properties": {
    "iso:country":"US",
    "sg:address":"802 W El Caminito Dr",
    "sg:city":"Phoenix",
    "sg:classifiers":[
        {
            "category":"Farming",
            "subcategory":"Farm",
            "type":"Manufacturing & Wholesale Goods"
        }
    ],
    "sg:phone":"+1 602 943 3128",
    "sg:postcode":"85021",
    "sg:province":"AZ",
    "wof:name":"Lazy R C Ranch",
    "wof:placetype":"venue"
},
  "geometry": {"coordinates":[-112.083812,33.558891],"type":"Point"}
}