{
  "type": "Feature",
  "properties": {
    "addr:full":"15033 N Cave Creek Rd Phoenix AZ 85032",
    "addr:housenumber":"15033",
    "addr:postcode":"85032",
    "addr:street":"N Cave Creek Rd",
    "iso:country":"US",
    "sg:address":"15033 N Cave Creek Rd",
    "sg:city":"Phoenix",
    "sg:classifiers":[
        {
            "category":"Retail",
            "subcategory":"Repair Shop",
            "type":"Services"
        }
    ],
    "sg:phone":"+1 602 404 7876",
    "sg:postcode":"85032",
    "sg:province":"AZ",
    "sg:tags":[
        "upholsterer"
    ],
    "wof:name":"Home Upholstery",
    "wof:placetype":"venue"
},
  "geometry": {"coordinates":[-112.03062799999999,33.625953],"type":"Point"}
}