{
  "type": "Feature",
  "properties": {
    "addr:full":"852 W Kroll Ave Gilbert AZ 85233",
    "addr:housenumber":"852",
    "addr:postcode":"85233",
    "addr:street":"W Kroll Ave",
    "iso:country":"US",
    "sg:address":"852 W Kroll Ave",
    "sg:city":"Gilbert",
    "sg:classifiers":[
        {
            "category":"Building & Trades",
            "subcategory":"Construction",
            "type":"Services"
        }
    ],
    "sg:phone":"+1 480 703 0638",
    "sg:postcode":"85233",
    "sg:province":"AZ",
    "sg:tags":[
        "contractor"
    ],
    "wof:name":"Messerly Drywall",
    "wof:placetype":"venue"
},
  "geometry": {"coordinates":[-111.807067,33.360914],"type":"Point"}
}