{
  "type": "Feature",
  "properties": {
    "iso:country":"US",
    "sg:address":"4501 E Grant Rd",
    "sg:city":"Tucson",
    "sg:classifiers":[
        {
            "category":"Professional",
            "subcategory":"Lawyer & Legal Services",
            "type":"Services"
        }
    ],
    "sg:phone":"+1 520 795 2363",
    "sg:postcode":"85712",
    "sg:province":"AZ",
    "sg:tags":[
        "attorney"
    ],
    "wof:name":"Charles R Hamm Law Offices",
    "wof:placetype":"venue"
},
  "geometry": {"coordinates":[-110.895798,32.250628],"type":"Point"}
}