{
  "type": "Feature",
  "properties": {
    "addr:full":"964 E Fry Blvd Sierra Vista AZ 85635",
    "addr:housenumber":"964",
    "addr:postcode":"85635",
    "addr:street":"E Fry Blvd",
    "iso:country":"US",
    "sg:address":"964 E Fry Blvd",
    "sg:city":"Sierra Vista",
    "sg:classifiers":[
        {
            "category":"Shopping",
            "subcategory":"Clothing, Apparel, & Fashions",
            "type":"Retail Goods"
        }
    ],
    "sg:phone":"+1 520 458 9133",
    "sg:postcode":"85635",
    "sg:province":"AZ",
    "sg:tags":[
        "navy",
        "army"
    ],
    "wof:name":"M I Store",
    "wof:placetype":"venue"
},
  "geometry": {"coordinates":[-110.28971900000001,31.554565],"type":"Point"}
}