{
  "type": "Feature",
  "properties": {
    "iso:country":"US",
    "sg:address":"5133 N Central Ave Ste 20",
    "sg:city":"Phoenix",
    "sg:classifiers":[
        {
            "category":"Real Estate",
            "subcategory":"Developer",
            "type":"Services"
        }
    ],
    "sg:phone":"+1 602 274 0049",
    "sg:postcode":"85012",
    "sg:province":"AZ",
    "sg:tags":[
        "investing"
    ],
    "wof:name":"Herro Investment Partnership",
    "wof:placetype":"venue"
},
  "geometry": {"coordinates":[-112.073738,33.512032],"type":"Point"}
}