{
  "type": "Feature",
  "properties": {
    "addr:full":"2050 N Alma School Rd Chandler AZ 85224",
    "addr:housenumber":"2050",
    "addr:postcode":"85224",
    "addr:street":"N Alma School Rd",
    "iso:country":"US",
    "sg:address":"2050 N Alma School Rd",
    "sg:city":"Chandler",
    "sg:classifiers":[
        {
            "category":"Personal",
            "subcategory":"Beauty Salon",
            "type":"Services"
        }
    ],
    "sg:phone":"+1 480 786 0550",
    "sg:postcode":"85224",
    "sg:province":"AZ",
    "sg:tags":[
        "spa"
    ],
    "wof:name":"Chandlers Hair Care",
    "wof:placetype":"venue"
},
  "geometry": {"coordinates":[-111.859183,33.335708],"type":"Point"}
}