{
  "type": "Feature",
  "properties": {
    "iso:country":"US",
    "sg:address":"1921 S Alma School Road",
    "sg:city":"Mesa",
    "sg:classifiers":[
        {
            "category":"Professional",
            "subcategory":"Employment Agencies",
            "type":"Services"
        }
    ],
    "sg:phone":"+1 480 491 9557",
    "sg:postcode":"85210",
    "sg:province":"AZ",
    "wof:name":"Modern Engineering Service Company",
    "wof:placetype":"venue"
},
  "geometry": {"coordinates":[-111.859494,33.380215],"type":"Point"}
}