{
  "type": "Feature",
  "properties": {
    "iso:country":"US",
    "sg:address":"655 W Elliot Rd",
    "sg:city":"Tempe",
    "sg:classifiers":[
        {
            "category":"Building & Trades",
            "subcategory":"Construction",
            "type":"Services"
        }
    ],
    "sg:phone":"+1 480 940 5189",
    "sg:postcode":"85284",
    "sg:province":"AZ",
    "sg:tags":[
        "general",
        "contractor"
    ],
    "wof:name":"Contractors Wardrobe",
    "wof:placetype":"venue"
},
  "geometry": {"coordinates":[-111.953305,33.349089],"type":"Point"}
}