{
  "type": "Feature",
  "properties": {
    "iso:country":"US",
    "sg:address":"5125 E Madison St",
    "sg:city":"Phoenix",
    "sg:classifiers":[
        {
            "category":"Wholesale",
            "subcategory":"Furniture",
            "type":"Manufacturing & Wholesale Goods"
        },
        {
            "category":"Home & Garden",
            "subcategory":"Furniture",
            "type":"Retail Goods"
        }
    ],
    "sg:phone":"+1 602 244 0434",
    "sg:postcode":"85034",
    "sg:province":"AZ",
    "sg:tags":[
        "store",
        "furniture-wholesale",
        "manufacturer"
    ],
    "wof:name":"Thornwood Furniture Mfg",
    "wof:placetype":"venue"
},
  "geometry": {"coordinates":[-111.97161,33.444616],"type":"Point"}
}