{
  "type": "Feature",
  "properties": {
    "iso:country":"US",
    "sg:address":"4232 E Bell Rd",
    "sg:city":"Phoenix",
    "sg:classifiers":[
        {
            "category":"Retail",
            "subcategory":"Laundry & Dry Cleaning",
            "type":"Services"
        }
    ],
    "sg:phone":"+1 602 486 0468",
    "sg:postcode":"85032",
    "sg:province":"AZ",
    "sg:tags":[
        "cleaner",
        "commercial"
    ],
    "wof:name":"Embassy Cleaners, Inc",
    "wof:placetype":"venue"
},
  "geometry": {"coordinates":[-111.990143,33.640739],"type":"Point"}
}