{
  "type": "Feature",
  "properties": {
    "addr:full":"2050 S Roslyn Mesa AZ 85209",
    "addr:housenumber":"2050",
    "addr:postcode":"85209",
    "addr:street":"S Roslyn",
    "iso:country":"US",
    "sg:address":"2050 S Roslyn",
    "sg:city":"Mesa",
    "sg:classifiers":[
        {
            "category":"Restaurant",
            "type":"Food & Drink"
        }
    ],
    "sg:phone":"+1 480 580 5290",
    "sg:postcode":"85209",
    "sg:province":"AZ",
    "sg:tags":[
        "parlor",
        "ice",
        "cream"
    ],
    "wof:name":"Creative Ice Creams Special",
    "wof:placetype":"venue"
},
  "geometry": {"coordinates":[-111.684251,33.378508],"type":"Point"}
}