{
  "type": "Feature",
  "properties": {
    "iso:country":"US",
    "sg:address":"1174 N Florence Dr",
    "sg:city":"Chandler",
    "sg:classifiers":[
        {
            "category":"Building & Trades",
            "subcategory":"Construction",
            "type":"Services"
        }
    ],
    "sg:phone":"+1 480 726 7201",
    "sg:postcode":"85226",
    "sg:province":"AZ",
    "sg:tags":[
        "house"
    ],
    "wof:name":"Quality Improvement Medical SE",
    "wof:placetype":"venue"
},
  "geometry": {"coordinates":[-111.899168,33.323017],"type":"Point"}
}