{
  "type": "Feature",
  "properties": {
    "iso:country":"US",
    "sg:address":"7430 E Stetson Dr Ste 100",
    "sg:city":"Scottsdale",
    "sg:classifiers":[
        {
            "category":"Banks & Credit Unions",
            "subcategory":"Financial Services",
            "type":"Services"
        }
    ],
    "sg:phone":"+1 800 383 2109",
    "sg:postcode":"85251",
    "sg:province":"AZ",
    "sg:tags":[
        "card-merchant"
    ],
    "sg:website":"http://www.merchant-processor.com/423",
    "wof:name":"ADVANCED MERCHANT CAPITAL",
    "wof:placetype":"venue"
},
  "geometry": {"coordinates":[-111.92097200000001,33.499558],"type":"Point"}
}