{
  "type": "Feature",
  "properties": {
    "iso:country":"US",
    "sg:address":"4130 N Goldwater Blvd",
    "sg:city":"Scottsdale",
    "sg:classifiers":[
        {
            "category":"Personal",
            "type":"Services"
        }
    ],
    "sg:phone":"+1 480 945 3080",
    "sg:postcode":"85251",
    "sg:province":"AZ",
    "sg:tags":[
        "therapist",
        "massage"
    ],
    "wof:name":"Body Zone Massage Therapy",
    "wof:placetype":"venue"
},
  "geometry": {"coordinates":[-111.93047,33.495857],"type":"Point"}
}