{
  "type": "Feature",
  "properties": {
    "iso:country":"US",
    "sg:address":"310 N Wilmot Rd",
    "sg:city":"Tucson",
    "sg:classifiers":[
        {
            "category":"Health Services",
            "subcategory":"Doctor",
            "type":"Services"
        }
    ],
    "sg:phone":"+1 520 325 0865",
    "sg:postcode":"85711",
    "sg:province":"AZ",
    "sg:tags":[
        "physician",
        "surgeon"
    ],
    "wof:name":"Gregory J Mac Iulla MD",
    "wof:placetype":"venue"
},
  "geometry": {"coordinates":[-110.857854,32.225561],"type":"Point"}
}