{
  "type": "Feature",
  "properties": {
    "iso:country":"US",
    "sg:address":"6202 S 16th Pl",
    "sg:city":"Phoenix",
    "sg:phone":"+1 602 243 1052",
    "sg:postcode":"85042",
    "sg:province":"AZ",
    "sg:tags":[
        "vending",
        "broker"
    ],
    "wof:name":"Ryan's Vending",
    "wof:placetype":"venue"
},
  "geometry": {"coordinates":[-112.046519,33.389409],"type":"Point"}
}