{
  "type": "Feature",
  "properties": {
    "iso:country":"US",
    "sg:address":"2245 W University Dr",
    "sg:city":"Tempe",
    "sg:classifiers":[
        {
            "category":"Shopping",
            "subcategory":"Discount & Variety Stores",
            "type":"Retail Goods"
        }
    ],
    "sg:phone":"+1 480 905 5657",
    "sg:postcode":"85281",
    "sg:province":"AZ",
    "sg:tags":[
        "post",
        "trading"
    ],
    "wof:name":"Sonora Trading Co",
    "wof:placetype":"venue"
},
  "geometry": {"coordinates":[-111.972351,33.421864],"type":"Point"}
}