{
  "type": "Feature",
  "properties": {
    "iso:country":"US",
    "sg:address":"1711 W University Dr # 153",
    "sg:city":"Tempe",
    "sg:classifiers":[
        {
            "category":"Professional",
            "subcategory":"Computer Services",
            "type":"Services"
        }
    ],
    "sg:phone":"+1 480 776 6866",
    "sg:postcode":"85281",
    "sg:province":"AZ",
    "sg:tags":[
        "technical",
        "assistance",
        "support"
    ],
    "wof:name":"Sabino Facility Solution",
    "wof:placetype":"venue"
},
  "geometry": {"coordinates":[-111.966331,33.42194],"type":"Point"}
}