{
  "type": "Feature",
  "properties": {
    "iso:country":"US",
    "sg:address":"15030 N 53rd St",
    "sg:city":"Scottsdale",
    "sg:classifiers":[
        {
            "category":"Building & Trades",
            "subcategory":"Landscaping Services",
            "type":"Services"
        }
    ],
    "sg:phone":"+1 602 996 1229",
    "sg:postcode":"85254",
    "sg:province":"AZ",
    "sg:tags":[
        "landscape",
        "contractor"
    ],
    "wof:name":"DCL Inc",
    "wof:placetype":"venue"
},
  "geometry": {"coordinates":[-111.967415,33.623353],"type":"Point"}
}