{
  "type": "Feature",
  "properties": {
    "iso:country":"US",
    "sg:address":"3626 W Folley St",
    "sg:city":"Chandler",
    "sg:classifiers":[
        {
            "category":"Retail",
            "subcategory":"Portrait Studio",
            "type":"Services"
        }
    ],
    "sg:phone":"+1 480 963 1596",
    "sg:postcode":"85226",
    "sg:province":"AZ",
    "sg:tags":[
        "rental",
        "photographic",
        "darkroom"
    ],
    "wof:name":"Joseph Moss",
    "wof:placetype":"venue"
},
  "geometry": {"coordinates":[-111.905141,33.298021],"type":"Point"}
}