{
  "type": "Feature",
  "properties": {
    "iso:country":"US",
    "sg:address":"4310 N Flowing Wells Rd",
    "sg:city":"Tucson",
    "sg:classifiers":[
        {
            "category":"Autos & Motor Vehicles",
            "subcategory":"Recreational Vehicle Sales",
            "type":"Retail Goods"
        }
    ],
    "sg:phone":"+1 520 293 1010",
    "sg:postcode":"85705",
    "sg:province":"AZ",
    "wof:name":"R V Nelson",
    "wof:placetype":"venue"
},
  "geometry": {"coordinates":[-110.994977,32.28605],"type":"Point"}
}