{
  "type": "Feature",
  "properties": {
    "iso:country":"US",
    "sg:address":"4201 N 24th St",
    "sg:city":"Phoenix",
    "sg:classifiers":[
        {
            "category":"Building & Trades",
            "subcategory":"Construction",
            "type":"Services"
        }
    ],
    "sg:phone":"+1 602 956 4500",
    "sg:postcode":"85016",
    "sg:province":"AZ",
    "wof:name":"CDM Constructors Inc",
    "wof:placetype":"venue"
},
  "geometry": {"coordinates":[-112.03012,33.495007],"type":"Point"}
}