{
  "type": "Feature",
  "properties": {
    "iso:country":"US",
    "sg:address":"2810 S 24th St",
    "sg:city":"Phoenix",
    "sg:classifiers":[
        {
            "category":"Wholesale",
            "subcategory":"Hardware",
            "type":"Manufacturing & Wholesale Goods"
        }
    ],
    "sg:phone":"+1 602 258 5835",
    "sg:postcode":"85034",
    "sg:province":"AZ",
    "sg:tags":[
        "builder"
    ],
    "sg:website":"www.ingersollrand.com",
    "wof:name":"Ir Security & Safety",
    "wof:placetype":"venue"
},
  "geometry": {"coordinates":[-112.030439,33.421725],"type":"Point"}
}