{
  "type": "Feature",
  "properties": {
    "iso:country":"US",
    "sg:address":"7111 N 77th Ave",
    "sg:city":"Glendale",
    "sg:classifiers":[
        {
            "category":"Wholesale",
            "subcategory":"Machinery & Supplies",
            "type":"Manufacturing & Wholesale Goods"
        }
    ],
    "sg:phone":"+1 623 939 1994",
    "sg:postcode":"85303",
    "sg:province":"AZ",
    "sg:tags":[
        "equipment",
        "establishment"
    ],
    "wof:name":"Robert E Kittredge",
    "wof:placetype":"venue"
},
  "geometry": {"coordinates":[-112.224201,33.539349],"type":"Point"}
}