{
  "type": "Feature",
  "properties": {
    "addr:full":"555 W Gold Hill Rd Nogales AZ 85621",
    "addr:housenumber":"555",
    "addr:postcode":"85621",
    "addr:street":"W Gold Hill Rd",
    "iso:country":"US",
    "sg:address":"555 W Gold Hill Rd",
    "sg:city":"Nogales",
    "sg:classifiers":[
        {
            "category":"Food & Beverages",
            "subcategory":"Fruits & Vegetables",
            "type":"Retail Goods"
        }
    ],
    "sg:phone":"+1 520 281 0918",
    "sg:postcode":"85621",
    "sg:province":"AZ",
    "sg:tags":[
        "produce"
    ],
    "wof:name":"Ocotillo Produce",
    "wof:placetype":"venue"
},
  "geometry": {"coordinates":[-110.94684599999999,31.384082],"type":"Point"}
}