{
  "type": "Feature",
  "properties": {
    "iso:country":"US",
    "sg:address":"101 E Allen St",
    "sg:city":"Tombstone",
    "sg:classifiers":[
        {
            "category":"Banks & Credit Unions",
            "subcategory":"Bank",
            "type":"Services"
        }
    ],
    "sg:phone":"+1 520 457 3551",
    "sg:postcode":"85638",
    "sg:province":"AZ",
    "wof:name":"Tombstone Federal Credit Union",
    "wof:placetype":"venue"
},
  "geometry": {"coordinates":[-110.070406,31.713904],"type":"Point"}
}