{
  "type": "Feature",
  "properties": {
    "iso:country":"US",
    "sg:address":"810 E Hammond Ln",
    "sg:city":"Phoenix",
    "sg:classifiers":[
        {
            "category":"Utilities",
            "subcategory":"Telephone",
            "type":"Services"
        },
        {
            "category":"Communications",
            "type":"Services"
        }
    ],
    "sg:phone":"+1 602 431 9399",
    "sg:postcode":"85034",
    "sg:province":"AZ",
    "sg:tags":[
        "data"
    ],
    "sg:website":"http://www.teltechnetworks.com",
    "wof:name":"Teltech Networks",
    "wof:placetype":"venue"
},
  "geometry": {"coordinates":[-112.062735,33.425063],"type":"Point"}
}