{
  "type": "Feature",
  "properties": {
    "iso:country":"US",
    "sg:address":"320 W Alturas St",
    "sg:city":"Tucson",
    "sg:classifiers":[
        {
            "category":"Professional",
            "subcategory":"Engineering",
            "type":"Services"
        }
    ],
    "sg:phone":"+1 520 770 1318",
    "sg:postcode":"85705",
    "sg:province":"AZ",
    "sg:tags":[
        "engineer"
    ],
    "wof:name":"Mc Carty Engineering Inc",
    "wof:placetype":"venue"
},
  "geometry": {"coordinates":[-110.977707,32.252189],"type":"Point"}
}