{
  "type": "Feature",
  "properties": {
    "iso:country":"US",
    "sg:address":"711 W University Dr",
    "sg:city":"Tempe",
    "sg:classifiers":[
        {
            "category":"Community Center",
            "subcategory":"Youth",
            "type":"Public Place"
        },
        {
            "category":"Organizations",
            "subcategory":"Religious Organization",
            "type":"Services"
        }
    ],
    "sg:phone":"+1 480 966 9850",
    "sg:postcode":"85281",
    "sg:province":"AZ",
    "sg:website":"http://www.youtharisena.org",
    "wof:name":"Youth Arise North America",
    "wof:placetype":"venue"
},
  "geometry": {"coordinates":[-111.948156,33.421891],"type":"Point"}
}