{
  "type": "Feature",
  "properties": {
    "addr:full":"2563 E Broadway Blvd Tucson AZ 85716",
    "addr:housenumber":"2563",
    "addr:postcode":"85716",
    "addr:street":"E Broadway Blvd",
    "iso:country":"US",
    "sg:address":"2563 E Broadway Blvd",
    "sg:city":"Tucson",
    "sg:classifiers":[
        {
            "category":"Personal",
            "subcategory":"Beauty Salon",
            "type":"Services"
        }
    ],
    "sg:phone":"+1 520 326 7787",
    "sg:postcode":"85716",
    "sg:province":"AZ",
    "sg:tags":[
        "manicuring"
    ],
    "wof:name":"Long Nails",
    "wof:placetype":"venue"
},
  "geometry": {"coordinates":[-110.931164,32.221589],"type":"Point"}
}