{
  "type": "Feature",
  "properties": {
    "iso:country":"US",
    "sg:address":"7375 W Buckeye Rd",
    "sg:city":"Phoenix",
    "sg:classifiers":[
        {
            "category":"Building & Trades",
            "subcategory":"Locksmith",
            "type":"Services"
        }
    ],
    "sg:phone":"+1 602 412 1419",
    "sg:postcode":"85043",
    "sg:province":"AZ",
    "sg:tags":[
        "key"
    ],
    "wof:name":"A-1 Locksmith",
    "wof:placetype":"venue"
},
  "geometry": {"coordinates":[-112.219425,33.437008],"type":"Point"}
}