{
  "type": "Feature",
  "properties": {
    "addr:full":"2411 W Northern Ave Ste 100 Phoenix AZ 85021",
    "addr:housenumber":"2411",
    "addr:postcode":"85021",
    "addr:street":"W Northern Ave Ste 100",
    "iso:country":"US",
    "sg:address":"2411 W Northern Ave Ste 100",
    "sg:city":"Phoenix",
    "sg:classifiers":[
        {
            "category":"Professional",
            "subcategory":"Employment Agencies",
            "type":"Services"
        }
    ],
    "sg:phone":"+1 602 328 9009",
    "sg:postcode":"85021",
    "sg:province":"AZ",
    "sg:tags":[
        "statistical"
    ],
    "wof:name":"Roberts Report",
    "wof:placetype":"venue"
},
  "geometry": {"coordinates":[-112.110513,33.553108],"type":"Point"}
}