{
  "type": "Feature",
  "properties": {
    "iso:country":"US",
    "sg:address":"515 E Marco Polo Rd",
    "sg:city":"Phoenix",
    "sg:classifiers":[
        {
            "category":"Wholesale",
            "subcategory":"Groceries",
            "type":"Manufacturing & Wholesale Goods"
        }
    ],
    "sg:phone":"+1 623 581 6143",
    "sg:postcode":"85024",
    "sg:province":"AZ",
    "sg:tags":[
        "grocers-wholesale"
    ],
    "wof:name":"Life Force Internaitional",
    "wof:placetype":"venue"
},
  "geometry": {"coordinates":[-112.066283,33.666243],"type":"Point"}
}