{
  "type": "Feature",
  "properties": {
    "iso:country":"US",
    "sg:address":"2412 W Durango St",
    "sg:city":"Phoenix",
    "sg:classifiers":[
        {
            "category":"Manufacturing",
            "subcategory":"Tools & Machinery",
            "type":"Manufacturing & Wholesale Goods"
        }
    ],
    "sg:phone":"+1 602 257 9445",
    "sg:postcode":"85009",
    "sg:province":"AZ",
    "sg:tags":[
        "machine",
        "shop"
    ],
    "wof:name":"Sun Valley Mfg",
    "wof:placetype":"venue"
},
  "geometry": {"coordinates":[-112.107657,33.429427],"type":"Point"}
}