{
  "type": "Feature",
  "properties": {
    "iso:country":"US",
    "sg:address":"1926 Pine Tree Dr",
    "sg:city":"Prescott",
    "sg:classifiers":[
        {
            "category":"Building & Trades",
            "subcategory":"Construction",
            "type":"Services"
        }
    ],
    "sg:phone":"+1 928 771 0744",
    "sg:postcode":"86303",
    "sg:province":"AZ",
    "sg:tags":[
        "home",
        "improvement"
    ],
    "wof:name":"Burton Painting & Wallpapering",
    "wof:placetype":"venue"
},
  "geometry": {"coordinates":[-112.506556,34.519332],"type":"Point"}
}