{
  "type": "Feature",
  "properties": {
    "iso:country":"US",
    "sg:address":"84 N Valentine St",
    "sg:city":"Wickenburg",
    "sg:classifiers":[
        {
            "category":"Retail",
            "subcategory":"Repair Shop",
            "type":"Services"
        }
    ],
    "sg:phone":"+1 928 684 4918",
    "sg:postcode":"85390",
    "sg:province":"AZ",
    "sg:tags":[
        "ironwork"
    ],
    "wof:name":"Popovich Ironworks",
    "wof:placetype":"venue"
},
  "geometry": {"coordinates":[-112.728984,33.969639],"type":"Point"}
}