{
  "type": "Feature",
  "properties": {
    "iso:country":"US",
    "sg:address":"2509 N Campbell Ave",
    "sg:city":"Tucson",
    "sg:classifiers":[
        {
            "category":"Wholesale",
            "subcategory":"Electrical",
            "type":"Manufacturing & Wholesale Goods"
        },
        {
            "category":"Manufacturing",
            "subcategory":"Tools & Machinery",
            "type":"Manufacturing & Wholesale Goods"
        }
    ],
    "sg:phone":"+1 520 320 1727",
    "sg:postcode":"85719",
    "sg:province":"AZ",
    "sg:tags":[
        "control",
        "security",
        "system",
        "mfg"
    ],
    "sg:website":"www.mikeforkan.com",
    "wof:name":"Mack Security Systems",
    "wof:placetype":"venue"
},
  "geometry": {"coordinates":[-110.94401,32.252841],"type":"Point"}
}