{
  "type": "Feature",
  "properties": {
    "iso:country":"US",
    "sg:address":"3219 N Canyon View Dr",
    "sg:city":"Nogales",
    "sg:classifiers":[
        {
            "category":"Building & Trades",
            "subcategory":"Construction",
            "type":"Services"
        }
    ],
    "sg:phone":"+1 520 839 9022",
    "sg:postcode":"85621",
    "sg:province":"AZ",
    "sg:tags":[
        "nonresidential"
    ],
    "wof:name":"Alleare LLC",
    "wof:placetype":"venue"
},
  "geometry": {"coordinates":[-110.924444,31.390665],"type":"Point"}
}