{
  "type": "Feature",
  "properties": {
    "addr:full":"5342 E Claire Dr Scottsdale AZ 85254",
    "addr:housenumber":"5342",
    "addr:postcode":"85254",
    "addr:street":"E Claire Dr",
    "iso:country":"US",
    "sg:address":"5342 E Claire Dr",
    "sg:city":"Scottsdale",
    "sg:classifiers":[
        {
            "category":"Recreation",
            "type":"Entertainment"
        }
    ],
    "sg:phone":"+1 602 971 1863",
    "sg:postcode":"85254",
    "sg:province":"AZ",
    "sg:tags":[
        "guide"
    ],
    "wof:name":"Parents Guide",
    "wof:placetype":"venue"
},
  "geometry": {"coordinates":[-111.965234,33.620515],"type":"Point"}
}