{
  "type": "Feature",
  "properties": {
    "iso:country":"US",
    "sg:address":"2020 W Pinnacle Peak Rd",
    "sg:city":"Phoenix",
    "sg:classifiers":[
        {
            "category":"Building & Trades",
            "subcategory":"Construction",
            "type":"Services"
        }
    ],
    "sg:phone":"+1 623 780 0005",
    "sg:postcode":"85027",
    "sg:province":"AZ",
    "sg:tags":[
        "rigger",
        "contractor"
    ],
    "sg:website":"www.masthead.net",
    "wof:name":"Masthead International",
    "wof:placetype":"venue"
},
  "geometry": {"coordinates":[-112.102784,33.698696],"type":"Point"}
}