{
  "type": "Feature",
  "properties": {
    "addr:full":"326 S Wilmot Rd Tucson AZ 85711",
    "addr:housenumber":"326",
    "addr:postcode":"85711",
    "addr:street":"S Wilmot Rd",
    "iso:country":"US",
    "sg:address":"326 S Wilmot Rd",
    "sg:city":"Tucson",
    "sg:classifiers":[
        {
            "category":"Health Services",
            "subcategory":"Clinic",
            "type":"Services"
        }
    ],
    "sg:phone":"+1 520 514 2754",
    "sg:postcode":"85711",
    "sg:province":"AZ",
    "wof:name":"Tender Loving Care Health Care",
    "wof:placetype":"venue"
},
  "geometry": {"coordinates":[-110.858088,32.216298],"type":"Point"}
}