{
  "type": "Feature",
  "properties": {
    "addr:full":"4230 W Union Hills Dr Glendale AZ 85308",
    "addr:housenumber":"4230",
    "addr:postcode":"85308",
    "addr:street":"W Union Hills Dr",
    "iso:country":"US",
    "sg:address":"4230 W Union Hills Dr",
    "sg:city":"Glendale",
    "sg:classifiers":[
        {
            "category":"Shopping",
            "subcategory":"Clothing, Apparel, & Fashions",
            "type":"Retail Goods"
        },
        {
            "category":"Shopping",
            "subcategory":"Department Store",
            "type":"Retail Goods"
        },
        {
            "category":"Shopping",
            "subcategory":"Discount & Variety Stores",
            "type":"Retail Goods"
        },
        {
            "category":"Shopping",
            "type":"Retail Goods"
        }
    ],
    "sg:phone":"+1 623 869 0779",
    "sg:postcode":"85308",
    "sg:province":"AZ",
    "sg:tags":[
        "clothing",
        "merchandise"
    ],
    "sg:website":"http://www.walmart.com",
    "wof:name":"Neighborhood Market",
    "wof:placetype":"venue"
},
  "geometry": {"coordinates":[-112.15046700000001,33.654598],"type":"Point"}
}