{
  "type": "Feature",
  "properties": {
    "iso:country":"US",
    "sg:address":"2454 E Mcdowell Rd",
    "sg:city":"Phoenix",
    "sg:classifiers":[
        {
            "category":"Home & Garden",
            "subcategory":"Household Appliances",
            "type":"Retail Goods"
        },
        {
            "category":"Wholesale",
            "subcategory":"Durable Goods & Equipment",
            "type":"Manufacturing & Wholesale Goods"
        }
    ],
    "sg:phone":"+1 602 267 9056",
    "sg:postcode":"85008",
    "sg:province":"AZ",
    "sg:tags":[
        "appliances-major-wholesale",
        "major",
        "manufacturer"
    ],
    "wof:name":"Tnt Appliances & More",
    "wof:placetype":"venue"
},
  "geometry": {"coordinates":[-112.02857299999999,33.465778],"type":"Point"}
}