{
  "type": "Feature",
  "properties": {
    "iso:country":"US",
    "sg:address":"1254 S Jay Cir",
    "sg:city":"Mesa",
    "sg:classifiers":[
        {
            "category":"Wholesale",
            "subcategory":"Construction Materials",
            "type":"Manufacturing & Wholesale Goods"
        }
    ],
    "sg:phone":"+1 480 833 1190",
    "sg:postcode":"85204",
    "sg:province":"AZ",
    "sg:tags":[
        "gates"
    ],
    "wof:name":"Mc Cowan Co Inc/Mi-Tee Gate",
    "wof:placetype":"venue"
},
  "geometry": {"coordinates":[-111.819516,33.392078],"type":"Point"}
}