{
  "type": "Feature",
  "properties": {
    "addr:full":"1616 W Ruby Dr Tempe AZ 85284",
    "addr:housenumber":"1616",
    "addr:postcode":"85284",
    "addr:street":"W Ruby Dr",
    "iso:country":"US",
    "sg:address":"1616 W Ruby Dr",
    "sg:city":"Tempe",
    "sg:classifiers":[
        {
            "category":"Restaurant",
            "type":"Food & Drink"
        }
    ],
    "sg:phone":"+1 480 735 5240",
    "sg:postcode":"85284",
    "sg:province":"AZ",
    "wof:name":"Life Cafe",
    "wof:placetype":"venue"
},
  "geometry": {"coordinates":[-111.964446,33.340175],"type":"Point"}
}