{
  "type": "Feature",
  "properties": {
    "iso:country":"US",
    "sg:address":"5076 N Highway 87",
    "sg:city":"Pine",
    "sg:classifiers":[
        {
            "category":"Restaurant",
            "type":"Food & Drink"
        }
    ],
    "sg:phone":"+1 928 476 3355",
    "sg:postcode":"85544",
    "sg:province":"AZ",
    "sg:tags":[
        "pizza"
    ],
    "wof:name":"Giuseppe's Restaurant",
    "wof:placetype":"venue"
},
  "geometry": {"coordinates":[-111.468834,34.397378],"type":"Point"}
}