{
  "type": "Feature",
  "properties": {
    "iso:country":"US",
    "sg:address":"1174 Hwy 95",
    "sg:city":"Bullhead City",
    "sg:classifiers":[
        {
            "category":"Personal",
            "subcategory":"Tattoo Parlor",
            "type":"Services"
        }
    ],
    "sg:phone":"+1 928 754 1114",
    "sg:postcode":"86429",
    "sg:province":"AZ",
    "sg:tags":[
        "tattooing"
    ],
    "wof:name":"Kind Connection Tattoos",
    "wof:placetype":"venue"
},
  "geometry": {"coordinates":[-114.568739,35.145235],"type":"Point"}
}