{
  "type": "Feature",
  "properties": {
    "iso:country":"US",
    "sg:address":"17210 E Roadrunner Rd",
    "sg:city":"Mayer",
    "sg:classifiers":[
        {
            "category":"Health Services",
            "subcategory":"Medical Lab",
            "type":"Services"
        }
    ],
    "sg:phone":"+1 928 632 4364",
    "sg:postcode":"86333",
    "sg:province":"AZ",
    "sg:tags":[
        "laboratory"
    ],
    "wof:name":"Bradshaw Mtn Diagnostic",
    "wof:placetype":"venue"
},
  "geometry": {"coordinates":[-112.160995,34.348184],"type":"Point"}
}