{
  "type": "Feature",
  "properties": {
    "iso:country":"US",
    "sg:address":"6830 E 39th St",
    "sg:city":"Tucson",
    "sg:classifiers":[
        {
            "category":"Building & Trades",
            "subcategory":"Landscaping Services",
            "type":"Services"
        }
    ],
    "sg:phone":"+1 520 745 0957",
    "sg:postcode":"85730",
    "sg:province":"AZ",
    "wof:name":"Hedge Hunters",
    "wof:placetype":"venue"
},
  "geometry": {"coordinates":[-110.845798,32.189262],"type":"Point"}
}