{
  "type": "Feature",
  "properties": {
    "iso:country":"US",
    "sg:address":"75 W Vista Ln",
    "sg:city":"Huachuca City",
    "sg:classifiers":[
        {
            "category":"Building & Trades",
            "subcategory":"Construction",
            "type":"Services"
        }
    ],
    "sg:phone":"+1 520 456 0493",
    "sg:postcode":"85616",
    "sg:province":"AZ",
    "sg:tags":[
        "paving",
        "contractor"
    ],
    "wof:name":"BNR Paving Co",
    "wof:placetype":"venue"
},
  "geometry": {"coordinates":[-110.351138,31.68417],"type":"Point"}
}