{
  "type": "Feature",
  "properties": {
    "addr:full":"4440 E Main St Mesa AZ 85205",
    "addr:housenumber":"4440",
    "addr:postcode":"85205",
    "addr:street":"E Main St",
    "iso:country":"US",
    "sg:address":"4440 E Main St",
    "sg:city":"Mesa",
    "sg:classifiers":[
        {
            "category":"Food & Beverages",
            "subcategory":"Groceries & Convenience Stores",
            "type":"Retail Goods"
        }
    ],
    "sg:phone":"+1 480 218 8540",
    "sg:postcode":"85205",
    "sg:province":"AZ",
    "wof:name":"Smiths",
    "wof:placetype":"venue"
},
  "geometry": {"coordinates":[-111.735034,33.415576],"type":"Point"}
}