{
  "type": "Feature",
  "properties": {
    "iso:country":"US",
    "sg:address":"4449 E 3rd St",
    "sg:city":"Tucson",
    "sg:classifiers":[
        {
            "category":"Personal",
            "type":"Services"
        }
    ],
    "sg:phone":"+1 520 245 6229",
    "sg:postcode":"85711",
    "sg:province":"AZ",
    "sg:tags":[
        "cosmetic"
    ],
    "wof:name":"Facephysics Ind Distr-Senegenc",
    "wof:placetype":"venue"
},
  "geometry": {"coordinates":[-110.897783,32.232634],"type":"Point"}
}