{
  "type": "Feature",
  "properties": {
    "iso:country":"US",
    "sg:address":"2338 E Aldine St",
    "sg:city":"Phoenix",
    "sg:classifiers":[
        {
            "category":"Building & Trades",
            "subcategory":"Electrical",
            "type":"Services"
        }
    ],
    "sg:phone":"+1 602 956 0404",
    "sg:postcode":"85022",
    "sg:province":"AZ",
    "sg:tags":[
        "electrical",
        "contractor"
    ],
    "wof:name":"Desert Sun Electrical",
    "wof:placetype":"venue"
},
  "geometry": {"coordinates":[-112.031166,33.5977],"type":"Point"}
}