{
  "type": "Feature",
  "properties": {
    "iso:country":"US",
    "sg:address":"1223 E Southern Ave",
    "sg:city":"Mesa",
    "sg:classifiers":[
        {
            "category":"Building & Trades",
            "subcategory":"Equipment Rental",
            "type":"Services"
        }
    ],
    "sg:phone":"+1 480 632 0823",
    "sg:postcode":"85204",
    "sg:province":"AZ",
    "sg:tags":[
        "leasing",
        "furniture"
    ],
    "wof:name":"Aarons Sales & Lease Ownership",
    "wof:placetype":"venue"
},
  "geometry": {"coordinates":[-111.80262399999999,33.393332],"type":"Point"}
}