{
  "type": "Feature",
  "properties": {
    "iso:country":"US",
    "sg:address":"1700 W Washington St",
    "sg:city":"Phoenix",
    "sg:classifiers":[
        {
            "category":"Education",
            "subcategory":"Library",
            "type":"Public Place"
        }
    ],
    "sg:phone":"+1 602 542 3701",
    "sg:postcode":"85007",
    "sg:province":"AZ",
    "sg:website":"www.lib.az.us",
    "wof:name":"State Law Library",
    "wof:placetype":"venue"
},
  "geometry": {"coordinates":[-112.095894,33.448518],"type":"Point"}
}