{
  "type": "Feature",
  "properties": {
    "addr:full":"230 S 3rd St Phoenix AZ 85004",
    "addr:housenumber":"230",
    "addr:postcode":"85004",
    "addr:street":"S 3Rd St",
    "iso:country":"US",
    "sg:address":"230 S 3rd St",
    "sg:city":"Phoenix",
    "sg:classifiers":[
        {
            "category":"Health Services",
            "subcategory":"Health Practitioner",
            "type":"Services"
        }
    ],
    "sg:phone":"+1 602 379 7545",
    "sg:postcode":"85004",
    "sg:province":"AZ",
    "sg:tags":[
        "therapist",
        "physical"
    ],
    "wof:name":"Physiotherapy Associates Inc",
    "wof:placetype":"venue"
},
  "geometry": {"coordinates":[-112.070008,33.445434],"type":"Point"}
}