{
  "type": "Feature",
  "properties": {
    "addr:full":"5231 W Fairview St Chandler AZ 85226",
    "addr:housenumber":"5231",
    "addr:postcode":"85226",
    "addr:street":"W Fairview St",
    "iso:country":"US",
    "sg:address":"5231 W Fairview St",
    "sg:city":"Chandler",
    "sg:classifiers":[
        {
            "category":"Real Estate",
            "subcategory":"Real Estate Agent",
            "type":"Services"
        }
    ],
    "sg:phone":"+1 480 961 4998",
    "sg:postcode":"85226",
    "sg:province":"AZ",
    "wof:name":"James Bobb Associates",
    "wof:placetype":"venue"
},
  "geometry": {"coordinates":[-111.93277399999999,33.294713],"type":"Point"}
}