{
  "type": "Feature",
  "properties": {
    "iso:country":"US",
    "sg:address":"1960 S Country Club Drive",
    "sg:city":"Mesa",
    "sg:classifiers":[
        {
            "category":"Retail",
            "subcategory":"Portrait Studio",
            "type":"Services"
        },
        {
            "category":"Shopping",
            "subcategory":"Pharmacy",
            "type":"Retail Goods"
        }
    ],
    "sg:phone":"+1 480 668 0165",
    "sg:postcode":"85210",
    "sg:province":"AZ",
    "sg:tags":[
        "photography",
        "drugstore",
        "store"
    ],
    "sg:website":"www.walgreens.com",
    "wof:name":"Walgreen Drug Stores",
    "wof:placetype":"venue"
},
  "geometry": {"coordinates":[-111.84101800000001,33.379244],"type":"Point"}
}