{
  "type": "Feature",
  "properties": {
    "iso:country":"US",
    "sg:address":"312 E Allen St",
    "sg:city":"Tombstone",
    "sg:classifiers":[
        {
            "category":"Shopping",
            "subcategory":"Hobbies, Toys, & Games",
            "type":"Retail Goods"
        }
    ],
    "sg:phone":"+1 520 457 3419",
    "sg:postcode":"85638",
    "sg:province":"AZ",
    "sg:tags":[
        "doll"
    ],
    "wof:name":"Gabe's Dolls",
    "wof:placetype":"venue"
},
  "geometry": {"coordinates":[-110.068153,31.713015],"type":"Point"}
}