{
  "type": "Feature",
  "properties": {
    "addr:full":"711 E Main St Mesa AZ 85203",
    "addr:housenumber":"711",
    "addr:postcode":"85203",
    "addr:street":"E Main St",
    "iso:country":"US",
    "sg:address":"711 E Main St",
    "sg:city":"Mesa",
    "sg:classifiers":[
        {
            "category":"Education",
            "subcategory":"Special Training",
            "type":"Public Place"
        }
    ],
    "sg:phone":"+1 480 890 2280",
    "sg:postcode":"85203",
    "sg:province":"AZ",
    "sg:tags":[
        "instrument",
        "musical"
    ],
    "wof:name":"Practice Pad",
    "wof:placetype":"venue"
},
  "geometry": {"coordinates":[-111.81522099999999,33.415033],"type":"Point"}
}