{
  "type": "Feature",
  "properties": {
    "iso:country":"US",
    "sg:address":"1125 W Birchwood Ave",
    "sg:city":"Mesa",
    "sg:classifiers":[
        {
            "category":"Shopping",
            "subcategory":"Computers & Home Electronics",
            "type":"Retail Goods"
        }
    ],
    "sg:phone":"+1 480 610 5155",
    "sg:postcode":"85210",
    "sg:province":"AZ",
    "sg:tags":[
        "system"
    ],
    "wof:name":"Severtson Corp",
    "wof:placetype":"venue"
},
  "geometry": {"coordinates":[-111.855451,33.409619],"type":"Point"}
}