{
  "type": "Feature",
  "properties": {
    "iso:country":"US",
    "sg:address":"4444 W Cielo Grande",
    "sg:city":"Glendale",
    "sg:classifiers":[
        {
            "category":"Professional",
            "subcategory":"Accounting & Tax Preparation",
            "type":"Services"
        }
    ],
    "sg:phone":"+1 623 516 9700",
    "sg:postcode":"85310",
    "sg:province":"AZ",
    "sg:tags":[
        "public",
        "accountants-certified"
    ],
    "wof:name":"Eve Devolites Company, Cpa",
    "wof:placetype":"venue"
},
  "geometry": {"coordinates":[-112.155584,33.701385],"type":"Point"}
}