{
  "type": "Feature",
  "properties": {
    "addr:full":"3618 E 34th St Tucson AZ 85713",
    "addr:housenumber":"3618",
    "addr:postcode":"85713",
    "addr:street":"E 34Th St",
    "iso:country":"US",
    "sg:address":"3618 E 34th St",
    "sg:city":"Tucson",
    "sg:classifiers":[
        {
            "category":"Wholesale",
            "subcategory":"Sporting Goods",
            "type":"Manufacturing & Wholesale Goods"
        }
    ],
    "sg:phone":"+1 520 325 5574",
    "sg:postcode":"85713",
    "sg:province":"AZ",
    "sg:tags":[
        "equipment",
        "pool",
        "swimming"
    ],
    "wof:name":"SCP Distributors",
    "wof:placetype":"venue"
},
  "geometry": {"coordinates":[-110.913315,32.194084],"type":"Point"}
}