{
  "type": "Feature",
  "properties": {
    "iso:country":"US",
    "sg:address":"844 N 91st Way",
    "sg:city":"Mesa",
    "sg:classifiers":[
        {
            "category":"Shopping",
            "subcategory":"Department Store",
            "type":"Retail Goods"
        }
    ],
    "sg:phone":"+1 480 357 0204",
    "sg:postcode":"85207",
    "sg:province":"AZ",
    "sg:tags":[
        "discount"
    ],
    "wof:name":"Wal Tam Investments Inc",
    "wof:placetype":"venue"
},
  "geometry": {"coordinates":[-111.63382,33.430152],"type":"Point"}
}