{
  "type": "Feature",
  "properties": {
    "iso:country":"US",
    "sg:address":"3921 E Baseline Rd",
    "sg:city":"Gilbert",
    "sg:classifiers":[
        {
            "category":"Health Services",
            "subcategory":"Doctor",
            "type":"Services"
        }
    ],
    "sg:phone":"+1 480 633 3995",
    "sg:postcode":"85234",
    "sg:province":"AZ",
    "sg:tags":[
        "physician",
        "surgeon"
    ],
    "wof:name":"Arizona Specialty Physicians",
    "wof:placetype":"venue"
},
  "geometry": {"coordinates":[-111.744231,33.379105],"type":"Point"}
}