{
  "type": "Feature",
  "properties": {
    "iso:country":"US",
    "sg:address":"4946 W Laurie Ln",
    "sg:city":"Glendale",
    "sg:classifiers":[
        {
            "category":"Government",
            "subcategory":"Fire Station",
            "type":"Public Place"
        },
        {
            "category":"Professional",
            "subcategory":"Detective & Security Services",
            "type":"Services"
        },
        {
            "category":"Home & Garden",
            "subcategory":"Hardware",
            "type":"Retail Goods"
        },
        {
            "category":"Building & Trades",
            "subcategory":"Electrical",
            "type":"Services"
        }
    ],
    "sg:phone":"+1 623 236 3900",
    "sg:postcode":"85302",
    "sg:province":"AZ",
    "sg:tags":[
        "control",
        "industrial",
        "monitoring",
        "supply",
        "consultant",
        "alarm",
        "commercial",
        "system",
        "equipment",
        "protection",
        "smoke",
        "sprinklers-residential",
        "detector",
        "automatic"
    ],
    "wof:name":"Ultimate Fire Protection",
    "wof:placetype":"venue"
},
  "geometry": {"coordinates":[-112.166815,33.558453],"type":"Point"}
}