{
  "type": "Feature",
  "properties": {
    "iso:country":"US",
    "sg:address":"11138 E Greenway Rd",
    "sg:city":"Scottsdale",
    "sg:phone":"+1 480 905 8400",
    "sg:postcode":"85255",
    "sg:province":"AZ",
    "sg:tags":[
        "petroleum",
        "broker"
    ],
    "wof:name":"Petroleum Resources Inc",
    "wof:placetype":"venue"
},
  "geometry": {"coordinates":[-111.837598,33.626857],"type":"Point"}
}