{
  "type": "Feature",
  "properties": {
    "iso:country":"US",
    "sg:address":"3920 E Thomas Rd",
    "sg:city":"Phoenix",
    "sg:classifiers":[
        {
            "category":"Government",
            "subcategory":"Post Office",
            "type":"Public Place"
        }
    ],
    "sg:phone":"+1 602 957 2693",
    "sg:postcode":"85018",
    "sg:province":"AZ",
    "sg:tags":[
        "postal",
        "us"
    ],
    "wof:name":"US Post Office",
    "wof:placetype":"venue"
},
  "geometry": {"coordinates":[-111.996028,33.4805],"type":"Point"}
}