{
  "type": "Feature",
  "properties": {
    "iso:country":"US",
    "sg:address":"1964 E Monterey St",
    "sg:city":"Chandler",
    "sg:classifiers":[
        {
            "category":"Banks & Credit Unions",
            "subcategory":"Financial Services",
            "type":"Services"
        }
    ],
    "sg:phone":"+1 602 315 3386",
    "sg:postcode":"85225",
    "sg:province":"AZ",
    "sg:tags":[
        "trust",
        "investment",
        "real estate"
    ],
    "wof:name":"Slobodan Popovic",
    "wof:placetype":"venue"
},
  "geometry": {"coordinates":[-111.808435,33.315142],"type":"Point"}
}