{
  "type": "Feature",
  "properties": {
    "addr:full":"28924 W Southern Ave Buckeye AZ 85326",
    "addr:housenumber":"28924",
    "addr:postcode":"85326",
    "addr:street":"W Southern Ave",
    "iso:country":"US",
    "sg:address":"28924 W Southern Ave",
    "sg:city":"Buckeye",
    "sg:classifiers":[
        {
            "category":"Farming",
            "subcategory":"Dairy Farm",
            "type":"Manufacturing & Wholesale Goods"
        }
    ],
    "sg:phone":"+1 623 386 2137",
    "sg:postcode":"85326",
    "sg:province":"AZ",
    "wof:name":"Butler Dairy",
    "wof:placetype":"venue"
},
  "geometry": {"coordinates":[-112.67159100000001,33.392223],"type":"Point"}
}