{
  "type": "Feature",
  "properties": {
    "iso:country":"US",
    "sg:address":"201 N Dusty Tyra Rd",
    "sg:city":"Benson",
    "sg:classifiers":[
        {
            "category":"Retail",
            "subcategory":"Auto Repair",
            "type":"Services"
        }
    ],
    "sg:phone":"+1 520 586 7531",
    "sg:postcode":"85602",
    "sg:province":"AZ",
    "sg:tags":[
        "body",
        "painting",
        "repairing",
        "automobile"
    ],
    "wof:name":"Eby's Body Shop",
    "wof:placetype":"venue"
},
  "geometry": {"coordinates":[-110.242633,31.973867],"type":"Point"}
}