{
  "type": "Feature",
  "properties": {
    "iso:country":"US",
    "sg:address":"702 E Thunderbird Rd",
    "sg:city":"Phoenix",
    "sg:classifiers":[
        {
            "category":"Social Services",
            "type":"Services"
        }
    ],
    "sg:phone":"+1 602 548 8508",
    "sg:postcode":"85022",
    "sg:province":"AZ",
    "sg:tags":[
        "counselor",
        "marriage",
        "family"
    ],
    "wof:name":"Phoenix Christian Counseling",
    "wof:placetype":"venue"
},
  "geometry": {"coordinates":[-112.064387,33.60771],"type":"Point"}
}