{
  "type": "Feature",
  "properties": {
    "iso:country":"US",
    "sg:address":"642 Dameron Dr",
    "sg:city":"Prescott",
    "sg:classifiers":[
        {
            "category":"Social Services",
            "type":"Services"
        }
    ],
    "sg:phone":"+1 928 445 5211",
    "sg:postcode":"86301",
    "sg:province":"AZ",
    "sg:tags":[
        "counselor",
        "marriage",
        "family"
    ],
    "sg:website":"www.wygc.org",
    "wof:name":"West Yavapai Guidance Clinic",
    "wof:placetype":"venue"
},
  "geometry": {"coordinates":[-112.47586,34.549376],"type":"Point"}
}