{
  "type": "Feature",
  "properties": {
    "addr:full":"1766 S Greenfield Rd Ste 105 Mesa AZ 85206",
    "addr:housenumber":"1766",
    "addr:postcode":"85206",
    "addr:street":"S Greenfield Rd Ste 105",
    "iso:country":"US",
    "sg:address":"1766 S Greenfield Rd Ste 105",
    "sg:city":"Mesa",
    "sg:classifiers":[
        {
            "category":"Shopping",
            "subcategory":"Hobbies, Toys, & Games",
            "type":"Retail Goods"
        }
    ],
    "sg:phone":"+1 480 632 0088",
    "sg:postcode":"85206",
    "sg:province":"AZ",
    "sg:tags":[
        "video",
        "supply"
    ],
    "sg:website":"http://www.gamestop.com/",
    "wof:name":"Gamestop",
    "wof:placetype":"venue"
},
  "geometry": {"coordinates":[-111.73921300000001,33.381835],"type":"Point"}
}