{
  "type": "Feature",
  "properties": {
    "iso:country":"US",
    "sg:address":"8134 E Cactus Rd Ste 620",
    "sg:city":"Scottsdale",
    "sg:classifiers":[
        {
            "category":"Health Services",
            "subcategory":"Doctor",
            "type":"Services"
        }
    ],
    "sg:phone":"+1 480 314 0388",
    "sg:postcode":"85260",
    "sg:province":"AZ",
    "sg:tags":[
        "physician",
        "management",
        "surgeons",
        "weight",
        "loss"
    ],
    "wof:name":"Desert Sierra Med Weight Loss",
    "wof:placetype":"venue"
},
  "geometry": {"coordinates":[-111.905302,33.596596],"type":"Point"}
}