{
  "type": "Feature",
  "properties": {
    "iso:country":"US",
    "sg:address":"13623 N 32nd St",
    "sg:city":"Phoenix",
    "sg:classifiers":[
        {
            "category":"Restaurant",
            "type":"Food & Drink"
        }
    ],
    "sg:phone":"+1 602 867 9010",
    "sg:postcode":"85032",
    "sg:province":"AZ",
    "sg:tags":[
        "eating"
    ],
    "wof:name":"Ollies Omelette House",
    "wof:placetype":"venue"
},
  "geometry": {"coordinates":[-112.013178,33.609898],"type":"Point"}
}