{
  "type": "Feature",
  "properties": {
    "iso:country":"US",
    "sg:address":"2921 N West St",
    "sg:city":"Flagstaff",
    "sg:classifiers":[
        {
            "category":"Manufacturing",
            "subcategory":"Apparel",
            "type":"Manufacturing & Wholesale Goods"
        }
    ],
    "sg:phone":"+1 928 226 0759",
    "sg:postcode":"86004",
    "sg:province":"AZ",
    "sg:tags":[
        "household",
        "furnishing",
        "mfg"
    ],
    "wof:name":"Oak Ridge Embroidery",
    "wof:placetype":"venue"
},
  "geometry": {"coordinates":[-111.621731,35.216669],"type":"Point"}
}