{
  "type": "Feature",
  "properties": {
    "iso:country":"US",
    "sg:address":"202 S 30th St",
    "sg:city":"Phoenix",
    "sg:classifiers":[
        {
            "category":"Building & Trades",
            "subcategory":"Construction",
            "type":"Services"
        },
        {
            "category":"Manufacturing",
            "subcategory":"Building Materials",
            "type":"Manufacturing & Wholesale Goods"
        }
    ],
    "sg:phone":"+1 602 267 1121",
    "sg:postcode":"85034",
    "sg:province":"AZ",
    "sg:tags":[
        "supply",
        "materials-wholesale",
        "contractor",
        "equipment",
        "drywall",
        "manufacturer"
    ],
    "wof:name":"Desert Building Materials",
    "wof:placetype":"venue"
},
  "geometry": {"coordinates":[-112.01725,33.446352],"type":"Point"}
}