{
  "type": "Feature",
  "properties": {
    "iso:country":"US",
    "sg:address":"27809 N 45th Way",
    "sg:city":"Cave Creek",
    "sg:classifiers":[
        {
            "category":"Banks & Credit Unions",
            "subcategory":"Bank",
            "type":"Services"
        }
    ],
    "sg:phone":"+1 480 585 7710",
    "sg:postcode":"85331",
    "sg:province":"AZ",
    "sg:tags":[
        "loan",
        "real estate"
    ],
    "sg:website":"www.swimmingpoolloans.com",
    "wof:name":"Opyne Capital Corp",
    "wof:placetype":"venue"
},
  "geometry": {"coordinates":[-111.981995,33.737659],"type":"Point"}
}