{
  "type": "Feature",
  "properties": {
    "iso:country":"US",
    "sg:address":"3350 S Price Rd",
    "sg:city":"Tempe",
    "sg:classifiers":[
        {
            "category":"Banks & Credit Unions",
            "subcategory":"Bank",
            "type":"Services"
        }
    ],
    "sg:phone":"+1 602 264 6421",
    "sg:postcode":"85282",
    "sg:province":"AZ",
    "sg:website":"www.azcentralcu.org",
    "wof:name":"Arizona Central Credit Union",
    "wof:placetype":"venue"
},
  "geometry": {"coordinates":[-111.892053,33.391919],"type":"Point"}
}