{
  "type": "Feature",
  "properties": {
    "addr:full":"17573 W Marconi Ave Surprise AZ 85388",
    "addr:housenumber":"17573",
    "addr:postcode":"85388",
    "addr:street":"W Marconi Ave",
    "iso:country":"US",
    "sg:address":"17573 W Marconi Ave",
    "sg:city":"Surprise",
    "sg:classifiers":[
        {
            "category":"Autos & Motor Vehicles",
            "subcategory":"Fuel & Gas Station",
            "type":"Retail Goods"
        }
    ],
    "sg:phone":"+1 623 399 6234",
    "sg:postcode":"85388",
    "sg:province":"AZ",
    "sg:tags":[
        "terminal",
        "truck"
    ],
    "wof:name":"Tks Enterprises, Inc.",
    "wof:placetype":"venue"
},
  "geometry": {"coordinates":[-112.437792,33.629123],"type":"Point"}
}