{
  "type": "Feature",
  "properties": {
    "iso:country":"US",
    "sg:address":"946 S Stapley Dr",
    "sg:city":"Mesa",
    "sg:classifiers":[
        {
            "category":"Social Services",
            "subcategory":"Job Training",
            "type":"Services"
        },
        {
            "category":"Social Services",
            "subcategory":"Adult Care",
            "type":"Services"
        }
    ],
    "sg:phone":"+1 480 986 3577",
    "sg:postcode":"85204",
    "sg:province":"AZ",
    "sg:tags":[
        "nurses-home",
        "nursing",
        "homes-skilled",
        "facility"
    ],
    "wof:name":"Preferred Assistence",
    "wof:placetype":"venue"
},
  "geometry": {"coordinates":[-111.80542,33.397364],"type":"Point"}
}