{
  "type": "Feature",
  "properties": {
    "addr:full":"570 W Southern Ave Tempe AZ 85282",
    "addr:housenumber":"570",
    "addr:postcode":"85282",
    "addr:street":"W Southern Ave",
    "iso:country":"US",
    "sg:address":"570 W Southern Ave",
    "sg:city":"Tempe",
    "sg:classifiers":[
        {
            "category":"Shopping",
            "subcategory":"Party Supplies",
            "type":"Retail Goods"
        },
        {
            "category":"Building & Trades",
            "subcategory":"Equipment Rental",
            "type":"Services"
        }
    ],
    "sg:phone":"+1 480 222 3180",
    "sg:postcode":"85282",
    "sg:province":"AZ",
    "sg:tags":[
        "yard",
        "store",
        "wedding"
    ],
    "sg:website":"http://www.videowestinc.com",
    "wof:name":"Video West Inc",
    "wof:placetype":"venue"
},
  "geometry": {"coordinates":[-111.947405,33.392841],"type":"Point"}
}