{
  "type": "Feature",
  "properties": {
    "iso:country":"US",
    "sg:address":"105 N Pantano Rd",
    "sg:city":"Tucson",
    "sg:classifiers":[
        {
            "category":"Insurance",
            "subcategory":"Insurance Agent",
            "type":"Services"
        }
    ],
    "sg:phone":"+1 520 885 6475",
    "sg:postcode":"85710",
    "sg:province":"AZ",
    "wof:name":"Farmers Insurance Group",
    "wof:placetype":"venue"
},
  "geometry": {"coordinates":[-110.823907,32.22318],"type":"Point"}
}