{
  "type": "Feature",
  "properties": {
    "iso:country":"US",
    "sg:address":"12510 W Alegre Dr",
    "sg:city":"Litchfield Park",
    "sg:classifiers":[
        {
            "category":"Freight",
            "type":"Transportation"
        }
    ],
    "sg:phone":"+1 623 535 3019",
    "sg:postcode":"85340",
    "sg:province":"AZ",
    "sg:tags":[
        "leasing",
        "dump",
        "haulage",
        "equipment",
        "construction",
        "truck"
    ],
    "wof:name":"All Contractors Services",
    "wof:placetype":"venue"
},
  "geometry": {"coordinates":[-112.328917,33.500713],"type":"Point"}
}