{
  "type": "Feature",
  "properties": {
    "iso:country":"US",
    "sg:address":"2631 S Roosevelt St",
    "sg:city":"Tempe",
    "sg:classifiers":[
        {
            "category":"Wholesale",
            "subcategory":"Office Equipment",
            "type":"Manufacturing & Wholesale Goods"
        },
        {
            "category":"Wholesale",
            "subcategory":"Computers",
            "type":"Manufacturing & Wholesale Goods"
        },
        {
            "category":"Professional",
            "subcategory":"Computer Services",
            "type":"Services"
        }
    ],
    "sg:phone":"+1 480 248 2600",
    "sg:postcode":"85282",
    "sg:province":"AZ",
    "sg:tags":[
        "furniture",
        "software"
    ],
    "wof:name":"Unicopy Digital Business Systs",
    "wof:placetype":"venue"
},
  "geometry": {"coordinates":[-111.947805,33.40073],"type":"Point"}
}