{
  "type": "Feature",
  "properties": {
    "addr:full":"1920 E Broadway Rd Tempe AZ 85282",
    "addr:housenumber":"1920",
    "addr:postcode":"85282",
    "addr:street":"E Broadway Rd",
    "iso:country":"US",
    "sg:address":"1920 E Broadway Rd",
    "sg:city":"Tempe",
    "sg:phone":"+1 480 214 0535",
    "sg:postcode":"85282",
    "sg:province":"AZ",
    "wof:name":"Free In Five",
    "wof:placetype":"venue"
},
  "geometry": {"coordinates":[-111.902496,33.407558],"type":"Point"}
}