{
  "type": "Feature",
  "properties": {
    "addr:full":"2707 S White Mountain Rd Show Low AZ 85901",
    "addr:housenumber":"2707",
    "addr:postcode":"85901",
    "addr:street":"S White Mountain Rd",
    "iso:country":"US",
    "sg:address":"2707 S White Mountain Rd",
    "sg:city":"Show Low",
    "sg:classifiers":[
        {
            "category":"Shopping",
            "type":"Retail Goods"
        }
    ],
    "sg:phone":"+1 928 537 8479",
    "sg:postcode":"85901",
    "sg:province":"AZ",
    "sg:tags":[
        "hearing",
        "equipment",
        "supply",
        "merchandise",
        "impaired"
    ],
    "sg:website":"www.miracle-ear.com",
    "wof:name":"Miracle-Ear",
    "wof:placetype":"venue"
},
  "geometry": {"coordinates":[-110.02914,34.224648],"type":"Point"}
}