{
  "type": "Feature",
  "properties": {
    "addr:full":"14435 S 48th St Apt 1172 Phoenix AZ 85044",
    "addr:housenumber":"14435;1172",
    "addr:postcode":"85044",
    "addr:street":"S 48Th St Apt",
    "iso:country":"US",
    "sg:address":"14435 S 48th St Apt 1172",
    "sg:city":"Phoenix",
    "sg:classifiers":[
        {
            "category":"Food & Beverages",
            "subcategory":"Bakery",
            "type":"Retail Goods"
        }
    ],
    "sg:phone":"+1 602 980 5873",
    "sg:postcode":"85044",
    "sg:province":"AZ",
    "sg:tags":[
        "cooky",
        "cracker"
    ],
    "wof:name":"The Elegant Cookie",
    "wof:placetype":"venue"
},
  "geometry": {"coordinates":[-111.980431,33.314899],"type":"Point"}
}