{
  "type": "Feature",
  "properties": {
    "iso:country":"US",
    "sg:address":"3646 W Brown St",
    "sg:city":"Phoenix",
    "sg:classifiers":[
        {
            "category":"Professional",
            "type":"Services"
        }
    ],
    "sg:phone":"+1 602 942 6734",
    "sg:postcode":"85051",
    "sg:province":"AZ",
    "wof:name":"Eci Expo Central International",
    "wof:placetype":"venue"
},
  "geometry": {"coordinates":[-112.13756600000001,33.578029],"type":"Point"}
}