{
  "type": "Feature",
  "properties": {
    "addr:full":"480 Raintree Rd Sedona AZ 86351",
    "addr:housenumber":"480",
    "addr:postcode":"86351",
    "addr:street":"Raintree Rd",
    "iso:country":"US",
    "sg:address":"480 Raintree Rd",
    "sg:city":"Sedona",
    "sg:classifiers":[
        {
            "category":"Building & Trades",
            "subcategory":"Construction",
            "type":"Services"
        }
    ],
    "sg:phone":"+1 928 284 1819",
    "sg:postcode":"86351",
    "sg:province":"AZ",
    "sg:tags":[
        "storage",
        "tank"
    ],
    "wof:name":"Lance Enterprises Inc",
    "wof:placetype":"venue"
},
  "geometry": {"coordinates":[-111.725099,34.795924],"type":"Point"}
}