{
  "type": "Feature",
  "properties": {
    "iso:country":"US",
    "sg:address":"22601 N 19th Ave Ste 214",
    "sg:city":"Phoenix",
    "sg:classifiers":[
        {
            "category":"Professional",
            "subcategory":"Computer Services",
            "type":"Services"
        }
    ],
    "sg:phone":"+1 623 572 7725",
    "sg:postcode":"85027",
    "sg:province":"AZ",
    "sg:tags":[
        "cd-rom"
    ],
    "wof:name":"Web Development Services",
    "wof:placetype":"venue"
},
  "geometry": {"coordinates":[-112.09987599999999,33.691059],"type":"Point"}
}