{
  "type": "Feature",
  "properties": {
    "addr:full":"5028 N Central Ave Phoenix AZ 85012",
    "addr:housenumber":"5028",
    "addr:postcode":"85012",
    "addr:street":"N Central Ave",
    "iso:country":"US",
    "sg:address":"5028 N Central Ave",
    "sg:city":"Phoenix",
    "sg:classifiers":[
        {
            "category":"Personal",
            "subcategory":"Shoe Repair & Shine",
            "type":"Services"
        }
    ],
    "sg:phone":"+1 602 279 1039",
    "sg:postcode":"85012",
    "sg:province":"AZ",
    "sg:tags":[
        "repairing",
        "boot"
    ],
    "wof:name":"Central Shoe Repair",
    "wof:placetype":"venue"
},
  "geometry": {"coordinates":[-112.073815,33.509861],"type":"Point"}
}