{
  "type": "Feature",
  "properties": {
    "addr:full":"4939 W Golden Ln Glendale AZ 85302",
    "addr:housenumber":"4939",
    "addr:postcode":"85302",
    "addr:street":"W Golden Ln",
    "iso:country":"US",
    "sg:address":"4939 W Golden Ln",
    "sg:city":"Glendale",
    "sg:classifiers":[
        {
            "category":"Professional",
            "subcategory":"Business Services",
            "type":"Services"
        }
    ],
    "sg:phone":"+1 623 915 2127",
    "sg:postcode":"85302",
    "sg:province":"AZ",
    "sg:tags":[
        "appraiser"
    ],
    "wof:name":"Appraisal Masters",
    "wof:placetype":"venue"
},
  "geometry": {"coordinates":[-112.166566,33.564132],"type":"Point"}
}