{
  "type": "Feature",
  "properties": {
    "addr:full":"2920 S 4th Ave Tucson AZ 85713",
    "addr:housenumber":"2920",
    "addr:postcode":"85713",
    "addr:street":"S 4Th Ave",
    "iso:country":"US",
    "sg:address":"2920 S 4th Ave",
    "sg:city":"Tucson",
    "sg:classifiers":[
        {
            "category":"Retail",
            "subcategory":"Auto Repair",
            "type":"Services"
        }
    ],
    "sg:phone":"+1 520 884 5085",
    "sg:postcode":"85713",
    "sg:province":"AZ",
    "sg:tags":[
        "body",
        "automobile",
        "painting",
        "customizing"
    ],
    "wof:name":"Dave's Auto Refinishing",
    "wof:placetype":"venue"
},
  "geometry": {"coordinates":[-110.96528499999999,32.189265],"type":"Point"}
}