{
  "type": "Feature",
  "properties": {
    "addr:full":"914 Christmas Tree Ln Pearce AZ 85625",
    "addr:housenumber":"914",
    "addr:postcode":"85625",
    "addr:street":"Christmas Tree Ln",
    "iso:country":"US",
    "sg:address":"914 Christmas Tree Ln",
    "sg:city":"Pearce",
    "sg:classifiers":[
        {
            "category":"Professional",
            "type":"Services"
        }
    ],
    "sg:phone":"+1 520 826 0199",
    "sg:postcode":"85625",
    "sg:province":"AZ",
    "wof:name":"V K Simrall",
    "wof:placetype":"venue"
},
  "geometry": {"coordinates":[-109.845375,31.934844],"type":"Point"}
}