{
  "type": "Feature",
  "properties": {
    "addr:full":"8658 E Sweetwater Ave Scottsdale AZ 85260",
    "addr:housenumber":"8658",
    "addr:postcode":"85260",
    "addr:street":"E Sweetwater Ave",
    "iso:country":"US",
    "sg:address":"8658 E Sweetwater Ave",
    "sg:city":"Scottsdale",
    "sg:classifiers":[
        {
            "category":"Home & Garden",
            "subcategory":"Building Materials",
            "type":"Retail Goods"
        },
        {
            "category":"Professional",
            "subcategory":"Printing & Photocopies",
            "type":"Services"
        }
    ],
    "sg:phone":"+1 623 877 1611",
    "sg:postcode":"85260",
    "sg:province":"AZ",
    "sg:tags":[
        "door",
        "garage",
        "opener",
        "door-overhead",
        "type"
    ],
    "wof:name":"Empire Door Corporation",
    "wof:placetype":"venue"
},
  "geometry": {"coordinates":[-111.89379,33.603768],"type":"Point"}
}