{
  "type": "Feature",
  "properties": {
    "iso:country":"US",
    "sg:address":"218 N Granite St",
    "sg:city":"Prescott",
    "sg:classifiers":[
        {
            "category":"Education",
            "subcategory":"Dance Studio",
            "type":"Public Place"
        }
    ],
    "sg:phone":"+1 928 778 7529",
    "sg:postcode":"86301",
    "sg:province":"AZ",
    "sg:tags":[
        "instruction",
        "dancing"
    ],
    "wof:name":"Academy Of Performing Arts",
    "wof:placetype":"venue"
},
  "geometry": {"coordinates":[-112.471574,34.545063],"type":"Point"}
}