{
  "type": "Feature",
  "properties": {
    "iso:country":"US",
    "sg:address":"11910 W Orange Grove Rd",
    "sg:city":"Tucson",
    "sg:classifiers":[
        {
            "category":"Shopping",
            "type":"Retail Goods"
        }
    ],
    "sg:phone":"+1 520 682 8228",
    "sg:postcode":"85743",
    "sg:province":"AZ",
    "sg:tags":[
        "pet",
        "food",
        "supply"
    ],
    "wof:name":"West Ajo Feeds",
    "wof:placetype":"venue"
},
  "geometry": {"coordinates":[-111.2213,32.320877],"type":"Point"}
}