{
  "type": "Feature",
  "properties": {
    "iso:country":"US",
    "sg:address":"730 W Fairmont Dr",
    "sg:city":"Tempe",
    "sg:classifiers":[
        {
            "category":"Wholesale",
            "subcategory":"Stationery",
            "type":"Manufacturing & Wholesale Goods"
        },
        {
            "category":"Manufacturing",
            "subcategory":"Paper Products",
            "type":"Manufacturing & Wholesale Goods"
        }
    ],
    "sg:phone":"+1 480 829 0989",
    "sg:postcode":"85282",
    "sg:province":"AZ",
    "sg:tags":[
        "machine",
        "sanitary",
        "vending",
        "mfg"
    ],
    "sg:website":"www.hospeco.com",
    "wof:name":"Hospital Specialty Co",
    "wof:placetype":"venue"
},
  "geometry": {"coordinates":[-111.95175500000001,33.396555],"type":"Point"}
}