{
  "type": "Feature",
  "properties": {
    "iso:country":"US",
    "sg:address":"1603 E Williams St",
    "sg:city":"Tempe",
    "sg:classifiers":[
        {
            "category":"Manufacturing",
            "subcategory":"Printing",
            "type":"Manufacturing & Wholesale Goods"
        }
    ],
    "sg:phone":"+1 480 967 0198",
    "sg:postcode":"85281",
    "sg:province":"AZ",
    "sg:tags":[
        "book"
    ],
    "wof:name":"Mica Press",
    "wof:placetype":"venue"
},
  "geometry": {"coordinates":[-111.910797,33.412512],"type":"Point"}
}