{
  "type": "Feature",
  "properties": {
    "iso:country":"US",
    "sg:address":"2025 W Indian School Rd",
    "sg:city":"Phoenix",
    "sg:classifiers":[
        {
            "category":"Real Estate",
            "subcategory":"Real Estate Services",
            "type":"Services"
        },
        {
            "category":"Real Estate",
            "subcategory":"Real Estate Operator",
            "type":"Services"
        }
    ],
    "sg:phone":"+1 602 279 9339",
    "sg:postcode":"85015",
    "sg:province":"AZ",
    "sg:tags":[
        "apartment",
        "rental",
        "finder"
    ],
    "wof:name":"Fountain Ridge",
    "wof:placetype":"venue"
},
  "geometry": {"coordinates":[-112.102631,33.495025],"type":"Point"}
}