{
  "type": "Feature",
  "properties": {
    "iso:country":"US",
    "sg:address":"3325 E Beaver Creek Rd",
    "sg:city":"Rimrock",
    "sg:classifiers":[
        {
            "category":"Real Estate",
            "subcategory":"Real Estate Services",
            "type":"Services"
        },
        {
            "category":"Real Estate",
            "subcategory":"Real Estate Agent",
            "type":"Services"
        }
    ],
    "sg:phone":"+1 928 567 7448",
    "sg:postcode":"86335",
    "sg:province":"AZ",
    "sg:tags":[
        "consultant",
        "broker",
        "vacancy",
        "listing",
        "buyer",
        "rental"
    ],
    "sg:website":"http://www.beavercreekrealty.com",
    "wof:name":"Beaver Creek Realty",
    "wof:placetype":"venue"
},
  "geometry": {"coordinates":[-111.793312,34.642445],"type":"Point"}
}