{
  "type": "Feature",
  "properties": {
    "addr:full":"1052 Willow Creek Rd Prescott AZ 86301",
    "addr:housenumber":"1052",
    "addr:postcode":"86301",
    "addr:street":"Willow Creek Rd",
    "iso:country":"US",
    "sg:address":"1052 Willow Creek Rd",
    "sg:city":"Prescott",
    "sg:classifiers":[
        {
            "category":"Building & Trades",
            "subcategory":"Construction",
            "type":"Services"
        }
    ],
    "sg:phone":"+1 928 445 6850",
    "sg:postcode":"86301",
    "sg:province":"AZ",
    "sg:tags":[
        "general",
        "contractor"
    ],
    "wof:name":"Alpha Construction Inc",
    "wof:placetype":"venue"
},
  "geometry": {"coordinates":[-112.48229600000001,34.562118],"type":"Point"}
}