{
  "type": "Feature",
  "properties": {
    "addr:full":"391 E Aspen Way Gilbert AZ 85234",
    "addr:housenumber":"391",
    "addr:postcode":"85234",
    "addr:street":"E Aspen Way",
    "iso:country":"US",
    "sg:address":"391 E Aspen Way",
    "sg:city":"Gilbert",
    "sg:classifiers":[
        {
            "category":"Shopping",
            "subcategory":"Clothing, Apparel, & Fashions",
            "type":"Retail Goods"
        },
        {
            "category":"Shopping",
            "subcategory":"Baby Store",
            "type":"Retail Goods"
        }
    ],
    "sg:phone":"+1 480 636 9090",
    "sg:postcode":"85234",
    "sg:province":"AZ",
    "sg:tags":[
        "infant",
        "accessories",
        "children's",
        "furnishing",
        "clothing",
        "wear"
    ],
    "wof:name":"Miss MaKena's Boutique",
    "wof:placetype":"venue"
},
  "geometry": {"coordinates":[-111.782611,33.363997],"type":"Point"}
}