{
  "type": "Feature",
  "properties": {
    "iso:country":"US",
    "sg:address":"4645 S 36th St",
    "sg:city":"Phoenix",
    "sg:classifiers":[
        {
            "category":"Wholesale",
            "subcategory":"Machinery & Supplies",
            "type":"Manufacturing & Wholesale Goods"
        },
        {
            "category":"Manufacturing",
            "subcategory":"Tools & Machinery",
            "type":"Manufacturing & Wholesale Goods"
        }
    ],
    "sg:phone":"+1 602 437 2220",
    "sg:postcode":"85040",
    "sg:province":"AZ",
    "sg:tags":[
        "machine",
        "industrial",
        "mfg"
    ],
    "sg:website":"www.methodswest.com",
    "wof:name":"Methods Machine Tools West",
    "wof:placetype":"venue"
},
  "geometry": {"coordinates":[-112.003923,33.40444],"type":"Point"}
}