{
  "type": "Feature",
  "properties": {
    "iso:country":"US",
    "sg:address":"3300 W Camelback Rd",
    "sg:city":"Phoenix",
    "sg:classifiers":[
        {
            "category":"Education",
            "subcategory":"Library",
            "type":"Public Place"
        }
    ],
    "sg:phone":"+1 602 589 2420",
    "sg:postcode":"85017",
    "sg:province":"AZ",
    "wof:name":"Fleming Library",
    "wof:placetype":"venue"
},
  "geometry": {"coordinates":[-112.131597,33.509437],"type":"Point"}
}