{
  "type": "Feature",
  "properties": {
    "iso:country":"US",
    "sg:address":"2349 W Plata Ave",
    "sg:city":"Mesa",
    "sg:classifiers":[
        {
            "category":"Building & Trades",
            "subcategory":"Pest Control",
            "type":"Services"
        }
    ],
    "sg:phone":"+1 480 496 4142",
    "sg:postcode":"85202",
    "sg:province":"AZ",
    "wof:name":"Amblers Pest Control",
    "wof:placetype":"venue"
},
  "geometry": {"coordinates":[-111.882428,33.360015],"type":"Point"}
}