{
  "type": "Feature",
  "properties": {
    "addr:full":"10201 N 39th St Phoenix AZ 85028",
    "addr:housenumber":"10201",
    "addr:postcode":"85028",
    "addr:street":"N 39Th St",
    "iso:country":"US",
    "sg:address":"10201 N 39th St",
    "sg:city":"Phoenix",
    "sg:classifiers":[
        {
            "category":"Manufacturing",
            "subcategory":"Signs",
            "type":"Manufacturing & Wholesale Goods"
        }
    ],
    "sg:phone":"+1 602 625 8365",
    "sg:postcode":"85028",
    "sg:province":"AZ",
    "wof:name":"Az Rock Design",
    "wof:placetype":"venue"
},
  "geometry": {"coordinates":[-111.99784200000001,33.582509],"type":"Point"}
}