{
  "type": "Feature",
  "properties": {
    "iso:country":"US",
    "sg:address":"8206 N Dreamy Draw Dr",
    "sg:city":"Phoenix",
    "sg:classifiers":[
        {
            "category":"Communications",
            "subcategory":"Film & Video Production",
            "type":"Services"
        },
        {
            "category":"Communications",
            "subcategory":"Television Station",
            "type":"Services"
        }
    ],
    "sg:phone":"+1 602 870 5558",
    "sg:postcode":"85020",
    "sg:province":"AZ",
    "sg:tags":[
        "companies-film",
        "producer",
        "tv",
        "program",
        "radio",
        "distributor"
    ],
    "wof:name":"Hagerman, Denise",
    "wof:placetype":"venue"
},
  "geometry": {"coordinates":[-112.03943,33.556807],"type":"Point"}
}