{
  "type": "Feature",
  "properties": {
    "iso:country":"US",
    "sg:address":"545 N Burk St",
    "sg:city":"Gilbert",
    "sg:classifiers":[
        {
            "category":"Education",
            "subcategory":"School",
            "type":"Public Place"
        }
    ],
    "sg:phone":"+1 480 926 3816",
    "sg:postcode":"85234",
    "sg:province":"AZ",
    "sg:tags":[
        "high",
        "middle",
        "elementary"
    ],
    "wof:name":"Burk Elementary School",
    "wof:placetype":"venue"
},
  "geometry": {"coordinates":[-111.781998,33.360199],"type":"Point"}
}