{
  "type": "Feature",
  "properties": {
    "iso:country":"US",
    "sg:address":"11811 N Tatum Blvd",
    "sg:city":"Phoenix",
    "sg:classifiers":[
        {
            "category":"Insurance",
            "subcategory":"Insurance Agent",
            "type":"Services"
        }
    ],
    "sg:phone":"+1 602 953 6653",
    "sg:postcode":"85028",
    "sg:province":"AZ",
    "sg:tags":[
        "adjuster"
    ],
    "wof:name":"Consumer Claims Advocates",
    "wof:placetype":"venue"
},
  "geometry": {"coordinates":[-111.97956,33.593276],"type":"Point"}
}