{
  "type": "Feature",
  "properties": {
    "iso:country":"US",
    "sg:address":"1204 E Baseline Rd Ste 201",
    "sg:city":"Tempe",
    "sg:classifiers":[
        {
            "category":"Banks & Credit Unions",
            "subcategory":"Financial Services",
            "type":"Services"
        }
    ],
    "sg:phone":"+1 480 295 4327",
    "sg:postcode":"85283",
    "sg:province":"AZ",
    "sg:tags":[
        "advising"
    ],
    "sg:website":"www.gocleancredit.com",
    "wof:name":"Go Clean Credit",
    "wof:placetype":"venue"
},
  "geometry": {"coordinates":[-111.920314,33.378478],"type":"Point"}
}