{
  "type": "Feature",
  "properties": {
    "iso:country":"US",
    "sg:address":"10738 E Forge Ave",
    "sg:city":"Mesa",
    "sg:classifiers":[
        {
            "category":"Wholesale",
            "subcategory":"Motor Vehicles",
            "type":"Manufacturing & Wholesale Goods"
        }
    ],
    "sg:phone":"+1 480 358 9682",
    "sg:postcode":"85208",
    "sg:province":"AZ",
    "sg:tags":[
        "durable"
    ],
    "wof:name":"Premier Fire Equipment Inc",
    "wof:placetype":"venue"
},
  "geometry": {"coordinates":[-111.599001,33.396534],"type":"Point"}
}