{
  "type": "Feature",
  "properties": {
    "iso:country":"US",
    "sg:address":"5154 N 27th Ave",
    "sg:city":"Phoenix",
    "sg:classifiers":[
        {
            "category":"Retail",
            "subcategory":"Auto Repair",
            "type":"Services"
        }
    ],
    "sg:phone":"+1 602 253 1630",
    "sg:postcode":"85017",
    "sg:province":"AZ",
    "sg:tags":[
        "body",
        "repairing",
        "painting",
        "automobile"
    ],
    "wof:name":"Capitol Collision",
    "wof:placetype":"venue"
},
  "geometry": {"coordinates":[-112.11698199999999,33.512622],"type":"Point"}
}