{
  "type": "Feature",
  "properties": {
    "iso:country":"US",
    "sg:address":"543 S Broad St",
    "sg:city":"Globe",
    "sg:classifiers":[
        {
            "category":"Health Services",
            "subcategory":"Doctor",
            "type":"Services"
        }
    ],
    "sg:phone":"+1 928 425 7603",
    "sg:postcode":"85501",
    "sg:province":"AZ",
    "sg:tags":[
        "dentist"
    ],
    "wof:name":"L H Mellor & Assoc",
    "wof:placetype":"venue"
},
  "geometry": {"coordinates":[-110.783842,33.392521],"type":"Point"}
}