{
  "type": "Feature",
  "properties": {
    "iso:country":"US",
    "sg:address":"307 N Florence St",
    "sg:city":"Casa Grande",
    "sg:classifiers":[
        {
            "category":"Shopping",
            "subcategory":"Gifts & Souvenirs",
            "type":"Retail Goods"
        }
    ],
    "sg:phone":"+1 520 876 4873",
    "sg:postcode":"85222",
    "sg:province":"AZ",
    "sg:tags":[
        "business"
    ],
    "wof:name":"Balloonarrifics",
    "wof:placetype":"venue"
},
  "geometry": {"coordinates":[-111.753021,32.877846],"type":"Point"}
}