{
  "type": "Feature",
  "properties": {
    "iso:country":"US",
    "sg:address":"4041 S McClintock Dr",
    "sg:city":"Tempe",
    "sg:classifiers":[
        {
            "category":"Professional",
            "subcategory":"Lawyer & Legal Services",
            "type":"Services"
        }
    ],
    "sg:phone":"+1 480 777 0600",
    "sg:postcode":"85282",
    "sg:province":"AZ",
    "sg:tags":[
        "personal",
        "injury"
    ],
    "wof:name":"Sacco Paul J Atty",
    "wof:placetype":"venue"
},
  "geometry": {"coordinates":[-111.908997,33.3867],"type":"Point"}
}