{
  "type": "Feature",
  "properties": {
    "addr:full":"5650 N 12th St Phoenix AZ 85014",
    "addr:housenumber":"5650",
    "addr:postcode":"85014",
    "addr:street":"N 12Th St",
    "iso:country":"US",
    "sg:address":"5650 N 12th St",
    "sg:city":"Phoenix",
    "sg:classifiers":[
        {
            "category":"Real Estate",
            "subcategory":"Real Estate Agent",
            "type":"Services"
        }
    ],
    "sg:phone":"+1 602 200 0815",
    "sg:postcode":"85014",
    "sg:province":"AZ",
    "sg:tags":[
        "investment"
    ],
    "wof:name":"John T Hansen Investments Rlty",
    "wof:placetype":"venue"
},
  "geometry": {"coordinates":[-112.056298,33.519867],"type":"Point"}
}