{
  "type": "Feature",
  "properties": {
    "iso:country":"US",
    "sg:address":"4003 E Cascalote Dr",
    "sg:city":"Cave Creek",
    "sg:classifiers":[
        {
            "category":"Retail",
            "subcategory":"Animal Services",
            "type":"Services"
        }
    ],
    "sg:phone":"+1 480 575 3190",
    "sg:postcode":"85331",
    "sg:province":"AZ",
    "wof:name":"United Farms",
    "wof:placetype":"venue"
},
  "geometry": {"coordinates":[-111.99499299999999,33.759654],"type":"Point"}
}