{
  "type": "Feature",
  "properties": {
    "iso:country":"US",
    "sg:address":"255 N Litchfield Rd",
    "sg:city":"Goodyear",
    "sg:classifiers":[
        {
            "category":"Sports & Exercise",
            "subcategory":"Gym",
            "type":"Entertainment"
        }
    ],
    "sg:phone":"+1 623 882 3700",
    "sg:postcode":"85338",
    "sg:province":"AZ",
    "sg:tags":[
        "club",
        "health",
        "studio",
        "gymnasium"
    ],
    "wof:name":"Infinity Fitness Ctr",
    "wof:placetype":"venue"
},
  "geometry": {"coordinates":[-112.35824100000001,33.437326],"type":"Point"}
}