{
  "type": "Feature",
  "properties": {
    "iso:country":"US",
    "sg:address":"2011 N 51st St Apt 11",
    "sg:city":"Phoenix",
    "sg:phone":"+1 602 286 0056",
    "sg:postcode":"85008",
    "sg:province":"AZ",
    "wof:name":"Premium Pest Control",
    "wof:placetype":"venue"
},
  "geometry": {"coordinates":[-111.97192800000001,33.469741],"type":"Point"}
}