{
  "type": "Feature",
  "properties": {
    "iso:country":"US",
    "sg:address":"5063 E Elliot Rd",
    "sg:city":"Phoenix",
    "sg:classifiers":[
        {
            "category":"Restaurant",
            "type":"Food & Drink"
        }
    ],
    "sg:menulink":"http://www.allmenus.com/az/phoenix/4288-caffe-boa/menu/",
    "sg:phone":"+1 480 893 3331",
    "sg:postcode":"85044",
    "sg:province":"AZ",
    "sg:tags":[
        "italian"
    ],
    "wof:name":"Caffe Boa",
    "wof:placetype":"venue"
},
  "geometry": {"coordinates":[-111.976462,33.348709],"type":"Point"}
}