{
  "type": "Feature",
  "properties": {
    "iso:country":"US",
    "sg:address":"3156 Troxler Cir",
    "sg:city":"Flagstaff",
    "sg:classifiers":[
        {
            "category":"Restaurant",
            "type":"Food & Drink"
        }
    ],
    "sg:phone":"+1 928 774 0578",
    "sg:postcode":"86001",
    "sg:province":"AZ",
    "sg:tags":[
        "drinking",
        "eating"
    ],
    "wof:name":"Historic Saginaw House",
    "wof:placetype":"venue"
},
  "geometry": {"coordinates":[-111.670289,35.172268],"type":"Point"}
}