{
  "type": "Feature",
  "properties": {
    "iso:country":"US",
    "sg:address":"7769 N 33rd Ave",
    "sg:city":"Phoenix",
    "sg:classifiers":[
        {
            "category":"Building & Trades",
            "subcategory":"Cleaning & Sanitation",
            "type":"Services"
        }
    ],
    "sg:phone":"+1 602 246 9982",
    "sg:postcode":"85051",
    "sg:province":"AZ",
    "sg:tags":[
        "ceiling"
    ],
    "wof:name":"Ceiling Solutions",
    "wof:placetype":"venue"
},
  "geometry": {"coordinates":[-112.12992800000001,33.550671],"type":"Point"}
}