{
  "type": "Feature",
  "properties": {
    "addr:full":"4607 E Thomas Rd Phoenix AZ 85018",
    "addr:housenumber":"4607",
    "addr:postcode":"85018",
    "addr:street":"E Thomas Rd",
    "iso:country":"US",
    "sg:address":"4607 E Thomas Rd",
    "sg:city":"Phoenix",
    "sg:classifiers":[
        {
            "category":"Personal",
            "subcategory":"Beauty Salon",
            "type":"Services"
        },
        {
            "category":"Personal",
            "subcategory":"Barber",
            "type":"Services"
        },
        {
            "category":"Personal",
            "subcategory":"Nail Salon",
            "type":"Services"
        }
    ],
    "sg:phone":"+1 602 840 7542",
    "sg:postcode":"85018",
    "sg:province":"AZ",
    "sg:tags":[
        "hair",
        "stylist"
    ],
    "wof:name":"Cutters Cottage",
    "wof:placetype":"venue"
},
  "geometry": {"coordinates":[-111.98243600000001,33.48017],"type":"Point"}
}