{
  "type": "Feature",
  "properties": {
    "iso:country":"US",
    "sg:address":"6990 E 22nd St",
    "sg:city":"Tucson",
    "sg:classifiers":[
        {
            "category":"Freight",
            "type":"Transportation"
        }
    ],
    "sg:phone":"+1 520 745 2707",
    "sg:postcode":"85710",
    "sg:province":"AZ",
    "sg:tags":[
        "shipping",
        "agent"
    ],
    "wof:name":"Postnet",
    "wof:placetype":"venue"
},
  "geometry": {"coordinates":[-110.841859,32.206413],"type":"Point"}
}