{
  "type": "Feature",
  "properties": {
    "iso:country":"US",
    "sg:address":"3244 E 47th St",
    "sg:city":"Tucson",
    "sg:classifiers":[
        {
            "category":"Building & Trades",
            "subcategory":"Construction",
            "type":"Services"
        }
    ],
    "sg:phone":"+1 520 574 1686",
    "sg:postcode":"85713",
    "sg:province":"AZ",
    "sg:tags":[
        "fence",
        "contractor"
    ],
    "wof:name":"All J Fence Co",
    "wof:placetype":"venue"
},
  "geometry": {"coordinates":[-110.925023,32.180275],"type":"Point"}
}