{
  "type": "Feature",
  "properties": {
    "iso:country":"US",
    "sg:address":"163 N Dobson Rd",
    "sg:city":"Mesa",
    "sg:classifiers":[
        {
            "category":"Government",
            "subcategory":"Office",
            "type":"Public Place"
        }
    ],
    "sg:phone":"+1 480 962 7678",
    "sg:postcode":"85201",
    "sg:province":"AZ",
    "sg:tags":[
        "state",
        "resource"
    ],
    "wof:name":"Economic Security Dept Job Svc",
    "wof:placetype":"venue"
},
  "geometry": {"coordinates":[-111.874315,33.418567],"type":"Point"}
}