{
  "type": "Feature",
  "properties": {
    "iso:country":"US",
    "sg:address":"1132 W McLellan Rd",
    "sg:city":"Mesa",
    "sg:classifiers":[
        {
            "category":"Real Estate",
            "subcategory":"Real Estate Operator",
            "type":"Services"
        }
    ],
    "sg:phone":"+1 480 834 1042",
    "sg:postcode":"85201",
    "sg:province":"AZ",
    "sg:tags":[
        "property",
        "commercial"
    ],
    "wof:name":"Johnson Stewart Materials",
    "wof:placetype":"venue"
},
  "geometry": {"coordinates":[-111.85623,33.444056],"type":"Point"}
}