{
  "type": "Feature",
  "properties": {
    "addr:full":"3101 W Peoria Ave Phoenix AZ 85029",
    "addr:housenumber":"3101",
    "addr:postcode":"85029",
    "addr:street":"W Peoria Ave",
    "iso:country":"US",
    "sg:address":"3101 W Peoria Ave",
    "sg:city":"Phoenix",
    "sg:classifiers":[
        {
            "category":"Insurance",
            "subcategory":"Insurance Agent",
            "type":"Services"
        }
    ],
    "sg:phone":"+1 602 504 0500",
    "sg:postcode":"85029",
    "sg:province":"AZ",
    "wof:name":"Kurt Bojarski Agency",
    "wof:placetype":"venue"
},
  "geometry": {"coordinates":[-112.127233,33.581951],"type":"Point"}
}