{
  "type": "Feature",
  "properties": {
    "iso:country":"US",
    "sg:address":"161 E 1st St Ste 5",
    "sg:city":"Mesa",
    "sg:classifiers":[
        {
            "category":"Professional",
            "subcategory":"Engineering",
            "type":"Services"
        },
        {
            "category":"Real Estate",
            "subcategory":"Surveying",
            "type":"Services"
        }
    ],
    "sg:phone":"+1 480 844 1717",
    "sg:postcode":"85201",
    "sg:province":"AZ",
    "sg:tags":[
        "consulting",
        "land",
        "civil",
        "surveyor",
        "engineer"
    ],
    "wof:name":"Ace Engineering Inc",
    "wof:placetype":"venue"
},
  "geometry": {"coordinates":[-111.826991,33.417248],"type":"Point"}
}