{
  "type": "Feature",
  "properties": {
    "iso:country":"US",
    "sg:address":"8600 E Shea Blvd #110",
    "sg:city":"Scottsdale",
    "sg:classifiers":[
        {
            "category":"Health Services",
            "subcategory":"Doctor",
            "type":"Services"
        }
    ],
    "sg:phone":"+1 602 357 6866",
    "sg:postcode":"85260",
    "sg:province":"AZ",
    "sg:tags":[
        "physician",
        "allergy",
        "immunology",
        "pediatrics-allergy",
        "surgeons"
    ],
    "sg:website":"http://allergyenvironmental.reachlocal.com/?scid=1760906",
    "wof:name":"Allergy Treatment Center",
    "wof:placetype":"venue"
},
  "geometry": {"coordinates":[-111.897057,33.582088],"type":"Point"}
}