{
  "type": "Feature",
  "properties": {
    "addr:full":"31381 Commercial Dr Parker AZ 85344",
    "addr:housenumber":"31381",
    "addr:postcode":"az 85344",
    "addr:street":"Commercial Dr",
    "iso:country":"US",
    "sg:address":"31381 Commercial Dr",
    "sg:city":"Parker",
    "sg:classifiers":[
        {
            "category":"Retail",
            "subcategory":"Auto Repair",
            "type":"Services"
        }
    ],
    "sg:phone":"+1 928 669 5400",
    "sg:postcode":"85344",
    "sg:province":"AZ",
    "sg:tags":[
        "wrecker"
    ],
    "wof:name":"A Toe Truck",
    "wof:placetype":"venue"
},
  "geometry": {"coordinates":[-114.226839,34.183849],"type":"Point"}
}