{
  "type": "Feature",
  "properties": {
    "iso:country":"US",
    "sg:address":"1647 E Broadway Blvd",
    "sg:city":"Tucson",
    "sg:classifiers":[
        {
            "category":"Building & Trades",
            "subcategory":"Equipment Rental",
            "type":"Services"
        }
    ],
    "sg:phone":"+1 520 884 0027",
    "sg:postcode":"85719",
    "sg:province":"AZ",
    "sg:tags":[
        "leasing"
    ],
    "wof:name":"Touchstone Leasing",
    "wof:placetype":"venue"
},
  "geometry": {"coordinates":[-110.947245,32.221473],"type":"Point"}
}