{
  "type": "Feature",
  "properties": {
    "iso:country":"US",
    "sg:address":"424 W Main St",
    "sg:city":"Safford",
    "sg:classifiers":[
        {
            "category":"Building & Trades",
            "subcategory":"Electrical",
            "type":"Services"
        }
    ],
    "sg:phone":"+1 928 428 2396",
    "sg:postcode":"85546",
    "sg:province":"AZ",
    "sg:tags":[
        "electric",
        "contractor"
    ],
    "wof:name":"Rocking D Electric",
    "wof:placetype":"venue"
},
  "geometry": {"coordinates":[-109.71152600000001,32.833381],"type":"Point"}
}