{
  "type": "Feature",
  "properties": {
    "iso:country":"US",
    "sg:address":"2419 N Black Canyon Hwy",
    "sg:city":"Phoenix",
    "sg:classifiers":[
        {
            "category":"Building & Trades",
            "subcategory":"Plumbing",
            "type":"Services"
        },
        {
            "category":"Building & Trades",
            "subcategory":"Cleaning & Sanitation",
            "type":"Services"
        }
    ],
    "sg:phone":"+1 602 254 3875",
    "sg:postcode":"85009",
    "sg:province":"AZ",
    "sg:tags":[
        "cleaner",
        "plumber",
        "industrial",
        "repairer",
        "sewer",
        "contractors-commercial",
        "plumbing-drain"
    ],
    "wof:name":"Standard Plumbing",
    "wof:placetype":"venue"
},
  "geometry": {"coordinates":[-112.112668,33.474234],"type":"Point"}
}