{
  "type": "Feature",
  "properties": {
    "addr:full":"1904 E Palomino Dr Gilbert AZ 85296",
    "addr:housenumber":"1904",
    "addr:postcode":"85296",
    "addr:street":"E Palomino Dr",
    "iso:country":"US",
    "sg:address":"1904 E Palomino Dr",
    "sg:city":"Gilbert",
    "sg:classifiers":[
        {
            "category":"Shopping",
            "subcategory":"Bicycles & Sporting Goods",
            "type":"Retail Goods"
        }
    ],
    "sg:phone":"+1 480 892 3987",
    "sg:postcode":"85296",
    "sg:province":"AZ",
    "wof:name":"Mad Lax",
    "wof:placetype":"venue"
},
  "geometry": {"coordinates":[-111.749526,33.338657],"type":"Point"}
}