{
  "type": "Feature",
  "properties": {
    "iso:country":"US",
    "sg:address":"6553 E Baywood Ave",
    "sg:city":"Mesa",
    "sg:classifiers":[
        {
            "category":"Health Services",
            "subcategory":"Doctor",
            "type":"Services"
        }
    ],
    "sg:phone":"+1 480 324 0999",
    "sg:postcode":"85206",
    "sg:province":"AZ",
    "sg:tags":[
        "physician",
        "surgeon"
    ],
    "wof:name":"Central Arizona Medical Assoc",
    "wof:placetype":"venue"
},
  "geometry": {"coordinates":[-111.69046,33.410352],"type":"Point"}
}