{
  "type": "Feature",
  "properties": {
    "addr:full":"201 S 4th Ave Yuma AZ 85364",
    "addr:housenumber":"201",
    "addr:postcode":"85364",
    "addr:street":"S 4Th Ave",
    "iso:country":"US",
    "sg:address":"201 S 4th Ave",
    "sg:city":"Yuma",
    "sg:classifiers":[
        {
            "category":"Government",
            "subcategory":"Office",
            "type":"Public Place"
        }
    ],
    "sg:phone":"+1 928 329 0471",
    "sg:postcode":"85364",
    "sg:province":"AZ",
    "sg:tags":[
        "state",
        "park"
    ],
    "wof:name":"Yuma Crssing State Historic Pk",
    "wof:placetype":"venue"
},
  "geometry": {"coordinates":[-114.624588,32.722819],"type":"Point"}
}