{
  "type": "Feature",
  "properties": {
    "addr:full":"6016 S Mcclintock Dr Tempe AZ 85283",
    "addr:housenumber":"6016",
    "addr:postcode":"85283",
    "addr:street":"S Mcclintock Dr",
    "iso:country":"US",
    "sg:address":"6016 S Mcclintock Dr",
    "sg:city":"Tempe",
    "sg:classifiers":[
        {
            "category":"Wholesale",
            "subcategory":"Medical Equipment & Supplies",
            "type":"Manufacturing & Wholesale Goods"
        },
        {
            "category":"Health Services",
            "subcategory":"Dentist",
            "type":"Services"
        }
    ],
    "sg:phone":"+1 480 831 7574",
    "sg:postcode":"85283",
    "sg:province":"AZ",
    "sg:tags":[
        "dental",
        "refinishing",
        "equipment-repairing"
    ],
    "sg:website":"http://www.hayeshandpiece.com",
    "wof:name":"Hayes Handpiece Repair",
    "wof:placetype":"venue"
},
  "geometry": {"coordinates":[-111.911277,33.36762],"type":"Point"}
}