{
  "type": "Feature",
  "properties": {
    "iso:country":"US",
    "sg:address":"2621 E Elk Run Ct",
    "sg:city":"Payson",
    "sg:classifiers":[
        {
            "category":"Building & Trades",
            "subcategory":"Construction",
            "type":"Services"
        }
    ],
    "sg:phone":"+1 928 468 2302",
    "sg:postcode":"85541",
    "sg:province":"AZ",
    "sg:tags":[
        "home",
        "builder"
    ],
    "wof:name":"Odysey Homes",
    "wof:placetype":"venue"
},
  "geometry": {"coordinates":[-111.282329,34.260881],"type":"Point"}
}