{
  "type": "Feature",
  "properties": {
    "addr:full":"525 E Pebble Beach Dr Tempe AZ 85282",
    "addr:housenumber":"525",
    "addr:postcode":"85282",
    "addr:street":"E Pebble Beach Dr",
    "iso:country":"US",
    "sg:address":"525 E Pebble Beach Dr",
    "sg:city":"Tempe",
    "sg:classifiers":[
        {
            "category":"Professional",
            "type":"Services"
        }
    ],
    "sg:phone":"+1 480 967 8892",
    "sg:postcode":"85282",
    "sg:province":"AZ",
    "wof:name":"Awakening Wave",
    "wof:placetype":"venue"
},
  "geometry": {"coordinates":[-111.931251,33.389421],"type":"Point"}
}