{
  "type": "Feature",
  "properties": {
    "addr:full":"1405 N Quail Ln Gilbert AZ 85233",
    "addr:housenumber":"1405",
    "addr:postcode":"85233",
    "addr:street":"N Quail Ln",
    "iso:country":"US",
    "sg:address":"1405 N Quail Ln",
    "sg:city":"Gilbert",
    "sg:classifiers":[
        {
            "category":"Home & Garden",
            "subcategory":"Building Materials",
            "type":"Retail Goods"
        }
    ],
    "sg:phone":"+1 480 292 7772",
    "sg:postcode":"85233",
    "sg:province":"AZ",
    "sg:tags":[
        "limestone",
        "lime"
    ],
    "wof:name":"Lime Magazine",
    "wof:placetype":"venue"
},
  "geometry": {"coordinates":[-111.80422299999999,33.375329],"type":"Point"}
}