{
  "type": "Feature",
  "properties": {
    "addr:full":"4190 W Milton Rd Tucson AZ 85746",
    "addr:housenumber":"4190",
    "addr:postcode":"85746",
    "addr:street":"W Milton Rd",
    "iso:country":"US",
    "sg:address":"4190 W Milton Rd",
    "sg:city":"Tucson",
    "sg:classifiers":[
        {
            "category":"Building & Trades",
            "subcategory":"Cleaning & Sanitation",
            "type":"Services"
        }
    ],
    "sg:phone":"+1 520 762 5923",
    "sg:postcode":"85746",
    "sg:province":"AZ",
    "sg:tags":[
        "janitor"
    ],
    "wof:name":"Kathy's Cleaning",
    "wof:placetype":"venue"
},
  "geometry": {"coordinates":[-111.053493,32.14644],"type":"Point"}
}