{
  "type": "Feature",
  "properties": {
    "addr:full":"4415 E Flower St Phoenix AZ 85018",
    "addr:housenumber":"4415",
    "addr:postcode":"85018",
    "addr:street":"E Flower St",
    "iso:country":"US",
    "sg:address":"4415 E Flower St",
    "sg:city":"Phoenix",
    "sg:classifiers":[
        {
            "category":"Shopping",
            "subcategory":"Florist",
            "type":"Retail Goods"
        }
    ],
    "sg:phone":"+1 602 667 5822",
    "sg:postcode":"85018",
    "sg:province":"AZ",
    "wof:name":"Flower Street Scene LLC",
    "wof:placetype":"venue"
},
  "geometry": {"coordinates":[-111.984335,33.485848],"type":"Point"}
}