{
  "type": "Feature",
  "properties": {
    "iso:country":"US",
    "sg:address":"1215 Sierra Dr",
    "sg:city":"Sierra Vista",
    "sg:classifiers":[
        {
            "category":"Organizations",
            "subcategory":"Religious Organization",
            "type":"Services"
        }
    ],
    "sg:phone":"+1 520 458 3995",
    "sg:postcode":"85635",
    "sg:province":"AZ",
    "sg:tags":[
        "church"
    ],
    "wof:name":"Sierra Vista Nazarene Church",
    "wof:placetype":"venue"
},
  "geometry": {"coordinates":[-110.285302,31.557335],"type":"Point"}
}