{
  "type": "Feature",
  "properties": {
    "iso:country":"US",
    "sg:address":"555 E Ray Rd",
    "sg:city":"Chandler",
    "sg:classifiers":[
        {
            "category":"Real Estate",
            "subcategory":"Real Estate Operator",
            "type":"Services"
        }
    ],
    "sg:phone":"+1 480 899 8862",
    "sg:postcode":"85225",
    "sg:province":"AZ",
    "sg:tags":[
        "building",
        "apartment"
    ],
    "wof:name":"Palm Terrace",
    "wof:placetype":"venue"
},
  "geometry": {"coordinates":[-111.83347500000001,33.320582],"type":"Point"}
}