{
  "type": "Feature",
  "properties": {
    "addr:full":"5808 W San Miguel Ave Glendale AZ 85301",
    "addr:housenumber":"5808",
    "addr:postcode":"85301",
    "addr:street":"W San Miguel Ave",
    "iso:country":"US",
    "sg:address":"5808 W San Miguel Ave",
    "sg:city":"Glendale",
    "sg:classifiers":[
        {
            "category":"Wholesale",
            "subcategory":"Construction Materials",
            "type":"Manufacturing & Wholesale Goods"
        }
    ],
    "sg:phone":"+1 623 847 7264",
    "sg:postcode":"85301",
    "sg:province":"AZ",
    "sg:tags":[
        "marble"
    ],
    "wof:name":"J L Marble & Granite",
    "wof:placetype":"venue"
},
  "geometry": {"coordinates":[-112.184022,33.519718],"type":"Point"}
}