{
  "type": "Feature",
  "properties": {
    "iso:country":"US",
    "sg:address":"660 S Tyler Ct",
    "sg:city":"Chandler",
    "sg:classifiers":[
        {
            "category":"Manufacturing",
            "subcategory":"Signs",
            "type":"Manufacturing & Wholesale Goods"
        }
    ],
    "sg:phone":"+1 602 615 3135",
    "sg:postcode":"85226",
    "sg:province":"AZ",
    "sg:tags":[
        "advertising",
        "specialty",
        "mfg"
    ],
    "sg:website":"signs-oflife.com/",
    "wof:name":"Signs Of Life",
    "wof:placetype":"venue"
},
  "geometry": {"coordinates":[-111.938942,33.293505],"type":"Point"}
}