{
  "type": "Feature",
  "properties": {
    "iso:country":"US",
    "sg:address":"4001 E Ryan Ave",
    "sg:city":"Kingman",
    "sg:classifiers":[
        {
            "category":"Professional",
            "subcategory":"Detective & Security Services",
            "type":"Services"
        }
    ],
    "sg:phone":"+1 928 757 1808",
    "sg:postcode":"86409",
    "sg:province":"AZ",
    "sg:tags":[
        "information",
        "bureau"
    ],
    "wof:name":"Douglas Beck",
    "wof:placetype":"venue"
},
  "geometry": {"coordinates":[-113.97643,35.259442],"type":"Point"}
}