{
  "type": "Feature",
  "properties": {
    "iso:country":"US",
    "sg:address":"1290 N Scottsdale Rd",
    "sg:city":"Tempe",
    "sg:classifiers":[
        {
            "category":"Shopping",
            "subcategory":"Clothing, Apparel, & Fashions",
            "type":"Retail Goods"
        }
    ],
    "sg:phone":"+1 480 829 7171",
    "sg:postcode":"85281",
    "sg:province":"AZ",
    "wof:name":"As Is Fashions",
    "wof:placetype":"venue"
},
  "geometry": {"coordinates":[-111.926382,33.442223],"type":"Point"}
}