{
  "type": "Feature",
  "properties": {
    "addr:full":"1590 Camino Ct Bullhead City AZ 86442",
    "addr:housenumber":"1590",
    "addr:postcode":"86442",
    "addr:street":"Camino Ct",
    "iso:country":"US",
    "sg:address":"1590 Camino Ct",
    "sg:city":"Bullhead City",
    "sg:classifiers":[
        {
            "category":"Farming",
            "subcategory":"Farm",
            "type":"Manufacturing & Wholesale Goods"
        }
    ],
    "sg:phone":"+1 928 758 1866",
    "sg:postcode":"86442",
    "sg:province":"AZ",
    "sg:tags":[
        "crop",
        "general"
    ],
    "wof:name":"Esperanza Farming",
    "wof:placetype":"venue"
},
  "geometry": {"coordinates":[-114.59916200000001,35.074187],"type":"Point"}
}