{
  "type": "Feature",
  "properties": {
    "iso:country":"US",
    "sg:address":"1590 Camino Ct",
    "sg:city":"Bullhead City",
    "sg:classifiers":[
        {
            "category":"Farming",
            "subcategory":"Farm",
            "type":"Manufacturing & Wholesale Goods"
        }
    ],
    "sg:phone":"+1 928 758 1866",
    "sg:postcode":"86442",
    "sg:province":"AZ",
    "sg:tags":[
        "crop",
        "general"
    ],
    "wof:name":"Esperanza Farming",
    "wof:placetype":"venue"
},
  "geometry": {"coordinates":[-114.599162,35.074187],"type":"Point"}
}