{
  "type": "Feature",
  "properties": {
    "iso:country":"US",
    "sg:address":"5642 W Carol Ave",
    "sg:city":"Glendale",
    "sg:classifiers":[
        {
            "category":"Professional",
            "subcategory":"Secretarial Services",
            "type":"Services"
        }
    ],
    "sg:phone":"+1 623 939 1199",
    "sg:postcode":"85302",
    "sg:province":"AZ",
    "sg:tags":[
        "proofreading"
    ],
    "wof:name":"Professional Proofreading",
    "wof:placetype":"venue"
},
  "geometry": {"coordinates":[-112.181172,33.571451],"type":"Point"}
}