{
  "type": "Feature",
  "properties": {
    "iso:country":"US",
    "sg:address":"5333 N 7th St",
    "sg:city":"Phoenix",
    "sg:classifiers":[
        {
            "category":"Professional",
            "subcategory":"Lawyer & Legal Services",
            "type":"Services"
        }
    ],
    "sg:phone":"+1 602 279 9777",
    "sg:postcode":"85014",
    "sg:province":"AZ",
    "sg:tags":[
        "attorney"
    ],
    "wof:name":"Klein Lundmark Barberich",
    "wof:placetype":"venue"
},
  "geometry": {"coordinates":[-112.064924,33.514815],"type":"Point"}
}