{
  "type": "Feature",
  "properties": {
    "iso:country":"US",
    "sg:address":"1800 Hwy 95",
    "sg:city":"Bullhead City",
    "sg:classifiers":[
        {
            "category":"Personal",
            "subcategory":"Beauty Salon",
            "type":"Services"
        }
    ],
    "sg:phone":"+1 928 704 7546",
    "sg:postcode":"86442",
    "sg:province":"AZ",
    "sg:tags":[
        "treatment",
        "skin"
    ],
    "wof:name":"Ageless Skin",
    "wof:placetype":"venue"
},
  "geometry": {"coordinates":[-114.58916600000001,35.120663],"type":"Point"}
}