{
  "type": "Feature",
  "properties": {
    "addr:full":"7310 N 16th St Phoenix AZ 85020",
    "addr:housenumber":"7310",
    "addr:postcode":"85020",
    "addr:street":"N 16Th St",
    "iso:country":"US",
    "sg:address":"7310 N 16th St",
    "sg:city":"Phoenix",
    "sg:classifiers":[
        {
            "category":"Insurance",
            "subcategory":"Insurance Agent",
            "type":"Services"
        }
    ],
    "sg:phone":"+1 602 870 7006",
    "sg:postcode":"85020",
    "sg:province":"AZ",
    "wof:name":"Cheryl D Dolby",
    "wof:placetype":"venue"
},
  "geometry": {"coordinates":[-112.047583,33.543796],"type":"Point"}
}