{
  "type": "Feature",
  "properties": {
    "iso:country":"US",
    "sg:address":"1139 E Huber St",
    "sg:city":"Mesa",
    "sg:classifiers":[
        {
            "category":"Professional",
            "subcategory":"Research",
            "type":"Services"
        },
        {
            "category":"Professional",
            "subcategory":"Business Services",
            "type":"Services"
        }
    ],
    "sg:phone":"+1 480 518 5106",
    "sg:postcode":"85203",
    "sg:province":"AZ",
    "sg:tags":[
        "development",
        "economic",
        "analysis"
    ],
    "wof:name":"Alaskan Business Services",
    "wof:placetype":"venue"
},
  "geometry": {"coordinates":[-111.807109,33.439788],"type":"Point"}
}