{
  "type": "Feature",
  "properties": {
    "iso:country":"US",
    "sg:address":"6145 N 36th Dr",
    "sg:city":"Phoenix",
    "sg:classifiers":[
        {
            "category":"Social Services",
            "subcategory":"Child Care",
            "type":"Services"
        }
    ],
    "sg:phone":"+1 602 374 4983",
    "sg:postcode":"85019",
    "sg:province":"AZ",
    "wof:name":"Rhema Christian Child Care",
    "wof:placetype":"venue"
},
  "geometry": {"coordinates":[-112.136866,33.526647],"type":"Point"}
}