{
  "type": "Feature",
  "properties": {
    "iso:country":"US",
    "sg:address":"2255 W Desert Cove Ave",
    "sg:city":"Phoenix",
    "sg:classifiers":[
        {
            "category":"Home & Garden",
            "subcategory":"Building Materials",
            "type":"Retail Goods"
        }
    ],
    "sg:phone":"+1 602 272 4001",
    "sg:postcode":"85029",
    "sg:province":"AZ",
    "sg:tags":[
        "glass",
        "window",
        "plate"
    ],
    "wof:name":"Ace Storefront & Glass",
    "wof:placetype":"venue"
},
  "geometry": {"coordinates":[-112.106602,33.585693],"type":"Point"}
}