{
  "type": "Feature",
  "properties": {
    "iso:country":"US",
    "sg:address":"2225 N Gemini Dr Ste E4",
    "sg:city":"Flagstaff",
    "sg:classifiers":[
        {
            "category":"Manufacturing",
            "subcategory":"Metals",
            "type":"Manufacturing & Wholesale Goods"
        },
        {
            "category":"Manufacturing",
            "subcategory":"Building Materials",
            "type":"Manufacturing & Wholesale Goods"
        }
    ],
    "sg:phone":"+1 928 863 3245",
    "sg:postcode":"86001",
    "sg:province":"AZ",
    "sg:tags":[
        "work-manufacturers",
        "fabricator",
        "work",
        "sheet"
    ],
    "wof:name":"Sedona Energy Labs, Limited Company",
    "wof:placetype":"venue"
},
  "geometry": {"coordinates":[-111.63262899999999,35.216358],"type":"Point"}
}