{
  "type": "Feature",
  "properties": {
    "iso:country":"US",
    "sg:address":"2358 E Tonto Pl",
    "sg:city":"Chandler",
    "sg:classifiers":[
        {
            "category":"Building & Trades",
            "subcategory":"Locksmith",
            "type":"Services"
        }
    ],
    "sg:phone":"+1 480 718 2452",
    "sg:postcode":"85249",
    "sg:province":"AZ",
    "sg:tags":[
        "key"
    ],
    "wof:name":"24 Emergency A Locksmith",
    "wof:placetype":"venue"
},
  "geometry": {"coordinates":[-111.800407,33.24156],"type":"Point"}
}