{
  "type": "Feature",
  "properties": {
    "iso:country":"US",
    "sg:address":"3411 N 5th Ave Ste 209",
    "sg:city":"Phoenix",
    "sg:classifiers":[
        {
            "category":"Shopping",
            "subcategory":"Pharmacy",
            "type":"Retail Goods"
        }
    ],
    "sg:phone":"+1 602 277 9507",
    "sg:postcode":"85013",
    "sg:province":"AZ",
    "wof:name":"Sanceutics Pharmacy",
    "wof:placetype":"venue"
},
  "geometry": {"coordinates":[-112.080878,33.487604],"type":"Point"}
}