{
  "type": "Feature",
  "properties": {
    "addr:full":"12601 N Cave Creek Rd Phoenix AZ 85022",
    "addr:housenumber":"12601",
    "addr:postcode":"85022",
    "addr:street":"N Cave Creek Rd",
    "iso:country":"US",
    "sg:address":"12601 N Cave Creek Rd",
    "sg:city":"Phoenix",
    "sg:classifiers":[
        {
            "category":"Organizations",
            "subcategory":"Religious Organization",
            "type":"Services"
        }
    ],
    "sg:phone":"+1 602 404 9757",
    "sg:postcode":"85022",
    "sg:province":"AZ",
    "wof:name":"Scott Hinkle Ministries",
    "wof:placetype":"venue"
},
  "geometry": {"coordinates":[-112.036931,33.602385],"type":"Point"}
}