{
  "type": "Feature",
  "properties": {
    "iso:country":"US",
    "sg:address":"7525 E Camelback Rd",
    "sg:city":"Scottsdale",
    "sg:classifiers":[
        {
            "category":"Communications",
            "subcategory":"Film & Video Production",
            "type":"Services"
        }
    ],
    "sg:phone":"+1 480 949 6817",
    "sg:postcode":"85251",
    "sg:province":"AZ",
    "sg:tags":[
        "taping"
    ],
    "wof:name":"Delta Productions",
    "wof:placetype":"venue"
},
  "geometry": {"coordinates":[-111.918064,33.50212],"type":"Point"}
}