{
  "type": "Feature",
  "properties": {
    "iso:country":"US",
    "sg:address":"3900 Northern Ave",
    "sg:city":"Kingman",
    "sg:classifiers":[
        {
            "category":"Building & Trades",
            "subcategory":"Construction",
            "type":"Services"
        }
    ],
    "sg:phone":"+1 928 757 0455",
    "sg:postcode":"86409",
    "sg:province":"AZ",
    "sg:tags":[
        "system",
        "contractor",
        "air conditioning"
    ],
    "wof:name":"A/C & Sons",
    "wof:placetype":"venue"
},
  "geometry": {"coordinates":[-113.980583,35.25386],"type":"Point"}
}