{
  "type": "Feature",
  "properties": {
    "iso:country":"US",
    "sg:address":"632 W Beale St",
    "sg:city":"Kingman",
    "sg:classifiers":[
        {
            "category":"Real Estate",
            "subcategory":"Real Estate Agent",
            "type":"Services"
        }
    ],
    "sg:phone":"+1 928 753 9060",
    "sg:postcode":"86401",
    "sg:province":"AZ",
    "wof:name":"E R Bruce Realty",
    "wof:placetype":"venue"
},
  "geometry": {"coordinates":[-114.064137,35.19053],"type":"Point"}
}