{
  "type": "Feature",
  "properties": {
    "addr:full":"1000 W Apache Trl Apache Junction AZ 85220",
    "addr:housenumber":"1000",
    "addr:postcode":"85220",
    "addr:street":"W Apache Trl",
    "iso:country":"US",
    "sg:address":"1000 W Apache Trl",
    "sg:city":"Apache Junction",
    "sg:classifiers":[
        {
            "category":"Insurance",
            "subcategory":"Insurance Agent",
            "type":"Services"
        }
    ],
    "sg:phone":"+1 480 633 2070",
    "sg:postcode":"85220",
    "sg:province":"AZ",
    "wof:name":"Randall Peterson",
    "wof:placetype":"venue"
},
  "geometry": {"coordinates":[-111.557475,33.41505],"type":"Point"}
}