{
  "type": "Feature",
  "properties": {
    "addr:full":"275 Rio Rico Dr Rio Rico AZ 85648",
    "addr:housenumber":"275",
    "addr:postcode":"85648",
    "addr:street":"Rio Rico Dr",
    "iso:country":"US",
    "sg:address":"275 Rio Rico Dr",
    "sg:city":"Rio Rico",
    "sg:classifiers":[
        {
            "category":"Building & Trades",
            "subcategory":"Construction",
            "type":"Services"
        }
    ],
    "sg:phone":"+1 520 281 8451",
    "sg:postcode":"85648",
    "sg:province":"AZ",
    "sg:tags":[
        "home",
        "builder"
    ],
    "wof:name":"Rio Rico Properties Inc",
    "wof:placetype":"venue"
},
  "geometry": {"coordinates":[-110.992609,31.469685],"type":"Point"}
}