{
  "type": "Feature",
  "properties": {
    "iso:country":"US",
    "sg:address":"245 N Power Rd",
    "sg:city":"Mesa",
    "sg:classifiers":[
        {
            "category":"Retail",
            "subcategory":"Veterinary Services",
            "type":"Services"
        }
    ],
    "sg:phone":"+1 480 807 7797",
    "sg:postcode":"85205",
    "sg:province":"AZ",
    "sg:tags":[
        "veterinarian"
    ],
    "wof:name":"Pet Haven Animal Hospital",
    "wof:placetype":"venue"
},
  "geometry": {"coordinates":[-111.684506,33.419434],"type":"Point"}
}