{
  "type": "Feature",
  "properties": {
    "iso:country":"US",
    "sg:address":"2700 E Executive Dr",
    "sg:city":"Tucson",
    "sg:classifiers":[
        {
            "category":"Manufacturing",
            "subcategory":"Retail Goods",
            "type":"Manufacturing & Wholesale Goods"
        }
    ],
    "sg:phone":"+1 520 547 4070",
    "sg:postcode":"85706",
    "sg:province":"AZ",
    "sg:tags":[
        "manufacturer"
    ],
    "wof:name":"Rigaku",
    "wof:placetype":"venue"
},
  "geometry": {"coordinates":[-110.933212,32.1323],"type":"Point"}
}