{
  "type": "Feature",
  "properties": {
    "iso:country":"US",
    "sg:address":"18637 N 27th St",
    "sg:city":"Phoenix",
    "sg:classifiers":[
        {
            "category":"Real Estate",
            "subcategory":"Real Estate Operator",
            "type":"Services"
        }
    ],
    "sg:phone":"+1 602 418 5524",
    "sg:postcode":"85050",
    "sg:province":"AZ",
    "sg:tags":[
        "building",
        "nonresidential"
    ],
    "wof:name":"Sunset Canyon Properties",
    "wof:placetype":"venue"
},
  "geometry": {"coordinates":[-112.024387,33.658702],"type":"Point"}
}