{
  "type": "Feature",
  "properties": {
    "addr:full":"1631 Cal Edison Laughlin NV 89028",
    "addr:housenumber":"1631",
    "addr:postcode":"nv 89028",
    "addr:street":"Cal Edison",
    "iso:country":"US",
    "sg:address":"1631 Cal Edison",
    "sg:city":"Laughlin",
    "sg:classifiers":[
        {
            "category":"Real Estate",
            "subcategory":"Developer",
            "type":"Services"
        }
    ],
    "sg:phone":"+1 702 298 3360",
    "sg:postcode":"89028",
    "sg:province":"NV",
    "wof:name":"Bilbray Industries",
    "wof:placetype":"venue"
},
  "geometry": {"coordinates":[-114.616743,35.135195],"type":"Point"}
}