{
  "type": "Feature",
  "properties": {
    "iso:country":"US",
    "sg:address":"86 S Main St",
    "sg:city":"Pima",
    "sg:classifiers":[
        {
            "category":"Retail",
            "subcategory":"Repair Shop",
            "type":"Services"
        }
    ],
    "sg:phone":"+1 928 485 2491",
    "sg:postcode":"85543",
    "sg:province":"AZ",
    "sg:tags":[
        "welder",
        "welding"
    ],
    "wof:name":"Bills Welding",
    "wof:placetype":"venue"
},
  "geometry": {"coordinates":[-109.827189,32.894631],"type":"Point"}
}