{
  "type": "Feature",
  "properties": {
    "addr:full":"302 S 28th St Phoenix AZ 85034",
    "addr:housenumber":"302",
    "addr:postcode":"85034",
    "addr:street":"S 28Th St",
    "iso:country":"US",
    "sg:address":"302 S 28th St",
    "sg:city":"Phoenix",
    "sg:classifiers":[
        {
            "category":"Utilities",
            "subcategory":"Recycling",
            "type":"Services"
        },
        {
            "category":"Professional",
            "subcategory":"Business Services",
            "type":"Services"
        },
        {
            "category":"Real Estate",
            "subcategory":"Architect",
            "type":"Services"
        }
    ],
    "sg:phone":"+1 602 267 8740",
    "sg:postcode":"85034",
    "sg:province":"AZ",
    "sg:tags":[
        "record",
        "document",
        "destruction"
    ],
    "sg:website":"http://www.acbvi.org",
    "wof:name":"Arizona Center For The Blind & Visually Impaired Recycling Center Inc",
    "wof:placetype":"venue"
},
  "geometry": {"coordinates":[-112.02158900000001,33.445432],"type":"Point"}
}