{
  "type": "Feature",
  "properties": {
    "iso:country":"US",
    "sg:address":"520 N Bullard Ave",
    "sg:city":"Goodyear",
    "sg:classifiers":[
        {
            "category":"Manufacturing",
            "subcategory":"Tools & Machinery",
            "type":"Manufacturing & Wholesale Goods"
        },
        {
            "category":"Manufacturing",
            "subcategory":"Buildings",
            "type":"Manufacturing & Wholesale Goods"
        },
        {
            "category":"Building & Trades",
            "subcategory":"Construction",
            "type":"Services"
        }
    ],
    "sg:phone":"+1 480 655 3170",
    "sg:postcode":"85338",
    "sg:province":"AZ",
    "sg:tags":[
        "equipment",
        "builder",
        "contractor",
        "home"
    ],
    "wof:name":"Orco Construction Supplies",
    "wof:placetype":"venue"
},
  "geometry": {"coordinates":[-112.37552599999999,33.450846],"type":"Point"}
}