{
  "type": "Feature",
  "properties": {
    "iso:country":"US",
    "sg:address":"15583 N 176th Ln",
    "sg:city":"Surprise",
    "sg:classifiers":[
        {
            "category":"Personal",
            "subcategory":"Beauty Salon",
            "type":"Services"
        }
    ],
    "sg:phone":"+1 623 680 3325",
    "sg:postcode":"85388",
    "sg:province":"AZ",
    "wof:name":"Arizona Wedding And Event Gall",
    "wof:placetype":"venue"
},
  "geometry": {"coordinates":[-112.438759,33.625974],"type":"Point"}
}