{
  "type": "Feature",
  "properties": {
    "addr:full":"1016 E Southern Ave Phoenix AZ 85040",
    "addr:housenumber":"1016",
    "addr:postcode":"85040",
    "addr:street":"E Southern Ave",
    "iso:country":"US",
    "sg:address":"1016 E Southern Ave",
    "sg:city":"Phoenix",
    "sg:classifiers":[
        {
            "category":"Retail",
            "subcategory":"Auto Repair",
            "type":"Services"
        }
    ],
    "sg:phone":"+1 602 323 0231",
    "sg:postcode":"85040",
    "sg:province":"AZ",
    "sg:tags":[
        "repairing",
        "automobile"
    ],
    "wof:name":"Charley's Auto",
    "wof:placetype":"venue"
},
  "geometry": {"coordinates":[-112.05724600000001,33.392349],"type":"Point"}
}