{
  "type": "Feature",
  "properties": {
    "addr:full":"4941 E 29th St Tucson AZ 85711",
    "addr:housenumber":"4941",
    "addr:postcode":"85711",
    "addr:street":"E 29Th St",
    "iso:country":"US",
    "sg:address":"4941 E 29th St",
    "sg:city":"Tucson",
    "sg:classifiers":[
        {
            "category":"Retail",
            "subcategory":"Auto Repair",
            "type":"Services"
        }
    ],
    "sg:phone":"+1 520 822 8471",
    "sg:postcode":"85711",
    "sg:province":"AZ",
    "sg:tags":[
        "repairing",
        "automobile"
    ],
    "wof:name":"Direct Buy Automotive Group",
    "wof:placetype":"venue"
},
  "geometry": {"coordinates":[-110.886323,32.199773],"type":"Point"}
}