{
  "type": "Feature",
  "properties": {
    "iso:country":"US",
    "sg:address":"1701 W Pershing Ave",
    "sg:city":"Phoenix",
    "sg:classifiers":[
        {
            "category":"Government",
            "subcategory":"Office",
            "type":"Public Place"
        }
    ],
    "sg:phone":"+1 602 942 3956",
    "sg:postcode":"85029",
    "sg:province":"AZ",
    "sg:tags":[
        "administrative",
        "program",
        "health"
    ],
    "wof:name":"Rhonda L Ewing",
    "wof:placetype":"venue"
},
  "geometry": {"coordinates":[-112.096825,33.605843],"type":"Point"}
}