{
  "type": "Feature",
  "properties": {
    "addr:full":"4943 W McLellan Rd Glendale AZ 85301",
    "addr:housenumber":"4943",
    "addr:postcode":"85301",
    "addr:street":"W Mclellan Rd",
    "iso:country":"US",
    "sg:address":"4943 W McLellan Rd",
    "sg:city":"Glendale",
    "sg:classifiers":[
        {
            "category":"Building & Trades",
            "subcategory":"Construction",
            "type":"Services"
        }
    ],
    "sg:phone":"+1 623 937 5742",
    "sg:postcode":"85301",
    "sg:province":"AZ",
    "sg:tags":[
        "contractor"
    ],
    "wof:name":"Juan Garcia Tile Contracting",
    "wof:placetype":"venue"
},
  "geometry": {"coordinates":[-112.167874,33.53281],"type":"Point"}
}