{
  "type": "Feature",
  "properties": {
    "addr:full":"4213 S 43rd Pl Phoenix AZ 85040",
    "addr:housenumber":"4213",
    "addr:postcode":"85040",
    "addr:street":"S 43Rd Pl",
    "iso:country":"US",
    "sg:address":"4213 S 43rd Pl",
    "sg:city":"Phoenix",
    "sg:classifiers":[
        {
            "category":"Retail",
            "subcategory":"Repair Shop",
            "type":"Services"
        }
    ],
    "sg:phone":"+1 602 233 2555",
    "sg:postcode":"85040",
    "sg:province":"AZ",
    "sg:tags":[
        "oil",
        "field",
        "mfg",
        "equipment",
        "part",
        "crane"
    ],
    "wof:name":"Crane & Hoist of Arizona Inc",
    "wof:placetype":"venue"
},
  "geometry": {"coordinates":[-111.987831,33.408758],"type":"Point"}
}