{
  "type": "Feature",
  "properties": {
    "addr:full":"7026 W Pinnacle Peak Rd Peoria AZ 85383",
    "addr:housenumber":"7026",
    "addr:postcode":"85383",
    "addr:street":"W Pinnacle Peak Rd",
    "iso:country":"US",
    "sg:address":"7026 W Pinnacle Peak Rd",
    "sg:city":"Peoria",
    "sg:classifiers":[
        {
            "category":"Professional",
            "subcategory":"Accounting & Tax Preparation",
            "type":"Services"
        }
    ],
    "sg:phone":"+1 623 376 9090",
    "sg:postcode":"85383",
    "sg:province":"AZ",
    "sg:tags":[
        "billing"
    ],
    "wof:name":"Contract Medical Svc Inc",
    "wof:placetype":"venue"
},
  "geometry": {"coordinates":[-112.212566,33.696403],"type":"Point"}
}