{
  "type": "Feature",
  "properties": {
    "addr:full":"8480 N Continential Links Dr Tucson AZ 85743",
    "addr:housenumber":"8480",
    "addr:postcode":"85743",
    "addr:street":"N Continential Links Dr",
    "iso:country":"US",
    "sg:address":"8480 N Continential Links Dr",
    "sg:city":"Tucson",
    "sg:classifiers":[
        {
            "category":"Sports & Exercise",
            "subcategory":"Golf",
            "type":"Entertainment"
        }
    ],
    "sg:phone":"+1 520 744 7443",
    "sg:postcode":"85743",
    "sg:province":"AZ",
    "sg:tags":[
        "course"
    ],
    "sg:website":"www.playthepines.com",
    "wof:name":"Pines Golf Club At Marana",
    "wof:placetype":"venue"
},
  "geometry": {"coordinates":[-111.100725,32.362572],"type":"Point"}
}