{
  "type": "Feature",
  "properties": {
    "iso:country":"US",
    "sg:address":"36889 N Tom Darlington Dr",
    "sg:city":"Carefree",
    "sg:classifiers":[
        {
            "category":"Building & Trades",
            "subcategory":"Construction",
            "type":"Services"
        }
    ],
    "sg:phone":"+1 480 595 0171",
    "sg:postcode":"85377",
    "sg:province":"AZ",
    "sg:tags":[
        "interior",
        "design"
    ],
    "wof:name":"Bickerdyke Sue Interiors",
    "wof:placetype":"venue"
},
  "geometry": {"coordinates":[-111.952003,33.833099],"type":"Point"}
}