{
  "type": "Feature",
  "properties": {
    "iso:country":"US",
    "sg:address":"660 W Cll de Marzo",
    "sg:city":"Green Valley",
    "sg:classifiers":[
        {
            "category":"Shopping",
            "subcategory":"Computers & Home Electronics",
            "type":"Retail Goods"
        }
    ],
    "sg:phone":"+1 520 625 8390",
    "sg:postcode":"85614",
    "sg:province":"AZ",
    "sg:tags":[
        "software"
    ],
    "wof:name":"Can Com Computing",
    "wof:placetype":"venue"
},
  "geometry": {"coordinates":[-110.979802,31.921586],"type":"Point"}
}