{
  "type": "Feature",
  "properties": {
    "iso:country":"US",
    "sg:address":"2302 N 7th St",
    "sg:city":"Phoenix",
    "sg:classifiers":[
        {
            "category":"Health Services",
            "subcategory":"Hospital",
            "type":"Services"
        }
    ],
    "sg:phone":"+1 602 424 1600",
    "sg:postcode":"85006",
    "sg:province":"AZ",
    "sg:tags":[
        "mental"
    ],
    "wof:name":"American Indian Prevention",
    "wof:placetype":"venue"
},
  "geometry": {"coordinates":[-112.065165,33.474764],"type":"Point"}
}