{
  "type": "Feature",
  "properties": {
    "addr:full":"16220 W Boulder Dr Surprise AZ 85374",
    "addr:housenumber":"16220",
    "addr:postcode":"85374",
    "addr:street":"W Boulder Dr",
    "iso:country":"US",
    "sg:address":"16220 W Boulder Dr",
    "sg:city":"Surprise",
    "sg:classifiers":[
        {
            "category":"Structure",
            "subcategory":"Office Building",
            "type":"Public Place"
        }
    ],
    "sg:phone":"+1 623 556 0685",
    "sg:postcode":"85374",
    "sg:province":"AZ",
    "sg:tags":[
        "park"
    ],
    "wof:name":"Frog Hollow Property 4",
    "wof:placetype":"venue"
},
  "geometry": {"coordinates":[-112.40844,33.652346],"type":"Point"}
}