{
  "type": "Feature",
  "properties": {
    "iso:country":"US",
    "sg:address":"970 E Fry Blvd",
    "sg:city":"Sierra Vista",
    "sg:classifiers":[
        {
            "category":"Shopping",
            "subcategory":"Clothing, Apparel, & Fashions",
            "type":"Retail Goods"
        }
    ],
    "sg:phone":"+1 520 458 0112",
    "sg:postcode":"85635",
    "sg:province":"AZ",
    "wof:name":"Main Street Styles",
    "wof:placetype":"venue"
},
  "geometry": {"coordinates":[-110.289644,31.554565],"type":"Point"}
}