{
  "type": "Feature",
  "properties": {
    "iso:country":"US",
    "sg:address":"141 E Palm Ln Ste 205",
    "sg:city":"Phoenix",
    "sg:classifiers":[
        {
            "category":"Manufacturing",
            "subcategory":"Buildings",
            "type":"Manufacturing & Wholesale Goods"
        },
        {
            "category":"Building & Trades",
            "subcategory":"Construction",
            "type":"Services"
        }
    ],
    "sg:phone":"+1 602 265 8339",
    "sg:postcode":"85004",
    "sg:province":"AZ",
    "sg:tags":[
        "industrial",
        "specialty",
        "builder",
        "heating",
        "contractor",
        "contractors-commercial",
        "home"
    ],
    "wof:name":"Brignall Construction Co., Inc.",
    "wof:placetype":"venue"
},
  "geometry": {"coordinates":[-112.070638,33.469372],"type":"Point"}
}