{
  "type": "Feature",
  "properties": {
    "iso:country":"US",
    "sg:address":"5151 N 16th St Ste 134",
    "sg:city":"Phoenix",
    "sg:classifiers":[
        {
            "category":"Manufacturing",
            "subcategory":"Tools & Machinery",
            "type":"Manufacturing & Wholesale Goods"
        },
        {
            "category":"Manufacturing",
            "subcategory":"Electronics",
            "type":"Manufacturing & Wholesale Goods"
        },
        {
            "category":"Shopping",
            "subcategory":"Computers & Home Electronics",
            "type":"Retail Goods"
        }
    ],
    "sg:phone":"+1 602 279 5776",
    "sg:postcode":"85016",
    "sg:province":"AZ",
    "sg:tags":[
        "electric",
        "consumer",
        "equipment-testing",
        "equipment",
        "supplies-wholesale",
        "manufacturer"
    ],
    "wof:name":"Wagner Group",
    "wof:placetype":"venue"
},
  "geometry": {"coordinates":[-112.047531,33.511955],"type":"Point"}
}