{
  "type": "Feature",
  "properties": {
    "iso:country":"US",
    "sg:address":"7283 W Basie Ct",
    "sg:city":"Tucson",
    "sg:classifiers":[
        {
            "category":"Autos & Motor Vehicles",
            "subcategory":"Automobile Sales",
            "type":"Retail Goods"
        }
    ],
    "sg:phone":"+1 520 548 1534",
    "sg:postcode":"85743",
    "sg:province":"AZ",
    "sg:tags":[
        "dealers-used",
        "car",
        "used",
        "cars-wholesale"
    ],
    "wof:name":"Island Empire Wholesale Automotive",
    "wof:placetype":"venue"
},
  "geometry": {"coordinates":[-111.120529,32.349735],"type":"Point"}
}