{
  "type": "Feature",
  "properties": {
    "addr:full":"7401 N la Cholla Blvd # 199 Tucson AZ 85741",
    "addr:housenumber":"7401",
    "addr:postcode":"85741",
    "addr:street":"N La Cholla Blvd # 199",
    "iso:country":"US",
    "sg:address":"7401 N la Cholla Blvd # 199",
    "sg:city":"Tucson",
    "sg:classifiers":[
        {
            "category":"Shopping",
            "subcategory":"Clothing, Apparel, & Fashions",
            "type":"Retail Goods"
        },
        {
            "category":"Shopping",
            "subcategory":"Party Supplies",
            "type":"Retail Goods"
        }
    ],
    "sg:phone":"+1 520 616 2800",
    "sg:postcode":"85741",
    "sg:province":"AZ",
    "sg:tags":[
        "decoration",
        "favors",
        "delivery",
        "balloons-retail",
        "costume"
    ],
    "sg:website":"http://www.partycity.com",
    "wof:name":"Party City",
    "wof:placetype":"venue"
},
  "geometry": {"coordinates":[-111.012852,32.341553],"type":"Point"}
}