{
  "type": "Feature",
  "properties": {
    "addr:full":"540 S West Rd Wickenburg AZ 85390",
    "addr:housenumber":"540",
    "addr:postcode":"85390",
    "addr:street":"S West Rd",
    "iso:country":"US",
    "sg:address":"540 S West Rd",
    "sg:city":"Wickenburg",
    "sg:classifiers":[
        {
            "category":"Building & Trades",
            "subcategory":"Construction",
            "type":"Services"
        }
    ],
    "sg:phone":"+1 928 684 1215",
    "sg:postcode":"85390",
    "sg:province":"AZ",
    "sg:tags":[
        "contractor"
    ],
    "wof:name":"Ricke Builders Inc",
    "wof:placetype":"venue"
},
  "geometry": {"coordinates":[-112.769761,33.959213],"type":"Point"}
}