{
  "type": "Feature",
  "properties": {
    "iso:country":"US",
    "sg:address":"2103 E Cedar St",
    "sg:city":"Tempe",
    "sg:classifiers":[
        {
            "category":"Restaurant",
            "type":"Food & Drink"
        }
    ],
    "sg:phone":"+1 480 736 1065",
    "sg:postcode":"85281",
    "sg:province":"AZ",
    "sg:tags":[
        "eating"
    ],
    "wof:name":"Virtual Resellers",
    "wof:placetype":"venue"
},
  "geometry": {"coordinates":[-111.895899,33.411961],"type":"Point"}
}