{
  "type": "Feature",
  "properties": {
    "iso:country":"US",
    "sg:address":"1795 E Skyline Dr",
    "sg:city":"Tucson",
    "sg:classifiers":[
        {
            "category":"Professional",
            "subcategory":"Management & Consulting",
            "type":"Services"
        }
    ],
    "sg:phone":"+1 520 219 1800",
    "sg:postcode":"85718",
    "sg:province":"AZ",
    "wof:name":"Presidio Group Wealth Mgmt",
    "wof:placetype":"venue"
},
  "geometry": {"coordinates":[-110.946443,32.335142],"type":"Point"}
}