{
  "type": "Feature",
  "properties": {
    "addr:full":"6717 N 59th Ave Glendale AZ 85301",
    "addr:housenumber":"6717",
    "addr:postcode":"85301",
    "addr:street":"N 59Th Ave",
    "iso:country":"US",
    "sg:address":"6717 N 59th Ave",
    "sg:city":"Glendale",
    "sg:classifiers":[
        {
            "category":"Health Services",
            "subcategory":"Doctor",
            "type":"Services"
        }
    ],
    "sg:phone":"+1 623 939 1411",
    "sg:postcode":"85301",
    "sg:province":"AZ",
    "sg:tags":[
        "physician",
        "surgeon"
    ],
    "wof:name":"Glendale Family Clinic",
    "wof:placetype":"venue"
},
  "geometry": {"coordinates":[-112.18613499999999,33.536422],"type":"Point"}
}