{
  "type": "Feature",
  "properties": {
    "addr:full":"9792 E Larry Hughes Dr Scottsdale AZ 85262",
    "addr:housenumber":"9792",
    "addr:postcode":"85262",
    "addr:street":"E Larry Hughes Dr",
    "iso:country":"US",
    "sg:address":"9792 E Larry Hughes Dr",
    "sg:city":"Scottsdale",
    "sg:classifiers":[
        {
            "category":"Recreation",
            "type":"Entertainment"
        }
    ],
    "sg:phone":"+1 480 595 4200",
    "sg:postcode":"85262",
    "sg:province":"AZ",
    "sg:tags":[
        "course",
        "golf"
    ],
    "wof:name":"Cochise-Geronimo Maintenance",
    "wof:placetype":"venue"
},
  "geometry": {"coordinates":[-111.869956,33.843739],"type":"Point"}
}