{
  "type": "Feature",
  "properties": {
    "iso:country":"US",
    "sg:address":"174 Bahia Ln W",
    "sg:city":"Litchfield Park",
    "sg:classifiers":[
        {
            "category":"Retail",
            "subcategory":"Laundry & Dry Cleaning",
            "type":"Services"
        }
    ],
    "sg:phone":"+1 480 488 2505",
    "sg:postcode":"85340",
    "sg:province":"AZ",
    "sg:tags":[
        "cleaners",
        "rug",
        "carpet"
    ],
    "wof:name":"Air Quality Control",
    "wof:placetype":"venue"
},
  "geometry": {"coordinates":[-112.35542100000001,33.491069],"type":"Point"}
}