{
  "type": "Feature",
  "properties": {
    "addr:full":"15937 W Monte Cristo Ave Surprise AZ 85374",
    "addr:housenumber":"15937",
    "addr:postcode":"85374",
    "addr:street":"W Monte Cristo Ave",
    "iso:country":"US",
    "sg:address":"15937 W Monte Cristo Ave",
    "sg:city":"Surprise",
    "sg:classifiers":[
        {
            "category":"Professional",
            "subcategory":"Lawyer & Legal Services",
            "type":"Services"
        }
    ],
    "sg:phone":"+1 623 266 3355",
    "sg:postcode":"85374",
    "sg:province":"AZ",
    "sg:tags":[
        "planning",
        "estate"
    ],
    "wof:name":"Estate Planning Consultants",
    "wof:placetype":"venue"
},
  "geometry": {"coordinates":[-112.407426,33.630117],"type":"Point"}
}