{
  "type": "Feature",
  "properties": {
    "iso:country":"US",
    "sg:address":"2530 N 7th St",
    "sg:city":"Phoenix",
    "sg:classifiers":[
        {
            "category":"Shopping",
            "subcategory":"Clothing, Apparel, & Fashions",
            "type":"Retail Goods"
        }
    ],
    "sg:phone":"+1 602 252 5660",
    "sg:postcode":"85006",
    "sg:province":"AZ",
    "sg:tags":[
        "swimwear",
        "accessory"
    ],
    "wof:name":"Euphoria Body Wear LLC",
    "wof:placetype":"venue"
},
  "geometry": {"coordinates":[-112.065166,33.476057],"type":"Point"}
}