{
  "type": "Feature",
  "properties": {
    "addr:full":"3217 S 66th Ave Phoenix AZ 85043",
    "addr:housenumber":"3217",
    "addr:postcode":"85043",
    "addr:street":"S 66Th Ave",
    "iso:country":"US",
    "sg:address":"3217 S 66th Ave",
    "sg:city":"Phoenix",
    "sg:classifiers":[
        {
            "category":"Home & Garden",
            "subcategory":"Home Furnishings",
            "type":"Retail Goods"
        }
    ],
    "sg:phone":"+1 623 936 7099",
    "sg:postcode":"85043",
    "sg:province":"AZ",
    "wof:name":"Harmony Windows",
    "wof:placetype":"venue"
},
  "geometry": {"coordinates":[-112.201803,33.418704],"type":"Point"}
}