{
  "type": "Feature",
  "properties": {
    "iso:country":"US",
    "sg:address":"1329 N 29th Ave Ste 9",
    "sg:city":"Phoenix",
    "sg:classifiers":[
        {
            "category":"Building & Trades",
            "subcategory":"Construction",
            "type":"Services"
        }
    ],
    "sg:phone":"+1 602 374 7305",
    "sg:postcode":"85009",
    "sg:province":"AZ",
    "sg:tags":[
        "finishing",
        "wood"
    ],
    "wof:name":"Dyad, Inc.",
    "wof:placetype":"venue"
},
  "geometry": {"coordinates":[-112.121514,33.46345],"type":"Point"}
}