{
  "type": "Feature",
  "properties": {
    "iso:country":"US",
    "sg:address":"1550 E Indian School Rd",
    "sg:city":"Phoenix",
    "sg:classifiers":[
        {
            "category":"Health Services",
            "subcategory":"Doctor",
            "type":"Services"
        }
    ],
    "sg:phone":"+1 602 263 1200",
    "sg:postcode":"85014",
    "sg:province":"AZ",
    "sg:tags":[
        "physician",
        "surgeon"
    ],
    "sg:website":"www.nih.gov",
    "wof:name":"National Institutes Of Health",
    "wof:placetype":"venue"
},
  "geometry": {"coordinates":[-112.047966,33.494797],"type":"Point"}
}