{
  "type": "Feature",
  "properties": {
    "iso:country":"US",
    "sg:address":"2001 N Ajo Gila Bend Hwy",
    "sg:city":"Ajo",
    "sg:classifiers":[
        {
            "category":"Communications",
            "type":"Services"
        },
        {
            "category":"Wholesale",
            "subcategory":"Electrical",
            "type":"Manufacturing & Wholesale Goods"
        }
    ],
    "sg:phone":"+1 520 387 6773",
    "sg:postcode":"85321",
    "sg:province":"AZ",
    "sg:tags":[
        "electronic"
    ],
    "wof:name":"Pacific Communications Pay Pho",
    "wof:placetype":"venue"
},
  "geometry": {"coordinates":[-112.872131,32.394132],"type":"Point"}
}