{
  "type": "Feature",
  "properties": {
    "iso:country":"US",
    "sg:address":"9758 E Cannon Pl",
    "sg:city":"Tucson",
    "sg:classifiers":[
        {
            "category":"Building & Trades",
            "subcategory":"Construction",
            "type":"Services"
        }
    ],
    "sg:phone":"+1 520 405 1087",
    "sg:postcode":"85748",
    "sg:province":"AZ",
    "sg:tags":[
        "coping",
        "plastering",
        "tiling",
        "pool",
        "swimming"
    ],
    "wof:name":"Blue Ribbon Pool Svc",
    "wof:placetype":"venue"
},
  "geometry": {"coordinates":[-110.78368,32.224896],"type":"Point"}
}