{
  "type": "Feature",
  "properties": {
    "iso:country":"US",
    "sg:address":"3702 W Wagoner Rd",
    "sg:city":"Glendale",
    "sg:classifiers":[
        {
            "category":"Shopping",
            "subcategory":"Pets & Pet Supplies",
            "type":"Retail Goods"
        },
        {
            "category":"Retail",
            "subcategory":"Animal Services",
            "type":"Services"
        }
    ],
    "sg:phone":"+1 602 548 0194",
    "sg:postcode":"85308",
    "sg:province":"AZ",
    "sg:tags":[
        "grooming",
        "dog",
        "cat"
    ],
    "wof:name":"Skyler Van Gogh",
    "wof:placetype":"venue"
},
  "geometry": {"coordinates":[-112.139395,33.6533],"type":"Point"}
}