{
  "type": "Feature",
  "properties": {
    "addr:full":"1440 E Washington St Phoenix AZ 85034",
    "addr:housenumber":"1440",
    "addr:postcode":"85034",
    "addr:street":"E Washington St",
    "iso:country":"US",
    "sg:address":"1440 E Washington St",
    "sg:city":"Phoenix",
    "sg:classifiers":[
        {
            "category":"Professional",
            "subcategory":"Lawyer & Legal Services",
            "type":"Services"
        }
    ],
    "sg:phone":"+1 602 258 8400",
    "sg:postcode":"85034",
    "sg:province":"AZ",
    "sg:tags":[
        "attorney"
    ],
    "wof:name":"Dixon Law Offices",
    "wof:placetype":"venue"
},
  "geometry": {"coordinates":[-112.050625,33.448381],"type":"Point"}
}