{
  "type": "Feature",
  "properties": {
    "addr:full":"4315 E Thunderbird Rd Phoenix AZ 85032",
    "addr:housenumber":"4315",
    "addr:postcode":"85032",
    "addr:street":"E Thunderbird Rd",
    "iso:country":"US",
    "sg:address":"4315 E Thunderbird Rd",
    "sg:city":"Phoenix",
    "sg:classifiers":[
        {
            "category":"Shopping",
            "subcategory":"Catalog Store",
            "type":"Retail Goods"
        }
    ],
    "sg:phone":"+1 773 485 8173",
    "sg:postcode":"85032",
    "sg:province":"AZ",
    "sg:tags":[
        "mail",
        "house"
    ],
    "wof:name":"Garnetts Collectibles",
    "wof:placetype":"venue"
},
  "geometry": {"coordinates":[-111.98853200000001,33.611672],"type":"Point"}
}