{
  "type": "Feature",
  "properties": {
    "addr:full":"2419 S 4th Ave Tucson AZ 85713",
    "addr:housenumber":"2419",
    "addr:postcode":"85713",
    "addr:street":"S 4Th Ave",
    "iso:country":"US",
    "sg:address":"2419 S 4th Ave",
    "sg:city":"Tucson",
    "sg:classifiers":[
        {
            "category":"Manufacturing",
            "subcategory":"Tools & Machinery",
            "type":"Manufacturing & Wholesale Goods"
        }
    ],
    "sg:phone":"+1 520 882 0325",
    "sg:postcode":"85713",
    "sg:province":"AZ",
    "sg:tags":[
        "equipment",
        "system",
        "vacuum"
    ],
    "wof:name":"Compressor & Equipment Co",
    "wof:placetype":"venue"
},
  "geometry": {"coordinates":[-110.965225,32.19366],"type":"Point"}
}