{
  "type": "Feature",
  "properties": {
    "iso:country":"US",
    "sg:address":"16605 N 56th St",
    "sg:city":"Scottsdale",
    "sg:phone":"+1 602 765 1440",
    "sg:postcode":"85254",
    "sg:province":"AZ",
    "sg:website":"http://www.kindercare.com/our-centers/center-details/000015/?cid=YP_KC000015",
    "wof:name":"Aire Libre KinderCare",
    "wof:placetype":"venue"
},
  "geometry": {"coordinates":[-111.960327,33.636925],"type":"Point"}
}