{
  "type": "Feature",
  "properties": {
    "addr:full":"4113 E Silverwood Dr Phoenix AZ 85048",
    "addr:housenumber":"4113",
    "addr:postcode":"85048",
    "addr:street":"E Silverwood Dr",
    "iso:country":"US",
    "sg:address":"4113 E Silverwood Dr",
    "sg:city":"Phoenix",
    "sg:classifiers":[
        {
            "category":"Building & Trades",
            "subcategory":"Construction",
            "type":"Services"
        }
    ],
    "sg:phone":"+1 480 706 1503",
    "sg:postcode":"85048",
    "sg:province":"AZ",
    "sg:tags":[
        "general",
        "contractor"
    ],
    "wof:name":"Cathryn Anne Construction",
    "wof:placetype":"venue"
},
  "geometry": {"coordinates":[-111.99298400000001,33.299959],"type":"Point"}
}