{
  "type": "Feature",
  "properties": {
    "iso:country":"US",
    "sg:address":"8621 N 79th Ave",
    "sg:city":"Peoria",
    "sg:classifiers":[
        {
            "category":"Building & Trades",
            "subcategory":"Construction",
            "type":"Services"
        },
        {
            "category":"Home & Garden",
            "subcategory":"Furniture",
            "type":"Retail Goods"
        }
    ],
    "sg:phone":"+1 623 486 7150",
    "sg:postcode":"85345",
    "sg:province":"AZ",
    "sg:tags":[
        "cabinet",
        "carpentry",
        "contractor"
    ],
    "wof:name":"Custom Woodcraft Inc",
    "wof:placetype":"venue"
},
  "geometry": {"coordinates":[-112.228928,33.56334],"type":"Point"}
}