{
  "type": "Feature",
  "properties": {
    "addr:full":"5653 Hwy 95 Fort Mohave AZ 86426",
    "addr:housenumber":"5653",
    "addr:postcode":"86426",
    "addr:street":"Hwy 95",
    "iso:country":"US",
    "sg:address":"5653 Hwy 95",
    "sg:city":"Fort Mohave",
    "sg:classifiers":[
        {
            "category":"Health Services",
            "subcategory":"Doctor",
            "type":"Services"
        }
    ],
    "sg:phone":"+1 928 768 2558",
    "sg:postcode":"86426",
    "sg:province":"AZ",
    "sg:tags":[
        "physician",
        "surgeon"
    ],
    "wof:name":"Colorado River Medical Ctr",
    "wof:placetype":"venue"
},
  "geometry": {"coordinates":[-114.598124,34.992444],"type":"Point"}
}