{
  "type": "Feature",
  "properties": {
    "addr:full":"5532 E Thomas Rd Phoenix AZ 85018",
    "addr:housenumber":"5532",
    "addr:postcode":"85018",
    "addr:street":"E Thomas Rd",
    "iso:country":"US",
    "sg:address":"5532 E Thomas Rd",
    "sg:city":"Phoenix",
    "sg:classifiers":[
        {
            "category":"Restaurant",
            "type":"Food & Drink"
        }
    ],
    "sg:menulink":"http://www.allmenus.com/az/phoenix/69413-dominos-pizza/menu/",
    "sg:phone":"+1 602 952 9300",
    "sg:postcode":"85018",
    "sg:province":"AZ",
    "sg:tags":[
        "american",
        "wing",
        "pizza"
    ],
    "wof:name":"Domino's Pizza",
    "wof:placetype":"venue"
},
  "geometry": {"coordinates":[-111.962138,33.480045],"type":"Point"}
}