{
  "type": "Feature",
  "properties": {
    "addr:full":"3510 W Bell Rd Phoenix AZ 85053",
    "addr:housenumber":"3510",
    "addr:postcode":"85053",
    "addr:street":"W Bell Rd",
    "iso:country":"US",
    "sg:address":"3510 W Bell Rd",
    "sg:city":"Phoenix",
    "sg:classifiers":[
        {
            "category":"Restaurant",
            "type":"Food & Drink"
        }
    ],
    "sg:phone":"+1 602 439 3535",
    "sg:postcode":"85053",
    "sg:province":"AZ",
    "wof:name":"Mr Gyros",
    "wof:placetype":"venue"
},
  "geometry": {"coordinates":[-112.13769000000001,33.639618],"type":"Point"}
}