{
  "type": "Feature",
  "properties": {
    "iso:country":"US",
    "sg:address":"501 S Rim View Cir",
    "sg:city":"Payson",
    "sg:classifiers":[
        {
            "category":"Mining & Drilling",
            "type":"Manufacturing & Wholesale Goods"
        }
    ],
    "sg:phone":"+1 928 472 8502",
    "sg:postcode":"85541",
    "sg:province":"AZ",
    "sg:tags":[
        "c",
        "mfg",
        "hydroponic",
        "metal",
        "refining",
        "precious"
    ],
    "wof:name":"Thorne Clay Company",
    "wof:placetype":"venue"
},
  "geometry": {"coordinates":[-111.34595899999999,34.235369],"type":"Point"}
}