{
  "type": "Feature",
  "properties": {
    "addr:full":"216 S Clark Dr Tempe AZ 85281",
    "addr:housenumber":"216",
    "addr:postcode":"85281",
    "addr:street":"S Clark Dr",
    "iso:country":"US",
    "sg:address":"216 S Clark Dr",
    "sg:city":"Tempe",
    "sg:classifiers":[
        {
            "category":"Professional",
            "subcategory":"Management & Consulting",
            "type":"Services"
        }
    ],
    "sg:phone":"+1 480 970 3804",
    "sg:postcode":"85281",
    "sg:province":"AZ",
    "sg:tags":[
        "consultant",
        "product",
        "computer",
        "resells"
    ],
    "wof:name":"Aln Associates",
    "wof:placetype":"venue"
},
  "geometry": {"coordinates":[-111.898805,33.426756],"type":"Point"}
}