{
  "type": "Feature",
  "properties": {
    "addr:full":"7475 E Rustling Pass Scottsdale AZ 85255",
    "addr:housenumber":"7475",
    "addr:postcode":"85255",
    "addr:street":"E Rustling Pass",
    "iso:country":"US",
    "sg:address":"7475 E Rustling Pass",
    "sg:city":"Scottsdale",
    "sg:classifiers":[
        {
            "category":"Professional",
            "type":"Services"
        }
    ],
    "sg:phone":"+1 480 473 7071",
    "sg:postcode":"85255",
    "sg:province":"AZ",
    "wof:name":"Write On",
    "wof:placetype":"venue"
},
  "geometry": {"coordinates":[-111.920391,33.681312],"type":"Point"}
}