{
  "type": "Feature",
  "properties": {
    "addr:full":"11438 N 71st St Scottsdale AZ 85254",
    "addr:housenumber":"11438",
    "addr:postcode":"85254",
    "addr:street":"N 71St St",
    "iso:country":"US",
    "sg:address":"11438 N 71st St",
    "sg:city":"Scottsdale",
    "sg:classifiers":[
        {
            "category":"Wholesale",
            "subcategory":"Home Furnishings",
            "type":"Manufacturing & Wholesale Goods"
        }
    ],
    "sg:phone":"+1 480 664 6386",
    "sg:postcode":"85254",
    "sg:province":"AZ",
    "sg:tags":[
        "textile",
        "retail"
    ],
    "wof:name":"Specialty Apron & Textile",
    "wof:placetype":"venue"
},
  "geometry": {"coordinates":[-111.928231,33.589911],"type":"Point"}
}