{
  "type": "Feature",
  "properties": {
    "iso:country":"US",
    "sg:address":"15436 N Central Ave",
    "sg:city":"Phoenix",
    "sg:classifiers":[
        {
            "category":"Professional",
            "type":"Services"
        }
    ],
    "sg:phone":"+1 602 789 7303",
    "sg:postcode":"85022",
    "sg:province":"AZ",
    "wof:name":"Reggie To Rescue",
    "wof:placetype":"venue"
},
  "geometry": {"coordinates":[-112.074188,33.62755],"type":"Point"}
}