{
  "type": "Feature",
  "properties": {
    "iso:country":"US",
    "sg:address":"3815 E Grove St",
    "sg:city":"Phoenix",
    "sg:classifiers":[
        {
            "category":"Wholesale",
            "subcategory":"Medical Equipment & Supplies",
            "type":"Manufacturing & Wholesale Goods"
        }
    ],
    "sg:phone":"+1 602 431 8670",
    "sg:postcode":"85040",
    "sg:province":"AZ",
    "wof:name":"Medical Specialties Corp",
    "wof:placetype":"venue"
},
  "geometry": {"coordinates":[-111.999232,33.398063],"type":"Point"}
}