{
  "type": "Feature",
  "properties": {
    "iso:country":"US",
    "sg:address":"2930 E Wood St",
    "sg:city":"Phoenix",
    "sg:classifiers":[
        {
            "category":"Wholesale",
            "subcategory":"Machinery & Supplies",
            "type":"Manufacturing & Wholesale Goods"
        }
    ],
    "sg:phone":"+1 602 276 1407",
    "sg:postcode":"85040",
    "sg:province":"AZ",
    "sg:tags":[
        "equipment",
        "welding"
    ],
    "wof:name":"Stud Welding Specialists Inc",
    "wof:placetype":"venue"
},
  "geometry": {"coordinates":[-112.019243,33.408908],"type":"Point"}
}