{
  "type": "Feature",
  "properties": {
    "addr:full":"5621 S Nogales Hwy Tucson AZ 85706",
    "addr:housenumber":"5621",
    "addr:postcode":"85706",
    "addr:street":"S Nogales Hwy",
    "iso:country":"US",
    "sg:address":"5621 S Nogales Hwy",
    "sg:city":"Tucson",
    "sg:classifiers":[
        {
            "category":"Freight",
            "type":"Transportation"
        }
    ],
    "sg:phone":"+1 520 806 4070",
    "sg:postcode":"85706",
    "sg:province":"AZ",
    "sg:tags":[
        "operator",
        "trucking"
    ],
    "wof:name":"CES Mobile Home Movers",
    "wof:placetype":"venue"
},
  "geometry": {"coordinates":[-110.96495899999999,32.155997],"type":"Point"}
}