{
  "type": "Feature",
  "properties": {
    "iso:country":"US",
    "sg:address":"7402 W Detroit St",
    "sg:city":"Chandler",
    "sg:classifiers":[
        {
            "category":"Organizations",
            "subcategory":"Religious Organization",
            "type":"Services"
        }
    ],
    "sg:phone":"+1 480 753 3601",
    "sg:postcode":"85226",
    "sg:province":"AZ",
    "sg:tags":[
        "place",
        "worship",
        "church"
    ],
    "sg:website":"http://www.foothillscommunitychurch.com",
    "wof:name":"Foothills Community Church",
    "wof:placetype":"venue"
},
  "geometry": {"coordinates":[-111.97098200000001,33.307038],"type":"Point"}
}