{
  "type": "Feature",
  "properties": {
    "iso:country":"US",
    "sg:address":"314 W Irvington Rd",
    "sg:city":"Tucson",
    "sg:classifiers":[
        {
            "category":"Building & Trades",
            "subcategory":"Construction",
            "type":"Services"
        }
    ],
    "sg:phone":"+1 520 746 1110",
    "sg:postcode":"85714",
    "sg:province":"AZ",
    "sg:tags":[
        "contractor"
    ],
    "wof:name":"Security Ornamental",
    "wof:placetype":"venue"
},
  "geometry": {"coordinates":[-110.97630599999999,32.163294],"type":"Point"}
}