{
  "type": "Feature",
  "properties": {
    "iso:country":"US",
    "sg:address":"3530 W Mescal St",
    "sg:city":"Phoenix",
    "sg:classifiers":[
        {
            "category":"Professional",
            "subcategory":"Art Services",
            "type":"Services"
        }
    ],
    "sg:phone":"+1 602 978 3326",
    "sg:postcode":"85029",
    "sg:province":"AZ",
    "sg:tags":[
        "graphic",
        "designer"
    ],
    "wof:name":"Bartholomew Graphics",
    "wof:placetype":"venue"
},
  "geometry": {"coordinates":[-112.13574,33.586277],"type":"Point"}
}