{
  "type": "Feature",
  "properties": {
    "addr:full":"3322 E Pierce St Phoenix AZ 85008",
    "addr:housenumber":"3322",
    "addr:postcode":"85008",
    "addr:street":"E Pierce St",
    "iso:country":"US",
    "sg:address":"3322 E Pierce St",
    "sg:city":"Phoenix",
    "sg:classifiers":[
        {
            "category":"Insurance",
            "subcategory":"Hazard Insurance",
            "type":"Services"
        }
    ],
    "sg:phone":"+1 602 225 2838",
    "sg:postcode":"85008",
    "sg:province":"AZ",
    "wof:name":"Hector Leon & Silvia Romo",
    "wof:placetype":"venue"
},
  "geometry": {"coordinates":[-112.01022,33.455816],"type":"Point"}
}