{
  "type": "Feature",
  "properties": {
    "addr:full":"734 N US Hwy 89 Chino Valley AZ 86323",
    "addr:housenumber":"734",
    "addr:postcode":"86323",
    "addr:street":"N Us Hwy 89 Chino Valley",
    "iso:country":"US",
    "sg:address":"734 N US Hwy 89",
    "sg:city":"Chino Valley",
    "sg:classifiers":[
        {
            "category":"Retail",
            "subcategory":"Auto Repair",
            "type":"Services"
        }
    ],
    "sg:phone":"+1 928 636 4159",
    "sg:postcode":"86323",
    "sg:province":"AZ",
    "sg:tags":[
        "automobile",
        "lubrication"
    ],
    "wof:name":"Cv Trailers",
    "wof:placetype":"venue"
},
  "geometry": {"coordinates":[-112.454297,34.734864],"type":"Point"}
}