{
  "type": "Feature",
  "properties": {
    "iso:country":"US",
    "sg:address":"3071 Chemehuevi Pl",
    "sg:city":"Lake Havasu City",
    "sg:classifiers":[
        {
            "category":"Building & Trades",
            "subcategory":"Landscaping Services",
            "type":"Services"
        }
    ],
    "sg:phone":"+1 928 854 2489",
    "sg:postcode":"86406",
    "sg:province":"AZ",
    "sg:tags":[
        "tree",
        "trimming"
    ],
    "wof:name":"Big TS",
    "wof:placetype":"venue"
},
  "geometry": {"coordinates":[-114.292469,34.473422],"type":"Point"}
}