{
  "type": "Feature",
  "properties": {
    "iso:country":"US",
    "sg:address":"900 S California Ave",
    "sg:city":"Parker",
    "sg:classifiers":[
        {
            "category":"Food & Beverages",
            "subcategory":"Liquor & Beverages",
            "type":"Retail Goods"
        }
    ],
    "sg:phone":"+1 928 669 8284",
    "sg:postcode":"85344",
    "sg:province":"AZ",
    "sg:tags":[
        "property",
        "commercial",
        "store",
        "lessor"
    ],
    "wof:name":"Little Brown Jug Inc",
    "wof:placetype":"venue"
},
  "geometry": {"coordinates":[-114.289752,34.151339],"type":"Point"}
}