{
  "type": "Feature",
  "properties": {
    "iso:country":"US",
    "sg:address":"366 Peregrine Ln",
    "sg:city":"Prescott",
    "sg:classifiers":[
        {
            "category":"Professional",
            "subcategory":"Computer Services",
            "type":"Services"
        }
    ],
    "sg:phone":"+1 928 771 1958",
    "sg:postcode":"86301",
    "sg:province":"AZ",
    "sg:tags":[
        "web",
        "design",
        "site",
        "software"
    ],
    "wof:name":"Cyber Visions",
    "wof:placetype":"venue"
},
  "geometry": {"coordinates":[-112.467158,34.574471],"type":"Point"}
}