{
  "type": "Feature",
  "properties": {
    "iso:country":"US",
    "sg:address":"288 N Ironwood Dr",
    "sg:city":"Apache Junction",
    "sg:classifiers":[
        {
            "category":"Building & Trades",
            "subcategory":"Construction",
            "type":"Services"
        }
    ],
    "sg:phone":"+1 480 982 7431",
    "sg:postcode":"85220",
    "sg:province":"AZ",
    "sg:tags":[
        "nonresidential"
    ],
    "wof:name":"Etw Group Inc",
    "wof:placetype":"venue"
},
  "geometry": {"coordinates":[-111.56342,33.416936],"type":"Point"}
}