{
  "type": "Feature",
  "properties": {
    "iso:country":"US",
    "sg:address":"9799 Sammy Pl",
    "sg:city":"Peoria",
    "sg:classifiers":[
        {
            "category":"Building & Trades",
            "subcategory":"Construction",
            "type":"Services"
        }
    ],
    "sg:phone":"+1 623 825 6068",
    "sg:postcode":"85383",
    "sg:province":"AZ",
    "sg:tags":[
        "framing",
        "stud",
        "contractor"
    ],
    "wof:name":"Arizona Lght Gauge Stl Systems",
    "wof:placetype":"venue"
},
  "geometry": {"coordinates":[-112.270917,33.729273],"type":"Point"}
}