{
  "type": "Feature",
  "properties": {
    "iso:country":"US",
    "sg:address":"562 State Hwy 82",
    "sg:city":"Huachuca City",
    "sg:classifiers":[
        {
            "category":"Building & Trades",
            "subcategory":"Construction",
            "type":"Services"
        }
    ],
    "sg:phone":"+1 520 456 2355",
    "sg:postcode":"85616",
    "sg:province":"AZ",
    "sg:tags":[
        "well",
        "drilling"
    ],
    "wof:name":"Bradly Drilling",
    "wof:placetype":"venue"
},
  "geometry": {"coordinates":[-110.363778,31.692381],"type":"Point"}
}