{
  "type": "Feature",
  "properties": {
    "addr:full":"601 Theater Dr Sierra Vista AZ 85635",
    "addr:housenumber":"601",
    "addr:postcode":"85635",
    "addr:street":"Theater Dr",
    "iso:country":"US",
    "sg:address":"601 Theater Dr",
    "sg:city":"Sierra Vista",
    "sg:classifiers":[
        {
            "category":"Retail",
            "subcategory":"Auto Repair",
            "type":"Services"
        }
    ],
    "sg:phone":"+1 520 458 5666",
    "sg:postcode":"85635",
    "sg:province":"AZ",
    "sg:tags":[
        "repairing",
        "automobile"
    ],
    "wof:name":"Pete's Place",
    "wof:placetype":"venue"
},
  "geometry": {"coordinates":[-110.29348299999999,31.560121],"type":"Point"}
}