{
  "type": "Feature",
  "properties": {
    "iso:country":"US",
    "sg:address":"7153 N 58th Ave",
    "sg:city":"Glendale",
    "sg:classifiers":[
        {
            "category":"Restaurant",
            "type":"Food & Drink"
        }
    ],
    "sg:menulink":"http://www.allmenus.com/az/phoenix/27820-cee-cees-on-the-corner/menu/",
    "sg:phone":"+1 623 847 0086",
    "sg:postcode":"85301",
    "sg:province":"AZ",
    "sg:tags":[
        "mexican"
    ],
    "wof:name":"Cee Cee's On The Corner",
    "wof:placetype":"venue"
},
  "geometry": {"coordinates":[-112.183645,33.541409],"type":"Point"}
}