{
  "type": "Feature",
  "properties": {
    "addr:full":"15829 N 83rd Ave Peoria AZ 85382",
    "addr:housenumber":"15829",
    "addr:postcode":"85382",
    "addr:street":"N 83Rd Ave",
    "iso:country":"US",
    "sg:address":"15829 N 83rd Ave",
    "sg:city":"Peoria",
    "sg:classifiers":[
        {
            "category":"Restaurant",
            "type":"Food & Drink"
        }
    ],
    "sg:menulink":"http://www.allmenus.com/az/phoenix/72179-sbarro/menu/",
    "sg:phone":"+1 623 773 3524",
    "sg:postcode":"85382",
    "sg:province":"AZ",
    "sg:tags":[
        "american",
        "pizza"
    ],
    "wof:name":"Sbarro",
    "wof:placetype":"venue"
},
  "geometry": {"coordinates":[-112.23615100000001,33.626599],"type":"Point"}
}