{
  "type": "Feature",
  "properties": {
    "iso:country":"US",
    "sg:address":"412 W Hatcher Rd",
    "sg:city":"Phoenix",
    "sg:classifiers":[
        {
            "category":"Professional",
            "type":"Services"
        }
    ],
    "sg:phone":"+1 602 867 6981",
    "sg:postcode":"85021",
    "sg:province":"AZ",
    "wof:name":"A Co Elite",
    "wof:placetype":"venue"
},
  "geometry": {"coordinates":[-112.080595,33.57135],"type":"Point"}
}