{
  "type": "Feature",
  "properties": {
    "iso:country":"US",
    "sg:address":"8520 W Peoria Ave",
    "sg:city":"Peoria",
    "sg:classifiers":[
        {
            "category":"Home & Garden",
            "subcategory":"Household Appliances",
            "type":"Retail Goods"
        },
        {
            "category":"Wholesale",
            "subcategory":"Durable Goods & Equipment",
            "type":"Manufacturing & Wholesale Goods"
        }
    ],
    "sg:phone":"+1 623 776 7122",
    "sg:postcode":"85345",
    "sg:province":"AZ",
    "sg:tags":[
        "machine",
        "appliances-major-wholesale",
        "major",
        "dishwashing",
        "manufacturer"
    ],
    "wof:name":"J & K Appliances",
    "wof:placetype":"venue"
},
  "geometry": {"coordinates":[-112.241561,33.581356],"type":"Point"}
}