{
  "type": "Feature",
  "properties": {
    "addr:full":"561 E Elliot Rd Chandler AZ 85225",
    "addr:housenumber":"561",
    "addr:postcode":"85225",
    "addr:street":"E Elliot Rd",
    "iso:country":"US",
    "sg:address":"561 E Elliot Rd",
    "sg:city":"Chandler",
    "sg:classifiers":[
        {
            "category":"Wholesale",
            "subcategory":"Hardware",
            "type":"Manufacturing & Wholesale Goods"
        }
    ],
    "sg:phone":"+1 480 892 9500",
    "sg:postcode":"85225",
    "sg:province":"AZ",
    "sg:tags":[
        "seal"
    ],
    "wof:name":"Mc Dowell & Co",
    "wof:placetype":"venue"
},
  "geometry": {"coordinates":[-111.833568,33.349676],"type":"Point"}
}