{
  "type": "Feature",
  "properties": {
    "addr:full":"6340 S Price Rd Tempe AZ 85282",
    "addr:housenumber":"6340",
    "addr:postcode":"85282",
    "addr:street":"S Price Rd",
    "iso:country":"US",
    "sg:address":"6340 S Price Rd",
    "sg:city":"Tempe",
    "sg:classifiers":[
        {
            "category":"Education",
            "subcategory":"School",
            "type":"Public Place"
        }
    ],
    "sg:phone":"+1 480 752 8993",
    "sg:postcode":"85282",
    "sg:province":"AZ",
    "sg:tags":[
        "religious"
    ],
    "sg:website":"www.bethanychristianschool.org",
    "wof:name":"Bethany Christian School",
    "wof:placetype":"venue"
},
  "geometry": {"coordinates":[-111.894505,33.365503],"type":"Point"}
}