{
  "type": "Feature",
  "properties": {
    "iso:country":"US",
    "sg:address":"6732 E Ashler Hills Dr",
    "sg:city":"Cave Creek",
    "sg:classifiers":[
        {
            "category":"Professional",
            "subcategory":"Computer Services",
            "type":"Services"
        }
    ],
    "sg:phone":"+1 480 575 0050",
    "sg:postcode":"85331",
    "sg:province":"AZ",
    "sg:tags":[
        "internet"
    ],
    "wof:name":"Martindale Hubbell",
    "wof:placetype":"venue"
},
  "geometry": {"coordinates":[-111.935995,33.77755],"type":"Point"}
}