{
  "type": "Feature",
  "properties": {
    "addr:full":"3708 S 6th Ave Tucson AZ 85713",
    "addr:housenumber":"3708",
    "addr:postcode":"85713",
    "addr:street":"S 6Th Ave",
    "iso:country":"US",
    "sg:address":"3708 S 6th Ave",
    "sg:city":"Tucson",
    "sg:classifiers":[
        {
            "category":"Retail",
            "subcategory":"Auto Repair",
            "type":"Services"
        }
    ],
    "sg:phone":"+1 520 624 5999",
    "sg:postcode":"85713",
    "sg:province":"AZ",
    "sg:tags":[
        "transmission"
    ],
    "wof:name":"Lee Myles Transmissions",
    "wof:placetype":"venue"
},
  "geometry": {"coordinates":[-110.968341,32.179793],"type":"Point"}
}