{
  "type": "Feature",
  "properties": {
    "iso:country":"US",
    "sg:address":"2544 W Broadway Rd",
    "sg:city":"Phoenix",
    "sg:classifiers":[
        {
            "category":"Wholesale",
            "subcategory":"Auto Parts",
            "type":"Manufacturing & Wholesale Goods"
        }
    ],
    "sg:phone":"+1 602 243 9402",
    "sg:postcode":"85041",
    "sg:province":"AZ",
    "sg:tags":[
        "used"
    ],
    "wof:name":"Joses Low Cost",
    "wof:placetype":"venue"
},
  "geometry": {"coordinates":[-112.115487,33.406803],"type":"Point"}
}