{
  "type": "Feature",
  "properties": {
    "iso:country":"US",
    "sg:address":"3391 Iroquois Dr",
    "sg:city":"Lake Havasu City",
    "sg:classifiers":[
        {
            "category":"Marine",
            "type":"Transportation"
        }
    ],
    "sg:phone":"+1 928 727 6945",
    "sg:postcode":"86404",
    "sg:province":"AZ",
    "sg:tags":[
        "towing"
    ],
    "wof:name":"Sea Tow Havasu",
    "wof:placetype":"venue"
},
  "geometry": {"coordinates":[-114.293967,34.501675],"type":"Point"}
}