{
  "type": "Feature",
  "properties": {
    "iso:country":"US",
    "sg:address":"3400 Copper Basin Rd",
    "sg:city":"Prescott",
    "sg:classifiers":[
        {
            "category":"Travel",
            "subcategory":"Campground",
            "type":"Entertainment"
        }
    ],
    "sg:phone":"+1 928 778 0091",
    "sg:postcode":"86303",
    "sg:province":"AZ",
    "sg:tags":[
        "camp"
    ],
    "wof:name":"Camp Charles Pearlstein",
    "wof:placetype":"venue"
},
  "geometry": {"coordinates":[-112.520231,34.511572],"type":"Point"}
}