{
  "type": "Feature",
  "properties": {
    "iso:country":"US",
    "sg:address":"3232 E 36th St",
    "sg:city":"Tucson",
    "sg:classifiers":[
        {
            "category":"Wholesale",
            "subcategory":"Hardware",
            "type":"Manufacturing & Wholesale Goods"
        },
        {
            "category":"Home & Garden",
            "subcategory":"Garden Supply",
            "type":"Retail Goods"
        },
        {
            "category":"Retail",
            "subcategory":"Repair Shop",
            "type":"Services"
        }
    ],
    "sg:phone":"+1 520 620 1000",
    "sg:postcode":"85713",
    "sg:province":"AZ",
    "sg:tags":[
        "renting",
        "lawn",
        "outdoor",
        "power",
        "landscaping",
        "equipment-sales",
        "equipment",
        "saw"
    ],
    "sg:website":"http://www.stihlusa.com/",
    "wof:name":"Unicoa Industrial Supply",
    "wof:placetype":"venue"
},
  "geometry": {"coordinates":[-110.919342,32.19105],"type":"Point"}
}