{
  "type": "Feature",
  "properties": {
    "addr:full":"310 E Bell Rd Phoenix AZ 85022",
    "addr:housenumber":"310",
    "addr:postcode":"85022",
    "addr:street":"E Bell Rd",
    "iso:country":"US",
    "sg:address":"310 E Bell Rd",
    "sg:city":"Phoenix",
    "sg:classifiers":[
        {
            "category":"Restaurant",
            "type":"Food & Drink"
        }
    ],
    "sg:phone":"+1 602 863 1581",
    "sg:postcode":"85022",
    "sg:province":"AZ",
    "sg:tags":[
        "eating"
    ],
    "wof:name":"Perkins Family Restaurant",
    "wof:placetype":"venue"
},
  "geometry": {"coordinates":[-112.069757,33.640352],"type":"Point"}
}