{
  "type": "Feature",
  "properties": {
    "iso:country":"US",
    "sg:address":"245 S Plumer Ave",
    "sg:city":"Tucson",
    "sg:classifiers":[
        {
            "category":"Manufacturing",
            "subcategory":"Tools & Machinery",
            "type":"Manufacturing & Wholesale Goods"
        }
    ],
    "sg:phone":"+1 520 792 3160",
    "sg:postcode":"85719",
    "sg:province":"AZ",
    "sg:tags":[
        "machine",
        "shop"
    ],
    "sg:website":"www.lindelengineering.com",
    "wof:name":"Lindel Engineering",
    "wof:placetype":"venue"
},
  "geometry": {"coordinates":[-110.939385,32.219361],"type":"Point"}
}