{
  "type": "Feature",
  "properties": {
    "addr:full":"2802 N 7th Ave Phoenix AZ 85007",
    "addr:housenumber":"2802",
    "addr:postcode":"85007",
    "addr:street":"N 7Th Ave",
    "iso:country":"US",
    "sg:address":"2802 N 7th Ave",
    "sg:city":"Phoenix",
    "sg:classifiers":[
        {
            "category":"Building & Trades",
            "subcategory":"Landfill",
            "type":"Services"
        }
    ],
    "sg:phone":"+1 602 254 4898",
    "sg:postcode":"85007",
    "sg:province":"AZ",
    "wof:name":"Rio Salado Materials",
    "wof:placetype":"venue"
},
  "geometry": {"coordinates":[-112.082993,33.479439],"type":"Point"}
}