{
  "type": "Feature",
  "properties": {
    "iso:country":"US",
    "sg:address":"12102 W Thunderbird Rd",
    "sg:city":"El Mirage",
    "sg:classifiers":[
        {
            "category":"Personal",
            "subcategory":"Barber",
            "type":"Services"
        }
    ],
    "sg:phone":"+1 623 933 2111",
    "sg:postcode":"85335",
    "sg:province":"AZ",
    "wof:name":"H & D Barber & Hair Salon",
    "wof:placetype":"venue"
},
  "geometry": {"coordinates":[-112.321241,33.609019],"type":"Point"}
}