{
  "type": "Feature",
  "properties": {
    "iso:country":"US",
    "sg:address":"5944 W Bethany Home Rd",
    "sg:city":"Glendale",
    "sg:classifiers":[
        {
            "category":"Bars & Pubs",
            "type":"Food & Drink"
        }
    ],
    "sg:phone":"+1 623 939 8709",
    "sg:postcode":"85301",
    "sg:province":"AZ",
    "sg:tags":[
        "drinking"
    ],
    "wof:name":"Cypress Lounge The",
    "wof:placetype":"venue"
},
  "geometry": {"coordinates":[-112.186794,33.524135],"type":"Point"}
}