{
  "type": "Feature",
  "properties": {
    "addr:full":"352 E Brown Rd Mesa AZ 85201",
    "addr:housenumber":"352",
    "addr:postcode":"85201",
    "addr:street":"E Brown Rd",
    "iso:country":"US",
    "sg:address":"352 E Brown Rd",
    "sg:city":"Mesa",
    "sg:classifiers":[
        {
            "category":"Restaurant",
            "type":"Food & Drink"
        }
    ],
    "sg:menulink":"http://www.allmenus.com/az/phoenix/204969-taco-bell/menu/",
    "sg:postcode":"85201",
    "sg:province":"AZ",
    "sg:tags":[
        "mexican"
    ],
    "wof:name":"Taco Bell",
    "wof:placetype":"venue"
},
  "geometry": {"coordinates":[-111.82307900000001,33.435925],"type":"Point"}
}