{
  "type": "Feature",
  "properties": {
    "iso:country":"US",
    "sg:address":"65201 E Rose Crest Ct",
    "sg:city":"Tucson",
    "sg:classifiers":[
        {
            "category":"Building & Trades",
            "subcategory":"Locksmith",
            "type":"Services"
        }
    ],
    "sg:phone":"+1 520 918 0830",
    "sg:postcode":"85739",
    "sg:province":"AZ",
    "sg:tags":[
        "key"
    ],
    "wof:name":"24 Locksmith",
    "wof:placetype":"venue"
},
  "geometry": {"coordinates":[-110.868134,32.548952],"type":"Point"}
}