{
  "type": "Feature",
  "properties": {
    "addr:full":"5775 W Poinsettia Dr Glendale AZ 85304",
    "addr:housenumber":"5775",
    "addr:postcode":"85304",
    "addr:street":"W Poinsettia Dr",
    "iso:country":"US",
    "sg:address":"5775 W Poinsettia Dr",
    "sg:city":"Glendale",
    "sg:classifiers":[
        {
            "category":"Wholesale",
            "subcategory":"Non-durable Goods",
            "type":"Manufacturing & Wholesale Goods"
        }
    ],
    "sg:phone":"+1 623 878 8262",
    "sg:postcode":"85304",
    "sg:province":"AZ",
    "sg:tags":[
        "dry",
        "goods-wholesale"
    ],
    "wof:name":"Devine Wholesale Provisions Ll",
    "wof:placetype":"venue"
},
  "geometry": {"coordinates":[-112.184104,33.593745],"type":"Point"}
}