{
  "type": "Feature",
  "properties": {
    "iso:country":"US",
    "sg:address":"5639 S Outrigger Rd",
    "sg:city":"Tempe",
    "sg:classifiers":[
        {
            "category":"Real Estate",
            "subcategory":"Real Estate Operator",
            "type":"Services"
        }
    ],
    "sg:phone":"+1 602 977 7523",
    "sg:postcode":"85283",
    "sg:province":"AZ",
    "sg:tags":[
        "building",
        "nonresidential"
    ],
    "wof:name":"EPC Properties",
    "wof:placetype":"venue"
},
  "geometry": {"coordinates":[-111.916874,33.371716],"type":"Point"}
}