{
  "type": "Feature",
  "properties": {
    "addr:full":"1161 W Irvington Rd Tucson AZ 85714",
    "addr:housenumber":"1161",
    "addr:postcode":"85714",
    "addr:street":"W Irvington Rd",
    "iso:country":"US",
    "sg:address":"1161 W Irvington Rd",
    "sg:city":"Tucson",
    "sg:classifiers":[
        {
            "category":"Farming",
            "subcategory":"Fish & Marine Products",
            "type":"Manufacturing & Wholesale Goods"
        },
        {
            "category":"Retail",
            "subcategory":"Repair Shop",
            "type":"Services"
        },
        {
            "category":"Shopping",
            "subcategory":"Crafts & Fabrics",
            "type":"Retail Goods"
        }
    ],
    "sg:phone":"+1 520 807 6290",
    "sg:postcode":"85714",
    "sg:province":"AZ",
    "sg:tags":[
        "picture",
        "art",
        "supply",
        "frame",
        "restoration",
        "framing"
    ],
    "sg:website":"http://www.michaels.com",
    "wof:name":"Michaels - The Arts & Craft Store",
    "wof:placetype":"venue"
},
  "geometry": {"coordinates":[-110.988889,32.163263],"type":"Point"}
}