{
  "type": "Feature",
  "properties": {
    "iso:country":"US",
    "sg:address":"175 S Hamilton Place",
    "sg:city":"Gilbert",
    "sg:classifiers":[
        {
            "category":"Arena",
            "subcategory":"Sports Club",
            "type":"Entertainment"
        }
    ],
    "sg:phone":"+1 480 839 3009",
    "sg:postcode":"85233",
    "sg:province":"AZ",
    "sg:tags":[
        "martial art"
    ],
    "wof:name":"Arizona Wado Karate",
    "wof:placetype":"venue"
},
  "geometry": {"coordinates":[-111.82424,33.348177],"type":"Point"}
}