{
  "type": "Feature",
  "properties": {
    "iso:country":"US",
    "sg:address":"114 N Parkwood Ln",
    "sg:city":"Payson",
    "sg:classifiers":[
        {
            "category":"Wholesale",
            "subcategory":"Dairy",
            "type":"Manufacturing & Wholesale Goods"
        }
    ],
    "sg:phone":"+1 928 474 2817",
    "sg:postcode":"85541",
    "sg:province":"AZ",
    "sg:tags":[
        "product",
        "distribution"
    ],
    "wof:name":"Bonnlenn",
    "wof:placetype":"venue"
},
  "geometry": {"coordinates":[-111.331552,34.242461],"type":"Point"}
}