{
  "type": "Feature",
  "properties": {
    "iso:country":"US",
    "sg:address":"1930 S Alma School Rd",
    "sg:city":"Mesa",
    "sg:classifiers":[
        {
            "category":"Banks & Credit Unions",
            "subcategory":"Bank",
            "type":"Services"
        }
    ],
    "sg:phone":"+1 480 838 4425",
    "sg:postcode":"85210",
    "sg:province":"AZ",
    "sg:tags":[
        "loan",
        "real estate"
    ],
    "wof:name":"Brownstone Mortgage Invstmnts",
    "wof:placetype":"venue"
},
  "geometry": {"coordinates":[-111.859813,33.379586],"type":"Point"}
}