{
  "type": "Feature",
  "properties": {
    "iso:country":"US",
    "sg:address":"2102 W Encanto Blvd",
    "sg:city":"Phoenix",
    "sg:classifiers":[
        {
            "category":"Government",
            "subcategory":"Police Station",
            "type":"Public Place"
        }
    ],
    "sg:phone":"+1 602 223 2286",
    "sg:postcode":"85009",
    "sg:province":"AZ",
    "sg:tags":[
        "state"
    ],
    "wof:name":"Law Enforcement Merit",
    "wof:placetype":"venue"
},
  "geometry": {"coordinates":[-112.105138,33.473294],"type":"Point"}
}