{
  "type": "Feature",
  "properties": {
    "addr:full":"2459 E Dolphin Ave Mesa AZ 85204",
    "addr:housenumber":"2459",
    "addr:postcode":"85204",
    "addr:street":"E Dolphin Ave",
    "iso:country":"US",
    "sg:address":"2459 E Dolphin Ave",
    "sg:city":"Mesa",
    "sg:classifiers":[
        {
            "category":"Building & Trades",
            "subcategory":"Landscaping Services",
            "type":"Services"
        }
    ],
    "sg:phone":"+1 480 969 2500",
    "sg:postcode":"85204",
    "sg:province":"AZ",
    "sg:tags":[
        "landscape"
    ],
    "wof:name":"Aztec Tree & Landscape",
    "wof:placetype":"venue"
},
  "geometry": {"coordinates":[-111.77895100000001,33.402507],"type":"Point"}
}