{
  "type": "Feature",
  "properties": {
    "addr:full":"2334 N Scottsdale Rd Scottsdale AZ 85257",
    "addr:housenumber":"2334",
    "addr:postcode":"85257",
    "addr:street":"N Scottsdale Rd",
    "iso:country":"US",
    "sg:address":"2334 N Scottsdale Rd",
    "sg:city":"Scottsdale",
    "sg:classifiers":[
        {
            "category":"Wholesale",
            "subcategory":"Non-durable Goods",
            "type":"Manufacturing & Wholesale Goods"
        },
        {
            "category":"Personal",
            "subcategory":"Beauty Salon",
            "type":"Services"
        },
        {
            "category":"Personal",
            "subcategory":"Barber",
            "type":"Services"
        },
        {
            "category":"Personal",
            "subcategory":"Day Spa",
            "type":"Services"
        }
    ],
    "sg:phone":"+1 480 945 2590",
    "sg:postcode":"85257",
    "sg:province":"AZ",
    "sg:tags":[
        "equipment",
        "manufacturer",
        "supplies-wholesale",
        "salons-equipment",
        "supply"
    ],
    "sg:website":"http://www.cameleonsalon.com",
    "wof:name":"Cameleon Salon & Spa",
    "wof:placetype":"venue"
},
  "geometry": {"coordinates":[-111.926197,33.47352],"type":"Point"}
}