{
  "type": "Feature",
  "properties": {
    "iso:country":"US",
    "sg:address":"1414 N Cooper Rd",
    "sg:city":"Gilbert",
    "sg:classifiers":[
        {
            "category":"Personal",
            "subcategory":"Beauty Salon",
            "type":"Services"
        },
        {
            "category":"Personal",
            "subcategory":"Day Spa",
            "type":"Services"
        }
    ],
    "sg:phone":"+1 480 507 7777",
    "sg:postcode":"85233",
    "sg:province":"AZ",
    "wof:name":"Beauty Brands Salon Spa Sprstr",
    "wof:placetype":"venue"
},
  "geometry": {"coordinates":[-111.807231,33.375215],"type":"Point"}
}