{
  "type": "Feature",
  "properties": {
    "iso:country":"US",
    "sg:address":"4025 E Aster Dr",
    "sg:city":"Phoenix",
    "sg:classifiers":[
        {
            "category":"Professional",
            "type":"Services"
        }
    ],
    "sg:phone":"+1 602 795 6159",
    "sg:postcode":"85032",
    "sg:province":"AZ",
    "sg:tags":[
        "establishment"
    ],
    "wof:name":"MRCOFFEEBEANS.COM",
    "wof:placetype":"venue"
},
  "geometry": {"coordinates":[-111.993356,33.60278],"type":"Point"}
}