{
  "type": "Feature",
  "properties": {
    "addr:full":"70 E Florence Rd Tucson AZ 85704",
    "addr:housenumber":"70",
    "addr:postcode":"85704",
    "addr:street":"E Florence Rd",
    "iso:country":"US",
    "sg:address":"70 E Florence Rd",
    "sg:city":"Tucson",
    "sg:classifiers":[
        {
            "category":"Professional",
            "type":"Services"
        }
    ],
    "sg:phone":"+1 520 575 0520",
    "sg:postcode":"85704",
    "sg:province":"AZ",
    "wof:name":"Jerry A Meyer Inc",
    "wof:placetype":"venue"
},
  "geometry": {"coordinates":[-110.970157,32.33014],"type":"Point"}
}