{
  "type": "Feature",
  "properties": {
    "addr:full":"9245 E Guadalupe Rd Mesa AZ 85212",
    "addr:housenumber":"9245",
    "addr:postcode":"85212",
    "addr:street":"E Guadalupe Rd",
    "iso:country":"US",
    "sg:address":"9245 E Guadalupe Rd",
    "sg:city":"Mesa",
    "sg:classifiers":[
        {
            "category":"Sports & Exercise",
            "subcategory":"Gym",
            "type":"Entertainment"
        },
        {
            "category":"Arena",
            "subcategory":"Sports Club",
            "type":"Entertainment"
        }
    ],
    "sg:phone":"+1 888 287 7417",
    "sg:postcode":"85212",
    "sg:province":"AZ",
    "sg:tags":[
        "trainer",
        "personal",
        "gymnasium",
        "health",
        "fitness"
    ],
    "sg:website":"http://www.purefitnessclubs.com",
    "wof:name":"Pure Fitness",
    "wof:placetype":"venue"
},
  "geometry": {"coordinates":[-111.634708,33.364644],"type":"Point"}
}