{
  "type": "Feature",
  "properties": {
    "iso:country":"US",
    "sg:address":"12626 E Turquoise Ave",
    "sg:city":"Scottsdale",
    "sg:classifiers":[
        {
            "category":"Home & Garden",
            "subcategory":"Carpets & Floor Coverings",
            "type":"Retail Goods"
        }
    ],
    "sg:phone":"+1 480 657 0010",
    "sg:postcode":"85259",
    "sg:province":"AZ",
    "wof:name":"American Flooring Systems",
    "wof:placetype":"venue"
},
  "geometry": {"coordinates":[-111.807831,33.577023],"type":"Point"}
}