{
  "type": "Feature",
  "properties": {
    "iso:country":"US",
    "sg:address":"2716 W Osborn Rd",
    "sg:city":"Phoenix",
    "sg:classifiers":[
        {
            "category":"Manufacturing",
            "subcategory":"Printing",
            "type":"Manufacturing & Wholesale Goods"
        }
    ],
    "sg:phone":"+1 602 252 7719",
    "sg:postcode":"85017",
    "sg:province":"AZ",
    "sg:tags":[
        "publication",
        "advertising-shoppers"
    ],
    "wof:name":"Native Impressions",
    "wof:placetype":"venue"
},
  "geometry": {"coordinates":[-112.118029,33.487726],"type":"Point"}
}