{
  "type": "Feature",
  "properties": {
    "iso:country":"US",
    "sg:address":"16251 N Cave Creek Rd",
    "sg:city":"Phoenix",
    "sg:classifiers":[
        {
            "category":"Retail",
            "subcategory":"Repair Shop",
            "type":"Services"
        }
    ],
    "sg:phone":"+1 602 867 3381",
    "sg:postcode":"85032",
    "sg:province":"AZ",
    "sg:tags":[
        "scooters-repairing",
        "motorcycle",
        "motor"
    ],
    "wof:name":"Valley Kawasaki",
    "wof:placetype":"venue"
},
  "geometry": {"coordinates":[-112.03079200000001,33.634563],"type":"Point"}
}