{
  "type": "Feature",
  "properties": {
    "addr:full":"3241 N 301st Dr Buckeye AZ 85396",
    "addr:housenumber":"3241",
    "addr:postcode":"85396",
    "addr:street":"N 301St Dr",
    "iso:country":"US",
    "sg:address":"3241 N 301st Dr",
    "sg:city":"Buckeye",
    "sg:classifiers":[
        {
            "category":"Shopping",
            "type":"Retail Goods"
        }
    ],
    "sg:phone":"+1 623 826 0445",
    "sg:postcode":"85396",
    "sg:province":"AZ",
    "sg:tags":[
        "merchandise"
    ],
    "wof:name":"Shop To Earn",
    "wof:placetype":"venue"
},
  "geometry": {"coordinates":[-112.700388,33.483266],"type":"Point"}
}