{
  "type": "Feature",
  "properties": {
    "iso:country":"US",
    "sg:address":"840 E Southern Ave",
    "sg:city":"Mesa",
    "sg:classifiers":[
        {
            "category":"Retail",
            "subcategory":"Funeral Services",
            "type":"Services"
        }
    ],
    "sg:phone":"+1 480 654 5795",
    "sg:postcode":"85204",
    "sg:province":"AZ",
    "sg:tags":[
        "director"
    ],
    "wof:name":"Arizona Cremation & Funeral",
    "wof:placetype":"venue"
},
  "geometry": {"coordinates":[-111.81155,33.393439],"type":"Point"}
}