{
  "type": "Feature",
  "properties": {
    "iso:country":"US",
    "sg:address":"4734 W Palmaire Ave",
    "sg:city":"Glendale",
    "sg:classifiers":[
        {
            "category":"Freight",
            "type":"Transportation"
        }
    ],
    "sg:phone":"+1 602 502 8338",
    "sg:postcode":"85301",
    "sg:province":"AZ",
    "sg:tags":[
        "hauling"
    ],
    "wof:name":"Williamson  John",
    "wof:placetype":"venue"
},
  "geometry": {"coordinates":[-112.160285,33.540714],"type":"Point"}
}