{
  "type": "Feature",
  "properties": {
    "iso:country":"US",
    "sg:address":"7705 E Doubletree Ranch Rd",
    "sg:city":"Scottsdale",
    "sg:classifiers":[
        {
            "category":"Wholesale",
            "subcategory":"Non-durable Goods",
            "type":"Manufacturing & Wholesale Goods"
        }
    ],
    "sg:phone":"+1 480 998 0790",
    "sg:postcode":"85258",
    "sg:province":"AZ",
    "sg:tags":[
        "dry",
        "goods-wholesale"
    ],
    "wof:name":"International Institute For Advanced Purchasing & Supply",
    "wof:placetype":"venue"
},
  "geometry": {"coordinates":[-111.913223,33.563961],"type":"Point"}
}