{
  "type": "Feature",
  "properties": {
    "addr:full":"Dobson & Frye Rd. Chandler AZ 85224",
    "addr:postcode":"85224",
    "addr:street":"Rd.",
    "iso:country":"US",
    "sg:address":"Dobson & Frye Rd.",
    "sg:city":"Chandler",
    "sg:classifiers":[
        {
            "category":"Health Services",
            "subcategory":"Clinic",
            "type":"Services"
        }
    ],
    "sg:phone":"+1 480 228 4333",
    "sg:postcode":"85224",
    "sg:province":"AZ",
    "sg:tags":[
        "medical"
    ],
    "sg:website":"awakeningnuenergy.com",
    "wof:name":"Awakening Nu Energy, LLC",
    "wof:placetype":"venue"
},
  "geometry": {"coordinates":[-111.876238,33.298606],"type":"Point"}
}