{
  "type": "Feature",
  "properties": {
    "iso:country":"US",
    "sg:address":"4920 S Wendler Dr",
    "sg:city":"Tempe",
    "sg:classifiers":[
        {
            "category":"Building & Trades",
            "subcategory":"Construction",
            "type":"Services"
        }
    ],
    "sg:phone":"+1 602 426 8201",
    "sg:postcode":"85282",
    "sg:province":"AZ",
    "sg:tags":[
        "home",
        "builder"
    ],
    "wof:name":"Home Owners Loan",
    "wof:placetype":"venue"
},
  "geometry": {"coordinates":[-111.969801,33.380987],"type":"Point"}
}