{
  "type": "Feature",
  "properties": {
    "addr:full":"106 S 9th St Williams AZ 86046",
    "addr:housenumber":"106",
    "addr:postcode":"86046",
    "addr:street":"S 9Th St",
    "iso:country":"US",
    "sg:address":"106 S 9th St",
    "sg:city":"Williams",
    "sg:classifiers":[
        {
            "category":"Communications",
            "subcategory":"Radio Station",
            "type":"Services"
        }
    ],
    "sg:phone":"+1 928 635 0696",
    "sg:postcode":"86046",
    "sg:province":"AZ",
    "sg:tags":[
        "broadcast"
    ],
    "wof:name":"Kwmx Radio Williams Offic",
    "wof:placetype":"venue"
},
  "geometry": {"coordinates":[-112.19637,35.248207],"type":"Point"}
}