{
  "type": "Feature",
  "properties": {
    "addr:full":"3445 E Wildwood Dr Phoenix AZ 85048",
    "addr:housenumber":"3445",
    "addr:postcode":"85048",
    "addr:street":"E Wildwood Dr",
    "iso:country":"US",
    "sg:address":"3445 E Wildwood Dr",
    "sg:city":"Phoenix",
    "sg:classifiers":[
        {
            "category":"Wholesale",
            "subcategory":"Electrical",
            "type":"Manufacturing & Wholesale Goods"
        }
    ],
    "sg:phone":"+1 480 759 0440",
    "sg:postcode":"85048",
    "sg:province":"AZ",
    "sg:tags":[
        "semiconductor",
        "device",
        "electronic"
    ],
    "wof:name":"Process Integration Management",
    "wof:placetype":"venue"
},
  "geometry": {"coordinates":[-112.007882,33.298676],"type":"Point"}
}