{
  "type": "Feature",
  "properties": {
    "addr:full":"7755 E Redfield Rd Scottsdale AZ 85260",
    "addr:housenumber":"7755",
    "addr:postcode":"85260",
    "addr:street":"E Redfield Rd",
    "iso:country":"US",
    "sg:address":"7755 E Redfield Rd",
    "sg:city":"Scottsdale",
    "sg:classifiers":[
        {
            "category":"Professional",
            "type":"Services"
        }
    ],
    "sg:phone":"+1 480 609 7007",
    "sg:postcode":"85260",
    "sg:province":"AZ",
    "wof:name":"Ronbrow",
    "wof:placetype":"venue"
},
  "geometry": {"coordinates":[-111.91286700000001,33.613866],"type":"Point"}
}