{
  "type": "Feature",
  "properties": {
    "iso:country":"US",
    "sg:address":"1301 W Bartlett Way",
    "sg:city":"Chandler",
    "sg:classifiers":[
        {
            "category":"Insurance",
            "subcategory":"Insurance Agent",
            "type":"Services"
        }
    ],
    "sg:phone":"+1 480 883 1150",
    "sg:postcode":"85248",
    "sg:province":"AZ",
    "wof:name":"White J Consulting LLC",
    "wof:placetype":"venue"
},
  "geometry": {"coordinates":[-111.863386,33.233095],"type":"Point"}
}