{
  "type": "Feature",
  "properties": {
    "addr:full":"11989 E Cam Aurelia Vail AZ 85641",
    "addr:housenumber":"11989",
    "addr:postcode":"85641",
    "addr:street":"E Cam Aurelia",
    "iso:country":"US",
    "sg:address":"11989 E Cam Aurelia",
    "sg:city":"Vail",
    "sg:classifiers":[
        {
            "category":"Freight",
            "type":"Transportation"
        }
    ],
    "sg:phone":"+1 520 762 9842",
    "sg:postcode":"85641",
    "sg:province":"AZ",
    "sg:tags":[
        "operator",
        "local",
        "trucking"
    ],
    "wof:name":"Pinch Pickup & Delivery Co LLC",
    "wof:placetype":"venue"
},
  "geometry": {"coordinates":[-110.738899,31.93177],"type":"Point"}
}