{
  "type": "Feature",
  "properties": {
    "iso:country":"US",
    "sg:address":"11201 N 74th Ln",
    "sg:city":"Peoria",
    "sg:classifiers":[
        {
            "category":"Shopping",
            "subcategory":"Bicycles & Sporting Goods",
            "type":"Retail Goods"
        }
    ],
    "sg:phone":"+1 623 979 8743",
    "sg:postcode":"85345",
    "sg:province":"AZ",
    "wof:name":"Disco Skateboards",
    "wof:placetype":"venue"
},
  "geometry": {"coordinates":[-112.219345,33.587469],"type":"Point"}
}