{
  "type": "Feature",
  "properties": {
    "iso:country":"US",
    "sg:address":"5225 State Hwy 95",
    "sg:city":"Parker",
    "sg:classifiers":[
        {
            "category":"Food & Beverages",
            "subcategory":"Groceries & Convenience Stores",
            "type":"Retail Goods"
        }
    ],
    "sg:phone":"+1 928 667 2448",
    "sg:postcode":"85344",
    "sg:province":"AZ",
    "sg:tags":[
        "grocer"
    ],
    "wof:name":"River Island Market",
    "wof:placetype":"venue"
},
  "geometry": {"coordinates":[-114.134977,34.254252],"type":"Point"}
}