{
  "type": "Feature",
  "properties": {
    "addr:full":"5225 State Hwy 95 Parker AZ 85344",
    "addr:housenumber":"5225",
    "addr:postcode":"az 85344",
    "addr:street":"State Hwy 95",
    "iso:country":"US",
    "sg:address":"5225 State Hwy 95",
    "sg:city":"Parker",
    "sg:classifiers":[
        {
            "category":"Food & Beverages",
            "subcategory":"Groceries & Convenience Stores",
            "type":"Retail Goods"
        }
    ],
    "sg:phone":"+1 928 667 2448",
    "sg:postcode":"85344",
    "sg:province":"AZ",
    "sg:tags":[
        "grocer"
    ],
    "wof:name":"River Island Market",
    "wof:placetype":"venue"
},
  "geometry": {"coordinates":[-114.13497700000001,34.254252],"type":"Point"}
}