{
  "type": "Feature",
  "properties": {
    "addr:full":"5839 E Speedway Blvd Tucson AZ 85712",
    "addr:housenumber":"5839",
    "addr:postcode":"85712",
    "addr:street":"E Speedway Blvd",
    "iso:country":"US",
    "sg:address":"5839 E Speedway Blvd",
    "sg:city":"Tucson",
    "sg:classifiers":[
        {
            "category":"Autos & Motor Vehicles",
            "subcategory":"Auto Supplies",
            "type":"Retail Goods"
        }
    ],
    "sg:phone":"+1 520 721 8787",
    "sg:postcode":"85712",
    "sg:province":"AZ",
    "sg:tags":[
        "wheel",
        "tire",
        "accessory"
    ],
    "sg:website":"www.ultraperformance.com",
    "wof:name":"Ultra Performance",
    "wof:placetype":"venue"
},
  "geometry": {"coordinates":[-110.867476,32.236243],"type":"Point"}
}