{
  "type": "Feature",
  "properties": {
    "iso:country":"US",
    "sg:address":"5125 N 16th St",
    "sg:city":"Phoenix",
    "sg:classifiers":[
        {
            "category":"Professional",
            "subcategory":"Engineering",
            "type":"Services"
        }
    ],
    "sg:phone":"+1 602 244 1700",
    "sg:postcode":"85016",
    "sg:province":"AZ",
    "sg:tags":[
        "civil",
        "engineer"
    ],
    "wof:name":"Salaber & Associates",
    "wof:placetype":"venue"
},
  "geometry": {"coordinates":[-112.047531,33.511469],"type":"Point"}
}