{
  "type": "Feature",
  "properties": {
    "addr:full":"45 W University Dr Ste B Mesa AZ 85201",
    "addr:housenumber":"45",
    "addr:postcode":"85201",
    "addr:street":"W University Dr Ste B",
    "iso:country":"US",
    "sg:address":"45 W University Dr Ste B",
    "sg:city":"Mesa",
    "sg:classifiers":[
        {
            "category":"Building & Trades",
            "subcategory":"Landscaping Services",
            "type":"Services"
        },
        {
            "category":"Health Services",
            "subcategory":"Nursing And Care Facility",
            "type":"Services"
        },
        {
            "category":"Health Services",
            "subcategory":"Health Practitioner",
            "type":"Services"
        }
    ],
    "sg:phone":"+1 480 966 9704",
    "sg:postcode":"85201",
    "sg:province":"AZ",
    "sg:tags":[
        "home",
        "eldercare-home",
        "aged",
        "homes-institutional"
    ],
    "wof:name":"Assistance For Independent Living Inc",
    "wof:placetype":"venue"
},
  "geometry": {"coordinates":[-111.832942,33.422343],"type":"Point"}
}