{
  "type": "Feature",
  "properties": {
    "addr:full":"7131 W Ray Rd Chandler AZ 85224",
    "addr:housenumber":"7131",
    "addr:postcode":"85224",
    "addr:street":"W Ray Rd",
    "iso:country":"US",
    "sg:address":"7131 W Ray Rd",
    "sg:city":"Chandler",
    "sg:classifiers":[
        {
            "category":"Shopping",
            "subcategory":"Clothing, Apparel, & Fashions",
            "type":"Retail Goods"
        }
    ],
    "sg:phone":"+1 480 785 7263",
    "sg:postcode":"85224",
    "sg:province":"AZ",
    "wof:name":"White House Inc",
    "wof:placetype":"venue"
},
  "geometry": {"coordinates":[-111.965125,33.319803],"type":"Point"}
}