{
  "type": "Feature",
  "properties": {
    "iso:country":"US",
    "sg:address":"1570 Northern Ave Ste A",
    "sg:city":"Kingman",
    "sg:classifiers":[
        {
            "category":"Restaurant",
            "type":"Food & Drink"
        }
    ],
    "sg:phone":"+1 928 757 8686",
    "sg:postcode":"86409",
    "sg:province":"AZ",
    "wof:name":"Rainbow Diner",
    "wof:placetype":"venue"
},
  "geometry": {"coordinates":[-114.033546,35.253929],"type":"Point"}
}