{
  "type": "Feature",
  "properties": {
    "iso:country":"US",
    "sg:address":"8140 E Cactus Rd",
    "sg:city":"Scottsdale",
    "sg:phone":"+1 480 344 4460",
    "sg:postcode":"85260",
    "sg:province":"AZ",
    "wof:name":"Arizona Allergy Associates",
    "wof:placetype":"venue"
},
  "geometry": {"coordinates":[-111.905202,33.596594],"type":"Point"}
}