{
  "type": "Feature",
  "properties": {
    "iso:country":"US",
    "sg:address":"3699 N Campbell Ave",
    "sg:city":"Tucson",
    "sg:classifiers":[
        {
            "category":"Restaurant",
            "type":"Food & Drink"
        }
    ],
    "sg:phone":"+1 520 320 0468",
    "sg:postcode":"85719",
    "sg:province":"AZ",
    "sg:tags":[
        "eating"
    ],
    "wof:name":"Sahara Food Catering LLC",
    "wof:placetype":"venue"
},
  "geometry": {"coordinates":[-110.943858,32.273256],"type":"Point"}
}