{
  "type": "Feature",
  "properties": {
    "addr:full":"2980 N Alma School Rd Ste 2 Chandler AZ 85224",
    "addr:housenumber":"2980",
    "addr:postcode":"85224",
    "addr:street":"N Alma School Rd Ste 2",
    "iso:country":"US",
    "sg:address":"2980 N Alma School Rd Ste 2",
    "sg:city":"Chandler",
    "sg:classifiers":[
        {
            "category":"Home & Garden",
            "subcategory":"Furniture",
            "type":"Retail Goods"
        }
    ],
    "sg:phone":"+1 480 899 3051",
    "sg:postcode":"85224",
    "sg:province":"AZ",
    "sg:tags":[
        "store"
    ],
    "wof:name":"Expo Furniture",
    "wof:placetype":"venue"
},
  "geometry": {"coordinates":[-111.859227,33.349131],"type":"Point"}
}