{
  "type": "Feature",
  "properties": {
    "addr:full":"3954 Frontage Rd Bullhead City AZ 86442",
    "addr:housenumber":"3954",
    "addr:postcode":"86442",
    "addr:street":"Frontage Rd",
    "iso:country":"US",
    "sg:address":"3954 Frontage Rd",
    "sg:city":"Bullhead City",
    "sg:classifiers":[
        {
            "category":"Personal",
            "subcategory":"Beauty Salon",
            "type":"Services"
        }
    ],
    "sg:phone":"+1 928 763 7010",
    "sg:postcode":"86442",
    "sg:province":"AZ",
    "sg:tags":[
        "manicuring"
    ],
    "wof:name":"Gina's Nail Images",
    "wof:placetype":"venue"
},
  "geometry": {"coordinates":[-114.59039,35.04237],"type":"Point"}
}