{
  "type": "Feature",
  "properties": {
    "iso:country":"US",
    "sg:address":"19425 N 25th St",
    "sg:city":"Phoenix",
    "sg:classifiers":[
        {
            "category":"Shopping",
            "subcategory":"Crafts & Fabrics",
            "type":"Retail Goods"
        }
    ],
    "sg:phone":"+1 602 788 2620",
    "sg:postcode":"85050",
    "sg:province":"AZ",
    "sg:tags":[
        "art",
        "supply"
    ],
    "wof:name":"Karylee Enterprises Inc",
    "wof:placetype":"venue"
},
  "geometry": {"coordinates":[-112.02907999999999,33.662903],"type":"Point"}
}