{
  "type": "Feature",
  "properties": {
    "addr:full":"2445 N Oracle Rd Tucson AZ 85705",
    "addr:housenumber":"2445",
    "addr:postcode":"85705",
    "addr:street":"N Oracle Rd",
    "iso:country":"US",
    "sg:address":"2445 N Oracle Rd",
    "sg:city":"Tucson",
    "sg:classifiers":[
        {
            "category":"Professional",
            "subcategory":"Management & Consulting",
            "type":"Services"
        }
    ],
    "sg:phone":"+1 520 624 0075",
    "sg:postcode":"85705",
    "sg:province":"AZ",
    "sg:tags":[
        "correctional",
        "institution"
    ],
    "wof:name":"New Beginnings Treatment Ctr",
    "wof:placetype":"venue"
},
  "geometry": {"coordinates":[-110.978042,32.250223],"type":"Point"}
}