{
  "type": "Feature",
  "properties": {
    "iso:country":"US",
    "sg:address":"1796 E Fry Blvd",
    "sg:city":"Sierra Vista",
    "sg:classifiers":[
        {
            "category":"Autos & Motor Vehicles",
            "subcategory":"Fuel & Gas Station",
            "type":"Retail Goods"
        }
    ],
    "sg:phone":"+1 520 458 7993",
    "sg:postcode":"85635",
    "sg:province":"AZ",
    "sg:tags":[
        "gasoline",
        "product",
        "station",
        "petroleum"
    ],
    "wof:name":"Chevron",
    "wof:placetype":"venue"
},
  "geometry": {"coordinates":[-110.279321,31.554562],"type":"Point"}
}