{
  "type": "Feature",
  "properties": {
    "iso:country":"US",
    "sg:address":"5900 N Granite Reef Rd",
    "sg:city":"Scottsdale",
    "sg:classifiers":[
        {
            "category":"Building & Trades",
            "subcategory":"Construction",
            "type":"Services"
        }
    ],
    "sg:phone":"+1 480 998 8005",
    "sg:postcode":"85250",
    "sg:province":"AZ",
    "sg:tags":[
        "general",
        "contractor"
    ],
    "wof:name":"W J Development Company LLC",
    "wof:placetype":"venue"
},
  "geometry": {"coordinates":[-111.90013999999999,33.522571],"type":"Point"}
}