{
  "type": "Feature",
  "properties": {
    "iso:country":"US",
    "sg:address":"4453 N Agua Fria Dr",
    "sg:city":"Prescott Valley",
    "sg:classifiers":[
        {
            "category":"Wholesale",
            "subcategory":"Stationery",
            "type":"Manufacturing & Wholesale Goods"
        }
    ],
    "sg:phone":"+1 928 759 3189",
    "sg:postcode":"86314",
    "sg:province":"AZ",
    "sg:tags":[
        "supply"
    ],
    "wof:name":"Astroline Products",
    "wof:placetype":"venue"
},
  "geometry": {"coordinates":[-112.338622,34.605689],"type":"Point"}
}