{
  "type": "Feature",
  "properties": {
    "iso:country":"US",
    "sg:address":"5517 E Friess Dr",
    "sg:city":"Scottsdale",
    "sg:classifiers":[
        {
            "category":"Professional",
            "type":"Services"
        }
    ],
    "sg:phone":"+1 602 996 9223",
    "sg:postcode":"85254",
    "sg:province":"AZ",
    "wof:name":"Aj Bizco LLC",
    "wof:placetype":"venue"
},
  "geometry": {"coordinates":[-111.961519,33.612836],"type":"Point"}
}