{
  "type": "Feature",
  "properties": {
    "iso:country":"US",
    "sg:address":"542 E Monroe St",
    "sg:city":"Phoenix",
    "sg:classifiers":[
        {
            "category":"Organizations",
            "subcategory":"Non-profit Organization",
            "type":"Services"
        }
    ],
    "sg:phone":"+1 480 727 2772",
    "sg:postcode":"85004",
    "sg:province":"AZ",
    "sg:tags":[
        "info",
        "addiction",
        "abuse",
        "treatment",
        "drug"
    ],
    "sg:website":"www.azprevention.org",
    "wof:name":"Arizona Prevention Resource",
    "wof:placetype":"venue"
},
  "geometry": {"coordinates":[-112.066686,33.450472],"type":"Point"}
}