{
  "type": "Feature",
  "properties": {
    "iso:country":"US",
    "sg:address":"475 W Vaughn St",
    "sg:city":"Tempe",
    "sg:classifiers":[
        {
            "category":"Professional",
            "subcategory":"Detective & Security Services",
            "type":"Services"
        }
    ],
    "sg:phone":"+1 480 820 1662",
    "sg:postcode":"85283",
    "sg:province":"AZ",
    "sg:tags":[
        "information",
        "bureau"
    ],
    "sg:website":"http://www.gkservices.com",
    "wof:name":"G & K Svc",
    "wof:placetype":"venue"
},
  "geometry": {"coordinates":[-111.945554,33.361462],"type":"Point"}
}