{
  "type": "Feature",
  "properties": {
    "addr:full":"6622 W Pioneer St Phoenix AZ 85043",
    "addr:housenumber":"6622",
    "addr:postcode":"85043",
    "addr:street":"W Pioneer St",
    "iso:country":"US",
    "sg:address":"6622 W Pioneer St",
    "sg:city":"Phoenix",
    "sg:classifiers":[
        {
            "category":"Building & Trades",
            "subcategory":"Locksmith",
            "type":"Services"
        }
    ],
    "sg:phone":"+1 602 412 1461",
    "sg:postcode":"85043",
    "sg:province":"AZ",
    "sg:tags":[
        "key"
    ],
    "wof:name":"Best Locksmith",
    "wof:placetype":"venue"
},
  "geometry": {"coordinates":[-112.202957,33.418206],"type":"Point"}
}