{
  "type": "Feature",
  "properties": {
    "iso:country":"US",
    "sg:address":"1565 Dover Ave",
    "sg:city":"Lake Havasu City",
    "sg:classifiers":[
        {
            "category":"Autos & Motor Vehicles",
            "subcategory":"Boat Sales",
            "type":"Retail Goods"
        },
        {
            "category":"Recreation",
            "subcategory":"Marina",
            "type":"Entertainment"
        }
    ],
    "sg:phone":"+1 928 453 1999",
    "sg:postcode":"86404",
    "sg:province":"AZ",
    "sg:tags":[
        "repairing"
    ],
    "wof:name":"R C Marine",
    "wof:placetype":"venue"
},
  "geometry": {"coordinates":[-114.358542,34.497144],"type":"Point"}
}