{
  "type": "Feature",
  "properties": {
    "addr:full":"7119 E Shea Blvd #109 Scottsdale AZ 85254",
    "addr:housenumber":"7119",
    "addr:postcode":"85254",
    "addr:street":"E Shea Blvd # 109",
    "iso:country":"US",
    "sg:address":"7119 E Shea Blvd #109",
    "sg:city":"Scottsdale",
    "sg:classifiers":[
        {
            "category":"Building & Trades",
            "subcategory":"Landscaping Services",
            "type":"Services"
        }
    ],
    "sg:phone":"+1 480 447 0829",
    "sg:postcode":"85254",
    "sg:province":"AZ",
    "sg:tags":[
        "tree"
    ],
    "sg:website":"http://www.tree-removal-phoenix.com/",
    "wof:name":"Tree Removal Phoenix",
    "wof:placetype":"venue"
},
  "geometry": {"coordinates":[-111.927693,33.582081],"type":"Point"}
}