{
  "type": "Feature",
  "properties": {
    "addr:full":"9164 N Jessy Ln Tucson AZ 85742",
    "addr:housenumber":"9164",
    "addr:postcode":"85742",
    "addr:street":"N Jessy Ln",
    "iso:country":"US",
    "sg:address":"9164 N Jessy Ln",
    "sg:city":"Tucson",
    "sg:classifiers":[
        {
            "category":"Building & Trades",
            "subcategory":"Landscaping Services",
            "type":"Services"
        }
    ],
    "sg:phone":"+1 520 579 2648",
    "sg:postcode":"85742",
    "sg:province":"AZ",
    "wof:name":"Curbscape",
    "wof:placetype":"venue"
},
  "geometry": {"coordinates":[-111.040941,32.372617],"type":"Point"}
}