{
  "type": "Feature",
  "properties": {
    "iso:country":"US",
    "sg:address":"5320 N 16th St",
    "sg:city":"Phoenix",
    "sg:classifiers":[
        {
            "category":"Organizations",
            "subcategory":"Non-profit Organization",
            "type":"Services"
        }
    ],
    "sg:phone":"+1 602 277 5737",
    "sg:postcode":"85016",
    "sg:province":"AZ",
    "wof:name":"Amalgamated Retirees Benefit",
    "wof:placetype":"venue"
},
  "geometry": {"coordinates":[-112.0476,33.516115],"type":"Point"}
}