{
  "type": "Feature",
  "properties": {
    "addr:full":"555 N Elm Mesa AZ 85201",
    "addr:housenumber":"555",
    "addr:postcode":"85201",
    "addr:street":"N Elm",
    "iso:country":"US",
    "sg:address":"555 N Elm",
    "sg:city":"Mesa",
    "sg:classifiers":[
        {
            "category":"Banks & Credit Unions",
            "subcategory":"Investment Brokerage",
            "type":"Services"
        }
    ],
    "sg:phone":"+1 480 897 7004",
    "sg:postcode":"85201",
    "sg:province":"AZ",
    "sg:tags":[
        "advisory",
        "financial"
    ],
    "wof:name":"Financial Network",
    "wof:placetype":"venue"
},
  "geometry": {"coordinates":[-111.85774499999999,33.425981],"type":"Point"}
}