{
  "type": "Feature",
  "properties": {
    "addr:full":"1394 S Yuma Palms Pkwy Yuma AZ 85365",
    "addr:housenumber":"1394",
    "addr:postcode":"85365",
    "addr:street":"S Yuma Palms Pkwy",
    "iso:country":"US",
    "sg:address":"1394 S Yuma Palms Pkwy",
    "sg:city":"Yuma",
    "sg:classifiers":[
        {
            "category":"Shopping",
            "subcategory":"Department Store",
            "type":"Retail Goods"
        },
        {
            "category":"Shopping",
            "subcategory":"Clothing, Apparel, & Fashions",
            "type":"Retail Goods"
        },
        {
            "category":"Shopping",
            "subcategory":"Discount & Variety Stores",
            "type":"Retail Goods"
        }
    ],
    "sg:phone":"+1 928 783 7353",
    "sg:postcode":"85365",
    "sg:province":"AZ",
    "sg:tags":[
        "clothing"
    ],
    "sg:website":"http://www.marshallsonline.com",
    "wof:name":"Marshalls",
    "wof:placetype":"venue"
},
  "geometry": {"coordinates":[-114.60458800000001,32.703254],"type":"Point"}
}