{
  "type": "Feature",
  "properties": {
    "iso:country":"US",
    "sg:address":"7700 W Arrowhead Towne Center",
    "sg:city":"Glendale",
    "sg:classifiers":[
        {
            "category":"Shopping",
            "subcategory":"Musical Instruments",
            "type":"Retail Goods"
        }
    ],
    "sg:phone":"+1 623 878 4939",
    "sg:postcode":"85308",
    "sg:province":"AZ",
    "sg:tags":[
        "retailer",
        "organ"
    ],
    "wof:name":"Fletcher Organ Studio",
    "wof:placetype":"venue"
},
  "geometry": {"coordinates":[-112.229277,33.643778],"type":"Point"}
}