{
  "type": "Feature",
  "properties": {
    "iso:country":"US",
    "sg:address":"16742 W Whitewing Way",
    "sg:city":"Marana",
    "sg:classifiers":[
        {
            "category":"Building & Trades",
            "subcategory":"Plumbing",
            "type":"Services"
        }
    ],
    "sg:phone":"+1 520 682 6995",
    "sg:postcode":"85653",
    "sg:province":"AZ",
    "sg:tags":[
        "contractor"
    ],
    "wof:name":"Heritage Plumbing",
    "wof:placetype":"venue"
},
  "geometry": {"coordinates":[-111.324027,32.400285],"type":"Point"}
}