{
  "type": "Feature",
  "properties": {
    "iso:country":"US",
    "sg:address":"6635 N 19th Ave",
    "sg:city":"Phoenix",
    "sg:classifiers":[
        {
            "category":"Real Estate",
            "subcategory":"Real Estate Operator",
            "type":"Services"
        }
    ],
    "sg:phone":"+1 602 242 6998",
    "sg:postcode":"85015",
    "sg:province":"AZ",
    "sg:tags":[
        "apartment"
    ],
    "wof:name":"Woodbridge Apartments",
    "wof:placetype":"venue"
},
  "geometry": {"coordinates":[-112.099611,33.534621],"type":"Point"}
}