{
  "type": "Feature",
  "properties": {
    "addr:full":"5050 N 19th Ave Phoenix AZ 85015",
    "addr:housenumber":"5050",
    "addr:postcode":"85015",
    "addr:street":"N 19Th Ave",
    "iso:country":"US",
    "sg:address":"5050 N 19th Ave",
    "sg:city":"Phoenix",
    "sg:classifiers":[
        {
            "category":"Shopping",
            "type":"Retail Goods"
        }
    ],
    "sg:phone":"+1 602 265 2248",
    "sg:postcode":"85015",
    "sg:province":"AZ",
    "sg:tags":[
        "merchandise"
    ],
    "wof:name":"Discount Tools",
    "wof:placetype":"venue"
},
  "geometry": {"coordinates":[-112.09990999999999,33.512518],"type":"Point"}
}