{
  "type": "Feature",
  "properties": {
    "iso:country":"US",
    "sg:address":"5540 W Glendale Ave",
    "sg:city":"Glendale",
    "sg:classifiers":[
        {
            "category":"Building & Trades",
            "subcategory":"Pest Control",
            "type":"Services"
        }
    ],
    "sg:phone":"+1 623 847 2333",
    "sg:postcode":"85301",
    "sg:province":"AZ",
    "wof:name":"Precision Pest Control",
    "wof:placetype":"venue"
},
  "geometry": {"coordinates":[-112.179803,33.538619],"type":"Point"}
}