{
  "type": "Feature",
  "properties": {
    "iso:country":"US",
    "sg:address":"10230 N 39th St",
    "sg:city":"Phoenix",
    "sg:classifiers":[
        {
            "category":"Banks & Credit Unions",
            "subcategory":"Investment Brokerage",
            "type":"Services"
        }
    ],
    "sg:phone":"+1 602 996 4166",
    "sg:postcode":"85028",
    "sg:province":"AZ",
    "sg:tags":[
        "advisory"
    ],
    "wof:name":"Ideas Fog",
    "wof:placetype":"venue"
},
  "geometry": {"coordinates":[-111.997873,33.577932],"type":"Point"}
}