{
  "type": "Feature",
  "properties": {
    "addr:full":"18037 N 39th Ave Glendale AZ 85308",
    "addr:housenumber":"18037",
    "addr:postcode":"85308",
    "addr:street":"N 39Th Ave",
    "iso:country":"US",
    "sg:address":"18037 N 39th Ave",
    "sg:city":"Glendale",
    "sg:classifiers":[
        {
            "category":"Real Estate",
            "subcategory":"Real Estate Services",
            "type":"Services"
        },
        {
            "category":"Building & Trades",
            "subcategory":"Cleaning & Sanitation",
            "type":"Services"
        }
    ],
    "sg:phone":"+1 602 694 4395",
    "sg:postcode":"85308",
    "sg:province":"AZ",
    "sg:tags":[
        "maintenance",
        "cleaners-interior"
    ],
    "wof:name":"Graham Slam Maintenance",
    "wof:placetype":"venue"
},
  "geometry": {"coordinates":[-112.14314299999999,33.650295],"type":"Point"}
}