{
  "type": "Feature",
  "properties": {
    "addr:full":"8627 W Mohave St Tolleson AZ 85353",
    "addr:housenumber":"8627",
    "addr:postcode":"85353",
    "addr:street":"W Mohave St",
    "iso:country":"US",
    "sg:address":"8627 W Mohave St",
    "sg:city":"Tolleson",
    "sg:classifiers":[
        {
            "category":"Retail",
            "subcategory":"Auto Repair",
            "type":"Services"
        }
    ],
    "sg:phone":"+1 602 369 7651",
    "sg:postcode":"85353",
    "sg:province":"AZ",
    "sg:tags":[
        "automobile",
        "top",
        "upholstery"
    ],
    "wof:name":"Leather Medic",
    "wof:placetype":"venue"
},
  "geometry": {"coordinates":[-112.24614,33.431295],"type":"Point"}
}