{
  "type": "Feature",
  "properties": {
    "iso:country":"US",
    "sg:address":"2800 N 44th St",
    "sg:city":"Phoenix",
    "sg:classifiers":[
        {
            "category":"Professional",
            "subcategory":"Employment Agencies",
            "type":"Services"
        }
    ],
    "sg:phone":"+1 602 954 8552",
    "sg:postcode":"85008",
    "sg:province":"AZ",
    "sg:tags":[
        "opportunity"
    ],
    "wof:name":"Johnson Staffing Inc",
    "wof:placetype":"venue"
},
  "geometry": {"coordinates":[-111.987076,33.479409],"type":"Point"}
}