{
  "type": "Feature",
  "properties": {
    "iso:country":"US",
    "sg:address":"3543 W Crocus Dr",
    "sg:city":"Phoenix",
    "sg:classifiers":[
        {
            "category":"Freight",
            "type":"Transportation"
        }
    ],
    "sg:phone":"+1 602 439 1475",
    "sg:postcode":"85053",
    "sg:province":"AZ",
    "sg:tags":[
        "operator",
        "local",
        "trucking"
    ],
    "wof:name":"Dorsett Trucking",
    "wof:placetype":"venue"
},
  "geometry": {"coordinates":[-112.135772,33.615293],"type":"Point"}
}