{
  "type": "Feature",
  "properties": {
    "iso:country":"US",
    "sg:address":"1342 W Park Ave",
    "sg:city":"Chandler",
    "sg:classifiers":[
        {
            "category":"Health Services",
            "subcategory":"Clinic",
            "type":"Services"
        }
    ],
    "sg:phone":"+1 480 792 9388",
    "sg:postcode":"85224",
    "sg:province":"AZ",
    "wof:name":"Dobson Pro Health Ctr",
    "wof:placetype":"venue"
},
  "geometry": {"coordinates":[-111.864805,33.321946],"type":"Point"}
}