{
  "type": "Feature",
  "properties": {
    "iso:country":"US",
    "sg:address":"6422 E Voltaire Ave",
    "sg:city":"Scottsdale",
    "sg:classifiers":[
        {
            "category":"Banks & Credit Unions",
            "subcategory":"Bank",
            "type":"Services"
        }
    ],
    "sg:phone":"+1 480 990 2099",
    "sg:postcode":"85254",
    "sg:province":"AZ",
    "sg:tags":[
        "loan",
        "real estate"
    ],
    "wof:name":"Choice One Mortgage",
    "wof:placetype":"venue"
},
  "geometry": {"coordinates":[-111.941438,33.60996],"type":"Point"}
}