{
  "type": "Feature",
  "properties": {
    "addr:full":"6422 E Voltaire Ave Scottsdale AZ 85254",
    "addr:housenumber":"6422",
    "addr:postcode":"85254",
    "addr:street":"E Voltaire Ave",
    "iso:country":"US",
    "sg:address":"6422 E Voltaire Ave",
    "sg:city":"Scottsdale",
    "sg:classifiers":[
        {
            "category":"Banks & Credit Unions",
            "subcategory":"Bank",
            "type":"Services"
        }
    ],
    "sg:phone":"+1 480 990 2099",
    "sg:postcode":"85254",
    "sg:province":"AZ",
    "sg:tags":[
        "loan",
        "real estate"
    ],
    "wof:name":"Choice One Mortgage",
    "wof:placetype":"venue"
},
  "geometry": {"coordinates":[-111.94143800000001,33.60996],"type":"Point"}
}