{
  "type": "Feature",
  "properties": {
    "iso:country":"US",
    "sg:address":"4747 N 71st Ave",
    "sg:city":"Phoenix",
    "sg:classifiers":[
        {
            "category":"Professional",
            "type":"Services"
        }
    ],
    "sg:phone":"+1 623 848 0937",
    "sg:postcode":"85033",
    "sg:province":"AZ",
    "sg:tags":[
        "transportation"
    ],
    "wof:name":"Advanced Travel Technology",
    "wof:placetype":"venue"
},
  "geometry": {"coordinates":[-112.211337,33.506712],"type":"Point"}
}