{
  "type": "Feature",
  "properties": {
    "iso:country":"US",
    "sg:address":"10575 W Indian School Rd",
    "sg:city":"Avondale",
    "sg:classifiers":[
        {
            "category":"Banks & Credit Unions",
            "subcategory":"Bank",
            "type":"Services"
        }
    ],
    "sg:phone":"+1 623 872 7979",
    "sg:postcode":"85392",
    "sg:province":"AZ",
    "sg:tags":[
        "cashing",
        "check"
    ],
    "wof:name":"Checkmate",
    "wof:placetype":"venue"
},
  "geometry": {"coordinates":[-112.28494000000001,33.493679],"type":"Point"}
}