{
  "type": "Feature",
  "properties": {
    "iso:country":"US",
    "sg:address":"580 Marina Blvd",
    "sg:city":"Bullhead City",
    "sg:classifiers":[
        {
            "category":"Home & Garden",
            "subcategory":"Building Materials",
            "type":"Retail Goods"
        }
    ],
    "sg:phone":"+1 928 763 6136",
    "sg:postcode":"86442",
    "sg:province":"AZ",
    "wof:name":"A Touch Of Glass",
    "wof:placetype":"venue"
},
  "geometry": {"coordinates":[-114.630271,35.10055],"type":"Point"}
}