{
  "type": "Feature",
  "properties": {
    "iso:country":"US",
    "sg:address":"573 W Princeton Ave",
    "sg:city":"Gilbert",
    "sg:classifiers":[
        {
            "category":"Building & Trades",
            "subcategory":"Construction",
            "type":"Services"
        }
    ],
    "sg:phone":"+1 480 813 6901",
    "sg:postcode":"85233",
    "sg:province":"AZ",
    "sg:tags":[
        "nonresidential"
    ],
    "wof:name":"Construction 21 LLC",
    "wof:placetype":"venue"
},
  "geometry": {"coordinates":[-111.801289,33.364897],"type":"Point"}
}