{
  "type": "Feature",
  "properties": {
    "iso:country":"US",
    "sg:address":"7010 Flightline Dr",
    "sg:city":"Kingman",
    "sg:classifiers":[
        {
            "category":"Building & Trades",
            "subcategory":"Equipment Rental",
            "type":"Services"
        }
    ],
    "sg:phone":"+1 928 692 0404",
    "sg:postcode":"86401",
    "sg:province":"AZ",
    "sg:tags":[
        "aircraft",
        "leasing",
        "charter"
    ],
    "wof:name":"KRMC-Guardian Air",
    "wof:placetype":"venue"
},
  "geometry": {"coordinates":[-113.945719,35.258794],"type":"Point"}
}