{
  "type": "Feature",
  "properties": {
    "iso:country":"US",
    "sg:address":"2015 N Dobson Rd",
    "sg:city":"Chandler",
    "sg:classifiers":[
        {
            "category":"Professional",
            "subcategory":"Business Services",
            "type":"Services"
        }
    ],
    "sg:phone":"+1 480 777 0000",
    "sg:postcode":"85224",
    "sg:province":"AZ",
    "sg:tags":[
        "process",
        "server"
    ],
    "sg:website":"www.7770000.com",
    "wof:name":"A-Plus Process Svc",
    "wof:placetype":"venue"
},
  "geometry": {"coordinates":[-111.876361,33.33764],"type":"Point"}
}