{
  "type": "Feature",
  "properties": {
    "addr:full":"502 W Morrow Dr Phoenix AZ 85027",
    "addr:housenumber":"502",
    "addr:postcode":"85027",
    "addr:street":"W Morrow Dr",
    "iso:country":"US",
    "sg:address":"502 W Morrow Dr",
    "sg:city":"Phoenix",
    "sg:classifiers":[
        {
            "category":"Building & Trades",
            "subcategory":"Landscaping Services",
            "type":"Services"
        }
    ],
    "sg:phone":"+1 623 581 7314",
    "sg:postcode":"85027",
    "sg:province":"AZ",
    "wof:name":"Coyote Lawn Care Inc",
    "wof:placetype":"venue"
},
  "geometry": {"coordinates":[-112.080575,33.657642],"type":"Point"}
}