{
  "type": "Feature",
  "properties": {
    "iso:country":"US",
    "sg:address":"2231 N 24th St Ste 2",
    "sg:city":"Phoenix",
    "sg:classifiers":[
        {
            "category":"Shopping",
            "subcategory":"Hobbies, Toys, & Games",
            "type":"Retail Goods"
        },
        {
            "category":"Recreation",
            "subcategory":"Gun Range",
            "type":"Entertainment"
        }
    ],
    "sg:phone":"+1 602 244 2080",
    "sg:postcode":"85008",
    "sg:province":"AZ",
    "sg:tags":[
        "safety",
        "instruction",
        "marksmanship",
        "gunsmith"
    ],
    "wof:name":"Guns & Stuff",
    "wof:placetype":"venue"
},
  "geometry": {"coordinates":[-112.030225,33.47208],"type":"Point"}
}