{
  "type": "Feature",
  "properties": {
    "iso:country":"US",
    "sg:address":"18743 E Bravo Ln",
    "sg:city":"Rio Verde",
    "sg:classifiers":[
        {
            "category":"Education",
            "subcategory":"Special Training",
            "type":"Public Place"
        }
    ],
    "sg:phone":"+1 480 471 3800",
    "sg:postcode":"85263",
    "sg:province":"AZ",
    "sg:tags":[
        "program"
    ],
    "wof:name":"American Society-Trng & Dev",
    "wof:placetype":"venue"
},
  "geometry": {"coordinates":[-111.675252,33.724365],"type":"Point"}
}