{
  "type": "Feature",
  "properties": {
    "iso:country":"US",
    "sg:address":"1975 S Casino Dr",
    "sg:city":"Laughlin",
    "sg:classifiers":[
        {
            "category":"Shopping",
            "subcategory":"Department Store",
            "type":"Retail Goods"
        }
    ],
    "sg:phone":"+1 702 298 0503",
    "sg:postcode":"89029",
    "sg:province":"NV",
    "sg:tags":[
        "shop"
    ],
    "wof:name":"Laughlin Discount Ctr",
    "wof:placetype":"venue"
},
  "geometry": {"coordinates":[-114.574794,35.160992],"type":"Point"}
}