{
  "type": "Feature",
  "properties": {
    "iso:country":"US",
    "sg:address":"2151 E Broadway Rd",
    "sg:city":"Tempe",
    "sg:classifiers":[
        {
            "category":"Professional",
            "type":"Services"
        }
    ],
    "sg:phone":"+1 480 449 9793",
    "sg:postcode":"85282",
    "sg:province":"AZ",
    "sg:tags":[
        "establishment"
    ],
    "wof:name":"Galaxy Classroom",
    "wof:placetype":"venue"
},
  "geometry": {"coordinates":[-111.895121,33.407421],"type":"Point"}
}