{
  "type": "Feature",
  "properties": {
    "iso:country":"US",
    "sg:address":"241 N Roosevelt Ave",
    "sg:city":"Chandler",
    "sg:classifiers":[
        {
            "category":"Restaurant",
            "type":"Food & Drink"
        }
    ],
    "sg:phone":"+1 480 961 0098",
    "sg:postcode":"85226",
    "sg:province":"AZ",
    "sg:tags":[
        "management"
    ],
    "wof:name":"Mindie's Management",
    "wof:placetype":"venue"
},
  "geometry": {"coordinates":[-111.951322,33.307314],"type":"Point"}
}