{
  "type": "Feature",
  "properties": {
    "addr:full":"2775 W Thomas Rd Phoenix AZ 85017",
    "addr:housenumber":"2775",
    "addr:postcode":"85017",
    "addr:street":"W Thomas Rd",
    "iso:country":"US",
    "sg:address":"2775 W Thomas Rd",
    "sg:city":"Phoenix",
    "sg:classifiers":[
        {
            "category":"Banks & Credit Unions",
            "subcategory":"Bank",
            "type":"Services"
        }
    ],
    "sg:phone":"+1 602 455 0410",
    "sg:postcode":"85017",
    "sg:province":"AZ",
    "sg:tags":[
        "loan"
    ],
    "wof:name":"Check Advance",
    "wof:placetype":"venue"
},
  "geometry": {"coordinates":[-112.119612,33.480355],"type":"Point"}
}