{
  "type": "Feature",
  "properties": {
    "iso:country":"US",
    "sg:address":"4087 N Eagle Dr",
    "sg:city":"Kingman",
    "sg:classifiers":[
        {
            "category":"Place Of Worship",
            "subcategory":"Church",
            "type":"Public Place"
        },
        {
            "category":"Place Of Worship",
            "type":"Public Place"
        },
        {
            "category":"Organizations",
            "subcategory":"Religious Organization",
            "type":"Services"
        }
    ],
    "sg:phone":"+1 928 757 2671",
    "sg:postcode":"86409",
    "sg:province":"AZ",
    "sg:tags":[
        "churches-pentecostal-independent",
        "churches-pentecostal"
    ],
    "sg:website":"http://www.pcg.org",
    "wof:name":"The Pentecostal Church Of God Extension Fund",
    "wof:placetype":"venue"
},
  "geometry": {"coordinates":[-113.993276,35.242739],"type":"Point"}
}