{
  "type": "Feature",
  "properties": {
    "iso:country":"US",
    "sg:address":"9034 W Windsor Ave",
    "sg:city":"Phoenix",
    "sg:classifiers":[
        {
            "category":"Professional",
            "type":"Services"
        }
    ],
    "sg:phone":"+1 623 936 0475",
    "sg:postcode":"85037",
    "sg:province":"AZ",
    "wof:name":"Claudia Sanchez Hurtado",
    "wof:placetype":"venue"
},
  "geometry": {"coordinates":[-112.25243500000001,33.476463],"type":"Point"}
}