{
  "type": "Feature",
  "properties": {
    "iso:country":"US",
    "sg:address":"2201 E Huntington Dr",
    "sg:city":"Flagstaff",
    "sg:phone":"+1 928 774 7600",
    "sg:postcode":"86004",
    "sg:province":"AZ",
    "sg:tags":[
        "oil",
        "gasoline"
    ],
    "wof:name":"Carter Oil Co",
    "wof:placetype":"venue"
},
  "geometry": {"coordinates":[-111.624392,35.193978],"type":"Point"}
}