{
  "type": "Feature",
  "properties": {
    "addr:full":"8326 N 7th St Phoenix AZ 85020",
    "addr:housenumber":"8326",
    "addr:postcode":"85020",
    "addr:street":"N 7Th St",
    "iso:country":"US",
    "sg:address":"8326 N 7th St",
    "sg:city":"Phoenix",
    "sg:classifiers":[
        {
            "category":"Professional",
            "type":"Services"
        }
    ],
    "sg:phone":"+1 602 242 9397",
    "sg:postcode":"85020",
    "sg:province":"AZ",
    "wof:name":"Steve & Cindy Family",
    "wof:placetype":"venue"
},
  "geometry": {"coordinates":[-112.065355,33.56024],"type":"Point"}
}