{
  "type": "Feature",
  "properties": {
    "iso:country":"US",
    "sg:address":"8326 W Union Hills Dr",
    "sg:city":"Peoria",
    "sg:classifiers":[
        {
            "category":"Food & Beverages",
            "subcategory":"Groceries & Convenience Stores",
            "type":"Retail Goods"
        }
    ],
    "sg:phone":"+1 623 362 2316",
    "sg:postcode":"85382",
    "sg:province":"AZ",
    "wof:name":"Circle K",
    "wof:placetype":"venue"
},
  "geometry": {"coordinates":[-112.239712,33.652774],"type":"Point"}
}