{
  "type": "Feature",
  "properties": {
    "iso:country":"US",
    "sg:address":"1627 W Bethany Home Rd",
    "sg:city":"Phoenix",
    "sg:classifiers":[
        {
            "category":"Wholesale",
            "subcategory":"Non-durable Goods",
            "type":"Manufacturing & Wholesale Goods"
        }
    ],
    "sg:phone":"+1 602 242 3580",
    "sg:postcode":"85015",
    "sg:province":"AZ",
    "wof:name":"Outwest Gifts",
    "wof:placetype":"venue"
},
  "geometry": {"coordinates":[-112.09495800000001,33.523923],"type":"Point"}
}