{
  "type": "Feature",
  "properties": {
    "addr:full":"201 N Switzer Canyon Dr Flagstaff AZ 86001",
    "addr:housenumber":"201",
    "addr:postcode":"86001",
    "addr:street":"N Switzer Canyon Dr",
    "iso:country":"US",
    "sg:address":"201 N Switzer Canyon Dr",
    "sg:city":"Flagstaff",
    "sg:classifiers":[
        {
            "category":"Food & Beverages",
            "subcategory":"Groceries & Convenience Stores",
            "type":"Retail Goods"
        }
    ],
    "sg:phone":"+1 928 774 2719",
    "sg:postcode":"86001",
    "sg:province":"AZ",
    "sg:tags":[
        "grocer"
    ],
    "wof:name":"Fry's Food Store",
    "wof:placetype":"venue"
},
  "geometry": {"coordinates":[-111.634384,35.194949],"type":"Point"}
}