{
  "type": "Feature",
  "properties": {
    "iso:country":"US",
    "sg:address":"3556 N Desert Oasis",
    "sg:city":"Mesa",
    "sg:classifiers":[
        {
            "category":"Real Estate",
            "subcategory":"Real Estate Services",
            "type":"Services"
        },
        {
            "category":"Banks & Credit Unions",
            "subcategory":"Financial Services",
            "type":"Services"
        }
    ],
    "sg:phone":"+1 480 924 9482",
    "sg:postcode":"85207",
    "sg:province":"AZ",
    "sg:tags":[
        "loan",
        "processing"
    ],
    "wof:name":"Southland Mortgage Corp",
    "wof:placetype":"venue"
},
  "geometry": {"coordinates":[-111.668137,33.480242],"type":"Point"}
}