{
  "type": "Feature",
  "properties": {
    "iso:country":"US",
    "sg:address":"1402 N Miller Rd",
    "sg:city":"Scottsdale",
    "sg:classifiers":[
        {
            "category":"Professional",
            "type":"Services"
        },
        {
            "category":"Professional",
            "subcategory":"Advertising",
            "type":"Services"
        }
    ],
    "sg:phone":"+1 480 941 3911",
    "sg:postcode":"85257",
    "sg:province":"AZ",
    "sg:tags":[
        "mailing",
        "shipping"
    ],
    "wof:name":"Ad Mark Mail",
    "wof:placetype":"venue"
},
  "geometry": {"coordinates":[-111.91757,33.464179],"type":"Point"}
}