{
  "type": "Feature",
  "properties": {
    "addr:full":"4015 E Bell Rd Phoenix AZ 85032",
    "addr:housenumber":"4015",
    "addr:postcode":"85032",
    "addr:street":"E Bell Rd",
    "iso:country":"US",
    "sg:address":"4015 E Bell Rd",
    "sg:city":"Phoenix",
    "sg:classifiers":[
        {
            "category":"Health Services",
            "subcategory":"Optometrist",
            "type":"Services"
        }
    ],
    "sg:phone":"+1 602 971 5858",
    "sg:postcode":"85032",
    "sg:province":"AZ",
    "wof:name":"Mc Auliffe Vision Ctr",
    "wof:placetype":"venue"
},
  "geometry": {"coordinates":[-111.994979,33.640614],"type":"Point"}
}