{
  "type": "Feature",
  "properties": {
    "iso:country":"US",
    "sg:address":"17039 N Boswell Blvd",
    "sg:city":"Sun City",
    "sg:classifiers":[
        {
            "category":"Autos & Motor Vehicles",
            "subcategory":"Auto Supplies",
            "type":"Retail Goods"
        }
    ],
    "sg:phone":"+1 623 974 5701",
    "sg:postcode":"85373",
    "sg:province":"AZ",
    "sg:website":"www.bigotires.com",
    "wof:name":"Big O Tires",
    "wof:placetype":"venue"
},
  "geometry": {"coordinates":[-112.279664,33.64145],"type":"Point"}
}