{
  "type": "Feature",
  "properties": {
    "addr:full":"16022 W Myrtle Ave Litchfield Park AZ 85340",
    "addr:housenumber":"16022",
    "addr:postcode":"85340",
    "addr:street":"W Myrtle Ave",
    "iso:country":"US",
    "sg:address":"16022 W Myrtle Ave",
    "sg:city":"Litchfield Park",
    "sg:classifiers":[
        {
            "category":"Building & Trades",
            "subcategory":"Construction",
            "type":"Services"
        }
    ],
    "sg:phone":"+1 623 935 2820",
    "sg:postcode":"85340",
    "sg:province":"AZ",
    "sg:tags":[
        "hanging",
        "contractor"
    ],
    "wof:name":"Nunez Painting Co",
    "wof:placetype":"venue"
},
  "geometry": {"coordinates":[-112.403784,33.54092],"type":"Point"}
}