{
  "type": "Feature",
  "properties": {
    "addr:full":"223 E Indian School Rd Phoenix AZ 85012",
    "addr:housenumber":"223",
    "addr:postcode":"85012",
    "addr:street":"E Indian School Rd",
    "iso:country":"US",
    "sg:address":"223 E Indian School Rd",
    "sg:city":"Phoenix",
    "sg:classifiers":[
        {
            "category":"Autos & Motor Vehicles",
            "subcategory":"Fuel & Gas Station",
            "type":"Retail Goods"
        },
        {
            "category":"Restaurant",
            "type":"Food & Drink"
        }
    ],
    "sg:phone":"+1 602 604 7970",
    "sg:postcode":"85012",
    "sg:province":"AZ",
    "sg:tags":[
        "convenience",
        "oil",
        "eating",
        "store"
    ],
    "wof:name":"Chevron Food Mart",
    "wof:placetype":"venue"
},
  "geometry": {"coordinates":[-112.07042199999999,33.49478],"type":"Point"}
}