{
  "type": "Feature",
  "properties": {
    "iso:country":"US",
    "sg:address":"6730 E Mcdowell Rd Ste 137",
    "sg:city":"Scottsdale",
    "sg:classifiers":[
        {
            "category":"Shopping",
            "subcategory":"Clothing, Apparel, & Fashions",
            "type":"Retail Goods"
        }
    ],
    "sg:phone":"+1 480 421 9616",
    "sg:postcode":"85257",
    "sg:province":"AZ",
    "sg:tags":[
        "tailor"
    ],
    "wof:name":"Fine Tailoring and Alterations",
    "wof:placetype":"venue"
},
  "geometry": {"coordinates":[-111.935951,33.465691],"type":"Point"}
}