{
  "type": "Feature",
  "properties": {
    "iso:country":"US",
    "sg:address":"4539 N 22nd St",
    "sg:city":"Phoenix",
    "sg:classifiers":[
        {
            "category":"Real Estate",
            "subcategory":"Real Estate Agent",
            "type":"Services"
        }
    ],
    "sg:phone":"+1 602 281 2870",
    "sg:postcode":"85016",
    "sg:province":"AZ",
    "sg:tags":[
        "appraiser"
    ],
    "wof:name":"JAZ Residential Partners",
    "wof:placetype":"venue"
},
  "geometry": {"coordinates":[-112.03447300000001,33.503118],"type":"Point"}
}