{
  "type": "Feature",
  "properties": {
    "addr:full":"5327 W Encanto Blvd Phoenix AZ 85035",
    "addr:housenumber":"5327",
    "addr:postcode":"85035",
    "addr:street":"W Encanto Blvd",
    "iso:country":"US",
    "sg:address":"5327 W Encanto Blvd",
    "sg:city":"Phoenix",
    "sg:classifiers":[
        {
            "category":"Professional",
            "subcategory":"Detective & Security Services",
            "type":"Services"
        }
    ],
    "sg:phone":"+1 602 272 2794",
    "sg:postcode":"85035",
    "sg:province":"AZ",
    "sg:tags":[
        "bodyguard",
        "patrol",
        "guard"
    ],
    "wof:name":"Pachecos Party Patrol",
    "wof:placetype":"venue"
},
  "geometry": {"coordinates":[-112.176039,33.473234],"type":"Point"}
}