{
  "type": "Feature",
  "properties": {
    "iso:country":"US",
    "sg:address":"6741 N Thornydale Rd",
    "sg:city":"Tucson",
    "sg:classifiers":[
        {
            "category":"Restaurant",
            "type":"Food & Drink"
        }
    ],
    "sg:phone":"+1 520 297 4422",
    "sg:postcode":"85741",
    "sg:province":"AZ",
    "sg:tags":[
        "eating"
    ],
    "wof:name":"Silverado Steak House & Lounge",
    "wof:placetype":"venue"
},
  "geometry": {"coordinates":[-111.046177,32.327916],"type":"Point"}
}