{
  "type": "Feature",
  "properties": {
    "iso:country":"US",
    "sg:address":"4550 E Thomas Rd",
    "sg:city":"Phoenix",
    "sg:classifiers":[
        {
            "category":"Banks & Credit Unions",
            "subcategory":"Bank",
            "type":"Services"
        }
    ],
    "sg:phone":"+1 602 262 2761",
    "sg:postcode":"85018",
    "sg:province":"AZ",
    "sg:tags":[
        "federal",
        "savings",
        "institution"
    ],
    "wof:name":"Bank of America",
    "wof:placetype":"venue"
},
  "geometry": {"coordinates":[-111.98370199999999,33.480273],"type":"Point"}
}