{
  "type": "Feature",
  "properties": {
    "iso:country":"US",
    "sg:address":"1413 E Redmon Dr",
    "sg:city":"Tempe",
    "sg:classifiers":[
        {
            "category":"Manufacturing",
            "subcategory":"Petroleum Products",
            "type":"Manufacturing & Wholesale Goods"
        }
    ],
    "sg:phone":"+1 480 820 7269",
    "sg:postcode":"85283",
    "sg:province":"AZ",
    "sg:tags":[
        "contract"
    ],
    "wof:name":"Crafts Man In Brass Mfg",
    "wof:placetype":"venue"
},
  "geometry": {"coordinates":[-111.917057,33.362507],"type":"Point"}
}