{
  "type": "Feature",
  "properties": {
    "addr:full":"1025 S Avondale Blvd Avondale AZ 85323",
    "addr:housenumber":"1025",
    "addr:postcode":"85323",
    "addr:street":"S Avondale Blvd",
    "iso:country":"US",
    "sg:address":"1025 S Avondale Blvd",
    "sg:city":"Avondale",
    "sg:classifiers":[
        {
            "category":"Freight",
            "type":"Transportation"
        }
    ],
    "sg:phone":"+1 623 936 4408",
    "sg:postcode":"85323",
    "sg:province":"AZ",
    "sg:tags":[
        "commercial",
        "storage"
    ],
    "wof:name":"Shurgard Storage Ctr",
    "wof:placetype":"venue"
},
  "geometry": {"coordinates":[-112.306371,33.437882],"type":"Point"}
}