{
  "type": "Feature",
  "properties": {
    "iso:country":"US",
    "sg:address":"2716 S 6th Ave",
    "sg:city":"Tucson",
    "sg:classifiers":[
        {
            "category":"Real Estate",
            "subcategory":"Real Estate Operator",
            "type":"Services"
        }
    ],
    "sg:phone":"+1 520 546 2740",
    "sg:postcode":"85713",
    "sg:province":"AZ",
    "sg:tags":[
        "building",
        "nonresidential"
    ],
    "wof:name":"Sonora Properties Inc",
    "wof:placetype":"venue"
},
  "geometry": {"coordinates":[-110.968433,32.190549],"type":"Point"}
}