{
  "type": "Feature",
  "properties": {
    "iso:country":"US",
    "sg:address":"13555 W McDowell Road Suite 103",
    "sg:city":"Goodyear",
    "sg:classifiers":[
        {
            "category":"Health Services",
            "subcategory":"Doctor",
            "type":"Services"
        }
    ],
    "sg:phone":"+1 623 935 6452",
    "sg:postcode":"85338",
    "sg:province":"AZ",
    "sg:tags":[
        "cardiologist"
    ],
    "wof:name":"Ehrlich Ira B MD",
    "wof:placetype":"venue"
},
  "geometry": {"coordinates":[-112.35086200000001,33.464244],"type":"Point"}
}