{
  "type": "Feature",
  "properties": {
    "iso:country":"US",
    "sg:address":"1745 W Deer Valley Rd",
    "sg:city":"Phoenix",
    "sg:classifiers":[
        {
            "category":"Health Services",
            "subcategory":"Dentist",
            "type":"Services"
        }
    ],
    "sg:phone":"+1 623 879 6066",
    "sg:postcode":"85027",
    "sg:province":"AZ",
    "sg:tags":[
        "dentists-orthodontists"
    ],
    "wof:name":"Gergen Orthodontic",
    "wof:placetype":"venue"
},
  "geometry": {"coordinates":[-112.096837,33.683689],"type":"Point"}
}