{
  "type": "Feature",
  "properties": {
    "iso:country":"US",
    "sg:address":"4255 N Winfield Scott Plz",
    "sg:city":"Scottsdale",
    "sg:classifiers":[
        {
            "category":"Shopping",
            "subcategory":"Clothing, Apparel, & Fashions",
            "type":"Retail Goods"
        }
    ],
    "sg:phone":"+1 480 970 9170",
    "sg:postcode":"85251",
    "sg:province":"AZ",
    "sg:tags":[
        "clothing",
        "boys'"
    ],
    "wof:name":"The Maximum Male",
    "wof:placetype":"venue"
},
  "geometry": {"coordinates":[-111.925203,33.497965],"type":"Point"}
}