{
  "type": "Feature",
  "properties": {
    "addr:full":"111 S 3rd Ave Phoenix AZ 85003",
    "addr:housenumber":"111",
    "addr:postcode":"85003",
    "addr:street":"S 3Rd Ave",
    "iso:country":"US",
    "sg:address":"111 S 3rd Ave",
    "sg:city":"Phoenix",
    "sg:classifiers":[
        {
            "category":"Government",
            "subcategory":"Jail",
            "type":"Public Place"
        }
    ],
    "sg:phone":"+1 602 506 3871",
    "sg:postcode":"85003",
    "sg:province":"AZ",
    "sg:tags":[
        "investigation"
    ],
    "wof:name":"Probation- Adult",
    "wof:placetype":"venue"
},
  "geometry": {"coordinates":[-112.077586,33.446179],"type":"Point"}
}