{
  "type": "Feature",
  "properties": {
    "addr:full":"805 S McQueen Rd Chandler AZ 85225",
    "addr:housenumber":"805",
    "addr:postcode":"85225",
    "addr:street":"S Mcqueen Rd",
    "iso:country":"US",
    "sg:address":"805 S McQueen Rd",
    "sg:city":"Chandler",
    "sg:classifiers":[
        {
            "category":"Professional",
            "type":"Services"
        }
    ],
    "sg:phone":"+1 480 782 8756",
    "sg:postcode":"85225",
    "sg:province":"AZ",
    "sg:tags":[
        "establishment"
    ],
    "wof:name":"Brown Family Communities",
    "wof:placetype":"venue"
},
  "geometry": {"coordinates":[-111.82420999999999,33.293912],"type":"Point"}
}