{
  "type": "Feature",
  "properties": {
    "iso:country":"US",
    "sg:address":"340 S 13th Dr",
    "sg:city":"Show Low",
    "sg:classifiers":[
        {
            "category":"Building & Trades",
            "subcategory":"Construction",
            "type":"Services"
        }
    ],
    "sg:phone":"+1 928 537 2640",
    "sg:postcode":"85901",
    "sg:province":"AZ",
    "sg:tags":[
        "sewer",
        "contractor"
    ],
    "wof:name":"Septic Tank Instillation",
    "wof:placetype":"venue"
},
  "geometry": {"coordinates":[-110.05673,34.246303],"type":"Point"}
}