{
  "type": "Feature",
  "properties": {
    "addr:full":"13720 N Sandario Rd Marana AZ 85653",
    "addr:housenumber":"13720",
    "addr:postcode":"85653",
    "addr:street":"N Sandario Rd",
    "iso:country":"US",
    "sg:address":"13720 N Sandario Rd",
    "sg:city":"Marana",
    "sg:classifiers":[
        {
            "category":"Building & Trades",
            "subcategory":"Construction",
            "type":"Services"
        }
    ],
    "sg:phone":"+1 520 682 2452",
    "sg:postcode":"85653",
    "sg:province":"AZ",
    "sg:tags":[
        "carpentry",
        "contractor"
    ],
    "wof:name":"Darrells Carpenter Shop",
    "wof:placetype":"venue"
},
  "geometry": {"coordinates":[-111.21692299999999,32.454644],"type":"Point"}
}