{
  "type": "Feature",
  "properties": {
    "iso:country":"US",
    "sg:address":"130 E Baseline Rd",
    "sg:city":"Tempe",
    "sg:classifiers":[
        {
            "category":"Professional",
            "subcategory":"Management & Consulting",
            "type":"Services"
        }
    ],
    "sg:phone":"+1 480 838 7515",
    "sg:postcode":"85283",
    "sg:province":"AZ",
    "sg:tags":[
        "retail",
        "direct",
        "sales"
    ],
    "wof:name":"Water n Ice",
    "wof:placetype":"venue"
},
  "geometry": {"coordinates":[-111.938142,33.378307],"type":"Point"}
}