{
  "type": "Feature",
  "properties": {
    "addr:full":"2385 S Cobblestone Cir Gilbert AZ 85296",
    "addr:housenumber":"2385",
    "addr:postcode":"85296",
    "addr:street":"S Cobblestone Cir",
    "iso:country":"US",
    "sg:address":"2385 S Cobblestone Cir",
    "sg:city":"Gilbert",
    "sg:classifiers":[
        {
            "category":"Professional",
            "type":"Services"
        }
    ],
    "sg:phone":"+1 480 812 8559",
    "sg:postcode":"85296",
    "sg:province":"AZ",
    "sg:tags":[
        "establishment"
    ],
    "wof:name":"Frye's Outdoors",
    "wof:placetype":"venue"
},
  "geometry": {"coordinates":[-111.760436,33.307826],"type":"Point"}
}