{
  "type": "Feature",
  "properties": {
    "iso:country":"US",
    "sg:address":"2850 E Van Buren St",
    "sg:city":"Phoenix",
    "sg:classifiers":[
        {
            "category":"Wholesale",
            "subcategory":"Toys & Hobbies",
            "type":"Manufacturing & Wholesale Goods"
        }
    ],
    "sg:phone":"+1 602 286 0955",
    "sg:postcode":"85008",
    "sg:province":"AZ",
    "sg:tags":[
        "wholesaler"
    ],
    "wof:name":"Bnt Auto Wholesale",
    "wof:placetype":"venue"
},
  "geometry": {"coordinates":[-112.020306,33.451401],"type":"Point"}
}