{
  "type": "Feature",
  "properties": {
    "addr:full":"3165 N Colorado St Chandler AZ 85225",
    "addr:housenumber":"3165",
    "addr:postcode":"85225",
    "addr:street":"N Colorado St",
    "iso:country":"US",
    "sg:address":"3165 N Colorado St",
    "sg:city":"Chandler",
    "sg:classifiers":[
        {
            "category":"Manufacturing",
            "subcategory":"Motor Vehicles & Parts",
            "type":"Manufacturing & Wholesale Goods"
        }
    ],
    "sg:phone":"+1 480 926 7733",
    "sg:postcode":"85225",
    "sg:province":"AZ",
    "sg:tags":[
        "vinyl",
        "embroidery",
        "graphics"
    ],
    "wof:name":"Speed Graphics",
    "wof:placetype":"venue"
},
  "geometry": {"coordinates":[-111.838379,33.353371],"type":"Point"}
}