{
  "type": "Feature",
  "properties": {
    "addr:full":"1305 S Yuma Palms Pkwy Yuma AZ 85365",
    "addr:housenumber":"1305",
    "addr:postcode":"85365",
    "addr:street":"S Yuma Palms Pkwy",
    "iso:country":"US",
    "sg:address":"1305 S Yuma Palms Pkwy",
    "sg:city":"Yuma",
    "sg:classifiers":[
        {
            "category":"Shopping",
            "subcategory":"Department Store",
            "type":"Retail Goods"
        },
        {
            "category":"Shopping",
            "subcategory":"Discount & Variety Stores",
            "type":"Retail Goods"
        }
    ],
    "sg:phone":"+1 928 329 4559",
    "sg:postcode":"85365",
    "sg:province":"AZ",
    "wof:name":"Westcor",
    "wof:placetype":"venue"
},
  "geometry": {"coordinates":[-114.605048,32.703506],"type":"Point"}
}