{
  "type": "Feature",
  "properties": {
    "iso:country":"US",
    "sg:address":"2311 E Hartford Ave",
    "sg:city":"Phoenix",
    "sg:classifiers":[
        {
            "category":"Shopping",
            "subcategory":"Gifts & Souvenirs",
            "type":"Retail Goods"
        }
    ],
    "sg:phone":"+1 602 485 5900",
    "sg:postcode":"85022",
    "sg:province":"AZ",
    "sg:tags":[
        "announcement",
        "invitation"
    ],
    "wof:name":"Rock Paper Scissors",
    "wof:placetype":"venue"
},
  "geometry": {"coordinates":[-112.032506,33.643146],"type":"Point"}
}