{
  "type": "Feature",
  "properties": {
    "iso:country":"US",
    "sg:address":"6080 N Oracle Rd",
    "sg:city":"Tucson",
    "sg:classifiers":[
        {
            "category":"Wholesale",
            "subcategory":"Construction Materials",
            "type":"Manufacturing & Wholesale Goods"
        }
    ],
    "sg:phone":"+1 520 297 1136",
    "sg:postcode":"85704",
    "sg:province":"AZ",
    "sg:tags":[
        "mobile",
        "home"
    ],
    "wof:name":"Graham Mh Sales",
    "wof:placetype":"venue"
},
  "geometry": {"coordinates":[-110.976413,32.315943],"type":"Point"}
}