{
  "type": "Feature",
  "properties": {
    "addr:full":"4685 Finance Way Kingman AZ 86401",
    "addr:housenumber":"4685",
    "addr:postcode":"86401",
    "addr:street":"Finance Way",
    "iso:country":"US",
    "sg:address":"4685 Finance Way",
    "sg:city":"Kingman",
    "sg:classifiers":[
        {
            "category":"Manufacturing",
            "subcategory":"Petroleum Products",
            "type":"Manufacturing & Wholesale Goods"
        }
    ],
    "sg:phone":"+1 928 692 9002",
    "sg:postcode":"86401",
    "sg:province":"AZ",
    "sg:tags":[
        "asphalt",
        "mfg"
    ],
    "wof:name":"Henry Company",
    "wof:placetype":"venue"
},
  "geometry": {"coordinates":[-113.94389,35.262376],"type":"Point"}
}