{
  "type": "Feature",
  "properties": {
    "iso:country":"US",
    "sg:address":"33 S Val Vista Dr",
    "sg:city":"Gilbert",
    "sg:classifiers":[
        {
            "category":"Food & Beverages",
            "subcategory":"Groceries & Convenience Stores",
            "type":"Retail Goods"
        }
    ],
    "sg:phone":"+1 480 632 2057",
    "sg:postcode":"85296",
    "sg:province":"AZ",
    "sg:website":"p66conoco76.conocophillips.com",
    "wof:name":"Phillips 66",
    "wof:placetype":"venue"
},
  "geometry": {"coordinates":[-111.755439,33.349511],"type":"Point"}
}