{
  "type": "Feature",
  "properties": {
    "iso:country":"US",
    "sg:address":"15757 N 78th St",
    "sg:city":"Scottsdale",
    "sg:classifiers":[
        {
            "category":"Real Estate",
            "subcategory":"Real Estate Agent",
            "type":"Services"
        }
    ],
    "sg:phone":"+1 480 905 7236",
    "sg:postcode":"85260",
    "sg:province":"AZ",
    "wof:name":"Palo Cristi Airpark-Prop Mgn",
    "wof:placetype":"venue"
},
  "geometry": {"coordinates":[-111.912705,33.629282],"type":"Point"}
}