{
  "type": "Feature",
  "properties": {
    "iso:country":"US",
    "sg:address":"820 E Southern Ave",
    "sg:city":"Mesa",
    "sg:classifiers":[
        {
            "category":"Retail",
            "subcategory":"Veterinary Services",
            "type":"Services"
        }
    ],
    "sg:phone":"+1 480 969 0900",
    "sg:postcode":"85204",
    "sg:province":"AZ",
    "wof:name":"Sheri Beck Dvm",
    "wof:placetype":"venue"
},
  "geometry": {"coordinates":[-111.811179,33.39344],"type":"Point"}
}