{
  "type": "Feature",
  "properties": {
    "iso:country":"US",
    "sg:address":"336 E Edward St",
    "sg:city":"Nogales",
    "sg:classifiers":[
        {
            "category":"Building & Trades",
            "subcategory":"Construction",
            "type":"Services"
        }
    ],
    "sg:phone":"+1 520 287 4330",
    "sg:postcode":"85621",
    "sg:province":"AZ",
    "sg:tags":[
        "home",
        "family"
    ],
    "wof:name":"Hl Construction Co",
    "wof:placetype":"venue"
},
  "geometry": {"coordinates":[-110.924466,31.345597],"type":"Point"}
}