{
  "type": "Feature",
  "properties": {
    "iso:country":"US",
    "sg:address":"4031 N 2nd Pl",
    "sg:city":"Phoenix",
    "sg:classifiers":[
        {
            "category":"Professional",
            "subcategory":"Detective & Security Services",
            "type":"Services"
        }
    ],
    "sg:phone":"+1 602 630 5668",
    "sg:postcode":"85012",
    "sg:province":"AZ",
    "sg:tags":[
        "information",
        "bureau"
    ],
    "wof:name":"Qwest Broadband Svc",
    "wof:placetype":"venue"
},
  "geometry": {"coordinates":[-112.070509,33.494003],"type":"Point"}
}