{
  "type": "Feature",
  "properties": {
    "iso:country":"US",
    "sg:address":"23420 W Hammond Dr",
    "sg:city":"Buckeye",
    "sg:classifiers":[
        {
            "category":"Real Estate",
            "subcategory":"Real Estate Agent",
            "type":"Services"
        }
    ],
    "sg:phone":"+1 623 386 6263",
    "sg:postcode":"85326",
    "sg:province":"AZ",
    "wof:name":"Sonoran West Real Estate",
    "wof:placetype":"venue"
},
  "geometry": {"coordinates":[-112.551951,33.423602],"type":"Point"}
}