{
  "type": "Feature",
  "properties": {
    "addr:full":"4344 W Indian School Rd Phoenix AZ 85031",
    "addr:housenumber":"4344",
    "addr:postcode":"85031",
    "addr:street":"W Indian School Rd",
    "iso:country":"US",
    "sg:address":"4344 W Indian School Rd",
    "sg:city":"Phoenix",
    "sg:classifiers":[
        {
            "category":"Shopping",
            "subcategory":"Discount & Variety Stores",
            "type":"Retail Goods"
        }
    ],
    "sg:phone":"+1 623 247 6039",
    "sg:postcode":"85031",
    "sg:province":"AZ",
    "wof:name":"Big Lots",
    "wof:placetype":"venue"
},
  "geometry": {"coordinates":[-112.153575,33.495031],"type":"Point"}
}