{
  "type": "Feature",
  "properties": {
    "iso:country":"US",
    "sg:address":"6718 W Greenway Rd",
    "sg:city":"Peoria",
    "sg:classifiers":[
        {
            "category":"Professional",
            "subcategory":"Engineering",
            "type":"Services"
        }
    ],
    "sg:phone":"+1 623 776 9750",
    "sg:postcode":"85381",
    "sg:province":"AZ",
    "sg:tags":[
        "engineer"
    ],
    "wof:name":"Brown Engineering Co Inc",
    "wof:placetype":"venue"
},
  "geometry": {"coordinates":[-112.20408,33.625163],"type":"Point"}
}