{
  "type": "Feature",
  "properties": {
    "iso:country":"US",
    "sg:address":"48 N Morley Ave",
    "sg:city":"Nogales",
    "sg:classifiers":[
        {
            "category":"Professional",
            "type":"Services"
        }
    ],
    "sg:phone":"+1 520 287 4111",
    "sg:postcode":"85621",
    "sg:province":"AZ",
    "sg:tags":[
        "establishment"
    ],
    "wof:name":"In Mart",
    "wof:placetype":"venue"
},
  "geometry": {"coordinates":[-110.940903,31.333438],"type":"Point"}
}