{
  "type": "Feature",
  "properties": {
    "iso:country":"US",
    "sg:address":"1817 E Southern Ave",
    "sg:city":"Tempe",
    "sg:classifiers":[
        {
            "category":"Wholesale",
            "subcategory":"Stationery",
            "type":"Manufacturing & Wholesale Goods"
        }
    ],
    "sg:phone":"+1 602 234 9058",
    "sg:postcode":"85282",
    "sg:province":"AZ",
    "sg:tags":[
        "paper",
        "printers-equipment",
        "printing",
        "supply",
        "writing"
    ],
    "wof:name":"Premium Imaging Products",
    "wof:placetype":"venue"
},
  "geometry": {"coordinates":[-111.908039,33.392972],"type":"Point"}
}