{
  "type": "Feature",
  "properties": {
    "addr:full":"3101 E Shea Blvd Phoenix AZ 85028",
    "addr:housenumber":"3101",
    "addr:postcode":"85028",
    "addr:street":"E Shea Blvd",
    "iso:country":"US",
    "sg:address":"3101 E Shea Blvd",
    "sg:city":"Phoenix",
    "sg:classifiers":[
        {
            "category":"Manufacturing",
            "subcategory":"Tools & Machinery",
            "type":"Manufacturing & Wholesale Goods"
        }
    ],
    "sg:phone":"+1 602 765 8208",
    "sg:postcode":"85028",
    "sg:province":"AZ",
    "sg:tags":[
        "lamp",
        "electric",
        "mfg"
    ],
    "wof:name":"Phillips Lighting",
    "wof:placetype":"venue"
},
  "geometry": {"coordinates":[-112.013104,33.582485],"type":"Point"}
}