{
  "type": "Feature",
  "properties": {
    "iso:country":"US",
    "sg:address":"416 N Herbert Ave",
    "sg:city":"Tucson",
    "sg:classifiers":[
        {
            "category":"Professional",
            "subcategory":"Business Services",
            "type":"Services"
        }
    ],
    "sg:phone":"+1 520 622 2440",
    "sg:postcode":"85705",
    "sg:province":"AZ",
    "sg:tags":[
        "translator",
        "interpreter"
    ],
    "wof:name":"Nexo English Spanish Comm",
    "wof:placetype":"venue"
},
  "geometry": {"coordinates":[-110.96635,32.227731],"type":"Point"}
}