{
  "type": "Feature",
  "properties": {
    "addr:full":"2001 N 4th St Flagstaff AZ 86004",
    "addr:housenumber":"2001",
    "addr:postcode":"86004",
    "addr:street":"N 4Th St",
    "iso:country":"US",
    "sg:address":"2001 N 4th St",
    "sg:city":"Flagstaff",
    "sg:classifiers":[
        {
            "category":"Health Services",
            "subcategory":"Chiropractor",
            "type":"Services"
        }
    ],
    "sg:phone":"+1 928 214 8969",
    "sg:postcode":"86004",
    "sg:province":"AZ",
    "sg:tags":[
        "chiropractic"
    ],
    "wof:name":"Michael Martin, DC",
    "wof:placetype":"venue"
},
  "geometry": {"coordinates":[-111.613449,35.207691],"type":"Point"}
}