{
  "type": "Feature",
  "properties": {
    "addr:full":"7400 N Glen Harbor Blvd Glendale AZ 85307",
    "addr:housenumber":"7400",
    "addr:postcode":"85307",
    "addr:street":"N Glen Harbor Blvd",
    "iso:country":"US",
    "sg:address":"7400 N Glen Harbor Blvd",
    "sg:city":"Glendale",
    "sg:classifiers":[
        {
            "category":"Autos & Motor Vehicles",
            "subcategory":"Auto Supplies",
            "type":"Retail Goods"
        }
    ],
    "sg:phone":"+1 623 872 8300",
    "sg:postcode":"85307",
    "sg:province":"AZ",
    "sg:tags":[
        "car",
        "polishing",
        "washing",
        "equipment"
    ],
    "wof:name":"Proto-Vest, Inc.",
    "wof:placetype":"venue"
},
  "geometry": {"coordinates":[-112.28816,33.542439],"type":"Point"}
}