{
  "type": "Feature",
  "properties": {
    "iso:country":"US",
    "sg:address":"10177 E Osborn Rd",
    "sg:city":"Scottsdale",
    "sg:classifiers":[
        {
            "category":"Real Estate",
            "subcategory":"Real Estate Services",
            "type":"Services"
        }
    ],
    "sg:phone":"+1 480 850 8980",
    "sg:postcode":"85256",
    "sg:province":"AZ",
    "sg:tags":[
        "consultant",
        "housing",
        "referral"
    ],
    "sg:website":"http://www.srmaterials.com",
    "wof:name":"Salt River Community Hsing Div",
    "wof:placetype":"venue"
},
  "geometry": {"coordinates":[-111.861549,33.487767],"type":"Point"}
}