{
  "type": "Feature",
  "properties": {
    "iso:country":"US",
    "sg:address":"3217 E Elmwood St",
    "sg:city":"Mesa",
    "sg:classifiers":[
        {
            "category":"Shopping",
            "subcategory":"Clothing, Apparel, & Fashions",
            "type":"Retail Goods"
        }
    ],
    "sg:phone":"+1 480 654 2621",
    "sg:postcode":"85213",
    "sg:province":"AZ",
    "wof:name":"Designers Dreams",
    "wof:placetype":"venue"
},
  "geometry": {"coordinates":[-111.75857,33.432199],"type":"Point"}
}