{
  "type": "Feature",
  "properties": {
    "addr:full":"3217 E Elmwood St Mesa AZ 85213",
    "addr:housenumber":"3217",
    "addr:postcode":"85213",
    "addr:street":"E Elmwood St",
    "iso:country":"US",
    "sg:address":"3217 E Elmwood St",
    "sg:city":"Mesa",
    "sg:classifiers":[
        {
            "category":"Shopping",
            "subcategory":"Clothing, Apparel, & Fashions",
            "type":"Retail Goods"
        }
    ],
    "sg:phone":"+1 480 654 2621",
    "sg:postcode":"85213",
    "sg:province":"AZ",
    "wof:name":"Designers Dreams",
    "wof:placetype":"venue"
},
  "geometry": {"coordinates":[-111.75857000000001,33.432199],"type":"Point"}
}