{
  "type": "Feature",
  "properties": {
    "iso:country":"US",
    "sg:address":"8125 E 22nd St",
    "sg:city":"Tucson",
    "sg:classifiers":[
        {
            "category":"Freight",
            "type":"Transportation"
        }
    ],
    "sg:phone":"+1 520 751 1019",
    "sg:postcode":"85710",
    "sg:province":"AZ",
    "sg:tags":[
        "commercial",
        "storage",
        "special"
    ],
    "wof:name":"A Atlas Discount Storage",
    "wof:placetype":"venue"
},
  "geometry": {"coordinates":[-110.818179,32.20649],"type":"Point"}
}