{
  "type": "Feature",
  "properties": {
    "iso:country":"US",
    "sg:address":"2340 W Cactus Rd",
    "sg:city":"Phoenix",
    "sg:classifiers":[
        {
            "category":"Social Services",
            "subcategory":"Child Care",
            "type":"Services"
        }
    ],
    "sg:phone":"+1 602 997 7439",
    "sg:postcode":"85029",
    "sg:province":"AZ",
    "sg:tags":[
        "kindergarten",
        "academic",
        "school"
    ],
    "wof:name":"Master's Preschool",
    "wof:placetype":"venue"
},
  "geometry": {"coordinates":[-112.110015,33.596503],"type":"Point"}
}