{
  "type": "Feature",
  "properties": {
    "iso:country":"US",
    "sg:address":"1648 W Wetmore Rd",
    "sg:city":"Tucson",
    "sg:classifiers":[
        {
            "category":"Building & Trades",
            "subcategory":"Construction",
            "type":"Services"
        }
    ],
    "sg:phone":"+1 520 293 3446",
    "sg:postcode":"85705",
    "sg:province":"AZ",
    "sg:tags":[
        "contractor",
        "general",
        "framing",
        "carpentry"
    ],
    "wof:name":"RCCI Carpentry Inc",
    "wof:placetype":"venue"
},
  "geometry": {"coordinates":[-111.003209,32.286942],"type":"Point"}
}