{
  "type": "Feature",
  "properties": {
    "addr:full":"12633 W Sheridan St Avondale AZ 85392",
    "addr:housenumber":"12633",
    "addr:postcode":"85392",
    "addr:street":"W Sheridan St",
    "iso:country":"US",
    "sg:address":"12633 W Sheridan St",
    "sg:city":"Avondale",
    "sg:classifiers":[
        {
            "category":"Banks & Credit Unions",
            "subcategory":"Financial Services",
            "type":"Services"
        }
    ],
    "sg:phone":"+1 602 705 6812",
    "sg:postcode":"85392",
    "sg:province":"AZ",
    "sg:tags":[
        "financing"
    ],
    "wof:name":"Collins Funding",
    "wof:placetype":"venue"
},
  "geometry": {"coordinates":[-112.33025499999999,33.473912],"type":"Point"}
}