{
  "type": "Feature",
  "properties": {
    "iso:country":"US",
    "sg:address":"100 S Clark Rd",
    "sg:city":"Show Low",
    "sg:classifiers":[
        {
            "category":"Retail",
            "subcategory":"Veterinary Services",
            "type":"Services"
        }
    ],
    "sg:phone":"+1 928 537 2880",
    "sg:postcode":"85901",
    "sg:province":"AZ",
    "wof:name":"Alta Sierra Veterinary Clinic",
    "wof:placetype":"venue"
},
  "geometry": {"coordinates":[-110.071751,34.24735],"type":"Point"}
}