{
  "type": "Feature",
  "properties": {
    "iso:country":"US",
    "sg:address":"401 1st Ave",
    "sg:city":"Kingman",
    "sg:classifiers":[
        {
            "category":"Freight",
            "type":"Transportation"
        }
    ],
    "sg:phone":"+1 928 753 2969",
    "sg:postcode":"86401",
    "sg:province":"AZ",
    "sg:tags":[
        "operator",
        "local",
        "hauling",
        "trucking"
    ],
    "wof:name":"Levy Trucking Co",
    "wof:placetype":"venue"
},
  "geometry": {"coordinates":[-114.052006,35.184788],"type":"Point"}
}