{
  "type": "Feature",
  "properties": {
    "iso:country":"US",
    "sg:address":"3305 Northern Ave",
    "sg:city":"Kingman",
    "sg:classifiers":[
        {
            "category":"Home & Garden",
            "subcategory":"Mobile Homes",
            "type":"Retail Goods"
        }
    ],
    "sg:phone":"+1 928 757 2161",
    "sg:postcode":"86401",
    "sg:province":"AZ",
    "sg:tags":[
        "equipment",
        "furniture"
    ],
    "wof:name":"Prestige Homes",
    "wof:placetype":"venue"
},
  "geometry": {"coordinates":[-114.001349,35.254021],"type":"Point"}
}