{
  "type": "Feature",
  "properties": {
    "iso:country":"US",
    "sg:address":"1 W Deer Valley Rd",
    "sg:city":"Phoenix",
    "sg:classifiers":[
        {
            "category":"Building & Trades",
            "subcategory":"Construction",
            "type":"Services"
        }
    ],
    "sg:phone":"+1 623 780 9228",
    "sg:postcode":"85027",
    "sg:province":"AZ",
    "sg:tags":[
        "painter"
    ],
    "wof:name":"Coyote Southwest Painting",
    "wof:placetype":"venue"
},
  "geometry": {"coordinates":[-112.07420399999999,33.683752],"type":"Point"}
}