{
  "type": "Feature",
  "properties": {
    "iso:country":"US",
    "sg:address":"16605 N 28th Ave",
    "sg:city":"Phoenix",
    "sg:classifiers":[
        {
            "category":"Professional",
            "subcategory":"Engineering",
            "type":"Services"
        }
    ],
    "sg:phone":"+1 602 285 1669",
    "sg:postcode":"85053",
    "sg:province":"AZ",
    "sg:tags":[
        "engineer"
    ],
    "wof:name":"Kraemer Engineering Inc",
    "wof:placetype":"venue"
},
  "geometry": {"coordinates":[-112.118915,33.633522],"type":"Point"}
}