{
  "type": "Feature",
  "properties": {
    "iso:country":"US",
    "sg:address":"1480 N Litchfield Rd",
    "sg:city":"Goodyear",
    "sg:classifiers":[
        {
            "category":"Restaurant",
            "type":"Food & Drink"
        }
    ],
    "sg:phone":"+1 623 209 0144",
    "sg:postcode":"85338",
    "sg:province":"AZ",
    "sg:tags":[
        "barbeque"
    ],
    "sg:website":"www.elpasobarbeque.com",
    "wof:name":"El Paso Grill & Bar-B-Que",
    "wof:placetype":"venue"
},
  "geometry": {"coordinates":[-112.358122,33.427701],"type":"Point"}
}