{
  "type": "Feature",
  "properties": {
    "iso:country":"US",
    "sg:address":"380 Raintree Rd",
    "sg:city":"Sedona",
    "sg:classifiers":[
        {
            "category":"Wholesale",
            "subcategory":"Books, Periodicals, & Newspapers",
            "type":"Manufacturing & Wholesale Goods"
        }
    ],
    "sg:phone":"+1 928 284 9055",
    "sg:postcode":"86351",
    "sg:province":"AZ",
    "wof:name":"Seeking New Solutions",
    "wof:placetype":"venue"
},
  "geometry": {"coordinates":[-111.724046,34.795071],"type":"Point"}
}