{
  "type": "Feature",
  "properties": {
    "iso:country":"US",
    "sg:address":"5831 N 46th Pl",
    "sg:city":"Phoenix",
    "sg:classifiers":[
        {
            "category":"Professional",
            "subcategory":"Art Services",
            "type":"Services"
        }
    ],
    "sg:phone":"+1 602 952 8767",
    "sg:postcode":"85018",
    "sg:province":"AZ",
    "sg:tags":[
        "sculptor"
    ],
    "sg:website":"http://www.kevincaron.com",
    "wof:name":"Oneoff Creations",
    "wof:placetype":"venue"
},
  "geometry": {"coordinates":[-111.97998,33.5214],"type":"Point"}
}