{
  "type": "Feature",
  "properties": {
    "addr:full":"180 S 4th W St Johns AZ 85936",
    "addr:housenumber":"180",
    "addr:postcode":"85936",
    "addr:street":"S 4Th W St Johns",
    "iso:country":"US",
    "sg:address":"180 S 4th W",
    "sg:city":"St Johns",
    "sg:classifiers":[
        {
            "category":"Manufacturing",
            "subcategory":"Printing",
            "type":"Manufacturing & Wholesale Goods"
        }
    ],
    "sg:phone":"+1 928 337 4814",
    "sg:postcode":"85936",
    "sg:province":"AZ",
    "sg:tags":[
        "newspaper"
    ],
    "wof:name":"Apache County Herald",
    "wof:placetype":"venue"
},
  "geometry": {"coordinates":[-109.371094,34.504223],"type":"Point"}
}