{
  "type": "Feature",
  "properties": {
    "iso:country":"US",
    "sg:address":"3302 E Main St",
    "sg:city":"Mesa",
    "sg:classifiers":[
        {
            "category":"Autos & Motor Vehicles",
            "subcategory":"Recreational Vehicle Sales",
            "type":"Retail Goods"
        }
    ],
    "sg:phone":"+1 480 985 4218",
    "sg:postcode":"85213",
    "sg:province":"AZ",
    "wof:name":"Beaudry Rv Mesa",
    "wof:placetype":"venue"
},
  "geometry": {"coordinates":[-111.75805200000001,33.415582],"type":"Point"}
}