{
  "type": "Feature",
  "properties": {
    "iso:country":"US",
    "sg:address":"1905 N Broad St",
    "sg:city":"Globe",
    "sg:classifiers":[
        {
            "category":"Wholesale",
            "subcategory":"Electrical",
            "type":"Manufacturing & Wholesale Goods"
        }
    ],
    "sg:phone":"+1 602 279 6444",
    "sg:postcode":"85501",
    "sg:province":"AZ",
    "sg:tags":[
        "control",
        "security",
        "system"
    ],
    "wof:name":"Advance Smartcard",
    "wof:placetype":"venue"
},
  "geometry": {"coordinates":[-110.802812,33.416665],"type":"Point"}
}