{
  "type": "Feature",
  "properties": {
    "iso:country":"US",
    "sg:address":"20000 N Ralston Rd",
    "sg:city":"Maricopa",
    "sg:classifiers":[
        {
            "category":"Farming",
            "subcategory":"Dairy Farm",
            "type":"Manufacturing & Wholesale Goods"
        }
    ],
    "sg:phone":"+1 480 786 3673",
    "sg:postcode":"85239",
    "sg:province":"AZ",
    "wof:name":"Dejong Dairy",
    "wof:placetype":"venue"
},
  "geometry": {"coordinates":[-112.117552,33.058065],"type":"Point"}
}