{
  "type": "Feature",
  "properties": {
    "iso:country":"US",
    "sg:address":"3201 N 16th St",
    "sg:city":"Phoenix",
    "sg:classifiers":[
        {
            "category":"Professional",
            "type":"Services"
        }
    ],
    "sg:phone":"+1 480 282 5167",
    "sg:postcode":"85016",
    "sg:province":"AZ",
    "sg:tags":[
        "marketing",
        "consultant"
    ],
    "wof:name":"Physicians Marketing Consultan",
    "wof:placetype":"venue"
},
  "geometry": {"coordinates":[-112.04766100000001,33.48497],"type":"Point"}
}