{
  "type": "Feature",
  "properties": {
    "iso:country":"US",
    "sg:address":"5675 N Oracle Rd",
    "sg:city":"Tucson",
    "sg:classifiers":[
        {
            "category":"Real Estate",
            "subcategory":"Real Estate Agent",
            "type":"Services"
        }
    ],
    "sg:phone":"+1 520 297 4062",
    "sg:postcode":"85704",
    "sg:province":"AZ",
    "sg:tags":[
        "appraiser"
    ],
    "wof:name":"T R Appraisals",
    "wof:placetype":"venue"
},
  "geometry": {"coordinates":[-110.978684,32.310259],"type":"Point"}
}