{
  "type": "Feature",
  "properties": {
    "iso:country":"US",
    "sg:address":"2525 E Thomas Rd",
    "sg:city":"Phoenix",
    "sg:classifiers":[
        {
            "category":"Manufacturing",
            "subcategory":"Printing",
            "type":"Manufacturing & Wholesale Goods"
        }
    ],
    "sg:phone":"+1 602 956 7760",
    "sg:postcode":"85016",
    "sg:province":"AZ",
    "sg:tags":[
        "printer"
    ],
    "wof:name":"Champion Printers",
    "wof:placetype":"venue"
},
  "geometry": {"coordinates":[-112.02736899999999,33.48026],"type":"Point"}
}