{
  "type": "Feature",
  "properties": {
    "iso:country":"US",
    "sg:address":"2439 E Maryland Dr",
    "sg:city":"Tempe",
    "sg:classifiers":[
        {
            "category":"Personal",
            "subcategory":"Beauty Salon",
            "type":"Services"
        }
    ],
    "sg:phone":"+1 480 668 0637",
    "sg:postcode":"85281",
    "sg:province":"AZ",
    "wof:name":"Josie's Beauty Salon",
    "wof:placetype":"venue"
},
  "geometry": {"coordinates":[-111.883309,33.420201],"type":"Point"}
}