{
  "type": "Feature",
  "properties": {
    "addr:full":"330 S 72nd Pl Mesa AZ 85208",
    "addr:housenumber":"330",
    "addr:postcode":"85208",
    "addr:street":"S 72Nd Pl",
    "iso:country":"US",
    "sg:address":"330 S 72nd Pl",
    "sg:city":"Mesa",
    "sg:classifiers":[
        {
            "category":"Home & Garden",
            "subcategory":"Mobile Homes",
            "type":"Retail Goods"
        }
    ],
    "sg:phone":"+1 480 854 1212",
    "sg:postcode":"85208",
    "sg:province":"AZ",
    "wof:name":"Frankie Johnson",
    "wof:placetype":"venue"
},
  "geometry": {"coordinates":[-111.675664,33.407908],"type":"Point"}
}