{
  "type": "Feature",
  "properties": {
    "iso:country":"US",
    "sg:address":"7145 E Indian School Rd",
    "sg:city":"Scottsdale",
    "sg:classifiers":[
        {
            "category":"Restaurant",
            "type":"Food & Drink"
        }
    ],
    "sg:menulink":"http://www.allmenus.com/az/phoenix/92790-fuddruckers/menu/",
    "sg:phone":"+1 480 946 9916",
    "sg:postcode":"85251",
    "sg:province":"AZ",
    "sg:tags":[
        "burger",
        "american"
    ],
    "wof:name":"Fuddruckers",
    "wof:placetype":"venue"
},
  "geometry": {"coordinates":[-111.926766,33.494643],"type":"Point"}
}