{
  "type": "Feature",
  "properties": {
    "iso:country":"US",
    "sg:address":"234 E Mohave St",
    "sg:city":"Phoenix",
    "sg:classifiers":[
        {
            "category":"Manufacturing",
            "subcategory":"Tools & Machinery",
            "type":"Manufacturing & Wholesale Goods"
        }
    ],
    "sg:phone":"+1 602 257 0407",
    "sg:postcode":"85004",
    "sg:province":"AZ",
    "sg:tags":[
        "optometrists'",
        "optic",
        "mfg",
        "supply",
        "module",
        "equipment",
        "controller",
        "motor",
        "mirror",
        "lense",
        "scanner"
    ],
    "sg:website":"http://www.lincolnlaser.com",
    "wof:name":"Lincoln Laser Company",
    "wof:placetype":"venue"
},
  "geometry": {"coordinates":[-112.07038300000001,33.431333],"type":"Point"}
}