{
  "type": "Feature",
  "properties": {
    "iso:country":"US",
    "sg:address":"2151 E Baseline Rd Ste 101",
    "sg:city":"Tempe",
    "sg:classifiers":[
        {
            "category":"Banks & Credit Unions",
            "subcategory":"Investment Brokerage",
            "type":"Services"
        },
        {
            "category":"Insurance",
            "subcategory":"Hazard Insurance",
            "type":"Services"
        }
    ],
    "sg:phone":"+1 480 635 4050",
    "sg:postcode":"85283",
    "sg:province":"AZ",
    "sg:tags":[
        "investing"
    ],
    "wof:name":"Capital Strategies Group, LLC",
    "wof:placetype":"venue"
},
  "geometry": {"coordinates":[-111.894461,33.377476],"type":"Point"}
}