{
  "type": "Feature",
  "properties": {
    "iso:country":"US",
    "sg:address":"25306 S 199th St",
    "sg:city":"Queen Creek",
    "sg:classifiers":[
        {
            "category":"Building & Trades",
            "subcategory":"Plumbing",
            "type":"Services"
        }
    ],
    "sg:phone":"+1 602 762 7841",
    "sg:postcode":"85242",
    "sg:province":"AZ",
    "sg:tags":[
        "contractor"
    ],
    "wof:name":"Aireco",
    "wof:placetype":"venue"
},
  "geometry": {"coordinates":[-111.653969,33.216786],"type":"Point"}
}