{
  "type": "Feature",
  "properties": {
    "addr:full":"2398 E Camelback Rd Ste 615 Phoenix AZ 85016",
    "addr:housenumber":"2398",
    "addr:postcode":"85016",
    "addr:street":"E Camelback Rd Ste 615",
    "iso:country":"US",
    "sg:address":"2398 E Camelback Rd Ste 615",
    "sg:city":"Phoenix",
    "sg:classifiers":[
        {
            "category":"Banks & Credit Unions",
            "subcategory":"Bank",
            "type":"Services"
        }
    ],
    "sg:phone":"+1 602 957 1170",
    "sg:postcode":"85016",
    "sg:province":"AZ",
    "wof:name":"Sonoma Bank",
    "wof:placetype":"venue"
},
  "geometry": {"coordinates":[-112.030281,33.509411],"type":"Point"}
}