{
  "type": "Feature",
  "properties": {
    "iso:country":"US",
    "sg:address":"4543 W Maryland Ave",
    "sg:city":"Glendale",
    "sg:classifiers":[
        {
            "category":"Building & Trades",
            "subcategory":"Construction",
            "type":"Services"
        }
    ],
    "sg:phone":"+1 623 847 0684",
    "sg:postcode":"85301",
    "sg:province":"AZ",
    "sg:tags":[
        "carpentry",
        "contractor"
    ],
    "wof:name":"R B Door Installation",
    "wof:placetype":"venue"
},
  "geometry": {"coordinates":[-112.157358,33.531115],"type":"Point"}
}