{
  "type": "Feature",
  "properties": {
    "iso:country":"US",
    "sg:address":"4835 W Buffalo St",
    "sg:city":"Chandler",
    "sg:classifiers":[
        {
            "category":"Banks & Credit Unions",
            "subcategory":"Investment Brokerage",
            "type":"Services"
        }
    ],
    "sg:phone":"+1 480 753 5750",
    "sg:postcode":"85226",
    "sg:province":"AZ",
    "sg:tags":[
        "consultant",
        "planning",
        "financial"
    ],
    "wof:name":"Raymond James Financial Svc",
    "wof:placetype":"venue"
},
  "geometry": {"coordinates":[-111.926022,33.303746],"type":"Point"}
}