{
  "type": "Feature",
  "properties": {
    "iso:country":"US",
    "sg:address":"49 W 1st St",
    "sg:city":"Mesa",
    "sg:classifiers":[
        {
            "category":"Real Estate",
            "subcategory":"Architect",
            "type":"Services"
        }
    ],
    "sg:phone":"+1 480 827 2759",
    "sg:postcode":"85201",
    "sg:province":"AZ",
    "sg:website":"www.bplw.com",
    "wof:name":"BPLW Architects & Engineers",
    "wof:placetype":"venue"
},
  "geometry": {"coordinates":[-111.833003,33.417207],"type":"Point"}
}