{
  "type": "Feature",
  "properties": {
    "addr:full":"2007 W McMillan St Tucson AZ 85705",
    "addr:housenumber":"2007",
    "addr:postcode":"85705",
    "addr:street":"W Mcmillan St",
    "iso:country":"US",
    "sg:address":"2007 W McMillan St",
    "sg:city":"Tucson",
    "sg:classifiers":[
        {
            "category":"Building & Trades",
            "subcategory":"Construction",
            "type":"Services"
        }
    ],
    "sg:phone":"+1 520 623 8988",
    "sg:postcode":"85705",
    "sg:province":"AZ",
    "sg:tags":[
        "masonry",
        "contractor"
    ],
    "wof:name":"Sun Valley Masonry",
    "wof:placetype":"venue"
},
  "geometry": {"coordinates":[-111.009097,32.278842],"type":"Point"}
}