{
  "type": "Feature",
  "properties": {
    "addr:full":"11838 S Foothills Blvd Yuma AZ 85367",
    "addr:housenumber":"11838",
    "addr:postcode":"85367",
    "addr:street":"S Foothills Blvd",
    "iso:country":"US",
    "sg:address":"11838 S Foothills Blvd",
    "sg:city":"Yuma",
    "sg:classifiers":[
        {
            "category":"Autos & Motor Vehicles",
            "subcategory":"Auto Supplies",
            "type":"Retail Goods"
        }
    ],
    "sg:phone":"+1 928 345 2640",
    "sg:postcode":"85367",
    "sg:province":"AZ",
    "sg:tags":[
        "lining",
        "truck"
    ],
    "wof:name":"Rhino Linings of Yuma",
    "wof:placetype":"venue"
},
  "geometry": {"coordinates":[-114.409913,32.657901],"type":"Point"}
}