{
  "type": "Feature",
  "properties": {
    "iso:country":"US",
    "sg:address":"5617 N 19th Ave",
    "sg:city":"Phoenix",
    "sg:classifiers":[
        {
            "category":"Shopping",
            "subcategory":"Music",
            "type":"Retail Goods"
        }
    ],
    "sg:phone":"+1 602 246 7041",
    "sg:postcode":"85015",
    "sg:province":"AZ",
    "wof:name":"Tower Records Videos & Books",
    "wof:placetype":"venue"
},
  "geometry": {"coordinates":[-112.099657,33.51978],"type":"Point"}
}