{
  "type": "Feature",
  "properties": {
    "addr:full":"5617 N 19th Ave Phoenix AZ 85015",
    "addr:housenumber":"5617",
    "addr:postcode":"85015",
    "addr:street":"N 19Th Ave",
    "iso:country":"US",
    "sg:address":"5617 N 19th Ave",
    "sg:city":"Phoenix",
    "sg:classifiers":[
        {
            "category":"Shopping",
            "subcategory":"Music",
            "type":"Retail Goods"
        }
    ],
    "sg:phone":"+1 602 246 7041",
    "sg:postcode":"85015",
    "sg:province":"AZ",
    "wof:name":"Tower Records Videos & Books",
    "wof:placetype":"venue"
},
  "geometry": {"coordinates":[-112.09965699999999,33.51978],"type":"Point"}
}