{
  "type": "Feature",
  "properties": {
    "addr:full":"100 Swanson Ave Lake Havasu City AZ 86403",
    "addr:housenumber":"100",
    "addr:postcode":"86403",
    "addr:street":"Swanson Ave",
    "iso:country":"US",
    "sg:address":"100 Swanson Ave",
    "sg:city":"Lake Havasu City",
    "sg:classifiers":[
        {
            "category":"Restaurant",
            "type":"Food & Drink"
        }
    ],
    "sg:menulink":"http://www.allmenus.com/az/kingman-south/190530-mcdonalds/menu/",
    "sg:postcode":"86403",
    "sg:province":"AZ",
    "sg:tags":[
        "burger",
        "american"
    ],
    "wof:name":"McDonald's",
    "wof:placetype":"venue"
},
  "geometry": {"coordinates":[-114.34173800000001,34.468383],"type":"Point"}
}