{
  "type": "Feature",
  "properties": {
    "iso:country":"US",
    "sg:address":"1019 N Main St",
    "sg:city":"Cottonwood",
    "sg:classifiers":[
        {
            "category":"Shopping",
            "subcategory":"Hobbies, Toys, & Games",
            "type":"Retail Goods"
        },
        {
            "category":"Manufacturing",
            "subcategory":"Jewelry",
            "type":"Manufacturing & Wholesale Goods"
        },
        {
            "category":"Shopping",
            "subcategory":"Gifts & Souvenirs",
            "type":"Retail Goods"
        }
    ],
    "sg:phone":"+1 928 649 1938",
    "sg:postcode":"86326",
    "sg:province":"AZ",
    "sg:tags":[
        "shop",
        "novelty",
        "basket",
        "hobby",
        "model"
    ],
    "wof:name":"Jim & Ellen's Rock Shop",
    "wof:placetype":"venue"
},
  "geometry": {"coordinates":[-112.027276,34.748432],"type":"Point"}
}