{
  "type": "Feature",
  "properties": {
    "iso:country":"US",
    "sg:address":"8228 W Robin Ln",
    "sg:city":"Peoria",
    "sg:classifiers":[
        {
            "category":"Banks & Credit Unions",
            "subcategory":"Investment Brokerage",
            "type":"Services"
        }
    ],
    "sg:phone":"+1 623 376 0448",
    "sg:postcode":"85383",
    "sg:province":"AZ",
    "sg:tags":[
        "advisory",
        "financial"
    ],
    "wof:name":"Amex Financial Advisor",
    "wof:placetype":"venue"
},
  "geometry": {"coordinates":[-112.235389,33.687843],"type":"Point"}
}