{
  "type": "Feature",
  "properties": {
    "iso:country":"US",
    "sg:address":"26 W Onondaga St",
    "sg:city":"Flagstaff",
    "sg:classifiers":[
        {
            "category":"Building & Trades",
            "subcategory":"Construction",
            "type":"Services"
        }
    ],
    "sg:phone":"+1 928 525 3381",
    "sg:postcode":"86001",
    "sg:province":"AZ",
    "sg:tags":[
        "floor",
        "laying",
        "contractor"
    ],
    "wof:name":"Sinson Wood Floors",
    "wof:placetype":"venue"
},
  "geometry": {"coordinates":[-111.667134,35.08552],"type":"Point"}
}