{
  "type": "Feature",
  "properties": {
    "iso:country":"US",
    "sg:address":"19829 N 27th Ave",
    "sg:city":"Phoenix",
    "sg:classifiers":[
        {
            "category":"Coffee & Tea",
            "type":"Food & Drink"
        }
    ],
    "sg:phone":"+1 602 621 0559",
    "sg:postcode":"85027",
    "sg:province":"AZ",
    "wof:name":"A Fresh Start Cofee Co.",
    "wof:placetype":"venue"
},
  "geometry": {"coordinates":[-112.117241,33.665619],"type":"Point"}
}