{
  "type": "Feature",
  "properties": {
    "iso:country":"US",
    "sg:address":"3299 Boundary Cone Rd",
    "sg:city":"Mohave Valley",
    "sg:classifiers":[
        {
            "category":"Travel",
            "subcategory":"Campground",
            "type":"Entertainment"
        }
    ],
    "sg:phone":"+1 928 768 3303",
    "sg:postcode":"86440",
    "sg:province":"AZ",
    "wof:name":"Blackstone Rv Park",
    "wof:placetype":"venue"
},
  "geometry": {"coordinates":[-114.533356,34.975386],"type":"Point"}
}