{
  "type": "Feature",
  "properties": {
    "iso:country":"US",
    "sg:address":"4020 N 24th St",
    "sg:city":"Phoenix",
    "sg:classifiers":[
        {
            "category":"Professional",
            "subcategory":"Management & Consulting",
            "type":"Services"
        }
    ],
    "sg:phone":"+1 602 956 5444",
    "sg:postcode":"85016",
    "sg:province":"AZ",
    "sg:tags":[
        "consultant",
        "lighting"
    ],
    "wof:name":"Lighting Design Resources Inc",
    "wof:placetype":"venue"
},
  "geometry": {"coordinates":[-112.030266,33.493109],"type":"Point"}
}