{
  "type": "Feature",
  "properties": {
    "iso:country":"US",
    "sg:address":"520 W el Camino Dr",
    "sg:city":"Phoenix",
    "sg:classifiers":[
        {
            "category":"Professional",
            "subcategory":"Advertising",
            "type":"Services"
        }
    ],
    "sg:phone":"+1 602 595 0567",
    "sg:postcode":"85021",
    "sg:province":"AZ",
    "sg:tags":[
        "counselor"
    ],
    "wof:name":"Karen & Co LTD",
    "wof:placetype":"venue"
},
  "geometry": {"coordinates":[-112.082015,33.557165],"type":"Point"}
}