{
  "type": "Feature",
  "properties": {
    "iso:country":"US",
    "sg:address":"3100 Grand Ave",
    "sg:city":"Phoenix",
    "sg:classifiers":[
        {
            "category":"Retail",
            "subcategory":"Auto Repair",
            "type":"Services"
        }
    ],
    "sg:phone":"+1 602 266 6065",
    "sg:postcode":"85017",
    "sg:province":"AZ",
    "sg:tags":[
        "repairing",
        "automobile"
    ],
    "wof:name":"Car Savers",
    "wof:placetype":"venue"
},
  "geometry": {"coordinates":[-112.12173799999999,33.484163],"type":"Point"}
}