{
  "type": "Feature",
  "properties": {
    "iso:country":"US",
    "sg:address":"742 N Monterey St",
    "sg:city":"Gilbert",
    "sg:classifiers":[
        {
            "category":"Building & Trades",
            "subcategory":"Construction",
            "type":"Services"
        }
    ],
    "sg:phone":"+1 480 892 8900",
    "sg:postcode":"85233",
    "sg:province":"AZ",
    "sg:tags":[
        "swimming",
        "pool",
        "contractor"
    ],
    "wof:name":"Hawaiian Pools Inc",
    "wof:placetype":"venue"
},
  "geometry": {"coordinates":[-111.800158,33.363598],"type":"Point"}
}