{
  "type": "Feature",
  "properties": {
    "addr:full":"4048 E Superior Ave Phoenix AZ 85040",
    "addr:housenumber":"4048",
    "addr:postcode":"85040",
    "addr:street":"E Superior Ave",
    "iso:country":"US",
    "sg:address":"4048 E Superior Ave",
    "sg:city":"Phoenix",
    "sg:classifiers":[
        {
            "category":"Autos & Motor Vehicles",
            "subcategory":"Auto Supplies",
            "type":"Retail Goods"
        },
        {
            "category":"Wholesale",
            "subcategory":"Auto Parts",
            "type":"Manufacturing & Wholesale Goods"
        }
    ],
    "sg:phone":"+1 602 424 2934",
    "sg:postcode":"85040",
    "sg:province":"AZ",
    "sg:tags":[
        "body",
        "shop",
        "automobile",
        "supply-wholesale",
        "equipment",
        "manufacturer"
    ],
    "wof:name":"Integro Parts",
    "wof:placetype":"venue"
},
  "geometry": {"coordinates":[-111.99523600000001,33.416612],"type":"Point"}
}