{
  "type": "Feature",
  "properties": {
    "iso:country":"US",
    "sg:address":"6757 N Pima Rd",
    "sg:city":"Scottsdale",
    "sg:classifiers":[
        {
            "category":"Retail",
            "subcategory":"Storage",
            "type":"Services"
        }
    ],
    "sg:phone":"+1 480 818 5985",
    "sg:postcode":"85250",
    "sg:province":"AZ",
    "sg:tags":[
        "automobile",
        "self",
        "commercial",
        "household"
    ],
    "sg:website":"http://phoenix.citysearch.com/profile/external/604185902/scottsdale_az/storagemax_scottsdale.html?publisher=yellowpages&reference_id=1&placement=ypwebsitemip",
    "wof:name":"StorageMax - Scottsdale",
    "wof:placetype":"venue"
},
  "geometry": {"coordinates":[-111.891502,33.535066],"type":"Point"}
}