{
  "type": "Feature",
  "properties": {
    "iso:country":"US",
    "sg:address":"6890 W Chervil Pl",
    "sg:city":"Tucson",
    "sg:classifiers":[
        {
            "category":"Shopping",
            "subcategory":"Gifts & Souvenirs",
            "type":"Retail Goods"
        }
    ],
    "sg:phone":"+1 520 579 1241",
    "sg:postcode":"85743",
    "sg:province":"AZ",
    "wof:name":"Mk Southwest Collectible",
    "wof:placetype":"venue"
},
  "geometry": {"coordinates":[-111.111512,32.354754],"type":"Point"}
}