{
  "type": "Feature",
  "properties": {
    "iso:country":"US",
    "sg:address":"500 Riordan Rd",
    "sg:city":"Flagstaff",
    "sg:classifiers":[
        {
            "category":"Organizations",
            "subcategory":"Religious Organization",
            "type":"Services"
        }
    ],
    "sg:phone":"+1 928 774 1572",
    "sg:postcode":"86001",
    "sg:province":"AZ",
    "sg:tags":[
        "church"
    ],
    "wof:name":"United Christian Ministries",
    "wof:placetype":"venue"
},
  "geometry": {"coordinates":[-111.660459,35.189891],"type":"Point"}
}