{
  "type": "Feature",
  "properties": {
    "addr:full":"8417 E Mcdowell Rd Scottsdale AZ 85257",
    "addr:housenumber":"8417",
    "addr:postcode":"85257",
    "addr:street":"E Mcdowell Rd",
    "iso:country":"US",
    "sg:address":"8417 E Mcdowell Rd",
    "sg:city":"Scottsdale",
    "sg:classifiers":[
        {
            "category":"Health Services",
            "subcategory":"Nursing And Care Facility",
            "type":"Services"
        },
        {
            "category":"Health Services",
            "subcategory":"Health Practitioner",
            "type":"Services"
        },
        {
            "category":"Health Services",
            "subcategory":"Chiropractor",
            "type":"Services"
        }
    ],
    "sg:phone":"+1 480 422 3413",
    "sg:postcode":"85257",
    "sg:province":"AZ",
    "sg:tags":[
        "control",
        "management",
        "pain",
        "weight",
        "chiropractic",
        "therapist",
        "reducing",
        "physical"
    ],
    "sg:website":"http://www.scottsdalechiro.com",
    "wof:name":"American Chiropractic & Physical Therapy",
    "wof:placetype":"venue"
},
  "geometry": {"coordinates":[-111.90010700000001,33.465762],"type":"Point"}
}