{
  "type": "Feature",
  "properties": {
    "iso:country":"US",
    "sg:address":"1621 N 56th Dr",
    "sg:city":"Phoenix",
    "sg:classifiers":[
        {
            "category":"Shopping",
            "type":"Retail Goods"
        }
    ],
    "sg:phone":"+1 602 484 9692",
    "sg:postcode":"85035",
    "sg:province":"AZ",
    "sg:tags":[
        "trade",
        "merchandise",
        "contractor"
    ],
    "wof:name":"Maricopa Awnings",
    "wof:placetype":"venue"
},
  "geometry": {"coordinates":[-112.180638,33.467269],"type":"Point"}
}