{
  "type": "Feature",
  "properties": {
    "iso:country":"US",
    "sg:address":"7902 E Jerome Ave",
    "sg:city":"Mesa",
    "sg:classifiers":[
        {
            "category":"Retail",
            "subcategory":"Laundry & Dry Cleaning",
            "type":"Services"
        }
    ],
    "sg:phone":"+1 480 357 0508",
    "sg:postcode":"85209",
    "sg:province":"AZ",
    "sg:tags":[
        "cleaners",
        "rug",
        "carpet"
    ],
    "wof:name":"Cleaning Mill",
    "wof:placetype":"venue"
},
  "geometry": {"coordinates":[-111.66090199999999,33.38127],"type":"Point"}
}