{
  "type": "Feature",
  "properties": {
    "iso:country":"US",
    "sg:address":"7777 S Pointe Pkwy W",
    "sg:city":"Phoenix",
    "sg:classifiers":[
        {
            "category":"Building & Trades",
            "subcategory":"Landscaping Services",
            "type":"Services"
        }
    ],
    "sg:phone":"+1 602 840 8869",
    "sg:postcode":"85044",
    "sg:province":"AZ",
    "wof:name":"Peak Physical Therapy",
    "wof:placetype":"venue"
},
  "geometry": {"coordinates":[-111.972864,33.376265],"type":"Point"}
}