{
  "type": "Feature",
  "properties": {
    "iso:country":"US",
    "sg:address":"8501 N Canta Bello",
    "sg:city":"Paradise Valley",
    "sg:classifiers":[
        {
            "category":"Professional",
            "type":"Services"
        }
    ],
    "sg:phone":"+1 480 948 2266",
    "sg:postcode":"85253",
    "sg:province":"AZ",
    "wof:name":"Philip W Tomczyk",
    "wof:placetype":"venue"
},
  "geometry": {"coordinates":[-111.94547,33.561193],"type":"Point"}
}