{
  "type": "Feature",
  "properties": {
    "addr:full":"774 S Val Vista Drive Gilbert AZ 85296",
    "addr:housenumber":"774",
    "addr:postcode":"85296",
    "addr:street":"S Val Vista Drive",
    "iso:country":"US",
    "sg:address":"774 S Val Vista Drive",
    "sg:city":"Gilbert",
    "sg:classifiers":[
        {
            "category":"Restaurant",
            "type":"Food & Drink"
        }
    ],
    "sg:phone":"+1 480 633 2424",
    "sg:postcode":"85296",
    "sg:province":"AZ",
    "sg:website":"www.mcdonalds.com",
    "wof:name":"McDonald's Restaurants",
    "wof:placetype":"venue"
},
  "geometry": {"coordinates":[-111.75578,33.336277],"type":"Point"}
}