{
  "type": "Feature",
  "properties": {
    "addr:full":"500 S 99th Ave Tolleson AZ 85353",
    "addr:housenumber":"500",
    "addr:postcode":"85353",
    "addr:street":"S 99Th Ave",
    "iso:country":"US",
    "sg:address":"500 S 99th Ave",
    "sg:city":"Tolleson",
    "sg:classifiers":[
        {
            "category":"Wholesale",
            "subcategory":"Non-durable Goods",
            "type":"Manufacturing & Wholesale Goods"
        }
    ],
    "sg:phone":"+1 623 936 2317",
    "sg:postcode":"85353",
    "sg:province":"AZ",
    "wof:name":"Southwest Distribution Center",
    "wof:placetype":"venue"
},
  "geometry": {"coordinates":[-112.27248299999999,33.44255],"type":"Point"}
}