{
  "type": "Feature",
  "properties": {
    "iso:country":"US",
    "sg:address":"9035 E Mountain View Rd",
    "sg:city":"Scottsdale",
    "sg:classifiers":[
        {
            "category":"Real Estate",
            "subcategory":"Real Estate Agent",
            "type":"Services"
        }
    ],
    "sg:phone":"+1 480 451 4279",
    "sg:postcode":"85258",
    "sg:province":"AZ",
    "wof:name":"Shapiro Realtors Inc",
    "wof:placetype":"venue"
},
  "geometry": {"coordinates":[-111.88505499999999,33.574859],"type":"Point"}
}