{
  "type": "Feature",
  "properties": {
    "iso:country":"US",
    "sg:address":"535 S Dobson Rd",
    "sg:city":"Mesa",
    "sg:classifiers":[
        {
            "category":"Professional",
            "subcategory":"Business Services",
            "type":"Services"
        }
    ],
    "sg:phone":"+1 480 833 6980",
    "sg:postcode":"85202",
    "sg:province":"AZ",
    "sg:tags":[
        "painter",
        "sign"
    ],
    "sg:website":"www.fastsigns.com",
    "wof:name":"Fastsigns International",
    "wof:placetype":"venue"
},
  "geometry": {"coordinates":[-111.874484,33.404918],"type":"Point"}
}