{
  "type": "Feature",
  "properties": {
    "addr:full":"5410 S Lakeshore Drive Tempe AZ 85283",
    "addr:housenumber":"5410",
    "addr:postcode":"85283",
    "addr:street":"S Lakeshore Drive",
    "iso:country":"US",
    "sg:address":"5410 S Lakeshore Drive",
    "sg:city":"Tempe",
    "sg:classifiers":[
        {
            "category":"Professional",
            "subcategory":"Accounting & Tax Preparation",
            "type":"Services"
        }
    ],
    "sg:phone":"+1 480 968 1761",
    "sg:postcode":"85283",
    "sg:province":"AZ",
    "sg:tags":[
        "accountant"
    ],
    "wof:name":"Sacry Sheryl K CPA PC",
    "wof:placetype":"venue"
},
  "geometry": {"coordinates":[-111.91922700000001,33.3745],"type":"Point"}
}