{
  "type": "Feature",
  "properties": {
    "iso:country":"US",
    "sg:address":"106 N 2nd Ave",
    "sg:city":"Holbrook",
    "sg:classifiers":[
        {
            "category":"Utilities",
            "subcategory":"Fuel Oil & Lpg",
            "type":"Services"
        }
    ],
    "sg:phone":"+1 928 524 3504",
    "sg:postcode":"86025",
    "sg:province":"AZ",
    "sg:tags":[
        "liquefied",
        "product",
        "gas",
        "petroleum"
    ],
    "wof:name":"AmeriGas Holbrook",
    "wof:placetype":"venue"
},
  "geometry": {"coordinates":[-110.162008,34.901035],"type":"Point"}
}