{
  "type": "Feature",
  "properties": {
    "iso:country":"US",
    "sg:address":"4500 S Lakeshore Dr Ste 415",
    "sg:city":"Tempe",
    "sg:classifiers":[
        {
            "category":"Health Services",
            "subcategory":"Doctor",
            "type":"Services"
        },
        {
            "category":"Health Services",
            "subcategory":"Clinic",
            "type":"Services"
        }
    ],
    "sg:phone":"+1 480 756 1669",
    "sg:postcode":"85282",
    "sg:province":"AZ",
    "sg:tags":[
        "psychological",
        "psychologist"
    ],
    "wof:name":"Jane H Debrown Psyd",
    "wof:placetype":"venue"
},
  "geometry": {"coordinates":[-111.926712,33.382309],"type":"Point"}
}