{
  "type": "Feature",
  "properties": {
    "iso:country":"US",
    "sg:address":"12821 N 18th Pl",
    "sg:city":"Phoenix",
    "sg:classifiers":[
        {
            "category":"Shopping",
            "subcategory":"Computers & Home Electronics",
            "type":"Retail Goods"
        }
    ],
    "sg:phone":"+1 602 992 2586",
    "sg:postcode":"85022",
    "sg:province":"AZ",
    "sg:tags":[
        "software"
    ],
    "sg:website":"www.quarterjr.com",
    "wof:name":"Racing Systems Analysis",
    "wof:placetype":"venue"
},
  "geometry": {"coordinates":[-112.042344,33.603615],"type":"Point"}
}