{
  "type": "Feature",
  "properties": {
    "iso:country":"US",
    "sg:address":"9801 W Van Buren St",
    "sg:city":"Tolleson",
    "sg:classifiers":[
        {
            "category":"Education",
            "subcategory":"School",
            "type":"Public Place"
        }
    ],
    "sg:phone":"+1 623 478 4000",
    "sg:postcode":"85353",
    "sg:province":"AZ",
    "sg:tags":[
        "high",
        "middle",
        "elementary"
    ],
    "wof:name":"Tolleson Union High School District No 214",
    "wof:placetype":"venue"
},
  "geometry": {"coordinates":[-112.27036,33.450228],"type":"Point"}
}