{
  "type": "Feature",
  "properties": {
    "addr:full":"8045 S Rita Rd Tucson AZ 85747",
    "addr:housenumber":"8045",
    "addr:postcode":"85747",
    "addr:street":"S Rita Rd",
    "iso:country":"US",
    "sg:address":"8045 S Rita Rd",
    "sg:city":"Tucson",
    "sg:classifiers":[
        {
            "category":"Health Services",
            "subcategory":"Doctor",
            "type":"Services"
        }
    ],
    "sg:phone":"+1 520 881 1977",
    "sg:postcode":"85747",
    "sg:province":"AZ",
    "sg:tags":[
        "physician",
        "surgeon"
    ],
    "wof:name":"Ironwood Ob/Gyn",
    "wof:placetype":"venue"
},
  "geometry": {"coordinates":[-110.80295700000001,32.106653],"type":"Point"}
}