{
  "type": "Feature",
  "properties": {
    "addr:full":"7850 N Silverbell Rd Tucson AZ 85743",
    "addr:housenumber":"7850",
    "addr:postcode":"85743",
    "addr:street":"N Silverbell Rd",
    "iso:country":"US",
    "sg:address":"7850 N Silverbell Rd",
    "sg:city":"Tucson",
    "sg:classifiers":[
        {
            "category":"Professional",
            "subcategory":"Advertising",
            "type":"Services"
        }
    ],
    "sg:phone":"+1 520 744 1999",
    "sg:postcode":"85743",
    "sg:province":"AZ",
    "sg:tags":[
        "mailing",
        "shipping"
    ],
    "wof:name":"UPS Store",
    "wof:placetype":"venue"
},
  "geometry": {"coordinates":[-111.09994500000001,32.34861],"type":"Point"}
}