{
  "type": "Feature",
  "properties": {
    "addr:full":"9220 E Dolores St Tucson AZ 85730",
    "addr:housenumber":"9220",
    "addr:postcode":"85730",
    "addr:street":"E Dolores St",
    "iso:country":"US",
    "sg:address":"9220 E Dolores St",
    "sg:city":"Tucson",
    "sg:classifiers":[
        {
            "category":"Home & Garden",
            "subcategory":"Carpets & Floor Coverings",
            "type":"Retail Goods"
        }
    ],
    "sg:phone":"+1 520 325 0190",
    "sg:postcode":"85730",
    "sg:province":"AZ",
    "wof:name":"Moons Floor Covering LLC",
    "wof:placetype":"venue"
},
  "geometry": {"coordinates":[-110.793931,32.189469],"type":"Point"}
}