{
  "type": "Feature",
  "properties": {
    "iso:country":"US",
    "sg:address":"3179 Willow Creek Rd",
    "sg:city":"Prescott",
    "sg:classifiers":[
        {
            "category":"Restaurant",
            "type":"Food & Drink"
        }
    ],
    "sg:phone":"+1 928 777 0097",
    "sg:postcode":"86301",
    "sg:province":"AZ",
    "sg:tags":[
        "parlor",
        "ice",
        "cream"
    ],
    "wof:name":"Dairy Queen",
    "wof:placetype":"venue"
},
  "geometry": {"coordinates":[-112.46654599999999,34.594899],"type":"Point"}
}