{
  "type": "Feature",
  "properties": {
    "addr:full":"2414 N Gilbert Rd Mesa AZ 85203",
    "addr:housenumber":"2414",
    "addr:postcode":"85203",
    "addr:street":"N Gilbert Rd",
    "iso:country":"US",
    "sg:address":"2414 N Gilbert Rd",
    "sg:city":"Mesa",
    "sg:classifiers":[
        {
            "category":"Retail",
            "subcategory":"Repair Shop",
            "type":"Services"
        },
        {
            "category":"Building & Trades",
            "subcategory":"Plumbing",
            "type":"Services"
        }
    ],
    "sg:phone":"+1 480 964 6622",
    "sg:postcode":"85203",
    "sg:province":"AZ",
    "sg:tags":[
        "plumbing",
        "drain",
        "cleaning",
        "sewer",
        "contractor"
    ],
    "sg:website":"www.falconplumbing.biz",
    "wof:name":"Falcon Plumbing Inc",
    "wof:placetype":"venue"
},
  "geometry": {"coordinates":[-111.787896,33.457769],"type":"Point"}
}