{
  "type": "Feature",
  "properties": {
    "iso:country":"US",
    "sg:address":"139 E Encanto Dr",
    "sg:city":"Tempe",
    "sg:classifiers":[
        {
            "category":"Professional",
            "subcategory":"Lawyer & Legal Services",
            "type":"Services"
        }
    ],
    "sg:phone":"+1 480 966 8116",
    "sg:postcode":"85281",
    "sg:province":"AZ",
    "sg:tags":[
        "clinic"
    ],
    "wof:name":"Middle Ground Prison Reform",
    "wof:placetype":"venue"
},
  "geometry": {"coordinates":[-111.936712,33.409435],"type":"Point"}
}