{
  "type": "Feature",
  "properties": {
    "iso:country":"US",
    "sg:address":"1308 Stockton Hill Rd",
    "sg:city":"Kingman",
    "sg:classifiers":[
        {
            "category":"Professional",
            "subcategory":"Advertising",
            "type":"Services"
        }
    ],
    "sg:phone":"+1 928 753 1119",
    "sg:postcode":"86401",
    "sg:province":"AZ",
    "wof:name":"Northern Arizona Specialty",
    "wof:placetype":"venue"
},
  "geometry": {"coordinates":[-114.03315,35.200895],"type":"Point"}
}