{
  "type": "Feature",
  "properties": {
    "addr:full":"326 S Alta Vis San Manuel AZ 85631",
    "addr:housenumber":"326",
    "addr:postcode":"85631",
    "addr:street":"S Alta Vis",
    "iso:country":"US",
    "sg:address":"326 S Alta Vis",
    "sg:city":"San Manuel",
    "sg:classifiers":[
        {
            "category":"Restaurant",
            "type":"Food & Drink"
        }
    ],
    "sg:phone":"+1 520 385 2041",
    "sg:postcode":"85631",
    "sg:province":"AZ",
    "sg:tags":[
        "eating"
    ],
    "wof:name":"San Pedro Valley Pizza Co",
    "wof:placetype":"venue"
},
  "geometry": {"coordinates":[-110.633145,32.604349],"type":"Point"}
}