{
  "type": "Feature",
  "properties": {
    "iso:country":"US",
    "sg:address":"13188 N 103rd Dr",
    "sg:city":"Sun City",
    "sg:classifiers":[
        {
            "category":"Health Services",
            "subcategory":"Doctor",
            "type":"Services"
        }
    ],
    "sg:phone":"+1 623 815 2484",
    "sg:postcode":"85351",
    "sg:province":"AZ",
    "sg:tags":[
        "physician",
        "surgeon"
    ],
    "wof:name":"Cardiac Care Consultants",
    "wof:placetype":"venue"
},
  "geometry": {"coordinates":[-112.282352,33.604198],"type":"Point"}
}