{
  "type": "Feature",
  "properties": {
    "iso:country":"US",
    "sg:address":"13641 S 33rd St",
    "sg:city":"Phoenix",
    "sg:classifiers":[
        {
            "category":"Professional",
            "subcategory":"Detective & Security Services",
            "type":"Services"
        }
    ],
    "sg:phone":"+1 480 496 5926",
    "sg:postcode":"85044",
    "sg:province":"AZ",
    "sg:tags":[
        "information",
        "bureau"
    ],
    "wof:name":"Arizona Ag Mediation Institute Inc",
    "wof:placetype":"venue"
},
  "geometry": {"coordinates":[-112.011711,33.321386],"type":"Point"}
}