{
  "type": "Feature",
  "properties": {
    "iso:country":"US",
    "sg:address":"10875 N 85th Ave",
    "sg:city":"Peoria",
    "sg:classifiers":[
        {
            "category":"Shopping",
            "subcategory":"Clothing, Apparel, & Fashions",
            "type":"Retail Goods"
        }
    ],
    "sg:phone":"+1 623 878 4221",
    "sg:postcode":"85345",
    "sg:province":"AZ",
    "sg:tags":[
        "alteration"
    ],
    "wof:name":"Alterations Plus",
    "wof:placetype":"venue"
},
  "geometry": {"coordinates":[-112.241938,33.581335],"type":"Point"}
}