{
  "type": "Feature",
  "properties": {
    "addr:full":"4195 US Hwy 68 Golden Valley AZ 86413",
    "addr:housenumber":"4195",
    "addr:postcode":"86413",
    "addr:street":"Us Hwy 68",
    "iso:country":"US",
    "sg:address":"4195 US Hwy 68",
    "sg:city":"Golden Valley",
    "sg:classifiers":[
        {
            "category":"Shopping",
            "subcategory":"Gifts & Souvenirs",
            "type":"Retail Goods"
        }
    ],
    "sg:phone":"+1 928 565 4977",
    "sg:postcode":"86413",
    "sg:province":"AZ",
    "sg:tags":[
        "collectible"
    ],
    "wof:name":"Joabee's Pickins",
    "wof:placetype":"venue"
},
  "geometry": {"coordinates":[-114.174083,35.220118],"type":"Point"}
}