{
  "type": "Feature",
  "properties": {
    "iso:country":"US",
    "sg:address":"12202 N 21st Ave",
    "sg:city":"Phoenix",
    "sg:classifiers":[
        {
            "category":"Education",
            "subcategory":"School",
            "type":"Public Place"
        }
    ],
    "sg:phone":"+1 602 347 4200",
    "sg:postcode":"85029",
    "sg:province":"AZ",
    "wof:name":"Shaw Butte School",
    "wof:placetype":"venue"
},
  "geometry": {"coordinates":[-112.103873,33.598528],"type":"Point"}
}