{
  "type": "Feature",
  "properties": {
    "iso:country":"US",
    "sg:address":"11851 N 109th St",
    "sg:city":"Scottsdale",
    "sg:classifiers":[
        {
            "category":"Professional",
            "type":"Services"
        }
    ],
    "sg:phone":"+1 480 661 5820",
    "sg:postcode":"85259",
    "sg:province":"AZ",
    "wof:name":"Ace Thatch & Bamboo Inc",
    "wof:placetype":"venue"
},
  "geometry": {"coordinates":[-111.842807,33.592837],"type":"Point"}
}