{
  "type": "Feature",
  "properties": {
    "addr:full":"374 N Hamilton St Chandler AZ 85225",
    "addr:housenumber":"374",
    "addr:postcode":"85225",
    "addr:street":"N Hamilton St",
    "iso:country":"US",
    "sg:address":"374 N Hamilton St",
    "sg:city":"Chandler",
    "sg:classifiers":[
        {
            "category":"Organizations",
            "subcategory":"Religious Organization",
            "type":"Services"
        }
    ],
    "sg:phone":"+1 480 917 0368",
    "sg:postcode":"85225",
    "sg:province":"AZ",
    "wof:name":"Apostolic Assembly of the Faith & Jesus Christ",
    "wof:placetype":"venue"
},
  "geometry": {"coordinates":[-111.833,33.309502],"type":"Point"}
}