{
  "type": "Feature",
  "properties": {
    "addr:full":"500 E Chandler Boulevard Chandler AZ 85225",
    "addr:housenumber":"500",
    "addr:postcode":"85225",
    "addr:street":"E Chandler Boulevard",
    "iso:country":"US",
    "sg:address":"500 E Chandler Boulevard",
    "sg:city":"Chandler",
    "sg:classifiers":[
        {
            "category":"Food & Beverages",
            "subcategory":"Groceries & Convenience Stores",
            "type":"Retail Goods"
        }
    ],
    "sg:phone":"+1 480 812 8938",
    "sg:postcode":"85225",
    "sg:province":"AZ",
    "wof:name":"Mi Amigos Food Mart",
    "wof:placetype":"venue"
},
  "geometry": {"coordinates":[-111.834198,33.306173],"type":"Point"}
}