{
  "type": "Feature",
  "properties": {
    "addr:full":"7601 E Indian Bend Rd Scottsdale AZ 85250",
    "addr:housenumber":"7601",
    "addr:postcode":"85250",
    "addr:street":"E Indian Bend Rd",
    "iso:country":"US",
    "sg:address":"7601 E Indian Bend Rd",
    "sg:city":"Scottsdale",
    "sg:classifiers":[
        {
            "category":"Professional",
            "type":"Services"
        }
    ],
    "sg:phone":"+1 480 922 5268",
    "sg:postcode":"85250",
    "sg:province":"AZ",
    "wof:name":"Janets",
    "wof:placetype":"venue"
},
  "geometry": {"coordinates":[-111.916625,33.538575],"type":"Point"}
}