{
  "type": "Feature",
  "properties": {
    "addr:full":"7720 E Catalina Dr Scottsdale AZ 85251",
    "addr:housenumber":"7720",
    "addr:postcode":"85251",
    "addr:street":"E Catalina Dr",
    "iso:country":"US",
    "sg:address":"7720 E Catalina Dr",
    "sg:city":"Scottsdale",
    "sg:classifiers":[
        {
            "category":"Building & Trades",
            "subcategory":"Construction",
            "type":"Services"
        }
    ],
    "sg:phone":"+1 602 369 6804",
    "sg:postcode":"85251",
    "sg:province":"AZ",
    "sg:tags":[
        "general",
        "contractor"
    ],
    "wof:name":"D A Nessler Construction Inc",
    "wof:placetype":"venue"
},
  "geometry": {"coordinates":[-111.915142,33.481948],"type":"Point"}
}