{
  "type": "Feature",
  "properties": {
    "addr:full":"6839 E Carefree Hwy Cave Creek AZ 85331",
    "addr:housenumber":"6839",
    "addr:postcode":"85331",
    "addr:street":"E Carefree Hwy",
    "iso:country":"US",
    "sg:address":"6839 E Carefree Hwy",
    "sg:city":"Cave Creek",
    "sg:classifiers":[
        {
            "category":"Building & Trades",
            "subcategory":"Construction",
            "type":"Services"
        }
    ],
    "sg:phone":"+1 480 575 8300",
    "sg:postcode":"85331",
    "sg:province":"AZ",
    "sg:tags":[
        "remodeling",
        "renovation",
        "contractor"
    ],
    "wof:name":"Western Building Concepts Inc",
    "wof:placetype":"venue"
},
  "geometry": {"coordinates":[-111.938244,33.799149],"type":"Point"}
}