{
  "type": "Feature",
  "properties": {
    "iso:country":"US",
    "sg:address":"9897 W McDowell Rd Ste 750",
    "sg:city":"Tolleson",
    "sg:classifiers":[
        {
            "category":"Personal",
            "subcategory":"Massage",
            "type":"Services"
        },
        {
            "category":"Personal",
            "subcategory":"Hair Removal",
            "type":"Services"
        },
        {
            "category":"Personal",
            "subcategory":"Skin Care",
            "type":"Services"
        },
        {
            "category":"Personal",
            "subcategory":"Day Spa",
            "type":"Services"
        }
    ],
    "sg:phone":"+1 623 907 8818",
    "sg:postcode":"85353",
    "sg:province":"AZ",
    "sg:website":"www.blusolspa.com",
    "wof:name":"Blu Sol Massage and Spa",
    "wof:placetype":"venue"
},
  "geometry": {"coordinates":[-112.27236,33.464673],"type":"Point"}
}