{
  "type": "Feature",
  "properties": {
    "iso:country":"US",
    "sg:address":"28240 N 168th Ave",
    "sg:city":"Surprise",
    "sg:classifiers":[
        {
            "category":"Building & Trades",
            "subcategory":"Plumbing",
            "type":"Services"
        }
    ],
    "sg:phone":"+1 623 546 3955",
    "sg:postcode":"85387",
    "sg:province":"AZ",
    "sg:tags":[
        "contractor"
    ],
    "wof:name":"Singletary Plumbing",
    "wof:placetype":"venue"
},
  "geometry": {"coordinates":[-112.423131,33.742295],"type":"Point"}
}