{
  "type": "Feature",
  "properties": {
    "iso:country":"US",
    "sg:address":"6265 S 20th Ave",
    "sg:city":"Safford",
    "sg:classifiers":[
        {
            "category":"Retail",
            "subcategory":"Animal Services",
            "type":"Services"
        }
    ],
    "sg:phone":"+1 928 348 8633",
    "sg:postcode":"85546",
    "sg:province":"AZ",
    "wof:name":"Rovers K9 Training",
    "wof:placetype":"venue"
},
  "geometry": {"coordinates":[-109.733052,32.755271],"type":"Point"}
}