{
  "type": "Feature",
  "properties": {
    "iso:country":"US",
    "sg:address":"9555 E Fairfield St",
    "sg:city":"Mesa",
    "sg:classifiers":[
        {
            "category":"Shopping",
            "subcategory":"Hobbies, Toys, & Games",
            "type":"Retail Goods"
        }
    ],
    "sg:phone":"+1 480 984 9163",
    "sg:postcode":"85207",
    "sg:province":"AZ",
    "sg:tags":[
        "toy",
        "store",
        "supply"
    ],
    "wof:name":"Treasures By Yvonne & Monique",
    "wof:placetype":"venue"
},
  "geometry": {"coordinates":[-111.624833,33.433919],"type":"Point"}
}