{
  "type": "Feature",
  "properties": {
    "addr:full":"300 W Southern Ave Mesa AZ 85210",
    "addr:housenumber":"300",
    "addr:postcode":"85210",
    "addr:street":"W Southern Ave",
    "iso:country":"US",
    "sg:address":"300 W Southern Ave",
    "sg:city":"Mesa",
    "sg:classifiers":[
        {
            "category":"Retail",
            "subcategory":"Repair Shop",
            "type":"Services"
        }
    ],
    "sg:phone":"+1 602 252 6030",
    "sg:postcode":"85210",
    "sg:province":"AZ",
    "sg:tags":[
        "appliance"
    ],
    "sg:website":"www.maytagstorephx.com",
    "wof:name":"Maytag Store",
    "wof:placetype":"venue"
},
  "geometry": {"coordinates":[-111.83878199999999,33.393418],"type":"Point"}
}