{
  "type": "Feature",
  "properties": {
    "iso:country":"US",
    "sg:address":"4144 N 44th St",
    "sg:city":"Phoenix",
    "sg:classifiers":[
        {
            "category":"Home & Garden",
            "subcategory":"Building Materials",
            "type":"Retail Goods"
        },
        {
            "category":"Building & Trades",
            "subcategory":"Construction",
            "type":"Services"
        }
    ],
    "sg:phone":"+1 602 952 5280",
    "sg:postcode":"85018",
    "sg:province":"AZ",
    "sg:tags":[
        "insulation",
        "equipment",
        "supply",
        "contractor"
    ],
    "sg:website":"http://www.zipweb.com/?businessName=RedlineCreativeGroup/",
    "wof:name":"Redline Creative Group",
    "wof:placetype":"venue"
},
  "geometry": {"coordinates":[-111.98690000000001,33.496287],"type":"Point"}
}