{
  "type": "Feature",
  "properties": {
    "addr:full":"28415 N 33rd Ave Phoenix AZ 85083",
    "addr:housenumber":"28415",
    "addr:postcode":"85083",
    "addr:street":"N 33Rd Ave",
    "iso:country":"US",
    "sg:address":"28415 N 33rd Ave",
    "sg:city":"Phoenix",
    "sg:classifiers":[
        {
            "category":"Building & Trades",
            "subcategory":"Construction",
            "type":"Services"
        }
    ],
    "sg:phone":"+1 623 869 8662",
    "sg:postcode":"85083",
    "sg:province":"AZ",
    "sg:tags":[
        "contractor"
    ],
    "wof:name":"A Tint of Excellence",
    "wof:placetype":"venue"
},
  "geometry": {"coordinates":[-112.13009599999999,33.742245],"type":"Point"}
}