{
  "type": "Feature",
  "properties": {
    "iso:country":"US",
    "sg:address":"1212 E Baseline Rd",
    "sg:city":"Tempe",
    "sg:classifiers":[
        {
            "category":"Health Services",
            "subcategory":"Clinic",
            "type":"Services"
        }
    ],
    "sg:phone":"+1 480 345 0315",
    "sg:postcode":"85283",
    "sg:province":"AZ",
    "sg:tags":[
        "home"
    ],
    "wof:name":"Comfort Care Senior Svc",
    "wof:placetype":"venue"
},
  "geometry": {"coordinates":[-111.917764,33.378426],"type":"Point"}
}