{
  "type": "Feature",
  "properties": {
    "iso:country":"US",
    "sg:address":"1514 W Bethany Home Rd",
    "sg:city":"Phoenix",
    "sg:classifiers":[
        {
            "category":"Professional",
            "type":"Services"
        }
    ],
    "sg:phone":"+1 602 246 6432",
    "sg:postcode":"85015",
    "sg:province":"AZ",
    "wof:name":"Lorri A Peltz",
    "wof:placetype":"venue"
},
  "geometry": {"coordinates":[-112.093067,33.524041],"type":"Point"}
}