{
  "type": "Feature",
  "properties": {
    "iso:country":"US",
    "sg:address":"6360 E Rose Circle Dr",
    "sg:city":"Scottsdale",
    "sg:classifiers":[
        {
            "category":"Wholesale",
            "subcategory":"Books, Periodicals, & Newspapers",
            "type":"Manufacturing & Wholesale Goods"
        }
    ],
    "sg:phone":"+1 602 361 0294",
    "sg:postcode":"85251",
    "sg:province":"AZ",
    "sg:tags":[
        "publisher",
        "book"
    ],
    "wof:name":"Pursuit Press",
    "wof:placetype":"venue"
},
  "geometry": {"coordinates":[-111.94399,33.486248],"type":"Point"}
}