{
  "type": "Feature",
  "properties": {
    "iso:country":"US",
    "sg:address":"10428 E Palm Way",
    "sg:city":"Apache Junction",
    "sg:classifiers":[
        {
            "category":"Shopping",
            "subcategory":"Books",
            "type":"Retail Goods"
        }
    ],
    "sg:phone":"+1 480 984 8008",
    "sg:postcode":"85218",
    "sg:province":"AZ",
    "sg:tags":[
        "indiana",
        "used",
        "art"
    ],
    "wof:name":"Treasures of South West",
    "wof:placetype":"venue"
},
  "geometry": {"coordinates":[-111.433602,33.364179],"type":"Point"}
}