{
  "type": "Feature",
  "properties": {
    "iso:country":"US",
    "sg:address":"4811 E Grant Rd",
    "sg:city":"Tucson",
    "sg:classifiers":[
        {
            "category":"Shopping",
            "type":"Retail Goods"
        }
    ],
    "sg:phone":"+1 520 318 0044",
    "sg:postcode":"85712",
    "sg:province":"AZ",
    "sg:tags":[
        "picture",
        "frame",
        "merchandise"
    ],
    "wof:name":"Hall of Frames",
    "wof:placetype":"venue"
},
  "geometry": {"coordinates":[-110.888605,32.250723],"type":"Point"}
}