{
  "type": "Feature",
  "properties": {
    "iso:country":"US",
    "sg:address":"10208 N 51st Dr",
    "sg:city":"Glendale",
    "sg:classifiers":[
        {
            "category":"Shopping",
            "subcategory":"Bicycles & Sporting Goods",
            "type":"Retail Goods"
        }
    ],
    "sg:phone":"+1 623 939 3877",
    "sg:postcode":"85302",
    "sg:province":"AZ",
    "wof:name":"Boomer Golf",
    "wof:placetype":"venue"
},
  "geometry": {"coordinates":[-112.169596,33.57879],"type":"Point"}
}