{
  "type": "Feature",
  "properties": {
    "iso:country":"US",
    "sg:address":"1122 W Thatcher Blvd",
    "sg:city":"Safford",
    "sg:classifiers":[
        {
            "category":"Manufacturing",
            "subcategory":"Printing",
            "type":"Manufacturing & Wholesale Goods"
        }
    ],
    "sg:phone":"+1 928 428 2681",
    "sg:postcode":"85546",
    "sg:province":"AZ",
    "sg:tags":[
        "printer"
    ],
    "wof:name":"Source",
    "wof:placetype":"venue"
},
  "geometry": {"coordinates":[-109.72075100000001,32.834954],"type":"Point"}
}