{
  "type": "Feature",
  "properties": {
    "iso:country":"US",
    "sg:address":"4545 S Mission Rd",
    "sg:city":"Tucson",
    "sg:classifiers":[
        {
            "category":"Professional",
            "subcategory":"Business Services",
            "type":"Services"
        }
    ],
    "sg:phone":"+1 520 294 8065",
    "sg:postcode":"85746",
    "sg:province":"AZ",
    "sg:tags":[
        "recording",
        "studio"
    ],
    "wof:name":"Glorybound Gospel Music",
    "wof:placetype":"venue"
},
  "geometry": {"coordinates":[-111.006108,32.166519],"type":"Point"}
}