{
  "type": "Feature",
  "properties": {
    "iso:country":"US",
    "sg:address":"11875 E Elin Ranch Rd",
    "sg:city":"Tucson",
    "sg:classifiers":[
        {
            "category":"Professional",
            "subcategory":"Management & Consulting",
            "type":"Services"
        }
    ],
    "sg:phone":"+1 520 760 0594",
    "sg:postcode":"85749",
    "sg:province":"AZ",
    "sg:tags":[
        "marketing",
        "program"
    ],
    "wof:name":"Metro Market Studies",
    "wof:placetype":"venue"
},
  "geometry": {"coordinates":[-110.73844,32.299043],"type":"Point"}
}