{
  "type": "Feature",
  "properties": {
    "iso:country":"US",
    "sg:address":"2601 N 16th St",
    "sg:city":"Phoenix",
    "sg:classifiers":[
        {
            "category":"Professional",
            "type":"Services"
        }
    ],
    "sg:phone":"+1 602 493 6350",
    "sg:postcode":"85006",
    "sg:province":"AZ",
    "wof:name":"Milone Vincent & Pauline Rev",
    "wof:placetype":"venue"
},
  "geometry": {"coordinates":[-112.047648,33.476616],"type":"Point"}
}