{
  "type": "Feature",
  "properties": {
    "iso:country":"US",
    "sg:address":"1134 W Newport Beach Dr",
    "sg:city":"Gilbert",
    "sg:classifiers":[
        {
            "category":"Building & Trades",
            "subcategory":"Equipment Rental",
            "type":"Services"
        }
    ],
    "sg:phone":"+1 480 892 6950",
    "sg:postcode":"85233",
    "sg:province":"AZ",
    "wof:name":"Songbird Plant Lenders",
    "wof:placetype":"venue"
},
  "geometry": {"coordinates":[-111.812658,33.340461],"type":"Point"}
}