{
  "type": "Feature",
  "properties": {
    "iso:country":"US",
    "sg:address":"5310 E Gloria Ln",
    "sg:city":"Cave Creek",
    "sg:classifiers":[
        {
            "category":"Building & Trades",
            "subcategory":"Construction",
            "type":"Services"
        }
    ],
    "sg:phone":"+1 480 575 2744",
    "sg:postcode":"85331",
    "sg:province":"AZ",
    "sg:tags":[
        "contractor"
    ],
    "wof:name":"Curt Boyd Fencing Inc",
    "wof:placetype":"venue"
},
  "geometry": {"coordinates":[-111.965605,33.771155],"type":"Point"}
}