{
  "type": "Feature",
  "properties": {
    "iso:country":"US",
    "sg:address":"4641 W Whispering Wind Dr",
    "sg:city":"Glendale",
    "sg:classifiers":[
        {
            "category":"Building & Trades",
            "subcategory":"Electrical",
            "type":"Services"
        }
    ],
    "sg:phone":"+1 623 580 8658",
    "sg:postcode":"85310",
    "sg:province":"AZ",
    "sg:tags":[
        "electric",
        "contractor"
    ],
    "wof:name":"Eavenson Electric",
    "wof:placetype":"venue"
},
  "geometry": {"coordinates":[-112.16098700000001,33.709641],"type":"Point"}
}