{
  "type": "Feature",
  "properties": {
    "iso:country":"US",
    "sg:address":"3202 E Greenway Rd",
    "sg:city":"Phoenix",
    "sg:classifiers":[
        {
            "category":"Health Services",
            "subcategory":"Optometrist",
            "type":"Services"
        }
    ],
    "sg:phone":"+1 602 788 8413",
    "sg:postcode":"85032",
    "sg:province":"AZ",
    "sg:website":"www.nationwidevision.com",
    "wof:name":"Nationwide Vision Ctr",
    "wof:placetype":"venue"
},
  "geometry": {"coordinates":[-112.009699,33.626398],"type":"Point"}
}