{
  "type": "Feature",
  "properties": {
    "iso:country":"US",
    "sg:address":"14700 N Airport Dr",
    "sg:city":"Scottsdale",
    "sg:classifiers":[
        {
            "category":"Education",
            "subcategory":"Special Training",
            "type":"Public Place"
        }
    ],
    "sg:phone":"+1 602 569 0200",
    "sg:postcode":"85260",
    "sg:province":"AZ",
    "sg:tags":[
        "aircraft",
        "school"
    ],
    "wof:name":"June Bonesteel Flight Training",
    "wof:placetype":"venue"
},
  "geometry": {"coordinates":[-111.918071,33.620881],"type":"Point"}
}