{
  "type": "Feature",
  "properties": {
    "iso:country":"US",
    "sg:address":"507 E Joan St",
    "sg:city":"Tucson",
    "sg:classifiers":[
        {
            "category":"Professional",
            "subcategory":"Computer Services",
            "type":"Services"
        }
    ],
    "sg:phone":"+1 520 990 0858",
    "sg:postcode":"85705",
    "sg:province":"AZ",
    "sg:tags":[
        "hardware",
        "provider",
        "internet",
        "software"
    ],
    "wof:name":"Emurjun Web Design-Tucson Ofc",
    "wof:placetype":"venue"
},
  "geometry": {"coordinates":[-110.962278,32.273582],"type":"Point"}
}