{
  "type": "Feature",
  "properties": {
    "addr:full":"3033 W Clarendon Ave Phoenix AZ 85017",
    "addr:housenumber":"3033",
    "addr:postcode":"85017",
    "addr:street":"W Clarendon Ave",
    "iso:country":"US",
    "sg:address":"3033 W Clarendon Ave",
    "sg:city":"Phoenix",
    "sg:classifiers":[
        {
            "category":"Wholesale",
            "subcategory":"Toys & Hobbies",
            "type":"Manufacturing & Wholesale Goods"
        },
        {
            "category":"Manufacturing",
            "subcategory":"Textiles",
            "type":"Manufacturing & Wholesale Goods"
        }
    ],
    "sg:phone":"+1 602 264 2885",
    "sg:postcode":"85017",
    "sg:province":"AZ",
    "sg:tags":[
        "material",
        "needlework",
        "sewing"
    ],
    "wof:name":"Decorative Woods Inc",
    "wof:placetype":"venue"
},
  "geometry": {"coordinates":[-112.12516599999999,33.492163],"type":"Point"}
}