{
  "type": "Feature",
  "properties": {
    "iso:country":"US",
    "sg:address":"1930 W Durango St Ste H",
    "sg:city":"Phoenix",
    "sg:classifiers":[
        {
            "category":"Wholesale",
            "subcategory":"Construction Materials",
            "type":"Manufacturing & Wholesale Goods"
        }
    ],
    "sg:phone":"+1 602 330 3058",
    "sg:postcode":"85009",
    "sg:province":"AZ",
    "sg:tags":[
        "equipment",
        "masonry",
        "supply"
    ],
    "wof:name":"A Beteer Look",
    "wof:placetype":"venue"
},
  "geometry": {"coordinates":[-112.100272,33.429496],"type":"Point"}
}