{
  "type": "Feature",
  "properties": {
    "addr:full":"6701 W Olive Ave Peoria AZ 85345",
    "addr:housenumber":"6701",
    "addr:postcode":"85345",
    "addr:street":"W Olive Ave",
    "iso:country":"US",
    "sg:address":"6701 W Olive Ave",
    "sg:city":"Peoria",
    "sg:classifiers":[
        {
            "category":"Autos & Motor Vehicles",
            "subcategory":"Fuel & Gas Station",
            "type":"Retail Goods"
        }
    ],
    "sg:phone":"+1 623 435 6550",
    "sg:postcode":"85345",
    "sg:province":"AZ",
    "sg:tags":[
        "oil"
    ],
    "wof:name":"Diamond Shamrock",
    "wof:placetype":"venue"
},
  "geometry": {"coordinates":[-112.203136,33.567155],"type":"Point"}
}