{
  "type": "Feature",
  "properties": {
    "iso:country":"US",
    "sg:address":"800 W University Ave",
    "sg:city":"Flagstaff",
    "sg:classifiers":[
        {
            "category":"Professional",
            "type":"Services"
        }
    ],
    "sg:phone":"+1 928 779 1428",
    "sg:postcode":"86001",
    "sg:province":"AZ",
    "wof:name":"Raprime",
    "wof:placetype":"venue"
},
  "geometry": {"coordinates":[-111.66541100000001,35.184288],"type":"Point"}
}