{
  "type": "Feature",
  "properties": {
    "iso:country":"US",
    "sg:address":"8209 E Balfour Dr",
    "sg:city":"Tucson",
    "sg:classifiers":[
        {
            "category":"Retail",
            "subcategory":"Car Wash",
            "type":"Services"
        }
    ],
    "sg:phone":"+1 520 409 7953",
    "sg:postcode":"85710",
    "sg:province":"AZ",
    "sg:tags":[
        "automobile",
        "detail",
        "clean"
    ],
    "wof:name":"Dolphins Auto Detailing",
    "wof:placetype":"venue"
},
  "geometry": {"coordinates":[-110.818397,32.228126],"type":"Point"}
}