{
  "type": "Feature",
  "properties": {
    "iso:country":"US",
    "sg:address":"6723 Corsair Ave",
    "sg:city":"Prescott",
    "sg:classifiers":[
        {
            "category":"Wholesale",
            "subcategory":"Toys & Hobbies",
            "type":"Manufacturing & Wholesale Goods"
        }
    ],
    "sg:phone":"+1 928 445 1433",
    "sg:postcode":"86301",
    "sg:province":"AZ",
    "sg:tags":[
        "wholesaler"
    ],
    "wof:name":"Dana Kepner Co",
    "wof:placetype":"venue"
},
  "geometry": {"coordinates":[-112.409485,34.65593],"type":"Point"}
}