{
  "type": "Feature",
  "properties": {
    "iso:country":"US",
    "sg:address":"7910 W Market St",
    "sg:city":"Peoria",
    "sg:classifiers":[
        {
            "category":"Building & Trades",
            "subcategory":"Construction",
            "type":"Services"
        }
    ],
    "sg:phone":"+1 623 979 7785",
    "sg:postcode":"85345",
    "sg:province":"AZ",
    "sg:tags":[
        "general",
        "contractor"
    ],
    "wof:name":"Kay Construction",
    "wof:placetype":"venue"
},
  "geometry": {"coordinates":[-112.232851,33.578121],"type":"Point"}
}