{
  "type": "Feature",
  "properties": {
    "addr:full":"1916 W Rawhide Ave Gilbert AZ 85233",
    "addr:housenumber":"1916",
    "addr:postcode":"85233",
    "addr:street":"W Rawhide Ave",
    "iso:country":"US",
    "sg:address":"1916 W Rawhide Ave",
    "sg:city":"Gilbert",
    "sg:classifiers":[
        {
            "category":"Home & Garden",
            "subcategory":"Garden Supply",
            "type":"Retail Goods"
        }
    ],
    "sg:phone":"+1 480 892 2537",
    "sg:postcode":"85233",
    "sg:province":"AZ",
    "sg:tags":[
        "lawn",
        "mower"
    ],
    "wof:name":"Wards Lawn Power Equipment",
    "wof:placetype":"venue"
},
  "geometry": {"coordinates":[-111.830865,33.3442],"type":"Point"}
}