{
  "type": "Feature",
  "properties": {
    "iso:country":"US",
    "sg:address":"44000 N Spur Cross Rd",
    "sg:city":"Cave Creek",
    "sg:classifiers":[
        {
            "category":"Park",
            "type":"Public Place"
        }
    ],
    "sg:phone":"+1 480 488 6601",
    "sg:postcode":"85331",
    "sg:province":"AZ",
    "sg:website":"www.maricopa.gov/parks/spur%5Fcross",
    "wof:name":"Spur Cross Ranch Conservation Area",
    "wof:placetype":"venue"
},
  "geometry": {"coordinates":[-111.960275,33.87153],"type":"Point"}
}