{
  "type": "Feature",
  "properties": {
    "iso:country":"US",
    "sg:address":"3535 W Messala Way",
    "sg:city":"Tucson",
    "sg:classifiers":[
        {
            "category":"Education",
            "subcategory":"School",
            "type":"Public Place"
        }
    ],
    "sg:phone":"+1 520 908 4100",
    "sg:postcode":"85746",
    "sg:province":"AZ",
    "wof:name":"Maldonado Elementary School",
    "wof:placetype":"venue"
},
  "geometry": {"coordinates":[-111.040636,32.117239],"type":"Point"}
}