{
  "type": "Feature",
  "properties": {
    "iso:country":"US",
    "sg:address":"907 N Main St",
    "sg:city":"Cottonwood",
    "sg:classifiers":[
        {
            "category":"Shopping",
            "subcategory":"Used Merchandise",
            "type":"Retail Goods"
        }
    ],
    "sg:phone":"+1 928 634 9529",
    "sg:postcode":"86326",
    "sg:province":"AZ",
    "sg:tags":[
        "furniture"
    ],
    "wof:name":"Finicky Used Furniture",
    "wof:placetype":"venue"
},
  "geometry": {"coordinates":[-112.027325,34.749235],"type":"Point"}
}