{
  "type": "Feature",
  "properties": {
    "addr:full":"2095 E 32nd St Yuma AZ 85365",
    "addr:housenumber":"2095",
    "addr:postcode":"85365",
    "addr:street":"E 32Nd St",
    "iso:country":"US",
    "sg:address":"2095 E 32nd St",
    "sg:city":"Yuma",
    "sg:classifiers":[
        {
            "category":"Airport",
            "type":"Transportation"
        }
    ],
    "sg:phone":"+1 928 726 4715",
    "sg:postcode":"85365",
    "sg:province":"AZ",
    "sg:tags":[
        "repair",
        "aircraft",
        "avionics",
        "equipment"
    ],
    "wof:name":"Suncare Air Ambulance",
    "wof:placetype":"venue"
},
  "geometry": {"coordinates":[-114.6005,32.6694],"type":"Point"}
}