{
  "type": "Feature",
  "properties": {
    "addr:full":"3421 W Clarendon Ave Phoenix AZ 85017",
    "addr:housenumber":"3421",
    "addr:postcode":"85017",
    "addr:street":"W Clarendon Ave",
    "iso:country":"US",
    "sg:address":"3421 W Clarendon Ave",
    "sg:city":"Phoenix",
    "sg:classifiers":[
        {
            "category":"Wholesale",
            "subcategory":"Medical Equipment & Supplies",
            "type":"Manufacturing & Wholesale Goods"
        },
        {
            "category":"Health Services",
            "subcategory":"Nursing And Care Facility",
            "type":"Services"
        },
        {
            "category":"Shopping",
            "subcategory":"Pharmacy",
            "type":"Retail Goods"
        }
    ],
    "sg:phone":"+1 602 278 0800",
    "sg:postcode":"85017",
    "sg:province":"AZ",
    "sg:tags":[
        "home",
        "therapy",
        "massage",
        "physical"
    ],
    "wof:name":"Aml La Stone Source",
    "wof:placetype":"venue"
},
  "geometry": {"coordinates":[-112.133124,33.491991],"type":"Point"}
}