{
  "type": "Feature",
  "properties": {
    "iso:country":"US",
    "sg:address":"1050 S Stapley Dr",
    "sg:city":"Mesa",
    "sg:classifiers":[
        {
            "category":"Banks & Credit Unions",
            "subcategory":"Bank",
            "type":"Services"
        }
    ],
    "sg:phone":"+1 480 461 9355",
    "sg:postcode":"85204",
    "sg:province":"AZ",
    "sg:tags":[
        "personal",
        "institution"
    ],
    "wof:name":"Cameron Rusch",
    "wof:placetype":"venue"
},
  "geometry": {"coordinates":[-111.805498,33.396778],"type":"Point"}
}