{
  "type": "Feature",
  "properties": {
    "iso:country":"US",
    "sg:address":"1583 S Avenue B",
    "sg:city":"Yuma",
    "sg:classifiers":[
        {
            "category":"Restaurant",
            "type":"Food & Drink"
        },
        {
            "category":"Bakery",
            "type":"Food & Drink"
        },
        {
            "category":"Donuts",
            "subcategory":"None",
            "type":"Food & Drink"
        }
    ],
    "sg:phone":"+1 928 343 7474",
    "sg:postcode":"85364",
    "sg:province":"AZ",
    "sg:tags":[
        "shop"
    ],
    "wof:name":"Arizona Donut & Cafe",
    "wof:placetype":"venue"
},
  "geometry": {"coordinates":[-114.650432,32.698798],"type":"Point"}
}