{
  "type": "Feature",
  "properties": {
    "iso:country":"US",
    "sg:address":"2405 S 27th Ave",
    "sg:city":"Phoenix",
    "sg:classifiers":[
        {
            "category":"Building & Trades",
            "subcategory":"Equipment Rental",
            "type":"Services"
        }
    ],
    "sg:phone":"+1 602 278 7400",
    "sg:postcode":"85009",
    "sg:province":"AZ",
    "sg:tags":[
        "contractor"
    ],
    "wof:name":"Resun Leasing",
    "wof:placetype":"venue"
},
  "geometry": {"coordinates":[-112.117119,33.422949],"type":"Point"}
}