{
  "type": "Feature",
  "properties": {
    "addr:full":"14217 N el Mirage Rd El Mirage AZ 85335",
    "addr:housenumber":"14217",
    "addr:postcode":"85335",
    "addr:street":"N El Mirage Rd",
    "iso:country":"US",
    "sg:address":"14217 N el Mirage Rd",
    "sg:city":"El Mirage",
    "sg:classifiers":[
        {
            "category":"Professional",
            "subcategory":"Accounting & Tax Preparation",
            "type":"Services"
        }
    ],
    "sg:phone":"+1 623 583 0258",
    "sg:postcode":"85335",
    "sg:province":"AZ",
    "sg:tags":[
        "return",
        "filing"
    ],
    "wof:name":"Mary Mattoon Tax Svc",
    "wof:placetype":"venue"
},
  "geometry": {"coordinates":[-112.324658,33.613351],"type":"Point"}
}