{
  "type": "Feature",
  "properties": {
    "addr:full":"2165 W 15TH ST TEMPE AZ 85281",
    "addr:housenumber":"2165",
    "addr:postcode":"85281",
    "addr:street":"W 15Th St",
    "iso:country":"US",
    "sg:address":"2165 W 15TH ST",
    "sg:city":"TEMPE",
    "sg:classifiers":[
        {
            "category":"Travel",
            "subcategory":"Hotels & Motels",
            "type":"Entertainment"
        }
    ],
    "sg:phone":"+1 480 557 8880",
    "sg:postcode":"85281",
    "sg:province":"AZ",
    "sg:tags":[
        "corporate",
        "lodging"
    ],
    "sg:website":"http://redirect.searchignite.com/si/cm/tracking/DGTrackingRedirect.aspx?siclientid=2918&siredirect=http%3A%2F%2Fwww%2Ehomesteadhotels%2Ecom%2FTEM&sisearchengine=155&siproduct=HS+Phoenix+%2D+Airport+%2D+Tempe&clearppc=1",
    "wof:name":"Homestead Studio Suites Phoenix - Airport - Tempe",
    "wof:placetype":"venue"
},
  "geometry": {"coordinates":[-111.972345,33.412282],"type":"Point"}
}