{
  "type": "Feature",
  "properties": {
    "addr:full":"7762 E Florentine Rd Prescott Valley AZ 86314",
    "addr:housenumber":"7762",
    "addr:postcode":"86314",
    "addr:street":"E Florentine Rd",
    "iso:country":"US",
    "sg:address":"7762 E Florentine Rd",
    "sg:city":"Prescott Valley",
    "sg:classifiers":[
        {
            "category":"Autos & Motor Vehicles",
            "subcategory":"Auto Supplies",
            "type":"Retail Goods"
        }
    ],
    "sg:phone":"+1 928 772 4744",
    "sg:postcode":"86314",
    "sg:province":"AZ",
    "sg:tags":[
        "automobile",
        "parts"
    ],
    "sg:website":"www.carquest.com",
    "wof:name":"Carquest Auto Parts",
    "wof:placetype":"venue"
},
  "geometry": {"coordinates":[-112.329683,34.588181],"type":"Point"}
}