{
  "type": "Feature",
  "properties": {
    "addr:full":"14417 S 24th Pl Phoenix AZ 85048",
    "addr:housenumber":"14417",
    "addr:postcode":"85048",
    "addr:street":"S 24Th Pl",
    "iso:country":"US",
    "sg:address":"14417 S 24th Pl",
    "sg:city":"Phoenix",
    "sg:classifiers":[
        {
            "category":"Personal",
            "type":"Services"
        }
    ],
    "sg:phone":"+1 480 759 0314",
    "sg:postcode":"85048",
    "sg:province":"AZ",
    "sg:tags":[
        "assistant"
    ],
    "wof:name":"Kelly D Desimone",
    "wof:placetype":"venue"
},
  "geometry": {"coordinates":[-112.027884,33.315392],"type":"Point"}
}