{
  "type": "Feature",
  "properties": {
    "addr:full":"1429 E Hadley St Phoenix AZ 85034",
    "addr:housenumber":"1429",
    "addr:postcode":"85034",
    "addr:street":"E Hadley St",
    "iso:country":"US",
    "sg:address":"1429 E Hadley St",
    "sg:city":"Phoenix",
    "sg:classifiers":[
        {
            "category":"Manufacturing",
            "subcategory":"Metals",
            "type":"Manufacturing & Wholesale Goods"
        }
    ],
    "sg:phone":"+1 602 462 1111",
    "sg:postcode":"85034",
    "sg:province":"AZ",
    "sg:tags":[
        "mfg",
        "structural"
    ],
    "wof:name":"Metal Wrks Cstm Fbrication LLC",
    "wof:placetype":"venue"
},
  "geometry": {"coordinates":[-112.049739,33.439035],"type":"Point"}
}