{
  "type": "Feature",
  "properties": {
    "iso:country":"US",
    "sg:address":"6980 E Sahuaro Dr",
    "sg:city":"Scottsdale",
    "sg:classifiers":[
        {
            "category":"Social Services",
            "type":"Services"
        }
    ],
    "sg:phone":"+1 602 790 0629",
    "sg:postcode":"85254",
    "sg:province":"AZ",
    "sg:tags":[
        "senior",
        "citizen"
    ],
    "wof:name":"Helping Hand Senior Svc",
    "wof:placetype":"venue"
},
  "geometry": {"coordinates":[-111.930861,33.584236],"type":"Point"}
}