{
  "type": "Feature",
  "properties": {
    "iso:country":"US",
    "sg:address":"400 W Gary Dr",
    "sg:city":"Chandler",
    "sg:classifiers":[
        {
            "category":"Shopping",
            "subcategory":"Computers & Home Electronics",
            "type":"Retail Goods"
        }
    ],
    "sg:phone":"+1 480 963 4611",
    "sg:postcode":"85225",
    "sg:province":"AZ",
    "sg:tags":[
        "publishing"
    ],
    "wof:name":"Designwrite Publication",
    "wof:placetype":"venue"
},
  "geometry": {"coordinates":[-111.848284,33.321819],"type":"Point"}
}