{
  "type": "Feature",
  "properties": {
    "iso:country":"US",
    "sg:address":"14448 S 41st Pl",
    "sg:city":"Phoenix",
    "sg:classifiers":[
        {
            "category":"Manufacturing",
            "subcategory":"Chemicals & Compounds",
            "type":"Manufacturing & Wholesale Goods"
        }
    ],
    "sg:phone":"+1 480 759 1200",
    "sg:postcode":"85044",
    "sg:province":"AZ",
    "sg:tags":[
        "metal",
        "mfg"
    ],
    "wof:name":"J and L Drum Recycling Co Inc",
    "wof:placetype":"venue"
},
  "geometry": {"coordinates":[-111.995071,33.314119],"type":"Point"}
}