{
  "type": "Feature",
  "properties": {
    "iso:country":"US",
    "sg:address":"300 S Park Ave",
    "sg:city":"Tucson",
    "sg:classifiers":[
        {
            "category":"Professional",
            "subcategory":"Business Services",
            "type":"Services"
        }
    ],
    "sg:phone":"+1 520 624 1133",
    "sg:postcode":"85719",
    "sg:province":"AZ",
    "sg:tags":[
        "interior",
        "consultant",
        "design",
        "decorator"
    ],
    "wof:name":"Studio Encanto",
    "wof:placetype":"venue"
},
  "geometry": {"coordinates":[-110.95647700000001,32.217771],"type":"Point"}
}