{
  "type": "Feature",
  "properties": {
    "iso:country":"US",
    "sg:address":"3135 N 29th Ave",
    "sg:city":"Phoenix",
    "sg:classifiers":[
        {
            "category":"Manufacturing",
            "subcategory":"Motor Vehicles & Parts",
            "type":"Manufacturing & Wholesale Goods"
        }
    ],
    "sg:phone":"+1 602 254 7712",
    "sg:postcode":"85017",
    "sg:province":"AZ",
    "sg:tags":[
        "mfg",
        "designer",
        "trailer",
        "custom"
    ],
    "sg:website":"www.progressivetrailers.com",
    "wof:name":"Progressive Industries Inc",
    "wof:placetype":"venue"
},
  "geometry": {"coordinates":[-112.12070900000001,33.487334],"type":"Point"}
}