{
  "type": "Feature",
  "properties": {
    "iso:country":"US",
    "sg:address":"2244 W Keating Ave",
    "sg:city":"Mesa",
    "sg:classifiers":[
        {
            "category":"Place Of Worship",
            "subcategory":"Church",
            "type":"Public Place"
        },
        {
            "category":"Place Of Worship",
            "type":"Public Place"
        }
    ],
    "sg:phone":"+1 480 831 5351",
    "sg:postcode":"85202",
    "sg:province":"AZ",
    "sg:tags":[
        "christ",
        "latter-day",
        "jesus",
        "churches-church",
        "saint"
    ],
    "wof:name":"Alma Seventh Ward",
    "wof:placetype":"venue"
},
  "geometry": {"coordinates":[-111.88226899999999,33.365944],"type":"Point"}
}