{
  "type": "Feature",
  "properties": {
    "iso:country":"US",
    "sg:address":"9012 N Cobre Dr",
    "sg:city":"Phoenix",
    "sg:classifiers":[
        {
            "category":"Professional",
            "subcategory":"Management & Consulting",
            "type":"Services"
        }
    ],
    "sg:phone":"+1 602 404 7544",
    "sg:postcode":"85028",
    "sg:province":"AZ",
    "sg:tags":[
        "fuel"
    ],
    "wof:name":"Labor Management",
    "wof:placetype":"venue"
},
  "geometry": {"coordinates":[-112.016334,33.568184],"type":"Point"}
}