{
  "type": "Feature",
  "properties": {
    "addr:full":"2319 E Cavalry Rd New River AZ 85087",
    "addr:housenumber":"2319",
    "addr:postcode":"85087",
    "addr:street":"E Cavalry Rd",
    "iso:country":"US",
    "sg:address":"2319 E Cavalry Rd",
    "sg:city":"New River",
    "sg:classifiers":[
        {
            "category":"Professional",
            "subcategory":"Credit Reporting & Collection",
            "type":"Services"
        }
    ],
    "sg:phone":"+1 602 494 1464",
    "sg:postcode":"85087",
    "sg:province":"AZ",
    "sg:tags":[
        "agency"
    ],
    "wof:name":"Commercial Collections Intl",
    "wof:placetype":"venue"
},
  "geometry": {"coordinates":[-112.03099,33.878818],"type":"Point"}
}