{
  "type": "Feature",
  "properties": {
    "addr:full":"468 W 20th St Tucson AZ 85701",
    "addr:housenumber":"468",
    "addr:postcode":"85701",
    "addr:street":"W 20Th St",
    "iso:country":"US",
    "sg:address":"468 W 20th St",
    "sg:city":"Tucson",
    "sg:classifiers":[
        {
            "category":"Building & Trades",
            "subcategory":"Landscaping Services",
            "type":"Services"
        }
    ],
    "sg:phone":"+1 520 891 0729",
    "sg:postcode":"85701",
    "sg:province":"AZ",
    "sg:tags":[
        "landscape",
        "contractor"
    ],
    "wof:name":"B and E Yard Service and Maint",
    "wof:placetype":"venue"
},
  "geometry": {"coordinates":[-110.975188,32.209512],"type":"Point"}
}