{
  "type": "Feature",
  "properties": {
    "iso:country":"US",
    "sg:address":"4402 N 36th St",
    "sg:city":"Phoenix",
    "sg:classifiers":[
        {
            "category":"Building & Trades",
            "subcategory":"Electrical",
            "type":"Services"
        }
    ],
    "sg:phone":"+1 602 954 7339",
    "sg:postcode":"85018",
    "sg:province":"AZ",
    "sg:tags":[
        "electric",
        "contractor"
    ],
    "wof:name":"Above Board Electric Inc",
    "wof:placetype":"venue"
},
  "geometry": {"coordinates":[-112.004242,33.502496],"type":"Point"}
}