{
  "type": "Feature",
  "properties": {
    "iso:country":"US",
    "sg:address":"8701 N 65th St",
    "sg:city":"Paradise Valley",
    "sg:classifiers":[
        {
            "category":"Professional",
            "type":"Services"
        }
    ],
    "sg:phone":"+1 480 948 8640",
    "sg:postcode":"85253",
    "sg:province":"AZ",
    "wof:name":"Edward M Kobel",
    "wof:placetype":"venue"
},
  "geometry": {"coordinates":[-111.939925,33.563811],"type":"Point"}
}