{
  "type": "Feature",
  "properties": {
    "addr:full":"2750 E University Dr Mesa AZ 85213",
    "addr:housenumber":"2750",
    "addr:postcode":"85213",
    "addr:street":"E University Dr",
    "iso:country":"US",
    "sg:address":"2750 E University Dr",
    "sg:city":"Mesa",
    "sg:classifiers":[
        {
            "category":"Autos & Motor Vehicles",
            "subcategory":"Fuel & Gas Station",
            "type":"Retail Goods"
        }
    ],
    "sg:phone":"+1 480 890 0248",
    "sg:postcode":"85213",
    "sg:province":"AZ",
    "sg:tags":[
        "oil"
    ],
    "wof:name":"Mobil Oil",
    "wof:placetype":"venue"
},
  "geometry": {"coordinates":[-111.772234,33.422763],"type":"Point"}
}