{
  "type": "Feature",
  "properties": {
    "iso:country":"US",
    "sg:address":"109 W Hilton Ave",
    "sg:city":"Phoenix",
    "sg:classifiers":[
        {
            "category":"Wholesale",
            "subcategory":"Construction Materials",
            "type":"Manufacturing & Wholesale Goods"
        }
    ],
    "sg:phone":"+1 602 254 8058",
    "sg:postcode":"85003",
    "sg:province":"AZ",
    "sg:tags":[
        "marble"
    ],
    "wof:name":"Magos Marble & Assoc",
    "wof:placetype":"venue"
},
  "geometry": {"coordinates":[-112.075611,33.428294],"type":"Point"}
}