{
  "type": "Feature",
  "properties": {
    "addr:full":"4407 S Rural Rd Tempe AZ 85282",
    "addr:housenumber":"4407",
    "addr:postcode":"85282",
    "addr:street":"S Rural Rd",
    "iso:country":"US",
    "sg:address":"4407 S Rural Rd",
    "sg:city":"Tempe",
    "sg:classifiers":[
        {
            "category":"Sports & Exercise",
            "subcategory":"Bowling",
            "type":"Entertainment"
        }
    ],
    "sg:phone":"+1 480 831 5322",
    "sg:postcode":"85282",
    "sg:province":"AZ",
    "sg:tags":[
        "park",
        "center",
        "amusement"
    ],
    "sg:website":"www.amf.com/tempevillagelanes/ce...",
    "wof:name":"Tempe Village Lanes",
    "wof:placetype":"venue"
},
  "geometry": {"coordinates":[-111.92600299999999,33.383701],"type":"Point"}
}