{
  "type": "Feature",
  "properties": {
    "iso:country":"US",
    "sg:address":"7230 S Frances Ave",
    "sg:city":"Tucson",
    "sg:classifiers":[
        {
            "category":"Retail",
            "subcategory":"Auto Repair",
            "type":"Services"
        }
    ],
    "sg:phone":"+1 520 574 8012",
    "sg:postcode":"85706",
    "sg:province":"AZ",
    "sg:tags":[
        "truck"
    ],
    "wof:name":"Accu-Trac",
    "wof:placetype":"venue"
},
  "geometry": {"coordinates":[-110.884857,32.121163],"type":"Point"}
}