{
  "type": "Feature",
  "properties": {
    "addr:full":"17674 N Litchfield Rd Surprise AZ 85374",
    "addr:housenumber":"17674",
    "addr:postcode":"85374",
    "addr:street":"N Litchfield Rd",
    "iso:country":"US",
    "sg:address":"17674 N Litchfield Rd",
    "sg:city":"Surprise",
    "sg:classifiers":[
        {
            "category":"Restaurant",
            "type":"Food & Drink"
        }
    ],
    "sg:phone":"+1 623 544 0900",
    "sg:postcode":"85374",
    "sg:province":"AZ",
    "sg:tags":[
        "style",
        "family",
        "buffet",
        "lunch",
        "american",
        "brunch",
        "breakfast"
    ],
    "sg:website":"http://www.goldencorral.com",
    "wof:name":"Golden Corral Restaurants",
    "wof:placetype":"venue"
},
  "geometry": {"coordinates":[-112.358627,33.644238],"type":"Point"}
}