{
  "type": "Feature",
  "properties": {
    "iso:country":"US",
    "sg:address":"2881 S Market St",
    "sg:city":"Gilbert",
    "sg:classifiers":[
        {
            "category":"Fast Food",
            "type":"Food & Drink"
        },
        {
            "category":"Restaurant",
            "type":"Food & Drink"
        }
    ],
    "sg:phone":"+1 480 855 5725",
    "sg:postcode":"85295",
    "sg:province":"AZ",
    "sg:tags":[
        "mexican"
    ],
    "sg:website":"http://www.tacobell.com",
    "wof:name":"Taco Bell",
    "wof:placetype":"venue"
},
  "geometry": {"coordinates":[-111.748936,33.296767],"type":"Point"}
}