{
  "type": "Feature",
  "properties": {
    "addr:full":"250 W Columbus Ave Flagstaff AZ 86001",
    "addr:housenumber":"250",
    "addr:postcode":"86001",
    "addr:street":"W Columbus Ave",
    "iso:country":"US",
    "sg:address":"250 W Columbus Ave",
    "sg:city":"Flagstaff",
    "sg:classifiers":[
        {
            "category":"Autos & Motor Vehicles",
            "subcategory":"Fuel & Gas Station",
            "type":"Retail Goods"
        }
    ],
    "sg:phone":"+1 928 779 3075",
    "sg:postcode":"86001",
    "sg:province":"AZ",
    "sg:tags":[
        "station",
        "gasoline"
    ],
    "wof:name":"Twin Pines Gaser Inc",
    "wof:placetype":"venue"
},
  "geometry": {"coordinates":[-111.647903,35.206758],"type":"Point"}
}