{
  "type": "Feature",
  "properties": {
    "addr:full":"308 E Congress St Tucson AZ 85701",
    "addr:housenumber":"308",
    "addr:postcode":"85701",
    "addr:street":"E Congress St",
    "iso:country":"US",
    "sg:address":"308 E Congress St",
    "sg:city":"Tucson",
    "sg:classifiers":[
        {
            "category":"Shopping",
            "type":"Retail Goods"
        }
    ],
    "sg:phone":"+1 520 622 3350",
    "sg:postcode":"85701",
    "sg:province":"AZ",
    "sg:tags":[
        "art",
        "gallery"
    ],
    "wof:name":"Eric Firestone Gallery",
    "wof:placetype":"venue"
},
  "geometry": {"coordinates":[-110.966407,32.222008],"type":"Point"}
}