{
  "type": "Feature",
  "properties": {
    "iso:country":"US",
    "sg:address":"5301 E Linden Pl",
    "sg:city":"Tucson",
    "sg:classifiers":[
        {
            "category":"Professional",
            "subcategory":"Advertising",
            "type":"Services"
        }
    ],
    "sg:phone":"+1 520 327 4676",
    "sg:postcode":"85712",
    "sg:province":"AZ",
    "sg:tags":[
        "counselor"
    ],
    "wof:name":"Martinez-Ross Marketing",
    "wof:placetype":"venue"
},
  "geometry": {"coordinates":[-110.878406,32.245225],"type":"Point"}
}