{
  "type": "Feature",
  "properties": {
    "iso:country":"US",
    "sg:address":"1026 N Pinal Ave",
    "sg:city":"Casa Grande",
    "sg:classifiers":[
        {
            "category":"Autos & Motor Vehicles",
            "subcategory":"Automobile Sales",
            "type":"Retail Goods"
        }
    ],
    "sg:phone":"+1 520 836 2112",
    "sg:postcode":"85222",
    "sg:province":"AZ",
    "sg:tags":[
        "used"
    ],
    "wof:name":"Crossroads Auto Center",
    "wof:placetype":"venue"
},
  "geometry": {"coordinates":[-111.75722,32.883219],"type":"Point"}
}