{
  "type": "Feature",
  "properties": {
    "addr:full":"385 Fox Dr Bullhead City AZ 86442",
    "addr:housenumber":"385",
    "addr:postcode":"86442",
    "addr:street":"Fox Dr",
    "iso:country":"US",
    "sg:address":"385 Fox Dr",
    "sg:city":"Bullhead City",
    "sg:classifiers":[
        {
            "category":"Real Estate",
            "subcategory":"Real Estate Agent",
            "type":"Services"
        }
    ],
    "sg:phone":"+1 928 704 9150",
    "sg:postcode":"86442",
    "sg:province":"AZ",
    "wof:name":"20th Century Realty",
    "wof:placetype":"venue"
},
  "geometry": {"coordinates":[-114.634041,35.098409],"type":"Point"}
}