{
  "type": "Feature",
  "properties": {
    "iso:country":"US",
    "sg:address":"4241 E Ellis Cir",
    "sg:city":"Mesa",
    "sg:classifiers":[
        {
            "category":"Organizations",
            "subcategory":"Religious Organization",
            "type":"Services"
        }
    ],
    "sg:phone":"+1 480 607 5525",
    "sg:postcode":"85205",
    "sg:province":"AZ",
    "sg:tags":[
        "church"
    ],
    "wof:name":"Crown Ministries Inc",
    "wof:placetype":"venue"
},
  "geometry": {"coordinates":[-111.740091,33.430564],"type":"Point"}
}