{
  "type": "Feature",
  "properties": {
    "iso:country":"US",
    "sg:address":"4539 N 22nd St",
    "sg:city":"Phoenix",
    "sg:classifiers":[
        {
            "category":"Manufacturing",
            "subcategory":"Printing",
            "type":"Manufacturing & Wholesale Goods"
        }
    ],
    "sg:phone":"+1 602 508 1920",
    "sg:postcode":"85016",
    "sg:province":"AZ",
    "sg:tags":[
        "publisher",
        "software"
    ],
    "wof:name":"Act Logic",
    "wof:placetype":"venue"
},
  "geometry": {"coordinates":[-112.034473,33.503118],"type":"Point"}
}