{
  "type": "Feature",
  "properties": {
    "iso:country":"US",
    "sg:address":"13229 S 48th St",
    "sg:city":"Phoenix",
    "sg:classifiers":[
        {
            "category":"Banks & Credit Unions",
            "subcategory":"Investment Brokerage",
            "type":"Services"
        }
    ],
    "sg:phone":"+1 480 785 5371",
    "sg:postcode":"85044",
    "sg:province":"AZ",
    "sg:tags":[
        "merger",
        "acquisition"
    ],
    "wof:name":"Southwest SDC & Acquisitions",
    "wof:placetype":"venue"
},
  "geometry": {"coordinates":[-111.979421,33.324103],"type":"Point"}
}