{
  "type": "Feature",
  "properties": {
    "iso:country":"US",
    "sg:address":"4320 S 6th Ave",
    "sg:city":"Tucson",
    "sg:classifiers":[
        {
            "category":"Health Services",
            "subcategory":"Doctor",
            "type":"Services"
        }
    ],
    "sg:phone":"+1 520 294 4872",
    "sg:postcode":"85714",
    "sg:province":"AZ",
    "sg:tags":[
        "dentist"
    ],
    "wof:name":"A L Hennington Jr DDS",
    "wof:placetype":"venue"
},
  "geometry": {"coordinates":[-110.968291,32.172427],"type":"Point"}
}