{
  "type": "Feature",
  "properties": {
    "iso:country":"US",
    "sg:address":"8476 E Chaparral Rd",
    "sg:city":"Scottsdale",
    "sg:classifiers":[
        {
            "category":"Real Estate",
            "subcategory":"Real Estate Agent",
            "type":"Services"
        }
    ],
    "sg:phone":"+1 480 390 8179",
    "sg:postcode":"85250",
    "sg:province":"AZ",
    "wof:name":"Young Property Management",
    "wof:placetype":"venue"
},
  "geometry": {"coordinates":[-111.898721,33.509448],"type":"Point"}
}