{
  "type": "Feature",
  "properties": {
    "iso:country":"US",
    "sg:address":"1065 W Fairway Dr",
    "sg:city":"Mesa",
    "sg:classifiers":[
        {
            "category":"Restaurant",
            "type":"Food & Drink"
        }
    ],
    "sg:phone":"+1 480 833 6903",
    "sg:postcode":"85201",
    "sg:province":"AZ",
    "sg:tags":[
        "bar"
    ],
    "wof:name":"Buddys Grill",
    "wof:placetype":"venue"
},
  "geometry": {"coordinates":[-111.855965,33.435149],"type":"Point"}
}