{
  "type": "Feature",
  "properties": {
    "addr:full":"5350 E High St Ste 109 Phoenix AZ 85054",
    "addr:housenumber":"5350",
    "addr:postcode":"85054",
    "addr:street":"E High St Ste 109",
    "iso:country":"US",
    "sg:address":"5350 E High St Ste 109",
    "sg:city":"Phoenix",
    "sg:classifiers":[
        {
            "category":"Shopping",
            "subcategory":"Clothing, Apparel, & Fashions",
            "type":"Retail Goods"
        },
        {
            "category":"Shopping",
            "subcategory":"Catalog Store",
            "type":"Retail Goods"
        }
    ],
    "sg:phone":"+1 480 563 0370",
    "sg:postcode":"85054",
    "sg:province":"AZ",
    "sg:tags":[
        "women's",
        "online",
        "apparel",
        "mail",
        "accessory",
        "clothing",
        "order"
    ],
    "sg:website":"http://www.coldwatercreek.com/",
    "wof:name":"Coldwater Creek",
    "wof:placetype":"venue"
},
  "geometry": {"coordinates":[-111.96566,33.676066],"type":"Point"}
}