{
  "type": "Feature",
  "properties": {
    "addr:full":"1618 E Greenway St Mesa AZ 85203",
    "addr:housenumber":"1618",
    "addr:postcode":"85203",
    "addr:street":"E Greenway St",
    "iso:country":"US",
    "sg:address":"1618 E Greenway St",
    "sg:city":"Mesa",
    "sg:classifiers":[
        {
            "category":"Travel",
            "subcategory":"Travel Agent",
            "type":"Entertainment"
        }
    ],
    "sg:phone":"+1 480 964 0109",
    "sg:postcode":"85203",
    "sg:province":"AZ",
    "sg:tags":[
        "agency"
    ],
    "wof:name":"Incentive Connection",
    "wof:placetype":"venue"
},
  "geometry": {"coordinates":[-111.792692,33.43787],"type":"Point"}
}