{
  "type": "Feature",
  "properties": {
    "iso:country":"US",
    "sg:address":"1743 E Prince Rd",
    "sg:city":"Tucson",
    "sg:classifiers":[
        {
            "category":"Retail",
            "subcategory":"Laundry & Dry Cleaning",
            "type":"Services"
        }
    ],
    "sg:phone":"+1 520 320 1710",
    "sg:postcode":"85719",
    "sg:province":"AZ",
    "sg:tags":[
        "cleaners"
    ],
    "sg:website":"www.yourdrycleaners.com",
    "wof:name":"Seville Cleaners",
    "wof:placetype":"venue"
},
  "geometry": {"coordinates":[-110.94423399999999,32.272278],"type":"Point"}
}