{
  "type": "Feature",
  "properties": {
    "addr:full":"7630 N 33rd Ave Phoenix AZ 85051",
    "addr:housenumber":"7630",
    "addr:postcode":"85051",
    "addr:street":"N 33Rd Ave",
    "iso:country":"US",
    "sg:address":"7630 N 33rd Ave",
    "sg:city":"Phoenix",
    "sg:classifiers":[
        {
            "category":"Retail",
            "subcategory":"Auto Repair",
            "type":"Services"
        }
    ],
    "sg:phone":"+1 602 841 0100",
    "sg:postcode":"85051",
    "sg:province":"AZ",
    "sg:tags":[
        "wrecker"
    ],
    "wof:name":"Desert Towing Auto Recovery",
    "wof:placetype":"venue"
},
  "geometry": {"coordinates":[-112.130021,33.548737],"type":"Point"}
}