{
  "type": "Feature",
  "properties": {
    "iso:country":"US",
    "sg:address":"1457 W Antiqua Dr",
    "sg:city":"Gilbert",
    "sg:classifiers":[
        {
            "category":"Professional",
            "subcategory":"Management & Consulting",
            "type":"Services"
        }
    ],
    "sg:phone":"+1 602 321 6952",
    "sg:postcode":"85233",
    "sg:province":"AZ",
    "sg:tags":[
        "consultant"
    ],
    "wof:name":"Fernau Consulting",
    "wof:placetype":"venue"
},
  "geometry": {"coordinates":[-111.821837,33.33954],"type":"Point"}
}