{
  "type": "Feature",
  "properties": {
    "iso:country":"US",
    "sg:address":"6031 N 67th Ave",
    "sg:city":"Glendale",
    "sg:classifiers":[
        {
            "category":"Shopping",
            "type":"Retail Goods"
        }
    ],
    "sg:phone":"+1 623 930 1733",
    "sg:postcode":"85301",
    "sg:province":"AZ",
    "sg:tags":[
        "merchandise"
    ],
    "wof:name":"Omar 99 Mart",
    "wof:placetype":"venue"
},
  "geometry": {"coordinates":[-112.203022,33.52514],"type":"Point"}
}