{
  "type": "Feature",
  "properties": {
    "iso:country":"US",
    "sg:address":"943 S 48th St Ste 108",
    "sg:city":"Tempe",
    "sg:classifiers":[
        {
            "category":"Professional",
            "subcategory":"Management & Consulting",
            "type":"Services"
        },
        {
            "category":"Professional",
            "subcategory":"Advertising",
            "type":"Services"
        }
    ],
    "sg:phone":"+1 480 966 8688",
    "sg:postcode":"85281",
    "sg:province":"AZ",
    "sg:tags":[
        "marketing",
        "program",
        "consultant"
    ],
    "wof:name":"Corner Stone Printg & Market",
    "wof:placetype":"venue"
},
  "geometry": {"coordinates":[-111.976983,33.42127],"type":"Point"}
}