{
  "type": "Feature",
  "properties": {
    "addr:full":"425 S 48th St Tempe AZ 85281",
    "addr:housenumber":"425",
    "addr:postcode":"85281",
    "addr:street":"S 48Th St",
    "iso:country":"US",
    "sg:address":"425 S 48th St",
    "sg:city":"Tempe",
    "sg:classifiers":[
        {
            "category":"Wholesale",
            "subcategory":"Medical Equipment & Supplies",
            "type":"Manufacturing & Wholesale Goods"
        }
    ],
    "sg:phone":"+1 480 317 0102",
    "sg:postcode":"85281",
    "sg:province":"AZ",
    "sg:tags":[
        "to",
        "product",
        "dental",
        "provides",
        "professional"
    ],
    "wof:name":"Sullivan Schein Dental",
    "wof:placetype":"venue"
},
  "geometry": {"coordinates":[-111.97628899999999,33.422482],"type":"Point"}
}