{
  "type": "Feature",
  "properties": {
    "addr:full":"2231 McCulloch Blvd N Lake Havasu City AZ 86403",
    "addr:housenumber":"2231",
    "addr:postcode":"86403",
    "addr:street":"Mcculloch Blvd N",
    "iso:country":"US",
    "sg:address":"2231 McCulloch Blvd N",
    "sg:city":"Lake Havasu City",
    "sg:classifiers":[
        {
            "category":"Banks & Credit Unions",
            "subcategory":"Bank",
            "type":"Services"
        }
    ],
    "sg:phone":"+1 928 505 4300",
    "sg:postcode":"86403",
    "sg:province":"AZ",
    "sg:tags":[
        "loan",
        "real estate"
    ],
    "wof:name":"Mortgage Tree Lending",
    "wof:placetype":"venue"
},
  "geometry": {"coordinates":[-114.321905,34.476053],"type":"Point"}
}