{
  "type": "Feature",
  "properties": {
    "addr:full":"151 W Superstition Blvd Apache Junction AZ 85220",
    "addr:housenumber":"151",
    "addr:postcode":"85220",
    "addr:street":"W Superstition Blvd",
    "iso:country":"US",
    "sg:address":"151 W Superstition Blvd",
    "sg:city":"Apache Junction",
    "sg:classifiers":[
        {
            "category":"Government",
            "subcategory":"Post Office",
            "type":"Public Place"
        }
    ],
    "sg:phone":"+1 480 983 7186",
    "sg:postcode":"85220",
    "sg:province":"AZ",
    "wof:name":"US Post Office",
    "wof:placetype":"venue"
},
  "geometry": {"coordinates":[-111.547842,33.422246],"type":"Point"}
}