{
  "type": "Feature",
  "properties": {
    "iso:country":"US",
    "sg:address":"1380 W Derringer Way",
    "sg:city":"Chandler",
    "sg:classifiers":[
        {
            "category":"Wholesale",
            "subcategory":"Hardware",
            "type":"Manufacturing & Wholesale Goods"
        },
        {
            "category":"Home & Garden",
            "subcategory":"Hardware",
            "type":"Retail Goods"
        },
        {
            "category":"Building & Trades",
            "subcategory":"Construction",
            "type":"Services"
        }
    ],
    "sg:phone":"+1 480 812 3548",
    "sg:postcode":"85286",
    "sg:province":"AZ",
    "sg:tags":[
        "brick-clay-common",
        "hardware-builders",
        "brick-fire",
        "store",
        "face"
    ],
    "sg:website":"http://www.elitedistribution.com",
    "wof:name":"Elite Distribution, Inc",
    "wof:placetype":"venue"
},
  "geometry": {"coordinates":[-111.866271,33.29084],"type":"Point"}
}