{
  "type": "Feature",
  "properties": {
    "iso:country":"US",
    "sg:address":"14703 E Williams Field Road",
    "sg:city":"Gilbert",
    "sg:classifiers":[
        {
            "category":"Home & Garden",
            "subcategory":"Garden Supply",
            "type":"Retail Goods"
        }
    ],
    "sg:phone":"+1 480 917 9847",
    "sg:postcode":"85296",
    "sg:province":"AZ",
    "sg:tags":[
        "nursery",
        "gardening"
    ],
    "wof:name":"V and P Nurseries",
    "wof:placetype":"venue"
},
  "geometry": {"coordinates":[-111.76711899999999,33.310188],"type":"Point"}
}