{
  "type": "Feature",
  "properties": {
    "iso:country":"US",
    "sg:address":"2765 N Scottsdale Rd",
    "sg:city":"Scottsdale",
    "sg:classifiers":[
        {
            "category":"Restaurant",
            "type":"Food & Drink"
        }
    ],
    "sg:phone":"+1 480 945 3182",
    "sg:postcode":"85257",
    "sg:province":"AZ",
    "wof:name":"Pho Az",
    "wof:placetype":"venue"
},
  "geometry": {"coordinates":[-111.926082,33.480055],"type":"Point"}
}