{
  "type": "Feature",
  "properties": {
    "addr:full":"6650 W Northern Ave Glendale AZ 85301",
    "addr:housenumber":"6650",
    "addr:postcode":"85301",
    "addr:street":"W Northern Ave",
    "iso:country":"US",
    "sg:address":"6650 W Northern Ave",
    "sg:city":"Glendale",
    "sg:classifiers":[
        {
            "category":"Home & Garden",
            "subcategory":"Mobile Homes",
            "type":"Retail Goods"
        }
    ],
    "sg:phone":"+1 623 931 5300",
    "sg:postcode":"85301",
    "sg:province":"AZ",
    "wof:name":"Majesty Homes",
    "wof:placetype":"venue"
},
  "geometry": {"coordinates":[-112.20019600000001,33.552909],"type":"Point"}
}