{
  "type": "Feature",
  "properties": {
    "iso:country":"US",
    "sg:address":"1130 W Grove Ave Ste 115",
    "sg:city":"Mesa",
    "sg:classifiers":[
        {
            "category":"Health Services",
            "subcategory":"Dentist",
            "type":"Services"
        }
    ],
    "sg:phone":"+1 480 964 2724",
    "sg:postcode":"85210",
    "sg:province":"AZ",
    "wof:name":"Arch Dental",
    "wof:placetype":"venue"
},
  "geometry": {"coordinates":[-111.855464,33.390368],"type":"Point"}
}