{
  "type": "Feature",
  "properties": {
    "iso:country":"US",
    "sg:address":"205 W Portland St",
    "sg:city":"Phoenix",
    "sg:classifiers":[
        {
            "category":"Professional",
            "subcategory":"Art Services",
            "type":"Services"
        }
    ],
    "sg:phone":"+1 602 330 7749",
    "sg:postcode":"85003",
    "sg:province":"AZ",
    "sg:tags":[
        "designer",
        "display",
        "producer"
    ],
    "wof:name":"Altered Design",
    "wof:placetype":"venue"
},
  "geometry": {"coordinates":[-112.07643299999999,33.459819],"type":"Point"}
}