{
  "type": "Feature",
  "properties": {
    "iso:country":"US",
    "sg:address":"81 Park Ave",
    "sg:city":"Clifton",
    "sg:classifiers":[
        {
            "category":"Shopping",
            "type":"Retail Goods"
        }
    ],
    "sg:phone":"+1 928 865 3467",
    "sg:postcode":"85533",
    "sg:province":"AZ",
    "sg:tags":[
        "art",
        "gallery",
        "dealer"
    ],
    "wof:name":"Art Depot",
    "wof:placetype":"venue"
},
  "geometry": {"coordinates":[-109.299346,33.057871],"type":"Point"}
}