{
  "type": "Feature",
  "properties": {
    "addr:full":"519 W Beale St Kingman AZ 86401",
    "addr:housenumber":"519",
    "addr:postcode":"86401",
    "addr:street":"W Beale St",
    "iso:country":"US",
    "sg:address":"519 W Beale St",
    "sg:city":"Kingman",
    "sg:classifiers":[
        {
            "category":"Government",
            "subcategory":"Office",
            "type":"Public Place"
        }
    ],
    "sg:phone":"+1 928 753 4868",
    "sg:postcode":"86401",
    "sg:province":"AZ",
    "sg:tags":[
        "state",
        "resource"
    ],
    "wof:name":"Developmental Disabilities",
    "wof:placetype":"venue"
},
  "geometry": {"coordinates":[-114.063557,35.190617],"type":"Point"}
}