{
  "type": "Feature",
  "properties": {
    "addr:full":"16808 W Ipswitch Way Surprise AZ 85374",
    "addr:housenumber":"16808",
    "addr:postcode":"85374",
    "addr:street":"W Ipswitch Way",
    "iso:country":"US",
    "sg:address":"16808 W Ipswitch Way",
    "sg:city":"Surprise",
    "sg:classifiers":[
        {
            "category":"Real Estate",
            "subcategory":"Real Estate Agent",
            "type":"Services"
        }
    ],
    "sg:phone":"+1 623 594 2664",
    "sg:postcode":"85374",
    "sg:province":"AZ",
    "sg:tags":[
        "inspection"
    ],
    "wof:name":"Eagle Eye Home Inspection",
    "wof:placetype":"venue"
},
  "geometry": {"coordinates":[-112.41910300000001,33.644383],"type":"Point"}
}