{
  "type": "Feature",
  "properties": {
    "iso:country":"US",
    "sg:address":"3317 S Higley Rd",
    "sg:city":"Gilbert",
    "sg:classifiers":[
        {
            "category":"Restaurant",
            "type":"Food & Drink"
        }
    ],
    "sg:menulink":"http://www.allmenus.com/az/chandler/129022-subway/menu/",
    "sg:phone":"+1 480 279 1460",
    "sg:postcode":"85297",
    "sg:province":"AZ",
    "sg:tags":[
        "american",
        "sandwich"
    ],
    "wof:name":"Subway",
    "wof:placetype":"venue"
},
  "geometry": {"coordinates":[-111.72041900000001,33.290453],"type":"Point"}
}