{
  "type": "Feature",
  "properties": {
    "iso:country":"US",
    "sg:address":"850 E Hatcher Rd",
    "sg:city":"Phoenix",
    "sg:classifiers":[
        {
            "category":"Professional",
            "subcategory":"Accounting & Tax Preparation",
            "type":"Services"
        }
    ],
    "sg:phone":"+1 602 331 0614",
    "sg:postcode":"85020",
    "sg:province":"AZ",
    "sg:tags":[
        "return",
        "filing"
    ],
    "wof:name":"H & R Block Tax Svc",
    "wof:placetype":"venue"
},
  "geometry": {"coordinates":[-112.06079,33.571441],"type":"Point"}
}