{
  "type": "Feature",
  "properties": {
    "addr:full":"14829 S Foxtail Ln Phoenix AZ 85048",
    "addr:housenumber":"14829",
    "addr:postcode":"85048",
    "addr:street":"S Foxtail Ln",
    "iso:country":"US",
    "sg:address":"14829 S Foxtail Ln",
    "sg:city":"Phoenix",
    "sg:classifiers":[
        {
            "category":"Professional",
            "type":"Services"
        }
    ],
    "sg:phone":"+1 480 759 5928",
    "sg:postcode":"85048",
    "sg:province":"AZ",
    "wof:name":"Angel Faces",
    "wof:placetype":"venue"
},
  "geometry": {"coordinates":[-112.037285,33.312012],"type":"Point"}
}