{
  "type": "Feature",
  "properties": {
    "iso:country":"US",
    "sg:address":"1411 E Hammond Ln",
    "sg:city":"Phoenix",
    "sg:classifiers":[
        {
            "category":"Home & Garden",
            "subcategory":"Building Materials",
            "type":"Retail Goods"
        }
    ],
    "sg:phone":"+1 602 462 1400",
    "sg:postcode":"85034",
    "sg:province":"AZ",
    "sg:tags":[
        "stone"
    ],
    "wof:name":"Sun Valley Stone Works Inc",
    "wof:placetype":"venue"
},
  "geometry": {"coordinates":[-112.050032,33.424944],"type":"Point"}
}