{
  "type": "Feature",
  "properties": {
    "iso:country":"US",
    "sg:address":"1665 E 22nd St",
    "sg:city":"Tucson",
    "sg:classifiers":[
        {
            "category":"Retail",
            "subcategory":"Repair Shop",
            "type":"Services"
        }
    ],
    "sg:phone":"+1 520 903 9944",
    "sg:postcode":"85713",
    "sg:province":"AZ",
    "sg:tags":[
        "refinish",
        "furniture"
    ],
    "sg:website":"www.walshbros.com",
    "wof:name":"Walsh Brothers Warehouse",
    "wof:placetype":"venue"
},
  "geometry": {"coordinates":[-110.947256,32.206978],"type":"Point"}
}