{
  "type": "Feature",
  "properties": {
    "addr:full":"7101 W Libby St Glendale AZ 85308",
    "addr:housenumber":"7101",
    "addr:postcode":"85308",
    "addr:street":"W Libby St",
    "iso:country":"US",
    "sg:address":"7101 W Libby St",
    "sg:city":"Glendale",
    "sg:classifiers":[
        {
            "category":"Shopping",
            "subcategory":"Books",
            "type":"Retail Goods"
        }
    ],
    "sg:phone":"+1 602 547 0995",
    "sg:postcode":"85308",
    "sg:province":"AZ",
    "sg:tags":[
        "dealer"
    ],
    "wof:name":"Electronic Filing Solutions",
    "wof:placetype":"venue"
},
  "geometry": {"coordinates":[-112.215963,33.64646],"type":"Point"}
}