{
  "type": "Feature",
  "properties": {
    "iso:country":"US",
    "sg:address":"2480 W Twin Buttes Rd",
    "sg:city":"Sahuarita",
    "sg:classifiers":[
        {
            "category":"Manufacturing",
            "subcategory":"Chemicals & Compounds",
            "type":"Manufacturing & Wholesale Goods"
        }
    ],
    "sg:phone":"+1 602 889 8354",
    "sg:postcode":"85629",
    "sg:province":"AZ",
    "sg:tags":[
        "inorganic",
        "industrial",
        "mfg"
    ],
    "wof:name":"Alkemin S De R L De C V",
    "wof:placetype":"venue"
},
  "geometry": {"coordinates":[-111.013401,31.935616],"type":"Point"}
}