{
  "type": "Feature",
  "properties": {
    "addr:full":"418 N Austin Blvd Willcox AZ 85643",
    "addr:housenumber":"418",
    "addr:postcode":"85643",
    "addr:street":"N Austin Blvd",
    "iso:country":"US",
    "sg:address":"418 N Austin Blvd",
    "sg:city":"Willcox",
    "sg:classifiers":[
        {
            "category":"Social Services",
            "subcategory":"Adult Care",
            "type":"Services"
        }
    ],
    "sg:phone":"+1 520 384 4855",
    "sg:postcode":"85643",
    "sg:province":"AZ",
    "sg:tags":[
        "home",
        "residential"
    ],
    "wof:name":"Circle B Adult Care Homes",
    "wof:placetype":"venue"
},
  "geometry": {"coordinates":[-109.832324,32.258814],"type":"Point"}
}