{
  "type": "Feature",
  "properties": {
    "addr:full":"3112 E Camelback Rd Phoenix AZ 85016",
    "addr:housenumber":"3112",
    "addr:postcode":"85016",
    "addr:street":"E Camelback Rd",
    "iso:country":"US",
    "sg:address":"3112 E Camelback Rd",
    "sg:city":"Phoenix",
    "sg:classifiers":[
        {
            "category":"Shopping",
            "type":"Retail Goods"
        }
    ],
    "sg:phone":"+1 602 522 1701",
    "sg:postcode":"85016",
    "sg:province":"AZ",
    "sg:tags":[
        "picture",
        "frame"
    ],
    "wof:name":"Fastframe",
    "wof:placetype":"venue"
},
  "geometry": {"coordinates":[-112.013322,33.510042],"type":"Point"}
}