{
  "type": "Feature",
  "properties": {
    "iso:country":"US",
    "sg:address":"3320 Stockton Hill Rd Ste B",
    "sg:city":"Kingman",
    "sg:classifiers":[
        {
            "category":"Shopping",
            "subcategory":"Pets & Pet Supplies",
            "type":"Retail Goods"
        },
        {
            "category":"Retail",
            "subcategory":"Animal Services",
            "type":"Services"
        },
        {
            "category":"Museum",
            "subcategory":"Aquarium",
            "type":"Entertainment"
        }
    ],
    "sg:phone":"+1 928 681 4101",
    "sg:postcode":"86409",
    "sg:province":"AZ",
    "sg:tags":[
        "food",
        "dog",
        "cat",
        "furnishing",
        "grooming",
        "store"
    ],
    "sg:website":"http://www.petco.com",
    "wof:name":"PETCO",
    "wof:placetype":"venue"
},
  "geometry": {"coordinates":[-114.03580100000001,35.220513],"type":"Point"}
}