{
  "type": "Feature",
  "properties": {
    "iso:country":"US",
    "sg:address":"3475 W Renegade Rd",
    "sg:city":"Prescott",
    "sg:classifiers":[
        {
            "category":"Building & Trades",
            "subcategory":"Construction",
            "type":"Services"
        }
    ],
    "sg:phone":"+1 928 717 0646",
    "sg:postcode":"86305",
    "sg:province":"AZ",
    "sg:tags":[
        "waterproofing",
        "contractor"
    ],
    "wof:name":"M D Development",
    "wof:placetype":"venue"
},
  "geometry": {"coordinates":[-112.526537,34.681709],"type":"Point"}
}