{
  "type": "Feature",
  "properties": {
    "iso:country":"US",
    "sg:address":"525 N Val Vista Dr",
    "sg:city":"Mesa",
    "sg:classifiers":[
        {
            "category":"Shopping",
            "subcategory":"Computers & Home Electronics",
            "type":"Retail Goods"
        }
    ],
    "sg:phone":"+1 480 964 3986",
    "sg:postcode":"85213",
    "sg:province":"AZ",
    "sg:tags":[
        "publishing"
    ],
    "wof:name":"Grade A Desktop Svcs",
    "wof:placetype":"venue"
},
  "geometry": {"coordinates":[-111.753547,33.425107],"type":"Point"}
}