{
  "type": "Feature",
  "properties": {
    "iso:country":"US",
    "sg:address":"1201 E 16th St",
    "sg:city":"Douglas",
    "sg:classifiers":[
        {
            "category":"Social Services",
            "subcategory":"Child Care",
            "type":"Services"
        }
    ],
    "sg:phone":"+1 520 364 5642",
    "sg:postcode":"85607",
    "sg:province":"AZ",
    "sg:tags":[
        "kindergarten",
        "academic",
        "school"
    ],
    "wof:name":"Bonita Head Start",
    "wof:placetype":"venue"
},
  "geometry": {"coordinates":[-109.543972,31.350597],"type":"Point"}
}