{
  "type": "Feature",
  "properties": {
    "iso:country":"US",
    "sg:address":"796 Myer Dr",
    "sg:city":"Sierra Vista",
    "sg:classifiers":[
        {
            "category":"Retail",
            "subcategory":"Auto Repair",
            "type":"Services"
        }
    ],
    "sg:phone":"+1 520 417 2505",
    "sg:postcode":"85635",
    "sg:province":"AZ",
    "sg:tags":[
        "repairing",
        "automobile"
    ],
    "wof:name":"Auto Logic",
    "wof:placetype":"venue"
},
  "geometry": {"coordinates":[-110.29168300000001,31.551348],"type":"Point"}
}