{
  "type": "Feature",
  "properties": {
    "iso:country":"US",
    "sg:address":"6111 W Bell Rd",
    "sg:city":"Glendale",
    "sg:phone":"+1 602 547 1998",
    "sg:postcode":"85308",
    "sg:province":"AZ",
    "sg:website":"http://www.jiffylube.com",
    "wof:name":"Jiffy Lube",
    "wof:placetype":"venue"
},
  "geometry": {"coordinates":[-112.19103800000001,33.638558],"type":"Point"}
}