{
  "type": "Feature",
  "properties": {
    "iso:country":"US",
    "sg:address":"2595 E Broken Rock Dr",
    "sg:city":"Oro Valley",
    "sg:classifiers":[
        {
            "category":"Personal",
            "subcategory":"Beauty Salon",
            "type":"Services"
        }
    ],
    "sg:phone":"+1 520 797 3572",
    "sg:postcode":"85737",
    "sg:province":"AZ",
    "sg:tags":[
        "treatment",
        "skin"
    ],
    "wof:name":"Nu Skin Independent Distr",
    "wof:placetype":"venue"
},
  "geometry": {"coordinates":[-110.93480700000001,32.411979],"type":"Point"}
}