{
  "type": "Feature",
  "properties": {
    "addr:full":"2619 N Stone Ave Tucson AZ 85705",
    "addr:housenumber":"2619",
    "addr:postcode":"85705",
    "addr:street":"N Stone Ave",
    "iso:country":"US",
    "sg:address":"2619 N Stone Ave",
    "sg:city":"Tucson",
    "sg:classifiers":[
        {
            "category":"Home & Garden",
            "subcategory":"Hardware",
            "type":"Retail Goods"
        }
    ],
    "sg:phone":"+1 520 623 5481",
    "sg:postcode":"85705",
    "sg:province":"AZ",
    "sg:tags":[
        "material"
    ],
    "wof:name":"Bimsco True Value Hardware",
    "wof:placetype":"venue"
},
  "geometry": {"coordinates":[-110.972039,32.255455],"type":"Point"}
}