{
  "type": "Feature",
  "properties": {
    "iso:country":"US",
    "sg:address":"3772 E Grant Rd",
    "sg:city":"Tucson",
    "sg:classifiers":[
        {
            "category":"Home & Garden",
            "subcategory":"Home Furnishings",
            "type":"Retail Goods"
        }
    ],
    "sg:phone":"+1 520 323 7838",
    "sg:postcode":"85716",
    "sg:province":"AZ",
    "sg:tags":[
        "lamp",
        "shades"
    ],
    "wof:name":"A Natural Lamp & Shade",
    "wof:placetype":"venue"
},
  "geometry": {"coordinates":[-110.913121,32.250493],"type":"Point"}
}