{
  "type": "Feature",
  "properties": {
    "iso:country":"US",
    "sg:address":"1616 S Stapley Dr",
    "sg:city":"Mesa",
    "sg:classifiers":[
        {
            "category":"Building & Trades",
            "subcategory":"Locksmith",
            "type":"Services"
        }
    ],
    "sg:phone":"+1 866 270 2658",
    "sg:postcode":"85204",
    "sg:province":"AZ",
    "sg:tags":[
        "key"
    ],
    "wof:name":"A 24 Hour Emergency Locksmith",
    "wof:placetype":"venue"
},
  "geometry": {"coordinates":[-111.805809,33.385212],"type":"Point"}
}