{
  "type": "Feature",
  "properties": {
    "addr:full":"150 S 12th St Phoenix AZ 85034",
    "addr:housenumber":"150",
    "addr:postcode":"85034",
    "addr:street":"S 12Th St",
    "iso:country":"US",
    "sg:address":"150 S 12th St",
    "sg:city":"Phoenix",
    "sg:classifiers":[
        {
            "category":"Government",
            "subcategory":"Fire Station",
            "type":"Public Place"
        }
    ],
    "sg:phone":"+1 602 262 6771",
    "sg:postcode":"85034",
    "sg:province":"AZ",
    "sg:tags":[
        "department"
    ],
    "sg:website":"www.phoenix.gov/fire",
    "wof:name":"Phoenix Fire Prevention Div",
    "wof:placetype":"venue"
},
  "geometry": {"coordinates":[-112.056427,33.446043],"type":"Point"}
}