{
  "type": "Feature",
  "properties": {
    "iso:country":"US",
    "sg:address":"41 W Iron Ave",
    "sg:city":"Mesa",
    "sg:classifiers":[
        {
            "category":"Manufacturing",
            "subcategory":"Tools & Machinery",
            "type":"Manufacturing & Wholesale Goods"
        },
        {
            "category":"Retail",
            "subcategory":"Auto Repair",
            "type":"Services"
        }
    ],
    "sg:phone":"+1 480 633 5301",
    "sg:postcode":"85210",
    "sg:province":"AZ",
    "sg:tags":[
        "shop",
        "automobile",
        "machine",
        "machinery-rebuild"
    ],
    "sg:website":"http://www.empire-cat.com",
    "wof:name":"Caterpillar",
    "wof:placetype":"venue"
},
  "geometry": {"coordinates":[-111.833202,33.383998],"type":"Point"}
}