{
  "type": "Feature",
  "properties": {
    "addr:full":"2721 W Shannon Ct Chandler AZ 85224",
    "addr:housenumber":"2721",
    "addr:postcode":"85224",
    "addr:street":"W Shannon Ct",
    "iso:country":"US",
    "sg:address":"2721 W Shannon Ct",
    "sg:city":"Chandler",
    "sg:classifiers":[
        {
            "category":"Banks & Credit Unions",
            "subcategory":"Bank",
            "type":"Services"
        }
    ],
    "sg:phone":"+1 480 593 7000",
    "sg:postcode":"85224",
    "sg:province":"AZ",
    "sg:tags":[
        "finance"
    ],
    "wof:name":"Startup Capital Inc",
    "wof:placetype":"venue"
},
  "geometry": {"coordinates":[-111.889062,33.318544],"type":"Point"}
}