{
  "type": "Feature",
  "properties": {
    "iso:country":"US",
    "sg:address":"1952 E Greentree Dr",
    "sg:city":"Tempe",
    "sg:classifiers":[
        {
            "category":"Building & Trades",
            "subcategory":"Landscaping Services",
            "type":"Services"
        }
    ],
    "sg:phone":"+1 480 818 3313",
    "sg:postcode":"85284",
    "sg:province":"AZ",
    "sg:tags":[
        "gardener"
    ],
    "wof:name":"Greenpro",
    "wof:placetype":"venue"
},
  "geometry": {"coordinates":[-111.905986,33.332082],"type":"Point"}
}