{
  "type": "Feature",
  "properties": {
    "iso:country":"US",
    "sg:address":"3238 N 16th St",
    "sg:city":"Phoenix",
    "sg:classifiers":[
        {
            "category":"Health Services",
            "subcategory":"Nursing And Care Facility",
            "type":"Services"
        }
    ],
    "sg:phone":"+1 602 279 5866",
    "sg:postcode":"85016",
    "sg:province":"AZ",
    "sg:tags":[
        "hospice"
    ],
    "wof:name":"Hospice Of The Valley",
    "wof:placetype":"venue"
},
  "geometry": {"coordinates":[-112.047725,33.484088],"type":"Point"}
}