{
  "type": "Feature",
  "properties": {
    "addr:full":"6373 E Tanque Verde Rd Tucson AZ 85715",
    "addr:housenumber":"6373",
    "addr:postcode":"85715",
    "addr:street":"E Tanque Verde Rd",
    "iso:country":"US",
    "sg:address":"6373 E Tanque Verde Rd",
    "sg:city":"Tucson",
    "sg:classifiers":[
        {
            "category":"Professional",
            "subcategory":"Employment Agencies",
            "type":"Services"
        }
    ],
    "sg:phone":"+1 520 308 6635",
    "sg:postcode":"85715",
    "sg:province":"AZ",
    "sg:tags":[
        "temporary",
        "contractor"
    ],
    "sg:website":"http://tucson.citysearch.com/profile/external/45674249/tucson_az/manpower.html?publisher=yellowpages&reference_id=1&placement=ypwebsitemip",
    "wof:name":"Manpower",
    "wof:placetype":"venue"
},
  "geometry": {"coordinates":[-110.856978,32.243645],"type":"Point"}
}