{
  "type": "Feature",
  "properties": {
    "iso:country":"US",
    "sg:address":"1301 W Arizona Ave Ste 5",
    "sg:city":"Parker",
    "sg:classifiers":[
        {
            "category":"Building & Trades",
            "subcategory":"Pest Control",
            "type":"Services"
        }
    ],
    "sg:phone":"+1 928 669 9444",
    "sg:postcode":"85344",
    "sg:province":"AZ",
    "sg:tags":[
        "mothproofing"
    ],
    "wof:name":"La Paz Pest Control",
    "wof:placetype":"venue"
},
  "geometry": {"coordinates":[-114.292267,34.145321],"type":"Point"}
}