{
  "type": "Feature",
  "properties": {
    "iso:country":"US",
    "sg:address":"327 S 15th St",
    "sg:city":"Cottonwood",
    "sg:classifiers":[
        {
            "category":"Education",
            "subcategory":"School",
            "type":"Public Place"
        }
    ],
    "sg:phone":"+1 928 634 3722",
    "sg:postcode":"86326",
    "sg:province":"AZ",
    "wof:name":"Arizona Upgrade Academy",
    "wof:placetype":"venue"
},
  "geometry": {"coordinates":[-112.01093400000001,34.733472],"type":"Point"}
}