{
  "type": "Feature",
  "properties": {
    "iso:country":"US",
    "sg:address":"920 S Warren Ave",
    "sg:city":"Tucson",
    "sg:classifiers":[
        {
            "category":"Recreation",
            "type":"Entertainment"
        }
    ],
    "sg:phone":"+1 520 440 4264",
    "sg:postcode":"85719",
    "sg:province":"AZ",
    "sg:tags":[
        "martial",
        "arts",
        "instruction"
    ],
    "wof:name":"Debrazil Jiu-Jitsu Academy",
    "wof:placetype":"venue"
},
  "geometry": {"coordinates":[-110.946271,32.210643],"type":"Point"}
}