{
  "type": "Feature",
  "properties": {
    "iso:country":"US",
    "sg:address":"6161 E Speedway Blvd",
    "sg:city":"Tucson",
    "sg:classifiers":[
        {
            "category":"Personal",
            "type":"Services"
        }
    ],
    "sg:phone":"+1 520 296 8448",
    "sg:postcode":"85712",
    "sg:province":"AZ",
    "sg:tags":[
        "electrolysis"
    ],
    "wof:name":"Academy Electrolysis",
    "wof:placetype":"venue"
},
  "geometry": {"coordinates":[-110.861367,32.236185],"type":"Point"}
}