{
  "type": "Feature",
  "properties": {
    "iso:country":"US",
    "sg:address":"120 E Watkins St",
    "sg:city":"Phoenix",
    "sg:classifiers":[
        {
            "category":"Manufacturing",
            "subcategory":"Metals",
            "type":"Manufacturing & Wholesale Goods"
        }
    ],
    "sg:phone":"+1 602 484 0191",
    "sg:postcode":"85004",
    "sg:province":"AZ",
    "sg:tags":[
        "installs",
        "windows"
    ],
    "wof:name":"Atrium Door & Window",
    "wof:placetype":"venue"
},
  "geometry": {"coordinates":[-112.07149,33.425915],"type":"Point"}
}