{
  "type": "Feature",
  "properties": {
    "addr:full":"2100 S 4th Ave Yuma AZ 85364",
    "addr:housenumber":"2100",
    "addr:postcode":"85364",
    "addr:street":"S 4Th Ave",
    "iso:country":"US",
    "sg:address":"2100 S 4th Ave",
    "sg:city":"Yuma",
    "sg:classifiers":[
        {
            "category":"Restaurant",
            "type":"Food & Drink"
        }
    ],
    "sg:phone":"+1 928 329 1672",
    "sg:postcode":"85364",
    "sg:province":"AZ",
    "sg:tags":[
        "chinese"
    ],
    "wof:name":"Tai San Restaurant",
    "wof:placetype":"venue"
},
  "geometry": {"coordinates":[-114.62462600000001,32.689307],"type":"Point"}
}