{
  "type": "Feature",
  "properties": {
    "iso:country":"US",
    "sg:address":"1359 E Butler Ave",
    "sg:city":"Flagstaff",
    "sg:classifiers":[
        {
            "category":"Wholesale",
            "subcategory":"Machinery & Supplies",
            "type":"Manufacturing & Wholesale Goods"
        }
    ],
    "sg:phone":"+1 928 779 3676",
    "sg:postcode":"86001",
    "sg:province":"AZ",
    "sg:tags":[
        "equipment",
        "industrial"
    ],
    "wof:name":"Applied Industrial Tech Inc",
    "wof:placetype":"venue"
},
  "geometry": {"coordinates":[-111.634109,35.191445],"type":"Point"}
}