{
  "type": "Feature",
  "properties": {
    "iso:country":"US",
    "sg:address":"694 Rio Mesa Trl",
    "sg:city":"Cottonwood",
    "sg:classifiers":[
        {
            "category":"Building & Trades",
            "subcategory":"Landscaping Services",
            "type":"Services"
        }
    ],
    "sg:phone":"+1 928 634 5152",
    "sg:postcode":"86326",
    "sg:province":"AZ",
    "sg:tags":[
        "tree"
    ],
    "wof:name":"Cottonwood Tree Svc",
    "wof:placetype":"venue"
},
  "geometry": {"coordinates":[-112.018372,34.706968],"type":"Point"}
}