{
  "type": "Feature",
  "properties": {
    "iso:country":"US",
    "sg:address":"6250 E Grant Rd",
    "sg:city":"Tucson",
    "sg:classifiers":[
        {
            "category":"Banks & Credit Unions",
            "subcategory":"Financial Services",
            "type":"Services"
        }
    ],
    "sg:phone":"+1 520 296 3570",
    "sg:postcode":"85712",
    "sg:province":"AZ",
    "sg:tags":[
        "trust",
        "management"
    ],
    "wof:name":"Grainger Family Revocable Tr",
    "wof:placetype":"venue"
},
  "geometry": {"coordinates":[-110.860351,32.250565],"type":"Point"}
}