{
  "type": "Feature",
  "properties": {
    "iso:country":"US",
    "sg:address":"856 E Main St",
    "sg:city":"Mesa",
    "sg:classifiers":[
        {
            "category":"Manufacturing",
            "subcategory":"Printing",
            "type":"Manufacturing & Wholesale Goods"
        }
    ],
    "sg:phone":"+1 480 374 5461",
    "sg:postcode":"85203",
    "sg:province":"AZ",
    "sg:tags":[
        "commercial",
        "lithographic",
        "sign"
    ],
    "sg:website":"http://www.americopy.com",
    "wof:name":"Americopy",
    "wof:placetype":"venue"
},
  "geometry": {"coordinates":[-111.81284100000001,33.415175],"type":"Point"}
}