{
  "type": "Feature",
  "properties": {
    "iso:country":"US",
    "sg:address":"4333 N Civic Center Plz",
    "sg:city":"Scottsdale",
    "sg:classifiers":[
        {
            "category":"Banks & Credit Unions",
            "subcategory":"Investment Brokerage",
            "type":"Services"
        }
    ],
    "sg:phone":"+1 480 941 2005",
    "sg:postcode":"85251",
    "sg:province":"AZ",
    "wof:name":"Idaho Creek LLC",
    "wof:placetype":"venue"
},
  "geometry": {"coordinates":[-111.921293,33.501228],"type":"Point"}
}