{
  "type": "Feature",
  "properties": {
    "iso:country":"US",
    "sg:address":"1601 N 7th St",
    "sg:city":"Phoenix",
    "sg:classifiers":[
        {
            "category":"Professional",
            "subcategory":"Engineering",
            "type":"Services"
        }
    ],
    "sg:phone":"+1 602 253 8444",
    "sg:postcode":"85006",
    "sg:province":"AZ",
    "sg:tags":[
        "consulting",
        "engineer"
    ],
    "wof:name":"Earth Tech",
    "wof:placetype":"venue"
},
  "geometry": {"coordinates":[-112.065079,33.46571],"type":"Point"}
}