{
  "type": "Feature",
  "properties": {
    "iso:country":"US",
    "sg:address":"28231 N 68th St",
    "sg:city":"Cave Creek",
    "sg:classifiers":[
        {
            "category":"Shopping",
            "type":"Retail Goods"
        }
    ],
    "sg:phone":"+1 480 585 2377",
    "sg:postcode":"85331",
    "sg:province":"AZ",
    "sg:tags":[
        "installs",
        "hot",
        "bathtub",
        "tub",
        "whirlpool"
    ],
    "wof:name":"Whirl Bathe",
    "wof:placetype":"venue"
},
  "geometry": {"coordinates":[-111.934572,33.741353],"type":"Point"}
}