{
  "type": "Feature",
  "properties": {
    "iso:country":"US",
    "sg:address":"661 E 32nd St",
    "sg:city":"Yuma",
    "sg:classifiers":[
        {
            "category":"Insurance",
            "subcategory":"Insurance Agent",
            "type":"Services"
        }
    ],
    "sg:phone":"+1 928 344 0140",
    "sg:postcode":"85365",
    "sg:province":"AZ",
    "sg:tags":[
        "company"
    ],
    "wof:name":"Allstate",
    "wof:placetype":"venue"
},
  "geometry": {"coordinates":[-114.613685,32.669352],"type":"Point"}
}