{
  "type": "Feature",
  "properties": {
    "addr:full":"50 E Dunlap Ave Phoenix AZ 85020",
    "addr:housenumber":"50",
    "addr:postcode":"85020",
    "addr:street":"E Dunlap Ave",
    "iso:country":"US",
    "sg:address":"50 E Dunlap Ave",
    "sg:city":"Phoenix",
    "sg:classifiers":[
        {
            "category":"Health Services",
            "subcategory":"Doctor",
            "type":"Services"
        }
    ],
    "sg:phone":"+1 623 487 3003",
    "sg:postcode":"85020",
    "sg:province":"AZ",
    "sg:tags":[
        "physician",
        "surgeon"
    ],
    "wof:name":"Keith Harr MD",
    "wof:placetype":"venue"
},
  "geometry": {"coordinates":[-112.073167,33.567819],"type":"Point"}
}