{
  "type": "Feature",
  "properties": {
    "iso:country":"US",
    "sg:address":"36602 N Lazy Ln",
    "sg:city":"Carefree",
    "sg:classifiers":[
        {
            "category":"Real Estate",
            "subcategory":"Architect",
            "type":"Services"
        }
    ],
    "sg:phone":"+1 480 488 6581",
    "sg:postcode":"85377",
    "sg:province":"AZ",
    "wof:name":"Allen F Tafoya Assoc Archs",
    "wof:placetype":"venue"
},
  "geometry": {"coordinates":[-111.921035,33.819336],"type":"Point"}
}