{
  "type": "Feature",
  "properties": {
    "addr:full":"379 N Mesa Dr Mesa AZ 85201",
    "addr:housenumber":"379",
    "addr:postcode":"85201",
    "addr:street":"N Mesa Dr",
    "iso:country":"US",
    "sg:address":"379 N Mesa Dr",
    "sg:city":"Mesa",
    "sg:classifiers":[
        {
            "category":"Recreation",
            "type":"Entertainment"
        },
        {
            "category":"Sports & Exercise",
            "subcategory":"Skate Park",
            "type":"Entertainment"
        }
    ],
    "sg:phone":"+1 866 337 3090",
    "sg:postcode":"85201",
    "sg:province":"AZ",
    "sg:tags":[
        "magician",
        "entertainers-family",
        "business"
    ],
    "wof:name":"Amazing Magicians of Philip & Henry U.S.A Inc.",
    "wof:placetype":"venue"
},
  "geometry": {"coordinates":[-111.82288800000001,33.422141],"type":"Point"}
}