{
  "type": "Feature",
  "properties": {
    "addr:full":"2532 N 22nd Dr Phoenix AZ 85009",
    "addr:housenumber":"2532",
    "addr:postcode":"85009",
    "addr:street":"N 22Nd Dr",
    "iso:country":"US",
    "sg:address":"2532 N 22nd Dr",
    "sg:city":"Phoenix",
    "sg:classifiers":[
        {
            "category":"Shopping",
            "subcategory":"Bicycles & Sporting Goods",
            "type":"Retail Goods"
        },
        {
            "category":"Parking",
            "subcategory":"Bicycle",
            "type":"Transportation"
        }
    ],
    "sg:phone":"+1 602 418 6956",
    "sg:postcode":"85009",
    "sg:province":"AZ",
    "sg:tags":[
        "shop",
        "security",
        "system",
        "rack"
    ],
    "wof:name":"Girlz Bike Wear",
    "wof:placetype":"venue"
},
  "geometry": {"coordinates":[-112.10744,33.476634],"type":"Point"}
}