{
  "type": "Feature",
  "properties": {
    "addr:full":"15999 N Oracle Rd Tucson AZ 85739",
    "addr:housenumber":"15999",
    "addr:postcode":"85739",
    "addr:street":"N Oracle Rd",
    "iso:country":"US",
    "sg:address":"15999 N Oracle Rd",
    "sg:city":"Tucson",
    "sg:classifiers":[
        {
            "category":"Retail",
            "subcategory":"Pet Boarding",
            "type":"Services"
        }
    ],
    "sg:phone":"+1 520 825 3211",
    "sg:postcode":"85739",
    "sg:province":"AZ",
    "sg:tags":[
        "boarding/pet",
        "sitting"
    ],
    "wof:name":"Mesquite Veterinary Hospital",
    "wof:placetype":"venue"
},
  "geometry": {"coordinates":[-110.92600299999999,32.495998],"type":"Point"}
}