{
  "type": "Feature",
  "properties": {
    "iso:country":"US",
    "sg:address":"2205 E Speedway Blvd",
    "sg:city":"Tucson",
    "sg:classifiers":[
        {
            "category":"Professional",
            "subcategory":"Lawyer & Legal Services",
            "type":"Services"
        }
    ],
    "sg:phone":"+1 520 321 0424",
    "sg:postcode":"85719",
    "sg:province":"AZ",
    "sg:tags":[
        "attorney"
    ],
    "wof:name":"Konigsberg Law Office PLLC",
    "wof:placetype":"venue"
},
  "geometry": {"coordinates":[-110.938191,32.236135],"type":"Point"}
}