{
  "type": "Feature",
  "properties": {
    "iso:country":"US",
    "sg:address":"114 US Hwy 66",
    "sg:city":"Flagstaff",
    "sg:classifiers":[
        {
            "category":"Banks & Credit Unions",
            "subcategory":"Bank",
            "type":"Services"
        }
    ],
    "sg:phone":"+1 928 774 7927",
    "sg:postcode":"86001",
    "sg:province":"AZ",
    "sg:tags":[
        "loan"
    ],
    "wof:name":"Community Loans Of America",
    "wof:placetype":"venue"
},
  "geometry": {"coordinates":[-111.653982,35.197677],"type":"Point"}
}