{
  "type": "Feature",
  "properties": {
    "iso:country":"US",
    "sg:address":"1501 W Van Buren St",
    "sg:city":"Phoenix",
    "sg:classifiers":[
        {
            "category":"Autos & Motor Vehicles",
            "subcategory":"Automobile Sales",
            "type":"Retail Goods"
        }
    ],
    "sg:phone":"+1 602 528 3491",
    "sg:postcode":"85007",
    "sg:province":"AZ",
    "sg:tags":[
        "used",
        "car",
        "dealers-used",
        "new",
        "cars-wholesale"
    ],
    "wof:name":"Arizona Motor Car",
    "wof:placetype":"venue"
},
  "geometry": {"coordinates":[-112.09131600000001,33.451359],"type":"Point"}
}