{
  "type": "Feature",
  "properties": {
    "iso:country":"US",
    "sg:address":"6780 W Deer Valley Rd",
    "sg:city":"Glendale",
    "sg:classifiers":[
        {
            "category":"Education",
            "subcategory":"Dance Studio",
            "type":"Public Place"
        }
    ],
    "sg:phone":"+1 623 581 6049",
    "sg:postcode":"85310",
    "sg:province":"AZ",
    "sg:tags":[
        "instruction",
        "dancing"
    ],
    "wof:name":"Arizona Dance & Co",
    "wof:placetype":"venue"
},
  "geometry": {"coordinates":[-112.205237,33.681912],"type":"Point"}
}