{
  "type": "Feature",
  "properties": {
    "iso:country":"US",
    "sg:address":"4722 N 24th St Ste 300",
    "sg:city":"Phoenix",
    "sg:classifiers":[
        {
            "category":"Professional",
            "subcategory":"Computer Services",
            "type":"Services"
        },
        {
            "category":"Internet Cafe",
            "subcategory":"None",
            "type":"Food & Drink"
        }
    ],
    "sg:phone":"+1 602 230 1300",
    "sg:postcode":"85016",
    "sg:province":"AZ",
    "sg:tags":[
        "product",
        "software"
    ],
    "sg:website":"http://www.rainbowstudios.com",
    "wof:name":"Rainbow Studios",
    "wof:placetype":"venue"
},
  "geometry": {"coordinates":[-112.030242,33.506446],"type":"Point"}
}