{
  "type": "Feature",
  "properties": {
    "addr:full":"2269 E Desert Cove Ave Phoenix AZ 85028",
    "addr:housenumber":"2269",
    "addr:postcode":"85028",
    "addr:street":"E Desert Cove Ave",
    "iso:country":"US",
    "sg:address":"2269 E Desert Cove Ave",
    "sg:city":"Phoenix",
    "sg:classifiers":[
        {
            "category":"Wholesale",
            "subcategory":"Machinery & Supplies",
            "type":"Manufacturing & Wholesale Goods"
        }
    ],
    "sg:phone":"+1 602 795 3494",
    "sg:postcode":"85028",
    "sg:province":"AZ",
    "sg:tags":[
        "equipment",
        "establishment"
    ],
    "wof:name":"Star One Concept Inc",
    "wof:placetype":"venue"
},
  "geometry": {"coordinates":[-112.034139,33.58684],"type":"Point"}
}