{
  "type": "Feature",
  "properties": {
    "addr:full":"23006 N 19th Way Phoenix AZ 85024",
    "addr:housenumber":"23006",
    "addr:postcode":"85024",
    "addr:street":"N 19Th Way",
    "iso:country":"US",
    "sg:address":"23006 N 19th Way",
    "sg:city":"Phoenix",
    "sg:classifiers":[
        {
            "category":"Manufacturing",
            "subcategory":"Tools & Machinery",
            "type":"Manufacturing & Wholesale Goods"
        },
        {
            "category":"Manufacturing",
            "subcategory":"Electronics",
            "type":"Manufacturing & Wholesale Goods"
        },
        {
            "category":"Shopping",
            "subcategory":"Computers & Home Electronics",
            "type":"Retail Goods"
        }
    ],
    "sg:phone":"+1 623 936 6876",
    "sg:postcode":"85024",
    "sg:province":"AZ",
    "sg:tags":[
        "electric",
        "consumer",
        "equipment-testing",
        "equipment",
        "supplies-wholesale",
        "manufacturer"
    ],
    "wof:name":"Stampede Presentation Products Inc",
    "wof:placetype":"venue"
},
  "geometry": {"coordinates":[-112.04033,33.695259],"type":"Point"}
}