{
  "type": "Feature",
  "properties": {
    "iso:country":"US",
    "sg:address":"4920 E Julie Dr",
    "sg:city":"Prescott",
    "sg:classifiers":[
        {
            "category":"Manufacturing",
            "subcategory":"Signs",
            "type":"Manufacturing & Wholesale Goods"
        }
    ],
    "sg:phone":"+1 928 445 8002",
    "sg:postcode":"86301",
    "sg:province":"AZ",
    "sg:tags":[
        "specialty",
        "mfg"
    ],
    "sg:website":"www.studiouno.com",
    "wof:name":"Studio Uno",
    "wof:placetype":"venue"
},
  "geometry": {"coordinates":[-112.384081,34.560237],"type":"Point"}
}