{
  "type": "Feature",
  "properties": {
    "iso:country":"US",
    "sg:address":"1573 W Ajo Way",
    "sg:city":"Tucson",
    "sg:classifiers":[
        {
            "category":"Education",
            "subcategory":"School",
            "type":"Public Place"
        }
    ],
    "sg:phone":"+1 520 908 4000",
    "sg:postcode":"85713",
    "sg:province":"AZ",
    "wof:name":"Lynn-Urquides School",
    "wof:placetype":"venue"
},
  "geometry": {"coordinates":[-110.996248,32.177791],"type":"Point"}
}