{
  "type": "Feature",
  "properties": {
    "addr:full":"1573 W Ajo Way Tucson AZ 85713",
    "addr:housenumber":"1573",
    "addr:postcode":"85713",
    "addr:street":"W Ajo Way",
    "iso:country":"US",
    "sg:address":"1573 W Ajo Way",
    "sg:city":"Tucson",
    "sg:classifiers":[
        {
            "category":"Education",
            "subcategory":"School",
            "type":"Public Place"
        }
    ],
    "sg:phone":"+1 520 908 4000",
    "sg:postcode":"85713",
    "sg:province":"AZ",
    "wof:name":"Lynn-Urquides School",
    "wof:placetype":"venue"
},
  "geometry": {"coordinates":[-110.99624799999999,32.177791],"type":"Point"}
}