{
  "type": "Feature",
  "properties": {
    "addr:full":"7763 E Florentine Rd Prescott Valley AZ 86314",
    "addr:housenumber":"7763",
    "addr:postcode":"86314",
    "addr:street":"E Florentine Rd",
    "iso:country":"US",
    "sg:address":"7763 E Florentine Rd",
    "sg:city":"Prescott Valley",
    "sg:classifiers":[
        {
            "category":"Health Services",
            "subcategory":"Doctor",
            "type":"Services"
        }
    ],
    "sg:phone":"+1 928 759 2200",
    "sg:postcode":"86314",
    "sg:province":"AZ",
    "sg:tags":[
        "clinic"
    ],
    "wof:name":"FMC Dialysis Ctr",
    "wof:placetype":"venue"
},
  "geometry": {"coordinates":[-112.329697,34.588032],"type":"Point"}
}