{
  "type": "Feature",
  "properties": {
    "addr:full":"1815 E Oasis Dr Tempe AZ 85283",
    "addr:housenumber":"1815",
    "addr:postcode":"85283",
    "addr:street":"E Oasis Dr",
    "iso:country":"US",
    "sg:address":"1815 E Oasis Dr",
    "sg:city":"Tempe",
    "sg:classifiers":[
        {
            "category":"Shopping",
            "subcategory":"Bicycles & Sporting Goods",
            "type":"Retail Goods"
        }
    ],
    "sg:phone":"+1 480 897 4600",
    "sg:postcode":"85283",
    "sg:province":"AZ",
    "sg:tags":[
        "equipment",
        "golf",
        "supply"
    ],
    "wof:name":"Aquasonics Inc",
    "wof:placetype":"venue"
},
  "geometry": {"coordinates":[-111.91050799999999,33.351593],"type":"Point"}
}