{
  "type": "Feature",
  "properties": {
    "iso:country":"US",
    "sg:address":"16446 E Tombstone Ave",
    "sg:city":"Fountain Hills",
    "sg:classifiers":[
        {
            "category":"Professional",
            "subcategory":"Advertising",
            "type":"Services"
        }
    ],
    "sg:phone":"+1 480 837 2184",
    "sg:postcode":"85268",
    "sg:province":"AZ",
    "sg:tags":[
        "mailing",
        "list"
    ],
    "sg:website":"www.sportsmailinglists.com",
    "wof:name":"Sports Marketing",
    "wof:placetype":"venue"
},
  "geometry": {"coordinates":[-111.729005,33.572917],"type":"Point"}
}