{
  "type": "Feature",
  "properties": {
    "addr:full":"1425 N 1st St Phoenix AZ 85004",
    "addr:housenumber":"1425",
    "addr:postcode":"85004",
    "addr:street":"N 1St St",
    "iso:country":"US",
    "sg:address":"1425 N 1st St",
    "sg:city":"Phoenix",
    "sg:classifiers":[
        {
            "category":"Professional",
            "subcategory":"Art Services",
            "type":"Services"
        },
        {
            "category":"Professional",
            "subcategory":"Business Services",
            "type":"Services"
        }
    ],
    "sg:phone":"+1 602 258 0176",
    "sg:postcode":"85004",
    "sg:province":"AZ",
    "sg:tags":[
        "development",
        "product",
        "graphic",
        "designers-industrial",
        "marketing",
        "commercial",
        "designer",
        "design"
    ],
    "wof:name":"Lulham Black Design Group",
    "wof:placetype":"venue"
},
  "geometry": {"coordinates":[-112.072453,33.464393],"type":"Point"}
}