{
  "type": "Feature",
  "properties": {
    "iso:country":"US",
    "sg:address":"3283 S 12th Ave",
    "sg:city":"Safford",
    "sg:classifiers":[
        {
            "category":"Utilities",
            "type":"Services"
        }
    ],
    "sg:phone":"+1 928 428 6131",
    "sg:postcode":"85546",
    "sg:province":"AZ",
    "wof:name":"Professional Maintenance Services",
    "wof:placetype":"venue"
},
  "geometry": {"coordinates":[-109.722042,32.77788],"type":"Point"}
}