{
  "type": "Feature",
  "properties": {
    "iso:country":"US",
    "sg:address":"2333 E Thomas Rd",
    "sg:city":"Phoenix",
    "sg:classifiers":[
        {
            "category":"Shopping",
            "subcategory":"Gifts & Souvenirs",
            "type":"Retail Goods"
        }
    ],
    "sg:phone":"+1 602 468 9728",
    "sg:postcode":"85016",
    "sg:province":"AZ",
    "sg:tags":[
        "shop"
    ],
    "wof:name":"Berdon's Too",
    "wof:placetype":"venue"
},
  "geometry": {"coordinates":[-112.03232,33.480222],"type":"Point"}
}