{
  "type": "Feature",
  "properties": {
    "iso:country":"US",
    "sg:address":"2418 S 6th Ave",
    "sg:city":"Phoenix",
    "sg:classifiers":[
        {
            "category":"Home & Garden",
            "subcategory":"Building Materials",
            "type":"Retail Goods"
        }
    ],
    "sg:phone":"+1 602 251 3941",
    "sg:postcode":"85003",
    "sg:province":"AZ",
    "sg:tags":[
        "shutter"
    ],
    "wof:name":"Skyline Shutters",
    "wof:placetype":"venue"
},
  "geometry": {"coordinates":[-112.081311,33.425593],"type":"Point"}
}