{
  "type": "Feature",
  "properties": {
    "addr:full":"1841 S Horne Mesa AZ 85204",
    "addr:housenumber":"1841",
    "addr:postcode":"85204",
    "addr:street":"S Horne",
    "iso:country":"US",
    "sg:address":"1841 S Horne",
    "sg:city":"Mesa",
    "sg:classifiers":[
        {
            "category":"Building & Trades",
            "subcategory":"Construction",
            "type":"Services"
        }
    ],
    "sg:phone":"+1 480 736 0659",
    "sg:postcode":"85204",
    "sg:province":"AZ",
    "sg:tags":[
        "dry wall",
        "contractor"
    ],
    "wof:name":"Pinnacle Drywall Corp",
    "wof:placetype":"venue"
},
  "geometry": {"coordinates":[-111.814178,33.383321],"type":"Point"}
}