{
  "type": "Feature",
  "properties": {
    "addr:full":"231 N Harris Dr Mesa AZ 85203",
    "addr:housenumber":"231",
    "addr:postcode":"85203",
    "addr:street":"N Harris Dr",
    "iso:country":"US",
    "sg:address":"231 N Harris Dr",
    "sg:city":"Mesa",
    "sg:classifiers":[
        {
            "category":"Retail",
            "subcategory":"Repair Shop",
            "type":"Services"
        }
    ],
    "sg:phone":"+1 480 464 2665",
    "sg:postcode":"85203",
    "sg:province":"AZ",
    "sg:tags":[
        "equipment",
        "conditioning",
        "air"
    ],
    "wof:name":"Evan's Air Conditioning & Heat",
    "wof:placetype":"venue"
},
  "geometry": {"coordinates":[-111.79609000000001,33.422381],"type":"Point"}
}