{
  "type": "Feature",
  "properties": {
    "iso:country":"US",
    "sg:address":"5255 E Williams Cir",
    "sg:city":"Tucson",
    "sg:classifiers":[
        {
            "category":"Banks & Credit Unions",
            "subcategory":"Bank",
            "type":"Services"
        }
    ],
    "sg:phone":"+1 520 750 8888",
    "sg:postcode":"85711",
    "sg:province":"AZ",
    "sg:tags":[
        "loan",
        "real estate"
    ],
    "sg:website":"www.lancedickson.com",
    "wof:name":"Nova Home Loans",
    "wof:placetype":"venue"
},
  "geometry": {"coordinates":[-110.880532,32.22059],"type":"Point"}
}