{
  "type": "Feature",
  "properties": {
    "iso:country":"US",
    "sg:address":"20908 W Durango St",
    "sg:city":"Buckeye",
    "sg:classifiers":[
        {
            "category":"Retail",
            "subcategory":"Animal Services",
            "type":"Services"
        }
    ],
    "sg:phone":"+1 623 386 2928",
    "sg:postcode":"85326",
    "sg:province":"AZ",
    "wof:name":"Command Performance Arabians",
    "wof:placetype":"venue"
},
  "geometry": {"coordinates":[-112.499243,33.42848],"type":"Point"}
}