{
  "type": "Feature",
  "properties": {
    "addr:full":"20908 W Durango St Buckeye AZ 85326",
    "addr:housenumber":"20908",
    "addr:postcode":"85326",
    "addr:street":"W Durango St",
    "iso:country":"US",
    "sg:address":"20908 W Durango St",
    "sg:city":"Buckeye",
    "sg:classifiers":[
        {
            "category":"Retail",
            "subcategory":"Animal Services",
            "type":"Services"
        }
    ],
    "sg:phone":"+1 623 386 2928",
    "sg:postcode":"85326",
    "sg:province":"AZ",
    "wof:name":"Command Performance Arabians",
    "wof:placetype":"venue"
},
  "geometry": {"coordinates":[-112.49924300000001,33.42848],"type":"Point"}
}