{
  "type": "Feature",
  "properties": {
    "iso:country":"US",
    "sg:address":"3815 N 3rd St",
    "sg:city":"Phoenix",
    "sg:classifiers":[
        {
            "category":"Manufacturing",
            "subcategory":"Printing",
            "type":"Manufacturing & Wholesale Goods"
        }
    ],
    "sg:phone":"+1 602 266 0550",
    "sg:postcode":"85012",
    "sg:province":"AZ",
    "sg:tags":[
        "publisher",
        "magazine"
    ],
    "sg:website":"http://www.echomag.com",
    "wof:name":"Echo Magazine",
    "wof:placetype":"venue"
},
  "geometry": {"coordinates":[-112.06941999999999,33.49168],"type":"Point"}
}