{
  "type": "Feature",
  "properties": {
    "addr:full":"5009 E Elliot Rd Phoenix AZ 85044",
    "addr:housenumber":"5009",
    "addr:postcode":"85044",
    "addr:street":"E Elliot Rd",
    "iso:country":"US",
    "sg:address":"5009 E Elliot Rd",
    "sg:city":"Phoenix",
    "sg:classifiers":[
        {
            "category":"Retail",
            "subcategory":"Laundry & Dry Cleaning",
            "type":"Services"
        }
    ],
    "sg:phone":"+1 480 893 9637",
    "sg:postcode":"85044",
    "sg:province":"AZ",
    "sg:tags":[
        "cleaners"
    ],
    "wof:name":"Ahwatukee Cleaners",
    "wof:placetype":"venue"
},
  "geometry": {"coordinates":[-111.976913,33.349057],"type":"Point"}
}