{
  "type": "Feature",
  "properties": {
    "iso:country":"US",
    "sg:address":"320 E Mcdowell Rd Ste 221",
    "sg:city":"Phoenix",
    "sg:classifiers":[
        {
            "category":"Sports & Exercise",
            "subcategory":"Sports Center",
            "type":"Entertainment"
        }
    ],
    "sg:phone":"+1 602 514 8300",
    "sg:postcode":"85004",
    "sg:province":"AZ",
    "sg:tags":[
        "club",
        "football"
    ],
    "wof:name":"Arizona Rattlers",
    "wof:placetype":"venue"
},
  "geometry": {"coordinates":[-112.068527,33.46571],"type":"Point"}
}