{
  "type": "Feature",
  "properties": {
    "iso:country":"US",
    "sg:address":"830 E Harmony Ave",
    "sg:city":"Mesa",
    "sg:classifiers":[
        {
            "category":"Retail",
            "subcategory":"Repair Shop",
            "type":"Services"
        }
    ],
    "sg:phone":"+1 480 251 5487",
    "sg:postcode":"85204",
    "sg:province":"AZ",
    "sg:tags":[
        "related"
    ],
    "wof:name":"LGB Repairs",
    "wof:placetype":"venue"
},
  "geometry": {"coordinates":[-111.8128,33.389294],"type":"Point"}
}