{
  "type": "Feature",
  "properties": {
    "iso:country":"US",
    "sg:address":"2715 W Northern Ave Ste 100",
    "sg:city":"Phoenix",
    "sg:classifiers":[
        {
            "category":"Health Services",
            "subcategory":"Dentist",
            "type":"Services"
        }
    ],
    "sg:phone":"+1 602 995 1440",
    "sg:postcode":"85051",
    "sg:province":"AZ",
    "sg:tags":[
        "dentists-orthodontists"
    ],
    "wof:name":"Mark K Mcalister Dds",
    "wof:placetype":"venue"
},
  "geometry": {"coordinates":[-112.118006,33.553059],"type":"Point"}
}