{
  "type": "Feature",
  "properties": {
    "iso:country":"US",
    "sg:address":"3056 W Main St",
    "sg:city":"Thatcher",
    "sg:classifiers":[
        {
            "category":"Health Services",
            "subcategory":"Chiropractor",
            "type":"Services"
        }
    ],
    "sg:phone":"+1 928 428 9355",
    "sg:postcode":"85552",
    "sg:province":"AZ",
    "wof:name":"Smith Chiropractic",
    "wof:placetype":"venue"
},
  "geometry": {"coordinates":[-109.751045,32.849085],"type":"Point"}
}