{
  "type": "Feature",
  "properties": {
    "iso:country":"US",
    "sg:address":"4008 W Indian School Rd",
    "sg:city":"Phoenix",
    "sg:classifiers":[
        {
            "category":"Autos & Motor Vehicles",
            "subcategory":"Auto Supplies",
            "type":"Retail Goods"
        }
    ],
    "sg:phone":"+1 602 278 2299",
    "sg:postcode":"85019",
    "sg:province":"AZ",
    "sg:tags":[
        "muffler",
        "system",
        "exhaust"
    ],
    "wof:name":"America Mfflrs Indian S",
    "wof:placetype":"venue"
},
  "geometry": {"coordinates":[-112.14526499999999,33.494968],"type":"Point"}
}