{
  "type": "Feature",
  "properties": {
    "iso:country":"US",
    "sg:address":"535 S Montezuma St",
    "sg:city":"Prescott",
    "sg:classifiers":[
        {
            "category":"Shopping",
            "subcategory":"Used Merchandise",
            "type":"Retail Goods"
        }
    ],
    "sg:phone":"+1 928 445 6007",
    "sg:postcode":"86303",
    "sg:province":"AZ",
    "sg:tags":[
        "new",
        "furniture"
    ],
    "wof:name":"Second Hand Man Inc",
    "wof:placetype":"venue"
},
  "geometry": {"coordinates":[-112.47031200000001,34.533552],"type":"Point"}
}