{
  "type": "Feature",
  "properties": {
    "addr:full":"2944 N Castro Ave Tucson AZ 85705",
    "addr:housenumber":"2944",
    "addr:postcode":"85705",
    "addr:street":"N Castro Ave",
    "iso:country":"US",
    "sg:address":"2944 N Castro Ave",
    "sg:city":"Tucson",
    "sg:classifiers":[
        {
            "category":"Farming",
            "subcategory":"Nursery",
            "type":"Manufacturing & Wholesale Goods"
        }
    ],
    "sg:phone":"+1 520 882 0969",
    "sg:postcode":"85705",
    "sg:province":"AZ",
    "sg:tags":[
        "ornamental"
    ],
    "wof:name":"Coronado Heights Nursery",
    "wof:placetype":"venue"
},
  "geometry": {"coordinates":[-110.974108,32.260402],"type":"Point"}
}