{
  "type": "Feature",
  "properties": {
    "iso:country":"US",
    "sg:address":"6725 E Tanque Verde Rd",
    "sg:city":"Tucson",
    "sg:classifiers":[
        {
            "category":"Home & Garden",
            "subcategory":"Furniture",
            "type":"Retail Goods"
        }
    ],
    "sg:phone":"+1 520 327 6466",
    "sg:postcode":"85715",
    "sg:province":"AZ",
    "sg:website":"www.homeontherangeaz.com",
    "wof:name":"Home On The Range",
    "wof:placetype":"venue"
},
  "geometry": {"coordinates":[-110.84973,32.248292],"type":"Point"}
}