{
  "type": "Feature",
  "properties": {
    "addr:full":"17045 N 29th Ave Phoenix AZ 85053",
    "addr:housenumber":"17045",
    "addr:postcode":"85053",
    "addr:street":"N 29Th Ave",
    "iso:country":"US",
    "sg:address":"17045 N 29th Ave",
    "sg:city":"Phoenix",
    "sg:classifiers":[
        {
            "category":"Recreation",
            "type":"Entertainment"
        }
    ],
    "sg:phone":"+1 602 803 1146",
    "sg:postcode":"85053",
    "sg:province":"AZ",
    "sg:tags":[
        "martial",
        "arts",
        "instruction"
    ],
    "wof:name":"Kodenkan Of Phoenix",
    "wof:placetype":"venue"
},
  "geometry": {"coordinates":[-112.121774,33.640879],"type":"Point"}
}