{
  "type": "Feature",
  "properties": {
    "addr:full":"7317 E 6th Ave Scottsdale AZ 85251",
    "addr:housenumber":"7317",
    "addr:postcode":"85251",
    "addr:street":"E 6Th Ave",
    "iso:country":"US",
    "sg:address":"7317 E 6th Ave",
    "sg:city":"Scottsdale",
    "sg:classifiers":[
        {
            "category":"Health Services",
            "subcategory":"Medical Lab",
            "type":"Services"
        }
    ],
    "sg:phone":"+1 480 994 3888",
    "sg:postcode":"85251",
    "sg:province":"AZ",
    "sg:tags":[
        "laboratory"
    ],
    "wof:name":"LA Boca Ceramic Studio",
    "wof:placetype":"venue"
},
  "geometry": {"coordinates":[-111.923293,33.498854],"type":"Point"}
}