{
  "type": "Feature",
  "properties": {
    "addr:full":"2742 E Croyden St Tucson AZ 85716",
    "addr:housenumber":"2742",
    "addr:postcode":"85716",
    "addr:street":"E Croyden St",
    "iso:country":"US",
    "sg:address":"2742 E Croyden St",
    "sg:city":"Tucson",
    "sg:classifiers":[
        {
            "category":"Building & Trades",
            "subcategory":"Construction",
            "type":"Services"
        }
    ],
    "sg:phone":"+1 520 624 3936",
    "sg:postcode":"85716",
    "sg:province":"AZ",
    "sg:tags":[
        "home",
        "improvement"
    ],
    "wof:name":"AAA Arizona Home Improvement",
    "wof:placetype":"venue"
},
  "geometry": {"coordinates":[-110.930024,32.217351],"type":"Point"}
}