{
  "type": "Feature",
  "properties": {
    "iso:country":"US",
    "sg:address":"4802 E Ray Rd Ste 23-234",
    "sg:city":"Phoenix",
    "sg:classifiers":[
        {
            "category":"Retail",
            "subcategory":"Repair Shop",
            "type":"Services"
        }
    ],
    "sg:phone":"+1 480 510 3195",
    "sg:postcode":"85044",
    "sg:province":"AZ",
    "sg:tags":[
        "dishwasher"
    ],
    "wof:name":"ACA Appliance Services",
    "wof:placetype":"venue"
},
  "geometry": {"coordinates":[-111.980334,33.319901],"type":"Point"}
}