{
  "type": "Feature",
  "properties": {
    "iso:country":"US",
    "sg:address":"2705 N 24th St",
    "sg:city":"Phoenix",
    "sg:classifiers":[
        {
            "category":"Manufacturing",
            "subcategory":"Printing",
            "type":"Manufacturing & Wholesale Goods"
        }
    ],
    "sg:phone":"+1 602 955 8450",
    "sg:postcode":"85008",
    "sg:province":"AZ",
    "sg:tags":[
        "lithographic",
        "screen",
        "commercial"
    ],
    "wof:name":"Joe Burdar Screen Print & Sgns",
    "wof:placetype":"venue"
},
  "geometry": {"coordinates":[-112.03010500000001,33.479337],"type":"Point"}
}