{
  "type": "Feature",
  "properties": {
    "iso:country":"US",
    "sg:address":"14936 W Calavar Rd",
    "sg:city":"Surprise",
    "sg:classifiers":[
        {
            "category":"Professional",
            "type":"Services"
        }
    ],
    "sg:phone":"+1 623 544 4452",
    "sg:postcode":"85379",
    "sg:province":"AZ",
    "wof:name":"Country At Heart",
    "wof:placetype":"venue"
},
  "geometry": {"coordinates":[-112.38161700000001,33.610571],"type":"Point"}
}