{
  "type": "Feature",
  "properties": {
    "addr:full":"3930 E Grant Rd Tucson AZ 85712",
    "addr:housenumber":"3930",
    "addr:postcode":"85712",
    "addr:street":"E Grant Rd",
    "iso:country":"US",
    "sg:address":"3930 E Grant Rd",
    "sg:city":"Tucson",
    "sg:classifiers":[
        {
            "category":"Food & Beverages",
            "subcategory":"Specialty",
            "type":"Retail Goods"
        }
    ],
    "sg:phone":"+1 520 881 1902",
    "sg:postcode":"85712",
    "sg:province":"AZ",
    "sg:tags":[
        "water",
        "bulk",
        "company"
    ],
    "wof:name":"Pure Water Technology Inc",
    "wof:placetype":"venue"
},
  "geometry": {"coordinates":[-110.90777199999999,32.250552],"type":"Point"}
}