{
  "type": "Feature",
  "properties": {
    "iso:country":"US",
    "sg:address":"3923 E Thunderbird Rd",
    "sg:city":"Phoenix",
    "sg:classifiers":[
        {
            "category":"Restaurant",
            "type":"Food & Drink"
        }
    ],
    "sg:phone":"+1 602 923 9901",
    "sg:postcode":"85032",
    "sg:province":"AZ",
    "sg:tags":[
        "eating"
    ],
    "wof:name":"Panda Express",
    "wof:placetype":"venue"
},
  "geometry": {"coordinates":[-111.99762800000001,33.61178],"type":"Point"}
}