{
  "type": "Feature",
  "properties": {
    "iso:country":"US",
    "sg:address":"1021 E Sandpiper Dr",
    "sg:city":"Tempe",
    "sg:classifiers":[
        {
            "category":"Manufacturing",
            "subcategory":"Electronics",
            "type":"Manufacturing & Wholesale Goods"
        }
    ],
    "sg:phone":"+1 480 345 1875",
    "sg:postcode":"85283",
    "sg:province":"AZ",
    "sg:tags":[
        "electronic",
        "component",
        "mfg"
    ],
    "wof:name":"Team Aerospace Inc",
    "wof:placetype":"venue"
},
  "geometry": {"coordinates":[-111.923911,33.37603],"type":"Point"}
}