{
  "type": "Feature",
  "properties": {
    "addr:full":"4206 US Hwy 70 Thatcher AZ 85552",
    "addr:housenumber":"4206",
    "addr:postcode":"85552",
    "addr:street":"Us Hwy 70 Thatcher",
    "iso:country":"US",
    "sg:address":"4206 US Hwy 70",
    "sg:city":"Thatcher",
    "sg:classifiers":[
        {
            "category":"Wholesale",
            "subcategory":"Machinery & Supplies",
            "type":"Manufacturing & Wholesale Goods"
        }
    ],
    "sg:phone":"+1 928 428 3273",
    "sg:postcode":"85552",
    "sg:province":"AZ",
    "sg:tags":[
        "pump"
    ],
    "wof:name":"Allen Pump Co",
    "wof:placetype":"venue"
},
  "geometry": {"coordinates":[-109.771367,32.84946],"type":"Point"}
}