{
  "type": "Feature",
  "properties": {
    "iso:country":"US",
    "sg:address":"3030 N 3rd St",
    "sg:city":"Phoenix",
    "sg:classifiers":[
        {
            "category":"Professional",
            "subcategory":"Advertising",
            "type":"Services"
        }
    ],
    "sg:phone":"+1 602 241 8580",
    "sg:postcode":"85012",
    "sg:province":"AZ",
    "sg:tags":[
        "counselor"
    ],
    "wof:name":"E P & P Consulting",
    "wof:placetype":"venue"
},
  "geometry": {"coordinates":[-112.069507,33.482724],"type":"Point"}
}