{
  "type": "Feature",
  "properties": {
    "iso:country":"US",
    "sg:address":"1717 E McDowell Rd",
    "sg:city":"Phoenix",
    "sg:classifiers":[
        {
            "category":"Retail",
            "subcategory":"Repair Shop",
            "type":"Services"
        }
    ],
    "sg:phone":"+1 602 257 4721",
    "sg:postcode":"85006",
    "sg:province":"AZ",
    "sg:tags":[
        "parts",
        "appliance"
    ],
    "wof:name":"Sears Roebuck and Co Inc",
    "wof:placetype":"venue"
},
  "geometry": {"coordinates":[-112.043631,33.465682],"type":"Point"}
}