{
  "type": "Feature",
  "properties": {
    "iso:country":"US",
    "sg:address":"34522 N Scottsdale Rd Ste 622",
    "sg:city":"Scottsdale",
    "sg:classifiers":[
        {
            "category":"Retail",
            "subcategory":"Auto Rental",
            "type":"Services"
        },
        {
            "category":"Airport",
            "type":"Transportation"
        },
        {
            "category":"Local Transit",
            "type":"Transportation"
        }
    ],
    "sg:phone":"+1 480 575 9700",
    "sg:postcode":"85266",
    "sg:province":"AZ",
    "sg:tags":[
        "shuttle",
        "limousine"
    ],
    "wof:name":"Airport Limousine Phoenix Scottsdale",
    "wof:placetype":"venue"
},
  "geometry": {"coordinates":[-111.928073,33.798458],"type":"Point"}
}