{
  "type": "Feature",
  "properties": {
    "iso:country":"US",
    "sg:address":"1515 Dunlap Rd",
    "sg:city":"Fort Mohave",
    "sg:classifiers":[
        {
            "category":"Restaurant",
            "type":"Food & Drink"
        }
    ],
    "sg:phone":"+1 928 758 3407",
    "sg:postcode":"86442",
    "sg:province":"AZ",
    "sg:tags":[
        "eating"
    ],
    "wof:name":"J & R Hotdogs Inc",
    "wof:placetype":"venue"
},
  "geometry": {"coordinates":[-114.597448,35.038871],"type":"Point"}
}