{
  "type": "Feature",
  "properties": {
    "addr:full":"3402 S Colt Dr Gilbert AZ 85297",
    "addr:housenumber":"3402",
    "addr:postcode":"85297",
    "addr:street":"S Colt Dr",
    "iso:country":"US",
    "sg:address":"3402 S Colt Dr",
    "sg:city":"Gilbert",
    "sg:classifiers":[
        {
            "category":"Communications",
            "subcategory":"Film & Video Production",
            "type":"Services"
        }
    ],
    "sg:phone":"+1 480 570 7701",
    "sg:postcode":"85297",
    "sg:province":"AZ",
    "sg:tags":[
        "taping"
    ],
    "wof:name":"Artistic Video Design",
    "wof:placetype":"venue"
},
  "geometry": {"coordinates":[-111.71679399999999,33.288965],"type":"Point"}
}