{
  "type": "Feature",
  "properties": {
    "addr:full":"501 E Elliot Rd Chandler AZ 85225",
    "addr:housenumber":"501",
    "addr:postcode":"85225",
    "addr:street":"E Elliot Rd",
    "iso:country":"US",
    "sg:address":"501 E Elliot Rd",
    "sg:city":"Chandler",
    "sg:classifiers":[
        {
            "category":"Travel",
            "subcategory":"Travel Agent",
            "type":"Entertainment"
        }
    ],
    "sg:phone":"+1 480 893 9660",
    "sg:postcode":"85225",
    "sg:province":"AZ",
    "sg:tags":[
        "agency"
    ],
    "wof:name":"Carlson Wagonlit Travel",
    "wof:placetype":"venue"
},
  "geometry": {"coordinates":[-111.835551,33.349671],"type":"Point"}
}