{
  "type": "Feature",
  "properties": {
    "iso:country":"US",
    "sg:address":"7050 W Chandler Blvd Ste 101",
    "sg:city":"Chandler",
    "sg:classifiers":[
        {
            "category":"Shopping",
            "subcategory":"Hobbies, Toys, & Games",
            "type":"Retail Goods"
        },
        {
            "category":"Recreation",
            "subcategory":"Gun Range",
            "type":"Entertainment"
        }
    ],
    "sg:phone":"+1 480 703 4653",
    "sg:postcode":"85226",
    "sg:province":"AZ",
    "sg:tags":[
        "safety",
        "instruction",
        "marksmanship",
        "gunsmith"
    ],
    "wof:name":"Weapons Showroom Co",
    "wof:placetype":"venue"
},
  "geometry": {"coordinates":[-111.963779,33.305332],"type":"Point"}
}