{
  "type": "Feature",
  "properties": {
    "addr:full":"2128 Injo Dr Lake Havasu City AZ 86403",
    "addr:housenumber":"2128",
    "addr:postcode":"86403",
    "addr:street":"Injo Dr",
    "iso:country":"US",
    "sg:address":"2128 Injo Dr",
    "sg:city":"Lake Havasu City",
    "sg:classifiers":[
        {
            "category":"Real Estate",
            "subcategory":"Real Estate Operator",
            "type":"Services"
        }
    ],
    "sg:phone":"+1 928 855 8418",
    "sg:postcode":"86403",
    "sg:province":"AZ",
    "sg:tags":[
        "apartment"
    ],
    "wof:name":"Arlington Apts",
    "wof:placetype":"venue"
},
  "geometry": {"coordinates":[-114.330127,34.478983],"type":"Point"}
}