{
  "type": "Feature",
  "properties": {
    "addr:full":"2325 S Hardy Dr Tempe AZ 85282",
    "addr:housenumber":"2325",
    "addr:postcode":"85282",
    "addr:street":"S Hardy Dr",
    "iso:country":"US",
    "sg:address":"2325 S Hardy Dr",
    "sg:city":"Tempe",
    "sg:classifiers":[
        {
            "category":"Shopping",
            "subcategory":"Stationery & Office Supplies",
            "type":"Retail Goods"
        },
        {
            "category":"Professional",
            "subcategory":"Advertising",
            "type":"Services"
        },
        {
            "category":"Shopping",
            "subcategory":"Catalog Store",
            "type":"Retail Goods"
        },
        {
            "category":"Professional",
            "subcategory":"Printing & Photocopies",
            "type":"Services"
        }
    ],
    "sg:phone":"+1 480 619 6798",
    "sg:postcode":"85282",
    "sg:province":"AZ",
    "sg:tags":[
        "announcement",
        "product",
        "designer",
        "services-commercial",
        "specialty",
        "invitation",
        "advertising-promotional",
        "compiler"
    ],
    "sg:website":"http://primesourceaz.reachlocal.com/?scid=1853019",
    "wof:name":"Business Printing & More",
    "wof:placetype":"venue"
},
  "geometry": {"coordinates":[-111.95214799999999,33.403518],"type":"Point"}
}