{
  "type": "Feature",
  "properties": {
    "addr:full":"4607 S 35th St Phoenix AZ 85040",
    "addr:housenumber":"4607",
    "addr:postcode":"85040",
    "addr:street":"S 35Th St",
    "iso:country":"US",
    "sg:address":"4607 S 35th St",
    "sg:city":"Phoenix",
    "sg:classifiers":[
        {
            "category":"Manufacturing",
            "subcategory":"Furniture",
            "type":"Manufacturing & Wholesale Goods"
        }
    ],
    "sg:phone":"+1 602 278 4672",
    "sg:postcode":"85040",
    "sg:province":"AZ",
    "sg:tags":[
        "wood",
        "mfg"
    ],
    "wof:name":"Finns Supply",
    "wof:placetype":"venue"
},
  "geometry": {"coordinates":[-112.006951,33.403427],"type":"Point"}
}