{
  "type": "Feature",
  "properties": {
    "iso:country":"US",
    "sg:address":"1835 E Guadalupe Rd Ste 103",
    "sg:city":"Tempe",
    "sg:classifiers":[
        {
            "category":"Education",
            "subcategory":"School",
            "type":"Public Place"
        }
    ],
    "sg:phone":"+1 480 456 0942",
    "sg:postcode":"85283",
    "sg:province":"AZ",
    "wof:name":"Academic Behavioral Accommodations",
    "wof:placetype":"venue"
},
  "geometry": {"coordinates":[-111.90957400000001,33.363632],"type":"Point"}
}