{
  "type": "Feature",
  "properties": {
    "addr:full":"99 E Virginia Ave Ste 175 Phoenix AZ 85004",
    "addr:housenumber":"99",
    "addr:postcode":"85004",
    "addr:street":"E Virginia Ave Ste 175",
    "iso:country":"US",
    "sg:address":"99 E Virginia Ave Ste 175",
    "sg:city":"Phoenix",
    "sg:classifiers":[
        {
            "category":"Real Estate",
            "subcategory":"Architect",
            "type":"Services"
        }
    ],
    "sg:phone":"+1 602 252 6678",
    "sg:postcode":"85004",
    "sg:province":"AZ",
    "sg:tags":[
        "architects'",
        "specification",
        "builders'",
        "construction",
        "architectural"
    ],
    "wof:name":"Ball Architects Inc",
    "wof:placetype":"venue"
},
  "geometry": {"coordinates":[-112.07096,33.476629],"type":"Point"}
}