{
  "type": "Feature",
  "properties": {
    "iso:country":"US",
    "sg:address":"7100 E Main St",
    "sg:city":"Scottsdale",
    "sg:classifiers":[
        {
            "category":"Shopping",
            "type":"Retail Goods"
        }
    ],
    "sg:phone":"+1 480 481 0187",
    "sg:postcode":"85251",
    "sg:province":"AZ",
    "sg:tags":[
        "art",
        "gallery",
        "dealer"
    ],
    "sg:website":"www.kinggalleries.com",
    "wof:name":"King Galleries",
    "wof:placetype":"venue"
},
  "geometry": {"coordinates":[-111.926102,33.493136],"type":"Point"}
}