{
  "type": "Feature",
  "properties": {
    "iso:country":"US",
    "sg:address":"4411 W Roosevelt St",
    "sg:city":"Phoenix",
    "sg:classifiers":[
        {
            "category":"Freight",
            "type":"Transportation"
        }
    ],
    "sg:phone":"+1 866 566 7921",
    "sg:postcode":"85043",
    "sg:province":"AZ",
    "sg:tags":[
        "broker",
        "trucking"
    ],
    "wof:name":"Greatwide Logistics Services, Inc.",
    "wof:placetype":"venue"
},
  "geometry": {"coordinates":[-112.15421600000001,33.458914],"type":"Point"}
}