{
  "type": "Feature",
  "properties": {
    "iso:country":"US",
    "sg:address":"4209 S 36th Pl",
    "sg:city":"Phoenix",
    "sg:classifiers":[
        {
            "category":"Wholesale",
            "subcategory":"Construction Materials",
            "type":"Manufacturing & Wholesale Goods"
        }
    ],
    "sg:phone":"+1 602 437 2811",
    "sg:postcode":"85040",
    "sg:province":"AZ",
    "sg:tags":[
        "distributor",
        "concrete",
        "product"
    ],
    "wof:name":"Blyth Concrete",
    "wof:placetype":"venue"
},
  "geometry": {"coordinates":[-112.003128,33.407566],"type":"Point"}
}