{
  "type": "Feature",
  "properties": {
    "iso:country":"US",
    "sg:address":"6900 E Camelback Rd Ste 601",
    "sg:city":"Scottsdale",
    "sg:classifiers":[
        {
            "category":"Banks & Credit Unions",
            "subcategory":"Bureau De Change",
            "type":"Services"
        },
        {
            "category":"Banks & Credit Unions",
            "subcategory":"Financial Services",
            "type":"Services"
        }
    ],
    "sg:phone":"+1 480 947 9340",
    "sg:postcode":"85251",
    "sg:province":"AZ",
    "sg:tags":[
        "factor"
    ],
    "wof:name":"Factors Southwest",
    "wof:placetype":"venue"
},
  "geometry": {"coordinates":[-111.931945,33.502276],"type":"Point"}
}