{
  "type": "Feature",
  "properties": {
    "addr:full":"24925 S Stoney Lake Dr Chandler AZ 85248",
    "addr:housenumber":"24925",
    "addr:postcode":"85248",
    "addr:street":"S Stoney Lake Dr",
    "iso:country":"US",
    "sg:address":"24925 S Stoney Lake Dr",
    "sg:city":"Chandler",
    "sg:classifiers":[
        {
            "category":"Shopping",
            "type":"Retail Goods"
        }
    ],
    "sg:phone":"+1 480 883 9796",
    "sg:postcode":"85248",
    "sg:province":"AZ",
    "sg:tags":[
        "merchandise"
    ],
    "wof:name":"Charmichaels",
    "wof:placetype":"venue"
},
  "geometry": {"coordinates":[-111.862595,33.219887],"type":"Point"}
}