{
  "type": "Feature",
  "properties": {
    "iso:country":"US",
    "sg:address":"2288 E Marlene Dr",
    "sg:city":"Gilbert",
    "sg:classifiers":[
        {
            "category":"Professional",
            "subcategory":"Advertising",
            "type":"Services"
        }
    ],
    "sg:phone":"+1 480 633 0425",
    "sg:postcode":"85296",
    "sg:province":"AZ",
    "wof:name":"Sanjon Lazer Engraving & Gifts",
    "wof:placetype":"venue"
},
  "geometry": {"coordinates":[-111.74077,33.346798],"type":"Point"}
}