{
  "type": "Feature",
  "properties": {
    "iso:country":"US",
    "sg:address":"9414 E San Salvador Dr",
    "sg:city":"Scottsdale",
    "sg:classifiers":[
        {
            "category":"Home & Garden",
            "subcategory":"Mobile Homes",
            "type":"Retail Goods"
        }
    ],
    "sg:phone":"+1 480 314 5814",
    "sg:postcode":"85258",
    "sg:province":"AZ",
    "sg:tags":[
        "commercial",
        "unit"
    ],
    "sg:website":"www.genmod.com",
    "wof:name":"General Modular Sales & Lsng",
    "wof:placetype":"venue"
},
  "geometry": {"coordinates":[-111.877607,33.570627],"type":"Point"}
}