{
  "type": "Feature",
  "properties": {
    "iso:country":"US",
    "sg:address":"10815 W Mcdowell Rd",
    "sg:city":"Avondale",
    "sg:classifiers":[
        {
            "category":"Professional",
            "subcategory":"Advertising",
            "type":"Services"
        }
    ],
    "sg:phone":"+1 602 824 4100",
    "sg:postcode":"85392",
    "sg:province":"AZ",
    "sg:tags":[
        "telemarketing"
    ],
    "wof:name":"Avondale Integrated Medical Services 1",
    "wof:placetype":"venue"
},
  "geometry": {"coordinates":[-112.292404,33.464448],"type":"Point"}
}