{
  "type": "Feature",
  "properties": {
    "iso:country":"US",
    "sg:address":"118 E Grant Ave",
    "sg:city":"Williams",
    "sg:classifiers":[
        {
            "category":"Coffee & Tea",
            "type":"Food & Drink"
        },
        {
            "category":"Restaurant",
            "type":"Food & Drink"
        }
    ],
    "sg:phone":"+1 928 635 5255",
    "sg:postcode":"86046",
    "sg:province":"AZ",
    "sg:tags":[
        "espresso"
    ],
    "wof:name":"Cafe Restaurant Group",
    "wof:placetype":"venue"
},
  "geometry": {"coordinates":[-112.186623,35.250016],"type":"Point"}
}