{
  "type": "Feature",
  "properties": {
    "iso:country":"US",
    "sg:address":"2610 E Sequoyah",
    "sg:city":"Tucson",
    "sg:classifiers":[
        {
            "category":"Retail",
            "subcategory":"Auto Repair",
            "type":"Services"
        }
    ],
    "sg:phone":"+1 520 326 7812",
    "sg:postcode":"85716",
    "sg:province":"AZ",
    "sg:tags":[
        "repairing",
        "automobile"
    ],
    "wof:name":"Motor Sport LTD",
    "wof:placetype":"venue"
},
  "geometry": {"coordinates":[-110.931178,32.254642],"type":"Point"}
}