{
  "type": "Feature",
  "properties": {
    "iso:country":"US",
    "sg:address":"4235 E Winslow Ave",
    "sg:city":"Phoenix",
    "sg:classifiers":[
        {
            "category":"Manufacturing",
            "subcategory":"Metals",
            "type":"Manufacturing & Wholesale Goods"
        }
    ],
    "sg:phone":"+1 602 437 9289",
    "sg:postcode":"85040",
    "sg:province":"AZ",
    "sg:tags":[
        "mfg"
    ],
    "wof:name":"Overhead Door Corporation",
    "wof:placetype":"venue"
},
  "geometry": {"coordinates":[-111.987529,33.421001],"type":"Point"}
}