{
  "type": "Feature",
  "properties": {
    "iso:country":"US",
    "sg:address":"4454 E 3rd St",
    "sg:city":"Tucson",
    "sg:classifiers":[
        {
            "category":"Professional",
            "type":"Services"
        }
    ],
    "sg:phone":"+1 520 881 3090",
    "sg:postcode":"85711",
    "sg:province":"AZ",
    "sg:tags":[
        "establishment"
    ],
    "wof:name":"Supported Living Systems",
    "wof:placetype":"venue"
},
  "geometry": {"coordinates":[-110.89730900000001,32.232482],"type":"Point"}
}