{
  "type": "Feature",
  "properties": {
    "iso:country":"US",
    "sg:address":"44047 N 43rd Ave",
    "sg:city":"Phoenix",
    "sg:classifiers":[
        {
            "category":"Government",
            "subcategory":"Post Office",
            "type":"Public Place"
        }
    ],
    "sg:phone":"+1 800 275 8777",
    "sg:postcode":"85087",
    "sg:province":"AZ",
    "sg:website":"http://www.usps.com",
    "wof:name":"USPS - United States Post Office - Phoenix Daisy Mountain",
    "wof:placetype":"venue"
},
  "geometry": {"coordinates":[-112.15228,33.884525],"type":"Point"}
}