{
  "type": "Feature",
  "properties": {
    "addr:full":"632 Teetsa Ln Lake Havasu City AZ 86403",
    "addr:housenumber":"632",
    "addr:postcode":"86403",
    "addr:street":"Teetsa Ln",
    "iso:country":"US",
    "sg:address":"632 Teetsa Ln",
    "sg:city":"Lake Havasu City",
    "sg:classifiers":[
        {
            "category":"Retail",
            "subcategory":"Auto Repair",
            "type":"Services"
        }
    ],
    "sg:phone":"+1 928 505 4973",
    "sg:postcode":"86403",
    "sg:province":"AZ",
    "sg:tags":[
        "repairing",
        "tire"
    ],
    "wof:name":"Benny's Road Svc",
    "wof:placetype":"venue"
},
  "geometry": {"coordinates":[-114.335036,34.494743],"type":"Point"}
}