{
  "type": "Feature",
  "properties": {
    "iso:country":"US",
    "sg:address":"16140 N Oracle Rd",
    "sg:city":"Tucson",
    "sg:classifiers":[
        {
            "category":"Restaurant",
            "type":"Food & Drink"
        }
    ],
    "sg:phone":"+1 520 825 2525",
    "sg:postcode":"85739",
    "sg:province":"AZ",
    "sg:tags":[
        "eating",
        "merchandise"
    ],
    "wof:name":"Claire's Cafe",
    "wof:placetype":"venue"
},
  "geometry": {"coordinates":[-110.92600299999999,32.498901],"type":"Point"}
}