{
  "type": "Feature",
  "properties": {
    "iso:country":"US",
    "sg:address":"10534 W Seldon Ln",
    "sg:city":"Peoria",
    "sg:classifiers":[
        {
            "category":"Shopping",
            "subcategory":"Bicycles & Sporting Goods",
            "type":"Retail Goods"
        }
    ],
    "sg:phone":"+1 623 583 0069",
    "sg:postcode":"85345",
    "sg:province":"AZ",
    "sg:tags":[
        "equipment",
        "golf",
        "supply"
    ],
    "wof:name":"Arizona Discount Golf",
    "wof:placetype":"venue"
},
  "geometry": {"coordinates":[-112.288846,33.559129],"type":"Point"}
}