{
  "type": "Feature",
  "properties": {
    "iso:country":"US",
    "sg:address":"1855 E Hope St",
    "sg:city":"Mesa",
    "sg:classifiers":[
        {
            "category":"Professional",
            "subcategory":"Management & Consulting",
            "type":"Services"
        }
    ],
    "sg:phone":"+1 480 464 8066",
    "sg:postcode":"85203",
    "sg:province":"AZ",
    "sg:tags":[
        "consultant",
        "business"
    ],
    "wof:name":"Livengood & Assoc",
    "wof:placetype":"venue"
},
  "geometry": {"coordinates":[-111.789415,33.442919],"type":"Point"}
}