{
  "type": "Feature",
  "properties": {
    "addr:full":"15333 N. Pima Rd. Ste. 245 Scottsdale AZ 85260",
    "addr:housenumber":"15333",
    "addr:postcode":"85260",
    "addr:street":"N. Pima Rd. Ste. 245",
    "iso:country":"US",
    "sg:address":"15333 N. Pima Rd. Ste. 245",
    "sg:city":"Scottsdale",
    "sg:classifiers":[
        {
            "category":"Professional",
            "subcategory":"Computer Services",
            "type":"Services"
        }
    ],
    "sg:phone":"+353 1 498 0700",
    "sg:postcode":"85260",
    "sg:province":"AZ",
    "sg:website":"http://www.worldres.com",
    "wof:name":"Worldres",
    "wof:placetype":"venue"
},
  "geometry": {"coordinates":[-111.890795,33.616689],"type":"Point"}
}