{
  "type": "Feature",
  "properties": {
    "iso:country":"US",
    "sg:address":"3773 W Ina Rd Ste 120",
    "sg:city":"Tucson",
    "sg:classifiers":[
        {
            "category":"Health Services",
            "subcategory":"Doctor",
            "type":"Services"
        },
        {
            "category":"Health Services",
            "subcategory":"Clinic",
            "type":"Services"
        },
        {
            "category":"Health Services",
            "subcategory":"Chiropractor",
            "type":"Services"
        }
    ],
    "sg:phone":"+1 520 744 4161",
    "sg:postcode":"85741",
    "sg:province":"AZ",
    "sg:tags":[
        "physician",
        "medical",
        "surgeon",
        "chiropractic"
    ],
    "wof:name":"Welch Family Chiropractic",
    "wof:placetype":"venue"
},
  "geometry": {"coordinates":[-111.045814,32.337471],"type":"Point"}
}