{
  "type": "Feature",
  "properties": {
    "iso:country":"US",
    "sg:address":"1646 N Litchfield Road",
    "sg:city":"Goodyear",
    "sg:classifiers":[
        {
            "category":"Health Services",
            "subcategory":"Dentist",
            "type":"Services"
        }
    ],
    "sg:phone":"+1 623 535 7899",
    "sg:postcode":"85338",
    "sg:province":"AZ",
    "wof:name":"Kane Robert S DDS",
    "wof:placetype":"venue"
},
  "geometry": {"coordinates":[-112.358237,33.464943],"type":"Point"}
}