{
  "type": "Feature",
  "properties": {
    "iso:country":"US",
    "sg:address":"2002 N Westridge Ave",
    "sg:city":"Tucson",
    "sg:classifiers":[
        {
            "category":"Building & Trades",
            "subcategory":"Construction",
            "type":"Services"
        }
    ],
    "sg:phone":"+1 520 743 3554",
    "sg:postcode":"85745",
    "sg:province":"AZ",
    "sg:tags":[
        "contractor"
    ],
    "wof:name":"Tito Drywall Contractors",
    "wof:placetype":"venue"
},
  "geometry": {"coordinates":[-111.033771,32.24614],"type":"Point"}
}