{
  "type": "Feature",
  "properties": {
    "iso:country":"US",
    "sg:address":"649 S Harvard Dr",
    "sg:city":"Tucson",
    "sg:classifiers":[
        {
            "category":"Building & Trades",
            "subcategory":"Construction",
            "type":"Services"
        }
    ],
    "sg:phone":"+1 520 977 6898",
    "sg:postcode":"85710",
    "sg:province":"AZ",
    "sg:tags":[
        "house"
    ],
    "wof:name":"Mike Cojanis",
    "wof:placetype":"venue"
},
  "geometry": {"coordinates":[-110.853301,32.214159],"type":"Point"}
}