{
  "type": "Feature",
  "properties": {
    "addr:full":"895 E Chandler Boulevard Chandler AZ 85225",
    "addr:housenumber":"895",
    "addr:postcode":"85225",
    "addr:street":"E Chandler Boulevard",
    "iso:country":"US",
    "sg:address":"895 E Chandler Boulevard",
    "sg:city":"Chandler",
    "sg:classifiers":[
        {
            "category":"Retail",
            "subcategory":"Auto Repair",
            "type":"Services"
        }
    ],
    "sg:phone":"+1 480 726 1960",
    "sg:postcode":"85225",
    "sg:province":"AZ",
    "sg:website":"www.sundevilauto.com",
    "wof:name":"Sun Devil Auto",
    "wof:placetype":"venue"
},
  "geometry": {"coordinates":[-111.827072,33.306174],"type":"Point"}
}