{
  "type": "Feature",
  "properties": {
    "iso:country":"US",
    "sg:address":"9034 N 23rd Ave",
    "sg:city":"Phoenix",
    "sg:classifiers":[
        {
            "category":"Building & Trades",
            "subcategory":"Construction",
            "type":"Services"
        }
    ],
    "sg:phone":"+1 602 254 1320",
    "sg:postcode":"85021",
    "sg:province":"AZ",
    "sg:tags":[
        "dry wall",
        "contractor"
    ],
    "wof:name":"Paul Johnson Drywall",
    "wof:placetype":"venue"
},
  "geometry": {"coordinates":[-112.108316,33.567911],"type":"Point"}
}