{
  "type": "Feature",
  "properties": {
    "iso:country":"US",
    "sg:address":"3503 N Campbell Ave # 155",
    "sg:city":"Tucson",
    "sg:classifiers":[
        {
            "category":"Health Services",
            "subcategory":"Clinic",
            "type":"Services"
        },
        {
            "category":"Community Center",
            "type":"Public Place"
        }
    ],
    "sg:phone":"+1 520 321 4057",
    "sg:postcode":"85719",
    "sg:province":"AZ",
    "sg:tags":[
        "medical",
        "welfare"
    ],
    "wof:name":"Southwest Pet Institute",
    "wof:placetype":"venue"
},
  "geometry": {"coordinates":[-110.94381,32.270397],"type":"Point"}
}