{
  "type": "Feature",
  "properties": {
    "iso:country":"US",
    "sg:address":"8601 E Golf Links Rd",
    "sg:city":"Tucson",
    "sg:classifiers":[
        {
            "category":"Autos & Motor Vehicles",
            "subcategory":"Fuel & Gas Station",
            "type":"Retail Goods"
        }
    ],
    "sg:phone":"+1 520 721 2483",
    "sg:postcode":"85730",
    "sg:province":"AZ",
    "sg:tags":[
        "oil"
    ],
    "wof:name":"C & T Oil",
    "wof:placetype":"venue"
},
  "geometry": {"coordinates":[-110.805311,32.191789],"type":"Point"}
}