{
  "type": "Feature",
  "properties": {
    "iso:country":"US",
    "sg:address":"16191 N 82nd St",
    "sg:city":"Scottsdale",
    "sg:classifiers":[
        {
            "category":"Home & Garden",
            "subcategory":"Home Furnishings",
            "type":"Retail Goods"
        },
        {
            "category":"Home & Garden",
            "subcategory":"Building Materials",
            "type":"Retail Goods"
        },
        {
            "category":"Manufacturing",
            "subcategory":"Glass & Minerals",
            "type":"Manufacturing & Wholesale Goods"
        },
        {
            "category":"Manufacturing",
            "subcategory":"Building Materials",
            "type":"Manufacturing & Wholesale Goods"
        }
    ],
    "sg:phone":"+1 480 447 0571",
    "sg:postcode":"85260",
    "sg:province":"AZ",
    "sg:tags":[
        "plate",
        "glass-auto",
        "accessory",
        "window",
        "doors",
        "mirror",
        "frames"
    ],
    "sg:website":"http://www.diamondglassandmirrorinc.com",
    "wof:name":"Diamond Glass & Mirror",
    "wof:placetype":"venue"
},
  "geometry": {"coordinates":[-111.90370900000001,33.632788],"type":"Point"}
}