{
  "type": "Feature",
  "properties": {
    "iso:country":"US",
    "sg:address":"1205 S Arizona Blvd",
    "sg:city":"Coolidge",
    "sg:classifiers":[
        {
            "category":"Professional",
            "type":"Services"
        }
    ],
    "sg:phone":"+1 520 723 0197",
    "sg:postcode":"85228",
    "sg:province":"AZ",
    "wof:name":"Inland Empire Shows",
    "wof:placetype":"venue"
},
  "geometry": {"coordinates":[-111.524028,32.966215],"type":"Point"}
}