{
  "type": "Feature",
  "properties": {
    "iso:country":"US",
    "sg:address":"6879 N Oracle Rd Ste B10",
    "sg:city":"Tucson",
    "sg:classifiers":[
        {
            "category":"Health Services",
            "subcategory":"Doctor",
            "type":"Services"
        }
    ],
    "sg:phone":"+1 520 531 0600",
    "sg:postcode":"85704",
    "sg:province":"AZ",
    "sg:tags":[
        "physician",
        "stomach",
        "gastroenterology",
        "surgeons",
        "surgeon",
        "intestines"
    ],
    "wof:name":"Elk Properties",
    "wof:placetype":"venue"
},
  "geometry": {"coordinates":[-110.977042,32.331584],"type":"Point"}
}