{
  "type": "Feature",
  "properties": {
    "iso:country":"US",
    "sg:address":"600 E 1st St",
    "sg:city":"Casa Grande",
    "sg:classifiers":[
        {
            "category":"Building & Trades",
            "subcategory":"Plumbing",
            "type":"Services"
        }
    ],
    "sg:phone":"+1 520 426 1469",
    "sg:postcode":"85222",
    "sg:province":"AZ",
    "sg:tags":[
        "contractor"
    ],
    "wof:name":"Pinal County Backflo Test",
    "wof:placetype":"venue"
},
  "geometry": {"coordinates":[-111.74753699999999,32.873689],"type":"Point"}
}