{
  "type": "Feature",
  "properties": {
    "iso:country":"US",
    "sg:address":"6644 E Baywood Ave",
    "sg:city":"Mesa",
    "sg:classifiers":[
        {
            "category":"Health Services",
            "subcategory":"Doctor",
            "type":"Services"
        }
    ],
    "sg:phone":"+1 480 985 8151",
    "sg:postcode":"85206",
    "sg:province":"AZ",
    "sg:tags":[
        "physician",
        "surgeon"
    ],
    "wof:name":"Mesa Obstetricians & Gyn LTD",
    "wof:placetype":"venue"
},
  "geometry": {"coordinates":[-111.688093,33.410514],"type":"Point"}
}