{
  "type": "Feature",
  "properties": {
    "iso:country":"US",
    "sg:address":"8354 E Balfour Dr",
    "sg:city":"Tucson",
    "sg:classifiers":[
        {
            "category":"Building & Trades",
            "subcategory":"Construction",
            "type":"Services"
        }
    ],
    "sg:phone":"+1 520 885 9149",
    "sg:postcode":"85710",
    "sg:province":"AZ",
    "sg:tags":[
        "house"
    ],
    "wof:name":"Artisan Construction Inc",
    "wof:placetype":"venue"
},
  "geometry": {"coordinates":[-110.812779,32.225301],"type":"Point"}
}