{
  "type": "Feature",
  "properties": {
    "addr:full":"27406 N 66th Ln Phoenix AZ 85083",
    "addr:housenumber":"27406",
    "addr:postcode":"85083",
    "addr:street":"N 66Th Ln",
    "iso:country":"US",
    "sg:address":"27406 N 66th Ln",
    "sg:city":"Phoenix",
    "sg:classifiers":[
        {
            "category":"Building & Trades",
            "subcategory":"Landscaping Services",
            "type":"Services"
        }
    ],
    "sg:phone":"+1 623 561 6645",
    "sg:postcode":"85083",
    "sg:province":"AZ",
    "sg:tags":[
        "landscape",
        "contractor"
    ],
    "wof:name":"Desert Mirage Landscaping",
    "wof:placetype":"venue"
},
  "geometry": {"coordinates":[-112.202037,33.734744],"type":"Point"}
}