{
  "type": "Feature",
  "properties": {
    "iso:country":"US",
    "sg:address":"25311 N Lake Pleasant Pkwy",
    "sg:city":"Peoria",
    "sg:classifiers":[
        {
            "category":"Home & Garden",
            "subcategory":"Household Appliances",
            "type":"Retail Goods"
        },
        {
            "category":"Home & Garden",
            "subcategory":"Building Materials",
            "type":"Retail Goods"
        },
        {
            "category":"Building & Trades",
            "subcategory":"Construction",
            "type":"Services"
        }
    ],
    "sg:phone":"+1 877 471 9739",
    "sg:postcode":"85383",
    "sg:province":"AZ",
    "sg:tags":[
        "repair",
        "major",
        "heater",
        "improvement",
        "water",
        "maintenance"
    ],
    "sg:website":"http://www.lowes.com",
    "wof:name":"Lowe's? Home Improvement",
    "wof:placetype":"venue"
},
  "geometry": {"coordinates":[-112.272199,33.711609],"type":"Point"}
}