{
  "type": "Feature",
  "properties": {
    "iso:country":"US",
    "sg:address":"6713 S Clementine Ct",
    "sg:city":"Tempe",
    "sg:classifiers":[
        {
            "category":"Farming",
            "subcategory":"Farm",
            "type":"Manufacturing & Wholesale Goods"
        }
    ],
    "sg:phone":"+1 480 820 0764",
    "sg:postcode":"85283",
    "sg:province":"AZ",
    "sg:website":"www.evergreenturf.com",
    "wof:name":"Celebration Bermudagrass",
    "wof:placetype":"venue"
},
  "geometry": {"coordinates":[-111.964503,33.358965],"type":"Point"}
}