{
  "type": "Feature",
  "properties": {
    "iso:country":"US",
    "sg:address":"13706 W Bell Rd",
    "sg:city":"Surprise",
    "sg:classifiers":[
        {
            "category":"Restaurant",
            "type":"Food & Drink"
        }
    ],
    "sg:phone":"+1 623 556 8108",
    "sg:postcode":"85374",
    "sg:province":"AZ",
    "sg:tags":[
        "delicatessen"
    ],
    "wof:name":"Hot Bagels & Deli",
    "wof:placetype":"venue"
},
  "geometry": {"coordinates":[-112.359165,33.638796],"type":"Point"}
}