{
  "type": "Feature",
  "properties": {
    "iso:country":"US",
    "sg:address":"185 W Apache Trl",
    "sg:city":"Apache Junction",
    "sg:classifiers":[
        {
            "category":"Shopping",
            "subcategory":"Pharmacy",
            "type":"Retail Goods"
        }
    ],
    "sg:phone":"+1 480 288 2143",
    "sg:postcode":"85220",
    "sg:province":"AZ",
    "wof:name":"Smiths",
    "wof:placetype":"venue"
},
  "geometry": {"coordinates":[-111.553419,33.414869],"type":"Point"}
}