{
  "type": "Feature",
  "properties": {
    "addr:full":"2502 W Myopia Ct Anthem AZ 85086",
    "addr:housenumber":"2502",
    "addr:postcode":"85086",
    "addr:street":"W Myopia Ct",
    "iso:country":"US",
    "sg:address":"2502 W Myopia Ct",
    "sg:city":"Anthem",
    "sg:classifiers":[
        {
            "category":"Shopping",
            "subcategory":"Gifts & Souvenirs",
            "type":"Retail Goods"
        }
    ],
    "sg:phone":"+1 623 551 5209",
    "sg:postcode":"85086",
    "sg:province":"AZ",
    "sg:tags":[
        "party",
        "supply"
    ],
    "wof:name":"Bounce Around Party Rentals",
    "wof:placetype":"venue"
},
  "geometry": {"coordinates":[-112.113989,33.863632],"type":"Point"}
}