{
  "type": "Feature",
  "properties": {
    "iso:country":"US",
    "sg:address":"402 W Roosevelt St Suite B",
    "sg:city":"Phoenix",
    "sg:classifiers":[
        {
            "category":"Professional",
            "subcategory":"Lawyer & Legal Services",
            "type":"Services"
        }
    ],
    "sg:phone":"+1 602 258 7868",
    "sg:postcode":"85003",
    "sg:province":"AZ",
    "sg:tags":[
        "attorney",
        "planning",
        "estate"
    ],
    "wof:name":"Coll, John R. - John R. Coll, P.L.C.",
    "wof:placetype":"venue"
},
  "geometry": {"coordinates":[-112.079507,33.458665],"type":"Point"}
}