{
  "type": "Feature",
  "properties": {
    "iso:country":"US",
    "sg:address":"5025 S Ash Ave",
    "sg:city":"Tempe",
    "sg:classifiers":[
        {
            "category":"Wholesale",
            "subcategory":"Electrical",
            "type":"Manufacturing & Wholesale Goods"
        }
    ],
    "sg:phone":"+1 602 242 0800",
    "sg:postcode":"85282",
    "sg:province":"AZ",
    "sg:tags":[
        "discharge",
        "machining"
    ],
    "wof:name":"Intech Edm",
    "wof:placetype":"venue"
},
  "geometry": {"coordinates":[-111.94144900000001,33.379485],"type":"Point"}
}