{
  "type": "Feature",
  "properties": {
    "iso:country":"US",
    "sg:address":"58 N Country Club Dr",
    "sg:city":"Mesa",
    "sg:classifiers":[
        {
            "category":"Personal",
            "subcategory":"Barber",
            "type":"Services"
        }
    ],
    "sg:phone":"+1 480 464 4403",
    "sg:postcode":"85201",
    "sg:province":"AZ",
    "wof:name":"Manny's Barber Shop",
    "wof:placetype":"venue"
},
  "geometry": {"coordinates":[-111.840015,33.415439],"type":"Point"}
}