{
  "type": "Feature",
  "properties": {
    "addr:full":"1121 W Pecos Ave Mesa AZ 85210",
    "addr:housenumber":"1121",
    "addr:postcode":"85210",
    "addr:street":"W Pecos Ave",
    "iso:country":"US",
    "sg:address":"1121 W Pecos Ave",
    "sg:city":"Mesa",
    "sg:classifiers":[
        {
            "category":"Shopping",
            "subcategory":"Discount & Variety Stores",
            "type":"Retail Goods"
        }
    ],
    "sg:phone":"+1 480 839 1447",
    "sg:postcode":"85210",
    "sg:province":"AZ",
    "sg:tags":[
        "merchandise",
        "general"
    ],
    "wof:name":"Ever Gloe Sales",
    "wof:placetype":"venue"
},
  "geometry": {"coordinates":[-111.85607,33.36029],"type":"Point"}
}