{
  "type": "Feature",
  "properties": {
    "iso:country":"US",
    "sg:address":"1421 N 43rd Pl",
    "sg:city":"Phoenix",
    "sg:classifiers":[
        {
            "category":"Wholesale",
            "subcategory":"Office Equipment",
            "type":"Manufacturing & Wholesale Goods"
        }
    ],
    "sg:phone":"+1 602 685 0373",
    "sg:postcode":"85008",
    "sg:province":"AZ",
    "wof:name":"Phoenix Wholesale Copiers Exch",
    "wof:placetype":"venue"
},
  "geometry": {"coordinates":[-111.988351,33.463022],"type":"Point"}
}