{
  "type": "Feature",
  "properties": {
    "iso:country":"US",
    "sg:address":"1829 Grand Ave",
    "sg:city":"Phoenix",
    "sg:classifiers":[
        {
            "category":"Autos & Motor Vehicles",
            "subcategory":"Automobile Sales",
            "type":"Retail Goods"
        }
    ],
    "sg:phone":"+1 602 258 1933",
    "sg:postcode":"85007",
    "sg:province":"AZ",
    "sg:tags":[
        "car",
        "dealer"
    ],
    "wof:name":"Grand Avenue Motors",
    "wof:placetype":"venue"
},
  "geometry": {"coordinates":[-112.099487,33.465284],"type":"Point"}
}