{
  "type": "Feature",
  "properties": {
    "iso:country":"US",
    "sg:address":"6595 N Oracle Rd",
    "sg:city":"Tucson",
    "sg:classifiers":[
        {
            "category":"Real Estate",
            "subcategory":"Real Estate Agent",
            "type":"Services"
        }
    ],
    "sg:phone":"+1 520 297 8960",
    "sg:postcode":"85704",
    "sg:province":"AZ",
    "sg:tags":[
        "property",
        "management",
        "brokerage"
    ],
    "wof:name":"Equity IV Brokerage & MGT",
    "wof:placetype":"venue"
},
  "geometry": {"coordinates":[-110.975762,32.326533],"type":"Point"}
}