{
  "type": "Feature",
  "properties": {
    "iso:country":"US",
    "sg:address":"1245 W Baseline Rd",
    "sg:city":"Mesa",
    "sg:classifiers":[
        {
            "category":"Shopping",
            "subcategory":"Bicycles & Sporting Goods",
            "type":"Retail Goods"
        }
    ],
    "sg:phone":"+1 480 777 8875",
    "sg:postcode":"85202",
    "sg:province":"AZ",
    "sg:tags":[
        "equipment",
        "soccer"
    ],
    "wof:name":"Soccer Extreme",
    "wof:placetype":"venue"
},
  "geometry": {"coordinates":[-111.862471,33.378633],"type":"Point"}
}