{
  "type": "Feature",
  "properties": {
    "iso:country":"US",
    "sg:address":"124 W McDowell Rd",
    "sg:city":"Phoenix",
    "sg:classifiers":[
        {
            "category":"Manufacturing",
            "subcategory":"Printing",
            "type":"Manufacturing & Wholesale Goods"
        }
    ],
    "sg:phone":"+1 602 252 0991",
    "sg:postcode":"85003",
    "sg:province":"AZ",
    "sg:tags":[
        "commercial"
    ],
    "wof:name":"Turnkey Color Inc",
    "wof:placetype":"venue"
},
  "geometry": {"coordinates":[-112.077992,33.465847],"type":"Point"}
}