{
  "type": "Feature",
  "properties": {
    "addr:full":"2432 W Silver Bell Tree Dr Tucson AZ 85745",
    "addr:housenumber":"2432",
    "addr:postcode":"85745",
    "addr:street":"W Silver Bell Tree Dr",
    "iso:country":"US",
    "sg:address":"2432 W Silver Bell Tree Dr",
    "sg:city":"Tucson",
    "sg:classifiers":[
        {
            "category":"Building & Trades",
            "subcategory":"Construction",
            "type":"Services"
        }
    ],
    "sg:phone":"+1 520 884 0378",
    "sg:postcode":"85745",
    "sg:province":"AZ",
    "sg:tags":[
        "home",
        "builder"
    ],
    "wof:name":"Monterey Homes",
    "wof:placetype":"venue"
},
  "geometry": {"coordinates":[-111.018179,32.269065],"type":"Point"}
}