{
  "type": "Feature",
  "properties": {
    "addr:full":"3936 S 6th Ave Tucson AZ 85714",
    "addr:housenumber":"3936",
    "addr:postcode":"85714",
    "addr:street":"S 6Th Ave",
    "iso:country":"US",
    "sg:address":"3936 S 6th Ave",
    "sg:city":"Tucson",
    "sg:classifiers":[
        {
            "category":"Personal",
            "subcategory":"Beauty Salon",
            "type":"Services"
        }
    ],
    "sg:phone":"+1 520 889 5557",
    "sg:postcode":"85714",
    "sg:province":"AZ",
    "wof:name":"Lupita's Styling Salon",
    "wof:placetype":"venue"
},
  "geometry": {"coordinates":[-110.968322,32.176291],"type":"Point"}
}