{
  "type": "Feature",
  "properties": {
    "iso:country":"US",
    "sg:address":"6336 N Oracle Rd",
    "sg:city":"Tucson",
    "sg:classifiers":[
        {
            "category":"Personal",
            "subcategory":"Beauty Salon",
            "type":"Services"
        }
    ],
    "sg:phone":"+1 520 235 1059",
    "sg:postcode":"85704",
    "sg:province":"AZ",
    "wof:name":"Johnsn Rayner Dba Hair Fl",
    "wof:placetype":"venue"
},
  "geometry": {"coordinates":[-110.974632,32.321911],"type":"Point"}
}