{
  "type": "Feature",
  "properties": {
    "iso:country":"US",
    "sg:address":"3437 S Jamaica Blvd",
    "sg:city":"Lake Havasu City",
    "sg:classifiers":[
        {
            "category":"Education",
            "subcategory":"School",
            "type":"Public Place"
        }
    ],
    "sg:phone":"+1 928 854 8660",
    "sg:postcode":"86406",
    "sg:province":"AZ",
    "wof:name":"Jamaica Elementary School",
    "wof:placetype":"venue"
},
  "geometry": {"coordinates":[-114.286368,34.492342],"type":"Point"}
}