{
  "type": "Feature",
  "properties": {
    "addr:full":"2069 N 107th Dr Avondale AZ 85392",
    "addr:housenumber":"2069",
    "addr:postcode":"85392",
    "addr:street":"N 107Th Dr",
    "iso:country":"US",
    "sg:address":"2069 N 107th Dr",
    "sg:city":"Avondale",
    "sg:classifiers":[
        {
            "category":"Retail",
            "subcategory":"Auto Rental",
            "type":"Services"
        }
    ],
    "sg:phone":"+1 480 226 5060",
    "sg:postcode":"85392",
    "sg:province":"AZ",
    "sg:tags":[
        "renting",
        "automobile"
    ],
    "wof:name":"Elite Car Rental Inc",
    "wof:placetype":"venue"
},
  "geometry": {"coordinates":[-112.29055,33.471317],"type":"Point"}
}