{
  "type": "Feature",
  "properties": {
    "addr:full":"3525 S Palo Verde Rd Tucson AZ 85713",
    "addr:housenumber":"3525",
    "addr:postcode":"85713",
    "addr:street":"S Palo Verde Rd",
    "iso:country":"US",
    "sg:address":"3525 S Palo Verde Rd",
    "sg:city":"Tucson",
    "sg:classifiers":[
        {
            "category":"Wholesale",
            "subcategory":"Machinery & Supplies",
            "type":"Manufacturing & Wholesale Goods"
        }
    ],
    "sg:phone":"+1 520 791 3026",
    "sg:postcode":"85713",
    "sg:province":"AZ",
    "sg:tags":[
        "distributor",
        "abrasive",
        "product",
        "industrial"
    ],
    "wof:name":"Tucson Abrasives LLC",
    "wof:placetype":"venue"
},
  "geometry": {"coordinates":[-110.91767900000001,32.182027],"type":"Point"}
}