{
  "type": "Feature",
  "properties": {
    "addr:full":"5060 Cactus Pl Prescott AZ 86301",
    "addr:housenumber":"5060",
    "addr:postcode":"86301",
    "addr:street":"Cactus Pl",
    "iso:country":"US",
    "sg:address":"5060 Cactus Pl",
    "sg:city":"Prescott",
    "sg:classifiers":[
        {
            "category":"Travel",
            "subcategory":"Travel Agent",
            "type":"Entertainment"
        }
    ],
    "sg:phone":"+1 928 778 3611",
    "sg:postcode":"86301",
    "sg:province":"AZ",
    "sg:tags":[
        "agency",
        "bureau"
    ],
    "sg:website":"www.prescott-travel.com",
    "wof:name":"Prescott Travel Agency",
    "wof:placetype":"venue"
},
  "geometry": {"coordinates":[-112.383386,34.557416],"type":"Point"}
}