{
  "type": "Feature",
  "properties": {
    "iso:country":"US",
    "sg:address":"2602 W Baseline Road",
    "sg:city":"Mesa",
    "sg:classifiers":[
        {
            "category":"Banks & Credit Unions",
            "subcategory":"Financial Services",
            "type":"Services"
        }
    ],
    "sg:phone":"+1 480 775 4323",
    "sg:postcode":"85202",
    "sg:province":"AZ",
    "sg:tags":[
        "broker",
        "mortgage"
    ],
    "wof:name":"Mpg Mortgage",
    "wof:placetype":"venue"
},
  "geometry": {"coordinates":[-111.89024000000001,33.378569],"type":"Point"}
}