{
  "type": "Feature",
  "properties": {
    "iso:country":"US",
    "sg:address":"4825 E Roosevelt St",
    "sg:city":"Phoenix",
    "sg:classifiers":[
        {
            "category":"Education",
            "subcategory":"School",
            "type":"Public Place"
        }
    ],
    "sg:phone":"+1 602 629 6400",
    "sg:postcode":"85008",
    "sg:province":"AZ",
    "wof:name":"Balsz School District",
    "wof:placetype":"venue"
},
  "geometry": {"coordinates":[-111.976175,33.458283],"type":"Point"}
}