{
  "type": "Feature",
  "properties": {
    "iso:country":"US",
    "sg:address":"2545 E Speedway Blvd",
    "sg:city":"Tucson",
    "sg:classifiers":[
        {
            "category":"Restaurant",
            "type":"Food & Drink"
        }
    ],
    "sg:phone":"+1 520 319 2559",
    "sg:postcode":"85716",
    "sg:province":"AZ",
    "sg:tags":[
        "eating"
    ],
    "sg:website":"www.alibaba.com",
    "wof:name":"Ali Baba Restaurant",
    "wof:placetype":"venue"
},
  "geometry": {"coordinates":[-110.934463,32.236149],"type":"Point"}
}