{
  "type": "Feature",
  "properties": {
    "iso:country":"US",
    "sg:address":"9175 E Indian Bend Rd",
    "sg:city":"Scottsdale",
    "sg:classifiers":[
        {
            "category":"Shopping",
            "subcategory":"Department Store",
            "type":"Retail Goods"
        },
        {
            "category":"Real Estate",
            "subcategory":"Real Estate Agent",
            "type":"Services"
        }
    ],
    "sg:phone":"+1 480 991 6007",
    "sg:postcode":"85250",
    "sg:province":"AZ",
    "wof:name":"Scottsdale Pavillions",
    "wof:placetype":"venue"
},
  "geometry": {"coordinates":[-111.885594,33.538355],"type":"Point"}
}