{
  "type": "Feature",
  "properties": {
    "addr:full":"7502 W Washington St Tolleson AZ 85353",
    "addr:housenumber":"7502",
    "addr:postcode":"85353",
    "addr:street":"W Washington St",
    "iso:country":"US",
    "sg:address":"7502 W Washington St",
    "sg:city":"Tolleson",
    "sg:classifiers":[
        {
            "category":"Autos & Motor Vehicles",
            "subcategory":"Auto Supplies",
            "type":"Retail Goods"
        }
    ],
    "sg:phone":"+1 623 936 5691",
    "sg:postcode":"85353",
    "sg:province":"AZ",
    "sg:tags":[
        "management"
    ],
    "wof:name":"Autozone",
    "wof:placetype":"venue"
},
  "geometry": {"coordinates":[-112.224402,33.448166],"type":"Point"}
}