{
  "type": "Feature",
  "properties": {
    "iso:country":"US",
    "sg:address":"2144 McCulloch Blvd N",
    "sg:city":"Lake Havasu City",
    "sg:classifiers":[
        {
            "category":"Shopping",
            "subcategory":"Bicycles & Sporting Goods",
            "type":"Retail Goods"
        }
    ],
    "sg:phone":"+1 928 855 3553",
    "sg:postcode":"86403",
    "sg:province":"AZ",
    "sg:tags":[
        "accessory"
    ],
    "wof:name":"Cycle Therapy Inc",
    "wof:placetype":"venue"
},
  "geometry": {"coordinates":[-114.326278,34.474787],"type":"Point"}
}