{
  "type": "Feature",
  "properties": {
    "iso:country":"US",
    "sg:address":"6401 E Aster Dr",
    "sg:city":"Scottsdale",
    "sg:classifiers":[
        {
            "category":"Organizations",
            "subcategory":"Religious Organization",
            "type":"Services"
        }
    ],
    "sg:phone":"+1 480 483 8777",
    "sg:postcode":"85254",
    "sg:province":"AZ",
    "sg:tags":[
        "church"
    ],
    "wof:name":"Logos Church & Holistic Ctr",
    "wof:placetype":"venue"
},
  "geometry": {"coordinates":[-111.939892,33.602827],"type":"Point"}
}