{
  "type": "Feature",
  "properties": {
    "addr:full":"1562 Marina Blvd Bullhead City AZ 86442",
    "addr:housenumber":"1562",
    "addr:postcode":"86442",
    "addr:street":"Marina Blvd",
    "iso:country":"US",
    "sg:address":"1562 Marina Blvd",
    "sg:city":"Bullhead City",
    "sg:classifiers":[
        {
            "category":"Restaurant",
            "type":"Food & Drink"
        }
    ],
    "sg:menulink":"http://www.allmenus.com/az/kingman-south/204820-taco-bell/menu/",
    "sg:postcode":"86442",
    "sg:province":"AZ",
    "sg:tags":[
        "mexican"
    ],
    "wof:name":"Taco Bell",
    "wof:placetype":"venue"
},
  "geometry": {"coordinates":[-114.59567699999999,35.101198],"type":"Point"}
}