{
  "type": "Feature",
  "properties": {
    "addr:full":"Arizona State University SkySong, Suite 200, 1475 N. Scottsdale Road Scottsdale AZ 85257",
    "addr:housenumber":"suite 200 1475 n.",
    "addr:postcode":"85257",
    "addr:street":"Arizona;Scottsdale Road",
    "iso:country":"US",
    "sg:address":"Arizona State University SkySong, Suite 200, 1475 N. Scottsdale Road",
    "sg:city":"Scottsdale",
    "sg:classifiers":[
        {
            "category":"Professional",
            "subcategory":"Computer Services",
            "type":"Services"
        }
    ],
    "sg:phone":"+1 480 884 1689",
    "sg:postcode":"85257",
    "sg:province":"AZ",
    "sg:website":"http://www.adaptivecurriculum.com",
    "wof:name":"Adaptive Curriculum",
    "wof:placetype":"venue"
},
  "geometry": {"coordinates":[-111.926427,33.453424],"type":"Point"}
}