{
  "type": "Feature",
  "properties": {
    "addr:full":"3126 W Thomas Rd Ste 104 Phoenix AZ 85017",
    "addr:housenumber":"3126",
    "addr:postcode":"85017",
    "addr:street":"W Thomas Rd Ste 104",
    "iso:country":"US",
    "sg:address":"3126 W Thomas Rd Ste 104",
    "sg:city":"Phoenix",
    "sg:classifiers":[
        {
            "category":"Home & Garden",
            "subcategory":"Furniture",
            "type":"Retail Goods"
        }
    ],
    "sg:phone":"+1 602 272 1133",
    "sg:postcode":"85017",
    "sg:province":"AZ",
    "sg:tags":[
        "equipment-household",
        "kitchen",
        "cabinet"
    ],
    "wof:name":"Dragon International Trading Inc",
    "wof:placetype":"venue"
},
  "geometry": {"coordinates":[-112.126705,33.480431],"type":"Point"}
}