{
  "type": "Feature",
  "properties": {
    "addr:full":"4613 E Cherry Hills Dr Chandler AZ 85249",
    "addr:housenumber":"4613",
    "addr:postcode":"85249",
    "addr:street":"E Cherry Hills Dr",
    "iso:country":"US",
    "sg:address":"4613 E Cherry Hills Dr",
    "sg:city":"Chandler",
    "sg:classifiers":[
        {
            "category":"Building & Trades",
            "subcategory":"Electrical",
            "type":"Services"
        }
    ],
    "sg:phone":"+1 480 219 9375",
    "sg:postcode":"85249",
    "sg:province":"AZ",
    "sg:tags":[
        "security",
        "telecommunication"
    ],
    "wof:name":"D L Brunson Home Systems",
    "wof:placetype":"venue"
},
  "geometry": {"coordinates":[-111.76039400000001,33.217039],"type":"Point"}
}