{
  "type": "Feature",
  "properties": {
    "addr:full":"2001 E Van Buren St Phoenix AZ 85006",
    "addr:housenumber":"2001",
    "addr:postcode":"85006",
    "addr:street":"E Van Buren St",
    "iso:country":"US",
    "sg:address":"2001 E Van Buren St",
    "sg:city":"Phoenix",
    "sg:classifiers":[
        {
            "category":"Restaurant",
            "type":"Food & Drink"
        }
    ],
    "sg:phone":"+1 602 253 8555",
    "sg:postcode":"85006",
    "sg:province":"AZ",
    "sg:tags":[
        "pizza"
    ],
    "wof:name":"Good Pizza Co",
    "wof:placetype":"venue"
},
  "geometry": {"coordinates":[-112.03898599999999,33.45142],"type":"Point"}
}