{
  "type": "Feature",
  "properties": {
    "iso:country":"US",
    "sg:address":"2929 N 37th Ave",
    "sg:city":"Phoenix",
    "sg:classifiers":[
        {
            "category":"Freight",
            "type":"Transportation"
        }
    ],
    "sg:phone":"+1 602 352 2060",
    "sg:postcode":"85019",
    "sg:province":"AZ",
    "sg:tags":[
        "operator",
        "local",
        "trucking"
    ],
    "wof:name":"UPS Delivery Info",
    "wof:placetype":"venue"
},
  "geometry": {"coordinates":[-112.138571,33.482238],"type":"Point"}
}