{
  "type": "Feature",
  "properties": {
    "iso:country":"US",
    "sg:address":"15199 W Paradise Ln",
    "sg:city":"Surprise",
    "sg:classifiers":[
        {
            "category":"Professional",
            "type":"Services"
        }
    ],
    "sg:phone":"+1 623 975 6085",
    "sg:postcode":"85374",
    "sg:province":"AZ",
    "wof:name":"James Mininger Incorporated",
    "wof:placetype":"venue"
},
  "geometry": {"coordinates":[-112.389955,33.631228],"type":"Point"}
}