{
  "type": "Feature",
  "properties": {
    "iso:country":"US",
    "sg:address":"5464 W Mohawk Ln",
    "sg:city":"Glendale",
    "sg:classifiers":[
        {
            "category":"Professional",
            "type":"Services"
        }
    ],
    "sg:phone":"+1 623 572 8707",
    "sg:postcode":"85308",
    "sg:province":"AZ",
    "wof:name":"Kurt Dodge",
    "wof:placetype":"venue"
},
  "geometry": {"coordinates":[-112.17641,33.672351],"type":"Point"}
}