{
  "type": "Feature",
  "properties": {
    "iso:country":"US",
    "sg:address":"10416 N 101st St",
    "sg:city":"Scottsdale",
    "sg:classifiers":[
        {
            "category":"Building & Trades",
            "subcategory":"Construction",
            "type":"Services"
        }
    ],
    "sg:phone":"+1 480 998 0703",
    "sg:postcode":"85258",
    "sg:province":"AZ",
    "sg:tags":[
        "residential"
    ],
    "wof:name":"Surety West Inc",
    "wof:placetype":"venue"
},
  "geometry": {"coordinates":[-111.863816,33.580766],"type":"Point"}
}