{
  "type": "Feature",
  "properties": {
    "iso:country":"US",
    "sg:address":"4752 S Tennessee Pl",
    "sg:city":"Tucson",
    "sg:classifiers":[
        {
            "category":"Wholesale",
            "subcategory":"Construction Materials",
            "type":"Manufacturing & Wholesale Goods"
        }
    ],
    "sg:phone":"+1 520 750 9800",
    "sg:postcode":"85714",
    "sg:province":"AZ",
    "sg:tags":[
        "house"
    ],
    "wof:name":"Shed Depot",
    "wof:placetype":"venue"
},
  "geometry": {"coordinates":[-110.905857,32.165686],"type":"Point"}
}