{
  "type": "Feature",
  "properties": {
    "addr:full":"3854 E Fort Lowell Rd Tucson AZ 85716",
    "addr:housenumber":"3854",
    "addr:postcode":"85716",
    "addr:street":"E Fort Lowell Rd",
    "iso:country":"US",
    "sg:address":"3854 E Fort Lowell Rd",
    "sg:city":"Tucson",
    "sg:classifiers":[
        {
            "category":"Personal",
            "subcategory":"Beauty Salon",
            "type":"Services"
        }
    ],
    "sg:phone":"+1 520 327 0407",
    "sg:postcode":"85716",
    "sg:province":"AZ",
    "wof:name":"Designing Heads",
    "wof:placetype":"venue"
},
  "geometry": {"coordinates":[-110.91036,32.265041],"type":"Point"}
}