{
  "type": "Feature",
  "properties": {
    "iso:country":"US",
    "sg:address":"4540 N 7th St",
    "sg:city":"Phoenix",
    "sg:classifiers":[
        {
            "category":"Cafe",
            "type":"Food & Drink"
        },
        {
            "category":"Restaurant",
            "type":"Food & Drink"
        }
    ],
    "sg:menulink":"http://www.allmenus.com/az/phoenix/4441-pookies-cafe/menu/",
    "sg:phone":"+1 602 277 2121",
    "sg:postcode":"85014",
    "sg:province":"AZ",
    "sg:tags":[
        "american"
    ],
    "wof:name":"Pookie's Cafe",
    "wof:placetype":"venue"
},
  "geometry": {"coordinates":[-112.06501900000001,33.503148],"type":"Point"}
}