{
  "type": "Feature",
  "properties": {
    "addr:full":"2801 E Adams Show Low AZ 85901",
    "addr:housenumber":"2801",
    "addr:postcode":"85901",
    "addr:street":"E",
    "iso:country":"US",
    "sg:address":"2801 E Adams",
    "sg:city":"Show Low",
    "sg:classifiers":[
        {
            "category":"Retail",
            "subcategory":"Auto Repair",
            "type":"Services"
        }
    ],
    "sg:phone":"+1 928 537 2001",
    "sg:postcode":"85901",
    "sg:province":"AZ",
    "sg:tags":[
        "body",
        "automobile",
        "painting"
    ],
    "wof:name":"DMC Auto Rebuilders",
    "wof:placetype":"venue"
},
  "geometry": {"coordinates":[-110.01187400000001,34.256904],"type":"Point"}
}