{
  "type": "Feature",
  "properties": {
    "iso:country":"US",
    "sg:address":"2302 E Buffalo St",
    "sg:city":"Chandler",
    "sg:classifiers":[
        {
            "category":"Wholesale",
            "subcategory":"Durable Goods & Equipment",
            "type":"Manufacturing & Wholesale Goods"
        }
    ],
    "sg:phone":"+1 480 899 5010",
    "sg:postcode":"85225",
    "sg:province":"AZ",
    "sg:tags":[
        "professional"
    ],
    "wof:name":"Eagles Sales",
    "wof:placetype":"venue"
},
  "geometry": {"coordinates":[-111.80158,33.305096],"type":"Point"}
}