{
  "type": "Feature",
  "properties": {
    "iso:country":"US",
    "sg:address":"3049 N 53rd Dr",
    "sg:city":"Phoenix",
    "sg:classifiers":[
        {
            "category":"Personal",
            "subcategory":"Nail Salon",
            "type":"Services"
        }
    ],
    "sg:phone":"+1 623 243 7447",
    "sg:postcode":"85031",
    "sg:province":"AZ",
    "wof:name":"Tabbys Nail Salon",
    "wof:placetype":"venue"
},
  "geometry": {"coordinates":[-112.174356,33.483927],"type":"Point"}
}