{
  "type": "Feature",
  "properties": {
    "iso:country":"US",
    "sg:address":"3256 S 80th St",
    "sg:city":"Mesa",
    "sg:classifiers":[
        {
            "category":"Retail",
            "subcategory":"Auto Repair",
            "type":"Services"
        }
    ],
    "sg:phone":"+1 480 986 5811",
    "sg:postcode":"85212",
    "sg:province":"AZ",
    "sg:tags":[
        "repairing",
        "automobile"
    ],
    "wof:name":"Lee's Auto Repair",
    "wof:placetype":"venue"
},
  "geometry": {"coordinates":[-111.662004,33.356182],"type":"Point"}
}