{
  "type": "Feature",
  "properties": {
    "addr:full":"245 S Power Rd Mesa AZ 85206",
    "addr:housenumber":"245",
    "addr:postcode":"85206",
    "addr:street":"S Power Rd",
    "iso:country":"US",
    "sg:address":"245 S Power Rd",
    "sg:city":"Mesa",
    "sg:classifiers":[
        {
            "category":"Retail",
            "subcategory":"Car Wash",
            "type":"Services"
        }
    ],
    "sg:phone":"+1 480 396 1122",
    "sg:postcode":"85206",
    "sg:province":"AZ",
    "sg:tags":[
        "polishing",
        "washing"
    ],
    "wof:name":"Indy Auto Wash",
    "wof:placetype":"venue"
},
  "geometry": {"coordinates":[-111.68446900000001,33.411166],"type":"Point"}
}