{
  "type": "Feature",
  "properties": {
    "iso:country":"US",
    "sg:address":"8856 E Windrose Dr",
    "sg:city":"Scottsdale",
    "sg:classifiers":[
        {
            "category":"Manufacturing",
            "subcategory":"Apparel",
            "type":"Manufacturing & Wholesale Goods"
        }
    ],
    "sg:phone":"+1 480 628 6689",
    "sg:postcode":"85260",
    "sg:province":"AZ",
    "sg:tags":[
        "product",
        "mfg",
        "pet",
        "supply",
        "fabricated",
        "textile",
        "foods-wholesale",
        "manufacturer"
    ],
    "wof:name":"Pawz In City",
    "wof:placetype":"venue"
},
  "geometry": {"coordinates":[-111.889906,33.602312],"type":"Point"}
}