{
  "type": "Feature",
  "properties": {
    "iso:country":"US",
    "sg:address":"8607 N 59th Ave",
    "sg:city":"Glendale",
    "sg:classifiers":[
        {
            "category":"Wholesale",
            "subcategory":"Jewelry",
            "type":"Manufacturing & Wholesale Goods"
        }
    ],
    "sg:phone":"+1 623 930 7755",
    "sg:postcode":"85302",
    "sg:province":"AZ",
    "sg:tags":[
        "stone",
        "watch"
    ],
    "wof:name":"Marian Imports",
    "wof:placetype":"venue"
},
  "geometry": {"coordinates":[-112.186176,33.563239],"type":"Point"}
}