{
  "type": "Feature",
  "properties": {
    "iso:country":"US",
    "sg:address":"609 E Hwy 89A",
    "sg:city":"Cottonwood",
    "sg:classifiers":[
        {
            "category":"Restaurant",
            "type":"Food & Drink"
        }
    ],
    "sg:phone":"+1 928 634 6310",
    "sg:postcode":"86326",
    "sg:province":"AZ",
    "wof:name":"Mesquite Grill & Bbq",
    "wof:placetype":"venue"
},
  "geometry": {"coordinates":[-112.022737,34.729543],"type":"Point"}
}