{
  "type": "Feature",
  "properties": {
    "iso:country":"US",
    "sg:address":"860 E Broadway Blvd",
    "sg:city":"Tucson",
    "sg:classifiers":[
        {
            "category":"Shopping",
            "subcategory":"Stationery & Office Supplies",
            "type":"Retail Goods"
        }
    ],
    "sg:phone":"+1 520 882 6659",
    "sg:postcode":"85719",
    "sg:province":"AZ",
    "wof:name":"Office Max",
    "wof:placetype":"venue"
},
  "geometry": {"coordinates":[-110.95873400000001,32.221286],"type":"Point"}
}