{
  "type": "Feature",
  "properties": {
    "iso:country":"US",
    "sg:address":"6825 N 16th St Ste 7",
    "sg:city":"Phoenix",
    "sg:classifiers":[
        {
            "category":"Professional",
            "subcategory":"Accounting & Tax Preparation",
            "type":"Services"
        },
        {
            "category":"Wholesale",
            "subcategory":"Office Equipment",
            "type":"Manufacturing & Wholesale Goods"
        },
        {
            "category":"Banks & Credit Unions",
            "subcategory":"Financial Services",
            "type":"Services"
        }
    ],
    "sg:phone":"+1 623 738 1684",
    "sg:postcode":"85016",
    "sg:province":"AZ",
    "sg:tags":[
        "return",
        "preparation-business",
        "taxes-consultants",
        "loan",
        "supply",
        "machine",
        "representative",
        "alternative",
        "bookkeeping"
    ],
    "sg:website":"http://phoenix.citysearch.com/profile/external/610254010/phoenix_az/h_r_block.html?publisher=yellowpages&reference_id=1&placement=ypwebsitemip",
    "wof:name":"H&R BLOCK",
    "wof:placetype":"venue"
},
  "geometry": {"coordinates":[-112.047493,33.536876],"type":"Point"}
}