{
  "type": "Feature",
  "properties": {
    "addr:full":"3944 N Brown Ave Scottsdale AZ 85251",
    "addr:housenumber":"3944",
    "addr:postcode":"85251",
    "addr:street":"N Brown Ave",
    "iso:country":"US",
    "sg:address":"3944 N Brown Ave",
    "sg:city":"Scottsdale",
    "sg:classifiers":[
        {
            "category":"Building & Trades",
            "subcategory":"Construction",
            "type":"Services"
        }
    ],
    "sg:phone":"+1 480 946 3434",
    "sg:postcode":"85251",
    "sg:province":"AZ",
    "sg:tags":[
        "altering",
        "remodeling",
        "contractor"
    ],
    "wof:name":"Rent My Husband Home Repairs",
    "wof:placetype":"venue"
},
  "geometry": {"coordinates":[-111.92453,33.493306],"type":"Point"}
}