{
  "type": "Feature",
  "properties": {
    "iso:country":"US",
    "sg:address":"2403 N Pebble Creek Pkwy",
    "sg:city":"Goodyear",
    "sg:classifiers":[
        {
            "category":"Building & Trades",
            "subcategory":"Locksmith",
            "type":"Services"
        }
    ],
    "sg:phone":"+1 866 242 4838",
    "sg:postcode":"85395",
    "sg:province":"AZ",
    "sg:tags":[
        "key"
    ],
    "wof:name":"24 Hour 7 Day Emergency Locksmith",
    "wof:placetype":"venue"
},
  "geometry": {"coordinates":[-112.392162,33.473313],"type":"Point"}
}