{
  "type": "Feature",
  "properties": {
    "addr:full":"4390 N Miller Rd Scottsdale AZ 85251",
    "addr:housenumber":"4390",
    "addr:postcode":"85251",
    "addr:street":"N Miller Rd",
    "iso:country":"US",
    "sg:address":"4390 N Miller Rd",
    "sg:city":"Scottsdale",
    "sg:classifiers":[
        {
            "category":"Bakery",
            "type":"Food & Drink"
        }
    ],
    "sg:phone":"+1 480 946 2737",
    "sg:postcode":"85251",
    "sg:province":"AZ",
    "sg:tags":[
        "cake",
        "pastry",
        "wedding"
    ],
    "wof:name":"Ithink On My Cake",
    "wof:placetype":"venue"
},
  "geometry": {"coordinates":[-111.917526,33.499806],"type":"Point"}
}