{
  "type": "Feature",
  "properties": {
    "iso:country":"US",
    "sg:address":"1897 W Apache Trl",
    "sg:city":"Apache Junction",
    "sg:classifiers":[
        {
            "category":"Restaurant",
            "type":"Food & Drink"
        }
    ],
    "sg:menulink":"http://www.allmenus.com/az/north-pinal/31890-los-favoritos-taco-shop/menu/",
    "sg:phone":"+1 480 982 1860",
    "sg:postcode":"85220",
    "sg:province":"AZ",
    "sg:tags":[
        "mexican"
    ],
    "wof:name":"Los Favoritos Taco Shop",
    "wof:placetype":"venue"
},
  "geometry": {"coordinates":[-111.566616,33.415091],"type":"Point"}
}