{
  "type": "Feature",
  "properties": {
    "iso:country":"US",
    "sg:address":"1670 N Kolb Rd",
    "sg:city":"Tucson",
    "sg:classifiers":[
        {
            "category":"Insurance",
            "subcategory":"Insurance Agent",
            "type":"Services"
        }
    ],
    "sg:phone":"+1 520 546 8800",
    "sg:postcode":"85715",
    "sg:province":"AZ",
    "wof:name":"Aflac",
    "wof:placetype":"venue"
},
  "geometry": {"coordinates":[-110.845889,32.245025],"type":"Point"}
}