{
  "type": "Feature",
  "properties": {
    "iso:country":"US",
    "sg:address":"4646 E Bowker St",
    "sg:city":"Phoenix",
    "sg:classifiers":[
        {
            "category":"Freight",
            "type":"Transportation"
        }
    ],
    "sg:phone":"+1 602 438 8166",
    "sg:postcode":"85040",
    "sg:province":"AZ",
    "sg:tags":[
        "courier"
    ],
    "wof:name":"Geaux Gaty",
    "wof:placetype":"venue"
},
  "geometry": {"coordinates":[-111.9808,33.396715],"type":"Point"}
}