{
  "type": "Feature",
  "properties": {
    "iso:country":"US",
    "sg:address":"1825 E Apache Blvd",
    "sg:city":"Tempe",
    "sg:classifiers":[
        {
            "category":"Bars & Pubs",
            "type":"Food & Drink"
        }
    ],
    "sg:phone":"+1 480 966 2896",
    "sg:postcode":"85281",
    "sg:province":"AZ",
    "sg:tags":[
        "drinking"
    ],
    "wof:name":"Champion Sports Bar",
    "wof:placetype":"venue"
},
  "geometry": {"coordinates":[-111.907107,33.414775],"type":"Point"}
}