{
  "type": "Feature",
  "properties": {
    "iso:country":"US",
    "sg:address":"7909 W Glendale Ave",
    "sg:city":"Glendale",
    "sg:classifiers":[
        {
            "category":"Real Estate",
            "subcategory":"Real Estate Services",
            "type":"Services"
        },
        {
            "category":"Real Estate",
            "subcategory":"Real Estate Agent",
            "type":"Services"
        }
    ],
    "sg:phone":"+1 623 930 7355",
    "sg:postcode":"85303",
    "sg:province":"AZ",
    "sg:tags":[
        "buyer",
        "management",
        "broker"
    ],
    "wof:name":"Cc Fox Realty",
    "wof:placetype":"venue"
},
  "geometry": {"coordinates":[-112.229479,33.537747],"type":"Point"}
}