{
  "type": "Feature",
  "properties": {
    "iso:country":"US",
    "sg:address":"1111 E Mcdowell Rd",
    "sg:city":"Phoenix",
    "sg:classifiers":[
        {
            "category":"Health Services",
            "subcategory":"Doctor",
            "type":"Services"
        }
    ],
    "sg:phone":"+1 602 251 3895",
    "sg:postcode":"85006",
    "sg:province":"AZ",
    "sg:tags":[
        "physician",
        "pediatrics-emergency",
        "pediatrics",
        "surgeons",
        "medicine",
        "surgeon"
    ],
    "wof:name":"Pediatrix",
    "wof:placetype":"venue"
},
  "geometry": {"coordinates":[-112.058303,33.46571],"type":"Point"}
}