{
  "type": "Feature",
  "properties": {
    "addr:full":"100 Swanson Ave Lake Havasu City AZ 86403",
    "addr:housenumber":"100",
    "addr:postcode":"86403",
    "addr:street":"Swanson Ave",
    "iso:country":"US",
    "sg:address":"100 Swanson Ave",
    "sg:city":"Lake Havasu City",
    "sg:classifiers":[
        {
            "category":"Restaurant",
            "type":"Food & Drink"
        }
    ],
    "sg:phone":"+1 928 855 1039",
    "sg:postcode":"86403",
    "sg:province":"AZ",
    "wof:name":"Mc Donald's",
    "wof:placetype":"venue"
},
  "geometry": {"coordinates":[-114.34358,34.470209],"type":"Point"}
}