{
  "type": "Feature",
  "properties": {
    "iso:country":"US",
    "sg:address":"8245 N 27th Ave",
    "sg:city":"Phoenix",
    "sg:classifiers":[
        {
            "category":"Real Estate",
            "subcategory":"Real Estate Operator",
            "type":"Services"
        }
    ],
    "sg:phone":"+1 602 995 4433",
    "sg:postcode":"85051",
    "sg:province":"AZ",
    "sg:tags":[
        "building",
        "apartment"
    ],
    "wof:name":"Desert Lakes Apartments",
    "wof:placetype":"venue"
},
  "geometry": {"coordinates":[-112.11687499999999,33.557849],"type":"Point"}
}