{
  "type": "Feature",
  "properties": {
    "iso:country":"US",
    "sg:address":"6210 E Cave Creek Rd",
    "sg:city":"Cave Creek",
    "sg:classifiers":[
        {
            "category":"Food & Beverages",
            "subcategory":"Groceries & Convenience Stores",
            "type":"Retail Goods"
        }
    ],
    "sg:phone":"+1 480 575 8898",
    "sg:postcode":"85331",
    "sg:province":"AZ",
    "wof:name":"Circle K",
    "wof:placetype":"venue"
},
  "geometry": {"coordinates":[-111.947255,33.832161],"type":"Point"}
}