{
  "type": "Feature",
  "properties": {
    "iso:country":"US",
    "sg:address":"6320 E Main St",
    "sg:city":"Mesa",
    "sg:classifiers":[
        {
            "category":"Restaurant",
            "type":"Food & Drink"
        }
    ],
    "sg:phone":"+1 480 854 4815",
    "sg:postcode":"85205",
    "sg:province":"AZ",
    "wof:name":"Bizkits & Gravey",
    "wof:placetype":"venue"
},
  "geometry": {"coordinates":[-111.694712,33.415721],"type":"Point"}
}