{
  "type": "Feature",
  "properties": {
    "addr:full":"940 W Apache Trl Apache Junction AZ 85220",
    "addr:housenumber":"940",
    "addr:postcode":"85220",
    "addr:street":"W Apache Trl",
    "iso:country":"US",
    "sg:address":"940 W Apache Trl",
    "sg:city":"Apache Junction",
    "sg:classifiers":[
        {
            "category":"Home & Garden",
            "subcategory":"Hardware",
            "type":"Retail Goods"
        }
    ],
    "sg:phone":"+1 480 983 3484",
    "sg:postcode":"85220",
    "sg:province":"AZ",
    "sg:tags":[
        "lt",
        "mining",
        "supply"
    ],
    "wof:name":"Pro-Mack South",
    "wof:placetype":"venue"
},
  "geometry": {"coordinates":[-111.55649699999999,33.415127],"type":"Point"}
}