{
  "type": "Feature",
  "properties": {
    "iso:country":"US",
    "sg:address":"6209 W Rose Garden Ln",
    "sg:city":"Glendale",
    "sg:classifiers":[
        {
            "category":"Freight",
            "type":"Transportation"
        }
    ],
    "sg:phone":"+1 623 376 0527",
    "sg:postcode":"85308",
    "sg:province":"AZ",
    "sg:tags":[
        "operator",
        "local",
        "trucking"
    ],
    "wof:name":"Rolling Rock Hauling LLC",
    "wof:placetype":"venue"
},
  "geometry": {"coordinates":[-112.194276,33.675719],"type":"Point"}
}