{
  "type": "Feature",
  "properties": {
    "iso:country":"US",
    "sg:address":"1240 E Bethany Home Rd",
    "sg:city":"Phoenix",
    "sg:classifiers":[
        {
            "category":"Professional",
            "type":"Services"
        }
    ],
    "sg:phone":"+1 602 266 1196",
    "sg:postcode":"85014",
    "sg:province":"AZ",
    "wof:name":"Crump PLC",
    "wof:placetype":"venue"
},
  "geometry": {"coordinates":[-112.055702,33.523803],"type":"Point"}
}