{
  "type": "Feature",
  "properties": {
    "iso:country":"US",
    "sg:address":"10846 E Dragoon Ave",
    "sg:city":"Mesa",
    "sg:classifiers":[
        {
            "category":"Professional",
            "type":"Services"
        }
    ],
    "sg:phone":"+1 480 354 8574",
    "sg:postcode":"85208",
    "sg:province":"AZ",
    "wof:name":"Diane Holden",
    "wof:placetype":"venue"
},
  "geometry": {"coordinates":[-111.594915,33.402776],"type":"Point"}
}