{
  "type": "Feature",
  "properties": {
    "iso:country":"US",
    "sg:address":"228 W Fry Blvd",
    "sg:city":"Sierra Vista",
    "sg:classifiers":[
        {
            "category":"Shopping",
            "subcategory":"Gifts & Souvenirs",
            "type":"Retail Goods"
        }
    ],
    "sg:phone":"+1 520 458 7208",
    "sg:postcode":"85635",
    "sg:province":"AZ",
    "sg:tags":[
        "shop",
        "mail",
        "order"
    ],
    "wof:name":"Misty's Gift Gallery",
    "wof:placetype":"venue"
},
  "geometry": {"coordinates":[-110.301873,31.554422],"type":"Point"}
}