{
  "type": "Feature",
  "properties": {
    "iso:country":"US",
    "sg:address":"10820 N 43rd St",
    "sg:city":"Phoenix",
    "sg:classifiers":[
        {
            "category":"Arts & Performance",
            "subcategory":"Dance",
            "type":"Entertainment"
        }
    ],
    "sg:phone":"+1 602 548 0460",
    "sg:postcode":"85028",
    "sg:province":"AZ",
    "sg:tags":[
        "instruction",
        "dancing"
    ],
    "wof:name":"Leap of Faith Dance Plus",
    "wof:placetype":"venue"
},
  "geometry": {"coordinates":[-111.987717,33.584751],"type":"Point"}
}