{
  "type": "Feature",
  "properties": {
    "iso:country":"US",
    "sg:address":"3134 E McKellips Rd",
    "sg:city":"Mesa",
    "sg:classifiers":[
        {
            "category":"Building & Trades",
            "subcategory":"Plumbing",
            "type":"Services"
        }
    ],
    "sg:phone":"+1 480 330 0789",
    "sg:postcode":"85213",
    "sg:province":"AZ",
    "sg:tags":[
        "contractor"
    ],
    "wof:name":"Vertical Plumbing",
    "wof:placetype":"venue"
},
  "geometry": {"coordinates":[-111.76259,33.451841],"type":"Point"}
}