{
  "type": "Feature",
  "properties": {
    "iso:country":"US",
    "sg:address":"5410 E White Pine Dr",
    "sg:city":"Cave Creek",
    "sg:classifiers":[
        {
            "category":"Utilities",
            "subcategory":"Telephone",
            "type":"Services"
        }
    ],
    "sg:phone":"+1 480 473 4766",
    "sg:postcode":"85331",
    "sg:province":"AZ",
    "sg:tags":[
        "company"
    ],
    "wof:name":"British Telecom",
    "wof:placetype":"venue"
},
  "geometry": {"coordinates":[-111.962538,33.776472],"type":"Point"}
}