{
  "type": "Feature",
  "properties": {
    "iso:country":"US",
    "sg:address":"11056 N 23rd Dr",
    "sg:city":"Phoenix",
    "sg:classifiers":[
        {
            "category":"Manufacturing",
            "subcategory":"Printing",
            "type":"Manufacturing & Wholesale Goods"
        }
    ],
    "sg:phone":"+1 623 247 8888",
    "sg:postcode":"85029",
    "sg:province":"AZ",
    "sg:tags":[
        "publishing",
        "periodical"
    ],
    "wof:name":"Trader Publishing Company",
    "wof:placetype":"venue"
},
  "geometry": {"coordinates":[-112.109937,33.587581],"type":"Point"}
}