{
  "type": "Feature",
  "properties": {
    "iso:country":"US",
    "sg:address":"7418 E Helm Dr",
    "sg:city":"Scottsdale",
    "sg:classifiers":[
        {
            "category":"Education",
            "subcategory":"School",
            "type":"Public Place"
        }
    ],
    "sg:phone":"+1 480 951 6545",
    "sg:postcode":"85260",
    "sg:province":"AZ",
    "wof:name":"Discovery Detective Academy",
    "wof:placetype":"venue"
},
  "geometry": {"coordinates":[-111.919497,33.620809],"type":"Point"}
}