{
  "type": "Feature",
  "properties": {
    "iso:country":"US",
    "sg:address":"202 E 2nd St",
    "sg:city":"Winslow",
    "sg:classifiers":[
        {
            "category":"Insurance",
            "subcategory":"Insurance Agent",
            "type":"Services"
        }
    ],
    "sg:phone":"+1 928 289 0900",
    "sg:postcode":"86047",
    "sg:province":"AZ",
    "wof:name":"Williams Insurance",
    "wof:placetype":"venue"
},
  "geometry": {"coordinates":[-110.696893,35.022956],"type":"Point"}
}