{
  "type": "Feature",
  "properties": {
    "iso:country":"US",
    "sg:address":"11808 N 64th St",
    "sg:city":"Scottsdale",
    "sg:classifiers":[
        {
            "category":"Education",
            "subcategory":"School",
            "type":"Public Place"
        }
    ],
    "sg:phone":"+1 480 484 3200",
    "sg:postcode":"85254",
    "sg:province":"AZ",
    "wof:name":"Sequoya Elementary School",
    "wof:placetype":"venue"
},
  "geometry": {"coordinates":[-111.943388,33.590529],"type":"Point"}
}