{
  "type": "Feature",
  "properties": {
    "iso:country":"US",
    "sg:address":"11315 E Appaloosa Pl",
    "sg:city":"Scottsdale",
    "sg:classifiers":[
        {
            "category":"Real Estate",
            "subcategory":"Real Estate Agent",
            "type":"Services"
        }
    ],
    "sg:phone":"+1 480 860 1192",
    "sg:postcode":"85259",
    "sg:province":"AZ",
    "wof:name":"Cabo Management LLC",
    "wof:placetype":"venue"
},
  "geometry": {"coordinates":[-111.833992,33.574287],"type":"Point"}
}