{
  "type": "Feature",
  "properties": {
    "iso:country":"US",
    "sg:address":"40 E 14th St",
    "sg:city":"Tucson",
    "sg:classifiers":[
        {
            "category":"Professional",
            "type":"Services"
        }
    ],
    "sg:phone":"+1 520 884 5188",
    "sg:postcode":"85701",
    "sg:province":"AZ",
    "sg:tags":[
        "establishment"
    ],
    "wof:name":"LA Frontera Ctr",
    "wof:placetype":"venue"
},
  "geometry": {"coordinates":[-110.969356,32.217177],"type":"Point"}
}