{
  "type": "Feature",
  "properties": {
    "addr:full":"884 W Warner Road Suite B3 Gilbert AZ 85233",
    "addr:housenumber":"884",
    "addr:postcode":"85233",
    "addr:street":"W Warner Road Suite B3",
    "iso:country":"US",
    "sg:address":"884 W Warner Road Suite B3",
    "sg:city":"Gilbert",
    "sg:classifiers":[
        {
            "category":"Personal",
            "subcategory":"Barber",
            "type":"Services"
        }
    ],
    "sg:phone":"+1 480 632 5983",
    "sg:postcode":"85233",
    "sg:province":"AZ",
    "wof:name":"Supercuts",
    "wof:placetype":"venue"
},
  "geometry": {"coordinates":[-111.808545,33.335431],"type":"Point"}
}