{
  "type": "Feature",
  "properties": {
    "iso:country":"US",
    "sg:address":"4055 N Runway Dr",
    "sg:city":"Tucson",
    "sg:classifiers":[
        {
            "category":"Shopping",
            "subcategory":"Bicycles & Sporting Goods",
            "type":"Retail Goods"
        },
        {
            "category":"Wholesale",
            "subcategory":"Chemicals & Plastics",
            "type":"Manufacturing & Wholesale Goods"
        },
        {
            "category":"Manufacturing",
            "subcategory":"Building Materials",
            "type":"Manufacturing & Wholesale Goods"
        },
        {
            "category":"Government",
            "subcategory":"Post Office",
            "type":"Public Place"
        }
    ],
    "sg:phone":"+1 520 884 9010",
    "sg:postcode":"85705",
    "sg:province":"AZ",
    "sg:tags":[
        "supply",
        "equipment",
        "painter",
        "distributor",
        "manufacturer",
        "supplies-wholesale",
        "pool",
        "swimming"
    ],
    "sg:website":"http://www.fwpools.com",
    "wof:name":"Superior Pool Products 511",
    "wof:placetype":"venue"
},
  "geometry": {"coordinates":[-111.014302,32.280721],"type":"Point"}
}