{
  "type": "Feature",
  "properties": {
    "addr:full":"2510 W Dunlap Ave Phoenix AZ 85021",
    "addr:housenumber":"2510",
    "addr:postcode":"85021",
    "addr:street":"W Dunlap Ave",
    "iso:country":"US",
    "sg:address":"2510 W Dunlap Ave",
    "sg:city":"Phoenix",
    "sg:classifiers":[
        {
            "category":"Wholesale",
            "subcategory":"Electrical",
            "type":"Manufacturing & Wholesale Goods"
        }
    ],
    "sg:phone":"+1 602 678 1711",
    "sg:postcode":"85021",
    "sg:province":"AZ",
    "sg:tags":[
        "supply"
    ],
    "wof:name":"CBS",
    "wof:placetype":"venue"
},
  "geometry": {"coordinates":[-112.116663,33.56765],"type":"Point"}
}