{
  "type": "Feature",
  "properties": {
    "addr:full":"120 S Houghton Rd Ste 118 Tucson AZ 85748",
    "addr:housenumber":"120",
    "addr:postcode":"85748",
    "addr:street":"S Houghton Rd Ste 118",
    "iso:country":"US",
    "sg:address":"120 S Houghton Rd Ste 118",
    "sg:city":"Tucson",
    "sg:classifiers":[
        {
            "category":"Building & Trades",
            "subcategory":"Pest Control",
            "type":"Services"
        }
    ],
    "sg:phone":"+1 520 296 3783",
    "sg:postcode":"85748",
    "sg:province":"AZ",
    "sg:tags":[
        "industrial",
        "services-commercial"
    ],
    "sg:website":"http://www.terminix.com",
    "wof:name":"Mighty National Cecil Dooley Exterminating Services",
    "wof:placetype":"venue"
},
  "geometry": {"coordinates":[-110.772722,32.219046],"type":"Point"}
}