{
  "type": "Feature",
  "properties": {
    "iso:country":"US",
    "sg:address":"4920 S Wendler Dr Ste 110",
    "sg:city":"Tempe",
    "sg:classifiers":[
        {
            "category":"Professional",
            "subcategory":"Business Services",
            "type":"Services"
        }
    ],
    "sg:phone":"+1 602 437 5588",
    "sg:postcode":"85282",
    "sg:province":"AZ",
    "sg:tags":[
        "testing"
    ],
    "wof:name":"Prometric Testing",
    "wof:placetype":"venue"
},
  "geometry": {"coordinates":[-111.969717,33.38067],"type":"Point"}
}