{
  "type": "Feature",
  "properties": {
    "addr:full":"320 N Thorpe Rd Flagstaff AZ 86001",
    "addr:housenumber":"320",
    "addr:postcode":"86001",
    "addr:street":"N Thorpe Rd",
    "iso:country":"US",
    "sg:address":"320 N Thorpe Rd",
    "sg:city":"Flagstaff",
    "sg:classifiers":[
        {
            "category":"Government",
            "subcategory":"Office",
            "type":"Public Place"
        }
    ],
    "sg:phone":"+1 928 773 3310",
    "sg:postcode":"86001",
    "sg:province":"AZ",
    "sg:tags":[
        "federal",
        "security"
    ],
    "wof:name":"Army National Guard Recruiter",
    "wof:placetype":"venue"
},
  "geometry": {"coordinates":[-111.658311,35.204094],"type":"Point"}
}