{
  "type": "Feature",
  "properties": {
    "iso:country":"US",
    "sg:address":"14201 N 87th St",
    "sg:city":"Scottsdale",
    "sg:classifiers":[
        {
            "category":"Professional",
            "subcategory":"Management & Consulting",
            "type":"Services"
        }
    ],
    "sg:phone":"+1 480 948 3197",
    "sg:postcode":"85260",
    "sg:province":"AZ",
    "sg:tags":[
        "marketing",
        "program"
    ],
    "wof:name":"Online Marketing",
    "wof:placetype":"venue"
},
  "geometry": {"coordinates":[-111.894697,33.613747],"type":"Point"}
}