{
  "type": "Feature",
  "properties": {
    "addr:full":"14 Les Springs Dr Sedona AZ 86336",
    "addr:housenumber":"14",
    "addr:postcode":"86336",
    "addr:street":"Les Springs Dr",
    "iso:country":"US",
    "sg:address":"14 Les Springs Dr",
    "sg:city":"Sedona",
    "sg:classifiers":[
        {
            "category":"Organizations",
            "subcategory":"Community Association",
            "type":"Services"
        }
    ],
    "sg:phone":"+1 928 203 4502",
    "sg:postcode":"86336",
    "sg:province":"AZ",
    "sg:tags":[
        "program",
        "incentive"
    ],
    "wof:name":"Creative Promotions & Incentives Inc",
    "wof:placetype":"venue"
},
  "geometry": {"coordinates":[-111.77660400000001,34.863232],"type":"Point"}
}