{
  "type": "Feature",
  "properties": {
    "iso:country":"US",
    "sg:address":"11459 N 28th Dr",
    "sg:city":"Phoenix",
    "sg:classifiers":[
        {
            "category":"Professional",
            "subcategory":"Accounting & Tax Preparation",
            "type":"Services"
        },
        {
            "category":"Arts & Performance",
            "subcategory":"Art Gallery",
            "type":"Entertainment"
        },
        {
            "category":"Professional",
            "subcategory":"Business Services",
            "type":"Services"
        },
        {
            "category":"Professional",
            "subcategory":"Printing & Photocopies",
            "type":"Services"
        },
        {
            "category":"Manufacturing",
            "subcategory":"Paper Products",
            "type":"Manufacturing & Wholesale Goods"
        }
    ],
    "sg:phone":"+1 480 389 9856",
    "sg:postcode":"85029",
    "sg:province":"AZ",
    "sg:tags":[
        "picture",
        "form",
        "printers-business",
        "notary",
        "laminations",
        "plastic",
        "public"
    ],
    "sg:website":"http://pwacciliencompanies.com",
    "wof:name":"Pwaccilien Companies",
    "wof:placetype":"venue"
},
  "geometry": {"coordinates":[-112.118988,33.591647],"type":"Point"}
}