{
  "type": "Feature",
  "properties": {
    "iso:country":"US",
    "sg:address":"1831 W Leah Ln",
    "sg:city":"Gilbert",
    "sg:classifiers":[
        {
            "category":"Real Estate",
            "subcategory":"Real Estate Agent",
            "type":"Services"
        }
    ],
    "sg:phone":"+1 480 820 6833",
    "sg:postcode":"85233",
    "sg:province":"AZ",
    "sg:website":"www.doubleagents.com",
    "wof:name":"Dan Smith Realty",
    "wof:placetype":"venue"
},
  "geometry": {"coordinates":[-111.829912,33.372551],"type":"Point"}
}