{
  "type": "Feature",
  "properties": {
    "addr:full":"9625 N 21st Dr Phoenix AZ 85021",
    "addr:housenumber":"9625",
    "addr:postcode":"85021",
    "addr:street":"N 21St Dr",
    "iso:country":"US",
    "sg:address":"9625 N 21st Dr",
    "sg:city":"Phoenix",
    "sg:classifiers":[
        {
            "category":"Retail",
            "subcategory":"Auto Repair",
            "type":"Services"
        }
    ],
    "sg:phone":"+1 602 997 0026",
    "sg:postcode":"85021",
    "sg:province":"AZ",
    "sg:tags":[
        "repairing",
        "automobile"
    ],
    "wof:name":"Moon Valley European",
    "wof:placetype":"venue"
},
  "geometry": {"coordinates":[-112.104445,33.573635],"type":"Point"}
}