{
  "type": "Feature",
  "properties": {
    "addr:full":"949 N Cabral Way Gilbert AZ 85234",
    "addr:housenumber":"949",
    "addr:postcode":"85234",
    "addr:street":"N Cabral Way",
    "iso:country":"US",
    "sg:address":"949 N Cabral Way",
    "sg:city":"Gilbert",
    "sg:classifiers":[
        {
            "category":"Wholesale",
            "subcategory":"Vending Machines",
            "type":"Manufacturing & Wholesale Goods"
        }
    ],
    "sg:phone":"+1 480 539 0356",
    "sg:postcode":"85234",
    "sg:province":"AZ",
    "wof:name":"D & C Vending",
    "wof:placetype":"venue"
},
  "geometry": {"coordinates":[-111.743959,33.367762],"type":"Point"}
}