{
  "type": "Feature",
  "properties": {
    "iso:country":"US",
    "sg:address":"125 W Cll de Las Tiendas",
    "sg:city":"Green Valley",
    "sg:classifiers":[
        {
            "category":"Shopping",
            "subcategory":"Used Merchandise",
            "type":"Retail Goods"
        },
        {
            "category":"Home & Garden",
            "subcategory":"Furniture",
            "type":"Retail Goods"
        }
    ],
    "sg:phone":"+1 520 625 0005",
    "sg:postcode":"85614",
    "sg:province":"AZ",
    "wof:name":"B J S Furniture",
    "wof:placetype":"venue"
},
  "geometry": {"coordinates":[-110.98927999999999,31.898684],"type":"Point"}
}