{
  "type": "Feature",
  "properties": {
    "addr:full":"818 E Grandview St Mesa AZ 85203",
    "addr:housenumber":"818",
    "addr:postcode":"85203",
    "addr:street":"E Grandview St",
    "iso:country":"US",
    "sg:address":"818 E Grandview St",
    "sg:city":"Mesa",
    "sg:classifiers":[
        {
            "category":"Building & Trades",
            "subcategory":"Construction",
            "type":"Services"
        }
    ],
    "sg:phone":"+1 602 402 6042",
    "sg:postcode":"85203",
    "sg:province":"AZ",
    "sg:tags":[
        "residential"
    ],
    "wof:name":"Kevin Martineau",
    "wof:placetype":"venue"
},
  "geometry": {"coordinates":[-111.813074,33.438388],"type":"Point"}
}