{
  "type": "Feature",
  "properties": {
    "iso:country":"US",
    "sg:address":"1799 Kiowa Ave",
    "sg:city":"Lake Havasu City",
    "sg:classifiers":[
        {
            "category":"Shopping",
            "subcategory":"Department Store",
            "type":"Retail Goods"
        }
    ],
    "sg:phone":"+1 928 680 9595",
    "sg:postcode":"86403",
    "sg:province":"AZ",
    "wof:name":"JC Penney",
    "wof:placetype":"venue"
},
  "geometry": {"coordinates":[-114.350993,34.502987],"type":"Point"}
}