{
  "type": "Feature",
  "properties": {
    "iso:country":"US",
    "sg:address":"2526 W Lompoc Ave",
    "sg:city":"Mesa",
    "sg:classifiers":[
        {
            "category":"Professional",
            "subcategory":"Computer Services",
            "type":"Services"
        }
    ],
    "sg:phone":"+1 480 529 1442",
    "sg:postcode":"85202",
    "sg:province":"AZ",
    "sg:tags":[
        "designer",
        "network",
        "technical",
        "consultant",
        "assistance",
        "system",
        "design",
        "support"
    ],
    "sg:website":"http://www.bluefishwebdesigns.com",
    "wof:name":"Bluefish Web Designs",
    "wof:placetype":"venue"
},
  "geometry": {"coordinates":[-111.887868,33.374975],"type":"Point"}
}