{
  "type": "Feature",
  "properties": {
    "iso:country":"US",
    "sg:address":"13216 N 12th Pl",
    "sg:city":"Phoenix",
    "sg:classifiers":[
        {
            "category":"Wholesale",
            "subcategory":"Electrical",
            "type":"Manufacturing & Wholesale Goods"
        }
    ],
    "sg:phone":"+1 602 433 2222",
    "sg:postcode":"85022",
    "sg:province":"AZ",
    "sg:tags":[
        "sound",
        "equipment",
        "electronic",
        "system"
    ],
    "wof:name":"Absolute Sound Systems",
    "wof:placetype":"venue"
},
  "geometry": {"coordinates":[-112.055825,33.606778],"type":"Point"}
}