{
  "type": "Feature",
  "properties": {
    "iso:country":"US",
    "sg:address":"15820 N 35th Ave",
    "sg:city":"Phoenix",
    "sg:classifiers":[
        {
            "category":"Professional",
            "subcategory":"Accounting & Tax Preparation",
            "type":"Services"
        }
    ],
    "sg:phone":"+1 602 439 0899",
    "sg:postcode":"85053",
    "sg:province":"AZ",
    "sg:tags":[
        "accountant"
    ],
    "wof:name":"E & B Accounting",
    "wof:placetype":"venue"
},
  "geometry": {"coordinates":[-112.13370999999999,33.630575],"type":"Point"}
}