{
  "type": "Feature",
  "properties": {
    "iso:country":"US",
    "sg:address":"2630 E Valencia Rd",
    "sg:city":"Tucson",
    "sg:classifiers":[
        {
            "category":"Restaurant",
            "type":"Food & Drink"
        }
    ],
    "sg:menulink":"http://www.allmenus.com/az/tucson/9348-dennys/menu/",
    "sg:phone":"+1 520 294 6131",
    "sg:postcode":"85706",
    "sg:province":"AZ",
    "sg:tags":[
        "american",
        "diner"
    ],
    "wof:name":"Denny's",
    "wof:placetype":"venue"
},
  "geometry": {"coordinates":[-110.93196399999999,32.134041],"type":"Point"}
}