{
  "type": "Feature",
  "properties": {
    "addr:full":"8240 N Hayden Rd Ste B106 Scottsdale AZ 85258",
    "addr:housenumber":"8240",
    "addr:postcode":"85258",
    "addr:street":"N Hayden Rd Ste B106",
    "iso:country":"US",
    "sg:address":"8240 N Hayden Rd Ste B106",
    "sg:city":"Scottsdale",
    "sg:classifiers":[
        {
            "category":"Sports & Exercise",
            "subcategory":"Golf",
            "type":"Entertainment"
        }
    ],
    "sg:phone":"+1 480 948 2050",
    "sg:postcode":"85258",
    "sg:province":"AZ",
    "sg:tags":[
        "courses-private"
    ],
    "sg:website":"http://www.lagunashoresgcc.com",
    "wof:name":"Laguna Shores Golf & Country C",
    "wof:placetype":"venue"
},
  "geometry": {"coordinates":[-111.89868,33.556266],"type":"Point"}
}