{
  "type": "Feature",
  "properties": {
    "addr:full":"244 W Osborn Rd Phoenix AZ 85013",
    "addr:housenumber":"244",
    "addr:postcode":"85013",
    "addr:street":"W Osborn Rd",
    "iso:country":"US",
    "sg:address":"244 W Osborn Rd",
    "sg:city":"Phoenix",
    "sg:classifiers":[
        {
            "category":"Real Estate",
            "subcategory":"Real Estate Services",
            "type":"Services"
        }
    ],
    "sg:phone":"+1 602 462 8000",
    "sg:postcode":"85013",
    "sg:province":"AZ",
    "sg:tags":[
        "title"
    ],
    "sg:website":"http://www.stewartaz.com",
    "wof:name":"Stewart Title Co",
    "wof:placetype":"venue"
},
  "geometry": {"coordinates":[-112.077264,33.487523],"type":"Point"}
}