{
  "type": "Feature",
  "properties": {
    "iso:country":"US",
    "sg:address":"835 E Camelback Rd",
    "sg:city":"Phoenix",
    "sg:classifiers":[
        {
            "category":"Home & Garden",
            "subcategory":"Carpets & Floor Coverings",
            "type":"Retail Goods"
        }
    ],
    "sg:phone":"+1 602 277 5592",
    "sg:postcode":"85014",
    "sg:province":"AZ",
    "sg:tags":[
        "dealer",
        "rug"
    ],
    "wof:name":"Baker Brothers",
    "wof:placetype":"venue"
},
  "geometry": {"coordinates":[-112.060694,33.509148],"type":"Point"}
}