{
  "type": "Feature",
  "properties": {
    "iso:country":"US",
    "sg:address":"730 S Cooper Road",
    "sg:city":"Gilbert",
    "sg:classifiers":[
        {
            "category":"Wholesale",
            "subcategory":"Fruits & Vegetables",
            "type":"Manufacturing & Wholesale Goods"
        },
        {
            "category":"Food & Beverages",
            "subcategory":"Groceries & Convenience Stores",
            "type":"Retail Goods"
        }
    ],
    "sg:phone":"+1 480 926 0405",
    "sg:postcode":"85233",
    "sg:province":"AZ",
    "sg:tags":[
        "veggie"
    ],
    "wof:name":"Sunflower Market",
    "wof:placetype":"venue"
},
  "geometry": {"coordinates":[-111.81212499999999,33.337409],"type":"Point"}
}