{
  "type": "Feature",
  "properties": {
    "iso:country":"US",
    "sg:address":"520 S Cortez St",
    "sg:city":"Prescott",
    "sg:classifiers":[
        {
            "category":"Shopping",
            "subcategory":"Gifts & Souvenirs",
            "type":"Retail Goods"
        }
    ],
    "sg:phone":"+1 928 771 9496",
    "sg:postcode":"86303",
    "sg:province":"AZ",
    "sg:tags":[
        "novelty"
    ],
    "wof:name":"Red Comb Productions LLC",
    "wof:placetype":"venue"
},
  "geometry": {"coordinates":[-112.468945,34.534019],"type":"Point"}
}