{
  "type": "Feature",
  "properties": {
    "addr:full":"3431 N Rose Circle Dr Scottsdale AZ 85251",
    "addr:housenumber":"3431",
    "addr:postcode":"85251",
    "addr:street":"N Rose Circle Dr",
    "iso:country":"US",
    "sg:address":"3431 N Rose Circle Dr",
    "sg:city":"Scottsdale",
    "sg:classifiers":[
        {
            "category":"Retail",
            "subcategory":"Portrait Studio",
            "type":"Services"
        }
    ],
    "sg:phone":"+1 480 994 8131",
    "sg:postcode":"85251",
    "sg:province":"AZ",
    "sg:tags":[
        "photographer"
    ],
    "wof:name":"Bill Flowers Photography",
    "wof:placetype":"venue"
},
  "geometry": {"coordinates":[-111.94375700000001,33.487956],"type":"Point"}
}