{
  "type": "Feature",
  "properties": {
    "iso:country":"US",
    "sg:address":"2051 W Guadalupe Rd",
    "sg:city":"Mesa",
    "sg:classifiers":[
        {
            "category":"Social Services",
            "subcategory":"Child Care",
            "type":"Services"
        },
        {
            "category":"Education",
            "subcategory":"Preschool",
            "type":"Public Place"
        },
        {
            "category":"Education",
            "subcategory":"School",
            "type":"Public Place"
        }
    ],
    "sg:phone":"+1 480 820 7111",
    "sg:postcode":"85202",
    "sg:province":"AZ",
    "sg:tags":[
        "elementary",
        "day"
    ],
    "wof:name":"Tutor Time Child Care Learning Centers",
    "wof:placetype":"venue"
},
  "geometry": {"coordinates":[-111.878998,33.363899],"type":"Point"}
}