{
  "type": "Feature",
  "properties": {
    "iso:country":"US",
    "sg:address":"2405 W Barrow Dr",
    "sg:city":"Chandler",
    "sg:classifiers":[
        {
            "category":"Building & Trades",
            "subcategory":"Construction",
            "type":"Services"
        }
    ],
    "sg:phone":"+1 480 726 0090",
    "sg:postcode":"85224",
    "sg:province":"AZ",
    "sg:tags":[
        "interior",
        "design"
    ],
    "wof:name":"Carol Mickey Design Inc",
    "wof:placetype":"venue"
},
  "geometry": {"coordinates":[-111.883003,33.3428],"type":"Point"}
}