{
  "type": "Feature",
  "properties": {
    "iso:country":"US",
    "sg:address":"10210 N 25th Ave",
    "sg:city":"Phoenix",
    "sg:classifiers":[
        {
            "category":"Professional",
            "subcategory":"Accounting & Tax Preparation",
            "type":"Services"
        }
    ],
    "sg:phone":"+1 602 627 9910",
    "sg:postcode":"85021",
    "sg:province":"AZ",
    "sg:tags":[
        "billing"
    ],
    "wof:name":"Insight Health Billing",
    "wof:placetype":"venue"
},
  "geometry": {"coordinates":[-112.11352599999999,33.578044],"type":"Point"}
}