{
  "type": "Feature",
  "properties": {
    "addr:full":"2520 E Lucky Ln Flagstaff AZ 86004",
    "addr:housenumber":"2520",
    "addr:postcode":"86004",
    "addr:street":"E Lucky Ln",
    "iso:country":"US",
    "sg:address":"2520 E Lucky Ln",
    "sg:city":"Flagstaff",
    "sg:phone":"+1 928 779 5121",
    "sg:postcode":"86004",
    "sg:province":"AZ",
    "sg:website":"http://www.howardjohnson.com",
    "wof:name":"Howard Johnson",
    "wof:placetype":"venue"
},
  "geometry": {"coordinates":[-111.619348,35.194292],"type":"Point"}
}