{
  "type": "Feature",
  "properties": {
    "addr:full":"5107 N 7th St Ste 2 Phoenix AZ 85014",
    "addr:housenumber":"5107",
    "addr:postcode":"85014",
    "addr:street":"N 7Th St Ste 2",
    "iso:country":"US",
    "sg:address":"5107 N 7th St Ste 2",
    "sg:city":"Phoenix",
    "sg:classifiers":[
        {
            "category":"Education",
            "subcategory":"Special Training",
            "type":"Public Place"
        }
    ],
    "sg:phone":"+1 602 274 4441",
    "sg:postcode":"85014",
    "sg:province":"AZ",
    "sg:tags":[
        "instruction",
        "speaking"
    ],
    "sg:website":"http://www.interlingua.com",
    "wof:name":"Interlingua",
    "wof:placetype":"venue"
},
  "geometry": {"coordinates":[-112.06501,33.510968],"type":"Point"}
}