{
  "type": "Feature",
  "properties": {
    "addr:full":"501 W Encanto Blvd Phoenix AZ 85003",
    "addr:housenumber":"501",
    "addr:postcode":"85003",
    "addr:street":"W Encanto Blvd",
    "iso:country":"US",
    "sg:address":"501 W Encanto Blvd",
    "sg:city":"Phoenix",
    "sg:classifiers":[
        {
            "category":"Professional",
            "subcategory":"Management & Consulting",
            "type":"Services"
        }
    ],
    "sg:phone":"+1 602 252 6808",
    "sg:postcode":"85003",
    "sg:province":"AZ",
    "sg:tags":[
        "consultant",
        "business"
    ],
    "wof:name":"Robert Lee Assoc Inc",
    "wof:placetype":"venue"
},
  "geometry": {"coordinates":[-112.08055400000001,33.472997],"type":"Point"}
}