{
  "type": "Feature",
  "properties": {
    "iso:country":"US",
    "sg:address":"5615 W Cactus Rd",
    "sg:city":"Glendale",
    "sg:classifiers":[
        {
            "category":"Banks & Credit Unions",
            "subcategory":"Financial Services",
            "type":"Services"
        }
    ],
    "sg:phone":"+1 623 979 3595",
    "sg:postcode":"85304",
    "sg:province":"AZ",
    "sg:tags":[
        "trust",
        "management"
    ],
    "wof:name":"Kendall Family Trust",
    "wof:placetype":"venue"
},
  "geometry": {"coordinates":[-112.17957699999999,33.596283],"type":"Point"}
}