{
  "type": "Feature",
  "properties": {
    "addr:full":"3402 E Kleindale Rd Tucson AZ 85716",
    "addr:housenumber":"3402",
    "addr:postcode":"85716",
    "addr:street":"E Kleindale Rd",
    "iso:country":"US",
    "sg:address":"3402 E Kleindale Rd",
    "sg:city":"Tucson",
    "sg:classifiers":[
        {
            "category":"Manufacturing",
            "subcategory":"Printing",
            "type":"Manufacturing & Wholesale Goods"
        }
    ],
    "sg:phone":"+1 520 881 6696",
    "sg:postcode":"85716",
    "sg:province":"AZ",
    "sg:tags":[
        "monthly",
        "periodical"
    ],
    "wof:name":"Fitness Plus Magazine",
    "wof:placetype":"venue"
},
  "geometry": {"coordinates":[-110.918187,32.268621],"type":"Point"}
}