{
  "type": "Feature",
  "properties": {
    "addr:full":"6321 E Acoma Dr Scottsdale AZ 85254",
    "addr:housenumber":"6321",
    "addr:postcode":"85254",
    "addr:street":"E Acoma Dr",
    "iso:country":"US",
    "sg:address":"6321 E Acoma Dr",
    "sg:city":"Scottsdale",
    "sg:classifiers":[
        {
            "category":"Food & Beverages",
            "subcategory":"Groceries & Convenience Stores",
            "type":"Retail Goods"
        }
    ],
    "sg:phone":"+1 480 368 0837",
    "sg:postcode":"85254",
    "sg:province":"AZ",
    "wof:name":"Guthart Catering & Food S",
    "wof:placetype":"venue"
},
  "geometry": {"coordinates":[-111.94394200000001,33.618643],"type":"Point"}
}