{
  "type": "Feature",
  "properties": {
    "addr:full":"4756 N 54th Ave Phoenix AZ 85031",
    "addr:housenumber":"4756",
    "addr:postcode":"85031",
    "addr:street":"N 54Th Ave",
    "iso:country":"US",
    "sg:address":"4756 N 54th Ave",
    "sg:city":"Phoenix",
    "sg:classifiers":[
        {
            "category":"Real Estate",
            "subcategory":"Real Estate Services",
            "type":"Services"
        },
        {
            "category":"Building & Trades",
            "subcategory":"Cleaning & Sanitation",
            "type":"Services"
        }
    ],
    "sg:phone":"+1 623 873 3788",
    "sg:postcode":"85031",
    "sg:province":"AZ",
    "sg:tags":[
        "maintenance",
        "cleaners-interior"
    ],
    "wof:name":"Prenventative Maint",
    "wof:placetype":"venue"
},
  "geometry": {"coordinates":[-112.174862,33.506789],"type":"Point"}
}