{
  "type": "Feature",
  "properties": {
    "addr:full":"1355 W 16th St Yuma AZ 85364",
    "addr:housenumber":"1355",
    "addr:postcode":"85364",
    "addr:street":"W 16Th St",
    "iso:country":"US",
    "sg:address":"1355 W 16th St",
    "sg:city":"Yuma",
    "sg:classifiers":[
        {
            "category":"Shopping",
            "type":"Retail Goods"
        }
    ],
    "sg:phone":"+1 928 314 4644",
    "sg:postcode":"85364",
    "sg:province":"AZ",
    "sg:tags":[
        "merchandise"
    ],
    "wof:name":"Burgess Hearing Aids",
    "wof:placetype":"venue"
},
  "geometry": {"coordinates":[-114.63696,32.698416],"type":"Point"}
}