{
  "type": "Feature",
  "properties": {
    "iso:country":"US",
    "sg:address":"8100 W Buckeye Rd",
    "sg:city":"Phoenix",
    "sg:classifiers":[
        {
            "category":"Wholesale",
            "subcategory":"Motor Vehicles",
            "type":"Manufacturing & Wholesale Goods"
        }
    ],
    "sg:phone":"+1 623 936 7545",
    "sg:postcode":"85043",
    "sg:province":"AZ",
    "sg:tags":[
        "recreational",
        "campers-wholesale",
        "manufacturer"
    ],
    "sg:website":"http://www.charioteaglewest.com",
    "wof:name":"Chariot Eagle West",
    "wof:placetype":"venue"
},
  "geometry": {"coordinates":[-112.23240699999999,33.437111],"type":"Point"}
}