{
  "type": "Feature",
  "properties": {
    "iso:country":"US",
    "sg:address":"1228 Willow Creek Rd",
    "sg:city":"Prescott",
    "sg:classifiers":[
        {
            "category":"Personal",
            "subcategory":"Beauty Salon",
            "type":"Services"
        }
    ],
    "sg:phone":"+1 928 778 2028",
    "sg:postcode":"86301",
    "sg:province":"AZ",
    "wof:name":"Dechado Salon & Gallery",
    "wof:placetype":"venue"
},
  "geometry": {"coordinates":[-112.482325,34.566242],"type":"Point"}
}