{
  "type": "Feature",
  "properties": {
    "addr:full":"610 W Broadway Rd Tempe AZ 85282",
    "addr:housenumber":"610",
    "addr:postcode":"85282",
    "addr:street":"W Broadway Rd",
    "iso:country":"US",
    "sg:address":"610 W Broadway Rd",
    "sg:city":"Tempe",
    "sg:classifiers":[
        {
            "category":"Organizations",
            "subcategory":"Non-profit Organization",
            "type":"Services"
        }
    ],
    "sg:phone":"+1 480 377 9156",
    "sg:postcode":"85282",
    "sg:province":"AZ",
    "sg:tags":[
        "information",
        "alcoholism",
        "treatment"
    ],
    "wof:name":"DWI Program",
    "wof:placetype":"venue"
},
  "geometry": {"coordinates":[-111.94991,33.40746],"type":"Point"}
}