{
  "type": "Feature",
  "properties": {
    "iso:country":"US",
    "sg:address":"2720 W Van Buren St",
    "sg:city":"Phoenix",
    "sg:classifiers":[
        {
            "category":"Arts & Performance",
            "subcategory":"Theater",
            "type":"Entertainment"
        }
    ],
    "sg:phone":"+1 602 515 9972",
    "sg:postcode":"85009",
    "sg:province":"AZ",
    "sg:tags":[
        "musician"
    ],
    "wof:name":"Mariachi Mexico Nuevo",
    "wof:placetype":"venue"
},
  "geometry": {"coordinates":[-112.118753,33.4512],"type":"Point"}
}