{
  "type": "Feature",
  "properties": {
    "iso:country":"US",
    "sg:address":"2012 E Broadway Blvd",
    "sg:city":"Tucson",
    "sg:classifiers":[
        {
            "category":"Wholesale",
            "subcategory":"Electrical",
            "type":"Manufacturing & Wholesale Goods"
        }
    ],
    "sg:phone":"+1 520 888 3333",
    "sg:postcode":"85719",
    "sg:province":"AZ",
    "sg:tags":[
        "communication",
        "radio",
        "system"
    ],
    "wof:name":"PACE Engineering",
    "wof:placetype":"venue"
},
  "geometry": {"coordinates":[-110.941069,32.221377],"type":"Point"}
}