{
  "type": "Feature",
  "properties": {
    "iso:country":"US",
    "sg:address":"3033 N Norfolk",
    "sg:city":"Mesa",
    "sg:classifiers":[
        {
            "category":"Building & Trades",
            "subcategory":"Construction",
            "type":"Services"
        }
    ],
    "sg:phone":"+1 480 425 8772",
    "sg:postcode":"85215",
    "sg:province":"AZ",
    "sg:tags":[
        "general",
        "nonresidential",
        "contractor"
    ],
    "wof:name":"Calvin Wadsworth Construction",
    "wof:placetype":"venue"
},
  "geometry": {"coordinates":[-111.740927,33.470721],"type":"Point"}
}