{
  "type": "Feature",
  "properties": {
    "iso:country":"US",
    "sg:address":"989 N High School Ave",
    "sg:city":"Thatcher",
    "sg:classifiers":[
        {
            "category":"Building & Trades",
            "subcategory":"Construction",
            "type":"Services"
        }
    ],
    "sg:phone":"+1 928 428 3408",
    "sg:postcode":"85552",
    "sg:province":"AZ",
    "sg:tags":[
        "roofing",
        "contractor"
    ],
    "wof:name":"Ferrin's State Roofing",
    "wof:placetype":"venue"
},
  "geometry": {"coordinates":[-109.759015,32.848206],"type":"Point"}
}