{
  "type": "Feature",
  "properties": {
    "iso:country":"US",
    "sg:address":"7440 N Oracle Rd",
    "sg:city":"Tucson",
    "sg:classifiers":[
        {
            "category":"Health Services",
            "subcategory":"Doctor",
            "type":"Services"
        }
    ],
    "sg:phone":"+1 520 529 2940",
    "sg:postcode":"85704",
    "sg:province":"AZ",
    "sg:tags":[
        "physician",
        "surgeon"
    ],
    "wof:name":"Jonathan Gross MD",
    "wof:placetype":"venue"
},
  "geometry": {"coordinates":[-110.976735,32.342512],"type":"Point"}
}