{
  "type": "Feature",
  "properties": {
    "iso:country":"US",
    "sg:address":"11365 E Greenway Rd",
    "sg:city":"Scottsdale",
    "sg:classifiers":[
        {
            "category":"Shopping",
            "type":"Retail Goods"
        }
    ],
    "sg:phone":"+1 480 585 4617",
    "sg:postcode":"85255",
    "sg:province":"AZ",
    "sg:tags":[
        "art",
        "gallery",
        "dealer"
    ],
    "wof:name":"Kimberly Mock Editions",
    "wof:placetype":"venue"
},
  "geometry": {"coordinates":[-111.835632,33.626084],"type":"Point"}
}