{
  "type": "Feature",
  "properties": {
    "iso:country":"US",
    "sg:address":"7161 W Willow Ave",
    "sg:city":"Peoria",
    "sg:classifiers":[
        {
            "category":"Building & Trades",
            "subcategory":"Construction",
            "type":"Services"
        },
        {
            "category":"Sports & Exercise",
            "subcategory":"Swimming Pool",
            "type":"Entertainment"
        }
    ],
    "sg:phone":"+1 623 878 5265",
    "sg:postcode":"85381",
    "sg:province":"AZ",
    "wof:name":"Discount Pools",
    "wof:placetype":"venue"
},
  "geometry": {"coordinates":[-112.212146,33.60641],"type":"Point"}
}