{
  "type": "Feature",
  "properties": {
    "iso:country":"US",
    "sg:address":"541 W Monte Vista Rd",
    "sg:city":"Phoenix",
    "sg:classifiers":[
        {
            "category":"Building & Trades",
            "subcategory":"Landscaping Services",
            "type":"Services"
        }
    ],
    "sg:phone":"+1 602 307 0010",
    "sg:postcode":"85003",
    "sg:province":"AZ",
    "wof:name":"Exteriors By Chad Robert",
    "wof:placetype":"venue"
},
  "geometry": {"coordinates":[-112.081924,33.471134],"type":"Point"}
}