{
  "type": "Feature",
  "properties": {
    "iso:country":"US",
    "sg:address":"3400 E Sky Harbor Blvd",
    "sg:city":"Phoenix",
    "sg:classifiers":[
        {
            "category":"Fast Food",
            "type":"Food & Drink"
        },
        {
            "category":"Restaurant",
            "type":"Food & Drink"
        }
    ],
    "sg:phone":"+1 602 275 1721",
    "sg:postcode":"85034",
    "sg:province":"AZ",
    "sg:tags":[
        "american",
        "hot",
        "hamburger",
        "dog"
    ],
    "sg:website":"http://www.bk.com",
    "wof:name":"Burger King",
    "wof:placetype":"venue"
},
  "geometry": {"coordinates":[-112.00878899999999,33.43578],"type":"Point"}
}