{
  "type": "Feature",
  "properties": {
    "iso:country":"US",
    "sg:address":"4505 E Chandler Blvd",
    "sg:city":"Phoenix",
    "sg:classifiers":[
        {
            "category":"Insurance",
            "subcategory":"Title Insurance",
            "type":"Services"
        }
    ],
    "sg:phone":"+1 602 325 8054",
    "sg:postcode":"85048",
    "sg:province":"AZ",
    "sg:website":"http://www.ewtaz.com",
    "wof:name":"Empire West Title Agency",
    "wof:placetype":"venue"
},
  "geometry": {"coordinates":[-111.986744,33.305143],"type":"Point"}
}