{
  "type": "Feature",
  "properties": {
    "iso:country":"US",
    "sg:address":"1472 S 42nd Dr",
    "sg:city":"Yuma",
    "sg:classifiers":[
        {
            "category":"Manufacturing",
            "subcategory":"Tools & Machinery",
            "type":"Manufacturing & Wholesale Goods"
        }
    ],
    "sg:phone":"+1 928 783 0705",
    "sg:postcode":"85364",
    "sg:province":"AZ",
    "sg:tags":[
        "pattern",
        "industrial",
        "mfg"
    ],
    "wof:name":"Beaded Flower Patterns",
    "wof:placetype":"venue"
},
  "geometry": {"coordinates":[-114.67122999999999,32.701491],"type":"Point"}
}