{
  "type": "Feature",
  "properties": {
    "addr:full":"4674 E Inwood Way Flagstaff AZ 86004",
    "addr:housenumber":"4674",
    "addr:postcode":"86004",
    "addr:street":"E Inwood Way",
    "iso:country":"US",
    "sg:address":"4674 E Inwood Way",
    "sg:city":"Flagstaff",
    "sg:classifiers":[
        {
            "category":"Professional",
            "subcategory":"Management & Consulting",
            "type":"Services"
        }
    ],
    "sg:phone":"+1 928 522 9065",
    "sg:postcode":"86004",
    "sg:province":"AZ",
    "sg:tags":[
        "counselor",
        "public",
        "relations"
    ],
    "wof:name":"Munger & Assoc",
    "wof:placetype":"venue"
},
  "geometry": {"coordinates":[-111.585667,35.209467],"type":"Point"}
}