{
  "type": "Feature",
  "properties": {
    "addr:full":"7407 W Mercer Ln Peoria AZ 85345",
    "addr:housenumber":"7407",
    "addr:postcode":"85345",
    "addr:street":"W Mercer Ln",
    "iso:country":"US",
    "sg:address":"7407 W Mercer Ln",
    "sg:city":"Peoria",
    "sg:classifiers":[
        {
            "category":"Retail",
            "subcategory":"Repair Shop",
            "type":"Services"
        }
    ],
    "sg:phone":"+1 602 919 8826",
    "sg:postcode":"85345",
    "sg:province":"AZ",
    "sg:tags":[
        "equipment",
        "conditioning",
        "air"
    ],
    "wof:name":"Gordon's A-C Svc",
    "wof:placetype":"venue"
},
  "geometry": {"coordinates":[-112.218773,33.584246],"type":"Point"}
}