{
  "type": "Feature",
  "properties": {
    "iso:country":"US",
    "sg:address":"38735 State Hwy 373",
    "sg:city":"Greer",
    "sg:classifiers":[
        {
            "category":"Bars & Pubs",
            "type":"Food & Drink"
        }
    ],
    "sg:phone":"+1 928 735 7657",
    "sg:postcode":"85927",
    "sg:province":"AZ",
    "sg:tags":[
        "grill",
        "bar"
    ],
    "wof:name":"Double D Sports Bar & Grill",
    "wof:placetype":"venue"
},
  "geometry": {"coordinates":[-109.460443,34.05632],"type":"Point"}
}