{
  "type": "Feature",
  "properties": {
    "iso:country":"US",
    "sg:address":"7820 N Cortaro Rd",
    "sg:city":"Tucson",
    "sg:classifiers":[
        {
            "category":"Banks & Credit Unions",
            "subcategory":"Bank",
            "type":"Services"
        }
    ],
    "sg:phone":"+1 520 572 6000",
    "sg:postcode":"85743",
    "sg:province":"AZ",
    "wof:name":"M & I Bank",
    "wof:placetype":"venue"
},
  "geometry": {"coordinates":[-111.09669700000001,32.35126],"type":"Point"}
}