{
  "type": "Feature",
  "properties": {
    "iso:country":"US",
    "sg:address":"7222 W Wier Ave",
    "sg:city":"Phoenix",
    "sg:classifiers":[
        {
            "category":"Personal",
            "type":"Services"
        },
        {
            "category":"Retail",
            "subcategory":"Laundry & Dry Cleaning",
            "type":"Services"
        },
        {
            "category":"Building & Trades",
            "subcategory":"Cleaning & Sanitation",
            "type":"Services"
        }
    ],
    "sg:phone":"+1 623 907 4097",
    "sg:postcode":"85043",
    "sg:province":"AZ",
    "sg:tags":[
        "house",
        "washing",
        "cleaning-exterior",
        "cleaner"
    ],
    "sg:website":"http://www.arkpw.com",
    "wof:name":"Ark Pressure Washing Co",
    "wof:placetype":"venue"
},
  "geometry": {"coordinates":[-112.215369,33.404594],"type":"Point"}
}