{
  "type": "Feature",
  "properties": {
    "addr:full":"1465 N Fiesta Blvd Gilbert AZ 85233",
    "addr:housenumber":"1465",
    "addr:postcode":"85233",
    "addr:street":"N Fiesta Blvd",
    "iso:country":"US",
    "sg:address":"1465 N Fiesta Blvd",
    "sg:city":"Gilbert",
    "sg:classifiers":[
        {
            "category":"Communications",
            "subcategory":"Film & Video Production",
            "type":"Services"
        }
    ],
    "sg:phone":"+1 480 497 8400",
    "sg:postcode":"85233",
    "sg:province":"AZ",
    "sg:tags":[
        "taping"
    ],
    "wof:name":"Network One",
    "wof:placetype":"venue"
},
  "geometry": {"coordinates":[-111.836915,33.375572],"type":"Point"}
}