{
  "type": "Feature",
  "properties": {
    "addr:full":"4233 S 35th Ave Phoenix AZ 85041",
    "addr:housenumber":"4233",
    "addr:postcode":"85041",
    "addr:street":"S 35Th Ave",
    "iso:country":"US",
    "sg:address":"4233 S 35th Ave",
    "sg:city":"Phoenix",
    "sg:classifiers":[
        {
            "category":"Autos & Motor Vehicles",
            "subcategory":"Automobile Sales",
            "type":"Retail Goods"
        },
        {
            "category":"Utilities",
            "subcategory":"Recycling",
            "type":"Services"
        },
        {
            "category":"Wholesale",
            "subcategory":"Scrap",
            "type":"Manufacturing & Wholesale Goods"
        }
    ],
    "sg:phone":"+1 602 268 0266",
    "sg:postcode":"85041",
    "sg:province":"AZ",
    "sg:tags":[
        "wrecking",
        "car",
        "truck",
        "new",
        "salvage"
    ],
    "wof:name":"Route 66 Auto & Truck Recycler",
    "wof:placetype":"venue"
},
  "geometry": {"coordinates":[-112.133745,33.407873],"type":"Point"}
}