{
  "type": "Feature",
  "properties": {
    "addr:full":"865 N Page Springs Rd Cornville AZ 86325",
    "addr:housenumber":"865",
    "addr:postcode":"az 86325",
    "addr:street":"N Page Springs Rd",
    "iso:country":"US",
    "sg:address":"865 N Page Springs Rd",
    "sg:city":"Cornville",
    "sg:classifiers":[
        {
            "category":"Building & Trades",
            "subcategory":"Construction",
            "type":"Services"
        }
    ],
    "sg:phone":"+1 928 634 0180",
    "sg:postcode":"86325",
    "sg:province":"AZ",
    "sg:tags":[
        "layer",
        "carpet"
    ],
    "wof:name":"Weatherford Floor Coverings",
    "wof:placetype":"venue"
},
  "geometry": {"coordinates":[-111.887006,34.748854],"type":"Point"}
}