{
  "type": "Feature",
  "properties": {
    "iso:country":"US",
    "sg:address":"926 E Vermont Ave",
    "sg:city":"Phoenix",
    "sg:classifiers":[
        {
            "category":"Building & Trades",
            "subcategory":"Construction",
            "type":"Services"
        }
    ],
    "sg:phone":"+1 602 266 1769",
    "sg:postcode":"85014",
    "sg:province":"AZ",
    "sg:tags":[
        "work",
        "concrete",
        "cutting",
        "breaking",
        "sawing"
    ],
    "wof:name":"A Sharper Cut Inc",
    "wof:placetype":"venue"
},
  "geometry": {"coordinates":[-112.060879,33.515087],"type":"Point"}
}