{
  "type": "Feature",
  "properties": {
    "iso:country":"US",
    "sg:address":"6840 W Garfield St",
    "sg:city":"Phoenix",
    "sg:classifiers":[
        {
            "category":"Retail",
            "subcategory":"Repair Shop",
            "type":"Services"
        }
    ],
    "sg:phone":"+1 602 232 5072",
    "sg:postcode":"85043",
    "sg:province":"AZ",
    "sg:tags":[
        "appliance"
    ],
    "wof:name":"AAAA Affordable Repair Svc",
    "wof:placetype":"venue"
},
  "geometry": {"coordinates":[-112.207328,33.457375],"type":"Point"}
}