{
  "type": "Feature",
  "properties": {
    "iso:country":"US",
    "sg:address":"1305 E Hatcher Rd",
    "sg:city":"Phoenix",
    "sg:classifiers":[
        {
            "category":"Professional",
            "subcategory":"Accounting & Tax Preparation",
            "type":"Services"
        }
    ],
    "sg:phone":"+1 602 371 8467",
    "sg:postcode":"85020",
    "sg:province":"AZ",
    "sg:tags":[
        "accountant"
    ],
    "wof:name":"Reid & Reid",
    "wof:placetype":"venue"
},
  "geometry": {"coordinates":[-112.053539,33.571224],"type":"Point"}
}