{
  "type": "Feature",
  "properties": {
    "addr:full":"3051 W Shamrell Blvd Flagstaff AZ 86001",
    "addr:housenumber":"3051",
    "addr:postcode":"86001",
    "addr:street":"W Shamrell Blvd",
    "iso:country":"US",
    "sg:address":"3051 W Shamrell Blvd",
    "sg:city":"Flagstaff",
    "sg:classifiers":[
        {
            "category":"Manufacturing",
            "subcategory":"Tools & Machinery",
            "type":"Manufacturing & Wholesale Goods"
        },
        {
            "category":"Manufacturing",
            "subcategory":"Electronics",
            "type":"Manufacturing & Wholesale Goods"
        },
        {
            "category":"Wholesale",
            "subcategory":"Electrical",
            "type":"Manufacturing & Wholesale Goods"
        },
        {
            "category":"Shopping",
            "subcategory":"Computers & Home Electronics",
            "type":"Retail Goods"
        }
    ],
    "sg:phone":"+1 813 237 0987",
    "sg:postcode":"86001",
    "sg:province":"AZ",
    "sg:tags":[
        "electric",
        "supply",
        "supplies-wholesale",
        "equipment-testing",
        "equipment",
        "consumer",
        "manufacturer"
    ],
    "wof:name":"City Electric Supply Co",
    "wof:placetype":"venue"
},
  "geometry": {"coordinates":[-111.681302,35.138207],"type":"Point"}
}