{
  "type": "Feature",
  "properties": {
    "addr:full":"452 W 2nd Ave Mesa AZ 85210",
    "addr:housenumber":"452",
    "addr:postcode":"85210",
    "addr:street":"W 2Nd Ave",
    "iso:country":"US",
    "sg:address":"452 W 2nd Ave",
    "sg:city":"Mesa",
    "sg:classifiers":[
        {
            "category":"Wholesale",
            "subcategory":"Motor Vehicles",
            "type":"Manufacturing & Wholesale Goods"
        }
    ],
    "sg:phone":"+1 480 898 9727",
    "sg:postcode":"85210",
    "sg:province":"AZ",
    "sg:tags":[
        "auto",
        "accessory"
    ],
    "wof:name":"Shell Happy Auto Accessories",
    "wof:placetype":"venue"
},
  "geometry": {"coordinates":[-111.841131,33.411555],"type":"Point"}
}