{
  "type": "Feature",
  "properties": {
    "iso:country":"US",
    "sg:address":"4531 N 75th Way",
    "sg:city":"Scottsdale",
    "sg:classifiers":[
        {
            "category":"Freight",
            "type":"Transportation"
        }
    ],
    "sg:phone":"+1 602 400 6600",
    "sg:postcode":"85251",
    "sg:province":"AZ",
    "sg:tags":[
        "line"
    ],
    "wof:name":"Espresso Transports",
    "wof:placetype":"venue"
},
  "geometry": {"coordinates":[-111.918374,33.5041],"type":"Point"}
}