{
  "type": "Feature",
  "properties": {
    "addr:full":"8440 S Hardy Dr Tempe AZ 85284",
    "addr:housenumber":"8440",
    "addr:postcode":"85284",
    "addr:street":"S Hardy Dr",
    "iso:country":"US",
    "sg:address":"8440 S Hardy Dr",
    "sg:city":"Tempe",
    "sg:classifiers":[
        {
            "category":"Professional",
            "subcategory":"Credit Reporting & Collection",
            "type":"Services"
        }
    ],
    "sg:phone":"+1 480 308 5000",
    "sg:postcode":"85284",
    "sg:province":"AZ",
    "sg:tags":[
        "agency"
    ],
    "wof:name":"Liberty Point",
    "wof:placetype":"venue"
},
  "geometry": {"coordinates":[-111.954437,33.338934],"type":"Point"}
}