{
  "type": "Feature",
  "properties": {
    "iso:country":"US",
    "sg:address":"17442 N 24th Dr",
    "sg:city":"Phoenix",
    "sg:classifiers":[
        {
            "category":"Home & Garden",
            "subcategory":"Carpets & Floor Coverings",
            "type":"Retail Goods"
        }
    ],
    "sg:phone":"+1 602 373 2542",
    "sg:postcode":"85023",
    "sg:province":"AZ",
    "wof:name":"Peneleys Carpet Service",
    "wof:placetype":"venue"
},
  "geometry": {"coordinates":[-112.111185,33.646376],"type":"Point"}
}