{
  "type": "Feature",
  "properties": {
    "addr:full":"7501 E McCormick Pkwy Scottsdale AZ 85258",
    "addr:housenumber":"7501",
    "addr:postcode":"85258",
    "addr:street":"E Mccormick Pkwy",
    "iso:country":"US",
    "sg:address":"7501 E McCormick Pkwy",
    "sg:city":"Scottsdale",
    "sg:classifiers":[
        {
            "category":"Professional",
            "subcategory":"Advertising",
            "type":"Services"
        }
    ],
    "sg:phone":"+1 480 367 1577",
    "sg:postcode":"85258",
    "sg:province":"AZ",
    "sg:tags":[
        "counselor"
    ],
    "sg:website":"www.emarketinginc.com",
    "wof:name":"E-Marketing",
    "wof:placetype":"venue"
},
  "geometry": {"coordinates":[-111.917547,33.548601],"type":"Point"}
}