{
  "type": "Feature",
  "properties": {
    "iso:country":"US",
    "sg:address":"37 N Tucson Blvd",
    "sg:city":"Tucson",
    "sg:classifiers":[
        {
            "category":"Building & Trades",
            "subcategory":"Construction",
            "type":"Services"
        }
    ],
    "sg:phone":"+1 520 882 7722",
    "sg:postcode":"85716",
    "sg:province":"AZ",
    "sg:tags":[
        "residential"
    ],
    "wof:name":"Drucon Company Company Inc",
    "wof:placetype":"venue"
},
  "geometry": {"coordinates":[-110.935282,32.222325],"type":"Point"}
}