{
  "type": "Feature",
  "properties": {
    "addr:full":"4330 N Civic Center Plz Scottsdale AZ 85251",
    "addr:housenumber":"4330",
    "addr:postcode":"85251",
    "addr:street":"N Civic Center Plz",
    "iso:country":"US",
    "sg:address":"4330 N Civic Center Plz",
    "sg:city":"Scottsdale",
    "sg:classifiers":[
        {
            "category":"Professional",
            "subcategory":"Management & Consulting",
            "type":"Services"
        },
        {
            "category":"Banks & Credit Unions",
            "subcategory":"Bank",
            "type":"Services"
        }
    ],
    "sg:phone":"+1 480 663 6602",
    "sg:postcode":"85251",
    "sg:province":"AZ",
    "sg:tags":[
        "consultant",
        "educational",
        "loan",
        "broker"
    ],
    "wof:name":"Foundation For Financial Liter",
    "wof:placetype":"venue"
},
  "geometry": {"coordinates":[-111.921443,33.501261],"type":"Point"}
}