{
  "type": "Feature",
  "properties": {
    "addr:full":"13815 N 7th St Phoenix AZ 85022",
    "addr:housenumber":"13815",
    "addr:postcode":"85022",
    "addr:street":"N 7Th St",
    "iso:country":"US",
    "sg:address":"13815 N 7th St",
    "sg:city":"Phoenix",
    "sg:classifiers":[
        {
            "category":"Wholesale",
            "subcategory":"Hardware",
            "type":"Manufacturing & Wholesale Goods"
        }
    ],
    "sg:phone":"+1 602 863 3859",
    "sg:postcode":"85022",
    "sg:province":"AZ",
    "sg:tags":[
        "system",
        "misting"
    ],
    "wof:name":"Southwest Outdoor Cooling",
    "wof:placetype":"venue"
},
  "geometry": {"coordinates":[-112.06535100000001,33.61157],"type":"Point"}
}