{
  "type": "Feature",
  "properties": {
    "iso:country":"US",
    "sg:address":"4400 E Broadway Blvd",
    "sg:city":"Tucson",
    "sg:classifiers":[
        {
            "category":"Real Estate",
            "subcategory":"Architect",
            "type":"Services"
        }
    ],
    "sg:phone":"+1 520 327 1716",
    "sg:postcode":"85711",
    "sg:province":"AZ",
    "wof:name":"CNWC-Architects",
    "wof:placetype":"venue"
},
  "geometry": {"coordinates":[-110.896578,32.221505],"type":"Point"}
}