{
  "type": "Feature",
  "properties": {
    "addr:full":"2155 E Conference Dr Tempe AZ 85284",
    "addr:housenumber":"2155",
    "addr:postcode":"85284",
    "addr:street":"E Conference Dr",
    "iso:country":"US",
    "sg:address":"2155 E Conference Dr",
    "sg:city":"Tempe",
    "sg:classifiers":[
        {
            "category":"Shopping",
            "subcategory":"Pharmacy",
            "type":"Retail Goods"
        }
    ],
    "sg:phone":"+1 480 775 4784",
    "sg:postcode":"85284",
    "sg:province":"AZ",
    "wof:name":"Apothecary Shop",
    "wof:placetype":"venue"
},
  "geometry": {"coordinates":[-111.894741,33.34291],"type":"Point"}
}