{
  "type": "Feature",
  "properties": {
    "iso:country":"US",
    "sg:address":"7135 E Camelback Rd",
    "sg:city":"Scottsdale",
    "sg:classifiers":[
        {
            "category":"Restaurant",
            "type":"Food & Drink"
        }
    ],
    "sg:phone":"+1 480 675 7777",
    "sg:postcode":"85251",
    "sg:province":"AZ",
    "wof:name":"Pink Taco",
    "wof:placetype":"venue"
},
  "geometry": {"coordinates":[-111.92690899999999,33.502193],"type":"Point"}
}