{
  "type": "Feature",
  "properties": {
    "iso:country":"US",
    "sg:address":"41532 N Clear Crossing Rd",
    "sg:city":"Phoenix",
    "sg:classifiers":[
        {
            "category":"Insurance",
            "subcategory":"Insurance Agent",
            "type":"Services"
        }
    ],
    "sg:phone":"+1 623 879 3722",
    "sg:postcode":"85086",
    "sg:province":"AZ",
    "wof:name":"Anthony Turchetta Frmrs Insur",
    "wof:placetype":"venue"
},
  "geometry": {"coordinates":[-112.124236,33.861306],"type":"Point"}
}