{
  "type": "Feature",
  "properties": {
    "iso:country":"US",
    "sg:address":"625 N Bedford Dr",
    "sg:city":"Tucson",
    "sg:classifiers":[
        {
            "category":"Retail",
            "subcategory":"Repair Shop",
            "type":"Services"
        }
    ],
    "sg:phone":"+1 520 290 5504",
    "sg:postcode":"85710",
    "sg:province":"AZ",
    "sg:tags":[
        "refinishing",
        "furniture"
    ],
    "wof:name":"Ron Keippel Furniture Repair",
    "wof:placetype":"venue"
},
  "geometry": {"coordinates":[-110.803403,32.229092],"type":"Point"}
}