{
  "type": "Feature",
  "properties": {
    "addr:full":"6759 E University Dr Mesa AZ 85205",
    "addr:housenumber":"6759",
    "addr:postcode":"85205",
    "addr:street":"E University Dr",
    "iso:country":"US",
    "sg:address":"6759 E University Dr",
    "sg:city":"Mesa",
    "sg:classifiers":[
        {
            "category":"Food & Beverages",
            "subcategory":"Groceries & Convenience Stores",
            "type":"Retail Goods"
        }
    ],
    "sg:phone":"+1 480 985 1920",
    "sg:postcode":"85205",
    "sg:province":"AZ",
    "wof:name":"Circle K",
    "wof:placetype":"venue"
},
  "geometry": {"coordinates":[-111.68592200000001,33.422856],"type":"Point"}
}