{
  "type": "Feature",
  "properties": {
    "addr:full":"1343 N Alma School Rd Chandler AZ 85224",
    "addr:housenumber":"1343",
    "addr:postcode":"85224",
    "addr:street":"N Alma School Rd",
    "iso:country":"US",
    "sg:address":"1343 N Alma School Rd",
    "sg:city":"Chandler",
    "sg:classifiers":[
        {
            "category":"Health Services",
            "subcategory":"Doctor",
            "type":"Services"
        }
    ],
    "sg:phone":"+1 480 857 6316",
    "sg:postcode":"85224",
    "sg:province":"AZ",
    "sg:tags":[
        "physician",
        "surgeon"
    ],
    "wof:name":"Southwestern Pediatrics",
    "wof:placetype":"venue"
},
  "geometry": {"coordinates":[-111.85903999999999,33.327392],"type":"Point"}
}