{
  "type": "Feature",
  "properties": {
    "iso:country":"US",
    "sg:address":"225 W Jackson Rd",
    "sg:city":"Benson",
    "sg:classifiers":[
        {
            "category":"Utilities",
            "subcategory":"Natural Gas",
            "type":"Services"
        }
    ],
    "sg:phone":"+1 520 586 3302",
    "sg:postcode":"85602",
    "sg:province":"AZ",
    "sg:tags":[
        "company"
    ],
    "wof:name":"El Paso Natural Gas Co",
    "wof:placetype":"venue"
},
  "geometry": {"coordinates":[-110.298972,31.97795],"type":"Point"}
}