{
  "type": "Feature",
  "properties": {
    "addr:full":"2889 Willow Creek Rd Prescott AZ 86301",
    "addr:housenumber":"2889",
    "addr:postcode":"86301",
    "addr:street":"Willow Creek Rd",
    "iso:country":"US",
    "sg:address":"2889 Willow Creek Rd",
    "sg:city":"Prescott",
    "sg:classifiers":[
        {
            "category":"Autos & Motor Vehicles",
            "subcategory":"Fuel & Gas Station",
            "type":"Retail Goods"
        }
    ],
    "sg:phone":"+1 928 778 6533",
    "sg:postcode":"86301",
    "sg:province":"AZ",
    "sg:tags":[
        "convenience",
        "gasoline",
        "store"
    ],
    "wof:name":"Get-N-Go Convenience Store",
    "wof:placetype":"venue"
},
  "geometry": {"coordinates":[-112.47020999999999,34.593006],"type":"Point"}
}