{
  "type": "Feature",
  "properties": {
    "addr:full":"10839 E Ludlow Dr Scottsdale AZ 85255",
    "addr:housenumber":"10839",
    "addr:postcode":"85255",
    "addr:street":"E Ludlow Dr",
    "iso:country":"US",
    "sg:address":"10839 E Ludlow Dr",
    "sg:city":"Scottsdale",
    "sg:classifiers":[
        {
            "category":"Banks & Credit Unions",
            "subcategory":"Investment Brokerage",
            "type":"Services"
        }
    ],
    "sg:phone":"+1 480 563 4383",
    "sg:postcode":"85255",
    "sg:province":"AZ",
    "sg:tags":[
        "advisory"
    ],
    "wof:name":"Homeview Financial LLC",
    "wof:placetype":"venue"
},
  "geometry": {"coordinates":[-111.846762,33.612192],"type":"Point"}
}