{
  "type": "Feature",
  "properties": {
    "iso:country":"US",
    "sg:address":"22 N 122nd Ln",
    "sg:city":"Avondale",
    "sg:classifiers":[
        {
            "category":"Professional",
            "subcategory":"Detective & Security Services",
            "type":"Services"
        }
    ],
    "sg:phone":"+1 623 772 0775",
    "sg:postcode":"85323",
    "sg:province":"AZ",
    "sg:tags":[
        "information",
        "bureau"
    ],
    "wof:name":"Old Swimming Hole Pool Service",
    "wof:placetype":"venue"
},
  "geometry": {"coordinates":[-112.323123,33.445553],"type":"Point"}
}