{
  "type": "Feature",
  "properties": {
    "iso:country":"US",
    "sg:address":"6503 E Tanque Verde Rd",
    "sg:city":"Tucson",
    "sg:classifiers":[
        {
            "category":"Recreation",
            "subcategory":"Arcade",
            "type":"Entertainment"
        }
    ],
    "sg:phone":"+1 520 885 3569",
    "sg:postcode":"85715",
    "sg:province":"AZ",
    "sg:tags":[
        "center",
        "family"
    ],
    "sg:website":"www.golfnstuff.com",
    "wof:name":"Golf N' Stuff",
    "wof:placetype":"venue"
},
  "geometry": {"coordinates":[-110.852369,32.246578],"type":"Point"}
}