{
  "type": "Feature",
  "properties": {
    "iso:country":"US",
    "sg:address":"6541 E Tanque Verde Rd",
    "sg:city":"Tucson",
    "sg:classifiers":[
        {
            "category":"Personal",
            "subcategory":"Beauty Salon",
            "type":"Services"
        }
    ],
    "sg:phone":"+1 520 885 1388",
    "sg:postcode":"85715",
    "sg:province":"AZ",
    "wof:name":"Classic Salon & Day Spa",
    "wof:placetype":"venue"
},
  "geometry": {"coordinates":[-110.853209,32.246065],"type":"Point"}
}