{
  "type": "Feature",
  "properties": {
    "iso:country":"US",
    "sg:address":"1113 W Beale St",
    "sg:city":"Kingman",
    "sg:classifiers":[
        {
            "category":"Autos & Motor Vehicles",
            "subcategory":"Automobile Sales",
            "type":"Retail Goods"
        }
    ],
    "sg:phone":"+1 928 718 1113",
    "sg:postcode":"86401",
    "sg:province":"AZ",
    "sg:tags":[
        "used"
    ],
    "wof:name":"Pro Auto Sales",
    "wof:placetype":"venue"
},
  "geometry": {"coordinates":[-114.070926,35.19258],"type":"Point"}
}