{
  "type": "Feature",
  "properties": {
    "iso:country":"US",
    "sg:address":"519 N Leroux St",
    "sg:city":"Flagstaff",
    "sg:classifiers":[
        {
            "category":"Health Services",
            "subcategory":"Chiropractor",
            "type":"Services"
        }
    ],
    "sg:phone":"+1 928 774 6333",
    "sg:postcode":"86001",
    "sg:province":"AZ",
    "sg:tags":[
        "chiropractic"
    ],
    "wof:name":"Caire Chiropractic",
    "wof:placetype":"venue"
},
  "geometry": {"coordinates":[-111.64692599999999,35.20234],"type":"Point"}
}