{
  "type": "Feature",
  "properties": {
    "addr:full":"3932 E Fry Blvd Sierra Vista AZ 85635",
    "addr:housenumber":"3932",
    "addr:postcode":"85635",
    "addr:street":"E Fry Blvd",
    "iso:country":"US",
    "sg:address":"3932 E Fry Blvd",
    "sg:city":"Sierra Vista",
    "sg:classifiers":[
        {
            "category":"Banks & Credit Unions",
            "subcategory":"Bank",
            "type":"Services"
        }
    ],
    "sg:phone":"+1 520 459 1235",
    "sg:postcode":"85635",
    "sg:province":"AZ",
    "wof:name":"Chase",
    "wof:placetype":"venue"
},
  "geometry": {"coordinates":[-110.260255,31.554555],"type":"Point"}
}