{
  "type": "Feature",
  "properties": {
    "iso:country":"US",
    "sg:address":"2621 E Hidalgo Ave",
    "sg:city":"Phoenix",
    "sg:classifiers":[
        {
            "category":"Banks & Credit Unions",
            "subcategory":"Investment Brokerage",
            "type":"Services"
        }
    ],
    "sg:phone":"+1 602 276 4700",
    "sg:postcode":"85040",
    "sg:province":"AZ",
    "wof:name":"HYFY Investments",
    "wof:placetype":"venue"
},
  "geometry": {"coordinates":[-112.02412,33.394419],"type":"Point"}
}