{
  "type": "Feature",
  "properties": {
    "iso:country":"US",
    "sg:address":"560 E Hampton Ave",
    "sg:city":"Mesa",
    "sg:classifiers":[
        {
            "category":"Shopping",
            "type":"Retail Goods"
        }
    ],
    "sg:phone":"+1 480 964 9755",
    "sg:postcode":"85204",
    "sg:province":"AZ",
    "sg:tags":[
        "merchandise",
        "real estate"
    ],
    "wof:name":"Alan Mannetter Realty",
    "wof:placetype":"venue"
},
  "geometry": {"coordinates":[-111.822021,33.389702],"type":"Point"}
}