{
  "type": "Feature",
  "properties": {
    "addr:full":"100 State Hwy 260 Payson AZ 85541",
    "addr:housenumber":"100",
    "addr:postcode":"85541",
    "addr:street":"State Hwy 260",
    "iso:country":"US",
    "sg:address":"100 State Hwy 260",
    "sg:city":"Payson",
    "sg:classifiers":[
        {
            "category":"Restaurant",
            "type":"Food & Drink"
        }
    ],
    "sg:phone":"+1 928 472 7476",
    "sg:postcode":"85541",
    "sg:province":"AZ",
    "wof:name":"Great China Buffet",
    "wof:placetype":"venue"
},
  "geometry": {"coordinates":[-111.322974,34.2419],"type":"Point"}
}