{
  "type": "Feature",
  "properties": {
    "addr:full":"8017 S Wild Primrose Ave Tucson AZ 85747",
    "addr:housenumber":"8017",
    "addr:postcode":"85747",
    "addr:street":"S Wild Primrose Ave",
    "iso:country":"US",
    "sg:address":"8017 S Wild Primrose Ave",
    "sg:city":"Tucson",
    "sg:classifiers":[
        {
            "category":"Education",
            "subcategory":"Special Training",
            "type":"Public Place"
        }
    ],
    "sg:phone":"+1 520 591 2512",
    "sg:postcode":"85747",
    "sg:province":"AZ",
    "sg:tags":[
        "aid",
        "instruction",
        "first"
    ],
    "wof:name":"CPR Plus & First Aid",
    "wof:placetype":"venue"
},
  "geometry": {"coordinates":[-110.79663499999999,32.108018],"type":"Point"}
}