{
  "type": "Feature",
  "properties": {
    "addr:full":"2011 Commercial Way Bullhead City AZ 86442",
    "addr:housenumber":"2011",
    "addr:postcode":"86442",
    "addr:street":"Commercial Way",
    "iso:country":"US",
    "sg:address":"2011 Commercial Way",
    "sg:city":"Bullhead City",
    "sg:classifiers":[
        {
            "category":"Professional",
            "subcategory":"Employment Agencies",
            "type":"Services"
        }
    ],
    "sg:phone":"+1 928 704 9675",
    "sg:postcode":"86442",
    "sg:province":"AZ",
    "sg:tags":[
        "opportunity"
    ],
    "wof:name":"Labor Ready Inc",
    "wof:placetype":"venue"
},
  "geometry": {"coordinates":[-114.62342200000001,35.099438],"type":"Point"}
}