{
  "type": "Feature",
  "properties": {
    "iso:country":"US",
    "sg:address":"1601 N Tucson Blvd",
    "sg:city":"Tucson",
    "sg:classifiers":[
        {
            "category":"Social Services",
            "type":"Services"
        }
    ],
    "sg:phone":"+1 520 325 3511",
    "sg:postcode":"85716",
    "sg:province":"AZ",
    "sg:tags":[
        "counselor",
        "marriage",
        "family"
    ],
    "wof:name":"Gail M Kranz",
    "wof:placetype":"venue"
},
  "geometry": {"coordinates":[-110.935373,32.24272],"type":"Point"}
}