{
  "type": "Feature",
  "properties": {
    "iso:country":"US",
    "sg:address":"6630 N 47th Ave",
    "sg:city":"Glendale",
    "sg:classifiers":[
        {
            "category":"Building & Trades",
            "subcategory":"Cleaning & Sanitation",
            "type":"Services"
        }
    ],
    "sg:phone":"+1 623 931 6216",
    "sg:postcode":"85301",
    "sg:province":"AZ",
    "sg:tags":[
        "janitor"
    ],
    "sg:website":"www.biojanitorial.com",
    "wof:name":"Bio-Janitorial Svc Inc",
    "wof:placetype":"venue"
},
  "geometry": {"coordinates":[-112.16010799999999,33.533245],"type":"Point"}
}