{
  "type": "Feature",
  "properties": {
    "addr:full":"2435 E Southern Ave Ste 7 Tempe AZ 85282",
    "addr:housenumber":"2435",
    "addr:postcode":"85282",
    "addr:street":"E Southern Ave Ste 7",
    "iso:country":"US",
    "sg:address":"2435 E Southern Ave Ste 7",
    "sg:city":"Tempe",
    "sg:classifiers":[
        {
            "category":"Health Services",
            "subcategory":"Health Practitioner",
            "type":"Services"
        },
        {
            "category":"Communications",
            "type":"Services"
        }
    ],
    "sg:phone":"+1 480 345 2012",
    "sg:postcode":"85282",
    "sg:province":"AZ",
    "sg:tags":[
        "pathologist",
        "speech-language",
        "myofunctional",
        "therapy"
    ],
    "wof:name":"Patricia Nedberg",
    "wof:placetype":"venue"
},
  "geometry": {"coordinates":[-111.887246,33.393009],"type":"Point"}
}