{
  "type": "Feature",
  "properties": {
    "addr:full":"5681 E 21st St Tucson AZ 85711",
    "addr:housenumber":"5681",
    "addr:postcode":"85711",
    "addr:street":"E 21St St",
    "iso:country":"US",
    "sg:address":"5681 E 21st St",
    "sg:city":"Tucson",
    "sg:classifiers":[
        {
            "category":"Professional",
            "subcategory":"Computer Services",
            "type":"Services"
        }
    ],
    "sg:phone":"+1 520 488 8666",
    "sg:postcode":"85711",
    "sg:province":"AZ",
    "sg:tags":[
        "technical",
        "assistance",
        "support"
    ],
    "sg:website":"http://www.logicitc.com",
    "wof:name":"Logic It Consulting",
    "wof:placetype":"venue"
},
  "geometry": {"coordinates":[-110.870959,32.208082],"type":"Point"}
}