{
  "type": "Feature",
  "properties": {
    "iso:country":"US",
    "sg:address":"4220 W Hartford Ave",
    "sg:city":"Glendale",
    "sg:classifiers":[
        {
            "category":"Shopping",
            "subcategory":"Hobbies, Toys, & Games",
            "type":"Retail Goods"
        }
    ],
    "sg:phone":"+1 623 742 7138",
    "sg:postcode":"85308",
    "sg:province":"AZ",
    "sg:tags":[
        "product",
        "ceramic"
    ],
    "wof:name":"Five Star Ceramics",
    "wof:placetype":"venue"
},
  "geometry": {"coordinates":[-112.149756,33.641906],"type":"Point"}
}