{
  "type": "Feature",
  "properties": {
    "iso:country":"US",
    "sg:address":"1042 N Higley Rd",
    "sg:city":"Mesa",
    "sg:classifiers":[
        {
            "category":"Banks & Credit Unions",
            "subcategory":"Bank",
            "type":"Services"
        }
    ],
    "sg:phone":"+1 480 325 0334",
    "sg:postcode":"85205",
    "sg:province":"AZ",
    "sg:tags":[
        "institution",
        "business"
    ],
    "wof:name":"Beneficial Arizona Inc",
    "wof:placetype":"venue"
},
  "geometry": {"coordinates":[-111.719094,33.434133],"type":"Point"}
}