{
  "type": "Feature",
  "properties": {
    "iso:country":"US",
    "sg:address":"1616 E Main St",
    "sg:city":"Mesa",
    "sg:classifiers":[
        {
            "category":"Cinema",
            "subcategory":"Movie Rental",
            "type":"Entertainment"
        }
    ],
    "sg:phone":"+1 480 733 8880",
    "sg:postcode":"85203",
    "sg:province":"AZ",
    "sg:tags":[
        "leasing",
        "video",
        "disc",
        "tape"
    ],
    "wof:name":"Clean Films",
    "wof:placetype":"venue"
},
  "geometry": {"coordinates":[-111.794736,33.415377],"type":"Point"}
}