{
  "type": "Feature",
  "properties": {
    "iso:country":"US",
    "sg:address":"2812 N. Norwalk Ste 116",
    "sg:city":"Mesa",
    "sg:classifiers":[
        {
            "category":"Building & Trades",
            "subcategory":"Construction",
            "type":"Services"
        },
        {
            "category":"Manufacturing",
            "subcategory":"Building Materials",
            "type":"Manufacturing & Wholesale Goods"
        },
        {
            "category":"Sports & Exercise",
            "subcategory":"Swimming Pool",
            "type":"Entertainment"
        }
    ],
    "sg:phone":"+1 480 491 2337",
    "sg:postcode":"85215",
    "sg:province":"AZ",
    "sg:tags":[
        "cover",
        "accessory",
        "gate",
        "contractor",
        "enclosure",
        "fence-sales"
    ],
    "sg:website":"http://www.entrydesignsllc.com",
    "wof:name":"Entry Designs LLC",
    "wof:placetype":"venue"
},
  "geometry": {"coordinates":[-111.742378,33.467461],"type":"Point"}
}