{
  "type": "Feature",
  "properties": {
    "iso:country":"US",
    "sg:address":"12419 E Nightingale Ln",
    "sg:city":"Chandler",
    "sg:classifiers":[
        {
            "category":"Manufacturing",
            "subcategory":"Tools & Machinery",
            "type":"Manufacturing & Wholesale Goods"
        }
    ],
    "sg:phone":"+1 480 895 6978",
    "sg:postcode":"85286",
    "sg:province":"AZ",
    "sg:tags":[
        "equipment",
        "industrial",
        "mfg"
    ],
    "wof:name":"Taig Tool",
    "wof:placetype":"venue"
},
  "geometry": {"coordinates":[-111.80690300000001,33.257052],"type":"Point"}
}