{
  "type": "Feature",
  "properties": {
    "addr:full":"46639 N Central Ave 6th Fl Phoenix AZ 85086",
    "addr:housenumber":"46639",
    "addr:postcode":"85086",
    "addr:street":"N Central Ave",
    "iso:country":"US",
    "sg:address":"46639 N Central Ave 6th Fl",
    "sg:city":"Phoenix",
    "sg:classifiers":[
        {
            "category":"Wholesale",
            "subcategory":"Computers",
            "type":"Manufacturing & Wholesale Goods"
        }
    ],
    "sg:phone":"+1 623 465 9310",
    "sg:postcode":"85086",
    "sg:province":"AZ",
    "sg:tags":[
        "equipment"
    ],
    "wof:name":"Iron Horse Distributing, Inc",
    "wof:placetype":"venue"
},
  "geometry": {"coordinates":[-112.074524,33.811769],"type":"Point"}
}