{
  "type": "Feature",
  "properties": {
    "iso:country":"US",
    "sg:address":"2101 W Alice Ave",
    "sg:city":"Phoenix",
    "sg:classifiers":[
        {
            "category":"Utilities",
            "subcategory":"Cable",
            "type":"Services"
        }
    ],
    "sg:phone":"+1 602 870 1277",
    "sg:postcode":"85021",
    "sg:province":"AZ",
    "sg:tags":[
        "television"
    ],
    "wof:name":"Tvmax Inc",
    "wof:placetype":"venue"
},
  "geometry": {"coordinates":[-112.103237,33.563826],"type":"Point"}
}