{
  "type": "Feature",
  "properties": {
    "iso:country":"US",
    "sg:address":"496 W Center St",
    "sg:city":"Chino Valley",
    "sg:classifiers":[
        {
            "category":"Freight",
            "type":"Transportation"
        }
    ],
    "sg:phone":"+1 928 636 2010",
    "sg:postcode":"86323",
    "sg:province":"AZ",
    "sg:tags":[
        "marina",
        "operation",
        "ware",
        "special",
        "general"
    ],
    "wof:name":"Budget Mini Storage",
    "wof:placetype":"venue"
},
  "geometry": {"coordinates":[-112.460367,34.745612],"type":"Point"}
}