{
  "type": "Feature",
  "properties": {
    "iso:country":"US",
    "sg:address":"2211 E Highland Ave",
    "sg:city":"Phoenix",
    "sg:classifiers":[
        {
            "category":"Professional",
            "subcategory":"Accounting & Tax Preparation",
            "type":"Services"
        }
    ],
    "sg:phone":"+1 602 957 6288",
    "sg:postcode":"85016",
    "sg:province":"AZ",
    "sg:tags":[
        "billing"
    ],
    "sg:website":"www.ihmsllc.com",
    "wof:name":"Integrated Health Management",
    "wof:placetype":"venue"
},
  "geometry": {"coordinates":[-112.03249599999999,33.505612],"type":"Point"}
}