{
  "type": "Feature",
  "properties": {
    "iso:country":"US",
    "sg:address":"1156 N Hohokam Dr",
    "sg:city":"Nogales",
    "sg:classifiers":[
        {
            "category":"Home & Garden",
            "subcategory":"Building Materials",
            "type":"Retail Goods"
        },
        {
            "category":"Building & Trades",
            "subcategory":"Construction",
            "type":"Services"
        }
    ],
    "sg:phone":"+1 520 281 2101",
    "sg:postcode":"85621",
    "sg:province":"AZ",
    "sg:tags":[
        "glass",
        "window",
        "work",
        "plate",
        "glazing"
    ],
    "wof:name":"Nogales Glass & Aluminum Co",
    "wof:placetype":"venue"
},
  "geometry": {"coordinates":[-110.928588,31.355636],"type":"Point"}
}