{
  "type": "Feature",
  "properties": {
    "iso:country":"US",
    "sg:address":"3553 W Dunlap Ave",
    "sg:city":"Phoenix",
    "sg:classifiers":[
        {
            "category":"Restaurant",
            "type":"Food & Drink"
        },
        {
            "category":"Food & Beverages",
            "subcategory":"Ethnic Foods",
            "type":"Retail Goods"
        }
    ],
    "sg:phone":"+1 602 324 9670",
    "sg:postcode":"85051",
    "sg:province":"AZ",
    "sg:tags":[
        "asian",
        "pan",
        "vietnamese"
    ],
    "wof:name":"Asian Bistro",
    "wof:placetype":"venue"
},
  "geometry": {"coordinates":[-112.135761,33.567558],"type":"Point"}
}