{
  "type": "Feature",
  "properties": {
    "addr:full":"3845 N 29th Ave Phoenix AZ 85017",
    "addr:housenumber":"3845",
    "addr:postcode":"85017",
    "addr:street":"N 29Th Ave",
    "iso:country":"US",
    "sg:address":"3845 N 29th Ave",
    "sg:city":"Phoenix",
    "sg:classifiers":[
        {
            "category":"Manufacturing",
            "subcategory":"Metals",
            "type":"Manufacturing & Wholesale Goods"
        }
    ],
    "sg:phone":"+1 602 279 4810",
    "sg:postcode":"85017",
    "sg:province":"AZ",
    "sg:tags":[
        "sheet",
        "metalwork",
        "component",
        "co",
        "mfg"
    ],
    "sg:website":"www.phxmetal.com",
    "wof:name":"Phoenix Metalcraft Inc",
    "wof:placetype":"venue"
},
  "geometry": {"coordinates":[-112.120869,33.493147],"type":"Point"}
}