{
  "type": "Feature",
  "properties": {
    "addr:full":"200 E Second St Winslow AZ 86047",
    "addr:housenumber":"200",
    "addr:postcode":"86047",
    "addr:street":"E Second St",
    "iso:country":"US",
    "sg:address":"200 E Second St",
    "sg:city":"Winslow",
    "sg:classifiers":[
        {
            "category":"Insurance",
            "subcategory":"Hazard Insurance",
            "type":"Services"
        }
    ],
    "sg:phone":"+1 928 289 2494",
    "sg:postcode":"86047",
    "sg:province":"AZ",
    "sg:tags":[
        "commercial",
        "business"
    ],
    "wof:name":"C & R Insurance",
    "wof:placetype":"venue"
},
  "geometry": {"coordinates":[-110.695849,35.022448],"type":"Point"}
}