{
  "type": "Feature",
  "properties": {
    "addr:full":"5010 N 95th Ave Glendale AZ 85305",
    "addr:housenumber":"5010",
    "addr:postcode":"85305",
    "addr:street":"N 95Th Ave",
    "iso:country":"US",
    "sg:address":"5010 N 95th Ave",
    "sg:city":"Glendale",
    "sg:classifiers":[
        {
            "category":"Banks & Credit Unions",
            "subcategory":"Bank",
            "type":"Services"
        }
    ],
    "sg:phone":"+1 623 877 4450",
    "sg:postcode":"85305",
    "sg:province":"AZ",
    "wof:name":"Sunbank",
    "wof:placetype":"venue"
},
  "geometry": {"coordinates":[-112.26399000000001,33.508873],"type":"Point"}
}