{
  "type": "Feature",
  "properties": {
    "addr:full":"5136 N 83rd Ave Glendale AZ 85303",
    "addr:housenumber":"5136",
    "addr:postcode":"85303",
    "addr:street":"N 83Rd Ave",
    "iso:country":"US",
    "sg:address":"5136 N 83rd Ave",
    "sg:city":"Glendale",
    "sg:classifiers":[
        {
            "category":"Building & Trades",
            "subcategory":"Construction",
            "type":"Services"
        }
    ],
    "sg:phone":"+1 623 872 1254",
    "sg:postcode":"85303",
    "sg:province":"AZ",
    "sg:tags":[
        "new",
        "housing",
        "general",
        "contractor"
    ],
    "wof:name":"Erk Construction Co",
    "wof:placetype":"venue"
},
  "geometry": {"coordinates":[-112.23776599999999,33.50975],"type":"Point"}
}