{
  "type": "Feature",
  "properties": {
    "addr:full":"15 N 57th Ave Phoenix AZ 85043",
    "addr:housenumber":"15",
    "addr:postcode":"85043",
    "addr:street":"N 57Th Ave",
    "iso:country":"US",
    "sg:address":"15 N 57th Ave",
    "sg:city":"Phoenix",
    "sg:classifiers":[
        {
            "category":"Manufacturing",
            "subcategory":"Metals",
            "type":"Manufacturing & Wholesale Goods"
        }
    ],
    "sg:phone":"+1 602 233 3580",
    "sg:postcode":"85043",
    "sg:province":"AZ",
    "sg:tags":[
        "plumbing",
        "fixture",
        "supply"
    ],
    "wof:name":"Arizona Partsmaster Inc",
    "wof:placetype":"venue"
},
  "geometry": {"coordinates":[-112.18303899999999,33.448005],"type":"Point"}
}