{
  "type": "Feature",
  "properties": {
    "iso:country":"US",
    "sg:address":"15 N 57th Ave",
    "sg:city":"Phoenix",
    "sg:classifiers":[
        {
            "category":"Manufacturing",
            "subcategory":"Metals",
            "type":"Manufacturing & Wholesale Goods"
        }
    ],
    "sg:phone":"+1 602 233 3580",
    "sg:postcode":"85043",
    "sg:province":"AZ",
    "sg:tags":[
        "plumbing",
        "fixture",
        "supply"
    ],
    "wof:name":"Arizona Partsmaster Inc",
    "wof:placetype":"venue"
},
  "geometry": {"coordinates":[-112.183039,33.448005],"type":"Point"}
}