{
  "type": "Feature",
  "properties": {
    "iso:country":"US",
    "sg:address":"1313 W Frier Dr",
    "sg:city":"Phoenix",
    "sg:classifiers":[
        {
            "category":"Professional",
            "subcategory":"Engineering",
            "type":"Services"
        }
    ],
    "sg:phone":"+1 602 943 3151",
    "sg:postcode":"85021",
    "sg:province":"AZ",
    "sg:tags":[
        "consulting",
        "engineer"
    ],
    "wof:name":"Campion Fuel Engineering Co",
    "wof:placetype":"venue"
},
  "geometry": {"coordinates":[-112.08878,33.54879],"type":"Point"}
}