{
  "type": "Feature",
  "properties": {
    "addr:full":"2339 Ashfork Ave Kingman AZ 86401",
    "addr:housenumber":"2339",
    "addr:postcode":"86401",
    "addr:street":"Ashfork Ave",
    "iso:country":"US",
    "sg:address":"2339 Ashfork Ave",
    "sg:city":"Kingman",
    "sg:classifiers":[
        {
            "category":"Mining & Drilling",
            "type":"Manufacturing & Wholesale Goods"
        }
    ],
    "sg:phone":"+1 928 753 1153",
    "sg:postcode":"86401",
    "sg:province":"AZ",
    "sg:tags":[
        "company"
    ],
    "wof:name":"Sawyers Mining Co",
    "wof:placetype":"venue"
},
  "geometry": {"coordinates":[-114.02386799999999,35.205283],"type":"Point"}
}