{
  "type": "Feature",
  "properties": {
    "iso:country":"US",
    "sg:address":"8034 E Via Bonita",
    "sg:city":"Scottsdale",
    "sg:classifiers":[
        {
            "category":"Shopping",
            "subcategory":"Beauty & Cosmetics",
            "type":"Retail Goods"
        }
    ],
    "sg:phone":"+1 480 443 0086",
    "sg:postcode":"85258",
    "sg:province":"AZ",
    "wof:name":"Susan Jacobson Cometics",
    "wof:placetype":"venue"
},
  "geometry": {"coordinates":[-111.909816,33.559723],"type":"Point"}
}