{
  "type": "Feature",
  "properties": {
    "iso:country":"US",
    "sg:address":"4075 S Arizona Avenue",
    "sg:city":"Chandler",
    "sg:classifiers":[
        {
            "category":"Fast Food",
            "type":"Food & Drink"
        },
        {
            "category":"Food & Beverages",
            "subcategory":"Meat & Fish",
            "type":"Retail Goods"
        }
    ],
    "sg:phone":"+1 480 895 4650",
    "sg:postcode":"85248",
    "sg:province":"AZ",
    "sg:tags":[
        "burger",
        "hot",
        "dog"
    ],
    "wof:name":"Burger King",
    "wof:placetype":"venue"
},
  "geometry": {"coordinates":[-111.84850299999999,33.250118],"type":"Point"}
}