{
  "type": "Feature",
  "properties": {
    "iso:country":"US",
    "sg:address":"8939 W Melinda Ln",
    "sg:city":"Peoria",
    "sg:classifiers":[
        {
            "category":"Building & Trades",
            "subcategory":"Electrical",
            "type":"Services"
        },
        {
            "category":"Building & Trades",
            "subcategory":"Plumbing",
            "type":"Services"
        }
    ],
    "sg:phone":"+1 623 825 1756",
    "sg:postcode":"85382",
    "sg:province":"AZ",
    "sg:tags":[
        "conditioning",
        "contractor",
        "electrical",
        "system",
        "air"
    ],
    "wof:name":"Infinity Electric & AC Inc",
    "wof:placetype":"venue"
},
  "geometry": {"coordinates":[-112.252048,33.67986],"type":"Point"}
}