{
  "type": "Feature",
  "properties": {
    "iso:country":"US",
    "sg:address":"24790 E Diversion Dam Rd",
    "sg:city":"Florence",
    "sg:classifiers":[
        {
            "category":"Farming",
            "subcategory":"Dairy Farm",
            "type":"Manufacturing & Wholesale Goods"
        }
    ],
    "sg:phone":"+1 520 868 5367",
    "sg:postcode":"85232",
    "sg:province":"AZ",
    "wof:name":"Ruby Carter",
    "wof:placetype":"venue"
},
  "geometry": {"coordinates":[-111.299473,33.086615],"type":"Point"}
}