{
  "type": "Feature",
  "properties": {
    "addr:full":"8687 E Via de Ventura Scottsdale AZ 85258",
    "addr:housenumber":"8687",
    "addr:postcode":"85258",
    "addr:street":"E Via De Ventura",
    "iso:country":"US",
    "sg:address":"8687 E Via de Ventura",
    "sg:city":"Scottsdale",
    "sg:classifiers":[
        {
            "category":"Real Estate",
            "subcategory":"Real Estate Agent",
            "type":"Services"
        }
    ],
    "sg:phone":"+1 480 443 4880",
    "sg:postcode":"85258",
    "sg:province":"AZ",
    "sg:tags":[
        "appraiser"
    ],
    "wof:name":"H W Zyck & Assoc",
    "wof:placetype":"venue"
},
  "geometry": {"coordinates":[-111.89585,33.553853],"type":"Point"}
}