{
  "type": "Feature",
  "properties": {
    "addr:full":"6955 S Priest Dr Tempe AZ 85283",
    "addr:housenumber":"6955",
    "addr:postcode":"85283",
    "addr:street":"S Priest Dr",
    "iso:country":"US",
    "sg:address":"6955 S Priest Dr",
    "sg:city":"Tempe",
    "sg:classifiers":[
        {
            "category":"Building & Trades",
            "subcategory":"Construction",
            "type":"Services"
        }
    ],
    "sg:phone":"+1 480 921 2727",
    "sg:postcode":"85283",
    "sg:province":"AZ",
    "sg:tags":[
        "industrial",
        "altering",
        "consultant",
        "contractor",
        "contractors-commercial",
        "remodeling"
    ],
    "wof:name":"Versatube Building Systems",
    "wof:placetype":"venue"
},
  "geometry": {"coordinates":[-111.963148,33.356051],"type":"Point"}
}