{
  "type": "Feature",
  "properties": {
    "addr:full":"1825 E Northern Ave Ste 1 Phoenix AZ 85020",
    "addr:housenumber":"1825",
    "addr:postcode":"85020",
    "addr:street":"E Northern Ave Ste 1",
    "iso:country":"US",
    "sg:address":"1825 E Northern Ave Ste 1",
    "sg:city":"Phoenix",
    "sg:classifiers":[
        {
            "category":"Health Services",
            "subcategory":"Doctor",
            "type":"Services"
        },
        {
            "category":"Health Services",
            "subcategory":"Clinic",
            "type":"Services"
        }
    ],
    "sg:phone":"+1 602 697 1286",
    "sg:postcode":"85020",
    "sg:province":"AZ",
    "sg:tags":[
        "psychological",
        "psychologist"
    ],
    "wof:name":"Arizona Child Psychology Center, Inc.",
    "wof:placetype":"venue"
},
  "geometry": {"coordinates":[-112.043031,33.555764],"type":"Point"}
}