{
  "type": "Feature",
  "properties": {
    "iso:country":"US",
    "sg:address":"4027 E Palm Ln",
    "sg:city":"Phoenix",
    "sg:classifiers":[
        {
            "category":"Taxi",
            "type":"Transportation"
        }
    ],
    "sg:phone":"+1 602 722 8792",
    "sg:postcode":"85008",
    "sg:province":"AZ",
    "sg:tags":[
        "taxicab"
    ],
    "wof:name":"Airstar Airport Shuttle-Taxi",
    "wof:placetype":"venue"
},
  "geometry": {"coordinates":[-111.993877,33.469282],"type":"Point"}
}