{
  "type": "Feature",
  "properties": {
    "addr:full":"1527 W Morrow Dr Phoenix AZ 85027",
    "addr:housenumber":"1527",
    "addr:postcode":"85027",
    "addr:street":"W Morrow Dr",
    "iso:country":"US",
    "sg:address":"1527 W Morrow Dr",
    "sg:city":"Phoenix",
    "sg:classifiers":[
        {
            "category":"Building & Trades",
            "subcategory":"Pest Control",
            "type":"Services"
        }
    ],
    "sg:phone":"+1 623 587 1538",
    "sg:postcode":"85027",
    "sg:province":"AZ",
    "wof:name":"Maricopa Exterminating Co",
    "wof:placetype":"venue"
},
  "geometry": {"coordinates":[-112.094617,33.657114],"type":"Point"}
}