{
  "type": "Feature",
  "properties": {
    "iso:country":"US",
    "sg:address":"6170 W Chandler Blvd",
    "sg:city":"Chandler",
    "sg:classifiers":[
        {
            "category":"Home & Garden",
            "subcategory":"Carpets & Floor Coverings",
            "type":"Retail Goods"
        }
    ],
    "sg:phone":"+1 480 893 2128",
    "sg:postcode":"85226",
    "sg:province":"AZ",
    "sg:tags":[
        "dealer",
        "rug"
    ],
    "wof:name":"Frye's Flooring",
    "wof:placetype":"venue"
},
  "geometry": {"coordinates":[-111.946588,33.305418],"type":"Point"}
}