{
  "type": "Feature",
  "properties": {
    "iso:country":"US",
    "sg:address":"1540 Countryshire Ave",
    "sg:city":"Lake Havasu City",
    "sg:classifiers":[
        {
            "category":"Home & Garden",
            "subcategory":"Home Furnishings",
            "type":"Retail Goods"
        }
    ],
    "sg:phone":"+1 928 855 2213",
    "sg:postcode":"86403",
    "sg:province":"AZ",
    "sg:tags":[
        "upholstery",
        "material",
        "made",
        "au",
        "curtain",
        "drapery",
        "furniture"
    ],
    "wof:name":"Laura's Inc",
    "wof:placetype":"venue"
},
  "geometry": {"coordinates":[-114.349714,34.491567],"type":"Point"}
}