{
  "type": "Feature",
  "properties": {
    "iso:country":"US",
    "sg:address":"2601 E Airport Dr",
    "sg:city":"Tucson",
    "sg:classifiers":[
        {
            "category":"Professional",
            "subcategory":"Research",
            "type":"Services"
        }
    ],
    "sg:phone":"+1 520 626 3322",
    "sg:postcode":"85706",
    "sg:province":"AZ",
    "sg:tags":[
        "laboratory"
    ],
    "wof:name":"Environmental Research Lab",
    "wof:placetype":"venue"
},
  "geometry": {"coordinates":[-110.932828,32.119818],"type":"Point"}
}