{
  "type": "Feature",
  "properties": {
    "iso:country":"US",
    "sg:address":"536 N Cheri Lynn Dr",
    "sg:city":"Chandler",
    "sg:classifiers":[
        {
            "category":"Freight",
            "type":"Transportation"
        }
    ],
    "sg:phone":"+1 480 963 7452",
    "sg:postcode":"85225",
    "sg:province":"AZ",
    "sg:tags":[
        "operator",
        "trucking"
    ],
    "wof:name":"Keystone Enterprises",
    "wof:placetype":"venue"
},
  "geometry": {"coordinates":[-111.853437,33.31284],"type":"Point"}
}