{
  "type": "Feature",
  "properties": {
    "iso:country":"US",
    "sg:address":"3800 S Cantabria Cir",
    "sg:city":"Chandler",
    "sg:classifiers":[
        {
            "category":"Banks & Credit Unions",
            "subcategory":"Investment Brokerage",
            "type":"Services"
        }
    ],
    "sg:phone":"+1 480 855 4325",
    "sg:postcode":"85248",
    "sg:province":"AZ",
    "sg:tags":[
        "advisory"
    ],
    "wof:name":"Harris Financial Services",
    "wof:placetype":"venue"
},
  "geometry": {"coordinates":[-111.869929,33.249618],"type":"Point"}
}