{
  "type": "Feature",
  "properties": {
    "iso:country":"US",
    "sg:address":"1961 Hwy 95",
    "sg:city":"Bullhead City",
    "sg:classifiers":[
        {
            "category":"Home & Garden",
            "subcategory":"Building Materials",
            "type":"Retail Goods"
        }
    ],
    "sg:phone":"+1 928 754 7004",
    "sg:postcode":"86442",
    "sg:province":"AZ",
    "sg:tags":[
        "glass",
        "window",
        "plate"
    ],
    "wof:name":"Advantage Windshield Repair",
    "wof:placetype":"venue"
},
  "geometry": {"coordinates":[-114.598088,35.117837],"type":"Point"}
}