{
  "type": "Feature",
  "properties": {
    "iso:country":"US",
    "sg:address":"2001 W Camelback Rd # 250",
    "sg:city":"Phoenix",
    "sg:classifiers":[
        {
            "category":"Professional",
            "subcategory":"Employment Agencies",
            "type":"Services"
        },
        {
            "category":"Health Services",
            "subcategory":"Nursing And Care Facility",
            "type":"Services"
        },
        {
            "category":"Health Services",
            "subcategory":"Health Practitioner",
            "type":"Services"
        }
    ],
    "sg:phone":"+1 602 249 0991",
    "sg:postcode":"85015",
    "sg:province":"AZ",
    "sg:tags":[
        "home",
        "eldercare-home",
        "contractor"
    ],
    "sg:website":"http://www.healthcaredepot.com",
    "wof:name":"Professional Nursing Services",
    "wof:placetype":"venue"
},
  "geometry": {"coordinates":[-112.10244,33.509602],"type":"Point"}
}