{
  "type": "Feature",
  "properties": {
    "iso:country":"US",
    "sg:address":"2235 W 1st St Ste 104",
    "sg:city":"Tempe",
    "sg:classifiers":[
        {
            "category":"Manufacturing",
            "subcategory":"Food",
            "type":"Manufacturing & Wholesale Goods"
        },
        {
            "category":"Restaurant",
            "type":"Food & Drink"
        }
    ],
    "sg:phone":"+1 480 456 1080",
    "sg:postcode":"85281",
    "sg:province":"AZ",
    "sg:tags":[
        "pasta",
        "product",
        "italian"
    ],
    "sg:website":"http://www.deciopasta.com",
    "wof:name":"Decio Pasta, Inc.",
    "wof:placetype":"venue"
},
  "geometry": {"coordinates":[-111.975016,33.42849],"type":"Point"}
}