{
  "type": "Feature",
  "properties": {
    "iso:country":"US",
    "sg:address":"2040 W Pinnacle Peak Rd",
    "sg:city":"Phoenix",
    "sg:classifiers":[
        {
            "category":"Building & Trades",
            "subcategory":"Equipment Rental",
            "type":"Services"
        }
    ],
    "sg:phone":"+1 623 869 7303",
    "sg:postcode":"85027",
    "sg:province":"AZ",
    "sg:tags":[
        "yard"
    ],
    "wof:name":"Hertz Equipment Rental Corp",
    "wof:placetype":"venue"
},
  "geometry": {"coordinates":[-112.103818,33.699166],"type":"Point"}
}