{
  "type": "Feature",
  "properties": {
    "iso:country":"US",
    "sg:address":"250 W Baseline Road Suite 106",
    "sg:city":"Tempe",
    "sg:classifiers":[
        {
            "category":"Professional",
            "subcategory":"Employment Agencies",
            "type":"Services"
        }
    ],
    "sg:phone":"+1 480 820 4366",
    "sg:postcode":"85283",
    "sg:province":"AZ",
    "wof:name":"Pro-Tem Service",
    "wof:placetype":"venue"
},
  "geometry": {"coordinates":[-111.943445,33.378243],"type":"Point"}
}