{
  "type": "Feature",
  "properties": {
    "addr:full":"1850 E 6th St Tempe AZ 85281",
    "addr:housenumber":"1850",
    "addr:postcode":"85281",
    "addr:street":"E 6Th St",
    "iso:country":"US",
    "sg:address":"1850 E 6th St",
    "sg:city":"Tempe",
    "sg:classifiers":[
        {
            "category":"Wholesale",
            "subcategory":"Construction Materials",
            "type":"Manufacturing & Wholesale Goods"
        }
    ],
    "sg:phone":"+1 480 824 1936",
    "sg:postcode":"85281",
    "sg:province":"AZ",
    "sg:tags":[
        "control",
        "system",
        "controls",
        "regulators-wholesale",
        "manufacturer"
    ],
    "wof:name":"Vilor Industries",
    "wof:placetype":"venue"
},
  "geometry": {"coordinates":[-111.90609000000001,33.42495],"type":"Point"}
}