{
  "type": "Feature",
  "properties": {
    "iso:country":"US",
    "sg:address":"7180 E Quail Run Dr",
    "sg:city":"Tucson",
    "sg:classifiers":[
        {
            "category":"Professional",
            "type":"Services"
        }
    ],
    "sg:phone":"+1 520 529 0797",
    "sg:postcode":"85750",
    "sg:province":"AZ",
    "sg:tags":[
        "establishment"
    ],
    "wof:name":"S W Flood Certification",
    "wof:placetype":"venue"
},
  "geometry": {"coordinates":[-110.839217,32.29025],"type":"Point"}
}