{
  "type": "Feature",
  "properties": {
    "addr:full":"250 S Arizona Ave Chandler AZ 85225",
    "addr:housenumber":"250",
    "addr:postcode":"85225",
    "addr:street":"S Arizona Ave",
    "iso:country":"US",
    "sg:address":"250 S Arizona Ave",
    "sg:city":"Chandler",
    "sg:classifiers":[
        {
            "category":"Shopping",
            "subcategory":"Discount & Variety Stores",
            "type":"Retail Goods"
        }
    ],
    "sg:phone":"+1 480 782 0590",
    "sg:postcode":"85225",
    "sg:province":"AZ",
    "sg:tags":[
        "merchandise",
        "general"
    ],
    "wof:name":"General Store",
    "wof:placetype":"venue"
},
  "geometry": {"coordinates":[-111.841506,33.298891],"type":"Point"}
}