{
  "type": "Feature",
  "properties": {
    "iso:country":"US",
    "sg:address":"3040 S Donald Ave",
    "sg:city":"Tucson",
    "sg:classifiers":[
        {
            "category":"Professional",
            "type":"Services"
        }
    ],
    "sg:phone":"+1 520 444 6802",
    "sg:postcode":"85735",
    "sg:province":"AZ",
    "wof:name":"Danika M Brown",
    "wof:placetype":"venue"
},
  "geometry": {"coordinates":[-111.099145,32.186383],"type":"Point"}
}