{
  "type": "Feature",
  "properties": {
    "iso:country":"US",
    "sg:address":"29826 N 48th Way",
    "sg:city":"Cave Creek",
    "sg:classifiers":[
        {
            "category":"Manufacturing",
            "subcategory":"Apparel",
            "type":"Manufacturing & Wholesale Goods"
        }
    ],
    "sg:phone":"+1 480 205 0821",
    "sg:postcode":"85331",
    "sg:province":"AZ",
    "sg:tags":[
        "textile",
        "product",
        "fabricated",
        "mfg"
    ],
    "wof:name":"Well Hung Tops LLC",
    "wof:placetype":"venue"
},
  "geometry": {"coordinates":[-111.977888,33.755511],"type":"Point"}
}