{
  "type": "Feature",
  "properties": {
    "iso:country":"US",
    "sg:address":"12599 N 72nd Pl",
    "sg:city":"Scottsdale",
    "sg:classifiers":[
        {
            "category":"Building & Trades",
            "subcategory":"Construction",
            "type":"Services"
        }
    ],
    "sg:phone":"+1 480 657 6633",
    "sg:postcode":"85260",
    "sg:province":"AZ",
    "sg:tags":[
        "residential"
    ],
    "wof:name":"Lobo Jody LLC",
    "wof:placetype":"venue"
},
  "geometry": {"coordinates":[-111.924887,33.600727],"type":"Point"}
}