{
  "type": "Feature",
  "properties": {
    "iso:country":"US",
    "sg:address":"16018 E Tumbleweed Dr",
    "sg:city":"Fountain Hills",
    "sg:classifiers":[
        {
            "category":"Restaurant",
            "type":"Food & Drink"
        }
    ],
    "sg:phone":"+1 480 837 3372",
    "sg:postcode":"85268",
    "sg:province":"AZ",
    "wof:name":"Sasparilla's Billiards",
    "wof:placetype":"venue"
},
  "geometry": {"coordinates":[-111.733679,33.613363],"type":"Point"}
}