{
  "type": "Feature",
  "properties": {
    "addr:full":"2130 W Camelback Rd Phoenix AZ 85015",
    "addr:housenumber":"2130",
    "addr:postcode":"85015",
    "addr:street":"W Camelback Rd",
    "iso:country":"US",
    "sg:address":"2130 W Camelback Rd",
    "sg:city":"Phoenix",
    "sg:classifiers":[
        {
            "category":"Personal",
            "subcategory":"Beauty Salon",
            "type":"Services"
        }
    ],
    "sg:phone":"+1 602 589 9245",
    "sg:postcode":"85015",
    "sg:province":"AZ",
    "wof:name":"Montserrat Beauty Salon",
    "wof:placetype":"venue"
},
  "geometry": {"coordinates":[-112.10575799999999,33.509637],"type":"Point"}
}