{
  "type": "Feature",
  "properties": {
    "iso:country":"US",
    "sg:address":"2130 W Camelback Rd",
    "sg:city":"Phoenix",
    "sg:classifiers":[
        {
            "category":"Personal",
            "subcategory":"Beauty Salon",
            "type":"Services"
        }
    ],
    "sg:phone":"+1 602 589 9245",
    "sg:postcode":"85015",
    "sg:province":"AZ",
    "wof:name":"Montserrat Beauty Salon",
    "wof:placetype":"venue"
},
  "geometry": {"coordinates":[-112.105758,33.509637],"type":"Point"}
}