{
  "type": "Feature",
  "properties": {
    "iso:country":"US",
    "sg:address":"17646 N Cave Creek Rd",
    "sg:city":"Phoenix",
    "sg:classifiers":[
        {
            "category":"Real Estate",
            "subcategory":"Real Estate Operator",
            "type":"Services"
        }
    ],
    "sg:phone":"+1 602 992 0048",
    "sg:postcode":"85032",
    "sg:province":"AZ",
    "sg:tags":[
        "building",
        "apartment"
    ],
    "wof:name":"Paradise Palms Apts & Suites",
    "wof:placetype":"venue"
},
  "geometry": {"coordinates":[-112.030922,33.645538],"type":"Point"}
}