{
  "type": "Feature",
  "properties": {
    "addr:full":"4997 E McDowell Rd Phoenix AZ 85008",
    "addr:housenumber":"4997",
    "addr:postcode":"85008",
    "addr:street":"E Mcdowell Rd",
    "iso:country":"US",
    "sg:address":"4997 E McDowell Rd",
    "sg:city":"Phoenix",
    "sg:classifiers":[
        {
            "category":"Building & Trades",
            "subcategory":"Electrical",
            "type":"Services"
        }
    ],
    "sg:phone":"+1 602 275 8271",
    "sg:postcode":"85008",
    "sg:province":"AZ",
    "sg:tags":[
        "electric",
        "contractor"
    ],
    "wof:name":"G & S Electric",
    "wof:placetype":"venue"
},
  "geometry": {"coordinates":[-111.97769599999999,33.46559],"type":"Point"}
}