{
  "type": "Feature",
  "properties": {
    "iso:country":"US",
    "sg:address":"382 E Palm Ln",
    "sg:city":"Phoenix",
    "sg:classifiers":[
        {
            "category":"Professional",
            "subcategory":"Lawyer & Legal Services",
            "type":"Services"
        }
    ],
    "sg:phone":"+1 602 252 4861",
    "sg:postcode":"85004",
    "sg:province":"AZ",
    "sg:tags":[
        "attorney"
    ],
    "wof:name":"Kleinman Lesselyong Novak & Ru",
    "wof:placetype":"venue"
},
  "geometry": {"coordinates":[-112.068447,33.469445],"type":"Point"}
}