{
  "type": "Feature",
  "properties": {
    "iso:country":"US",
    "sg:address":"3250 N Majesty Dr",
    "sg:city":"Prescott Valley",
    "sg:classifiers":[
        {
            "category":"Real Estate",
            "subcategory":"Real Estate Operator",
            "type":"Services"
        }
    ],
    "sg:phone":"+1 928 772 4441",
    "sg:postcode":"86314",
    "sg:province":"AZ",
    "sg:tags":[
        "apartment"
    ],
    "wof:name":"Prescott Valley Plaza Apts",
    "wof:placetype":"venue"
},
  "geometry": {"coordinates":[-112.312659,34.588207],"type":"Point"}
}