{
  "type": "Feature",
  "properties": {
    "addr:full":"2150 N 46th St Phoenix AZ 85008",
    "addr:housenumber":"2150",
    "addr:postcode":"85008",
    "addr:street":"N 46Th St",
    "iso:country":"US",
    "sg:address":"2150 N 46th St",
    "sg:city":"Phoenix",
    "sg:classifiers":[
        {
            "category":"Recreation",
            "type":"Entertainment"
        }
    ],
    "sg:phone":"+1 602 262 6199",
    "sg:postcode":"85008",
    "sg:province":"AZ",
    "sg:tags":[
        "con"
    ],
    "wof:name":"Parks and Recreation Dept",
    "wof:placetype":"venue"
},
  "geometry": {"coordinates":[-111.98275099999999,33.4707],"type":"Point"}
}