{
  "type": "Feature",
  "properties": {
    "iso:country":"US",
    "sg:address":"933 E University Dr",
    "sg:city":"Tempe",
    "sg:classifiers":[
        {
            "category":"Shopping",
            "subcategory":"Jewelry",
            "type":"Retail Goods"
        }
    ],
    "sg:phone":"+1 480 804 7499",
    "sg:postcode":"85281",
    "sg:province":"AZ",
    "sg:tags":[
        "jeweler"
    ],
    "wof:name":"Pala Jewelers LLC",
    "wof:placetype":"venue"
},
  "geometry": {"coordinates":[-111.92371900000001,33.421962],"type":"Point"}
}