{
  "type": "Feature",
  "properties": {
    "addr:full":"2217 E WASHINGTON ST PHOENIX AZ 85034",
    "addr:housenumber":"2217",
    "addr:postcode":"85034",
    "addr:street":"E Washington St",
    "iso:country":"US",
    "sg:address":"2217 E WASHINGTON ST",
    "sg:city":"PHOENIX",
    "sg:classifiers":[
        {
            "category":"Retail",
            "subcategory":"Auto Rental",
            "type":"Services"
        }
    ],
    "sg:phone":"+1 800 899 4320",
    "sg:postcode":"85034",
    "sg:province":"AZ",
    "sg:tags":[
        "renting",
        "car",
        "leasing",
        "van",
        "trailer"
    ],
    "sg:website":"http://www.a1leasing.com",
    "wof:name":"A1 Van Rentals & Leasing",
    "wof:placetype":"venue"
},
  "geometry": {"coordinates":[-112.033815,33.448207],"type":"Point"}
}