{
  "type": "Feature",
  "properties": {
    "addr:full":"70 Chavez Ranch Rd Sedona AZ 86336",
    "addr:housenumber":"70",
    "addr:postcode":"86336",
    "addr:street":"Chavez Ranch Rd",
    "iso:country":"US",
    "sg:address":"70 Chavez Ranch Rd",
    "sg:city":"Sedona",
    "sg:classifiers":[
        {
            "category":"Restaurant",
            "type":"Food & Drink"
        }
    ],
    "sg:phone":"+1 928 282 0257",
    "sg:postcode":"86336",
    "sg:province":"AZ",
    "sg:tags":[
        "operation",
        "eating"
    ],
    "wof:name":"Stoneflower Bed & Breakfast",
    "wof:placetype":"venue"
},
  "geometry": {"coordinates":[-111.81267800000001,34.833136],"type":"Point"}
}