{
  "type": "Feature",
  "properties": {
    "iso:country":"US",
    "sg:address":"70 Chavez Ranch Rd",
    "sg:city":"Sedona",
    "sg:classifiers":[
        {
            "category":"Restaurant",
            "type":"Food & Drink"
        }
    ],
    "sg:phone":"+1 928 282 0257",
    "sg:postcode":"86336",
    "sg:province":"AZ",
    "sg:tags":[
        "operation",
        "eating"
    ],
    "wof:name":"Stoneflower Bed & Breakfast",
    "wof:placetype":"venue"
},
  "geometry": {"coordinates":[-111.812678,34.833136],"type":"Point"}
}