{
  "type": "Feature",
  "properties": {
    "iso:country":"US",
    "sg:address":"219 E Cherry Ave",
    "sg:city":"Flagstaff",
    "sg:classifiers":[
        {
            "category":"Government",
            "subcategory":"Office",
            "type":"Public Place"
        }
    ],
    "sg:phone":"+1 928 779 6695",
    "sg:postcode":"86001",
    "sg:province":"AZ",
    "sg:tags":[
        "parish",
        "government-county"
    ],
    "sg:website":"http://www.fmn.org",
    "wof:name":"County Managers Office",
    "wof:placetype":"venue"
},
  "geometry": {"coordinates":[-111.64548600000001,35.199553],"type":"Point"}
}