{
  "type": "Feature",
  "properties": {
    "iso:country":"US",
    "sg:address":"100 N 15th Ave Ste 202",
    "sg:city":"Phoenix",
    "sg:classifiers":[
        {
            "category":"Government",
            "subcategory":"Office",
            "type":"Public Place"
        }
    ],
    "sg:phone":"+1 602 542 1405",
    "sg:postcode":"85007",
    "sg:province":"AZ",
    "sg:website":"http://www.az.gov",
    "wof:name":"General Services Division",
    "wof:placetype":"venue"
},
  "geometry": {"coordinates":[-112.091423,33.448706],"type":"Point"}
}