{
  "type": "Feature",
  "properties": {
    "iso:country":"US",
    "sg:address":"11022 N 28th Dr Suite 290",
    "sg:city":"Phoenix",
    "sg:classifiers":[
        {
            "category":"Professional",
            "subcategory":"Lawyer & Legal Services",
            "type":"Services"
        }
    ],
    "sg:phone":"+1 602 910 6795",
    "sg:postcode":"85029",
    "sg:province":"AZ",
    "sg:tags":[
        "attorney",
        "family",
        "divorce",
        "child",
        "law",
        "custody"
    ],
    "sg:website":"http://www.angelaadamslaw.com",
    "wof:name":"The Law Office of Angela Adams, PLLC",
    "wof:placetype":"venue"
},
  "geometry": {"coordinates":[-112.12189100000001,33.58707],"type":"Point"}
}