{
  "type": "Feature",
  "properties": {
    "iso:country":"US",
    "sg:address":"2056 E Brooks St",
    "sg:city":"Gilbert",
    "sg:classifiers":[
        {
            "category":"Professional",
            "subcategory":"Detective & Security Services",
            "type":"Services"
        }
    ],
    "sg:phone":"+1 480 241 7700",
    "sg:postcode":"85296",
    "sg:province":"AZ",
    "sg:tags":[
        "fingerprinting"
    ],
    "wof:name":"A Lasting Impression",
    "wof:placetype":"venue"
},
  "geometry": {"coordinates":[-111.745482,33.335224],"type":"Point"}
}