{
  "type": "Feature",
  "properties": {
    "addr:full":"3235 S Allred Dr Tempe AZ 85282",
    "addr:housenumber":"3235",
    "addr:postcode":"85282",
    "addr:street":"S Allred Dr",
    "iso:country":"US",
    "sg:address":"3235 S Allred Dr",
    "sg:city":"Tempe",
    "sg:classifiers":[
        {
            "category":"Building & Trades",
            "subcategory":"Plumbing",
            "type":"Services"
        }
    ],
    "sg:phone":"+1 480 838 0276",
    "sg:postcode":"85282",
    "sg:province":"AZ",
    "sg:tags":[
        "clean",
        "boilers-repair"
    ],
    "wof:name":"American Pioneer",
    "wof:placetype":"venue"
},
  "geometry": {"coordinates":[-111.885386,33.393383],"type":"Point"}
}