{
  "type": "Feature",
  "properties": {
    "addr:full":"2323 E Edna Ave Phoenix AZ 85022",
    "addr:housenumber":"2323",
    "addr:postcode":"85022",
    "addr:street":"E Edna Ave",
    "iso:country":"US",
    "sg:address":"2323 E Edna Ave",
    "sg:city":"Phoenix",
    "sg:classifiers":[
        {
            "category":"Wholesale",
            "subcategory":"Electrical",
            "type":"Manufacturing & Wholesale Goods"
        }
    ],
    "sg:phone":"+1 602 225 2454",
    "sg:postcode":"85022",
    "sg:province":"AZ",
    "sg:tags":[
        "lighting"
    ],
    "wof:name":"No Jip Lighting",
    "wof:placetype":"venue"
},
  "geometry": {"coordinates":[-112.033681,33.636424],"type":"Point"}
}