{
  "type": "Feature",
  "properties": {
    "addr:full":"26 W Baseline Rd Phoenix AZ 85041",
    "addr:housenumber":"26",
    "addr:postcode":"85041",
    "addr:street":"W Baseline Rd",
    "iso:country":"US",
    "sg:address":"26 W Baseline Rd",
    "sg:city":"Phoenix",
    "sg:phone":"+1 602 304 0560",
    "sg:postcode":"85041",
    "sg:province":"AZ",
    "sg:website":"http://www.factory2u.com",
    "wof:name":"Factory 2u",
    "wof:placetype":"venue"
},
  "geometry": {"coordinates":[-112.07452499999999,33.37775],"type":"Point"}
}