{
  "type": "Feature",
  "properties": {
    "addr:full":"3721 S Hawthorn Dr Chandler AZ 85248",
    "addr:housenumber":"3721",
    "addr:postcode":"85248",
    "addr:street":"S Hawthorn Dr",
    "iso:country":"US",
    "sg:address":"3721 S Hawthorn Dr",
    "sg:city":"Chandler",
    "sg:classifiers":[
        {
            "category":"Professional",
            "subcategory":"Business Services",
            "type":"Services"
        }
    ],
    "sg:phone":"+1 480 899 8807",
    "sg:postcode":"85248",
    "sg:province":"AZ",
    "sg:tags":[
        "interior",
        "consultant",
        "design",
        "decorator"
    ],
    "wof:name":"Ewoldt Interiors LTD",
    "wof:placetype":"venue"
},
  "geometry": {"coordinates":[-111.881255,33.250579],"type":"Point"}
}