{
  "type": "Feature",
  "properties": {
    "iso:country":"US",
    "sg:address":"48890 Ehrenberg-Poston Hwy",
    "sg:city":"Ehrenberg",
    "sg:classifiers":[
        {
            "category":"Real Estate",
            "subcategory":"Real Estate Operator",
            "type":"Services"
        }
    ],
    "sg:phone":"+1 928 923 9741",
    "sg:postcode":"85334",
    "sg:province":"AZ",
    "sg:tags":[
        "apartment"
    ],
    "wof:name":"Casa Riviera Apartments",
    "wof:placetype":"venue"
},
  "geometry": {"coordinates":[-114.50019399999999,33.624012],"type":"Point"}
}