{
  "type": "Feature",
  "properties": {
    "iso:country":"US",
    "sg:address":"1949 W Ray Rd",
    "sg:city":"Chandler",
    "sg:classifiers":[
        {
            "category":"Wholesale",
            "subcategory":"Motor Vehicles",
            "type":"Manufacturing & Wholesale Goods"
        },
        {
            "category":"Banks & Credit Unions",
            "subcategory":"Bank",
            "type":"Services"
        }
    ],
    "sg:phone":"+1 480 899 5600",
    "sg:postcode":"85224",
    "sg:province":"AZ",
    "sg:tags":[
        "automobile",
        "truck",
        "broker",
        "business",
        "institution"
    ],
    "wof:name":"Auto Source",
    "wof:placetype":"venue"
},
  "geometry": {"coordinates":[-111.87473900000001,33.320511],"type":"Point"}
}