{
  "type": "Feature",
  "properties": {
    "iso:country":"US",
    "sg:address":"8033 W Wandering Spring Way",
    "sg:city":"Tucson",
    "sg:classifiers":[
        {
            "category":"Real Estate",
            "subcategory":"Real Estate Agent",
            "type":"Services"
        }
    ],
    "sg:phone":"+1 520 572 2528",
    "sg:postcode":"85743",
    "sg:province":"AZ",
    "wof:name":"SRF Properties Inc",
    "wof:placetype":"venue"
},
  "geometry": {"coordinates":[-111.136207,32.376859],"type":"Point"}
}