{
  "type": "Feature",
  "properties": {
    "iso:country":"US",
    "sg:address":"2200 N Central Ave",
    "sg:city":"Phoenix",
    "sg:classifiers":[
        {
            "category":"Utilities",
            "subcategory":"Natural Gas",
            "type":"Services"
        }
    ],
    "sg:phone":"+1 602 256 2210",
    "sg:postcode":"85004",
    "sg:province":"AZ",
    "sg:tags":[
        "distribution"
    ],
    "wof:name":"S W Gas",
    "wof:placetype":"venue"
},
  "geometry": {"coordinates":[-112.073774,33.472929],"type":"Point"}
}