{
  "type": "Feature",
  "properties": {
    "addr:full":"1305 W Saint Marys Rd Tucson AZ 85745",
    "addr:housenumber":"1305",
    "addr:postcode":"85745",
    "addr:street":"W Saint Marys Rd",
    "iso:country":"US",
    "sg:address":"1305 W Saint Marys Rd",
    "sg:city":"Tucson",
    "sg:classifiers":[
        {
            "category":"Food & Beverages",
            "subcategory":"Meat & Fish",
            "type":"Retail Goods"
        }
    ],
    "sg:phone":"+1 520 791 3715",
    "sg:postcode":"85745",
    "sg:province":"AZ",
    "wof:name":"Super Carneceria El Herradero",
    "wof:placetype":"venue"
},
  "geometry": {"coordinates":[-110.994422,32.229101],"type":"Point"}
}