{
  "type": "Feature",
  "properties": {
    "addr:full":"1328 E Florence Blvd Casa Grande AZ 85222",
    "addr:housenumber":"1328",
    "addr:postcode":"85222",
    "addr:street":"E Florence Blvd",
    "iso:country":"US",
    "sg:address":"1328 E Florence Blvd",
    "sg:city":"Casa Grande",
    "sg:classifiers":[
        {
            "category":"Restaurant",
            "type":"Food & Drink"
        }
    ],
    "sg:menulink":"http://www.allmenus.com/az/casa-grande/102767-the-pita-pit/menu/",
    "sg:phone":"+1 520 426 1855",
    "sg:postcode":"85222",
    "sg:province":"AZ",
    "sg:tags":[
        "salad",
        "soup",
        "eastern",
        "mediterranean",
        "middle",
        "american",
        "greek"
    ],
    "wof:name":"The Pita Pit",
    "wof:placetype":"venue"
},
  "geometry": {"coordinates":[-111.729626,32.87956],"type":"Point"}
}