{
  "type": "Feature",
  "properties": {
    "addr:full":"5160 E Bellevue St Tucson AZ 85712",
    "addr:housenumber":"5160",
    "addr:postcode":"85712",
    "addr:street":"E Bellevue St",
    "iso:country":"US",
    "sg:address":"5160 E Bellevue St",
    "sg:city":"Tucson",
    "sg:classifiers":[
        {
            "category":"Banks & Credit Unions",
            "subcategory":"Financial Services",
            "type":"Services"
        }
    ],
    "sg:phone":"+1 520 327 5537",
    "sg:postcode":"85712",
    "sg:province":"AZ",
    "sg:tags":[
        "investor"
    ],
    "wof:name":"Denman Investments LLC",
    "wof:placetype":"venue"
},
  "geometry": {"coordinates":[-110.882217,32.237929],"type":"Point"}
}