{
  "type": "Feature",
  "properties": {
    "iso:country":"US",
    "sg:address":"2633 E Indian School Rd # 340",
    "sg:city":"Phoenix",
    "sg:classifiers":[
        {
            "category":"Professional",
            "type":"Services"
        }
    ],
    "sg:phone":"+1 602 952 2050",
    "sg:postcode":"85016",
    "sg:province":"AZ",
    "sg:tags":[
        "shows",
        "exposition",
        "fair",
        "trade"
    ],
    "sg:website":"http://www.oasis.org",
    "wof:name":"Oasis",
    "wof:placetype":"venue"
},
  "geometry": {"coordinates":[-112.025199,33.494927],"type":"Point"}
}