{
  "type": "Feature",
  "properties": {
    "addr:full":"11448 S Avenue G 9 E Yuma AZ 85365",
    "addr:housenumber":"11448;9 e",
    "addr:postcode":"85365",
    "addr:street":"S Avenue G",
    "iso:country":"US",
    "sg:address":"11448 S Avenue G 9 E",
    "sg:city":"Yuma",
    "sg:classifiers":[
        {
            "category":"Building & Trades",
            "subcategory":"Construction",
            "type":"Services"
        }
    ],
    "sg:phone":"+1 928 726 4922",
    "sg:postcode":"85365",
    "sg:province":"AZ",
    "sg:tags":[
        "manufactured",
        "housing-communities"
    ],
    "wof:name":"Country Breeze Mobile Home Pk",
    "wof:placetype":"venue"
},
  "geometry": {"coordinates":[-114.736283,32.654759],"type":"Point"}
}