{
  "type": "Feature",
  "properties": {
    "addr:full":"12819 S Warpaint Dr Phoenix AZ 85044",
    "addr:housenumber":"12819",
    "addr:postcode":"85044",
    "addr:street":"S Warpaint Dr",
    "iso:country":"US",
    "sg:address":"12819 S Warpaint Dr",
    "sg:city":"Phoenix",
    "sg:classifiers":[
        {
            "category":"Wholesale",
            "subcategory":"Motor Vehicles",
            "type":"Manufacturing & Wholesale Goods"
        }
    ],
    "sg:phone":"+1 480 460 3075",
    "sg:postcode":"85044",
    "sg:province":"AZ",
    "sg:tags":[
        "automobile",
        "used"
    ],
    "wof:name":"Trans USA",
    "wof:placetype":"venue"
},
  "geometry": {"coordinates":[-112.010491,33.33023],"type":"Point"}
}