{
  "type": "Feature",
  "properties": {
    "addr:full":"220 E Baseline Rd Tempe AZ 85283",
    "addr:housenumber":"220",
    "addr:postcode":"85283",
    "addr:street":"E Baseline Rd",
    "iso:country":"US",
    "sg:address":"220 E Baseline Rd",
    "sg:city":"Tempe",
    "sg:classifiers":[
        {
            "category":"Retail",
            "subcategory":"Veterinary Services",
            "type":"Services"
        }
    ],
    "sg:phone":"+1 480 839 2824",
    "sg:postcode":"85283",
    "sg:province":"AZ",
    "sg:tags":[
        "sitting",
        "pet",
        "hospital",
        "clinic",
        "veterinarian",
        "boarding/pet"
    ],
    "sg:website":"www.baselinevet.com/",
    "wof:name":"Baseline Animal Clinic",
    "wof:placetype":"venue"
},
  "geometry": {"coordinates":[-111.93699599999999,33.378101],"type":"Point"}
}