{
  "type": "Feature",
  "properties": {
    "iso:country":"US",
    "sg:address":"624 W San Angelo St",
    "sg:city":"Gilbert",
    "sg:classifiers":[
        {
            "category":"Building & Trades",
            "subcategory":"Locksmith",
            "type":"Services"
        }
    ],
    "sg:phone":"+1 602 903 4232",
    "sg:postcode":"85233",
    "sg:province":"AZ",
    "sg:tags":[
        "key"
    ],
    "wof:name":"Locksmith 24 Hr",
    "wof:placetype":"venue"
},
  "geometry": {"coordinates":[-111.803414,33.369749],"type":"Point"}
}