{
  "type": "Feature",
  "properties": {
    "addr:full":"305 W Washington St Phoenix AZ 85003",
    "addr:housenumber":"305",
    "addr:postcode":"85003",
    "addr:street":"W Washington St",
    "iso:country":"US",
    "sg:address":"305 W Washington St",
    "sg:city":"Phoenix",
    "sg:classifiers":[
        {
            "category":"Utilities",
            "subcategory":"Water",
            "type":"Services"
        }
    ],
    "sg:phone":"+1 602 262 6251",
    "sg:postcode":"85003",
    "sg:province":"AZ",
    "sg:tags":[
        "management",
        "supply"
    ],
    "wof:name":"Water Services Department",
    "wof:placetype":"venue"
},
  "geometry": {"coordinates":[-112.078889,33.448165],"type":"Point"}
}