{
  "type": "Feature",
  "properties": {
    "iso:country":"US",
    "sg:address":"3007 N 25th Pl",
    "sg:city":"Phoenix",
    "sg:classifiers":[
        {
            "category":"Home & Garden",
            "subcategory":"Building Materials",
            "type":"Retail Goods"
        },
        {
            "category":"Building & Trades",
            "subcategory":"Construction",
            "type":"Services"
        }
    ],
    "sg:phone":"+1 602 294 0306",
    "sg:postcode":"85016",
    "sg:province":"AZ",
    "sg:tags":[
        "concrete",
        "staining",
        "contractor"
    ],
    "sg:website":"http://www.superiorconcreteservices.net",
    "wof:name":"Superior Concrete Services",
    "wof:placetype":"venue"
},
  "geometry": {"coordinates":[-112.026932,33.48219],"type":"Point"}
}