{
  "type": "Feature",
  "properties": {
    "iso:country":"US",
    "sg:address":"5236 W Peoria Ave Ste 119",
    "sg:city":"Glendale",
    "sg:classifiers":[
        {
            "category":"Real Estate",
            "subcategory":"Real Estate Services",
            "type":"Services"
        }
    ],
    "sg:phone":"+1 623 979 4045",
    "sg:postcode":"85302",
    "sg:province":"AZ",
    "sg:tags":[
        "management",
        "condominium",
        "vacancy",
        "apartment",
        "listing",
        "rental",
        "finder"
    ],
    "wof:name":"Sunset Estates Condominiums",
    "wof:placetype":"venue"
},
  "geometry": {"coordinates":[-112.172117,33.581931],"type":"Point"}
}