{
  "type": "Feature",
  "properties": {
    "addr:full":"4325 N Wells Fargo Ave Scottsdale AZ 85251",
    "addr:housenumber":"4325",
    "addr:postcode":"85251",
    "addr:street":"N Wells Fargo Ave",
    "iso:country":"US",
    "sg:address":"4325 N Wells Fargo Ave",
    "sg:city":"Scottsdale",
    "sg:classifiers":[
        {
            "category":"Health Services",
            "subcategory":"Doctor",
            "type":"Services"
        },
        {
            "category":"Health Services",
            "subcategory":"Clinic",
            "type":"Services"
        }
    ],
    "sg:phone":"+1 480 949 6570",
    "sg:postcode":"85251",
    "sg:province":"AZ",
    "sg:tags":[
        "physician",
        "surgeon",
        "surgeons",
        "proctology"
    ],
    "sg:website":"http://detoxforlife.biz",
    "wof:name":"Detox For Life Colon",
    "wof:placetype":"venue"
},
  "geometry": {"coordinates":[-111.922867,33.499378],"type":"Point"}
}