{
  "type": "Feature",
  "properties": {
    "addr:full":"2013 S 8th Ave Safford AZ 85546",
    "addr:housenumber":"2013",
    "addr:postcode":"85546",
    "addr:street":"S 8Th Ave",
    "iso:country":"US",
    "sg:address":"2013 S 8th Ave",
    "sg:city":"Safford",
    "sg:classifiers":[
        {
            "category":"Education",
            "subcategory":"School",
            "type":"Public Place"
        }
    ],
    "sg:phone":"+1 928 348 7010",
    "sg:postcode":"85546",
    "sg:province":"AZ",
    "sg:website":"www.saffordusd.k12.az.us",
    "wof:name":"Safford Unified School",
    "wof:placetype":"venue"
},
  "geometry": {"coordinates":[-109.716052,32.814053],"type":"Point"}
}