{
  "type": "Feature",
  "properties": {
    "iso:country":"US",
    "sg:address":"7580 E Gray Rd",
    "sg:city":"Scottsdale",
    "sg:classifiers":[
        {
            "category":"Building & Trades",
            "subcategory":"Construction",
            "type":"Services"
        }
    ],
    "sg:phone":"+1 480 951 4086",
    "sg:postcode":"85260",
    "sg:province":"AZ",
    "sg:tags":[
        "course",
        "golf"
    ],
    "wof:name":"Sema Golf",
    "wof:placetype":"venue"
},
  "geometry": {"coordinates":[-111.91719000000001,33.612716],"type":"Point"}
}