{
  "type": "Feature",
  "properties": {
    "addr:full":"751 N Arizona Ave Gilbert AZ 85233",
    "addr:housenumber":"751",
    "addr:postcode":"85233",
    "addr:street":"N Arizona Ave",
    "iso:country":"US",
    "sg:address":"751 N Arizona Ave",
    "sg:city":"Gilbert",
    "sg:classifiers":[
        {
            "category":"Building & Trades",
            "subcategory":"Locksmith",
            "type":"Services"
        }
    ],
    "sg:phone":"+1 480 371 3321",
    "sg:postcode":"85233",
    "sg:province":"AZ",
    "sg:tags":[
        "key"
    ],
    "wof:name":"Affordable Locksmith",
    "wof:placetype":"venue"
},
  "geometry": {"coordinates":[-111.84165,33.36317],"type":"Point"}
}