{
  "type": "Feature",
  "properties": {
    "iso:country":"US",
    "sg:address":"10625 N 25th Ave",
    "sg:city":"Phoenix",
    "sg:classifiers":[
        {
            "category":"Professional",
            "subcategory":"Accounting & Tax Preparation",
            "type":"Services"
        }
    ],
    "sg:phone":"+1 602 674 8226",
    "sg:postcode":"85029",
    "sg:province":"AZ",
    "sg:tags":[
        "accountant"
    ],
    "wof:name":"Monica J Stern Pllc",
    "wof:placetype":"venue"
},
  "geometry": {"coordinates":[-112.116189,33.586816],"type":"Point"}
}