{
  "type": "Feature",
  "properties": {
    "addr:full":"1645 N Lindsay Rd Mesa AZ 85213",
    "addr:housenumber":"1645",
    "addr:postcode":"85213",
    "addr:street":"N Lindsay Rd",
    "iso:country":"US",
    "sg:address":"1645 N Lindsay Rd",
    "sg:city":"Mesa",
    "sg:classifiers":[
        {
            "category":"Wholesale",
            "subcategory":"Construction Materials",
            "type":"Manufacturing & Wholesale Goods"
        },
        {
            "category":"Home & Garden",
            "subcategory":"Building Materials",
            "type":"Retail Goods"
        },
        {
            "category":"Building & Trades",
            "subcategory":"Construction",
            "type":"Services"
        },
        {
            "category":"Military Area",
            "subcategory":"Armory",
            "type":"Public Place"
        }
    ],
    "sg:phone":"+1 480 832 7968",
    "sg:postcode":"85213",
    "sg:province":"AZ",
    "sg:tags":[
        "repair",
        "fence",
        "fence-sales",
        "contractor",
        "fence-wholesale",
        "welder",
        "manufacturer"
    ],
    "wof:name":"Augie's Shop",
    "wof:placetype":"venue"
},
  "geometry": {"coordinates":[-111.770853,33.445412],"type":"Point"}
}