{
  "type": "Feature",
  "properties": {
    "iso:country":"US",
    "sg:address":"4201 E Cathedral Rock Dr",
    "sg:city":"Phoenix",
    "sg:classifiers":[
        {
            "category":"Professional",
            "subcategory":"Management & Consulting",
            "type":"Services"
        },
        {
            "category":"Professional",
            "subcategory":"Engineering",
            "type":"Services"
        }
    ],
    "sg:phone":"+1 602 956 0638",
    "sg:postcode":"85044",
    "sg:province":"AZ",
    "sg:tags":[
        "consultant",
        "ecological",
        "engineer",
        "environmental"
    ],
    "sg:website":"http://www.ralconsulting.com",
    "wof:name":"Ral Consulting Inc",
    "wof:placetype":"venue"
},
  "geometry": {"coordinates":[-111.991508,33.30965],"type":"Point"}
}