{
  "type": "Feature",
  "properties": {
    "iso:country":"US",
    "sg:address":"4040 E Mcdowell Rd",
    "sg:city":"Phoenix",
    "sg:classifiers":[
        {
            "category":"Wholesale",
            "subcategory":"Books, Periodicals, & Newspapers",
            "type":"Manufacturing & Wholesale Goods"
        }
    ],
    "sg:phone":"+1 602 683 4300",
    "sg:postcode":"85008",
    "sg:province":"AZ",
    "sg:tags":[
        "publishers-periodical"
    ],
    "wof:name":"Teleritmo Magazine",
    "wof:placetype":"venue"
},
  "geometry": {"coordinates":[-111.992973,33.465691],"type":"Point"}
}