{
  "type": "Feature",
  "properties": {
    "iso:country":"US",
    "sg:address":"2711 US Hwy 70",
    "sg:city":"Thatcher",
    "sg:classifiers":[
        {
            "category":"Home & Garden",
            "subcategory":"Building Materials",
            "type":"Retail Goods"
        }
    ],
    "sg:phone":"+1 928 428 2535",
    "sg:postcode":"85552",
    "sg:province":"AZ",
    "sg:tags":[
        "glass",
        "window",
        "plate"
    ],
    "sg:website":"www.eaglass.net",
    "wof:name":"E A Glass",
    "wof:placetype":"venue"
},
  "geometry": {"coordinates":[-109.744729,32.84552],"type":"Point"}
}