{
  "type": "Feature",
  "properties": {
    "addr:full":"751 N Arizona Avenue Chandler AZ 85225",
    "addr:housenumber":"751",
    "addr:postcode":"85225",
    "addr:street":"N Arizona Avenue",
    "iso:country":"US",
    "sg:address":"751 N Arizona Avenue",
    "sg:city":"Chandler",
    "sg:classifiers":[
        {
            "category":"Retail",
            "subcategory":"Auto Repair",
            "type":"Services"
        }
    ],
    "sg:phone":"+1 480 206 5721",
    "sg:postcode":"85225",
    "sg:province":"AZ",
    "wof:name":"Cactus Radiators",
    "wof:placetype":"venue"
},
  "geometry": {"coordinates":[-111.841679,33.316074],"type":"Point"}
}