{
  "type": "Feature",
  "properties": {
    "addr:full":"5005 E Madison St Phoenix AZ 85034",
    "addr:housenumber":"5005",
    "addr:postcode":"85034",
    "addr:street":"E Madison St",
    "iso:country":"US",
    "sg:address":"5005 E Madison St",
    "sg:city":"Phoenix",
    "sg:classifiers":[
        {
            "category":"Mining & Drilling",
            "type":"Manufacturing & Wholesale Goods"
        },
        {
            "category":"Wholesale",
            "subcategory":"Construction Materials",
            "type":"Manufacturing & Wholesale Goods"
        }
    ],
    "sg:phone":"+1 602 914 2202",
    "sg:postcode":"85034",
    "sg:province":"AZ",
    "sg:tags":[
        "granite",
        "stone"
    ],
    "wof:name":"Cactus Stone, Lc",
    "wof:placetype":"venue"
},
  "geometry": {"coordinates":[-111.974099,33.444838],"type":"Point"}
}