{
  "type": "Feature",
  "properties": {
    "addr:full":"10447 W Caron Dr Sun City AZ 85351",
    "addr:housenumber":"10447",
    "addr:postcode":"85351",
    "addr:street":"W Caron Dr",
    "iso:country":"US",
    "sg:address":"10447 W Caron Dr",
    "sg:city":"Sun City",
    "sg:classifiers":[
        {
            "category":"Utilities",
            "subcategory":"Telephone",
            "type":"Services"
        }
    ],
    "sg:phone":"+1 623 933 7703",
    "sg:postcode":"85351",
    "sg:province":"AZ",
    "sg:tags":[
        "communications"
    ],
    "wof:name":"Cobra Installation Services",
    "wof:placetype":"venue"
},
  "geometry": {"coordinates":[-112.283618,33.566244],"type":"Point"}
}