{
  "type": "Feature",
  "properties": {
    "iso:country":"US",
    "sg:address":"4840 E Indian School Rd",
    "sg:city":"Phoenix",
    "sg:classifiers":[
        {
            "category":"Health Services",
            "subcategory":"Doctor",
            "type":"Services"
        }
    ],
    "sg:phone":"+1 602 224 1900",
    "sg:postcode":"85018",
    "sg:province":"AZ",
    "sg:tags":[
        "physician",
        "family",
        "practice",
        "surgeons",
        "medicine",
        "surgeon"
    ],
    "wof:name":"Biltmore Family Physicians",
    "wof:placetype":"venue"
},
  "geometry": {"coordinates":[-111.97730300000001,33.494598],"type":"Point"}
}