{
  "type": "Feature",
  "properties": {
    "addr:full":"1729 S Brooks Cir Mesa AZ 85202",
    "addr:housenumber":"1729",
    "addr:postcode":"85202",
    "addr:street":"S Brooks Cir",
    "iso:country":"US",
    "sg:address":"1729 S Brooks Cir",
    "sg:city":"Mesa",
    "sg:classifiers":[
        {
            "category":"Shopping",
            "subcategory":"Computers & Home Electronics",
            "type":"Retail Goods"
        }
    ],
    "sg:phone":"+1 602 820 4445",
    "sg:postcode":"85202",
    "sg:province":"AZ",
    "wof:name":"Have Computer Will Travel",
    "wof:placetype":"venue"
},
  "geometry": {"coordinates":[-111.86601899999999,33.383109],"type":"Point"}
}