{
  "type": "Feature",
  "properties": {
    "iso:country":"US",
    "sg:address":"1630 E Southern Ave",
    "sg:city":"Phoenix",
    "sg:classifiers":[
        {
            "category":"Autos & Motor Vehicles",
            "subcategory":"Auto Supplies",
            "type":"Retail Goods"
        }
    ],
    "sg:phone":"+1 602 243 6506",
    "sg:postcode":"85040",
    "sg:province":"AZ",
    "sg:tags":[
        "wheel",
        "cover"
    ],
    "wof:name":"Big Willy's Custom Rims & Trs",
    "wof:placetype":"venue"
},
  "geometry": {"coordinates":[-112.04576400000001,33.39287],"type":"Point"}
}