{
  "type": "Feature",
  "properties": {
    "iso:country":"US",
    "sg:address":"2141 E University Dr",
    "sg:city":"Tempe",
    "sg:classifiers":[
        {
            "category":"Real Estate",
            "subcategory":"Real Estate Operator",
            "type":"Services"
        }
    ],
    "sg:phone":"+1 480 968 5660",
    "sg:postcode":"85281",
    "sg:province":"AZ",
    "sg:tags":[
        "building",
        "apartment"
    ],
    "wof:name":"Tempe Apartments",
    "wof:placetype":"venue"
},
  "geometry": {"coordinates":[-111.89225999999999,33.421941],"type":"Point"}
}