{
  "type": "Feature",
  "properties": {
    "iso:country":"US",
    "sg:address":"744 E 44th St",
    "sg:city":"Tucson",
    "sg:classifiers":[
        {
            "category":"Building & Trades",
            "subcategory":"Plumbing",
            "type":"Services"
        }
    ],
    "sg:phone":"+1 520 670 9696",
    "sg:postcode":"85713",
    "sg:province":"AZ",
    "sg:tags":[
        "contractor"
    ],
    "wof:name":"Tafsco",
    "wof:placetype":"venue"
},
  "geometry": {"coordinates":[-110.95891,32.183782],"type":"Point"}
}