{
  "type": "Feature",
  "properties": {
    "iso:country":"US",
    "sg:address":"7613 W Beryl Ave",
    "sg:city":"Peoria",
    "sg:classifiers":[
        {
            "category":"Home & Garden",
            "subcategory":"Home Furnishings",
            "type":"Retail Goods"
        }
    ],
    "sg:phone":"+1 623 979 3775",
    "sg:postcode":"85345",
    "sg:province":"AZ",
    "wof:name":"KS Gift & Houseware",
    "wof:placetype":"venue"
},
  "geometry": {"coordinates":[-112.222616,33.578251],"type":"Point"}
}