{
  "type": "Feature",
  "properties": {
    "iso:country":"US",
    "sg:address":"3449 E Broadway Rd",
    "sg:city":"Phoenix",
    "sg:classifiers":[
        {
            "category":"Home & Garden",
            "subcategory":"Building Materials",
            "type":"Retail Goods"
        },
        {
            "category":"Professional",
            "subcategory":"Business Services",
            "type":"Services"
        },
        {
            "category":"Building & Trades",
            "subcategory":"Construction",
            "type":"Services"
        },
        {
            "category":"Home & Garden",
            "subcategory":"Carpets & Floor Coverings",
            "type":"Retail Goods"
        }
    ],
    "sg:phone":"+1 602 323 0118",
    "sg:postcode":"85040",
    "sg:province":"AZ",
    "sg:tags":[
        "flooring",
        "marble-natural",
        "contractor",
        "marble-natural-wholesale",
        "tile-contractors",
        "granite",
        "manufacturer"
    ],
    "wof:name":"Anatolia Natural Stone Ltd",
    "wof:placetype":"venue"
},
  "geometry": {"coordinates":[-112.007225,33.407115],"type":"Point"}
}