{
  "type": "Feature",
  "properties": {
    "iso:country":"US",
    "sg:address":"9625 N 21st Dr",
    "sg:city":"Phoenix",
    "sg:classifiers":[
        {
            "category":"Autos & Motor Vehicles",
            "subcategory":"Motorcycle Sales",
            "type":"Retail Goods"
        }
    ],
    "sg:phone":"+1 602 331 2595",
    "sg:postcode":"85021",
    "sg:province":"AZ",
    "sg:tags":[
        "scooter"
    ],
    "wof:name":"Highway Thunder Customs",
    "wof:placetype":"venue"
},
  "geometry": {"coordinates":[-112.104445,33.573635],"type":"Point"}
}