{
  "type": "Feature",
  "properties": {
    "addr:full":"1012 N Main St Cottonwood AZ 86326",
    "addr:housenumber":"1012",
    "addr:postcode":"86326",
    "addr:street":"N Main St",
    "iso:country":"US",
    "sg:address":"1012 N Main St",
    "sg:city":"Cottonwood",
    "sg:classifiers":[
        {
            "category":"Shopping",
            "subcategory":"Gifts & Souvenirs",
            "type":"Retail Goods"
        }
    ],
    "sg:phone":"+1 928 639 0676",
    "sg:postcode":"86326",
    "sg:province":"AZ",
    "sg:tags":[
        "shop"
    ],
    "wof:name":"Little Lisa",
    "wof:placetype":"venue"
},
  "geometry": {"coordinates":[-112.029667,34.74997],"type":"Point"}
}