{
  "type": "Feature",
  "properties": {
    "iso:country":"US",
    "sg:address":"2328 US Hwy 89 Alt Scn",
    "sg:city":"Fredonia",
    "sg:classifiers":[
        {
            "category":"Building & Trades",
            "subcategory":"Construction",
            "type":"Services"
        }
    ],
    "sg:phone":"+1 928 643 6800",
    "sg:postcode":"86022",
    "sg:province":"AZ",
    "sg:tags":[
        "planning",
        "remodeling",
        "kitchen"
    ],
    "wof:name":"Kitchens Kreations",
    "wof:placetype":"venue"
},
  "geometry": {"coordinates":[-112.52999,36.999498],"type":"Point"}
}