{
  "type": "Feature",
  "properties": {
    "addr:full":"12112 N Rancho Vistoso Blvd Oro Valley AZ 85755",
    "addr:housenumber":"12112",
    "addr:postcode":"85755",
    "addr:street":"N Rancho Vistoso Blvd",
    "iso:country":"US",
    "sg:address":"12112 N Rancho Vistoso Blvd",
    "sg:city":"Oro Valley",
    "sg:classifiers":[
        {
            "category":"Building & Trades",
            "subcategory":"Locksmith",
            "type":"Services"
        }
    ],
    "sg:phone":"+1 866 226 0573",
    "sg:postcode":"85755",
    "sg:province":"AZ",
    "sg:tags":[
        "key"
    ],
    "wof:name":"24 Hour 7 Day Emergency Locksmith",
    "wof:placetype":"venue"
},
  "geometry": {"coordinates":[-110.961023,32.425467],"type":"Point"}
}