{
  "type": "Feature",
  "properties": {
    "iso:country":"US",
    "sg:address":"7401 Easy St",
    "sg:city":"Carefree",
    "sg:classifiers":[
        {
            "category":"Personal",
            "subcategory":"Beauty Salon",
            "type":"Services"
        }
    ],
    "sg:phone":"+1 480 595 7658",
    "sg:postcode":"85377",
    "sg:province":"AZ",
    "wof:name":"Salon Voila",
    "wof:placetype":"venue"
},
  "geometry": {"coordinates":[-111.92173699999999,33.823258],"type":"Point"}
}