{
  "type": "Feature",
  "properties": {
    "iso:country":"US",
    "sg:address":"11541 W Bell Rd",
    "sg:city":"Surprise",
    "sg:classifiers":[
        {
            "category":"Local Transit",
            "type":"Transportation"
        }
    ],
    "sg:phone":"+1 480 419 8976",
    "sg:postcode":"85374",
    "sg:province":"AZ",
    "sg:tags":[
        "airport"
    ],
    "wof:name":"A-1 Airport Shuttle-Sedan",
    "wof:placetype":"venue"
},
  "geometry": {"coordinates":[-112.309082,33.638677],"type":"Point"}
}