{
  "type": "Feature",
  "properties": {
    "iso:country":"US",
    "sg:address":"12418 N 28th Dr",
    "sg:city":"Phoenix",
    "sg:classifiers":[
        {
            "category":"Restaurant",
            "type":"Food & Drink"
        }
    ],
    "sg:phone":"+1 602 375 1221",
    "sg:postcode":"85029",
    "sg:province":"AZ",
    "sg:tags":[
        "italian"
    ],
    "sg:website":"http://www.anzios.com",
    "wof:name":"Anzio's Italian Restaurant",
    "wof:placetype":"venue"
},
  "geometry": {"coordinates":[-112.11982399999999,33.598109],"type":"Point"}
}