{
  "type": "Feature",
  "properties": {
    "iso:country":"US",
    "sg:address":"416 N Warren Ave",
    "sg:city":"Tucson",
    "sg:classifiers":[
        {
            "category":"Education",
            "subcategory":"College",
            "type":"Public Place"
        }
    ],
    "sg:phone":"+1 520 620 9374",
    "sg:postcode":"85719",
    "sg:province":"AZ",
    "sg:tags":[
        "academic",
        "school"
    ],
    "wof:name":"University Of Arizona Intl",
    "wof:placetype":"venue"
},
  "geometry": {"coordinates":[-110.946522,32.227531],"type":"Point"}
}