{
  "type": "Feature",
  "properties": {
    "iso:country":"US",
    "sg:address":"1930 E Grant Rd",
    "sg:city":"Tucson",
    "sg:classifiers":[
        {
            "category":"Shopping",
            "subcategory":"Used Merchandise",
            "type":"Retail Goods"
        }
    ],
    "sg:phone":"+1 520 325 5767",
    "sg:postcode":"85719",
    "sg:province":"AZ",
    "wof:name":"Bookmans Used Books",
    "wof:placetype":"venue"
},
  "geometry": {"coordinates":[-110.943006,32.250245],"type":"Point"}
}