{
  "type": "Feature",
  "properties": {
    "iso:country":"US",
    "sg:address":"2344 E Baseline Rd",
    "sg:city":"Mesa",
    "sg:classifiers":[
        {
            "category":"Home & Garden",
            "subcategory":"Carpets & Floor Coverings",
            "type":"Retail Goods"
        }
    ],
    "sg:phone":"+1 480 545 9090",
    "sg:postcode":"85204",
    "sg:province":"AZ",
    "sg:tags":[
        "dealer",
        "rug"
    ],
    "wof:name":"Aaron America Inc",
    "wof:placetype":"venue"
},
  "geometry": {"coordinates":[-111.780494,33.379117],"type":"Point"}
}