{
  "type": "Feature",
  "properties": {
    "iso:country":"US",
    "sg:address":"3345 W Greenway Rd",
    "sg:city":"Phoenix",
    "sg:classifiers":[
        {
            "category":"Restaurant",
            "type":"Food & Drink"
        }
    ],
    "sg:phone":"+1 602 358 8444",
    "sg:postcode":"85053",
    "sg:province":"AZ",
    "sg:tags":[
        "pizza",
        "italian"
    ],
    "wof:name":"Amante Pizza & Pasta",
    "wof:placetype":"venue"
},
  "geometry": {"coordinates":[-112.13044499999999,33.625278],"type":"Point"}
}