{
  "type": "Feature",
  "properties": {
    "addr:full":"9775 N Clayton Rd Marana AZ 85653",
    "addr:housenumber":"9775",
    "addr:postcode":"85653",
    "addr:street":"N Clayton Rd",
    "iso:country":"US",
    "sg:address":"9775 N Clayton Rd",
    "sg:city":"Marana",
    "sg:classifiers":[
        {
            "category":"Health Services",
            "subcategory":"Chiropractor",
            "type":"Services"
        }
    ],
    "sg:phone":"+1 520 906 6902",
    "sg:postcode":"85653",
    "sg:province":"AZ",
    "sg:tags":[
        "chiropractic"
    ],
    "wof:name":"Silver Wolf Chiropractic",
    "wof:placetype":"venue"
},
  "geometry": {"coordinates":[-111.242526,32.386853],"type":"Point"}
}