{
  "type": "Feature",
  "properties": {
    "addr:full":"7680 E State Rte 69 Prescott Valley AZ 86314",
    "addr:housenumber":"7680",
    "addr:postcode":"86314",
    "addr:street":"E State Rte 69",
    "iso:country":"US",
    "sg:address":"7680 E State Rte 69",
    "sg:city":"Prescott Valley",
    "sg:classifiers":[
        {
            "category":"Restaurant",
            "type":"Food & Drink"
        }
    ],
    "sg:phone":"+1 928 772 2053",
    "sg:postcode":"86314",
    "sg:province":"AZ",
    "wof:name":"Michael's",
    "wof:placetype":"venue"
},
  "geometry": {"coordinates":[-112.33182499999999,34.585243],"type":"Point"}
}