{
  "type": "Feature",
  "properties": {
    "addr:full":"601 Miller Valley Rd Prescott AZ 86301",
    "addr:housenumber":"601",
    "addr:postcode":"86301",
    "addr:street":"Miller Valley Rd",
    "iso:country":"US",
    "sg:address":"601 Miller Valley Rd",
    "sg:city":"Prescott",
    "sg:classifiers":[
        {
            "category":"Professional",
            "type":"Services"
        }
    ],
    "sg:phone":"+1 928 776 2950",
    "sg:postcode":"86301",
    "sg:province":"AZ",
    "wof:name":"Jade Healing Thermatics",
    "wof:placetype":"venue"
},
  "geometry": {"coordinates":[-112.479737,34.551874],"type":"Point"}
}