{
  "type": "Feature",
  "properties": {
    "iso:country":"US",
    "sg:address":"4080 W Clarendon Ave",
    "sg:city":"Phoenix",
    "sg:classifiers":[
        {
            "category":"Manufacturing",
            "subcategory":"Metals",
            "type":"Manufacturing & Wholesale Goods"
        }
    ],
    "sg:phone":"+1 602 272 2550",
    "sg:postcode":"85019",
    "sg:province":"AZ",
    "sg:tags":[
        "fabrication"
    ],
    "wof:name":"Altrafab Products",
    "wof:placetype":"venue"
},
  "geometry": {"coordinates":[-112.150206,33.492271],"type":"Point"}
}