{
  "type": "Feature",
  "properties": {
    "iso:country":"US",
    "sg:address":"10720 E 22nd St",
    "sg:city":"Tucson",
    "sg:classifiers":[
        {
            "category":"Education",
            "subcategory":"School",
            "type":"Public Place"
        }
    ],
    "sg:phone":"+1 520 733 0096",
    "sg:postcode":"85748",
    "sg:province":"AZ",
    "wof:name":"Academy Of Tucson",
    "wof:placetype":"venue"
},
  "geometry": {"coordinates":[-110.767333,32.206226],"type":"Point"}
}