{
  "type": "Feature",
  "properties": {
    "iso:country":"US",
    "sg:address":"2081 N Arizona Ave",
    "sg:city":"Chandler",
    "sg:classifiers":[
        {
            "category":"Home & Garden",
            "subcategory":"Household Appliances",
            "type":"Retail Goods"
        }
    ],
    "sg:phone":"+1 480 786 0559",
    "sg:postcode":"85225",
    "sg:province":"AZ",
    "wof:name":"Ceiling Fan Store",
    "wof:placetype":"venue"
},
  "geometry": {"coordinates":[-111.841637,33.336273],"type":"Point"}
}