{
  "type": "Feature",
  "properties": {
    "iso:country":"US",
    "sg:address":"8510 W Hughes Dr",
    "sg:city":"Tolleson",
    "sg:classifiers":[
        {
            "category":"Wholesale",
            "subcategory":"Computers",
            "type":"Manufacturing & Wholesale Goods"
        }
    ],
    "sg:phone":"+1 623 936 1309",
    "sg:postcode":"85353",
    "sg:province":"AZ",
    "sg:tags":[
        "equipment"
    ],
    "wof:name":"Computer One Power Systems",
    "wof:placetype":"venue"
},
  "geometry": {"coordinates":[-112.24388500000001,33.425129],"type":"Point"}
}