{
  "type": "Feature",
  "properties": {
    "iso:country":"US",
    "sg:address":"7734 W Michigan Ave",
    "sg:city":"Glendale",
    "sg:classifiers":[
        {
            "category":"Home & Garden",
            "subcategory":"Hardware",
            "type":"Retail Goods"
        }
    ],
    "sg:phone":"+1 602 439 0993",
    "sg:postcode":"85308",
    "sg:province":"AZ",
    "wof:name":"Mdb Sales Inc",
    "wof:placetype":"venue"
},
  "geometry": {"coordinates":[-112.227344,33.649276],"type":"Point"}
}