{
  "type": "Feature",
  "properties": {
    "iso:country":"US",
    "sg:address":"8260 E Raintree Dr",
    "sg:city":"Scottsdale",
    "sg:classifiers":[
        {
            "category":"Shopping",
            "subcategory":"Computers & Home Electronics",
            "type":"Retail Goods"
        }
    ],
    "sg:phone":"+1 480 483 3399",
    "sg:postcode":"85260",
    "sg:province":"AZ",
    "sg:tags":[
        "audio"
    ],
    "sg:website":"www.immediaavs.com",
    "wof:name":"Immedia",
    "wof:placetype":"venue"
},
  "geometry": {"coordinates":[-111.9033,33.619065],"type":"Point"}
}