{
  "type": "Feature",
  "properties": {
    "iso:country":"US",
    "sg:address":"1100 W Valley View Rd",
    "sg:city":"Prescott",
    "sg:classifiers":[
        {
            "category":"Manufacturing",
            "subcategory":"Metals",
            "type":"Manufacturing & Wholesale Goods"
        }
    ],
    "sg:phone":"+1 928 778 4995",
    "sg:postcode":"86303",
    "sg:province":"AZ",
    "sg:tags":[
        "plating"
    ],
    "wof:name":"Royal Gold Plating",
    "wof:placetype":"venue"
},
  "geometry": {"coordinates":[-112.486462,34.516252],"type":"Point"}
}