{
  "type": "Feature",
  "properties": {
    "iso:country":"US",
    "sg:address":"2047 E Camelback Rd",
    "sg:city":"Phoenix",
    "sg:classifiers":[
        {
            "category":"Shopping",
            "subcategory":"Jewelry",
            "type":"Retail Goods"
        }
    ],
    "sg:phone":"+1 602 956 0606",
    "sg:postcode":"85016",
    "sg:province":"AZ",
    "sg:tags":[
        "diamond"
    ],
    "sg:website":"http://www.jewelsbygdo.com",
    "wof:name":"Jewels By G. Darrell Olson",
    "wof:placetype":"venue"
},
  "geometry": {"coordinates":[-112.037971,33.509258],"type":"Point"}
}