{
  "type": "Feature",
  "properties": {
    "iso:country":"US",
    "sg:address":"6214 E Cll Rosa",
    "sg:city":"Scottsdale",
    "sg:classifiers":[
        {
            "category":"Manufacturing",
            "subcategory":"Retail Goods",
            "type":"Manufacturing & Wholesale Goods"
        },
        {
            "category":"Real Estate",
            "subcategory":"Real Estate Agent",
            "type":"Services"
        }
    ],
    "sg:phone":"+1 480 998 4890",
    "sg:postcode":"85251",
    "sg:province":"AZ",
    "sg:tags":[
        "product",
        "mfg"
    ],
    "wof:name":"Setting The Stage",
    "wof:placetype":"venue"
},
  "geometry": {"coordinates":[-111.946659,33.493308],"type":"Point"}
}