{
  "type": "Feature",
  "properties": {
    "addr:full":"2549 E Blanton Dr Tucson AZ 85716",
    "addr:housenumber":"2549",
    "addr:postcode":"85716",
    "addr:street":"E Blanton Dr",
    "iso:country":"US",
    "sg:address":"2549 E Blanton Dr",
    "sg:city":"Tucson",
    "sg:classifiers":[
        {
            "category":"Manufacturing",
            "subcategory":"Toys & Sporting Goods",
            "type":"Manufacturing & Wholesale Goods"
        }
    ],
    "sg:phone":"+1 520 326 0734",
    "sg:postcode":"85716",
    "sg:province":"AZ",
    "sg:tags":[
        "mfg"
    ],
    "wof:name":"Mantis A Research and Dev Co",
    "wof:placetype":"venue"
},
  "geometry": {"coordinates":[-110.932855,32.264059],"type":"Point"}
}