{
  "type": "Feature",
  "properties": {
    "iso:country":"US",
    "sg:address":"2726 E Gelding Dr",
    "sg:city":"Phoenix",
    "sg:classifiers":[
        {
            "category":"Professional",
            "subcategory":"Management & Consulting",
            "type":"Services"
        }
    ],
    "sg:phone":"+1 602 482 1788",
    "sg:postcode":"85032",
    "sg:province":"AZ",
    "sg:tags":[
        "conference",
        "consultant",
        "meeting"
    ],
    "wof:name":"Corporate Destination Svc-Az",
    "wof:placetype":"venue"
},
  "geometry": {"coordinates":[-112.023475,33.617701],"type":"Point"}
}