{
  "type": "Feature",
  "properties": {
    "iso:country":"US",
    "sg:address":"2375 S Stinson Way",
    "sg:city":"Chandler",
    "sg:classifiers":[
        {
            "category":"Wholesale",
            "subcategory":"Machinery & Supplies",
            "type":"Manufacturing & Wholesale Goods"
        }
    ],
    "sg:phone":"+1 480 732 9118",
    "sg:postcode":"85286",
    "sg:province":"AZ",
    "sg:tags":[
        "aircraft",
        "parts",
        "maintenance"
    ],
    "sg:website":"www.chandleraviation.com",
    "wof:name":"Chandler Aviation Inc",
    "wof:placetype":"venue"
},
  "geometry": {"coordinates":[-111.81318899999999,33.273393],"type":"Point"}
}