{
  "type": "Feature",
  "properties": {
    "iso:country":"US",
    "sg:address":"1701 S 4th Ave",
    "sg:city":"Tucson",
    "sg:classifiers":[
        {
            "category":"Professional",
            "type":"Services"
        }
    ],
    "sg:phone":"+1 520 622 2746",
    "sg:postcode":"85713",
    "sg:province":"AZ",
    "wof:name":"Rising Sun Restorations",
    "wof:placetype":"venue"
},
  "geometry": {"coordinates":[-110.965352,32.20059],"type":"Point"}
}