{
  "type": "Feature",
  "properties": {
    "iso:country":"US",
    "sg:address":"3305 E Greenway Rd",
    "sg:city":"Phoenix",
    "sg:classifiers":[
        {
            "category":"Health Services",
            "subcategory":"Chiropractor",
            "type":"Services"
        }
    ],
    "sg:phone":"+1 602 787 9511",
    "sg:postcode":"85032",
    "sg:province":"AZ",
    "wof:name":"First Chiropractic",
    "wof:placetype":"venue"
},
  "geometry": {"coordinates":[-112.011278,33.626251],"type":"Point"}
}