{
  "type": "Feature",
  "properties": {
    "iso:country":"US",
    "sg:address":"5101 E Earll Dr",
    "sg:city":"Phoenix",
    "sg:classifiers":[
        {
            "category":"Building & Trades",
            "subcategory":"Construction",
            "type":"Services"
        }
    ],
    "sg:phone":"+1 602 291 0062",
    "sg:postcode":"85018",
    "sg:province":"AZ",
    "sg:tags":[
        "contractor"
    ],
    "wof:name":"Bowles Reinforcing Inc",
    "wof:placetype":"venue"
},
  "geometry": {"coordinates":[-111.969515,33.483672],"type":"Point"}
}