{
  "type": "Feature",
  "properties": {
    "iso:country":"US",
    "sg:address":"251 S Chelsea Park Pl",
    "sg:city":"Tucson",
    "sg:classifiers":[
        {
            "category":"Shopping",
            "type":"Retail Goods"
        }
    ],
    "sg:phone":"+1 520 733 1146",
    "sg:postcode":"85748",
    "sg:province":"AZ",
    "sg:tags":[
        "cosmetic",
        "perfume"
    ],
    "wof:name":"Mary Kay Cosmetics",
    "wof:placetype":"venue"
},
  "geometry": {"coordinates":[-110.767938,32.218225],"type":"Point"}
}