{
  "type": "Feature",
  "properties": {
    "addr:full":"13229 S 48th Pl Phoenix AZ 85044",
    "addr:housenumber":"13229",
    "addr:postcode":"85044",
    "addr:street":"S 48Th Pl",
    "iso:country":"US",
    "sg:address":"13229 S 48th Pl",
    "sg:city":"Phoenix",
    "sg:classifiers":[
        {
            "category":"Insurance",
            "subcategory":"Insurance Agent",
            "type":"Services"
        }
    ],
    "sg:phone":"+1 480 248 9813",
    "sg:postcode":"85044",
    "sg:province":"AZ",
    "wof:name":"Harding Insurance Svc",
    "wof:placetype":"venue"
},
  "geometry": {"coordinates":[-111.980754,33.325671],"type":"Point"}
}