{
  "type": "Feature",
  "properties": {
    "iso:country":"US",
    "sg:address":"3149 N 31st Ave",
    "sg:city":"Phoenix",
    "sg:classifiers":[
        {
            "category":"Real Estate",
            "subcategory":"Architect",
            "type":"Services"
        }
    ],
    "sg:phone":"+1 602 272 1166",
    "sg:postcode":"85017",
    "sg:province":"AZ",
    "wof:name":"Architectural Resource Team",
    "wof:placetype":"venue"
},
  "geometry": {"coordinates":[-112.125602,33.483553],"type":"Point"}
}