{
  "type": "Feature",
  "properties": {
    "iso:country":"US",
    "sg:address":"2409 S Rural Rd",
    "sg:city":"Tempe",
    "sg:classifiers":[
        {
            "category":"Health Services",
            "subcategory":"Health Practitioner",
            "type":"Services"
        }
    ],
    "sg:phone":"+1 480 967 9496",
    "sg:postcode":"85282",
    "sg:province":"AZ",
    "sg:tags":[
        "hypnotist"
    ],
    "wof:name":"AZHYPTNOSISM.COM",
    "wof:placetype":"venue"
},
  "geometry": {"coordinates":[-111.926222,33.402121],"type":"Point"}
}