{
  "type": "Feature",
  "properties": {
    "addr:full":"1409 E Bernard Dr Tucson AZ 85714",
    "addr:housenumber":"1409",
    "addr:postcode":"85714",
    "addr:street":"E Bernard Dr",
    "iso:country":"US",
    "sg:address":"1409 E Bernard Dr",
    "sg:city":"Tucson",
    "sg:classifiers":[
        {
            "category":"Professional",
            "type":"Services"
        },
        {
            "category":"Shopping",
            "subcategory":"Bicycles & Sporting Goods",
            "type":"Retail Goods"
        },
        {
            "category":"Personal",
            "subcategory":"Sauna",
            "type":"Services"
        },
        {
            "category":"Sports & Exercise",
            "subcategory":"Swimming Pool",
            "type":"Entertainment"
        }
    ],
    "sg:phone":"+1 520 573 9260",
    "sg:postcode":"85714",
    "sg:province":"AZ",
    "sg:tags":[
        "repair",
        "supply",
        "tubs-repair",
        "equipment",
        "hot",
        "spa"
    ],
    "sg:website":"http://www.aquaclearpoolservice.biz",
    "wof:name":"Kdl Enterprise",
    "wof:placetype":"venue"
},
  "geometry": {"coordinates":[-110.9496,32.177421],"type":"Point"}
}