{
  "type": "Feature",
  "properties": {
    "iso:country":"US",
    "sg:address":"3324 E Coconino St",
    "sg:city":"Phoenix",
    "sg:classifiers":[
        {
            "category":"Arts & Performance",
            "subcategory":"Theater",
            "type":"Entertainment"
        }
    ],
    "sg:phone":"+1 480 966 2929",
    "sg:postcode":"85044",
    "sg:province":"AZ",
    "sg:tags":[
        "live",
        "music"
    ],
    "wof:name":"Citron Sound Svc D J's",
    "wof:placetype":"venue"
},
  "geometry": {"coordinates":[-112.0121,33.330599],"type":"Point"}
}