{
  "type": "Feature",
  "properties": {
    "iso:country":"US",
    "sg:address":"456 N Vineyard",
    "sg:city":"Mesa",
    "sg:classifiers":[
        {
            "category":"Professional",
            "type":"Services"
        },
        {
            "category":"Shopping",
            "subcategory":"Gifts & Souvenirs",
            "type":"Retail Goods"
        }
    ],
    "sg:phone":"+1 480 834 1608",
    "sg:postcode":"85201",
    "sg:province":"AZ",
    "sg:tags":[
        "establishment"
    ],
    "wof:name":"Goodies To Go",
    "wof:placetype":"venue"
},
  "geometry": {"coordinates":[-111.841897,33.423889],"type":"Point"}
}