{
  "type": "Feature",
  "properties": {
    "addr:full":"18818 Grandview Dr Sun City West AZ 85375",
    "addr:housenumber":"18818",
    "addr:postcode":"85375",
    "addr:street":"Grandview Dr",
    "iso:country":"US",
    "sg:address":"18818 Grandview Dr",
    "sg:city":"Sun City West",
    "sg:classifiers":[
        {
            "category":"Retail",
            "subcategory":"Repair Shop",
            "type":"Services"
        }
    ],
    "sg:phone":"+1 623 584 4116",
    "sg:postcode":"85375",
    "sg:province":"AZ",
    "sg:tags":[
        "repairing",
        "piano",
        "refinishing"
    ],
    "wof:name":"A-440 Piano Tuning",
    "wof:placetype":"venue"
},
  "geometry": {"coordinates":[-112.366349,33.656311],"type":"Point"}
}