{
  "type": "Feature",
  "properties": {
    "addr:full":"3150 N 35th Ave Phoenix AZ 85017",
    "addr:housenumber":"3150",
    "addr:postcode":"85017",
    "addr:street":"N 35Th Ave",
    "iso:country":"US",
    "sg:address":"3150 N 35th Ave",
    "sg:city":"Phoenix",
    "sg:classifiers":[
        {
            "category":"Organizations",
            "subcategory":"Religious Organization",
            "type":"Services"
        }
    ],
    "sg:phone":"+1 602 252 1144",
    "sg:postcode":"85017",
    "sg:province":"AZ",
    "sg:tags":[
        "church"
    ],
    "wof:name":"Berean Baptist Church",
    "wof:placetype":"venue"
},
  "geometry": {"coordinates":[-112.13442000000001,33.482899],"type":"Point"}
}