{
  "type": "Feature",
  "properties": {
    "iso:country":"US",
    "sg:address":"829 E North Ln",
    "sg:city":"Phoenix",
    "sg:classifiers":[
        {
            "category":"Home & Garden",
            "subcategory":"Garden Supply",
            "type":"Retail Goods"
        }
    ],
    "sg:phone":"+1 602 561 4405",
    "sg:postcode":"85020",
    "sg:province":"AZ",
    "sg:tags":[
        "sprinkler"
    ],
    "wof:name":"AASI",
    "wof:placetype":"venue"
},
  "geometry": {"coordinates":[-112.062871,33.58081],"type":"Point"}
}