{
  "type": "Feature",
  "properties": {
    "iso:country":"US",
    "sg:address":"9243 Cll Sahuaro",
    "sg:city":"Guadalupe",
    "sg:classifiers":[
        {
            "category":"Wholesale",
            "subcategory":"Construction Materials",
            "type":"Manufacturing & Wholesale Goods"
        }
    ],
    "sg:phone":"+1 480 839 2748",
    "sg:postcode":"85283",
    "sg:province":"AZ",
    "sg:tags":[
        "fence"
    ],
    "wof:name":"Guzman Fence Co",
    "wof:placetype":"venue"
},
  "geometry": {"coordinates":[-111.965253,33.362261],"type":"Point"}
}