{
  "type": "Feature",
  "properties": {
    "addr:full":"40 N White Mountain Rd Show Low AZ 85901",
    "addr:housenumber":"40",
    "addr:postcode":"85901",
    "addr:street":"N White Mountain Rd",
    "iso:country":"US",
    "sg:address":"40 N White Mountain Rd",
    "sg:city":"Show Low",
    "sg:classifiers":[
        {
            "category":"Professional",
            "subcategory":"Accounting & Tax Preparation",
            "type":"Services"
        }
    ],
    "sg:phone":"+1 928 537 7780",
    "sg:postcode":"85901",
    "sg:province":"AZ",
    "sg:tags":[
        "accountant"
    ],
    "wof:name":"Jeff Walker CPA",
    "wof:placetype":"venue"
},
  "geometry": {"coordinates":[-110.02862,34.250271],"type":"Point"}
}