{
  "type": "Feature",
  "properties": {
    "addr:full":"1073 E Baseline Rd Gilbert AZ 85233",
    "addr:housenumber":"1073",
    "addr:postcode":"85233",
    "addr:street":"E Baseline Rd",
    "iso:country":"US",
    "sg:address":"1073 E Baseline Rd",
    "sg:city":"Gilbert",
    "sg:classifiers":[
        {
            "category":"Shopping",
            "subcategory":"Clothing, Apparel, & Fashions",
            "type":"Retail Goods"
        }
    ],
    "sg:phone":"+1 480 558 1259",
    "sg:postcode":"85233",
    "sg:province":"AZ",
    "sg:tags":[
        "clothing",
        "women's"
    ],
    "wof:name":"Styles for Less",
    "wof:placetype":"venue"
},
  "geometry": {"coordinates":[-111.80998099999999,33.378839],"type":"Point"}
}