{
  "type": "Feature",
  "properties": {
    "addr:full":"3820 N 56th St Phoenix AZ 85018",
    "addr:housenumber":"3820",
    "addr:postcode":"85018",
    "addr:street":"N 56Th St",
    "iso:country":"US",
    "sg:address":"3820 N 56th St",
    "sg:city":"Phoenix",
    "sg:classifiers":[
        {
            "category":"Banks & Credit Unions",
            "subcategory":"Financial Services",
            "type":"Services"
        }
    ],
    "sg:phone":"+1 602 955 4949",
    "sg:postcode":"85018",
    "sg:province":"AZ",
    "sg:tags":[
        "company",
        "holding"
    ],
    "wof:name":"J E Jackson Holdings LLC",
    "wof:placetype":"venue"
},
  "geometry": {"coordinates":[-111.960837,33.494519],"type":"Point"}
}