{
  "type": "Feature",
  "properties": {
    "iso:country":"US",
    "sg:address":"24 S Dunnam St",
    "sg:city":"Flagstaff",
    "sg:classifiers":[
        {
            "category":"Retail",
            "subcategory":"Storage",
            "type":"Services"
        }
    ],
    "sg:phone":"+1 928 779 1771",
    "sg:postcode":"86001",
    "sg:province":"AZ",
    "sg:tags":[
        "self",
        "commercial",
        "household"
    ],
    "wof:name":"Hutton Plaza Mini Storage",
    "wof:placetype":"venue"
},
  "geometry": {"coordinates":[-111.67831,35.188023],"type":"Point"}
}