{
  "type": "Feature",
  "properties": {
    "iso:country":"US",
    "sg:address":"1320 Grand Ave",
    "sg:city":"Phoenix",
    "sg:classifiers":[
        {
            "category":"Shopping",
            "type":"Retail Goods"
        }
    ],
    "sg:phone":"+1 602 254 5078",
    "sg:postcode":"85007",
    "sg:province":"AZ",
    "sg:tags":[
        "awning",
        "canopy"
    ],
    "wof:name":"Azteca Awnings",
    "wof:placetype":"venue"
},
  "geometry": {"coordinates":[-112.091028,33.458549],"type":"Point"}
}