{
  "type": "Feature",
  "properties": {
    "iso:country":"US",
    "sg:address":"4828 S 16th St",
    "sg:city":"Phoenix",
    "sg:classifiers":[
        {
            "category":"Retail",
            "subcategory":"Auto Repair",
            "type":"Services"
        }
    ],
    "sg:phone":"+1 602 323 0320",
    "sg:postcode":"85040",
    "sg:province":"AZ",
    "sg:tags":[
        "body",
        "automobile",
        "painting"
    ],
    "wof:name":"Advantage Imports LTD",
    "wof:placetype":"venue"
},
  "geometry": {"coordinates":[-112.04732,33.399739],"type":"Point"}
}