{
  "type": "Feature",
  "properties": {
    "addr:full":"6413 E Sweetwater Ave Scottsdale AZ 85254",
    "addr:housenumber":"6413",
    "addr:postcode":"85254",
    "addr:street":"E Sweetwater Ave",
    "iso:country":"US",
    "sg:address":"6413 E Sweetwater Ave",
    "sg:city":"Scottsdale",
    "sg:classifiers":[
        {
            "category":"Retail",
            "subcategory":"Portrait Studio",
            "type":"Services"
        }
    ],
    "sg:phone":"+1 480 998 4997",
    "sg:postcode":"85254",
    "sg:province":"AZ",
    "sg:tags":[
        "photographer"
    ],
    "sg:website":"www.edgoodmanphotography.com",
    "wof:name":"Ed Goodman Photography",
    "wof:placetype":"venue"
},
  "geometry": {"coordinates":[-111.94136,33.603987],"type":"Point"}
}