{
  "type": "Feature",
  "properties": {
    "iso:country":"US",
    "sg:address":"2101 E Apache Blvd",
    "sg:city":"Tempe",
    "sg:classifiers":[
        {
            "category":"Travel",
            "subcategory":"Hotels & Motels",
            "type":"Entertainment"
        }
    ],
    "sg:phone":"+1 480 966 5832",
    "sg:postcode":"85281",
    "sg:province":"AZ",
    "wof:name":"Econo Lodge",
    "wof:placetype":"venue"
},
  "geometry": {"coordinates":[-111.89193,33.414798],"type":"Point"}
}