{
  "type": "Feature",
  "properties": {
    "iso:country":"US",
    "sg:address":"2115 Eagle Dr",
    "sg:city":"Lake Havasu City",
    "sg:classifiers":[
        {
            "category":"Building & Trades",
            "subcategory":"Construction",
            "type":"Services"
        }
    ],
    "sg:phone":"+1 928 855 6598",
    "sg:postcode":"86406",
    "sg:province":"AZ",
    "sg:tags":[
        "general",
        "contractor"
    ],
    "wof:name":"Ben Thomas Development Inc",
    "wof:placetype":"venue"
},
  "geometry": {"coordinates":[-114.319796,34.459992],"type":"Point"}
}