{
  "type": "Feature",
  "properties": {
    "addr:full":"2601 W Belmont Ave Phoenix AZ 85051",
    "addr:housenumber":"2601",
    "addr:postcode":"85051",
    "addr:street":"W Belmont Ave",
    "iso:country":"US",
    "sg:address":"2601 W Belmont Ave",
    "sg:city":"Phoenix",
    "sg:classifiers":[
        {
            "category":"Organizations",
            "subcategory":"Religious Organization",
            "type":"Services"
        }
    ],
    "sg:phone":"+1 602 841 1697",
    "sg:postcode":"85051",
    "sg:province":"AZ",
    "wof:name":"Along Side Ministries",
    "wof:placetype":"venue"
},
  "geometry": {"coordinates":[-112.116958,33.549239],"type":"Point"}
}