{
  "type": "Feature",
  "properties": {
    "addr:full":"3801 E Anne St Phoenix AZ 85040",
    "addr:housenumber":"3801",
    "addr:postcode":"85040",
    "addr:street":"E Anne St",
    "iso:country":"US",
    "sg:address":"3801 E Anne St",
    "sg:city":"Phoenix",
    "sg:classifiers":[
        {
            "category":"Manufacturing",
            "subcategory":"Tools & Machinery",
            "type":"Manufacturing & Wholesale Goods"
        },
        {
            "category":"Wholesale",
            "subcategory":"Machinery & Supplies",
            "type":"Manufacturing & Wholesale Goods"
        }
    ],
    "sg:phone":"+1 888 793 2351",
    "sg:postcode":"85040",
    "sg:province":"AZ",
    "sg:tags":[
        "machine",
        "equipment",
        "industrial"
    ],
    "sg:website":"http://www.plastifab.net",
    "wof:name":"Plastifab Inc",
    "wof:placetype":"venue"
},
  "geometry": {"coordinates":[-111.999702,33.412998],"type":"Point"}
}