{
  "type": "Feature",
  "properties": {
    "addr:full":"3735 N Romero Rd Tucson AZ 85705",
    "addr:housenumber":"3735",
    "addr:postcode":"85705",
    "addr:street":"N Romero Rd",
    "iso:country":"US",
    "sg:address":"3735 N Romero Rd",
    "sg:city":"Tucson",
    "sg:classifiers":[
        {
            "category":"Manufacturing",
            "subcategory":"Metals",
            "type":"Manufacturing & Wholesale Goods"
        }
    ],
    "sg:phone":"+1 520 887 1727",
    "sg:postcode":"85705",
    "sg:province":"AZ",
    "sg:tags":[
        "fabricator",
        "sheet"
    ],
    "sg:website":"www.abrams.com",
    "wof:name":"Abrams Airborne Mfg Inc",
    "wof:placetype":"venue"
},
  "geometry": {"coordinates":[-111.00347499999999,32.274559],"type":"Point"}
}