{
  "type": "Feature",
  "properties": {
    "iso:country":"US",
    "sg:address":"142 W Cedar Dr",
    "sg:city":"Chandler",
    "sg:classifiers":[
        {
            "category":"Insurance",
            "subcategory":"Insurance Agent",
            "type":"Services"
        }
    ],
    "sg:phone":"+1 480 699 9660",
    "sg:postcode":"85248",
    "sg:province":"AZ",
    "wof:name":"Alecia White State Farm Agent",
    "wof:placetype":"venue"
},
  "geometry": {"coordinates":[-111.844228,33.228581],"type":"Point"}
}