{
  "type": "Feature",
  "properties": {
    "iso:country":"US",
    "sg:address":"915 N 7th St",
    "sg:city":"Phoenix",
    "sg:classifiers":[
        {
            "category":"Retail",
            "subcategory":"Auto Repair",
            "type":"Services"
        }
    ],
    "sg:phone":"+1 602 254 2644",
    "sg:postcode":"85006",
    "sg:province":"AZ",
    "sg:tags":[
        "repairing",
        "automobile"
    ],
    "wof:name":"Roosevelt Power Repair",
    "wof:placetype":"venue"
},
  "geometry": {"coordinates":[-112.065143,33.458518],"type":"Point"}
}