{
  "type": "Feature",
  "properties": {
    "iso:country":"US",
    "sg:address":"637 S 48th St",
    "sg:city":"Tempe",
    "sg:classifiers":[
        {
            "category":"Professional",
            "subcategory":"Advertising",
            "type":"Services"
        }
    ],
    "sg:phone":"+1 480 966 7033",
    "sg:postcode":"85281",
    "sg:province":"AZ",
    "sg:tags":[
        "counselor"
    ],
    "wof:name":"Financial Peaks Inc",
    "wof:placetype":"venue"
},
  "geometry": {"coordinates":[-111.977242,33.423907],"type":"Point"}
}