{
  "type": "Feature",
  "properties": {
    "addr:full":"2081 N Tanque Verde Loop Rd Tucson AZ 85749",
    "addr:housenumber":"2081",
    "addr:postcode":"85749",
    "addr:street":"N Tanque Verde Loop Rd",
    "iso:country":"US",
    "sg:address":"2081 N Tanque Verde Loop Rd",
    "sg:city":"Tucson",
    "sg:classifiers":[
        {
            "category":"Professional",
            "subcategory":"Detective & Security Services",
            "type":"Services"
        },
        {
            "category":"Manufacturing",
            "subcategory":"Electronics",
            "type":"Manufacturing & Wholesale Goods"
        },
        {
            "category":"Shopping",
            "subcategory":"Computers & Home Electronics",
            "type":"Retail Goods"
        },
        {
            "category":"Building & Trades",
            "subcategory":"Electrical",
            "type":"Services"
        }
    ],
    "sg:phone":"+1 520 760 1388",
    "sg:postcode":"85749",
    "sg:province":"AZ",
    "sg:tags":[
        "control",
        "monitoring",
        "equipment-wholesale",
        "consultant",
        "alarm",
        "system",
        "surveillance",
        "equipment",
        "smoke",
        "detector",
        "manufacturer"
    ],
    "wof:name":"Security Hardware Systems",
    "wof:placetype":"venue"
},
  "geometry": {"coordinates":[-110.755623,32.247819],"type":"Point"}
}