{
  "type": "Feature",
  "properties": {
    "iso:country":"US",
    "sg:address":"7343 W Carole Ln",
    "sg:city":"Glendale",
    "sg:classifiers":[
        {
            "category":"Building & Trades",
            "subcategory":"Landscaping Services",
            "type":"Services"
        }
    ],
    "sg:phone":"+1 623 463 6473",
    "sg:postcode":"85303",
    "sg:province":"AZ",
    "sg:tags":[
        "lawn",
        "landscape",
        "maintenance",
        "grounds"
    ],
    "wof:name":"Nunez Creative Landscape Inc",
    "wof:placetype":"venue"
},
  "geometry": {"coordinates":[-112.21754,33.547274],"type":"Point"}
}