{
  "type": "Feature",
  "properties": {
    "iso:country":"US",
    "sg:address":"10038 N Bighorn Butte Dr",
    "sg:city":"Tucson",
    "sg:classifiers":[
        {
            "category":"Restaurant",
            "type":"Food & Drink"
        }
    ],
    "sg:phone":"+1 520 797 2048",
    "sg:postcode":"85737",
    "sg:province":"AZ",
    "sg:tags":[
        "eating"
    ],
    "wof:name":"Galley The",
    "wof:placetype":"venue"
},
  "geometry": {"coordinates":[-110.950126,32.388187],"type":"Point"}
}