{
  "type": "Feature",
  "properties": {
    "iso:country":"US",
    "sg:address":"1300 S Litchfield Rd",
    "sg:city":"Goodyear",
    "sg:classifiers":[
        {
            "category":"Wholesale",
            "subcategory":"Machinery & Supplies",
            "type":"Manufacturing & Wholesale Goods"
        }
    ],
    "sg:phone":"+1 623 932 4063",
    "sg:postcode":"85338",
    "sg:province":"AZ",
    "sg:tags":[
        "rebuilding",
        "aircraft"
    ],
    "wof:name":"Galaxy International Inc",
    "wof:placetype":"venue"
},
  "geometry": {"coordinates":[-112.358168,33.430164],"type":"Point"}
}