{
  "type": "Feature",
  "properties": {
    "addr:full":"250 S Craycroft Rd # 140 Tucson AZ 85711",
    "addr:housenumber":"250",
    "addr:postcode":"85711",
    "addr:street":"S Craycroft Rd # 140",
    "iso:country":"US",
    "sg:address":"250 S Craycroft Rd # 140",
    "sg:city":"Tucson",
    "sg:classifiers":[
        {
            "category":"Bars & Pubs",
            "type":"Food & Drink"
        },
        {
            "category":"Restaurant",
            "type":"Food & Drink"
        },
        {
            "category":"Bars & Pubs",
            "subcategory":"Lounge",
            "type":"Food & Drink"
        }
    ],
    "sg:phone":"+1 520 584 1610",
    "sg:postcode":"85711",
    "sg:province":"AZ",
    "sg:tags":[
        "cocktail"
    ],
    "wof:name":"Outpost Group",
    "wof:placetype":"venue"
},
  "geometry": {"coordinates":[-110.875294,32.218023],"type":"Point"}
}