{
  "type": "Feature",
  "properties": {
    "iso:country":"US",
    "sg:address":"6206 S Arabian Dr",
    "sg:city":"Hereford",
    "sg:classifiers":[
        {
            "category":"Shopping",
            "subcategory":"Catalog Store",
            "type":"Retail Goods"
        }
    ],
    "sg:phone":"+1 520 803 0730",
    "sg:postcode":"85615",
    "sg:province":"AZ",
    "sg:tags":[
        "house",
        "mail"
    ],
    "wof:name":"5th Wind Trading Co",
    "wof:placetype":"venue"
},
  "geometry": {"coordinates":[-110.200444,31.453493],"type":"Point"}
}