{
  "type": "Feature",
  "properties": {
    "iso:country":"US",
    "sg:address":"6042 E Hidden Valley Dr",
    "sg:city":"Cave Creek",
    "sg:classifiers":[
        {
            "category":"Shopping",
            "type":"Retail Goods"
        }
    ],
    "sg:phone":"+1 480 575 6684",
    "sg:postcode":"85331",
    "sg:province":"AZ",
    "sg:tags":[
        "art",
        "gallery",
        "dealer"
    ],
    "wof:name":"Mother Lode Fine Art Gallery",
    "wof:placetype":"venue"
},
  "geometry": {"coordinates":[-111.949978,33.831257],"type":"Point"}
}