{
  "type": "Feature",
  "properties": {
    "iso:country":"US",
    "sg:address":"800 E Camelback Rd",
    "sg:city":"Phoenix",
    "sg:classifiers":[
        {
            "category":"Shopping",
            "subcategory":"Tobacco",
            "type":"Retail Goods"
        }
    ],
    "sg:phone":"+1 602 277 6066",
    "sg:postcode":"85014",
    "sg:province":"AZ",
    "sg:tags":[
        "cigarette",
        "cigar",
        "dealer"
    ],
    "wof:name":"Good Fellas Cigar Lounge",
    "wof:placetype":"venue"
},
  "geometry": {"coordinates":[-112.063388,33.509301],"type":"Point"}
}