{
  "type": "Feature",
  "properties": {
    "iso:country":"US",
    "sg:address":"280 S Main St",
    "sg:city":"Cottonwood",
    "sg:classifiers":[
        {
            "category":"Shopping",
            "subcategory":"Department Store",
            "type":"Retail Goods"
        }
    ],
    "sg:phone":"+1 928 639 2392",
    "sg:postcode":"86326",
    "sg:province":"AZ",
    "wof:name":"H & J Dollar Store",
    "wof:placetype":"venue"
},
  "geometry": {"coordinates":[-112.00984200000001,34.734253],"type":"Point"}
}