{
  "type": "Feature",
  "properties": {
    "iso:country":"US",
    "sg:address":"2875 E Linda Ln",
    "sg:city":"Gilbert",
    "sg:classifiers":[
        {
            "category":"Real Estate",
            "subcategory":"Real Estate Agent",
            "type":"Services"
        }
    ],
    "sg:phone":"+1 480 899 2884",
    "sg:postcode":"85234",
    "sg:province":"AZ",
    "wof:name":"Varoga Realty Inc",
    "wof:placetype":"venue"
},
  "geometry": {"coordinates":[-111.72659,33.352134],"type":"Point"}
}