{
  "type": "Feature",
  "properties": {
    "addr:full":"1652 S Cedar Dr Apache Junction AZ 85220",
    "addr:housenumber":"1652",
    "addr:postcode":"85220",
    "addr:street":"S Cedar Dr",
    "iso:country":"US",
    "sg:address":"1652 S Cedar Dr",
    "sg:city":"Apache Junction",
    "sg:classifiers":[
        {
            "category":"Travel",
            "subcategory":"Travel Agent",
            "type":"Entertainment"
        }
    ],
    "sg:phone":"+1 480 671 7457",
    "sg:postcode":"85220",
    "sg:province":"AZ",
    "sg:tags":[
        "operator",
        "tour"
    ],
    "wof:name":"Adventures West Tours",
    "wof:placetype":"venue"
},
  "geometry": {"coordinates":[-111.578579,33.399451],"type":"Point"}
}