{
  "type": "Feature",
  "properties": {
    "iso:country":"US",
    "sg:address":"7050 S 24th St",
    "sg:city":"Phoenix",
    "sg:classifiers":[
        {
            "category":"Education",
            "subcategory":"Library",
            "type":"Public Place"
        }
    ],
    "sg:phone":"+1 602 243 8345",
    "sg:postcode":"85042",
    "sg:province":"AZ",
    "wof:name":"Aaec - Smcc Campus",
    "wof:placetype":"venue"
},
  "geometry": {"coordinates":[-112.030258,33.382703],"type":"Point"}
}