{
  "type": "Feature",
  "properties": {
    "addr:full":"21043 N Cave Creek Rd Phoenix AZ 85024",
    "addr:housenumber":"21043",
    "addr:postcode":"85024",
    "addr:street":"N Cave Creek Rd",
    "iso:country":"US",
    "sg:address":"21043 N Cave Creek Rd",
    "sg:city":"Phoenix",
    "sg:classifiers":[
        {
            "category":"Restaurant",
            "type":"Food & Drink"
        }
    ],
    "sg:menulink":"http://www.allmenus.com/az/phoenix/110832-quiznos-sub/menu/",
    "sg:phone":"+1 602 765 0535",
    "sg:postcode":"85024",
    "sg:province":"AZ",
    "sg:tags":[
        "wrap",
        "american",
        "sandwich"
    ],
    "wof:name":"Quiznos Sub",
    "wof:placetype":"venue"
},
  "geometry": {"coordinates":[-112.029978,33.678981],"type":"Point"}
}