{
  "type": "Feature",
  "properties": {
    "iso:country":"US",
    "sg:address":"6990 E Shea Blvd",
    "sg:city":"Scottsdale",
    "sg:classifiers":[
        {
            "category":"Shopping",
            "subcategory":"Clothing, Apparel, & Fashions",
            "type":"Retail Goods"
        }
    ],
    "sg:phone":"+1 480 998 3320",
    "sg:postcode":"85254",
    "sg:province":"AZ",
    "wof:name":"O'Yes",
    "wof:placetype":"venue"
},
  "geometry": {"coordinates":[-111.93189099999999,33.582226],"type":"Point"}
}