{
  "type": "Feature",
  "properties": {
    "iso:country":"US",
    "sg:address":"9634 N 33rd Ave",
    "sg:city":"Phoenix",
    "sg:classifiers":[
        {
            "category":"Retail",
            "subcategory":"Animal Services",
            "type":"Services"
        }
    ],
    "sg:phone":"+1 602 795 2124",
    "sg:postcode":"85051",
    "sg:province":"AZ",
    "sg:tags":[
        "pet",
        "grooming"
    ],
    "wof:name":"The Velvet Paw",
    "wof:placetype":"venue"
},
  "geometry": {"coordinates":[-112.129865,33.573239],"type":"Point"}
}