{
  "type": "Feature",
  "properties": {
    "iso:country":"US",
    "sg:address":"2341 S Ironwood Dr",
    "sg:city":"Apache Junction",
    "sg:classifiers":[
        {
            "category":"Autos & Motor Vehicles",
            "subcategory":"Fuel & Gas Station",
            "type":"Retail Goods"
        }
    ],
    "sg:phone":"+1 480 288 5648",
    "sg:postcode":"85220",
    "sg:province":"AZ",
    "sg:tags":[
        "station"
    ],
    "wof:name":"Diamond Shamrock",
    "wof:placetype":"venue"
},
  "geometry": {"coordinates":[-111.563238,33.393845],"type":"Point"}
}