{
  "type": "Feature",
  "properties": {
    "iso:country":"US",
    "sg:address":"2402 E Camelback Rd",
    "sg:city":"Phoenix",
    "sg:classifiers":[
        {
            "category":"Home & Garden",
            "subcategory":"Home Furnishings",
            "type":"Retail Goods"
        }
    ],
    "sg:phone":"+1 602 957 2297",
    "sg:postcode":"85016",
    "sg:province":"AZ",
    "sg:tags":[
        "housewares"
    ],
    "sg:website":"www.potterybarn.com",
    "wof:name":"Pottery Barn",
    "wof:placetype":"venue"
},
  "geometry": {"coordinates":[-112.025514,33.509599],"type":"Point"}
}