{
  "type": "Feature",
  "properties": {
    "iso:country":"US",
    "sg:address":"3302 S Pantano Rd",
    "sg:city":"Tucson",
    "sg:classifiers":[
        {
            "category":"Real Estate",
            "subcategory":"Real Estate Operator",
            "type":"Services"
        }
    ],
    "sg:phone":"+1 520 790 1275",
    "sg:postcode":"85730",
    "sg:province":"AZ",
    "sg:tags":[
        "building",
        "apartment"
    ],
    "wof:name":"Ridgewood Gardens",
    "wof:placetype":"venue"
},
  "geometry": {"coordinates":[-110.823929,32.183328],"type":"Point"}
}