{
  "type": "Feature",
  "properties": {
    "iso:country":"US",
    "sg:address":"4010 E Raymond St",
    "sg:city":"Phoenix",
    "sg:classifiers":[
        {
            "category":"Communications",
            "type":"Services"
        }
    ],
    "sg:phone":"+1 602 438 9688",
    "sg:postcode":"85040",
    "sg:province":"AZ",
    "wof:name":"Blue Communications Inc",
    "wof:placetype":"venue"
},
  "geometry": {"coordinates":[-111.991301,33.413273],"type":"Point"}
}