{
  "type": "Feature",
  "properties": {
    "iso:country":"US",
    "sg:address":"4601 E Darrow St",
    "sg:city":"Phoenix",
    "sg:classifiers":[
        {
            "category":"Building & Trades",
            "subcategory":"Construction",
            "type":"Services"
        }
    ],
    "sg:phone":"+1 602 768 4461",
    "sg:postcode":"85042",
    "sg:province":"AZ",
    "sg:tags":[
        "designer",
        "dealer",
        "pool",
        "swimming"
    ],
    "wof:name":"Adam's Shorcrete",
    "wof:placetype":"venue"
},
  "geometry": {"coordinates":[-111.981058,33.378693],"type":"Point"}
}