{
  "type": "Feature",
  "properties": {
    "iso:country":"US",
    "sg:address":"1155 S Country Club Dr",
    "sg:city":"Mesa",
    "sg:classifiers":[
        {
            "category":"Shopping",
            "type":"Retail Goods"
        }
    ],
    "sg:phone":"+1 480 610 6322",
    "sg:postcode":"85210",
    "sg:province":"AZ",
    "sg:tags":[
        "merchandise"
    ],
    "wof:name":"M & M Mart",
    "wof:placetype":"venue"
},
  "geometry": {"coordinates":[-111.840073,33.394119],"type":"Point"}
}