{
  "type": "Feature",
  "properties": {
    "iso:country":"US",
    "sg:address":"789 E Ash St",
    "sg:city":"Globe",
    "sg:classifiers":[
        {
            "category":"Retail",
            "subcategory":"Car Wash",
            "type":"Services"
        }
    ],
    "sg:phone":"+1 928 425 6062",
    "sg:postcode":"85501",
    "sg:province":"AZ",
    "sg:tags":[
        "polishing",
        "washing"
    ],
    "wof:name":"Mike's Auto Detailing",
    "wof:placetype":"venue"
},
  "geometry": {"coordinates":[-110.779154,33.393658],"type":"Point"}
}