{
  "type": "Feature",
  "properties": {
    "iso:country":"US",
    "sg:address":"5130 N Central Ave",
    "sg:city":"Phoenix",
    "sg:classifiers":[
        {
            "category":"Professional",
            "type":"Services"
        }
    ],
    "sg:phone":"+1 602 843 5500",
    "sg:postcode":"85012",
    "sg:province":"AZ",
    "sg:tags":[
        "establishment"
    ],
    "wof:name":"Cle West",
    "wof:placetype":"venue"
},
  "geometry": {"coordinates":[-112.073809,33.512861],"type":"Point"}
}