{
  "type": "Feature",
  "properties": {
    "addr:full":"6120 N 16th St Phoenix AZ 85016",
    "addr:housenumber":"6120",
    "addr:postcode":"85016",
    "addr:street":"N 16Th St",
    "iso:country":"US",
    "sg:address":"6120 N 16th St",
    "sg:city":"Phoenix",
    "sg:classifiers":[
        {
            "category":"Health Services",
            "subcategory":"Doctor",
            "type":"Services"
        }
    ],
    "sg:phone":"+1 602 266 1195",
    "sg:postcode":"85016",
    "sg:province":"AZ",
    "sg:tags":[
        "physician",
        "surgeon",
        "radiology",
        "surgeons",
        "pediatrics-radiology"
    ],
    "wof:name":"University Imaging Ii",
    "wof:placetype":"venue"
},
  "geometry": {"coordinates":[-112.047501,33.526191],"type":"Point"}
}