{
  "type": "Feature",
  "properties": {
    "addr:full":"19917 E Via de Arboles Queen Creek AZ 85242",
    "addr:housenumber":"19917",
    "addr:postcode":"85242",
    "addr:street":"E Via De Arboles",
    "iso:country":"US",
    "sg:address":"19917 E Via de Arboles",
    "sg:city":"Queen Creek",
    "sg:classifiers":[
        {
            "category":"Freight",
            "type":"Transportation"
        }
    ],
    "sg:phone":"+1 480 987 3034",
    "sg:postcode":"85242",
    "sg:province":"AZ",
    "wof:name":"Double A Transport LLC",
    "wof:placetype":"venue"
},
  "geometry": {"coordinates":[-111.654832,33.229392],"type":"Point"}
}