{
  "type": "Feature",
  "properties": {
    "iso:country":"US",
    "sg:address":"4735 S 12th Ave",
    "sg:city":"Tucson",
    "sg:classifiers":[
        {
            "category":"Food & Beverages",
            "subcategory":"Candy",
            "type":"Retail Goods"
        }
    ],
    "sg:phone":"+1 520 272 1110",
    "sg:postcode":"85714",
    "sg:province":"AZ",
    "sg:tags":[
        "confectionery"
    ],
    "wof:name":"Karel Pinatas & Party Supply",
    "wof:placetype":"venue"
},
  "geometry": {"coordinates":[-110.977447,32.165689],"type":"Point"}
}