{
  "type": "Feature",
  "properties": {
    "iso:country":"US",
    "sg:address":"12801 W Bell Rd",
    "sg:city":"Surprise",
    "sg:classifiers":[
        {
            "category":"Banks & Credit Unions",
            "subcategory":"Investment Brokerage",
            "type":"Services"
        }
    ],
    "sg:phone":"+1 623 815 9523",
    "sg:postcode":"85374",
    "sg:province":"AZ",
    "sg:tags":[
        "security"
    ],
    "wof:name":"Edward Jones 17706",
    "wof:placetype":"venue"
},
  "geometry": {"coordinates":[-112.336465,33.638562],"type":"Point"}
}