{
  "type": "Feature",
  "properties": {
    "addr:full":"111 N. Gilbert Rd Mesa AZ 85203",
    "addr:housenumber":"111",
    "addr:postcode":"85203",
    "addr:street":"N. Gilbert Rd",
    "iso:country":"US",
    "sg:address":"111 N. Gilbert Rd",
    "sg:city":"Mesa",
    "sg:classifiers":[
        {
            "category":"Food & Beverages",
            "subcategory":"Specialty",
            "type":"Retail Goods"
        },
        {
            "category":"Shopping",
            "subcategory":"Pharmacy",
            "type":"Retail Goods"
        }
    ],
    "sg:phone":"+1 480 254 1612",
    "sg:postcode":"85203",
    "sg:province":"AZ",
    "sg:tags":[
        "wellness",
        "product",
        "health",
        "diet"
    ],
    "sg:website":"http://WWW.NICHOLASJOHNSTONPRODUCTS.COM",
    "wof:name":"HERBALIFE PRODUCTS! (INDEPENDENT DISTRIBUTOR)",
    "wof:placetype":"venue"
},
  "geometry": {"coordinates":[-111.788195,33.417757],"type":"Point"}
}