{
  "type": "Feature",
  "properties": {
    "iso:country":"US",
    "sg:address":"575 W Pecos Rd",
    "sg:city":"Chandler",
    "sg:classifiers":[
        {
            "category":"Wholesale",
            "subcategory":"Durable Goods & Equipment",
            "type":"Manufacturing & Wholesale Goods"
        }
    ],
    "sg:phone":"+1 480 782 9373",
    "sg:postcode":"85225",
    "sg:province":"AZ",
    "wof:name":"Electromed Supply",
    "wof:placetype":"venue"
},
  "geometry": {"coordinates":[-111.84924700000001,33.291484],"type":"Point"}
}