{
  "type": "Feature",
  "properties": {
    "addr:full":"6016 S Mcclintock Dr Tempe AZ 85283",
    "addr:housenumber":"6016",
    "addr:postcode":"85283",
    "addr:street":"S Mcclintock Dr",
    "iso:country":"US",
    "sg:address":"6016 S Mcclintock Dr",
    "sg:city":"Tempe",
    "sg:classifiers":[
        {
            "category":"Retail",
            "subcategory":"Repair Shop",
            "type":"Services"
        },
        {
            "category":"Food & Beverages",
            "subcategory":"Groceries & Convenience Stores",
            "type":"Retail Goods"
        }
    ],
    "sg:phone":"+1 480 897 7800",
    "sg:postcode":"85283",
    "sg:province":"AZ",
    "sg:tags":[
        "major",
        "refinishing",
        "appliance",
        "refrigerant",
        "small",
        "freezers-repair",
        "refrigerator",
        "recovery"
    ],
    "sg:website":"http://www.allkleenwindows.com",
    "wof:name":"All Kleen",
    "wof:placetype":"venue"
},
  "geometry": {"coordinates":[-111.911277,33.36762],"type":"Point"}
}