{
  "type": "Feature",
  "properties": {
    "iso:country":"US",
    "sg:address":"3060 S 27th Ave",
    "sg:city":"Phoenix",
    "sg:classifiers":[
        {
            "category":"Utilities",
            "subcategory":"Refuse",
            "type":"Services"
        }
    ],
    "sg:phone":"+1 602 353 9099",
    "sg:postcode":"85009",
    "sg:province":"AZ",
    "sg:tags":[
        "system"
    ],
    "wof:name":"Waste Management",
    "wof:placetype":"venue"
},
  "geometry": {"coordinates":[-112.117204,33.420905],"type":"Point"}
}