{
  "type": "Feature",
  "properties": {
    "addr:full":"7407 E 22nd St Tucson AZ 85710",
    "addr:housenumber":"7407",
    "addr:postcode":"85710",
    "addr:street":"E 22Nd St",
    "iso:country":"US",
    "sg:address":"7407 E 22nd St",
    "sg:city":"Tucson",
    "sg:classifiers":[
        {
            "category":"Health Services",
            "subcategory":"Health Practitioner",
            "type":"Services"
        }
    ],
    "sg:phone":"+1 520 290 1665",
    "sg:postcode":"85710",
    "sg:province":"AZ",
    "sg:tags":[
        "therapist",
        "physical"
    ],
    "wof:name":"Halili Physical Therapy",
    "wof:placetype":"venue"
},
  "geometry": {"coordinates":[-110.832778,32.206543],"type":"Point"}
}