{
  "type": "Feature",
  "properties": {
    "iso:country":"US",
    "sg:address":"28230 N 32nd Ln",
    "sg:city":"Phoenix",
    "sg:classifiers":[
        {
            "category":"Shopping",
            "subcategory":"Bridal",
            "type":"Retail Goods"
        }
    ],
    "sg:phone":"+1 623 694 9910",
    "sg:postcode":"85083",
    "sg:province":"AZ",
    "sg:tags":[
        "shop"
    ],
    "wof:name":"Phoenix Quinceaneras Y Novias",
    "wof:placetype":"venue"
},
  "geometry": {"coordinates":[-112.129272,33.74136],"type":"Point"}
}