{
  "type": "Feature",
  "properties": {
    "addr:full":"4020 W Glenrosa Ave Phoenix AZ 85019",
    "addr:housenumber":"4020",
    "addr:postcode":"85019",
    "addr:street":"W Glenrosa Ave",
    "iso:country":"US",
    "sg:address":"4020 W Glenrosa Ave",
    "sg:city":"Phoenix",
    "sg:classifiers":[
        {
            "category":"Recreation",
            "type":"Entertainment"
        }
    ],
    "sg:phone":"+1 602 262 4539",
    "sg:postcode":"85019",
    "sg:province":"AZ",
    "sg:tags":[
        "parks"
    ],
    "wof:name":"Cielito Park",
    "wof:placetype":"venue"
},
  "geometry": {"coordinates":[-112.148433,33.498703],"type":"Point"}
}