{
  "type": "Feature",
  "properties": {
    "iso:country":"US",
    "sg:address":"15771 N Oracle Rd",
    "sg:city":"Tucson",
    "sg:classifiers":[
        {
            "category":"Wholesale",
            "subcategory":"Farm Supplies",
            "type":"Manufacturing & Wholesale Goods"
        }
    ],
    "sg:phone":"+1 520 825 2969",
    "sg:postcode":"85739",
    "sg:province":"AZ",
    "sg:tags":[
        "feed"
    ],
    "wof:name":"Rancher's Supply",
    "wof:placetype":"venue"
},
  "geometry": {"coordinates":[-110.925411,32.492914],"type":"Point"}
}