{
  "type": "Feature",
  "properties": {
    "iso:country":"US",
    "sg:address":"2666 W 16th St",
    "sg:city":"Yuma",
    "sg:classifiers":[
        {
            "category":"Manufacturing",
            "subcategory":"Chemicals & Compounds",
            "type":"Manufacturing & Wholesale Goods"
        }
    ],
    "sg:phone":"+1 928 782 3129",
    "sg:postcode":"85364",
    "sg:province":"AZ",
    "sg:tags":[
        "paint",
        "mfg"
    ],
    "wof:name":"Frazee Industries Inc",
    "wof:placetype":"venue"
},
  "geometry": {"coordinates":[-114.650909,32.698535],"type":"Point"}
}