{
  "type": "Feature",
  "properties": {
    "iso:country":"US",
    "sg:address":"1853 W Broadway Rd",
    "sg:city":"Mesa",
    "sg:classifiers":[
        {
            "category":"Restaurant",
            "type":"Food & Drink"
        }
    ],
    "sg:phone":"+1 480 898 8282",
    "sg:postcode":"85202",
    "sg:province":"AZ",
    "sg:tags":[
        "eating"
    ],
    "wof:name":"Happy Foods II",
    "wof:placetype":"venue"
},
  "geometry": {"coordinates":[-111.874,33.407514],"type":"Point"}
}