{
  "type": "Feature",
  "properties": {
    "iso:country":"US",
    "sg:address":"688 W 4th St Ste D",
    "sg:city":"Benson",
    "sg:classifiers":[
        {
            "category":"Professional",
            "subcategory":"Lawyer & Legal Services",
            "type":"Services"
        }
    ],
    "sg:phone":"+1 520 586 0178",
    "sg:postcode":"85602",
    "sg:province":"AZ",
    "sg:tags":[
        "attorney",
        "practice"
    ],
    "wof:name":"A Boegemann Law Firm, Plc",
    "wof:placetype":"venue"
},
  "geometry": {"coordinates":[-110.308907,31.970638],"type":"Point"}
}