{
  "type": "Feature",
  "properties": {
    "addr:full":"4908 S Power Rd Mesa AZ 85212",
    "addr:housenumber":"4908",
    "addr:postcode":"85212",
    "addr:street":"S Power Rd",
    "iso:country":"US",
    "sg:address":"4908 S Power Rd",
    "sg:city":"Mesa",
    "sg:classifiers":[
        {
            "category":"Restaurant",
            "type":"Food & Drink"
        }
    ],
    "sg:menulink":"http://www.allmenus.com/az/chandler/179604-chick-fil-a/menu/",
    "sg:phone":"+1 480 988 6252",
    "sg:postcode":"85212",
    "sg:province":"AZ",
    "sg:tags":[
        "wrap",
        "soup",
        "american",
        "sandwich",
        "salad"
    ],
    "wof:name":"Chick-fil-A",
    "wof:placetype":"venue"
},
  "geometry": {"coordinates":[-111.687139,33.335184],"type":"Point"}
}