{
  "type": "Feature",
  "properties": {
    "addr:full":"7824 S 29th Ave Laveen AZ 85339",
    "addr:housenumber":"7824",
    "addr:postcode":"85339",
    "addr:street":"S 29Th Ave",
    "iso:country":"US",
    "sg:address":"7824 S 29th Ave",
    "sg:city":"Laveen",
    "sg:classifiers":[
        {
            "category":"Manufacturing",
            "subcategory":"Glass & Minerals",
            "type":"Manufacturing & Wholesale Goods"
        },
        {
            "category":"Manufacturing",
            "subcategory":"Building Materials",
            "type":"Manufacturing & Wholesale Goods"
        }
    ],
    "sg:phone":"+1 602 254 9842",
    "sg:postcode":"85339",
    "sg:province":"AZ",
    "sg:tags":[
        "plate",
        "repair",
        "glazier",
        "window",
        "replacement"
    ],
    "wof:name":"J R Glass & Mirror",
    "wof:placetype":"venue"
},
  "geometry": {"coordinates":[-112.12184600000001,33.375434],"type":"Point"}
}