{
  "type": "Feature",
  "properties": {
    "iso:country":"US",
    "sg:address":"250 W Cll de Las Tiendas",
    "sg:city":"Green Valley",
    "sg:classifiers":[
        {
            "category":"Retail",
            "subcategory":"Auto Repair",
            "type":"Services"
        }
    ],
    "sg:phone":"+1 520 648 0180",
    "sg:postcode":"85614",
    "sg:province":"AZ",
    "sg:tags":[
        "repairing",
        "automobile"
    ],
    "sg:website":"www.hickeyautomotive.com",
    "wof:name":"Hickey Automotive",
    "wof:placetype":"venue"
},
  "geometry": {"coordinates":[-110.993071,31.899104],"type":"Point"}
}