{
  "type": "Feature",
  "properties": {
    "iso:country":"US",
    "sg:address":"7820 E Shea Blvd",
    "sg:city":"Scottsdale",
    "sg:classifiers":[
        {
            "category":"Insurance",
            "subcategory":"Insurance Agent",
            "type":"Services"
        }
    ],
    "sg:phone":"+1 480 596 1525",
    "sg:postcode":"85260",
    "sg:province":"AZ",
    "wof:name":"Sachs Group",
    "wof:placetype":"venue"
},
  "geometry": {"coordinates":[-111.910477,33.582144],"type":"Point"}
}