{
  "type": "Feature",
  "properties": {
    "addr:full":"1600 S 4th Ave Tucson AZ 85713",
    "addr:housenumber":"1600",
    "addr:postcode":"85713",
    "addr:street":"S 4Th Ave",
    "iso:country":"US",
    "sg:address":"1600 S 4th Ave",
    "sg:city":"Tucson",
    "sg:classifiers":[
        {
            "category":"Retail",
            "subcategory":"Repair Shop",
            "type":"Services"
        }
    ],
    "sg:phone":"+1 520 882 5678",
    "sg:postcode":"85713",
    "sg:province":"AZ",
    "sg:tags":[
        "upholsterer"
    ],
    "wof:name":"Rubens Upholstery",
    "wof:placetype":"venue"
},
  "geometry": {"coordinates":[-110.965395,32.201648],"type":"Point"}
}