{
  "type": "Feature",
  "properties": {
    "addr:full":"1404 N Rose St Tempe AZ 85281",
    "addr:housenumber":"1404",
    "addr:postcode":"85281",
    "addr:street":"N Rose St",
    "iso:country":"US",
    "sg:address":"1404 N Rose St",
    "sg:city":"Tempe",
    "sg:classifiers":[
        {
            "category":"Professional",
            "subcategory":"Management & Consulting",
            "type":"Services"
        }
    ],
    "sg:phone":"+1 480 949 0894",
    "sg:postcode":"85281",
    "sg:province":"AZ",
    "sg:tags":[
        "marketing",
        "dental",
        "suppl",
        "merchandise",
        "general"
    ],
    "wof:name":"Shairon International Trade",
    "wof:placetype":"venue"
},
  "geometry": {"coordinates":[-111.921114,33.444428],"type":"Point"}
}