{
  "type": "Feature",
  "properties": {
    "iso:country":"US",
    "sg:address":"3535 Chino Dr",
    "sg:city":"Golden Valley",
    "sg:classifiers":[
        {
            "category":"Real Estate",
            "subcategory":"Real Estate Operator",
            "type":"Services"
        }
    ],
    "sg:phone":"+1 928 565 4627",
    "sg:postcode":"86413",
    "sg:province":"AZ",
    "sg:tags":[
        "mobile",
        "home",
        "community"
    ],
    "wof:name":"Desert Sunset Trailer Park",
    "wof:placetype":"venue"
},
  "geometry": {"coordinates":[-114.148809,35.228952],"type":"Point"}
}