{
  "type": "Feature",
  "properties": {
    "iso:country":"US",
    "sg:address":"5930 W Greenway Rd Ste 5",
    "sg:city":"Glendale",
    "sg:classifiers":[
        {
            "category":"Bars & Pubs",
            "type":"Food & Drink"
        },
        {
            "category":"Bars & Pubs",
            "subcategory":"Lounge",
            "type":"Food & Drink"
        }
    ],
    "sg:phone":"+1 602 938 1956",
    "sg:postcode":"85306",
    "sg:province":"AZ",
    "sg:tags":[
        "cocktail"
    ],
    "wof:name":"Tony's Cocktail Lounge",
    "wof:placetype":"venue"
},
  "geometry": {"coordinates":[-112.186912,33.625177],"type":"Point"}
}