{
  "type": "Feature",
  "properties": {
    "iso:country":"US",
    "sg:address":"3910 E Roeser Rd",
    "sg:city":"Phoenix",
    "sg:classifiers":[
        {
            "category":"Manufacturing",
            "subcategory":"Metals",
            "type":"Manufacturing & Wholesale Goods"
        }
    ],
    "sg:phone":"+1 602 426 9147",
    "sg:postcode":"85040",
    "sg:province":"AZ",
    "sg:tags":[
        "plumbing",
        "fitting",
        "fixture",
        "mfg"
    ],
    "wof:name":"Double K Sales Company",
    "wof:placetype":"venue"
},
  "geometry": {"coordinates":[-111.996282,33.399889],"type":"Point"}
}