{
  "type": "Feature",
  "properties": {
    "iso:country":"US",
    "sg:address":"713 S Burk St",
    "sg:city":"Gilbert",
    "sg:classifiers":[
        {
            "category":"Personal",
            "type":"Services"
        }
    ],
    "sg:phone":"+1 480 558 9247",
    "sg:postcode":"85296",
    "sg:province":"AZ",
    "sg:tags":[
        "car",
        "loading",
        "unloading"
    ],
    "wof:name":"Smart Movers",
    "wof:placetype":"venue"
},
  "geometry": {"coordinates":[-111.782009,33.337313],"type":"Point"}
}