{
  "type": "Feature",
  "properties": {
    "iso:country":"US",
    "sg:address":"10210 W Indian School Rd",
    "sg:city":"Phoenix",
    "sg:classifiers":[
        {
            "category":"Fast Food",
            "type":"Food & Drink"
        },
        {
            "category":"Restaurant",
            "type":"Food & Drink"
        }
    ],
    "sg:phone":"+1 623 872 7878",
    "sg:postcode":"85037",
    "sg:province":"AZ",
    "sg:tags":[
        "traditional",
        "american"
    ],
    "sg:website":"www.sonicdrivein.com",
    "wof:name":"Sonic Drive-In",
    "wof:placetype":"venue"
},
  "geometry": {"coordinates":[-112.279645,33.49419],"type":"Point"}
}