{
  "type": "Feature",
  "properties": {
    "iso:country":"US",
    "sg:address":"4038 E Windrose Dr",
    "sg:city":"Phoenix",
    "sg:classifiers":[
        {
            "category":"Shopping",
            "subcategory":"Bicycles & Sporting Goods",
            "type":"Retail Goods"
        }
    ],
    "sg:phone":"+1 602 971 0622",
    "sg:postcode":"85032",
    "sg:province":"AZ",
    "sg:tags":[
        "sale",
        "bicycles-repair"
    ],
    "wof:name":"Bicycle Paradise Inc",
    "wof:placetype":"venue"
},
  "geometry": {"coordinates":[-111.994282,33.602375],"type":"Point"}
}