{
  "type": "Feature",
  "properties": {
    "addr:full":"305 E Cherry Ave Flagstaff AZ 86001",
    "addr:housenumber":"305",
    "addr:postcode":"86001",
    "addr:street":"E Cherry Ave",
    "iso:country":"US",
    "sg:address":"305 E Cherry Ave",
    "sg:city":"Flagstaff",
    "sg:classifiers":[
        {
            "category":"Building & Trades",
            "subcategory":"Construction",
            "type":"Services"
        }
    ],
    "sg:phone":"+1 928 779 5740",
    "sg:postcode":"86001",
    "sg:province":"AZ",
    "sg:tags":[
        "masonry",
        "contractor"
    ],
    "wof:name":"Canyon Pines Stoneworks Inc",
    "wof:placetype":"venue"
},
  "geometry": {"coordinates":[-111.64459100000001,35.199203],"type":"Point"}
}