{
  "type": "Feature",
  "properties": {
    "iso:country":"US",
    "sg:address":"5903 E Pima St",
    "sg:city":"Tucson",
    "sg:classifiers":[
        {
            "category":"Insurance",
            "subcategory":"Insurance Agent",
            "type":"Services"
        }
    ],
    "sg:phone":"+1 520 881 9481",
    "sg:postcode":"85712",
    "sg:province":"AZ",
    "wof:name":"Aslin Group",
    "wof:placetype":"venue"
},
  "geometry": {"coordinates":[-110.865235,32.243464],"type":"Point"}
}