{
  "type": "Feature",
  "properties": {
    "iso:country":"US",
    "sg:address":"2001 E Washington St",
    "sg:city":"Phoenix",
    "sg:classifiers":[
        {
            "category":"Bars & Pubs",
            "type":"Food & Drink"
        }
    ],
    "sg:phone":"+1 602 262 9500",
    "sg:postcode":"85034",
    "sg:province":"AZ",
    "sg:tags":[
        "lounge",
        "cocktail"
    ],
    "wof:name":"Copper State Buffet",
    "wof:placetype":"venue"
},
  "geometry": {"coordinates":[-112.03805199999999,33.448305],"type":"Point"}
}