{
  "type": "Feature",
  "properties": {
    "iso:country":"US",
    "sg:address":"5995 N 78th St",
    "sg:city":"Scottsdale",
    "sg:classifiers":[
        {
            "category":"Real Estate",
            "subcategory":"Real Estate Operator",
            "type":"Services"
        }
    ],
    "sg:phone":"+1 480 990 0520",
    "sg:postcode":"85250",
    "sg:province":"AZ",
    "sg:tags":[
        "apartment"
    ],
    "wof:name":"Bella Vita Of Scottsdale",
    "wof:placetype":"venue"
},
  "geometry": {"coordinates":[-111.912576,33.523887],"type":"Point"}
}