{
  "type": "Feature",
  "properties": {
    "addr:full":"4711 E Falcon Dr Mesa AZ 85215",
    "addr:housenumber":"4711",
    "addr:postcode":"85215",
    "addr:street":"E Falcon Dr",
    "iso:country":"US",
    "sg:address":"4711 E Falcon Dr",
    "sg:city":"Mesa",
    "sg:classifiers":[
        {
            "category":"Professional",
            "type":"Services"
        }
    ],
    "sg:phone":"+1 480 654 3716",
    "sg:postcode":"85215",
    "sg:province":"AZ",
    "wof:name":"Mr Quotes",
    "wof:placetype":"venue"
},
  "geometry": {"coordinates":[-111.728193,33.453804],"type":"Point"}
}