{
  "type": "Feature",
  "properties": {
    "addr:full":"7071 N 138th Ave Glendale AZ 85307",
    "addr:housenumber":"7071",
    "addr:postcode":"85307",
    "addr:street":"N 138Th Ave",
    "iso:country":"US",
    "sg:address":"7071 N 138th Ave",
    "sg:city":"Glendale",
    "sg:classifiers":[
        {
            "category":"Food & Beverages",
            "subcategory":"Specialty",
            "type":"Retail Goods"
        },
        {
            "category":"Restaurant",
            "type":"Food & Drink"
        }
    ],
    "sg:phone":"+1 623 935 6224",
    "sg:postcode":"85307",
    "sg:province":"AZ",
    "sg:tags":[
        "product",
        "health",
        "diet"
    ],
    "sg:website":"http://www.smoothieking.com",
    "wof:name":"Smoothie King",
    "wof:placetype":"venue"
},
  "geometry": {"coordinates":[-112.35552800000001,33.538199],"type":"Point"}
}