{
  "type": "Feature",
  "properties": {
    "iso:country":"US",
    "sg:address":"327 N 1st St",
    "sg:city":"Buckeye",
    "sg:classifiers":[
        {
            "category":"Professional",
            "subcategory":"Business Services",
            "type":"Services"
        }
    ],
    "sg:phone":"+1 623 386 2502",
    "sg:postcode":"85326",
    "sg:province":"AZ",
    "sg:tags":[
        "water",
        "treatment"
    ],
    "wof:name":"Odom's Inc",
    "wof:placetype":"venue"
},
  "geometry": {"coordinates":[-112.59087,33.372695],"type":"Point"}
}