{
  "type": "Feature",
  "properties": {
    "iso:country":"US",
    "sg:address":"1425 S Lindsay Rd",
    "sg:city":"Mesa",
    "sg:classifiers":[
        {
            "category":"Manufacturing",
            "subcategory":"Petroleum Products",
            "type":"Manufacturing & Wholesale Goods"
        }
    ],
    "sg:phone":"+1 480 539 4911",
    "sg:postcode":"85204",
    "sg:province":"AZ",
    "sg:tags":[
        "refiner"
    ],
    "wof:name":"Scentsual Aromatherapy",
    "wof:placetype":"venue"
},
  "geometry": {"coordinates":[-111.771136,33.39178],"type":"Point"}
}