{
  "type": "Feature",
  "properties": {
    "addr:full":"4102 E Winslow Ave Phoenix AZ 85040",
    "addr:housenumber":"4102",
    "addr:postcode":"85040",
    "addr:street":"E Winslow Ave",
    "iso:country":"US",
    "sg:address":"4102 E Winslow Ave",
    "sg:city":"Phoenix",
    "sg:classifiers":[
        {
            "category":"Manufacturing",
            "subcategory":"Metals",
            "type":"Manufacturing & Wholesale Goods"
        }
    ],
    "sg:phone":"+1 602 437 0379",
    "sg:postcode":"85040",
    "sg:province":"AZ",
    "wof:name":"Bur-Gon",
    "wof:placetype":"venue"
},
  "geometry": {"coordinates":[-111.993049,33.421009],"type":"Point"}
}