{
  "type": "Feature",
  "properties": {
    "iso:country":"US",
    "sg:address":"12411 N 57th St",
    "sg:city":"Scottsdale",
    "sg:classifiers":[
        {
            "category":"Professional",
            "subcategory":"Accounting & Tax Preparation",
            "type":"Services"
        }
    ],
    "sg:phone":"+1 480 951 9365",
    "sg:postcode":"85254",
    "sg:province":"AZ",
    "sg:tags":[
        "accountant"
    ],
    "wof:name":"Warren D Meyer CPA",
    "wof:placetype":"venue"
},
  "geometry": {"coordinates":[-111.95867800000001,33.59996],"type":"Point"}
}