{
  "type": "Feature",
  "properties": {
    "iso:country":"US",
    "sg:address":"1002 E Wahalla Ln",
    "sg:city":"Phoenix",
    "sg:classifiers":[
        {
            "category":"Professional",
            "type":"Services"
        }
    ],
    "sg:phone":"+1 602 869 6709",
    "sg:postcode":"85024",
    "sg:province":"AZ",
    "wof:name":"Beat Heat",
    "wof:placetype":"venue"
},
  "geometry": {"coordinates":[-112.059183,33.667549],"type":"Point"}
}