{
  "type": "Feature",
  "properties": {
    "iso:country":"US",
    "sg:address":"4255 Stockton Hill Rd # 1",
    "sg:city":"Kingman",
    "sg:classifiers":[
        {
            "category":"Shopping",
            "subcategory":"Jewelry",
            "type":"Retail Goods"
        },
        {
            "category":"Manufacturing",
            "subcategory":"Jewelry",
            "type":"Manufacturing & Wholesale Goods"
        }
    ],
    "sg:phone":"+1 928 757 9229",
    "sg:postcode":"86409",
    "sg:province":"AZ",
    "sg:tags":[
        "stone",
        "jewelers-wholesale",
        "jeweler",
        "precious",
        "semi-precious",
        "manufacturer"
    ],
    "wof:name":"Benco Diamonds & Jwly Distrs",
    "wof:placetype":"venue"
},
  "geometry": {"coordinates":[-114.03838500000001,35.245341],"type":"Point"}
}