{
  "type": "Feature",
  "properties": {
    "addr:full":"5102 E Pima St Tucson AZ 85712",
    "addr:housenumber":"5102",
    "addr:postcode":"85712",
    "addr:street":"E Pima St",
    "iso:country":"US",
    "sg:address":"5102 E Pima St",
    "sg:city":"Tucson",
    "sg:classifiers":[
        {
            "category":"Health Services",
            "subcategory":"Doctor",
            "type":"Services"
        }
    ],
    "sg:phone":"+1 520 323 9076",
    "sg:postcode":"85712",
    "sg:province":"AZ",
    "sg:tags":[
        "physician",
        "surgeon"
    ],
    "wof:name":"Michael S Kuntzelman MD",
    "wof:placetype":"venue"
},
  "geometry": {"coordinates":[-110.881978,32.243357],"type":"Point"}
}