{
  "type": "Feature",
  "properties": {
    "addr:full":"7107 E Laguna Azul Ave Mesa AZ 85209",
    "addr:housenumber":"7107",
    "addr:postcode":"85209",
    "addr:street":"E Laguna Azul Ave",
    "iso:country":"US",
    "sg:address":"7107 E Laguna Azul Ave",
    "sg:city":"Mesa",
    "sg:classifiers":[
        {
            "category":"Building & Trades",
            "subcategory":"Construction",
            "type":"Services"
        }
    ],
    "sg:phone":"+1 480 985 3784",
    "sg:postcode":"85209",
    "sg:province":"AZ",
    "sg:tags":[
        "general",
        "contractor"
    ],
    "wof:name":"L S REGAL Special LLP",
    "wof:placetype":"venue"
},
  "geometry": {"coordinates":[-111.681673,33.374997],"type":"Point"}
}