{
  "type": "Feature",
  "properties": {
    "addr:full":"24626 N 40th Ln Glendale AZ 85310",
    "addr:housenumber":"24626",
    "addr:postcode":"85310",
    "addr:street":"N 40Th Ln",
    "iso:country":"US",
    "sg:address":"24626 N 40th Ln",
    "sg:city":"Glendale",
    "sg:classifiers":[
        {
            "category":"Building & Trades",
            "subcategory":"Construction",
            "type":"Services"
        }
    ],
    "sg:phone":"+1 623 582 2517",
    "sg:postcode":"85310",
    "sg:province":"AZ",
    "sg:tags":[
        "resurfacing",
        "laying",
        "refinishing",
        "floor"
    ],
    "wof:name":"Oasis Painting Inc",
    "wof:placetype":"venue"
},
  "geometry": {"coordinates":[-112.147499,33.708545],"type":"Point"}
}