{
  "type": "Feature",
  "properties": {
    "iso:country":"US",
    "sg:address":"1412 E Bayview Dr",
    "sg:city":"Tempe",
    "sg:classifiers":[
        {
            "category":"Health Services",
            "subcategory":"Clinic",
            "type":"Services"
        }
    ],
    "sg:phone":"+1 480 838 2341",
    "sg:postcode":"85283",
    "sg:province":"AZ",
    "sg:tags":[
        "medical",
        "group"
    ],
    "wof:name":"Squaw Peak Anesthesia Inc",
    "wof:placetype":"venue"
},
  "geometry": {"coordinates":[-111.916685,33.377244],"type":"Point"}
}