{
  "type": "Feature",
  "properties": {
    "iso:country":"US",
    "sg:address":"16741 N Forecastle Ave",
    "sg:city":"Tucson",
    "sg:classifiers":[
        {
            "category":"Building & Trades",
            "subcategory":"Construction",
            "type":"Services"
        }
    ],
    "sg:phone":"+1 520 825 2951",
    "sg:postcode":"85739",
    "sg:province":"AZ",
    "sg:tags":[
        "general",
        "contractor"
    ],
    "wof:name":"J D Browning Construction",
    "wof:placetype":"venue"
},
  "geometry": {"coordinates":[-110.91447100000001,32.509502],"type":"Point"}
}