{
  "type": "Feature",
  "properties": {
    "iso:country":"US",
    "sg:address":"2525 W Deer Valley Rd",
    "sg:city":"Phoenix",
    "sg:classifiers":[
        {
            "category":"Restaurant",
            "type":"Food & Drink"
        }
    ],
    "sg:phone":"+1 623 587 1227",
    "sg:postcode":"85027",
    "sg:province":"AZ",
    "sg:tags":[
        "style",
        "family",
        "lunch",
        "american",
        "brunch",
        "breakfast"
    ],
    "sg:website":"http://www.dennys.com",
    "wof:name":"Denny's",
    "wof:placetype":"venue"
},
  "geometry": {"coordinates":[-112.11456200000001,33.6838],"type":"Point"}
}