{
  "type": "Feature",
  "properties": {
    "iso:country":"US",
    "sg:address":"2815 McCulloch Blvd N",
    "sg:city":"Lake Havasu City",
    "sg:classifiers":[
        {
            "category":"Building & Trades",
            "subcategory":"Landscaping Services",
            "type":"Services"
        }
    ],
    "sg:phone":"+1 928 680 1765",
    "sg:postcode":"86403",
    "sg:province":"AZ",
    "sg:tags":[
        "landscape",
        "contractor"
    ],
    "wof:name":"Color Arts Landscaping",
    "wof:placetype":"venue"
},
  "geometry": {"coordinates":[-114.304973,34.484978],"type":"Point"}
}