{
  "type": "Feature",
  "properties": {
    "iso:country":"US",
    "sg:address":"2326 E Indian School Rd",
    "sg:city":"Phoenix",
    "sg:classifiers":[
        {
            "category":"Utilities",
            "subcategory":"Mobile Phone",
            "type":"Services"
        }
    ],
    "sg:phone":"+1 602 954 4607",
    "sg:postcode":"85016",
    "sg:province":"AZ",
    "sg:tags":[
        "telephone",
        "cellular"
    ],
    "wof:name":"Kit KAT Cellular",
    "wof:placetype":"venue"
},
  "geometry": {"coordinates":[-112.030676,33.494917],"type":"Point"}
}