{
  "type": "Feature",
  "properties": {
    "iso:country":"US",
    "sg:address":"11737 W Thunderbird Rd",
    "sg:city":"El Mirage",
    "sg:classifiers":[
        {
            "category":"Organizations",
            "subcategory":"Religious Organization",
            "type":"Services"
        }
    ],
    "sg:phone":"+1 623 583 1660",
    "sg:postcode":"85335",
    "sg:province":"AZ",
    "sg:tags":[
        "church"
    ],
    "wof:name":"Centro Misionero Pentecostes",
    "wof:placetype":"venue"
},
  "geometry": {"coordinates":[-112.314471,33.608834],"type":"Point"}
}