{
  "type": "Feature",
  "properties": {
    "iso:country":"US",
    "sg:address":"9425 N Cave Creek Rd",
    "sg:city":"Phoenix",
    "sg:classifiers":[
        {
            "category":"Bars & Pubs",
            "type":"Food & Drink"
        }
    ],
    "sg:phone":"+1 602 943 9966",
    "sg:postcode":"85020",
    "sg:province":"AZ",
    "wof:name":"Driftwood Tap Room",
    "wof:placetype":"venue"
},
  "geometry": {"coordinates":[-112.05928900000001,33.572609],"type":"Point"}
}