{
  "type": "Feature",
  "properties": {
    "iso:country":"US",
    "sg:address":"5224 W Camelback Rd",
    "sg:city":"Glendale",
    "sg:classifiers":[
        {
            "category":"Autos & Motor Vehicles",
            "subcategory":"Auto Supplies",
            "type":"Retail Goods"
        }
    ],
    "sg:phone":"+1 602 312 3012",
    "sg:postcode":"85301",
    "sg:province":"AZ",
    "sg:tags":[
        "lube",
        "oil"
    ],
    "wof:name":"Lube In N Out",
    "wof:placetype":"venue"
},
  "geometry": {"coordinates":[-112.172067,33.509482],"type":"Point"}
}