{
  "type": "Feature",
  "properties": {
    "addr:full":"7149 N 58th Dr Glendale AZ 85301",
    "addr:housenumber":"7149",
    "addr:postcode":"85301",
    "addr:street":"N 58Th Dr",
    "iso:country":"US",
    "sg:address":"7149 N 58th Dr",
    "sg:city":"Glendale",
    "sg:classifiers":[
        {
            "category":"Insurance",
            "subcategory":"Insurance Agent",
            "type":"Services"
        }
    ],
    "sg:phone":"+1 623 412 1176",
    "sg:postcode":"85301",
    "sg:province":"AZ",
    "wof:name":"Farmers Insurance",
    "wof:placetype":"venue"
},
  "geometry": {"coordinates":[-112.18487,33.541934],"type":"Point"}
}