{
  "type": "Feature",
  "properties": {
    "iso:country":"US",
    "sg:address":"2415 E Camelback Rd",
    "sg:city":"Phoenix",
    "sg:classifiers":[
        {
            "category":"Banks & Credit Unions",
            "subcategory":"Bank",
            "type":"Services"
        }
    ],
    "sg:phone":"+1 602 522 8900",
    "sg:postcode":"85016",
    "sg:province":"AZ",
    "sg:tags":[
        "cashing",
        "check"
    ],
    "sg:website":"www.callcheckmate.com",
    "wof:name":"LMSA Financial Corp",
    "wof:placetype":"venue"
},
  "geometry": {"coordinates":[-112.025789,33.509426],"type":"Point"}
}