{
  "type": "Feature",
  "properties": {
    "iso:country":"US",
    "sg:address":"3010 S Priest Dr Ste 103",
    "sg:city":"Tempe",
    "sg:classifiers":[
        {
            "category":"Professional",
            "subcategory":"Management & Consulting",
            "type":"Services"
        },
        {
            "category":"Professional",
            "subcategory":"Advertising",
            "type":"Services"
        }
    ],
    "sg:phone":"+1 480 967 1405",
    "sg:postcode":"85282",
    "sg:province":"AZ",
    "sg:tags":[
        "marketing",
        "program",
        "agency",
        "specialty",
        "consultant"
    ],
    "sg:website":"http://www.lemmontree.com",
    "wof:name":"Lemmon Aid Marketing Services",
    "wof:placetype":"venue"
},
  "geometry": {"coordinates":[-111.960769,33.39632],"type":"Point"}
}