{
  "type": "Feature",
  "properties": {
    "addr:full":"17602 N Black Canyon Hwy Phoenix AZ 85053",
    "addr:housenumber":"17602",
    "addr:postcode":"85053",
    "addr:street":"N Black Canyon Hwy",
    "iso:country":"US",
    "sg:address":"17602 N Black Canyon Hwy",
    "sg:city":"Phoenix",
    "sg:classifiers":[
        {
            "category":"Professional",
            "subcategory":"Management & Consulting",
            "type":"Services"
        }
    ],
    "sg:phone":"+1 602 795 4592",
    "sg:postcode":"85053",
    "sg:province":"AZ",
    "sg:tags":[
        "consultant",
        "resource",
        "human"
    ],
    "wof:name":"Human Resources",
    "wof:placetype":"venue"
},
  "geometry": {"coordinates":[-112.11571600000001,33.644746],"type":"Point"}
}