{
  "type": "Feature",
  "properties": {
    "addr:full":"1644 E Bethany Home Rd Phoenix AZ 85016",
    "addr:housenumber":"1644",
    "addr:postcode":"85016",
    "addr:street":"E Bethany Home Rd",
    "iso:country":"US",
    "sg:address":"1644 E Bethany Home Rd",
    "sg:city":"Phoenix",
    "sg:classifiers":[
        {
            "category":"Banks & Credit Unions",
            "subcategory":"Financial Services",
            "type":"Services"
        }
    ],
    "sg:phone":"+1 602 279 7777",
    "sg:postcode":"85016",
    "sg:province":"AZ",
    "sg:tags":[
        "mortgage"
    ],
    "wof:name":"Prostaff Mortgage Corp",
    "wof:placetype":"venue"
},
  "geometry": {"coordinates":[-112.046007,33.523761],"type":"Point"}
}