{
  "type": "Feature",
  "properties": {
    "addr:full":"1638 N 40th St Phoenix AZ 85008",
    "addr:housenumber":"1638",
    "addr:postcode":"85008",
    "addr:street":"N 40Th St",
    "iso:country":"US",
    "sg:address":"1638 N 40th St",
    "sg:city":"Phoenix",
    "sg:classifiers":[
        {
            "category":"Retail",
            "subcategory":"Laundry & Dry Cleaning",
            "type":"Services"
        }
    ],
    "sg:phone":"+1 602 275 5273",
    "sg:postcode":"85008",
    "sg:province":"AZ",
    "sg:tags":[
        "cleaner"
    ],
    "wof:name":"Alpine Cleaners",
    "wof:placetype":"venue"
},
  "geometry": {"coordinates":[-111.995598,33.466333],"type":"Point"}
}