{
  "type": "Feature",
  "properties": {
    "addr:full":"280 W Oak St Huachuca City AZ 85616",
    "addr:housenumber":"280",
    "addr:postcode":"85616",
    "addr:street":"W Oak St",
    "iso:country":"US",
    "sg:address":"280 W Oak St",
    "sg:city":"Huachuca City",
    "sg:classifiers":[
        {
            "category":"Retail",
            "subcategory":"Auto Repair",
            "type":"Services"
        }
    ],
    "sg:phone":"+1 520 456 0455",
    "sg:postcode":"85616",
    "sg:province":"AZ",
    "sg:tags":[
        "wrecker"
    ],
    "wof:name":"Whetstone Towing",
    "wof:placetype":"venue"
},
  "geometry": {"coordinates":[-110.35561800000001,31.686804],"type":"Point"}
}