{
  "type": "Feature",
  "properties": {
    "iso:country":"US",
    "sg:address":"17230 N 20th St",
    "sg:city":"Phoenix",
    "sg:classifiers":[
        {
            "category":"Building & Trades",
            "subcategory":"Landscaping Services",
            "type":"Services"
        }
    ],
    "sg:phone":"+1 602 942 0421",
    "sg:postcode":"85022",
    "sg:province":"AZ",
    "sg:tags":[
        "tree"
    ],
    "sg:website":"http://www.tidytreetrimming.com",
    "wof:name":"Tidy Tree Trimming",
    "wof:placetype":"venue"
},
  "geometry": {"coordinates":[-112.039517,33.641886],"type":"Point"}
}