{
  "type": "Feature",
  "properties": {
    "iso:country":"US",
    "sg:address":"2561 E Fort Lowell Rd",
    "sg:city":"Tucson",
    "sg:classifiers":[
        {
            "category":"Professional",
            "subcategory":"Accounting & Tax Preparation",
            "type":"Services"
        }
    ],
    "sg:phone":"+1 520 885 1040",
    "sg:postcode":"85716",
    "sg:province":"AZ",
    "sg:tags":[
        "accountant"
    ],
    "wof:name":"Accounting & Tax Svc",
    "wof:placetype":"venue"
},
  "geometry": {"coordinates":[-110.933455,32.264996],"type":"Point"}
}