{
  "type": "Feature",
  "properties": {
    "addr:full":"11425 N Dysart Rd El Mirage AZ 85335",
    "addr:housenumber":"11425",
    "addr:postcode":"85335",
    "addr:street":"N Dysart Rd",
    "iso:country":"US",
    "sg:address":"11425 N Dysart Rd",
    "sg:city":"El Mirage",
    "sg:classifiers":[
        {
            "category":"Education",
            "subcategory":"School",
            "type":"Public Place"
        }
    ],
    "sg:phone":"+1 623 876 7500",
    "sg:postcode":"85335",
    "sg:province":"AZ",
    "sg:website":"www.dysart.org",
    "wof:name":"Dysart High School",
    "wof:placetype":"venue"
},
  "geometry": {"coordinates":[-112.341796,33.592625],"type":"Point"}
}