{
  "type": "Feature",
  "properties": {
    "iso:country":"US",
    "sg:address":"4330 N Campbell Ave",
    "sg:city":"Tucson",
    "sg:classifiers":[
        {
            "category":"Real Estate",
            "subcategory":"Architect",
            "type":"Services"
        }
    ],
    "sg:phone":"+1 520 408 1044",
    "sg:postcode":"85718",
    "sg:province":"AZ",
    "wof:name":"Welman Sperides Mickelberg",
    "wof:placetype":"venue"
},
  "geometry": {"coordinates":[-110.943735,32.284348],"type":"Point"}
}