{
  "type": "Feature",
  "properties": {
    "addr:full":"960 W Elliot Rd Tempe AZ 85284",
    "addr:housenumber":"960",
    "addr:postcode":"85284",
    "addr:street":"W Elliot Rd",
    "iso:country":"US",
    "sg:address":"960 W Elliot Rd",
    "sg:city":"Tempe",
    "sg:classifiers":[
        {
            "category":"Banks & Credit Unions",
            "subcategory":"Bank",
            "type":"Services"
        }
    ],
    "sg:phone":"+1 480 222 2920",
    "sg:postcode":"85284",
    "sg:province":"AZ",
    "sg:tags":[
        "loan"
    ],
    "wof:name":"Finansure Student Loans",
    "wof:placetype":"venue"
},
  "geometry": {"coordinates":[-111.951247,33.349251],"type":"Point"}
}