{
  "type": "Feature",
  "properties": {
    "iso:country":"US",
    "sg:address":"4380 N Miller Rd",
    "sg:city":"Scottsdale",
    "sg:classifiers":[
        {
            "category":"Shopping",
            "subcategory":"Pharmacy",
            "type":"Retail Goods"
        }
    ],
    "sg:phone":"+1 480 941 0194",
    "sg:postcode":"85251",
    "sg:province":"AZ",
    "wof:name":"Sav-On Drugs",
    "wof:placetype":"venue"
},
  "geometry": {"coordinates":[-111.917553,33.498759],"type":"Point"}
}