{
  "type": "Feature",
  "properties": {
    "addr:full":"26541 N 56th Ln Phoenix AZ 85083",
    "addr:housenumber":"26541",
    "addr:postcode":"85083",
    "addr:street":"N 56Th Ln",
    "iso:country":"US",
    "sg:address":"26541 N 56th Ln",
    "sg:city":"Phoenix",
    "sg:classifiers":[
        {
            "category":"Utilities",
            "subcategory":"Telephone",
            "type":"Services"
        }
    ],
    "sg:phone":"+1 623 256 6314",
    "sg:postcode":"85083",
    "sg:province":"AZ",
    "sg:tags":[
        "communication"
    ],
    "wof:name":"Worldwide Telecom Concepts",
    "wof:placetype":"venue"
},
  "geometry": {"coordinates":[-112.181679,33.724455],"type":"Point"}
}