{
  "type": "Feature",
  "properties": {
    "iso:country":"US",
    "sg:address":"1211 W Marlboro Dr",
    "sg:city":"Chandler",
    "sg:classifiers":[
        {
            "category":"Professional",
            "subcategory":"Art Services",
            "type":"Services"
        }
    ],
    "sg:phone":"+1 480 899 2912",
    "sg:postcode":"85224",
    "sg:province":"AZ",
    "sg:tags":[
        "interior",
        "designer",
        "decorator"
    ],
    "wof:name":"Yolanda Rivera Interior",
    "wof:placetype":"venue"
},
  "geometry": {"coordinates":[-111.86263,33.3484],"type":"Point"}
}