{
  "type": "Feature",
  "properties": {
    "addr:full":"196 W Simpson St Tucson AZ 85701",
    "addr:housenumber":"196",
    "addr:postcode":"85701",
    "addr:street":"W Simpson St",
    "iso:country":"US",
    "sg:address":"196 W Simpson St",
    "sg:city":"Tucson",
    "sg:classifiers":[
        {
            "category":"Real Estate",
            "subcategory":"Architect",
            "type":"Services"
        }
    ],
    "sg:phone":"+1 520 882 0488",
    "sg:postcode":"85701",
    "sg:province":"AZ",
    "wof:name":"Arquitectura Limited",
    "wof:placetype":"venue"
},
  "geometry": {"coordinates":[-110.972036,32.215907],"type":"Point"}
}