{
  "type": "Feature",
  "properties": {
    "iso:country":"US",
    "sg:address":"4710 E Thunderbird Rd",
    "sg:city":"Phoenix",
    "sg:classifiers":[
        {
            "category":"Shopping",
            "type":"Retail Goods"
        }
    ],
    "sg:phone":"+1 602 494 9000",
    "sg:postcode":"85032",
    "sg:province":"AZ",
    "sg:tags":[
        "picture",
        "frame",
        "framing"
    ],
    "sg:website":"www.hallofframes.com",
    "wof:name":"Paradise Picture Frame",
    "wof:placetype":"venue"
},
  "geometry": {"coordinates":[-111.97957599999999,33.611574],"type":"Point"}
}