{
  "type": "Feature",
  "properties": {
    "addr:full":"9970 W Beardsley Rd Peoria AZ 85382",
    "addr:housenumber":"9970",
    "addr:postcode":"85382",
    "addr:street":"W Beardsley Rd",
    "iso:country":"US",
    "sg:address":"9970 W Beardsley Rd",
    "sg:city":"Peoria",
    "sg:classifiers":[
        {
            "category":"Education",
            "subcategory":"School",
            "type":"Public Place"
        }
    ],
    "sg:phone":"+1 623 412 5400",
    "sg:postcode":"85382",
    "sg:province":"AZ",
    "wof:name":"Parkridge Elementary School",
    "wof:placetype":"venue"
},
  "geometry": {"coordinates":[-112.272047,33.667262],"type":"Point"}
}