{
  "type": "Feature",
  "properties": {
    "iso:country":"US",
    "sg:address":"5314 W Encanto Blvd",
    "sg:city":"Phoenix",
    "sg:classifiers":[
        {
            "category":"Professional",
            "subcategory":"Art Services",
            "type":"Services"
        }
    ],
    "sg:phone":"+1 602 547 2561",
    "sg:postcode":"85035",
    "sg:province":"AZ",
    "sg:tags":[
        "designer",
        "display",
        "producer"
    ],
    "wof:name":"Angelo D' Design Studio",
    "wof:placetype":"venue"
},
  "geometry": {"coordinates":[-112.174133,33.473225],"type":"Point"}
}