{
  "type": "Feature",
  "properties": {
    "addr:full":"15035 N 74th St Scottsdale AZ 85260",
    "addr:housenumber":"15035",
    "addr:postcode":"85260",
    "addr:street":"N 74Th St",
    "iso:country":"US",
    "sg:address":"15035 N 74th St",
    "sg:city":"Scottsdale",
    "sg:classifiers":[
        {
            "category":"Wholesale",
            "subcategory":"Machinery & Supplies",
            "type":"Manufacturing & Wholesale Goods"
        }
    ],
    "sg:phone":"+1 480 951 5800",
    "sg:postcode":"85260",
    "sg:province":"AZ",
    "sg:tags":[
        "aircraft",
        "parts",
        "commercial"
    ],
    "sg:website":"www.gh-aerospace.com",
    "wof:name":"G & H Aerospace Inc",
    "wof:placetype":"venue"
},
  "geometry": {"coordinates":[-111.91995799999999,33.62307],"type":"Point"}
}