{
  "type": "Feature",
  "properties": {
    "iso:country":"US",
    "sg:address":"507 E Florence Blvd",
    "sg:city":"Casa Grande",
    "sg:classifiers":[
        {
            "category":"Shopping",
            "subcategory":"Used Merchandise",
            "type":"Retail Goods"
        }
    ],
    "sg:phone":"+1 520 836 3659",
    "sg:postcode":"85222",
    "sg:province":"AZ",
    "sg:tags":[
        "business"
    ],
    "wof:name":"Little Brrel Antq Collectables",
    "wof:placetype":"venue"
},
  "geometry": {"coordinates":[-111.748154,32.879528],"type":"Point"}
}