{
  "type": "Feature",
  "properties": {
    "iso:country":"US",
    "sg:address":"1292 W 5th St",
    "sg:city":"Yuma",
    "sg:classifiers":[
        {
            "category":"Manufacturing",
            "subcategory":"Printing",
            "type":"Manufacturing & Wholesale Goods"
        }
    ],
    "sg:phone":"+1 928 783 3300",
    "sg:postcode":"85364",
    "sg:province":"AZ",
    "sg:tags":[
        "newspaper",
        "news"
    ],
    "wof:name":"Yuma Advantage The",
    "wof:placetype":"venue"
},
  "geometry": {"coordinates":[-114.63579900000001,32.717967],"type":"Point"}
}