{
  "type": "Feature",
  "properties": {
    "iso:country":"US",
    "sg:address":"2390 W Wetmore Rd",
    "sg:city":"Tucson",
    "sg:classifiers":[
        {
            "category":"Education",
            "subcategory":"School",
            "type":"Public Place"
        }
    ],
    "sg:phone":"+1 520 696 8870",
    "sg:postcode":"85705",
    "sg:province":"AZ",
    "wof:name":"Flowing Wells School District 8 (Unified)",
    "wof:placetype":"venue"
},
  "geometry": {"coordinates":[-111.018275,32.287028],"type":"Point"}
}