{
  "type": "Feature",
  "properties": {
    "iso:country":"US",
    "sg:address":"1625 N 52nd St",
    "sg:city":"Phoenix",
    "sg:classifiers":[
        {
            "category":"Travel",
            "subcategory":"Hotels & Motels",
            "type":"Entertainment"
        }
    ],
    "sg:phone":"+1 480 446 9500",
    "sg:postcode":"85008",
    "sg:province":"AZ",
    "sg:tags":[
        "lodging"
    ],
    "wof:name":"Comfort Suites Airport Phoenix",
    "wof:placetype":"venue"
},
  "geometry": {"coordinates":[-111.969742,33.465866],"type":"Point"}
}