{
  "type": "Feature",
  "properties": {
    "iso:country":"US",
    "sg:address":"2662 S Beverly Ln",
    "sg:city":"Yuma",
    "sg:classifiers":[
        {
            "category":"Banks & Credit Unions",
            "subcategory":"Investment Brokerage",
            "type":"Services"
        }
    ],
    "sg:phone":"+1 928 344 0221",
    "sg:postcode":"85365",
    "sg:province":"AZ",
    "sg:tags":[
        "advisory"
    ],
    "wof:name":"J&M Ent",
    "wof:placetype":"venue"
},
  "geometry": {"coordinates":[-114.613201,32.679218],"type":"Point"}
}