{
  "type": "Feature",
  "properties": {
    "iso:country":"US",
    "sg:address":"1430 E Missouri Ave # 265",
    "sg:city":"Phoenix",
    "sg:classifiers":[
        {
            "category":"Professional",
            "subcategory":"Management & Consulting",
            "type":"Services"
        },
        {
            "category":"Banks & Credit Unions",
            "subcategory":"Investment Brokerage",
            "type":"Services"
        },
        {
            "category":"Banks & Credit Unions",
            "subcategory":"Financial Services",
            "type":"Services"
        }
    ],
    "sg:phone":"+1 602 230 9545",
    "sg:postcode":"85014",
    "sg:province":"AZ",
    "sg:tags":[
        "planning",
        "advisory",
        "financing",
        "planner",
        "consultant"
    ],
    "wof:name":"G Mchaelis Inc",
    "wof:placetype":"venue"
},
  "geometry": {"coordinates":[-112.051107,33.516472],"type":"Point"}
}