{
  "type": "Feature",
  "properties": {
    "addr:full":"14521 N 115th Ave El Mirage AZ 85335",
    "addr:housenumber":"14521",
    "addr:postcode":"85335",
    "addr:street":"N 115Th Ave",
    "iso:country":"US",
    "sg:address":"14521 N 115th Ave",
    "sg:city":"El Mirage",
    "sg:classifiers":[
        {
            "category":"Building & Trades",
            "subcategory":"Construction",
            "type":"Services"
        }
    ],
    "sg:phone":"+1 623 875 1201",
    "sg:postcode":"85335",
    "sg:province":"AZ",
    "sg:tags":[
        "general",
        "contractor"
    ],
    "wof:name":"Bunney's Inc",
    "wof:placetype":"venue"
},
  "geometry": {"coordinates":[-112.30753,33.617571],"type":"Point"}
}