{
  "type": "Feature",
  "properties": {
    "iso:country":"US",
    "sg:address":"14300 N Northsight Blvd",
    "sg:city":"Scottsdale",
    "sg:classifiers":[
        {
            "category":"Professional",
            "type":"Services"
        }
    ],
    "sg:phone":"+1 480 991 5124",
    "sg:postcode":"85260",
    "sg:province":"AZ",
    "sg:tags":[
        "establishment"
    ],
    "wof:name":"Jamesleodba",
    "wof:placetype":"venue"
},
  "geometry": {"coordinates":[-111.897852,33.614886],"type":"Point"}
}