{
  "type": "Feature",
  "properties": {
    "iso:country":"US",
    "sg:address":"5450 S Country Club Rd",
    "sg:city":"Tucson",
    "sg:classifiers":[
        {
            "category":"Freight",
            "type":"Transportation"
        }
    ],
    "sg:phone":"+1 520 741 2221",
    "sg:postcode":"85706",
    "sg:province":"AZ",
    "sg:tags":[
        "commercial",
        "storage"
    ],
    "wof:name":"A Atlas Discount Storage",
    "wof:placetype":"venue"
},
  "geometry": {"coordinates":[-110.926355,32.153223],"type":"Point"}
}