{
  "type": "Feature",
  "properties": {
    "iso:country":"US",
    "sg:address":"13342 W Lisbon Ln",
    "sg:city":"Surprise",
    "sg:classifiers":[
        {
            "category":"Shopping",
            "subcategory":"Gifts & Souvenirs",
            "type":"Retail Goods"
        }
    ],
    "sg:phone":"+1 623 544 4037",
    "sg:postcode":"85379",
    "sg:province":"AZ",
    "sg:tags":[
        "collectible"
    ],
    "wof:name":"E Sanchez",
    "wof:placetype":"venue"
},
  "geometry": {"coordinates":[-112.348283,33.616927],"type":"Point"}
}