{
  "type": "Feature",
  "properties": {
    "iso:country":"US",
    "sg:address":"4542 E Forest Pleasant Pl",
    "sg:city":"Cave Creek",
    "sg:classifiers":[
        {
            "category":"Building & Trades",
            "subcategory":"Electrical",
            "type":"Services"
        }
    ],
    "sg:phone":"+1 480 437 1300",
    "sg:postcode":"85331",
    "sg:province":"AZ",
    "sg:tags":[
        "electrician",
        "contractor"
    ],
    "wof:name":"Electrend Electric Constructors",
    "wof:placetype":"venue"
},
  "geometry": {"coordinates":[-111.98400100000001,33.773701],"type":"Point"}
}