{
  "type": "Feature",
  "properties": {
    "iso:country":"US",
    "sg:address":"2201 N Cam Principal",
    "sg:city":"Tucson",
    "sg:classifiers":[
        {
            "category":"Real Estate",
            "subcategory":"Real Estate Agent",
            "type":"Services"
        }
    ],
    "sg:phone":"+1 520 795 6915",
    "sg:postcode":"85715",
    "sg:province":"AZ",
    "wof:name":"Persellin & Son Realtors",
    "wof:placetype":"venue"
},
  "geometry": {"coordinates":[-110.84733300000001,32.249498],"type":"Point"}
}