{
  "type": "Feature",
  "properties": {
    "addr:full":"4111 N 36th St Phoenix AZ 85018",
    "addr:housenumber":"4111",
    "addr:postcode":"85018",
    "addr:street":"N 36Th St",
    "iso:country":"US",
    "sg:address":"4111 N 36th St",
    "sg:city":"Phoenix",
    "sg:phone":"+1 602 955 5980",
    "sg:postcode":"85018",
    "sg:province":"AZ",
    "wof:name":"Blue Cross Veterinary Clinic",
    "wof:placetype":"venue"
},
  "geometry": {"coordinates":[-112.004214,33.495597],"type":"Point"}
}