{
  "type": "Feature",
  "properties": {
    "addr:full":"7239 W Brown St Peoria AZ 85345",
    "addr:housenumber":"7239",
    "addr:postcode":"85345",
    "addr:street":"W Brown St",
    "iso:country":"US",
    "sg:address":"7239 W Brown St",
    "sg:city":"Peoria",
    "sg:classifiers":[
        {
            "category":"Building & Trades",
            "subcategory":"Construction",
            "type":"Services"
        }
    ],
    "sg:phone":"+1 602 410 5073",
    "sg:postcode":"85345",
    "sg:province":"AZ",
    "sg:tags":[
        "dry wall",
        "contractor"
    ],
    "wof:name":"Affinity Drywall",
    "wof:placetype":"venue"
},
  "geometry": {"coordinates":[-112.212788,33.577104],"type":"Point"}
}