{
  "type": "Feature",
  "properties": {
    "iso:country":"US",
    "sg:address":"2223 S 48th St Ste A",
    "sg:city":"Tempe",
    "sg:classifiers":[
        {
            "category":"Manufacturing",
            "subcategory":"Tools & Machinery",
            "type":"Manufacturing & Wholesale Goods"
        }
    ],
    "sg:phone":"+1 480 449 9276",
    "sg:postcode":"85282",
    "sg:province":"AZ",
    "sg:tags":[
        "equipment",
        "supplies-wholesale",
        "electric",
        "manufacturer"
    ],
    "wof:name":"Guardian Interlock-Arizona",
    "wof:placetype":"venue"
},
  "geometry": {"coordinates":[-111.978302,33.404364],"type":"Point"}
}