{
  "type": "Feature",
  "properties": {
    "iso:country":"US",
    "sg:address":"2401 W Phelps Rd Ste D",
    "sg:city":"Phoenix",
    "sg:classifiers":[
        {
            "category":"Health Services",
            "subcategory":"Hospital",
            "type":"Services"
        }
    ],
    "sg:phone":"+1 602 548 9307",
    "sg:postcode":"85023",
    "sg:province":"AZ",
    "sg:tags":[
        "equipment",
        "supply"
    ],
    "wof:name":"Canyon State Imaging Inc",
    "wof:placetype":"venue"
},
  "geometry": {"coordinates":[-112.109771,33.63714],"type":"Point"}
}