{
  "type": "Feature",
  "properties": {
    "addr:full":"1135 N McQueen Road Gilbert AZ 85233",
    "addr:housenumber":"1135",
    "addr:postcode":"85233",
    "addr:street":"N Mcqueen Road",
    "iso:country":"US",
    "sg:address":"1135 N McQueen Road",
    "sg:city":"Gilbert",
    "sg:classifiers":[
        {
            "category":"Building & Trades",
            "subcategory":"Plumbing",
            "type":"Services"
        }
    ],
    "sg:phone":"+1 480 503 3683",
    "sg:postcode":"85233",
    "sg:province":"AZ",
    "wof:name":"Kpm Plumbing",
    "wof:placetype":"venue"
},
  "geometry": {"coordinates":[-111.824499,33.370397],"type":"Point"}
}