{
  "type": "Feature",
  "properties": {
    "iso:country":"US",
    "sg:address":"7108 N 71st Dr",
    "sg:city":"Glendale",
    "sg:classifiers":[
        {
            "category":"Professional",
            "subcategory":"Computer Services",
            "type":"Services"
        }
    ],
    "sg:phone":"+1 602 451 9932",
    "sg:postcode":"85303",
    "sg:province":"AZ",
    "sg:tags":[
        "design",
        "system",
        "network"
    ],
    "wof:name":"Support Professionals",
    "wof:placetype":"venue"
},
  "geometry": {"coordinates":[-112.212357,33.538753],"type":"Point"}
}