{
  "type": "Feature",
  "properties": {
    "iso:country":"US",
    "sg:address":"4312 W Cactus Rd",
    "sg:city":"Glendale",
    "sg:classifiers":[
        {
            "category":"Shopping",
            "subcategory":"Gifts & Souvenirs",
            "type":"Retail Goods"
        }
    ],
    "sg:phone":"+1 602 547 9204",
    "sg:postcode":"85029",
    "sg:province":"AZ",
    "wof:name":"Jelaco",
    "wof:placetype":"venue"
},
  "geometry": {"coordinates":[-112.154034,33.596415],"type":"Point"}
}