{
  "type": "Feature",
  "properties": {
    "iso:country":"US",
    "sg:address":"7445 E Cll Convidado",
    "sg:city":"Tucson",
    "sg:classifiers":[
        {
            "category":"Real Estate",
            "subcategory":"Real Estate Operator",
            "type":"Services"
        }
    ],
    "sg:phone":"+1 520 731 3447",
    "sg:postcode":"85715",
    "sg:province":"AZ",
    "sg:tags":[
        "building",
        "nonresidential"
    ],
    "wof:name":"California Arizona Properties",
    "wof:placetype":"venue"
},
  "geometry": {"coordinates":[-110.833862,32.252328],"type":"Point"}
}