{
  "type": "Feature",
  "properties": {
    "iso:country":"US",
    "sg:address":"10717 W Montecito Ave",
    "sg:city":"Phoenix",
    "sg:classifiers":[
        {
            "category":"Professional",
            "subcategory":"Management & Consulting",
            "type":"Services"
        }
    ],
    "sg:phone":"+1 623 877 6335",
    "sg:postcode":"85037",
    "sg:province":"AZ",
    "sg:tags":[
        "promotion",
        "sales"
    ],
    "wof:name":"Coupons Direct",
    "wof:placetype":"venue"
},
  "geometry": {"coordinates":[-112.29163,33.497811],"type":"Point"}
}