{
  "type": "Feature",
  "properties": {
    "iso:country":"US",
    "sg:address":"21741 N Van Loo Dr",
    "sg:city":"Maricopa",
    "sg:classifiers":[
        {
            "category":"Health Services",
            "subcategory":"Nursing And Care Facility",
            "type":"Services"
        },
        {
            "category":"Health Services",
            "subcategory":"Health Practitioner",
            "type":"Services"
        }
    ],
    "sg:phone":"+1 602 466 2769",
    "sg:postcode":"85138",
    "sg:province":"AZ",
    "sg:tags":[
        "home",
        "eldercare-home"
    ],
    "wof:name":"Vidal Medical Office, P.L.C.",
    "wof:placetype":"venue"
},
  "geometry": {"coordinates":[-112.020721,33.077869],"type":"Point"}
}