{
  "type": "Feature",
  "properties": {
    "iso:country":"US",
    "sg:address":"6107 N 12th St Unit 10",
    "sg:city":"Phoenix",
    "sg:classifiers":[
        {
            "category":"Education",
            "subcategory":"Special Training",
            "type":"Public Place"
        }
    ],
    "sg:phone":"+1 602 274 7738",
    "sg:postcode":"85014",
    "sg:province":"AZ",
    "sg:website":"http://www.newsolutions-dyslexia.com",
    "wof:name":"New Solutions Dyslexia Correct",
    "wof:placetype":"venue"
},
  "geometry": {"coordinates":[-112.056236,33.525905],"type":"Point"}
}