{
  "type": "Feature",
  "properties": {
    "addr:full":"228 S Clark Dr Tempe AZ 85281",
    "addr:housenumber":"228",
    "addr:postcode":"85281",
    "addr:street":"S Clark Dr",
    "iso:country":"US",
    "sg:address":"228 S Clark Dr",
    "sg:city":"Tempe",
    "sg:classifiers":[
        {
            "category":"Building & Trades",
            "subcategory":"Construction",
            "type":"Services"
        },
        {
            "category":"Professional",
            "subcategory":"Computer Services",
            "type":"Services"
        }
    ],
    "sg:phone":"+1 480 968 1744",
    "sg:postcode":"85281",
    "sg:province":"AZ",
    "sg:tags":[
        "general",
        "datum",
        "for",
        "contractor"
    ],
    "sg:website":"www.rsft.com",
    "wof:name":"Rancho Santa Fe Technology",
    "wof:placetype":"venue"
},
  "geometry": {"coordinates":[-111.898805,33.426865],"type":"Point"}
}