{
  "type": "Feature",
  "properties": {
    "addr:full":"1018 W Navajo St Tucson AZ 85705",
    "addr:housenumber":"1018",
    "addr:postcode":"85705",
    "addr:street":"W Navajo St",
    "iso:country":"US",
    "sg:address":"1018 W Navajo St",
    "sg:city":"Tucson",
    "sg:classifiers":[
        {
            "category":"Wholesale",
            "subcategory":"Durable Goods & Equipment",
            "type":"Manufacturing & Wholesale Goods"
        }
    ],
    "sg:phone":"+1 520 293 2317",
    "sg:postcode":"85705",
    "sg:province":"AZ",
    "wof:name":"Pelphrey Productions Inc",
    "wof:placetype":"venue"
},
  "geometry": {"coordinates":[-110.98905999999999,32.265981],"type":"Point"}
}