{
  "type": "Feature",
  "properties": {
    "iso:country":"US",
    "sg:address":"102 N 56th St",
    "sg:city":"Phoenix",
    "sg:classifiers":[
        {
            "category":"Building & Trades",
            "subcategory":"Construction",
            "type":"Services"
        }
    ],
    "sg:phone":"+1 602 267 0111",
    "sg:postcode":"85034",
    "sg:province":"AZ",
    "sg:tags":[
        "painter"
    ],
    "wof:name":"DCW Inc",
    "wof:placetype":"venue"
},
  "geometry": {"coordinates":[-111.960961,33.445854],"type":"Point"}
}