{
  "type": "Feature",
  "properties": {
    "addr:full":"894 E Warner Rd Gilbert AZ 85296",
    "addr:housenumber":"894",
    "addr:postcode":"85296",
    "addr:street":"E Warner Rd",
    "iso:country":"US",
    "sg:address":"894 E Warner Rd",
    "sg:city":"Gilbert",
    "sg:classifiers":[
        {
            "category":"Shopping",
            "subcategory":"Tobacco",
            "type":"Retail Goods"
        }
    ],
    "sg:phone":"+1 480 539 4207",
    "sg:postcode":"85296",
    "sg:province":"AZ",
    "sg:tags":[
        "shop"
    ],
    "wof:name":"Angel Eyes Smoke Shop",
    "wof:placetype":"venue"
},
  "geometry": {"coordinates":[-111.770741,33.335677],"type":"Point"}
}