{
  "type": "Feature",
  "properties": {
    "iso:country":"US",
    "sg:address":"4888 W de la Canoa Dr",
    "sg:city":"Amado",
    "sg:classifiers":[
        {
            "category":"Organizations",
            "subcategory":"Non-profit Organization",
            "type":"Services"
        }
    ],
    "sg:phone":"+1 520 398 8342",
    "sg:postcode":"85645",
    "sg:province":"AZ",
    "sg:tags":[
        "disability"
    ],
    "wof:name":"Fresh Start Hndcpd Workers Inc",
    "wof:placetype":"venue"
},
  "geometry": {"coordinates":[-111.067401,31.73097],"type":"Point"}
}