{
  "type": "Feature",
  "properties": {
    "iso:country":"US",
    "sg:address":"2341 W Alta Vista Rd",
    "sg:city":"Phoenix",
    "sg:classifiers":[
        {
            "category":"Farming",
            "subcategory":"Farm",
            "type":"Manufacturing & Wholesale Goods"
        }
    ],
    "sg:phone":"+1 602 870 3646",
    "sg:postcode":"85041",
    "sg:province":"AZ",
    "wof:name":"Osborn Farms",
    "wof:placetype":"venue"
},
  "geometry": {"coordinates":[-112.108861,33.388169],"type":"Point"}
}