{
  "type": "Feature",
  "properties": {
    "iso:country":"US",
    "sg:address":"15845 E el Lago Dr",
    "sg:city":"Fountain Hills",
    "sg:classifiers":[
        {
            "category":"Building & Trades",
            "subcategory":"Construction",
            "type":"Services"
        }
    ],
    "sg:phone":"+1 480 837 9710",
    "sg:postcode":"85268",
    "sg:province":"AZ",
    "sg:tags":[
        "carpentry",
        "contractor"
    ],
    "wof:name":"Carpentry Connection Inc",
    "wof:placetype":"venue"
},
  "geometry": {"coordinates":[-111.735578,33.60615],"type":"Point"}
}