{
  "type": "Feature",
  "properties": {
    "iso:country":"US",
    "sg:address":"4151 W Bell Rd",
    "sg:city":"Phoenix",
    "sg:classifiers":[
        {
            "category":"Restaurant",
            "type":"Food & Drink"
        }
    ],
    "sg:menulink":"http://www.allmenus.com/az/phoenix/180220-jack-in-the-box/menu/",
    "sg:phone":"+1 602 843 5716",
    "sg:postcode":"85053",
    "sg:province":"AZ",
    "sg:tags":[
        "burger",
        "american"
    ],
    "wof:name":"Jack in the Box",
    "wof:placetype":"venue"
},
  "geometry": {"coordinates":[-112.148585,33.639073],"type":"Point"}
}