{
  "type": "Feature",
  "properties": {
    "addr:full":"2443 E Emerald Ave Mesa AZ 85204",
    "addr:housenumber":"2443",
    "addr:postcode":"85204",
    "addr:street":"E Emerald Ave",
    "iso:country":"US",
    "sg:address":"2443 E Emerald Ave",
    "sg:city":"Mesa",
    "sg:classifiers":[
        {
            "category":"Banks & Credit Unions",
            "subcategory":"Investment Brokerage",
            "type":"Services"
        }
    ],
    "sg:phone":"+1 480 892 6461",
    "sg:postcode":"85204",
    "sg:province":"AZ",
    "wof:name":"Groombridge Investments",
    "wof:placetype":"venue"
},
  "geometry": {"coordinates":[-111.77606,33.397174],"type":"Point"}
}