{
  "type": "Feature",
  "properties": {
    "iso:country":"US",
    "sg:address":"33 N Stone Ave",
    "sg:city":"Tucson",
    "sg:classifiers":[
        {
            "category":"Professional",
            "subcategory":"Lawyer & Legal Services",
            "type":"Services"
        }
    ],
    "sg:phone":"+1 520 791 0900",
    "sg:postcode":"85701",
    "sg:province":"AZ",
    "sg:tags":[
        "attorney"
    ],
    "wof:name":"Vingelli & Errico",
    "wof:placetype":"venue"
},
  "geometry": {"coordinates":[-110.971414,32.222512],"type":"Point"}
}