{
  "type": "Feature",
  "properties": {
    "addr:full":"4530 N 32nd St Phoenix AZ 85018",
    "addr:housenumber":"4530",
    "addr:postcode":"85018",
    "addr:street":"N 32Nd St",
    "iso:country":"US",
    "sg:address":"4530 N 32nd St",
    "sg:city":"Phoenix",
    "sg:classifiers":[
        {
            "category":"Health Services",
            "subcategory":"Doctor",
            "type":"Services"
        }
    ],
    "sg:phone":"+1 602 314 1258",
    "sg:postcode":"85018",
    "sg:province":"AZ",
    "sg:tags":[
        "physician",
        "family",
        "practice",
        "surgeons",
        "medicine",
        "surgeon"
    ],
    "sg:website":"www.camelbackwomenshealth.com",
    "wof:name":"Camelback Women's Health",
    "wof:placetype":"venue"
},
  "geometry": {"coordinates":[-112.01299,33.503333],"type":"Point"}
}