{
  "type": "Feature",
  "properties": {
    "iso:country":"US",
    "sg:address":"276 S Orange Ave",
    "sg:city":"Yuma",
    "sg:classifiers":[
        {
            "category":"Building & Trades",
            "subcategory":"Construction",
            "type":"Services"
        }
    ],
    "sg:phone":"+1 928 343 9927",
    "sg:postcode":"85364",
    "sg:province":"AZ",
    "sg:tags":[
        "warehouse",
        "for"
    ],
    "wof:name":"Sheriffs Office Warehouse",
    "wof:placetype":"venue"
},
  "geometry": {"coordinates":[-114.622494,32.719096],"type":"Point"}
}