{
  "type": "Feature",
  "properties": {
    "iso:country":"US",
    "sg:address":"1365 E Black Diamond Dr",
    "sg:city":"Gilbert",
    "sg:classifiers":[
        {
            "category":"Restaurant",
            "type":"Food & Drink"
        }
    ],
    "sg:phone":"+1 480 580 5773",
    "sg:postcode":"85296",
    "sg:province":"AZ",
    "sg:tags":[
        "eating"
    ],
    "wof:name":"Creative Elegance",
    "wof:placetype":"venue"
},
  "geometry": {"coordinates":[-111.75964399999999,33.328798],"type":"Point"}
}