{
  "type": "Feature",
  "properties": {
    "addr:full":"130 Pebble Dr Sedona AZ 86351",
    "addr:housenumber":"130",
    "addr:postcode":"86351",
    "addr:street":"Pebble Dr",
    "iso:country":"US",
    "sg:address":"130 Pebble Dr",
    "sg:city":"Sedona",
    "sg:classifiers":[
        {
            "category":"Professional",
            "type":"Services"
        }
    ],
    "sg:phone":"+1 928 284 1268",
    "sg:postcode":"86351",
    "sg:province":"AZ",
    "wof:name":"Fletcher Advisors Inc",
    "wof:placetype":"venue"
},
  "geometry": {"coordinates":[-111.750145,34.788937],"type":"Point"}
}