{
  "type": "Feature",
  "properties": {
    "iso:country":"US",
    "sg:address":"5154 E Adobe Rd",
    "sg:city":"Mesa",
    "sg:classifiers":[
        {
            "category":"Social Services",
            "subcategory":"Child Care",
            "type":"Services"
        }
    ],
    "sg:phone":"+1 480 830 6755",
    "sg:postcode":"85205",
    "sg:province":"AZ",
    "wof:name":"Childtime Learning Ctr",
    "wof:placetype":"venue"
},
  "geometry": {"coordinates":[-111.719334,33.430173],"type":"Point"}
}