{
  "type": "Feature",
  "properties": {
    "iso:country":"US",
    "sg:address":"3143 N 32nd St",
    "sg:city":"Phoenix",
    "sg:classifiers":[
        {
            "category":"Health Services",
            "subcategory":"Doctor",
            "type":"Services"
        }
    ],
    "sg:phone":"+1 602 381 1200",
    "sg:postcode":"85018",
    "sg:province":"AZ",
    "sg:tags":[
        "physician",
        "surgeon"
    ],
    "wof:name":"Biltmore Health Care",
    "wof:placetype":"venue"
},
  "geometry": {"coordinates":[-112.012845,33.483737],"type":"Point"}
}