{
  "type": "Feature",
  "properties": {
    "iso:country":"US",
    "sg:address":"9449 N 90th St",
    "sg:city":"Scottsdale",
    "sg:classifiers":[
        {
            "category":"Health Services",
            "subcategory":"Chiropractor",
            "type":"Services"
        }
    ],
    "sg:phone":"+1 602 863 9003",
    "sg:postcode":"85258",
    "sg:province":"AZ",
    "wof:name":"A-Alyesh Chiropractic Clinic",
    "wof:placetype":"venue"
},
  "geometry": {"coordinates":[-111.88707,33.570688],"type":"Point"}
}