{
  "type": "Feature",
  "properties": {
    "addr:full":"9449 N 90th St Scottsdale AZ 85258",
    "addr:housenumber":"9449",
    "addr:postcode":"85258",
    "addr:street":"N 90Th St",
    "iso:country":"US",
    "sg:address":"9449 N 90th St",
    "sg:city":"Scottsdale",
    "sg:classifiers":[
        {
            "category":"Health Services",
            "subcategory":"Chiropractor",
            "type":"Services"
        }
    ],
    "sg:phone":"+1 602 863 9003",
    "sg:postcode":"85258",
    "sg:province":"AZ",
    "wof:name":"A-Alyesh Chiropractic Clinic",
    "wof:placetype":"venue"
},
  "geometry": {"coordinates":[-111.88706999999999,33.570688],"type":"Point"}
}