{
  "type": "Feature",
  "properties": {
    "iso:country":"US",
    "sg:address":"10723 W Indian School Rd",
    "sg:city":"Phoenix",
    "sg:classifiers":[
        {
            "category":"Health Services",
            "subcategory":"Clinic",
            "type":"Services"
        },
        {
            "category":"Health Services",
            "subcategory":"Chiropractor",
            "type":"Services"
        }
    ],
    "sg:phone":"+1 623 848 6991",
    "sg:postcode":"85392",
    "sg:province":"AZ",
    "sg:tags":[
        "chiropractic"
    ],
    "sg:website":"http://www.naturallifecenter.com",
    "wof:name":"Natural Life Center",
    "wof:placetype":"venue"
},
  "geometry": {"coordinates":[-112.291353,33.493585],"type":"Point"}
}