{
  "type": "Feature",
  "properties": {
    "iso:country":"US",
    "sg:address":"2530 N 7th St",
    "sg:city":"Phoenix",
    "sg:classifiers":[
        {
            "category":"Manufacturing",
            "subcategory":"Printing",
            "type":"Manufacturing & Wholesale Goods"
        }
    ],
    "sg:phone":"+1 602 242 8633",
    "sg:postcode":"85006",
    "sg:province":"AZ",
    "sg:tags":[
        "printer"
    ],
    "sg:website":"www.businessink.net",
    "wof:name":"Business Ink",
    "wof:placetype":"venue"
},
  "geometry": {"coordinates":[-112.065166,33.476057],"type":"Point"}
}