{
  "type": "Feature",
  "properties": {
    "iso:country":"US",
    "sg:address":"3131 E Clarendon Ave",
    "sg:city":"Phoenix",
    "sg:classifiers":[
        {
            "category":"Manufacturing",
            "subcategory":"Buildings",
            "type":"Manufacturing & Wholesale Goods"
        },
        {
            "category":"Building & Trades",
            "subcategory":"Construction",
            "type":"Services"
        }
    ],
    "sg:phone":"+1 602 441 2680",
    "sg:postcode":"85016",
    "sg:province":"AZ",
    "sg:tags":[
        "home",
        "builder",
        "contractor"
    ],
    "wof:name":"Nobella Townhomes, Lp",
    "wof:placetype":"venue"
},
  "geometry": {"coordinates":[-112.014907,33.491523],"type":"Point"}
}