{
  "type": "Feature",
  "properties": {
    "iso:country":"US",
    "sg:address":"14862 N 90th Pl",
    "sg:city":"Scottsdale",
    "sg:classifiers":[
        {
            "category":"Shopping",
            "subcategory":"Computers & Home Electronics",
            "type":"Retail Goods"
        }
    ],
    "sg:phone":"+1 480 634 5821",
    "sg:postcode":"85260",
    "sg:province":"AZ",
    "sg:tags":[
        "software"
    ],
    "wof:name":"Krystalsky Software Inc",
    "wof:placetype":"venue"
},
  "geometry": {"coordinates":[-111.88649700000001,33.620843],"type":"Point"}
}