{
  "type": "Feature",
  "properties": {
    "iso:country":"US",
    "sg:address":"216 E Prince Rd",
    "sg:city":"Tucson",
    "sg:classifiers":[
        {
            "category":"Social Services",
            "subcategory":"Child Care",
            "type":"Services"
        }
    ],
    "sg:phone":"+1 520 888 1415",
    "sg:postcode":"85705",
    "sg:province":"AZ",
    "wof:name":"Kids Forever Learning Ctr",
    "wof:placetype":"venue"
},
  "geometry": {"coordinates":[-110.970553,32.271915],"type":"Point"}
}