{
  "type": "Feature",
  "properties": {
    "iso:country":"US",
    "sg:address":"9020 S Mcclintock Dr # 26",
    "sg:city":"Tempe",
    "sg:classifiers":[
        {
            "category":"Wholesale",
            "subcategory":"Non-durable Goods",
            "type":"Manufacturing & Wholesale Goods"
        },
        {
            "category":"Personal",
            "subcategory":"Beauty Salon",
            "type":"Services"
        },
        {
            "category":"Personal",
            "subcategory":"Barber",
            "type":"Services"
        }
    ],
    "sg:phone":"+1 480 777 7638",
    "sg:postcode":"85284",
    "sg:province":"AZ",
    "sg:tags":[
        "stylist",
        "supply",
        "hair",
        "equipment",
        "salons-equipment",
        "supplies-wholesale",
        "manufacturer"
    ],
    "wof:name":"Color Works Hair",
    "wof:placetype":"venue"
},
  "geometry": {"coordinates":[-111.911165,33.332374],"type":"Point"}
}