{
  "type": "Feature",
  "properties": {
    "addr:full":"5613 S 27th Pl Phoenix AZ 85040",
    "addr:housenumber":"5613",
    "addr:postcode":"85040",
    "addr:street":"S 27Th Pl",
    "iso:country":"US",
    "sg:address":"5613 S 27th Pl",
    "sg:city":"Phoenix",
    "sg:classifiers":[
        {
            "category":"Manufacturing",
            "subcategory":"Wood Products",
            "type":"Manufacturing & Wholesale Goods"
        }
    ],
    "sg:phone":"+1 602 276 2659",
    "sg:postcode":"85040",
    "sg:province":"AZ",
    "sg:tags":[
        "mfg",
        "furniture"
    ],
    "wof:name":"Axkhelm E-Z Lay Tile Racks",
    "wof:placetype":"venue"
},
  "geometry": {"coordinates":[-112.022454,33.393765],"type":"Point"}
}