{
  "type": "Feature",
  "properties": {
    "iso:country":"US",
    "sg:address":"4530 N 23rd Ave",
    "sg:city":"Phoenix",
    "sg:classifiers":[
        {
            "category":"Real Estate",
            "subcategory":"Real Estate Services",
            "type":"Services"
        },
        {
            "category":"Real Estate",
            "subcategory":"Real Estate Operator",
            "type":"Services"
        }
    ],
    "sg:phone":"+1 877 880 8242",
    "sg:postcode":"85015",
    "sg:province":"AZ",
    "sg:tags":[
        "apartment",
        "vacancy",
        "listing",
        "rental",
        "finder"
    ],
    "wof:name":"Sundowner",
    "wof:placetype":"venue"
},
  "geometry": {"coordinates":[-112.108383,33.503139],"type":"Point"}
}