{
  "type": "Feature",
  "properties": {
    "iso:country":"US",
    "sg:address":"1385 W Hwy 89A",
    "sg:city":"Sedona",
    "sg:classifiers":[
        {
            "category":"Professional",
            "type":"Services"
        }
    ],
    "sg:phone":"+1 928 203 9365",
    "sg:postcode":"86336",
    "sg:province":"AZ",
    "sg:tags":[
        "establishment"
    ],
    "wof:name":"Lemuria Calling",
    "wof:placetype":"venue"
},
  "geometry": {"coordinates":[-111.784735,34.862736],"type":"Point"}
}