{
  "type": "Feature",
  "properties": {
    "iso:country":"US",
    "sg:address":"1100 W Fresno St",
    "sg:city":"Tucson",
    "sg:classifiers":[
        {
            "category":"Government",
            "subcategory":"Office",
            "type":"Public Place"
        }
    ],
    "sg:phone":"+1 520 791 4356",
    "sg:postcode":"85745",
    "sg:province":"AZ",
    "sg:tags":[
        "village"
    ],
    "wof:name":"Tucson City Government Menlo",
    "wof:placetype":"venue"
},
  "geometry": {"coordinates":[-110.991586,32.224674],"type":"Point"}
}