{
  "type": "Feature",
  "properties": {
    "iso:country":"US",
    "sg:address":"1290 Meadowridge Rd",
    "sg:city":"Prescott",
    "sg:classifiers":[
        {
            "category":"Building & Trades",
            "subcategory":"Construction",
            "type":"Services"
        }
    ],
    "sg:phone":"+1 928 778 1849",
    "sg:postcode":"86305",
    "sg:province":"AZ",
    "sg:tags":[
        "general",
        "contractor"
    ],
    "wof:name":"P M Taylor Development",
    "wof:placetype":"venue"
},
  "geometry": {"coordinates":[-112.49332099999999,34.567057],"type":"Point"}
}