{
  "type": "Feature",
  "properties": {
    "addr:full":"624 W Yearling Rd Phoenix AZ 85085",
    "addr:housenumber":"624",
    "addr:postcode":"85085",
    "addr:street":"W Yearling Rd",
    "iso:country":"US",
    "sg:address":"624 W Yearling Rd",
    "sg:city":"Phoenix",
    "sg:classifiers":[
        {
            "category":"Industrial Area",
            "type":"Public Place"
        }
    ],
    "sg:phone":"+1 623 670 6522",
    "sg:postcode":"85085",
    "sg:province":"AZ",
    "sg:tags":[
        "floors-industrial"
    ],
    "wof:name":"Elite Specialty Coatings",
    "wof:placetype":"venue"
},
  "geometry": {"coordinates":[-112.07941,33.720262],"type":"Point"}
}