{
  "type": "Feature",
  "properties": {
    "iso:country":"US",
    "sg:address":"10414 N 19th Ave",
    "sg:city":"Phoenix",
    "sg:classifiers":[
        {
            "category":"Bakery",
            "type":"Food & Drink"
        }
    ],
    "sg:phone":"+1 602 997 5475",
    "sg:postcode":"85021",
    "sg:province":"AZ",
    "sg:website":"http://www.englishmuffin.com",
    "wof:name":"Oroweat Foods",
    "wof:placetype":"venue"
},
  "geometry": {"coordinates":[-112.099581,33.580617],"type":"Point"}
}