{
  "type": "Feature",
  "properties": {
    "iso:country":"US",
    "sg:address":"1207 W Palmer Ave",
    "sg:city":"Flagstaff",
    "sg:classifiers":[
        {
            "category":"Freight",
            "type":"Transportation"
        }
    ],
    "sg:phone":"+1 928 779 1046",
    "sg:postcode":"86001",
    "sg:province":"AZ",
    "wof:name":"T&R Transport Inc",
    "wof:placetype":"venue"
},
  "geometry": {"coordinates":[-111.680252,35.163189],"type":"Point"}
}