{
  "type": "Feature",
  "properties": {
    "addr:full":"4804 W Caron St Glendale AZ 85302",
    "addr:housenumber":"4804",
    "addr:postcode":"85302",
    "addr:street":"W Caron St",
    "iso:country":"US",
    "sg:address":"4804 W Caron St",
    "sg:city":"Glendale",
    "sg:classifiers":[
        {
            "category":"Building & Trades",
            "subcategory":"Cleaning & Sanitation",
            "type":"Services"
        }
    ],
    "sg:phone":"+1 623 332 9665",
    "sg:postcode":"85302",
    "sg:province":"AZ",
    "sg:tags":[
        "janitor"
    ],
    "wof:name":"Just N Time Inc",
    "wof:placetype":"venue"
},
  "geometry": {"coordinates":[-112.163764,33.568062],"type":"Point"}
}