{
  "type": "Feature",
  "properties": {
    "iso:country":"US",
    "sg:address":"3221 E Washington St",
    "sg:city":"Phoenix",
    "sg:classifiers":[
        {
            "category":"Wholesale",
            "subcategory":"Non-durable Goods",
            "type":"Manufacturing & Wholesale Goods"
        }
    ],
    "sg:phone":"+1 602 230 9669",
    "sg:postcode":"85034",
    "sg:province":"AZ",
    "sg:tags":[
        "advertising"
    ],
    "wof:name":"Logo Logistics",
    "wof:placetype":"venue"
},
  "geometry": {"coordinates":[-112.011888,33.448102],"type":"Point"}
}