{
  "type": "Feature",
  "properties": {
    "iso:country":"US",
    "sg:address":"8831 E Apache Trl",
    "sg:city":"Mesa",
    "sg:classifiers":[
        {
            "category":"Education",
            "subcategory":"Dance Studio",
            "type":"Public Place"
        }
    ],
    "sg:phone":"+1 480 373 9000",
    "sg:postcode":"85207",
    "sg:province":"AZ",
    "sg:tags":[
        "instruction",
        "dancing"
    ],
    "wof:name":"Dance Express",
    "wof:placetype":"venue"
},
  "geometry": {"coordinates":[-111.637597,33.415057],"type":"Point"}
}