{
  "type": "Feature",
  "properties": {
    "iso:country":"US",
    "sg:address":"28626 N 46th Way",
    "sg:city":"Cave Creek",
    "sg:classifiers":[
        {
            "category":"Sports & Exercise",
            "subcategory":"Gym",
            "type":"Entertainment"
        }
    ],
    "sg:phone":"+1 480 515 9473",
    "sg:postcode":"85331",
    "sg:province":"AZ",
    "sg:tags":[
        "club",
        "health",
        "studio",
        "gymnasium"
    ],
    "wof:name":"Ladies Workout Express",
    "wof:placetype":"venue"
},
  "geometry": {"coordinates":[-111.97898499999999,33.746821],"type":"Point"}
}