{
  "type": "Feature",
  "properties": {
    "addr:full":"14201 N Hayden Rd Scottsdale AZ 85260",
    "addr:housenumber":"14201",
    "addr:postcode":"85260",
    "addr:street":"N Hayden Rd",
    "iso:country":"US",
    "sg:address":"14201 N Hayden Rd",
    "sg:city":"Scottsdale",
    "sg:classifiers":[
        {
            "category":"Shopping",
            "subcategory":"Gifts & Souvenirs",
            "type":"Retail Goods"
        },
        {
            "category":"Manufacturing",
            "subcategory":"Retail Goods",
            "type":"Manufacturing & Wholesale Goods"
        }
    ],
    "sg:phone":"+1 480 922 4304",
    "sg:postcode":"85260",
    "sg:province":"AZ",
    "sg:tags":[
        "shop",
        "giftware's-wholesale",
        "manufacturer"
    ],
    "wof:name":"Who International Design",
    "wof:placetype":"venue"
},
  "geometry": {"coordinates":[-111.90836299999999,33.613911],"type":"Point"}
}