{
  "type": "Feature",
  "properties": {
    "addr:full":"150 N 18th Ave Phoenix AZ 85007",
    "addr:housenumber":"150",
    "addr:postcode":"85007",
    "addr:street":"N 18Th Ave",
    "iso:country":"US",
    "sg:address":"150 N 18th Ave",
    "sg:city":"Phoenix",
    "sg:classifiers":[
        {
            "category":"Government",
            "subcategory":"Office",
            "type":"Public Place"
        }
    ],
    "sg:phone":"+1 602 364 3150",
    "sg:postcode":"85007",
    "sg:province":"AZ",
    "sg:tags":[
        "state",
        "resource"
    ],
    "wof:name":"Emergency Medical Svc",
    "wof:placetype":"venue"
},
  "geometry": {"coordinates":[-112.098277,33.449731],"type":"Point"}
}