{
  "type": "Feature",
  "properties": {
    "addr:full":"1177 N Woodburne Dr Chandler AZ 85224",
    "addr:housenumber":"1177",
    "addr:postcode":"85224",
    "addr:street":"N Woodburne Dr",
    "iso:country":"US",
    "sg:address":"1177 N Woodburne Dr",
    "sg:city":"Chandler",
    "sg:classifiers":[
        {
            "category":"Freight",
            "type":"Transportation"
        },
        {
            "category":"Retail",
            "subcategory":"Storage",
            "type":"Services"
        }
    ],
    "sg:phone":"+1 623 695 5457",
    "sg:postcode":"85224",
    "sg:province":"AZ",
    "sg:tags":[
        "cargo",
        "container"
    ],
    "wof:name":"Custom Air Cargo",
    "wof:placetype":"venue"
},
  "geometry": {"coordinates":[-111.885766,33.323031],"type":"Point"}
}