{
  "type": "Feature",
  "properties": {
    "addr:full":"1222 Hancock Rd Bullhead City AZ 86442",
    "addr:housenumber":"1222",
    "addr:postcode":"86442",
    "addr:street":"Hancock Rd",
    "iso:country":"US",
    "sg:address":"1222 Hancock Rd",
    "sg:city":"Bullhead City",
    "sg:classifiers":[
        {
            "category":"Government",
            "subcategory":"Court House",
            "type":"Public Place"
        }
    ],
    "sg:phone":"+1 928 758 0727",
    "sg:postcode":"86442",
    "sg:province":"AZ",
    "sg:tags":[
        "county",
        "counsel"
    ],
    "wof:name":"Mohave County Attorney",
    "wof:placetype":"venue"
},
  "geometry": {"coordinates":[-114.604939,35.107815],"type":"Point"}
}