{
  "type": "Feature",
  "properties": {
    "iso:country":"US",
    "sg:address":"1707 S Maple",
    "sg:city":"Mesa",
    "sg:classifiers":[
        {
            "category":"Building & Trades",
            "subcategory":"Landscaping Services",
            "type":"Services"
        }
    ],
    "sg:phone":"+1 480 332 0322",
    "sg:postcode":"85206",
    "sg:province":"AZ",
    "sg:tags":[
        "lawn"
    ],
    "wof:name":"Ashleys Landscaping",
    "wof:placetype":"venue"
},
  "geometry": {"coordinates":[-111.74786400000001,33.384375],"type":"Point"}
}