{
  "type": "Feature",
  "properties": {
    "iso:country":"US",
    "sg:address":"914 W Hatcher Rd",
    "sg:city":"Phoenix",
    "sg:classifiers":[
        {
            "category":"Professional",
            "type":"Services"
        }
    ],
    "sg:phone":"+1 602 749 1584",
    "sg:postcode":"85021",
    "sg:province":"AZ",
    "sg:tags":[
        "counselors-licensed"
    ],
    "wof:name":"Family Service Agency",
    "wof:placetype":"venue"
},
  "geometry": {"coordinates":[-112.085528,33.57122],"type":"Point"}
}