{
  "type": "Feature",
  "properties": {
    "iso:country":"US",
    "sg:address":"18768 N 89th Ln",
    "sg:city":"Peoria",
    "sg:classifiers":[
        {
            "category":"Arts & Performance",
            "subcategory":"Music",
            "type":"Entertainment"
        }
    ],
    "sg:phone":"+1 623 566 6007",
    "sg:postcode":"85382",
    "sg:province":"AZ",
    "sg:tags":[
        "musician"
    ],
    "wof:name":"Schackner Associated Musicians",
    "wof:placetype":"venue"
},
  "geometry": {"coordinates":[-112.25214800000001,33.654588],"type":"Point"}
}