{
  "type": "Feature",
  "properties": {
    "iso:country":"US",
    "sg:address":"4636 S 6th Ave",
    "sg:city":"Tucson",
    "sg:classifiers":[
        {
            "category":"Shopping",
            "subcategory":"Shoes",
            "type":"Retail Goods"
        }
    ],
    "sg:phone":"+1 520 622 2638",
    "sg:postcode":"85714",
    "sg:province":"AZ",
    "sg:tags":[
        "boot"
    ],
    "wof:name":"Osuna Boots & Shoe Repair",
    "wof:placetype":"venue"
},
  "geometry": {"coordinates":[-110.968238,32.165609],"type":"Point"}
}