{
  "type": "Feature",
  "properties": {
    "iso:country":"US",
    "sg:address":"620 E Roosevelt St",
    "sg:city":"Phoenix",
    "sg:classifiers":[
        {
            "category":"Restaurant",
            "type":"Food & Drink"
        },
        {
            "category":"Donuts",
            "subcategory":"None",
            "type":"Food & Drink"
        }
    ],
    "sg:phone":"+1 602 253 6277",
    "sg:postcode":"85004",
    "sg:province":"AZ",
    "sg:tags":[
        "shop"
    ],
    "wof:name":"Krispy Creme Doughnuts",
    "wof:placetype":"venue"
},
  "geometry": {"coordinates":[-112.06601000000001,33.458649],"type":"Point"}
}