{
  "type": "Feature",
  "properties": {
    "addr:full":"900 W Chandler Blvd Ste C Chandler AZ 85225",
    "addr:housenumber":"900",
    "addr:postcode":"85225",
    "addr:street":"W Chandler Blvd Ste C",
    "iso:country":"US",
    "sg:address":"900 W Chandler Blvd Ste C",
    "sg:city":"Chandler",
    "sg:classifiers":[
        {
            "category":"Health Services",
            "subcategory":"Doctor",
            "type":"Services"
        },
        {
            "category":"Health Services",
            "subcategory":"Clinic",
            "type":"Services"
        }
    ],
    "sg:phone":"+1 480 786 9000",
    "sg:postcode":"85225",
    "sg:province":"AZ",
    "sg:tags":[
        "psychological",
        "psychologist"
    ],
    "wof:name":"Robert B Roden",
    "wof:placetype":"venue"
},
  "geometry": {"coordinates":[-111.856903,33.30611],"type":"Point"}
}