{
  "type": "Feature",
  "properties": {
    "iso:country":"US",
    "sg:address":"2001 N 35th Ave",
    "sg:city":"Phoenix",
    "sg:classifiers":[
        {
            "category":"Autos & Motor Vehicles",
            "subcategory":"Auto Supplies",
            "type":"Retail Goods"
        }
    ],
    "sg:phone":"+1 602 353 0288",
    "sg:postcode":"85009",
    "sg:province":"AZ",
    "sg:tags":[
        "automobile",
        "stereo",
        "radio",
        "system"
    ],
    "wof:name":"Discount Audio",
    "wof:placetype":"venue"
},
  "geometry": {"coordinates":[-112.13445299999999,33.469429],"type":"Point"}
}