{
  "type": "Feature",
  "properties": {
    "iso:country":"US",
    "sg:address":"4116 W Orangewood Dr",
    "sg:city":"Tucson",
    "sg:classifiers":[
        {
            "category":"Building & Trades",
            "subcategory":"Electrical",
            "type":"Services"
        }
    ],
    "sg:phone":"+1 520 579 0467",
    "sg:postcode":"85741",
    "sg:province":"AZ",
    "sg:tags":[
        "general",
        "electrical",
        "contractor"
    ],
    "wof:name":"JR Electric Inc",
    "wof:placetype":"venue"
},
  "geometry": {"coordinates":[-111.054339,32.347101],"type":"Point"}
}