{
  "type": "Feature",
  "properties": {
    "addr:full":"1658 N el Camino Dr Tempe AZ 85281",
    "addr:housenumber":"1658",
    "addr:postcode":"85281",
    "addr:street":"N El Camino Dr",
    "iso:country":"US",
    "sg:address":"1658 N el Camino Dr",
    "sg:city":"Tempe",
    "sg:classifiers":[
        {
            "category":"Professional",
            "type":"Services"
        }
    ],
    "sg:phone":"+1 480 945 8474",
    "sg:postcode":"85281",
    "sg:province":"AZ",
    "wof:name":"Bodyknows",
    "wof:placetype":"venue"
},
  "geometry": {"coordinates":[-111.93374300000001,33.446312],"type":"Point"}
}