{
  "type": "Feature",
  "properties": {
    "iso:country":"US",
    "sg:address":"6444 E State Rte 69",
    "sg:city":"Prescott Valley",
    "sg:classifiers":[
        {
            "category":"Manufacturing",
            "subcategory":"Retail Goods",
            "type":"Manufacturing & Wholesale Goods"
        }
    ],
    "sg:phone":"+1 928 778 5521",
    "sg:postcode":"86314",
    "sg:province":"AZ",
    "sg:tags":[
        "marking",
        "mfg",
        "lithographic",
        "devices",
        "print",
        "fab"
    ],
    "wof:name":"Whiskey Row Screen Printing",
    "wof:placetype":"venue"
},
  "geometry": {"coordinates":[-112.352895,34.581139],"type":"Point"}
}