{
  "type": "Feature",
  "properties": {
    "addr:full":"2780 Chandler Blvd Chandler AZ 85224",
    "addr:housenumber":"2780",
    "addr:postcode":"85224",
    "addr:street":"Chandler Blvd",
    "iso:country":"US",
    "sg:address":"2780 Chandler Blvd",
    "sg:city":"Chandler",
    "sg:classifiers":[
        {
            "category":"Food & Beverages",
            "subcategory":"Bakery",
            "type":"Retail Goods"
        }
    ],
    "sg:phone":"+1 480 782 6453",
    "sg:postcode":"85224",
    "sg:province":"AZ",
    "sg:tags":[
        "sandwich"
    ],
    "sg:website":"www.jerseymikes.com/locations/de...",
    "wof:name":"Jersey Mike's Subs",
    "wof:placetype":"venue"
},
  "geometry": {"coordinates":[-111.891435,33.306413],"type":"Point"}
}