{
  "type": "Feature",
  "properties": {
    "iso:country":"US",
    "sg:address":"5799 E Hidden Springs Rd",
    "sg:city":"Cave Creek",
    "sg:classifiers":[
        {
            "category":"Professional",
            "subcategory":"Business Services",
            "type":"Services"
        }
    ],
    "sg:phone":"+1 480 595 9215",
    "sg:postcode":"85331",
    "sg:province":"AZ",
    "sg:tags":[
        "fixed",
        "motor",
        "freight",
        "facility"
    ],
    "wof:name":"Desert Dwllngs Insptn Svcs LLC",
    "wof:placetype":"venue"
},
  "geometry": {"coordinates":[-111.95666,33.863343],"type":"Point"}
}