{
  "type": "Feature",
  "properties": {
    "iso:country":"US",
    "sg:address":"411 N Central Ave",
    "sg:city":"Phoenix",
    "sg:classifiers":[
        {
            "category":"Parking",
            "type":"Transportation"
        }
    ],
    "sg:phone":"+1 602 254 8586",
    "sg:postcode":"85004",
    "sg:province":"AZ",
    "sg:tags":[
        "garage"
    ],
    "wof:name":"AMPCO System Parking",
    "wof:placetype":"venue"
},
  "geometry": {"coordinates":[-112.073738,33.453373],"type":"Point"}
}