{
  "type": "Feature",
  "properties": {
    "iso:country":"US",
    "sg:address":"16355 S Houghton Rd # 165",
    "sg:city":"Vail",
    "sg:classifiers":[
        {
            "category":"Personal",
            "subcategory":"Beauty Salon",
            "type":"Services"
        },
        {
            "category":"Personal",
            "subcategory":"Nail Salon",
            "type":"Services"
        }
    ],
    "sg:phone":"+1 520 762 5252",
    "sg:postcode":"85641",
    "sg:province":"AZ",
    "sg:tags":[
        "hair",
        "stylist"
    ],
    "wof:name":"Corona's Cut Above",
    "wof:placetype":"venue"
},
  "geometry": {"coordinates":[-110.77243,31.958873],"type":"Point"}
}