{
  "type": "Feature",
  "properties": {
    "iso:country":"US",
    "sg:address":"7424 E Desert Cove Ave",
    "sg:city":"Scottsdale",
    "sg:classifiers":[
        {
            "category":"Professional",
            "subcategory":"Business Services",
            "type":"Services"
        }
    ],
    "sg:phone":"+1 480 348 8981",
    "sg:postcode":"85260",
    "sg:province":"AZ",
    "sg:tags":[
        "paralegal"
    ],
    "wof:name":"L M Paralegal Svc Inc",
    "wof:placetype":"venue"
},
  "geometry": {"coordinates":[-111.920703,33.585224],"type":"Point"}
}