{
  "type": "Feature",
  "properties": {
    "iso:country":"US",
    "sg:address":"194 S Sonoran Heights Dr",
    "sg:city":"Tucson",
    "sg:classifiers":[
        {
            "category":"Professional",
            "subcategory":"Computer Services",
            "type":"Services"
        }
    ],
    "sg:phone":"+1 520 312 6590",
    "sg:postcode":"85748",
    "sg:province":"AZ",
    "sg:tags":[
        "repair"
    ],
    "wof:name":"24 Hour Computer Doc",
    "wof:placetype":"venue"
},
  "geometry": {"coordinates":[-110.77346,32.217444],"type":"Point"}
}