{
  "type": "Feature",
  "properties": {
    "iso:country":"US",
    "sg:address":"12471 S Frontage Rd",
    "sg:city":"Yuma",
    "sg:classifiers":[
        {
            "category":"Utilities",
            "subcategory":"Fuel Oil & Lpg",
            "type":"Services"
        }
    ],
    "sg:phone":"+1 928 342 5521",
    "sg:postcode":"85367",
    "sg:province":"AZ",
    "sg:tags":[
        "liquefied",
        "gas",
        "petroleum"
    ],
    "wof:name":"Heritage Propane",
    "wof:placetype":"venue"
},
  "geometry": {"coordinates":[-114.42196800000001,32.670085],"type":"Point"}
}