{
  "type": "Feature",
  "properties": {
    "iso:country":"US",
    "sg:address":"5028 S Ash Ave",
    "sg:city":"Tempe",
    "sg:classifiers":[
        {
            "category":"Restaurant",
            "type":"Food & Drink"
        }
    ],
    "sg:phone":"+1 480 776 0017",
    "sg:postcode":"85282",
    "sg:province":"AZ",
    "sg:tags":[
        "caterer"
    ],
    "wof:name":"Morrison Catering",
    "wof:placetype":"venue"
},
  "geometry": {"coordinates":[-111.94164600000001,33.379978],"type":"Point"}
}