{
  "type": "Feature",
  "properties": {
    "addr:full":"7373 E Doubletree Ranch Rd Scottsdale AZ 85258",
    "addr:housenumber":"7373",
    "addr:postcode":"85258",
    "addr:street":"E Doubletree Ranch Rd",
    "iso:country":"US",
    "sg:address":"7373 E Doubletree Ranch Rd",
    "sg:city":"Scottsdale",
    "sg:classifiers":[
        {
            "category":"Real Estate",
            "subcategory":"Developer",
            "type":"Services"
        },
        {
            "category":"Real Estate",
            "subcategory":"Real Estate Agent",
            "type":"Services"
        }
    ],
    "sg:phone":"+1 480 607 1494",
    "sg:postcode":"85258",
    "sg:province":"AZ",
    "sg:tags":[
        "company",
        "land",
        "investment"
    ],
    "wof:name":"Heylcorp",
    "wof:placetype":"venue"
},
  "geometry": {"coordinates":[-111.922754,33.567118],"type":"Point"}
}