{
  "type": "Feature",
  "properties": {
    "iso:country":"US",
    "sg:address":"2260 S 4th Ave",
    "sg:city":"Yuma",
    "sg:classifiers":[
        {
            "category":"Banks & Credit Unions",
            "subcategory":"Investment Brokerage",
            "type":"Services"
        }
    ],
    "sg:phone":"+1 928 783 6000",
    "sg:postcode":"85364",
    "sg:province":"AZ",
    "sg:tags":[
        "security"
    ],
    "wof:name":"Dean Witter",
    "wof:placetype":"venue"
},
  "geometry": {"coordinates":[-114.624711,32.686033],"type":"Point"}
}