{
  "type": "Feature",
  "properties": {
    "addr:full":"2729 S Alma School Rd Mesa AZ 85210",
    "addr:housenumber":"2729",
    "addr:postcode":"85210",
    "addr:street":"S Alma School Rd",
    "iso:country":"US",
    "sg:address":"2729 S Alma School Rd",
    "sg:city":"Mesa",
    "sg:classifiers":[
        {
            "category":"Food & Beverages",
            "subcategory":"Bakery",
            "type":"Retail Goods"
        }
    ],
    "sg:phone":"+1 480 838 0994",
    "sg:postcode":"85210",
    "sg:province":"AZ",
    "sg:tags":[
        "donut"
    ],
    "wof:name":"Dunkin Donuts",
    "wof:placetype":"venue"
},
  "geometry": {"coordinates":[-111.85900100000001,33.365601],"type":"Point"}
}