{
  "type": "Feature",
  "properties": {
    "iso:country":"US",
    "sg:address":"1225 Hancock Rd",
    "sg:city":"Bullhead City",
    "sg:classifiers":[
        {
            "category":"Building & Trades",
            "subcategory":"Cleaning & Sanitation",
            "type":"Services"
        }
    ],
    "sg:phone":"+1 928 763 4793",
    "sg:postcode":"86442",
    "sg:province":"AZ",
    "sg:tags":[
        "janitor"
    ],
    "wof:name":"Advanced Quality Janitorial",
    "wof:placetype":"venue"
},
  "geometry": {"coordinates":[-114.604845,35.107965],"type":"Point"}
}