{
  "type": "Feature",
  "properties": {
    "iso:country":"US",
    "sg:address":"3170 W el Camino del Cerro",
    "sg:city":"Tucson",
    "sg:classifiers":[
        {
            "category":"Utilities",
            "subcategory":"Fuel Oil & Lpg",
            "type":"Services"
        }
    ],
    "sg:phone":"+1 520 690 1880",
    "sg:postcode":"85745",
    "sg:province":"AZ",
    "sg:tags":[
        "liquefied",
        "gas",
        "petroleum"
    ],
    "wof:name":"Heritage Propane",
    "wof:placetype":"venue"
},
  "geometry": {"coordinates":[-111.035472,32.294298],"type":"Point"}
}