{
  "type": "Feature",
  "properties": {
    "iso:country":"US",
    "sg:address":"4748 E Sunrise Dr",
    "sg:city":"Tucson",
    "sg:classifiers":[
        {
            "category":"Shopping",
            "subcategory":"Pharmacy",
            "type":"Retail Goods"
        }
    ],
    "sg:phone":"+1 520 299 9195",
    "sg:postcode":"85718",
    "sg:province":"AZ",
    "wof:name":"Osco Drug",
    "wof:placetype":"venue"
},
  "geometry": {"coordinates":[-110.891113,32.3083],"type":"Point"}
}