{
  "type": "Feature",
  "properties": {
    "iso:country":"US",
    "sg:address":"11131 N 82nd Dr",
    "sg:city":"Peoria",
    "sg:classifiers":[
        {
            "category":"Manufacturing",
            "subcategory":"Tools & Machinery",
            "type":"Manufacturing & Wholesale Goods"
        }
    ],
    "sg:phone":"+1 623 878 9540",
    "sg:postcode":"85345",
    "sg:province":"AZ",
    "sg:tags":[
        "mfg"
    ],
    "wof:name":"Along The Woods",
    "wof:placetype":"venue"
},
  "geometry": {"coordinates":[-112.23627,33.585297],"type":"Point"}
}