{
  "type": "Feature",
  "properties": {
    "iso:country":"US",
    "sg:address":"5060 W Bethany Home Rd",
    "sg:city":"Glendale",
    "sg:classifiers":[
        {
            "category":"Bars & Pubs",
            "type":"Food & Drink"
        }
    ],
    "sg:phone":"+1 623 915 1396",
    "sg:postcode":"85301",
    "sg:province":"AZ",
    "wof:name":"Naked Truth Sports Bar Andgrll",
    "wof:placetype":"venue"
},
  "geometry": {"coordinates":[-112.167065,33.524025],"type":"Point"}
}