{
  "type": "Feature",
  "properties": {
    "iso:country":"US",
    "sg:address":"10464 E Penstamin Dr",
    "sg:city":"Scottsdale",
    "sg:classifiers":[
        {
            "category":"Banks & Credit Unions",
            "subcategory":"Financial Services",
            "type":"Services"
        }
    ],
    "sg:phone":"+1 480 563 8165",
    "sg:postcode":"85255",
    "sg:province":"AZ",
    "sg:tags":[
        "investor"
    ],
    "wof:name":"Azny Investments LLC",
    "wof:placetype":"venue"
},
  "geometry": {"coordinates":[-111.85450299999999,33.633339],"type":"Point"}
}