{
  "type": "Feature",
  "properties": {
    "iso:country":"US",
    "sg:address":"7530 W Bell Rd",
    "sg:city":"Glendale",
    "sg:classifiers":[
        {
            "category":"Shopping",
            "type":"Retail Goods"
        }
    ],
    "sg:phone":"+1 602 504 9200",
    "sg:postcode":"85308",
    "sg:province":"AZ",
    "sg:tags":[
        "spa",
        "hot",
        "tub"
    ],
    "wof:name":"Diamondback Spas",
    "wof:placetype":"venue"
},
  "geometry": {"coordinates":[-112.223902,33.638283],"type":"Point"}
}