{
  "type": "Feature",
  "properties": {
    "iso:country":"US",
    "sg:address":"2401 S 28th Dr",
    "sg:city":"Phoenix",
    "sg:classifiers":[
        {
            "category":"Professional",
            "subcategory":"Management & Consulting",
            "type":"Services"
        },
        {
            "category":"Professional",
            "subcategory":"Research",
            "type":"Services"
        },
        {
            "category":"Government",
            "subcategory":"Office",
            "type":"Public Place"
        }
    ],
    "sg:phone":"+1 602 506 1701",
    "sg:postcode":"85009",
    "sg:province":"AZ",
    "sg:tags":[
        "facility",
        "consultant",
        "space",
        "analysis",
        "planning",
        "economic",
        "government-county",
        "parish"
    ],
    "sg:website":"http://www.phxses.com",
    "wof:name":"Facilities Management",
    "wof:placetype":"venue"
},
  "geometry": {"coordinates":[-112.120148,33.425701],"type":"Point"}
}