{
  "type": "Feature",
  "properties": {
    "iso:country":"US",
    "sg:address":"4229 E Cortez St",
    "sg:city":"Phoenix",
    "sg:classifiers":[
        {
            "category":"Banks & Credit Unions",
            "subcategory":"Bank",
            "type":"Services"
        }
    ],
    "sg:phone":"+1 602 494 2978",
    "sg:postcode":"85028",
    "sg:province":"AZ",
    "sg:tags":[
        "personal",
        "institution"
    ],
    "wof:name":"Stephen Shenfield Financal Svc",
    "wof:placetype":"venue"
},
  "geometry": {"coordinates":[-111.990323,33.591859],"type":"Point"}
}