{
  "type": "Feature",
  "properties": {
    "iso:country":"US",
    "sg:address":"1532 W Northern Ave",
    "sg:city":"Phoenix",
    "sg:classifiers":[
        {
            "category":"Real Estate",
            "subcategory":"Real Estate Operator",
            "type":"Services"
        }
    ],
    "sg:phone":"+1 602 997 1301",
    "sg:postcode":"85021",
    "sg:province":"AZ",
    "sg:tags":[
        "property",
        "lessor",
        "closed",
        "investment"
    ],
    "wof:name":"DMS Investments",
    "wof:placetype":"venue"
},
  "geometry": {"coordinates":[-112.093069,33.553085],"type":"Point"}
}