{
  "type": "Feature",
  "properties": {
    "addr:full":"806 W Osborn Rd Phoenix AZ 85013",
    "addr:housenumber":"806",
    "addr:postcode":"85013",
    "addr:street":"W Osborn Rd",
    "iso:country":"US",
    "sg:address":"806 W Osborn Rd",
    "sg:city":"Phoenix",
    "sg:classifiers":[
        {
            "category":"Personal",
            "subcategory":"Beauty Salon",
            "type":"Services"
        }
    ],
    "sg:phone":"+1 602 265 0051",
    "sg:postcode":"85013",
    "sg:province":"AZ",
    "wof:name":"Country Club Beauty Salon",
    "wof:placetype":"venue"
},
  "geometry": {"coordinates":[-112.084067,33.487762],"type":"Point"}
}