{
  "type": "Feature",
  "properties": {
    "iso:country":"US",
    "sg:address":"2502 W Curtis Rd",
    "sg:city":"Tucson",
    "sg:classifiers":[
        {
            "category":"Building & Trades",
            "subcategory":"Construction",
            "type":"Services"
        }
    ],
    "sg:phone":"+1 520 408 0718",
    "sg:postcode":"85705",
    "sg:province":"AZ",
    "sg:tags":[
        "television",
        "telephone",
        "cable",
        "contractor"
    ],
    "wof:name":"Greenway Communications",
    "wof:placetype":"venue"
},
  "geometry": {"coordinates":[-111.022687,32.301568],"type":"Point"}
}