{
  "type": "Feature",
  "properties": {
    "iso:country":"US",
    "sg:address":"21038 S Gilbert Rd",
    "sg:city":"Chandler",
    "sg:classifiers":[
        {
            "category":"Farming",
            "subcategory":"Farm",
            "type":"Manufacturing & Wholesale Goods"
        }
    ],
    "sg:phone":"+1 480 802 5309",
    "sg:postcode":"85286",
    "sg:province":"AZ",
    "wof:name":"Freeman Farms",
    "wof:placetype":"venue"
},
  "geometry": {"coordinates":[-111.789498,33.25674],"type":"Point"}
}