{
  "type": "Feature",
  "properties": {
    "addr:full":"2423 W Dunlap Ave Ste 130 Phoenix AZ 85021",
    "addr:housenumber":"2423",
    "addr:postcode":"85021",
    "addr:street":"W Dunlap Ave Ste 130",
    "iso:country":"US",
    "sg:address":"2423 W Dunlap Ave Ste 130",
    "sg:city":"Phoenix",
    "sg:classifiers":[
        {
            "category":"Health Services",
            "subcategory":"Clinic",
            "type":"Services"
        }
    ],
    "sg:phone":"+1 602 944 0265",
    "sg:postcode":"85021",
    "sg:province":"AZ",
    "sg:tags":[
        "welfare"
    ],
    "wof:name":"John C Lincoln Family Medicine",
    "wof:placetype":"venue"
},
  "geometry": {"coordinates":[-112.110777,33.567539],"type":"Point"}
}