{
  "type": "Feature",
  "properties": {
    "iso:country":"US",
    "sg:address":"5125 N 16th St Ste A106",
    "sg:city":"Phoenix",
    "sg:classifiers":[
        {
            "category":"Communications",
            "subcategory":"Film & Video Production",
            "type":"Services"
        }
    ],
    "sg:phone":"+1 602 745 2400",
    "sg:postcode":"85016",
    "sg:province":"AZ",
    "sg:tags":[
        "tv",
        "radio",
        "services-commercial",
        "companies-film"
    ],
    "sg:website":"http://www.studio522.com",
    "wof:name":"Studio 522 Productions, Inc",
    "wof:placetype":"venue"
},
  "geometry": {"coordinates":[-112.047531,33.511469],"type":"Point"}
}