{
  "type": "Feature",
  "properties": {
    "iso:country":"US",
    "sg:address":"2535 E Linda Cir",
    "sg:city":"Phoenix",
    "sg:classifiers":[
        {
            "category":"Shopping",
            "type":"Retail Goods"
        }
    ],
    "sg:phone":"+1 602 569 1204",
    "sg:postcode":"85050",
    "sg:province":"AZ",
    "sg:tags":[
        "merchandise"
    ],
    "wof:name":"Johnson Alarm",
    "wof:placetype":"venue"
},
  "geometry": {"coordinates":[-112.02719,33.656895],"type":"Point"}
}