{
  "type": "Feature",
  "properties": {
    "iso:country":"US",
    "sg:address":"11434 S Pawnee Cir",
    "sg:city":"Phoenix",
    "sg:classifiers":[
        {
            "category":"Sports & Exercise",
            "subcategory":"Golf",
            "type":"Entertainment"
        }
    ],
    "sg:phone":"+1 480 893 2092",
    "sg:postcode":"85044",
    "sg:province":"AZ",
    "sg:tags":[
        "instruction"
    ],
    "sg:website":"http://www.peterlongogolfshow.com",
    "wof:name":"Peter Longo Golf Show",
    "wof:placetype":"venue"
},
  "geometry": {"coordinates":[-111.984308,33.343968],"type":"Point"}
}