{
  "type": "Feature",
  "properties": {
    "iso:country":"US",
    "sg:address":"4431 S White Mountain Rd",
    "sg:city":"Show Low",
    "sg:classifiers":[
        {
            "category":"Shopping",
            "subcategory":"Shoes",
            "type":"Retail Goods"
        }
    ],
    "sg:phone":"+1 928 537 8662",
    "sg:postcode":"85901",
    "sg:province":"AZ",
    "wof:name":"Payless Shoe Source",
    "wof:placetype":"venue"
},
  "geometry": {"coordinates":[-110.02565199999999,34.210877],"type":"Point"}
}