{
  "type": "Feature",
  "properties": {
    "iso:country":"US",
    "sg:address":"200 W Wigwam Blvd",
    "sg:city":"Litchfield Park",
    "sg:classifiers":[
        {
            "category":"Communications",
            "subcategory":"Newspaper",
            "type":"Services"
        }
    ],
    "sg:phone":"+1 623 535 8439",
    "sg:postcode":"85340",
    "sg:province":"AZ",
    "sg:tags":[
        "print",
        "medium"
    ],
    "wof:name":"West Valley View",
    "wof:placetype":"venue"
},
  "geometry": {"coordinates":[-112.360001,33.493599],"type":"Point"}
}