{
  "type": "Feature",
  "properties": {
    "iso:country":"US",
    "sg:address":"17861 S Placita de Plata",
    "sg:city":"Sahuarita",
    "sg:classifiers":[
        {
            "category":"Building & Trades",
            "subcategory":"Plumbing",
            "type":"Services"
        }
    ],
    "sg:phone":"+1 520 625 2135",
    "sg:postcode":"85629",
    "sg:province":"AZ",
    "sg:tags":[
        "plumber",
        "industrial",
        "contractors-commercial"
    ],
    "wof:name":"Madera Plumbing",
    "wof:placetype":"venue"
},
  "geometry": {"coordinates":[-110.992182,31.926444],"type":"Point"}
}