{
  "type": "Feature",
  "properties": {
    "iso:country":"US",
    "sg:address":"1340 W 3rd St",
    "sg:city":"Yuma",
    "sg:classifiers":[
        {
            "category":"Real Estate",
            "subcategory":"Real Estate Operator",
            "type":"Services"
        }
    ],
    "sg:phone":"+1 928 783 9431",
    "sg:postcode":"85364",
    "sg:province":"AZ",
    "sg:tags":[
        "mobile",
        "home",
        "camp",
        "site"
    ],
    "wof:name":"Northwind Properties",
    "wof:placetype":"venue"
},
  "geometry": {"coordinates":[-114.636304,32.721594],"type":"Point"}
}