{
  "type": "Feature",
  "properties": {
    "iso:country":"US",
    "sg:address":"325 Deer Pass Dr",
    "sg:city":"Sedona",
    "sg:classifiers":[
        {
            "category":"Professional",
            "type":"Services"
        },
        {
            "category":"Shopping",
            "subcategory":"Clothing, Apparel, & Fashions",
            "type":"Retail Goods"
        }
    ],
    "sg:phone":"+1 928 282 4377",
    "sg:postcode":"86351",
    "sg:province":"AZ",
    "sg:tags":[
        "establishment",
        "family"
    ],
    "wof:name":"Desert Dancer III",
    "wof:placetype":"venue"
},
  "geometry": {"coordinates":[-111.784516,34.777451],"type":"Point"}
}