{
  "type": "Feature",
  "properties": {
    "addr:full":"5621 N Oracle Rd Tucson AZ 85704",
    "addr:housenumber":"5621",
    "addr:postcode":"85704",
    "addr:street":"N Oracle Rd",
    "iso:country":"US",
    "sg:address":"5621 N Oracle Rd",
    "sg:city":"Tucson",
    "sg:classifiers":[
        {
            "category":"Home & Garden",
            "subcategory":"Furniture",
            "type":"Retail Goods"
        }
    ],
    "sg:phone":"+1 520 887 5621",
    "sg:postcode":"85704",
    "sg:province":"AZ",
    "sg:website":"www.ethanallen.com",
    "wof:name":"Ethan Allen Home Interiors",
    "wof:placetype":"venue"
},
  "geometry": {"coordinates":[-110.978695,32.3091],"type":"Point"}
}