{
  "type": "Feature",
  "properties": {
    "iso:country":"US",
    "sg:address":"2633 W Cypress St",
    "sg:city":"Phoenix",
    "sg:classifiers":[
        {
            "category":"Wholesale",
            "subcategory":"Groceries",
            "type":"Manufacturing & Wholesale Goods"
        },
        {
            "category":"Food & Beverages",
            "subcategory":"Supermarket",
            "type":"Retail Goods"
        },
        {
            "category":"Farming",
            "subcategory":"Farm",
            "type":"Manufacturing & Wholesale Goods"
        },
        {
            "category":"Food & Beverages",
            "subcategory":"Groceries & Convenience Stores",
            "type":"Retail Goods"
        }
    ],
    "sg:phone":"+1 602 272 1561",
    "sg:postcode":"85009",
    "sg:province":"AZ",
    "sg:tags":[
        "grocers-wholesale",
        "super"
    ],
    "wof:name":"M & L Distributing",
    "wof:placetype":"venue"
},
  "geometry": {"coordinates":[-112.113113,33.47171],"type":"Point"}
}