{
  "type": "Feature",
  "properties": {
    "addr:full":"231 E Paseo Way Tempe AZ 85283",
    "addr:housenumber":"231",
    "addr:postcode":"85283",
    "addr:street":"E Paseo Way",
    "iso:country":"US",
    "sg:address":"231 E Paseo Way",
    "sg:city":"Tempe",
    "sg:classifiers":[
        {
            "category":"Wholesale",
            "subcategory":"Construction Materials",
            "type":"Manufacturing & Wholesale Goods"
        }
    ],
    "sg:phone":"+1 480 820 8188",
    "sg:postcode":"85283",
    "sg:province":"AZ",
    "sg:tags":[
        "building"
    ],
    "wof:name":"W R S & Associates Inc",
    "wof:placetype":"venue"
},
  "geometry": {"coordinates":[-111.934181,33.363124],"type":"Point"}
}