{
  "type": "Feature",
  "properties": {
    "iso:country":"US",
    "sg:address":"4531 N 16th St",
    "sg:city":"Phoenix",
    "sg:classifiers":[
        {
            "category":"Insurance",
            "subcategory":"Insurance Agent",
            "type":"Services"
        }
    ],
    "sg:phone":"+1 602 277 1737",
    "sg:postcode":"85016",
    "sg:province":"AZ",
    "wof:name":"Frank Brabec Insurance",
    "wof:placetype":"venue"
},
  "geometry": {"coordinates":[-112.047479,33.503211],"type":"Point"}
}