{
  "type": "Feature",
  "properties": {
    "addr:full":"8635 E 3rd St Tucson AZ 85710",
    "addr:housenumber":"8635",
    "addr:postcode":"85710",
    "addr:street":"E 3Rd St",
    "iso:country":"US",
    "sg:address":"8635 E 3rd St",
    "sg:city":"Tucson",
    "sg:classifiers":[
        {
            "category":"Home & Garden",
            "subcategory":"Building Materials",
            "type":"Retail Goods"
        }
    ],
    "sg:phone":"+1 520 298 8085",
    "sg:postcode":"85710",
    "sg:province":"AZ",
    "wof:name":"Breit Electric",
    "wof:placetype":"venue"
},
  "geometry": {"coordinates":[-110.808834,32.231571],"type":"Point"}
}