{
  "type": "Feature",
  "properties": {
    "addr:full":"5282 W Dublin Ct Chandler AZ 85226",
    "addr:housenumber":"5282",
    "addr:postcode":"85226",
    "addr:street":"W Dublin Ct",
    "iso:country":"US",
    "sg:address":"5282 W Dublin Ct",
    "sg:city":"Chandler",
    "sg:classifiers":[
        {
            "category":"Banks & Credit Unions",
            "subcategory":"Investment Brokerage",
            "type":"Services"
        }
    ],
    "sg:phone":"+1 480 206 4615",
    "sg:postcode":"85226",
    "sg:province":"AZ",
    "sg:tags":[
        "advisory"
    ],
    "wof:name":"M2 Business Advisory Services",
    "wof:placetype":"venue"
},
  "geometry": {"coordinates":[-111.933988,33.318178],"type":"Point"}
}