{
  "type": "Feature",
  "properties": {
    "iso:country":"US",
    "sg:address":"15810 S 45th St Ste 105",
    "sg:city":"Phoenix",
    "sg:classifiers":[
        {
            "category":"Health Services",
            "subcategory":"Clinic",
            "type":"Services"
        },
        {
            "category":"Health Services",
            "subcategory":"Health Practitioner",
            "type":"Services"
        }
    ],
    "sg:phone":"+1 480 893 1321",
    "sg:postcode":"85048",
    "sg:province":"AZ",
    "sg:tags":[
        "therapist",
        "therapy",
        "physical"
    ],
    "wof:name":"Peak Physical Therapy",
    "wof:placetype":"venue"
},
  "geometry": {"coordinates":[-111.98683800000001,33.303801],"type":"Point"}
}