{
  "type": "Feature",
  "properties": {
    "addr:full":"1503 E Hackamore St Mesa AZ 85203",
    "addr:housenumber":"1503",
    "addr:postcode":"85203",
    "addr:street":"E Hackamore St",
    "iso:country":"US",
    "sg:address":"1503 E Hackamore St",
    "sg:city":"Mesa",
    "sg:classifiers":[
        {
            "category":"Professional",
            "type":"Services"
        }
    ],
    "sg:phone":"+1 480 807 9060",
    "sg:postcode":"85203",
    "sg:province":"AZ",
    "wof:name":"Jerry Dingman Inc",
    "wof:placetype":"venue"
},
  "geometry": {"coordinates":[-111.79943299999999,33.441117],"type":"Point"}
}