{
  "type": "Feature",
  "properties": {
    "iso:country":"US",
    "sg:address":"3202 E Greenway Rd",
    "sg:city":"Phoenix",
    "sg:classifiers":[
        {
            "category":"Wholesale",
            "subcategory":"Groceries",
            "type":"Manufacturing & Wholesale Goods"
        }
    ],
    "sg:phone":"+1 602 971 8010",
    "sg:postcode":"85032",
    "sg:province":"AZ",
    "sg:tags":[
        "bakery",
        "retail",
        "eating",
        "mfg"
    ],
    "wof:name":"Chompies Deli Restuarant Bak",
    "wof:placetype":"venue"
},
  "geometry": {"coordinates":[-112.009699,33.626398],"type":"Point"}
}