{
  "type": "Feature",
  "properties": {
    "addr:full":"11429 E Mark Ln Scottsdale AZ 85262",
    "addr:housenumber":"11429",
    "addr:postcode":"85262",
    "addr:street":"E Mark Ln",
    "iso:country":"US",
    "sg:address":"11429 E Mark Ln",
    "sg:city":"Scottsdale",
    "sg:classifiers":[
        {
            "category":"Real Estate",
            "subcategory":"Architect",
            "type":"Services"
        }
    ],
    "sg:phone":"+1 480 473 0277",
    "sg:postcode":"85262",
    "sg:province":"AZ",
    "sg:tags":[
        "course",
        "golf"
    ],
    "wof:name":"Bruce W Devlin Inc",
    "wof:placetype":"venue"
},
  "geometry": {"coordinates":[-111.83457799999999,33.742223],"type":"Point"}
}