{
  "type": "Feature",
  "properties": {
    "iso:country":"US",
    "sg:address":"11429 E Mark Ln",
    "sg:city":"Scottsdale",
    "sg:classifiers":[
        {
            "category":"Real Estate",
            "subcategory":"Architect",
            "type":"Services"
        }
    ],
    "sg:phone":"+1 480 473 0277",
    "sg:postcode":"85262",
    "sg:province":"AZ",
    "sg:tags":[
        "course",
        "golf"
    ],
    "wof:name":"Bruce W Devlin Inc",
    "wof:placetype":"venue"
},
  "geometry": {"coordinates":[-111.834578,33.742223],"type":"Point"}
}