{
  "type": "Feature",
  "properties": {
    "iso:country":"US",
    "sg:address":"32409 N Scottsdale Rd",
    "sg:city":"Scottsdale",
    "sg:classifiers":[
        {
            "category":"Fast Food",
            "type":"Food & Drink"
        },
        {
            "category":"Food & Beverages",
            "subcategory":"Meat & Fish",
            "type":"Retail Goods"
        }
    ],
    "sg:phone":"+1 480 575 8040",
    "sg:postcode":"85266",
    "sg:province":"AZ",
    "sg:tags":[
        "burger",
        "hot",
        "dog"
    ],
    "wof:name":"Blue Burger",
    "wof:placetype":"venue"
},
  "geometry": {"coordinates":[-111.925585,33.779952],"type":"Point"}
}