{
  "type": "Feature",
  "properties": {
    "iso:country":"US",
    "sg:address":"9204 N 7th St",
    "sg:city":"Phoenix",
    "sg:classifiers":[
        {
            "category":"Shopping",
            "subcategory":"Music",
            "type":"Retail Goods"
        }
    ],
    "sg:phone":"+1 602 997 0153",
    "sg:postcode":"85020",
    "sg:province":"AZ",
    "sg:tags":[
        "compact",
        "record",
        "disc",
        "tape"
    ],
    "wof:name":"Discoteca Barrio Latino",
    "wof:placetype":"venue"
},
  "geometry": {"coordinates":[-112.065286,33.570008],"type":"Point"}
}