{
  "type": "Feature",
  "properties": {
    "iso:country":"US",
    "sg:address":"113 W 2nd St",
    "sg:city":"Winslow",
    "sg:classifiers":[
        {
            "category":"Restaurant",
            "type":"Food & Drink"
        }
    ],
    "sg:phone":"+1 928 289 0616",
    "sg:postcode":"86047",
    "sg:province":"AZ",
    "wof:name":"Bo Jo's Grill & Sports Club",
    "wof:placetype":"venue"
},
  "geometry": {"coordinates":[-110.69910299999999,35.023656],"type":"Point"}
}