{
  "type": "Feature",
  "properties": {
    "iso:country":"US",
    "sg:address":"455 E Warner Rd",
    "sg:city":"Chandler",
    "sg:classifiers":[
        {
            "category":"Recreation",
            "subcategory":"Amusement Park",
            "type":"Entertainment"
        }
    ],
    "sg:phone":"+1 480 270 8008",
    "sg:postcode":"85225",
    "sg:province":"AZ",
    "sg:website":"www.gotjump.com",
    "wof:name":"Jump Street",
    "wof:placetype":"venue"
},
  "geometry": {"coordinates":[-111.834302,33.3351],"type":"Point"}
}