{
  "type": "Feature",
  "properties": {
    "addr:full":"2017 W Silvergate Dr Chandler AZ 85224",
    "addr:housenumber":"2017",
    "addr:postcode":"85224",
    "addr:street":"W Silvergate Dr",
    "iso:country":"US",
    "sg:address":"2017 W Silvergate Dr",
    "sg:city":"Chandler",
    "sg:classifiers":[
        {
            "category":"Manufacturing",
            "subcategory":"Tools & Machinery",
            "type":"Manufacturing & Wholesale Goods"
        }
    ],
    "sg:phone":"+1 480 820 1314",
    "sg:postcode":"85224",
    "sg:province":"AZ",
    "sg:tags":[
        "industry",
        "mfg"
    ],
    "wof:name":"Southwest Slump Meter",
    "wof:placetype":"venue"
},
  "geometry": {"coordinates":[-111.877849,33.351623],"type":"Point"}
}