{
  "type": "Feature",
  "properties": {
    "addr:full":"1418 N 35th Ave Phoenix AZ 85009",
    "addr:housenumber":"1418",
    "addr:postcode":"85009",
    "addr:street":"N 35Th Ave",
    "iso:country":"US",
    "sg:address":"1418 N 35th Ave",
    "sg:city":"Phoenix",
    "sg:classifiers":[
        {
            "category":"Shopping",
            "subcategory":"Shoes",
            "type":"Retail Goods"
        }
    ],
    "sg:phone":"+1 602 278 1899",
    "sg:postcode":"85009",
    "sg:province":"AZ",
    "sg:website":"www.stevesshoes.com",
    "wof:name":"Steven's Shoes",
    "wof:placetype":"venue"
},
  "geometry": {"coordinates":[-112.134568,33.46489],"type":"Point"}
}