{
  "type": "Feature",
  "properties": {
    "addr:full":"1815 E Prince Rd Tucson AZ 85719",
    "addr:housenumber":"1815",
    "addr:postcode":"85719",
    "addr:street":"E Prince Rd",
    "iso:country":"US",
    "sg:address":"1815 E Prince Rd",
    "sg:city":"Tucson",
    "sg:classifiers":[
        {
            "category":"Real Estate",
            "subcategory":"Real Estate Agent",
            "type":"Services"
        }
    ],
    "sg:phone":"+1 520 327 0011",
    "sg:postcode":"85719",
    "sg:province":"AZ",
    "wof:name":"Exit Realty New West Grp",
    "wof:placetype":"venue"
},
  "geometry": {"coordinates":[-110.944886,32.27227],"type":"Point"}
}