{
  "type": "Feature",
  "properties": {
    "addr:full":"1936 E Libra Dr Tempe AZ 85283",
    "addr:housenumber":"1936",
    "addr:postcode":"85283",
    "addr:street":"E Libra Dr",
    "iso:country":"US",
    "sg:address":"1936 E Libra Dr",
    "sg:city":"Tempe",
    "sg:classifiers":[
        {
            "category":"Health Services",
            "subcategory":"Clinic",
            "type":"Services"
        }
    ],
    "sg:phone":"+1 480 775 0340",
    "sg:postcode":"85283",
    "sg:province":"AZ",
    "wof:name":"One World Therapy",
    "wof:placetype":"venue"
},
  "geometry": {"coordinates":[-111.90411,33.366681],"type":"Point"}
}