{
  "type": "Feature",
  "properties": {
    "addr:full":"7310 N 16th Pl Phoenix AZ 85020",
    "addr:housenumber":"7310",
    "addr:postcode":"85020",
    "addr:street":"N 16Th Pl",
    "iso:country":"US",
    "sg:address":"7310 N 16th Pl",
    "sg:city":"Phoenix",
    "sg:classifiers":[
        {
            "category":"Professional",
            "subcategory":"Engineering",
            "type":"Services"
        }
    ],
    "sg:phone":"+1 602 943 1003",
    "sg:postcode":"85020",
    "sg:province":"AZ",
    "sg:tags":[
        "engineer"
    ],
    "sg:website":"www.pbsj.com",
    "wof:name":"PBS & J",
    "wof:placetype":"venue"
},
  "geometry": {"coordinates":[-112.04602,33.545261],"type":"Point"}
}