{
  "type": "Feature",
  "properties": {
    "iso:country":"US",
    "sg:address":"3605 W Osborn Rd",
    "sg:city":"Phoenix",
    "sg:classifiers":[
        {
            "category":"Real Estate",
            "subcategory":"Real Estate Operator",
            "type":"Services"
        }
    ],
    "sg:phone":"+1 602 278 0931",
    "sg:postcode":"85019",
    "sg:province":"AZ",
    "sg:tags":[
        "building",
        "apartment"
    ],
    "wof:name":"Puerta Del Sol Apartments",
    "wof:placetype":"venue"
},
  "geometry": {"coordinates":[-112.137969,33.487618],"type":"Point"}
}