{
  "type": "Feature",
  "properties": {
    "iso:country":"US",
    "sg:address":"6666 W Peoria Ave",
    "sg:city":"Glendale",
    "sg:classifiers":[
        {
            "category":"Banks & Credit Unions",
            "subcategory":"Bank",
            "type":"Services"
        }
    ],
    "sg:phone":"+1 623 486 5214",
    "sg:postcode":"85302",
    "sg:province":"AZ",
    "sg:tags":[
        "cashing",
        "check"
    ],
    "wof:name":"Check Into Cash",
    "wof:placetype":"venue"
},
  "geometry": {"coordinates":[-112.20129900000001,33.581809],"type":"Point"}
}