{
  "type": "Feature",
  "properties": {
    "addr:full":"1533 W Wahalla Ln Phoenix AZ 85027",
    "addr:housenumber":"1533",
    "addr:postcode":"85027",
    "addr:street":"W Wahalla Ln",
    "iso:country":"US",
    "sg:address":"1533 W Wahalla Ln",
    "sg:city":"Phoenix",
    "sg:classifiers":[
        {
            "category":"Restaurant",
            "type":"Food & Drink"
        }
    ],
    "sg:phone":"+1 623 582 5285",
    "sg:postcode":"85027",
    "sg:province":"AZ",
    "sg:tags":[
        "caterer"
    ],
    "wof:name":"PJF",
    "wof:placetype":"venue"
},
  "geometry": {"coordinates":[-112.09342700000001,33.666899],"type":"Point"}
}