{
  "type": "Feature",
  "properties": {
    "addr:full":"31 Kipper St Rio Rico AZ 85648",
    "addr:housenumber":"31",
    "addr:postcode":"85648",
    "addr:street":"Kipper St",
    "iso:country":"US",
    "sg:address":"31 Kipper St",
    "sg:city":"Rio Rico",
    "sg:classifiers":[
        {
            "category":"Food & Beverages",
            "subcategory":"Fruits & Vegetables",
            "type":"Retail Goods"
        },
        {
            "category":"Wholesale",
            "subcategory":"Fruits & Vegetables",
            "type":"Manufacturing & Wholesale Goods"
        }
    ],
    "sg:phone":"+1 520 761 1442",
    "sg:postcode":"85648",
    "sg:province":"AZ",
    "sg:tags":[
        "produce"
    ],
    "wof:name":"Proffer Wholesale Produce Inc",
    "wof:placetype":"venue"
},
  "geometry": {"coordinates":[-110.984044,31.458008],"type":"Point"}
}