{
  "type": "Feature",
  "properties": {
    "iso:country":"US",
    "sg:address":"2716 N Dobson Rd",
    "sg:city":"Chandler",
    "sg:classifiers":[
        {
            "category":"Organizations",
            "subcategory":"Religious Organization",
            "type":"Services"
        }
    ],
    "sg:phone":"+1 480 899 3330",
    "sg:postcode":"85224",
    "sg:province":"AZ",
    "sg:tags":[
        "church"
    ],
    "wof:name":"St Katherine Greek Orthodox",
    "wof:placetype":"venue"
},
  "geometry": {"coordinates":[-111.876534,33.346373],"type":"Point"}
}