{
  "type": "Feature",
  "properties": {
    "addr:full":"1409 E Alta Vista Rd Phoenix AZ 85042",
    "addr:housenumber":"1409",
    "addr:postcode":"85042",
    "addr:street":"E Alta Vista Rd",
    "iso:country":"US",
    "sg:address":"1409 E Alta Vista Rd",
    "sg:city":"Phoenix",
    "sg:classifiers":[
        {
            "category":"Professional",
            "type":"Services"
        }
    ],
    "sg:phone":"+1 602 232 2255",
    "sg:postcode":"85042",
    "sg:province":"AZ",
    "sg:tags":[
        "caterer"
    ],
    "wof:name":"Sapphire Catering",
    "wof:placetype":"venue"
},
  "geometry": {"coordinates":[-112.051024,33.38863],"type":"Point"}
}