{
  "type": "Feature",
  "properties": {
    "iso:country":"US",
    "sg:address":"5020 N Oracle Rd",
    "sg:city":"Tucson",
    "sg:classifiers":[
        {
            "category":"Personal",
            "subcategory":"Beauty Salon",
            "type":"Services"
        },
        {
            "category":"Personal",
            "subcategory":"Nail Salon",
            "type":"Services"
        }
    ],
    "sg:phone":"+1 520 888 2197",
    "sg:postcode":"85704",
    "sg:province":"AZ",
    "wof:name":"River Nails",
    "wof:placetype":"venue"
},
  "geometry": {"coordinates":[-110.97825,32.297694],"type":"Point"}
}