{
  "type": "Feature",
  "properties": {
    "addr:full":"7902 W Glendale Ave Glendale AZ 85303",
    "addr:housenumber":"7902",
    "addr:postcode":"85303",
    "addr:street":"W Glendale Ave",
    "iso:country":"US",
    "sg:address":"7902 W Glendale Ave",
    "sg:city":"Glendale",
    "sg:classifiers":[
        {
            "category":"Manufacturing",
            "subcategory":"Printing",
            "type":"Manufacturing & Wholesale Goods"
        }
    ],
    "sg:phone":"+1 623 939 6688",
    "sg:postcode":"85303",
    "sg:province":"AZ",
    "sg:tags":[
        "screen",
        "bottle",
        "plastic"
    ],
    "wof:name":"Custom Containers",
    "wof:placetype":"venue"
},
  "geometry": {"coordinates":[-112.229551,33.537881],"type":"Point"}
}