{
  "type": "Feature",
  "properties": {
    "iso:country":"US",
    "sg:address":"421 Pennsylvania Ave",
    "sg:city":"Patagonia",
    "sg:classifiers":[
        {
            "category":"Government",
            "subcategory":"Fire Station",
            "type":"Public Place"
        }
    ],
    "sg:phone":"+1 520 604 6525",
    "sg:postcode":"85624",
    "sg:province":"AZ",
    "sg:tags":[
        "department"
    ],
    "wof:name":"Santa Cruz County Fire",
    "wof:placetype":"venue"
},
  "geometry": {"coordinates":[-110.75752199999999,31.541053],"type":"Point"}
}