{
  "type": "Feature",
  "properties": {
    "iso:country":"US",
    "sg:address":"3921 S Adelle",
    "sg:city":"Mesa",
    "sg:classifiers":[
        {
            "category":"Building & Trades",
            "subcategory":"Pest Control",
            "type":"Services"
        }
    ],
    "sg:phone":"+1 480 209 1589",
    "sg:postcode":"85212",
    "sg:province":"AZ",
    "sg:tags":[
        "industrial",
        "services-commercial",
        "termite",
        "bee",
        "insect",
        "device",
        "removal"
    ],
    "sg:website":"http://www.extermadorpestcontrol.com",
    "wof:name":"Extermador Pest Control",
    "wof:placetype":"venue"
},
  "geometry": {"coordinates":[-111.584604,33.343637],"type":"Point"}
}