{
  "type": "Feature",
  "properties": {
    "addr:full":"2435 S 6th Ave Phoenix AZ 85003",
    "addr:housenumber":"2435",
    "addr:postcode":"85003",
    "addr:street":"S 6Th Ave",
    "iso:country":"US",
    "sg:address":"2435 S 6th Ave",
    "sg:city":"Phoenix",
    "sg:classifiers":[
        {
            "category":"Building & Trades",
            "subcategory":"Construction",
            "type":"Services"
        }
    ],
    "sg:phone":"+1 480 963 3416",
    "sg:postcode":"85003",
    "sg:province":"AZ",
    "sg:tags":[
        "sealcoating",
        "asphalt",
        "paving"
    ],
    "sg:website":"http://www.regionalaz.com",
    "wof:name":"Regional Pavement Maintenance Of Arizona, Inc.",
    "wof:placetype":"venue"
},
  "geometry": {"coordinates":[-112.08122,33.424649],"type":"Point"}
}