{
  "type": "Feature",
  "properties": {
    "addr:full":"6602 E Cave Creek Road Cave Creek AZ 85331",
    "addr:housenumber":"6602",
    "addr:postcode":"85331",
    "addr:street":"E Cave Creek Road",
    "iso:country":"US",
    "sg:address":"6602 E Cave Creek Road",
    "sg:city":"Cave Creek",
    "sg:classifiers":[
        {
            "category":"Home & Garden",
            "subcategory":"Furniture",
            "type":"Retail Goods"
        }
    ],
    "sg:phone":"+1 480 575 1357",
    "sg:postcode":"85331",
    "sg:province":"AZ",
    "sg:tags":[
        "store"
    ],
    "wof:name":"Big Bronco Furniture Barn",
    "wof:placetype":"venue"
},
  "geometry": {"coordinates":[-111.93896100000001,33.833187],"type":"Point"}
}