{
  "type": "Feature",
  "properties": {
    "iso:country":"US",
    "sg:address":"2822 N Izabel St",
    "sg:city":"Flagstaff",
    "sg:classifiers":[
        {
            "category":"Place Of Worship",
            "subcategory":"Church",
            "type":"Public Place"
        },
        {
            "category":"Place Of Worship",
            "type":"Public Place"
        }
    ],
    "sg:phone":"+1 928 774 4116",
    "sg:postcode":"86004",
    "sg:province":"AZ",
    "sg:tags":[
        "jesus",
        "churches-church",
        "christ",
        "saint",
        "latter-day"
    ],
    "sg:website":"http://www.lds.org",
    "wof:name":"The Corp Of Church Of Christ Latter-Day St",
    "wof:placetype":"venue"
},
  "geometry": {"coordinates":[-111.6225,35.215511],"type":"Point"}
}