{
  "type": "Feature",
  "properties": {
    "iso:country":"US",
    "sg:address":"1139 W Hilton Ave",
    "sg:city":"Phoenix",
    "sg:classifiers":[
        {
            "category":"Wholesale",
            "subcategory":"Construction Materials",
            "type":"Manufacturing & Wholesale Goods"
        },
        {
            "category":"Professional",
            "subcategory":"Art Services",
            "type":"Services"
        }
    ],
    "sg:phone":"+1 602 256 0260",
    "sg:postcode":"85007",
    "sg:province":"AZ",
    "sg:tags":[
        "coatings-protective",
        "painting-production"
    ],
    "sg:website":"http://www.paintbypip.com",
    "wof:name":"Precision Industrial Painting Inc",
    "wof:placetype":"venue"
},
  "geometry": {"coordinates":[-112.087204,33.427212],"type":"Point"}
}