{
  "type": "Feature",
  "properties": {
    "addr:full":"25235 N 104th Way Scottsdale AZ 85255",
    "addr:housenumber":"25235",
    "addr:postcode":"85255",
    "addr:street":"N 104Th Way",
    "iso:country":"US",
    "sg:address":"25235 N 104th Way",
    "sg:city":"Scottsdale",
    "sg:classifiers":[
        {
            "category":"Shopping",
            "subcategory":"Jewelry",
            "type":"Retail Goods"
        }
    ],
    "sg:phone":"+1 480 585 4967",
    "sg:postcode":"85255",
    "sg:province":"AZ",
    "wof:name":"Custom Touch",
    "wof:placetype":"venue"
},
  "geometry": {"coordinates":[-111.856195,33.71717],"type":"Point"}
}