{
  "type": "Feature",
  "properties": {
    "iso:country":"US",
    "sg:address":"127 E 5th St",
    "sg:city":"Eagar",
    "sg:classifiers":[
        {
            "category":"Communications",
            "subcategory":"Film & Video Production",
            "type":"Services"
        }
    ],
    "sg:phone":"+1 928 751 0022",
    "sg:postcode":"85925",
    "sg:province":"AZ",
    "sg:tags":[
        "tv",
        "radio",
        "services-commercial",
        "companies-film"
    ],
    "wof:name":"S Myra Production",
    "wof:placetype":"venue"
},
  "geometry": {"coordinates":[-109.289025,34.10231],"type":"Point"}
}