{
  "type": "Feature",
  "properties": {
    "iso:country":"US",
    "sg:address":"3830 E Elm St",
    "sg:city":"Phoenix",
    "sg:classifiers":[
        {
            "category":"Real Estate",
            "subcategory":"Real Estate Agent",
            "type":"Services"
        }
    ],
    "sg:phone":"+1 602 954 7135",
    "sg:postcode":"85018",
    "sg:province":"AZ",
    "sg:tags":[
        "investment"
    ],
    "wof:name":"Degrassi Enterprises",
    "wof:placetype":"venue"
},
  "geometry": {"coordinates":[-111.998077,33.507662],"type":"Point"}
}