{
  "type": "Feature",
  "properties": {
    "iso:country":"US",
    "sg:address":"2882 N Scottsdale Rd",
    "sg:city":"Scottsdale",
    "sg:classifiers":[
        {
            "category":"Restaurant",
            "type":"Food & Drink"
        }
    ],
    "sg:phone":"+1 480 946 7809",
    "sg:postcode":"85257",
    "sg:province":"AZ",
    "sg:tags":[
        "fast"
    ],
    "wof:name":"McDonalds",
    "wof:placetype":"venue"
},
  "geometry": {"coordinates":[-111.926233,33.478923],"type":"Point"}
}