{
  "type": "Feature",
  "properties": {
    "addr:full":"5947 W Orangewood Ave Glendale AZ 85301",
    "addr:housenumber":"5947",
    "addr:postcode":"85301",
    "addr:street":"W Orangewood Ave",
    "iso:country":"US",
    "sg:address":"5947 W Orangewood Ave",
    "sg:city":"Glendale",
    "sg:classifiers":[
        {
            "category":"Building & Trades",
            "subcategory":"Cleaning & Sanitation",
            "type":"Services"
        }
    ],
    "sg:phone":"+1 623 933 5159",
    "sg:postcode":"85301",
    "sg:province":"AZ",
    "sg:tags":[
        "janitor"
    ],
    "wof:name":"Rita's Cleaning Inc",
    "wof:placetype":"venue"
},
  "geometry": {"coordinates":[-112.187985,33.545727],"type":"Point"}
}