{
  "type": "Feature",
  "properties": {
    "iso:country":"US",
    "sg:address":"5605 E River Rd",
    "sg:city":"Tucson",
    "sg:classifiers":[
        {
            "category":"Professional",
            "type":"Services"
        }
    ],
    "sg:phone":"+1 520 232 0126",
    "sg:postcode":"85750",
    "sg:province":"AZ",
    "sg:tags":[
        "establishment"
    ],
    "wof:name":"El Patron",
    "wof:placetype":"venue"
},
  "geometry": {"coordinates":[-110.873722,32.273464],"type":"Point"}
}