{
  "type": "Feature",
  "properties": {
    "addr:full":"505 S Val Vista Dr Mesa AZ 85204",
    "addr:housenumber":"505",
    "addr:postcode":"85204",
    "addr:street":"S Val Vista Dr",
    "iso:country":"US",
    "sg:address":"505 S Val Vista Dr",
    "sg:city":"Mesa",
    "sg:classifiers":[
        {
            "category":"Banks & Credit Unions",
            "subcategory":"Bank",
            "type":"Services"
        }
    ],
    "sg:phone":"+1 480 325 6072",
    "sg:postcode":"85204",
    "sg:province":"AZ",
    "sg:tags":[
        "other",
        "plan",
        "card"
    ],
    "wof:name":"Cardservice International",
    "wof:placetype":"venue"
},
  "geometry": {"coordinates":[-111.753687,33.407046],"type":"Point"}
}