{
  "type": "Feature",
  "properties": {
    "addr:full":"1108 West Indian School Rd Phoenix AZ 85013",
    "addr:housenumber":"1108",
    "addr:postcode":"85013",
    "addr:street":"West Indian School Rd",
    "iso:country":"US",
    "sg:address":"1108 West Indian School Rd",
    "sg:city":"Phoenix",
    "sg:classifiers":[
        {
            "category":"Health Services",
            "subcategory":"Doctor",
            "type":"Services"
        },
        {
            "category":"Health Services",
            "subcategory":"Clinic",
            "type":"Services"
        }
    ],
    "sg:phone":"+1 602 773 5600",
    "sg:postcode":"85013",
    "sg:province":"AZ",
    "sg:tags":[
        "physician",
        "medical",
        "surgeon"
    ],
    "sg:website":"http://www.phoenixfamilymedical.com",
    "wof:name":"Phoenix Family Medical Clinic",
    "wof:placetype":"venue"
},
  "geometry": {"coordinates":[-112.08701600000001,33.494912],"type":"Point"}
}