{
  "type": "Feature",
  "properties": {
    "addr:full":"3929 E Main St Mesa AZ 85205",
    "addr:housenumber":"3929",
    "addr:postcode":"85205",
    "addr:street":"E Main St",
    "iso:country":"US",
    "sg:address":"3929 E Main St",
    "sg:city":"Mesa",
    "sg:classifiers":[
        {
            "category":"Education",
            "subcategory":"Dance Studio",
            "type":"Public Place"
        }
    ],
    "sg:phone":"+1 480 832 9111",
    "sg:postcode":"85205",
    "sg:province":"AZ",
    "sg:tags":[
        "instruction",
        "dancing"
    ],
    "wof:name":"Stardust Dance Club",
    "wof:placetype":"venue"
},
  "geometry": {"coordinates":[-111.745059,33.415398],"type":"Point"}
}