{
  "type": "Feature",
  "properties": {
    "addr:full":"932 12th Pl Prescott AZ 86305",
    "addr:housenumber":"932",
    "addr:postcode":"86305",
    "addr:street":"12Th Pl",
    "iso:country":"US",
    "sg:address":"932 12th Pl",
    "sg:city":"Prescott",
    "sg:classifiers":[
        {
            "category":"Personal",
            "subcategory":"Beauty Salon",
            "type":"Services"
        }
    ],
    "sg:phone":"+1 928 445 9140",
    "sg:postcode":"86305",
    "sg:province":"AZ",
    "wof:name":"Hair Now",
    "wof:placetype":"venue"
},
  "geometry": {"coordinates":[-112.483656,34.564889],"type":"Point"}
}