{
  "type": "Feature",
  "properties": {
    "addr:full":"13129 E 49th St Yuma AZ 85367",
    "addr:housenumber":"13129",
    "addr:postcode":"85367",
    "addr:street":"E 49Th St",
    "iso:country":"US",
    "sg:address":"13129 E 49th St",
    "sg:city":"Yuma",
    "sg:classifiers":[
        {
            "category":"Building & Trades",
            "subcategory":"Construction",
            "type":"Services"
        }
    ],
    "sg:phone":"+1 602 935 1131",
    "sg:postcode":"85367",
    "sg:province":"AZ",
    "sg:tags":[
        "contractor"
    ],
    "wof:name":"H2o Contracting Services",
    "wof:placetype":"venue"
},
  "geometry": {"coordinates":[-114.40786900000001,32.639702],"type":"Point"}
}