{
  "type": "Feature",
  "properties": {
    "iso:country":"US",
    "sg:address":"4328 E Coronado Rd",
    "sg:city":"Phoenix",
    "sg:classifiers":[
        {
            "category":"Shopping",
            "subcategory":"Used Merchandise",
            "type":"Retail Goods"
        }
    ],
    "sg:phone":"+1 602 273 9296",
    "sg:postcode":"85008",
    "sg:province":"AZ",
    "sg:website":"www.pricelesspieces.com",
    "wof:name":"Priceless Pieces",
    "wof:placetype":"venue"
},
  "geometry": {"coordinates":[-111.98743,33.468006],"type":"Point"}
}