{
  "type": "Feature",
  "properties": {
    "iso:country":"US",
    "sg:address":"3805 N 21st Pl",
    "sg:city":"Phoenix",
    "sg:classifiers":[
        {
            "category":"Wholesale",
            "subcategory":"Construction Materials",
            "type":"Manufacturing & Wholesale Goods"
        }
    ],
    "sg:phone":"+1 602 522 2398",
    "sg:postcode":"85016",
    "sg:province":"AZ",
    "wof:name":"Valencia Island Doors Inc",
    "wof:placetype":"venue"
},
  "geometry": {"coordinates":[-112.03556,33.492953],"type":"Point"}
}