{
  "type": "Feature",
  "properties": {
    "addr:full":"9616 N 7th Ave Phoenix AZ 85021",
    "addr:housenumber":"9616",
    "addr:postcode":"85021",
    "addr:street":"N 7Th Ave",
    "iso:country":"US",
    "sg:address":"9616 N 7th Ave",
    "sg:city":"Phoenix",
    "sg:classifiers":[
        {
            "category":"Retail",
            "subcategory":"Repair Shop",
            "type":"Services"
        }
    ],
    "sg:phone":"+1 602 943 2638",
    "sg:postcode":"85021",
    "sg:province":"AZ",
    "sg:tags":[
        "machine",
        "washing"
    ],
    "wof:name":"Paul's Washer & Dryer",
    "wof:placetype":"venue"
},
  "geometry": {"coordinates":[-112.08116200000001,33.574792],"type":"Point"}
}