{
  "type": "Feature",
  "properties": {
    "iso:country":"US",
    "sg:address":"7220 N 16th St Ste H",
    "sg:city":"Phoenix",
    "sg:classifiers":[
        {
            "category":"Professional",
            "subcategory":"Lawyer & Legal Services",
            "type":"Services"
        }
    ],
    "sg:phone":"+1 602 249 4972",
    "sg:postcode":"85020",
    "sg:province":"AZ",
    "sg:tags":[
        "criminal",
        "attorney",
        "law",
        "plan"
    ],
    "wof:name":"Randall Evans Law Offices",
    "wof:placetype":"venue"
},
  "geometry": {"coordinates":[-112.047524,33.542729],"type":"Point"}
}