{
  "type": "Feature",
  "properties": {
    "addr:full":"9617 N Metro Pkwy E Phoenix AZ 85051",
    "addr:housenumber":"9617",
    "addr:postcode":"85051",
    "addr:street":"N Metro Pkwy E",
    "iso:country":"US",
    "sg:address":"9617 N Metro Pkwy E",
    "sg:city":"Phoenix",
    "sg:classifiers":[
        {
            "category":"Restaurant",
            "type":"Food & Drink"
        }
    ],
    "sg:menulink":"http://www.allmenus.com/az/phoenix/103465-ruby-tuesdays/menu/",
    "sg:phone":"+1 602 997 0620",
    "sg:postcode":"85051",
    "sg:province":"AZ",
    "sg:tags":[
        "burger",
        "american"
    ],
    "wof:name":"Ruby Tuesdays",
    "wof:placetype":"venue"
},
  "geometry": {"coordinates":[-112.118341,33.574458],"type":"Point"}
}