{
  "type": "Feature",
  "properties": {
    "addr:full":"331 E Chandler Blvd Chandler AZ 85225",
    "addr:housenumber":"331",
    "addr:postcode":"85225",
    "addr:street":"E Chandler Blvd",
    "iso:country":"US",
    "sg:address":"331 E Chandler Blvd",
    "sg:city":"Chandler",
    "sg:classifiers":[
        {
            "category":"Local Transit",
            "type":"Transportation"
        }
    ],
    "sg:phone":"+1 480 963 7961",
    "sg:postcode":"85225",
    "sg:province":"AZ",
    "sg:tags":[
        "bus",
        "line"
    ],
    "wof:name":"Greyhound Bus Lines",
    "wof:placetype":"venue"
},
  "geometry": {"coordinates":[-111.83607499999999,33.306106],"type":"Point"}
}