{
  "type": "Feature",
  "properties": {
    "iso:country":"US",
    "sg:address":"9072 E Evans Dr",
    "sg:city":"Scottsdale",
    "sg:classifiers":[
        {
            "category":"Professional",
            "subcategory":"Detective & Security Services",
            "type":"Services"
        }
    ],
    "sg:phone":"+1 480 661 4025",
    "sg:postcode":"85260",
    "sg:province":"AZ",
    "sg:tags":[
        "information",
        "bureau"
    ],
    "wof:name":"Do Right Pool Service",
    "wof:placetype":"venue"
},
  "geometry": {"coordinates":[-111.885227,33.61829],"type":"Point"}
}