{
  "type": "Feature",
  "properties": {
    "iso:country":"US",
    "sg:address":"8805 W Union Hills Dr #102",
    "sg:city":"Peoria",
    "sg:classifiers":[
        {
            "category":"Insurance",
            "subcategory":"Insurance Agent",
            "type":"Services"
        },
        {
            "category":"Insurance",
            "subcategory":"Hazard Insurance",
            "type":"Services"
        },
        {
            "category":"Insurance",
            "subcategory":"Title Insurance",
            "type":"Services"
        },
        {
            "category":"Insurance",
            "subcategory":"Life Insurance",
            "type":"Services"
        }
    ],
    "sg:phone":"+1 623 386 9968",
    "sg:postcode":"85382",
    "sg:province":"AZ",
    "sg:tags":[
        "auto",
        "commercial",
        "business",
        "homeowner"
    ],
    "sg:website":"http://www.farmersagent.com/dlanvin/",
    "wof:name":"Debra Lanvin Navarrete - Farmers Insurance",
    "wof:placetype":"venue"
},
  "geometry": {"coordinates":[-112.24859499999999,33.65266],"type":"Point"}
}