{
  "type": "Feature",
  "properties": {
    "iso:country":"US",
    "sg:address":"1725 E Mountain View Rd",
    "sg:city":"Phoenix",
    "sg:classifiers":[
        {
            "category":"Manufacturing",
            "subcategory":"Printing",
            "type":"Manufacturing & Wholesale Goods"
        }
    ],
    "sg:phone":"+1 602 997 2448",
    "sg:postcode":"85020",
    "sg:province":"AZ",
    "sg:tags":[
        "publisher",
        "book"
    ],
    "sg:website":"http://www.readingmanipulatives.com",
    "wof:name":"Reading Manipulatives Inc",
    "wof:placetype":"venue"
},
  "geometry": {"coordinates":[-112.044601,33.57547],"type":"Point"}
}