{
  "type": "Feature",
  "properties": {
    "iso:country":"US",
    "sg:address":"11062 N 24th Ave",
    "sg:city":"Phoenix",
    "sg:classifiers":[
        {
            "category":"Professional",
            "subcategory":"Computer Services",
            "type":"Services"
        }
    ],
    "sg:phone":"+1 602 404 9055",
    "sg:postcode":"85029",
    "sg:province":"AZ",
    "sg:tags":[
        "software",
        "design",
        "network",
        "system"
    ],
    "wof:name":"Computas Corporation",
    "wof:placetype":"venue"
},
  "geometry": {"coordinates":[-112.111591,33.586435],"type":"Point"}
}