{
  "type": "Feature",
  "properties": {
    "iso:country":"US",
    "sg:address":"281 N Roosevelt Ave",
    "sg:city":"Chandler",
    "sg:classifiers":[
        {
            "category":"Wholesale",
            "subcategory":"Medical Equipment & Supplies",
            "type":"Manufacturing & Wholesale Goods"
        }
    ],
    "sg:phone":"+1 480 785 2500",
    "sg:postcode":"85226",
    "sg:province":"AZ",
    "wof:name":"Atp One Medical & Sports Sups",
    "wof:placetype":"venue"
},
  "geometry": {"coordinates":[-111.951053,33.305958],"type":"Point"}
}