{
  "type": "Feature",
  "properties": {
    "iso:country":"US",
    "sg:address":"1400 E Butler Ave",
    "sg:city":"Flagstaff",
    "sg:classifiers":[
        {
            "category":"Wholesale",
            "subcategory":"Construction Materials",
            "type":"Manufacturing & Wholesale Goods"
        }
    ],
    "sg:phone":"+1 928 214 0400",
    "sg:postcode":"86001",
    "sg:province":"AZ",
    "sg:tags":[
        "marble"
    ],
    "wof:name":"American Marble Co",
    "wof:placetype":"venue"
},
  "geometry": {"coordinates":[-111.633444,35.191386],"type":"Point"}
}