{
  "type": "Feature",
  "properties": {
    "iso:country":"US",
    "sg:address":"2055 N Kolb Rd",
    "sg:city":"Tucson",
    "sg:classifiers":[
        {
            "category":"Real Estate",
            "subcategory":"Architect",
            "type":"Services"
        }
    ],
    "sg:phone":"+1 520 722 3668",
    "sg:postcode":"85715",
    "sg:province":"AZ",
    "wof:name":"Bruce R Call Architecture",
    "wof:placetype":"venue"
},
  "geometry": {"coordinates":[-110.849614,32.2476],"type":"Point"}
}