{
  "type": "Feature",
  "properties": {
    "iso:country":"US",
    "sg:address":"2600 N Fenimore Ave",
    "sg:city":"Tucson",
    "sg:classifiers":[
        {
            "category":"Education",
            "subcategory":"School",
            "type":"Public Place"
        }
    ],
    "sg:phone":"+1 520 749 3224",
    "sg:postcode":"85749",
    "sg:province":"AZ",
    "wof:name":"TVES After School Program",
    "wof:placetype":"venue"
},
  "geometry": {"coordinates":[-110.729283,32.254673],"type":"Point"}
}