{
  "type": "Feature",
  "properties": {
    "iso:country":"US",
    "sg:address":"1881 E Bendix Dr",
    "sg:city":"Tempe",
    "sg:classifiers":[
        {
            "category":"Arts & Performance",
            "subcategory":"Art Gallery",
            "type":"Entertainment"
        },
        {
            "category":"Education",
            "subcategory":"Special Training",
            "type":"Public Place"
        }
    ],
    "sg:phone":"+1 480 839 4836",
    "sg:postcode":"85283",
    "sg:province":"AZ",
    "sg:tags":[
        "consultant",
        "school",
        "instruction",
        "galleries"
    ],
    "wof:name":"Heirlooms By Design",
    "wof:placetype":"venue"
},
  "geometry": {"coordinates":[-111.907239,33.359083],"type":"Point"}
}