{
  "type": "Feature",
  "properties": {
    "iso:country":"US",
    "sg:address":"750 N Gilbert Rd",
    "sg:city":"Gilbert",
    "sg:classifiers":[
        {
            "category":"Shopping",
            "subcategory":"Pharmacy",
            "type":"Retail Goods"
        }
    ],
    "sg:phone":"+1 480 892 1159",
    "sg:postcode":"85234",
    "sg:province":"AZ",
    "sg:website":"www.albertsons.com",
    "wof:name":"Osco Drug",
    "wof:placetype":"venue"
},
  "geometry": {"coordinates":[-111.789872,33.362653],"type":"Point"}
}