{
  "type": "Feature",
  "properties": {
    "iso:country":"US",
    "sg:address":"5052 W Olive Ave",
    "sg:city":"Glendale",
    "sg:classifiers":[
        {
            "category":"Banks & Credit Unions",
            "subcategory":"Bank",
            "type":"Services"
        }
    ],
    "sg:phone":"+1 623 939 6532",
    "sg:postcode":"85302",
    "sg:province":"AZ",
    "sg:tags":[
        "cashing",
        "check"
    ],
    "wof:name":"ACE Cash Express",
    "wof:placetype":"venue"
},
  "geometry": {"coordinates":[-112.167485,33.567586],"type":"Point"}
}