{
  "type": "Feature",
  "properties": {
    "iso:country":"US",
    "sg:address":"843 S Longmore",
    "sg:city":"Mesa",
    "sg:classifiers":[
        {
            "category":"Home & Garden",
            "subcategory":"Hardware",
            "type":"Retail Goods"
        }
    ],
    "sg:phone":"+1 480 833 5478",
    "sg:postcode":"85202",
    "sg:province":"AZ",
    "sg:tags":[
        "tool",
        "used"
    ],
    "wof:name":"Best Tool",
    "wof:placetype":"venue"
},
  "geometry": {"coordinates":[-111.865703,33.400259],"type":"Point"}
}