{
  "type": "Feature",
  "properties": {
    "addr:full":"751 E Union Hills Dr Phoenix AZ 85024",
    "addr:housenumber":"751",
    "addr:postcode":"85024",
    "addr:street":"E Union Hills Dr",
    "iso:country":"US",
    "sg:address":"751 E Union Hills Dr",
    "sg:city":"Phoenix",
    "sg:classifiers":[
        {
            "category":"Organizations",
            "subcategory":"Religious Organization",
            "type":"Services"
        }
    ],
    "sg:phone":"+1 602 765 6700",
    "sg:postcode":"85024",
    "sg:province":"AZ",
    "sg:tags":[
        "book"
    ],
    "wof:name":"Jesus Chapel Discount Bookstor",
    "wof:placetype":"venue"
},
  "geometry": {"coordinates":[-112.06270499999999,33.654773],"type":"Point"}
}