{
  "type": "Feature",
  "properties": {
    "iso:country":"US",
    "sg:address":"70 E Apache St",
    "sg:city":"Wickenburg",
    "sg:classifiers":[
        {
            "category":"Building & Trades",
            "subcategory":"Electrical",
            "type":"Services"
        }
    ],
    "sg:phone":"+1 928 684 7155",
    "sg:postcode":"85390",
    "sg:province":"AZ",
    "sg:tags":[
        "electric",
        "contractor"
    ],
    "wof:name":"PECO",
    "wof:placetype":"venue"
},
  "geometry": {"coordinates":[-112.731517,33.969091],"type":"Point"}
}