{
  "type": "Feature",
  "properties": {
    "addr:full":"937 E Broadway Rd Tempe AZ 85282",
    "addr:housenumber":"937",
    "addr:postcode":"85282",
    "addr:street":"E Broadway Rd",
    "iso:country":"US",
    "sg:address":"937 E Broadway Rd",
    "sg:city":"Tempe",
    "sg:classifiers":[
        {
            "category":"Restaurant",
            "type":"Food & Drink"
        }
    ],
    "sg:phone":"+1 480 377 9241",
    "sg:postcode":"85282",
    "sg:province":"AZ",
    "wof:name":"Rock-N-Roll Fingers",
    "wof:placetype":"venue"
},
  "geometry": {"coordinates":[-111.926135,33.407471],"type":"Point"}
}