{
  "type": "Feature",
  "properties": {
    "addr:full":"949 W Pampa Ave Mesa AZ 85210",
    "addr:housenumber":"949",
    "addr:postcode":"85210",
    "addr:street":"W Pampa Ave",
    "iso:country":"US",
    "sg:address":"949 W Pampa Ave",
    "sg:city":"Mesa",
    "sg:classifiers":[
        {
            "category":"Building & Trades",
            "subcategory":"Construction",
            "type":"Services"
        }
    ],
    "sg:phone":"+1 480 777 8453",
    "sg:postcode":"85210",
    "sg:province":"AZ",
    "sg:tags":[
        "contractor"
    ],
    "wof:name":"Affordable Floors",
    "wof:placetype":"venue"
},
  "geometry": {"coordinates":[-111.85411499999999,33.35911],"type":"Point"}
}