{
  "type": "Feature",
  "properties": {
    "addr:full":"321 W Hatcher Rd Phoenix AZ 85021",
    "addr:housenumber":"321",
    "addr:postcode":"85021",
    "addr:street":"W Hatcher Rd",
    "iso:country":"US",
    "sg:address":"321 W Hatcher Rd",
    "sg:city":"Phoenix",
    "sg:classifiers":[
        {
            "category":"Building & Trades",
            "subcategory":"Plumbing",
            "type":"Services"
        }
    ],
    "sg:phone":"+1 602 861 1458",
    "sg:postcode":"85021",
    "sg:province":"AZ",
    "sg:tags":[
        "balancing",
        "air"
    ],
    "wof:name":"Environmental Testing & Blnc",
    "wof:placetype":"venue"
},
  "geometry": {"coordinates":[-112.07829599999999,33.571232],"type":"Point"}
}