{
  "type": "Feature",
  "properties": {
    "iso:country":"US",
    "sg:address":"4 S 84th Ave",
    "sg:city":"Tolleson",
    "sg:classifiers":[
        {
            "category":"Professional",
            "subcategory":"Business Services",
            "type":"Services"
        },
        {
            "category":"Manufacturing",
            "subcategory":"Rubber & Plastics",
            "type":"Manufacturing & Wholesale Goods"
        }
    ],
    "sg:phone":"+1 623 760 1028",
    "sg:postcode":"85353",
    "sg:province":"AZ",
    "sg:tags":[
        "packaging",
        "product",
        "mfg"
    ],
    "wof:name":"Portola Packaging Inc",
    "wof:placetype":"venue"
},
  "geometry": {"coordinates":[-112.241382,33.445391],"type":"Point"}
}