{
  "type": "Feature",
  "properties": {
    "addr:full":"8502 N Black Canyon Hwy Phoenix AZ 85051",
    "addr:housenumber":"8502",
    "addr:postcode":"85051",
    "addr:street":"N Black Canyon Hwy",
    "iso:country":"US",
    "sg:address":"8502 N Black Canyon Hwy",
    "sg:city":"Phoenix",
    "sg:classifiers":[
        {
            "category":"Manufacturing",
            "subcategory":"Tools & Machinery",
            "type":"Manufacturing & Wholesale Goods"
        }
    ],
    "sg:phone":"+1 602 864 0587",
    "sg:postcode":"85051",
    "sg:province":"AZ",
    "sg:tags":[
        "devices",
        "mfg"
    ],
    "wof:name":"Foster Sale Co Dale",
    "wof:placetype":"venue"
},
  "geometry": {"coordinates":[-112.11705600000001,33.56424],"type":"Point"}
}