{
  "type": "Feature",
  "properties": {
    "iso:country":"US",
    "sg:address":"15060 N Northsight Blvd",
    "sg:city":"Scottsdale",
    "sg:classifiers":[
        {
            "category":"Home & Garden",
            "subcategory":"Carpets & Floor Coverings",
            "type":"Retail Goods"
        }
    ],
    "sg:phone":"+1 480 556 9977",
    "sg:postcode":"85260",
    "sg:province":"AZ",
    "wof:name":"Corporation NY",
    "wof:placetype":"venue"
},
  "geometry": {"coordinates":[-111.896916,33.622505],"type":"Point"}
}