{
  "type": "Feature",
  "properties": {
    "iso:country":"US",
    "sg:address":"101 N 20th St",
    "sg:city":"Phoenix",
    "sg:classifiers":[
        {
            "category":"Retail",
            "subcategory":"Auto Repair",
            "type":"Services"
        }
    ],
    "sg:phone":"+1 602 220 0118",
    "sg:postcode":"85034",
    "sg:province":"AZ",
    "sg:tags":[
        "transmission"
    ],
    "wof:name":"A 1 Transmission & Auto Repair",
    "wof:placetype":"venue"
},
  "geometry": {"coordinates":[-112.038977,33.450449],"type":"Point"}
}