{
  "type": "Feature",
  "properties": {
    "addr:full":"4001 E Chandler Blvd Phoenix AZ 85048",
    "addr:housenumber":"4001",
    "addr:postcode":"85048",
    "addr:street":"E Chandler Blvd",
    "iso:country":"US",
    "sg:address":"4001 E Chandler Blvd",
    "sg:city":"Phoenix",
    "sg:classifiers":[
        {
            "category":"Food & Beverages",
            "subcategory":"Groceries & Convenience Stores",
            "type":"Retail Goods"
        }
    ],
    "sg:phone":"+1 480 704 0359",
    "sg:postcode":"85048",
    "sg:province":"AZ",
    "sg:website":"http://www.circlek.com",
    "wof:name":"Circle K",
    "wof:placetype":"venue"
},
  "geometry": {"coordinates":[-111.997192,33.305119],"type":"Point"}
}