{
  "type": "Feature",
  "properties": {
    "addr:full":"2818 W Cactus Rd Phoenix AZ 85029",
    "addr:housenumber":"2818",
    "addr:postcode":"85029",
    "addr:street":"W Cactus Rd",
    "iso:country":"US",
    "sg:address":"2818 W Cactus Rd",
    "sg:city":"Phoenix",
    "sg:classifiers":[
        {
            "category":"Autos & Motor Vehicles",
            "subcategory":"Auto Supplies",
            "type":"Retail Goods"
        },
        {
            "category":"Retail",
            "subcategory":"Auto Repair",
            "type":"Services"
        }
    ],
    "sg:phone":"+1 602 843 2234",
    "sg:postcode":"85029",
    "sg:province":"AZ",
    "sg:tags":[
        "automobile",
        "part",
        "truck"
    ],
    "sg:website":"http://clickserve.dartsearch.net/link/click?lid=43000000313869136&ds_s_kwgid=58000000006820725&ds_e_matchtype={MatchType}&ds_e_kwdid={OrderItemId}&ds_e_adid={AdId}&ds_url_v=2",
    "wof:name":"Cadi Shop",
    "wof:placetype":"venue"
},
  "geometry": {"coordinates":[-112.118492,33.596432],"type":"Point"}
}