{
  "type": "Feature",
  "properties": {
    "addr:full":"21617 N 2nd Ave Phoenix AZ 85027",
    "addr:housenumber":"21617",
    "addr:postcode":"85027",
    "addr:street":"N 2Nd Ave",
    "iso:country":"US",
    "sg:address":"21617 N 2nd Ave",
    "sg:city":"Phoenix",
    "sg:classifiers":[
        {
            "category":"Insurance",
            "subcategory":"Hazard Insurance",
            "type":"Services"
        },
        {
            "category":"Insurance",
            "subcategory":"Health Insurance",
            "type":"Services"
        }
    ],
    "sg:phone":"+1 623 516 8818",
    "sg:postcode":"85027",
    "sg:province":"AZ",
    "sg:tags":[
        "employee",
        "benefit"
    ],
    "wof:name":"Asi Svc",
    "wof:placetype":"venue"
},
  "geometry": {"coordinates":[-112.07607299999999,33.682905],"type":"Point"}
}