{
  "type": "Feature",
  "properties": {
    "iso:country":"US",
    "sg:address":"16443 N Cave Creek Rd",
    "sg:city":"Phoenix",
    "sg:classifiers":[
        {
            "category":"Bars & Pubs",
            "type":"Food & Drink"
        }
    ],
    "sg:phone":"+1 602 992 9910",
    "sg:postcode":"85032",
    "sg:province":"AZ",
    "sg:tags":[
        "drinking"
    ],
    "wof:name":"A T's Sports Bar",
    "wof:placetype":"venue"
},
  "geometry": {"coordinates":[-112.030709,33.635585],"type":"Point"}
}