{
  "type": "Feature",
  "properties": {
    "iso:country":"US",
    "sg:address":"1003 E Camelback Rd",
    "sg:city":"Phoenix",
    "sg:classifiers":[
        {
            "category":"Autos & Motor Vehicles",
            "subcategory":"Automobile Sales",
            "type":"Retail Goods"
        }
    ],
    "sg:phone":"+1 602 287 8754",
    "sg:postcode":"85014",
    "sg:province":"AZ",
    "sg:tags":[
        "used",
        "car",
        "dealers-used",
        "new",
        "cars-wholesale"
    ],
    "wof:name":"Import Auto Sales",
    "wof:placetype":"venue"
},
  "geometry": {"coordinates":[-112.060522,33.509251],"type":"Point"}
}