{
  "type": "Feature",
  "properties": {
    "iso:country":"US",
    "sg:address":"2704 N Stockton Hill Rd",
    "sg:city":"Kingman",
    "sg:classifiers":[
        {
            "category":"Wholesale",
            "subcategory":"Medical Equipment & Supplies",
            "type":"Manufacturing & Wholesale Goods"
        }
    ],
    "sg:phone":"+1 928 718 2301",
    "sg:postcode":"86401",
    "sg:province":"AZ",
    "sg:tags":[
        "device",
        "surgical",
        "orthopedic",
        "appliance",
        "prosthetic"
    ],
    "wof:name":"Hanger Prosthetics & Orthotics",
    "wof:placetype":"venue"
},
  "geometry": {"coordinates":[-114.034862,35.210394],"type":"Point"}
}