{
  "type": "Feature",
  "properties": {
    "iso:country":"US",
    "sg:address":"561 E Houston Ave",
    "sg:city":"Gilbert",
    "sg:classifiers":[
        {
            "category":"Retail",
            "subcategory":"Auto Repair",
            "type":"Services"
        }
    ],
    "sg:phone":"+1 480 632 0322",
    "sg:postcode":"85234",
    "sg:province":"AZ",
    "sg:tags":[
        "glass",
        "coating",
        "tinting"
    ],
    "wof:name":"Diamond Seal",
    "wof:placetype":"venue"
},
  "geometry": {"coordinates":[-111.778748,33.371694],"type":"Point"}
}