{
  "type": "Feature",
  "properties": {
    "iso:country":"US",
    "sg:address":"7501 E Civic Cir",
    "sg:city":"Prescott Valley",
    "sg:classifiers":[
        {
            "category":"Recreation",
            "type":"Entertainment"
        }
    ],
    "sg:phone":"+1 928 759 3090",
    "sg:postcode":"86314",
    "sg:province":"AZ",
    "sg:tags":[
        "parks"
    ],
    "sg:website":"www.pvaz.net",
    "wof:name":"Prescott Valley Parks & Rec",
    "wof:placetype":"venue"
},
  "geometry": {"coordinates":[-112.335088,34.596479],"type":"Point"}
}