{
  "type": "Feature",
  "properties": {
    "iso:country":"US",
    "sg:address":"9214 N 13th Ave",
    "sg:city":"Phoenix",
    "sg:classifiers":[
        {
            "category":"Manufacturing",
            "subcategory":"Metals",
            "type":"Manufacturing & Wholesale Goods"
        }
    ],
    "sg:phone":"+1 602 944 7914",
    "sg:postcode":"85021",
    "sg:province":"AZ",
    "sg:tags":[
        "metalwork",
        "sheet",
        "business",
        "mfg",
        "trade",
        "contractor"
    ],
    "wof:name":"Metal Craft",
    "wof:placetype":"venue"
},
  "geometry": {"coordinates":[-112.08936300000001,33.571012],"type":"Point"}
}