{
  "type": "Feature",
  "properties": {
    "iso:country":"US",
    "sg:address":"11495 N 136th St",
    "sg:city":"Scottsdale",
    "sg:classifiers":[
        {
            "category":"Retail",
            "subcategory":"Veterinary Services",
            "type":"Services"
        }
    ],
    "sg:phone":"+1 480 391 7297",
    "sg:postcode":"85259",
    "sg:province":"AZ",
    "sg:tags":[
        "clinic",
        "veterinarian",
        "hospital"
    ],
    "sg:website":"http://www.hillsidepets.com",
    "wof:name":"Hillside Animal Hospital",
    "wof:placetype":"venue"
},
  "geometry": {"coordinates":[-111.78731999999999,33.588973],"type":"Point"}
}