{
  "type": "Feature",
  "properties": {
    "iso:country":"US",
    "sg:address":"4446 E University Dr",
    "sg:city":"Mesa",
    "sg:classifiers":[
        {
            "category":"Building & Trades",
            "subcategory":"Plumbing",
            "type":"Services"
        }
    ],
    "sg:phone":"+1 480 981 7827",
    "sg:postcode":"85205",
    "sg:province":"AZ",
    "sg:tags":[
        "plumbing",
        "contractor"
    ],
    "wof:name":"ASR",
    "wof:placetype":"venue"
},
  "geometry": {"coordinates":[-111.733161,33.422886],"type":"Point"}
}