{
  "type": "Feature",
  "properties": {
    "iso:country":"US",
    "sg:address":"1180 W Duval Rd",
    "sg:city":"Green Valley",
    "sg:classifiers":[
        {
            "category":"Building & Trades",
            "subcategory":"Construction",
            "type":"Services"
        }
    ],
    "sg:phone":"+1 520 625 2391",
    "sg:postcode":"85614",
    "sg:province":"AZ",
    "sg:tags":[
        "water",
        "fire",
        "restoration"
    ],
    "wof:name":"Jeffreys",
    "wof:placetype":"venue"
},
  "geometry": {"coordinates":[-111.00381400000001,31.899581],"type":"Point"}
}