{
  "type": "Feature",
  "properties": {
    "iso:country":"US",
    "sg:address":"1824 E McDowell Rd",
    "sg:city":"Phoenix",
    "sg:classifiers":[
        {
            "category":"Shopping",
            "type":"Retail Goods"
        }
    ],
    "sg:phone":"+1 602 253 5784",
    "sg:postcode":"85006",
    "sg:province":"AZ",
    "sg:tags":[
        "art",
        "gallery",
        "dealer"
    ],
    "sg:website":"www.armstrong-prior.com",
    "wof:name":"Armstrong-Prior Inc",
    "wof:placetype":"venue"
},
  "geometry": {"coordinates":[-112.041668,33.465833],"type":"Point"}
}