{
  "type": "Feature",
  "properties": {
    "iso:country":"US",
    "sg:address":"850 E Ohio St",
    "sg:city":"Tucson",
    "sg:classifiers":[
        {
            "category":"Building & Trades",
            "subcategory":"Plumbing",
            "type":"Services"
        }
    ],
    "sg:phone":"+1 520 807 1940",
    "sg:postcode":"85714",
    "sg:province":"AZ",
    "sg:tags":[
        "contractor"
    ],
    "wof:name":"Reyna Heating & Cooling",
    "wof:placetype":"venue"
},
  "geometry": {"coordinates":[-110.95721899999999,32.167434],"type":"Point"}
}