{
  "type": "Feature",
  "properties": {
    "addr:full":"2949 E Blackhawk Dr Phoenix AZ 85050",
    "addr:housenumber":"2949",
    "addr:postcode":"85050",
    "addr:street":"E Blackhawk Dr",
    "iso:country":"US",
    "sg:address":"2949 E Blackhawk Dr",
    "sg:city":"Phoenix",
    "sg:classifiers":[
        {
            "category":"Shopping",
            "subcategory":"Books",
            "type":"Retail Goods"
        },
        {
            "category":"Wholesale",
            "subcategory":"Books, Periodicals, & Newspapers",
            "type":"Manufacturing & Wholesale Goods"
        }
    ],
    "sg:phone":"+1 602 569 1433",
    "sg:postcode":"85050",
    "sg:province":"AZ",
    "sg:tags":[
        "books-wholesale",
        "store",
        "manufacturer"
    ],
    "wof:name":"Dlg-Delightful Little Goodies Bakery, Books And More",
    "wof:placetype":"venue"
},
  "geometry": {"coordinates":[-112.01943,33.670839],"type":"Point"}
}