{
  "type": "Feature",
  "properties": {
    "addr:full":"2760 N Tucson Blvd Tucson AZ 85716",
    "addr:housenumber":"2760",
    "addr:postcode":"85716",
    "addr:street":"N Tucson Blvd",
    "iso:country":"US",
    "sg:address":"2760 N Tucson Blvd",
    "sg:city":"Tucson",
    "sg:classifiers":[
        {
            "category":"Food & Beverages",
            "subcategory":"Specialty",
            "type":"Retail Goods"
        },
        {
            "category":"Restaurant",
            "type":"Food & Drink"
        }
    ],
    "sg:phone":"+1 520 325 3122",
    "sg:postcode":"85716",
    "sg:province":"AZ",
    "sg:tags":[
        "gourmet",
        "florist",
        "delicatessen",
        "market"
    ],
    "sg:website":"http://www.tedscountrystore.com",
    "wof:name":"Ted's Country Store",
    "wof:placetype":"venue"
},
  "geometry": {"coordinates":[-110.935311,32.257017],"type":"Point"}
}