{
  "type": "Feature",
  "properties": {
    "iso:country":"US",
    "sg:address":"4299 N 43rd Ave",
    "sg:city":"Phoenix",
    "sg:classifiers":[
        {
            "category":"Home & Garden",
            "subcategory":"Building Materials",
            "type":"Retail Goods"
        }
    ],
    "sg:phone":"+1 602 455 8676",
    "sg:postcode":"85031",
    "sg:province":"AZ",
    "sg:tags":[
        "shutter"
    ],
    "wof:name":"Innovative Surfaces",
    "wof:placetype":"venue"
},
  "geometry": {"coordinates":[-112.151688,33.494959],"type":"Point"}
}