{
  "type": "Feature",
  "properties": {
    "iso:country":"US",
    "sg:address":"306 S O'Leary St",
    "sg:city":"Flagstaff",
    "sg:classifiers":[
        {
            "category":"Social Services",
            "subcategory":"Adult Care",
            "type":"Services"
        }
    ],
    "sg:phone":"+1 928 226 8600",
    "sg:postcode":"86001",
    "sg:province":"AZ",
    "sg:tags":[
        "home",
        "group"
    ],
    "wof:name":"Aspen House",
    "wof:placetype":"venue"
},
  "geometry": {"coordinates":[-111.64702,35.19244],"type":"Point"}
}