{
  "type": "Feature",
  "properties": {
    "iso:country":"US",
    "sg:address":"116 N Roosevelt Ave",
    "sg:city":"Chandler",
    "sg:classifiers":[
        {
            "category":"Government",
            "subcategory":"Fire Station",
            "type":"Public Place"
        },
        {
            "category":"Home & Garden",
            "subcategory":"Hardware",
            "type":"Retail Goods"
        }
    ],
    "sg:phone":"+1 480 785 5414",
    "sg:postcode":"85226",
    "sg:province":"AZ",
    "sg:tags":[
        "industrial",
        "protection",
        "consultant",
        "commercial",
        "sprinklers-residential",
        "automatic"
    ],
    "wof:name":"Pacific West Fire Protection",
    "wof:placetype":"venue"
},
  "geometry": {"coordinates":[-111.951033,33.304484],"type":"Point"}
}