{
  "type": "Feature",
  "properties": {
    "iso:country":"US",
    "sg:address":"14652 N 7th Pl",
    "sg:city":"Phoenix",
    "sg:classifiers":[
        {
            "category":"Banks & Credit Unions",
            "subcategory":"Investment Brokerage",
            "type":"Services"
        }
    ],
    "sg:phone":"+1 602 993 1382",
    "sg:postcode":"85022",
    "sg:province":"AZ",
    "sg:tags":[
        "security"
    ],
    "wof:name":"Edward Jones 14882",
    "wof:placetype":"venue"
},
  "geometry": {"coordinates":[-112.064737,33.620494],"type":"Point"}
}