{
  "type": "Feature",
  "properties": {
    "iso:country":"US",
    "sg:address":"2014 S Rural Rd",
    "sg:city":"Tempe",
    "sg:classifiers":[
        {
            "category":"Autos & Motor Vehicles",
            "subcategory":"Auto Supplies",
            "type":"Retail Goods"
        },
        {
            "category":"Retail",
            "subcategory":"Auto Repair",
            "type":"Services"
        }
    ],
    "sg:phone":"+1 480 921 9695",
    "sg:postcode":"85282",
    "sg:province":"AZ",
    "sg:tags":[
        "oil",
        "automotive",
        "automobile",
        "lube",
        "equipment-service",
        "air conditioning",
        "tune"
    ],
    "sg:website":"http://www.jiffylube.com",
    "wof:name":"Jiffy Lube",
    "wof:placetype":"venue"
},
  "geometry": {"coordinates":[-111.926277,33.407309],"type":"Point"}
}