{
  "type": "Feature",
  "properties": {
    "iso:country":"US",
    "sg:address":"15855 N Twin Lakes Dr",
    "sg:city":"Tucson",
    "sg:classifiers":[
        {
            "category":"Place Of Worship",
            "subcategory":"Church",
            "type":"Public Place"
        },
        {
            "category":"Place Of Worship",
            "type":"Public Place"
        },
        {
            "category":"Organizations",
            "subcategory":"Religious Organization",
            "type":"Services"
        }
    ],
    "sg:phone":"+1 520 825 9255",
    "sg:postcode":"85739",
    "sg:province":"AZ",
    "sg:tags":[
        "lutheran",
        "america",
        "churches-lutheran",
        "churches-lutheran-evangelical"
    ],
    "wof:name":"Catalina Lutheran Church",
    "wof:placetype":"venue"
},
  "geometry": {"coordinates":[-110.916,32.493401],"type":"Point"}
}