{
  "type": "Feature",
  "properties": {
    "iso:country":"US",
    "sg:address":"13041 N 35th Ave",
    "sg:city":"Phoenix",
    "sg:classifiers":[
        {
            "category":"Real Estate",
            "subcategory":"Real Estate Agent",
            "type":"Services"
        }
    ],
    "sg:phone":"+1 602 705 3970",
    "sg:postcode":"85029",
    "sg:province":"AZ",
    "wof:name":"P and C Acquisitions LLC",
    "wof:placetype":"venue"
},
  "geometry": {"coordinates":[-112.133811,33.604395],"type":"Point"}
}