{
  "type": "Feature",
  "properties": {
    "iso:country":"US",
    "sg:address":"2302 W Durango St",
    "sg:city":"Phoenix",
    "sg:classifiers":[
        {
            "category":"Government",
            "subcategory":"Office",
            "type":"Public Place"
        }
    ],
    "sg:phone":"+1 602 712 8329",
    "sg:postcode":"85009",
    "sg:province":"AZ",
    "sg:tags":[
        "government-united",
        "state"
    ],
    "sg:website":"http://www.arizonahighways.com",
    "wof:name":"Traffic Operations Center",
    "wof:placetype":"venue"
},
  "geometry": {"coordinates":[-112.109145,33.429509],"type":"Point"}
}