{
  "type": "Feature",
  "properties": {
    "iso:country":"US",
    "sg:address":"832 W Kiva Ave",
    "sg:city":"Mesa",
    "sg:classifiers":[
        {
            "category":"Building & Trades",
            "subcategory":"Landscaping Services",
            "type":"Services"
        }
    ],
    "sg:phone":"+1 602 721 7161",
    "sg:postcode":"85210",
    "sg:province":"AZ",
    "sg:tags":[
        "landscape",
        "contractor"
    ],
    "wof:name":"Richard Trotti Inc",
    "wof:placetype":"venue"
},
  "geometry": {"coordinates":[-111.851692,33.377541],"type":"Point"}
}