{
  "type": "Feature",
  "properties": {
    "iso:country":"US",
    "sg:address":"1202 W Watkins St",
    "sg:city":"Phoenix",
    "sg:classifiers":[
        {
            "category":"Home & Garden",
            "subcategory":"Home Furnishings",
            "type":"Retail Goods"
        },
        {
            "category":"Building & Trades",
            "subcategory":"Construction",
            "type":"Services"
        },
        {
            "category":"Manufacturing",
            "subcategory":"Building Materials",
            "type":"Manufacturing & Wholesale Goods"
        },
        {
            "category":"Home & Garden",
            "subcategory":"Furniture",
            "type":"Retail Goods"
        }
    ],
    "sg:phone":"+1 602 257 4147",
    "sg:postcode":"85007",
    "sg:province":"AZ",
    "sg:tags":[
        "industrial",
        "cabinetmakers-commercial",
        "cabinet",
        "refacing",
        "resurfacing",
        "equipment-household",
        "maker",
        "cabinets-refinishing",
        "kitchen"
    ],
    "wof:name":"National Counter Tops & Cabinets",
    "wof:placetype":"venue"
},
  "geometry": {"coordinates":[-112.088258,33.425804],"type":"Point"}
}