{
  "type": "Feature",
  "properties": {
    "addr:full":"9258 W Van Buren St Tolleson AZ 85353",
    "addr:housenumber":"9258",
    "addr:postcode":"85353",
    "addr:street":"W Van Buren St",
    "iso:country":"US",
    "sg:address":"9258 W Van Buren St",
    "sg:city":"Tolleson",
    "sg:classifiers":[
        {
            "category":"Local Transit",
            "type":"Transportation"
        }
    ],
    "sg:phone":"+1 623 936 1156",
    "sg:postcode":"85353",
    "sg:province":"AZ",
    "sg:tags":[
        "bus",
        "line",
        "charter"
    ],
    "wof:name":"Greyhound Bus Lines",
    "wof:placetype":"venue"
},
  "geometry": {"coordinates":[-112.259473,33.450431],"type":"Point"}
}