{
  "type": "Feature",
  "properties": {
    "addr:full":"1001 Lake Havasu Ave N Lake Havasu City AZ 86403",
    "addr:housenumber":"1001",
    "addr:postcode":"86403",
    "addr:street":"Lake Havasu Ave N",
    "iso:country":"US",
    "sg:address":"1001 Lake Havasu Ave N",
    "sg:city":"Lake Havasu City",
    "sg:classifiers":[
        {
            "category":"Autos & Motor Vehicles",
            "subcategory":"Automobile Sales",
            "type":"Retail Goods"
        }
    ],
    "sg:phone":"+1 928 680 8733",
    "sg:postcode":"86403",
    "sg:province":"AZ",
    "sg:tags":[
        "car",
        "used",
        "dealer"
    ],
    "wof:name":"Paradise Auto & Truck Center",
    "wof:placetype":"venue"
},
  "geometry": {"coordinates":[-114.347967,34.504357],"type":"Point"}
}