{
  "type": "Feature",
  "properties": {
    "addr:full":"13244 N 37th Way Phoenix AZ 85032",
    "addr:housenumber":"13244",
    "addr:postcode":"85032",
    "addr:street":"N 37Th Way",
    "iso:country":"US",
    "sg:address":"13244 N 37th Way",
    "sg:city":"Phoenix",
    "sg:classifiers":[
        {
            "category":"Food & Beverages",
            "subcategory":"Candy",
            "type":"Retail Goods"
        }
    ],
    "sg:phone":"+1 602 441 5501",
    "sg:postcode":"85032",
    "sg:province":"AZ",
    "sg:tags":[
        "confectionery"
    ],
    "wof:name":"Candy Wrapper People Of Arizon",
    "wof:placetype":"venue"
},
  "geometry": {"coordinates":[-112.00102099999999,33.606965],"type":"Point"}
}