{
  "type": "Feature",
  "properties": {
    "iso:country":"US",
    "sg:address":"13244 N 37th Way",
    "sg:city":"Phoenix",
    "sg:classifiers":[
        {
            "category":"Food & Beverages",
            "subcategory":"Candy",
            "type":"Retail Goods"
        }
    ],
    "sg:phone":"+1 602 441 5501",
    "sg:postcode":"85032",
    "sg:province":"AZ",
    "sg:tags":[
        "confectionery"
    ],
    "wof:name":"Candy Wrapper People Of Arizon",
    "wof:placetype":"venue"
},
  "geometry": {"coordinates":[-112.001021,33.606965],"type":"Point"}
}