{
  "type": "Feature",
  "properties": {
    "addr:full":"90 Bell Rock Plz Sedona AZ 86351",
    "addr:housenumber":"90",
    "addr:postcode":"86351",
    "addr:street":"Bell Rock Plz",
    "iso:country":"US",
    "sg:address":"90 Bell Rock Plz",
    "sg:city":"Sedona",
    "sg:classifiers":[
        {
            "category":"Manufacturing",
            "subcategory":"Printing",
            "type":"Manufacturing & Wholesale Goods"
        }
    ],
    "sg:phone":"+1 928 284 4005",
    "sg:postcode":"86351",
    "sg:province":"AZ",
    "sg:tags":[
        "publisher"
    ],
    "sg:website":"www.swiminfo.com",
    "wof:name":"Sports Publications",
    "wof:placetype":"venue"
},
  "geometry": {"coordinates":[-111.764072,34.788947],"type":"Point"}
}