{
  "type": "Feature",
  "properties": {
    "iso:country":"US",
    "sg:address":"8730 E Via de la Luna",
    "sg:city":"Scottsdale",
    "sg:classifiers":[
        {
            "category":"Wholesale",
            "subcategory":"Electrical",
            "type":"Manufacturing & Wholesale Goods"
        }
    ],
    "sg:phone":"+1 480 563 4393",
    "sg:postcode":"85258",
    "sg:province":"AZ",
    "sg:tags":[
        "high",
        "fidelity",
        "stereophonic"
    ],
    "sg:website":"www.mbl-hifi.com",
    "wof:name":"MBL Of America",
    "wof:placetype":"venue"
},
  "geometry": {"coordinates":[-111.891904,33.548085],"type":"Point"}
}