{
  "type": "Feature",
  "properties": {
    "addr:full":"2555 E University Dr Phoenix AZ 85034",
    "addr:housenumber":"2555",
    "addr:postcode":"85034",
    "addr:street":"E University Dr",
    "iso:country":"US",
    "sg:address":"2555 E University Dr",
    "sg:city":"Phoenix",
    "sg:classifiers":[
        {
            "category":"Wholesale",
            "subcategory":"Metals & Minerals",
            "type":"Manufacturing & Wholesale Goods"
        }
    ],
    "sg:phone":"+1 602 275 0990",
    "sg:postcode":"85034",
    "sg:province":"AZ",
    "sg:tags":[
        "machine",
        "shop",
        "center"
    ],
    "wof:name":"State Industrial Products Inc",
    "wof:placetype":"venue"
},
  "geometry": {"coordinates":[-112.026022,33.423958],"type":"Point"}
}