{
  "type": "Feature",
  "properties": {
    "iso:country":"US",
    "sg:address":"1876 E Hayden Ln",
    "sg:city":"Tempe",
    "sg:classifiers":[
        {
            "category":"Real Estate",
            "subcategory":"Real Estate Operator",
            "type":"Services"
        }
    ],
    "sg:phone":"+1 480 829 1155",
    "sg:postcode":"85281",
    "sg:province":"AZ",
    "sg:tags":[
        "apartment"
    ],
    "wof:name":"Hayden Lane Apartments",
    "wof:placetype":"venue"
},
  "geometry": {"coordinates":[-111.90440700000001,33.41913],"type":"Point"}
}