{
  "type": "Feature",
  "properties": {
    "addr:full":"1537 S Craycroft Rd Tucson AZ 85711",
    "addr:housenumber":"1537",
    "addr:postcode":"85711",
    "addr:street":"S Craycroft Rd",
    "iso:country":"US",
    "sg:address":"1537 S Craycroft Rd",
    "sg:city":"Tucson",
    "sg:classifiers":[
        {
            "category":"Shopping",
            "subcategory":"Discount & Variety Stores",
            "type":"Retail Goods"
        }
    ],
    "sg:phone":"+1 520 790 8700",
    "sg:postcode":"85711",
    "sg:province":"AZ",
    "sg:tags":[
        "salvage",
        "surplus",
        "merchandise"
    ],
    "sg:website":"http://www.millerssurplus.com",
    "wof:name":"Miller's Surplus",
    "wof:placetype":"venue"
},
  "geometry": {"coordinates":[-110.875107,32.202966],"type":"Point"}
}