{
  "type": "Feature",
  "properties": {
    "addr:full":"15249 N 99th Ave Sun City AZ 85351",
    "addr:housenumber":"15249",
    "addr:postcode":"85351",
    "addr:street":"N 99Th Ave",
    "iso:country":"US",
    "sg:address":"15249 N 99th Ave",
    "sg:city":"Sun City",
    "sg:classifiers":[
        {
            "category":"Banks & Credit Unions",
            "subcategory":"Bank",
            "type":"Services"
        }
    ],
    "sg:phone":"+1 623 875 0555",
    "sg:postcode":"85351",
    "sg:province":"AZ",
    "wof:name":"Marine Bank",
    "wof:placetype":"venue"
},
  "geometry": {"coordinates":[-112.26862,33.620754],"type":"Point"}
}