{
  "type": "Feature",
  "properties": {
    "iso:country":"US",
    "sg:address":"1850 W Broadway Rd",
    "sg:city":"Phoenix",
    "sg:classifiers":[
        {
            "category":"Building & Trades",
            "subcategory":"Construction",
            "type":"Services"
        }
    ],
    "sg:phone":"+1 602 304 9888",
    "sg:postcode":"85041",
    "sg:province":"AZ",
    "sg:tags":[
        "general",
        "contractor"
    ],
    "wof:name":"Signature Home Communities",
    "wof:placetype":"venue"
},
  "geometry": {"coordinates":[-112.098606,33.406811],"type":"Point"}
}