{
  "type": "Feature",
  "properties": {
    "iso:country":"US",
    "sg:address":"2943 Desert Sky Dr",
    "sg:city":"Bullhead City",
    "sg:classifiers":[
        {
            "category":"Social Services",
            "subcategory":"Adult Care",
            "type":"Services"
        }
    ],
    "sg:phone":"+1 928 763 4570",
    "sg:postcode":"86442",
    "sg:province":"AZ",
    "sg:tags":[
        "home",
        "residential"
    ],
    "sg:website":"www.alcco.com",
    "wof:name":"Davis House",
    "wof:placetype":"venue"
},
  "geometry": {"coordinates":[-114.5515,35.077341],"type":"Point"}
}