{
  "type": "Feature",
  "properties": {
    "iso:country":"US",
    "sg:address":"1147 N Us Highway 89",
    "sg:city":"Chino Valley",
    "sg:classifiers":[
        {
            "category":"Restaurant",
            "type":"Food & Drink"
        }
    ],
    "sg:menulink":"http://www.allmenus.com/az/prescott/204928-taco-bell/menu/",
    "sg:postcode":"86323",
    "sg:province":"AZ",
    "sg:tags":[
        "mexican"
    ],
    "wof:name":"Taco Bell",
    "wof:placetype":"venue"
},
  "geometry": {"coordinates":[-112.453346,34.761493],"type":"Point"}
}