{
  "type": "Feature",
  "properties": {
    "iso:country":"US",
    "sg:address":"5455 N 51st Ave",
    "sg:city":"Glendale",
    "sg:classifiers":[
        {
            "category":"Professional",
            "subcategory":"Computer Services",
            "type":"Services"
        }
    ],
    "sg:phone":"+1 623 334 9277",
    "sg:postcode":"85301",
    "sg:province":"AZ",
    "sg:tags":[
        "rom",
        "cd"
    ],
    "sg:website":"www.cd-lab.com",
    "wof:name":"CD-Lab",
    "wof:placetype":"venue"
},
  "geometry": {"coordinates":[-112.168639,33.515622],"type":"Point"}
}