{
  "type": "Feature",
  "properties": {
    "addr:full":"6036 N 19th Ave # 206 Phoenix AZ 85015",
    "addr:housenumber":"6036",
    "addr:postcode":"85015",
    "addr:street":"N 19Th Ave # 206",
    "iso:country":"US",
    "sg:address":"6036 N 19th Ave # 206",
    "sg:city":"Phoenix",
    "sg:classifiers":[
        {
            "category":"Health Services",
            "subcategory":"Doctor",
            "type":"Services"
        },
        {
            "category":"Health Services",
            "subcategory":"Clinic",
            "type":"Services"
        },
        {
            "category":"Community Center",
            "type":"Public Place"
        }
    ],
    "sg:phone":"+1 602 242 6248",
    "sg:postcode":"85015",
    "sg:province":"AZ",
    "sg:tags":[
        "physician",
        "medical",
        "surgeons",
        "pediatrics-orthopedic",
        "orthopedics",
        "surgeon",
        "surgery"
    ],
    "wof:name":"Chiang, Sepein, Do - Illini Orthopedic Surgeons Ltd",
    "wof:placetype":"venue"
},
  "geometry": {"coordinates":[-112.099693,33.52541],"type":"Point"}
}