{
  "type": "Feature",
  "properties": {
    "addr:full":"6497 W Stampede Way Casa Grande AZ 85294",
    "addr:housenumber":"6497",
    "addr:postcode":"85294",
    "addr:street":"W Stampede Way",
    "iso:country":"US",
    "sg:address":"6497 W Stampede Way",
    "sg:city":"Casa Grande",
    "sg:classifiers":[
        {
            "category":"Retail",
            "subcategory":"Veterinary Services",
            "type":"Services"
        }
    ],
    "sg:phone":"+1 520 426 9349",
    "sg:postcode":"85294",
    "sg:province":"AZ",
    "wof:name":"Darrel R Kramer DMV",
    "wof:placetype":"venue"
},
  "geometry": {"coordinates":[-111.639025,32.830354],"type":"Point"}
}