{
  "type": "Feature",
  "properties": {
    "iso:country":"US",
    "sg:address":"525 E Main St",
    "sg:city":"Mesa",
    "sg:classifiers":[
        {
            "category":"Place Of Worship",
            "type":"Public Place"
        },
        {
            "category":"Place Of Worship",
            "subcategory":"Temple",
            "type":"Public Place"
        }
    ],
    "sg:phone":"+1 480 964 7164",
    "sg:postcode":"85203",
    "sg:province":"AZ",
    "sg:tags":[
        "church"
    ],
    "sg:website":"http://www.lds.org",
    "wof:name":"Tourist Center Visitor Center",
    "wof:placetype":"venue"
},
  "geometry": {"coordinates":[-111.820114,33.415014],"type":"Point"}
}