{
  "type": "Feature",
  "properties": {
    "iso:country":"US",
    "sg:address":"8280 W Bell Rd",
    "sg:city":"Glendale",
    "sg:classifiers":[
        {
            "category":"Shopping",
            "subcategory":"Computers & Home Electronics",
            "type":"Retail Goods"
        }
    ],
    "sg:phone":"+1 623 487 7426",
    "sg:postcode":"85308",
    "sg:province":"AZ",
    "sg:tags":[
        "equipment",
        "electronic",
        "supply"
    ],
    "wof:name":"Magnolia Home Theater",
    "wof:placetype":"venue"
},
  "geometry": {"coordinates":[-112.229396,33.638254],"type":"Point"}
}