{
  "type": "Feature",
  "properties": {
    "addr:full":"9388 Riverside Dr Parker AZ 85344",
    "addr:housenumber":"9388",
    "addr:postcode":"az 85344",
    "addr:street":"Riverside Dr",
    "iso:country":"US",
    "sg:address":"9388 Riverside Dr",
    "sg:city":"Parker",
    "sg:classifiers":[
        {
            "category":"Travel",
            "subcategory":"Hotels & Motels",
            "type":"Entertainment"
        }
    ],
    "sg:phone":"+1 928 667 2685",
    "sg:postcode":"85344",
    "sg:province":"AZ",
    "wof:name":"Arizona Shores",
    "wof:placetype":"venue"
},
  "geometry": {"coordinates":[-114.223269,34.191802],"type":"Point"}
}