{
  "type": "Feature",
  "properties": {
    "iso:country":"US",
    "sg:address":"14500 N Northsight Blvd",
    "sg:city":"Scottsdale",
    "sg:classifiers":[
        {
            "category":"Banks & Credit Unions",
            "subcategory":"Financial Services",
            "type":"Services"
        }
    ],
    "sg:phone":"+1 480 355 2566",
    "sg:postcode":"85260",
    "sg:province":"AZ",
    "sg:tags":[
        "financing"
    ],
    "wof:name":"Bridgeview Legal Funding",
    "wof:placetype":"venue"
},
  "geometry": {"coordinates":[-111.89785000000001,33.616501],"type":"Point"}
}