{
  "type": "Feature",
  "properties": {
    "iso:country":"US",
    "sg:address":"1202 W Encanto Blvd",
    "sg:city":"Phoenix",
    "sg:phone":"+1 602 254 1200",
    "sg:postcode":"85007",
    "sg:province":"AZ",
    "sg:website":"http://www.enchantedisland.com",
    "wof:name":"Enchanted Island Amusement",
    "wof:placetype":"venue"
},
  "geometry": {"coordinates":[-112.088821,33.472681],"type":"Point"}
}