{
  "type": "Feature",
  "properties": {
    "iso:country":"US",
    "sg:address":"6812 S Hardy Dr",
    "sg:city":"Tempe",
    "sg:classifiers":[
        {
            "category":"Real Estate",
            "subcategory":"Real Estate Agent",
            "type":"Services"
        }
    ],
    "sg:phone":"+1 480 897 9396",
    "sg:postcode":"85283",
    "sg:province":"AZ",
    "wof:name":"John Holland Associates",
    "wof:placetype":"venue"
},
  "geometry": {"coordinates":[-111.955569,33.359117],"type":"Point"}
}