{
  "type": "Feature",
  "properties": {
    "iso:country":"US",
    "sg:address":"1110 E Washington St",
    "sg:city":"Phoenix",
    "sg:classifiers":[
        {
            "category":"Education",
            "subcategory":"Dance Studio",
            "type":"Public Place"
        }
    ],
    "sg:phone":"+1 602 254 4244",
    "sg:postcode":"85034",
    "sg:province":"AZ",
    "sg:tags":[
        "instruction",
        "dancing"
    ],
    "wof:name":"Footprints A Dance & Exercise",
    "wof:placetype":"venue"
},
  "geometry": {"coordinates":[-112.05663300000001,33.448351],"type":"Point"}
}