{
  "type": "Feature",
  "properties": {
    "iso:country":"US",
    "sg:address":"3131 N Country Club Rd",
    "sg:city":"Tucson",
    "sg:classifiers":[
        {
            "category":"Building & Trades",
            "subcategory":"Construction",
            "type":"Services"
        }
    ],
    "sg:phone":"+1 520 742 7005",
    "sg:postcode":"85716",
    "sg:province":"AZ",
    "sg:tags":[
        "masonry",
        "contractor"
    ],
    "wof:name":"Sunrise Masonry",
    "wof:placetype":"venue"
},
  "geometry": {"coordinates":[-110.926822,32.264395],"type":"Point"}
}