{
  "type": "Feature",
  "properties": {
    "addr:full":"5501 N 62nd Dr Glendale AZ 85301",
    "addr:housenumber":"5501",
    "addr:postcode":"85301",
    "addr:street":"N 62Nd Dr",
    "iso:country":"US",
    "sg:address":"5501 N 62nd Dr",
    "sg:city":"Glendale",
    "sg:classifiers":[
        {
            "category":"Manufacturing",
            "subcategory":"Printing",
            "type":"Manufacturing & Wholesale Goods"
        }
    ],
    "sg:phone":"+1 623 842 4988",
    "sg:postcode":"85301",
    "sg:province":"AZ",
    "sg:tags":[
        "lithographic",
        "commercial"
    ],
    "wof:name":"Integrity Graphics",
    "wof:placetype":"venue"
},
  "geometry": {"coordinates":[-112.194838,33.521217],"type":"Point"}
}