{
  "type": "Feature",
  "properties": {
    "iso:country":"US",
    "sg:address":"8225 E Butherus Dr",
    "sg:city":"Scottsdale",
    "sg:classifiers":[
        {
            "category":"Professional",
            "type":"Services"
        }
    ],
    "sg:phone":"+1 480 998 0924",
    "sg:postcode":"85260",
    "sg:province":"AZ",
    "sg:tags":[
        "establishment"
    ],
    "wof:name":"Campbell Family",
    "wof:placetype":"venue"
},
  "geometry": {"coordinates":[-111.90238,33.621996],"type":"Point"}
}