{
  "type": "Feature",
  "properties": {
    "addr:full":"2514 E Maryland Dr Tempe AZ 85281",
    "addr:housenumber":"2514",
    "addr:postcode":"85281",
    "addr:street":"E Maryland Dr",
    "iso:country":"US",
    "sg:address":"2514 E Maryland Dr",
    "sg:city":"Tempe",
    "sg:classifiers":[
        {
            "category":"Shopping",
            "subcategory":"Jewelry",
            "type":"Retail Goods"
        }
    ],
    "sg:phone":"+1 480 966 2445",
    "sg:postcode":"85281",
    "sg:province":"AZ",
    "sg:tags":[
        "jeweler"
    ],
    "wof:name":"Connie's Jewelry",
    "wof:placetype":"venue"
},
  "geometry": {"coordinates":[-111.88445900000001,33.420347],"type":"Point"}
}