{
  "type": "Feature",
  "properties": {
    "addr:full":"1172 S Goodsell Ave Yuma AZ 85365",
    "addr:housenumber":"1172",
    "addr:postcode":"85365",
    "addr:street":"S Goodsell Ave",
    "iso:country":"US",
    "sg:address":"1172 S Goodsell Ave",
    "sg:city":"Yuma",
    "sg:classifiers":[
        {
            "category":"Shopping",
            "subcategory":"Gifts & Souvenirs",
            "type":"Retail Goods"
        }
    ],
    "sg:phone":"+1 928 344 5515",
    "sg:postcode":"85365",
    "sg:province":"AZ",
    "wof:name":"Crown Interior & Gift Services",
    "wof:placetype":"venue"
},
  "geometry": {"coordinates":[-114.58358,32.653181],"type":"Point"}
}