{
  "type": "Feature",
  "properties": {
    "iso:country":"US",
    "sg:address":"1741 W Rose Garden Ln",
    "sg:city":"Phoenix",
    "sg:classifiers":[
        {
            "category":"Wholesale",
            "subcategory":"Machinery & Supplies",
            "type":"Manufacturing & Wholesale Goods"
        }
    ],
    "sg:phone":"+1 623 516 8560",
    "sg:postcode":"85027",
    "sg:province":"AZ",
    "sg:tags":[
        "equipment",
        "transportation"
    ],
    "wof:name":"Simon Ventures II LP",
    "wof:placetype":"venue"
},
  "geometry": {"coordinates":[-112.09609500000001,33.67641],"type":"Point"}
}