{
  "type": "Feature",
  "properties": {
    "addr:full":"20950 N Tatum Blvd Phoenix AZ 85050",
    "addr:housenumber":"20950",
    "addr:postcode":"85050",
    "addr:street":"N Tatum Blvd",
    "iso:country":"US",
    "sg:address":"20950 N Tatum Blvd",
    "sg:city":"Phoenix",
    "sg:classifiers":[
        {
            "category":"Health Services",
            "subcategory":"Doctor",
            "type":"Services"
        }
    ],
    "sg:phone":"+1 602 222 7246",
    "sg:postcode":"85050",
    "sg:province":"AZ",
    "sg:tags":[
        "physician",
        "surgeon"
    ],
    "wof:name":"Arizona Center For Pain Relief",
    "wof:placetype":"venue"
},
  "geometry": {"coordinates":[-111.977417,33.678788],"type":"Point"}
}