{
  "type": "Feature",
  "properties": {
    "iso:country":"US",
    "sg:address":"3038 E Thunderhill Pl",
    "sg:city":"Phoenix",
    "sg:classifiers":[
        {
            "category":"Professional",
            "subcategory":"Accounting & Tax Preparation",
            "type":"Services"
        }
    ],
    "sg:phone":"+1 480 706 6544",
    "sg:postcode":"85048",
    "sg:province":"AZ",
    "sg:tags":[
        "accountant"
    ],
    "wof:name":"Sperry Professional Corp",
    "wof:placetype":"venue"
},
  "geometry": {"coordinates":[-112.01943,33.308422],"type":"Point"}
}