{
  "type": "Feature",
  "properties": {
    "iso:country":"US",
    "sg:address":"3431 W Thunderbird Rd",
    "sg:city":"Phoenix",
    "sg:classifiers":[
        {
            "category":"Health Services",
            "subcategory":"Doctor",
            "type":"Services"
        }
    ],
    "sg:phone":"+1 623 434 8251",
    "sg:postcode":"85053",
    "sg:province":"AZ",
    "sg:tags":[
        "clinic"
    ],
    "wof:name":"All Pipes Clinic",
    "wof:placetype":"venue"
},
  "geometry": {"coordinates":[-112.133037,33.610741],"type":"Point"}
}