{
  "type": "Feature",
  "properties": {
    "iso:country":"US",
    "sg:address":"15004 W Caribbean Ln",
    "sg:city":"Surprise",
    "sg:classifiers":[
        {
            "category":"Retail",
            "subcategory":"Portrait Studio",
            "type":"Services"
        }
    ],
    "sg:phone":"+1 623 486 3205",
    "sg:postcode":"85379",
    "sg:province":"AZ",
    "sg:tags":[
        "photographer"
    ],
    "wof:name":"Eden Kenyon Photography",
    "wof:placetype":"venue"
},
  "geometry": {"coordinates":[-112.384799,33.62344],"type":"Point"}
}