{
  "type": "Feature",
  "properties": {
    "iso:country":"US",
    "sg:address":"7275 W Detroit St",
    "sg:city":"Chandler",
    "sg:classifiers":[
        {
            "category":"Autos & Motor Vehicles",
            "subcategory":"Automobile Sales",
            "type":"Retail Goods"
        }
    ],
    "sg:phone":"+1 480 505 8260",
    "sg:postcode":"85226",
    "sg:province":"AZ",
    "sg:tags":[
        "equipment",
        "aircraft",
        "parts",
        "supply"
    ],
    "wof:name":"Avsets",
    "wof:placetype":"venue"
},
  "geometry": {"coordinates":[-111.968284,33.306967],"type":"Point"}
}