{
  "type": "Feature",
  "properties": {
    "iso:country":"US",
    "sg:address":"200 S Arizona Avenue",
    "sg:city":"Chandler",
    "sg:classifiers":[
        {
            "category":"Restaurant",
            "type":"Food & Drink"
        }
    ],
    "sg:phone":"+1 480 963 4277",
    "sg:postcode":"85225",
    "sg:province":"AZ",
    "wof:name":"Pirate's Fish & Chips",
    "wof:placetype":"venue"
},
  "geometry": {"coordinates":[-111.84165900000001,33.300317],"type":"Point"}
}