{
  "type": "Feature",
  "properties": {
    "iso:country":"US",
    "sg:address":"1181 N Hwy 89",
    "sg:city":"Chino Valley",
    "sg:classifiers":[
        {
            "category":"Autos & Motor Vehicles",
            "subcategory":"Auto Supplies",
            "type":"Retail Goods"
        }
    ],
    "sg:phone":"+1 928 636 6022",
    "sg:postcode":"86323",
    "sg:province":"AZ",
    "sg:tags":[
        "trailer",
        "hitch"
    ],
    "wof:name":"Triple T Sales",
    "wof:placetype":"venue"
},
  "geometry": {"coordinates":[-112.453443,34.763108],"type":"Point"}
}