{
  "type": "Feature",
  "properties": {
    "iso:country":"US",
    "sg:address":"2854 N Stone Ave",
    "sg:city":"Tucson",
    "sg:classifiers":[
        {
            "category":"Autos & Motor Vehicles",
            "subcategory":"Automobile Sales",
            "type":"Retail Goods"
        }
    ],
    "sg:phone":"+1 520 882 7001",
    "sg:postcode":"85705",
    "sg:province":"AZ",
    "sg:tags":[
        "used"
    ],
    "wof:name":"European Motor Cars Inc",
    "wof:placetype":"venue"
},
  "geometry": {"coordinates":[-110.971916,32.258418],"type":"Point"}
}